{
  "type": "Feature",
  "properties": {
    "iso:country": "XX",
    "media:fingerprint": "8607cfa2dad911fc78481700b86f4488d317544f",
    "media:imagehash_avg": "a:ffffff0000000000",
    "media:imagehash_diff": "d:cdacad797d091c34",
    "media:medium": "image",
    "media:mimetype": "image/tiff",
    "media:properties": {
      "colours": [
        {
          "hex": "#808080",
          "name": "#808080",
          "reference": "vibrant"
        }, 
        {
          "hex": "#c0c0c0",
          "name": "#c0c0c0",
          "reference": "vibrant"
        }, 
        {
          "hex": "#404040",
          "name": "#404040",
          "reference": "vibrant"
        }
      ],
      "sizes": {
        "b": {
          "extension": "jpg",
          "height": 727,
          "mimetype": "image/jpeg",
          "secret": "DPDgoCZBbASzIpha0ml4myXvFN8U92zB",
          "width": 1024
        },
        "c": {
          "extension": "jpg",
          "height": 568,
          "mimetype": "image/jpeg",
          "secret": "DPDgoCZBbASzIpha0ml4myXvFN8U92zB",
          "width": 800
        },
        "dc": {
          "extension": "jpg",
          "height": 568,
          "mimetype": "image/jpeg",
          "secret": "DPDgoCZBbASzIpha0ml4myXvFN8U92zB",
          "width": 800
        },
        "ds": {
          "extension": "jpg",
          "height": 320,
          "mimetype": "image/jpeg",
          "secret": "DPDgoCZBbASzIpha0ml4myXvFN8U92zB",
          "width": 320
        },
        "k": {
          "extension": "jpg",
          "height": 1455,
          "mimetype": "image/jpeg",
          "secret": "DPDgoCZBbASzIpha0ml4myXvFN8U92zB",
          "width": 2048
        },
        "n": {
          "extension": "jpg",
          "height": 227,
          "mimetype": "image/jpeg",
          "secret": "DPDgoCZBbASzIpha0ml4myXvFN8U92zB",
          "width": 320
        },
        "o": {
          "extension": "jpg",
          "height": 5890,
          "mimetype": "image/jpeg",
          "secret": "8U3jaoiDWEgGEUgZeJ7FLWkLAEvekHeT",
          "width": 8290
        },
        "s": {
          "extension": "jpg",
          "height": 320,
          "mimetype": "image/jpeg",
          "secret": "DPDgoCZBbASzIpha0ml4myXvFN8U92zB",
          "width": 320
        },
        "z": {
          "extension": "jpg",
          "height": 454,
          "mimetype": "image/jpeg",
          "secret": "DPDgoCZBbASzIpha0ml4myXvFN8U92zB",
          "width": 640
        }
      }
    },
    "media:uri_template": "https://millsfield.sfomuseum.org/media/152/782/159/1/1527821591_{secret}_{label}.{extention}",
    "sfomuseum:filename": "38882.tif",
    "sfomuseum:image_index": 5,
    "sfomuseum:placetype": "image",
    "sfomuseum:primary_image": 1,
    "wof:depicts": [
      1511950029
    ],
    "wof:name": "negative: Mills Field Municipal Airport of San Francisco, dedication ceremony",
    "wof:placetype": "media"
  },
  "geometry": {"coordinates":[-122.386155,37.616358],"type":"Point"}
}
