{
  "type": "Feature",
  "properties": {
    "iso:country": "XX",
    "media:fingerprint": "43e9f254f273fb2530a250e6844071392a4136d7",
    "media:imagehash_avg": "a:0f8189fbb3230101",
    "media:imagehash_diff": "d:5f5953636747cf0f",
    "media:medium": "image",
    "media:mimetype": "image/tiff",
    "media:properties": {
      "colours": [
        {
          "hex": "#868686",
          "name": "#868686",
          "reference": "vibrant"
        },
        {
          "hex": "#b8b8b8",
          "name": "#b8b8b8",
          "reference": "vibrant"
        },
        {
          "hex": "#484848",
          "name": "#484848",
          "reference": "vibrant"
        }
      ],
      "sizes": {
        "b": {
          "extension": "jpg",
          "height": 768,
          "mimetype": "image/jpeg",
          "secret": "oVLw1CAJr1B6qc03nP3jcb6K8xrRKo5E",
          "width": 643
        },
        "c": {
          "extension": "jpg",
          "height": 600,
          "mimetype": "image/jpeg",
          "secret": "oVLw1CAJr1B6qc03nP3jcb6K8xrRKo5E",
          "width": 502
        },
        "dc": {
          "extension": "jpg",
          "height": 600,
          "mimetype": "image/jpeg",
          "secret": "oVLw1CAJr1B6qc03nP3jcb6K8xrRKo5E",
          "width": 502
        },
        "ds": {
          "extension": "jpg",
          "height": 320,
          "mimetype": "image/jpeg",
          "secret": "oVLw1CAJr1B6qc03nP3jcb6K8xrRKo5E",
          "width": 320
        },
        "k": {
          "extension": "jpg",
          "height": 1536,
          "mimetype": "image/jpeg",
          "secret": "oVLw1CAJr1B6qc03nP3jcb6K8xrRKo5E",
          "width": 1286
        },
        "n": {
          "extension": "jpg",
          "height": 240,
          "mimetype": "image/jpeg",
          "secret": "oVLw1CAJr1B6qc03nP3jcb6K8xrRKo5E",
          "width": 201
        },
        "o": {
          "extension": "jpg",
          "height": 2097,
          "mimetype": "image/jpeg",
          "secret": "mrb9RjAO2eDcdfwoc5WZK80hcejP2ekS",
          "width": 1757
        },
        "s": {
          "extension": "jpg",
          "height": 320,
          "mimetype": "image/jpeg",
          "secret": "oVLw1CAJr1B6qc03nP3jcb6K8xrRKo5E",
          "width": 320
        },
        "z": {
          "extension": "jpg",
          "height": 480,
          "mimetype": "image/jpeg",
          "secret": "oVLw1CAJr1B6qc03nP3jcb6K8xrRKo5E",
          "width": 402
        }
      }
    },
    "media:uri_template": "https://static.sfomuseum.org/media/152/783/054/7/1527830547_{secret}_{label}.{extention}",
    "sfomuseum:filename": "57625.tif",
    "sfomuseum:image_index": 5,
    "sfomuseum:image_type": "studio",
    "sfomuseum:placetype": "image",
    "sfomuseum:primary_image": 0,
    "wof:depicts": [
      1159284989,
      1511954893,
      1159286839
    ],
    "wof:name": "career history questionnaire: World Wings International, Angeline (Nikki) Natalie Jester",
    "wof:placetype": "custom",
    "wof:placetype_alt": "image"
  },
  "geometry": {"coordinates":[-122.386155,37.616358],"type":"Point"}
}
