{
  "type": "Feature",
  "properties": {
    "iso:country": "XX",
    "media:fingerprint": "fe809284b5d6bb240cb65f92a93c5d53d3a07baa",
    "media:imagehash_avg": "a:ffba18baba1abafe",
    "media:imagehash_diff": "d:2a72726272727262",
    "media:medium": "image",
    "media:mimetype": "image/tiff",
    "media:properties": {
      "colours": [
        {
          "hex": "#4e56b0",
          "name": "#4e56b0",
          "reference": "vibrant"
        },
        {
          "hex": "#f8f5e8",
          "name": "#f8f5e8",
          "reference": "vibrant"
        },
        {
          "hex": "#111997",
          "name": "#111997",
          "reference": "vibrant"
        },
        {
          "hex": "#827b75",
          "name": "#827b75",
          "reference": "vibrant"
        },
        {
          "hex": "#8c91c7",
          "name": "#8c91c7",
          "reference": "vibrant"
        }
      ],
      "sizes": {
        "b": {
          "extension": "jpg",
          "height": 717,
          "mimetype": "image/jpeg",
          "secret": "ZR5yfLNYbV50vMGuajsal5Hvf0CMHEhm",
          "width": 1024
        },
        "c": {
          "extension": "jpg",
          "height": 560,
          "mimetype": "image/jpeg",
          "secret": "ZR5yfLNYbV50vMGuajsal5Hvf0CMHEhm",
          "width": 800
        },
        "dc": {
          "extension": "jpg",
          "height": 560,
          "mimetype": "image/jpeg",
          "secret": "ZR5yfLNYbV50vMGuajsal5Hvf0CMHEhm",
          "width": 800
        },
        "ds": {
          "extension": "jpg",
          "height": 320,
          "mimetype": "image/jpeg",
          "secret": "ZR5yfLNYbV50vMGuajsal5Hvf0CMHEhm",
          "width": 320
        },
        "k": {
          "extension": "jpg",
          "height": 1434,
          "mimetype": "image/jpeg",
          "secret": "ZR5yfLNYbV50vMGuajsal5Hvf0CMHEhm",
          "width": 2048
        },
        "n": {
          "extension": "jpg",
          "height": 224,
          "mimetype": "image/jpeg",
          "secret": "ZR5yfLNYbV50vMGuajsal5Hvf0CMHEhm",
          "width": 320
        },
        "o": {
          "extension": "jpg",
          "height": 1605,
          "mimetype": "image/jpeg",
          "secret": "aJLJyYMTSIH2zdo2LrJ9f6xmPbVU3EKl",
          "width": 2292
        },
        "s": {
          "extension": "jpg",
          "height": 320,
          "mimetype": "image/jpeg",
          "secret": "ZR5yfLNYbV50vMGuajsal5Hvf0CMHEhm",
          "width": 320
        },
        "z": {
          "extension": "jpg",
          "height": 448,
          "mimetype": "image/jpeg",
          "secret": "ZR5yfLNYbV50vMGuajsal5Hvf0CMHEhm",
          "width": 640
        }
      }
    },
    "media:uri_template": "https://static.sfomuseum.org/media/152/784/835/1/1527848351_{secret}_{label}.{extention}",
    "sfomuseum:filename": "2006059307194_inside.tif",
    "sfomuseum:image_index": 5,
    "sfomuseum:image_type": "studio",
    "sfomuseum:placetype": "image",
    "sfomuseum:primary_image": 0,
    "wof:depicts": [
      1159285413,
      1511928589
    ],
    "wof:name": "menu: United Airlines, First Class",
    "wof:placetype": "custom",
    "wof:placetype_alt": "image"
  },
  "geometry": {"coordinates":[-122.386155,37.616358],"type":"Point"}
}
