{
  "type": "Feature",
  "properties": {
    "media:fingerprint": "08e5045e6654f70f23064ea4bc67a0721bd1ec95",
    "media:imagehash_avg": "a:20fefefe1f170703",
    "media:imagehash_diff": "d:c8c8b0b0b0ececce",
    "media:mimetype": "image/tiff",
    "media:properties": {
      "colours": [
        {
          "hex": "#787878",
          "name": "#787878",
          "reference": "vibrant"
        },
        {
          "hex": "#b8b8b8",
          "name": "#b8b8b8",
          "reference": "vibrant"
        },
        {
          "hex": "#404040",
          "name": "#404040",
          "reference": "vibrant"
        }
      ],
      "sizes": {
        "b": {
          "extension": "jpg",
          "height": 768,
          "mimetype": "image/jpeg",
          "secret": "E0pyTJF3RlmKwxkUnh23CA46uJ0L25Nr",
          "width": 601
        },
        "c": {
          "extension": "jpg",
          "height": 600,
          "mimetype": "image/jpeg",
          "secret": "E0pyTJF3RlmKwxkUnh23CA46uJ0L25Nr",
          "width": 470
        },
        "dc": {
          "extension": "jpg",
          "height": 600,
          "mimetype": "image/jpeg",
          "secret": "E0pyTJF3RlmKwxkUnh23CA46uJ0L25Nr",
          "width": 470
        },
        "ds": {
          "extension": "jpg",
          "height": 320,
          "mimetype": "image/jpeg",
          "secret": "E0pyTJF3RlmKwxkUnh23CA46uJ0L25Nr",
          "width": 320
        },
        "k": {
          "extension": "jpg",
          "height": 1536,
          "mimetype": "image/jpeg",
          "secret": "E0pyTJF3RlmKwxkUnh23CA46uJ0L25Nr",
          "width": 1203
        },
        "n": {
          "extension": "jpg",
          "height": 240,
          "mimetype": "image/jpeg",
          "secret": "E0pyTJF3RlmKwxkUnh23CA46uJ0L25Nr",
          "width": 188
        },
        "o": {
          "extension": "jpg",
          "height": 2665,
          "mimetype": "image/jpeg",
          "secret": "gQ2hReLZEs6EhScw1jRtHlf0p9Nc7NSR",
          "width": 2088
        },
        "s": {
          "extension": "jpg",
          "height": 320,
          "mimetype": "image/jpeg",
          "secret": "E0pyTJF3RlmKwxkUnh23CA46uJ0L25Nr",
          "width": 320
        },
        "z": {
          "extension": "jpg",
          "height": 480,
          "mimetype": "image/jpeg",
          "secret": "E0pyTJF3RlmKwxkUnh23CA46uJ0L25Nr",
          "width": 376
        }
      }
    },
    "media:uri_template": "https://static.sfomuseum.org/media/174/651/207/9/1746512079_{secret}_{label}.{extention}",
    "sfomuseum:filename": "45895.tif",
    "sfomuseum:image_index": 0,
    "sfomuseum:image_type": "studio",
    "sfomuseum:placetype": "image",
    "sfomuseum:primary_image": 1,
    "wof:depicts": [
      1159287531,
      1729563709,
      1159285393
    ],
    "wof:name": "negative: TWA (Trans World Airlines), A. B. Krueger, Director of Sales",
    "wof:placetype": "custom",
    "wof:placetype_alt": "image"
  },
  "geometry": {"coordinates":[-122.386155,37.616357],"type":"Point"}
}
