{
  "type": "Feature",
  "properties": {
    "date:cessation_lower": "1995-01-01",
    "date:cessation_upper": "1995-12-31",
    "date:inception_lower": "1995-01-01",
    "date:inception_upper": "1995-12-31",
    "iso:country": "XX",
    "media:imagehash_avg": "a:ffc7c3f3f1c1e3ff",
    "media:imagehash_diff": "d:8c8e8666a387c6e6",
    "media:imagetext": "UNITED AIRLINES\nNIM AMUNES\nKENGRANDE",
    "media:imagetext_created": 1701937905,
    "media:mimetype": "image/jpeg",
    "media:properties": {
    },
    "media:uri_template": "https://static.sfomuseum.org/media/174/668/015/1/1746680151_{secret}_{label}.{extention}",
    "millsfield:images_texts": [
      "UNITED AIRLINES\nNIM AMUNES\nKENGRANDE"
    ],
    "millsfield:images_texts_ids": [
      1746680151
    ],
    "sfomuseum:filename": "13809.jpg",
    "sfomuseum:image_index": 1,
    "sfomuseum:image_type": "studio",
    "sfomuseum:placetype": "image",
    "sfomuseum:primary_image": 1,
    "wof:depicts": [
      1159285413,
      1511908309,
      1159288779
    ],
    "wof:name": "amenity kit: United Airlines",
    "wof:placetype": "custom"
  },
  "geometry": {"coordinates":[-122.386155,37.616358],"type":"Point"}
}
