{
  "type": "Feature",
  "properties": {
    "iso:country": "XX",
    "media:fingerprint": "fef42e90ff829e58db90685caef504bd0e715889",
    "media:imagehash_avg": "a:ff1f8fff7f610000",
    "media:imagehash_diff": "d:ed7d3959c9cb7860",
    "media:medium": "image",
    "media:mimetype": "image/tiff",
    "media:properties": {
      "colours": [
        {
          "hex": "#808080",
          "name": "#808080",
          "reference": "vibrant"
        }, 
        {
          "hex": "#b8b8b8",
          "name": "#b8b8b8",
          "reference": "vibrant"
        }, 
        {
          "hex": "#484848",
          "name": "#484848",
          "reference": "vibrant"
        }
      ],
      "sizes": {
        "b": {
          "extension": "jpg",
          "height": 767,
          "mimetype": "image/jpeg",
          "secret": "FtabdVqLYhTbAVN3pgbAUE7qD9If6Rdq",
          "width": 998
        },
        "c": {
          "extension": "jpg",
          "height": 600,
          "mimetype": "image/jpeg",
          "secret": "FtabdVqLYhTbAVN3pgbAUE7qD9If6Rdq",
          "width": 779
        },
        "dc": {
          "extension": "jpg",
          "height": 600,
          "mimetype": "image/jpeg",
          "secret": "FtabdVqLYhTbAVN3pgbAUE7qD9If6Rdq",
          "width": 779
        },
        "ds": {
          "extension": "jpg",
          "height": 320,
          "mimetype": "image/jpeg",
          "secret": "FtabdVqLYhTbAVN3pgbAUE7qD9If6Rdq",
          "width": 320
        },
        "k": {
          "extension": "jpg",
          "height": 1535,
          "mimetype": "image/jpeg",
          "secret": "FtabdVqLYhTbAVN3pgbAUE7qD9If6Rdq",
          "width": 1996
        },
        "n": {
          "extension": "jpg",
          "height": 240,
          "mimetype": "image/jpeg",
          "secret": "FtabdVqLYhTbAVN3pgbAUE7qD9If6Rdq",
          "width": 311
        },
        "o": {
          "extension": "jpg",
          "height": 2140,
          "mimetype": "image/jpeg",
          "secret": "DTq2CZXbIfLc6RG76kvl06Kz5YbE7dqm",
          "width": 2781
        },
        "s": {
          "extension": "jpg",
          "height": 320,
          "mimetype": "image/jpeg",
          "secret": "FtabdVqLYhTbAVN3pgbAUE7qD9If6Rdq",
          "width": 320
        },
        "z": {
          "extension": "jpg",
          "height": 480,
          "mimetype": "image/jpeg",
          "secret": "FtabdVqLYhTbAVN3pgbAUE7qD9If6Rdq",
          "width": 623
        }
      }
    },
    "media:uri_template": "https://millsfield.sfomuseum.org/media/152/782/194/5/1527821945_{secret}_{label}.{extention}",
    "sfomuseum:filename": "40024.tif",
    "sfomuseum:image_index": 5,
    "sfomuseum:placetype": "image",
    "sfomuseum:primary_image": 1,
    "wof:depicts": [
      1511943865
    ],
    "wof:name": "negative: San Francisco Airport, 25th anniversary celebration",
    "wof:placetype": "media"
  },
  "geometry": {"coordinates":[-122.386155,37.616358],"type":"Point"}
}
