{
  "type": "Feature",
  "properties": {
    "media:fingerprint": "edca840367b5b99d45dfff577b50b4b707ab9128",
    "media:imagehash_avg": "a:e7c703011919097b",
    "media:imagehash_diff": "d:8f0fcfd3f3f3f3fb",
    "media:mimetype": "image/tiff",
    "media:properties": {
      "colours": [
        {
          "hex": "#d40917",
          "name": "#d40917",
          "reference": "vibrant"
        },
        {
          "hex": "#e6a8a8",
          "name": "#e6a8a8",
          "reference": "vibrant"
        },
        {
          "hex": "#8f7170",
          "name": "#8f7170",
          "reference": "vibrant"
        },
        {
          "hex": "#e0d8c8",
          "name": "#e0d8c8",
          "reference": "vibrant"
        },
        {
          "hex": "#4d4c4b",
          "name": "#4d4c4b",
          "reference": "vibrant"
        }
      ],
      "sizes": {
        "b": {
          "extension": "jpg",
          "height": 768,
          "mimetype": "image/jpeg",
          "secret": "BbOvzFhyBLtyGQVayicKU7m7izYSn0K2",
          "width": 285
        },
        "c": {
          "extension": "jpg",
          "height": 600,
          "mimetype": "image/jpeg",
          "secret": "BbOvzFhyBLtyGQVayicKU7m7izYSn0K2",
          "width": 222
        },
        "dc": {
          "extension": "jpg",
          "height": 600,
          "mimetype": "image/jpeg",
          "secret": "BbOvzFhyBLtyGQVayicKU7m7izYSn0K2",
          "width": 222
        },
        "ds": {
          "extension": "jpg",
          "height": 320,
          "mimetype": "image/jpeg",
          "secret": "BbOvzFhyBLtyGQVayicKU7m7izYSn0K2",
          "width": 320
        },
        "k": {
          "extension": "jpg",
          "height": 1536,
          "mimetype": "image/jpeg",
          "secret": "BbOvzFhyBLtyGQVayicKU7m7izYSn0K2",
          "width": 570
        },
        "n": {
          "extension": "jpg",
          "height": 240,
          "mimetype": "image/jpeg",
          "secret": "BbOvzFhyBLtyGQVayicKU7m7izYSn0K2",
          "width": 89
        },
        "o": {
          "extension": "jpg",
          "height": 2724,
          "mimetype": "image/jpeg",
          "secret": "gX42Y3H3av6tEhkyjQtITJjyPwTvSOb6",
          "width": 1011
        },
        "s": {
          "extension": "jpg",
          "height": 320,
          "mimetype": "image/jpeg",
          "secret": "BbOvzFhyBLtyGQVayicKU7m7izYSn0K2",
          "width": 320
        },
        "z": {
          "extension": "jpg",
          "height": 480,
          "mimetype": "image/jpeg",
          "secret": "BbOvzFhyBLtyGQVayicKU7m7izYSn0K2",
          "width": 178
        }
      }
    },
    "media:uri_template": "https://static.sfomuseum.org/media/174/668/073/5/1746680735_{secret}_{label}.{extention}",
    "sfomuseum:filename": "63931.tif",
    "sfomuseum:image_index": 1,
    "sfomuseum:image_type": "curator",
    "sfomuseum:placetype": "image",
    "sfomuseum:primary_image": 1,
    "wof:depicts": [
      1511936931,
      1159286629,
      1159284973
    ],
    "wof:name": "timetable: Pacific Southwest Airlines (PSA)",
    "wof:placetype": "custom"
  },
  "geometry": {"coordinates":[-122.386155,37.616357],"type":"Point"}
}
