{
  "type": "Feature",
  "properties": {
    "iso:country": "XX",
    "media:fingerprint": "7d1edcafa99c4074e93a23bc5d983d4f46b3d16c",
    "media:imagehash_avg": "a:fc3cbcfec8c28000",
    "media:imagehash_diff": "d:f07979381a1e3627",
    "media:medium": "image",
    "media:mimetype": "image/tiff",
    "media:properties": {
      "colours": [
        {
          "hex": "#808080",
          "name": "#808080",
          "reference": "vibrant"
        }, 
        {
          "hex": "#b6b6b6",
          "name": "#b6b6b6",
          "reference": "vibrant"
        }, 
        {
          "hex": "#484848",
          "name": "#484848",
          "reference": "vibrant"
        }
      ],
      "sizes": {
        "b": {
          "extension": "jpg",
          "height": 725,
          "mimetype": "image/jpeg",
          "secret": "cFKfWj0LF6RIV6nXA0HV519jCYhW21ru",
          "width": 1024
        },
        "c": {
          "extension": "jpg",
          "height": 566,
          "mimetype": "image/jpeg",
          "secret": "cFKfWj0LF6RIV6nXA0HV519jCYhW21ru",
          "width": 800
        },
        "dc": {
          "extension": "jpg",
          "height": 566,
          "mimetype": "image/jpeg",
          "secret": "cFKfWj0LF6RIV6nXA0HV519jCYhW21ru",
          "width": 800
        },
        "ds": {
          "extension": "jpg",
          "height": 320,
          "mimetype": "image/jpeg",
          "secret": "cFKfWj0LF6RIV6nXA0HV519jCYhW21ru",
          "width": 320
        },
        "k": {
          "extension": "jpg",
          "height": 1450,
          "mimetype": "image/jpeg",
          "secret": "cFKfWj0LF6RIV6nXA0HV519jCYhW21ru",
          "width": 2048
        },
        "n": {
          "extension": "jpg",
          "height": 226,
          "mimetype": "image/jpeg",
          "secret": "cFKfWj0LF6RIV6nXA0HV519jCYhW21ru",
          "width": 320
        },
        "o": {
          "extension": "jpg",
          "height": 1997,
          "mimetype": "image/jpeg",
          "secret": "hSNsPjoNH475zJrJbj03f3PDKcib7YW2",
          "width": 2820
        },
        "s": {
          "extension": "jpg",
          "height": 320,
          "mimetype": "image/jpeg",
          "secret": "cFKfWj0LF6RIV6nXA0HV519jCYhW21ru",
          "width": 320
        },
        "z": {
          "extension": "jpg",
          "height": 453,
          "mimetype": "image/jpeg",
          "secret": "cFKfWj0LF6RIV6nXA0HV519jCYhW21ru",
          "width": 640
        }
      }
    },
    "media:uri_template": "https://millsfield.sfomuseum.org/media/152/782/102/5/1527821025_{secret}_{label}.{extention}",
    "sfomuseum:filename": "33291.tif",
    "sfomuseum:image_index": 5,
    "sfomuseum:placetype": "image",
    "sfomuseum:primary_image": 1,
    "wof:depicts": [
      1511931223
    ],
    "wof:name": "photograph: Pan American Airways, air transport pilots in training",
    "wof:placetype": "media"
  },
  "geometry": {"coordinates":[-122.386155,37.616358],"type":"Point"}
}
