{
  "type": "Feature",
  "properties": {
    "iso:country": "XX",
    "media:fingerprint": "62c48025067bb9aab613380bed46fa5cf5cbb709",
    "media:imagehash_avg": "a:ffff103a40c00000",
    "media:imagehash_diff": "d:f783b4d292164367",
    "media:medium": "image",
    "media:mimetype": "image/tiff",
    "media:properties": {
      "colours": [
        {
          "hex": "#808080",
          "name": "#808080",
          "reference": "vibrant"
        }, 
        {
          "hex": "#c0c0c0",
          "name": "#c0c0c0",
          "reference": "vibrant"
        }, 
        {
          "hex": "#474747",
          "name": "#474747",
          "reference": "vibrant"
        }
      ],
      "sizes": {
        "b": {
          "extension": "jpg",
          "height": 768,
          "mimetype": "image/jpeg",
          "secret": "djnaH7P25tspYrjMvDK0yKBWjNDigadY",
          "width": 768
        },
        "c": {
          "extension": "jpg",
          "height": 600,
          "mimetype": "image/jpeg",
          "secret": "djnaH7P25tspYrjMvDK0yKBWjNDigadY",
          "width": 600
        },
        "dc": {
          "extension": "jpg",
          "height": 600,
          "mimetype": "image/jpeg",
          "secret": "djnaH7P25tspYrjMvDK0yKBWjNDigadY",
          "width": 600
        },
        "ds": {
          "extension": "jpg",
          "height": 320,
          "mimetype": "image/jpeg",
          "secret": "djnaH7P25tspYrjMvDK0yKBWjNDigadY",
          "width": 320
        },
        "k": {
          "extension": "jpg",
          "height": 1536,
          "mimetype": "image/jpeg",
          "secret": "djnaH7P25tspYrjMvDK0yKBWjNDigadY",
          "width": 1536
        },
        "n": {
          "extension": "jpg",
          "height": 239,
          "mimetype": "image/jpeg",
          "secret": "djnaH7P25tspYrjMvDK0yKBWjNDigadY",
          "width": 239
        },
        "o": {
          "extension": "jpg",
          "height": 2563,
          "mimetype": "image/jpeg",
          "secret": "K8NvW7ay3246tO2rgivptIYwKBfjLP9A",
          "width": 2563
        },
        "s": {
          "extension": "jpg",
          "height": 320,
          "mimetype": "image/jpeg",
          "secret": "djnaH7P25tspYrjMvDK0yKBWjNDigadY",
          "width": 320
        },
        "z": {
          "extension": "jpg",
          "height": 479,
          "mimetype": "image/jpeg",
          "secret": "djnaH7P25tspYrjMvDK0yKBWjNDigadY",
          "width": 479
        }
      }
    },
    "media:uri_template": "https://millsfield.sfomuseum.org/media/152/782/688/5/1527826885_{secret}_{label}.{extention}",
    "sfomuseum:filename": "43841.tif",
    "sfomuseum:image_index": 5,
    "sfomuseum:placetype": "image",
    "sfomuseum:primary_image": 1,
    "wof:depicts": [
      1511947925
    ],
    "wof:name": "negative: San Francisco International Airport (SFO), road construction",
    "wof:placetype": "media"
  },
  "geometry": {"coordinates":[-122.386155,37.616358],"type":"Point"}
}
