{
  "type": "Feature",
  "properties": {
    "iso:country": "XX",
    "media:fingerprint": "f8a923fa394eed7c16e04c7498332695d9596c55",
    "media:imagehash_avg": "a:00003c7f83c3ffff",
    "media:imagehash_diff": "d:fef0f0f02f17dcf0",
    "media:medium": "image",
    "media:mimetype": "image/tiff",
    "media:properties": {
      "colours": [
        {
          "hex": "#a83d27",
          "name": "#a83d27",
          "reference": "vibrant"
        }, 
        {
          "hex": "#a03823",
          "name": "#a03823",
          "reference": "vibrant"
        }, 
        {
          "hex": "#aa5a49",
          "name": "#aa5a49",
          "reference": "vibrant"
        }, 
        {
          "hex": "#c6c4c3",
          "name": "#c6c4c3",
          "reference": "vibrant"
        }, 
        {
          "hex": "#5d5c59",
          "name": "#5d5c59",
          "reference": "vibrant"
        }
      ],
      "sizes": {
        "b": {
          "extension": "jpg",
          "height": 768,
          "mimetype": "image/jpeg",
          "secret": "Za9QpwajNUCY02S6YgIPWDdSHMKtRHzo",
          "width": 965
        },
        "c": {
          "extension": "jpg",
          "height": 600,
          "mimetype": "image/jpeg",
          "secret": "Za9QpwajNUCY02S6YgIPWDdSHMKtRHzo",
          "width": 754
        },
        "dc": {
          "extension": "jpg",
          "height": 600,
          "mimetype": "image/jpeg",
          "secret": "Za9QpwajNUCY02S6YgIPWDdSHMKtRHzo",
          "width": 754
        },
        "ds": {
          "extension": "jpg",
          "height": 320,
          "mimetype": "image/jpeg",
          "secret": "Za9QpwajNUCY02S6YgIPWDdSHMKtRHzo",
          "width": 320
        },
        "k": {
          "extension": "jpg",
          "height": 1536,
          "mimetype": "image/jpeg",
          "secret": "Za9QpwajNUCY02S6YgIPWDdSHMKtRHzo",
          "width": 1931
        },
        "n": {
          "extension": "jpg",
          "height": 240,
          "mimetype": "image/jpeg",
          "secret": "Za9QpwajNUCY02S6YgIPWDdSHMKtRHzo",
          "width": 301
        },
        "o": {
          "extension": "jpg",
          "height": 1667,
          "mimetype": "image/jpeg",
          "secret": "X7M9xc1EUrHR3vs2ybTNPBqz9dNqYJ1r",
          "width": 2096
        },
        "s": {
          "extension": "jpg",
          "height": 320,
          "mimetype": "image/jpeg",
          "secret": "Za9QpwajNUCY02S6YgIPWDdSHMKtRHzo",
          "width": 320
        },
        "z": {
          "extension": "jpg",
          "height": 480,
          "mimetype": "image/jpeg",
          "secret": "Za9QpwajNUCY02S6YgIPWDdSHMKtRHzo",
          "width": 603
        }
      }
    },
    "media:uri_template": "https://millsfield.sfomuseum.org/media/152/785/853/3/1527858533_{secret}_{label}.{extention}",
    "sfomuseum:filename": "2002.112.005.tif",
    "sfomuseum:image_index": 0,
    "sfomuseum:placetype": "image",
    "sfomuseum:primary_image": 1,
    "wof:depicts": [
      1511923723
    ],
    "wof:name": "coffee cup: Continental Airlines",
    "wof:placetype": "media"
  },
  "geometry": {"coordinates":[-122.386155,37.616358],"type":"Point"}
}
