{
  "type": "Feature",
  "properties": {
    "iso:country": "XX",
    "media:fingerprint": "70ba043e7ca6dee32cec7b435f7a8eb12f4cd2ad",
    "media:imagehash_avg": "a:ffffff0000602000",
    "media:imagehash_diff": "d:e0e0c00130c0c8e0",
    "media:medium": "image",
    "media:mimetype": "image/tiff",
    "media:properties": {
      "colours": [
        {
          "hex": "#808080",
          "name": "#808080",
          "reference": "vibrant"
        },
        {
          "hex": "#b8b8b8",
          "name": "#b8b8b8",
          "reference": "vibrant"
        },
        {
          "hex": "#404040",
          "name": "#404040",
          "reference": "vibrant"
        }
      ],
      "sizes": {
        "b": {
          "extension": "jpg",
          "height": 768,
          "mimetype": "image/jpeg",
          "secret": "P0Ktwp4C1CETGAcFY4cNbzZeEDl68kT1",
          "width": 767
        },
        "c": {
          "extension": "jpg",
          "height": 600,
          "mimetype": "image/jpeg",
          "secret": "P0Ktwp4C1CETGAcFY4cNbzZeEDl68kT1",
          "width": 599
        },
        "dc": {
          "extension": "jpg",
          "height": 600,
          "mimetype": "image/jpeg",
          "secret": "P0Ktwp4C1CETGAcFY4cNbzZeEDl68kT1",
          "width": 599
        },
        "ds": {
          "extension": "jpg",
          "height": 320,
          "mimetype": "image/jpeg",
          "secret": "P0Ktwp4C1CETGAcFY4cNbzZeEDl68kT1",
          "width": 320
        },
        "k": {
          "extension": "jpg",
          "height": 1536,
          "mimetype": "image/jpeg",
          "secret": "P0Ktwp4C1CETGAcFY4cNbzZeEDl68kT1",
          "width": 1535
        },
        "n": {
          "extension": "jpg",
          "height": 240,
          "mimetype": "image/jpeg",
          "secret": "P0Ktwp4C1CETGAcFY4cNbzZeEDl68kT1",
          "width": 239
        },
        "o": {
          "extension": "jpg",
          "height": 1836,
          "mimetype": "image/jpeg",
          "secret": "BZ0t87ZCDfnTxaGqvH3FdGPMW5pdRhxB",
          "width": 1835
        },
        "s": {
          "extension": "jpg",
          "height": 320,
          "mimetype": "image/jpeg",
          "secret": "P0Ktwp4C1CETGAcFY4cNbzZeEDl68kT1",
          "width": 320
        },
        "z": {
          "extension": "jpg",
          "height": 480,
          "mimetype": "image/jpeg",
          "secret": "P0Ktwp4C1CETGAcFY4cNbzZeEDl68kT1",
          "width": 479
        }
      }
    },
    "media:uri_template": "https://static.sfomuseum.org/media/152/782/643/3/1527826433_{secret}_{label}.{extention}",
    "sfomuseum:filename": "43638.tif",
    "sfomuseum:image_index": 5,
    "sfomuseum:image_type": "studio",
    "sfomuseum:placetype": "image",
    "sfomuseum:primary_image": 1,
    "wof:depicts": [
      102527513,
      1159285415,
      1511947473
    ],
    "wof:name": "photograph: San Francisco International Airport (SFO), construction",
    "wof:placetype": "custom",
    "wof:placetype_alt": "image"
  },
  "geometry": {"coordinates":[-122.386155,37.616358],"type":"Point"}
}
