{
  "type": "Feature",
  "properties": {
    "iso:country": "XX",
    "media:fingerprint": "ecb74630cc4b2447ccbdf0cf74a81b9145434da7",
    "media:imagehash_avg": "a:000010101e3f3f7f",
    "media:imagehash_diff": "d:e0f0f0b4f0f0d5d9",
    "media:medium": "image",
    "media:mimetype": "image/tiff",
    "media:properties": {
      "colours": [
        {
          "hex": "#c52b4d",
          "name": "#c52b4d",
          "reference": "vibrant"
        },
        {
          "hex": "#68818d",
          "name": "#68818d",
          "reference": "vibrant"
        },
        {
          "hex": "#c6b6c3",
          "name": "#c6b6c3",
          "reference": "vibrant"
        },
        {
          "hex": "#474b3d",
          "name": "#474b3d",
          "reference": "vibrant"
        }
      ],
      "sizes": {
        "b": {
          "extension": "jpg",
          "height": 675,
          "mimetype": "image/jpeg",
          "secret": "YF3xJ9GzxdwCg2iLqKOdz7nV6S0FyQSg",
          "width": 1024
        },
        "c": {
          "extension": "jpg",
          "height": 527,
          "mimetype": "image/jpeg",
          "secret": "YF3xJ9GzxdwCg2iLqKOdz7nV6S0FyQSg",
          "width": 800
        },
        "dc": {
          "extension": "jpg",
          "height": 527,
          "mimetype": "image/jpeg",
          "secret": "YF3xJ9GzxdwCg2iLqKOdz7nV6S0FyQSg",
          "width": 800
        },
        "ds": {
          "extension": "jpg",
          "height": 320,
          "mimetype": "image/jpeg",
          "secret": "YF3xJ9GzxdwCg2iLqKOdz7nV6S0FyQSg",
          "width": 320
        },
        "k": {
          "extension": "jpg",
          "height": 1350,
          "mimetype": "image/jpeg",
          "secret": "YF3xJ9GzxdwCg2iLqKOdz7nV6S0FyQSg",
          "width": 2048
        },
        "n": {
          "extension": "jpg",
          "height": 210,
          "mimetype": "image/jpeg",
          "secret": "YF3xJ9GzxdwCg2iLqKOdz7nV6S0FyQSg",
          "width": 320
        },
        "o": {
          "extension": "jpg",
          "height": 1058,
          "mimetype": "image/jpeg",
          "secret": "hGwx3eZJ2BEuAWtjn9axsDtXPWAy35r1",
          "width": 1605
        },
        "s": {
          "extension": "jpg",
          "height": 320,
          "mimetype": "image/jpeg",
          "secret": "YF3xJ9GzxdwCg2iLqKOdz7nV6S0FyQSg",
          "width": 320
        },
        "z": {
          "extension": "jpg",
          "height": 421,
          "mimetype": "image/jpeg",
          "secret": "YF3xJ9GzxdwCg2iLqKOdz7nV6S0FyQSg",
          "width": 640
        }
      }
    },
    "media:uri_template": "https://static.sfomuseum.org/media/152/782/835/1/1527828351_{secret}_{label}.{extention}",
    "sfomuseum:filename": "44553.tif",
    "sfomuseum:image_index": 5,
    "sfomuseum:image_type": "studio",
    "sfomuseum:placetype": "image",
    "sfomuseum:primary_image": 1,
    "wof:depicts": [
      102527513,
      1511949383
    ],
    "wof:name": "negative: San Francisco International Airport (SFO)",
    "wof:placetype": "custom",
    "wof:placetype_alt": "image"
  },
  "geometry": {"coordinates":[-122.386155,37.616358],"type":"Point"}
}
