{
  "type": "Feature",
  "properties": {
    "iso:country": "XX",
    "media:fingerprint": "825f9be5bc48ef4c57eefcc6fa93ffbf947806ba",
    "media:imagehash_avg": "a:3f7e1c0080030f2f",
    "media:imagehash_diff": "d:f9d8f0241c5fdfdc",
    "media:medium": "image",
    "media:mimetype": "image/tiff",
    "media:properties": {
      "colours": [
        {
          "hex": "#808080",
          "name": "#808080",
          "reference": "vibrant"
        }, 
        {
          "hex": "#c0c0c0",
          "name": "#c0c0c0",
          "reference": "vibrant"
        }, 
        {
          "hex": "#404040",
          "name": "#404040",
          "reference": "vibrant"
        }
      ],
      "sizes": {
        "b": {
          "extension": "jpg",
          "height": 768,
          "mimetype": "image/jpeg",
          "secret": "fFeNyXDbmyOnyvTen1bgD2FMqOYHBSVz",
          "width": 767
        },
        "c": {
          "extension": "jpg",
          "height": 600,
          "mimetype": "image/jpeg",
          "secret": "fFeNyXDbmyOnyvTen1bgD2FMqOYHBSVz",
          "width": 599
        },
        "dc": {
          "extension": "jpg",
          "height": 600,
          "mimetype": "image/jpeg",
          "secret": "fFeNyXDbmyOnyvTen1bgD2FMqOYHBSVz",
          "width": 599
        },
        "ds": {
          "extension": "jpg",
          "height": 320,
          "mimetype": "image/jpeg",
          "secret": "fFeNyXDbmyOnyvTen1bgD2FMqOYHBSVz",
          "width": 320
        },
        "k": {
          "extension": "jpg",
          "height": 1536,
          "mimetype": "image/jpeg",
          "secret": "fFeNyXDbmyOnyvTen1bgD2FMqOYHBSVz",
          "width": 1535
        },
        "n": {
          "extension": "jpg",
          "height": 240,
          "mimetype": "image/jpeg",
          "secret": "fFeNyXDbmyOnyvTen1bgD2FMqOYHBSVz",
          "width": 239
        },
        "o": {
          "extension": "jpg",
          "height": 1836,
          "mimetype": "image/jpeg",
          "secret": "kSDsbQdiGKnmyBROQvsnVG1EMk9znFD7",
          "width": 1835
        },
        "s": {
          "extension": "jpg",
          "height": 320,
          "mimetype": "image/jpeg",
          "secret": "fFeNyXDbmyOnyvTen1bgD2FMqOYHBSVz",
          "width": 320
        },
        "z": {
          "extension": "jpg",
          "height": 480,
          "mimetype": "image/jpeg",
          "secret": "fFeNyXDbmyOnyvTen1bgD2FMqOYHBSVz",
          "width": 479
        }
      }
    },
    "media:uri_template": "https://millsfield.sfomuseum.org/media/152/782/644/7/1527826447_{secret}_{label}.{extention}",
    "sfomuseum:filename": "43644.tif",
    "sfomuseum:image_index": 5,
    "sfomuseum:placetype": "image",
    "sfomuseum:primary_image": 1,
    "wof:depicts": [
      1511947487
    ],
    "wof:name": "photograph: San Francisco International Airport (SFO), Delta Air Lines building construction",
    "wof:placetype": "media"
  },
  "geometry": {"coordinates":[-122.386155,37.616358],"type":"Point"}
}
