{
  "type": "Feature",
  "properties": {
    "iso:country": "XX",
    "media:fingerprint": "08235e392701d0ceb43f2d1bd3d330d4defb8c80",
    "media:imagehash_avg": "a:01ffe7e727070737",
    "media:imagehash_diff": "d:e75f4d4d4fcfcd6d",
    "media:medium": "image",
    "media:mimetype": "image/tiff",
    "media:properties": {
      "colours": [
        {
          "hex": "#f1e8e0",
          "name": "#f1e8e0",
          "reference": "vibrant"
        }, 
        {
          "hex": "#71808f",
          "name": "#71808f",
          "reference": "vibrant"
        }, 
        {
          "hex": "#c3baaf",
          "name": "#c3baaf",
          "reference": "vibrant"
        }, 
        {
          "hex": "#4b4945",
          "name": "#4b4945",
          "reference": "vibrant"
        }
      ],
      "sizes": {
        "b": {
          "extension": "jpg",
          "height": 768,
          "mimetype": "image/jpeg",
          "secret": "zGYSkZGtDmkTYJLixkBcQWn6WzT9l1Rx",
          "width": 507
        },
        "c": {
          "extension": "jpg",
          "height": 600,
          "mimetype": "image/jpeg",
          "secret": "zGYSkZGtDmkTYJLixkBcQWn6WzT9l1Rx",
          "width": 396
        },
        "dc": {
          "extension": "jpg",
          "height": 600,
          "mimetype": "image/jpeg",
          "secret": "zGYSkZGtDmkTYJLixkBcQWn6WzT9l1Rx",
          "width": 396
        },
        "ds": {
          "extension": "jpg",
          "height": 320,
          "mimetype": "image/jpeg",
          "secret": "zGYSkZGtDmkTYJLixkBcQWn6WzT9l1Rx",
          "width": 320
        },
        "k": {
          "extension": "jpg",
          "height": 1536,
          "mimetype": "image/jpeg",
          "secret": "zGYSkZGtDmkTYJLixkBcQWn6WzT9l1Rx",
          "width": 1014
        },
        "n": {
          "extension": "jpg",
          "height": 240,
          "mimetype": "image/jpeg",
          "secret": "zGYSkZGtDmkTYJLixkBcQWn6WzT9l1Rx",
          "width": 158
        },
        "o": {
          "extension": "jpg",
          "height": 2706,
          "mimetype": "image/jpeg",
          "secret": "GVlswh1qjPatOynYbia85CjVjVrC9QYo",
          "width": 1788
        },
        "s": {
          "extension": "jpg",
          "height": 320,
          "mimetype": "image/jpeg",
          "secret": "zGYSkZGtDmkTYJLixkBcQWn6WzT9l1Rx",
          "width": 320
        },
        "z": {
          "extension": "jpg",
          "height": 480,
          "mimetype": "image/jpeg",
          "secret": "zGYSkZGtDmkTYJLixkBcQWn6WzT9l1Rx",
          "width": 317
        }
      }
    },
    "media:uri_template": "https://millsfield.sfomuseum.org/media/152/782/358/7/1527823587_{secret}_{label}.{extention}",
    "sfomuseum:filename": "41674.tif",
    "sfomuseum:image_index": 5,
    "sfomuseum:placetype": "image",
    "sfomuseum:primary_image": 0,
    "wof:depicts": [
      1511908447
    ],
    "wof:name": "airsickness bag: Braniff International",
    "wof:placetype": "media"
  },
  "geometry": {"coordinates":[-122.386155,37.616358],"type":"Point"}
}
