{
  "type": "Feature",
  "properties": {
    "iso:country": "MM",
    "media:fingerprint": "b110eae28b1375f276e501b25bd4fd6f4c027c31",
    "media:imagehash_avg": "a:407e7f7e77667600",
    "media:imagehash_diff": "d:9b9adcdecccccc2b",
    "media:medium": "image",
    "media:mimetype": "image/tiff",
    "media:properties": {
      "colours": [
        {
          "hex": "#dd1a1c",
          "name": "#dd1a1c",
          "reference": "vibrant"
        }, 
        {
          "hex": "#f36869",
          "name": "#f36869",
          "reference": "vibrant"
        }, 
        {
          "hex": "#293b9d",
          "name": "#293b9d",
          "reference": "vibrant"
        }, 
        {
          "hex": "#7d7e91",
          "name": "#7d7e91",
          "reference": "vibrant"
        }, 
        {
          "hex": "#959ed0",
          "name": "#959ed0",
          "reference": "vibrant"
        }
      ],
      "sizes": {
        "b": {
          "extension": "jpg",
          "height": 588,
          "mimetype": "image/jpeg",
          "secret": "25n1zK1iSYT5swRO5ZCWnZynuKIpU5ey",
          "width": 1024
        },
        "c": {
          "extension": "jpg",
          "height": 459,
          "mimetype": "image/jpeg",
          "secret": "25n1zK1iSYT5swRO5ZCWnZynuKIpU5ey",
          "width": 800
        },
        "dc": {
          "extension": "jpg",
          "height": 459,
          "mimetype": "image/jpeg",
          "secret": "25n1zK1iSYT5swRO5ZCWnZynuKIpU5ey",
          "width": 800
        },
        "ds": {
          "extension": "jpg",
          "height": 320,
          "mimetype": "image/jpeg",
          "secret": "25n1zK1iSYT5swRO5ZCWnZynuKIpU5ey",
          "width": 320
        },
        "k": {
          "extension": "jpg",
          "height": 1176,
          "mimetype": "image/jpeg",
          "secret": "25n1zK1iSYT5swRO5ZCWnZynuKIpU5ey",
          "width": 2048
        },
        "n": {
          "extension": "jpg",
          "height": 183,
          "mimetype": "image/jpeg",
          "secret": "25n1zK1iSYT5swRO5ZCWnZynuKIpU5ey",
          "width": 320
        },
        "o": {
          "extension": "jpg",
          "height": 1158,
          "mimetype": "image/jpeg",
          "secret": "hgmsRM04kfWtfGQ8mADYoeHtQDnWfW24",
          "width": 2016
        },
        "s": {
          "extension": "jpg",
          "height": 320,
          "mimetype": "image/jpeg",
          "secret": "25n1zK1iSYT5swRO5ZCWnZynuKIpU5ey",
          "width": 320
        },
        "z": {
          "extension": "jpg",
          "height": 367,
          "mimetype": "image/jpeg",
          "secret": "25n1zK1iSYT5swRO5ZCWnZynuKIpU5ey",
          "width": 640
        }
      }
    },
    "media:uri_template": "https://millsfield.sfomuseum.org/media/152/782/951/9/1527829519_{secret}_{label}.{extention}",
    "sfomuseum:filename": "48279.tif",
    "sfomuseum:image_index": 5,
    "sfomuseum:placetype": "image",
    "sfomuseum:primary_image": 0,
    "wof:depicts": [
      1511907015
    ],
    "wof:name": "airmail flight cover: Pan American World Airways, Rangoon - Tokyo route",
    "wof:placetype": "media"
  },
  "geometry": {"coordinates":[-122.386155,37.616358],"type":"Point"}
}
