{
  "type": "Feature",
  "properties": {
    "iso:country": "XX",
    "media:fingerprint": "64627a1d6bdf8cd0d87fb12bbf47899208d656b6",
    "media:imagehash_avg": "a:7efffe783e1af0c0",
    "media:imagehash_diff": "d:c0c8c0c0ecf24481",
    "media:medium": "image",
    "media:mimetype": "image/tiff",
    "media:properties": {
      "colours": [
        {
          "hex": "#808080",
          "name": "#808080",
          "reference": "vibrant"
        }, 
        {
          "hex": "#b6b6b6",
          "name": "#b6b6b6",
          "reference": "vibrant"
        }, 
        {
          "hex": "#404040",
          "name": "#404040",
          "reference": "vibrant"
        }
      ],
      "sizes": {
        "b": {
          "extension": "jpg",
          "height": 768,
          "mimetype": "image/jpeg",
          "secret": "C10r9woUI8WaYPZasmiyEujENRXliEUr",
          "width": 972
        },
        "c": {
          "extension": "jpg",
          "height": 600,
          "mimetype": "image/jpeg",
          "secret": "C10r9woUI8WaYPZasmiyEujENRXliEUr",
          "width": 759
        },
        "dc": {
          "extension": "jpg",
          "height": 600,
          "mimetype": "image/jpeg",
          "secret": "C10r9woUI8WaYPZasmiyEujENRXliEUr",
          "width": 759
        },
        "ds": {
          "extension": "jpg",
          "height": 320,
          "mimetype": "image/jpeg",
          "secret": "C10r9woUI8WaYPZasmiyEujENRXliEUr",
          "width": 320
        },
        "k": {
          "extension": "jpg",
          "height": 1536,
          "mimetype": "image/jpeg",
          "secret": "C10r9woUI8WaYPZasmiyEujENRXliEUr",
          "width": 1944
        },
        "n": {
          "extension": "jpg",
          "height": 240,
          "mimetype": "image/jpeg",
          "secret": "C10r9woUI8WaYPZasmiyEujENRXliEUr",
          "width": 303
        },
        "o": {
          "extension": "jpg",
          "height": 2154,
          "mimetype": "image/jpeg",
          "secret": "xiPv8cHp3WerFXiE4IbWNnKiGyOpo3jc",
          "width": 2727
        },
        "s": {
          "extension": "jpg",
          "height": 320,
          "mimetype": "image/jpeg",
          "secret": "C10r9woUI8WaYPZasmiyEujENRXliEUr",
          "width": 320
        },
        "z": {
          "extension": "jpg",
          "height": 480,
          "mimetype": "image/jpeg",
          "secret": "C10r9woUI8WaYPZasmiyEujENRXliEUr",
          "width": 607
        }
      }
    },
    "media:uri_template": "https://millsfield.sfomuseum.org/media/152/782/395/9/1527823959_{secret}_{label}.{extention}",
    "sfomuseum:filename": "41891.tif",
    "sfomuseum:image_index": 5,
    "sfomuseum:placetype": "image",
    "sfomuseum:primary_image": 1,
    "wof:depicts": [
      1511945281
    ],
    "wof:name": "negative: San Francisco International Airport (SFO), parking garage construction",
    "wof:placetype": "media"
  },
  "geometry": {"coordinates":[-122.386155,37.616358],"type":"Point"}
}
