{
  "type": "Feature",
  "properties": {
    "iso:country": "XX",
    "media:fingerprint": "9680d41329f8a11a17ddd12dd3a443a5aee70af2",
    "media:imagehash_avg": "a:1f3f7f7f1f000000",
    "media:imagehash_diff": "d:fcf8f2f4f5f7f6f1",
    "media:medium": "image",
    "media:mimetype": "image/tiff",
    "media:properties": {
      "colours": [
        {
          "hex": "#868686",
          "name": "#868686",
          "reference": "vibrant"
        }, 
        {
          "hex": "#b8b8b8",
          "name": "#b8b8b8",
          "reference": "vibrant"
        }, 
        {
          "hex": "#464646",
          "name": "#464646",
          "reference": "vibrant"
        }
      ],
      "sizes": {
        "b": {
          "extension": "jpg",
          "height": 768,
          "mimetype": "image/jpeg",
          "secret": "vpjo5oNMeXmVhxAEjUhkOgxIOLjYnbMK",
          "width": 991
        },
        "c": {
          "extension": "jpg",
          "height": 600,
          "mimetype": "image/jpeg",
          "secret": "vpjo5oNMeXmVhxAEjUhkOgxIOLjYnbMK",
          "width": 774
        },
        "dc": {
          "extension": "jpg",
          "height": 600,
          "mimetype": "image/jpeg",
          "secret": "vpjo5oNMeXmVhxAEjUhkOgxIOLjYnbMK",
          "width": 774
        },
        "ds": {
          "extension": "jpg",
          "height": 320,
          "mimetype": "image/jpeg",
          "secret": "vpjo5oNMeXmVhxAEjUhkOgxIOLjYnbMK",
          "width": 320
        },
        "k": {
          "extension": "jpg",
          "height": 1536,
          "mimetype": "image/jpeg",
          "secret": "vpjo5oNMeXmVhxAEjUhkOgxIOLjYnbMK",
          "width": 1983
        },
        "n": {
          "extension": "jpg",
          "height": 240,
          "mimetype": "image/jpeg",
          "secret": "vpjo5oNMeXmVhxAEjUhkOgxIOLjYnbMK",
          "width": 309
        },
        "o": {
          "extension": "jpg",
          "height": 2154,
          "mimetype": "image/jpeg",
          "secret": "P9iecw0hOP0kMs6y4WcbPswm5gMLkwu5",
          "width": 2781
        },
        "s": {
          "extension": "jpg",
          "height": 320,
          "mimetype": "image/jpeg",
          "secret": "vpjo5oNMeXmVhxAEjUhkOgxIOLjYnbMK",
          "width": 320
        },
        "z": {
          "extension": "jpg",
          "height": 480,
          "mimetype": "image/jpeg",
          "secret": "vpjo5oNMeXmVhxAEjUhkOgxIOLjYnbMK",
          "width": 619
        }
      }
    },
    "media:uri_template": "https://millsfield.sfomuseum.org/media/152/782/161/9/1527821619_{secret}_{label}.{extention}",
    "sfomuseum:filename": "38894.tif",
    "sfomuseum:image_index": 5,
    "sfomuseum:placetype": "image",
    "sfomuseum:primary_image": 1,
    "wof:depicts": [
      1511943695
    ],
    "wof:name": "negative: San Francisco Airport, passenger waiting room",
    "wof:placetype": "media"
  },
  "geometry": {"coordinates":[-122.386155,37.616358],"type":"Point"}
}
