{
  "type": "Feature",
  "properties": {
    "iso:country": "XX",
    "media:fingerprint": "df085dee3887d52c43d13dafba4a5299a50b9f7f",
    "media:imagehash_avg": "a:ffffffffffe1c1e3",
    "media:imagehash_diff": "d:c617c9cd8d8d8387",
    "media:medium": "image",
    "media:mimetype": "image/tiff",
    "media:properties": {
      "colours": [
        {
          "hex": "#376bbe",
          "name": "#376bbe",
          "reference": "vibrant"
        }, 
        {
          "hex": "#f8efe1",
          "name": "#f8efe1",
          "reference": "vibrant"
        }, 
        {
          "hex": "#363971",
          "name": "#363971",
          "reference": "vibrant"
        }, 
        {
          "hex": "#78828a",
          "name": "#78828a",
          "reference": "vibrant"
        }, 
        {
          "hex": "#b4b9bf",
          "name": "#b4b9bf",
          "reference": "vibrant"
        }
      ],
      "sizes": {
        "b": {
          "extension": "jpg",
          "height": 767,
          "mimetype": "image/jpeg",
          "secret": "gBjkWqapVIUISAyox1nJBSF1DlhyZJrL",
          "width": 414
        },
        "c": {
          "extension": "jpg",
          "height": 600,
          "mimetype": "image/jpeg",
          "secret": "gBjkWqapVIUISAyox1nJBSF1DlhyZJrL",
          "width": 324
        },
        "dc": {
          "extension": "jpg",
          "height": 600,
          "mimetype": "image/jpeg",
          "secret": "gBjkWqapVIUISAyox1nJBSF1DlhyZJrL",
          "width": 324
        },
        "ds": {
          "extension": "jpg",
          "height": 320,
          "mimetype": "image/jpeg",
          "secret": "gBjkWqapVIUISAyox1nJBSF1DlhyZJrL",
          "width": 320
        },
        "k": {
          "extension": "jpg",
          "height": 1535,
          "mimetype": "image/jpeg",
          "secret": "gBjkWqapVIUISAyox1nJBSF1DlhyZJrL",
          "width": 829
        },
        "n": {
          "extension": "jpg",
          "height": 240,
          "mimetype": "image/jpeg",
          "secret": "gBjkWqapVIUISAyox1nJBSF1DlhyZJrL",
          "width": 129
        },
        "o": {
          "extension": "jpg",
          "height": 2874,
          "mimetype": "image/jpeg",
          "secret": "VgsnUHtDUdEjY71BkItXydFA0r2jHVGI",
          "width": 1553
        },
        "s": {
          "extension": "jpg",
          "height": 320,
          "mimetype": "image/jpeg",
          "secret": "gBjkWqapVIUISAyox1nJBSF1DlhyZJrL",
          "width": 320
        },
        "z": {
          "extension": "jpg",
          "height": 480,
          "mimetype": "image/jpeg",
          "secret": "gBjkWqapVIUISAyox1nJBSF1DlhyZJrL",
          "width": 259
        }
      }
    },
    "media:uri_template": "https://millsfield.sfomuseum.org/media/152/782/355/9/1527823559_{secret}_{label}.{extention}",
    "sfomuseum:filename": "41661.tif",
    "sfomuseum:image_index": 5,
    "sfomuseum:placetype": "image",
    "sfomuseum:primary_image": 1,
    "wof:depicts": [
      1511908431
    ],
    "wof:name": "airsickness bag: ANA (All Nippon Airways)",
    "wof:placetype": "media"
  },
  "geometry": {"coordinates":[-122.386155,37.616358],"type":"Point"}
}
