{
  "type": "Feature",
  "properties": {
    "iso:country": "XX",
    "media:fingerprint": "a118deeaf89d43de678fd938cdc7742db6aa5cf4",
    "media:imagehash_avg": "a:0390f0fdffffff80",
    "media:imagehash_diff": "d:7363e1d1c5a3930a",
    "media:medium": "image",
    "media:mimetype": "image/tiff",
    "media:properties": {
      "colours": [
        {
          "hex": "#c3351e",
          "name": "#c3351e",
          "reference": "vibrant"
        }, 
        {
          "hex": "#d8c196",
          "name": "#d8c196",
          "reference": "vibrant"
        }, 
        {
          "hex": "#b11905",
          "name": "#b11905",
          "reference": "vibrant"
        }, 
        {
          "hex": "#8c8971",
          "name": "#8c8971",
          "reference": "vibrant"
        }, 
        {
          "hex": "#d0ba96",
          "name": "#d0ba96",
          "reference": "vibrant"
        }
      ],
      "sizes": {
        "b": {
          "extension": "jpg",
          "height": 579,
          "mimetype": "image/jpeg",
          "secret": "uJ1Ydf4F9sRukcHdileJPquiAbrG0TCw",
          "width": 1024
        },
        "c": {
          "extension": "jpg",
          "height": 452,
          "mimetype": "image/jpeg",
          "secret": "uJ1Ydf4F9sRukcHdileJPquiAbrG0TCw",
          "width": 800
        },
        "dc": {
          "extension": "jpg",
          "height": 452,
          "mimetype": "image/jpeg",
          "secret": "uJ1Ydf4F9sRukcHdileJPquiAbrG0TCw",
          "width": 800
        },
        "ds": {
          "extension": "jpg",
          "height": 320,
          "mimetype": "image/jpeg",
          "secret": "uJ1Ydf4F9sRukcHdileJPquiAbrG0TCw",
          "width": 320
        },
        "k": {
          "extension": "jpg",
          "height": 1158,
          "mimetype": "image/jpeg",
          "secret": "uJ1Ydf4F9sRukcHdileJPquiAbrG0TCw",
          "width": 2048
        },
        "n": {
          "extension": "jpg",
          "height": 180,
          "mimetype": "image/jpeg",
          "secret": "uJ1Ydf4F9sRukcHdileJPquiAbrG0TCw",
          "width": 320
        },
        "o": {
          "extension": "jpg",
          "height": 1132,
          "mimetype": "image/jpeg",
          "secret": "Oz19fin2MrCPExzrj3cpmAk5A6AWVx6Y",
          "width": 2002
        },
        "s": {
          "extension": "jpg",
          "height": 320,
          "mimetype": "image/jpeg",
          "secret": "uJ1Ydf4F9sRukcHdileJPquiAbrG0TCw",
          "width": 320
        },
        "z": {
          "extension": "jpg",
          "height": 361,
          "mimetype": "image/jpeg",
          "secret": "uJ1Ydf4F9sRukcHdileJPquiAbrG0TCw",
          "width": 640
        }
      }
    },
    "media:uri_template": "https://millsfield.sfomuseum.org/media/152/782/041/7/1527820417_{secret}_{label}.{extention}",
    "sfomuseum:filename": "31600.tif",
    "sfomuseum:image_index": 5,
    "sfomuseum:placetype": "image",
    "sfomuseum:primary_image": 1,
    "wof:depicts": [
      1511924621
    ],
    "wof:name": "airmail flight cover: New Zealand - Canton Island route",
    "wof:placetype": "media"
  },
  "geometry": {"coordinates":[-122.386155,37.616358],"type":"Point"}
}
