{
  "type": "Feature",
  "properties": {
    "iso:country": "XX",
    "media:fingerprint": "3973f584f0a933c25c235f9bccf1d7074c10bd7d",
    "media:imagehash_avg": "a:000008383efefc3e",
    "media:imagehash_diff": "d:f0f0f8f362786062",
    "media:medium": "image",
    "media:mimetype": "image/tiff",
    "media:properties": {
      "colours": [
        {
          "hex": "#808080",
          "name": "#808080",
          "reference": "vibrant"
        },
        {
          "hex": "#c0c0c0",
          "name": "#c0c0c0",
          "reference": "vibrant"
        },
        {
          "hex": "#484848",
          "name": "#484848",
          "reference": "vibrant"
        }
      ],
      "sizes": {
        "b": {
          "extension": "jpg",
          "height": 768,
          "mimetype": "image/jpeg",
          "secret": "gIxH7OEISQwoELZsKcUsCAyNUo7KSLOk",
          "width": 968
        },
        "c": {
          "extension": "jpg",
          "height": 600,
          "mimetype": "image/jpeg",
          "secret": "gIxH7OEISQwoELZsKcUsCAyNUo7KSLOk",
          "width": 756
        },
        "dc": {
          "extension": "jpg",
          "height": 600,
          "mimetype": "image/jpeg",
          "secret": "gIxH7OEISQwoELZsKcUsCAyNUo7KSLOk",
          "width": 756
        },
        "ds": {
          "extension": "jpg",
          "height": 320,
          "mimetype": "image/jpeg",
          "secret": "gIxH7OEISQwoELZsKcUsCAyNUo7KSLOk",
          "width": 320
        },
        "k": {
          "extension": "jpg",
          "height": 1536,
          "mimetype": "image/jpeg",
          "secret": "gIxH7OEISQwoELZsKcUsCAyNUo7KSLOk",
          "width": 1936
        },
        "n": {
          "extension": "jpg",
          "height": 240,
          "mimetype": "image/jpeg",
          "secret": "gIxH7OEISQwoELZsKcUsCAyNUo7KSLOk",
          "width": 302
        },
        "o": {
          "extension": "jpg",
          "height": 2195,
          "mimetype": "image/jpeg",
          "secret": "P0Uwvyvc2uIrWQ4ZjFlhFp6w8Nd5izKS",
          "width": 2768
        },
        "s": {
          "extension": "jpg",
          "height": 320,
          "mimetype": "image/jpeg",
          "secret": "gIxH7OEISQwoELZsKcUsCAyNUo7KSLOk",
          "width": 320
        },
        "z": {
          "extension": "jpg",
          "height": 480,
          "mimetype": "image/jpeg",
          "secret": "gIxH7OEISQwoELZsKcUsCAyNUo7KSLOk",
          "width": 605
        }
      }
    },
    "media:uri_template": "https://static.sfomuseum.org/media/152/782/576/3/1527825763_{secret}_{label}.{extention}",
    "sfomuseum:filename": "43325.tif",
    "sfomuseum:image_index": 5,
    "sfomuseum:image_type": "studio",
    "sfomuseum:placetype": "image",
    "sfomuseum:primary_image": 1,
    "wof:depicts": [
      102527513,
      1511946799
    ],
    "wof:name": "negative: San Francisco International Airport (SFO), aerial",
    "wof:placetype": "custom",
    "wof:placetype_alt": "image"
  },
  "geometry": {"coordinates":[-122.386155,37.616358],"type":"Point"}
}
