{
  "type": "Feature",
  "properties": {
    "iso:country": "PH",
    "media:fingerprint": "bd36dd98f7a29d76e2ead326aca5d903df6e5c26",
    "media:imagehash_avg": "a:0338f8d99fdbffe1",
    "media:imagehash_diff": "d:57f1b1313137a62b",
    "media:medium": "image",
    "media:mimetype": "image/tiff",
    "media:properties": {
      "colours": [
        {
          "hex": "#b12512",
          "name": "#b12512",
          "reference": "vibrant"
        }, 
        {
          "hex": "#a81f09",
          "name": "#a81f09",
          "reference": "vibrant"
        }, 
        {
          "hex": "#a17f6c",
          "name": "#a17f6c",
          "reference": "vibrant"
        }, 
        {
          "hex": "#d8bdb2",
          "name": "#d8bdb2",
          "reference": "vibrant"
        }, 
        {
          "hex": "#4a4f54",
          "name": "#4a4f54",
          "reference": "vibrant"
        }
      ],
      "sizes": {
        "b": {
          "extension": "jpg",
          "height": 574,
          "mimetype": "image/jpeg",
          "secret": "OAOCr71iEQiPXfBJfHyZwCpuFmYCKWUz",
          "width": 1023
        },
        "c": {
          "extension": "jpg",
          "height": 448,
          "mimetype": "image/jpeg",
          "secret": "OAOCr71iEQiPXfBJfHyZwCpuFmYCKWUz",
          "width": 800
        },
        "dc": {
          "extension": "jpg",
          "height": 448,
          "mimetype": "image/jpeg",
          "secret": "OAOCr71iEQiPXfBJfHyZwCpuFmYCKWUz",
          "width": 800
        },
        "ds": {
          "extension": "jpg",
          "height": 320,
          "mimetype": "image/jpeg",
          "secret": "OAOCr71iEQiPXfBJfHyZwCpuFmYCKWUz",
          "width": 320
        },
        "k": {
          "extension": "jpg",
          "height": 1148,
          "mimetype": "image/jpeg",
          "secret": "OAOCr71iEQiPXfBJfHyZwCpuFmYCKWUz",
          "width": 2047
        },
        "n": {
          "extension": "jpg",
          "height": 179,
          "mimetype": "image/jpeg",
          "secret": "OAOCr71iEQiPXfBJfHyZwCpuFmYCKWUz",
          "width": 320
        },
        "o": {
          "extension": "jpg",
          "height": 1117,
          "mimetype": "image/jpeg",
          "secret": "pbPTkZLzKvCe1gd7YaE249SmMd0jrgje",
          "width": 1992
        },
        "s": {
          "extension": "jpg",
          "height": 320,
          "mimetype": "image/jpeg",
          "secret": "OAOCr71iEQiPXfBJfHyZwCpuFmYCKWUz",
          "width": 320
        },
        "z": {
          "extension": "jpg",
          "height": 358,
          "mimetype": "image/jpeg",
          "secret": "OAOCr71iEQiPXfBJfHyZwCpuFmYCKWUz",
          "width": 640
        }
      }
    },
    "media:uri_template": "https://millsfield.sfomuseum.org/media/152/782/936/5/1527829365_{secret}_{label}.{extention}",
    "sfomuseum:filename": "48207.tif",
    "sfomuseum:image_index": 5,
    "sfomuseum:placetype": "image",
    "sfomuseum:primary_image": 1,
    "wof:depicts": [
      1511906951
    ],
    "wof:name": "airmail flight cover: Pan American World Airways, Manila - Bangkok route",
    "wof:placetype": "media"
  },
  "geometry": {"coordinates":[-122.386155,37.616358],"type":"Point"}
}
