{
  "type": "Feature",
  "properties": {
    "media:fingerprint": "d705e6e7c195e178f6649132d65165164851671e",
    "media:imagehash_avg": "a:010060747e7c387f",
    "media:imagehash_diff": "d:adc3818dcce8e1dd",
    "media:mimetype": "image/tiff",
    "media:properties": {
      "colours": [
        {
          "hex": "#7a7a7a",
          "name": "#7a7a7a",
          "reference": "vibrant"
        },
        {
          "hex": "#b6b6b6",
          "name": "#b6b6b6",
          "reference": "vibrant"
        },
        {
          "hex": "#484848",
          "name": "#484848",
          "reference": "vibrant"
        }
      ],
      "sizes": {
        "b": {
          "extension": "jpg",
          "height": 712,
          "mimetype": "image/jpeg",
          "secret": "XuGEfTrtrCTsSGjNjB4hOBREzB6w5p1O",
          "width": 1024
        },
        "c": {
          "extension": "jpg",
          "height": 556,
          "mimetype": "image/jpeg",
          "secret": "XuGEfTrtrCTsSGjNjB4hOBREzB6w5p1O",
          "width": 800
        },
        "dc": {
          "extension": "jpg",
          "height": 556,
          "mimetype": "image/jpeg",
          "secret": "XuGEfTrtrCTsSGjNjB4hOBREzB6w5p1O",
          "width": 800
        },
        "ds": {
          "extension": "jpg",
          "height": 320,
          "mimetype": "image/jpeg",
          "secret": "XuGEfTrtrCTsSGjNjB4hOBREzB6w5p1O",
          "width": 320
        },
        "k": {
          "extension": "jpg",
          "height": 1425,
          "mimetype": "image/jpeg",
          "secret": "XuGEfTrtrCTsSGjNjB4hOBREzB6w5p1O",
          "width": 2048
        },
        "n": {
          "extension": "jpg",
          "height": 222,
          "mimetype": "image/jpeg",
          "secret": "XuGEfTrtrCTsSGjNjB4hOBREzB6w5p1O",
          "width": 320
        },
        "o": {
          "extension": "jpg",
          "height": 3876,
          "mimetype": "image/jpeg",
          "secret": "P9HgcRfXngrhYIklOGhFiNXl4UuJ3ayc",
          "width": 5569
        },
        "s": {
          "extension": "jpg",
          "height": 320,
          "mimetype": "image/jpeg",
          "secret": "XuGEfTrtrCTsSGjNjB4hOBREzB6w5p1O",
          "width": 320
        },
        "z": {
          "extension": "jpg",
          "height": 445,
          "mimetype": "image/jpeg",
          "secret": "XuGEfTrtrCTsSGjNjB4hOBREzB6w5p1O",
          "width": 640
        }
      }
    },
    "media:uri_template": "https://static.sfomuseum.org/media/174/668/034/5/1746680345_{secret}_{label}.{extention}",
    "sfomuseum:filename": "54822.tif",
    "sfomuseum:image_index": 3,
    "sfomuseum:image_type": "curator",
    "sfomuseum:placetype": "image",
    "sfomuseum:primary_image": 1,
    "wof:depicts": [
      1159285395,
      1729564521,
      1159290415,
      1159287531
    ],
    "wof:name": "photograph: Transcontinental \u0026 Western Air (TWA), Douglas DC-2",
    "wof:placetype": "custom"
  },
  "geometry": {"coordinates":[-122.386155,37.616357],"type":"Point"}
}
