{
  "type": "Feature",
  "properties": {
    "iso:country": "XX",
    "media:fingerprint": "eab82443963571b157aec35e59e1eaf42024ebfc",
    "media:imagehash_avg": "a:ff0c1c3c1f1f0fff",
    "media:imagehash_diff": "d:1d7969697d79795d",
    "media:medium": "image",
    "media:mimetype": "image/tiff",
    "media:properties": {
      "colours": [
        {
          "hex": "#c7a32a",
          "name": "#c7a32a",
          "reference": "vibrant"
        }, 
        {
          "hex": "#d8c69e",
          "name": "#d8c69e",
          "reference": "vibrant"
        }, 
        {
          "hex": "#7f6e38",
          "name": "#7f6e38",
          "reference": "vibrant"
        }, 
        {
          "hex": "#958869",
          "name": "#958869",
          "reference": "vibrant"
        }, 
        {
          "hex": "#d2bb98",
          "name": "#d2bb98",
          "reference": "vibrant"
        }
      ],
      "sizes": {
        "b": {
          "extension": "jpg",
          "height": 464,
          "mimetype": "image/jpeg",
          "secret": "EuCzPZtnLeWR0IQ6CegkNWm5Kn0gC1JK",
          "width": 1024
        },
        "c": {
          "extension": "jpg",
          "height": 362,
          "mimetype": "image/jpeg",
          "secret": "EuCzPZtnLeWR0IQ6CegkNWm5Kn0gC1JK",
          "width": 800
        },
        "dc": {
          "extension": "jpg",
          "height": 362,
          "mimetype": "image/jpeg",
          "secret": "EuCzPZtnLeWR0IQ6CegkNWm5Kn0gC1JK",
          "width": 800
        },
        "ds": {
          "extension": "jpg",
          "height": 320,
          "mimetype": "image/jpeg",
          "secret": "EuCzPZtnLeWR0IQ6CegkNWm5Kn0gC1JK",
          "width": 320
        },
        "k": {
          "extension": "jpg",
          "height": 928,
          "mimetype": "image/jpeg",
          "secret": "EuCzPZtnLeWR0IQ6CegkNWm5Kn0gC1JK",
          "width": 2048
        },
        "n": {
          "extension": "jpg",
          "height": 145,
          "mimetype": "image/jpeg",
          "secret": "EuCzPZtnLeWR0IQ6CegkNWm5Kn0gC1JK",
          "width": 320
        },
        "o": {
          "extension": "jpg",
          "height": 1756,
          "mimetype": "image/jpeg",
          "secret": "iEha0EHQlP4fL0ran9GKP5SfvmBez7sd",
          "width": 3874
        },
        "s": {
          "extension": "jpg",
          "height": 320,
          "mimetype": "image/jpeg",
          "secret": "EuCzPZtnLeWR0IQ6CegkNWm5Kn0gC1JK",
          "width": 320
        },
        "z": {
          "extension": "jpg",
          "height": 290,
          "mimetype": "image/jpeg",
          "secret": "EuCzPZtnLeWR0IQ6CegkNWm5Kn0gC1JK",
          "width": 640
        }
      }
    },
    "media:uri_template": "https://millsfield.sfomuseum.org/media/152/781/825/9/1527818259_{secret}_{label}.{extention}",
    "sfomuseum:filename": "16318.tif",
    "sfomuseum:image_index": 5,
    "sfomuseum:placetype": "image",
    "sfomuseum:primary_image": 1,
    "wof:depicts": [
      1511931661
    ],
    "wof:name": "airmail flight cover: Archbold Trans-Pacific Flight, Honolulu - Hollandia, Dutch New Guinea",
    "wof:placetype": "media"
  },
  "geometry": {"coordinates":[-122.386155,37.616358],"type":"Point"}
}
