{
  "type": "Feature",
  "properties": {
    "iso:country": "XX",
    "media:fingerprint": "9cd0e63e3f820510079f38f38ac30ac615d9f1b3",
    "media:imagehash_avg": "a:ffc7c3c3c3c3c3ff",
    "media:imagehash_diff": "d:fc8e9e9697170f9c",
    "media:medium": "image",
    "media:mimetype": "image/tiff",
    "media:properties": {
      "colours": [
        {
          "hex": "#d24008",
          "name": "#d24008",
          "reference": "vibrant"
        }, 
        {
          "hex": "#f07f63",
          "name": "#f07f63",
          "reference": "vibrant"
        }, 
        {
          "hex": "#a42904",
          "name": "#a42904",
          "reference": "vibrant"
        }, 
        {
          "hex": "#9d776f",
          "name": "#9d776f",
          "reference": "vibrant"
        }, 
        {
          "hex": "#b8b8b8",
          "name": "#b8b8b8",
          "reference": "vibrant"
        }
      ],
      "sizes": {
        "b": {
          "extension": "jpg",
          "height": 768,
          "mimetype": "image/jpeg",
          "secret": "SILkYmjlK2qnHszVK8xUOhyeph7wCemB",
          "width": 965
        },
        "c": {
          "extension": "jpg",
          "height": 600,
          "mimetype": "image/jpeg",
          "secret": "SILkYmjlK2qnHszVK8xUOhyeph7wCemB",
          "width": 754
        },
        "dc": {
          "extension": "jpg",
          "height": 600,
          "mimetype": "image/jpeg",
          "secret": "SILkYmjlK2qnHszVK8xUOhyeph7wCemB",
          "width": 754
        },
        "ds": {
          "extension": "jpg",
          "height": 320,
          "mimetype": "image/jpeg",
          "secret": "SILkYmjlK2qnHszVK8xUOhyeph7wCemB",
          "width": 320
        },
        "k": {
          "extension": "jpg",
          "height": 1536,
          "mimetype": "image/jpeg",
          "secret": "SILkYmjlK2qnHszVK8xUOhyeph7wCemB",
          "width": 1931
        },
        "n": {
          "extension": "jpg",
          "height": 240,
          "mimetype": "image/jpeg",
          "secret": "SILkYmjlK2qnHszVK8xUOhyeph7wCemB",
          "width": 301
        },
        "o": {
          "extension": "jpg",
          "height": 1326,
          "mimetype": "image/jpeg",
          "secret": "UlL5ynCjvE96EFzbo9R3YQEXa6KWj91q",
          "width": 1667
        },
        "s": {
          "extension": "jpg",
          "height": 320,
          "mimetype": "image/jpeg",
          "secret": "SILkYmjlK2qnHszVK8xUOhyeph7wCemB",
          "width": 320
        },
        "z": {
          "extension": "jpg",
          "height": 480,
          "mimetype": "image/jpeg",
          "secret": "SILkYmjlK2qnHszVK8xUOhyeph7wCemB",
          "width": 603
        }
      }
    },
    "media:uri_template": "https://millsfield.sfomuseum.org/media/152/785/714/1/1527857141_{secret}_{label}.{extention}",
    "sfomuseum:filename": "2001.146.005ab_ft1.tif",
    "sfomuseum:image_index": 5,
    "sfomuseum:placetype": "image",
    "sfomuseum:primary_image": 1,
    "wof:depicts": [
      1511922379
    ],
    "wof:name": "airline bag: Aloha Airlines",
    "wof:placetype": "media"
  },
  "geometry": {"coordinates":[-122.386155,37.616358],"type":"Point"}
}
