{
  "type": "Feature",
  "properties": {
    "iso:country": "XX",
    "media:fingerprint": "7496a4f09c71059b06b16778e6d9e49ee79fd502",
    "media:imagehash_avg": "a:ffff010111010101",
    "media:imagehash_diff": "d:e9fddfe3e1e5616f",
    "media:medium": "image",
    "media:mimetype": "image/tiff",
    "media:properties": {
      "colours": [
        {
          "hex": "#808080",
          "name": "#808080",
          "reference": "vibrant"
        }, 
        {
          "hex": "#c0c0c0",
          "name": "#c0c0c0",
          "reference": "vibrant"
        }, 
        {
          "hex": "#484848",
          "name": "#484848",
          "reference": "vibrant"
        }
      ],
      "sizes": {
        "b": {
          "extension": "jpg",
          "height": 724,
          "mimetype": "image/jpeg",
          "secret": "OdieZnbD10Neus2sypVWY1PyP3eUtcSv",
          "width": 1024
        },
        "c": {
          "extension": "jpg",
          "height": 566,
          "mimetype": "image/jpeg",
          "secret": "OdieZnbD10Neus2sypVWY1PyP3eUtcSv",
          "width": 800
        },
        "dc": {
          "extension": "jpg",
          "height": 566,
          "mimetype": "image/jpeg",
          "secret": "OdieZnbD10Neus2sypVWY1PyP3eUtcSv",
          "width": 800
        },
        "ds": {
          "extension": "jpg",
          "height": 320,
          "mimetype": "image/jpeg",
          "secret": "OdieZnbD10Neus2sypVWY1PyP3eUtcSv",
          "width": 320
        },
        "k": {
          "extension": "jpg",
          "height": 1449,
          "mimetype": "image/jpeg",
          "secret": "OdieZnbD10Neus2sypVWY1PyP3eUtcSv",
          "width": 2048
        },
        "n": {
          "extension": "jpg",
          "height": 226,
          "mimetype": "image/jpeg",
          "secret": "OdieZnbD10Neus2sypVWY1PyP3eUtcSv",
          "width": 320
        },
        "o": {
          "extension": "jpg",
          "height": 5976,
          "mimetype": "image/jpeg",
          "secret": "M1PutdPEuElobxF7dzaHPSmv5m5QB2vA",
          "width": 8446
        },
        "s": {
          "extension": "jpg",
          "height": 320,
          "mimetype": "image/jpeg",
          "secret": "OdieZnbD10Neus2sypVWY1PyP3eUtcSv",
          "width": 320
        },
        "z": {
          "extension": "jpg",
          "height": 452,
          "mimetype": "image/jpeg",
          "secret": "OdieZnbD10Neus2sypVWY1PyP3eUtcSv",
          "width": 640
        }
      }
    },
    "media:uri_template": "https://millsfield.sfomuseum.org/media/152/782/128/7/1527821287_{secret}_{label}.{extention}",
    "sfomuseum:filename": "38671.tif",
    "sfomuseum:image_index": 5,
    "sfomuseum:placetype": "image",
    "sfomuseum:primary_image": 1,
    "wof:depicts": [
      1511949785
    ],
    "wof:name": "negative: Mills Field Municipal Airport of San Francisco, Hangar No. 2 construction",
    "wof:placetype": "media"
  },
  "geometry": {"coordinates":[-122.386155,37.616358],"type":"Point"}
}
