{
  "type": "Feature",
  "properties": {
    "iso:country": "XX",
    "media:fingerprint": "26c429dea458ebc81557ee48b32e1aff66c91e23",
    "media:imagehash_avg": "a:0c0c0e3f3e3f1e1e",
    "media:imagehash_diff": "d:f8f8f878f0f3eafc",
    "media:medium": "image",
    "media:mimetype": "image/tiff",
    "media:properties": {
      "colours": [
        {
          "hex": "#868686",
          "name": "#868686",
          "reference": "vibrant"
        },
        {
          "hex": "#c0c0c0",
          "name": "#c0c0c0",
          "reference": "vibrant"
        },
        {
          "hex": "#484848",
          "name": "#484848",
          "reference": "vibrant"
        }
      ],
      "sizes": {
        "b": {
          "extension": "jpg",
          "height": 767,
          "mimetype": "image/jpeg",
          "secret": "HGkjgBF7naERBSUErp1vztkxvkqsePCY",
          "width": 988
        },
        "c": {
          "extension": "jpg",
          "height": 600,
          "mimetype": "image/jpeg",
          "secret": "HGkjgBF7naERBSUErp1vztkxvkqsePCY",
          "width": 772
        },
        "dc": {
          "extension": "jpg",
          "height": 600,
          "mimetype": "image/jpeg",
          "secret": "HGkjgBF7naERBSUErp1vztkxvkqsePCY",
          "width": 772
        },
        "ds": {
          "extension": "jpg",
          "height": 320,
          "mimetype": "image/jpeg",
          "secret": "HGkjgBF7naERBSUErp1vztkxvkqsePCY",
          "width": 320
        },
        "k": {
          "extension": "jpg",
          "height": 1535,
          "mimetype": "image/jpeg",
          "secret": "HGkjgBF7naERBSUErp1vztkxvkqsePCY",
          "width": 1976
        },
        "n": {
          "extension": "jpg",
          "height": 240,
          "mimetype": "image/jpeg",
          "secret": "HGkjgBF7naERBSUErp1vztkxvkqsePCY",
          "width": 308
        },
        "o": {
          "extension": "jpg",
          "height": 2140,
          "mimetype": "image/jpeg",
          "secret": "cIHvhWQaEfnReKmbl4QKcJGCrKPBWiyI",
          "width": 2754
        },
        "s": {
          "extension": "jpg",
          "height": 320,
          "mimetype": "image/jpeg",
          "secret": "HGkjgBF7naERBSUErp1vztkxvkqsePCY",
          "width": 320
        },
        "z": {
          "extension": "jpg",
          "height": 480,
          "mimetype": "image/jpeg",
          "secret": "HGkjgBF7naERBSUErp1vztkxvkqsePCY",
          "width": 617
        }
      }
    },
    "media:uri_template": "https://static.sfomuseum.org/media/152/782/255/7/1527822557_{secret}_{label}.{extention}",
    "sfomuseum:filename": "40801.tif",
    "sfomuseum:image_index": 5,
    "sfomuseum:image_type": "studio",
    "sfomuseum:placetype": "image",
    "sfomuseum:primary_image": 1,
    "wof:depicts": [
      1511944463,
      102527513
    ],
    "wof:name": "negative: San Francisco, view of Bay Bridge and clouds",
    "wof:placetype": "custom",
    "wof:placetype_alt": "image"
  },
  "geometry": {"coordinates":[-122.386155,37.616358],"type":"Point"}
}
