{
  "type": "Feature",
  "properties": {
    "iso:country": "XX",
    "media:fingerprint": "201bc8d75d8de1a72db5cd938bca8e5b9a1dee9a",
    "media:imagehash_avg": "a:fffffce000000000",
    "media:imagehash_diff": "d:04000003786028e2",
    "media:medium": "image",
    "media:mimetype": "image/tiff",
    "media:properties": {
      "colours": [
        {
          "hex": "#808080",
          "name": "#808080",
          "reference": "vibrant"
        }, 
        {
          "hex": "#c8c8c8",
          "name": "#c8c8c8",
          "reference": "vibrant"
        }, 
        {
          "hex": "#404040",
          "name": "#404040",
          "reference": "vibrant"
        }
      ],
      "sizes": {
        "b": {
          "extension": "jpg",
          "height": 768,
          "mimetype": "image/jpeg",
          "secret": "ByhgDbwvVGhOF8k2TihanoHroELebBA4",
          "width": 768
        },
        "c": {
          "extension": "jpg",
          "height": 600,
          "mimetype": "image/jpeg",
          "secret": "ByhgDbwvVGhOF8k2TihanoHroELebBA4",
          "width": 600
        },
        "dc": {
          "extension": "jpg",
          "height": 600,
          "mimetype": "image/jpeg",
          "secret": "ByhgDbwvVGhOF8k2TihanoHroELebBA4",
          "width": 600
        },
        "ds": {
          "extension": "jpg",
          "height": 320,
          "mimetype": "image/jpeg",
          "secret": "ByhgDbwvVGhOF8k2TihanoHroELebBA4",
          "width": 320
        },
        "k": {
          "extension": "jpg",
          "height": 1536,
          "mimetype": "image/jpeg",
          "secret": "ByhgDbwvVGhOF8k2TihanoHroELebBA4",
          "width": 1536
        },
        "n": {
          "extension": "jpg",
          "height": 239,
          "mimetype": "image/jpeg",
          "secret": "ByhgDbwvVGhOF8k2TihanoHroELebBA4",
          "width": 239
        },
        "o": {
          "extension": "jpg",
          "height": 2563,
          "mimetype": "image/jpeg",
          "secret": "ZvojM6ucRIduJUuirMuPoUH5JGT8bwhN",
          "width": 2563
        },
        "s": {
          "extension": "jpg",
          "height": 320,
          "mimetype": "image/jpeg",
          "secret": "ByhgDbwvVGhOF8k2TihanoHroELebBA4",
          "width": 320
        },
        "z": {
          "extension": "jpg",
          "height": 479,
          "mimetype": "image/jpeg",
          "secret": "ByhgDbwvVGhOF8k2TihanoHroELebBA4",
          "width": 479
        }
      }
    },
    "media:uri_template": "https://millsfield.sfomuseum.org/media/152/782/510/7/1527825107_{secret}_{label}.{extention}",
    "sfomuseum:filename": "42967.tif",
    "sfomuseum:image_index": 5,
    "sfomuseum:placetype": "image",
    "sfomuseum:primary_image": 1,
    "wof:depicts": [
      1511946033
    ],
    "wof:name": "negative: San Francisco International Airport (SFO), aerial",
    "wof:placetype": "media"
  },
  "geometry": {"coordinates":[-122.386155,37.616358],"type":"Point"}
}
