{
  "type": "Feature",
  "properties": {
    "iso:country": "XX",
    "media:fingerprint": "e339a452bc30581514ea19cd0befad9426fc5287",
    "media:imagehash_avg": "a:3cdbdfc300193c38",
    "media:imagehash_diff": "d:71b7b697caabf1f0",
    "media:medium": "image",
    "media:mimetype": "image/tiff",
    "media:properties": {
      "colours": [
        {
          "hex": "#808080",
          "name": "#808080",
          "reference": "vibrant"
        }, 
        {
          "hex": "#c0c0c0",
          "name": "#c0c0c0",
          "reference": "vibrant"
        }, 
        {
          "hex": "#484848",
          "name": "#484848",
          "reference": "vibrant"
        }
      ],
      "sizes": {
        "b": {
          "extension": "jpg",
          "height": 767,
          "mimetype": "image/jpeg",
          "secret": "BdO1PfbBJy72Y4oVEIsgeTbnN7oQ8601",
          "width": 978
        },
        "c": {
          "extension": "jpg",
          "height": 600,
          "mimetype": "image/jpeg",
          "secret": "BdO1PfbBJy72Y4oVEIsgeTbnN7oQ8601",
          "width": 764
        },
        "dc": {
          "extension": "jpg",
          "height": 600,
          "mimetype": "image/jpeg",
          "secret": "BdO1PfbBJy72Y4oVEIsgeTbnN7oQ8601",
          "width": 764
        },
        "ds": {
          "extension": "jpg",
          "height": 320,
          "mimetype": "image/jpeg",
          "secret": "BdO1PfbBJy72Y4oVEIsgeTbnN7oQ8601",
          "width": 320
        },
        "k": {
          "extension": "jpg",
          "height": 1535,
          "mimetype": "image/jpeg",
          "secret": "BdO1PfbBJy72Y4oVEIsgeTbnN7oQ8601",
          "width": 1957
        },
        "n": {
          "extension": "jpg",
          "height": 240,
          "mimetype": "image/jpeg",
          "secret": "BdO1PfbBJy72Y4oVEIsgeTbnN7oQ8601",
          "width": 305
        },
        "o": {
          "extension": "jpg",
          "height": 2140,
          "mimetype": "image/jpeg",
          "secret": "dFYG2xea2S01gV7swaqUMIarSoqQf5BR",
          "width": 2727
        },
        "s": {
          "extension": "jpg",
          "height": 320,
          "mimetype": "image/jpeg",
          "secret": "BdO1PfbBJy72Y4oVEIsgeTbnN7oQ8601",
          "width": 320
        },
        "z": {
          "extension": "jpg",
          "height": 480,
          "mimetype": "image/jpeg",
          "secret": "BdO1PfbBJy72Y4oVEIsgeTbnN7oQ8601",
          "width": 611
        }
      }
    },
    "media:uri_template": "https://millsfield.sfomuseum.org/media/152/782/306/1/1527823061_{secret}_{label}.{extention}",
    "sfomuseum:filename": "41217.tif",
    "sfomuseum:image_index": 5,
    "sfomuseum:placetype": "image",
    "sfomuseum:primary_image": 1,
    "wof:depicts": [
      1511944957
    ],
    "wof:name": "negative: San Francisco International Airport (SFO), terminal interior",
    "wof:placetype": "media"
  },
  "geometry": {"coordinates":[-122.386155,37.616358],"type":"Point"}
}
