{
  "type": "Feature",
  "properties": {
    "iso:country": "XX",
    "media:fingerprint": "d093283eec3ad2626d14f0267041bbf2bc8adcd3",
    "media:imagehash_avg": "a:fffffff101000000",
    "media:imagehash_diff": "d:b4b2a287e7f29225",
    "media:medium": "image",
    "media:mimetype": "image/tiff",
    "media:properties": {
      "colours": [
        {
          "hex": "#808080",
          "name": "#808080",
          "reference": "vibrant"
        }, 
        {
          "hex": "#b8b8b8",
          "name": "#b8b8b8",
          "reference": "vibrant"
        }, 
        {
          "hex": "#404040",
          "name": "#404040",
          "reference": "vibrant"
        }
      ],
      "sizes": {
        "b": {
          "extension": "jpg",
          "height": 743,
          "mimetype": "image/jpeg",
          "secret": "Njrtn0WLEaqYdqjCHGkbWSvgAgHtc6Sp",
          "width": 1024
        },
        "c": {
          "extension": "jpg",
          "height": 580,
          "mimetype": "image/jpeg",
          "secret": "Njrtn0WLEaqYdqjCHGkbWSvgAgHtc6Sp",
          "width": 800
        },
        "dc": {
          "extension": "jpg",
          "height": 580,
          "mimetype": "image/jpeg",
          "secret": "Njrtn0WLEaqYdqjCHGkbWSvgAgHtc6Sp",
          "width": 800
        },
        "ds": {
          "extension": "jpg",
          "height": 320,
          "mimetype": "image/jpeg",
          "secret": "Njrtn0WLEaqYdqjCHGkbWSvgAgHtc6Sp",
          "width": 320
        },
        "k": {
          "extension": "jpg",
          "height": 1487,
          "mimetype": "image/jpeg",
          "secret": "Njrtn0WLEaqYdqjCHGkbWSvgAgHtc6Sp",
          "width": 2048
        },
        "n": {
          "extension": "jpg",
          "height": 232,
          "mimetype": "image/jpeg",
          "secret": "Njrtn0WLEaqYdqjCHGkbWSvgAgHtc6Sp",
          "width": 320
        },
        "o": {
          "extension": "jpg",
          "height": 3058,
          "mimetype": "image/jpeg",
          "secret": "ux1L1EPT5HOSFBGDN6DhtXUgNBJIwB3O",
          "width": 4211
        },
        "s": {
          "extension": "jpg",
          "height": 320,
          "mimetype": "image/jpeg",
          "secret": "Njrtn0WLEaqYdqjCHGkbWSvgAgHtc6Sp",
          "width": 320
        },
        "z": {
          "extension": "jpg",
          "height": 464,
          "mimetype": "image/jpeg",
          "secret": "Njrtn0WLEaqYdqjCHGkbWSvgAgHtc6Sp",
          "width": 640
        }
      }
    },
    "media:uri_template": "https://millsfield.sfomuseum.org/media/152/782/125/5/1527821255_{secret}_{label}.{extention}",
    "sfomuseum:filename": "38655.tif",
    "sfomuseum:image_index": 5,
    "sfomuseum:placetype": "image",
    "sfomuseum:primary_image": 1,
    "wof:depicts": [
      1511949749
    ],
    "wof:name": "negative: Mills Field Municipal Airport of San Francisco, Hangar No. 1",
    "wof:placetype": "media"
  },
  "geometry": {"coordinates":[-122.386155,37.616358],"type":"Point"}
}
