{
  "type": "Feature",
  "properties": {
    "iso:country": "XX",
    "media:fingerprint": "25fc6835321824252522ca51d62be145b113be84",
    "media:imagehash_avg": "a:cfc7c7c7c7c3c3ff",
    "media:imagehash_diff": "d:1d1d1d1f1f9f8787",
    "media:medium": "image",
    "media:mimetype": "image/tiff",
    "media:properties": {
      "colours": [
        {
          "hex": "#a15844",
          "name": "#a15844",
          "reference": "vibrant"
        }, 
        {
          "hex": "#e6d8ca",
          "name": "#e6d8ca",
          "reference": "vibrant"
        }, 
        {
          "hex": "#a47e59",
          "name": "#a47e59",
          "reference": "vibrant"
        }, 
        {
          "hex": "#d2c1a4",
          "name": "#d2c1a4",
          "reference": "vibrant"
        }, 
        {
          "hex": "#383b5c",
          "name": "#383b5c",
          "reference": "vibrant"
        }
      ],
      "sizes": {
        "b": {
          "extension": "jpg",
          "height": 768,
          "mimetype": "image/jpeg",
          "secret": "wcvBSVZpEwSRqifS8mlyPhQXUvN5cSJG",
          "width": 524
        },
        "c": {
          "extension": "jpg",
          "height": 600,
          "mimetype": "image/jpeg",
          "secret": "wcvBSVZpEwSRqifS8mlyPhQXUvN5cSJG",
          "width": 409
        },
        "dc": {
          "extension": "jpg",
          "height": 600,
          "mimetype": "image/jpeg",
          "secret": "wcvBSVZpEwSRqifS8mlyPhQXUvN5cSJG",
          "width": 409
        },
        "ds": {
          "extension": "jpg",
          "height": 320,
          "mimetype": "image/jpeg",
          "secret": "wcvBSVZpEwSRqifS8mlyPhQXUvN5cSJG",
          "width": 320
        },
        "k": {
          "extension": "jpg",
          "height": 1536,
          "mimetype": "image/jpeg",
          "secret": "wcvBSVZpEwSRqifS8mlyPhQXUvN5cSJG",
          "width": 1049
        },
        "n": {
          "extension": "jpg",
          "height": 240,
          "mimetype": "image/jpeg",
          "secret": "wcvBSVZpEwSRqifS8mlyPhQXUvN5cSJG",
          "width": 163
        },
        "o": {
          "extension": "jpg",
          "height": 3285,
          "mimetype": "image/jpeg",
          "secret": "hFwRANES7M32iF3XjJlVEuwrRr7d04gf",
          "width": 2244
        },
        "s": {
          "extension": "jpg",
          "height": 320,
          "mimetype": "image/jpeg",
          "secret": "wcvBSVZpEwSRqifS8mlyPhQXUvN5cSJG",
          "width": 320
        },
        "z": {
          "extension": "jpg",
          "height": 480,
          "mimetype": "image/jpeg",
          "secret": "wcvBSVZpEwSRqifS8mlyPhQXUvN5cSJG",
          "width": 327
        }
      }
    },
    "media:uri_template": "https://millsfield.sfomuseum.org/media/152/781/833/9/1527818339_{secret}_{label}.{extention}",
    "sfomuseum:filename": "17943.tif",
    "sfomuseum:image_index": 5,
    "sfomuseum:placetype": "image",
    "sfomuseum:primary_image": 1,
    "wof:depicts": [
      1511941357
    ],
    "wof:name": "menu: Pan American Airways, Moana Hotel, Hawaii [digital scan]",
    "wof:placetype": "media"
  },
  "geometry": {"coordinates":[-122.386155,37.616358],"type":"Point"}
}
