{
  "type": "Feature",
  "properties": {
    "iso:country": "XX",
    "media:fingerprint": "28fad1ef24a57c725b7df0ca5b0f423fe9ddbc9b",
    "media:imagehash_avg": "a:ffe181808181ffff",
    "media:imagehash_diff": "d:17014f0d33373360",
    "media:medium": "image",
    "media:mimetype": "image/tiff",
    "media:properties": {
      "colours": [
        {
          "hex": "#e62915",
          "name": "#e62915",
          "reference": "vibrant"
        },
        {
          "hex": "#f06d5c",
          "name": "#f06d5c",
          "reference": "vibrant"
        },
        {
          "hex": "#a07200",
          "name": "#a07200",
          "reference": "vibrant"
        },
        {
          "hex": "#898a7e",
          "name": "#898a7e",
          "reference": "vibrant"
        },
        {
          "hex": "#dfd6c0",
          "name": "#dfd6c0",
          "reference": "vibrant"
        }
      ],
      "sizes": {
        "b": {
          "extension": "jpg",
          "height": 768,
          "mimetype": "image/jpeg",
          "secret": "sPlo2ydRSftxaFAZmKjebp536d84Wg5q",
          "width": 353
        },
        "c": {
          "extension": "jpg",
          "height": 600,
          "mimetype": "image/jpeg",
          "secret": "sPlo2ydRSftxaFAZmKjebp536d84Wg5q",
          "width": 276
        },
        "dc": {
          "extension": "jpg",
          "height": 600,
          "mimetype": "image/jpeg",
          "secret": "sPlo2ydRSftxaFAZmKjebp536d84Wg5q",
          "width": 276
        },
        "ds": {
          "extension": "jpg",
          "height": 320,
          "mimetype": "image/jpeg",
          "secret": "sPlo2ydRSftxaFAZmKjebp536d84Wg5q",
          "width": 320
        },
        "k": {
          "extension": "jpg",
          "height": 1536,
          "mimetype": "image/jpeg",
          "secret": "sPlo2ydRSftxaFAZmKjebp536d84Wg5q",
          "width": 706
        },
        "n": {
          "extension": "jpg",
          "height": 240,
          "mimetype": "image/jpeg",
          "secret": "sPlo2ydRSftxaFAZmKjebp536d84Wg5q",
          "width": 110
        },
        "o": {
          "extension": "jpg",
          "height": 3063,
          "mimetype": "image/jpeg",
          "secret": "PzyhQuAm5k5eufUue0wuY5gYfR7AnzTt",
          "width": 1409
        },
        "s": {
          "extension": "jpg",
          "height": 320,
          "mimetype": "image/jpeg",
          "secret": "sPlo2ydRSftxaFAZmKjebp536d84Wg5q",
          "width": 320
        },
        "z": {
          "extension": "jpg",
          "height": 480,
          "mimetype": "image/jpeg",
          "secret": "sPlo2ydRSftxaFAZmKjebp536d84Wg5q",
          "width": 220
        }
      }
    },
    "media:uri_template": "https://static.sfomuseum.org/media/152/784/500/1/1527845001_{secret}_{label}.{extention}",
    "sfomuseum:filename": "69525.tif",
    "sfomuseum:image_index": 5,
    "sfomuseum:image_type": "studio",
    "sfomuseum:placetype": "image",
    "sfomuseum:primary_image": 1,
    "wof:depicts": [
      1159284563,
      1511921451
    ],
    "wof:name": "menu: JAL (Japan Airlines)",
    "wof:placetype": "custom",
    "wof:placetype_alt": "image"
  },
  "geometry": {"coordinates":[-122.386155,37.616358],"type":"Point"}
}
