{
  "type": "Feature",
  "properties": {
    "iso:country": "XX",
    "media:fingerprint": "c49ba55e5b79f3081d47b8490e4ed873d11d2047",
    "media:imagehash_avg": "a:0001ffff8100ffff",
    "media:imagehash_diff": "d:ffffe8ce2706c2c1",
    "media:medium": "image",
    "media:mimetype": "image/tiff",
    "media:properties": {
      "colours": [
        {
          "hex": "#808080",
          "name": "#808080",
          "reference": "vibrant"
        }, 
        {
          "hex": "#b8b8b8",
          "name": "#b8b8b8",
          "reference": "vibrant"
        }, 
        {
          "hex": "#474747",
          "name": "#474747",
          "reference": "vibrant"
        }
      ],
      "sizes": {
        "b": {
          "extension": "jpg",
          "height": 768,
          "mimetype": "image/jpeg",
          "secret": "R4Fr65Tw9zICnyRuwugFUdsUDABMC7Qk",
          "width": 768
        },
        "c": {
          "extension": "jpg",
          "height": 600,
          "mimetype": "image/jpeg",
          "secret": "R4Fr65Tw9zICnyRuwugFUdsUDABMC7Qk",
          "width": 600
        },
        "dc": {
          "extension": "jpg",
          "height": 600,
          "mimetype": "image/jpeg",
          "secret": "R4Fr65Tw9zICnyRuwugFUdsUDABMC7Qk",
          "width": 600
        },
        "ds": {
          "extension": "jpg",
          "height": 320,
          "mimetype": "image/jpeg",
          "secret": "R4Fr65Tw9zICnyRuwugFUdsUDABMC7Qk",
          "width": 320
        },
        "k": {
          "extension": "jpg",
          "height": 1536,
          "mimetype": "image/jpeg",
          "secret": "R4Fr65Tw9zICnyRuwugFUdsUDABMC7Qk",
          "width": 1536
        },
        "n": {
          "extension": "jpg",
          "height": 240,
          "mimetype": "image/jpeg",
          "secret": "R4Fr65Tw9zICnyRuwugFUdsUDABMC7Qk",
          "width": 240
        },
        "o": {
          "extension": "jpg",
          "height": 2536,
          "mimetype": "image/jpeg",
          "secret": "Iq8bpvGib5i1cP3tvRYSjmLzMS7zO12L",
          "width": 2536
        },
        "s": {
          "extension": "jpg",
          "height": 320,
          "mimetype": "image/jpeg",
          "secret": "R4Fr65Tw9zICnyRuwugFUdsUDABMC7Qk",
          "width": 320
        },
        "z": {
          "extension": "jpg",
          "height": 480,
          "mimetype": "image/jpeg",
          "secret": "R4Fr65Tw9zICnyRuwugFUdsUDABMC7Qk",
          "width": 480
        }
      }
    },
    "media:uri_template": "https://millsfield.sfomuseum.org/media/152/782/679/9/1527826799_{secret}_{label}.{extention}",
    "sfomuseum:filename": "43801.tif",
    "sfomuseum:image_index": 5,
    "sfomuseum:placetype": "image",
    "sfomuseum:primary_image": 1,
    "wof:depicts": [
      1511947837
    ],
    "wof:name": "negative: San Francisco International Airport (SFO), Western Airlines building",
    "wof:placetype": "media"
  },
  "geometry": {"coordinates":[-122.386155,37.616358],"type":"Point"}
}
