{
  "type": "Feature",
  "properties": {
    "iso:country": "XX",
    "media:fingerprint": "ffd86573815e5e1b4b60bc32a291af2f3eb232ae",
    "media:imagehash_avg": "a:ffffffff010001bf",
    "media:imagehash_diff": "d:4361616979713f7f",
    "media:medium": "image",
    "media:mimetype": "image/tiff",
    "media:properties": {
      "colours": [
        {
          "hex": "#c8b88a",
          "name": "#c8b88a",
          "reference": "vibrant"
        },
        {
          "hex": "#e1d8bf",
          "name": "#e1d8bf",
          "reference": "vibrant"
        },
        {
          "hex": "#1b190a",
          "name": "#1b190a",
          "reference": "vibrant"
        },
        {
          "hex": "#948865",
          "name": "#948865",
          "reference": "vibrant"
        },
        {
          "hex": "#d0c6a7",
          "name": "#d0c6a7",
          "reference": "vibrant"
        }
      ],
      "sizes": {
        "b": {
          "extension": "jpg",
          "height": 744,
          "mimetype": "image/jpeg",
          "secret": "W1O9c4DNmetzFoyT9vkQ5XFbSIxB8aSk",
          "width": 1024
        },
        "c": {
          "extension": "jpg",
          "height": 581,
          "mimetype": "image/jpeg",
          "secret": "W1O9c4DNmetzFoyT9vkQ5XFbSIxB8aSk",
          "width": 799
        },
        "dc": {
          "extension": "jpg",
          "height": 581,
          "mimetype": "image/jpeg",
          "secret": "W1O9c4DNmetzFoyT9vkQ5XFbSIxB8aSk",
          "width": 799
        },
        "ds": {
          "extension": "jpg",
          "height": 320,
          "mimetype": "image/jpeg",
          "secret": "W1O9c4DNmetzFoyT9vkQ5XFbSIxB8aSk",
          "width": 320
        },
        "k": {
          "extension": "jpg",
          "height": 1489,
          "mimetype": "image/jpeg",
          "secret": "W1O9c4DNmetzFoyT9vkQ5XFbSIxB8aSk",
          "width": 2048
        },
        "n": {
          "extension": "jpg",
          "height": 232,
          "mimetype": "image/jpeg",
          "secret": "W1O9c4DNmetzFoyT9vkQ5XFbSIxB8aSk",
          "width": 320
        },
        "o": {
          "extension": "jpg",
          "height": 1852,
          "mimetype": "image/jpeg",
          "secret": "SvtCRKqN5AnPMk8IdSbh5jz3OM1eaJKe",
          "width": 2547
        },
        "s": {
          "extension": "jpg",
          "height": 320,
          "mimetype": "image/jpeg",
          "secret": "W1O9c4DNmetzFoyT9vkQ5XFbSIxB8aSk",
          "width": 320
        },
        "z": {
          "extension": "jpg",
          "height": 465,
          "mimetype": "image/jpeg",
          "secret": "W1O9c4DNmetzFoyT9vkQ5XFbSIxB8aSk",
          "width": 640
        }
      }
    },
    "media:uri_template": "https://static.sfomuseum.org/media/152/785/579/9/1527855799_{secret}_{label}.{extention}",
    "sfomuseum:filename": "100453.tif",
    "sfomuseum:image_index": 5,
    "sfomuseum:image_type": "studio",
    "sfomuseum:placetype": "image",
    "sfomuseum:primary_image": 1,
    "wof:depicts": [
      1511942645
    ],
    "wof:name": "photograph: San Francisco Bay Area aerial, Mount Tamalpais",
    "wof:placetype": "custom",
    "wof:placetype_alt": "image"
  },
  "geometry": {"coordinates":[-122.386155,37.616358],"type":"Point"}
}
