{
  "type": "Feature",
  "properties": {
    "iso:country": "XX",
    "media:fingerprint": "ab53d7dcca50213b4490e29bc269891947e74a6e",
    "media:imagehash_avg": "a:00e7e7fb7f3d3e00",
    "media:imagehash_diff": "d:27aecc96b2f1747c",
    "media:medium": "image",
    "media:mimetype": "image/tiff",
    "media:properties": {
      "colours": [
        {
          "hex": "#c61f04",
          "name": "#c61f04",
          "reference": "vibrant"
        }, 
        {
          "hex": "#e1c097",
          "name": "#e1c097",
          "reference": "vibrant"
        }, 
        {
          "hex": "#921103",
          "name": "#921103",
          "reference": "vibrant"
        }, 
        {
          "hex": "#94816c",
          "name": "#94816c",
          "reference": "vibrant"
        }, 
        {
          "hex": "#cfb890",
          "name": "#cfb890",
          "reference": "vibrant"
        }
      ],
      "sizes": {
        "b": {
          "extension": "jpg",
          "height": 580,
          "mimetype": "image/jpeg",
          "secret": "nOATlRfT2vjmJxZ95qUFqMYnZBoV15JW",
          "width": 1024
        },
        "c": {
          "extension": "jpg",
          "height": 453,
          "mimetype": "image/jpeg",
          "secret": "nOATlRfT2vjmJxZ95qUFqMYnZBoV15JW",
          "width": 800
        },
        "dc": {
          "extension": "jpg",
          "height": 453,
          "mimetype": "image/jpeg",
          "secret": "nOATlRfT2vjmJxZ95qUFqMYnZBoV15JW",
          "width": 800
        },
        "ds": {
          "extension": "jpg",
          "height": 320,
          "mimetype": "image/jpeg",
          "secret": "nOATlRfT2vjmJxZ95qUFqMYnZBoV15JW",
          "width": 320
        },
        "k": {
          "extension": "jpg",
          "height": 1160,
          "mimetype": "image/jpeg",
          "secret": "nOATlRfT2vjmJxZ95qUFqMYnZBoV15JW",
          "width": 2048
        },
        "n": {
          "extension": "jpg",
          "height": 181,
          "mimetype": "image/jpeg",
          "secret": "nOATlRfT2vjmJxZ95qUFqMYnZBoV15JW",
          "width": 320
        },
        "o": {
          "extension": "jpg",
          "height": 1112,
          "mimetype": "image/jpeg",
          "secret": "3K8oUiUo2icD4ydHhs3gFkto3Hn3qxHv",
          "width": 1962
        },
        "s": {
          "extension": "jpg",
          "height": 320,
          "mimetype": "image/jpeg",
          "secret": "nOATlRfT2vjmJxZ95qUFqMYnZBoV15JW",
          "width": 320
        },
        "z": {
          "extension": "jpg",
          "height": 362,
          "mimetype": "image/jpeg",
          "secret": "nOATlRfT2vjmJxZ95qUFqMYnZBoV15JW",
          "width": 640
        }
      }
    },
    "media:uri_template": "https://millsfield.sfomuseum.org/media/152/785/304/7/1527853047_{secret}_{label}.{extention}",
    "sfomuseum:filename": "2012.149.2195 a_verso.tif",
    "sfomuseum:image_index": 5,
    "sfomuseum:placetype": "image",
    "sfomuseum:primary_image": 0,
    "wof:depicts": [
      1511954219
    ],
    "wof:name": "airmail flight cover: First airmail flight, FAM-5, Miami - Puerto Barrios route, Juan Trippe",
    "wof:placetype": "media"
  },
  "geometry": {"coordinates":[-122.386155,37.616358],"type":"Point"}
}
