{
  "type": "Feature",
  "properties": {
    "iso:country": "XX",
    "media:fingerprint": "129c3b8093b967ba461e808628fc6d6daabd4191",
    "media:imagehash_avg": "a:ff9f800000f2fffe",
    "media:imagehash_diff": "d:707333311326e0f0",
    "media:medium": "image",
    "media:mimetype": "image/tiff",
    "media:properties": {
      "colours": [
        {
          "hex": "#808080",
          "name": "#808080",
          "reference": "vibrant"
        }, 
        {
          "hex": "#b8b8b8",
          "name": "#b8b8b8",
          "reference": "vibrant"
        }, 
        {
          "hex": "#484848",
          "name": "#484848",
          "reference": "vibrant"
        }
      ],
      "sizes": {
        "b": {
          "extension": "jpg",
          "height": 768,
          "mimetype": "image/jpeg",
          "secret": "dKPZS42RTxECJvgHKpo4S3QDWmkHLBDN",
          "width": 755
        },
        "c": {
          "extension": "jpg",
          "height": 600,
          "mimetype": "image/jpeg",
          "secret": "dKPZS42RTxECJvgHKpo4S3QDWmkHLBDN",
          "width": 590
        },
        "dc": {
          "extension": "jpg",
          "height": 600,
          "mimetype": "image/jpeg",
          "secret": "dKPZS42RTxECJvgHKpo4S3QDWmkHLBDN",
          "width": 590
        },
        "ds": {
          "extension": "jpg",
          "height": 320,
          "mimetype": "image/jpeg",
          "secret": "dKPZS42RTxECJvgHKpo4S3QDWmkHLBDN",
          "width": 320
        },
        "k": {
          "extension": "jpg",
          "height": 1536,
          "mimetype": "image/jpeg",
          "secret": "dKPZS42RTxECJvgHKpo4S3QDWmkHLBDN",
          "width": 1511
        },
        "n": {
          "extension": "jpg",
          "height": 240,
          "mimetype": "image/jpeg",
          "secret": "dKPZS42RTxECJvgHKpo4S3QDWmkHLBDN",
          "width": 236
        },
        "o": {
          "extension": "jpg",
          "height": 1772,
          "mimetype": "image/jpeg",
          "secret": "u75aLfi4Ps9Lklm0zZgp6GS34sLgUsRL",
          "width": 1744
        },
        "s": {
          "extension": "jpg",
          "height": 320,
          "mimetype": "image/jpeg",
          "secret": "dKPZS42RTxECJvgHKpo4S3QDWmkHLBDN",
          "width": 320
        },
        "z": {
          "extension": "jpg",
          "height": 480,
          "mimetype": "image/jpeg",
          "secret": "dKPZS42RTxECJvgHKpo4S3QDWmkHLBDN",
          "width": 472
        }
      }
    },
    "media:uri_template": "https://millsfield.sfomuseum.org/media/152/782/497/1/1527824971_{secret}_{label}.{extention}",
    "sfomuseum:filename": "42906.tif",
    "sfomuseum:image_index": 5,
    "sfomuseum:placetype": "image",
    "sfomuseum:primary_image": 1,
    "wof:depicts": [
      1511945853
    ],
    "wof:name": "photograph: San Francisco International Airport (SFO), parking garage construction",
    "wof:placetype": "media"
  },
  "geometry": {"coordinates":[-122.386155,37.616358],"type":"Point"}
}
