{
  "type": "Feature",
  "properties": {
    "iso:country": "XX",
    "media:fingerprint": "6c71271ede831b627f6867ed4ac93b619d4aa254",
    "media:imagehash_avg": "a:0000077fffffe7e7",
    "media:imagehash_diff": "d:f8dccccccce88c8e",
    "media:medium": "image",
    "media:mimetype": "image/tiff",
    "media:properties": {
      "colours": [
        {
          "hex": "#7e8383",
          "name": "#7e8383",
          "reference": "vibrant"
        }, 
        {
          "hex": "#a9b7c4",
          "name": "#a9b7c4",
          "reference": "vibrant"
        }, 
        {
          "hex": "#434344",
          "name": "#434344",
          "reference": "vibrant"
        }
      ],
      "sizes": {
        "b": {
          "extension": "jpg",
          "height": 768,
          "mimetype": "image/jpeg",
          "secret": "k4T8QN1lW7PE36FzxA34ODxhavZSL3n6",
          "width": 965
        },
        "c": {
          "extension": "jpg",
          "height": 600,
          "mimetype": "image/jpeg",
          "secret": "k4T8QN1lW7PE36FzxA34ODxhavZSL3n6",
          "width": 754
        },
        "dc": {
          "extension": "jpg",
          "height": 600,
          "mimetype": "image/jpeg",
          "secret": "k4T8QN1lW7PE36FzxA34ODxhavZSL3n6",
          "width": 754
        },
        "ds": {
          "extension": "jpg",
          "height": 320,
          "mimetype": "image/jpeg",
          "secret": "k4T8QN1lW7PE36FzxA34ODxhavZSL3n6",
          "width": 320
        },
        "k": {
          "extension": "jpg",
          "height": 1536,
          "mimetype": "image/jpeg",
          "secret": "k4T8QN1lW7PE36FzxA34ODxhavZSL3n6",
          "width": 1931
        },
        "n": {
          "extension": "jpg",
          "height": 240,
          "mimetype": "image/jpeg",
          "secret": "k4T8QN1lW7PE36FzxA34ODxhavZSL3n6",
          "width": 301
        },
        "o": {
          "extension": "jpg",
          "height": 1667,
          "mimetype": "image/jpeg",
          "secret": "DQgDqn3p8vzf2rPaRW43KnN4fHiVdFmu",
          "width": 2096
        },
        "s": {
          "extension": "jpg",
          "height": 320,
          "mimetype": "image/jpeg",
          "secret": "k4T8QN1lW7PE36FzxA34ODxhavZSL3n6",
          "width": 320
        },
        "z": {
          "extension": "jpg",
          "height": 480,
          "mimetype": "image/jpeg",
          "secret": "k4T8QN1lW7PE36FzxA34ODxhavZSL3n6",
          "width": 603
        }
      }
    },
    "media:uri_template": "https://millsfield.sfomuseum.org/media/152/785/851/7/1527858517_{secret}_{label}.{extention}",
    "sfomuseum:filename": "2002.018.242.tif",
    "sfomuseum:image_index": 0,
    "sfomuseum:placetype": "image",
    "sfomuseum:primary_image": 1,
    "wof:depicts": [
      1511922963
    ],
    "wof:name": "cordial glass: Continental Airlines",
    "wof:placetype": "media"
  },
  "geometry": {"coordinates":[-122.386155,37.616358],"type":"Point"}
}
