{
  "type": "Feature",
  "properties": {
    "iso:country": "XX",
    "media:fingerprint": "f0824c5508d47cf7588d7c4736112648fb5dc428",
    "media:imagehash_avg": "a:fffe9e8080c6feff",
    "media:imagehash_diff": "d:406c3e3b0b1e4030",
    "media:medium": "image",
    "media:mimetype": "image/tiff",
    "media:properties": {
      "colours": [
        {
          "hex": "#986838",
          "name": "#986838",
          "reference": "vibrant"
        },
        {
          "hex": "#5e3118",
          "name": "#5e3118",
          "reference": "vibrant"
        },
        {
          "hex": "#ac976a",
          "name": "#ac976a",
          "reference": "vibrant"
        },
        {
          "hex": "#c2c4b5",
          "name": "#c2c4b5",
          "reference": "vibrant"
        },
        {
          "hex": "#36371c",
          "name": "#36371c",
          "reference": "vibrant"
        }
      ],
      "sizes": {
        "b": {
          "extension": "jpg",
          "height": 768,
          "mimetype": "image/jpeg",
          "secret": "xG7boDPmBa1kzZQqDtUIlctB3pzcByOx",
          "width": 489
        },
        "c": {
          "extension": "jpg",
          "height": 600,
          "mimetype": "image/jpeg",
          "secret": "xG7boDPmBa1kzZQqDtUIlctB3pzcByOx",
          "width": 382
        },
        "dc": {
          "extension": "jpg",
          "height": 600,
          "mimetype": "image/jpeg",
          "secret": "xG7boDPmBa1kzZQqDtUIlctB3pzcByOx",
          "width": 382
        },
        "ds": {
          "extension": "jpg",
          "height": 320,
          "mimetype": "image/jpeg",
          "secret": "xG7boDPmBa1kzZQqDtUIlctB3pzcByOx",
          "width": 320
        },
        "k": {
          "extension": "jpg",
          "height": 1536,
          "mimetype": "image/jpeg",
          "secret": "xG7boDPmBa1kzZQqDtUIlctB3pzcByOx",
          "width": 978
        },
        "n": {
          "extension": "jpg",
          "height": 240,
          "mimetype": "image/jpeg",
          "secret": "xG7boDPmBa1kzZQqDtUIlctB3pzcByOx",
          "width": 152
        },
        "o": {
          "extension": "jpg",
          "height": 2317,
          "mimetype": "image/jpeg",
          "secret": "VDRZxihKHFw1cXxEpJUOyxuGlAS3TaUX",
          "width": 1476
        },
        "s": {
          "extension": "jpg",
          "height": 320,
          "mimetype": "image/jpeg",
          "secret": "xG7boDPmBa1kzZQqDtUIlctB3pzcByOx",
          "width": 320
        },
        "z": {
          "extension": "jpg",
          "height": 480,
          "mimetype": "image/jpeg",
          "secret": "xG7boDPmBa1kzZQqDtUIlctB3pzcByOx",
          "width": 305
        }
      }
    },
    "media:uri_template": "https://static.sfomuseum.org/media/152/784/547/9/1527845479_{secret}_{label}.{extention}",
    "sfomuseum:filename": "2006034136_front.tif",
    "sfomuseum:image_index": 5,
    "sfomuseum:image_type": "studio",
    "sfomuseum:placetype": "image",
    "sfomuseum:primary_image": 1,
    "wof:depicts": [
      1159285163,
      1511927769
    ],
    "wof:name": "menu: Singapore Airlines, First Class",
    "wof:placetype": "custom",
    "wof:placetype_alt": "image"
  },
  "geometry": {"coordinates":[-122.386155,37.616358],"type":"Point"}
}
