{
  "type": "Feature",
  "properties": {
    "iso:country": "XX",
    "media:fingerprint": "ce462ab0aa9dfc5fc467d7d11609b76bfd5ebe15",
    "media:imagehash_avg": "a:ff8bffffe7810000",
    "media:imagehash_diff": "d:0e171e0e0f371f07",
    "media:medium": "image",
    "media:mimetype": "image/tiff",
    "media:properties": {
      "colours": [
        {
          "hex": "#c01800",
          "name": "#c01800",
          "reference": "vibrant"
        }, 
        {
          "hex": "#d69ca1",
          "name": "#d69ca1",
          "reference": "vibrant"
        }, 
        {
          "hex": "#b61502",
          "name": "#b61502",
          "reference": "vibrant"
        }, 
        {
          "hex": "#8b8268",
          "name": "#8b8268",
          "reference": "vibrant"
        }, 
        {
          "hex": "#ddc5c0",
          "name": "#ddc5c0",
          "reference": "vibrant"
        }
      ],
      "sizes": {
        "b": {
          "extension": "jpg",
          "height": 768,
          "mimetype": "image/jpeg",
          "secret": "NpyKzBXFt92LaVWomSMLA4yJ2kqLnz81",
          "width": 357
        },
        "c": {
          "extension": "jpg",
          "height": 600,
          "mimetype": "image/jpeg",
          "secret": "NpyKzBXFt92LaVWomSMLA4yJ2kqLnz81",
          "width": 278
        },
        "dc": {
          "extension": "jpg",
          "height": 600,
          "mimetype": "image/jpeg",
          "secret": "NpyKzBXFt92LaVWomSMLA4yJ2kqLnz81",
          "width": 278
        },
        "ds": {
          "extension": "jpg",
          "height": 320,
          "mimetype": "image/jpeg",
          "secret": "NpyKzBXFt92LaVWomSMLA4yJ2kqLnz81",
          "width": 320
        },
        "k": {
          "extension": "jpg",
          "height": 1536,
          "mimetype": "image/jpeg",
          "secret": "NpyKzBXFt92LaVWomSMLA4yJ2kqLnz81",
          "width": 714
        },
        "n": {
          "extension": "jpg",
          "height": 240,
          "mimetype": "image/jpeg",
          "secret": "NpyKzBXFt92LaVWomSMLA4yJ2kqLnz81",
          "width": 111
        },
        "o": {
          "extension": "jpg",
          "height": 2422,
          "mimetype": "image/jpeg",
          "secret": "p8V9pxVmTun9DfvLkUzUgMLZpnCqN1yf",
          "width": 1126
        },
        "s": {
          "extension": "jpg",
          "height": 320,
          "mimetype": "image/jpeg",
          "secret": "NpyKzBXFt92LaVWomSMLA4yJ2kqLnz81",
          "width": 320
        },
        "z": {
          "extension": "jpg",
          "height": 480,
          "mimetype": "image/jpeg",
          "secret": "NpyKzBXFt92LaVWomSMLA4yJ2kqLnz81",
          "width": 223
        }
      }
    },
    "media:uri_template": "https://millsfield.sfomuseum.org/media/152/782/072/7/1527820727_{secret}_{label}.{extention}",
    "sfomuseum:filename": "32461.tif",
    "sfomuseum:image_index": 5,
    "sfomuseum:placetype": "image",
    "sfomuseum:primary_image": 1,
    "wof:depicts": [
      1511929513
    ],
    "wof:name": "brochure: TWA (Trans World Airlines), Boeing 747",
    "wof:placetype": "media"
  },
  "geometry": {"coordinates":[-122.386155,37.616358],"type":"Point"}
}
