{
  "type": "Feature",
  "properties": {
    "iso:country": "XX",
    "media:fingerprint": "d86530e8594f4ccdd7800a732e7651757c648bc6",
    "media:imagehash_avg": "a:ffffff8703000000",
    "media:imagehash_diff": "d:5b4d4d4f0f4f5d5b",
    "media:medium": "image",
    "media:mimetype": "image/tiff",
    "media:properties": {
      "colours": [
        {
          "hex": "#255521",
          "name": "#255521",
          "reference": "vibrant"
        },
        {
          "hex": "#7b8583",
          "name": "#7b8583",
          "reference": "vibrant"
        },
        {
          "hex": "#bfccc6",
          "name": "#bfccc6",
          "reference": "vibrant"
        },
        {
          "hex": "#336333",
          "name": "#336333",
          "reference": "vibrant"
        }
      ],
      "sizes": {
        "b": {
          "extension": "jpg",
          "height": 768,
          "mimetype": "image/jpeg",
          "secret": "fw7ubyHXA5IiZfPcDe8uR5gRv0fsbAxl",
          "width": 514
        },
        "c": {
          "extension": "jpg",
          "height": 600,
          "mimetype": "image/jpeg",
          "secret": "fw7ubyHXA5IiZfPcDe8uR5gRv0fsbAxl",
          "width": 402
        },
        "dc": {
          "extension": "jpg",
          "height": 600,
          "mimetype": "image/jpeg",
          "secret": "fw7ubyHXA5IiZfPcDe8uR5gRv0fsbAxl",
          "width": 402
        },
        "ds": {
          "extension": "jpg",
          "height": 320,
          "mimetype": "image/jpeg",
          "secret": "fw7ubyHXA5IiZfPcDe8uR5gRv0fsbAxl",
          "width": 320
        },
        "k": {
          "extension": "jpg",
          "height": 1536,
          "mimetype": "image/jpeg",
          "secret": "fw7ubyHXA5IiZfPcDe8uR5gRv0fsbAxl",
          "width": 1029
        },
        "n": {
          "extension": "jpg",
          "height": 240,
          "mimetype": "image/jpeg",
          "secret": "fw7ubyHXA5IiZfPcDe8uR5gRv0fsbAxl",
          "width": 160
        },
        "o": {
          "extension": "jpg",
          "height": 2097,
          "mimetype": "image/jpeg",
          "secret": "HTLWU980C9FrhOhF2P3gN9rO7iZyRsmK",
          "width": 1406
        },
        "s": {
          "extension": "jpg",
          "height": 320,
          "mimetype": "image/jpeg",
          "secret": "fw7ubyHXA5IiZfPcDe8uR5gRv0fsbAxl",
          "width": 320
        },
        "z": {
          "extension": "jpg",
          "height": 480,
          "mimetype": "image/jpeg",
          "secret": "fw7ubyHXA5IiZfPcDe8uR5gRv0fsbAxl",
          "width": 321
        }
      }
    },
    "media:uri_template": "https://static.sfomuseum.org/media/152/783/152/9/1527831529_{secret}_{label}.{extention}",
    "sfomuseum:filename": "60564.tif",
    "sfomuseum:image_index": 5,
    "sfomuseum:image_type": "studio",
    "sfomuseum:placetype": "image",
    "sfomuseum:primary_image": 0,
    "wof:depicts": [
      102527513,
      1511954981
    ],
    "wof:name": "airport bond: City and County of San Francisco",
    "wof:placetype": "custom",
    "wof:placetype_alt": "image"
  },
  "geometry": {"coordinates":[-122.386155,37.616358],"type":"Point"}
}
