{
  "type": "Feature",
  "properties": {
    "iso:country": "XX",
    "media:fingerprint": "0c99c78ef90f107d45710ffc7a967994392789f8",
    "media:imagehash_avg": "a:f7c181a5a5b1b181",
    "media:imagehash_diff": "d:270f374d4d65632b",
    "media:medium": "image",
    "media:mimetype": "image/tiff",
    "media:properties": {
      "colours": [
        {
          "hex": "#283474",
          "name": "#283474",
          "reference": "vibrant"
        }, 
        {
          "hex": "#e6d9c6",
          "name": "#e6d9c6",
          "reference": "vibrant"
        }, 
        {
          "hex": "#383878",
          "name": "#383878",
          "reference": "vibrant"
        }, 
        {
          "hex": "#676b95",
          "name": "#676b95",
          "reference": "vibrant"
        }, 
        {
          "hex": "#c9bfac",
          "name": "#c9bfac",
          "reference": "vibrant"
        }
      ],
      "sizes": {
        "b": {
          "extension": "jpg",
          "height": 768,
          "mimetype": "image/jpeg",
          "secret": "FzYkRUrLmqCHAqmWaFfx8m3S7PUwxoGr",
          "width": 515
        },
        "c": {
          "extension": "jpg",
          "height": 600,
          "mimetype": "image/jpeg",
          "secret": "FzYkRUrLmqCHAqmWaFfx8m3S7PUwxoGr",
          "width": 402
        },
        "dc": {
          "extension": "jpg",
          "height": 600,
          "mimetype": "image/jpeg",
          "secret": "FzYkRUrLmqCHAqmWaFfx8m3S7PUwxoGr",
          "width": 402
        },
        "ds": {
          "extension": "jpg",
          "height": 320,
          "mimetype": "image/jpeg",
          "secret": "FzYkRUrLmqCHAqmWaFfx8m3S7PUwxoGr",
          "width": 320
        },
        "k": {
          "extension": "jpg",
          "height": 1536,
          "mimetype": "image/jpeg",
          "secret": "FzYkRUrLmqCHAqmWaFfx8m3S7PUwxoGr",
          "width": 1031
        },
        "n": {
          "extension": "jpg",
          "height": 240,
          "mimetype": "image/jpeg",
          "secret": "FzYkRUrLmqCHAqmWaFfx8m3S7PUwxoGr",
          "width": 161
        },
        "o": {
          "extension": "jpg",
          "height": 2688,
          "mimetype": "image/jpeg",
          "secret": "jn0AF5lG6IQF6lVJuHmYCS8oLPXiUm5i",
          "width": 1805
        },
        "s": {
          "extension": "jpg",
          "height": 320,
          "mimetype": "image/jpeg",
          "secret": "FzYkRUrLmqCHAqmWaFfx8m3S7PUwxoGr",
          "width": 320
        },
        "z": {
          "extension": "jpg",
          "height": 480,
          "mimetype": "image/jpeg",
          "secret": "FzYkRUrLmqCHAqmWaFfx8m3S7PUwxoGr",
          "width": 322
        }
      }
    },
    "media:uri_template": "https://millsfield.sfomuseum.org/media/152/782/455/1/1527824551_{secret}_{label}.{extention}",
    "sfomuseum:filename": "42623.tif",
    "sfomuseum:image_index": 5,
    "sfomuseum:placetype": "image",
    "sfomuseum:primary_image": 1,
    "wof:depicts": [
      1511923119
    ],
    "wof:name": "airsickness bag: Continental Airlines",
    "wof:placetype": "media"
  },
  "geometry": {"coordinates":[-122.386155,37.616358],"type":"Point"}
}
