{
  "type": "Feature",
  "properties": {
    "iso:country": "XX",
    "media:fingerprint": "e86198249046c4de16311f3dc95e0d5f4a2ecec5",
    "media:imagehash_avg": "a:00007e7f37000800",
    "media:imagehash_diff": "d:f0f0f0e8e64b39f0",
    "media:medium": "image",
    "media:mimetype": "image/tiff",
    "media:properties": {
      "colours": [
        {
          "hex": "#777777",
          "name": "#777777",
          "reference": "vibrant"
        },
        {
          "hex": "#bcc1b8",
          "name": "#bcc1b8",
          "reference": "vibrant"
        },
        {
          "hex": "#353a43",
          "name": "#353a43",
          "reference": "vibrant"
        }
      ],
      "sizes": {
        "b": {
          "extension": "jpg",
          "height": 753,
          "mimetype": "image/jpeg",
          "secret": "6qZ8C3loMWcakU9QKNKrt5BqiUfMskmO",
          "width": 1024
        },
        "c": {
          "extension": "jpg",
          "height": 588,
          "mimetype": "image/jpeg",
          "secret": "6qZ8C3loMWcakU9QKNKrt5BqiUfMskmO",
          "width": 800
        },
        "dc": {
          "extension": "jpg",
          "height": 588,
          "mimetype": "image/jpeg",
          "secret": "6qZ8C3loMWcakU9QKNKrt5BqiUfMskmO",
          "width": 800
        },
        "ds": {
          "extension": "jpg",
          "height": 320,
          "mimetype": "image/jpeg",
          "secret": "6qZ8C3loMWcakU9QKNKrt5BqiUfMskmO",
          "width": 320
        },
        "k": {
          "extension": "jpg",
          "height": 1506,
          "mimetype": "image/jpeg",
          "secret": "6qZ8C3loMWcakU9QKNKrt5BqiUfMskmO",
          "width": 2048
        },
        "n": {
          "extension": "jpg",
          "height": 235,
          "mimetype": "image/jpeg",
          "secret": "6qZ8C3loMWcakU9QKNKrt5BqiUfMskmO",
          "width": 320
        },
        "o": {
          "extension": "jpg",
          "height": 3546,
          "mimetype": "image/jpeg",
          "secret": "TBA6SklPB6NgHw41Z7sJof3rdQbMPL0Q",
          "width": 4820
        },
        "s": {
          "extension": "jpg",
          "height": 320,
          "mimetype": "image/jpeg",
          "secret": "6qZ8C3loMWcakU9QKNKrt5BqiUfMskmO",
          "width": 320
        },
        "z": {
          "extension": "jpg",
          "height": 470,
          "mimetype": "image/jpeg",
          "secret": "6qZ8C3loMWcakU9QKNKrt5BqiUfMskmO",
          "width": 640
        }
      }
    },
    "media:uri_template": "https://static.sfomuseum.org/media/152/785/101/1/1527851011_{secret}_{label}.{extention}",
    "sfomuseum:filename": "82719.tif",
    "sfomuseum:image_index": 5,
    "sfomuseum:image_type": "studio",
    "sfomuseum:placetype": "image",
    "sfomuseum:primary_image": 1,
    "wof:depicts": [
      1511922603,
      1159284711
    ],
    "wof:name": "entree dish: Lufthansa German Airlines",
    "wof:placetype": "custom",
    "wof:placetype_alt": "image"
  },
  "geometry": {"coordinates":[-122.386155,37.616358],"type":"Point"}
}
