{
  "type": "Feature",
  "properties": {
    "media:fingerprint": "a8962e54eb7ba33b4c8bcf635e7934d0f16cfc88",
    "media:imagehash_avg": "a:e707ffff81837301",
    "media:imagehash_diff": "d:0d0caa3a371ee652",
    "media:medium": "image",
    "media:mimetype": "image/tiff",
    "media:properties": {
      "colours": [
        {
          "hex": "#b40f00",
          "name": "#b40f00",
          "reference": "vibrant"
        }, 
        {
          "hex": "#d8c295",
          "name": "#d8c295",
          "reference": "vibrant"
        }, 
        {
          "hex": "#b82a04",
          "name": "#b82a04",
          "reference": "vibrant"
        }, 
        {
          "hex": "#aa844a",
          "name": "#aa844a",
          "reference": "vibrant"
        }, 
        {
          "hex": "#c6ac80",
          "name": "#c6ac80",
          "reference": "vibrant"
        }
      ],
      "sizes": {
        "b": {
          "extension": "jpg",
          "height": 450,
          "mimetype": "image/jpeg",
          "secret": "WxBWnRMqXeZNUn8Hq3syB6M0XpRGzrJU",
          "width": 1024
        },
        "c": {
          "extension": "jpg",
          "height": 351,
          "mimetype": "image/jpeg",
          "secret": "WxBWnRMqXeZNUn8Hq3syB6M0XpRGzrJU",
          "width": 800
        },
        "dc": {
          "extension": "jpg",
          "height": 351,
          "mimetype": "image/jpeg",
          "secret": "WxBWnRMqXeZNUn8Hq3syB6M0XpRGzrJU",
          "width": 800
        },
        "ds": {
          "extension": "jpg",
          "height": 320,
          "mimetype": "image/jpeg",
          "secret": "WxBWnRMqXeZNUn8Hq3syB6M0XpRGzrJU",
          "width": 320
        },
        "k": {
          "extension": "jpg",
          "height": 900,
          "mimetype": "image/jpeg",
          "secret": "WxBWnRMqXeZNUn8Hq3syB6M0XpRGzrJU",
          "width": 2048
        },
        "n": {
          "extension": "jpg",
          "height": 140,
          "mimetype": "image/jpeg",
          "secret": "WxBWnRMqXeZNUn8Hq3syB6M0XpRGzrJU",
          "width": 320
        },
        "o": {
          "extension": "jpg",
          "height": 1267,
          "mimetype": "image/jpeg",
          "secret": "TYagYdq6nrcZMdPCKkbUrs1LK1LpeyiV",
          "width": 2880
        },
        "s": {
          "extension": "jpg",
          "height": 320,
          "mimetype": "image/jpeg",
          "secret": "WxBWnRMqXeZNUn8Hq3syB6M0XpRGzrJU",
          "width": 320
        },
        "z": {
          "extension": "jpg",
          "height": 281,
          "mimetype": "image/jpeg",
          "secret": "WxBWnRMqXeZNUn8Hq3syB6M0XpRGzrJU",
          "width": 640
        }
      }
    },
    "media:uri_template": "https://millsfield.sfomuseum.org/media/152/781/990/7/1527819907_{secret}_{label}.{extention}",
    "sfomuseum:filename": "31163.tif",
    "sfomuseum:image_index": 5,
    "sfomuseum:placetype": "image",
    "sfomuseum:primary_image": 0,
    "wof:depicts": [
      1511907979
    ],
    "wof:name": "airmail flight cover: Golden Gate International Exposition, National Air Mail Week, May 15-21, 1939",
    "wof:placetype": "media"
  },
  "geometry": {"coordinates":[-122.386155,37.616358],"type":"Point"}
}
