{
  "type": "Feature",
  "properties": {
    "iso:country": "XX",
    "media:fingerprint": "e65e15943c910c6490230d9b6e9a1def617b40f8",
    "media:imagehash_avg": "a:fefefefee6e6e6c2",
    "media:imagehash_diff": "d:242664664c0e0c0c",
    "media:medium": "image",
    "media:mimetype": "image/tiff",
    "media:properties": {
      "colours": [
        {
          "hex": "#cbb74c",
          "name": "#cbb74c",
          "reference": "vibrant"
        },
        {
          "hex": "#e5dab0",
          "name": "#e5dab0",
          "reference": "vibrant"
        },
        {
          "hex": "#2f2c11",
          "name": "#2f2c11",
          "reference": "vibrant"
        },
        {
          "hex": "#9c8753",
          "name": "#9c8753",
          "reference": "vibrant"
        },
        {
          "hex": "#cec3b0",
          "name": "#cec3b0",
          "reference": "vibrant"
        }
      ],
      "sizes": {
        "b": {
          "extension": "jpg",
          "height": 768,
          "mimetype": "image/jpeg",
          "secret": "3gu7QFuDXayvNqvmQt8VKDiNWQyUY5eh",
          "width": 608
        },
        "c": {
          "extension": "jpg",
          "height": 600,
          "mimetype": "image/jpeg",
          "secret": "3gu7QFuDXayvNqvmQt8VKDiNWQyUY5eh",
          "width": 475
        },
        "dc": {
          "extension": "jpg",
          "height": 600,
          "mimetype": "image/jpeg",
          "secret": "3gu7QFuDXayvNqvmQt8VKDiNWQyUY5eh",
          "width": 475
        },
        "ds": {
          "extension": "jpg",
          "height": 320,
          "mimetype": "image/jpeg",
          "secret": "3gu7QFuDXayvNqvmQt8VKDiNWQyUY5eh",
          "width": 320
        },
        "k": {
          "extension": "jpg",
          "height": 1536,
          "mimetype": "image/jpeg",
          "secret": "3gu7QFuDXayvNqvmQt8VKDiNWQyUY5eh",
          "width": 1216
        },
        "n": {
          "extension": "jpg",
          "height": 240,
          "mimetype": "image/jpeg",
          "secret": "3gu7QFuDXayvNqvmQt8VKDiNWQyUY5eh",
          "width": 190
        },
        "o": {
          "extension": "jpg",
          "height": 2125,
          "mimetype": "image/jpeg",
          "secret": "XOKeBONf2am5jZ4ZRFjdcd7z0CnoQBPh",
          "width": 1683
        },
        "s": {
          "extension": "jpg",
          "height": 320,
          "mimetype": "image/jpeg",
          "secret": "3gu7QFuDXayvNqvmQt8VKDiNWQyUY5eh",
          "width": 320
        },
        "z": {
          "extension": "jpg",
          "height": 480,
          "mimetype": "image/jpeg",
          "secret": "3gu7QFuDXayvNqvmQt8VKDiNWQyUY5eh",
          "width": 380
        }
      }
    },
    "media:uri_template": "https://static.sfomuseum.org/media/152/784/541/9/1527845419_{secret}_{label}.{extention}",
    "sfomuseum:filename": "2011126452_front.tif",
    "sfomuseum:image_index": 5,
    "sfomuseum:image_type": "studio",
    "sfomuseum:placetype": "image",
    "sfomuseum:primary_image": 1,
    "wof:depicts": [
      1159285415,
      1511951041,
      1159288779
    ],
    "wof:name": "menu: United Air Lines",
    "wof:placetype": "custom",
    "wof:placetype_alt": "image"
  },
  "geometry": {"coordinates":[-122.386155,37.616358],"type":"Point"}
}
