{
  "type": "Feature",
  "properties": {
    "iso:country": "XX",
    "media:fingerprint": "828e0683d9453818a2b2924477a6e956d74a80fb",
    "media:imagehash_avg": "a:ffc1c181818381ff",
    "media:imagehash_diff": "d:0313131b2f3f3f01",
    "media:medium": "image",
    "media:mimetype": "image/tiff",
    "media:properties": {
      "colours": [
        {
          "hex": "#c25d04",
          "name": "#c25d04",
          "reference": "vibrant"
        },
        {
          "hex": "#c36e85",
          "name": "#c36e85",
          "reference": "vibrant"
        },
        {
          "hex": "#84390b",
          "name": "#84390b",
          "reference": "vibrant"
        },
        {
          "hex": "#777482",
          "name": "#777482",
          "reference": "vibrant"
        },
        {
          "hex": "#c4c5bc",
          "name": "#c4c5bc",
          "reference": "vibrant"
        }
      ],
      "sizes": {
        "b": {
          "extension": "jpg",
          "height": 768,
          "mimetype": "image/jpeg",
          "secret": "SiA0smYwnEHyQvRLC51rvgUs5VLBjm0x",
          "width": 544
        },
        "c": {
          "extension": "jpg",
          "height": 600,
          "mimetype": "image/jpeg",
          "secret": "SiA0smYwnEHyQvRLC51rvgUs5VLBjm0x",
          "width": 425
        },
        "dc": {
          "extension": "jpg",
          "height": 600,
          "mimetype": "image/jpeg",
          "secret": "SiA0smYwnEHyQvRLC51rvgUs5VLBjm0x",
          "width": 425
        },
        "ds": {
          "extension": "jpg",
          "height": 320,
          "mimetype": "image/jpeg",
          "secret": "SiA0smYwnEHyQvRLC51rvgUs5VLBjm0x",
          "width": 320
        },
        "k": {
          "extension": "jpg",
          "height": 1536,
          "mimetype": "image/jpeg",
          "secret": "SiA0smYwnEHyQvRLC51rvgUs5VLBjm0x",
          "width": 1088
        },
        "n": {
          "extension": "jpg",
          "height": 240,
          "mimetype": "image/jpeg",
          "secret": "SiA0smYwnEHyQvRLC51rvgUs5VLBjm0x",
          "width": 170
        },
        "o": {
          "extension": "jpg",
          "height": 1996,
          "mimetype": "image/jpeg",
          "secret": "CyCouQ6FIgroG6dsWIMR3o6q6Z8IBcWB",
          "width": 1415
        },
        "s": {
          "extension": "jpg",
          "height": 320,
          "mimetype": "image/jpeg",
          "secret": "SiA0smYwnEHyQvRLC51rvgUs5VLBjm0x",
          "width": 320
        },
        "z": {
          "extension": "jpg",
          "height": 480,
          "mimetype": "image/jpeg",
          "secret": "SiA0smYwnEHyQvRLC51rvgUs5VLBjm0x",
          "width": 340
        }
      }
    },
    "media:uri_template": "https://static.sfomuseum.org/media/152/784/433/7/1527844337_{secret}_{label}.{extention}",
    "sfomuseum:filename": "2006059306006_front.tif",
    "sfomuseum:image_index": 5,
    "sfomuseum:image_type": "studio",
    "sfomuseum:placetype": "image",
    "sfomuseum:primary_image": 1,
    "wof:depicts": [
      1159284021,
      1511928503
    ],
    "wof:name": "menu: British Airways, Economy Class",
    "wof:placetype": "custom",
    "wof:placetype_alt": "image"
  },
  "geometry": {"coordinates":[-122.386155,37.616358],"type":"Point"}
}
