{
  "type": "Feature",
  "properties": {
    "iso:country": "XX",
    "media:fingerprint": "ac9910a9d52c4ccc994342ea22dd5f06d2a3d078",
    "media:imagehash_avg": "a:bf1f071f1f17179f",
    "media:imagehash_diff": "d:75776d7773657479",
    "media:medium": "image",
    "media:mimetype": "image/tiff",
    "media:properties": {
      "colours": [
        {
          "hex": "#0068b8",
          "name": "#0068b8",
          "reference": "vibrant"
        }, 
        {
          "hex": "#e6d6b8",
          "name": "#e6d6b8",
          "reference": "vibrant"
        }, 
        {
          "hex": "#025088",
          "name": "#025088",
          "reference": "vibrant"
        }, 
        {
          "hex": "#867f6d",
          "name": "#867f6d",
          "reference": "vibrant"
        }, 
        {
          "hex": "#d5c5a7",
          "name": "#d5c5a7",
          "reference": "vibrant"
        }
      ],
      "sizes": {
        "b": {
          "extension": "jpg",
          "height": 768,
          "mimetype": "image/jpeg",
          "secret": "DVP7gscwu2m9Q9MaOxMuKkoExYbSea0J",
          "width": 688
        },
        "c": {
          "extension": "jpg",
          "height": 600,
          "mimetype": "image/jpeg",
          "secret": "DVP7gscwu2m9Q9MaOxMuKkoExYbSea0J",
          "width": 538
        },
        "dc": {
          "extension": "jpg",
          "height": 600,
          "mimetype": "image/jpeg",
          "secret": "DVP7gscwu2m9Q9MaOxMuKkoExYbSea0J",
          "width": 538
        },
        "ds": {
          "extension": "jpg",
          "height": 320,
          "mimetype": "image/jpeg",
          "secret": "DVP7gscwu2m9Q9MaOxMuKkoExYbSea0J",
          "width": 320
        },
        "k": {
          "extension": "jpg",
          "height": 1536,
          "mimetype": "image/jpeg",
          "secret": "DVP7gscwu2m9Q9MaOxMuKkoExYbSea0J",
          "width": 1377
        },
        "n": {
          "extension": "jpg",
          "height": 239,
          "mimetype": "image/jpeg",
          "secret": "DVP7gscwu2m9Q9MaOxMuKkoExYbSea0J",
          "width": 215
        },
        "o": {
          "extension": "jpg",
          "height": 2729,
          "mimetype": "image/jpeg",
          "secret": "4Tuq8xrA9P3jVGaVOz4gnu4YLCfoYtT6",
          "width": 2448
        },
        "s": {
          "extension": "jpg",
          "height": 320,
          "mimetype": "image/jpeg",
          "secret": "DVP7gscwu2m9Q9MaOxMuKkoExYbSea0J",
          "width": 320
        },
        "z": {
          "extension": "jpg",
          "height": 479,
          "mimetype": "image/jpeg",
          "secret": "DVP7gscwu2m9Q9MaOxMuKkoExYbSea0J",
          "width": 430
        }
      }
    },
    "media:uri_template": "https://millsfield.sfomuseum.org/media/152/785/509/7/1527855097_{secret}_{label}.{extention}",
    "sfomuseum:filename": "2005.132.052.013_interior.tif",
    "sfomuseum:image_index": 5,
    "sfomuseum:placetype": "image",
    "sfomuseum:primary_image": 0,
    "wof:depicts": [
      1511937743
    ],
    "wof:name": "timetable: West Coast Airlines, winter and spring schedule",
    "wof:placetype": "media"
  },
  "geometry": {"coordinates":[-122.386155,37.616358],"type":"Point"}
}
