{
  "type": "Feature",
  "properties": {
    "iso:country": "XX",
    "media:fingerprint": "8ea60bceb100837f4ba0bbd795ffcfadce4ff106",
    "media:imagehash_avg": "a:2030508e8ebe727e",
    "media:imagehash_diff": "d:4d65a43c7852e2ca",
    "media:medium": "image",
    "media:mimetype": "image/tiff",
    "media:properties": {
      "colours": [
        {
          "hex": "#e4ab26",
          "name": "#e4ab26",
          "reference": "vibrant"
        },
        {
          "hex": "#f2e9d4",
          "name": "#f2e9d4",
          "reference": "vibrant"
        },
        {
          "hex": "#7e070d",
          "name": "#7e070d",
          "reference": "vibrant"
        },
        {
          "hex": "#5b6294",
          "name": "#5b6294",
          "reference": "vibrant"
        },
        {
          "hex": "#cbbcaa",
          "name": "#cbbcaa",
          "reference": "vibrant"
        }
      ],
      "sizes": {
        "b": {
          "extension": "jpg",
          "height": 768,
          "mimetype": "image/jpeg",
          "secret": "2rEy71ZdcasZwWgdtVzPFn1dMBl8ls7R",
          "width": 554
        },
        "c": {
          "extension": "jpg",
          "height": 600,
          "mimetype": "image/jpeg",
          "secret": "2rEy71ZdcasZwWgdtVzPFn1dMBl8ls7R",
          "width": 433
        },
        "dc": {
          "extension": "jpg",
          "height": 600,
          "mimetype": "image/jpeg",
          "secret": "2rEy71ZdcasZwWgdtVzPFn1dMBl8ls7R",
          "width": 433
        },
        "ds": {
          "extension": "jpg",
          "height": 320,
          "mimetype": "image/jpeg",
          "secret": "2rEy71ZdcasZwWgdtVzPFn1dMBl8ls7R",
          "width": 320
        },
        "k": {
          "extension": "jpg",
          "height": 1536,
          "mimetype": "image/jpeg",
          "secret": "2rEy71ZdcasZwWgdtVzPFn1dMBl8ls7R",
          "width": 1108
        },
        "n": {
          "extension": "jpg",
          "height": 240,
          "mimetype": "image/jpeg",
          "secret": "2rEy71ZdcasZwWgdtVzPFn1dMBl8ls7R",
          "width": 173
        },
        "o": {
          "extension": "jpg",
          "height": 2107,
          "mimetype": "image/jpeg",
          "secret": "Z1y65FANbIiSrKHf9Wa17XpCfVrh0p1o",
          "width": 1521
        },
        "s": {
          "extension": "jpg",
          "height": 320,
          "mimetype": "image/jpeg",
          "secret": "2rEy71ZdcasZwWgdtVzPFn1dMBl8ls7R",
          "width": 320
        },
        "z": {
          "extension": "jpg",
          "height": 480,
          "mimetype": "image/jpeg",
          "secret": "2rEy71ZdcasZwWgdtVzPFn1dMBl8ls7R",
          "width": 346
        }
      }
    },
    "media:uri_template": "https://static.sfomuseum.org/media/152/784/808/5/1527848085_{secret}_{label}.{extention}",
    "sfomuseum:filename": "2002113307_front.tif",
    "sfomuseum:image_index": 5,
    "sfomuseum:image_type": "studio",
    "sfomuseum:placetype": "image",
    "sfomuseum:primary_image": 1,
    "wof:depicts": [
      1159285393,
      1511925159
    ],
    "wof:name": "menu: TWA (Trans World Airlines), Ambassador (Business) Class",
    "wof:placetype": "custom",
    "wof:placetype_alt": "image"
  },
  "geometry": {"coordinates":[-122.386155,37.616358],"type":"Point"}
}
