{
  "type": "Feature",
  "properties": {
    "iso:country": "XX",
    "media:fingerprint": "76c5c5fc83104a99a036b3f8a0eec491e6e713fd",
    "media:imagehash_avg": "a:bc0080f0c0e0fcfd",
    "media:imagehash_diff": "d:694d0941050d4141",
    "media:medium": "image",
    "media:mimetype": "image/jpeg",
    "media:properties": {
      "colours": [
        {
          "hex": "#121c4d",
          "name": "#121c4d",
          "reference": "vibrant"
        }, 
        {
          "hex": "#88867a",
          "name": "#88867a",
          "reference": "vibrant"
        }, 
        {
          "hex": "#bab8a7",
          "name": "#bab8a7",
          "reference": "vibrant"
        }, 
        {
          "hex": "#424650",
          "name": "#424650",
          "reference": "vibrant"
        }
      ],
      "sizes": {
        "b": {
          "extension": "jpg",
          "height": 768,
          "mimetype": "image/jpeg",
          "secret": "04u7YArt2ehBxu3UI8Ls085aL3uI6kVB",
          "width": 555
        },
        "c": {
          "extension": "jpg",
          "height": 600,
          "mimetype": "image/jpeg",
          "secret": "04u7YArt2ehBxu3UI8Ls085aL3uI6kVB",
          "width": 433
        },
        "dc": {
          "extension": "jpg",
          "height": 600,
          "mimetype": "image/jpeg",
          "secret": "04u7YArt2ehBxu3UI8Ls085aL3uI6kVB",
          "width": 433
        },
        "ds": {
          "extension": "jpg",
          "height": 320,
          "mimetype": "image/jpeg",
          "secret": "04u7YArt2ehBxu3UI8Ls085aL3uI6kVB",
          "width": 320
        },
        "k": {
          "extension": "jpg",
          "height": 1536,
          "mimetype": "image/jpeg",
          "secret": "04u7YArt2ehBxu3UI8Ls085aL3uI6kVB",
          "width": 1110
        },
        "n": {
          "extension": "jpg",
          "height": 240,
          "mimetype": "image/jpeg",
          "secret": "04u7YArt2ehBxu3UI8Ls085aL3uI6kVB",
          "width": 173
        },
        "o": {
          "extension": "jpg",
          "height": 2821,
          "mimetype": "image/jpeg",
          "secret": "lyaKMDQPgmY2Gbncj6Cthiq0JqjvPCyo",
          "width": 2040
        },
        "s": {
          "extension": "jpg",
          "height": 320,
          "mimetype": "image/jpeg",
          "secret": "04u7YArt2ehBxu3UI8Ls085aL3uI6kVB",
          "width": 320
        },
        "z": {
          "extension": "jpg",
          "height": 480,
          "mimetype": "image/jpeg",
          "secret": "04u7YArt2ehBxu3UI8Ls085aL3uI6kVB",
          "width": 347
        }
      }
    },
    "media:uri_template": "https://millsfield.sfomuseum.org/media/152/781/825/5/1527818255_{secret}_{label}.{extention}",
    "sfomuseum:filename": "16316.jpg",
    "sfomuseum:image_index": 5,
    "sfomuseum:placetype": "image",
    "sfomuseum:primary_image": 1,
    "wof:depicts": [
      1511925737
    ],
    "wof:name": "menu cover: Pan American Airways Inn, Midway",
    "wof:placetype": "media"
  },
  "geometry": {"coordinates":[-122.386155,37.616358],"type":"Point"}
}
