{
  "type": "Feature",
  "properties": {
    "iso:country": "XX",
    "media:fingerprint": "39ffb5c79aab5acaff022da4c436f47751a438cd",
    "media:imagehash_avg": "a:ffffff3c30000000",
    "media:imagehash_diff": "d:fcf0f8f8e0e0f078",
    "media:medium": "image",
    "media:mimetype": "image/tiff",
    "media:properties": {
      "colours": [
        {
          "hex": "#808080",
          "name": "#808080",
          "reference": "vibrant"
        }, 
        {
          "hex": "#b6b6b6",
          "name": "#b6b6b6",
          "reference": "vibrant"
        }, 
        {
          "hex": "#464646",
          "name": "#464646",
          "reference": "vibrant"
        }
      ],
      "sizes": {
        "b": {
          "extension": "jpg",
          "height": 768,
          "mimetype": "image/jpeg",
          "secret": "tAZiqkTfBMi1oKaU9vnmDJWlCMRtNJmH",
          "width": 980
        },
        "c": {
          "extension": "jpg",
          "height": 600,
          "mimetype": "image/jpeg",
          "secret": "tAZiqkTfBMi1oKaU9vnmDJWlCMRtNJmH",
          "width": 766
        },
        "dc": {
          "extension": "jpg",
          "height": 600,
          "mimetype": "image/jpeg",
          "secret": "tAZiqkTfBMi1oKaU9vnmDJWlCMRtNJmH",
          "width": 766
        },
        "ds": {
          "extension": "jpg",
          "height": 320,
          "mimetype": "image/jpeg",
          "secret": "tAZiqkTfBMi1oKaU9vnmDJWlCMRtNJmH",
          "width": 320
        },
        "k": {
          "extension": "jpg",
          "height": 1536,
          "mimetype": "image/jpeg",
          "secret": "tAZiqkTfBMi1oKaU9vnmDJWlCMRtNJmH",
          "width": 1961
        },
        "n": {
          "extension": "jpg",
          "height": 240,
          "mimetype": "image/jpeg",
          "secret": "tAZiqkTfBMi1oKaU9vnmDJWlCMRtNJmH",
          "width": 306
        },
        "o": {
          "extension": "jpg",
          "height": 2168,
          "mimetype": "image/jpeg",
          "secret": "ItyvuOIUn9k9SU9G1GsBeNemhmJuxqvM",
          "width": 2768
        },
        "s": {
          "extension": "jpg",
          "height": 320,
          "mimetype": "image/jpeg",
          "secret": "tAZiqkTfBMi1oKaU9vnmDJWlCMRtNJmH",
          "width": 320
        },
        "z": {
          "extension": "jpg",
          "height": 480,
          "mimetype": "image/jpeg",
          "secret": "tAZiqkTfBMi1oKaU9vnmDJWlCMRtNJmH",
          "width": 612
        }
      }
    },
    "media:uri_template": "https://millsfield.sfomuseum.org/media/152/782/495/1/1527824951_{secret}_{label}.{extention}",
    "sfomuseum:filename": "42897.tif",
    "sfomuseum:image_index": 5,
    "sfomuseum:placetype": "image",
    "sfomuseum:primary_image": 1,
    "wof:depicts": [
      1511945833
    ],
    "wof:name": "negative: San Francisco International Airport (SFO), aerial",
    "wof:placetype": "media"
  },
  "geometry": {"coordinates":[-122.386155,37.616358],"type":"Point"}
}
