{
  "type": "Feature",
  "properties": {
    "iso:country": "XX",
    "media:fingerprint": "f124ca62216e819135a59819ae1fe3c743a64f8e",
    "media:imagehash_avg": "a:ffff03000000ffff",
    "media:imagehash_diff": "d:382867e40f3f33b2",
    "media:medium": "image",
    "media:mimetype": "image/tiff",
    "media:properties": {
      "colours": [
        {
          "hex": "#808080",
          "name": "#808080",
          "reference": "vibrant"
        }, 
        {
          "hex": "#c0c0c0",
          "name": "#c0c0c0",
          "reference": "vibrant"
        }, 
        {
          "hex": "#404040",
          "name": "#404040",
          "reference": "vibrant"
        }
      ],
      "sizes": {
        "b": {
          "extension": "jpg",
          "height": 768,
          "mimetype": "image/jpeg",
          "secret": "MQGHMp8qmGBy75uMAbQn5L5zw7VBCBOI",
          "width": 998
        },
        "c": {
          "extension": "jpg",
          "height": 600,
          "mimetype": "image/jpeg",
          "secret": "MQGHMp8qmGBy75uMAbQn5L5zw7VBCBOI",
          "width": 780
        },
        "dc": {
          "extension": "jpg",
          "height": 600,
          "mimetype": "image/jpeg",
          "secret": "MQGHMp8qmGBy75uMAbQn5L5zw7VBCBOI",
          "width": 780
        },
        "ds": {
          "extension": "jpg",
          "height": 320,
          "mimetype": "image/jpeg",
          "secret": "MQGHMp8qmGBy75uMAbQn5L5zw7VBCBOI",
          "width": 320
        },
        "k": {
          "extension": "jpg",
          "height": 1536,
          "mimetype": "image/jpeg",
          "secret": "MQGHMp8qmGBy75uMAbQn5L5zw7VBCBOI",
          "width": 1996
        },
        "n": {
          "extension": "jpg",
          "height": 240,
          "mimetype": "image/jpeg",
          "secret": "MQGHMp8qmGBy75uMAbQn5L5zw7VBCBOI",
          "width": 312
        },
        "o": {
          "extension": "jpg",
          "height": 1043,
          "mimetype": "image/jpeg",
          "secret": "w5AI7AgJURQ7U4HECLJg9qK1XWqQkDvc",
          "width": 1356
        },
        "s": {
          "extension": "jpg",
          "height": 320,
          "mimetype": "image/jpeg",
          "secret": "MQGHMp8qmGBy75uMAbQn5L5zw7VBCBOI",
          "width": 320
        },
        "z": {
          "extension": "jpg",
          "height": 480,
          "mimetype": "image/jpeg",
          "secret": "MQGHMp8qmGBy75uMAbQn5L5zw7VBCBOI",
          "width": 624
        }
      }
    },
    "media:uri_template": "https://millsfield.sfomuseum.org/media/152/782/097/9/1527820979_{secret}_{label}.{extention}",
    "sfomuseum:filename": "33268.tif",
    "sfomuseum:image_index": 5,
    "sfomuseum:placetype": "image",
    "sfomuseum:primary_image": 1,
    "wof:depicts": [
      1511931445
    ],
    "wof:name": "photograph: Pan American Airways, Lockheed L-049 Constellation",
    "wof:placetype": "media"
  },
  "geometry": {"coordinates":[-122.386155,37.616358],"type":"Point"}
}
