{
  "type": "Feature",
  "properties": {
    "date:cessation_lower": "1954-01-01",
    "date:cessation_upper": "1954-12-31",
    "date:inception_lower": "1954-01-01",
    "date:inception_upper": "1954-12-31",
    "iso:country": "XX",
    "sfomuseum:image_index": 5,
    "sfomuseum:image_type": "studio",
    "sfomuseum:placetype": "image",
    "sfomuseum:primary_image": 1,
    "wof:depicts": [
      1511932839,
      1159284989,
      1159289651,
      1159293593
    ],
    "wof:name": "menu: Pan American World Airways, San Francisco 49ers, Clementine the Mule mascot",
    "wof:placetype": "custom"
  },
  "geometry": {"coordinates":[-122.386155,37.616357],"type":"Point"}
}
