{
  "type": "Feature",
  "properties": {
    "iso:country": "XX",
    "media:fingerprint": "62a6b56b4b34a31d377fb63ca1143c90684d8429",
    "media:imagehash_avg": "a:c7838181c1c7c1ff",
    "media:imagehash_diff": "d:2f0f3b2b0b0f0f2d",
    "media:medium": "image",
    "media:mimetype": "image/tiff",
    "media:properties": {
      "colours": [
        {
          "hex": "#d5b088",
          "name": "#d5b088",
          "reference": "vibrant"
        }, 
        {
          "hex": "#ddc898",
          "name": "#ddc898",
          "reference": "vibrant"
        }, 
        {
          "hex": "#88867e",
          "name": "#88867e",
          "reference": "vibrant"
        }, 
        {
          "hex": "#c2c1b6",
          "name": "#c2c1b6",
          "reference": "vibrant"
        }, 
        {
          "hex": "#4a4643",
          "name": "#4a4643",
          "reference": "vibrant"
        }
      ],
      "sizes": {
        "b": {
          "extension": "jpg",
          "height": 768,
          "mimetype": "image/jpeg",
          "secret": "wtBD5Ve1SrprFJcZA74rCFPYZ5OWUcXE",
          "width": 596
        },
        "c": {
          "extension": "jpg",
          "height": 600,
          "mimetype": "image/jpeg",
          "secret": "wtBD5Ve1SrprFJcZA74rCFPYZ5OWUcXE",
          "width": 465
        },
        "dc": {
          "extension": "jpg",
          "height": 600,
          "mimetype": "image/jpeg",
          "secret": "wtBD5Ve1SrprFJcZA74rCFPYZ5OWUcXE",
          "width": 465
        },
        "ds": {
          "extension": "jpg",
          "height": 320,
          "mimetype": "image/jpeg",
          "secret": "wtBD5Ve1SrprFJcZA74rCFPYZ5OWUcXE",
          "width": 320
        },
        "k": {
          "extension": "jpg",
          "height": 1536,
          "mimetype": "image/jpeg",
          "secret": "wtBD5Ve1SrprFJcZA74rCFPYZ5OWUcXE",
          "width": 1192
        },
        "n": {
          "extension": "jpg",
          "height": 240,
          "mimetype": "image/jpeg",
          "secret": "wtBD5Ve1SrprFJcZA74rCFPYZ5OWUcXE",
          "width": 186
        },
        "o": {
          "extension": "jpg",
          "height": 3377,
          "mimetype": "image/jpeg",
          "secret": "J3i5aYxnYnZEoP8KRol9uYt98FYSC3QJ",
          "width": 2622
        },
        "s": {
          "extension": "jpg",
          "height": 320,
          "mimetype": "image/jpeg",
          "secret": "wtBD5Ve1SrprFJcZA74rCFPYZ5OWUcXE",
          "width": 320
        },
        "z": {
          "extension": "jpg",
          "height": 480,
          "mimetype": "image/jpeg",
          "secret": "wtBD5Ve1SrprFJcZA74rCFPYZ5OWUcXE",
          "width": 372
        }
      }
    },
    "media:uri_template": "https://millsfield.sfomuseum.org/media/152/782/116/1/1527821161_{secret}_{label}.{extention}",
    "sfomuseum:filename": "37315.tif",
    "sfomuseum:image_index": 5,
    "sfomuseum:placetype": "image",
    "sfomuseum:primary_image": 1,
    "wof:depicts": [
      1511956167
    ],
    "wof:name": "airmail flight cover: First U.S. Navy Flight, San Francisco - Honolulu, August 31, 1925",
    "wof:placetype": "media"
  },
  "geometry": {"coordinates":[-122.386155,37.616358],"type":"Point"}
}
