{
  "type": "Feature",
  "properties": {
    "iso:country": "XX",
    "media:fingerprint": "d3338eea833228261336939ca04ba0828a87f4f4",
    "media:imagehash_avg": "a:79e18001070f1f3f",
    "media:imagehash_diff": "d:e1870d3b6f1e3f7d",
    "media:medium": "image",
    "media:mimetype": "image/tiff",
    "media:properties": {
      "colours": [
        {
          "hex": "#808080",
          "name": "#808080",
          "reference": "vibrant"
        }, 
        {
          "hex": "#b7b7b7",
          "name": "#b7b7b7",
          "reference": "vibrant"
        }, 
        {
          "hex": "#484848",
          "name": "#484848",
          "reference": "vibrant"
        }
      ],
      "sizes": {
        "b": {
          "extension": "jpg",
          "height": 768,
          "mimetype": "image/jpeg",
          "secret": "uJUhSmpciamXAZfCJVuwJKb9ntDTzbcB",
          "width": 760
        },
        "c": {
          "extension": "jpg",
          "height": 600,
          "mimetype": "image/jpeg",
          "secret": "uJUhSmpciamXAZfCJVuwJKb9ntDTzbcB",
          "width": 594
        },
        "dc": {
          "extension": "jpg",
          "height": 600,
          "mimetype": "image/jpeg",
          "secret": "uJUhSmpciamXAZfCJVuwJKb9ntDTzbcB",
          "width": 594
        },
        "ds": {
          "extension": "jpg",
          "height": 320,
          "mimetype": "image/jpeg",
          "secret": "uJUhSmpciamXAZfCJVuwJKb9ntDTzbcB",
          "width": 320
        },
        "k": {
          "extension": "jpg",
          "height": 1536,
          "mimetype": "image/jpeg",
          "secret": "uJUhSmpciamXAZfCJVuwJKb9ntDTzbcB",
          "width": 1520
        },
        "n": {
          "extension": "jpg",
          "height": 240,
          "mimetype": "image/jpeg",
          "secret": "uJUhSmpciamXAZfCJVuwJKb9ntDTzbcB",
          "width": 237
        },
        "o": {
          "extension": "jpg",
          "height": 1925,
          "mimetype": "image/jpeg",
          "secret": "pjf0L8XYZNPtp8EMWOnSih3MlXCGHKrD",
          "width": 1906
        },
        "s": {
          "extension": "jpg",
          "height": 320,
          "mimetype": "image/jpeg",
          "secret": "uJUhSmpciamXAZfCJVuwJKb9ntDTzbcB",
          "width": 320
        },
        "z": {
          "extension": "jpg",
          "height": 480,
          "mimetype": "image/jpeg",
          "secret": "uJUhSmpciamXAZfCJVuwJKb9ntDTzbcB",
          "width": 475
        }
      }
    },
    "media:uri_template": "https://millsfield.sfomuseum.org/media/152/782/272/1/1527822721_{secret}_{label}.{extention}",
    "sfomuseum:filename": "40875.tif",
    "sfomuseum:image_index": 5,
    "sfomuseum:placetype": "image",
    "sfomuseum:primary_image": 1,
    "wof:depicts": [
      1511944627
    ],
    "wof:name": "photograph: San Francisco International Airport (SFO), construction",
    "wof:placetype": "media"
  },
  "geometry": {"coordinates":[-122.386155,37.616358],"type":"Point"}
}
