{
  "type": "Feature",
  "properties": {
    "iso:country": "XX",
    "media:fingerprint": "33a50735693e43a9d882b55b2d87b4bbd152813f",
    "media:imagehash_avg": "a:3f7f7fffefc38181",
    "media:imagehash_diff": "d:f8f0eeccce133b0f",
    "media:medium": "image",
    "media:mimetype": "image/tiff",
    "media:properties": {
      "colours": [
        {
          "hex": "#808080",
          "name": "#808080",
          "reference": "vibrant"
        }, 
        {
          "hex": "#b5b5b5",
          "name": "#b5b5b5",
          "reference": "vibrant"
        }, 
        {
          "hex": "#404040",
          "name": "#404040",
          "reference": "vibrant"
        }
      ],
      "sizes": {
        "b": {
          "extension": "jpg",
          "height": 767,
          "mimetype": "image/jpeg",
          "secret": "cBio8VOrNfyTnm9keFfbKfw5UmGu6ifi",
          "width": 605
        },
        "c": {
          "extension": "jpg",
          "height": 600,
          "mimetype": "image/jpeg",
          "secret": "cBio8VOrNfyTnm9keFfbKfw5UmGu6ifi",
          "width": 472
        },
        "dc": {
          "extension": "jpg",
          "height": 600,
          "mimetype": "image/jpeg",
          "secret": "cBio8VOrNfyTnm9keFfbKfw5UmGu6ifi",
          "width": 472
        },
        "ds": {
          "extension": "jpg",
          "height": 320,
          "mimetype": "image/jpeg",
          "secret": "cBio8VOrNfyTnm9keFfbKfw5UmGu6ifi",
          "width": 320
        },
        "k": {
          "extension": "jpg",
          "height": 1535,
          "mimetype": "image/jpeg",
          "secret": "cBio8VOrNfyTnm9keFfbKfw5UmGu6ifi",
          "width": 1210
        },
        "n": {
          "extension": "jpg",
          "height": 240,
          "mimetype": "image/jpeg",
          "secret": "cBio8VOrNfyTnm9keFfbKfw5UmGu6ifi",
          "width": 189
        },
        "o": {
          "extension": "jpg",
          "height": 2768,
          "mimetype": "image/jpeg",
          "secret": "X79D6onKGy5i4k86XSmYsjKM4OhgEv8M",
          "width": 2181
        },
        "s": {
          "extension": "jpg",
          "height": 320,
          "mimetype": "image/jpeg",
          "secret": "cBio8VOrNfyTnm9keFfbKfw5UmGu6ifi",
          "width": 320
        },
        "z": {
          "extension": "jpg",
          "height": 480,
          "mimetype": "image/jpeg",
          "secret": "cBio8VOrNfyTnm9keFfbKfw5UmGu6ifi",
          "width": 378
        }
      }
    },
    "media:uri_template": "https://millsfield.sfomuseum.org/media/152/782/696/3/1527826963_{secret}_{label}.{extention}",
    "sfomuseum:filename": "43875.tif",
    "sfomuseum:image_index": 5,
    "sfomuseum:placetype": "image",
    "sfomuseum:primary_image": 1,
    "wof:depicts": [
      1511948001
    ],
    "wof:name": "negative: San Francisco International Airport (SFO), Victor Philpot",
    "wof:placetype": "media"
  },
  "geometry": {"coordinates":[-122.386155,37.616358],"type":"Point"}
}
