{
  "type": "Feature",
  "properties": {
    "iso:country": "XX",
    "media:fingerprint": "d0a9ecbf05eda9d77542634d90fffdceecbfebb0",
    "media:imagehash_avg": "a:7f7f7f7f3e000000",
    "media:imagehash_diff": "d:f8f8f8f8f0e0e0f8",
    "media:medium": "image",
    "media:mimetype": "image/tiff",
    "media:properties": {
      "colours": [
        {
          "hex": "#85847b",
          "name": "#85847b",
          "reference": "vibrant"
        }, 
        {
          "hex": "#b3b3cf",
          "name": "#b3b3cf",
          "reference": "vibrant"
        }, 
        {
          "hex": "#3e4b40",
          "name": "#3e4b40",
          "reference": "vibrant"
        }
      ],
      "sizes": {
        "b": {
          "extension": "jpg",
          "height": 671,
          "mimetype": "image/jpeg",
          "secret": "m4WFZDGmbClSwru58fRy4YMeZu2czSGo",
          "width": 1024
        },
        "c": {
          "extension": "jpg",
          "height": 524,
          "mimetype": "image/jpeg",
          "secret": "m4WFZDGmbClSwru58fRy4YMeZu2czSGo",
          "width": 800
        },
        "dc": {
          "extension": "jpg",
          "height": 524,
          "mimetype": "image/jpeg",
          "secret": "m4WFZDGmbClSwru58fRy4YMeZu2czSGo",
          "width": 800
        },
        "ds": {
          "extension": "jpg",
          "height": 320,
          "mimetype": "image/jpeg",
          "secret": "m4WFZDGmbClSwru58fRy4YMeZu2czSGo",
          "width": 320
        },
        "k": {
          "extension": "jpg",
          "height": 1342,
          "mimetype": "image/jpeg",
          "secret": "m4WFZDGmbClSwru58fRy4YMeZu2czSGo",
          "width": 2048
        },
        "n": {
          "extension": "jpg",
          "height": 209,
          "mimetype": "image/jpeg",
          "secret": "m4WFZDGmbClSwru58fRy4YMeZu2czSGo",
          "width": 320
        },
        "o": {
          "extension": "jpg",
          "height": 1090,
          "mimetype": "image/jpeg",
          "secret": "3IybywkuWiOiGxMiwqOyg37qr1FyAWCm",
          "width": 1663
        },
        "s": {
          "extension": "jpg",
          "height": 320,
          "mimetype": "image/jpeg",
          "secret": "m4WFZDGmbClSwru58fRy4YMeZu2czSGo",
          "width": 320
        },
        "z": {
          "extension": "jpg",
          "height": 419,
          "mimetype": "image/jpeg",
          "secret": "m4WFZDGmbClSwru58fRy4YMeZu2czSGo",
          "width": 640
        }
      }
    },
    "media:uri_template": "https://millsfield.sfomuseum.org/media/152/782/822/1/1527828221_{secret}_{label}.{extention}",
    "sfomuseum:filename": "44436.tif",
    "sfomuseum:image_index": 5,
    "sfomuseum:placetype": "image",
    "sfomuseum:primary_image": 1,
    "wof:depicts": [
      1511949253
    ],
    "wof:name": "negative: San Francisco International Airport (SFO), Concorde",
    "wof:placetype": "media"
  },
  "geometry": {"coordinates":[-122.386155,37.616358],"type":"Point"}
}
