{
  "type": "Feature",
  "properties": {
    "iso:country": "XX",
    "media:fingerprint": "170737fc27b0797ac12fe44de97afd854388c668",
    "media:imagehash_avg": "a:003e60c01e1f3f7f",
    "media:imagehash_diff": "d:b874868830b27cf0",
    "media:medium": "image",
    "media:mimetype": "image/tiff",
    "media:properties": {
      "colours": [
        {
          "hex": "#787878",
          "name": "#787878",
          "reference": "vibrant"
        }, 
        {
          "hex": "#c0c0c0",
          "name": "#c0c0c0",
          "reference": "vibrant"
        }, 
        {
          "hex": "#4a4a4a",
          "name": "#4a4a4a",
          "reference": "vibrant"
        }
      ],
      "sizes": {
        "b": {
          "extension": "jpg",
          "height": 768,
          "mimetype": "image/jpeg",
          "secret": "06PKGe5znFlRVXZT8mLa1flcg7U0crRg",
          "width": 970
        },
        "c": {
          "extension": "jpg",
          "height": 600,
          "mimetype": "image/jpeg",
          "secret": "06PKGe5znFlRVXZT8mLa1flcg7U0crRg",
          "width": 758
        },
        "dc": {
          "extension": "jpg",
          "height": 600,
          "mimetype": "image/jpeg",
          "secret": "06PKGe5znFlRVXZT8mLa1flcg7U0crRg",
          "width": 758
        },
        "ds": {
          "extension": "jpg",
          "height": 320,
          "mimetype": "image/jpeg",
          "secret": "06PKGe5znFlRVXZT8mLa1flcg7U0crRg",
          "width": 320
        },
        "k": {
          "extension": "jpg",
          "height": 1536,
          "mimetype": "image/jpeg",
          "secret": "06PKGe5znFlRVXZT8mLa1flcg7U0crRg",
          "width": 1941
        },
        "n": {
          "extension": "jpg",
          "height": 240,
          "mimetype": "image/jpeg",
          "secret": "06PKGe5znFlRVXZT8mLa1flcg7U0crRg",
          "width": 303
        },
        "o": {
          "extension": "jpg",
          "height": 2227,
          "mimetype": "image/jpeg",
          "secret": "tKcXRtvrks4p3H5GIYqZGIuEv4ANFXBb",
          "width": 2815
        },
        "s": {
          "extension": "jpg",
          "height": 320,
          "mimetype": "image/jpeg",
          "secret": "06PKGe5znFlRVXZT8mLa1flcg7U0crRg",
          "width": 320
        },
        "z": {
          "extension": "jpg",
          "height": 480,
          "mimetype": "image/jpeg",
          "secret": "06PKGe5znFlRVXZT8mLa1flcg7U0crRg",
          "width": 606
        }
      }
    },
    "media:uri_template": "https://millsfield.sfomuseum.org/media/152/782/463/9/1527824639_{secret}_{label}.{extention}",
    "sfomuseum:filename": "42707.tif",
    "sfomuseum:image_index": 5,
    "sfomuseum:placetype": "image",
    "sfomuseum:primary_image": 1,
    "wof:depicts": [
      1511945727
    ],
    "wof:name": "negative: San Francisco International Airport (SFO), Central Terminal lobby",
    "wof:placetype": "media"
  },
  "geometry": {"coordinates":[-122.386155,37.616358],"type":"Point"}
}
