{
  "type": "Feature",
  "properties": {
    "media:fingerprint": "ca5fe1f33e94431d5a0ba2931904aabb70643f5a",
    "media:imagehash_avg": "a:000000c0e2ffefff",
    "media:imagehash_diff": "d:c08020360e880cc0",
    "media:mimetype": "image/tiff",
    "media:properties": {
      "colours": [
        {
          "hex": "#787878",
          "name": "#787878",
          "reference": "vibrant"
        },
        {
          "hex": "#cec0a7",
          "name": "#cec0a7",
          "reference": "vibrant"
        },
        {
          "hex": "#323f53",
          "name": "#323f53",
          "reference": "vibrant"
        }
      ],
      "sizes": {
        "b": {
          "extension": "jpg",
          "height": 768,
          "mimetype": "image/jpeg",
          "secret": "90QYa0QTtGli2EpewkSDVRlTCycqOcBL",
          "width": 960
        },
        "c": {
          "extension": "jpg",
          "height": 600,
          "mimetype": "image/jpeg",
          "secret": "90QYa0QTtGli2EpewkSDVRlTCycqOcBL",
          "width": 750
        },
        "dc": {
          "extension": "jpg",
          "height": 600,
          "mimetype": "image/jpeg",
          "secret": "90QYa0QTtGli2EpewkSDVRlTCycqOcBL",
          "width": 750
        },
        "ds": {
          "extension": "jpg",
          "height": 320,
          "mimetype": "image/jpeg",
          "secret": "90QYa0QTtGli2EpewkSDVRlTCycqOcBL",
          "width": 320
        },
        "k": {
          "extension": "jpg",
          "height": 1536,
          "mimetype": "image/jpeg",
          "secret": "90QYa0QTtGli2EpewkSDVRlTCycqOcBL",
          "width": 1920
        },
        "n": {
          "extension": "jpg",
          "height": 240,
          "mimetype": "image/jpeg",
          "secret": "90QYa0QTtGli2EpewkSDVRlTCycqOcBL",
          "width": 300
        },
        "o": {
          "extension": "jpg",
          "height": 1600,
          "mimetype": "image/jpeg",
          "secret": "D8VMycLOhStJlIGYNxCHVYhsK2ExFB9s",
          "width": 2000
        },
        "s": {
          "extension": "jpg",
          "height": 320,
          "mimetype": "image/jpeg",
          "secret": "90QYa0QTtGli2EpewkSDVRlTCycqOcBL",
          "width": 320
        },
        "z": {
          "extension": "jpg",
          "height": 480,
          "mimetype": "image/jpeg",
          "secret": "90QYa0QTtGli2EpewkSDVRlTCycqOcBL",
          "width": 600
        }
      }
    },
    "media:uri_template": "https://static.sfomuseum.org/media/174/651/223/3/1746512233_{secret}_{label}.{extention}",
    "sfomuseum:filename": "2002.013.001a.tif",
    "sfomuseum:image_index": 5,
    "sfomuseum:image_type": "studio",
    "sfomuseum:placetype": "image",
    "sfomuseum:primary_image": 0,
    "wof:depicts": [
      1159284989,
      1511922859,
      1159290431
    ],
    "wof:name": "model airplane: Pan American World Airways, Douglas DC-6B",
    "wof:placetype": "custom",
    "wof:placetype_alt": "image"
  },
  "geometry": {"coordinates":[-122.386155,37.616357],"type":"Point"}
}
