{
  "type": "Feature",
  "properties": {
    "iso:country": "XX",
    "media:fingerprint": "84d4dd05ae8d187a9be265359db3d5a2d26f04f6",
    "media:imagehash_avg": "a:fffb3b3b180000f9",
    "media:imagehash_diff": "d:2333737373716141",
    "media:medium": "image",
    "media:mimetype": "image/tiff",
    "media:properties": {
      "colours": [
        {
          "hex": "#808080",
          "name": "#808080",
          "reference": "vibrant"
        }, 
        {
          "hex": "#c0c0c0",
          "name": "#c0c0c0",
          "reference": "vibrant"
        }, 
        {
          "hex": "#3a3a3a",
          "name": "#3a3a3a",
          "reference": "vibrant"
        }
      ],
      "sizes": {
        "b": {
          "extension": "jpg",
          "height": 697,
          "mimetype": "image/jpeg",
          "secret": "tbGLDohcd1aEQHD46eqpVg5AcPqtfsk5",
          "width": 1024
        },
        "c": {
          "extension": "jpg",
          "height": 545,
          "mimetype": "image/jpeg",
          "secret": "tbGLDohcd1aEQHD46eqpVg5AcPqtfsk5",
          "width": 800
        },
        "dc": {
          "extension": "jpg",
          "height": 545,
          "mimetype": "image/jpeg",
          "secret": "tbGLDohcd1aEQHD46eqpVg5AcPqtfsk5",
          "width": 800
        },
        "ds": {
          "extension": "jpg",
          "height": 320,
          "mimetype": "image/jpeg",
          "secret": "tbGLDohcd1aEQHD46eqpVg5AcPqtfsk5",
          "width": 320
        },
        "k": {
          "extension": "jpg",
          "height": 1395,
          "mimetype": "image/jpeg",
          "secret": "tbGLDohcd1aEQHD46eqpVg5AcPqtfsk5",
          "width": 2048
        },
        "n": {
          "extension": "jpg",
          "height": 218,
          "mimetype": "image/jpeg",
          "secret": "tbGLDohcd1aEQHD46eqpVg5AcPqtfsk5",
          "width": 320
        },
        "o": {
          "extension": "jpg",
          "height": 1911,
          "mimetype": "image/jpeg",
          "secret": "QDOBmbdWXbB1MUB8EAjcRBW4S7D0sQ3w",
          "width": 2804
        },
        "s": {
          "extension": "jpg",
          "height": 320,
          "mimetype": "image/jpeg",
          "secret": "tbGLDohcd1aEQHD46eqpVg5AcPqtfsk5",
          "width": 320
        },
        "z": {
          "extension": "jpg",
          "height": 436,
          "mimetype": "image/jpeg",
          "secret": "tbGLDohcd1aEQHD46eqpVg5AcPqtfsk5",
          "width": 640
        }
      }
    },
    "media:uri_template": "https://millsfield.sfomuseum.org/media/152/782/272/7/1527822727_{secret}_{label}.{extention}",
    "sfomuseum:filename": "40878.tif",
    "sfomuseum:image_index": 5,
    "sfomuseum:placetype": "image",
    "sfomuseum:primary_image": 1,
    "wof:depicts": [
      1511944633
    ],
    "wof:name": "photograph: San Francisco International Airport (SFO), construction",
    "wof:placetype": "media"
  },
  "geometry": {"coordinates":[-122.386155,37.616358],"type":"Point"}
}
