{
  "type": "Feature",
  "properties": {
    "iso:country": "XX",
    "media:fingerprint": "2713a5ddb9d3be6cf2c30eefedaa1ea195466207",
    "media:imagehash_avg": "a:ff8181818181ffff",
    "media:imagehash_diff": "d:63670f0f6f471d0e",
    "media:medium": "image",
    "media:mimetype": "image/tiff",
    "media:properties": {
      "colours": [
        {
          "hex": "#c96a28",
          "name": "#c96a28",
          "reference": "vibrant"
        },
        {
          "hex": "#f3e1b7",
          "name": "#f3e1b7",
          "reference": "vibrant"
        },
        {
          "hex": "#7e4e3c",
          "name": "#7e4e3c",
          "reference": "vibrant"
        },
        {
          "hex": "#5683a0",
          "name": "#5683a0",
          "reference": "vibrant"
        },
        {
          "hex": "#c8c4b6",
          "name": "#c8c4b6",
          "reference": "vibrant"
        }
      ],
      "sizes": {
        "b": {
          "extension": "jpg",
          "height": 739,
          "mimetype": "image/jpeg",
          "secret": "1XfsNJxe24QnBO1n3djTmICK1THQqJAi",
          "width": 1024
        },
        "c": {
          "extension": "jpg",
          "height": 577,
          "mimetype": "image/jpeg",
          "secret": "1XfsNJxe24QnBO1n3djTmICK1THQqJAi",
          "width": 800
        },
        "dc": {
          "extension": "jpg",
          "height": 577,
          "mimetype": "image/jpeg",
          "secret": "1XfsNJxe24QnBO1n3djTmICK1THQqJAi",
          "width": 800
        },
        "ds": {
          "extension": "jpg",
          "height": 320,
          "mimetype": "image/jpeg",
          "secret": "1XfsNJxe24QnBO1n3djTmICK1THQqJAi",
          "width": 320
        },
        "k": {
          "extension": "jpg",
          "height": 1478,
          "mimetype": "image/jpeg",
          "secret": "1XfsNJxe24QnBO1n3djTmICK1THQqJAi",
          "width": 2048
        },
        "n": {
          "extension": "jpg",
          "height": 230,
          "mimetype": "image/jpeg",
          "secret": "1XfsNJxe24QnBO1n3djTmICK1THQqJAi",
          "width": 320
        },
        "o": {
          "extension": "jpg",
          "height": 1533,
          "mimetype": "image/jpeg",
          "secret": "mVy237Mr7NVdQ9UiA1EqTqeFGaUl7PbZ",
          "width": 2124
        },
        "s": {
          "extension": "jpg",
          "height": 320,
          "mimetype": "image/jpeg",
          "secret": "1XfsNJxe24QnBO1n3djTmICK1THQqJAi",
          "width": 320
        },
        "z": {
          "extension": "jpg",
          "height": 461,
          "mimetype": "image/jpeg",
          "secret": "1XfsNJxe24QnBO1n3djTmICK1THQqJAi",
          "width": 640
        }
      }
    },
    "media:uri_template": "https://millsfield.sfomuseum.org/media/152/784/617/1/1527846171_{secret}_{label}.{extention}",
    "sfomuseum:filename": "2001080207_front.tif",
    "sfomuseum:image_index": 5,
    "sfomuseum:placetype": "image",
    "sfomuseum:primary_image": 1,
    "wof:depicts": [
      1511922133
    ],
    "wof:name": "menu: Pan American World Airways, Historic First Flights series, Fokker.VII",
    "wof:placetype": "custom",
    "wof:placetype_alt": "image"
  },
  "geometry": {"coordinates":[-122.386155,37.616358],"type":"Point"}
}
