{
  "type": "Feature",
  "properties": {
    "iso:country": "XX",
    "media:fingerprint": "91bfb8b7a41300763b2b34f12e46a13e6978796a",
    "media:imagehash_avg": "a:7fc38181c38383bf",
    "media:imagehash_diff": "d:e70307270717276f",
    "media:medium": "image",
    "media:mimetype": "image/tiff",
    "media:properties": {
      "colours": [
        {
          "hex": "#d62453",
          "name": "#d62453",
          "reference": "vibrant"
        }, 
        {
          "hex": "#e2a6ae",
          "name": "#e2a6ae",
          "reference": "vibrant"
        }, 
        {
          "hex": "#c81540",
          "name": "#c81540",
          "reference": "vibrant"
        }, 
        {
          "hex": "#858682",
          "name": "#858682",
          "reference": "vibrant"
        }, 
        {
          "hex": "#c3baab",
          "name": "#c3baab",
          "reference": "vibrant"
        }
      ],
      "sizes": {
        "b": {
          "extension": "jpg",
          "height": 768,
          "mimetype": "image/jpeg",
          "secret": "eXSFduaVZ2SaQHo0RahXDnGv3aALRsEl",
          "width": 516
        },
        "c": {
          "extension": "jpg",
          "height": 600,
          "mimetype": "image/jpeg",
          "secret": "eXSFduaVZ2SaQHo0RahXDnGv3aALRsEl",
          "width": 403
        },
        "dc": {
          "extension": "jpg",
          "height": 600,
          "mimetype": "image/jpeg",
          "secret": "eXSFduaVZ2SaQHo0RahXDnGv3aALRsEl",
          "width": 403
        },
        "ds": {
          "extension": "jpg",
          "height": 320,
          "mimetype": "image/jpeg",
          "secret": "eXSFduaVZ2SaQHo0RahXDnGv3aALRsEl",
          "width": 320
        },
        "k": {
          "extension": "jpg",
          "height": 1536,
          "mimetype": "image/jpeg",
          "secret": "eXSFduaVZ2SaQHo0RahXDnGv3aALRsEl",
          "width": 1033
        },
        "n": {
          "extension": "jpg",
          "height": 240,
          "mimetype": "image/jpeg",
          "secret": "eXSFduaVZ2SaQHo0RahXDnGv3aALRsEl",
          "width": 161
        },
        "o": {
          "extension": "jpg",
          "height": 2898,
          "mimetype": "image/jpeg",
          "secret": "DhbD0UvLYWHcC8Fmtgz2FjU7Mp4IT9kx",
          "width": 1950
        },
        "s": {
          "extension": "jpg",
          "height": 320,
          "mimetype": "image/jpeg",
          "secret": "eXSFduaVZ2SaQHo0RahXDnGv3aALRsEl",
          "width": 320
        },
        "z": {
          "extension": "jpg",
          "height": 480,
          "mimetype": "image/jpeg",
          "secret": "eXSFduaVZ2SaQHo0RahXDnGv3aALRsEl",
          "width": 322
        }
      }
    },
    "media:uri_template": "https://millsfield.sfomuseum.org/media/152/782/359/1/1527823591_{secret}_{label}.{extention}",
    "sfomuseum:filename": "41676.tif",
    "sfomuseum:image_index": 5,
    "sfomuseum:placetype": "image",
    "sfomuseum:primary_image": 0,
    "wof:depicts": [
      1511908449
    ],
    "wof:name": "airsickness bag: Braniff International",
    "wof:placetype": "media"
  },
  "geometry": {"coordinates":[-122.386155,37.616358],"type":"Point"}
}
