{
  "type": "Feature",
  "properties": {
    "iso:country": "XX",
    "media:fingerprint": "79071b28f30a978b6c0a70453ed6a6d62b18e184",
    "media:imagehash_avg": "a:ff1f1d0d010000ff",
    "media:imagehash_diff": "d:7f71797979717151",
    "media:medium": "image",
    "media:mimetype": "image/tiff",
    "media:properties": {
      "colours": [
        {
          "hex": "#d8c8a8",
          "name": "#d8c8a8",
          "reference": "vibrant"
        },
        {
          "hex": "#383818",
          "name": "#383818",
          "reference": "vibrant"
        },
        {
          "hex": "#87836b",
          "name": "#87836b",
          "reference": "vibrant"
        },
        {
          "hex": "#d8d2b8",
          "name": "#d8d2b8",
          "reference": "vibrant"
        },
        {
          "hex": "#555137",
          "name": "#555137",
          "reference": "vibrant"
        }
      ],
      "sizes": {
        "b": {
          "extension": "jpg",
          "height": 768,
          "mimetype": "image/jpeg",
          "secret": "GKW2iP1gcT0UnS9wTrvkorotzkMPCt7n",
          "width": 988
        },
        "c": {
          "extension": "jpg",
          "height": 600,
          "mimetype": "image/jpeg",
          "secret": "GKW2iP1gcT0UnS9wTrvkorotzkMPCt7n",
          "width": 772
        },
        "dc": {
          "extension": "jpg",
          "height": 600,
          "mimetype": "image/jpeg",
          "secret": "GKW2iP1gcT0UnS9wTrvkorotzkMPCt7n",
          "width": 772
        },
        "ds": {
          "extension": "jpg",
          "height": 320,
          "mimetype": "image/jpeg",
          "secret": "GKW2iP1gcT0UnS9wTrvkorotzkMPCt7n",
          "width": 320
        },
        "k": {
          "extension": "jpg",
          "height": 1536,
          "mimetype": "image/jpeg",
          "secret": "GKW2iP1gcT0UnS9wTrvkorotzkMPCt7n",
          "width": 1976
        },
        "n": {
          "extension": "jpg",
          "height": 240,
          "mimetype": "image/jpeg",
          "secret": "GKW2iP1gcT0UnS9wTrvkorotzkMPCt7n",
          "width": 308
        },
        "o": {
          "extension": "jpg",
          "height": 2050,
          "mimetype": "image/jpeg",
          "secret": "Z3eZ3sSwPxXtiO7lwiMTKiYA4PM7xJQs",
          "width": 2638
        },
        "s": {
          "extension": "jpg",
          "height": 320,
          "mimetype": "image/jpeg",
          "secret": "GKW2iP1gcT0UnS9wTrvkorotzkMPCt7n",
          "width": 320
        },
        "z": {
          "extension": "jpg",
          "height": 480,
          "mimetype": "image/jpeg",
          "secret": "GKW2iP1gcT0UnS9wTrvkorotzkMPCt7n",
          "width": 617
        }
      }
    },
    "media:uri_template": "https://static.sfomuseum.org/media/152/785/605/7/1527856057_{secret}_{label}.{extention}",
    "sfomuseum:filename": "100571.tif",
    "sfomuseum:image_index": 5,
    "sfomuseum:image_type": "studio",
    "sfomuseum:placetype": "image",
    "sfomuseum:primary_image": 1,
    "wof:depicts": [
      1511942923
    ],
    "wof:name": "photograph: San Francisco Bay Area aerial, fleet of ships in Bay",
    "wof:placetype": "custom",
    "wof:placetype_alt": "image"
  },
  "geometry": {"coordinates":[-122.386155,37.616358],"type":"Point"}
}
