{
  "type": "Feature",
  "properties": {
    "iso:country": "US",
    "media:fingerprint": "52a3f5c9fcac00ea68f3e18d051570d675a4daa4",
    "media:imagehash_avg": "a:ffefcd0000fffffc",
    "media:imagehash_diff": "d:591c191958703020",
    "media:medium": "image",
    "media:mimetype": "image/tiff",
    "media:properties": {
      "colours": [
        {
          "hex": "#808080",
          "name": "#808080",
          "reference": "vibrant"
        }, 
        {
          "hex": "#b8b8b8",
          "name": "#b8b8b8",
          "reference": "vibrant"
        }, 
        {
          "hex": "#404040",
          "name": "#404040",
          "reference": "vibrant"
        }
      ],
      "sizes": {
        "b": {
          "extension": "jpg",
          "height": 768,
          "mimetype": "image/jpeg",
          "secret": "BPTjRfAkDi1rpwShnqHQj7tKEl2zTF5O",
          "width": 956
        },
        "c": {
          "extension": "jpg",
          "height": 600,
          "mimetype": "image/jpeg",
          "secret": "BPTjRfAkDi1rpwShnqHQj7tKEl2zTF5O",
          "width": 747
        },
        "dc": {
          "extension": "jpg",
          "height": 600,
          "mimetype": "image/jpeg",
          "secret": "BPTjRfAkDi1rpwShnqHQj7tKEl2zTF5O",
          "width": 747
        },
        "ds": {
          "extension": "jpg",
          "height": 320,
          "mimetype": "image/jpeg",
          "secret": "BPTjRfAkDi1rpwShnqHQj7tKEl2zTF5O",
          "width": 320
        },
        "k": {
          "extension": "jpg",
          "height": 1536,
          "mimetype": "image/jpeg",
          "secret": "BPTjRfAkDi1rpwShnqHQj7tKEl2zTF5O",
          "width": 1913
        },
        "n": {
          "extension": "jpg",
          "height": 239,
          "mimetype": "image/jpeg",
          "secret": "BPTjRfAkDi1rpwShnqHQj7tKEl2zTF5O",
          "width": 299
        },
        "o": {
          "extension": "jpg",
          "height": 4632,
          "mimetype": "image/jpeg",
          "secret": "JPnUBjF3CdKfFPj2AF245SC6i8IMR7rm",
          "width": 5771
        },
        "s": {
          "extension": "jpg",
          "height": 320,
          "mimetype": "image/jpeg",
          "secret": "BPTjRfAkDi1rpwShnqHQj7tKEl2zTF5O",
          "width": 320
        },
        "z": {
          "extension": "jpg",
          "height": 479,
          "mimetype": "image/jpeg",
          "secret": "BPTjRfAkDi1rpwShnqHQj7tKEl2zTF5O",
          "width": 598
        }
      }
    },
    "media:uri_template": "https://millsfield.sfomuseum.org/media/152/782/878/9/1527828789_{secret}_{label}.{extention}",
    "sfomuseum:filename": "46300.tif",
    "sfomuseum:image_index": 5,
    "sfomuseum:placetype": "image",
    "sfomuseum:primary_image": 1,
    "wof:depicts": [
      1511942981
    ],
    "wof:name": "photograph: San Francisco Airport, Administration Building",
    "wof:placetype": "media"
  },
  "geometry": {"coordinates":[-122.386155,37.616358],"type":"Point"}
}
