{
  "type": "Feature",
  "properties": {
    "iso:country": "XX",
    "media:fingerprint": "0f81860085bf8d09f8782daa7cacc16a55827380",
    "media:imagehash_avg": "a:007e6e6e7e7e7e00",
    "media:imagehash_diff": "d:c290989cc8d8d890",
    "media:medium": "image",
    "media:mimetype": "image/tiff",
    "media:properties": {
      "colours": [
        {
          "hex": "#808080",
          "name": "#808080",
          "reference": "vibrant"
        }, 
        {
          "hex": "#b8b8b8",
          "name": "#b8b8b8",
          "reference": "vibrant"
        }, 
        {
          "hex": "#464646",
          "name": "#464646",
          "reference": "vibrant"
        }
      ],
      "sizes": {
        "b": {
          "extension": "jpg",
          "height": 768,
          "mimetype": "image/jpeg",
          "secret": "uer9eofLZmQ3GLbj5aOHU3fANILrupAv",
          "width": 941
        },
        "c": {
          "extension": "jpg",
          "height": 600,
          "mimetype": "image/jpeg",
          "secret": "uer9eofLZmQ3GLbj5aOHU3fANILrupAv",
          "width": 735
        },
        "dc": {
          "extension": "jpg",
          "height": 600,
          "mimetype": "image/jpeg",
          "secret": "uer9eofLZmQ3GLbj5aOHU3fANILrupAv",
          "width": 735
        },
        "ds": {
          "extension": "jpg",
          "height": 320,
          "mimetype": "image/jpeg",
          "secret": "uer9eofLZmQ3GLbj5aOHU3fANILrupAv",
          "width": 320
        },
        "k": {
          "extension": "jpg",
          "height": 1536,
          "mimetype": "image/jpeg",
          "secret": "uer9eofLZmQ3GLbj5aOHU3fANILrupAv",
          "width": 1883
        },
        "n": {
          "extension": "jpg",
          "height": 240,
          "mimetype": "image/jpeg",
          "secret": "uer9eofLZmQ3GLbj5aOHU3fANILrupAv",
          "width": 294
        },
        "o": {
          "extension": "jpg",
          "height": 2413,
          "mimetype": "image/jpeg",
          "secret": "71HbveK4LpkpeKpfcClK0657dbaLRYjP",
          "width": 2959
        },
        "s": {
          "extension": "jpg",
          "height": 320,
          "mimetype": "image/jpeg",
          "secret": "uer9eofLZmQ3GLbj5aOHU3fANILrupAv",
          "width": 320
        },
        "z": {
          "extension": "jpg",
          "height": 480,
          "mimetype": "image/jpeg",
          "secret": "uer9eofLZmQ3GLbj5aOHU3fANILrupAv",
          "width": 588
        }
      }
    },
    "media:uri_template": "https://millsfield.sfomuseum.org/media/152/782/290/5/1527822905_{secret}_{label}.{extention}",
    "sfomuseum:filename": "41126.tif",
    "sfomuseum:image_index": 5,
    "sfomuseum:placetype": "image",
    "sfomuseum:primary_image": 1,
    "wof:depicts": [
      1511944799
    ],
    "wof:name": "negative: San Francisco International Airport (SFO), architectural diagram",
    "wof:placetype": "media"
  },
  "geometry": {"coordinates":[-122.386155,37.616358],"type":"Point"}
}
