{
  "type": "Feature",
  "properties": {
    "iso:country": "XX",
    "media:fingerprint": "5413b8b216f38383de0d3072d2a2a6e4cf80b9eb",
    "media:imagehash_avg": "a:c0c0c0e1e3ffffff",
    "media:imagehash_diff": "d:19171d4f4b595f59",
    "media:medium": "image",
    "media:mimetype": "image/tiff",
    "media:properties": {
      "colours": [
        {
          "hex": "#e42604",
          "name": "#e42604",
          "reference": "vibrant"
        }, 
        {
          "hex": "#e8d3b1",
          "name": "#e8d3b1",
          "reference": "vibrant"
        }, 
        {
          "hex": "#5f100a",
          "name": "#5f100a",
          "reference": "vibrant"
        }, 
        {
          "hex": "#5e7199",
          "name": "#5e7199",
          "reference": "vibrant"
        }, 
        {
          "hex": "#dad4b9",
          "name": "#dad4b9",
          "reference": "vibrant"
        }
      ],
      "sizes": {
        "b": {
          "extension": "jpg",
          "height": 491,
          "mimetype": "image/jpeg",
          "secret": "jAZykuKTsHKQfIciIH3vAbetoSwlLBmM",
          "width": 1024
        },
        "c": {
          "extension": "jpg",
          "height": 383,
          "mimetype": "image/jpeg",
          "secret": "jAZykuKTsHKQfIciIH3vAbetoSwlLBmM",
          "width": 800
        },
        "dc": {
          "extension": "jpg",
          "height": 383,
          "mimetype": "image/jpeg",
          "secret": "jAZykuKTsHKQfIciIH3vAbetoSwlLBmM",
          "width": 800
        },
        "ds": {
          "extension": "jpg",
          "height": 320,
          "mimetype": "image/jpeg",
          "secret": "jAZykuKTsHKQfIciIH3vAbetoSwlLBmM",
          "width": 320
        },
        "k": {
          "extension": "jpg",
          "height": 982,
          "mimetype": "image/jpeg",
          "secret": "jAZykuKTsHKQfIciIH3vAbetoSwlLBmM",
          "width": 2048
        },
        "n": {
          "extension": "jpg",
          "height": 153,
          "mimetype": "image/jpeg",
          "secret": "jAZykuKTsHKQfIciIH3vAbetoSwlLBmM",
          "width": 320
        },
        "o": {
          "extension": "jpg",
          "height": 1216,
          "mimetype": "image/jpeg",
          "secret": "sYFfTzEaHcvjtnI2AbgIiQnJnUV2rhPM",
          "width": 2534
        },
        "s": {
          "extension": "jpg",
          "height": 320,
          "mimetype": "image/jpeg",
          "secret": "jAZykuKTsHKQfIciIH3vAbetoSwlLBmM",
          "width": 320
        },
        "z": {
          "extension": "jpg",
          "height": 307,
          "mimetype": "image/jpeg",
          "secret": "jAZykuKTsHKQfIciIH3vAbetoSwlLBmM",
          "width": 640
        }
      }
    },
    "media:uri_template": "https://millsfield.sfomuseum.org/media/152/781/958/1/1527819581_{secret}_{label}.{extention}",
    "sfomuseum:filename": "30943.tif",
    "sfomuseum:image_index": 5,
    "sfomuseum:placetype": "image",
    "sfomuseum:primary_image": 0,
    "wof:depicts": [
      1511930679
    ],
    "wof:name": "flight information packet: American Airlines, Boeing 707",
    "wof:placetype": "media"
  },
  "geometry": {"coordinates":[-122.386155,37.616358],"type":"Point"}
}
