{
  "type": "Feature",
  "properties": {
    "iso:country": "XX",
    "media:fingerprint": "5e5ff7fd92c0d69037c07172ff16c2561b56e74d",
    "media:imagehash_avg": "a:ffffff0400000000",
    "media:imagehash_diff": "d:70a8d5d5cd95d4fc",
    "media:medium": "image",
    "media:mimetype": "image/tiff",
    "media:properties": {
      "colours": [
        {
          "hex": "#808080",
          "name": "#808080",
          "reference": "vibrant"
        }, 
        {
          "hex": "#c0c0c0",
          "name": "#c0c0c0",
          "reference": "vibrant"
        }, 
        {
          "hex": "#404040",
          "name": "#404040",
          "reference": "vibrant"
        }
      ],
      "sizes": {
        "b": {
          "extension": "jpg",
          "height": 768,
          "mimetype": "image/jpeg",
          "secret": "5xeGtB4GVZJfZu5DmRChB43gQB1vCQ3v",
          "width": 604
        },
        "c": {
          "extension": "jpg",
          "height": 600,
          "mimetype": "image/jpeg",
          "secret": "5xeGtB4GVZJfZu5DmRChB43gQB1vCQ3v",
          "width": 472
        },
        "dc": {
          "extension": "jpg",
          "height": 600,
          "mimetype": "image/jpeg",
          "secret": "5xeGtB4GVZJfZu5DmRChB43gQB1vCQ3v",
          "width": 472
        },
        "ds": {
          "extension": "jpg",
          "height": 320,
          "mimetype": "image/jpeg",
          "secret": "5xeGtB4GVZJfZu5DmRChB43gQB1vCQ3v",
          "width": 320
        },
        "k": {
          "extension": "jpg",
          "height": 1536,
          "mimetype": "image/jpeg",
          "secret": "5xeGtB4GVZJfZu5DmRChB43gQB1vCQ3v",
          "width": 1209
        },
        "n": {
          "extension": "jpg",
          "height": 240,
          "mimetype": "image/jpeg",
          "secret": "5xeGtB4GVZJfZu5DmRChB43gQB1vCQ3v",
          "width": 188
        },
        "o": {
          "extension": "jpg",
          "height": 2754,
          "mimetype": "image/jpeg",
          "secret": "U4R6gN1ObixMO3t3sFhE8efe68wICJIh",
          "width": 2168
        },
        "s": {
          "extension": "jpg",
          "height": 320,
          "mimetype": "image/jpeg",
          "secret": "5xeGtB4GVZJfZu5DmRChB43gQB1vCQ3v",
          "width": 320
        },
        "z": {
          "extension": "jpg",
          "height": 480,
          "mimetype": "image/jpeg",
          "secret": "5xeGtB4GVZJfZu5DmRChB43gQB1vCQ3v",
          "width": 377
        }
      }
    },
    "media:uri_template": "https://millsfield.sfomuseum.org/media/152/782/140/7/1527821407_{secret}_{label}.{extention}",
    "sfomuseum:filename": "38733.tif",
    "sfomuseum:image_index": 5,
    "sfomuseum:placetype": "image",
    "sfomuseum:primary_image": 1,
    "wof:depicts": [
      1511943553
    ],
    "wof:name": "negative: San Francisco Airport, Cahill group",
    "wof:placetype": "media"
  },
  "geometry": {"coordinates":[-122.386155,37.616358],"type":"Point"}
}
