{
  "type": "Feature",
  "properties": {
    "iso:country": "XX",
    "media:fingerprint": "8059354db47be9492f57702ef214c38e30a28f80",
    "media:imagehash_avg": "a:ffffc98393bf0707",
    "media:imagehash_diff": "d:4212333767656f0d",
    "media:medium": "image",
    "media:mimetype": "image/tiff",
    "media:properties": {
      "colours": [
        {
          "hex": "#070899",
          "name": "#070899",
          "reference": "vibrant"
        },
        {
          "hex": "#eee8d3",
          "name": "#eee8d3",
          "reference": "vibrant"
        },
        {
          "hex": "#472800",
          "name": "#472800",
          "reference": "vibrant"
        },
        {
          "hex": "#988158",
          "name": "#988158",
          "reference": "vibrant"
        },
        {
          "hex": "#c4b595",
          "name": "#c4b595",
          "reference": "vibrant"
        }
      ],
      "sizes": {
        "b": {
          "extension": "jpg",
          "height": 658,
          "mimetype": "image/jpeg",
          "secret": "qNzxcaygPFxdZFYF4X4wP6SvAIa2erVj",
          "width": 1024
        },
        "c": {
          "extension": "jpg",
          "height": 514,
          "mimetype": "image/jpeg",
          "secret": "qNzxcaygPFxdZFYF4X4wP6SvAIa2erVj",
          "width": 800
        },
        "dc": {
          "extension": "jpg",
          "height": 514,
          "mimetype": "image/jpeg",
          "secret": "qNzxcaygPFxdZFYF4X4wP6SvAIa2erVj",
          "width": 800
        },
        "ds": {
          "extension": "jpg",
          "height": 320,
          "mimetype": "image/jpeg",
          "secret": "qNzxcaygPFxdZFYF4X4wP6SvAIa2erVj",
          "width": 320
        },
        "k": {
          "extension": "jpg",
          "height": 1317,
          "mimetype": "image/jpeg",
          "secret": "qNzxcaygPFxdZFYF4X4wP6SvAIa2erVj",
          "width": 2048
        },
        "n": {
          "extension": "jpg",
          "height": 205,
          "mimetype": "image/jpeg",
          "secret": "qNzxcaygPFxdZFYF4X4wP6SvAIa2erVj",
          "width": 320
        },
        "o": {
          "extension": "jpg",
          "height": 802,
          "mimetype": "image/jpeg",
          "secret": "7mwiy4iQWPIFeFUOMw7GY1v8HMZ2cv5M",
          "width": 1247
        },
        "s": {
          "extension": "jpg",
          "height": 320,
          "mimetype": "image/jpeg",
          "secret": "qNzxcaygPFxdZFYF4X4wP6SvAIa2erVj",
          "width": 320
        },
        "z": {
          "extension": "jpg",
          "height": 411,
          "mimetype": "image/jpeg",
          "secret": "qNzxcaygPFxdZFYF4X4wP6SvAIa2erVj",
          "width": 640
        }
      }
    },
    "media:uri_template": "https://static.sfomuseum.org/media/152/784/333/3/1527843333_{secret}_{label}.{extention}",
    "sfomuseum:filename": "2010.225.036.tif",
    "sfomuseum:image_index": 5,
    "sfomuseum:placetype": "image",
    "sfomuseum:primary_image": 1,
    "wof:depicts": [
      1511943091
    ],
    "wof:name": "timetable: Air Maritime",
    "wof:placetype": "custom",
    "wof:placetype_alt": "image"
  },
  "geometry": {"coordinates":[-122.386155,37.616358],"type":"Point"}
}
