{
  "type": "Feature",
  "properties": {
    "iso:country": "XX",
    "media:medium": "image",
    "sfomuseum:filename": "2008.056.1125.tif",
    "sfomuseum:image_index": 5,
    "sfomuseum:image_type": "studio",
    "sfomuseum:placetype": "image",
    "sfomuseum:primary_image": 1,
    "wof:depicts": [
      1159284989,
      1511931193
    ],
    "wof:name": "photograph: Pan American World Airways, stewardess uniform",
    "wof:placetype": "custom",
    "wof:placetype_alt": "image"
  },
  "geometry": {"coordinates":[-122.386155,37.616358],"type":"Point"}
}
