{
  "type": "Feature",
  "properties": {
    "iso:country": "XX",
    "media:fingerprint": "e03700a1e0ec0ef484600f7b6f48678f371f4b29",
    "media:imagehash_avg": "a:ff818181818181ff",
    "media:imagehash_diff": "d:4f0f4d0f0f0f4951",
    "media:medium": "image",
    "media:mimetype": "image/jpeg",
    "media:properties": {
      "colours": [
        {
          "hex": "#cebe83",
          "name": "#cebe83",
          "reference": "vibrant"
        }, 
        {
          "hex": "#6a98a3",
          "name": "#6a98a3",
          "reference": "vibrant"
        }, 
        {
          "hex": "#b2c5c6",
          "name": "#b2c5c6",
          "reference": "vibrant"
        }, 
        {
          "hex": "#645834",
          "name": "#645834",
          "reference": "vibrant"
        }
      ],
      "sizes": {
        "b": {
          "extension": "jpg",
          "height": 697,
          "mimetype": "image/jpeg",
          "secret": "vlv98b68mzakAuoeqymM8TEuS4EuWBQM",
          "width": 1024
        },
        "c": {
          "extension": "jpg",
          "height": 544,
          "mimetype": "image/jpeg",
          "secret": "vlv98b68mzakAuoeqymM8TEuS4EuWBQM",
          "width": 800
        },
        "dc": {
          "extension": "jpg",
          "height": 544,
          "mimetype": "image/jpeg",
          "secret": "vlv98b68mzakAuoeqymM8TEuS4EuWBQM",
          "width": 800
        },
        "ds": {
          "extension": "jpg",
          "height": 320,
          "mimetype": "image/jpeg",
          "secret": "vlv98b68mzakAuoeqymM8TEuS4EuWBQM",
          "width": 320
        },
        "k": {
          "extension": "jpg",
          "height": 1394,
          "mimetype": "image/jpeg",
          "secret": "vlv98b68mzakAuoeqymM8TEuS4EuWBQM",
          "width": 2048
        },
        "n": {
          "extension": "jpg",
          "height": 217,
          "mimetype": "image/jpeg",
          "secret": "vlv98b68mzakAuoeqymM8TEuS4EuWBQM",
          "width": 320
        },
        "o": {
          "extension": "jpg",
          "height": 833,
          "mimetype": "image/jpeg",
          "secret": "19P3Dhcs1y5WTelVFrVPhNdJCgD2wNVm",
          "width": 1223
        },
        "s": {
          "extension": "jpg",
          "height": 320,
          "mimetype": "image/jpeg",
          "secret": "vlv98b68mzakAuoeqymM8TEuS4EuWBQM",
          "width": 320
        },
        "z": {
          "extension": "jpg",
          "height": 435,
          "mimetype": "image/jpeg",
          "secret": "vlv98b68mzakAuoeqymM8TEuS4EuWBQM",
          "width": 640
        }
      }
    },
    "media:uri_template": "https://millsfield.sfomuseum.org/media/152/781/945/9/1527819459_{secret}_{label}.{extention}",
    "sfomuseum:filename": "30791.jpg",
    "sfomuseum:image_index": 5,
    "sfomuseum:placetype": "image",
    "sfomuseum:primary_image": 1,
    "wof:depicts": [
      1511942093
    ],
    "wof:name": "membership card: Stanley Henry Page",
    "wof:placetype": "media"
  },
  "geometry": {"coordinates":[-122.386155,37.616358],"type":"Point"}
}
