{
  "type": "Feature",
  "properties": {
    "iso:country": "XX",
    "media:fingerprint": "3833c52daad36880dad080003dfe571400d44eb7",
    "media:imagehash_avg": "a:c90080807f7f0000",
    "media:imagehash_diff": "d:11151d3dcaee1b59",
    "media:medium": "image",
    "media:mimetype": "image/tiff",
    "media:properties": {
      "colours": [
        {
          "hex": "#dd2a2a",
          "name": "#dd2a2a",
          "reference": "vibrant"
        }, 
        {
          "hex": "#cd969b",
          "name": "#cd969b",
          "reference": "vibrant"
        }, 
        {
          "hex": "#742134",
          "name": "#742134",
          "reference": "vibrant"
        }, 
        {
          "hex": "#5b6eae",
          "name": "#5b6eae",
          "reference": "vibrant"
        }, 
        {
          "hex": "#adafc7",
          "name": "#adafc7",
          "reference": "vibrant"
        }
      ],
      "sizes": {
        "b": {
          "extension": "jpg",
          "height": 768,
          "mimetype": "image/jpeg",
          "secret": "G9LCYteGp2qzM38Lch2xsiMYuoMlR0jY",
          "width": 342
        },
        "c": {
          "extension": "jpg",
          "height": 600,
          "mimetype": "image/jpeg",
          "secret": "G9LCYteGp2qzM38Lch2xsiMYuoMlR0jY",
          "width": 267
        },
        "dc": {
          "extension": "jpg",
          "height": 600,
          "mimetype": "image/jpeg",
          "secret": "G9LCYteGp2qzM38Lch2xsiMYuoMlR0jY",
          "width": 267
        },
        "ds": {
          "extension": "jpg",
          "height": 320,
          "mimetype": "image/jpeg",
          "secret": "G9LCYteGp2qzM38Lch2xsiMYuoMlR0jY",
          "width": 320
        },
        "k": {
          "extension": "jpg",
          "height": 1536,
          "mimetype": "image/jpeg",
          "secret": "G9LCYteGp2qzM38Lch2xsiMYuoMlR0jY",
          "width": 685
        },
        "n": {
          "extension": "jpg",
          "height": 239,
          "mimetype": "image/jpeg",
          "secret": "G9LCYteGp2qzM38Lch2xsiMYuoMlR0jY",
          "width": 107
        },
        "o": {
          "extension": "jpg",
          "height": 2717,
          "mimetype": "image/jpeg",
          "secret": "WHpw2YrkpDnZsaXW2AEDpLzQSywh8GUd",
          "width": 1213
        },
        "s": {
          "extension": "jpg",
          "height": 320,
          "mimetype": "image/jpeg",
          "secret": "G9LCYteGp2qzM38Lch2xsiMYuoMlR0jY",
          "width": 320
        },
        "z": {
          "extension": "jpg",
          "height": 479,
          "mimetype": "image/jpeg",
          "secret": "G9LCYteGp2qzM38Lch2xsiMYuoMlR0jY",
          "width": 214
        }
      }
    },
    "media:uri_template": "https://millsfield.sfomuseum.org/media/152/782/112/1/1527821121_{secret}_{label}.{extention}",
    "sfomuseum:filename": "37250.tif",
    "sfomuseum:image_index": 5,
    "sfomuseum:placetype": "image",
    "sfomuseum:primary_image": 1,
    "wof:depicts": [
      1511943341
    ],
    "wof:name": "traveler information brochure: Air France",
    "wof:placetype": "media"
  },
  "geometry": {"coordinates":[-122.386155,37.616358],"type":"Point"}
}
