{
  "type": "Feature",
  "properties": {
    "iso:country": "XX",
    "media:fingerprint": "d1752c0c30790bce2586b701883317f5472dbe9a",
    "media:imagehash_avg": "a:fffee48080808080",
    "media:imagehash_diff": "d:e0700c4c2c616430",
    "media:medium": "image",
    "media:mimetype": "image/tiff",
    "media:properties": {
      "colours": [
        {
          "hex": "#868686",
          "name": "#868686",
          "reference": "vibrant"
        }, 
        {
          "hex": "#b8b8b8",
          "name": "#b8b8b8",
          "reference": "vibrant"
        }, 
        {
          "hex": "#484848",
          "name": "#484848",
          "reference": "vibrant"
        }
      ],
      "sizes": {
        "b": {
          "extension": "jpg",
          "height": 700,
          "mimetype": "image/jpeg",
          "secret": "lbluFyk5NYeFfK9S2nhAlX4oeleUPBn5",
          "width": 1024
        },
        "c": {
          "extension": "jpg",
          "height": 547,
          "mimetype": "image/jpeg",
          "secret": "lbluFyk5NYeFfK9S2nhAlX4oeleUPBn5",
          "width": 800
        },
        "dc": {
          "extension": "jpg",
          "height": 547,
          "mimetype": "image/jpeg",
          "secret": "lbluFyk5NYeFfK9S2nhAlX4oeleUPBn5",
          "width": 800
        },
        "ds": {
          "extension": "jpg",
          "height": 320,
          "mimetype": "image/jpeg",
          "secret": "lbluFyk5NYeFfK9S2nhAlX4oeleUPBn5",
          "width": 320
        },
        "k": {
          "extension": "jpg",
          "height": 1400,
          "mimetype": "image/jpeg",
          "secret": "lbluFyk5NYeFfK9S2nhAlX4oeleUPBn5",
          "width": 2048
        },
        "n": {
          "extension": "jpg",
          "height": 218,
          "mimetype": "image/jpeg",
          "secret": "lbluFyk5NYeFfK9S2nhAlX4oeleUPBn5",
          "width": 320
        },
        "o": {
          "extension": "jpg",
          "height": 1063,
          "mimetype": "image/jpeg",
          "secret": "eHyXmzm6reJfGML5heBiWxYaAOH6ajvk",
          "width": 1554
        },
        "s": {
          "extension": "jpg",
          "height": 320,
          "mimetype": "image/jpeg",
          "secret": "lbluFyk5NYeFfK9S2nhAlX4oeleUPBn5",
          "width": 320
        },
        "z": {
          "extension": "jpg",
          "height": 437,
          "mimetype": "image/jpeg",
          "secret": "lbluFyk5NYeFfK9S2nhAlX4oeleUPBn5",
          "width": 640
        }
      }
    },
    "media:uri_template": "https://millsfield.sfomuseum.org/media/152/782/853/1/1527828531_{secret}_{label}.{extention}",
    "sfomuseum:filename": "44640.tif",
    "sfomuseum:image_index": 5,
    "sfomuseum:placetype": "image",
    "sfomuseum:primary_image": 1,
    "wof:depicts": [
      1511949563
    ],
    "wof:name": "negative: San Francisco International Airport (SFO), Central Terminal interior",
    "wof:placetype": "media"
  },
  "geometry": {"coordinates":[-122.386155,37.616358],"type":"Point"}
}
