{
  "type": "Feature",
  "properties": {
    "iso:country": "XX",
    "media:fingerprint": "8ffaa6dd48c891ea521c756f3d51415a1f29d124",
    "media:imagehash_avg": "a:d0c0c0c89780ffff",
    "media:imagehash_diff": "d:23210919242f2b47",
    "media:medium": "image",
    "media:mimetype": "image/tiff",
    "media:properties": {
      "colours": [
        {
          "hex": "#baca89",
          "name": "#baca89",
          "reference": "vibrant"
        }, 
        {
          "hex": "#eee386",
          "name": "#eee386",
          "reference": "vibrant"
        }, 
        {
          "hex": "#9aac79",
          "name": "#9aac79",
          "reference": "vibrant"
        }, 
        {
          "hex": "#a8d0d4",
          "name": "#a8d0d4",
          "reference": "vibrant"
        }, 
        {
          "hex": "#484f37",
          "name": "#484f37",
          "reference": "vibrant"
        }
      ],
      "sizes": {
        "b": {
          "extension": "jpg",
          "height": 768,
          "mimetype": "image/jpeg",
          "secret": "W3b9mebzMxHrWE43hFVwqv9P9CLeaSxD",
          "width": 516
        },
        "c": {
          "extension": "jpg",
          "height": 600,
          "mimetype": "image/jpeg",
          "secret": "W3b9mebzMxHrWE43hFVwqv9P9CLeaSxD",
          "width": 403
        },
        "dc": {
          "extension": "jpg",
          "height": 600,
          "mimetype": "image/jpeg",
          "secret": "W3b9mebzMxHrWE43hFVwqv9P9CLeaSxD",
          "width": 403
        },
        "ds": {
          "extension": "jpg",
          "height": 320,
          "mimetype": "image/jpeg",
          "secret": "W3b9mebzMxHrWE43hFVwqv9P9CLeaSxD",
          "width": 320
        },
        "k": {
          "extension": "jpg",
          "height": 1536,
          "mimetype": "image/jpeg",
          "secret": "W3b9mebzMxHrWE43hFVwqv9P9CLeaSxD",
          "width": 1033
        },
        "n": {
          "extension": "jpg",
          "height": 240,
          "mimetype": "image/jpeg",
          "secret": "W3b9mebzMxHrWE43hFVwqv9P9CLeaSxD",
          "width": 161
        },
        "o": {
          "extension": "jpg",
          "height": 2825,
          "mimetype": "image/jpeg",
          "secret": "UBV03JUnVxabQO8znG7j7bTr1s8MJv7y",
          "width": 1901
        },
        "s": {
          "extension": "jpg",
          "height": 320,
          "mimetype": "image/jpeg",
          "secret": "W3b9mebzMxHrWE43hFVwqv9P9CLeaSxD",
          "width": 320
        },
        "z": {
          "extension": "jpg",
          "height": 480,
          "mimetype": "image/jpeg",
          "secret": "W3b9mebzMxHrWE43hFVwqv9P9CLeaSxD",
          "width": 323
        }
      }
    },
    "media:uri_template": "https://millsfield.sfomuseum.org/media/152/782/179/9/1527821799_{secret}_{label}.{extention}",
    "sfomuseum:filename": "39254.tif",
    "sfomuseum:image_index": 5,
    "sfomuseum:placetype": "image",
    "sfomuseum:primary_image": 1,
    "wof:depicts": [
      1511931039
    ],
    "wof:name": "menu: Pan American Airways, Eastern division sales meeting",
    "wof:placetype": "media"
  },
  "geometry": {"coordinates":[-122.386155,37.616358],"type":"Point"}
}
