{
  "type": "Feature",
  "properties": {
    "iso:country": "XX",
    "media:fingerprint": "f0b33b3ec5d016eedd5eb1d40ff710fed09066f5",
    "media:imagehash_avg": "a:ffff8080800000ff",
    "media:imagehash_diff": "d:530b71717171490b",
    "media:medium": "image",
    "media:mimetype": "image/tiff",
    "media:properties": {
      "colours": [
        {
          "hex": "#f8f5e8",
          "name": "#f8f5e8",
          "reference": "vibrant"
        },
        {
          "hex": "#828276",
          "name": "#828276",
          "reference": "vibrant"
        },
        {
          "hex": "#c8c9c1",
          "name": "#c8c9c1",
          "reference": "vibrant"
        },
        {
          "hex": "#45463d",
          "name": "#45463d",
          "reference": "vibrant"
        }
      ],
      "sizes": {
        "b": {
          "extension": "jpg",
          "height": 768,
          "mimetype": "image/jpeg",
          "secret": "yRgUslP0sgTrtPlm5A09cDkh6caPa1m8",
          "width": 524
        },
        "c": {
          "extension": "jpg",
          "height": 600,
          "mimetype": "image/jpeg",
          "secret": "yRgUslP0sgTrtPlm5A09cDkh6caPa1m8",
          "width": 409
        },
        "dc": {
          "extension": "jpg",
          "height": 600,
          "mimetype": "image/jpeg",
          "secret": "yRgUslP0sgTrtPlm5A09cDkh6caPa1m8",
          "width": 409
        },
        "ds": {
          "extension": "jpg",
          "height": 320,
          "mimetype": "image/jpeg",
          "secret": "yRgUslP0sgTrtPlm5A09cDkh6caPa1m8",
          "width": 320
        },
        "k": {
          "extension": "jpg",
          "height": 1536,
          "mimetype": "image/jpeg",
          "secret": "yRgUslP0sgTrtPlm5A09cDkh6caPa1m8",
          "width": 1048
        },
        "n": {
          "extension": "jpg",
          "height": 240,
          "mimetype": "image/jpeg",
          "secret": "yRgUslP0sgTrtPlm5A09cDkh6caPa1m8",
          "width": 163
        },
        "o": {
          "extension": "jpg",
          "height": 3534,
          "mimetype": "image/jpeg",
          "secret": "84Jmk4MOIUnEiZ0vsMjmPXqzF7Yyv6Pw",
          "width": 2412
        },
        "s": {
          "extension": "jpg",
          "height": 320,
          "mimetype": "image/jpeg",
          "secret": "yRgUslP0sgTrtPlm5A09cDkh6caPa1m8",
          "width": 320
        },
        "z": {
          "extension": "jpg",
          "height": 480,
          "mimetype": "image/jpeg",
          "secret": "yRgUslP0sgTrtPlm5A09cDkh6caPa1m8",
          "width": 327
        }
      }
    },
    "media:uri_template": "https://static.sfomuseum.org/media/152/784/478/9/1527844789_{secret}_{label}.{extention}",
    "sfomuseum:filename": "69422.tif",
    "sfomuseum:image_index": 5,
    "sfomuseum:image_type": "studio",
    "sfomuseum:placetype": "image",
    "sfomuseum:primary_image": 1,
    "wof:depicts": [
      1159285479,
      1511949977
    ],
    "wof:name": "timetable: Vietnam Airlines",
    "wof:placetype": "custom",
    "wof:placetype_alt": "image"
  },
  "geometry": {"coordinates":[-122.386155,37.616358],"type":"Point"}
}
