{
  "type": "Feature",
  "properties": {
    "iso:country": "XX",
    "media:fingerprint": "39f76f4aa3f08f4ba5e231c802b0f5dbbc3e681a",
    "media:imagehash_avg": "a:7fff8f0000f0f0f9",
    "media:imagehash_diff": "d:f2727e0b480081c1",
    "media:medium": "image",
    "media:mimetype": "image/tiff",
    "media:properties": {
      "colours": [
        {
          "hex": "#868686",
          "name": "#868686",
          "reference": "vibrant"
        }, 
        {
          "hex": "#b8b8b8",
          "name": "#b8b8b8",
          "reference": "vibrant"
        }, 
        {
          "hex": "#404040",
          "name": "#404040",
          "reference": "vibrant"
        }
      ],
      "sizes": {
        "b": {
          "extension": "jpg",
          "height": 767,
          "mimetype": "image/jpeg",
          "secret": "rBCeWHFzQjhkZGzyi1vFCEpnJiZGNrJ4",
          "width": 988
        },
        "c": {
          "extension": "jpg",
          "height": 600,
          "mimetype": "image/jpeg",
          "secret": "rBCeWHFzQjhkZGzyi1vFCEpnJiZGNrJ4",
          "width": 772
        },
        "dc": {
          "extension": "jpg",
          "height": 600,
          "mimetype": "image/jpeg",
          "secret": "rBCeWHFzQjhkZGzyi1vFCEpnJiZGNrJ4",
          "width": 772
        },
        "ds": {
          "extension": "jpg",
          "height": 320,
          "mimetype": "image/jpeg",
          "secret": "rBCeWHFzQjhkZGzyi1vFCEpnJiZGNrJ4",
          "width": 320
        },
        "k": {
          "extension": "jpg",
          "height": 1535,
          "mimetype": "image/jpeg",
          "secret": "rBCeWHFzQjhkZGzyi1vFCEpnJiZGNrJ4",
          "width": 1976
        },
        "n": {
          "extension": "jpg",
          "height": 240,
          "mimetype": "image/jpeg",
          "secret": "rBCeWHFzQjhkZGzyi1vFCEpnJiZGNrJ4",
          "width": 308
        },
        "o": {
          "extension": "jpg",
          "height": 2140,
          "mimetype": "image/jpeg",
          "secret": "pfj1j8zliBtwqlS18ktT6ZawkiV5WOMG",
          "width": 2754
        },
        "s": {
          "extension": "jpg",
          "height": 320,
          "mimetype": "image/jpeg",
          "secret": "rBCeWHFzQjhkZGzyi1vFCEpnJiZGNrJ4",
          "width": 320
        },
        "z": {
          "extension": "jpg",
          "height": 480,
          "mimetype": "image/jpeg",
          "secret": "rBCeWHFzQjhkZGzyi1vFCEpnJiZGNrJ4",
          "width": 617
        }
      }
    },
    "media:uri_template": "https://millsfield.sfomuseum.org/media/152/782/227/5/1527822275_{secret}_{label}.{extention}",
    "sfomuseum:filename": "40636.tif",
    "sfomuseum:image_index": 5,
    "sfomuseum:placetype": "image",
    "sfomuseum:primary_image": 1,
    "wof:depicts": [
      1511944181
    ],
    "wof:name": "negative: San Francisco International Airport (SFO), drainage canals",
    "wof:placetype": "media"
  },
  "geometry": {"coordinates":[-122.386155,37.616358],"type":"Point"}
}
