{
  "type": "Feature",
  "properties": {
    "iso:country": "XX",
    "media:fingerprint": "0ef133b99b213098ffc69a6fea3207ad5cdf6c10",
    "media:imagehash_avg": "a:071f7f7f7f7f0100",
    "media:imagehash_diff": "d:3f3eb6b6bb895b1f",
    "media:medium": "image",
    "media:mimetype": "image/tiff",
    "media:properties": {
      "colours": [
        {
          "hex": "#3f4384",
          "name": "#3f4384",
          "reference": "vibrant"
        }, 
        {
          "hex": "#f8f8e8",
          "name": "#f8f8e8",
          "reference": "vibrant"
        }, 
        {
          "hex": "#31336c",
          "name": "#31336c",
          "reference": "vibrant"
        }, 
        {
          "hex": "#6a6b99",
          "name": "#6a6b99",
          "reference": "vibrant"
        }, 
        {
          "hex": "#b5bcc6",
          "name": "#b5bcc6",
          "reference": "vibrant"
        }
      ],
      "sizes": {
        "b": {
          "extension": "jpg",
          "height": 768,
          "mimetype": "image/jpeg",
          "secret": "vqubluqR97qG5V2SrTXVJ6JCM9SQyNiR",
          "width": 403
        },
        "c": {
          "extension": "jpg",
          "height": 600,
          "mimetype": "image/jpeg",
          "secret": "vqubluqR97qG5V2SrTXVJ6JCM9SQyNiR",
          "width": 315
        },
        "dc": {
          "extension": "jpg",
          "height": 600,
          "mimetype": "image/jpeg",
          "secret": "vqubluqR97qG5V2SrTXVJ6JCM9SQyNiR",
          "width": 315
        },
        "ds": {
          "extension": "jpg",
          "height": 320,
          "mimetype": "image/jpeg",
          "secret": "vqubluqR97qG5V2SrTXVJ6JCM9SQyNiR",
          "width": 320
        },
        "k": {
          "extension": "jpg",
          "height": 1536,
          "mimetype": "image/jpeg",
          "secret": "vqubluqR97qG5V2SrTXVJ6JCM9SQyNiR",
          "width": 806
        },
        "n": {
          "extension": "jpg",
          "height": 240,
          "mimetype": "image/jpeg",
          "secret": "vqubluqR97qG5V2SrTXVJ6JCM9SQyNiR",
          "width": 126
        },
        "o": {
          "extension": "jpg",
          "height": 3300,
          "mimetype": "image/jpeg",
          "secret": "mB5rwTBaFJvait1BQtedNL02VEv9WzvW",
          "width": 1733
        },
        "s": {
          "extension": "jpg",
          "height": 320,
          "mimetype": "image/jpeg",
          "secret": "vqubluqR97qG5V2SrTXVJ6JCM9SQyNiR",
          "width": 320
        },
        "z": {
          "extension": "jpg",
          "height": 480,
          "mimetype": "image/jpeg",
          "secret": "vqubluqR97qG5V2SrTXVJ6JCM9SQyNiR",
          "width": 252
        }
      }
    },
    "media:uri_template": "https://millsfield.sfomuseum.org/media/152/782/362/5/1527823625_{secret}_{label}.{extention}",
    "sfomuseum:filename": "41691.tif",
    "sfomuseum:image_index": 5,
    "sfomuseum:placetype": "image",
    "sfomuseum:primary_image": 1,
    "wof:depicts": [
      1511908465
    ],
    "wof:name": "airsickness bag: British Caledonian Airways",
    "wof:placetype": "media"
  },
  "geometry": {"coordinates":[-122.386155,37.616358],"type":"Point"}
}
