{
  "type": "Feature",
  "properties": {
    "iso:country":"XX",
    "media:medium":"image",
    "sfomuseum:filename":"2000.018.064.002b.tif",
    "sfomuseum:image_index":0,
    "sfomuseum:placetype":"image",
    "sfomuseum:primary_image":0,
    "wof:depicts":[
        1511958021
    ],
    "wof:name":"correspondence: Aviation Committee of Down Town Association, Mills Field Municipal Airport of San Francisco",
    "wof:placetype":"media"
},
  "geometry": {"coordinates":[-122.386155,37.616358],"type":"Point"}
}