{
  "type": "Feature",
  "properties": {
    "iso:country": "XX",
    "media:fingerprint": "67b4c90c8552b1d930c9e91355490c68ac56006b",
    "media:imagehash_avg": "a:9909012121207fff",
    "media:imagehash_diff": "d:713363414345d4cc",
    "media:medium": "image",
    "media:mimetype": "image/tiff",
    "media:properties": {
      "colours": [
        {
          "hex": "#767f85",
          "name": "#767f85",
          "reference": "vibrant"
        }, 
        {
          "hex": "#aab4bc",
          "name": "#aab4bc",
          "reference": "vibrant"
        }, 
        {
          "hex": "#364150",
          "name": "#364150",
          "reference": "vibrant"
        }
      ],
      "sizes": {
        "b": {
          "extension": "jpg",
          "height": 768,
          "mimetype": "image/jpeg",
          "secret": "htLTnjbkSWLrMCWiCR0Ae8a3wZjxrVBb",
          "width": 412
        },
        "c": {
          "extension": "jpg",
          "height": 600,
          "mimetype": "image/jpeg",
          "secret": "htLTnjbkSWLrMCWiCR0Ae8a3wZjxrVBb",
          "width": 321
        },
        "dc": {
          "extension": "jpg",
          "height": 600,
          "mimetype": "image/jpeg",
          "secret": "htLTnjbkSWLrMCWiCR0Ae8a3wZjxrVBb",
          "width": 321
        },
        "ds": {
          "extension": "jpg",
          "height": 320,
          "mimetype": "image/jpeg",
          "secret": "htLTnjbkSWLrMCWiCR0Ae8a3wZjxrVBb",
          "width": 320
        },
        "k": {
          "extension": "jpg",
          "height": 1536,
          "mimetype": "image/jpeg",
          "secret": "htLTnjbkSWLrMCWiCR0Ae8a3wZjxrVBb",
          "width": 824
        },
        "n": {
          "extension": "jpg",
          "height": 240,
          "mimetype": "image/jpeg",
          "secret": "htLTnjbkSWLrMCWiCR0Ae8a3wZjxrVBb",
          "width": 128
        },
        "o": {
          "extension": "jpg",
          "height": 2850,
          "mimetype": "image/jpeg",
          "secret": "Rr2lrAWu5b7gZwvcTeVcfuNAs26in6jJ",
          "width": 1529
        },
        "s": {
          "extension": "jpg",
          "height": 320,
          "mimetype": "image/jpeg",
          "secret": "htLTnjbkSWLrMCWiCR0Ae8a3wZjxrVBb",
          "width": 320
        },
        "z": {
          "extension": "jpg",
          "height": 480,
          "mimetype": "image/jpeg",
          "secret": "htLTnjbkSWLrMCWiCR0Ae8a3wZjxrVBb",
          "width": 257
        }
      }
    },
    "media:uri_template": "https://millsfield.sfomuseum.org/media/152/782/371/7/1527823717_{secret}_{label}.{extention}",
    "sfomuseum:filename": "41754.tif",
    "sfomuseum:image_index": 5,
    "sfomuseum:placetype": "image",
    "sfomuseum:primary_image": 0,
    "wof:depicts": [
      1511927507
    ],
    "wof:name": "airsickness bag: Arkia Israel Airlines",
    "wof:placetype": "media"
  },
  "geometry": {"coordinates":[-122.386155,37.616358],"type":"Point"}
}
