{
  "type": "Feature",
  "properties": {
    "iso:country": "US",
    "media:fingerprint": "dcdf74290078c06e5b94005aa792a354eb5163a9",
    "media:imagehash_avg": "a:8181838387878787",
    "media:imagehash_diff": "d:1313671f4d5d5f4f",
    "media:medium": "image",
    "media:mimetype": "image/tiff",
    "media:properties": {
      "colours": [
        {
          "hex": "#cc4536",
          "name": "#cc4536",
          "reference": "vibrant"
        }, 
        {
          "hex": "#bd746c",
          "name": "#bd746c",
          "reference": "vibrant"
        }, 
        {
          "hex": "#303e67",
          "name": "#303e67",
          "reference": "vibrant"
        }, 
        {
          "hex": "#71798e",
          "name": "#71798e",
          "reference": "vibrant"
        }, 
        {
          "hex": "#bfbfb5",
          "name": "#bfbfb5",
          "reference": "vibrant"
        }
      ],
      "sizes": {
        "b": {
          "extension": "jpg",
          "height": 637,
          "mimetype": "image/jpeg",
          "secret": "oHIpQICXtukB9bIBcRoZktFVOMptGfgQ",
          "width": 1024
        },
        "c": {
          "extension": "jpg",
          "height": 497,
          "mimetype": "image/jpeg",
          "secret": "oHIpQICXtukB9bIBcRoZktFVOMptGfgQ",
          "width": 800
        },
        "dc": {
          "extension": "jpg",
          "height": 497,
          "mimetype": "image/jpeg",
          "secret": "oHIpQICXtukB9bIBcRoZktFVOMptGfgQ",
          "width": 800
        },
        "ds": {
          "extension": "jpg",
          "height": 320,
          "mimetype": "image/jpeg",
          "secret": "oHIpQICXtukB9bIBcRoZktFVOMptGfgQ",
          "width": 320
        },
        "k": {
          "extension": "jpg",
          "height": 1274,
          "mimetype": "image/jpeg",
          "secret": "oHIpQICXtukB9bIBcRoZktFVOMptGfgQ",
          "width": 2048
        },
        "n": {
          "extension": "jpg",
          "height": 199,
          "mimetype": "image/jpeg",
          "secret": "oHIpQICXtukB9bIBcRoZktFVOMptGfgQ",
          "width": 320
        },
        "o": {
          "extension": "jpg",
          "height": 1116,
          "mimetype": "image/jpeg",
          "secret": "nCpiCfM93dsK4spQjR7eAwoTslRetbyS",
          "width": 1793
        },
        "s": {
          "extension": "jpg",
          "height": 320,
          "mimetype": "image/jpeg",
          "secret": "oHIpQICXtukB9bIBcRoZktFVOMptGfgQ",
          "width": 320
        },
        "z": {
          "extension": "jpg",
          "height": 398,
          "mimetype": "image/jpeg",
          "secret": "oHIpQICXtukB9bIBcRoZktFVOMptGfgQ",
          "width": 640
        }
      }
    },
    "media:uri_template": "https://millsfield.sfomuseum.org/media/152/782/077/3/1527820773_{secret}_{label}.{extention}",
    "sfomuseum:filename": "32911.tif",
    "sfomuseum:image_index": 5,
    "sfomuseum:placetype": "image",
    "sfomuseum:primary_image": 0,
    "wof:depicts": [
      1511908979
    ],
    "wof:name": "flight information packet: Pan American World Airways",
    "wof:placetype": "media"
  },
  "geometry": {"coordinates":[-122.386155,37.616358],"type":"Point"}
}
