{
  "type": "Feature",
  "properties": {
    "iso:country": "XX",
    "media:fingerprint": "13b1d7959e43ccea1b110e8371e7ce9cdd4c7883",
    "media:imagehash_avg": "a:ffcfdfffbf000000",
    "media:imagehash_diff": "d:ff9eb2b22633f9d1",
    "media:medium": "image",
    "media:mimetype": "image/tiff",
    "media:properties": {
      "colours": [
        {
          "hex": "#808080",
          "name": "#808080",
          "reference": "vibrant"
        }, 
        {
          "hex": "#bababa",
          "name": "#bababa",
          "reference": "vibrant"
        }, 
        {
          "hex": "#404040",
          "name": "#404040",
          "reference": "vibrant"
        }
      ],
      "sizes": {
        "b": {
          "extension": "jpg",
          "height": 768,
          "mimetype": "image/jpeg",
          "secret": "Zi4ZAdPmFQ0YAriS8HTVl8h2s7frdH4c",
          "width": 599
        },
        "c": {
          "extension": "jpg",
          "height": 600,
          "mimetype": "image/jpeg",
          "secret": "Zi4ZAdPmFQ0YAriS8HTVl8h2s7frdH4c",
          "width": 468
        },
        "dc": {
          "extension": "jpg",
          "height": 600,
          "mimetype": "image/jpeg",
          "secret": "Zi4ZAdPmFQ0YAriS8HTVl8h2s7frdH4c",
          "width": 468
        },
        "ds": {
          "extension": "jpg",
          "height": 320,
          "mimetype": "image/jpeg",
          "secret": "Zi4ZAdPmFQ0YAriS8HTVl8h2s7frdH4c",
          "width": 320
        },
        "k": {
          "extension": "jpg",
          "height": 1536,
          "mimetype": "image/jpeg",
          "secret": "Zi4ZAdPmFQ0YAriS8HTVl8h2s7frdH4c",
          "width": 1199
        },
        "n": {
          "extension": "jpg",
          "height": 240,
          "mimetype": "image/jpeg",
          "secret": "Zi4ZAdPmFQ0YAriS8HTVl8h2s7frdH4c",
          "width": 187
        },
        "o": {
          "extension": "jpg",
          "height": 2740,
          "mimetype": "image/jpeg",
          "secret": "8ymtYOzamwiOkV0Su8Ti4NTSZcTx8r0u",
          "width": 2140
        },
        "s": {
          "extension": "jpg",
          "height": 320,
          "mimetype": "image/jpeg",
          "secret": "Zi4ZAdPmFQ0YAriS8HTVl8h2s7frdH4c",
          "width": 320
        },
        "z": {
          "extension": "jpg",
          "height": 480,
          "mimetype": "image/jpeg",
          "secret": "Zi4ZAdPmFQ0YAriS8HTVl8h2s7frdH4c",
          "width": 374
        }
      }
    },
    "media:uri_template": "https://millsfield.sfomuseum.org/media/152/782/404/1/1527824041_{secret}_{label}.{extention}",
    "sfomuseum:filename": "42239.tif",
    "sfomuseum:image_index": 5,
    "sfomuseum:placetype": "image",
    "sfomuseum:primary_image": 1,
    "wof:depicts": [
      1511945359
    ],
    "wof:name": "negative: San Francisco International Airport (SFO), Jorgen W. Jorgensen",
    "wof:placetype": "media"
  },
  "geometry": {"coordinates":[-122.386155,37.616358],"type":"Point"}
}
