{
  "type": "Feature",
  "properties": {
    "iso:country": "XX",
    "media:fingerprint": "fdfd7e5e373ad7c794ed0e0da8168df088f1a738",
    "media:imagehash_avg": "a:1f1f34f6f0f07f7e",
    "media:imagehash_diff": "d:746c6cc4c7c196f0",
    "media:medium": "image",
    "media:mimetype": "image/tiff",
    "media:properties": {
      "colours": [
        {
          "hex": "#8e5934",
          "name": "#8e5934",
          "reference": "vibrant"
        }, 
        {
          "hex": "#dac083",
          "name": "#dac083",
          "reference": "vibrant"
        }, 
        {
          "hex": "#7c5339",
          "name": "#7c5339",
          "reference": "vibrant"
        }, 
        {
          "hex": "#a8855b",
          "name": "#a8855b",
          "reference": "vibrant"
        }, 
        {
          "hex": "#a3b4ce",
          "name": "#a3b4ce",
          "reference": "vibrant"
        }
      ],
      "sizes": {
        "b": {
          "extension": "jpg",
          "height": 671,
          "mimetype": "image/jpeg",
          "secret": "s3nF6fPZFAhIVPkQLitbIOT5PI7mMhjb",
          "width": 1024
        },
        "c": {
          "extension": "jpg",
          "height": 524,
          "mimetype": "image/jpeg",
          "secret": "s3nF6fPZFAhIVPkQLitbIOT5PI7mMhjb",
          "width": 800
        },
        "dc": {
          "extension": "jpg",
          "height": 524,
          "mimetype": "image/jpeg",
          "secret": "s3nF6fPZFAhIVPkQLitbIOT5PI7mMhjb",
          "width": 800
        },
        "ds": {
          "extension": "jpg",
          "height": 320,
          "mimetype": "image/jpeg",
          "secret": "s3nF6fPZFAhIVPkQLitbIOT5PI7mMhjb",
          "width": 320
        },
        "k": {
          "extension": "jpg",
          "height": 1342,
          "mimetype": "image/jpeg",
          "secret": "s3nF6fPZFAhIVPkQLitbIOT5PI7mMhjb",
          "width": 2048
        },
        "n": {
          "extension": "jpg",
          "height": 209,
          "mimetype": "image/jpeg",
          "secret": "s3nF6fPZFAhIVPkQLitbIOT5PI7mMhjb",
          "width": 320
        },
        "o": {
          "extension": "jpg",
          "height": 1454,
          "mimetype": "image/jpeg",
          "secret": "Giw89x2edEHazqutCOSXFAlIFEtTvy3J",
          "width": 2218
        },
        "s": {
          "extension": "jpg",
          "height": 320,
          "mimetype": "image/jpeg",
          "secret": "s3nF6fPZFAhIVPkQLitbIOT5PI7mMhjb",
          "width": 320
        },
        "z": {
          "extension": "jpg",
          "height": 419,
          "mimetype": "image/jpeg",
          "secret": "s3nF6fPZFAhIVPkQLitbIOT5PI7mMhjb",
          "width": 640
        }
      }
    },
    "media:uri_template": "https://millsfield.sfomuseum.org/media/152/782/706/1/1527827061_{secret}_{label}.{extention}",
    "sfomuseum:filename": "43919.tif",
    "sfomuseum:image_index": 5,
    "sfomuseum:placetype": "image",
    "sfomuseum:primary_image": 1,
    "wof:depicts": [
      1511948101
    ],
    "wof:name": "negative: San Francisco International Airport (SFO), office interior",
    "wof:placetype": "media"
  },
  "geometry": {"coordinates":[-122.386155,37.616358],"type":"Point"}
}
