{
  "type": "Feature",
  "properties": {
    "iso:country": "XX",
    "media:fingerprint": "eb4363a708d5095ec08cd52c4952884b1e100ca4",
    "media:imagehash_avg": "a:ffff1e0000000000",
    "media:imagehash_diff": "d:80c0f4e0e0a8e080",
    "media:medium": "image",
    "media:mimetype": "image/tiff",
    "media:properties": {
      "colours": [
        {
          "hex": "#808080",
          "name": "#808080",
          "reference": "vibrant"
        }, 
        {
          "hex": "#bababa",
          "name": "#bababa",
          "reference": "vibrant"
        }, 
        {
          "hex": "#484848",
          "name": "#484848",
          "reference": "vibrant"
        }
      ],
      "sizes": {
        "b": {
          "extension": "jpg",
          "height": 768,
          "mimetype": "image/jpeg",
          "secret": "5ipY93ir3O1deOLiQagNXQVI19sBDVaX",
          "width": 970
        },
        "c": {
          "extension": "jpg",
          "height": 600,
          "mimetype": "image/jpeg",
          "secret": "5ipY93ir3O1deOLiQagNXQVI19sBDVaX",
          "width": 758
        },
        "dc": {
          "extension": "jpg",
          "height": 600,
          "mimetype": "image/jpeg",
          "secret": "5ipY93ir3O1deOLiQagNXQVI19sBDVaX",
          "width": 758
        },
        "ds": {
          "extension": "jpg",
          "height": 320,
          "mimetype": "image/jpeg",
          "secret": "5ipY93ir3O1deOLiQagNXQVI19sBDVaX",
          "width": 320
        },
        "k": {
          "extension": "jpg",
          "height": 1536,
          "mimetype": "image/jpeg",
          "secret": "5ipY93ir3O1deOLiQagNXQVI19sBDVaX",
          "width": 1941
        },
        "n": {
          "extension": "jpg",
          "height": 240,
          "mimetype": "image/jpeg",
          "secret": "5ipY93ir3O1deOLiQagNXQVI19sBDVaX",
          "width": 303
        },
        "o": {
          "extension": "jpg",
          "height": 2168,
          "mimetype": "image/jpeg",
          "secret": "d2sAfCDiGgRr7ImfVP2sPagSY06vDLWy",
          "width": 2740
        },
        "s": {
          "extension": "jpg",
          "height": 320,
          "mimetype": "image/jpeg",
          "secret": "5ipY93ir3O1deOLiQagNXQVI19sBDVaX",
          "width": 320
        },
        "z": {
          "extension": "jpg",
          "height": 480,
          "mimetype": "image/jpeg",
          "secret": "5ipY93ir3O1deOLiQagNXQVI19sBDVaX",
          "width": 606
        }
      }
    },
    "media:uri_template": "https://millsfield.sfomuseum.org/media/152/782/494/1/1527824941_{secret}_{label}.{extention}",
    "sfomuseum:filename": "42893.tif",
    "sfomuseum:image_index": 5,
    "sfomuseum:placetype": "image",
    "sfomuseum:primary_image": 1,
    "wof:depicts": [
      1511945823
    ],
    "wof:name": "negative: San Francisco International Airport (SFO), aerial",
    "wof:placetype": "media"
  },
  "geometry": {"coordinates":[-122.386155,37.616358],"type":"Point"}
}
