{
  "type": "Feature",
  "properties": {
    "media:fingerprint": "d1d342b746170a81ad1faa5ed49383ef3fcac8ae",
    "media:imagehash_avg": "a:ffff010101010181",
    "media:imagehash_diff": "d:0b0f514943515143",
    "media:mimetype": "image/tiff",
    "media:properties": {
      "colours": [
        {
          "hex": "#b42a21",
          "name": "#b42a21",
          "reference": "vibrant"
        },
        {
          "hex": "#091557",
          "name": "#091557",
          "reference": "vibrant"
        },
        {
          "hex": "#a18474",
          "name": "#a18474",
          "reference": "vibrant"
        },
        {
          "hex": "#c4bcab",
          "name": "#c4bcab",
          "reference": "vibrant"
        },
        {
          "hex": "#383364",
          "name": "#383364",
          "reference": "vibrant"
        }
      ],
      "sizes": {
        "b": {
          "extension": "jpg",
          "height": 767,
          "mimetype": "image/jpeg",
          "secret": "QzH3fBvnw0Em5nIb2qUdQsbNuBqR4g1b",
          "width": 350
        },
        "c": {
          "extension": "jpg",
          "height": 600,
          "mimetype": "image/jpeg",
          "secret": "QzH3fBvnw0Em5nIb2qUdQsbNuBqR4g1b",
          "width": 274
        },
        "dc": {
          "extension": "jpg",
          "height": 600,
          "mimetype": "image/jpeg",
          "secret": "QzH3fBvnw0Em5nIb2qUdQsbNuBqR4g1b",
          "width": 274
        },
        "ds": {
          "extension": "jpg",
          "height": 320,
          "mimetype": "image/jpeg",
          "secret": "QzH3fBvnw0Em5nIb2qUdQsbNuBqR4g1b",
          "width": 320
        },
        "k": {
          "extension": "jpg",
          "height": 1535,
          "mimetype": "image/jpeg",
          "secret": "QzH3fBvnw0Em5nIb2qUdQsbNuBqR4g1b",
          "width": 701
        },
        "n": {
          "extension": "jpg",
          "height": 240,
          "mimetype": "image/jpeg",
          "secret": "QzH3fBvnw0Em5nIb2qUdQsbNuBqR4g1b",
          "width": 109
        },
        "o": {
          "extension": "jpg",
          "height": 2749,
          "mimetype": "image/jpeg",
          "secret": "lp6d4v6vYGjvgQ732UCySWRyGNado6wj",
          "width": 1256
        },
        "s": {
          "extension": "jpg",
          "height": 320,
          "mimetype": "image/jpeg",
          "secret": "QzH3fBvnw0Em5nIb2qUdQsbNuBqR4g1b",
          "width": 320
        },
        "z": {
          "extension": "jpg",
          "height": 480,
          "mimetype": "image/jpeg",
          "secret": "QzH3fBvnw0Em5nIb2qUdQsbNuBqR4g1b",
          "width": 219
        }
      }
    },
    "media:uri_template": "https://static.sfomuseum.org/media/174/668/056/5/1746680565_{secret}_{label}.{extention}",
    "sfomuseum:filename": "63828.tif",
    "sfomuseum:image_index": 1,
    "sfomuseum:image_type": "curator",
    "sfomuseum:placetype": "image",
    "sfomuseum:primary_image": 1,
    "wof:depicts": [
      1159285393,
      1159287531,
      1511938469
    ],
    "wof:name": "timetable: TWA (Trans World Airlines)",
    "wof:placetype": "custom"
  },
  "geometry": {"coordinates":[-122.386155,37.616357],"type":"Point"}
}
