{
  "type": "Feature",
  "properties": {
    "iso:country": "XX",
    "media:fingerprint": "07c8459c5c34e49ceb6c898b62511f4d3f29e95e",
    "media:imagehash_avg": "a:fd9898181d1f3fff",
    "media:imagehash_diff": "d:7171317171f1f7e7",
    "media:medium": "image",
    "media:mimetype": "image/tiff",
    "media:properties": {
      "colours": [
        {
          "hex": "#a61103",
          "name": "#a61103",
          "reference": "vibrant"
        }, 
        {
          "hex": "#d9c99d",
          "name": "#d9c99d",
          "reference": "vibrant"
        }, 
        {
          "hex": "#630906",
          "name": "#630906",
          "reference": "vibrant"
        }, 
        {
          "hex": "#998863",
          "name": "#998863",
          "reference": "vibrant"
        }, 
        {
          "hex": "#c3b78c",
          "name": "#c3b78c",
          "reference": "vibrant"
        }
      ],
      "sizes": {
        "b": {
          "extension": "jpg",
          "height": 581,
          "mimetype": "image/jpeg",
          "secret": "rjCFGha2O8boxXYq6XiWsSKFAOjW3WAW",
          "width": 1024
        },
        "c": {
          "extension": "jpg",
          "height": 454,
          "mimetype": "image/jpeg",
          "secret": "rjCFGha2O8boxXYq6XiWsSKFAOjW3WAW",
          "width": 800
        },
        "dc": {
          "extension": "jpg",
          "height": 454,
          "mimetype": "image/jpeg",
          "secret": "rjCFGha2O8boxXYq6XiWsSKFAOjW3WAW",
          "width": 800
        },
        "ds": {
          "extension": "jpg",
          "height": 320,
          "mimetype": "image/jpeg",
          "secret": "rjCFGha2O8boxXYq6XiWsSKFAOjW3WAW",
          "width": 320
        },
        "k": {
          "extension": "jpg",
          "height": 1162,
          "mimetype": "image/jpeg",
          "secret": "rjCFGha2O8boxXYq6XiWsSKFAOjW3WAW",
          "width": 2048
        },
        "n": {
          "extension": "jpg",
          "height": 181,
          "mimetype": "image/jpeg",
          "secret": "rjCFGha2O8boxXYq6XiWsSKFAOjW3WAW",
          "width": 320
        },
        "o": {
          "extension": "jpg",
          "height": 1126,
          "mimetype": "image/jpeg",
          "secret": "hnjmibfzxAwZ68AHRFyTyIW3ULJudP3R",
          "width": 1984
        },
        "s": {
          "extension": "jpg",
          "height": 320,
          "mimetype": "image/jpeg",
          "secret": "rjCFGha2O8boxXYq6XiWsSKFAOjW3WAW",
          "width": 320
        },
        "z": {
          "extension": "jpg",
          "height": 363,
          "mimetype": "image/jpeg",
          "secret": "rjCFGha2O8boxXYq6XiWsSKFAOjW3WAW",
          "width": 640
        }
      }
    },
    "media:uri_template": "https://millsfield.sfomuseum.org/media/152/782/030/9/1527820309_{secret}_{label}.{extention}",
    "sfomuseum:filename": "31514.tif",
    "sfomuseum:image_index": 5,
    "sfomuseum:placetype": "image",
    "sfomuseum:primary_image": 1,
    "wof:depicts": [
      1511922473
    ],
    "wof:name": "airmail flight cover: Pan American Airways, first mail flight, Transpacific service",
    "wof:placetype": "media"
  },
  "geometry": {"coordinates":[-122.386155,37.616358],"type":"Point"}
}
