{
  "type": "Feature",
  "properties": {
    "iso:country": "XX",
    "media:fingerprint": "d7d58358225bfe5b3c132aad4f7813cf2661fd1f",
    "media:imagehash_avg": "a:383c7c7c7c7c3c28",
    "media:imagehash_diff": "d:e1e1e1c1e9e9e9d2",
    "media:medium": "image",
    "media:mimetype": "image/tiff",
    "media:properties": {
      "colours": [
        {
          "hex": "#808080",
          "name": "#808080",
          "reference": "vibrant"
        }, 
        {
          "hex": "#bababa",
          "name": "#bababa",
          "reference": "vibrant"
        }, 
        {
          "hex": "#4a4a4a",
          "name": "#4a4a4a",
          "reference": "vibrant"
        }
      ],
      "sizes": {
        "b": {
          "extension": "jpg",
          "height": 767,
          "mimetype": "image/jpeg",
          "secret": "aXe9vZORM1cjh29P9Ps2qoNcNeCnC5Nd",
          "width": 993
        },
        "c": {
          "extension": "jpg",
          "height": 600,
          "mimetype": "image/jpeg",
          "secret": "aXe9vZORM1cjh29P9Ps2qoNcNeCnC5Nd",
          "width": 776
        },
        "dc": {
          "extension": "jpg",
          "height": 600,
          "mimetype": "image/jpeg",
          "secret": "aXe9vZORM1cjh29P9Ps2qoNcNeCnC5Nd",
          "width": 776
        },
        "ds": {
          "extension": "jpg",
          "height": 320,
          "mimetype": "image/jpeg",
          "secret": "aXe9vZORM1cjh29P9Ps2qoNcNeCnC5Nd",
          "width": 320
        },
        "k": {
          "extension": "jpg",
          "height": 1535,
          "mimetype": "image/jpeg",
          "secret": "aXe9vZORM1cjh29P9Ps2qoNcNeCnC5Nd",
          "width": 1986
        },
        "n": {
          "extension": "jpg",
          "height": 240,
          "mimetype": "image/jpeg",
          "secret": "aXe9vZORM1cjh29P9Ps2qoNcNeCnC5Nd",
          "width": 310
        },
        "o": {
          "extension": "jpg",
          "height": 2140,
          "mimetype": "image/jpeg",
          "secret": "jxKsMtJAOIo5bZdSXSXxY9TPbEeiRhwo",
          "width": 2768
        },
        "s": {
          "extension": "jpg",
          "height": 320,
          "mimetype": "image/jpeg",
          "secret": "aXe9vZORM1cjh29P9Ps2qoNcNeCnC5Nd",
          "width": 320
        },
        "z": {
          "extension": "jpg",
          "height": 480,
          "mimetype": "image/jpeg",
          "secret": "aXe9vZORM1cjh29P9Ps2qoNcNeCnC5Nd",
          "width": 620
        }
      }
    },
    "media:uri_template": "https://millsfield.sfomuseum.org/media/152/782/155/7/1527821557_{secret}_{label}.{extention}",
    "sfomuseum:filename": "38867.tif",
    "sfomuseum:image_index": 5,
    "sfomuseum:placetype": "image",
    "sfomuseum:primary_image": 1,
    "wof:depicts": [
      1511943645
    ],
    "wof:name": "negative: San Francisco Airport, maintenance",
    "wof:placetype": "media"
  },
  "geometry": {"coordinates":[-122.386155,37.616358],"type":"Point"}
}
