{
  "type": "Feature",
  "properties": {
    "iso:country": "XX",
    "media:fingerprint": "fb7c1c6083bbe3465057842c46b008de74e65846",
    "media:imagehash_avg": "a:c7ffe7e3c1c1e5ff",
    "media:imagehash_diff": "d:17370dcf0f3b2fab",
    "media:medium": "image",
    "media:mimetype": "image/tiff",
    "media:properties": {
      "colours": [
        {
          "hex": "#ba8524",
          "name": "#ba8524",
          "reference": "vibrant"
        }, 
        {
          "hex": "#eab65d",
          "name": "#eab65d",
          "reference": "vibrant"
        }, 
        {
          "hex": "#84837c",
          "name": "#84837c",
          "reference": "vibrant"
        }, 
        {
          "hex": "#b8bdcd",
          "name": "#b8bdcd",
          "reference": "vibrant"
        }, 
        {
          "hex": "#5e6364",
          "name": "#5e6364",
          "reference": "vibrant"
        }
      ],
      "sizes": {
        "b": {
          "extension": "jpg",
          "height": 767,
          "mimetype": "image/jpeg",
          "secret": "nehuyF7Fz3kIRuUdo5qhZ8PuT4Mh3iTZ",
          "width": 405
        },
        "c": {
          "extension": "jpg",
          "height": 600,
          "mimetype": "image/jpeg",
          "secret": "nehuyF7Fz3kIRuUdo5qhZ8PuT4Mh3iTZ",
          "width": 316
        },
        "dc": {
          "extension": "jpg",
          "height": 600,
          "mimetype": "image/jpeg",
          "secret": "nehuyF7Fz3kIRuUdo5qhZ8PuT4Mh3iTZ",
          "width": 316
        },
        "ds": {
          "extension": "jpg",
          "height": 320,
          "mimetype": "image/jpeg",
          "secret": "nehuyF7Fz3kIRuUdo5qhZ8PuT4Mh3iTZ",
          "width": 320
        },
        "k": {
          "extension": "jpg",
          "height": 1535,
          "mimetype": "image/jpeg",
          "secret": "nehuyF7Fz3kIRuUdo5qhZ8PuT4Mh3iTZ",
          "width": 811
        },
        "n": {
          "extension": "jpg",
          "height": 240,
          "mimetype": "image/jpeg",
          "secret": "nehuyF7Fz3kIRuUdo5qhZ8PuT4Mh3iTZ",
          "width": 126
        },
        "o": {
          "extension": "jpg",
          "height": 2988,
          "mimetype": "image/jpeg",
          "secret": "gamdCj5WzfLcsu1PWFq027NFzN8pA9Bv",
          "width": 1578
        },
        "s": {
          "extension": "jpg",
          "height": 320,
          "mimetype": "image/jpeg",
          "secret": "nehuyF7Fz3kIRuUdo5qhZ8PuT4Mh3iTZ",
          "width": 320
        },
        "z": {
          "extension": "jpg",
          "height": 480,
          "mimetype": "image/jpeg",
          "secret": "nehuyF7Fz3kIRuUdo5qhZ8PuT4Mh3iTZ",
          "width": 253
        }
      }
    },
    "media:uri_template": "https://millsfield.sfomuseum.org/media/152/782/383/3/1527823833_{secret}_{label}.{extention}",
    "sfomuseum:filename": "41809.tif",
    "sfomuseum:image_index": 5,
    "sfomuseum:placetype": "image",
    "sfomuseum:primary_image": 1,
    "wof:depicts": [
      1511908535
    ],
    "wof:name": "airsickness bag: China Northern Airlines",
    "wof:placetype": "media"
  },
  "geometry": {"coordinates":[-122.386155,37.616358],"type":"Point"}
}
