{
  "type": "Feature",
  "properties": {
    "media:fingerprint": "b34588e667e0df05f38052fbaa1dace6816725b8",
    "media:imagehash_avg": "a:ffe1e1e1c1c1c087",
    "media:imagehash_diff": "d:0d0d090101010d1d",
    "media:mimetype": "image/tiff",
    "media:properties": {
      "colours": [
        {
          "hex": "#c2a651",
          "name": "#c2a651",
          "reference": "vibrant"
        },
        {
          "hex": "#f8e8c8",
          "name": "#f8e8c8",
          "reference": "vibrant"
        },
        {
          "hex": "#25200a",
          "name": "#25200a",
          "reference": "vibrant"
        },
        {
          "hex": "#888064",
          "name": "#888064",
          "reference": "vibrant"
        },
        {
          "hex": "#d1cab3",
          "name": "#d1cab3",
          "reference": "vibrant"
        }
      ],
      "sizes": {
        "b": {
          "extension": "jpg",
          "height": 768,
          "mimetype": "image/jpeg",
          "secret": "4O7GBW0kd580QAgwZ9ViDXP3vdXcuXC7",
          "width": 489
        },
        "c": {
          "extension": "jpg",
          "height": 600,
          "mimetype": "image/jpeg",
          "secret": "4O7GBW0kd580QAgwZ9ViDXP3vdXcuXC7",
          "width": 382
        },
        "dc": {
          "extension": "jpg",
          "height": 600,
          "mimetype": "image/jpeg",
          "secret": "4O7GBW0kd580QAgwZ9ViDXP3vdXcuXC7",
          "width": 382
        },
        "ds": {
          "extension": "jpg",
          "height": 320,
          "mimetype": "image/jpeg",
          "secret": "4O7GBW0kd580QAgwZ9ViDXP3vdXcuXC7",
          "width": 320
        },
        "k": {
          "extension": "jpg",
          "height": 1536,
          "mimetype": "image/jpeg",
          "secret": "4O7GBW0kd580QAgwZ9ViDXP3vdXcuXC7",
          "width": 979
        },
        "n": {
          "extension": "jpg",
          "height": 240,
          "mimetype": "image/jpeg",
          "secret": "4O7GBW0kd580QAgwZ9ViDXP3vdXcuXC7",
          "width": 153
        },
        "o": {
          "extension": "jpg",
          "height": 2000,
          "mimetype": "image/jpeg",
          "secret": "W3e4Y6RycYFEm5B6JFQvL1dGXYJF09nZ",
          "width": 1276
        },
        "s": {
          "extension": "jpg",
          "height": 320,
          "mimetype": "image/jpeg",
          "secret": "4O7GBW0kd580QAgwZ9ViDXP3vdXcuXC7",
          "width": 320
        },
        "z": {
          "extension": "jpg",
          "height": 480,
          "mimetype": "image/jpeg",
          "secret": "4O7GBW0kd580QAgwZ9ViDXP3vdXcuXC7",
          "width": 306
        }
      }
    },
    "media:uri_template": "https://static.sfomuseum.org/media/174/630/804/1/1746308041_{secret}_{label}.{extention}",
    "sfomuseum:filename": "1997.59.39.02_bk.tif",
    "sfomuseum:image_index": 5,
    "sfomuseum:image_type": "studio",
    "sfomuseum:placetype": "image",
    "sfomuseum:primary_image": 0,
    "wof:depicts": [
      1511908249,
      1159284989
    ],
    "wof:name": "menu: Pan American World Airways",
    "wof:placetype": "custom",
    "wof:placetype_alt": "image"
  },
  "geometry": {"coordinates":[-122.386155,37.616357],"type":"Point"}
}
