{
  "type": "Feature",
  "properties": {
    "iso:country": "XX",
    "media:fingerprint": "1a6252913b3bb9d8a5e856c5d49ba87971646f27",
    "media:imagehash_avg": "a:030b8fefe723019f",
    "media:imagehash_diff": "d:1f3b2b4e4e4e3737",
    "media:medium": "image",
    "media:mimetype": "image/tiff",
    "media:properties": {
      "colours": [
        {
          "hex": "#767676",
          "name": "#767676",
          "reference": "vibrant"
        },
        {
          "hex": "#b8b8b8",
          "name": "#b8b8b8",
          "reference": "vibrant"
        },
        {
          "hex": "#464646",
          "name": "#464646",
          "reference": "vibrant"
        }
      ],
      "sizes": {
        "b": {
          "extension": "jpg",
          "height": 689,
          "mimetype": "image/jpeg",
          "secret": "geylIDjnL8AG6rdaZhmCjfRM7AIA2xGz",
          "width": 1024
        },
        "c": {
          "extension": "jpg",
          "height": 538,
          "mimetype": "image/jpeg",
          "secret": "geylIDjnL8AG6rdaZhmCjfRM7AIA2xGz",
          "width": 800
        },
        "dc": {
          "extension": "jpg",
          "height": 538,
          "mimetype": "image/jpeg",
          "secret": "geylIDjnL8AG6rdaZhmCjfRM7AIA2xGz",
          "width": 800
        },
        "ds": {
          "extension": "jpg",
          "height": 320,
          "mimetype": "image/jpeg",
          "secret": "geylIDjnL8AG6rdaZhmCjfRM7AIA2xGz",
          "width": 320
        },
        "k": {
          "extension": "jpg",
          "height": 1378,
          "mimetype": "image/jpeg",
          "secret": "geylIDjnL8AG6rdaZhmCjfRM7AIA2xGz",
          "width": 2048
        },
        "n": {
          "extension": "jpg",
          "height": 215,
          "mimetype": "image/jpeg",
          "secret": "geylIDjnL8AG6rdaZhmCjfRM7AIA2xGz",
          "width": 320
        },
        "o": {
          "extension": "jpg",
          "height": 2658,
          "mimetype": "image/jpeg",
          "secret": "C190Hr2J8qap4peNQep0su63Urvigz5S",
          "width": 3948
        },
        "s": {
          "extension": "jpg",
          "height": 320,
          "mimetype": "image/jpeg",
          "secret": "geylIDjnL8AG6rdaZhmCjfRM7AIA2xGz",
          "width": 320
        },
        "z": {
          "extension": "jpg",
          "height": 430,
          "mimetype": "image/jpeg",
          "secret": "geylIDjnL8AG6rdaZhmCjfRM7AIA2xGz",
          "width": 640
        }
      }
    },
    "media:uri_template": "https://static.sfomuseum.org/media/172/956/540/7/1729565407_{secret}_{label}.{extention}",
    "sfomuseum:filename": "39614.tif",
    "sfomuseum:image_index": 0,
    "sfomuseum:image_type": "studio",
    "sfomuseum:placetype": "image",
    "sfomuseum:primary_image": 1,
    "wof:depicts": [
      1159287531,
      1159285393,
      1729564315
    ],
    "wof:name": "photograph: TWA (Trans World Airlines), flight attendant",
    "wof:placetype": "custom",
    "wof:placetype_alt": "image"
  },
  "geometry": {"coordinates":[-122.386155,37.616357],"type":"Point"}
}
