{
  "type": "Feature",
  "properties": {
    "media:fingerprint": "c7eeb683860631db903ccd8e17b0eaf373b19246",
    "media:imagehash_avg": "a:f3f1e1818399ffff",
    "media:imagehash_diff": "d:e7e78f273f33f3e0",
    "media:mimetype": "image/tiff",
    "media:properties": {
      "colours": [
        {
          "hex": "#cb2028",
          "name": "#cb2028",
          "reference": "vibrant"
        },
        {
          "hex": "#e787a5",
          "name": "#e787a5",
          "reference": "vibrant"
        },
        {
          "hex": "#1b4268",
          "name": "#1b4268",
          "reference": "vibrant"
        },
        {
          "hex": "#8a7b68",
          "name": "#8a7b68",
          "reference": "vibrant"
        },
        {
          "hex": "#a5b0d6",
          "name": "#a5b0d6",
          "reference": "vibrant"
        }
      ],
      "sizes": {
        "b": {
          "extension": "jpg",
          "height": 682,
          "mimetype": "image/jpeg",
          "secret": "V4ZEZ4a9ulWoMKzS05MaYrVrJ72K5rVB",
          "width": 1024
        },
        "c": {
          "extension": "jpg",
          "height": 533,
          "mimetype": "image/jpeg",
          "secret": "V4ZEZ4a9ulWoMKzS05MaYrVrJ72K5rVB",
          "width": 800
        },
        "dc": {
          "extension": "jpg",
          "height": 533,
          "mimetype": "image/jpeg",
          "secret": "V4ZEZ4a9ulWoMKzS05MaYrVrJ72K5rVB",
          "width": 800
        },
        "ds": {
          "extension": "jpg",
          "height": 320,
          "mimetype": "image/jpeg",
          "secret": "V4ZEZ4a9ulWoMKzS05MaYrVrJ72K5rVB",
          "width": 320
        },
        "k": {
          "extension": "jpg",
          "height": 1365,
          "mimetype": "image/jpeg",
          "secret": "V4ZEZ4a9ulWoMKzS05MaYrVrJ72K5rVB",
          "width": 2048
        },
        "n": {
          "extension": "jpg",
          "height": 213,
          "mimetype": "image/jpeg",
          "secret": "V4ZEZ4a9ulWoMKzS05MaYrVrJ72K5rVB",
          "width": 320
        },
        "o": {
          "extension": "jpg",
          "height": 2400,
          "mimetype": "image/jpeg",
          "secret": "OtitNRzpxnQ9z34omHtSdMymkzs3S140",
          "width": 3600
        },
        "s": {
          "extension": "jpg",
          "height": 320,
          "mimetype": "image/jpeg",
          "secret": "V4ZEZ4a9ulWoMKzS05MaYrVrJ72K5rVB",
          "width": 320
        },
        "z": {
          "extension": "jpg",
          "height": 426,
          "mimetype": "image/jpeg",
          "secret": "V4ZEZ4a9ulWoMKzS05MaYrVrJ72K5rVB",
          "width": 640
        }
      }
    },
    "media:uri_template": "https://static.sfomuseum.org/media/174/668/079/3/1746680793_{secret}_{label}.{extention}",
    "sfomuseum:filename": "69973.tif",
    "sfomuseum:image_index": 1,
    "sfomuseum:image_type": "curator",
    "sfomuseum:placetype": "image",
    "sfomuseum:primary_image": 1,
    "wof:depicts": [
      1511909405
    ],
    "wof:name": "game: Wings, the Air Mail Game",
    "wof:placetype": "custom"
  },
  "geometry": {"coordinates":[-122.386155,37.616357],"type":"Point"}
}
