{
  "type": "Feature",
  "properties": {
    "iso:country": "XX",
    "media:fingerprint": "10b4b5bafd00f89fa5c8466897d7465413448319",
    "media:imagehash_avg": "a:00ff7f7f777f7f00",
    "media:imagehash_diff": "d:139ce0cc8e8ea005",
    "media:medium": "image",
    "media:mimetype": "image/tiff",
    "media:properties": {
      "colours": [
        {
          "hex": "#d22c2e",
          "name": "#d22c2e",
          "reference": "vibrant"
        }, 
        {
          "hex": "#f06261",
          "name": "#f06261",
          "reference": "vibrant"
        }, 
        {
          "hex": "#211d66",
          "name": "#211d66",
          "reference": "vibrant"
        }, 
        {
          "hex": "#53568c",
          "name": "#53568c",
          "reference": "vibrant"
        }, 
        {
          "hex": "#d0cbbf",
          "name": "#d0cbbf",
          "reference": "vibrant"
        }
      ],
      "sizes": {
        "b": {
          "extension": "jpg",
          "height": 460,
          "mimetype": "image/jpeg",
          "secret": "o2NfWy0XhPRA5T6fPKJTPmplKr68anqB",
          "width": 1024
        },
        "c": {
          "extension": "jpg",
          "height": 359,
          "mimetype": "image/jpeg",
          "secret": "o2NfWy0XhPRA5T6fPKJTPmplKr68anqB",
          "width": 800
        },
        "dc": {
          "extension": "jpg",
          "height": 359,
          "mimetype": "image/jpeg",
          "secret": "o2NfWy0XhPRA5T6fPKJTPmplKr68anqB",
          "width": 800
        },
        "ds": {
          "extension": "jpg",
          "height": 320,
          "mimetype": "image/jpeg",
          "secret": "o2NfWy0XhPRA5T6fPKJTPmplKr68anqB",
          "width": 320
        },
        "k": {
          "extension": "jpg",
          "height": 921,
          "mimetype": "image/jpeg",
          "secret": "o2NfWy0XhPRA5T6fPKJTPmplKr68anqB",
          "width": 2048
        },
        "n": {
          "extension": "jpg",
          "height": 143,
          "mimetype": "image/jpeg",
          "secret": "o2NfWy0XhPRA5T6fPKJTPmplKr68anqB",
          "width": 320
        },
        "o": {
          "extension": "jpg",
          "height": 1325,
          "mimetype": "image/jpeg",
          "secret": "WhmaAlYPlRCg0oEQt1xYjWfrJPXNXRlR",
          "width": 2946
        },
        "s": {
          "extension": "jpg",
          "height": 320,
          "mimetype": "image/jpeg",
          "secret": "o2NfWy0XhPRA5T6fPKJTPmplKr68anqB",
          "width": 320
        },
        "z": {
          "extension": "jpg",
          "height": 287,
          "mimetype": "image/jpeg",
          "secret": "o2NfWy0XhPRA5T6fPKJTPmplKr68anqB",
          "width": 640
        }
      }
    },
    "media:uri_template": "https://millsfield.sfomuseum.org/media/152/782/901/3/1527829013_{secret}_{label}.{extention}",
    "sfomuseum:filename": "47478.tif",
    "sfomuseum:image_index": 5,
    "sfomuseum:placetype": "image",
    "sfomuseum:primary_image": 0,
    "wof:depicts": [
      1511906911
    ],
    "wof:name": "airmail flight cover: Pan American Airways, Singapore - Guam route",
    "wof:placetype": "media"
  },
  "geometry": {"coordinates":[-122.386155,37.616358],"type":"Point"}
}
