{
  "type": "Feature",
  "properties": {
    "iso:country": "XX",
    "media:fingerprint": "20f9ef86d3a076ef6cd3f1740d3ba5b2d5c4c830",
    "media:imagehash_avg": "a:ffffffff000000d9",
    "media:imagehash_diff": "d:22222a2a61819b33",
    "media:medium": "image",
    "media:mimetype": "image/tiff",
    "media:properties": {
      "colours": [
        {
          "hex": "#808080",
          "name": "#808080",
          "reference": "vibrant"
        }, 
        {
          "hex": "#c0c0c0",
          "name": "#c0c0c0",
          "reference": "vibrant"
        }, 
        {
          "hex": "#484848",
          "name": "#484848",
          "reference": "vibrant"
        }
      ],
      "sizes": {
        "b": {
          "extension": "jpg",
          "height": 768,
          "mimetype": "image/jpeg",
          "secret": "F8rlB0DnBXrUIFwvIQLstbvjti6OrDrR",
          "width": 763
        },
        "c": {
          "extension": "jpg",
          "height": 600,
          "mimetype": "image/jpeg",
          "secret": "F8rlB0DnBXrUIFwvIQLstbvjti6OrDrR",
          "width": 596
        },
        "dc": {
          "extension": "jpg",
          "height": 600,
          "mimetype": "image/jpeg",
          "secret": "F8rlB0DnBXrUIFwvIQLstbvjti6OrDrR",
          "width": 596
        },
        "ds": {
          "extension": "jpg",
          "height": 320,
          "mimetype": "image/jpeg",
          "secret": "F8rlB0DnBXrUIFwvIQLstbvjti6OrDrR",
          "width": 320
        },
        "k": {
          "extension": "jpg",
          "height": 1536,
          "mimetype": "image/jpeg",
          "secret": "F8rlB0DnBXrUIFwvIQLstbvjti6OrDrR",
          "width": 1526
        },
        "n": {
          "extension": "jpg",
          "height": 240,
          "mimetype": "image/jpeg",
          "secret": "F8rlB0DnBXrUIFwvIQLstbvjti6OrDrR",
          "width": 238
        },
        "o": {
          "extension": "jpg",
          "height": 1739,
          "mimetype": "image/jpeg",
          "secret": "63PX4r6oSgh3LwJ6f0DQwof3LeSvBslX",
          "width": 1728
        },
        "s": {
          "extension": "jpg",
          "height": 320,
          "mimetype": "image/jpeg",
          "secret": "F8rlB0DnBXrUIFwvIQLstbvjti6OrDrR",
          "width": 320
        },
        "z": {
          "extension": "jpg",
          "height": 480,
          "mimetype": "image/jpeg",
          "secret": "F8rlB0DnBXrUIFwvIQLstbvjti6OrDrR",
          "width": 476
        }
      }
    },
    "media:uri_template": "https://millsfield.sfomuseum.org/media/152/782/658/7/1527826587_{secret}_{label}.{extention}",
    "sfomuseum:filename": "43707.tif",
    "sfomuseum:image_index": 5,
    "sfomuseum:placetype": "image",
    "sfomuseum:primary_image": 1,
    "wof:depicts": [
      1511947625
    ],
    "wof:name": "photograph: San Francisco International Airport (SFO), construction of Pacific Southwest Airlines (PSA) pier and jetway",
    "wof:placetype": "media"
  },
  "geometry": {"coordinates":[-122.386155,37.616358],"type":"Point"}
}
