{
  "type": "Feature",
  "properties": {
    "iso:country": "XX",
    "media:fingerprint": "8d29a81c4a3910bbec409df7c2ba75661f7a740f",
    "media:imagehash_avg": "a:0007170703030301",
    "media:imagehash_diff": "d:80ef2fa7d78787c7",
    "media:medium": "image",
    "media:mimetype": "image/tiff",
    "media:properties": {
      "colours": [
        {
          "hex": "#868686",
          "name": "#868686",
          "reference": "vibrant"
        }, 
        {
          "hex": "#c0c0c0",
          "name": "#c0c0c0",
          "reference": "vibrant"
        }, 
        {
          "hex": "#404040",
          "name": "#404040",
          "reference": "vibrant"
        }
      ],
      "sizes": {
        "b": {
          "extension": "jpg",
          "height": 768,
          "mimetype": "image/jpeg",
          "secret": "NJhqIaBVR4cMa7faiVzQXZAOrClY9iOP",
          "width": 776
        },
        "c": {
          "extension": "jpg",
          "height": 600,
          "mimetype": "image/jpeg",
          "secret": "NJhqIaBVR4cMa7faiVzQXZAOrClY9iOP",
          "width": 606
        },
        "dc": {
          "extension": "jpg",
          "height": 600,
          "mimetype": "image/jpeg",
          "secret": "NJhqIaBVR4cMa7faiVzQXZAOrClY9iOP",
          "width": 606
        },
        "ds": {
          "extension": "jpg",
          "height": 320,
          "mimetype": "image/jpeg",
          "secret": "NJhqIaBVR4cMa7faiVzQXZAOrClY9iOP",
          "width": 320
        },
        "k": {
          "extension": "jpg",
          "height": 1536,
          "mimetype": "image/jpeg",
          "secret": "NJhqIaBVR4cMa7faiVzQXZAOrClY9iOP",
          "width": 1552
        },
        "n": {
          "extension": "jpg",
          "height": 240,
          "mimetype": "image/jpeg",
          "secret": "NJhqIaBVR4cMa7faiVzQXZAOrClY9iOP",
          "width": 242
        },
        "o": {
          "extension": "jpg",
          "height": 2536,
          "mimetype": "image/jpeg",
          "secret": "HAPqe9Z46V03qpV9mZVpusV7FJ2dDUzX",
          "width": 2563
        },
        "s": {
          "extension": "jpg",
          "height": 320,
          "mimetype": "image/jpeg",
          "secret": "NJhqIaBVR4cMa7faiVzQXZAOrClY9iOP",
          "width": 320
        },
        "z": {
          "extension": "jpg",
          "height": 480,
          "mimetype": "image/jpeg",
          "secret": "NJhqIaBVR4cMa7faiVzQXZAOrClY9iOP",
          "width": 485
        }
      }
    },
    "media:uri_template": "https://millsfield.sfomuseum.org/media/152/782/616/3/1527826163_{secret}_{label}.{extention}",
    "sfomuseum:filename": "43518.tif",
    "sfomuseum:image_index": 5,
    "sfomuseum:placetype": "image",
    "sfomuseum:primary_image": 1,
    "wof:depicts": [
      1511947191
    ],
    "wof:name": "negative: San Francisco International Airport (SFO), Terminal Building, custodial staff",
    "wof:placetype": "media"
  },
  "geometry": {"coordinates":[-122.386155,37.616358],"type":"Point"}
}
