{
  "type": "Feature",
  "properties": {
    "iso:country": "XX",
    "media:fingerprint": "1f40b4b4754f0de88d1a8fb5ddb0ec9eef853cc9",
    "media:imagehash_avg": "a:007e7e7e7e7e7e00",
    "media:imagehash_diff": "d:8e8ee6e6ecccaeb6",
    "media:medium": "image",
    "media:mimetype": "image/tiff",
    "media:properties": {
      "colours": [
        {
          "hex": "#847f76",
          "name": "#847f76",
          "reference": "vibrant"
        }, 
        {
          "hex": "#c8c8b8",
          "name": "#c8c8b8",
          "reference": "vibrant"
        }, 
        {
          "hex": "#474340",
          "name": "#474340",
          "reference": "vibrant"
        }
      ],
      "sizes": {
        "b": {
          "extension": "jpg",
          "height": 768,
          "mimetype": "image/jpeg",
          "secret": "tc1zl2mqFSaWJEZ6eCg9KnHgBTuqi4Ow",
          "width": 509
        },
        "c": {
          "extension": "jpg",
          "height": 600,
          "mimetype": "image/jpeg",
          "secret": "tc1zl2mqFSaWJEZ6eCg9KnHgBTuqi4Ow",
          "width": 397
        },
        "dc": {
          "extension": "jpg",
          "height": 600,
          "mimetype": "image/jpeg",
          "secret": "tc1zl2mqFSaWJEZ6eCg9KnHgBTuqi4Ow",
          "width": 397
        },
        "ds": {
          "extension": "jpg",
          "height": 320,
          "mimetype": "image/jpeg",
          "secret": "tc1zl2mqFSaWJEZ6eCg9KnHgBTuqi4Ow",
          "width": 320
        },
        "k": {
          "extension": "jpg",
          "height": 1536,
          "mimetype": "image/jpeg",
          "secret": "tc1zl2mqFSaWJEZ6eCg9KnHgBTuqi4Ow",
          "width": 1018
        },
        "n": {
          "extension": "jpg",
          "height": 240,
          "mimetype": "image/jpeg",
          "secret": "tc1zl2mqFSaWJEZ6eCg9KnHgBTuqi4Ow",
          "width": 159
        },
        "o": {
          "extension": "jpg",
          "height": 2478,
          "mimetype": "image/jpeg",
          "secret": "XbxNyquPgrBrDX5cjqBzpQgZXwWVDb94",
          "width": 1643
        },
        "s": {
          "extension": "jpg",
          "height": 320,
          "mimetype": "image/jpeg",
          "secret": "tc1zl2mqFSaWJEZ6eCg9KnHgBTuqi4Ow",
          "width": 320
        },
        "z": {
          "extension": "jpg",
          "height": 480,
          "mimetype": "image/jpeg",
          "secret": "tc1zl2mqFSaWJEZ6eCg9KnHgBTuqi4Ow",
          "width": 318
        }
      }
    },
    "media:uri_template": "https://millsfield.sfomuseum.org/media/152/782/042/9/1527820429_{secret}_{label}.{extention}",
    "sfomuseum:filename": "31605.tif",
    "sfomuseum:image_index": 5,
    "sfomuseum:placetype": "image",
    "sfomuseum:primary_image": 0,
    "wof:depicts": [
      1511923727
    ],
    "wof:name": "Letter: Honolulu, Hawaii",
    "wof:placetype": "media"
  },
  "geometry": {"coordinates":[-122.386155,37.616358],"type":"Point"}
}
