{
  "type": "Feature",
  "properties": {
    "iso:country": "XX",
    "media:fingerprint": "e9485e718d15a618194e24bcb6a8cabd62d9496b",
    "media:imagehash_avg": "a:8783cf81037f7f3f",
    "media:imagehash_diff": "d:1e1f1f3f2fffb9f3",
    "media:medium": "image",
    "media:mimetype": "image/tiff",
    "media:properties": {
      "colours": [
        {
          "hex": "#d82838",
          "name": "#d82838",
          "reference": "vibrant"
        }, 
        {
          "hex": "#e7777f",
          "name": "#e7777f",
          "reference": "vibrant"
        }, 
        {
          "hex": "#858e90",
          "name": "#858e90",
          "reference": "vibrant"
        }, 
        {
          "hex": "#d0bba2",
          "name": "#d0bba2",
          "reference": "vibrant"
        }, 
        {
          "hex": "#595148",
          "name": "#595148",
          "reference": "vibrant"
        }
      ],
      "sizes": {
        "b": {
          "extension": "jpg",
          "height": 767,
          "mimetype": "image/jpeg",
          "secret": "Kp1GFLbRhOas8FCOKavqbLY9Mf5DPDHR",
          "width": 403
        },
        "c": {
          "extension": "jpg",
          "height": 600,
          "mimetype": "image/jpeg",
          "secret": "Kp1GFLbRhOas8FCOKavqbLY9Mf5DPDHR",
          "width": 315
        },
        "dc": {
          "extension": "jpg",
          "height": 600,
          "mimetype": "image/jpeg",
          "secret": "Kp1GFLbRhOas8FCOKavqbLY9Mf5DPDHR",
          "width": 315
        },
        "ds": {
          "extension": "jpg",
          "height": 320,
          "mimetype": "image/jpeg",
          "secret": "Kp1GFLbRhOas8FCOKavqbLY9Mf5DPDHR",
          "width": 320
        },
        "k": {
          "extension": "jpg",
          "height": 1535,
          "mimetype": "image/jpeg",
          "secret": "Kp1GFLbRhOas8FCOKavqbLY9Mf5DPDHR",
          "width": 807
        },
        "n": {
          "extension": "jpg",
          "height": 240,
          "mimetype": "image/jpeg",
          "secret": "Kp1GFLbRhOas8FCOKavqbLY9Mf5DPDHR",
          "width": 126
        },
        "o": {
          "extension": "jpg",
          "height": 2874,
          "mimetype": "image/jpeg",
          "secret": "8Kc0wy2zVq1hCvjlDzAsCwWSO7NifeQt",
          "width": 1511
        },
        "s": {
          "extension": "jpg",
          "height": 320,
          "mimetype": "image/jpeg",
          "secret": "Kp1GFLbRhOas8FCOKavqbLY9Mf5DPDHR",
          "width": 320
        },
        "z": {
          "extension": "jpg",
          "height": 480,
          "mimetype": "image/jpeg",
          "secret": "Kp1GFLbRhOas8FCOKavqbLY9Mf5DPDHR",
          "width": 252
        }
      }
    },
    "media:uri_template": "https://millsfield.sfomuseum.org/media/152/782/369/5/1527823695_{secret}_{label}.{extention}",
    "sfomuseum:filename": "41744.tif",
    "sfomuseum:image_index": 5,
    "sfomuseum:placetype": "image",
    "sfomuseum:primary_image": 0,
    "wof:depicts": [
      1511927365
    ],
    "wof:name": "airsickness bag: British Airways",
    "wof:placetype": "media"
  },
  "geometry": {"coordinates":[-122.386155,37.616358],"type":"Point"}
}
