{
  "type": "Feature",
  "properties": {
    "iso:country": "XX",
    "media:fingerprint": "44b3c39f587b98ceaea609cace0fec0ebd700509",
    "media:imagehash_avg": "a:2030f0f2f0fffe70",
    "media:imagehash_diff": "d:60c4c4c6c6e7c0c0",
    "media:medium": "image",
    "media:mimetype": "image/tiff",
    "media:properties": {
      "colours": [
        {
          "hex": "#808080",
          "name": "#808080",
          "reference": "vibrant"
        }, 
        {
          "hex": "#b6b6b6",
          "name": "#b6b6b6",
          "reference": "vibrant"
        }, 
        {
          "hex": "#464646",
          "name": "#464646",
          "reference": "vibrant"
        }
      ],
      "sizes": {
        "b": {
          "extension": "jpg",
          "height": 768,
          "mimetype": "image/jpeg",
          "secret": "LXf3jwyCR84Fs841RraQKEoEGrtjdOEc",
          "width": 768
        },
        "c": {
          "extension": "jpg",
          "height": 600,
          "mimetype": "image/jpeg",
          "secret": "LXf3jwyCR84Fs841RraQKEoEGrtjdOEc",
          "width": 600
        },
        "dc": {
          "extension": "jpg",
          "height": 600,
          "mimetype": "image/jpeg",
          "secret": "LXf3jwyCR84Fs841RraQKEoEGrtjdOEc",
          "width": 600
        },
        "ds": {
          "extension": "jpg",
          "height": 320,
          "mimetype": "image/jpeg",
          "secret": "LXf3jwyCR84Fs841RraQKEoEGrtjdOEc",
          "width": 320
        },
        "k": {
          "extension": "jpg",
          "height": 1536,
          "mimetype": "image/jpeg",
          "secret": "LXf3jwyCR84Fs841RraQKEoEGrtjdOEc",
          "width": 1536
        },
        "n": {
          "extension": "jpg",
          "height": 239,
          "mimetype": "image/jpeg",
          "secret": "LXf3jwyCR84Fs841RraQKEoEGrtjdOEc",
          "width": 239
        },
        "o": {
          "extension": "jpg",
          "height": 2563,
          "mimetype": "image/jpeg",
          "secret": "W4fndfBf7FXUFXVEdsiUoL6MtVqFdUIk",
          "width": 2563
        },
        "s": {
          "extension": "jpg",
          "height": 320,
          "mimetype": "image/jpeg",
          "secret": "LXf3jwyCR84Fs841RraQKEoEGrtjdOEc",
          "width": 320
        },
        "z": {
          "extension": "jpg",
          "height": 479,
          "mimetype": "image/jpeg",
          "secret": "LXf3jwyCR84Fs841RraQKEoEGrtjdOEc",
          "width": 479
        }
      }
    },
    "media:uri_template": "https://millsfield.sfomuseum.org/media/152/782/640/7/1527826407_{secret}_{label}.{extention}",
    "sfomuseum:filename": "43626.tif",
    "sfomuseum:image_index": 5,
    "sfomuseum:placetype": "image",
    "sfomuseum:primary_image": 1,
    "wof:depicts": [
      1511947445
    ],
    "wof:name": "negative: San Francisco International Airport (SFO), construction or maintenance equipment",
    "wof:placetype": "media"
  },
  "geometry": {"coordinates":[-122.386155,37.616358],"type":"Point"}
}
