{
  "type": "Feature",
  "properties": {
    "iso:country": "XX",
    "media:fingerprint": "88fd23fe42e2cf90ebf8ca9b9c5d44b8e307f1d4",
    "media:imagehash_avg": "a:0899991909999f9f",
    "media:imagehash_diff": "d:5233333b3123333b",
    "media:medium": "image",
    "media:mimetype": "image/tiff",
    "media:properties": {
      "colours": [
        {
          "hex": "#f8f0d8",
          "name": "#f8f0d8",
          "reference": "vibrant"
        },
        {
          "hex": "#94866c",
          "name": "#94866c",
          "reference": "vibrant"
        },
        {
          "hex": "#cfc8af",
          "name": "#cfc8af",
          "reference": "vibrant"
        },
        {
          "hex": "#7e7159",
          "name": "#7e7159",
          "reference": "vibrant"
        }
      ],
      "sizes": {
        "b": {
          "extension": "jpg",
          "height": 768,
          "mimetype": "image/jpeg",
          "secret": "maXiXyDLBZbmuXWe8yZ50Qr6NWZMVZeu",
          "width": 941
        },
        "c": {
          "extension": "jpg",
          "height": 600,
          "mimetype": "image/jpeg",
          "secret": "maXiXyDLBZbmuXWe8yZ50Qr6NWZMVZeu",
          "width": 735
        },
        "dc": {
          "extension": "jpg",
          "height": 600,
          "mimetype": "image/jpeg",
          "secret": "maXiXyDLBZbmuXWe8yZ50Qr6NWZMVZeu",
          "width": 735
        },
        "ds": {
          "extension": "jpg",
          "height": 320,
          "mimetype": "image/jpeg",
          "secret": "maXiXyDLBZbmuXWe8yZ50Qr6NWZMVZeu",
          "width": 320
        },
        "k": {
          "extension": "jpg",
          "height": 1536,
          "mimetype": "image/jpeg",
          "secret": "maXiXyDLBZbmuXWe8yZ50Qr6NWZMVZeu",
          "width": 1882
        },
        "n": {
          "extension": "jpg",
          "height": 240,
          "mimetype": "image/jpeg",
          "secret": "maXiXyDLBZbmuXWe8yZ50Qr6NWZMVZeu",
          "width": 294
        },
        "o": {
          "extension": "jpg",
          "height": 1958,
          "mimetype": "image/jpeg",
          "secret": "VB0IOL1wGRmYfrD9HVD4cMLCNEr5dXqj",
          "width": 2400
        },
        "s": {
          "extension": "jpg",
          "height": 320,
          "mimetype": "image/jpeg",
          "secret": "maXiXyDLBZbmuXWe8yZ50Qr6NWZMVZeu",
          "width": 320
        },
        "z": {
          "extension": "jpg",
          "height": 480,
          "mimetype": "image/jpeg",
          "secret": "maXiXyDLBZbmuXWe8yZ50Qr6NWZMVZeu",
          "width": 588
        }
      }
    },
    "media:uri_template": "https://static.sfomuseum.org/media/152/784/472/7/1527844727_{secret}_{label}.{extention}",
    "sfomuseum:filename": "69386.tif",
    "sfomuseum:image_index": 5,
    "sfomuseum:image_type": "studio",
    "sfomuseum:placetype": "image",
    "sfomuseum:primary_image": 0,
    "wof:depicts": [
      1159284989,
      1511921229
    ],
    "wof:name": "menu: Pan American World Airways",
    "wof:placetype": "custom",
    "wof:placetype_alt": "image"
  },
  "geometry": {"coordinates":[-122.386155,37.616358],"type":"Point"}
}
