{
  "type": "Feature",
  "properties": {
    "iso:country": "XX",
    "media:fingerprint": "efb9ac923030d548c156148c26e20114ef9ef997",
    "media:imagehash_avg": "a:ff0f0f0b0303021b",
    "media:imagehash_diff": "d:6afb7b3bbefa7676",
    "media:medium": "image",
    "media:mimetype": "image/tiff",
    "media:properties": {
      "colours": [
        {
          "hex": "#808080",
          "name": "#808080",
          "reference": "vibrant"
        },
        {
          "hex": "#c0c0c0",
          "name": "#c0c0c0",
          "reference": "vibrant"
        },
        {
          "hex": "#4a4a4a",
          "name": "#4a4a4a",
          "reference": "vibrant"
        }
      ],
      "sizes": {
        "b": {
          "extension": "jpg",
          "height": 666,
          "mimetype": "image/jpeg",
          "secret": "cWtGs3PJox8dPcbPAEmoZLbJW2defrjg",
          "width": 1024
        },
        "c": {
          "extension": "jpg",
          "height": 520,
          "mimetype": "image/jpeg",
          "secret": "cWtGs3PJox8dPcbPAEmoZLbJW2defrjg",
          "width": 800
        },
        "dc": {
          "extension": "jpg",
          "height": 520,
          "mimetype": "image/jpeg",
          "secret": "cWtGs3PJox8dPcbPAEmoZLbJW2defrjg",
          "width": 800
        },
        "ds": {
          "extension": "jpg",
          "height": 320,
          "mimetype": "image/jpeg",
          "secret": "cWtGs3PJox8dPcbPAEmoZLbJW2defrjg",
          "width": 320
        },
        "k": {
          "extension": "jpg",
          "height": 1332,
          "mimetype": "image/jpeg",
          "secret": "cWtGs3PJox8dPcbPAEmoZLbJW2defrjg",
          "width": 2048
        },
        "n": {
          "extension": "jpg",
          "height": 208,
          "mimetype": "image/jpeg",
          "secret": "cWtGs3PJox8dPcbPAEmoZLbJW2defrjg",
          "width": 320
        },
        "o": {
          "extension": "jpg",
          "height": 1062,
          "mimetype": "image/jpeg",
          "secret": "FXgveuSDAbpht17Mdr1YeUdbduzhY2I9",
          "width": 1632
        },
        "s": {
          "extension": "jpg",
          "height": 320,
          "mimetype": "image/jpeg",
          "secret": "cWtGs3PJox8dPcbPAEmoZLbJW2defrjg",
          "width": 320
        },
        "z": {
          "extension": "jpg",
          "height": 416,
          "mimetype": "image/jpeg",
          "secret": "cWtGs3PJox8dPcbPAEmoZLbJW2defrjg",
          "width": 640
        }
      }
    },
    "media:uri_template": "https://static.sfomuseum.org/media/152/782/830/5/1527828305_{secret}_{label}.{extention}",
    "sfomuseum:filename": "44532.tif",
    "sfomuseum:image_index": 5,
    "sfomuseum:image_type": "studio",
    "sfomuseum:placetype": "image",
    "sfomuseum:primary_image": 1,
    "wof:depicts": [
      102527513,
      1511949337
    ],
    "wof:name": "negative: San Francisco International Airport (SFO), terminal interior",
    "wof:placetype": "custom",
    "wof:placetype_alt": "image"
  },
  "geometry": {"coordinates":[-122.386155,37.616358],"type":"Point"}
}
