{
  "type": "Feature",
  "properties": {
    "iso:country": "XX",
    "media:fingerprint": "a7d297ea04873de5369e75fd78a1a82a9329a838",
    "media:imagehash_avg": "a:ffcefcffffb92000",
    "media:imagehash_diff": "d:1e1c1554646b494d",
    "media:medium": "image",
    "media:mimetype": "image/tiff",
    "media:properties": {
      "colours": [
        {
          "hex": "#4886bf",
          "name": "#4886bf",
          "reference": "vibrant"
        }, 
        {
          "hex": "#5b99ca",
          "name": "#5b99ca",
          "reference": "vibrant"
        }, 
        {
          "hex": "#233e50",
          "name": "#233e50",
          "reference": "vibrant"
        }, 
        {
          "hex": "#848377",
          "name": "#848377",
          "reference": "vibrant"
        }, 
        {
          "hex": "#cecbba",
          "name": "#cecbba",
          "reference": "vibrant"
        }
      ],
      "sizes": {
        "b": {
          "extension": "jpg",
          "height": 768,
          "mimetype": "image/jpeg",
          "secret": "Ikdt4AyT8OmemjmFbz0lFW8TwEuTjMCL",
          "width": 350
        },
        "c": {
          "extension": "jpg",
          "height": 600,
          "mimetype": "image/jpeg",
          "secret": "Ikdt4AyT8OmemjmFbz0lFW8TwEuTjMCL",
          "width": 273
        },
        "dc": {
          "extension": "jpg",
          "height": 600,
          "mimetype": "image/jpeg",
          "secret": "Ikdt4AyT8OmemjmFbz0lFW8TwEuTjMCL",
          "width": 273
        },
        "ds": {
          "extension": "jpg",
          "height": 320,
          "mimetype": "image/jpeg",
          "secret": "Ikdt4AyT8OmemjmFbz0lFW8TwEuTjMCL",
          "width": 320
        },
        "k": {
          "extension": "jpg",
          "height": 1536,
          "mimetype": "image/jpeg",
          "secret": "Ikdt4AyT8OmemjmFbz0lFW8TwEuTjMCL",
          "width": 700
        },
        "n": {
          "extension": "jpg",
          "height": 239,
          "mimetype": "image/jpeg",
          "secret": "Ikdt4AyT8OmemjmFbz0lFW8TwEuTjMCL",
          "width": 109
        },
        "o": {
          "extension": "jpg",
          "height": 2717,
          "mimetype": "image/jpeg",
          "secret": "PNoTGreltKTJjHXdVnf8M3BHtq4vmste",
          "width": 1239
        },
        "s": {
          "extension": "jpg",
          "height": 320,
          "mimetype": "image/jpeg",
          "secret": "Ikdt4AyT8OmemjmFbz0lFW8TwEuTjMCL",
          "width": 320
        },
        "z": {
          "extension": "jpg",
          "height": 479,
          "mimetype": "image/jpeg",
          "secret": "Ikdt4AyT8OmemjmFbz0lFW8TwEuTjMCL",
          "width": 218
        }
      }
    },
    "media:uri_template": "https://millsfield.sfomuseum.org/media/152/782/111/3/1527821113_{secret}_{label}.{extention}",
    "sfomuseum:filename": "37236.tif",
    "sfomuseum:image_index": 5,
    "sfomuseum:placetype": "image",
    "sfomuseum:primary_image": 1,
    "wof:depicts": [
      1511937939
    ],
    "wof:name": "timetable: KLM (Royal Dutch Airlines), winter schedules",
    "wof:placetype": "media"
  },
  "geometry": {"coordinates":[-122.386155,37.616358],"type":"Point"}
}
