{
  "type": "Feature",
  "properties": {
    "iso:country": "XX",
    "media:fingerprint": "11446b4ead5e879c25116d432f0d4895eed80b39",
    "media:imagehash_avg": "a:ffe7c3c3c3c3e7ff",
    "media:imagehash_diff": "d:0e0f1f0f0f1f0f0e",
    "media:medium": "image",
    "media:mimetype": "image/tiff",
    "media:properties": {
      "colours": [
        {
          "hex": "#7fbe78",
          "name": "#7fbe78",
          "reference": "vibrant"
        },
        {
          "hex": "#9fd098",
          "name": "#9fd098",
          "reference": "vibrant"
        },
        {
          "hex": "#65a15f",
          "name": "#65a15f",
          "reference": "vibrant"
        },
        {
          "hex": "#adcbbf",
          "name": "#adcbbf",
          "reference": "vibrant"
        },
        {
          "hex": "#385838",
          "name": "#385838",
          "reference": "vibrant"
        }
      ],
      "sizes": {
        "b": {
          "extension": "jpg",
          "height": 685,
          "mimetype": "image/jpeg",
          "secret": "JVQj9vSyXWyi2SP0A5w8v4exlnhbTGNz",
          "width": 1024
        },
        "c": {
          "extension": "jpg",
          "height": 535,
          "mimetype": "image/jpeg",
          "secret": "JVQj9vSyXWyi2SP0A5w8v4exlnhbTGNz",
          "width": 800
        },
        "dc": {
          "extension": "jpg",
          "height": 535,
          "mimetype": "image/jpeg",
          "secret": "JVQj9vSyXWyi2SP0A5w8v4exlnhbTGNz",
          "width": 800
        },
        "ds": {
          "extension": "jpg",
          "height": 320,
          "mimetype": "image/jpeg",
          "secret": "JVQj9vSyXWyi2SP0A5w8v4exlnhbTGNz",
          "width": 320
        },
        "k": {
          "extension": "jpg",
          "height": 1371,
          "mimetype": "image/jpeg",
          "secret": "JVQj9vSyXWyi2SP0A5w8v4exlnhbTGNz",
          "width": 2048
        },
        "n": {
          "extension": "jpg",
          "height": 214,
          "mimetype": "image/jpeg",
          "secret": "JVQj9vSyXWyi2SP0A5w8v4exlnhbTGNz",
          "width": 320
        },
        "o": {
          "extension": "jpg",
          "height": 2400,
          "mimetype": "image/jpeg",
          "secret": "NTznjT5IkFajInyVbWmisFmBylOMVORx",
          "width": 3585
        },
        "s": {
          "extension": "jpg",
          "height": 320,
          "mimetype": "image/jpeg",
          "secret": "JVQj9vSyXWyi2SP0A5w8v4exlnhbTGNz",
          "width": 320
        },
        "z": {
          "extension": "jpg",
          "height": 428,
          "mimetype": "image/jpeg",
          "secret": "JVQj9vSyXWyi2SP0A5w8v4exlnhbTGNz",
          "width": 640
        }
      }
    },
    "media:uri_template": "https://millsfield.sfomuseum.org/media/152/785/412/3/1527854123_{secret}_{label}.{extention}",
    "sfomuseum:filename": "2012.147.136 front.tif",
    "sfomuseum:image_index": 5,
    "sfomuseum:placetype": "image",
    "sfomuseum:primary_image": 1,
    "wof:depicts": [
      1511952613
    ],
    "wof:name": "token: Braniff International",
    "wof:placetype": "custom",
    "wof:placetype_alt": "image"
  },
  "geometry": {"coordinates":[-122.386155,37.616358],"type":"Point"}
}
