{
  "type": "Feature",
  "properties": {
    "iso:country": "XX",
    "media:fingerprint": "6653d2844c106fadabae0e389a2ae1cacea98429",
    "media:imagehash_avg": "a:3e381b0f0e0e0e0e",
    "media:imagehash_diff": "d:f4f0f6ec3c3c7cfc",
    "media:medium": "image",
    "media:mimetype": "image/tiff",
    "media:properties": {
      "colours": [
        {
          "hex": "#e4efc7",
          "name": "#e4efc7",
          "reference": "vibrant"
        }, 
        {
          "hex": "#7c906a",
          "name": "#7c906a",
          "reference": "vibrant"
        }, 
        {
          "hex": "#bbd0b2",
          "name": "#bbd0b2",
          "reference": "vibrant"
        }, 
        {
          "hex": "#534b37",
          "name": "#534b37",
          "reference": "vibrant"
        }
      ],
      "sizes": {
        "b": {
          "extension": "jpg",
          "height": 675,
          "mimetype": "image/jpeg",
          "secret": "1Mv6MVO9AaXaMqLlk6XyJ8sTuV3KtvKH",
          "width": 1023
        },
        "c": {
          "extension": "jpg",
          "height": 527,
          "mimetype": "image/jpeg",
          "secret": "1Mv6MVO9AaXaMqLlk6XyJ8sTuV3KtvKH",
          "width": 800
        },
        "dc": {
          "extension": "jpg",
          "height": 527,
          "mimetype": "image/jpeg",
          "secret": "1Mv6MVO9AaXaMqLlk6XyJ8sTuV3KtvKH",
          "width": 800
        },
        "ds": {
          "extension": "jpg",
          "height": 320,
          "mimetype": "image/jpeg",
          "secret": "1Mv6MVO9AaXaMqLlk6XyJ8sTuV3KtvKH",
          "width": 320
        },
        "k": {
          "extension": "jpg",
          "height": 1351,
          "mimetype": "image/jpeg",
          "secret": "1Mv6MVO9AaXaMqLlk6XyJ8sTuV3KtvKH",
          "width": 2047
        },
        "n": {
          "extension": "jpg",
          "height": 211,
          "mimetype": "image/jpeg",
          "secret": "1Mv6MVO9AaXaMqLlk6XyJ8sTuV3KtvKH",
          "width": 320
        },
        "o": {
          "extension": "jpg",
          "height": 1094,
          "mimetype": "image/jpeg",
          "secret": "eEYRFDAujIRsbvmOTvFKdYyzdODxiGg9",
          "width": 1658
        },
        "s": {
          "extension": "jpg",
          "height": 320,
          "mimetype": "image/jpeg",
          "secret": "1Mv6MVO9AaXaMqLlk6XyJ8sTuV3KtvKH",
          "width": 320
        },
        "z": {
          "extension": "jpg",
          "height": 422,
          "mimetype": "image/jpeg",
          "secret": "1Mv6MVO9AaXaMqLlk6XyJ8sTuV3KtvKH",
          "width": 640
        }
      }
    },
    "media:uri_template": "https://millsfield.sfomuseum.org/media/152/782/858/5/1527828585_{secret}_{label}.{extention}",
    "sfomuseum:filename": "44665.tif",
    "sfomuseum:image_index": 5,
    "sfomuseum:placetype": "image",
    "sfomuseum:primary_image": 1,
    "wof:depicts": [
      1511949619
    ],
    "wof:name": "negative: San Francisco International Airport (SFO), Annual report press conference",
    "wof:placetype": "media"
  },
  "geometry": {"coordinates":[-122.386155,37.616358],"type":"Point"}
}
