{
  "type": "Feature",
  "properties": {
    "iso:country": "XX",
    "media:fingerprint": "1d005cc4498dc5bf752478077e5b4fb49fc4f429",
    "media:imagehash_avg": "a:001effffff040000",
    "media:imagehash_diff": "d:f8f8f8f8d9cdfef3",
    "media:medium": "image",
    "media:mimetype": "image/tiff",
    "media:properties": {
      "colours": [
        {
          "hex": "#868686",
          "name": "#868686",
          "reference": "vibrant"
        }, 
        {
          "hex": "#b8b8b8",
          "name": "#b8b8b8",
          "reference": "vibrant"
        }, 
        {
          "hex": "#383838",
          "name": "#383838",
          "reference": "vibrant"
        }
      ],
      "sizes": {
        "b": {
          "extension": "jpg",
          "height": 768,
          "mimetype": "image/jpeg",
          "secret": "kyG5eyPBXODbymhZWa0YWKJTRa0v6FXF",
          "width": 974
        },
        "c": {
          "extension": "jpg",
          "height": 600,
          "mimetype": "image/jpeg",
          "secret": "kyG5eyPBXODbymhZWa0YWKJTRa0v6FXF",
          "width": 761
        },
        "dc": {
          "extension": "jpg",
          "height": 600,
          "mimetype": "image/jpeg",
          "secret": "kyG5eyPBXODbymhZWa0YWKJTRa0v6FXF",
          "width": 761
        },
        "ds": {
          "extension": "jpg",
          "height": 320,
          "mimetype": "image/jpeg",
          "secret": "kyG5eyPBXODbymhZWa0YWKJTRa0v6FXF",
          "width": 320
        },
        "k": {
          "extension": "jpg",
          "height": 1536,
          "mimetype": "image/jpeg",
          "secret": "kyG5eyPBXODbymhZWa0YWKJTRa0v6FXF",
          "width": 1949
        },
        "n": {
          "extension": "jpg",
          "height": 240,
          "mimetype": "image/jpeg",
          "secret": "kyG5eyPBXODbymhZWa0YWKJTRa0v6FXF",
          "width": 304
        },
        "o": {
          "extension": "jpg",
          "height": 2181,
          "mimetype": "image/jpeg",
          "secret": "p5hwBVzcLFNZ02pHNzIO9mTEAbg862rj",
          "width": 2768
        },
        "s": {
          "extension": "jpg",
          "height": 320,
          "mimetype": "image/jpeg",
          "secret": "kyG5eyPBXODbymhZWa0YWKJTRa0v6FXF",
          "width": 320
        },
        "z": {
          "extension": "jpg",
          "height": 480,
          "mimetype": "image/jpeg",
          "secret": "kyG5eyPBXODbymhZWa0YWKJTRa0v6FXF",
          "width": 609
        }
      }
    },
    "media:uri_template": "https://millsfield.sfomuseum.org/media/152/782/624/9/1527826249_{secret}_{label}.{extention}",
    "sfomuseum:filename": "43556.tif",
    "sfomuseum:image_index": 5,
    "sfomuseum:placetype": "image",
    "sfomuseum:primary_image": 1,
    "wof:depicts": [
      1511947277
    ],
    "wof:name": "negative: San Francisco International Airport (SFO), Central Terminal and United Air Lines Douglas DC-8",
    "wof:placetype": "media"
  },
  "geometry": {"coordinates":[-122.386155,37.616358],"type":"Point"}
}
