{
  "type": "Feature",
  "properties": {
    "iso:country": "XX",
    "media:fingerprint": "c489e3fed694b16fb49e9302e4a40bc086f26097",
    "media:imagehash_avg": "a:c2dfc7f23eb8b000",
    "media:imagehash_diff": "d:36371787606121a1",
    "media:medium": "image",
    "media:mimetype": "image/tiff",
    "media:properties": {
      "colours": [
        {
          "hex": "#d83c2d",
          "name": "#d83c2d",
          "reference": "vibrant"
        }, 
        {
          "hex": "#d4c29c",
          "name": "#d4c29c",
          "reference": "vibrant"
        }, 
        {
          "hex": "#5e3225",
          "name": "#5e3225",
          "reference": "vibrant"
        }, 
        {
          "hex": "#608895",
          "name": "#608895",
          "reference": "vibrant"
        }, 
        {
          "hex": "#c2a680",
          "name": "#c2a680",
          "reference": "vibrant"
        }
      ],
      "sizes": {
        "b": {
          "extension": "jpg",
          "height": 768,
          "mimetype": "image/jpeg",
          "secret": "NlFXAauG9g2yFYEe6PSuZNykLC9NpJAN",
          "width": 594
        },
        "c": {
          "extension": "jpg",
          "height": 600,
          "mimetype": "image/jpeg",
          "secret": "NlFXAauG9g2yFYEe6PSuZNykLC9NpJAN",
          "width": 464
        },
        "dc": {
          "extension": "jpg",
          "height": 600,
          "mimetype": "image/jpeg",
          "secret": "NlFXAauG9g2yFYEe6PSuZNykLC9NpJAN",
          "width": 464
        },
        "ds": {
          "extension": "jpg",
          "height": 320,
          "mimetype": "image/jpeg",
          "secret": "NlFXAauG9g2yFYEe6PSuZNykLC9NpJAN",
          "width": 320
        },
        "k": {
          "extension": "jpg",
          "height": 1536,
          "mimetype": "image/jpeg",
          "secret": "NlFXAauG9g2yFYEe6PSuZNykLC9NpJAN",
          "width": 1189
        },
        "n": {
          "extension": "jpg",
          "height": 240,
          "mimetype": "image/jpeg",
          "secret": "NlFXAauG9g2yFYEe6PSuZNykLC9NpJAN",
          "width": 185
        },
        "o": {
          "extension": "jpg",
          "height": 3066,
          "mimetype": "image/jpeg",
          "secret": "KcQEJHJK1PCSlgv1x3AgTe1eYOVvr96q",
          "width": 2375
        },
        "s": {
          "extension": "jpg",
          "height": 320,
          "mimetype": "image/jpeg",
          "secret": "NlFXAauG9g2yFYEe6PSuZNykLC9NpJAN",
          "width": 320
        },
        "z": {
          "extension": "jpg",
          "height": 480,
          "mimetype": "image/jpeg",
          "secret": "NlFXAauG9g2yFYEe6PSuZNykLC9NpJAN",
          "width": 371
        }
      }
    },
    "media:uri_template": "https://millsfield.sfomuseum.org/media/152/781/944/3/1527819443_{secret}_{label}.{extention}",
    "sfomuseum:filename": "30545.tif",
    "sfomuseum:image_index": 5,
    "sfomuseum:placetype": "image",
    "sfomuseum:primary_image": 1,
    "wof:depicts": [
      1511956177
    ],
    "wof:name": "advertisement: Air France, Sunset",
    "wof:placetype": "media"
  },
  "geometry": {"coordinates":[-122.386155,37.616358],"type":"Point"}
}
