{
  "type": "Feature",
  "properties": {
    "iso:country": "XX",
    "media:fingerprint": "331a7c219bb65dd0ecc39dbc466a7ce3e3975d79",
    "media:imagehash_avg": "a:1c9cdbd91801031f",
    "media:imagehash_diff": "d:683092b3f1c3d6f9",
    "media:medium": "image",
    "media:mimetype": "image/jpeg",
    "media:properties": {
      "colours": [
        {
          "hex": "#9b946c",
          "name": "#9b946c",
          "reference": "vibrant"
        }, 
        {
          "hex": "#b6b7bb",
          "name": "#b6b7bb",
          "reference": "vibrant"
        }, 
        {
          "hex": "#43454b",
          "name": "#43454b",
          "reference": "vibrant"
        }
      ],
      "sizes": {
        "b": {
          "extension": "jpg",
          "height": 768,
          "mimetype": "image/jpeg",
          "secret": "vuJYmBgnfv31DoG8W3KOptgAW6X4jHEX",
          "width": 671
        },
        "c": {
          "extension": "jpg",
          "height": 600,
          "mimetype": "image/jpeg",
          "secret": "vuJYmBgnfv31DoG8W3KOptgAW6X4jHEX",
          "width": 524
        },
        "dc": {
          "extension": "jpg",
          "height": 600,
          "mimetype": "image/jpeg",
          "secret": "vuJYmBgnfv31DoG8W3KOptgAW6X4jHEX",
          "width": 524
        },
        "ds": {
          "extension": "jpg",
          "height": 320,
          "mimetype": "image/jpeg",
          "secret": "vuJYmBgnfv31DoG8W3KOptgAW6X4jHEX",
          "width": 320
        },
        "k": {
          "extension": "jpg",
          "height": 1536,
          "mimetype": "image/jpeg",
          "secret": "vuJYmBgnfv31DoG8W3KOptgAW6X4jHEX",
          "width": 1343
        },
        "n": {
          "extension": "jpg",
          "height": 240,
          "mimetype": "image/jpeg",
          "secret": "vuJYmBgnfv31DoG8W3KOptgAW6X4jHEX",
          "width": 209
        },
        "o": {
          "extension": "jpg",
          "height": 3459,
          "mimetype": "image/jpeg",
          "secret": "lGBZKIQsHz7pVN2WJWXyV1DRObd98zNQ",
          "width": 3026
        },
        "s": {
          "extension": "jpg",
          "height": 320,
          "mimetype": "image/jpeg",
          "secret": "vuJYmBgnfv31DoG8W3KOptgAW6X4jHEX",
          "width": 320
        },
        "z": {
          "extension": "jpg",
          "height": 480,
          "mimetype": "image/jpeg",
          "secret": "vuJYmBgnfv31DoG8W3KOptgAW6X4jHEX",
          "width": 419
        }
      }
    },
    "media:uri_template": "https://millsfield.sfomuseum.org/media/152/782/218/5/1527822185_{secret}_{label}.{extention}",
    "sfomuseum:filename": "40431.jpg",
    "sfomuseum:image_index": 5,
    "sfomuseum:placetype": "image",
    "sfomuseum:primary_image": 1,
    "wof:depicts": [
      1511951797
    ],
    "wof:name": "photographic design drawing: San Francisco International Airport",
    "wof:placetype": "media"
  },
  "geometry": {"coordinates":[-122.386155,37.616358],"type":"Point"}
}
