{
  "type": "Feature",
  "properties": {
    "iso:country": "XX",
    "media:fingerprint": "726fc0118df8c34ed837f55d3f15b5b61eb35db3",
    "media:imagehash_avg": "a:ff8181bd818181ff",
    "media:imagehash_diff": "d:6901717169010161",
    "media:medium": "image",
    "media:mimetype": "image/tiff",
    "media:properties": {
      "colours": [
        {
          "hex": "#848578",
          "name": "#848578",
          "reference": "vibrant"
        },
        {
          "hex": "#c8c8be",
          "name": "#c8c8be",
          "reference": "vibrant"
        },
        {
          "hex": "#62593e",
          "name": "#62593e",
          "reference": "vibrant"
        }
      ],
      "sizes": {
        "b": {
          "extension": "jpg",
          "height": 768,
          "mimetype": "image/jpeg",
          "secret": "9XZy32dFqpdi68oBLtIgUcvY2qEIb2Xu",
          "width": 556
        },
        "c": {
          "extension": "jpg",
          "height": 600,
          "mimetype": "image/jpeg",
          "secret": "9XZy32dFqpdi68oBLtIgUcvY2qEIb2Xu",
          "width": 434
        },
        "dc": {
          "extension": "jpg",
          "height": 600,
          "mimetype": "image/jpeg",
          "secret": "9XZy32dFqpdi68oBLtIgUcvY2qEIb2Xu",
          "width": 434
        },
        "ds": {
          "extension": "jpg",
          "height": 320,
          "mimetype": "image/jpeg",
          "secret": "9XZy32dFqpdi68oBLtIgUcvY2qEIb2Xu",
          "width": 320
        },
        "k": {
          "extension": "jpg",
          "height": 1536,
          "mimetype": "image/jpeg",
          "secret": "9XZy32dFqpdi68oBLtIgUcvY2qEIb2Xu",
          "width": 1113
        },
        "n": {
          "extension": "jpg",
          "height": 240,
          "mimetype": "image/jpeg",
          "secret": "9XZy32dFqpdi68oBLtIgUcvY2qEIb2Xu",
          "width": 173
        },
        "o": {
          "extension": "jpg",
          "height": 2862,
          "mimetype": "image/jpeg",
          "secret": "i3bf0HMv4GrD8DbhqR8SQEkPp1RSAcjS",
          "width": 2074
        },
        "s": {
          "extension": "jpg",
          "height": 320,
          "mimetype": "image/jpeg",
          "secret": "9XZy32dFqpdi68oBLtIgUcvY2qEIb2Xu",
          "width": 320
        },
        "z": {
          "extension": "jpg",
          "height": 480,
          "mimetype": "image/jpeg",
          "secret": "9XZy32dFqpdi68oBLtIgUcvY2qEIb2Xu",
          "width": 347
        }
      }
    },
    "media:uri_template": "https://static.sfomuseum.org/media/152/785/371/5/1527853715_{secret}_{label}.{extention}",
    "sfomuseum:filename": "92855.tif",
    "sfomuseum:image_index": 5,
    "sfomuseum:image_type": "studio",
    "sfomuseum:placetype": "image",
    "sfomuseum:primary_image": 1,
    "wof:depicts": [
      1511956653,
      1159285413
    ],
    "wof:name": "menu: United Airlines, First Class",
    "wof:placetype": "custom",
    "wof:placetype_alt": "image"
  },
  "geometry": {"coordinates":[-122.386155,37.616358],"type":"Point"}
}
