{
  "type": "Feature",
  "properties": {
    "iso:country": "XX",
    "media:fingerprint": "7d1d3d73fb7c28a5142492d1c747691208ee2ed5",
    "media:imagehash_avg": "a:ff010183878fbf3f",
    "media:imagehash_diff": "d:333f37174e7e7def",
    "media:medium": "image",
    "media:mimetype": "image/tiff",
    "media:properties": {
      "colours": [
        {
          "hex": "#7b7878",
          "name": "#7b7878",
          "reference": "vibrant"
        },
        {
          "hex": "#b9b6b5",
          "name": "#b9b6b5",
          "reference": "vibrant"
        },
        {
          "hex": "#464342",
          "name": "#464342",
          "reference": "vibrant"
        }
      ],
      "sizes": {
        "b": {
          "extension": "jpg",
          "height": 768,
          "mimetype": "image/jpeg",
          "secret": "4IBpzRoefepbXzmWGuwguPys5Es6lJw0",
          "width": 969
        },
        "c": {
          "extension": "jpg",
          "height": 600,
          "mimetype": "image/jpeg",
          "secret": "4IBpzRoefepbXzmWGuwguPys5Es6lJw0",
          "width": 757
        },
        "dc": {
          "extension": "jpg",
          "height": 600,
          "mimetype": "image/jpeg",
          "secret": "4IBpzRoefepbXzmWGuwguPys5Es6lJw0",
          "width": 757
        },
        "ds": {
          "extension": "jpg",
          "height": 320,
          "mimetype": "image/jpeg",
          "secret": "4IBpzRoefepbXzmWGuwguPys5Es6lJw0",
          "width": 320
        },
        "k": {
          "extension": "jpg",
          "height": 1536,
          "mimetype": "image/jpeg",
          "secret": "4IBpzRoefepbXzmWGuwguPys5Es6lJw0",
          "width": 1938
        },
        "n": {
          "extension": "jpg",
          "height": 240,
          "mimetype": "image/jpeg",
          "secret": "4IBpzRoefepbXzmWGuwguPys5Es6lJw0",
          "width": 302
        },
        "o": {
          "extension": "jpg",
          "height": 1585,
          "mimetype": "image/jpeg",
          "secret": "2LknL43z9WIhUZ5TXCgmZHebWQKXTQMC",
          "width": 2000
        },
        "s": {
          "extension": "jpg",
          "height": 320,
          "mimetype": "image/jpeg",
          "secret": "4IBpzRoefepbXzmWGuwguPys5Es6lJw0",
          "width": 320
        },
        "z": {
          "extension": "jpg",
          "height": 480,
          "mimetype": "image/jpeg",
          "secret": "4IBpzRoefepbXzmWGuwguPys5Es6lJw0",
          "width": 605
        }
      }
    },
    "media:uri_template": "https://static.sfomuseum.org/media/152/785/830/7/1527858307_{secret}_{label}.{extention}",
    "sfomuseum:filename": "2011.032.0081.tif",
    "sfomuseum:image_index": 5,
    "sfomuseum:image_type": "studio",
    "sfomuseum:placetype": "image",
    "sfomuseum:primary_image": 1,
    "wof:depicts": [
      1360695653,
      1511943503,
      102527513
    ],
    "wof:name": "negative: Mills Field Municipal Airport of San Francisco, aerial",
    "wof:placetype": "custom",
    "wof:placetype_alt": "image"
  },
  "geometry": {"coordinates":[-122.386155,37.616358],"type":"Point"}
}
