{
  "type": "Feature",
  "properties": {
    "iso:country": "XX",
    "media:fingerprint": "196e731f2d12a1b6e01e3b02c5f8b22cf1ae8f07",
    "media:imagehash_avg": "a:ff818181818181ff",
    "media:imagehash_diff": "d:65797b2d21256367",
    "media:medium": "image",
    "media:mimetype": "image/tiff",
    "media:properties": {
      "colours": [
        {
          "hex": "#e84848",
          "name": "#e84848",
          "reference": "vibrant"
        }, 
        {
          "hex": "#f68281",
          "name": "#f68281",
          "reference": "vibrant"
        }, 
        {
          "hex": "#602b2f",
          "name": "#602b2f",
          "reference": "vibrant"
        }, 
        {
          "hex": "#797991",
          "name": "#797991",
          "reference": "vibrant"
        }, 
        {
          "hex": "#beb6bf",
          "name": "#beb6bf",
          "reference": "vibrant"
        }
      ],
      "sizes": {
        "b": {
          "extension": "jpg",
          "height": 767,
          "mimetype": "image/jpeg",
          "secret": "ivAx7eV7qlXDmPyKdLru0v5QyPnWLSoh",
          "width": 415
        },
        "c": {
          "extension": "jpg",
          "height": 600,
          "mimetype": "image/jpeg",
          "secret": "ivAx7eV7qlXDmPyKdLru0v5QyPnWLSoh",
          "width": 324
        },
        "dc": {
          "extension": "jpg",
          "height": 600,
          "mimetype": "image/jpeg",
          "secret": "ivAx7eV7qlXDmPyKdLru0v5QyPnWLSoh",
          "width": 324
        },
        "ds": {
          "extension": "jpg",
          "height": 320,
          "mimetype": "image/jpeg",
          "secret": "ivAx7eV7qlXDmPyKdLru0v5QyPnWLSoh",
          "width": 320
        },
        "k": {
          "extension": "jpg",
          "height": 1535,
          "mimetype": "image/jpeg",
          "secret": "ivAx7eV7qlXDmPyKdLru0v5QyPnWLSoh",
          "width": 831
        },
        "n": {
          "extension": "jpg",
          "height": 240,
          "mimetype": "image/jpeg",
          "secret": "ivAx7eV7qlXDmPyKdLru0v5QyPnWLSoh",
          "width": 129
        },
        "o": {
          "extension": "jpg",
          "height": 2868,
          "mimetype": "image/jpeg",
          "secret": "ywAB3XI5IFdbUYXUuaJz2QUNQ92VlqNu",
          "width": 1553
        },
        "s": {
          "extension": "jpg",
          "height": 320,
          "mimetype": "image/jpeg",
          "secret": "ivAx7eV7qlXDmPyKdLru0v5QyPnWLSoh",
          "width": 320
        },
        "z": {
          "extension": "jpg",
          "height": 480,
          "mimetype": "image/jpeg",
          "secret": "ivAx7eV7qlXDmPyKdLru0v5QyPnWLSoh",
          "width": 259
        }
      }
    },
    "media:uri_template": "https://millsfield.sfomuseum.org/media/152/782/439/9/1527824399_{secret}_{label}.{extention}",
    "sfomuseum:filename": "42548.tif",
    "sfomuseum:image_index": 5,
    "sfomuseum:placetype": "image",
    "sfomuseum:primary_image": 1,
    "wof:depicts": [
      1511908547
    ],
    "wof:name": "airsickness bag: Crossair",
    "wof:placetype": "media"
  },
  "geometry": {"coordinates":[-122.386155,37.616358],"type":"Point"}
}
