{
  "type": "Feature",
  "properties": {
    "iso:country": "XX",
    "media:fingerprint": "1ffc0c12340dca2ab2ca500113da9429cd804059",
    "media:imagehash_avg": "a:ffffff0000000000",
    "media:imagehash_diff": "d:611d4d5393131313",
    "media:medium": "image",
    "media:mimetype": "image/tiff",
    "media:properties": {
      "colours": [
        {
          "hex": "#305578",
          "name": "#305578",
          "reference": "vibrant"
        },
        {
          "hex": "#dfd2ad",
          "name": "#dfd2ad",
          "reference": "vibrant"
        },
        {
          "hex": "#072c63",
          "name": "#072c63",
          "reference": "vibrant"
        },
        {
          "hex": "#618295",
          "name": "#618295",
          "reference": "vibrant"
        },
        {
          "hex": "#c1c3a9",
          "name": "#c1c3a9",
          "reference": "vibrant"
        }
      ],
      "sizes": {
        "b": {
          "extension": "jpg",
          "height": 650,
          "mimetype": "image/jpeg",
          "secret": "ivEXJ89lSoTcoLQ2fK7Y6DZWUrgHWkIU",
          "width": 1024
        },
        "c": {
          "extension": "jpg",
          "height": 508,
          "mimetype": "image/jpeg",
          "secret": "ivEXJ89lSoTcoLQ2fK7Y6DZWUrgHWkIU",
          "width": 800
        },
        "dc": {
          "extension": "jpg",
          "height": 508,
          "mimetype": "image/jpeg",
          "secret": "ivEXJ89lSoTcoLQ2fK7Y6DZWUrgHWkIU",
          "width": 800
        },
        "ds": {
          "extension": "jpg",
          "height": 320,
          "mimetype": "image/jpeg",
          "secret": "ivEXJ89lSoTcoLQ2fK7Y6DZWUrgHWkIU",
          "width": 320
        },
        "k": {
          "extension": "jpg",
          "height": 1300,
          "mimetype": "image/jpeg",
          "secret": "ivEXJ89lSoTcoLQ2fK7Y6DZWUrgHWkIU",
          "width": 2048
        },
        "n": {
          "extension": "jpg",
          "height": 203,
          "mimetype": "image/jpeg",
          "secret": "ivEXJ89lSoTcoLQ2fK7Y6DZWUrgHWkIU",
          "width": 320
        },
        "o": {
          "extension": "jpg",
          "height": 898,
          "mimetype": "image/jpeg",
          "secret": "IcYx2kctdWEgJLcoF06Th4d174p0gjPC",
          "width": 1414
        },
        "s": {
          "extension": "jpg",
          "height": 320,
          "mimetype": "image/jpeg",
          "secret": "ivEXJ89lSoTcoLQ2fK7Y6DZWUrgHWkIU",
          "width": 320
        },
        "z": {
          "extension": "jpg",
          "height": 406,
          "mimetype": "image/jpeg",
          "secret": "ivEXJ89lSoTcoLQ2fK7Y6DZWUrgHWkIU",
          "width": 640
        }
      }
    },
    "media:uri_template": "https://static.sfomuseum.org/media/152/785/299/9/1527852999_{secret}_{label}.{extention}",
    "sfomuseum:filename": "2012.149.1516.tif",
    "sfomuseum:image_index": 5,
    "sfomuseum:image_type": "studio",
    "sfomuseum:placetype": "image",
    "sfomuseum:primary_image": 1,
    "wof:depicts": [
      1511953037
    ],
    "wof:name": "postage stamps: United States Airmail",
    "wof:placetype": "custom",
    "wof:placetype_alt": "image"
  },
  "geometry": {"coordinates":[-122.386155,37.616358],"type":"Point"}
}
