{
  "type": "Feature",
  "properties": {
    "iso:country": "XX",
    "media:fingerprint": "73ccd1d4330818d78348935bc8d61302500f0761",
    "media:imagehash_avg": "a:fffffbe0e000c0e0",
    "media:imagehash_diff": "d:340e029800100004",
    "media:medium": "image",
    "media:mimetype": "image/tiff",
    "media:properties": {
      "colours": [
        {
          "hex": "#808080",
          "name": "#808080",
          "reference": "vibrant"
        }, 
        {
          "hex": "#b8b8b8",
          "name": "#b8b8b8",
          "reference": "vibrant"
        }, 
        {
          "hex": "#454545",
          "name": "#454545",
          "reference": "vibrant"
        }
      ],
      "sizes": {
        "b": {
          "extension": "jpg",
          "height": 768,
          "mimetype": "image/jpeg",
          "secret": "LWyVZ5HfsqVOP0ZcMtL7T7D0dQeTYZvE",
          "width": 762
        },
        "c": {
          "extension": "jpg",
          "height": 600,
          "mimetype": "image/jpeg",
          "secret": "LWyVZ5HfsqVOP0ZcMtL7T7D0dQeTYZvE",
          "width": 595
        },
        "dc": {
          "extension": "jpg",
          "height": 600,
          "mimetype": "image/jpeg",
          "secret": "LWyVZ5HfsqVOP0ZcMtL7T7D0dQeTYZvE",
          "width": 595
        },
        "ds": {
          "extension": "jpg",
          "height": 320,
          "mimetype": "image/jpeg",
          "secret": "LWyVZ5HfsqVOP0ZcMtL7T7D0dQeTYZvE",
          "width": 320
        },
        "k": {
          "extension": "jpg",
          "height": 1536,
          "mimetype": "image/jpeg",
          "secret": "LWyVZ5HfsqVOP0ZcMtL7T7D0dQeTYZvE",
          "width": 1524
        },
        "n": {
          "extension": "jpg",
          "height": 240,
          "mimetype": "image/jpeg",
          "secret": "LWyVZ5HfsqVOP0ZcMtL7T7D0dQeTYZvE",
          "width": 238
        },
        "o": {
          "extension": "jpg",
          "height": 1764,
          "mimetype": "image/jpeg",
          "secret": "SgmC20dJg4fkHeYGt6Q641LSH8sUFpKG",
          "width": 1751
        },
        "s": {
          "extension": "jpg",
          "height": 320,
          "mimetype": "image/jpeg",
          "secret": "LWyVZ5HfsqVOP0ZcMtL7T7D0dQeTYZvE",
          "width": 320
        },
        "z": {
          "extension": "jpg",
          "height": 480,
          "mimetype": "image/jpeg",
          "secret": "LWyVZ5HfsqVOP0ZcMtL7T7D0dQeTYZvE",
          "width": 476
        }
      }
    },
    "media:uri_template": "https://millsfield.sfomuseum.org/media/152/782/659/5/1527826595_{secret}_{label}.{extention}",
    "sfomuseum:filename": "43711.tif",
    "sfomuseum:image_index": 5,
    "sfomuseum:placetype": "image",
    "sfomuseum:primary_image": 1,
    "wof:depicts": [
      1511947635
    ],
    "wof:name": "photograph: San Francisco International Airport (SFO), construction of Pacific Southwest Airlines (PSA) pier and jetway",
    "wof:placetype": "media"
  },
  "geometry": {"coordinates":[-122.386155,37.616358],"type":"Point"}
}
