{
  "type": "Feature",
  "properties": {
    "iso:country": "XX",
    "media:fingerprint": "e711356b4118d65bca9c5ea32aff647148216ea1",
    "media:imagehash_avg": "a:ffffffff00000000",
    "media:imagehash_diff": "d:4040002063f6e174",
    "media:medium": "image",
    "media:mimetype": "image/tiff",
    "media:properties": {
      "colours": [
        {
          "hex": "#b08321",
          "name": "#b08321",
          "reference": "vibrant"
        }, 
        {
          "hex": "#9dd1b5",
          "name": "#9dd1b5",
          "reference": "vibrant"
        }, 
        {
          "hex": "#6d5e21",
          "name": "#6d5e21",
          "reference": "vibrant"
        }, 
        {
          "hex": "#8e9b69",
          "name": "#8e9b69",
          "reference": "vibrant"
        }, 
        {
          "hex": "#a1cc9c",
          "name": "#a1cc9c",
          "reference": "vibrant"
        }
      ],
      "sizes": {
        "b": {
          "extension": "jpg",
          "height": 768,
          "mimetype": "image/jpeg",
          "secret": "WVTYJWbnxm0JOHvMghJeZRNU0NdondvQ",
          "width": 776
        },
        "c": {
          "extension": "jpg",
          "height": 600,
          "mimetype": "image/jpeg",
          "secret": "WVTYJWbnxm0JOHvMghJeZRNU0NdondvQ",
          "width": 606
        },
        "dc": {
          "extension": "jpg",
          "height": 600,
          "mimetype": "image/jpeg",
          "secret": "WVTYJWbnxm0JOHvMghJeZRNU0NdondvQ",
          "width": 606
        },
        "ds": {
          "extension": "jpg",
          "height": 320,
          "mimetype": "image/jpeg",
          "secret": "WVTYJWbnxm0JOHvMghJeZRNU0NdondvQ",
          "width": 320
        },
        "k": {
          "extension": "jpg",
          "height": 1536,
          "mimetype": "image/jpeg",
          "secret": "WVTYJWbnxm0JOHvMghJeZRNU0NdondvQ",
          "width": 1552
        },
        "n": {
          "extension": "jpg",
          "height": 240,
          "mimetype": "image/jpeg",
          "secret": "WVTYJWbnxm0JOHvMghJeZRNU0NdondvQ",
          "width": 242
        },
        "o": {
          "extension": "jpg",
          "height": 2536,
          "mimetype": "image/jpeg",
          "secret": "VA03Nzypj5hH3PFPjLjT8oFUS8cGfmTD",
          "width": 2563
        },
        "s": {
          "extension": "jpg",
          "height": 320,
          "mimetype": "image/jpeg",
          "secret": "WVTYJWbnxm0JOHvMghJeZRNU0NdondvQ",
          "width": 320
        },
        "z": {
          "extension": "jpg",
          "height": 480,
          "mimetype": "image/jpeg",
          "secret": "WVTYJWbnxm0JOHvMghJeZRNU0NdondvQ",
          "width": 485
        }
      }
    },
    "media:uri_template": "https://millsfield.sfomuseum.org/media/152/782/779/5/1527827795_{secret}_{label}.{extention}",
    "sfomuseum:filename": "44246.tif",
    "sfomuseum:image_index": 5,
    "sfomuseum:placetype": "image",
    "sfomuseum:primary_image": 1,
    "wof:depicts": [
      1511948829
    ],
    "wof:name": "negative: San Francisco International Airport (SFO), construction and maintenance equipment",
    "wof:placetype": "media"
  },
  "geometry": {"coordinates":[-122.386155,37.616358],"type":"Point"}
}
