{
  "type": "Feature",
  "properties": {
    "iso:country": "XX",
    "media:fingerprint": "275c52a3451433d34347118431c6a8bea48ea350",
    "media:imagehash_avg": "a:ffff3eff7cd80000",
    "media:imagehash_diff": "d:f0f0f870d030f0f0",
    "media:medium": "image",
    "media:mimetype": "image/tiff",
    "media:properties": {
      "colours": [
        {
          "hex": "#808080",
          "name": "#808080",
          "reference": "vibrant"
        }, 
        {
          "hex": "#b8b8b8",
          "name": "#b8b8b8",
          "reference": "vibrant"
        }, 
        {
          "hex": "#404040",
          "name": "#404040",
          "reference": "vibrant"
        }
      ],
      "sizes": {
        "b": {
          "extension": "jpg",
          "height": 767,
          "mimetype": "image/jpeg",
          "secret": "GB5uiU1KHK612FCOiZCajsfypCmuxem2",
          "width": 988
        },
        "c": {
          "extension": "jpg",
          "height": 600,
          "mimetype": "image/jpeg",
          "secret": "GB5uiU1KHK612FCOiZCajsfypCmuxem2",
          "width": 772
        },
        "dc": {
          "extension": "jpg",
          "height": 600,
          "mimetype": "image/jpeg",
          "secret": "GB5uiU1KHK612FCOiZCajsfypCmuxem2",
          "width": 772
        },
        "ds": {
          "extension": "jpg",
          "height": 320,
          "mimetype": "image/jpeg",
          "secret": "GB5uiU1KHK612FCOiZCajsfypCmuxem2",
          "width": 320
        },
        "k": {
          "extension": "jpg",
          "height": 1535,
          "mimetype": "image/jpeg",
          "secret": "GB5uiU1KHK612FCOiZCajsfypCmuxem2",
          "width": 1976
        },
        "n": {
          "extension": "jpg",
          "height": 240,
          "mimetype": "image/jpeg",
          "secret": "GB5uiU1KHK612FCOiZCajsfypCmuxem2",
          "width": 308
        },
        "o": {
          "extension": "jpg",
          "height": 2140,
          "mimetype": "image/jpeg",
          "secret": "mbhO3bXDkIR1017sIngQByfIiMjROQnQ",
          "width": 2754
        },
        "s": {
          "extension": "jpg",
          "height": 320,
          "mimetype": "image/jpeg",
          "secret": "GB5uiU1KHK612FCOiZCajsfypCmuxem2",
          "width": 320
        },
        "z": {
          "extension": "jpg",
          "height": 480,
          "mimetype": "image/jpeg",
          "secret": "GB5uiU1KHK612FCOiZCajsfypCmuxem2",
          "width": 617
        }
      }
    },
    "media:uri_template": "https://millsfield.sfomuseum.org/media/152/782/243/9/1527822439_{secret}_{label}.{extention}",
    "sfomuseum:filename": "40747.tif",
    "sfomuseum:image_index": 5,
    "sfomuseum:placetype": "image",
    "sfomuseum:primary_image": 1,
    "wof:depicts": [
      1511944345
    ],
    "wof:name": "negative: San Francisco International Airport (SFO), aerial",
    "wof:placetype": "media"
  },
  "geometry": {"coordinates":[-122.386155,37.616358],"type":"Point"}
}
