{
  "type": "Feature",
  "properties": {
    "iso:country": "XX",
    "media:fingerprint": "b24a03dda6ec3350c845b0d1dd96c56601c17456",
    "media:imagehash_avg": "a:f9ffff3e00000000",
    "media:imagehash_diff": "d:e3e6e4f8f8c0e0f0",
    "media:medium": "image",
    "media:mimetype": "image/tiff",
    "media:properties": {
      "colours": [
        {
          "hex": "#808080",
          "name": "#808080",
          "reference": "vibrant"
        }, 
        {
          "hex": "#c0c0c0",
          "name": "#c0c0c0",
          "reference": "vibrant"
        }, 
        {
          "hex": "#464646",
          "name": "#464646",
          "reference": "vibrant"
        }
      ],
      "sizes": {
        "b": {
          "extension": "jpg",
          "height": 768,
          "mimetype": "image/jpeg",
          "secret": "ZGd4j0LUmNuqFhT2oTdPt0H67RUB2H95",
          "width": 980
        },
        "c": {
          "extension": "jpg",
          "height": 600,
          "mimetype": "image/jpeg",
          "secret": "ZGd4j0LUmNuqFhT2oTdPt0H67RUB2H95",
          "width": 766
        },
        "dc": {
          "extension": "jpg",
          "height": 600,
          "mimetype": "image/jpeg",
          "secret": "ZGd4j0LUmNuqFhT2oTdPt0H67RUB2H95",
          "width": 766
        },
        "ds": {
          "extension": "jpg",
          "height": 320,
          "mimetype": "image/jpeg",
          "secret": "ZGd4j0LUmNuqFhT2oTdPt0H67RUB2H95",
          "width": 320
        },
        "k": {
          "extension": "jpg",
          "height": 1536,
          "mimetype": "image/jpeg",
          "secret": "ZGd4j0LUmNuqFhT2oTdPt0H67RUB2H95",
          "width": 1961
        },
        "n": {
          "extension": "jpg",
          "height": 240,
          "mimetype": "image/jpeg",
          "secret": "ZGd4j0LUmNuqFhT2oTdPt0H67RUB2H95",
          "width": 306
        },
        "o": {
          "extension": "jpg",
          "height": 2168,
          "mimetype": "image/jpeg",
          "secret": "at0fWLE7sNYs2UctU7CYxrwGYsMpfoWK",
          "width": 2768
        },
        "s": {
          "extension": "jpg",
          "height": 320,
          "mimetype": "image/jpeg",
          "secret": "ZGd4j0LUmNuqFhT2oTdPt0H67RUB2H95",
          "width": 320
        },
        "z": {
          "extension": "jpg",
          "height": 480,
          "mimetype": "image/jpeg",
          "secret": "ZGd4j0LUmNuqFhT2oTdPt0H67RUB2H95",
          "width": 612
        }
      }
    },
    "media:uri_template": "https://millsfield.sfomuseum.org/media/152/782/675/7/1527826757_{secret}_{label}.{extention}",
    "sfomuseum:filename": "43783.tif",
    "sfomuseum:image_index": 5,
    "sfomuseum:placetype": "image",
    "sfomuseum:primary_image": 1,
    "wof:depicts": [
      1511947797
    ],
    "wof:name": "negative: San Francisco International Airport (SFO), aerial",
    "wof:placetype": "media"
  },
  "geometry": {"coordinates":[-122.386155,37.616358],"type":"Point"}
}
