{
  "type": "Feature",
  "properties": {
    "media:fingerprint": "438fef76d5832dab2d6ac250ed13251a02559d1c",
    "media:imagehash_avg": "a:ff818181818183c7",
    "media:imagehash_diff": "d:0139391909031f0f",
    "media:mimetype": "image/tiff",
    "media:properties": {
      "colours": [
        {
          "hex": "#f2ebdf",
          "name": "#f2ebdf",
          "reference": "vibrant"
        },
        {
          "hex": "#858980",
          "name": "#858980",
          "reference": "vibrant"
        },
        {
          "hex": "#c8c8a8",
          "name": "#c8c8a8",
          "reference": "vibrant"
        },
        {
          "hex": "#44473c",
          "name": "#44473c",
          "reference": "vibrant"
        }
      ],
      "sizes": {
        "b": {
          "extension": "jpg",
          "height": 768,
          "mimetype": "image/jpeg",
          "secret": "8W41W7tmysHzgSQThm6mV0bcsQvdLrwm",
          "width": 948
        },
        "c": {
          "extension": "jpg",
          "height": 600,
          "mimetype": "image/jpeg",
          "secret": "8W41W7tmysHzgSQThm6mV0bcsQvdLrwm",
          "width": 741
        },
        "dc": {
          "extension": "jpg",
          "height": 600,
          "mimetype": "image/jpeg",
          "secret": "8W41W7tmysHzgSQThm6mV0bcsQvdLrwm",
          "width": 741
        },
        "ds": {
          "extension": "jpg",
          "height": 320,
          "mimetype": "image/jpeg",
          "secret": "8W41W7tmysHzgSQThm6mV0bcsQvdLrwm",
          "width": 320
        },
        "k": {
          "extension": "jpg",
          "height": 1536,
          "mimetype": "image/jpeg",
          "secret": "8W41W7tmysHzgSQThm6mV0bcsQvdLrwm",
          "width": 1897
        },
        "n": {
          "extension": "jpg",
          "height": 240,
          "mimetype": "image/jpeg",
          "secret": "8W41W7tmysHzgSQThm6mV0bcsQvdLrwm",
          "width": 296
        },
        "o": {
          "extension": "jpg",
          "height": 1619,
          "mimetype": "image/jpeg",
          "secret": "A3YTXnc2RT0OEUbnbsnijePU6Agkx0iw",
          "width": 2000
        },
        "s": {
          "extension": "jpg",
          "height": 320,
          "mimetype": "image/jpeg",
          "secret": "8W41W7tmysHzgSQThm6mV0bcsQvdLrwm",
          "width": 320
        },
        "z": {
          "extension": "jpg",
          "height": 480,
          "mimetype": "image/jpeg",
          "secret": "8W41W7tmysHzgSQThm6mV0bcsQvdLrwm",
          "width": 592
        }
      }
    },
    "media:uri_template": "https://static.sfomuseum.org/media/174/628/157/7/1746281577_{secret}_{label}.{extention}",
    "sfomuseum:filename": "2006.037.205.019.tif",
    "sfomuseum:image_index": 0,
    "sfomuseum:placetype": "image",
    "sfomuseum:primary_image": 1,
    "wof:depicts": [
      1729565101
    ],
    "wof:name": "photograph: Granville Brothers",
    "wof:placetype": "custom",
    "wof:placetype_alt": "image"
  },
  "geometry": {"coordinates":[-122.386155,37.616357],"type":"Point"}
}
