{
  "type": "Feature",
  "properties": {
    "iso:country": "XX",
    "media:fingerprint": "655856cbce2a01fbb8c68e3187fd569230d0374c",
    "media:imagehash_avg": "a:fe3c7c3e7c707808",
    "media:imagehash_diff": "d:f0f8e0f0e0c0d0f0",
    "media:medium": "image",
    "media:mimetype": "image/tiff",
    "media:properties": {
      "colours": [
        {
          "hex": "#808080",
          "name": "#808080",
          "reference": "vibrant"
        }, 
        {
          "hex": "#b6b6b6",
          "name": "#b6b6b6",
          "reference": "vibrant"
        }, 
        {
          "hex": "#404040",
          "name": "#404040",
          "reference": "vibrant"
        }
      ],
      "sizes": {
        "b": {
          "extension": "jpg",
          "height": 767,
          "mimetype": "image/jpeg",
          "secret": "Cvsh1Zv2t7hCMflrXKTFZJCPA0RJKuRs",
          "width": 988
        },
        "c": {
          "extension": "jpg",
          "height": 600,
          "mimetype": "image/jpeg",
          "secret": "Cvsh1Zv2t7hCMflrXKTFZJCPA0RJKuRs",
          "width": 772
        },
        "dc": {
          "extension": "jpg",
          "height": 600,
          "mimetype": "image/jpeg",
          "secret": "Cvsh1Zv2t7hCMflrXKTFZJCPA0RJKuRs",
          "width": 772
        },
        "ds": {
          "extension": "jpg",
          "height": 320,
          "mimetype": "image/jpeg",
          "secret": "Cvsh1Zv2t7hCMflrXKTFZJCPA0RJKuRs",
          "width": 320
        },
        "k": {
          "extension": "jpg",
          "height": 1535,
          "mimetype": "image/jpeg",
          "secret": "Cvsh1Zv2t7hCMflrXKTFZJCPA0RJKuRs",
          "width": 1976
        },
        "n": {
          "extension": "jpg",
          "height": 240,
          "mimetype": "image/jpeg",
          "secret": "Cvsh1Zv2t7hCMflrXKTFZJCPA0RJKuRs",
          "width": 308
        },
        "o": {
          "extension": "jpg",
          "height": 2140,
          "mimetype": "image/jpeg",
          "secret": "oAwcqKaxlxiuzYPunUrCGj0TZJp64D3U",
          "width": 2754
        },
        "s": {
          "extension": "jpg",
          "height": 320,
          "mimetype": "image/jpeg",
          "secret": "Cvsh1Zv2t7hCMflrXKTFZJCPA0RJKuRs",
          "width": 320
        },
        "z": {
          "extension": "jpg",
          "height": 480,
          "mimetype": "image/jpeg",
          "secret": "Cvsh1Zv2t7hCMflrXKTFZJCPA0RJKuRs",
          "width": 617
        }
      }
    },
    "media:uri_template": "https://millsfield.sfomuseum.org/media/152/782/241/5/1527822415_{secret}_{label}.{extention}",
    "sfomuseum:filename": "40736.tif",
    "sfomuseum:image_index": 5,
    "sfomuseum:placetype": "image",
    "sfomuseum:primary_image": 1,
    "wof:depicts": [
      1511944321
    ],
    "wof:name": "negative: San Francisco International Airport (SFO), aerial",
    "wof:placetype": "media"
  },
  "geometry": {"coordinates":[-122.386155,37.616358],"type":"Point"}
}
