{
  "type": "Feature",
  "properties": {
    "iso:country": "XX",
    "media:fingerprint": "d38477905af0bc407b34a483620cdedf114a4e71",
    "media:imagehash_avg": "a:bf0303bfbf9f880d",
    "media:imagehash_diff": "d:3f3773776b733959",
    "media:medium": "image",
    "media:mimetype": "image/tiff",
    "media:properties": {
      "colours": [
        {
          "hex": "#d87c29",
          "name": "#d87c29",
          "reference": "vibrant"
        }, 
        {
          "hex": "#cfbf9a",
          "name": "#cfbf9a",
          "reference": "vibrant"
        }, 
        {
          "hex": "#1a385f",
          "name": "#1a385f",
          "reference": "vibrant"
        }, 
        {
          "hex": "#8f6866",
          "name": "#8f6866",
          "reference": "vibrant"
        }, 
        {
          "hex": "#c8b898",
          "name": "#c8b898",
          "reference": "vibrant"
        }
      ],
      "sizes": {
        "b": {
          "extension": "jpg",
          "height": 768,
          "mimetype": "image/jpeg",
          "secret": "oCVLUeZvwczcbHr98fYhifAw5QWhOzCL",
          "width": 971
        },
        "c": {
          "extension": "jpg",
          "height": 600,
          "mimetype": "image/jpeg",
          "secret": "oCVLUeZvwczcbHr98fYhifAw5QWhOzCL",
          "width": 758
        },
        "dc": {
          "extension": "jpg",
          "height": 600,
          "mimetype": "image/jpeg",
          "secret": "oCVLUeZvwczcbHr98fYhifAw5QWhOzCL",
          "width": 758
        },
        "ds": {
          "extension": "jpg",
          "height": 320,
          "mimetype": "image/jpeg",
          "secret": "oCVLUeZvwczcbHr98fYhifAw5QWhOzCL",
          "width": 320
        },
        "k": {
          "extension": "jpg",
          "height": 1536,
          "mimetype": "image/jpeg",
          "secret": "oCVLUeZvwczcbHr98fYhifAw5QWhOzCL",
          "width": 1942
        },
        "n": {
          "extension": "jpg",
          "height": 240,
          "mimetype": "image/jpeg",
          "secret": "oCVLUeZvwczcbHr98fYhifAw5QWhOzCL",
          "width": 303
        },
        "o": {
          "extension": "jpg",
          "height": 1269,
          "mimetype": "image/jpeg",
          "secret": "uJiXwhGL9V3fYTAzYGYFPShFlmrxGyeq",
          "width": 1605
        },
        "s": {
          "extension": "jpg",
          "height": 320,
          "mimetype": "image/jpeg",
          "secret": "oCVLUeZvwczcbHr98fYhifAw5QWhOzCL",
          "width": 320
        },
        "z": {
          "extension": "jpg",
          "height": 480,
          "mimetype": "image/jpeg",
          "secret": "oCVLUeZvwczcbHr98fYhifAw5QWhOzCL",
          "width": 607
        }
      }
    },
    "media:uri_template": "https://millsfield.sfomuseum.org/media/152/782/032/3/1527820323_{secret}_{label}.{extention}",
    "sfomuseum:filename": "31520.tif",
    "sfomuseum:image_index": 5,
    "sfomuseum:placetype": "image",
    "sfomuseum:primary_image": 1,
    "wof:depicts": [
      1511923513
    ],
    "wof:name": "airmail flight cover: Panair do Brasil, first airmail flight, Manaus - Belem route",
    "wof:placetype": "media"
  },
  "geometry": {"coordinates":[-122.386155,37.616358],"type":"Point"}
}
