{
  "type": "Feature",
  "properties": {
    "iso:country": "XX",
    "media:fingerprint": "9d3a107d8e43b104f5c6232304059ecb2e1bc0a8",
    "media:imagehash_avg": "a:0f0cefefff3f1fbf",
    "media:imagehash_diff": "d:3939090b496d6969",
    "media:medium": "image",
    "media:mimetype": "image/tiff",
    "media:properties": {
      "colours": [
        {
          "hex": "#22277c",
          "name": "#22277c",
          "reference": "vibrant"
        },
        {
          "hex": "#e8e0c8",
          "name": "#e8e0c8",
          "reference": "vibrant"
        },
        {
          "hex": "#090d7a",
          "name": "#090d7a",
          "reference": "vibrant"
        },
        {
          "hex": "#6b6b93",
          "name": "#6b6b93",
          "reference": "vibrant"
        },
        {
          "hex": "#ccc3b5",
          "name": "#ccc3b5",
          "reference": "vibrant"
        }
      ],
      "sizes": {
        "b": {
          "extension": "jpg",
          "height": 662,
          "mimetype": "image/jpeg",
          "secret": "bojJ2Vf26YqBXE5wB5q68uFzC5h9HdGS",
          "width": 1023
        },
        "c": {
          "extension": "jpg",
          "height": 517,
          "mimetype": "image/jpeg",
          "secret": "bojJ2Vf26YqBXE5wB5q68uFzC5h9HdGS",
          "width": 800
        },
        "dc": {
          "extension": "jpg",
          "height": 517,
          "mimetype": "image/jpeg",
          "secret": "bojJ2Vf26YqBXE5wB5q68uFzC5h9HdGS",
          "width": 800
        },
        "ds": {
          "extension": "jpg",
          "height": 320,
          "mimetype": "image/jpeg",
          "secret": "bojJ2Vf26YqBXE5wB5q68uFzC5h9HdGS",
          "width": 320
        },
        "k": {
          "extension": "jpg",
          "height": 1324,
          "mimetype": "image/jpeg",
          "secret": "bojJ2Vf26YqBXE5wB5q68uFzC5h9HdGS",
          "width": 2047
        },
        "n": {
          "extension": "jpg",
          "height": 206,
          "mimetype": "image/jpeg",
          "secret": "bojJ2Vf26YqBXE5wB5q68uFzC5h9HdGS",
          "width": 320
        },
        "o": {
          "extension": "jpg",
          "height": 1092,
          "mimetype": "image/jpeg",
          "secret": "Gzkuy5vLBP0omLcPTaRQgv36FcNc8rhb",
          "width": 1689
        },
        "s": {
          "extension": "jpg",
          "height": 320,
          "mimetype": "image/jpeg",
          "secret": "bojJ2Vf26YqBXE5wB5q68uFzC5h9HdGS",
          "width": 320
        },
        "z": {
          "extension": "jpg",
          "height": 413,
          "mimetype": "image/jpeg",
          "secret": "bojJ2Vf26YqBXE5wB5q68uFzC5h9HdGS",
          "width": 640
        }
      }
    },
    "media:uri_template": "https://static.sfomuseum.org/media/152/785/621/5/1527856215_{secret}_{label}.{extention}",
    "sfomuseum:filename": "2014.095.220_bk.tif",
    "sfomuseum:image_index": 5,
    "sfomuseum:image_type": "studio",
    "sfomuseum:placetype": "image",
    "sfomuseum:primary_image": 0,
    "wof:depicts": [
      1159285415,
      1511957005,
      1159288779
    ],
    "wof:name": "menu: United Air Lines",
    "wof:placetype": "custom",
    "wof:placetype_alt": "image"
  },
  "geometry": {"coordinates":[-122.386155,37.616358],"type":"Point"}
}
