{
  "type": "Feature",
  "properties": {
    "iso:country": "XX",
    "media:fingerprint": "d254656408a5b2f2ae280846f0ea8e0f485d9581",
    "media:imagehash_avg": "a:7fff3f0f3000003b",
    "media:imagehash_diff": "d:f8f8f9ffe3c8f6f7",
    "media:medium": "image",
    "media:mimetype": "image/tiff",
    "media:properties": {
      "colours": [
        {
          "hex": "#808080",
          "name": "#808080",
          "reference": "vibrant"
        }, 
        {
          "hex": "#b5b5b5",
          "name": "#b5b5b5",
          "reference": "vibrant"
        }, 
        {
          "hex": "#464646",
          "name": "#464646",
          "reference": "vibrant"
        }
      ],
      "sizes": {
        "b": {
          "extension": "jpg",
          "height": 768,
          "mimetype": "image/jpeg",
          "secret": "7SyD7VNX3JIWbdV5Joi48wLSTUgWbp7X",
          "width": 970
        },
        "c": {
          "extension": "jpg",
          "height": 600,
          "mimetype": "image/jpeg",
          "secret": "7SyD7VNX3JIWbdV5Joi48wLSTUgWbp7X",
          "width": 758
        },
        "dc": {
          "extension": "jpg",
          "height": 600,
          "mimetype": "image/jpeg",
          "secret": "7SyD7VNX3JIWbdV5Joi48wLSTUgWbp7X",
          "width": 758
        },
        "ds": {
          "extension": "jpg",
          "height": 320,
          "mimetype": "image/jpeg",
          "secret": "7SyD7VNX3JIWbdV5Joi48wLSTUgWbp7X",
          "width": 320
        },
        "k": {
          "extension": "jpg",
          "height": 1536,
          "mimetype": "image/jpeg",
          "secret": "7SyD7VNX3JIWbdV5Joi48wLSTUgWbp7X",
          "width": 1941
        },
        "n": {
          "extension": "jpg",
          "height": 240,
          "mimetype": "image/jpeg",
          "secret": "7SyD7VNX3JIWbdV5Joi48wLSTUgWbp7X",
          "width": 303
        },
        "o": {
          "extension": "jpg",
          "height": 2168,
          "mimetype": "image/jpeg",
          "secret": "QVMuqcAhKq08QdMkG6Ov7G1dVwb1YBTt",
          "width": 2740
        },
        "s": {
          "extension": "jpg",
          "height": 320,
          "mimetype": "image/jpeg",
          "secret": "7SyD7VNX3JIWbdV5Joi48wLSTUgWbp7X",
          "width": 320
        },
        "z": {
          "extension": "jpg",
          "height": 480,
          "mimetype": "image/jpeg",
          "secret": "7SyD7VNX3JIWbdV5Joi48wLSTUgWbp7X",
          "width": 606
        }
      }
    },
    "media:uri_template": "https://millsfield.sfomuseum.org/media/152/782/487/7/1527824877_{secret}_{label}.{extention}",
    "sfomuseum:filename": "42864.tif",
    "sfomuseum:image_index": 5,
    "sfomuseum:placetype": "image",
    "sfomuseum:primary_image": 1,
    "wof:depicts": [
      1511945759
    ],
    "wof:name": "negative: San Francisco International Airport (SFO), maintenance buildings",
    "wof:placetype": "media"
  },
  "geometry": {"coordinates":[-122.386155,37.616358],"type":"Point"}
}
