{
  "type": "Feature",
  "properties": {
    "iso:country": "XX",
    "media:fingerprint": "5df0f62005caf75ca0193f260f280e288bec20c6",
    "media:imagehash_avg": "a:03020b0f1f5e1adb",
    "media:imagehash_diff": "d:9e9296bafad89292",
    "media:medium": "image",
    "media:mimetype": "image/tiff",
    "media:properties": {
      "colours": [
        {
          "hex": "#a58c64",
          "name": "#a58c64",
          "reference": "vibrant"
        },
        {
          "hex": "#c5c2af",
          "name": "#c5c2af",
          "reference": "vibrant"
        },
        {
          "hex": "#483725",
          "name": "#483725",
          "reference": "vibrant"
        }
      ],
      "sizes": {
        "b": {
          "extension": "jpg",
          "height": 654,
          "mimetype": "image/jpeg",
          "secret": "Y6JPBJQhmtR1CiBLYdygUkESn2X94QgM",
          "width": 1024
        },
        "c": {
          "extension": "jpg",
          "height": 511,
          "mimetype": "image/jpeg",
          "secret": "Y6JPBJQhmtR1CiBLYdygUkESn2X94QgM",
          "width": 800
        },
        "dc": {
          "extension": "jpg",
          "height": 511,
          "mimetype": "image/jpeg",
          "secret": "Y6JPBJQhmtR1CiBLYdygUkESn2X94QgM",
          "width": 800
        },
        "ds": {
          "extension": "jpg",
          "height": 320,
          "mimetype": "image/jpeg",
          "secret": "Y6JPBJQhmtR1CiBLYdygUkESn2X94QgM",
          "width": 320
        },
        "k": {
          "extension": "jpg",
          "height": 1309,
          "mimetype": "image/jpeg",
          "secret": "Y6JPBJQhmtR1CiBLYdygUkESn2X94QgM",
          "width": 2048
        },
        "n": {
          "extension": "jpg",
          "height": 204,
          "mimetype": "image/jpeg",
          "secret": "Y6JPBJQhmtR1CiBLYdygUkESn2X94QgM",
          "width": 320
        },
        "o": {
          "extension": "jpg",
          "height": 1063,
          "mimetype": "image/jpeg",
          "secret": "LnE5EtiYskcwiN6Qg92j3kv1we3zmsPA",
          "width": 1663
        },
        "s": {
          "extension": "jpg",
          "height": 320,
          "mimetype": "image/jpeg",
          "secret": "Y6JPBJQhmtR1CiBLYdygUkESn2X94QgM",
          "width": 320
        },
        "z": {
          "extension": "jpg",
          "height": 409,
          "mimetype": "image/jpeg",
          "secret": "Y6JPBJQhmtR1CiBLYdygUkESn2X94QgM",
          "width": 640
        }
      }
    },
    "media:uri_template": "https://static.sfomuseum.org/media/152/782/845/1/1527828451_{secret}_{label}.{extention}",
    "sfomuseum:filename": "44605.tif",
    "sfomuseum:image_index": 5,
    "sfomuseum:image_type": "studio",
    "sfomuseum:placetype": "image",
    "sfomuseum:primary_image": 1,
    "wof:depicts": [
      102527513,
      1511949485
    ],
    "wof:name": "negative: San Francisco International Airport (SFO), medical clinic",
    "wof:placetype": "custom",
    "wof:placetype_alt": "image"
  },
  "geometry": {"coordinates":[-122.386155,37.616358],"type":"Point"}
}
