{
  "type": "Feature",
  "properties": {
    "iso:country": "XX",
    "media:fingerprint": "ee83ad4063becc30b3fc690449dd3e3dbe8d342e",
    "media:imagehash_avg": "a:fcffffff00000000",
    "media:imagehash_diff": "d:61f1400d1b909898",
    "media:medium": "image",
    "media:mimetype": "image/tiff",
    "media:properties": {
      "colours": [
        {
          "hex": "#808080",
          "name": "#808080",
          "reference": "vibrant"
        }, 
        {
          "hex": "#b8b8b8",
          "name": "#b8b8b8",
          "reference": "vibrant"
        }, 
        {
          "hex": "#464646",
          "name": "#464646",
          "reference": "vibrant"
        }
      ],
      "sizes": {
        "b": {
          "extension": "jpg",
          "height": 768,
          "mimetype": "image/jpeg",
          "secret": "g5YoYM2pRSHEk1felVaJM2iziJW2FL4g",
          "width": 596
        },
        "c": {
          "extension": "jpg",
          "height": 600,
          "mimetype": "image/jpeg",
          "secret": "g5YoYM2pRSHEk1felVaJM2iziJW2FL4g",
          "width": 466
        },
        "dc": {
          "extension": "jpg",
          "height": 600,
          "mimetype": "image/jpeg",
          "secret": "g5YoYM2pRSHEk1felVaJM2iziJW2FL4g",
          "width": 466
        },
        "ds": {
          "extension": "jpg",
          "height": 320,
          "mimetype": "image/jpeg",
          "secret": "g5YoYM2pRSHEk1felVaJM2iziJW2FL4g",
          "width": 320
        },
        "k": {
          "extension": "jpg",
          "height": 1536,
          "mimetype": "image/jpeg",
          "secret": "g5YoYM2pRSHEk1felVaJM2iziJW2FL4g",
          "width": 1193
        },
        "n": {
          "extension": "jpg",
          "height": 240,
          "mimetype": "image/jpeg",
          "secret": "g5YoYM2pRSHEk1felVaJM2iziJW2FL4g",
          "width": 186
        },
        "o": {
          "extension": "jpg",
          "height": 2754,
          "mimetype": "image/jpeg",
          "secret": "gPTQUOQOPoSfHmNczbNPGAvHFg8Jj6Ze",
          "width": 2140
        },
        "s": {
          "extension": "jpg",
          "height": 320,
          "mimetype": "image/jpeg",
          "secret": "g5YoYM2pRSHEk1felVaJM2iziJW2FL4g",
          "width": 320
        },
        "z": {
          "extension": "jpg",
          "height": 480,
          "mimetype": "image/jpeg",
          "secret": "g5YoYM2pRSHEk1felVaJM2iziJW2FL4g",
          "width": 372
        }
      }
    },
    "media:uri_template": "https://millsfield.sfomuseum.org/media/152/782/247/1/1527822471_{secret}_{label}.{extention}",
    "sfomuseum:filename": "40761.tif",
    "sfomuseum:image_index": 5,
    "sfomuseum:placetype": "image",
    "sfomuseum:primary_image": 1,
    "wof:depicts": [
      1511944377
    ],
    "wof:name": "negative: San Francisco International Airport (SFO), construction of United Air Lines baggage conveyor",
    "wof:placetype": "media"
  },
  "geometry": {"coordinates":[-122.386155,37.616358],"type":"Point"}
}
