{
  "type": "Feature",
  "properties": {
    "iso:country": "XX",
    "media:fingerprint": "3089916399eff217f1a14f77cb3b8c5c14d99092",
    "media:imagehash_avg": "a:fffeb08080000000",
    "media:imagehash_diff": "d:c68464651614c9b6",
    "media:medium": "image",
    "media:mimetype": "image/tiff",
    "media:properties": {
      "colours": [
        {
          "hex": "#787878",
          "name": "#787878",
          "reference": "vibrant"
        }, 
        {
          "hex": "#c0c0c0",
          "name": "#c0c0c0",
          "reference": "vibrant"
        }, 
        {
          "hex": "#484848",
          "name": "#484848",
          "reference": "vibrant"
        }
      ],
      "sizes": {
        "b": {
          "extension": "jpg",
          "height": 768,
          "mimetype": "image/jpeg",
          "secret": "rLuNRb4HFaPD2O324CB6M17asPKBYBZH",
          "width": 762
        },
        "c": {
          "extension": "jpg",
          "height": 600,
          "mimetype": "image/jpeg",
          "secret": "rLuNRb4HFaPD2O324CB6M17asPKBYBZH",
          "width": 595
        },
        "dc": {
          "extension": "jpg",
          "height": 600,
          "mimetype": "image/jpeg",
          "secret": "rLuNRb4HFaPD2O324CB6M17asPKBYBZH",
          "width": 595
        },
        "ds": {
          "extension": "jpg",
          "height": 320,
          "mimetype": "image/jpeg",
          "secret": "rLuNRb4HFaPD2O324CB6M17asPKBYBZH",
          "width": 320
        },
        "k": {
          "extension": "jpg",
          "height": 1536,
          "mimetype": "image/jpeg",
          "secret": "rLuNRb4HFaPD2O324CB6M17asPKBYBZH",
          "width": 1524
        },
        "n": {
          "extension": "jpg",
          "height": 240,
          "mimetype": "image/jpeg",
          "secret": "rLuNRb4HFaPD2O324CB6M17asPKBYBZH",
          "width": 238
        },
        "o": {
          "extension": "jpg",
          "height": 1752,
          "mimetype": "image/jpeg",
          "secret": "1vzAurJUYg8lCNF8HLMicSDbuP49POR3",
          "width": 1739
        },
        "s": {
          "extension": "jpg",
          "height": 320,
          "mimetype": "image/jpeg",
          "secret": "rLuNRb4HFaPD2O324CB6M17asPKBYBZH",
          "width": 320
        },
        "z": {
          "extension": "jpg",
          "height": 480,
          "mimetype": "image/jpeg",
          "secret": "rLuNRb4HFaPD2O324CB6M17asPKBYBZH",
          "width": 476
        }
      }
    },
    "media:uri_template": "https://millsfield.sfomuseum.org/media/152/782/660/5/1527826605_{secret}_{label}.{extention}",
    "sfomuseum:filename": "43715.tif",
    "sfomuseum:image_index": 5,
    "sfomuseum:placetype": "image",
    "sfomuseum:primary_image": 1,
    "wof:depicts": [
      1511947643
    ],
    "wof:name": "photograph: San Francisco International Airport (SFO), construction of Pacific Southwest Airlines (PSA) pier and jetway",
    "wof:placetype": "media"
  },
  "geometry": {"coordinates":[-122.386155,37.616358],"type":"Point"}
}
