{
  "type": "Feature",
  "properties": {
    "iso:country": "XX",
    "media:fingerprint": "63674f2abad770fd364f31cf3e4d22aaed3d98a3",
    "media:imagehash_avg": "a:ffffffffff000000",
    "media:imagehash_diff": "d:fcfcfcf9cb8a66f4",
    "media:medium": "image",
    "media:mimetype": "image/tiff",
    "media:properties": {
      "colours": [
        {
          "hex": "#808080",
          "name": "#808080",
          "reference": "vibrant"
        }, 
        {
          "hex": "#c0c0c0",
          "name": "#c0c0c0",
          "reference": "vibrant"
        }, 
        {
          "hex": "#404040",
          "name": "#404040",
          "reference": "vibrant"
        }
      ],
      "sizes": {
        "b": {
          "extension": "jpg",
          "height": 768,
          "mimetype": "image/jpeg",
          "secret": "3H1xzKzf1JSLHG2Zk2iUEuftfCVWG6jk",
          "width": 776
        },
        "c": {
          "extension": "jpg",
          "height": 600,
          "mimetype": "image/jpeg",
          "secret": "3H1xzKzf1JSLHG2Zk2iUEuftfCVWG6jk",
          "width": 606
        },
        "dc": {
          "extension": "jpg",
          "height": 600,
          "mimetype": "image/jpeg",
          "secret": "3H1xzKzf1JSLHG2Zk2iUEuftfCVWG6jk",
          "width": 606
        },
        "ds": {
          "extension": "jpg",
          "height": 320,
          "mimetype": "image/jpeg",
          "secret": "3H1xzKzf1JSLHG2Zk2iUEuftfCVWG6jk",
          "width": 320
        },
        "k": {
          "extension": "jpg",
          "height": 1536,
          "mimetype": "image/jpeg",
          "secret": "3H1xzKzf1JSLHG2Zk2iUEuftfCVWG6jk",
          "width": 1552
        },
        "n": {
          "extension": "jpg",
          "height": 240,
          "mimetype": "image/jpeg",
          "secret": "3H1xzKzf1JSLHG2Zk2iUEuftfCVWG6jk",
          "width": 242
        },
        "o": {
          "extension": "jpg",
          "height": 2590,
          "mimetype": "image/jpeg",
          "secret": "iPHIBwGHDnDuEUVjstNoYl7QIA1S1AjT",
          "width": 2618
        },
        "s": {
          "extension": "jpg",
          "height": 320,
          "mimetype": "image/jpeg",
          "secret": "3H1xzKzf1JSLHG2Zk2iUEuftfCVWG6jk",
          "width": 320
        },
        "z": {
          "extension": "jpg",
          "height": 480,
          "mimetype": "image/jpeg",
          "secret": "3H1xzKzf1JSLHG2Zk2iUEuftfCVWG6jk",
          "width": 485
        }
      }
    },
    "media:uri_template": "https://millsfield.sfomuseum.org/media/152/782/641/7/1527826417_{secret}_{label}.{extention}",
    "sfomuseum:filename": "43631.tif",
    "sfomuseum:image_index": 5,
    "sfomuseum:placetype": "image",
    "sfomuseum:primary_image": 1,
    "wof:depicts": [
      1511947457
    ],
    "wof:name": "negative: San Francisco International Airport (SFO), construction",
    "wof:placetype": "media"
  },
  "geometry": {"coordinates":[-122.386155,37.616358],"type":"Point"}
}
