{
  "type": "Feature",
  "properties": {
    "iso:country": "XX",
    "media:fingerprint": "f5536aa76e04c198cf31dff6ddfed4bfe1593efa",
    "media:imagehash_avg": "a:ff7f31c1c1c3477f",
    "media:imagehash_diff": "d:cfcd67a78b9f9f97",
    "media:medium": "image",
    "media:mimetype": "image/tiff",
    "media:properties": {
      "colours": [
        {
          "hex": "#ce3a31",
          "name": "#ce3a31",
          "reference": "vibrant"
        }, 
        {
          "hex": "#e8bd8d",
          "name": "#e8bd8d",
          "reference": "vibrant"
        }, 
        {
          "hex": "#a57d61",
          "name": "#a57d61",
          "reference": "vibrant"
        }, 
        {
          "hex": "#e8dfd2",
          "name": "#e8dfd2",
          "reference": "vibrant"
        }, 
        {
          "hex": "#42486d",
          "name": "#42486d",
          "reference": "vibrant"
        }
      ],
      "sizes": {
        "b": {
          "extension": "jpg",
          "height": 768,
          "mimetype": "image/jpeg",
          "secret": "4fTGndqoXUTOY3A76Q9hrfow4hyv8Qo0",
          "width": 420
        },
        "c": {
          "extension": "jpg",
          "height": 600,
          "mimetype": "image/jpeg",
          "secret": "4fTGndqoXUTOY3A76Q9hrfow4hyv8Qo0",
          "width": 328
        },
        "dc": {
          "extension": "jpg",
          "height": 600,
          "mimetype": "image/jpeg",
          "secret": "4fTGndqoXUTOY3A76Q9hrfow4hyv8Qo0",
          "width": 328
        },
        "ds": {
          "extension": "jpg",
          "height": 320,
          "mimetype": "image/jpeg",
          "secret": "4fTGndqoXUTOY3A76Q9hrfow4hyv8Qo0",
          "width": 320
        },
        "k": {
          "extension": "jpg",
          "height": 1536,
          "mimetype": "image/jpeg",
          "secret": "4fTGndqoXUTOY3A76Q9hrfow4hyv8Qo0",
          "width": 841
        },
        "n": {
          "extension": "jpg",
          "height": 240,
          "mimetype": "image/jpeg",
          "secret": "4fTGndqoXUTOY3A76Q9hrfow4hyv8Qo0",
          "width": 131
        },
        "o": {
          "extension": "jpg",
          "height": 2748,
          "mimetype": "image/jpeg",
          "secret": "PvyhHxi9jaQyi7UxeHQ73XjtOLPKwuN0",
          "width": 1506
        },
        "s": {
          "extension": "jpg",
          "height": 320,
          "mimetype": "image/jpeg",
          "secret": "4fTGndqoXUTOY3A76Q9hrfow4hyv8Qo0",
          "width": 320
        },
        "z": {
          "extension": "jpg",
          "height": 480,
          "mimetype": "image/jpeg",
          "secret": "4fTGndqoXUTOY3A76Q9hrfow4hyv8Qo0",
          "width": 263
        }
      }
    },
    "media:uri_template": "https://millsfield.sfomuseum.org/media/152/782/349/1/1527823491_{secret}_{label}.{extention}",
    "sfomuseum:filename": "41610.tif",
    "sfomuseum:image_index": 5,
    "sfomuseum:placetype": "image",
    "sfomuseum:primary_image": 1,
    "wof:depicts": [
      1511908409
    ],
    "wof:name": "airsickness bag: Air UK",
    "wof:placetype": "media"
  },
  "geometry": {"coordinates":[-122.386155,37.616358],"type":"Point"}
}
