{
  "type": "Feature",
  "properties": {
    "iso:country": "XX",
    "media:fingerprint": "f738c3a4bce9acae65effd5517c80817b0cb12a1",
    "media:imagehash_avg": "a:1f0f0f0f0f0f5fbf",
    "media:imagehash_diff": "d:3572921b13dfba74",
    "media:medium": "image",
    "media:mimetype": "image/tiff",
    "media:properties": {
      "colours": [
        {
          "hex": "#d30103",
          "name": "#d30103",
          "reference": "vibrant"
        },
        {
          "hex": "#e0afa0",
          "name": "#e0afa0",
          "reference": "vibrant"
        },
        {
          "hex": "#0636a7",
          "name": "#0636a7",
          "reference": "vibrant"
        },
        {
          "hex": "#737a7f",
          "name": "#737a7f",
          "reference": "vibrant"
        },
        {
          "hex": "#cec2be",
          "name": "#cec2be",
          "reference": "vibrant"
        }
      ],
      "sizes": {
        "b": {
          "extension": "jpg",
          "height": 631,
          "mimetype": "image/jpeg",
          "secret": "r3Td279LTrpSfWYkN0Q1dUIu1EdQnTpV",
          "width": 1024
        },
        "c": {
          "extension": "jpg",
          "height": 493,
          "mimetype": "image/jpeg",
          "secret": "r3Td279LTrpSfWYkN0Q1dUIu1EdQnTpV",
          "width": 800
        },
        "dc": {
          "extension": "jpg",
          "height": 493,
          "mimetype": "image/jpeg",
          "secret": "r3Td279LTrpSfWYkN0Q1dUIu1EdQnTpV",
          "width": 800
        },
        "ds": {
          "extension": "jpg",
          "height": 320,
          "mimetype": "image/jpeg",
          "secret": "r3Td279LTrpSfWYkN0Q1dUIu1EdQnTpV",
          "width": 320
        },
        "k": {
          "extension": "jpg",
          "height": 1262,
          "mimetype": "image/jpeg",
          "secret": "r3Td279LTrpSfWYkN0Q1dUIu1EdQnTpV",
          "width": 2048
        },
        "n": {
          "extension": "jpg",
          "height": 197,
          "mimetype": "image/jpeg",
          "secret": "r3Td279LTrpSfWYkN0Q1dUIu1EdQnTpV",
          "width": 320
        },
        "o": {
          "extension": "jpg",
          "height": 1054,
          "mimetype": "image/jpeg",
          "secret": "UpDkASUiUekHybZej62Flf4KhwSd5D3D",
          "width": 1710
        },
        "s": {
          "extension": "jpg",
          "height": 320,
          "mimetype": "image/jpeg",
          "secret": "r3Td279LTrpSfWYkN0Q1dUIu1EdQnTpV",
          "width": 320
        },
        "z": {
          "extension": "jpg",
          "height": 394,
          "mimetype": "image/jpeg",
          "secret": "r3Td279LTrpSfWYkN0Q1dUIu1EdQnTpV",
          "width": 640
        }
      }
    },
    "media:uri_template": "https://static.sfomuseum.org/media/152/784/313/3/1527843133_{secret}_{label}.{extention}",
    "sfomuseum:filename": "2008.007.006_front.tif",
    "sfomuseum:image_index": 5,
    "sfomuseum:image_type": "studio",
    "sfomuseum:placetype": "image",
    "sfomuseum:primary_image": 1,
    "wof:depicts": [
      1159285415,
      1511930821,
      1159288779
    ],
    "wof:name": "menu: United Air Lines",
    "wof:placetype": "custom",
    "wof:placetype_alt": "image"
  },
  "geometry": {"coordinates":[-122.386155,37.616358],"type":"Point"}
}
