{
  "type": "Feature",
  "properties": {
    "iso:country": "XX",
    "media:fingerprint": "60e5e78483cbd5b6561678412aac5a09f5e1cdf8",
    "media:imagehash_avg": "a:808080c0fcffffff",
    "media:imagehash_diff": "d:000030326068f0f8",
    "media:medium": "image",
    "media:mimetype": "image/tiff",
    "media:properties": {
      "colours": [
        {
          "hex": "#868686",
          "name": "#868686",
          "reference": "vibrant"
        }, 
        {
          "hex": "#b8b8b8",
          "name": "#b8b8b8",
          "reference": "vibrant"
        }, 
        {
          "hex": "#484848",
          "name": "#484848",
          "reference": "vibrant"
        }
      ],
      "sizes": {
        "b": {
          "extension": "jpg",
          "height": 768,
          "mimetype": "image/jpeg",
          "secret": "35JUVu3oOwUuKVAdUWBr53rO2NJC0GIU",
          "width": 972
        },
        "c": {
          "extension": "jpg",
          "height": 600,
          "mimetype": "image/jpeg",
          "secret": "35JUVu3oOwUuKVAdUWBr53rO2NJC0GIU",
          "width": 759
        },
        "dc": {
          "extension": "jpg",
          "height": 600,
          "mimetype": "image/jpeg",
          "secret": "35JUVu3oOwUuKVAdUWBr53rO2NJC0GIU",
          "width": 759
        },
        "ds": {
          "extension": "jpg",
          "height": 320,
          "mimetype": "image/jpeg",
          "secret": "35JUVu3oOwUuKVAdUWBr53rO2NJC0GIU",
          "width": 320
        },
        "k": {
          "extension": "jpg",
          "height": 1536,
          "mimetype": "image/jpeg",
          "secret": "35JUVu3oOwUuKVAdUWBr53rO2NJC0GIU",
          "width": 1944
        },
        "n": {
          "extension": "jpg",
          "height": 240,
          "mimetype": "image/jpeg",
          "secret": "35JUVu3oOwUuKVAdUWBr53rO2NJC0GIU",
          "width": 303
        },
        "o": {
          "extension": "jpg",
          "height": 2154,
          "mimetype": "image/jpeg",
          "secret": "TwMoOKgyQr18EmK8WzTCF9CjnU0tOCh0",
          "width": 2727
        },
        "s": {
          "extension": "jpg",
          "height": 320,
          "mimetype": "image/jpeg",
          "secret": "35JUVu3oOwUuKVAdUWBr53rO2NJC0GIU",
          "width": 320
        },
        "z": {
          "extension": "jpg",
          "height": 480,
          "mimetype": "image/jpeg",
          "secret": "35JUVu3oOwUuKVAdUWBr53rO2NJC0GIU",
          "width": 607
        }
      }
    },
    "media:uri_template": "https://millsfield.sfomuseum.org/media/152/782/401/3/1527824013_{secret}_{label}.{extention}",
    "sfomuseum:filename": "42226.tif",
    "sfomuseum:image_index": 5,
    "sfomuseum:placetype": "image",
    "sfomuseum:primary_image": 1,
    "wof:depicts": [
      1511945331
    ],
    "wof:name": "negative: San Francisco Bay Area, view of clouds",
    "wof:placetype": "media"
  },
  "geometry": {"coordinates":[-122.386155,37.616358],"type":"Point"}
}
