{
  "type": "Feature",
  "properties": {
    "iso:country": "XX",
    "media:fingerprint": "b58a37ad0140bd90de3cbc971a4e7a2192e99ecc",
    "media:imagehash_avg": "a:f3919181c18181ff",
    "media:imagehash_diff": "d:2763636313376767",
    "media:medium": "image",
    "media:mimetype": "image/jpeg",
    "media:properties": {
      "colours": [
        {
          "hex": "#d16545",
          "name": "#d16545",
          "reference": "vibrant"
        }, 
        {
          "hex": "#912111",
          "name": "#912111",
          "reference": "vibrant"
        }, 
        {
          "hex": "#ae6d53",
          "name": "#ae6d53",
          "reference": "vibrant"
        }, 
        {
          "hex": "#bda999",
          "name": "#bda999",
          "reference": "vibrant"
        }, 
        {
          "hex": "#232b43",
          "name": "#232b43",
          "reference": "vibrant"
        }
      ],
      "sizes": {
        "b": {
          "extension": "jpg",
          "height": 768,
          "mimetype": "image/jpeg",
          "secret": "e4OvJTUpeH0uynkGzOFUmchpNiUF47hz",
          "width": 636
        },
        "c": {
          "extension": "jpg",
          "height": 600,
          "mimetype": "image/jpeg",
          "secret": "e4OvJTUpeH0uynkGzOFUmchpNiUF47hz",
          "width": 497
        },
        "dc": {
          "extension": "jpg",
          "height": 600,
          "mimetype": "image/jpeg",
          "secret": "e4OvJTUpeH0uynkGzOFUmchpNiUF47hz",
          "width": 497
        },
        "ds": {
          "extension": "jpg",
          "height": 320,
          "mimetype": "image/jpeg",
          "secret": "e4OvJTUpeH0uynkGzOFUmchpNiUF47hz",
          "width": 320
        },
        "k": {
          "extension": "jpg",
          "height": 1536,
          "mimetype": "image/jpeg",
          "secret": "e4OvJTUpeH0uynkGzOFUmchpNiUF47hz",
          "width": 1273
        },
        "n": {
          "extension": "jpg",
          "height": 240,
          "mimetype": "image/jpeg",
          "secret": "e4OvJTUpeH0uynkGzOFUmchpNiUF47hz",
          "width": 199
        },
        "o": {
          "extension": "jpg",
          "height": 2648,
          "mimetype": "image/jpeg",
          "secret": "Q1FtUFQHoCqHFvKebtuiyCesZzfnPDA5",
          "width": 2196
        },
        "s": {
          "extension": "jpg",
          "height": 320,
          "mimetype": "image/jpeg",
          "secret": "e4OvJTUpeH0uynkGzOFUmchpNiUF47hz",
          "width": 320
        },
        "z": {
          "extension": "jpg",
          "height": 480,
          "mimetype": "image/jpeg",
          "secret": "e4OvJTUpeH0uynkGzOFUmchpNiUF47hz",
          "width": 398
        }
      }
    },
    "media:uri_template": "https://millsfield.sfomuseum.org/media/172/956/640/3/1729566403_{secret}_{label}.{extention}",
    "sfomuseum:filename": "97922.jpg",
    "sfomuseum:image_index": 5,
    "sfomuseum:placetype": "image",
    "sfomuseum:primary_image": 1,
    "wof:depicts": [
      1159285393, 
      1729564249
    ],
    "wof:name": "scrapbook: TWA (Trans World Airlines), Roberta Sturges Theurer",
    "wof:placetype": "media"
  },
  "geometry": {"coordinates":[-122.386155,37.616357],"type":"Point"}
}
