{
  "type": "Feature",
  "properties": {
    "iso:country": "XX",
    "media:fingerprint": "615edfa3c268bfff0f209673177f9320bd53cf90",
    "media:imagehash_avg": "a:f7e7c7c3c38181c3",
    "media:imagehash_diff": "d:4d0d0f0f135b1b13",
    "media:medium": "image",
    "media:mimetype": "image/tiff",
    "media:properties": {
      "colours": [
        {
          "hex": "#e8d8b7",
          "name": "#e8d8b7",
          "reference": "vibrant"
        }, 
        {
          "hex": "#0d1756",
          "name": "#0d1756",
          "reference": "vibrant"
        }, 
        {
          "hex": "#978e72",
          "name": "#978e72",
          "reference": "vibrant"
        }, 
        {
          "hex": "#d8cdb3",
          "name": "#d8cdb3",
          "reference": "vibrant"
        }, 
        {
          "hex": "#665835",
          "name": "#665835",
          "reference": "vibrant"
        }
      ],
      "sizes": {
        "b": {
          "extension": "jpg",
          "height": 581,
          "mimetype": "image/jpeg",
          "secret": "rhnGfusgI3zFvtoT3wtgZH2VxVFYAGYH",
          "width": 1024
        },
        "c": {
          "extension": "jpg",
          "height": 454,
          "mimetype": "image/jpeg",
          "secret": "rhnGfusgI3zFvtoT3wtgZH2VxVFYAGYH",
          "width": 800
        },
        "dc": {
          "extension": "jpg",
          "height": 454,
          "mimetype": "image/jpeg",
          "secret": "rhnGfusgI3zFvtoT3wtgZH2VxVFYAGYH",
          "width": 800
        },
        "ds": {
          "extension": "jpg",
          "height": 320,
          "mimetype": "image/jpeg",
          "secret": "rhnGfusgI3zFvtoT3wtgZH2VxVFYAGYH",
          "width": 320
        },
        "k": {
          "extension": "jpg",
          "height": 1163,
          "mimetype": "image/jpeg",
          "secret": "rhnGfusgI3zFvtoT3wtgZH2VxVFYAGYH",
          "width": 2048
        },
        "n": {
          "extension": "jpg",
          "height": 181,
          "mimetype": "image/jpeg",
          "secret": "rhnGfusgI3zFvtoT3wtgZH2VxVFYAGYH",
          "width": 320
        },
        "o": {
          "extension": "jpg",
          "height": 1120,
          "mimetype": "image/jpeg",
          "secret": "NukdzHUOQzbDlRdsn95pkMKnoWSH89CT",
          "width": 1971
        },
        "s": {
          "extension": "jpg",
          "height": 320,
          "mimetype": "image/jpeg",
          "secret": "rhnGfusgI3zFvtoT3wtgZH2VxVFYAGYH",
          "width": 320
        },
        "z": {
          "extension": "jpg",
          "height": 363,
          "mimetype": "image/jpeg",
          "secret": "rhnGfusgI3zFvtoT3wtgZH2VxVFYAGYH",
          "width": 640
        }
      }
    },
    "media:uri_template": "https://millsfield.sfomuseum.org/media/152/782/932/9/1527829329_{secret}_{label}.{extention}",
    "sfomuseum:filename": "48189.tif",
    "sfomuseum:image_index": 5,
    "sfomuseum:placetype": "image",
    "sfomuseum:primary_image": 0,
    "wof:depicts": [
      1511906935
    ],
    "wof:name": "airmail flight cover: Pan American World Airways, FAM-14, Guam - Shanghai route",
    "wof:placetype": "media"
  },
  "geometry": {"coordinates":[-122.386155,37.616358],"type":"Point"}
}
