{
  "type": "Feature",
  "properties": {
    "iso:country": "XX",
    "media:fingerprint": "a60639c1e6636380878db1c319b1f3a1cb65b740",
    "media:imagehash_avg": "a:42e6fefefe9af800",
    "media:imagehash_diff": "d:cc8eb2b2b232a28e",
    "media:medium": "image",
    "media:mimetype": "image/tiff",
    "media:properties": {
      "colours": [
        {
          "hex": "#cc2628",
          "name": "#cc2628",
          "reference": "vibrant"
        },
        {
          "hex": "#dbaf98",
          "name": "#dbaf98",
          "reference": "vibrant"
        },
        {
          "hex": "#633e12",
          "name": "#633e12",
          "reference": "vibrant"
        },
        {
          "hex": "#a46e47",
          "name": "#a46e47",
          "reference": "vibrant"
        },
        {
          "hex": "#cdbea4",
          "name": "#cdbea4",
          "reference": "vibrant"
        }
      ],
      "sizes": {
        "b": {
          "extension": "jpg",
          "height": 702,
          "mimetype": "image/jpeg",
          "secret": "dLZ5lOUw8Idgc97k3a0757xsUlOFP5mP",
          "width": 1024
        },
        "c": {
          "extension": "jpg",
          "height": 549,
          "mimetype": "image/jpeg",
          "secret": "dLZ5lOUw8Idgc97k3a0757xsUlOFP5mP",
          "width": 800
        },
        "dc": {
          "extension": "jpg",
          "height": 549,
          "mimetype": "image/jpeg",
          "secret": "dLZ5lOUw8Idgc97k3a0757xsUlOFP5mP",
          "width": 800
        },
        "ds": {
          "extension": "jpg",
          "height": 320,
          "mimetype": "image/jpeg",
          "secret": "dLZ5lOUw8Idgc97k3a0757xsUlOFP5mP",
          "width": 320
        },
        "k": {
          "extension": "jpg",
          "height": 1405,
          "mimetype": "image/jpeg",
          "secret": "dLZ5lOUw8Idgc97k3a0757xsUlOFP5mP",
          "width": 2048
        },
        "n": {
          "extension": "jpg",
          "height": 219,
          "mimetype": "image/jpeg",
          "secret": "dLZ5lOUw8Idgc97k3a0757xsUlOFP5mP",
          "width": 320
        },
        "o": {
          "extension": "jpg",
          "height": 1456,
          "mimetype": "image/jpeg",
          "secret": "tWzYIRMlVs8ZOxbBVesmHn7sdgUDWN5d",
          "width": 2121
        },
        "s": {
          "extension": "jpg",
          "height": 320,
          "mimetype": "image/jpeg",
          "secret": "dLZ5lOUw8Idgc97k3a0757xsUlOFP5mP",
          "width": 320
        },
        "z": {
          "extension": "jpg",
          "height": 439,
          "mimetype": "image/jpeg",
          "secret": "dLZ5lOUw8Idgc97k3a0757xsUlOFP5mP",
          "width": 640
        }
      }
    },
    "media:uri_template": "https://static.sfomuseum.org/media/152/785/027/3/1527850273_{secret}_{label}.{extention}",
    "sfomuseum:filename": "2006059165001_insi.tif",
    "sfomuseum:image_index": 5,
    "sfomuseum:image_type": "studio",
    "sfomuseum:placetype": "image",
    "sfomuseum:primary_image": 0,
    "wof:depicts": [
      1159287531,
      1511928509,
      1159285393
    ],
    "wof:name": "menu: TWA (Trans World Airlines)",
    "wof:placetype": "custom",
    "wof:placetype_alt": "image"
  },
  "geometry": {"coordinates":[-122.386155,37.616358],"type":"Point"}
}
