{
  "type": "Feature",
  "properties": {
    "iso:country": "XX",
    "media:fingerprint": "6809f1069237a37eba247475c65f3c40df8fb67c",
    "media:imagehash_avg": "a:fffff8b0f0200000",
    "media:imagehash_diff": "d:60e0606040405888",
    "media:medium": "image",
    "media:mimetype": "image/tiff",
    "media:properties": {
      "colours": [
        {
          "hex": "#868686",
          "name": "#868686",
          "reference": "vibrant"
        }, 
        {
          "hex": "#b8b8b8",
          "name": "#b8b8b8",
          "reference": "vibrant"
        }, 
        {
          "hex": "#484848",
          "name": "#484848",
          "reference": "vibrant"
        }
      ],
      "sizes": {
        "b": {
          "extension": "jpg",
          "height": 767,
          "mimetype": "image/jpeg",
          "secret": "JY62Q4TKjXYq5a8ACxCVRfreAe09tqgL",
          "width": 978
        },
        "c": {
          "extension": "jpg",
          "height": 600,
          "mimetype": "image/jpeg",
          "secret": "JY62Q4TKjXYq5a8ACxCVRfreAe09tqgL",
          "width": 764
        },
        "dc": {
          "extension": "jpg",
          "height": 600,
          "mimetype": "image/jpeg",
          "secret": "JY62Q4TKjXYq5a8ACxCVRfreAe09tqgL",
          "width": 764
        },
        "ds": {
          "extension": "jpg",
          "height": 320,
          "mimetype": "image/jpeg",
          "secret": "JY62Q4TKjXYq5a8ACxCVRfreAe09tqgL",
          "width": 320
        },
        "k": {
          "extension": "jpg",
          "height": 1535,
          "mimetype": "image/jpeg",
          "secret": "JY62Q4TKjXYq5a8ACxCVRfreAe09tqgL",
          "width": 1957
        },
        "n": {
          "extension": "jpg",
          "height": 240,
          "mimetype": "image/jpeg",
          "secret": "JY62Q4TKjXYq5a8ACxCVRfreAe09tqgL",
          "width": 305
        },
        "o": {
          "extension": "jpg",
          "height": 2140,
          "mimetype": "image/jpeg",
          "secret": "Io8yKRJWkZkNjIJdTjV5KbmThxZs6OSD",
          "width": 2727
        },
        "s": {
          "extension": "jpg",
          "height": 320,
          "mimetype": "image/jpeg",
          "secret": "JY62Q4TKjXYq5a8ACxCVRfreAe09tqgL",
          "width": 320
        },
        "z": {
          "extension": "jpg",
          "height": 480,
          "mimetype": "image/jpeg",
          "secret": "JY62Q4TKjXYq5a8ACxCVRfreAe09tqgL",
          "width": 611
        }
      }
    },
    "media:uri_template": "https://millsfield.sfomuseum.org/media/152/782/313/1/1527823131_{secret}_{label}.{extention}",
    "sfomuseum:filename": "41248.tif",
    "sfomuseum:image_index": 5,
    "sfomuseum:placetype": "image",
    "sfomuseum:primary_image": 1,
    "wof:depicts": [
      1511945029
    ],
    "wof:name": "negative: San Francisco International Airport (SFO), aerial",
    "wof:placetype": "media"
  },
  "geometry": {"coordinates":[-122.386155,37.616358],"type":"Point"}
}
