{
  "type": "Feature",
  "properties": {
    "iso:country": "XX",
    "media:fingerprint": "9d00f04353d98742d8dfd179320fcc0b57d010ad",
    "media:imagehash_avg": "a:7d7f7f67677e6700",
    "media:imagehash_diff": "d:e5e5e58dccec8691",
    "media:medium": "image",
    "media:mimetype": "image/tiff",
    "media:properties": {
      "colours": [
        {
          "hex": "#e84938",
          "name": "#e84938",
          "reference": "vibrant"
        }, 
        {
          "hex": "#f38378",
          "name": "#f38378",
          "reference": "vibrant"
        }, 
        {
          "hex": "#6d7c8c",
          "name": "#6d7c8c",
          "reference": "vibrant"
        }, 
        {
          "hex": "#c6b2a5",
          "name": "#c6b2a5",
          "reference": "vibrant"
        }, 
        {
          "hex": "#5e5951",
          "name": "#5e5951",
          "reference": "vibrant"
        }
      ],
      "sizes": {
        "b": {
          "extension": "jpg",
          "height": 768,
          "mimetype": "image/jpeg",
          "secret": "XYJuUQXuLYIPanrg9ayx3nPDrA4xIgKp",
          "width": 418
        },
        "c": {
          "extension": "jpg",
          "height": 600,
          "mimetype": "image/jpeg",
          "secret": "XYJuUQXuLYIPanrg9ayx3nPDrA4xIgKp",
          "width": 327
        },
        "dc": {
          "extension": "jpg",
          "height": 600,
          "mimetype": "image/jpeg",
          "secret": "XYJuUQXuLYIPanrg9ayx3nPDrA4xIgKp",
          "width": 327
        },
        "ds": {
          "extension": "jpg",
          "height": 320,
          "mimetype": "image/jpeg",
          "secret": "XYJuUQXuLYIPanrg9ayx3nPDrA4xIgKp",
          "width": 320
        },
        "k": {
          "extension": "jpg",
          "height": 1536,
          "mimetype": "image/jpeg",
          "secret": "XYJuUQXuLYIPanrg9ayx3nPDrA4xIgKp",
          "width": 837
        },
        "n": {
          "extension": "jpg",
          "height": 240,
          "mimetype": "image/jpeg",
          "secret": "XYJuUQXuLYIPanrg9ayx3nPDrA4xIgKp",
          "width": 130
        },
        "o": {
          "extension": "jpg",
          "height": 2891,
          "mimetype": "image/jpeg",
          "secret": "Me4KAGedlbv0kQDrV7GeOec1M28D1pl8",
          "width": 1577
        },
        "s": {
          "extension": "jpg",
          "height": 320,
          "mimetype": "image/jpeg",
          "secret": "XYJuUQXuLYIPanrg9ayx3nPDrA4xIgKp",
          "width": 320
        },
        "z": {
          "extension": "jpg",
          "height": 480,
          "mimetype": "image/jpeg",
          "secret": "XYJuUQXuLYIPanrg9ayx3nPDrA4xIgKp",
          "width": 261
        }
      }
    },
    "media:uri_template": "https://millsfield.sfomuseum.org/media/152/782/364/1/1527823641_{secret}_{label}.{extention}",
    "sfomuseum:filename": "41698.tif",
    "sfomuseum:image_index": 5,
    "sfomuseum:placetype": "image",
    "sfomuseum:primary_image": 0,
    "wof:depicts": [
      1511908473
    ],
    "wof:name": "airsickness bag: British Midland Airways",
    "wof:placetype": "media"
  },
  "geometry": {"coordinates":[-122.386155,37.616358],"type":"Point"}
}
