{
  "type": "Feature",
  "properties": {
    "iso:country": "US",
    "media:fingerprint": "b8b3f78d573746d9621bd1475906a6fea7f7c731",
    "media:imagehash_avg": "a:f3838b8b930303f3",
    "media:imagehash_diff": "d:06323b3b23331fa3",
    "media:medium": "image",
    "media:mimetype": "image/jpeg",
    "media:properties": {
      "colours": [
        {
          "hex": "#808080",
          "name": "#808080",
          "reference": "vibrant"
        }, 
        {
          "hex": "#c0c0c0",
          "name": "#c0c0c0",
          "reference": "vibrant"
        }, 
        {
          "hex": "#404040",
          "name": "#404040",
          "reference": "vibrant"
        }
      ],
      "sizes": {
        "b": {
          "extension": "jpg",
          "height": 768,
          "mimetype": "image/jpeg",
          "secret": "tC4CNYCYo5xZbFMx4RtG8QmMJ2vNDVcV",
          "width": 525
        },
        "c": {
          "extension": "jpg",
          "height": 600,
          "mimetype": "image/jpeg",
          "secret": "tC4CNYCYo5xZbFMx4RtG8QmMJ2vNDVcV",
          "width": 410
        },
        "dc": {
          "extension": "jpg",
          "height": 600,
          "mimetype": "image/jpeg",
          "secret": "tC4CNYCYo5xZbFMx4RtG8QmMJ2vNDVcV",
          "width": 410
        },
        "ds": {
          "extension": "jpg",
          "height": 320,
          "mimetype": "image/jpeg",
          "secret": "tC4CNYCYo5xZbFMx4RtG8QmMJ2vNDVcV",
          "width": 320
        },
        "k": {
          "extension": "jpg",
          "height": 1536,
          "mimetype": "image/jpeg",
          "secret": "tC4CNYCYo5xZbFMx4RtG8QmMJ2vNDVcV",
          "width": 1051
        },
        "n": {
          "extension": "jpg",
          "height": 239,
          "mimetype": "image/jpeg",
          "secret": "tC4CNYCYo5xZbFMx4RtG8QmMJ2vNDVcV",
          "width": 164
        },
        "o": {
          "extension": "jpg",
          "height": 2928,
          "mimetype": "image/jpeg",
          "secret": "X2x7DJngdIPqQMNOwXMDyBcTD2VaHGtX",
          "width": 2004
        },
        "s": {
          "extension": "jpg",
          "height": 320,
          "mimetype": "image/jpeg",
          "secret": "tC4CNYCYo5xZbFMx4RtG8QmMJ2vNDVcV",
          "width": 320
        },
        "z": {
          "extension": "jpg",
          "height": 479,
          "mimetype": "image/jpeg",
          "secret": "tC4CNYCYo5xZbFMx4RtG8QmMJ2vNDVcV",
          "width": 328
        }
      }
    },
    "media:uri_template": "https://millsfield.sfomuseum.org/media/152/782/877/5/1527828775_{secret}_{label}.{extention}",
    "sfomuseum:filename": "46252.jpg",
    "sfomuseum:image_index": 5,
    "sfomuseum:placetype": "image",
    "sfomuseum:primary_image": 0,
    "wof:depicts": [
      1511921573
    ],
    "wof:name": "program: Official Souvenir Program, Aviation Meet (Tanforan - San Francisco)",
    "wof:placetype": "media"
  },
  "geometry": {"coordinates":[-122.386155,37.616358],"type":"Point"}
}
