{
  "type": "Feature",
  "properties": {
    "iso:country": "XX",
    "media:fingerprint": "6171b0e9f254173bdee1ac84a0558b1ab7249f08",
    "media:imagehash_avg": "a:fefefef9594e4200",
    "media:imagehash_diff": "d:a0aaaaabbb9a9e9e",
    "media:medium": "image",
    "media:mimetype": "image/tiff",
    "media:properties": {
      "colours": [
        {
          "hex": "#1f2a7f",
          "name": "#1f2a7f",
          "reference": "vibrant"
        }, 
        {
          "hex": "#1b2766",
          "name": "#1b2766",
          "reference": "vibrant"
        }, 
        {
          "hex": "#778273",
          "name": "#778273",
          "reference": "vibrant"
        }, 
        {
          "hex": "#b6c5ac",
          "name": "#b6c5ac",
          "reference": "vibrant"
        }, 
        {
          "hex": "#54553b",
          "name": "#54553b",
          "reference": "vibrant"
        }
      ],
      "sizes": {
        "b": {
          "extension": "jpg",
          "height": 654,
          "mimetype": "image/jpeg",
          "secret": "y2uyYVj27PgMT9LI30MX2jdTh362Odpi",
          "width": 1024
        },
        "c": {
          "extension": "jpg",
          "height": 511,
          "mimetype": "image/jpeg",
          "secret": "y2uyYVj27PgMT9LI30MX2jdTh362Odpi",
          "width": 800
        },
        "dc": {
          "extension": "jpg",
          "height": 511,
          "mimetype": "image/jpeg",
          "secret": "y2uyYVj27PgMT9LI30MX2jdTh362Odpi",
          "width": 800
        },
        "ds": {
          "extension": "jpg",
          "height": 320,
          "mimetype": "image/jpeg",
          "secret": "y2uyYVj27PgMT9LI30MX2jdTh362Odpi",
          "width": 320
        },
        "k": {
          "extension": "jpg",
          "height": 1309,
          "mimetype": "image/jpeg",
          "secret": "y2uyYVj27PgMT9LI30MX2jdTh362Odpi",
          "width": 2048
        },
        "n": {
          "extension": "jpg",
          "height": 204,
          "mimetype": "image/jpeg",
          "secret": "y2uyYVj27PgMT9LI30MX2jdTh362Odpi",
          "width": 320
        },
        "o": {
          "extension": "jpg",
          "height": 1063,
          "mimetype": "image/jpeg",
          "secret": "zM80B97EM1Q7e5KtLyXeHYOGb9TKAVP8",
          "width": 1663
        },
        "s": {
          "extension": "jpg",
          "height": 320,
          "mimetype": "image/jpeg",
          "secret": "y2uyYVj27PgMT9LI30MX2jdTh362Odpi",
          "width": 320
        },
        "z": {
          "extension": "jpg",
          "height": 409,
          "mimetype": "image/jpeg",
          "secret": "y2uyYVj27PgMT9LI30MX2jdTh362Odpi",
          "width": 640
        }
      }
    },
    "media:uri_template": "https://millsfield.sfomuseum.org/media/152/782/843/7/1527828437_{secret}_{label}.{extention}",
    "sfomuseum:filename": "44598.tif",
    "sfomuseum:image_index": 5,
    "sfomuseum:placetype": "image",
    "sfomuseum:primary_image": 1,
    "wof:depicts": [
      1511949469
    ],
    "wof:name": "negative: San Francisco International Airport (SFO), medical clinic",
    "wof:placetype": "media"
  },
  "geometry": {"coordinates":[-122.386155,37.616358],"type":"Point"}
}
