{
  "type": "Feature",
  "properties": {
    "iso:country": "XX",
    "media:fingerprint": "79bc8d0fd2fb9c122736a2d7715a2d42e09de619",
    "media:imagehash_avg": "a:ffffffc080000080",
    "media:imagehash_diff": "d:e6fc121307067e7e",
    "media:medium": "image",
    "media:mimetype": "image/tiff",
    "media:properties": {
      "colours": [
        {
          "hex": "#808080",
          "name": "#808080",
          "reference": "vibrant"
        }, 
        {
          "hex": "#b8b8b8",
          "name": "#b8b8b8",
          "reference": "vibrant"
        }, 
        {
          "hex": "#404040",
          "name": "#404040",
          "reference": "vibrant"
        }
      ],
      "sizes": {
        "b": {
          "extension": "jpg",
          "height": 745,
          "mimetype": "image/jpeg",
          "secret": "1KjqkcgN5x85nvgParFG30xQi5nwHaWJ",
          "width": 1024
        },
        "c": {
          "extension": "jpg",
          "height": 582,
          "mimetype": "image/jpeg",
          "secret": "1KjqkcgN5x85nvgParFG30xQi5nwHaWJ",
          "width": 800
        },
        "dc": {
          "extension": "jpg",
          "height": 582,
          "mimetype": "image/jpeg",
          "secret": "1KjqkcgN5x85nvgParFG30xQi5nwHaWJ",
          "width": 800
        },
        "ds": {
          "extension": "jpg",
          "height": 320,
          "mimetype": "image/jpeg",
          "secret": "1KjqkcgN5x85nvgParFG30xQi5nwHaWJ",
          "width": 320
        },
        "k": {
          "extension": "jpg",
          "height": 1490,
          "mimetype": "image/jpeg",
          "secret": "1KjqkcgN5x85nvgParFG30xQi5nwHaWJ",
          "width": 2048
        },
        "n": {
          "extension": "jpg",
          "height": 232,
          "mimetype": "image/jpeg",
          "secret": "1KjqkcgN5x85nvgParFG30xQi5nwHaWJ",
          "width": 320
        },
        "o": {
          "extension": "jpg",
          "height": 6054,
          "mimetype": "image/jpeg",
          "secret": "eqe1IGj0MW8dqLH72y9FgBYo8s8PjBhG",
          "width": 8318
        },
        "s": {
          "extension": "jpg",
          "height": 320,
          "mimetype": "image/jpeg",
          "secret": "1KjqkcgN5x85nvgParFG30xQi5nwHaWJ",
          "width": 320
        },
        "z": {
          "extension": "jpg",
          "height": 465,
          "mimetype": "image/jpeg",
          "secret": "1KjqkcgN5x85nvgParFG30xQi5nwHaWJ",
          "width": 640
        }
      }
    },
    "media:uri_template": "https://millsfield.sfomuseum.org/media/152/782/144/7/1527821447_{secret}_{label}.{extention}",
    "sfomuseum:filename": "38753.tif",
    "sfomuseum:image_index": 5,
    "sfomuseum:placetype": "image",
    "sfomuseum:primary_image": 1,
    "wof:depicts": [
      1511949881
    ],
    "wof:name": "negative: San Francisco Airport, Hangar No. 1",
    "wof:placetype": "media"
  },
  "geometry": {"coordinates":[-122.386155,37.616358],"type":"Point"}
}
