{
  "type": "Feature",
  "properties": {
    "iso:country": "XX",
    "media:fingerprint": "a76e1c2550ff33fd04b9ed1c57207704034ba027",
    "media:imagehash_avg": "a:0203321a2820fcff",
    "media:imagehash_diff": "d:4666667648c94851",
    "media:medium": "image",
    "media:mimetype": "image/tiff",
    "media:properties": {
      "colours": [
        {
          "hex": "#d7a932",
          "name": "#d7a932",
          "reference": "vibrant"
        }, 
        {
          "hex": "#f8eedd",
          "name": "#f8eedd",
          "reference": "vibrant"
        }, 
        {
          "hex": "#643c21",
          "name": "#643c21",
          "reference": "vibrant"
        }, 
        {
          "hex": "#957153",
          "name": "#957153",
          "reference": "vibrant"
        }, 
        {
          "hex": "#cbbbb1",
          "name": "#cbbbb1",
          "reference": "vibrant"
        }
      ],
      "sizes": {
        "b": {
          "extension": "jpg",
          "height": 768,
          "mimetype": "image/jpeg",
          "secret": "cOuclO8VKlcAaHJwatS9RPBm04mkS7jI",
          "width": 557
        },
        "c": {
          "extension": "jpg",
          "height": 600,
          "mimetype": "image/jpeg",
          "secret": "cOuclO8VKlcAaHJwatS9RPBm04mkS7jI",
          "width": 435
        },
        "dc": {
          "extension": "jpg",
          "height": 600,
          "mimetype": "image/jpeg",
          "secret": "cOuclO8VKlcAaHJwatS9RPBm04mkS7jI",
          "width": 435
        },
        "ds": {
          "extension": "jpg",
          "height": 320,
          "mimetype": "image/jpeg",
          "secret": "cOuclO8VKlcAaHJwatS9RPBm04mkS7jI",
          "width": 320
        },
        "k": {
          "extension": "jpg",
          "height": 1536,
          "mimetype": "image/jpeg",
          "secret": "cOuclO8VKlcAaHJwatS9RPBm04mkS7jI",
          "width": 1114
        },
        "n": {
          "extension": "jpg",
          "height": 240,
          "mimetype": "image/jpeg",
          "secret": "cOuclO8VKlcAaHJwatS9RPBm04mkS7jI",
          "width": 174
        },
        "o": {
          "extension": "jpg",
          "height": 3324,
          "mimetype": "image/jpeg",
          "secret": "ZbcfIrwiMc6bfV3hKfhfV2TDAIFo85z9",
          "width": 2411
        },
        "s": {
          "extension": "jpg",
          "height": 320,
          "mimetype": "image/jpeg",
          "secret": "cOuclO8VKlcAaHJwatS9RPBm04mkS7jI",
          "width": 320
        },
        "z": {
          "extension": "jpg",
          "height": 480,
          "mimetype": "image/jpeg",
          "secret": "cOuclO8VKlcAaHJwatS9RPBm04mkS7jI",
          "width": 348
        }
      }
    },
    "media:uri_template": "https://millsfield.sfomuseum.org/media/152/781/944/1/1527819441_{secret}_{label}.{extention}",
    "sfomuseum:filename": "30522.tif",
    "sfomuseum:image_index": 5,
    "sfomuseum:placetype": "image",
    "sfomuseum:primary_image": 1,
    "wof:depicts": [
      1511956175
    ],
    "wof:name": "advertisement: Air France",
    "wof:placetype": "media"
  },
  "geometry": {"coordinates":[-122.386155,37.616358],"type":"Point"}
}
