{
  "type": "Feature",
  "properties": {
    "iso:country": "XX",
    "media:fingerprint": "3fc00a2e3fc0de1e7d7b54a05a375188d72c93af",
    "media:imagehash_avg": "a:007f7e763e3e3e20",
    "media:imagehash_diff": "d:d6c6c6c6c6decaea",
    "media:medium": "image",
    "media:mimetype": "image/tiff",
    "media:properties": {
      "colours": [
        {
          "hex": "#f4efe8",
          "name": "#f4efe8",
          "reference": "vibrant"
        }, 
        {
          "hex": "#697988",
          "name": "#697988",
          "reference": "vibrant"
        }, 
        {
          "hex": "#a9b8c2",
          "name": "#a9b8c2",
          "reference": "vibrant"
        }, 
        {
          "hex": "#474746",
          "name": "#474746",
          "reference": "vibrant"
        }
      ],
      "sizes": {
        "b": {
          "extension": "jpg",
          "height": 768,
          "mimetype": "image/jpeg",
          "secret": "Bs8F5nFIZxtScqL7UqcrX75XHOJx474b",
          "width": 505
        },
        "c": {
          "extension": "jpg",
          "height": 600,
          "mimetype": "image/jpeg",
          "secret": "Bs8F5nFIZxtScqL7UqcrX75XHOJx474b",
          "width": 394
        },
        "dc": {
          "extension": "jpg",
          "height": 600,
          "mimetype": "image/jpeg",
          "secret": "Bs8F5nFIZxtScqL7UqcrX75XHOJx474b",
          "width": 394
        },
        "ds": {
          "extension": "jpg",
          "height": 320,
          "mimetype": "image/jpeg",
          "secret": "Bs8F5nFIZxtScqL7UqcrX75XHOJx474b",
          "width": 320
        },
        "k": {
          "extension": "jpg",
          "height": 1536,
          "mimetype": "image/jpeg",
          "secret": "Bs8F5nFIZxtScqL7UqcrX75XHOJx474b",
          "width": 1010
        },
        "n": {
          "extension": "jpg",
          "height": 240,
          "mimetype": "image/jpeg",
          "secret": "Bs8F5nFIZxtScqL7UqcrX75XHOJx474b",
          "width": 157
        },
        "o": {
          "extension": "jpg",
          "height": 2772,
          "mimetype": "image/jpeg",
          "secret": "sf8dihUmuj34cU2jOkL1fem845LayjIT",
          "width": 1824
        },
        "s": {
          "extension": "jpg",
          "height": 320,
          "mimetype": "image/jpeg",
          "secret": "Bs8F5nFIZxtScqL7UqcrX75XHOJx474b",
          "width": 320
        },
        "z": {
          "extension": "jpg",
          "height": 480,
          "mimetype": "image/jpeg",
          "secret": "Bs8F5nFIZxtScqL7UqcrX75XHOJx474b",
          "width": 315
        }
      }
    },
    "media:uri_template": "https://millsfield.sfomuseum.org/media/152/782/353/3/1527823533_{secret}_{label}.{extention}",
    "sfomuseum:filename": "41641.tif",
    "sfomuseum:image_index": 5,
    "sfomuseum:placetype": "image",
    "sfomuseum:primary_image": 0,
    "wof:depicts": [
      1511924551
    ],
    "wof:name": "airsickness bag / seat occupied: Alaska Airlines",
    "wof:placetype": "media"
  },
  "geometry": {"coordinates":[-122.386155,37.616358],"type":"Point"}
}
