{
  "type": "Feature",
  "properties": {
    "iso:country": "XX",
    "media:fingerprint": "b5dadca8659b30c614c28df90d25ab70a66639e9",
    "media:imagehash_avg": "a:fffdf1c181818181",
    "media:imagehash_diff": "d:01010307477d1f0f",
    "media:medium": "image",
    "media:mimetype": "image/tiff",
    "media:properties": {
      "colours": [
        {
          "hex": "#e6dbc6",
          "name": "#e6dbc6",
          "reference": "vibrant"
        },
        {
          "hex": "#90896f",
          "name": "#90896f",
          "reference": "vibrant"
        },
        {
          "hex": "#cbc6a8",
          "name": "#cbc6a8",
          "reference": "vibrant"
        },
        {
          "hex": "#554d38",
          "name": "#554d38",
          "reference": "vibrant"
        }
      ],
      "sizes": {
        "b": {
          "extension": "jpg",
          "height": 768,
          "mimetype": "image/jpeg",
          "secret": "CB4NKDjS9tpTDJyuSg7BZHyRktIdxf7g",
          "width": 483
        },
        "c": {
          "extension": "jpg",
          "height": 600,
          "mimetype": "image/jpeg",
          "secret": "CB4NKDjS9tpTDJyuSg7BZHyRktIdxf7g",
          "width": 378
        },
        "dc": {
          "extension": "jpg",
          "height": 600,
          "mimetype": "image/jpeg",
          "secret": "CB4NKDjS9tpTDJyuSg7BZHyRktIdxf7g",
          "width": 378
        },
        "ds": {
          "extension": "jpg",
          "height": 320,
          "mimetype": "image/jpeg",
          "secret": "CB4NKDjS9tpTDJyuSg7BZHyRktIdxf7g",
          "width": 320
        },
        "k": {
          "extension": "jpg",
          "height": 1536,
          "mimetype": "image/jpeg",
          "secret": "CB4NKDjS9tpTDJyuSg7BZHyRktIdxf7g",
          "width": 967
        },
        "n": {
          "extension": "jpg",
          "height": 239,
          "mimetype": "image/jpeg",
          "secret": "CB4NKDjS9tpTDJyuSg7BZHyRktIdxf7g",
          "width": 151
        },
        "o": {
          "extension": "jpg",
          "height": 1768,
          "mimetype": "image/jpeg",
          "secret": "ydJC18HpJEocKtMpNhWqBknoO8GERkKG",
          "width": 1114
        },
        "s": {
          "extension": "jpg",
          "height": 320,
          "mimetype": "image/jpeg",
          "secret": "CB4NKDjS9tpTDJyuSg7BZHyRktIdxf7g",
          "width": 320
        },
        "z": {
          "extension": "jpg",
          "height": 479,
          "mimetype": "image/jpeg",
          "secret": "CB4NKDjS9tpTDJyuSg7BZHyRktIdxf7g",
          "width": 302
        }
      }
    },
    "media:uri_template": "https://static.sfomuseum.org/media/152/785/547/5/1527855475_{secret}_{label}.{extention}",
    "sfomuseum:filename": "2010.174.237.tif",
    "sfomuseum:image_index": 5,
    "sfomuseum:image_type": "studio",
    "sfomuseum:placetype": "image",
    "sfomuseum:primary_image": 1,
    "wof:depicts": [
      1511942235
    ],
    "wof:name": "photograph: San Francisco Bay Area aerial, two men in grounded biplane",
    "wof:placetype": "custom",
    "wof:placetype_alt": "image"
  },
  "geometry": {"coordinates":[-122.386155,37.616358],"type":"Point"}
}
