{
  "type": "Feature",
  "properties": {
    "iso:country": "XX",
    "media:fingerprint": "e9b4702c0882631607ef105a5e30353a1852dd4e",
    "media:imagehash_avg": "a:00feffe7e3e1e060",
    "media:imagehash_diff": "d:e0d89c1e9f83c3c1",
    "media:medium": "image",
    "media:mimetype": "image/tiff",
    "media:properties": {
      "colours": [
        {
          "hex": "#808080",
          "name": "#808080",
          "reference": "vibrant"
        }, 
        {
          "hex": "#bababa",
          "name": "#bababa",
          "reference": "vibrant"
        }, 
        {
          "hex": "#484848",
          "name": "#484848",
          "reference": "vibrant"
        }
      ],
      "sizes": {
        "b": {
          "extension": "jpg",
          "height": 768,
          "mimetype": "image/jpeg",
          "secret": "WeyWu3VKgXbVreRUjDekaLO0MXDjnGzC",
          "width": 784
        },
        "c": {
          "extension": "jpg",
          "height": 600,
          "mimetype": "image/jpeg",
          "secret": "WeyWu3VKgXbVreRUjDekaLO0MXDjnGzC",
          "width": 613
        },
        "dc": {
          "extension": "jpg",
          "height": 600,
          "mimetype": "image/jpeg",
          "secret": "WeyWu3VKgXbVreRUjDekaLO0MXDjnGzC",
          "width": 613
        },
        "ds": {
          "extension": "jpg",
          "height": 320,
          "mimetype": "image/jpeg",
          "secret": "WeyWu3VKgXbVreRUjDekaLO0MXDjnGzC",
          "width": 320
        },
        "k": {
          "extension": "jpg",
          "height": 1536,
          "mimetype": "image/jpeg",
          "secret": "WeyWu3VKgXbVreRUjDekaLO0MXDjnGzC",
          "width": 1569
        },
        "n": {
          "extension": "jpg",
          "height": 240,
          "mimetype": "image/jpeg",
          "secret": "WeyWu3VKgXbVreRUjDekaLO0MXDjnGzC",
          "width": 245
        },
        "o": {
          "extension": "jpg",
          "height": 1672,
          "mimetype": "image/jpeg",
          "secret": "r8ucNxhxYCNdEPBpEvTUJcJkxPn0KF8z",
          "width": 1709
        },
        "s": {
          "extension": "jpg",
          "height": 320,
          "mimetype": "image/jpeg",
          "secret": "WeyWu3VKgXbVreRUjDekaLO0MXDjnGzC",
          "width": 320
        },
        "z": {
          "extension": "jpg",
          "height": 480,
          "mimetype": "image/jpeg",
          "secret": "WeyWu3VKgXbVreRUjDekaLO0MXDjnGzC",
          "width": 490
        }
      }
    },
    "media:uri_template": "https://millsfield.sfomuseum.org/media/152/782/627/1/1527826271_{secret}_{label}.{extention}",
    "sfomuseum:filename": "43566.tif",
    "sfomuseum:image_index": 5,
    "sfomuseum:placetype": "image",
    "sfomuseum:primary_image": 1,
    "wof:depicts": [
      1511947311
    ],
    "wof:name": "negative: San Francisco International Airport (SFO), construction",
    "wof:placetype": "media"
  },
  "geometry": {"coordinates":[-122.386155,37.616358],"type":"Point"}
}
