{
  "type": "Feature",
  "properties": {
    "date:cessation_lower": "1970-01-01",
    "date:cessation_upper": "1970-12-31",
    "date:inception_lower": "1970-01-01",
    "date:inception_upper": "1970-12-31",
    "iso:country": "XX",
    "media:medium": "image",
    "millsfield:exhibition_ids": [
      1159160381
    ],
    "millsfield:on_view": 0,
    "sfomuseum:filename": "2012.042.136.tif",
    "sfomuseum:image_index": 5,
    "sfomuseum:image_type": "studio",
    "sfomuseum:placetype": "image",
    "sfomuseum:primary_image": 1,
    "wof:depicts": [
      1729564835,
      1159288387,
      1159285345
    ],
    "wof:name": "ticket: Trans Australia Airlines (TAA)",
    "wof:placetype": "custom",
    "wof:placetype_alt": "image"
  },
  "geometry": {"coordinates":[-122.386155,37.616357],"type":"Point"}
}
