{
  "type": "Feature",
  "properties": {
    "iso:country": "XX",
    "media:fingerprint": "f71ea6d445b300a522a7b3965cc6142ad196ab35",
    "media:imagehash_avg": "a:81081c3e7e3e3081",
    "media:imagehash_diff": "d:3b717070e468632f",
    "media:medium": "image",
    "media:mimetype": "image/tiff",
    "media:properties": {
      "colours": [
        {
          "hex": "#c88820",
          "name": "#c88820",
          "reference": "vibrant"
        }, 
        {
          "hex": "#e5d9bf",
          "name": "#e5d9bf",
          "reference": "vibrant"
        }, 
        {
          "hex": "#713406",
          "name": "#713406",
          "reference": "vibrant"
        }, 
        {
          "hex": "#778991",
          "name": "#778991",
          "reference": "vibrant"
        }, 
        {
          "hex": "#ccc2a6",
          "name": "#ccc2a6",
          "reference": "vibrant"
        }
      ],
      "sizes": {
        "b": {
          "extension": "jpg",
          "height": 657,
          "mimetype": "image/jpeg",
          "secret": "5yByYWuOMANqJSa3oSodFJvNgvuJ4amJ",
          "width": 1024
        },
        "c": {
          "extension": "jpg",
          "height": 513,
          "mimetype": "image/jpeg",
          "secret": "5yByYWuOMANqJSa3oSodFJvNgvuJ4amJ",
          "width": 800
        },
        "dc": {
          "extension": "jpg",
          "height": 513,
          "mimetype": "image/jpeg",
          "secret": "5yByYWuOMANqJSa3oSodFJvNgvuJ4amJ",
          "width": 800
        },
        "ds": {
          "extension": "jpg",
          "height": 320,
          "mimetype": "image/jpeg",
          "secret": "5yByYWuOMANqJSa3oSodFJvNgvuJ4amJ",
          "width": 320
        },
        "k": {
          "extension": "jpg",
          "height": 1315,
          "mimetype": "image/jpeg",
          "secret": "5yByYWuOMANqJSa3oSodFJvNgvuJ4amJ",
          "width": 2048
        },
        "n": {
          "extension": "jpg",
          "height": 205,
          "mimetype": "image/jpeg",
          "secret": "5yByYWuOMANqJSa3oSodFJvNgvuJ4amJ",
          "width": 320
        },
        "o": {
          "extension": "jpg",
          "height": 1074,
          "mimetype": "image/jpeg",
          "secret": "XLKcCTVPpXr3wVpRgkUztln7J3J4VDV7",
          "width": 1672
        },
        "s": {
          "extension": "jpg",
          "height": 320,
          "mimetype": "image/jpeg",
          "secret": "5yByYWuOMANqJSa3oSodFJvNgvuJ4amJ",
          "width": 320
        },
        "z": {
          "extension": "jpg",
          "height": 411,
          "mimetype": "image/jpeg",
          "secret": "5yByYWuOMANqJSa3oSodFJvNgvuJ4amJ",
          "width": 640
        }
      }
    },
    "media:uri_template": "https://millsfield.sfomuseum.org/media/152/781/947/7/1527819477_{secret}_{label}.{extention}",
    "sfomuseum:filename": "30866.tif",
    "sfomuseum:image_index": 5,
    "sfomuseum:placetype": "image",
    "sfomuseum:primary_image": 0,
    "wof:depicts": [
      1511920177
    ],
    "wof:name": "flight information packet: American Airlines, Douglas DC-3",
    "wof:placetype": "media"
  },
  "geometry": {"coordinates":[-122.386155,37.616358],"type":"Point"}
}
