{
  "type": "Feature",
  "properties": {
    "iso:country": "XX",
    "media:fingerprint": "e0c056387f57645141ac99c0476798b4cb6ff801",
    "media:imagehash_avg": "a:1f0f3d1f1f010006",
    "media:imagehash_diff": "d:7c56e1f0f9f7e43c",
    "media:medium": "image",
    "media:mimetype": "image/tiff",
    "media:properties": {
      "colours": [
        {
          "hex": "#868686",
          "name": "#868686",
          "reference": "vibrant"
        }, 
        {
          "hex": "#c0c0c0",
          "name": "#c0c0c0",
          "reference": "vibrant"
        }, 
        {
          "hex": "#383838",
          "name": "#383838",
          "reference": "vibrant"
        }
      ],
      "sizes": {
        "b": {
          "extension": "jpg",
          "height": 768,
          "mimetype": "image/jpeg",
          "secret": "DiLdzsjMug681xNxZ2Sc6TZMsxJKBfCP",
          "width": 972
        },
        "c": {
          "extension": "jpg",
          "height": 600,
          "mimetype": "image/jpeg",
          "secret": "DiLdzsjMug681xNxZ2Sc6TZMsxJKBfCP",
          "width": 759
        },
        "dc": {
          "extension": "jpg",
          "height": 600,
          "mimetype": "image/jpeg",
          "secret": "DiLdzsjMug681xNxZ2Sc6TZMsxJKBfCP",
          "width": 759
        },
        "ds": {
          "extension": "jpg",
          "height": 320,
          "mimetype": "image/jpeg",
          "secret": "DiLdzsjMug681xNxZ2Sc6TZMsxJKBfCP",
          "width": 320
        },
        "k": {
          "extension": "jpg",
          "height": 1536,
          "mimetype": "image/jpeg",
          "secret": "DiLdzsjMug681xNxZ2Sc6TZMsxJKBfCP",
          "width": 1944
        },
        "n": {
          "extension": "jpg",
          "height": 240,
          "mimetype": "image/jpeg",
          "secret": "DiLdzsjMug681xNxZ2Sc6TZMsxJKBfCP",
          "width": 303
        },
        "o": {
          "extension": "jpg",
          "height": 2208,
          "mimetype": "image/jpeg",
          "secret": "YdmBP9BDbxieZs6zrczZ6RvfB2ahZ0Yd",
          "width": 2795
        },
        "s": {
          "extension": "jpg",
          "height": 320,
          "mimetype": "image/jpeg",
          "secret": "DiLdzsjMug681xNxZ2Sc6TZMsxJKBfCP",
          "width": 320
        },
        "z": {
          "extension": "jpg",
          "height": 480,
          "mimetype": "image/jpeg",
          "secret": "DiLdzsjMug681xNxZ2Sc6TZMsxJKBfCP",
          "width": 607
        }
      }
    },
    "media:uri_template": "https://millsfield.sfomuseum.org/media/152/782/097/5/1527820975_{secret}_{label}.{extention}",
    "sfomuseum:filename": "33266.tif",
    "sfomuseum:image_index": 5,
    "sfomuseum:placetype": "image",
    "sfomuseum:primary_image": 1,
    "wof:depicts": [
      1511931441
    ],
    "wof:name": "photograph: Pan American World Airways, Lockheed L-749 Constellation",
    "wof:placetype": "media"
  },
  "geometry": {"coordinates":[-122.386155,37.616358],"type":"Point"}
}
