{
  "type": "Feature",
  "properties": {
    "iso:country": "XX",
    "media:fingerprint": "0fc4d3b2e9f40641a0354658b7581837ea610a75",
    "media:imagehash_avg": "a:7f7f7f7f3c000000",
    "media:imagehash_diff": "d:f8f8f8f8f8f0e4f8",
    "media:medium": "image",
    "media:mimetype": "image/tiff",
    "media:properties": {
      "colours": [
        {
          "hex": "#987bc0",
          "name": "#987bc0",
          "reference": "vibrant"
        }, 
        {
          "hex": "#877e7d",
          "name": "#877e7d",
          "reference": "vibrant"
        }, 
        {
          "hex": "#c8b8b7",
          "name": "#c8b8b7",
          "reference": "vibrant"
        }, 
        {
          "hex": "#423d2d",
          "name": "#423d2d",
          "reference": "vibrant"
        }
      ],
      "sizes": {
        "b": {
          "extension": "jpg",
          "height": 664,
          "mimetype": "image/jpeg",
          "secret": "H5APu1pPCizvreK6326NQOQsBdOtm9dc",
          "width": 1024
        },
        "c": {
          "extension": "jpg",
          "height": 519,
          "mimetype": "image/jpeg",
          "secret": "H5APu1pPCizvreK6326NQOQsBdOtm9dc",
          "width": 800
        },
        "dc": {
          "extension": "jpg",
          "height": 519,
          "mimetype": "image/jpeg",
          "secret": "H5APu1pPCizvreK6326NQOQsBdOtm9dc",
          "width": 800
        },
        "ds": {
          "extension": "jpg",
          "height": 320,
          "mimetype": "image/jpeg",
          "secret": "H5APu1pPCizvreK6326NQOQsBdOtm9dc",
          "width": 320
        },
        "k": {
          "extension": "jpg",
          "height": 1329,
          "mimetype": "image/jpeg",
          "secret": "H5APu1pPCizvreK6326NQOQsBdOtm9dc",
          "width": 2048
        },
        "n": {
          "extension": "jpg",
          "height": 207,
          "mimetype": "image/jpeg",
          "secret": "H5APu1pPCizvreK6326NQOQsBdOtm9dc",
          "width": 320
        },
        "o": {
          "extension": "jpg",
          "height": 1009,
          "mimetype": "image/jpeg",
          "secret": "zbPGgIFCYmZi978rg6WCNXNLGLG7ZrGi",
          "width": 1554
        },
        "s": {
          "extension": "jpg",
          "height": 320,
          "mimetype": "image/jpeg",
          "secret": "H5APu1pPCizvreK6326NQOQsBdOtm9dc",
          "width": 320
        },
        "z": {
          "extension": "jpg",
          "height": 415,
          "mimetype": "image/jpeg",
          "secret": "H5APu1pPCizvreK6326NQOQsBdOtm9dc",
          "width": 640
        }
      }
    },
    "media:uri_template": "https://millsfield.sfomuseum.org/media/152/782/825/3/1527828253_{secret}_{label}.{extention}",
    "sfomuseum:filename": "44498.tif",
    "sfomuseum:image_index": 5,
    "sfomuseum:placetype": "image",
    "sfomuseum:primary_image": 1,
    "wof:depicts": [
      1511949287
    ],
    "wof:name": "negative: San Francisco International Airport (SFO), South Terminal",
    "wof:placetype": "media"
  },
  "geometry": {"coordinates":[-122.386155,37.616358],"type":"Point"}
}
