{
  "type": "Feature",
  "properties": {
    "iso:country": "XX",
    "media:fingerprint": "e63de8d29c672169980e905093dc8d122d9bb7ce",
    "media:imagehash_avg": "a:e7e7e3e1e0202c3c",
    "media:imagehash_diff": "d:cc96978342c8cc78",
    "media:medium": "image",
    "media:mimetype": "image/tiff",
    "media:properties": {
      "colours": [
        {
          "hex": "#987194",
          "name": "#987194",
          "reference": "vibrant"
        },
        {
          "hex": "#c6a0c3",
          "name": "#c6a0c3",
          "reference": "vibrant"
        },
        {
          "hex": "#593951",
          "name": "#593951",
          "reference": "vibrant"
        }
      ],
      "sizes": {
        "b": {
          "extension": "jpg",
          "height": 669,
          "mimetype": "image/jpeg",
          "secret": "i8wY4Zu6k3NpcZEni0BQbzCT9qowWVNt",
          "width": 1024
        },
        "c": {
          "extension": "jpg",
          "height": 523,
          "mimetype": "image/jpeg",
          "secret": "i8wY4Zu6k3NpcZEni0BQbzCT9qowWVNt",
          "width": 800
        },
        "dc": {
          "extension": "jpg",
          "height": 523,
          "mimetype": "image/jpeg",
          "secret": "i8wY4Zu6k3NpcZEni0BQbzCT9qowWVNt",
          "width": 800
        },
        "ds": {
          "extension": "jpg",
          "height": 320,
          "mimetype": "image/jpeg",
          "secret": "i8wY4Zu6k3NpcZEni0BQbzCT9qowWVNt",
          "width": 320
        },
        "k": {
          "extension": "jpg",
          "height": 1339,
          "mimetype": "image/jpeg",
          "secret": "i8wY4Zu6k3NpcZEni0BQbzCT9qowWVNt",
          "width": 2048
        },
        "n": {
          "extension": "jpg",
          "height": 209,
          "mimetype": "image/jpeg",
          "secret": "i8wY4Zu6k3NpcZEni0BQbzCT9qowWVNt",
          "width": 320
        },
        "o": {
          "extension": "jpg",
          "height": 1372,
          "mimetype": "image/jpeg",
          "secret": "jsMdZrcxvxOEpqOprtf81ndOVYmgXpAU",
          "width": 2097
        },
        "s": {
          "extension": "jpg",
          "height": 320,
          "mimetype": "image/jpeg",
          "secret": "i8wY4Zu6k3NpcZEni0BQbzCT9qowWVNt",
          "width": 320
        },
        "z": {
          "extension": "jpg",
          "height": 418,
          "mimetype": "image/jpeg",
          "secret": "i8wY4Zu6k3NpcZEni0BQbzCT9qowWVNt",
          "width": 640
        }
      }
    },
    "media:uri_template": "https://static.sfomuseum.org/media/152/783/105/5/1527831055_{secret}_{label}.{extention}",
    "sfomuseum:filename": "58093.tif",
    "sfomuseum:image_index": 5,
    "sfomuseum:image_type": "studio",
    "sfomuseum:placetype": "image",
    "sfomuseum:primary_image": 0,
    "wof:depicts": [
      1159284989,
      1511955163,
      1159286839
    ],
    "wof:name": "career history questionnaire: World Wings International, Sherry Morlock Parsons",
    "wof:placetype": "custom",
    "wof:placetype_alt": "image"
  },
  "geometry": {"coordinates":[-122.386155,37.616358],"type":"Point"}
}
