{
  "type": "Feature",
  "properties": {
    "iso:country": "XX",
    "media:fingerprint": "8f20b7aab6540e0c19372c6385da8f566d83c30b",
    "media:imagehash_avg": "a:fffff78181e3e7ff",
    "media:imagehash_diff": "d:44c6070f170f0f0f",
    "media:medium": "image",
    "media:mimetype": "image/tiff",
    "media:properties": {
      "colours": [
        {
          "hex": "#cd9f47",
          "name": "#cd9f47",
          "reference": "vibrant"
        },
        {
          "hex": "#e0c68e",
          "name": "#e0c68e",
          "reference": "vibrant"
        },
        {
          "hex": "#661910",
          "name": "#661910",
          "reference": "vibrant"
        },
        {
          "hex": "#b39050",
          "name": "#b39050",
          "reference": "vibrant"
        },
        {
          "hex": "#a8a8a8",
          "name": "#a8a8a8",
          "reference": "vibrant"
        }
      ],
      "sizes": {
        "b": {
          "extension": "jpg",
          "height": 768,
          "mimetype": "image/jpeg",
          "secret": "9e3CFXV4t5vXBEZ0P5N40RYWCoPNxGCE",
          "width": 965
        },
        "c": {
          "extension": "jpg",
          "height": 600,
          "mimetype": "image/jpeg",
          "secret": "9e3CFXV4t5vXBEZ0P5N40RYWCoPNxGCE",
          "width": 754
        },
        "dc": {
          "extension": "jpg",
          "height": 600,
          "mimetype": "image/jpeg",
          "secret": "9e3CFXV4t5vXBEZ0P5N40RYWCoPNxGCE",
          "width": 754
        },
        "ds": {
          "extension": "jpg",
          "height": 320,
          "mimetype": "image/jpeg",
          "secret": "9e3CFXV4t5vXBEZ0P5N40RYWCoPNxGCE",
          "width": 320
        },
        "k": {
          "extension": "jpg",
          "height": 1536,
          "mimetype": "image/jpeg",
          "secret": "9e3CFXV4t5vXBEZ0P5N40RYWCoPNxGCE",
          "width": 1931
        },
        "n": {
          "extension": "jpg",
          "height": 240,
          "mimetype": "image/jpeg",
          "secret": "9e3CFXV4t5vXBEZ0P5N40RYWCoPNxGCE",
          "width": 301
        },
        "o": {
          "extension": "jpg",
          "height": 1667,
          "mimetype": "image/jpeg",
          "secret": "8JdBKjF5c9Ui1WQ0d0u6GuAyhOxvyvyn",
          "width": 2096
        },
        "s": {
          "extension": "jpg",
          "height": 320,
          "mimetype": "image/jpeg",
          "secret": "9e3CFXV4t5vXBEZ0P5N40RYWCoPNxGCE",
          "width": 320
        },
        "z": {
          "extension": "jpg",
          "height": 480,
          "mimetype": "image/jpeg",
          "secret": "9e3CFXV4t5vXBEZ0P5N40RYWCoPNxGCE",
          "width": 603
        }
      }
    },
    "media:uri_template": "https://millsfield.sfomuseum.org/media/152/785/836/7/1527858367_{secret}_{label}.{extention}",
    "sfomuseum:filename": "2012.147.435.tif",
    "sfomuseum:image_index": 0,
    "sfomuseum:placetype": "image",
    "sfomuseum:primary_image": 1,
    "wof:depicts": [
      1511952711
    ],
    "wof:name": "flight officer wings: Kuwait Airways",
    "wof:placetype": "custom",
    "wof:placetype_alt": "image"
  },
  "geometry": {"coordinates":[-122.386155,37.616358],"type":"Point"}
}
