{
  "type": "Feature",
  "properties": {
    "iso:country": "XX",
    "media:fingerprint": "6120095e9acf35bcb4725263555c438eaa460926",
    "media:imagehash_avg": "a:ffc383c30103ffff",
    "media:imagehash_diff": "d:ea07178f5f73d3d3",
    "media:medium": "image",
    "media:mimetype": "image/tiff",
    "media:properties": {
      "colours": [
        {
          "hex": "#435d9a",
          "name": "#435d9a",
          "reference": "vibrant"
        }, 
        {
          "hex": "#f4eddb",
          "name": "#f4eddb",
          "reference": "vibrant"
        }, 
        {
          "hex": "#2d467d",
          "name": "#2d467d",
          "reference": "vibrant"
        }, 
        {
          "hex": "#526da6",
          "name": "#526da6",
          "reference": "vibrant"
        }, 
        {
          "hex": "#a8b3c1",
          "name": "#a8b3c1",
          "reference": "vibrant"
        }
      ],
      "sizes": {
        "b": {
          "extension": "jpg",
          "height": 768,
          "mimetype": "image/jpeg",
          "secret": "thq3gmVFRVkabltfMcnTQGdCdyOpFq5A",
          "width": 460
        },
        "c": {
          "extension": "jpg",
          "height": 600,
          "mimetype": "image/jpeg",
          "secret": "thq3gmVFRVkabltfMcnTQGdCdyOpFq5A",
          "width": 359
        },
        "dc": {
          "extension": "jpg",
          "height": 600,
          "mimetype": "image/jpeg",
          "secret": "thq3gmVFRVkabltfMcnTQGdCdyOpFq5A",
          "width": 359
        },
        "ds": {
          "extension": "jpg",
          "height": 320,
          "mimetype": "image/jpeg",
          "secret": "thq3gmVFRVkabltfMcnTQGdCdyOpFq5A",
          "width": 320
        },
        "k": {
          "extension": "jpg",
          "height": 1536,
          "mimetype": "image/jpeg",
          "secret": "thq3gmVFRVkabltfMcnTQGdCdyOpFq5A",
          "width": 921
        },
        "n": {
          "extension": "jpg",
          "height": 240,
          "mimetype": "image/jpeg",
          "secret": "thq3gmVFRVkabltfMcnTQGdCdyOpFq5A",
          "width": 143
        },
        "o": {
          "extension": "jpg",
          "height": 3191,
          "mimetype": "image/jpeg",
          "secret": "nJ98wmYJbqJieRcOI57XnbgVgTj46y41",
          "width": 1914
        },
        "s": {
          "extension": "jpg",
          "height": 320,
          "mimetype": "image/jpeg",
          "secret": "thq3gmVFRVkabltfMcnTQGdCdyOpFq5A",
          "width": 320
        },
        "z": {
          "extension": "jpg",
          "height": 480,
          "mimetype": "image/jpeg",
          "secret": "thq3gmVFRVkabltfMcnTQGdCdyOpFq5A",
          "width": 287
        }
      }
    },
    "media:uri_template": "https://millsfield.sfomuseum.org/media/152/782/346/1/1527823461_{secret}_{label}.{extention}",
    "sfomuseum:filename": "41597.tif",
    "sfomuseum:image_index": 5,
    "sfomuseum:placetype": "image",
    "sfomuseum:primary_image": 0,
    "wof:depicts": [
      1511908395
    ],
    "wof:name": "airsickness bag: Air New Zealand",
    "wof:placetype": "media"
  },
  "geometry": {"coordinates":[-122.386155,37.616358],"type":"Point"}
}
