{
  "type": "Feature",
  "properties": {
    "iso:country": "XX",
    "media:fingerprint": "7a5c851431401c12e8ea218674df569b128e9925",
    "media:imagehash_avg": "a:00ffffffff910000",
    "media:imagehash_diff": "d:7171717171717171",
    "media:medium": "image",
    "media:mimetype": "image/tiff",
    "media:properties": {
      "colours": [
        {
          "hex": "#808080",
          "name": "#808080",
          "reference": "vibrant"
        },
        {
          "hex": "#b8b8b8",
          "name": "#b8b8b8",
          "reference": "vibrant"
        },
        {
          "hex": "#464646",
          "name": "#464646",
          "reference": "vibrant"
        }
      ],
      "sizes": {
        "b": {
          "extension": "jpg",
          "height": 768,
          "mimetype": "image/jpeg",
          "secret": "d3lLOsxUfjgxJlh6lgoz6kYVnUE2Ut6Z",
          "width": 876
        },
        "c": {
          "extension": "jpg",
          "height": 600,
          "mimetype": "image/jpeg",
          "secret": "d3lLOsxUfjgxJlh6lgoz6kYVnUE2Ut6Z",
          "width": 684
        },
        "dc": {
          "extension": "jpg",
          "height": 600,
          "mimetype": "image/jpeg",
          "secret": "d3lLOsxUfjgxJlh6lgoz6kYVnUE2Ut6Z",
          "width": 684
        },
        "ds": {
          "extension": "jpg",
          "height": 320,
          "mimetype": "image/jpeg",
          "secret": "d3lLOsxUfjgxJlh6lgoz6kYVnUE2Ut6Z",
          "width": 320
        },
        "k": {
          "extension": "jpg",
          "height": 1536,
          "mimetype": "image/jpeg",
          "secret": "d3lLOsxUfjgxJlh6lgoz6kYVnUE2Ut6Z",
          "width": 1753
        },
        "n": {
          "extension": "jpg",
          "height": 240,
          "mimetype": "image/jpeg",
          "secret": "d3lLOsxUfjgxJlh6lgoz6kYVnUE2Ut6Z",
          "width": 273
        },
        "o": {
          "extension": "jpg",
          "height": 3808,
          "mimetype": "image/jpeg",
          "secret": "1bgKOHPoOvoM7bzkL9DNyv27SRC0gOeb",
          "width": 4346
        },
        "s": {
          "extension": "jpg",
          "height": 320,
          "mimetype": "image/jpeg",
          "secret": "d3lLOsxUfjgxJlh6lgoz6kYVnUE2Ut6Z",
          "width": 320
        },
        "z": {
          "extension": "jpg",
          "height": 480,
          "mimetype": "image/jpeg",
          "secret": "d3lLOsxUfjgxJlh6lgoz6kYVnUE2Ut6Z",
          "width": 547
        }
      }
    },
    "media:uri_template": "https://static.sfomuseum.org/media/152/785/186/7/1527851867_{secret}_{label}.{extention}",
    "sfomuseum:filename": "85251.tif",
    "sfomuseum:image_index": 5,
    "sfomuseum:image_type": "studio",
    "sfomuseum:placetype": "image",
    "sfomuseum:primary_image": 1,
    "wof:depicts": [
      1511956343
    ],
    "wof:name": "negative: Stanley Henry Page, San Francisco Bay Area, Bay and clouds",
    "wof:placetype": "custom",
    "wof:placetype_alt": "image"
  },
  "geometry": {"coordinates":[-122.386155,37.616358],"type":"Point"}
}
