{
  "type": "Feature",
  "properties": {
    "iso:country": "XX",
    "media:fingerprint": "349eb56d06a92fe63eba9c3fcc3827b2841d93e0",
    "media:imagehash_avg": "a:bd1800003c3e7cf8",
    "media:imagehash_diff": "d:756171795d6ce161",
    "media:medium": "image",
    "media:mimetype": "image/tiff",
    "media:properties": {
      "colours": [
        {
          "hex": "#e8d037",
          "name": "#e8d037",
          "reference": "vibrant"
        }, 
        {
          "hex": "#7b040f",
          "name": "#7b040f",
          "reference": "vibrant"
        }, 
        {
          "hex": "#90614b",
          "name": "#90614b",
          "reference": "vibrant"
        }, 
        {
          "hex": "#c2b5a0",
          "name": "#c2b5a0",
          "reference": "vibrant"
        }, 
        {
          "hex": "#5f3046",
          "name": "#5f3046",
          "reference": "vibrant"
        }
      ],
      "sizes": {
        "b": {
          "extension": "jpg",
          "height": 768,
          "mimetype": "image/jpeg",
          "secret": "9iBUTeM45ebY6KN45uJzuJMAZgEeJe9w",
          "width": 371
        },
        "c": {
          "extension": "jpg",
          "height": 600,
          "mimetype": "image/jpeg",
          "secret": "9iBUTeM45ebY6KN45uJzuJMAZgEeJe9w",
          "width": 290
        },
        "dc": {
          "extension": "jpg",
          "height": 600,
          "mimetype": "image/jpeg",
          "secret": "9iBUTeM45ebY6KN45uJzuJMAZgEeJe9w",
          "width": 290
        },
        "ds": {
          "extension": "jpg",
          "height": 320,
          "mimetype": "image/jpeg",
          "secret": "9iBUTeM45ebY6KN45uJzuJMAZgEeJe9w",
          "width": 320
        },
        "k": {
          "extension": "jpg",
          "height": 1536,
          "mimetype": "image/jpeg",
          "secret": "9iBUTeM45ebY6KN45uJzuJMAZgEeJe9w",
          "width": 742
        },
        "n": {
          "extension": "jpg",
          "height": 240,
          "mimetype": "image/jpeg",
          "secret": "9iBUTeM45ebY6KN45uJzuJMAZgEeJe9w",
          "width": 116
        },
        "o": {
          "extension": "jpg",
          "height": 2569,
          "mimetype": "image/jpeg",
          "secret": "tgOuh4Zwl25iLne73KHQjePnY1P2g7K7",
          "width": 1242
        },
        "s": {
          "extension": "jpg",
          "height": 320,
          "mimetype": "image/jpeg",
          "secret": "9iBUTeM45ebY6KN45uJzuJMAZgEeJe9w",
          "width": 320
        },
        "z": {
          "extension": "jpg",
          "height": 480,
          "mimetype": "image/jpeg",
          "secret": "9iBUTeM45ebY6KN45uJzuJMAZgEeJe9w",
          "width": 232
        }
      }
    },
    "media:uri_template": "https://millsfield.sfomuseum.org/media/152/781/914/3/1527819143_{secret}_{label}.{extention}",
    "sfomuseum:filename": "20181.tif",
    "sfomuseum:image_index": 5,
    "sfomuseum:placetype": "image",
    "sfomuseum:primary_image": 1,
    "wof:depicts": [
      1511932903
    ],
    "wof:name": "timetable: Alaska Airlines, including Horizon Air",
    "wof:placetype": "media"
  },
  "geometry": {"coordinates":[-122.386155,37.616358],"type":"Point"}
}
