{
  "type": "Feature",
  "properties": {
    "iso:country": "XX",
    "media:fingerprint": "26e94e8d1ff5c2d71772dba1c809c8231cb74daf",
    "media:imagehash_avg": "a:00e1fffcfcf8fff8",
    "media:imagehash_diff": "d:9c8d0d0880010301",
    "media:medium": "image",
    "media:mimetype": "image/tiff",
    "media:properties": {
      "colours": [
        {
          "hex": "#ecbc14",
          "name": "#ecbc14",
          "reference": "vibrant"
        },
        {
          "hex": "#f2e996",
          "name": "#f2e996",
          "reference": "vibrant"
        },
        {
          "hex": "#503211",
          "name": "#503211",
          "reference": "vibrant"
        },
        {
          "hex": "#a59860",
          "name": "#a59860",
          "reference": "vibrant"
        },
        {
          "hex": "#c9bf8f",
          "name": "#c9bf8f",
          "reference": "vibrant"
        }
      ],
      "sizes": {
        "b": {
          "extension": "jpg",
          "height": 768,
          "mimetype": "image/jpeg",
          "secret": "erDsTdb6gJfutQvO8B0VNIyuJVqVPUe9",
          "width": 463
        },
        "c": {
          "extension": "jpg",
          "height": 600,
          "mimetype": "image/jpeg",
          "secret": "erDsTdb6gJfutQvO8B0VNIyuJVqVPUe9",
          "width": 362
        },
        "dc": {
          "extension": "jpg",
          "height": 600,
          "mimetype": "image/jpeg",
          "secret": "erDsTdb6gJfutQvO8B0VNIyuJVqVPUe9",
          "width": 362
        },
        "ds": {
          "extension": "jpg",
          "height": 320,
          "mimetype": "image/jpeg",
          "secret": "erDsTdb6gJfutQvO8B0VNIyuJVqVPUe9",
          "width": 320
        },
        "k": {
          "extension": "jpg",
          "height": 1536,
          "mimetype": "image/jpeg",
          "secret": "erDsTdb6gJfutQvO8B0VNIyuJVqVPUe9",
          "width": 926
        },
        "n": {
          "extension": "jpg",
          "height": 240,
          "mimetype": "image/jpeg",
          "secret": "erDsTdb6gJfutQvO8B0VNIyuJVqVPUe9",
          "width": 144
        },
        "o": {
          "extension": "jpg",
          "height": 2970,
          "mimetype": "image/jpeg",
          "secret": "pwDs4d8EXWL3TuBC6HKSK0CfuajzMXsc",
          "width": 1792
        },
        "s": {
          "extension": "jpg",
          "height": 320,
          "mimetype": "image/jpeg",
          "secret": "erDsTdb6gJfutQvO8B0VNIyuJVqVPUe9",
          "width": 320
        },
        "z": {
          "extension": "jpg",
          "height": 480,
          "mimetype": "image/jpeg",
          "secret": "erDsTdb6gJfutQvO8B0VNIyuJVqVPUe9",
          "width": 289
        }
      }
    },
    "media:uri_template": "https://static.sfomuseum.org/media/152/784/397/9/1527843979_{secret}_{label}.{extention}",
    "sfomuseum:filename": "68765.tif",
    "sfomuseum:image_index": 5,
    "sfomuseum:image_type": "studio",
    "sfomuseum:placetype": "image",
    "sfomuseum:primary_image": 0,
    "wof:depicts": [
      1159284127,
      1511927655
    ],
    "wof:name": "menu: Cathay Pacific Airways, Business Class",
    "wof:placetype": "custom",
    "wof:placetype_alt": "image"
  },
  "geometry": {"coordinates":[-122.386155,37.616358],"type":"Point"}
}
