{
  "type": "Feature",
  "properties": {
    "date:cessation_lower": "1935-01-01",
    "date:cessation_upper": "1935-12-31",
    "date:inception_lower": "1935-01-01",
    "date:inception_upper": "1935-12-31",
    "iso:country": "XX",
    "sfomuseum:filename": "202189.tif",
    "sfomuseum:image_index": 0,
    "sfomuseum:image_type": "curator",
    "sfomuseum:placetype": "image",
    "sfomuseum:primary_image": 1,
    "wof:depicts": [
      1511930851
    ],
    "wof:name": "brochure: Pratt \u0026 Whitney, Wasp and Hornet engines",
    "wof:placetype": "custom"
  },
  "geometry": {"coordinates":[-122.386155,37.616357],"type":"Point"}
}
