{
  "type": "Feature",
  "properties": {
    "iso:country": "XX",
    "media:fingerprint": "1e1bc6e4c4fa5be51466631b91e7ac5c217ed892",
    "media:imagehash_avg": "a:f7bfbf9f8f0705bf",
    "media:imagehash_diff": "d:4d6d71337b595959",
    "media:medium": "image",
    "media:mimetype": "image/tiff",
    "media:properties": {
      "colours": [
        {
          "hex": "#c8ad78",
          "name": "#c8ad78",
          "reference": "vibrant"
        }, 
        {
          "hex": "#e3cc9c",
          "name": "#e3cc9c",
          "reference": "vibrant"
        }, 
        {
          "hex": "#433a1e",
          "name": "#433a1e",
          "reference": "vibrant"
        }, 
        {
          "hex": "#9f9068",
          "name": "#9f9068",
          "reference": "vibrant"
        }, 
        {
          "hex": "#d1cdbd",
          "name": "#d1cdbd",
          "reference": "vibrant"
        }
      ],
      "sizes": {
        "b": {
          "extension": "jpg",
          "height": 575,
          "mimetype": "image/jpeg",
          "secret": "a5hOfENCwBjHpScVCSBrPFatnVhikvDz",
          "width": 1023
        },
        "c": {
          "extension": "jpg",
          "height": 449,
          "mimetype": "image/jpeg",
          "secret": "a5hOfENCwBjHpScVCSBrPFatnVhikvDz",
          "width": 800
        },
        "dc": {
          "extension": "jpg",
          "height": 449,
          "mimetype": "image/jpeg",
          "secret": "a5hOfENCwBjHpScVCSBrPFatnVhikvDz",
          "width": 800
        },
        "ds": {
          "extension": "jpg",
          "height": 320,
          "mimetype": "image/jpeg",
          "secret": "a5hOfENCwBjHpScVCSBrPFatnVhikvDz",
          "width": 320
        },
        "k": {
          "extension": "jpg",
          "height": 1151,
          "mimetype": "image/jpeg",
          "secret": "a5hOfENCwBjHpScVCSBrPFatnVhikvDz",
          "width": 2047
        },
        "n": {
          "extension": "jpg",
          "height": 179,
          "mimetype": "image/jpeg",
          "secret": "a5hOfENCwBjHpScVCSBrPFatnVhikvDz",
          "width": 320
        },
        "o": {
          "extension": "jpg",
          "height": 1121,
          "mimetype": "image/jpeg",
          "secret": "rjmnCQpmfRgVuDK4YnDs28svu3twNBEj",
          "width": 1993
        },
        "s": {
          "extension": "jpg",
          "height": 320,
          "mimetype": "image/jpeg",
          "secret": "a5hOfENCwBjHpScVCSBrPFatnVhikvDz",
          "width": 320
        },
        "z": {
          "extension": "jpg",
          "height": 359,
          "mimetype": "image/jpeg",
          "secret": "a5hOfENCwBjHpScVCSBrPFatnVhikvDz",
          "width": 640
        }
      }
    },
    "media:uri_template": "https://millsfield.sfomuseum.org/media/152/782/049/3/1527820493_{secret}_{label}.{extention}",
    "sfomuseum:filename": "31643.tif",
    "sfomuseum:image_index": 5,
    "sfomuseum:placetype": "image",
    "sfomuseum:primary_image": 0,
    "wof:depicts": [
      1511923741
    ],
    "wof:name": "airmail flight cover: Pan American Airways, Venezuela - Canal Zone route",
    "wof:placetype": "media"
  },
  "geometry": {"coordinates":[-122.386155,37.616358],"type":"Point"}
}
