{
  "type": "Feature",
  "properties": {
    "iso:country": "XX",
    "media:fingerprint": "f9a124fe9d56470597b315419766c3cf129788c0",
    "media:imagehash_avg": "a:003c7fefff81833f",
    "media:imagehash_diff": "d:f8f0b8dcdc3b0fe0",
    "media:medium": "image",
    "media:mimetype": "image/tiff",
    "media:properties": {
      "colours": [
        {
          "hex": "#7f7c7b",
          "name": "#7f7c7b",
          "reference": "vibrant"
        },
        {
          "hex": "#b7c1c9",
          "name": "#b7c1c9",
          "reference": "vibrant"
        },
        {
          "hex": "#3d3b39",
          "name": "#3d3b39",
          "reference": "vibrant"
        }
      ],
      "sizes": {
        "b": {
          "extension": "jpg",
          "height": 753,
          "mimetype": "image/jpeg",
          "secret": "15zWVcSi0ijLwh8pXhJ0ftSmVsHUXkwr",
          "width": 1024
        },
        "c": {
          "extension": "jpg",
          "height": 588,
          "mimetype": "image/jpeg",
          "secret": "15zWVcSi0ijLwh8pXhJ0ftSmVsHUXkwr",
          "width": 800
        },
        "dc": {
          "extension": "jpg",
          "height": 588,
          "mimetype": "image/jpeg",
          "secret": "15zWVcSi0ijLwh8pXhJ0ftSmVsHUXkwr",
          "width": 800
        },
        "ds": {
          "extension": "jpg",
          "height": 320,
          "mimetype": "image/jpeg",
          "secret": "15zWVcSi0ijLwh8pXhJ0ftSmVsHUXkwr",
          "width": 320
        },
        "k": {
          "extension": "jpg",
          "height": 1506,
          "mimetype": "image/jpeg",
          "secret": "15zWVcSi0ijLwh8pXhJ0ftSmVsHUXkwr",
          "width": 2048
        },
        "n": {
          "extension": "jpg",
          "height": 235,
          "mimetype": "image/jpeg",
          "secret": "15zWVcSi0ijLwh8pXhJ0ftSmVsHUXkwr",
          "width": 320
        },
        "o": {
          "extension": "jpg",
          "height": 2900,
          "mimetype": "image/jpeg",
          "secret": "1tnfQTC1cG84lkclQO4k3qrOla17mZEf",
          "width": 3943
        },
        "s": {
          "extension": "jpg",
          "height": 320,
          "mimetype": "image/jpeg",
          "secret": "15zWVcSi0ijLwh8pXhJ0ftSmVsHUXkwr",
          "width": 320
        },
        "z": {
          "extension": "jpg",
          "height": 470,
          "mimetype": "image/jpeg",
          "secret": "15zWVcSi0ijLwh8pXhJ0ftSmVsHUXkwr",
          "width": 640
        }
      }
    },
    "media:uri_template": "https://static.sfomuseum.org/media/152/785/086/1/1527850861_{secret}_{label}.{extention}",
    "sfomuseum:filename": "82488.tif",
    "sfomuseum:image_index": 5,
    "sfomuseum:image_type": "studio",
    "sfomuseum:placetype": "image",
    "sfomuseum:primary_image": 0,
    "wof:depicts": [
      1511923369,
      1159283539
    ],
    "wof:name": "coffee cup: AeroMexico",
    "wof:placetype": "custom",
    "wof:placetype_alt": "image"
  },
  "geometry": {"coordinates":[-122.386155,37.616358],"type":"Point"}
}
