{
  "type": "Feature",
  "properties": {
    "iso:country": "XX",
    "media:fingerprint": "b1d574134ffd628cc26ea3008a470e0a1dbc9f3a",
    "media:imagehash_avg": "a:27e6fcfefe001004",
    "media:imagehash_diff": "d:ce4e6878e0e0e0f8",
    "media:medium": "image",
    "media:mimetype": "image/tiff",
    "media:properties": {
      "colours": [
        {
          "hex": "#868686",
          "name": "#868686",
          "reference": "vibrant"
        }, 
        {
          "hex": "#b6b6b6",
          "name": "#b6b6b6",
          "reference": "vibrant"
        }, 
        {
          "hex": "#484848",
          "name": "#484848",
          "reference": "vibrant"
        }
      ],
      "sizes": {
        "b": {
          "extension": "jpg",
          "height": 768,
          "mimetype": "image/jpeg",
          "secret": "XKVpx8klfg7RmzGJDWXSKb6w7wPFgEMT",
          "width": 970
        },
        "c": {
          "extension": "jpg",
          "height": 600,
          "mimetype": "image/jpeg",
          "secret": "XKVpx8klfg7RmzGJDWXSKb6w7wPFgEMT",
          "width": 758
        },
        "dc": {
          "extension": "jpg",
          "height": 600,
          "mimetype": "image/jpeg",
          "secret": "XKVpx8klfg7RmzGJDWXSKb6w7wPFgEMT",
          "width": 758
        },
        "ds": {
          "extension": "jpg",
          "height": 320,
          "mimetype": "image/jpeg",
          "secret": "XKVpx8klfg7RmzGJDWXSKb6w7wPFgEMT",
          "width": 320
        },
        "k": {
          "extension": "jpg",
          "height": 1536,
          "mimetype": "image/jpeg",
          "secret": "XKVpx8klfg7RmzGJDWXSKb6w7wPFgEMT",
          "width": 1941
        },
        "n": {
          "extension": "jpg",
          "height": 240,
          "mimetype": "image/jpeg",
          "secret": "XKVpx8klfg7RmzGJDWXSKb6w7wPFgEMT",
          "width": 303
        },
        "o": {
          "extension": "jpg",
          "height": 2168,
          "mimetype": "image/jpeg",
          "secret": "7SRp80L3KqvTqY7CdOAlhl5ru1rXq9xQ",
          "width": 2740
        },
        "s": {
          "extension": "jpg",
          "height": 320,
          "mimetype": "image/jpeg",
          "secret": "XKVpx8klfg7RmzGJDWXSKb6w7wPFgEMT",
          "width": 320
        },
        "z": {
          "extension": "jpg",
          "height": 480,
          "mimetype": "image/jpeg",
          "secret": "XKVpx8klfg7RmzGJDWXSKb6w7wPFgEMT",
          "width": 606
        }
      }
    },
    "media:uri_template": "https://millsfield.sfomuseum.org/media/152/782/426/3/1527824263_{secret}_{label}.{extention}",
    "sfomuseum:filename": "42341.tif",
    "sfomuseum:image_index": 5,
    "sfomuseum:placetype": "image",
    "sfomuseum:primary_image": 1,
    "wof:depicts": [
      1511945585
    ],
    "wof:name": "negative: San Francisco International Airport (SFO), environs",
    "wof:placetype": "media"
  },
  "geometry": {"coordinates":[-122.386155,37.616358],"type":"Point"}
}
