{
  "type": "Feature",
  "properties": {
    "sfomuseum:filename": "2002.113.278.jpg",
    "sfomuseum:image_index": 1,
    "sfomuseum:placetype": "image",
    "sfomuseum:primary_image": 1,
    "wof:depicts": [
      1729564237,
      1159285393,
      1159291139
    ],
    "wof:name": "manual: TWA (Trans World Airlines), Lockheed L-1049 Super Constellation Pocket Handbook",
    "wof:placetype": "custom"
  },
  "geometry": {"coordinates":[-122.386155,37.616357],"type":"Point"}
}
