{
  "type": "Feature",
  "properties": {
    "iso:country": "XX",
    "media:fingerprint": "2832411550165fa76047cd743c536270b90fff57",
    "media:imagehash_avg": "a:ffff8381818181c3",
    "media:imagehash_diff": "d:4d0f1f1f0f0f170b",
    "media:medium": "image",
    "media:mimetype": "image/tiff",
    "media:properties": {
      "colours": [
        {
          "hex": "#d8c8a7",
          "name": "#d8c8a7",
          "reference": "vibrant"
        }, 
        {
          "hex": "#383818",
          "name": "#383818",
          "reference": "vibrant"
        }, 
        {
          "hex": "#959074",
          "name": "#959074",
          "reference": "vibrant"
        }, 
        {
          "hex": "#d8d0a8",
          "name": "#d8d0a8",
          "reference": "vibrant"
        }, 
        {
          "hex": "#544c36",
          "name": "#544c36",
          "reference": "vibrant"
        }
      ],
      "sizes": {
        "b": {
          "extension": "jpg",
          "height": 768,
          "mimetype": "image/jpeg",
          "secret": "Zmh1rmh9kPWBFhs6mc14OJGItgHknVF0",
          "width": 599
        },
        "c": {
          "extension": "jpg",
          "height": 600,
          "mimetype": "image/jpeg",
          "secret": "Zmh1rmh9kPWBFhs6mc14OJGItgHknVF0",
          "width": 468
        },
        "dc": {
          "extension": "jpg",
          "height": 600,
          "mimetype": "image/jpeg",
          "secret": "Zmh1rmh9kPWBFhs6mc14OJGItgHknVF0",
          "width": 468
        },
        "ds": {
          "extension": "jpg",
          "height": 320,
          "mimetype": "image/jpeg",
          "secret": "Zmh1rmh9kPWBFhs6mc14OJGItgHknVF0",
          "width": 320
        },
        "k": {
          "extension": "jpg",
          "height": 1536,
          "mimetype": "image/jpeg",
          "secret": "Zmh1rmh9kPWBFhs6mc14OJGItgHknVF0",
          "width": 1199
        },
        "n": {
          "extension": "jpg",
          "height": 240,
          "mimetype": "image/jpeg",
          "secret": "Zmh1rmh9kPWBFhs6mc14OJGItgHknVF0",
          "width": 187
        },
        "o": {
          "extension": "jpg",
          "height": 1800,
          "mimetype": "image/jpeg",
          "secret": "kjfFx8ZhVW7PMxjpU5cmaWpzZuJqlYL8",
          "width": 1406
        },
        "s": {
          "extension": "jpg",
          "height": 320,
          "mimetype": "image/jpeg",
          "secret": "Zmh1rmh9kPWBFhs6mc14OJGItgHknVF0",
          "width": 320
        },
        "z": {
          "extension": "jpg",
          "height": 480,
          "mimetype": "image/jpeg",
          "secret": "Zmh1rmh9kPWBFhs6mc14OJGItgHknVF0",
          "width": 374
        }
      }
    },
    "media:uri_template": "https://millsfield.sfomuseum.org/media/152/785/689/7/1527856897_{secret}_{label}.{extention}",
    "sfomuseum:filename": "2000.018.040.005a.tif",
    "sfomuseum:image_index": 0,
    "sfomuseum:placetype": "image",
    "sfomuseum:primary_image": 1,
    "wof:depicts": [
      1511957951
    ],
    "wof:name": "correspondence: Mills Estate Incorporated, Joseph J. Phillips, Right of Way Agent for City and County of San Francisco",
    "wof:placetype": "media"
  },
  "geometry": {"coordinates":[-122.386155,37.616358],"type":"Point"}
}
