{
  "type": "Feature",
  "properties": {
    "iso:country": "XX",
    "media:fingerprint": "b92afa1158acbc59f59bf8636010a92faee6f0b1",
    "media:imagehash_avg": "a:0e3e3e3e3e3e3e0c",
    "media:imagehash_diff": "d:7cdcdcdcdcdcdcdc",
    "media:medium": "image",
    "media:mimetype": "image/tiff",
    "media:properties": {
      "colours": [
        {
          "hex": "#c4ba78",
          "name": "#c4ba78",
          "reference": "vibrant"
        },
        {
          "hex": "#a49a6d",
          "name": "#a49a6d",
          "reference": "vibrant"
        },
        {
          "hex": "#c5c6a7",
          "name": "#c5c6a7",
          "reference": "vibrant"
        },
        {
          "hex": "#534c3d",
          "name": "#534c3d",
          "reference": "vibrant"
        }
      ],
      "sizes": {
        "b": {
          "extension": "jpg",
          "height": 768,
          "mimetype": "image/jpeg",
          "secret": "1QtqpXdadOvSBj4yRHW9Nx19lJ6HyaTo",
          "width": 877
        },
        "c": {
          "extension": "jpg",
          "height": 600,
          "mimetype": "image/jpeg",
          "secret": "1QtqpXdadOvSBj4yRHW9Nx19lJ6HyaTo",
          "width": 685
        },
        "dc": {
          "extension": "jpg",
          "height": 600,
          "mimetype": "image/jpeg",
          "secret": "1QtqpXdadOvSBj4yRHW9Nx19lJ6HyaTo",
          "width": 685
        },
        "ds": {
          "extension": "jpg",
          "height": 320,
          "mimetype": "image/jpeg",
          "secret": "1QtqpXdadOvSBj4yRHW9Nx19lJ6HyaTo",
          "width": 320
        },
        "k": {
          "extension": "jpg",
          "height": 1536,
          "mimetype": "image/jpeg",
          "secret": "1QtqpXdadOvSBj4yRHW9Nx19lJ6HyaTo",
          "width": 1754
        },
        "n": {
          "extension": "jpg",
          "height": 239,
          "mimetype": "image/jpeg",
          "secret": "1QtqpXdadOvSBj4yRHW9Nx19lJ6HyaTo",
          "width": 274
        },
        "o": {
          "extension": "jpg",
          "height": 1470,
          "mimetype": "image/jpeg",
          "secret": "jLTfUCIfA2fORFMEcEtA9tdceq29Tph7",
          "width": 1679
        },
        "s": {
          "extension": "jpg",
          "height": 320,
          "mimetype": "image/jpeg",
          "secret": "1QtqpXdadOvSBj4yRHW9Nx19lJ6HyaTo",
          "width": 320
        },
        "z": {
          "extension": "jpg",
          "height": 479,
          "mimetype": "image/jpeg",
          "secret": "1QtqpXdadOvSBj4yRHW9Nx19lJ6HyaTo",
          "width": 548
        }
      }
    },
    "media:uri_template": "https://static.sfomuseum.org/media/152/785/416/1/1527854161_{secret}_{label}.{extention}",
    "sfomuseum:filename": "2010.174.017_interior.tif",
    "sfomuseum:image_index": 5,
    "sfomuseum:image_type": "studio",
    "sfomuseum:placetype": "image",
    "sfomuseum:primary_image": 0,
    "wof:depicts": [
      1511942101
    ],
    "wof:name": "logbook: Stanley Henry Page",
    "wof:placetype": "custom",
    "wof:placetype_alt": "image"
  },
  "geometry": {"coordinates":[-122.386155,37.616358],"type":"Point"}
}
