{
  "type": "Feature",
  "properties": {
    "iso:country": "XX",
    "media:fingerprint": "47c8c8629b280f8ee4280130fc78d383dc89cc7a",
    "media:imagehash_avg": "a:000d8fffeffff1f7",
    "media:imagehash_diff": "d:1b795c5c19150707",
    "media:medium": "image",
    "media:mimetype": "image/tiff",
    "media:properties": {
      "colours": [
        {
          "hex": "#f8f8e8",
          "name": "#f8f8e8",
          "reference": "vibrant"
        },
        {
          "hex": "#888576",
          "name": "#888576",
          "reference": "vibrant"
        },
        {
          "hex": "#d2cbb7",
          "name": "#d2cbb7",
          "reference": "vibrant"
        },
        {
          "hex": "#544832",
          "name": "#544832",
          "reference": "vibrant"
        }
      ],
      "sizes": {
        "b": {
          "extension": "jpg",
          "height": 768,
          "mimetype": "image/jpeg",
          "secret": "uvf1GaNZglrw6ip2iYNa5MOv57yAemAh",
          "width": 662
        },
        "c": {
          "extension": "jpg",
          "height": 600,
          "mimetype": "image/jpeg",
          "secret": "uvf1GaNZglrw6ip2iYNa5MOv57yAemAh",
          "width": 517
        },
        "dc": {
          "extension": "jpg",
          "height": 600,
          "mimetype": "image/jpeg",
          "secret": "uvf1GaNZglrw6ip2iYNa5MOv57yAemAh",
          "width": 517
        },
        "ds": {
          "extension": "jpg",
          "height": 320,
          "mimetype": "image/jpeg",
          "secret": "uvf1GaNZglrw6ip2iYNa5MOv57yAemAh",
          "width": 320
        },
        "k": {
          "extension": "jpg",
          "height": 1536,
          "mimetype": "image/jpeg",
          "secret": "uvf1GaNZglrw6ip2iYNa5MOv57yAemAh",
          "width": 1325
        },
        "n": {
          "extension": "jpg",
          "height": 240,
          "mimetype": "image/jpeg",
          "secret": "uvf1GaNZglrw6ip2iYNa5MOv57yAemAh",
          "width": 207
        },
        "o": {
          "extension": "jpg",
          "height": 2718,
          "mimetype": "image/jpeg",
          "secret": "SsuWaw6rfagFQcxTApqT5XLYlJlPUxtI",
          "width": 2346
        },
        "s": {
          "extension": "jpg",
          "height": 320,
          "mimetype": "image/jpeg",
          "secret": "uvf1GaNZglrw6ip2iYNa5MOv57yAemAh",
          "width": 320
        },
        "z": {
          "extension": "jpg",
          "height": 480,
          "mimetype": "image/jpeg",
          "secret": "uvf1GaNZglrw6ip2iYNa5MOv57yAemAh",
          "width": 414
        }
      }
    },
    "media:uri_template": "https://static.sfomuseum.org/media/152/785/051/7/1527850517_{secret}_{label}.{extention}",
    "sfomuseum:filename": "81925.tif",
    "sfomuseum:image_index": 5,
    "sfomuseum:image_type": "studio",
    "sfomuseum:placetype": "image",
    "sfomuseum:primary_image": 0,
    "wof:depicts": [
      1511931955,
      1159285163
    ],
    "wof:name": "timetable: Singapore Airlines",
    "wof:placetype": "custom",
    "wof:placetype_alt": "image"
  },
  "geometry": {"coordinates":[-122.386155,37.616358],"type":"Point"}
}
