{
  "type": "Feature",
  "properties": {
    "iso:country": "TH",
    "media:fingerprint": "44c6ebdbb24e03c480faaebd320ce5bfcc7856c4",
    "media:imagehash_avg": "a:c27e7e7efe3e1e00",
    "media:imagehash_diff": "d:16bcb8ecccdefead",
    "media:medium": "image",
    "media:mimetype": "image/tiff",
    "media:properties": {
      "colours": [
        {
          "hex": "#b41d0a",
          "name": "#b41d0a",
          "reference": "vibrant"
        }, 
        {
          "hex": "#a81807",
          "name": "#a81807",
          "reference": "vibrant"
        }, 
        {
          "hex": "#8a8979",
          "name": "#8a8979",
          "reference": "vibrant"
        }, 
        {
          "hex": "#c8c5b0",
          "name": "#c8c5b0",
          "reference": "vibrant"
        }, 
        {
          "hex": "#3a4152",
          "name": "#3a4152",
          "reference": "vibrant"
        }
      ],
      "sizes": {
        "b": {
          "extension": "jpg",
          "height": 590,
          "mimetype": "image/jpeg",
          "secret": "RrQOp0adp2S3rvmla8mWu7BGJsNWMguA",
          "width": 1024
        },
        "c": {
          "extension": "jpg",
          "height": 461,
          "mimetype": "image/jpeg",
          "secret": "RrQOp0adp2S3rvmla8mWu7BGJsNWMguA",
          "width": 800
        },
        "dc": {
          "extension": "jpg",
          "height": 461,
          "mimetype": "image/jpeg",
          "secret": "RrQOp0adp2S3rvmla8mWu7BGJsNWMguA",
          "width": 800
        },
        "ds": {
          "extension": "jpg",
          "height": 320,
          "mimetype": "image/jpeg",
          "secret": "RrQOp0adp2S3rvmla8mWu7BGJsNWMguA",
          "width": 320
        },
        "k": {
          "extension": "jpg",
          "height": 1180,
          "mimetype": "image/jpeg",
          "secret": "RrQOp0adp2S3rvmla8mWu7BGJsNWMguA",
          "width": 2048
        },
        "n": {
          "extension": "jpg",
          "height": 184,
          "mimetype": "image/jpeg",
          "secret": "RrQOp0adp2S3rvmla8mWu7BGJsNWMguA",
          "width": 320
        },
        "o": {
          "extension": "jpg",
          "height": 1144,
          "mimetype": "image/jpeg",
          "secret": "ZP6qK5RBHYUyzYDusAPl5zYhX8XYDc87",
          "width": 1985
        },
        "s": {
          "extension": "jpg",
          "height": 320,
          "mimetype": "image/jpeg",
          "secret": "RrQOp0adp2S3rvmla8mWu7BGJsNWMguA",
          "width": 320
        },
        "z": {
          "extension": "jpg",
          "height": 368,
          "mimetype": "image/jpeg",
          "secret": "RrQOp0adp2S3rvmla8mWu7BGJsNWMguA",
          "width": 640
        }
      }
    },
    "media:uri_template": "https://millsfield.sfomuseum.org/media/152/782/943/9/1527829439_{secret}_{label}.{extention}",
    "sfomuseum:filename": "48242.tif",
    "sfomuseum:image_index": 5,
    "sfomuseum:placetype": "image",
    "sfomuseum:primary_image": 1,
    "wof:depicts": [
      1511906979
    ],
    "wof:name": "airmail flight cover: Pan American World Airways, Bangkok - Honolulu route",
    "wof:placetype": "media"
  },
  "geometry": {"coordinates":[-122.386155,37.616358],"type":"Point"}
}
