{
  "type": "Feature",
  "properties": {
    "iso:country": "XX",
    "media:fingerprint": "424dcbec2a8a18f075347270cc2556805a7a6dcb",
    "media:imagehash_avg": "a:ffffe7fefefa00fe",
    "media:imagehash_diff": "d:d88e0e4ee4c24364",
    "media:medium": "image",
    "media:mimetype": "image/tiff",
    "media:properties": {
      "colours": [
        {
          "hex": "#ba1906",
          "name": "#ba1906",
          "reference": "vibrant"
        },
        {
          "hex": "#e1a394",
          "name": "#e1a394",
          "reference": "vibrant"
        },
        {
          "hex": "#782a02",
          "name": "#782a02",
          "reference": "vibrant"
        },
        {
          "hex": "#6b8f74",
          "name": "#6b8f74",
          "reference": "vibrant"
        },
        {
          "hex": "#d7c5ac",
          "name": "#d7c5ac",
          "reference": "vibrant"
        }
      ],
      "sizes": {
        "b": {
          "extension": "jpg",
          "height": 768,
          "mimetype": "image/jpeg",
          "secret": "zHReJHiFpfHhiX0fORVsv2xNw3RmgaW0",
          "width": 594
        },
        "c": {
          "extension": "jpg",
          "height": 600,
          "mimetype": "image/jpeg",
          "secret": "zHReJHiFpfHhiX0fORVsv2xNw3RmgaW0",
          "width": 464
        },
        "dc": {
          "extension": "jpg",
          "height": 600,
          "mimetype": "image/jpeg",
          "secret": "zHReJHiFpfHhiX0fORVsv2xNw3RmgaW0",
          "width": 464
        },
        "ds": {
          "extension": "jpg",
          "height": 320,
          "mimetype": "image/jpeg",
          "secret": "zHReJHiFpfHhiX0fORVsv2xNw3RmgaW0",
          "width": 320
        },
        "k": {
          "extension": "jpg",
          "height": 1536,
          "mimetype": "image/jpeg",
          "secret": "zHReJHiFpfHhiX0fORVsv2xNw3RmgaW0",
          "width": 1188
        },
        "n": {
          "extension": "jpg",
          "height": 240,
          "mimetype": "image/jpeg",
          "secret": "zHReJHiFpfHhiX0fORVsv2xNw3RmgaW0",
          "width": 185
        },
        "o": {
          "extension": "jpg",
          "height": 2310,
          "mimetype": "image/jpeg",
          "secret": "iK9S0uHDu5wPncFmrRtMio85sI656bte",
          "width": 1788
        },
        "s": {
          "extension": "jpg",
          "height": 320,
          "mimetype": "image/jpeg",
          "secret": "zHReJHiFpfHhiX0fORVsv2xNw3RmgaW0",
          "width": 320
        },
        "z": {
          "extension": "jpg",
          "height": 480,
          "mimetype": "image/jpeg",
          "secret": "zHReJHiFpfHhiX0fORVsv2xNw3RmgaW0",
          "width": 371
        }
      }
    },
    "media:uri_template": "https://static.sfomuseum.org/media/152/784/817/7/1527848177_{secret}_{label}.{extention}",
    "sfomuseum:filename": "2006034157_front.tif",
    "sfomuseum:image_index": 5,
    "sfomuseum:image_type": "studio",
    "sfomuseum:placetype": "image",
    "sfomuseum:primary_image": 1,
    "wof:depicts": [
      1159285413,
      1511927789
    ],
    "wof:name": "menu: United Airlines",
    "wof:placetype": "custom",
    "wof:placetype_alt": "image"
  },
  "geometry": {"coordinates":[-122.386155,37.616358],"type":"Point"}
}
