{
  "type": "Feature",
  "properties": {
    "iso:country": "XX",
    "media:fingerprint": "4dd157eaebb76ed3aaec40219311690cae5fde0d",
    "media:imagehash_avg": "a:ff81c3d7970303fd",
    "media:imagehash_diff": "d:4d4d13346d5f7731",
    "media:medium": "image",
    "media:mimetype": "image/tiff",
    "media:properties": {
      "colours": [
        {
          "hex": "#f0d79e",
          "name": "#f0d79e",
          "reference": "vibrant"
        }, 
        {
          "hex": "#564a23",
          "name": "#564a23",
          "reference": "vibrant"
        }, 
        {
          "hex": "#988b62",
          "name": "#988b62",
          "reference": "vibrant"
        }, 
        {
          "hex": "#c6b996",
          "name": "#c6b996",
          "reference": "vibrant"
        }, 
        {
          "hex": "#675c35",
          "name": "#675c35",
          "reference": "vibrant"
        }
      ],
      "sizes": {
        "b": {
          "extension": "jpg",
          "height": 768,
          "mimetype": "image/jpeg",
          "secret": "XFyI0fZ56AyxeUdyDIWNnOt0iHtECbrk",
          "width": 965
        },
        "c": {
          "extension": "jpg",
          "height": 600,
          "mimetype": "image/jpeg",
          "secret": "XFyI0fZ56AyxeUdyDIWNnOt0iHtECbrk",
          "width": 754
        },
        "dc": {
          "extension": "jpg",
          "height": 600,
          "mimetype": "image/jpeg",
          "secret": "XFyI0fZ56AyxeUdyDIWNnOt0iHtECbrk",
          "width": 754
        },
        "ds": {
          "extension": "jpg",
          "height": 320,
          "mimetype": "image/jpeg",
          "secret": "XFyI0fZ56AyxeUdyDIWNnOt0iHtECbrk",
          "width": 320
        },
        "k": {
          "extension": "jpg",
          "height": 1536,
          "mimetype": "image/jpeg",
          "secret": "XFyI0fZ56AyxeUdyDIWNnOt0iHtECbrk",
          "width": 1930
        },
        "n": {
          "extension": "jpg",
          "height": 240,
          "mimetype": "image/jpeg",
          "secret": "XFyI0fZ56AyxeUdyDIWNnOt0iHtECbrk",
          "width": 301
        },
        "o": {
          "extension": "jpg",
          "height": 1161,
          "mimetype": "image/jpeg",
          "secret": "AUglmjogS6x64kQClw5hjVejNnUa3mUA",
          "width": 1459
        },
        "s": {
          "extension": "jpg",
          "height": 320,
          "mimetype": "image/jpeg",
          "secret": "XFyI0fZ56AyxeUdyDIWNnOt0iHtECbrk",
          "width": 320
        },
        "z": {
          "extension": "jpg",
          "height": 480,
          "mimetype": "image/jpeg",
          "secret": "XFyI0fZ56AyxeUdyDIWNnOt0iHtECbrk",
          "width": 603
        }
      }
    },
    "media:uri_template": "https://millsfield.sfomuseum.org/media/152/782/041/3/1527820413_{secret}_{label}.{extention}",
    "sfomuseum:filename": "31598.tif",
    "sfomuseum:image_index": 5,
    "sfomuseum:placetype": "image",
    "sfomuseum:primary_image": 0,
    "wof:depicts": [
      1511924619
    ],
    "wof:name": "airmail flight cover: Pan American Airways, first airmail flight, Auckland - Pago Pago (Samoa) route",
    "wof:placetype": "media"
  },
  "geometry": {"coordinates":[-122.386155,37.616358],"type":"Point"}
}
