{
  "type": "Feature",
  "properties": {
    "iso:country": "XX",
    "media:fingerprint": "507a1c1a877300c4dc1011efc48ceec6bf135823",
    "media:imagehash_avg": "a:fffef08040c04000",
    "media:imagehash_diff": "d:0000002080008000",
    "media:medium": "image",
    "media:mimetype": "image/tiff",
    "media:properties": {
      "colours": [
        {
          "hex": "#787878",
          "name": "#787878",
          "reference": "vibrant"
        }, 
        {
          "hex": "#c0c0c0",
          "name": "#c0c0c0",
          "reference": "vibrant"
        }, 
        {
          "hex": "#464646",
          "name": "#464646",
          "reference": "vibrant"
        }
      ],
      "sizes": {
        "b": {
          "extension": "jpg",
          "height": 767,
          "mimetype": "image/jpeg",
          "secret": "b4vWc9nNU4xktIx7diNn4eNxBsHVOjic",
          "width": 978
        },
        "c": {
          "extension": "jpg",
          "height": 600,
          "mimetype": "image/jpeg",
          "secret": "b4vWc9nNU4xktIx7diNn4eNxBsHVOjic",
          "width": 764
        },
        "dc": {
          "extension": "jpg",
          "height": 600,
          "mimetype": "image/jpeg",
          "secret": "b4vWc9nNU4xktIx7diNn4eNxBsHVOjic",
          "width": 764
        },
        "ds": {
          "extension": "jpg",
          "height": 320,
          "mimetype": "image/jpeg",
          "secret": "b4vWc9nNU4xktIx7diNn4eNxBsHVOjic",
          "width": 320
        },
        "k": {
          "extension": "jpg",
          "height": 1535,
          "mimetype": "image/jpeg",
          "secret": "b4vWc9nNU4xktIx7diNn4eNxBsHVOjic",
          "width": 1957
        },
        "n": {
          "extension": "jpg",
          "height": 240,
          "mimetype": "image/jpeg",
          "secret": "b4vWc9nNU4xktIx7diNn4eNxBsHVOjic",
          "width": 305
        },
        "o": {
          "extension": "jpg",
          "height": 2140,
          "mimetype": "image/jpeg",
          "secret": "W13M6K7XJcqSH5PJ17KM4na24UEJuLZk",
          "width": 2727
        },
        "s": {
          "extension": "jpg",
          "height": 320,
          "mimetype": "image/jpeg",
          "secret": "b4vWc9nNU4xktIx7diNn4eNxBsHVOjic",
          "width": 320
        },
        "z": {
          "extension": "jpg",
          "height": 480,
          "mimetype": "image/jpeg",
          "secret": "b4vWc9nNU4xktIx7diNn4eNxBsHVOjic",
          "width": 611
        }
      }
    },
    "media:uri_template": "https://millsfield.sfomuseum.org/media/152/782/501/1/1527825011_{secret}_{label}.{extention}",
    "sfomuseum:filename": "42925.tif",
    "sfomuseum:image_index": 5,
    "sfomuseum:placetype": "image",
    "sfomuseum:primary_image": 1,
    "wof:depicts": [
      1511945921
    ],
    "wof:name": "negative: San Francisco International Airport (SFO), aerial",
    "wof:placetype": "media"
  },
  "geometry": {"coordinates":[-122.386155,37.616358],"type":"Point"}
}
