{
  "type": "Feature",
  "properties": {
    "iso:country": "XX",
    "media:fingerprint": "55830cd8337e8cd241c2859b7a245970e05b259f",
    "media:imagehash_avg": "a:fffbf19910808081",
    "media:imagehash_diff": "d:73c1457171276167",
    "media:medium": "image",
    "media:mimetype": "image/tiff",
    "media:properties": {
      "colours": [
        {
          "hex": "#e8eff4",
          "name": "#e8eff4",
          "reference": "vibrant"
        },
        {
          "hex": "#86837b",
          "name": "#86837b",
          "reference": "vibrant"
        },
        {
          "hex": "#c4c0b5",
          "name": "#c4c0b5",
          "reference": "vibrant"
        },
        {
          "hex": "#423f3a",
          "name": "#423f3a",
          "reference": "vibrant"
        }
      ],
      "sizes": {
        "b": {
          "extension": "jpg",
          "height": 768,
          "mimetype": "image/jpeg",
          "secret": "MObr2bIwMsXljKTYJ2oie4auqDm12ARz",
          "width": 938
        },
        "c": {
          "extension": "jpg",
          "height": 600,
          "mimetype": "image/jpeg",
          "secret": "MObr2bIwMsXljKTYJ2oie4auqDm12ARz",
          "width": 733
        },
        "dc": {
          "extension": "jpg",
          "height": 600,
          "mimetype": "image/jpeg",
          "secret": "MObr2bIwMsXljKTYJ2oie4auqDm12ARz",
          "width": 733
        },
        "ds": {
          "extension": "jpg",
          "height": 320,
          "mimetype": "image/jpeg",
          "secret": "MObr2bIwMsXljKTYJ2oie4auqDm12ARz",
          "width": 320
        },
        "k": {
          "extension": "jpg",
          "height": 1536,
          "mimetype": "image/jpeg",
          "secret": "MObr2bIwMsXljKTYJ2oie4auqDm12ARz",
          "width": 1877
        },
        "n": {
          "extension": "jpg",
          "height": 240,
          "mimetype": "image/jpeg",
          "secret": "MObr2bIwMsXljKTYJ2oie4auqDm12ARz",
          "width": 293
        },
        "o": {
          "extension": "jpg",
          "height": 2448,
          "mimetype": "image/jpeg",
          "secret": "UgvztAk4xkBMXwHaLSKrLlY9XmdiWzEC",
          "width": 2993
        },
        "s": {
          "extension": "jpg",
          "height": 320,
          "mimetype": "image/jpeg",
          "secret": "MObr2bIwMsXljKTYJ2oie4auqDm12ARz",
          "width": 320
        },
        "z": {
          "extension": "jpg",
          "height": 480,
          "mimetype": "image/jpeg",
          "secret": "MObr2bIwMsXljKTYJ2oie4auqDm12ARz",
          "width": 586
        }
      }
    },
    "media:uri_template": "https://static.sfomuseum.org/media/152/783/041/9/1527830419_{secret}_{label}.{extention}",
    "sfomuseum:filename": "53690.tif",
    "sfomuseum:image_index": 0,
    "sfomuseum:image_type": "studio",
    "sfomuseum:placetype": "image",
    "sfomuseum:primary_image": 1,
    "wof:depicts": [
      1511910161,
      1360695653
    ],
    "wof:name": "photograph: Mills Field area, residential property",
    "wof:placetype": "custom",
    "wof:placetype_alt": "image"
  },
  "geometry": {"coordinates":[-122.386155,37.616358],"type":"Point"}
}
