{
  "type": "Feature",
  "properties": {
    "iso:country": "XX",
    "media:fingerprint": "eafa403206e7e8f74f6b6b4af90aaeb24fc482c8",
    "media:imagehash_avg": "a:000103fffffffefe",
    "media:imagehash_diff": "d:860717b7b7b69282",
    "media:medium": "image",
    "media:mimetype": "image/jpeg",
    "media:properties": {
      "colours": [
        {
          "hex": "#83603f",
          "name": "#83603f",
          "reference": "vibrant"
        }, 
        {
          "hex": "#dee8f0",
          "name": "#dee8f0",
          "reference": "vibrant"
        }, 
        {
          "hex": "#a1815b",
          "name": "#a1815b",
          "reference": "vibrant"
        }, 
        {
          "hex": "#b5bac4",
          "name": "#b5bac4",
          "reference": "vibrant"
        }, 
        {
          "hex": "#40444a",
          "name": "#40444a",
          "reference": "vibrant"
        }
      ],
      "sizes": {
        "b": {
          "extension": "jpg",
          "height": 768,
          "mimetype": "image/jpeg",
          "secret": "DdubY3wKeX21uASpsot6QxzMVkVYHw5N",
          "width": 586
        },
        "c": {
          "extension": "jpg",
          "height": 600,
          "mimetype": "image/jpeg",
          "secret": "DdubY3wKeX21uASpsot6QxzMVkVYHw5N",
          "width": 458
        },
        "dc": {
          "extension": "jpg",
          "height": 600,
          "mimetype": "image/jpeg",
          "secret": "DdubY3wKeX21uASpsot6QxzMVkVYHw5N",
          "width": 458
        },
        "ds": {
          "extension": "jpg",
          "height": 320,
          "mimetype": "image/jpeg",
          "secret": "DdubY3wKeX21uASpsot6QxzMVkVYHw5N",
          "width": 320
        },
        "k": {
          "extension": "jpg",
          "height": 1536,
          "mimetype": "image/jpeg",
          "secret": "DdubY3wKeX21uASpsot6QxzMVkVYHw5N",
          "width": 1173
        },
        "n": {
          "extension": "jpg",
          "height": 240,
          "mimetype": "image/jpeg",
          "secret": "DdubY3wKeX21uASpsot6QxzMVkVYHw5N",
          "width": 183
        },
        "o": {
          "extension": "jpg",
          "height": 1807,
          "mimetype": "image/jpeg",
          "secret": "phtAJESIsq021LOC74PEiYEC2R0togF9",
          "width": 1380
        },
        "s": {
          "extension": "jpg",
          "height": 320,
          "mimetype": "image/jpeg",
          "secret": "DdubY3wKeX21uASpsot6QxzMVkVYHw5N",
          "width": 320
        },
        "z": {
          "extension": "jpg",
          "height": 480,
          "mimetype": "image/jpeg",
          "secret": "DdubY3wKeX21uASpsot6QxzMVkVYHw5N",
          "width": 366
        }
      }
    },
    "media:uri_template": "https://millsfield.sfomuseum.org/media/152/782/919/9/1527829199_{secret}_{label}.{extention}",
    "sfomuseum:filename": "47562.jpg",
    "sfomuseum:image_index": 5,
    "sfomuseum:placetype": "image",
    "sfomuseum:primary_image": 1,
    "wof:depicts": [
      1511951153
    ],
    "wof:name": "advertisement: Pan American Airways, The Living Age",
    "wof:placetype": "media"
  },
  "geometry": {"coordinates":[-122.386155,37.616358],"type":"Point"}
}
