{
  "type": "Feature",
  "properties": {
    "iso:country": "XX",
    "media:fingerprint": "453aa7c8faa40b5d16e152968a809559fef86b45",
    "media:imagehash_avg": "a:0000001fffff3f3e",
    "media:imagehash_diff": "d:fefff9f270f0f0f0",
    "media:medium": "image",
    "media:mimetype": "image/tiff",
    "media:properties": {
      "colours": [
        {
          "hex": "#808080",
          "name": "#808080",
          "reference": "vibrant"
        },
        {
          "hex": "#b8b8b8",
          "name": "#b8b8b8",
          "reference": "vibrant"
        },
        {
          "hex": "#404040",
          "name": "#404040",
          "reference": "vibrant"
        }
      ],
      "sizes": {
        "b": {
          "extension": "jpg",
          "height": 768,
          "mimetype": "image/jpeg",
          "secret": "mnWRz9zUk3udIfDAVOLXyHqFBG30jl43",
          "width": 981
        },
        "c": {
          "extension": "jpg",
          "height": 600,
          "mimetype": "image/jpeg",
          "secret": "mnWRz9zUk3udIfDAVOLXyHqFBG30jl43",
          "width": 767
        },
        "dc": {
          "extension": "jpg",
          "height": 600,
          "mimetype": "image/jpeg",
          "secret": "mnWRz9zUk3udIfDAVOLXyHqFBG30jl43",
          "width": 767
        },
        "ds": {
          "extension": "jpg",
          "height": 320,
          "mimetype": "image/jpeg",
          "secret": "mnWRz9zUk3udIfDAVOLXyHqFBG30jl43",
          "width": 320
        },
        "k": {
          "extension": "jpg",
          "height": 1536,
          "mimetype": "image/jpeg",
          "secret": "mnWRz9zUk3udIfDAVOLXyHqFBG30jl43",
          "width": 1963
        },
        "n": {
          "extension": "jpg",
          "height": 240,
          "mimetype": "image/jpeg",
          "secret": "mnWRz9zUk3udIfDAVOLXyHqFBG30jl43",
          "width": 306
        },
        "o": {
          "extension": "jpg",
          "height": 2154,
          "mimetype": "image/jpeg",
          "secret": "4mazBqBCqbRwut0OFRWyoT8lEQBs3PbY",
          "width": 2754
        },
        "s": {
          "extension": "jpg",
          "height": 320,
          "mimetype": "image/jpeg",
          "secret": "mnWRz9zUk3udIfDAVOLXyHqFBG30jl43",
          "width": 320
        },
        "z": {
          "extension": "jpg",
          "height": 480,
          "mimetype": "image/jpeg",
          "secret": "mnWRz9zUk3udIfDAVOLXyHqFBG30jl43",
          "width": 613
        }
      }
    },
    "media:uri_template": "https://static.sfomuseum.org/media/152/782/437/7/1527824377_{secret}_{label}.{extention}",
    "sfomuseum:filename": "42395.tif",
    "sfomuseum:image_index": 5,
    "sfomuseum:image_type": "studio",
    "sfomuseum:placetype": "image",
    "sfomuseum:primary_image": 1,
    "wof:depicts": [
      102527513,
      1511945699
    ],
    "wof:name": "negative: San Francisco",
    "wof:placetype": "custom",
    "wof:placetype_alt": "image"
  },
  "geometry": {"coordinates":[-122.386155,37.616358],"type":"Point"}
}
