{
  "type": "Feature",
  "properties": {
    "iso:country": "XX",
    "media:fingerprint": "83f8ed8d8502cf4192e19c9df4ed832ce395b84e",
    "media:imagehash_avg": "a:ffff3f17c3100083",
    "media:imagehash_diff": "d:562e7e3616725f0e",
    "media:medium": "image",
    "media:mimetype": "image/tiff",
    "media:properties": {
      "colours": [
        {
          "hex": "#d15f14",
          "name": "#d15f14",
          "reference": "vibrant"
        },
        {
          "hex": "#e9be88",
          "name": "#e9be88",
          "reference": "vibrant"
        },
        {
          "hex": "#852a1b",
          "name": "#852a1b",
          "reference": "vibrant"
        },
        {
          "hex": "#8c6d7f",
          "name": "#8c6d7f",
          "reference": "vibrant"
        },
        {
          "hex": "#cab9bd",
          "name": "#cab9bd",
          "reference": "vibrant"
        }
      ],
      "sizes": {
        "b": {
          "extension": "jpg",
          "height": 768,
          "mimetype": "image/jpeg",
          "secret": "TJf2fqBXE0utxrAa7EnemcRfUuw3Zkax",
          "width": 439
        },
        "c": {
          "extension": "jpg",
          "height": 600,
          "mimetype": "image/jpeg",
          "secret": "TJf2fqBXE0utxrAa7EnemcRfUuw3Zkax",
          "width": 342
        },
        "dc": {
          "extension": "jpg",
          "height": 600,
          "mimetype": "image/jpeg",
          "secret": "TJf2fqBXE0utxrAa7EnemcRfUuw3Zkax",
          "width": 342
        },
        "ds": {
          "extension": "jpg",
          "height": 320,
          "mimetype": "image/jpeg",
          "secret": "TJf2fqBXE0utxrAa7EnemcRfUuw3Zkax",
          "width": 320
        },
        "k": {
          "extension": "jpg",
          "height": 1536,
          "mimetype": "image/jpeg",
          "secret": "TJf2fqBXE0utxrAa7EnemcRfUuw3Zkax",
          "width": 878
        },
        "n": {
          "extension": "jpg",
          "height": 240,
          "mimetype": "image/jpeg",
          "secret": "TJf2fqBXE0utxrAa7EnemcRfUuw3Zkax",
          "width": 137
        },
        "o": {
          "extension": "jpg",
          "height": 2904,
          "mimetype": "image/jpeg",
          "secret": "a5h1yRrxsc2b7HqhKm8lUzf5lIV8z1wr",
          "width": 1660
        },
        "s": {
          "extension": "jpg",
          "height": 320,
          "mimetype": "image/jpeg",
          "secret": "TJf2fqBXE0utxrAa7EnemcRfUuw3Zkax",
          "width": 320
        },
        "z": {
          "extension": "jpg",
          "height": 480,
          "mimetype": "image/jpeg",
          "secret": "TJf2fqBXE0utxrAa7EnemcRfUuw3Zkax",
          "width": 274
        }
      }
    },
    "media:uri_template": "https://static.sfomuseum.org/media/152/784/619/7/1527846197_{secret}_{label}.{extention}",
    "sfomuseum:filename": "70778.tif",
    "sfomuseum:image_index": 5,
    "sfomuseum:image_type": "studio",
    "sfomuseum:placetype": "image",
    "sfomuseum:primary_image": 1,
    "wof:depicts": [
      1511928545,
      1159285413
    ],
    "wof:name": "menu: United Airlines, First Class",
    "wof:placetype": "custom",
    "wof:placetype_alt": "image"
  },
  "geometry": {"coordinates":[-122.386155,37.616358],"type":"Point"}
}
