{
  "type": "Feature",
  "properties": {
    "iso:country": "XX",
    "media:fingerprint": "7343150edae623859db2b9e74686296d026f3c83",
    "media:imagehash_avg": "a:ffff700000000000",
    "media:imagehash_diff": "d:c0808191dde18793",
    "media:medium": "image",
    "media:mimetype": "image/tiff",
    "media:properties": {
      "colours": [
        {
          "hex": "#808080",
          "name": "#808080",
          "reference": "vibrant"
        }, 
        {
          "hex": "#c0c0c0",
          "name": "#c0c0c0",
          "reference": "vibrant"
        }, 
        {
          "hex": "#404040",
          "name": "#404040",
          "reference": "vibrant"
        }
      ],
      "sizes": {
        "b": {
          "extension": "jpg",
          "height": 671,
          "mimetype": "image/jpeg",
          "secret": "5OrzCZhTzWoGDUh4fRh06vaWw4dCoFhZ",
          "width": 1024
        },
        "c": {
          "extension": "jpg",
          "height": 524,
          "mimetype": "image/jpeg",
          "secret": "5OrzCZhTzWoGDUh4fRh06vaWw4dCoFhZ",
          "width": 800
        },
        "dc": {
          "extension": "jpg",
          "height": 524,
          "mimetype": "image/jpeg",
          "secret": "5OrzCZhTzWoGDUh4fRh06vaWw4dCoFhZ",
          "width": 800
        },
        "ds": {
          "extension": "jpg",
          "height": 320,
          "mimetype": "image/jpeg",
          "secret": "5OrzCZhTzWoGDUh4fRh06vaWw4dCoFhZ",
          "width": 320
        },
        "k": {
          "extension": "jpg",
          "height": 1343,
          "mimetype": "image/jpeg",
          "secret": "5OrzCZhTzWoGDUh4fRh06vaWw4dCoFhZ",
          "width": 2048
        },
        "n": {
          "extension": "jpg",
          "height": 209,
          "mimetype": "image/jpeg",
          "secret": "5OrzCZhTzWoGDUh4fRh06vaWw4dCoFhZ",
          "width": 320
        },
        "o": {
          "extension": "jpg",
          "height": 5584,
          "mimetype": "image/jpeg",
          "secret": "p3L4q7uC8gJkbfpuZ2kSCtamuac8PISq",
          "width": 8515
        },
        "s": {
          "extension": "jpg",
          "height": 320,
          "mimetype": "image/jpeg",
          "secret": "5OrzCZhTzWoGDUh4fRh06vaWw4dCoFhZ",
          "width": 320
        },
        "z": {
          "extension": "jpg",
          "height": 419,
          "mimetype": "image/jpeg",
          "secret": "5OrzCZhTzWoGDUh4fRh06vaWw4dCoFhZ",
          "width": 640
        }
      }
    },
    "media:uri_template": "https://millsfield.sfomuseum.org/media/152/782/126/1/1527821261_{secret}_{label}.{extention}",
    "sfomuseum:filename": "38658.tif",
    "sfomuseum:image_index": 5,
    "sfomuseum:placetype": "image",
    "sfomuseum:primary_image": 1,
    "wof:depicts": [
      1511949757
    ],
    "wof:name": "negative: Mills Field Municipal Airport of San Francisco",
    "wof:placetype": "media"
  },
  "geometry": {"coordinates":[-122.386155,37.616358],"type":"Point"}
}
