{
  "type": "Feature",
  "properties": {
    "iso:country":"XX",
    "media:medium":"image",
    "sfomuseum:filename":"58117.tif",
    "sfomuseum:image_index":5,
    "sfomuseum:placetype":"image",
    "sfomuseum:primary_image":0,
    "wof:depicts":[
        1511955175
    ],
    "wof:name":"career history questionnaire: World Wings International, Dian Stirn Groh",
    "wof:placetype":"media"
},
  "geometry": {"coordinates":[-122.386155,37.616358],"type":"Point"}
}