{
  "type": "Feature",
  "properties": {
    "iso:country": "XX",
    "media:fingerprint": "c1d2b9dcef5d228903878ca26426dbd0d70dc814",
    "media:imagehash_avg": "a:7f71711f5f1b0101",
    "media:imagehash_diff": "d:cfd3d397939397d3",
    "media:medium": "image",
    "media:mimetype": "image/tiff",
    "media:properties": {
      "colours": [
        {
          "hex": "#5582b0",
          "name": "#5582b0",
          "reference": "vibrant"
        }, 
        {
          "hex": "#e3d8b8",
          "name": "#e3d8b8",
          "reference": "vibrant"
        }, 
        {
          "hex": "#375585",
          "name": "#375585",
          "reference": "vibrant"
        }, 
        {
          "hex": "#6f7f90",
          "name": "#6f7f90",
          "reference": "vibrant"
        }, 
        {
          "hex": "#d8cab1",
          "name": "#d8cab1",
          "reference": "vibrant"
        }
      ],
      "sizes": {
        "b": {
          "extension": "jpg",
          "height": 768,
          "mimetype": "image/jpeg",
          "secret": "XrK1QHc0lh3evpAsJrADRWNBWJsgWDv0",
          "width": 390
        },
        "c": {
          "extension": "jpg",
          "height": 600,
          "mimetype": "image/jpeg",
          "secret": "XrK1QHc0lh3evpAsJrADRWNBWJsgWDv0",
          "width": 305
        },
        "dc": {
          "extension": "jpg",
          "height": 600,
          "mimetype": "image/jpeg",
          "secret": "XrK1QHc0lh3evpAsJrADRWNBWJsgWDv0",
          "width": 305
        },
        "ds": {
          "extension": "jpg",
          "height": 320,
          "mimetype": "image/jpeg",
          "secret": "XrK1QHc0lh3evpAsJrADRWNBWJsgWDv0",
          "width": 320
        },
        "k": {
          "extension": "jpg",
          "height": 1536,
          "mimetype": "image/jpeg",
          "secret": "XrK1QHc0lh3evpAsJrADRWNBWJsgWDv0",
          "width": 781
        },
        "n": {
          "extension": "jpg",
          "height": 240,
          "mimetype": "image/jpeg",
          "secret": "XrK1QHc0lh3evpAsJrADRWNBWJsgWDv0",
          "width": 122
        },
        "o": {
          "extension": "jpg",
          "height": 2933,
          "mimetype": "image/jpeg",
          "secret": "43VuV9tH1dIcQyMqJ5KtZTFGc5EKylBn",
          "width": 1493
        },
        "s": {
          "extension": "jpg",
          "height": 320,
          "mimetype": "image/jpeg",
          "secret": "XrK1QHc0lh3evpAsJrADRWNBWJsgWDv0",
          "width": 320
        },
        "z": {
          "extension": "jpg",
          "height": 480,
          "mimetype": "image/jpeg",
          "secret": "XrK1QHc0lh3evpAsJrADRWNBWJsgWDv0",
          "width": 244
        }
      }
    },
    "media:uri_template": "https://millsfield.sfomuseum.org/media/152/782/373/5/1527823735_{secret}_{label}.{extention}",
    "sfomuseum:filename": "41766.tif",
    "sfomuseum:image_index": 5,
    "sfomuseum:placetype": "image",
    "sfomuseum:primary_image": 0,
    "wof:depicts": [
      1511908487
    ],
    "wof:name": "airsickness bag: CAAC (Civil Aviation Administration of China)",
    "wof:placetype": "media"
  },
  "geometry": {"coordinates":[-122.386155,37.616358],"type":"Point"}
}
