{
  "type": "Feature",
  "properties": {
    "sfomuseum:filename": "19341.JPG",
    "sfomuseum:image_index": 1,
    "sfomuseum:image_type": "curator",
    "sfomuseum:placetype": "image",
    "sfomuseum:primary_image": 1,
    "wof:depicts": [
      1511942359,
      1159285551
    ],
    "wof:name": "retractable ID clip: World Airways",
    "wof:placetype": "custom"
  },
  "geometry": {"coordinates":[-122.386155,37.616357],"type":"Point"}
}
