{
  "type": "Feature",
  "properties": {
    "date:cessation_lower": "1960-01-01",
    "date:cessation_upper": "1969-12-31",
    "date:inception_lower": "1960-01-01",
    "date:inception_upper": "1969-12-31",
    "iso:country": "XX",
    "media:imagehash_avg": "a:ef8381918181c3ff",
    "media:imagehash_diff": "d:8f0f37636f0f0f0e",
    "media:mimetype": "image/jpeg",
    "media:properties": {
    },
    "media:uri_template": "https://static.sfomuseum.org/media/174/668/013/1/1746680131_{secret}_{label}.{extention}",
    "sfomuseum:filename": "13093.jpg",
    "sfomuseum:image_index": 1,
    "sfomuseum:image_type": "studio",
    "sfomuseum:placetype": "image",
    "sfomuseum:primary_image": 1,
    "wof:depicts": [
      1159287479,
      1729563859,
      1159285043
    ],
    "wof:name": "disk: Qantas Airways",
    "wof:placetype": "custom"
  },
  "geometry": {"coordinates":[-122.386155,37.616357],"type":"Point"}
}
