{
  "type": "Feature",
  "properties": {
    "iso:country": "XX",
    "media:fingerprint": "fe06123076ab3fe34286da6d4493238c500d670f",
    "media:imagehash_avg": "a:01f8f0fdffffff01",
    "media:imagehash_diff": "d:63a121b1303a985b",
    "media:medium": "image",
    "media:mimetype": "image/tiff",
    "media:properties": {
      "colours": [
        {
          "hex": "#df2512",
          "name": "#df2512",
          "reference": "vibrant"
        }, 
        {
          "hex": "#f2ceb2",
          "name": "#f2ceb2",
          "reference": "vibrant"
        }, 
        {
          "hex": "#c1210f",
          "name": "#c1210f",
          "reference": "vibrant"
        }, 
        {
          "hex": "#91755a",
          "name": "#91755a",
          "reference": "vibrant"
        }, 
        {
          "hex": "#bcc7b4",
          "name": "#bcc7b4",
          "reference": "vibrant"
        }
      ],
      "sizes": {
        "b": {
          "extension": "jpg",
          "height": 460,
          "mimetype": "image/jpeg",
          "secret": "x3K3PdPhADn2ynsfW0hwpQ9i3s01gClG",
          "width": 1024
        },
        "c": {
          "extension": "jpg",
          "height": 359,
          "mimetype": "image/jpeg",
          "secret": "x3K3PdPhADn2ynsfW0hwpQ9i3s01gClG",
          "width": 800
        },
        "dc": {
          "extension": "jpg",
          "height": 359,
          "mimetype": "image/jpeg",
          "secret": "x3K3PdPhADn2ynsfW0hwpQ9i3s01gClG",
          "width": 800
        },
        "ds": {
          "extension": "jpg",
          "height": 320,
          "mimetype": "image/jpeg",
          "secret": "x3K3PdPhADn2ynsfW0hwpQ9i3s01gClG",
          "width": 320
        },
        "k": {
          "extension": "jpg",
          "height": 921,
          "mimetype": "image/jpeg",
          "secret": "x3K3PdPhADn2ynsfW0hwpQ9i3s01gClG",
          "width": 2048
        },
        "n": {
          "extension": "jpg",
          "height": 143,
          "mimetype": "image/jpeg",
          "secret": "x3K3PdPhADn2ynsfW0hwpQ9i3s01gClG",
          "width": 320
        },
        "o": {
          "extension": "jpg",
          "height": 1325,
          "mimetype": "image/jpeg",
          "secret": "DgUb6IY1yU9LFLB709SkXZMQdqfWTLn2",
          "width": 2946
        },
        "s": {
          "extension": "jpg",
          "height": 320,
          "mimetype": "image/jpeg",
          "secret": "x3K3PdPhADn2ynsfW0hwpQ9i3s01gClG",
          "width": 320
        },
        "z": {
          "extension": "jpg",
          "height": 287,
          "mimetype": "image/jpeg",
          "secret": "x3K3PdPhADn2ynsfW0hwpQ9i3s01gClG",
          "width": 640
        }
      }
    },
    "media:uri_template": "https://millsfield.sfomuseum.org/media/152/782/911/5/1527829115_{secret}_{label}.{extention}",
    "sfomuseum:filename": "47524.tif",
    "sfomuseum:image_index": 5,
    "sfomuseum:placetype": "image",
    "sfomuseum:primary_image": 1,
    "wof:depicts": [
      1511907267
    ],
    "wof:name": "airmail flight cover: Pan American Airways, first airmail flight, Noumea (New Caledonia) - Canton Island route",
    "wof:placetype": "media"
  },
  "geometry": {"coordinates":[-122.386155,37.616358],"type":"Point"}
}
