{
  "type": "Feature",
  "properties": {
    "iso:country": "XX",
    "media:fingerprint": "4df9941aebcd436de5c483746cca4185f6a7d997",
    "media:imagehash_avg": "a:ff818181818181ff",
    "media:imagehash_diff": "d:39357d7f475f7531",
    "media:medium": "image",
    "media:mimetype": "image/tiff",
    "media:properties": {
      "colours": [
        {
          "hex": "#f5ebcd",
          "name": "#f5ebcd",
          "reference": "vibrant"
        },
        {
          "hex": "#1b1a0b",
          "name": "#1b1a0b",
          "reference": "vibrant"
        },
        {
          "hex": "#988b68",
          "name": "#988b68",
          "reference": "vibrant"
        },
        {
          "hex": "#ccc4a5",
          "name": "#ccc4a5",
          "reference": "vibrant"
        },
        {
          "hex": "#49442a",
          "name": "#49442a",
          "reference": "vibrant"
        }
      ],
      "sizes": {
        "b": {
          "extension": "jpg",
          "height": 740,
          "mimetype": "image/jpeg",
          "secret": "RF2B1X8H9Vew96pn8WGFVBHGpXp78zVg",
          "width": 1024
        },
        "c": {
          "extension": "jpg",
          "height": 578,
          "mimetype": "image/jpeg",
          "secret": "RF2B1X8H9Vew96pn8WGFVBHGpXp78zVg",
          "width": 800
        },
        "dc": {
          "extension": "jpg",
          "height": 578,
          "mimetype": "image/jpeg",
          "secret": "RF2B1X8H9Vew96pn8WGFVBHGpXp78zVg",
          "width": 800
        },
        "ds": {
          "extension": "jpg",
          "height": 320,
          "mimetype": "image/jpeg",
          "secret": "RF2B1X8H9Vew96pn8WGFVBHGpXp78zVg",
          "width": 320
        },
        "k": {
          "extension": "jpg",
          "height": 1481,
          "mimetype": "image/jpeg",
          "secret": "RF2B1X8H9Vew96pn8WGFVBHGpXp78zVg",
          "width": 2048
        },
        "n": {
          "extension": "jpg",
          "height": 231,
          "mimetype": "image/jpeg",
          "secret": "RF2B1X8H9Vew96pn8WGFVBHGpXp78zVg",
          "width": 320
        },
        "o": {
          "extension": "jpg",
          "height": 1535,
          "mimetype": "image/jpeg",
          "secret": "bkaKk7JYRl4WU0yGYkeV9WJjEt3Ca36a",
          "width": 2122
        },
        "s": {
          "extension": "jpg",
          "height": 320,
          "mimetype": "image/jpeg",
          "secret": "RF2B1X8H9Vew96pn8WGFVBHGpXp78zVg",
          "width": 320
        },
        "z": {
          "extension": "jpg",
          "height": 462,
          "mimetype": "image/jpeg",
          "secret": "RF2B1X8H9Vew96pn8WGFVBHGpXp78zVg",
          "width": 640
        }
      }
    },
    "media:uri_template": "https://static.sfomuseum.org/media/152/785/567/7/1527855677_{secret}_{label}.{extention}",
    "sfomuseum:filename": "2010.174.327.tif",
    "sfomuseum:image_index": 5,
    "sfomuseum:image_type": "studio",
    "sfomuseum:placetype": "image",
    "sfomuseum:primary_image": 1,
    "wof:depicts": [
      1511942523
    ],
    "wof:name": "photograph: San Francisco Bay Area aerial, South of Market",
    "wof:placetype": "custom",
    "wof:placetype_alt": "image"
  },
  "geometry": {"coordinates":[-122.386155,37.616358],"type":"Point"}
}
