{
  "type": "Feature",
  "properties": {
    "iso:country": "XX",
    "media:fingerprint": "ff72452b801bad10812dbcc059a24536de3d29d9",
    "media:imagehash_avg": "a:ff8181818181bdff",
    "media:imagehash_diff": "d:0f33230303256521",
    "media:medium": "image",
    "media:mimetype": "image/tiff",
    "media:properties": {
      "colours": [
        {
          "hex": "#d30000",
          "name": "#d30000",
          "reference": "vibrant"
        },
        {
          "hex": "#eba29c",
          "name": "#eba29c",
          "reference": "vibrant"
        },
        {
          "hex": "#912617",
          "name": "#912617",
          "reference": "vibrant"
        },
        {
          "hex": "#b45955",
          "name": "#b45955",
          "reference": "vibrant"
        },
        {
          "hex": "#b5a293",
          "name": "#b5a293",
          "reference": "vibrant"
        }
      ],
      "sizes": {
        "b": {
          "extension": "jpg",
          "height": 768,
          "mimetype": "image/jpeg",
          "secret": "9JYcC7qJu7xgHmtg2IdNqB5hc1C3A2N4",
          "width": 544
        },
        "c": {
          "extension": "jpg",
          "height": 600,
          "mimetype": "image/jpeg",
          "secret": "9JYcC7qJu7xgHmtg2IdNqB5hc1C3A2N4",
          "width": 425
        },
        "dc": {
          "extension": "jpg",
          "height": 600,
          "mimetype": "image/jpeg",
          "secret": "9JYcC7qJu7xgHmtg2IdNqB5hc1C3A2N4",
          "width": 425
        },
        "ds": {
          "extension": "jpg",
          "height": 320,
          "mimetype": "image/jpeg",
          "secret": "9JYcC7qJu7xgHmtg2IdNqB5hc1C3A2N4",
          "width": 320
        },
        "k": {
          "extension": "jpg",
          "height": 1536,
          "mimetype": "image/jpeg",
          "secret": "9JYcC7qJu7xgHmtg2IdNqB5hc1C3A2N4",
          "width": 1089
        },
        "n": {
          "extension": "jpg",
          "height": 240,
          "mimetype": "image/jpeg",
          "secret": "9JYcC7qJu7xgHmtg2IdNqB5hc1C3A2N4",
          "width": 170
        },
        "o": {
          "extension": "jpg",
          "height": 2163,
          "mimetype": "image/jpeg",
          "secret": "e9aLgTKgFc0GJzHvRPsNLorhwT69gRzI",
          "width": 1534
        },
        "s": {
          "extension": "jpg",
          "height": 320,
          "mimetype": "image/jpeg",
          "secret": "9JYcC7qJu7xgHmtg2IdNqB5hc1C3A2N4",
          "width": 320
        },
        "z": {
          "extension": "jpg",
          "height": 480,
          "mimetype": "image/jpeg",
          "secret": "9JYcC7qJu7xgHmtg2IdNqB5hc1C3A2N4",
          "width": 340
        }
      }
    },
    "media:uri_template": "https://static.sfomuseum.org/media/152/784/647/9/1527846479_{secret}_{label}.{extention}",
    "sfomuseum:filename": "2006059307245_front.tif",
    "sfomuseum:image_index": 5,
    "sfomuseum:image_type": "studio",
    "sfomuseum:placetype": "image",
    "sfomuseum:primary_image": 1,
    "wof:depicts": [
      1159285415,
      1159285413,
      1511928601,
      1159288779
    ],
    "wof:name": "menu: United Airlines",
    "wof:placetype": "custom",
    "wof:placetype_alt": "image"
  },
  "geometry": {"coordinates":[-122.386155,37.616358],"type":"Point"}
}
