{
  "type": "Feature",
  "properties": {
    "sfomuseum:filename": "15425.JPG",
    "sfomuseum:image_index": 1,
    "sfomuseum:image_type": "curator",
    "sfomuseum:placetype": "image",
    "sfomuseum:primary_image": 1,
    "wof:depicts": [
      1159286839,
      1159284991,
      1511910287
    ],
    "wof:name": "propeller tip desk clock: Pan American Airways",
    "wof:placetype": "custom"
  },
  "geometry": {"coordinates":[-122.386155,37.616357],"type":"Point"}
}
