{
  "type": "Feature",
  "properties": {
    "iso:country": "XX",
    "media:fingerprint": "159b84db829584cde48e4c2bababf3291693ca1c",
    "media:imagehash_avg": "a:0000003f3f01ffff",
    "media:imagehash_diff": "d:09475f747d1f1b03",
    "media:medium": "image",
    "media:mimetype": "image/tiff",
    "media:properties": {
      "colours": [
        {
          "hex": "#45a2e1",
          "name": "#45a2e1",
          "reference": "vibrant"
        }, 
        {
          "hex": "#55a8e1",
          "name": "#55a8e1",
          "reference": "vibrant"
        }, 
        {
          "hex": "#1c265f",
          "name": "#1c265f",
          "reference": "vibrant"
        }, 
        {
          "hex": "#ae9962",
          "name": "#ae9962",
          "reference": "vibrant"
        }, 
        {
          "hex": "#d2c2a4",
          "name": "#d2c2a4",
          "reference": "vibrant"
        }
      ],
      "sizes": {
        "b": {
          "extension": "jpg",
          "height": 376,
          "mimetype": "image/jpeg",
          "secret": "9tVytmWoWJrU06oT02uf3uDXlVYNq9Po",
          "width": 1024
        },
        "c": {
          "extension": "jpg",
          "height": 294,
          "mimetype": "image/jpeg",
          "secret": "9tVytmWoWJrU06oT02uf3uDXlVYNq9Po",
          "width": 800
        },
        "dc": {
          "extension": "jpg",
          "height": 294,
          "mimetype": "image/jpeg",
          "secret": "9tVytmWoWJrU06oT02uf3uDXlVYNq9Po",
          "width": 800
        },
        "ds": {
          "extension": "jpg",
          "height": 320,
          "mimetype": "image/jpeg",
          "secret": "9tVytmWoWJrU06oT02uf3uDXlVYNq9Po",
          "width": 320
        },
        "k": {
          "extension": "jpg",
          "height": 752,
          "mimetype": "image/jpeg",
          "secret": "9tVytmWoWJrU06oT02uf3uDXlVYNq9Po",
          "width": 2048
        },
        "n": {
          "extension": "jpg",
          "height": 117,
          "mimetype": "image/jpeg",
          "secret": "9tVytmWoWJrU06oT02uf3uDXlVYNq9Po",
          "width": 320
        },
        "o": {
          "extension": "jpg",
          "height": 1103,
          "mimetype": "image/jpeg",
          "secret": "nuq6wsKq3khMCZHn3hY9muiCcmYI1obV",
          "width": 3000
        },
        "s": {
          "extension": "jpg",
          "height": 320,
          "mimetype": "image/jpeg",
          "secret": "9tVytmWoWJrU06oT02uf3uDXlVYNq9Po",
          "width": 320
        },
        "z": {
          "extension": "jpg",
          "height": 235,
          "mimetype": "image/jpeg",
          "secret": "9tVytmWoWJrU06oT02uf3uDXlVYNq9Po",
          "width": 640
        }
      }
    },
    "media:uri_template": "https://millsfield.sfomuseum.org/media/152/785/873/1/1527858731_{secret}_{label}.{extention}",
    "sfomuseum:filename": "2006.010.765.tif",
    "sfomuseum:image_index": 0,
    "sfomuseum:placetype": "image",
    "sfomuseum:primary_image": 1,
    "wof:depicts": [
      1511930269
    ],
    "wof:name": "brochure: UTA (Union de Transports Aériens), Boeing 747-200",
    "wof:placetype": "media"
  },
  "geometry": {"coordinates":[-122.386155,37.616358],"type":"Point"}
}
