{
  "type": "Feature",
  "properties": {
    "iso:country":"XX",
    "media:fingerprint":"29f512edeeae66febb6297f750c14532afc8c025",
    "media:imagehash_avg":"a:ffc78393f7b99080",
    "media:imagehash_diff":"d:0f0f0727276b3169",
    "media:medium":"image",
    "media:mimetype":"image/tiff",
    "media:properties":{
        "colours":[
            {
                "hex":"#7b7a82",
                "name":"#7b7a82",
                "reference":"vibrant"
            },
            {
                "hex":"#b9afb7",
                "name":"#b9afb7",
                "reference":"vibrant"
            },
            {
                "hex":"#494144",
                "name":"#494144",
                "reference":"vibrant"
            }
        ],
        "sizes":{
            "b":{
                "extension":"jpg",
                "height":768,
                "mimetype":"image/jpeg",
                "secret":"53wfcOvQeQ0d786cOZIHGLmLx6V9zhAe",
                "width":614
            },
            "c":{
                "extension":"jpg",
                "height":600,
                "mimetype":"image/jpeg",
                "secret":"53wfcOvQeQ0d786cOZIHGLmLx6V9zhAe",
                "width":480
            },
            "dc":{
                "extension":"jpg",
                "height":600,
                "mimetype":"image/jpeg",
                "secret":"53wfcOvQeQ0d786cOZIHGLmLx6V9zhAe",
                "width":480
            },
            "ds":{
                "extension":"jpg",
                "height":320,
                "mimetype":"image/jpeg",
                "secret":"53wfcOvQeQ0d786cOZIHGLmLx6V9zhAe",
                "width":320
            },
            "k":{
                "extension":"jpg",
                "height":1536,
                "mimetype":"image/jpeg",
                "secret":"53wfcOvQeQ0d786cOZIHGLmLx6V9zhAe",
                "width":1229
            },
            "n":{
                "extension":"jpg",
                "height":240,
                "mimetype":"image/jpeg",
                "secret":"53wfcOvQeQ0d786cOZIHGLmLx6V9zhAe",
                "width":192
            },
            "o":{
                "extension":"jpg",
                "height":2097,
                "mimetype":"image/jpeg",
                "secret":"BJZSBuVbUCYJu5IWZMv80htIASviQX1w",
                "width":1678
            },
            "s":{
                "extension":"jpg",
                "height":320,
                "mimetype":"image/jpeg",
                "secret":"53wfcOvQeQ0d786cOZIHGLmLx6V9zhAe",
                "width":320
            },
            "z":{
                "extension":"jpg",
                "height":480,
                "mimetype":"image/jpeg",
                "secret":"53wfcOvQeQ0d786cOZIHGLmLx6V9zhAe",
                "width":384
            }
        }
    },
    "media:uri_template":"https://millsfield.sfomuseum.org/media/152/783/079/5/1527830795_{secret}_{label}.{extention}",
    "sfomuseum:filename":"57739.tif",
    "sfomuseum:image_index":5,
    "sfomuseum:placetype":"image",
    "sfomuseum:primary_image":1,
    "wof:depicts":[
        1159284989,
        1511955037
    ],
    "wof:name":"career history questionnaire: World Wings International, Laila Saether",
    "wof:placetype":"media"
},
  "geometry": {"coordinates":[-122.386155,37.616358],"type":"Point"}
}