{
  "type": "Feature",
  "properties": {
    "iso:country": "XX",
    "media:fingerprint": "79c83303e83fe48ccb50254c0abb7e768c542a21",
    "media:imagehash_avg": "a:fffefffeff9f0000",
    "media:imagehash_diff": "d:98b0b83c397b3329",
    "media:medium": "image",
    "media:mimetype": "image/jpeg",
    "media:properties": {
      "colours": [
        {
          "hex": "#c94731",
          "name": "#c94731",
          "reference": "vibrant"
        }, 
        {
          "hex": "#d48358",
          "name": "#d48358",
          "reference": "vibrant"
        }, 
        {
          "hex": "#263265",
          "name": "#263265",
          "reference": "vibrant"
        }, 
        {
          "hex": "#99795f",
          "name": "#99795f",
          "reference": "vibrant"
        }, 
        {
          "hex": "#c9c5b0",
          "name": "#c9c5b0",
          "reference": "vibrant"
        }
      ],
      "sizes": {
        "b": {
          "extension": "jpg",
          "height": 451,
          "mimetype": "image/jpeg",
          "secret": "JBmzAlvYDOEilR0HNwRwN0NZcvq04JHr",
          "width": 1024
        },
        "c": {
          "extension": "jpg",
          "height": 352,
          "mimetype": "image/jpeg",
          "secret": "JBmzAlvYDOEilR0HNwRwN0NZcvq04JHr",
          "width": 800
        },
        "dc": {
          "extension": "jpg",
          "height": 352,
          "mimetype": "image/jpeg",
          "secret": "JBmzAlvYDOEilR0HNwRwN0NZcvq04JHr",
          "width": 800
        },
        "ds": {
          "extension": "jpg",
          "height": 320,
          "mimetype": "image/jpeg",
          "secret": "JBmzAlvYDOEilR0HNwRwN0NZcvq04JHr",
          "width": 320
        },
        "k": {
          "extension": "jpg",
          "height": 902,
          "mimetype": "image/jpeg",
          "secret": "JBmzAlvYDOEilR0HNwRwN0NZcvq04JHr",
          "width": 2048
        },
        "n": {
          "extension": "jpg",
          "height": 141,
          "mimetype": "image/jpeg",
          "secret": "JBmzAlvYDOEilR0HNwRwN0NZcvq04JHr",
          "width": 320
        },
        "o": {
          "extension": "jpg",
          "height": 1189,
          "mimetype": "image/jpeg",
          "secret": "1B8O2I3vhta1bmgMlWH4KmjnqZovkVRO",
          "width": 2698
        },
        "s": {
          "extension": "jpg",
          "height": 320,
          "mimetype": "image/jpeg",
          "secret": "JBmzAlvYDOEilR0HNwRwN0NZcvq04JHr",
          "width": 320
        },
        "z": {
          "extension": "jpg",
          "height": 282,
          "mimetype": "image/jpeg",
          "secret": "JBmzAlvYDOEilR0HNwRwN0NZcvq04JHr",
          "width": 640
        }
      }
    },
    "media:uri_template": "https://millsfield.sfomuseum.org/media/152/782/067/1/1527820671_{secret}_{label}.{extention}",
    "sfomuseum:filename": "31871.jpg",
    "sfomuseum:image_index": 5,
    "sfomuseum:placetype": "image",
    "sfomuseum:primary_image": 1,
    "wof:depicts": [
      1511943133
    ],
    "wof:name": "airmail flight cover: Pan American Airways, CNAC (China National Aviation Corporation), FAM-14, first scheduled airmail flight, Hong Kong - San Francisco route",
    "wof:placetype": "media"
  },
  "geometry": {"coordinates":[-122.386155,37.616358],"type":"Point"}
}
