{
  "type": "Feature",
  "properties": {
    "iso:country": "XX",
    "media:fingerprint": "f6d8dcca5c18bc204b03880073b741c384f178d6",
    "media:imagehash_avg": "a:3fffffffc0000c00",
    "media:imagehash_diff": "d:f1f1f0d18581f9f1",
    "media:medium": "image",
    "media:mimetype": "image/tiff",
    "media:properties": {
      "colours": [
        {
          "hex": "#808080",
          "name": "#808080",
          "reference": "vibrant"
        }, 
        {
          "hex": "#b9b9b9",
          "name": "#b9b9b9",
          "reference": "vibrant"
        }, 
        {
          "hex": "#404040",
          "name": "#404040",
          "reference": "vibrant"
        }
      ],
      "sizes": {
        "b": {
          "extension": "jpg",
          "height": 767,
          "mimetype": "image/jpeg",
          "secret": "AixF4ZKlAf90JtGl6ydirjVUg1tx1Ovh",
          "width": 973
        },
        "c": {
          "extension": "jpg",
          "height": 600,
          "mimetype": "image/jpeg",
          "secret": "AixF4ZKlAf90JtGl6ydirjVUg1tx1Ovh",
          "width": 760
        },
        "dc": {
          "extension": "jpg",
          "height": 600,
          "mimetype": "image/jpeg",
          "secret": "AixF4ZKlAf90JtGl6ydirjVUg1tx1Ovh",
          "width": 760
        },
        "ds": {
          "extension": "jpg",
          "height": 320,
          "mimetype": "image/jpeg",
          "secret": "AixF4ZKlAf90JtGl6ydirjVUg1tx1Ovh",
          "width": 320
        },
        "k": {
          "extension": "jpg",
          "height": 1535,
          "mimetype": "image/jpeg",
          "secret": "AixF4ZKlAf90JtGl6ydirjVUg1tx1Ovh",
          "width": 1947
        },
        "n": {
          "extension": "jpg",
          "height": 240,
          "mimetype": "image/jpeg",
          "secret": "AixF4ZKlAf90JtGl6ydirjVUg1tx1Ovh",
          "width": 304
        },
        "o": {
          "extension": "jpg",
          "height": 2140,
          "mimetype": "image/jpeg",
          "secret": "bia9nCYjOqNnMrtIpq0dov7YMdnKV8mo",
          "width": 2713
        },
        "s": {
          "extension": "jpg",
          "height": 320,
          "mimetype": "image/jpeg",
          "secret": "AixF4ZKlAf90JtGl6ydirjVUg1tx1Ovh",
          "width": 320
        },
        "z": {
          "extension": "jpg",
          "height": 480,
          "mimetype": "image/jpeg",
          "secret": "AixF4ZKlAf90JtGl6ydirjVUg1tx1Ovh",
          "width": 608
        }
      }
    },
    "media:uri_template": "https://millsfield.sfomuseum.org/media/152/782/408/1/1527824081_{secret}_{label}.{extention}",
    "sfomuseum:filename": "42256.tif",
    "sfomuseum:image_index": 5,
    "sfomuseum:placetype": "image",
    "sfomuseum:primary_image": 1,
    "wof:depicts": [
      1511945399
    ],
    "wof:name": "negative: San Francisco International Airport (SFO), firefighting equipment",
    "wof:placetype": "media"
  },
  "geometry": {"coordinates":[-122.386155,37.616358],"type":"Point"}
}
