{
  "type": "Feature",
  "properties": {
    "iso:country": "XX",
    "media:fingerprint": "6ea2af6a56db2f3c2eee44f3a8fe793cbdb10b83",
    "media:imagehash_avg": "a:000007c3c3c3ffff",
    "media:imagehash_diff": "d:e0cc949e9686e4f0",
    "media:medium": "image",
    "media:mimetype": "image/jpeg",
    "media:properties": {
      "colours": [
        {
          "hex": "#c22c2b",
          "name": "#c22c2b",
          "reference": "vibrant"
        }, 
        {
          "hex": "#e35550",
          "name": "#e35550",
          "reference": "vibrant"
        }, 
        {
          "hex": "#6b1314",
          "name": "#6b1314",
          "reference": "vibrant"
        }, 
        {
          "hex": "#b36a63",
          "name": "#b36a63",
          "reference": "vibrant"
        }, 
        {
          "hex": "#cabfb6",
          "name": "#cabfb6",
          "reference": "vibrant"
        }
      ],
      "sizes": {
        "b": {
          "extension": "jpg",
          "height": 682,
          "mimetype": "image/jpeg",
          "secret": "G3Li3TwNC81K7UyS0dGfMAWBEHIHj3xH",
          "width": 1024
        },
        "c": {
          "extension": "jpg",
          "height": 533,
          "mimetype": "image/jpeg",
          "secret": "G3Li3TwNC81K7UyS0dGfMAWBEHIHj3xH",
          "width": 800
        },
        "dc": {
          "extension": "jpg",
          "height": 533,
          "mimetype": "image/jpeg",
          "secret": "G3Li3TwNC81K7UyS0dGfMAWBEHIHj3xH",
          "width": 800
        },
        "ds": {
          "extension": "jpg",
          "height": 320,
          "mimetype": "image/jpeg",
          "secret": "G3Li3TwNC81K7UyS0dGfMAWBEHIHj3xH",
          "width": 320
        },
        "k": {
          "extension": "jpg",
          "height": 1365,
          "mimetype": "image/jpeg",
          "secret": "G3Li3TwNC81K7UyS0dGfMAWBEHIHj3xH",
          "width": 2048
        },
        "n": {
          "extension": "jpg",
          "height": 213,
          "mimetype": "image/jpeg",
          "secret": "G3Li3TwNC81K7UyS0dGfMAWBEHIHj3xH",
          "width": 320
        },
        "o": {
          "extension": "jpg",
          "height": 2400,
          "mimetype": "image/jpeg",
          "secret": "7nQrmEw67pQ7q4zLxNfvgNFKmwFBGVQ0",
          "width": 3600
        },
        "s": {
          "extension": "jpg",
          "height": 320,
          "mimetype": "image/jpeg",
          "secret": "G3Li3TwNC81K7UyS0dGfMAWBEHIHj3xH",
          "width": 320
        },
        "z": {
          "extension": "jpg",
          "height": 426,
          "mimetype": "image/jpeg",
          "secret": "G3Li3TwNC81K7UyS0dGfMAWBEHIHj3xH",
          "width": 640
        }
      }
    },
    "media:uri_template": "https://millsfield.sfomuseum.org/media/152/781/937/3/1527819373_{secret}_{label}.{extention}",
    "sfomuseum:filename": "28657.jpg",
    "sfomuseum:image_index": 5,
    "sfomuseum:placetype": "image",
    "sfomuseum:primary_image": 1,
    "wof:depicts": [
      1511922553
    ],
    "wof:name": "miniature airline bag: TWA (Trans World Airlines)",
    "wof:placetype": "media"
  },
  "geometry": {"coordinates":[-122.386155,37.616358],"type":"Point"}
}
