{
  "type": "Feature",
  "properties": {
    "iso:country": "XX",
    "media:fingerprint": "cf31d17a92d6cb554f8cb647c55470641a989d81",
    "media:imagehash_avg": "a:18fefffff7f70000",
    "media:imagehash_diff": "d:e0f0f0f0ac2561e1",
    "media:medium": "image",
    "media:mimetype": "image/tiff",
    "media:properties": {
      "colours": [
        {
          "hex": "#808080",
          "name": "#808080",
          "reference": "vibrant"
        }, 
        {
          "hex": "#c0c0c0",
          "name": "#c0c0c0",
          "reference": "vibrant"
        }, 
        {
          "hex": "#454545",
          "name": "#454545",
          "reference": "vibrant"
        }
      ],
      "sizes": {
        "b": {
          "extension": "jpg",
          "height": 768,
          "mimetype": "image/jpeg",
          "secret": "DAfS3fJq4mErkI1RDnsUhmvc4YuVl0MJ",
          "width": 982
        },
        "c": {
          "extension": "jpg",
          "height": 600,
          "mimetype": "image/jpeg",
          "secret": "DAfS3fJq4mErkI1RDnsUhmvc4YuVl0MJ",
          "width": 767
        },
        "dc": {
          "extension": "jpg",
          "height": 600,
          "mimetype": "image/jpeg",
          "secret": "DAfS3fJq4mErkI1RDnsUhmvc4YuVl0MJ",
          "width": 767
        },
        "ds": {
          "extension": "jpg",
          "height": 320,
          "mimetype": "image/jpeg",
          "secret": "DAfS3fJq4mErkI1RDnsUhmvc4YuVl0MJ",
          "width": 320
        },
        "k": {
          "extension": "jpg",
          "height": 1536,
          "mimetype": "image/jpeg",
          "secret": "DAfS3fJq4mErkI1RDnsUhmvc4YuVl0MJ",
          "width": 1965
        },
        "n": {
          "extension": "jpg",
          "height": 240,
          "mimetype": "image/jpeg",
          "secret": "DAfS3fJq4mErkI1RDnsUhmvc4YuVl0MJ",
          "width": 307
        },
        "o": {
          "extension": "jpg",
          "height": 2195,
          "mimetype": "image/jpeg",
          "secret": "o12qc7fGAvbshWk3sc1cpOY3XUPYVQjQ",
          "width": 2809
        },
        "s": {
          "extension": "jpg",
          "height": 320,
          "mimetype": "image/jpeg",
          "secret": "DAfS3fJq4mErkI1RDnsUhmvc4YuVl0MJ",
          "width": 320
        },
        "z": {
          "extension": "jpg",
          "height": 480,
          "mimetype": "image/jpeg",
          "secret": "DAfS3fJq4mErkI1RDnsUhmvc4YuVl0MJ",
          "width": 614
        }
      }
    },
    "media:uri_template": "https://millsfield.sfomuseum.org/media/152/782/250/1/1527822501_{secret}_{label}.{extention}",
    "sfomuseum:filename": "40774.tif",
    "sfomuseum:image_index": 5,
    "sfomuseum:placetype": "image",
    "sfomuseum:primary_image": 1,
    "wof:depicts": [
      1511944405
    ],
    "wof:name": "negative: San Francisco International Airport (SFO), Terminal Building and TWA (Trans World Airlines), Boeing 707",
    "wof:placetype": "media"
  },
  "geometry": {"coordinates":[-122.386155,37.616358],"type":"Point"}
}
