{
  "type": "Feature",
  "properties": {
    "sfomuseum:filename": "L2018.1901.015.JPG",
    "sfomuseum:image_index": 0,
    "sfomuseum:image_type": "curator",
    "sfomuseum:placetype": "image",
    "sfomuseum:primary_image": 1,
    "wof:depicts": [
      1511915501
    ],
    "wof:name": "Adventures in the air. Being memorable experiences of great aeronauts",
    "wof:placetype": "custom"
  },
  "geometry": {"coordinates":[-122.386155,37.616357],"type":"Point"}
}
