{
  "type": "Feature",
  "properties": {
    "iso:country": "XX",
    "media:fingerprint": "c33544b46454a670111ce235aa967746eeaf232f",
    "media:imagehash_avg": "a:f89899ffffe7a1ff",
    "media:imagehash_diff": "d:71717179794d4d59",
    "media:medium": "image",
    "media:mimetype": "image/tiff",
    "media:properties": {
      "colours": [
        {
          "hex": "#b89f6a",
          "name": "#b89f6a",
          "reference": "vibrant"
        }, 
        {
          "hex": "#d8b888",
          "name": "#d8b888",
          "reference": "vibrant"
        }, 
        {
          "hex": "#9c906c",
          "name": "#9c906c",
          "reference": "vibrant"
        }, 
        {
          "hex": "#dad3bf",
          "name": "#dad3bf",
          "reference": "vibrant"
        }, 
        {
          "hex": "#524b3c",
          "name": "#524b3c",
          "reference": "vibrant"
        }
      ],
      "sizes": {
        "b": {
          "extension": "jpg",
          "height": 450,
          "mimetype": "image/jpeg",
          "secret": "btiITPmPfF0L16jp6HLO5r1v4sN1dAsy",
          "width": 1024
        },
        "c": {
          "extension": "jpg",
          "height": 351,
          "mimetype": "image/jpeg",
          "secret": "btiITPmPfF0L16jp6HLO5r1v4sN1dAsy",
          "width": 799
        },
        "dc": {
          "extension": "jpg",
          "height": 351,
          "mimetype": "image/jpeg",
          "secret": "btiITPmPfF0L16jp6HLO5r1v4sN1dAsy",
          "width": 799
        },
        "ds": {
          "extension": "jpg",
          "height": 320,
          "mimetype": "image/jpeg",
          "secret": "btiITPmPfF0L16jp6HLO5r1v4sN1dAsy",
          "width": 320
        },
        "k": {
          "extension": "jpg",
          "height": 900,
          "mimetype": "image/jpeg",
          "secret": "btiITPmPfF0L16jp6HLO5r1v4sN1dAsy",
          "width": 2048
        },
        "n": {
          "extension": "jpg",
          "height": 140,
          "mimetype": "image/jpeg",
          "secret": "btiITPmPfF0L16jp6HLO5r1v4sN1dAsy",
          "width": 320
        },
        "o": {
          "extension": "jpg",
          "height": 1185,
          "mimetype": "image/jpeg",
          "secret": "sd8xSnOMLNKaWEqW51OB2xpVdEgavFaE",
          "width": 2696
        },
        "s": {
          "extension": "jpg",
          "height": 320,
          "mimetype": "image/jpeg",
          "secret": "btiITPmPfF0L16jp6HLO5r1v4sN1dAsy",
          "width": 320
        },
        "z": {
          "extension": "jpg",
          "height": 281,
          "mimetype": "image/jpeg",
          "secret": "btiITPmPfF0L16jp6HLO5r1v4sN1dAsy",
          "width": 640
        }
      }
    },
    "media:uri_template": "https://millsfield.sfomuseum.org/media/152/781/826/3/1527818263_{secret}_{label}.{extention}",
    "sfomuseum:filename": "16333.tif",
    "sfomuseum:image_index": 5,
    "sfomuseum:placetype": "image",
    "sfomuseum:primary_image": 1,
    "wof:depicts": [
      1511931567
    ],
    "wof:name": "mail ship cover: Pacific Naval Ship, U.S.S. Stewart, January 10, 1930",
    "wof:placetype": "media"
  },
  "geometry": {"coordinates":[-122.386155,37.616358],"type":"Point"}
}
