{
  "type": "Feature",
  "properties": {
    "iso:country": "XX",
    "media:fingerprint": "486dd6e286878ed658e264b7c380788e7119076b",
    "media:imagehash_avg": "a:b8303c1c3c33333f",
    "media:imagehash_diff": "d:6064e0e1e1e666ea",
    "media:medium": "image",
    "media:mimetype": "image/tiff",
    "media:properties": {
      "colours": [
        {
          "hex": "#7a7a7a",
          "name": "#7a7a7a",
          "reference": "vibrant"
        }, 
        {
          "hex": "#b8b8b8",
          "name": "#b8b8b8",
          "reference": "vibrant"
        }, 
        {
          "hex": "#484848",
          "name": "#484848",
          "reference": "vibrant"
        }
      ],
      "sizes": {
        "b": {
          "extension": "jpg",
          "height": 767,
          "mimetype": "image/jpeg",
          "secret": "76gPE0PYTthKV4huL7smxSPBQK0uAop0",
          "width": 978
        },
        "c": {
          "extension": "jpg",
          "height": 600,
          "mimetype": "image/jpeg",
          "secret": "76gPE0PYTthKV4huL7smxSPBQK0uAop0",
          "width": 764
        },
        "dc": {
          "extension": "jpg",
          "height": 600,
          "mimetype": "image/jpeg",
          "secret": "76gPE0PYTthKV4huL7smxSPBQK0uAop0",
          "width": 764
        },
        "ds": {
          "extension": "jpg",
          "height": 320,
          "mimetype": "image/jpeg",
          "secret": "76gPE0PYTthKV4huL7smxSPBQK0uAop0",
          "width": 320
        },
        "k": {
          "extension": "jpg",
          "height": 1535,
          "mimetype": "image/jpeg",
          "secret": "76gPE0PYTthKV4huL7smxSPBQK0uAop0",
          "width": 1957
        },
        "n": {
          "extension": "jpg",
          "height": 240,
          "mimetype": "image/jpeg",
          "secret": "76gPE0PYTthKV4huL7smxSPBQK0uAop0",
          "width": 305
        },
        "o": {
          "extension": "jpg",
          "height": 2140,
          "mimetype": "image/jpeg",
          "secret": "kxVfv4WuJRsdj8dMs731r9gvObqMuUrI",
          "width": 2727
        },
        "s": {
          "extension": "jpg",
          "height": 320,
          "mimetype": "image/jpeg",
          "secret": "76gPE0PYTthKV4huL7smxSPBQK0uAop0",
          "width": 320
        },
        "z": {
          "extension": "jpg",
          "height": 480,
          "mimetype": "image/jpeg",
          "secret": "76gPE0PYTthKV4huL7smxSPBQK0uAop0",
          "width": 611
        }
      }
    },
    "media:uri_template": "https://millsfield.sfomuseum.org/media/152/782/296/9/1527822969_{secret}_{label}.{extention}",
    "sfomuseum:filename": "41159.tif",
    "sfomuseum:image_index": 5,
    "sfomuseum:placetype": "image",
    "sfomuseum:primary_image": 1,
    "wof:depicts": [
      1511944863
    ],
    "wof:name": "negative: San Francisco International Airport (SFO), South Terminal construction",
    "wof:placetype": "media"
  },
  "geometry": {"coordinates":[-122.386155,37.616358],"type":"Point"}
}
