{
  "type": "Feature",
  "properties": {
    "iso:country": "XX",
    "media:fingerprint": "5906739830593148ce01ffc09f2228376409c572",
    "media:imagehash_avg": "a:ffffffffff010163",
    "media:imagehash_diff": "d:7f3f3f7fef67c7c7",
    "media:medium": "image",
    "media:mimetype": "image/tiff",
    "media:properties": {
      "colours": [
        {
          "hex": "#4f81ba",
          "name": "#4f81ba",
          "reference": "vibrant"
        },
        {
          "hex": "#8abde8",
          "name": "#8abde8",
          "reference": "vibrant"
        },
        {
          "hex": "#282a67",
          "name": "#282a67",
          "reference": "vibrant"
        },
        {
          "hex": "#a68161",
          "name": "#a68161",
          "reference": "vibrant"
        },
        {
          "hex": "#a9acd6",
          "name": "#a9acd6",
          "reference": "vibrant"
        }
      ],
      "sizes": {
        "b": {
          "extension": "jpg",
          "height": 768,
          "mimetype": "image/jpeg",
          "secret": "RERLuB9P0Hdw95Nd48zIZzci670f8RN4",
          "width": 337
        },
        "c": {
          "extension": "jpg",
          "height": 600,
          "mimetype": "image/jpeg",
          "secret": "RERLuB9P0Hdw95Nd48zIZzci670f8RN4",
          "width": 263
        },
        "dc": {
          "extension": "jpg",
          "height": 600,
          "mimetype": "image/jpeg",
          "secret": "RERLuB9P0Hdw95Nd48zIZzci670f8RN4",
          "width": 263
        },
        "ds": {
          "extension": "jpg",
          "height": 320,
          "mimetype": "image/jpeg",
          "secret": "RERLuB9P0Hdw95Nd48zIZzci670f8RN4",
          "width": 320
        },
        "k": {
          "extension": "jpg",
          "height": 1536,
          "mimetype": "image/jpeg",
          "secret": "RERLuB9P0Hdw95Nd48zIZzci670f8RN4",
          "width": 675
        },
        "n": {
          "extension": "jpg",
          "height": 240,
          "mimetype": "image/jpeg",
          "secret": "RERLuB9P0Hdw95Nd48zIZzci670f8RN4",
          "width": 105
        },
        "o": {
          "extension": "jpg",
          "height": 2794,
          "mimetype": "image/jpeg",
          "secret": "RteiAEYUpBrOU64TgL8cnK3kzEgSwRla",
          "width": 1229
        },
        "s": {
          "extension": "jpg",
          "height": 320,
          "mimetype": "image/jpeg",
          "secret": "RERLuB9P0Hdw95Nd48zIZzci670f8RN4",
          "width": 320
        },
        "z": {
          "extension": "jpg",
          "height": 480,
          "mimetype": "image/jpeg",
          "secret": "RERLuB9P0Hdw95Nd48zIZzci670f8RN4",
          "width": 211
        }
      }
    },
    "media:uri_template": "https://static.sfomuseum.org/media/152/784/254/5/1527842545_{secret}_{label}.{extention}",
    "sfomuseum:filename": "2003.105.101.001.tif",
    "sfomuseum:image_index": 5,
    "sfomuseum:placetype": "image",
    "sfomuseum:primary_image": 1,
    "wof:depicts": [
      1159285589,
      1511939663
    ],
    "wof:name": "timetable: Swissair",
    "wof:placetype": "custom",
    "wof:placetype_alt": "image"
  },
  "geometry": {"coordinates":[-122.386155,37.616358],"type":"Point"}
}
