{
  "type": "Feature",
  "properties": {
    "date:cessation_lower": "1940-01-01",
    "date:cessation_upper": "1940-12-31",
    "date:inception_lower": "1940-01-01",
    "date:inception_upper": "1940-12-31",
    "iso:country": "XX",
    "media:imagehash_avg": "a:3f1f4f630f030103",
    "media:imagehash_diff": "d:f77b9fcf7fbf9f9f",
    "media:imagetext": "Stratoliner\nTWA\nBroader Wings\nNOW SPAN THE NATION",
    "media:imagetext_created": 1701938228,
    "media:mimetype": "image/jpeg",
    "media:properties": {
    },
    "media:uri_template": "https://static.sfomuseum.org/media/174/668/021/7/1746680217_{secret}_{label}.{extention}",
    "millsfield:exhibition_ids": [
      1159160275
    ],
    "millsfield:images_texts": [
      "Stratoliner\nTWA\nBroader Wings\nNOW SPAN THE NATION"
    ],
    "millsfield:images_texts_ids": [
      1746680217
    ],
    "millsfield:on_view": 0,
    "sfomuseum:filename": "21251.JPG",
    "sfomuseum:image_index": 3,
    "sfomuseum:image_type": "studio",
    "sfomuseum:placetype": "image",
    "sfomuseum:primary_image": 1,
    "wof:depicts": [
      1159293593,
      1729564185,
      1159285395,
      1159289617
    ],
    "wof:name": "brochure: Transcontinental \u0026 Western Air (TWA), Boeing 307 Stratoliner",
    "wof:placetype": "custom"
  },
  "geometry": {"coordinates":[-122.386155,37.616357],"type":"Point"}
}
