{
  "type": "Feature",
  "properties": {
    "sfomuseum:filename": "21251.JPG",
    "sfomuseum:image_index": 3,
    "sfomuseum:image_type": "curator",
    "sfomuseum:placetype": "image",
    "sfomuseum:primary_image": 1,
    "wof:depicts": [
      1729564185,
      1159285395,
      1159289617
    ],
    "wof:name": "brochure: Transcontinental \u0026 Western Air (TWA), Boeing 307 Stratoliner",
    "wof:placetype": "custom"
  },
  "geometry": {"coordinates":[-122.386155,37.616357],"type":"Point"}
}
