{
  "type": "Feature",
  "properties": {
    "iso:country": "XX",
    "media:fingerprint": "6036cc0b470133d8fcc49473a169262f160a79a0",
    "media:imagehash_avg": "a:00000000ffffff3c",
    "media:imagehash_diff": "d:20e07178e8f070f0",
    "media:medium": "image",
    "media:mimetype": "image/tiff",
    "media:properties": {
      "colours": [
        {
          "hex": "#808080",
          "name": "#808080",
          "reference": "vibrant"
        }, 
        {
          "hex": "#c0c0c0",
          "name": "#c0c0c0",
          "reference": "vibrant"
        }, 
        {
          "hex": "#484848",
          "name": "#484848",
          "reference": "vibrant"
        }
      ],
      "sizes": {
        "b": {
          "extension": "jpg",
          "height": 767,
          "mimetype": "image/jpeg",
          "secret": "tPWwmMXFeMxmwCf1DVlhZG8ADGnCRV0K",
          "width": 988
        },
        "c": {
          "extension": "jpg",
          "height": 600,
          "mimetype": "image/jpeg",
          "secret": "tPWwmMXFeMxmwCf1DVlhZG8ADGnCRV0K",
          "width": 772
        },
        "dc": {
          "extension": "jpg",
          "height": 600,
          "mimetype": "image/jpeg",
          "secret": "tPWwmMXFeMxmwCf1DVlhZG8ADGnCRV0K",
          "width": 772
        },
        "ds": {
          "extension": "jpg",
          "height": 320,
          "mimetype": "image/jpeg",
          "secret": "tPWwmMXFeMxmwCf1DVlhZG8ADGnCRV0K",
          "width": 320
        },
        "k": {
          "extension": "jpg",
          "height": 1535,
          "mimetype": "image/jpeg",
          "secret": "tPWwmMXFeMxmwCf1DVlhZG8ADGnCRV0K",
          "width": 1976
        },
        "n": {
          "extension": "jpg",
          "height": 240,
          "mimetype": "image/jpeg",
          "secret": "tPWwmMXFeMxmwCf1DVlhZG8ADGnCRV0K",
          "width": 308
        },
        "o": {
          "extension": "jpg",
          "height": 2140,
          "mimetype": "image/jpeg",
          "secret": "9a8P6bv3nI4VHBKZ1aXVxJ5BJdJpBVTE",
          "width": 2754
        },
        "s": {
          "extension": "jpg",
          "height": 320,
          "mimetype": "image/jpeg",
          "secret": "tPWwmMXFeMxmwCf1DVlhZG8ADGnCRV0K",
          "width": 320
        },
        "z": {
          "extension": "jpg",
          "height": 480,
          "mimetype": "image/jpeg",
          "secret": "tPWwmMXFeMxmwCf1DVlhZG8ADGnCRV0K",
          "width": 617
        }
      }
    },
    "media:uri_template": "https://millsfield.sfomuseum.org/media/152/782/246/9/1527822469_{secret}_{label}.{extention}",
    "sfomuseum:filename": "40760.tif",
    "sfomuseum:image_index": 5,
    "sfomuseum:placetype": "image",
    "sfomuseum:primary_image": 1,
    "wof:depicts": [
      1511944375
    ],
    "wof:name": "negative: San Francisco International Airport (SFO), terminal interior",
    "wof:placetype": "media"
  },
  "geometry": {"coordinates":[-122.386155,37.616358],"type":"Point"}
}
