{
  "type": "Feature",
  "properties": {
    "iso:country": "XX",
    "media:fingerprint": "6f1c1d2da6d58819a905d84f583c1acbd92876d1",
    "media:imagehash_avg": "a:0310009ddf0f079f",
    "media:imagehash_diff": "d:77655139bc3c1679",
    "media:medium": "image",
    "media:mimetype": "image/tiff",
    "media:properties": {
      "colours": [
        {
          "hex": "#a11305",
          "name": "#a11305",
          "reference": "vibrant"
        }, 
        {
          "hex": "#d8caad",
          "name": "#d8caad",
          "reference": "vibrant"
        }, 
        {
          "hex": "#ac2b19",
          "name": "#ac2b19",
          "reference": "vibrant"
        }, 
        {
          "hex": "#699963",
          "name": "#699963",
          "reference": "vibrant"
        }, 
        {
          "hex": "#d0c8ac",
          "name": "#d0c8ac",
          "reference": "vibrant"
        }
      ],
      "sizes": {
        "b": {
          "extension": "jpg",
          "height": 583,
          "mimetype": "image/jpeg",
          "secret": "9Oo8zTDW1l3Zv08pfaljWQWXrkVfvnPy",
          "width": 1023
        },
        "c": {
          "extension": "jpg",
          "height": 455,
          "mimetype": "image/jpeg",
          "secret": "9Oo8zTDW1l3Zv08pfaljWQWXrkVfvnPy",
          "width": 800
        },
        "dc": {
          "extension": "jpg",
          "height": 455,
          "mimetype": "image/jpeg",
          "secret": "9Oo8zTDW1l3Zv08pfaljWQWXrkVfvnPy",
          "width": 800
        },
        "ds": {
          "extension": "jpg",
          "height": 320,
          "mimetype": "image/jpeg",
          "secret": "9Oo8zTDW1l3Zv08pfaljWQWXrkVfvnPy",
          "width": 320
        },
        "k": {
          "extension": "jpg",
          "height": 1166,
          "mimetype": "image/jpeg",
          "secret": "9Oo8zTDW1l3Zv08pfaljWQWXrkVfvnPy",
          "width": 2047
        },
        "n": {
          "extension": "jpg",
          "height": 182,
          "mimetype": "image/jpeg",
          "secret": "9Oo8zTDW1l3Zv08pfaljWQWXrkVfvnPy",
          "width": 320
        },
        "o": {
          "extension": "jpg",
          "height": 1135,
          "mimetype": "image/jpeg",
          "secret": "Hg3O8VhWMHRFR0TKVjzhqvSKT5x0mlcu",
          "width": 1993
        },
        "s": {
          "extension": "jpg",
          "height": 320,
          "mimetype": "image/jpeg",
          "secret": "9Oo8zTDW1l3Zv08pfaljWQWXrkVfvnPy",
          "width": 320
        },
        "z": {
          "extension": "jpg",
          "height": 364,
          "mimetype": "image/jpeg",
          "secret": "9Oo8zTDW1l3Zv08pfaljWQWXrkVfvnPy",
          "width": 640
        }
      }
    },
    "media:uri_template": "https://millsfield.sfomuseum.org/media/152/782/051/9/1527820519_{secret}_{label}.{extention}",
    "sfomuseum:filename": "31665.tif",
    "sfomuseum:image_index": 5,
    "sfomuseum:placetype": "image",
    "sfomuseum:primary_image": 1,
    "wof:depicts": [
      1511923769
    ],
    "wof:name": "airmail flight cover: Pan American World Airways, first airmail flight, Beirut - Rangoon route",
    "wof:placetype": "media"
  },
  "geometry": {"coordinates":[-122.386155,37.616358],"type":"Point"}
}
