{
  "type": "Feature",
  "properties": {
    "iso:country": "XX",
    "media:fingerprint": "8becb324b75329c89441abb4e82f67943f0650f5",
    "media:imagehash_avg": "a:ffffffffc3000000",
    "media:imagehash_diff": "d:0216161e1f137358",
    "media:medium": "image",
    "media:mimetype": "image/tiff",
    "media:properties": {
      "colours": [
        {
          "hex": "#808080",
          "name": "#808080",
          "reference": "vibrant"
        }, 
        {
          "hex": "#b8b8b8",
          "name": "#b8b8b8",
          "reference": "vibrant"
        }, 
        {
          "hex": "#464646",
          "name": "#464646",
          "reference": "vibrant"
        }
      ],
      "sizes": {
        "b": {
          "extension": "jpg",
          "height": 768,
          "mimetype": "image/jpeg",
          "secret": "K21OBzBF3dRVuhbCTfRPfEQorTrdRENg",
          "width": 608
        },
        "c": {
          "extension": "jpg",
          "height": 600,
          "mimetype": "image/jpeg",
          "secret": "K21OBzBF3dRVuhbCTfRPfEQorTrdRENg",
          "width": 475
        },
        "dc": {
          "extension": "jpg",
          "height": 600,
          "mimetype": "image/jpeg",
          "secret": "K21OBzBF3dRVuhbCTfRPfEQorTrdRENg",
          "width": 475
        },
        "ds": {
          "extension": "jpg",
          "height": 320,
          "mimetype": "image/jpeg",
          "secret": "K21OBzBF3dRVuhbCTfRPfEQorTrdRENg",
          "width": 320
        },
        "k": {
          "extension": "jpg",
          "height": 1536,
          "mimetype": "image/jpeg",
          "secret": "K21OBzBF3dRVuhbCTfRPfEQorTrdRENg",
          "width": 1216
        },
        "n": {
          "extension": "jpg",
          "height": 240,
          "mimetype": "image/jpeg",
          "secret": "K21OBzBF3dRVuhbCTfRPfEQorTrdRENg",
          "width": 190
        },
        "o": {
          "extension": "jpg",
          "height": 2754,
          "mimetype": "image/jpeg",
          "secret": "CrSFNMZeOKnPsUPS15sPFKfM70Ei0Hgs",
          "width": 2181
        },
        "s": {
          "extension": "jpg",
          "height": 320,
          "mimetype": "image/jpeg",
          "secret": "K21OBzBF3dRVuhbCTfRPfEQorTrdRENg",
          "width": 320
        },
        "z": {
          "extension": "jpg",
          "height": 480,
          "mimetype": "image/jpeg",
          "secret": "K21OBzBF3dRVuhbCTfRPfEQorTrdRENg",
          "width": 380
        }
      }
    },
    "media:uri_template": "https://millsfield.sfomuseum.org/media/152/782/315/1/1527823151_{secret}_{label}.{extention}",
    "sfomuseum:filename": "41257.tif",
    "sfomuseum:image_index": 5,
    "sfomuseum:placetype": "image",
    "sfomuseum:primary_image": 1,
    "wof:depicts": [
      1511945049
    ],
    "wof:name": "negative: San Francisco International Airport (SFO)",
    "wof:placetype": "media"
  },
  "geometry": {"coordinates":[-122.386155,37.616358],"type":"Point"}
}
