{
  "type": "Feature",
  "properties": {
    "iso:country": "XX",
    "media:fingerprint": "f435266f2589ac76625b9f9b7eba9ce8ab38b3ea",
    "media:imagehash_avg": "a:ff818181818181ff",
    "media:imagehash_diff": "d:0141614949697971",
    "media:medium": "image",
    "media:mimetype": "image/tiff",
    "media:properties": {
      "colours": [
        {
          "hex": "#d8c8ae",
          "name": "#d8c8ae",
          "reference": "vibrant"
        },
        {
          "hex": "#201e0d",
          "name": "#201e0d",
          "reference": "vibrant"
        },
        {
          "hex": "#948867",
          "name": "#948867",
          "reference": "vibrant"
        },
        {
          "hex": "#d0c8a8",
          "name": "#d0c8a8",
          "reference": "vibrant"
        },
        {
          "hex": "#534a32",
          "name": "#534a32",
          "reference": "vibrant"
        }
      ],
      "sizes": {
        "b": {
          "extension": "jpg",
          "height": 726,
          "mimetype": "image/jpeg",
          "secret": "0QtUS8OF9MNyWtGcnkzWsx1v6Fh1ajkU",
          "width": 1024
        },
        "c": {
          "extension": "jpg",
          "height": 567,
          "mimetype": "image/jpeg",
          "secret": "0QtUS8OF9MNyWtGcnkzWsx1v6Fh1ajkU",
          "width": 800
        },
        "dc": {
          "extension": "jpg",
          "height": 567,
          "mimetype": "image/jpeg",
          "secret": "0QtUS8OF9MNyWtGcnkzWsx1v6Fh1ajkU",
          "width": 800
        },
        "ds": {
          "extension": "jpg",
          "height": 320,
          "mimetype": "image/jpeg",
          "secret": "0QtUS8OF9MNyWtGcnkzWsx1v6Fh1ajkU",
          "width": 320
        },
        "k": {
          "extension": "jpg",
          "height": 1452,
          "mimetype": "image/jpeg",
          "secret": "0QtUS8OF9MNyWtGcnkzWsx1v6Fh1ajkU",
          "width": 2048
        },
        "n": {
          "extension": "jpg",
          "height": 226,
          "mimetype": "image/jpeg",
          "secret": "0QtUS8OF9MNyWtGcnkzWsx1v6Fh1ajkU",
          "width": 320
        },
        "o": {
          "extension": "jpg",
          "height": 1509,
          "mimetype": "image/jpeg",
          "secret": "UFwN9fsfPWi9DxLXyXJvQrMGwbrF6d3g",
          "width": 2128
        },
        "s": {
          "extension": "jpg",
          "height": 320,
          "mimetype": "image/jpeg",
          "secret": "0QtUS8OF9MNyWtGcnkzWsx1v6Fh1ajkU",
          "width": 320
        },
        "z": {
          "extension": "jpg",
          "height": 453,
          "mimetype": "image/jpeg",
          "secret": "0QtUS8OF9MNyWtGcnkzWsx1v6Fh1ajkU",
          "width": 640
        }
      }
    },
    "media:uri_template": "https://static.sfomuseum.org/media/152/785/569/1/1527855691_{secret}_{label}.{extention}",
    "sfomuseum:filename": "2010.174.333.tif",
    "sfomuseum:image_index": 5,
    "sfomuseum:image_type": "studio",
    "sfomuseum:placetype": "image",
    "sfomuseum:primary_image": 1,
    "wof:depicts": [
      1511942537
    ],
    "wof:name": "photograph: San Francisco, Telegraph Hill, aerial",
    "wof:placetype": "custom",
    "wof:placetype_alt": "image"
  },
  "geometry": {"coordinates":[-122.386155,37.616358],"type":"Point"}
}
