{
  "type": "Feature",
  "properties": {
    "media:fingerprint": "1d832881b0689c904b2b4046575d049c2c98256e",
    "media:imagehash_avg": "a:8181819199998181",
    "media:imagehash_diff": "d:7171717171717171",
    "media:mimetype": "image/tiff",
    "media:properties": {
      "colours": [
        {
          "hex": "#ccb075",
          "name": "#ccb075",
          "reference": "vibrant"
        },
        {
          "hex": "#e8d8a8",
          "name": "#e8d8a8",
          "reference": "vibrant"
        },
        {
          "hex": "#5c4f2c",
          "name": "#5c4f2c",
          "reference": "vibrant"
        },
        {
          "hex": "#938459",
          "name": "#938459",
          "reference": "vibrant"
        },
        {
          "hex": "#c6b9a1",
          "name": "#c6b9a1",
          "reference": "vibrant"
        }
      ],
      "sizes": {
        "b": {
          "extension": "jpg",
          "height": 768,
          "mimetype": "image/jpeg",
          "secret": "ZdK4WmEpz4Nw9p8SC6TGAT6BZ8kVt9gR",
          "width": 490
        },
        "c": {
          "extension": "jpg",
          "height": 600,
          "mimetype": "image/jpeg",
          "secret": "ZdK4WmEpz4Nw9p8SC6TGAT6BZ8kVt9gR",
          "width": 383
        },
        "dc": {
          "extension": "jpg",
          "height": 600,
          "mimetype": "image/jpeg",
          "secret": "ZdK4WmEpz4Nw9p8SC6TGAT6BZ8kVt9gR",
          "width": 383
        },
        "ds": {
          "extension": "jpg",
          "height": 320,
          "mimetype": "image/jpeg",
          "secret": "ZdK4WmEpz4Nw9p8SC6TGAT6BZ8kVt9gR",
          "width": 320
        },
        "k": {
          "extension": "jpg",
          "height": 1536,
          "mimetype": "image/jpeg",
          "secret": "ZdK4WmEpz4Nw9p8SC6TGAT6BZ8kVt9gR",
          "width": 980
        },
        "n": {
          "extension": "jpg",
          "height": 240,
          "mimetype": "image/jpeg",
          "secret": "ZdK4WmEpz4Nw9p8SC6TGAT6BZ8kVt9gR",
          "width": 153
        },
        "o": {
          "extension": "jpg",
          "height": 2000,
          "mimetype": "image/jpeg",
          "secret": "bEvLE3YNkIwLmKUNPunqwxkrES3gPywS",
          "width": 1277
        },
        "s": {
          "extension": "jpg",
          "height": 320,
          "mimetype": "image/jpeg",
          "secret": "ZdK4WmEpz4Nw9p8SC6TGAT6BZ8kVt9gR",
          "width": 320
        },
        "z": {
          "extension": "jpg",
          "height": 480,
          "mimetype": "image/jpeg",
          "secret": "ZdK4WmEpz4Nw9p8SC6TGAT6BZ8kVt9gR",
          "width": 306
        }
      }
    },
    "media:uri_template": "https://static.sfomuseum.org/media/174/630/808/3/1746308083_{secret}_{label}.{extention}",
    "sfomuseum:filename": "2000.058.0593_bk.tif",
    "sfomuseum:image_index": 5,
    "sfomuseum:image_type": "studio",
    "sfomuseum:placetype": "image",
    "sfomuseum:primary_image": 0,
    "wof:depicts": [
      1511910353,
      1159284989,
      1159286839
    ],
    "wof:name": "menu: Pan American World Airways",
    "wof:placetype": "custom",
    "wof:placetype_alt": "image"
  },
  "geometry": {"coordinates":[-122.386155,37.616357],"type":"Point"}
}
