{
  "type": "Feature",
  "properties": {
    "iso:country": "XX",
    "media:fingerprint": "38676670739ae90f7d58757830258a663563e8eb",
    "media:imagehash_avg": "a:fffde3c3070701ff",
    "media:imagehash_diff": "d:7971070f4d7d7d27",
    "media:medium": "image",
    "media:mimetype": "image/tiff",
    "media:properties": {
      "colours": [
        {
          "hex": "#c4a254",
          "name": "#c4a254",
          "reference": "vibrant"
        }, 
        {
          "hex": "#ece9cc",
          "name": "#ece9cc",
          "reference": "vibrant"
        }, 
        {
          "hex": "#391129",
          "name": "#391129",
          "reference": "vibrant"
        }, 
        {
          "hex": "#9e9053",
          "name": "#9e9053",
          "reference": "vibrant"
        }, 
        {
          "hex": "#c6c4a2",
          "name": "#c6c4a2",
          "reference": "vibrant"
        }
      ],
      "sizes": {
        "b": {
          "extension": "jpg",
          "height": 767,
          "mimetype": "image/jpeg",
          "secret": "I9NbV7XLjvze9gfxuT6SfgoCjBjDP8nk",
          "width": 992
        },
        "c": {
          "extension": "jpg",
          "height": 600,
          "mimetype": "image/jpeg",
          "secret": "I9NbV7XLjvze9gfxuT6SfgoCjBjDP8nk",
          "width": 775
        },
        "dc": {
          "extension": "jpg",
          "height": 600,
          "mimetype": "image/jpeg",
          "secret": "I9NbV7XLjvze9gfxuT6SfgoCjBjDP8nk",
          "width": 775
        },
        "ds": {
          "extension": "jpg",
          "height": 320,
          "mimetype": "image/jpeg",
          "secret": "I9NbV7XLjvze9gfxuT6SfgoCjBjDP8nk",
          "width": 320
        },
        "k": {
          "extension": "jpg",
          "height": 1535,
          "mimetype": "image/jpeg",
          "secret": "I9NbV7XLjvze9gfxuT6SfgoCjBjDP8nk",
          "width": 1984
        },
        "n": {
          "extension": "jpg",
          "height": 240,
          "mimetype": "image/jpeg",
          "secret": "I9NbV7XLjvze9gfxuT6SfgoCjBjDP8nk",
          "width": 310
        },
        "o": {
          "extension": "jpg",
          "height": 2591,
          "mimetype": "image/jpeg",
          "secret": "Qf5369g5vPrxvFQKaw1Wm80OISwQMgyU",
          "width": 3348
        },
        "s": {
          "extension": "jpg",
          "height": 320,
          "mimetype": "image/jpeg",
          "secret": "I9NbV7XLjvze9gfxuT6SfgoCjBjDP8nk",
          "width": 320
        },
        "z": {
          "extension": "jpg",
          "height": 480,
          "mimetype": "image/jpeg",
          "secret": "I9NbV7XLjvze9gfxuT6SfgoCjBjDP8nk",
          "width": 620
        }
      }
    },
    "media:uri_template": "https://millsfield.sfomuseum.org/media/152/782/180/1/1527821801_{secret}_{label}.{extention}",
    "sfomuseum:filename": "39255.tif",
    "sfomuseum:image_index": 5,
    "sfomuseum:placetype": "image",
    "sfomuseum:primary_image": 1,
    "wof:depicts": [
      1511931043
    ],
    "wof:name": "menu: Pan American World Airways, Historic First Flights series, Sikorsky S-38",
    "wof:placetype": "media"
  },
  "geometry": {"coordinates":[-122.386155,37.616358],"type":"Point"}
}
