{
  "type": "Feature",
  "properties": {
    "date:cessation_lower": "1936-01-01",
    "date:cessation_upper": "1936-12-31",
    "date:inception_lower": "1936-01-01",
    "date:inception_upper": "1936-12-31",
    "iso:country": "XX",
    "media:imagehash_avg": "a:ff7f331f0f000105",
    "media:imagehash_diff": "d:7fefc7fa7967775d",
    "media:imagetext": "SKYROADS\nWITH\nHURRICANE\nHAWK\nTHE\nBIG LITTLE\nBOOK",
    "media:imagetext_created": 1701940828,
    "media:mimetype": "image/jpeg",
    "media:properties": {
    },
    "media:uri_template": "https://static.sfomuseum.org/media/174/668/044/1/1746680441_{secret}_{label}.{extention}",
    "millsfield:exhibition_ids": [
      1159160363
    ],
    "millsfield:images_texts": [
      "SKYROADS\nWITH\nHURRICANE\nHAWK\nTHE\nBIG LITTLE\nBOOK"
    ],
    "millsfield:images_texts_ids": [
      1746680441
    ],
    "millsfield:on_view": 0,
    "sfomuseum:filename": "57551.JPG",
    "sfomuseum:image_index": 1,
    "sfomuseum:image_type": "studio",
    "sfomuseum:placetype": "image",
    "sfomuseum:primary_image": 1,
    "wof:depicts": [
      1511951977
    ],
    "wof:name": "Skyroads with Hurricane Hawk",
    "wof:placetype": "custom"
  },
  "geometry": {"coordinates":[-122.386155,37.616357],"type":"Point"}
}
