{
  "type": "Feature",
  "properties": {
    "iso:country": "XX",
    "media:fingerprint": "4e27229dd8396f09f91a0227301e49d3bb3df8b9",
    "media:imagehash_avg": "a:fffffeffd0900000",
    "media:imagehash_diff": "d:3e21383236256326",
    "media:medium": "image",
    "media:mimetype": "image/tiff",
    "media:properties": {
      "colours": [
        {
          "hex": "#808080",
          "name": "#808080",
          "reference": "vibrant"
        }, 
        {
          "hex": "#c0c0c0",
          "name": "#c0c0c0",
          "reference": "vibrant"
        }, 
        {
          "hex": "#464646",
          "name": "#464646",
          "reference": "vibrant"
        }
      ],
      "sizes": {
        "b": {
          "extension": "jpg",
          "height": 768,
          "mimetype": "image/jpeg",
          "secret": "hcVhtQA0EMQfwS1twIHAnClQhwCNlCoL",
          "width": 776
        },
        "c": {
          "extension": "jpg",
          "height": 600,
          "mimetype": "image/jpeg",
          "secret": "hcVhtQA0EMQfwS1twIHAnClQhwCNlCoL",
          "width": 606
        },
        "dc": {
          "extension": "jpg",
          "height": 600,
          "mimetype": "image/jpeg",
          "secret": "hcVhtQA0EMQfwS1twIHAnClQhwCNlCoL",
          "width": 606
        },
        "ds": {
          "extension": "jpg",
          "height": 320,
          "mimetype": "image/jpeg",
          "secret": "hcVhtQA0EMQfwS1twIHAnClQhwCNlCoL",
          "width": 320
        },
        "k": {
          "extension": "jpg",
          "height": 1536,
          "mimetype": "image/jpeg",
          "secret": "hcVhtQA0EMQfwS1twIHAnClQhwCNlCoL",
          "width": 1552
        },
        "n": {
          "extension": "jpg",
          "height": 239,
          "mimetype": "image/jpeg",
          "secret": "hcVhtQA0EMQfwS1twIHAnClQhwCNlCoL",
          "width": 242
        },
        "o": {
          "extension": "jpg",
          "height": 2563,
          "mimetype": "image/jpeg",
          "secret": "qeL1ZInahZz2ng4Xtqe7Y9plxdZk8Dog",
          "width": 2590
        },
        "s": {
          "extension": "jpg",
          "height": 320,
          "mimetype": "image/jpeg",
          "secret": "hcVhtQA0EMQfwS1twIHAnClQhwCNlCoL",
          "width": 320
        },
        "z": {
          "extension": "jpg",
          "height": 479,
          "mimetype": "image/jpeg",
          "secret": "hcVhtQA0EMQfwS1twIHAnClQhwCNlCoL",
          "width": 485
        }
      }
    },
    "media:uri_template": "https://millsfield.sfomuseum.org/media/152/782/579/3/1527825793_{secret}_{label}.{extention}",
    "sfomuseum:filename": "43338.tif",
    "sfomuseum:image_index": 5,
    "sfomuseum:placetype": "image",
    "sfomuseum:primary_image": 1,
    "wof:depicts": [
      1511946829
    ],
    "wof:name": "negative: San Francisco International Airport (SFO), conference on airport bond issue",
    "wof:placetype": "media"
  },
  "geometry": {"coordinates":[-122.386155,37.616358],"type":"Point"}
}
