{
  "type": "Feature",
  "properties": {
    "iso:country": "US",
    "media:fingerprint": "0150728c31fd619ff60893ca4481d1fc339d99ba",
    "media:imagehash_avg": "a:00007fffffff7f3f",
    "media:imagehash_diff": "d:b1e1e19f0d79f9f8",
    "media:medium": "image",
    "media:mimetype": "image/jpeg",
    "media:properties": {
      "colours": [
        {
          "hex": "#a19d68",
          "name": "#a19d68",
          "reference": "vibrant"
        }, 
        {
          "hex": "#879dc2",
          "name": "#879dc2",
          "reference": "vibrant"
        }, 
        {
          "hex": "#482f38",
          "name": "#482f38",
          "reference": "vibrant"
        }
      ],
      "sizes": {
        "b": {
          "extension": "jpg",
          "height": 768,
          "mimetype": "image/jpeg",
          "secret": "tBbp5w63g8cBgCHrUTuq31wyHPF5Z9bg",
          "width": 379
        },
        "c": {
          "extension": "jpg",
          "height": 600,
          "mimetype": "image/jpeg",
          "secret": "tBbp5w63g8cBgCHrUTuq31wyHPF5Z9bg",
          "width": 296
        },
        "dc": {
          "extension": "jpg",
          "height": 600,
          "mimetype": "image/jpeg",
          "secret": "tBbp5w63g8cBgCHrUTuq31wyHPF5Z9bg",
          "width": 296
        },
        "ds": {
          "extension": "jpg",
          "height": 320,
          "mimetype": "image/jpeg",
          "secret": "tBbp5w63g8cBgCHrUTuq31wyHPF5Z9bg",
          "width": 320
        },
        "k": {
          "extension": "jpg",
          "height": 1536,
          "mimetype": "image/jpeg",
          "secret": "tBbp5w63g8cBgCHrUTuq31wyHPF5Z9bg",
          "width": 759
        },
        "n": {
          "extension": "jpg",
          "height": 240,
          "mimetype": "image/jpeg",
          "secret": "tBbp5w63g8cBgCHrUTuq31wyHPF5Z9bg",
          "width": 118
        },
        "o": {
          "extension": "jpg",
          "height": 2891,
          "mimetype": "image/jpeg",
          "secret": "pe3rSnAUZn6xdbIwmn5C7FM75epljP8h",
          "width": 1430
        },
        "s": {
          "extension": "jpg",
          "height": 320,
          "mimetype": "image/jpeg",
          "secret": "tBbp5w63g8cBgCHrUTuq31wyHPF5Z9bg",
          "width": 320
        },
        "z": {
          "extension": "jpg",
          "height": 480,
          "mimetype": "image/jpeg",
          "secret": "tBbp5w63g8cBgCHrUTuq31wyHPF5Z9bg",
          "width": 237
        }
      }
    },
    "media:uri_template": "https://millsfield.sfomuseum.org/media/152/781/949/9/1527819499_{secret}_{label}.{extention}",
    "sfomuseum:filename": "30887.jpg",
    "sfomuseum:image_index": 5,
    "sfomuseum:placetype": "image",
    "sfomuseum:primary_image": 1,
    "wof:depicts": [
      1511909413
    ],
    "wof:name": "flight information packet: American Airlines",
    "wof:placetype": "media"
  },
  "geometry": {"coordinates":[-122.386155,37.616358],"type":"Point"}
}
