{
  "type": "Feature",
  "properties": {
    "iso:country": "XX",
    "media:fingerprint": "831b09acf55231598cdd05dee61252307f76c344",
    "media:imagehash_avg": "a:ffffff3f3f000000",
    "media:imagehash_diff": "d:e4e4f4f4f4f0f4fe",
    "media:medium": "image",
    "media:mimetype": "image/tiff",
    "media:properties": {
      "colours": [
        {
          "hex": "#8d7f67",
          "name": "#8d7f67",
          "reference": "vibrant"
        }, 
        {
          "hex": "#d1c5b8",
          "name": "#d1c5b8",
          "reference": "vibrant"
        }, 
        {
          "hex": "#505753",
          "name": "#505753",
          "reference": "vibrant"
        }
      ],
      "sizes": {
        "b": {
          "extension": "jpg",
          "height": 664,
          "mimetype": "image/jpeg",
          "secret": "V2pm5jgwAKlTqcJiaHegLbJzmre0yIdP",
          "width": 1024
        },
        "c": {
          "extension": "jpg",
          "height": 519,
          "mimetype": "image/jpeg",
          "secret": "V2pm5jgwAKlTqcJiaHegLbJzmre0yIdP",
          "width": 800
        },
        "dc": {
          "extension": "jpg",
          "height": 519,
          "mimetype": "image/jpeg",
          "secret": "V2pm5jgwAKlTqcJiaHegLbJzmre0yIdP",
          "width": 800
        },
        "ds": {
          "extension": "jpg",
          "height": 320,
          "mimetype": "image/jpeg",
          "secret": "V2pm5jgwAKlTqcJiaHegLbJzmre0yIdP",
          "width": 320
        },
        "k": {
          "extension": "jpg",
          "height": 1329,
          "mimetype": "image/jpeg",
          "secret": "V2pm5jgwAKlTqcJiaHegLbJzmre0yIdP",
          "width": 2048
        },
        "n": {
          "extension": "jpg",
          "height": 207,
          "mimetype": "image/jpeg",
          "secret": "V2pm5jgwAKlTqcJiaHegLbJzmre0yIdP",
          "width": 320
        },
        "o": {
          "extension": "jpg",
          "height": 1009,
          "mimetype": "image/jpeg",
          "secret": "W6HlHWZR2nWr1U4lKAqC2hinsnxYtxt3",
          "width": 1554
        },
        "s": {
          "extension": "jpg",
          "height": 320,
          "mimetype": "image/jpeg",
          "secret": "V2pm5jgwAKlTqcJiaHegLbJzmre0yIdP",
          "width": 320
        },
        "z": {
          "extension": "jpg",
          "height": 415,
          "mimetype": "image/jpeg",
          "secret": "V2pm5jgwAKlTqcJiaHegLbJzmre0yIdP",
          "width": 640
        }
      }
    },
    "media:uri_template": "https://millsfield.sfomuseum.org/media/152/782/824/3/1527828243_{secret}_{label}.{extention}",
    "sfomuseum:filename": "44452.tif",
    "sfomuseum:image_index": 5,
    "sfomuseum:placetype": "image",
    "sfomuseum:primary_image": 1,
    "wof:depicts": [
      1511949275
    ],
    "wof:name": "negative: San Francisco International Airport (SFO), Concorde",
    "wof:placetype": "media"
  },
  "geometry": {"coordinates":[-122.386155,37.616358],"type":"Point"}
}
