{
  "type": "Feature",
  "properties": {
    "iso:country": "XX",
    "media:fingerprint": "6af66b2e7766a49f5789485bf2818cb115e8faa7",
    "media:imagehash_avg": "a:0000fc7cfcfefef2",
    "media:imagehash_diff": "d:864858d83090ccc6",
    "media:medium": "image",
    "media:mimetype": "image/tiff",
    "media:properties": {
      "colours": [
        {
          "hex": "#808080",
          "name": "#808080",
          "reference": "vibrant"
        }, 
        {
          "hex": "#b6b6b6",
          "name": "#b6b6b6",
          "reference": "vibrant"
        }, 
        {
          "hex": "#464646",
          "name": "#464646",
          "reference": "vibrant"
        }
      ],
      "sizes": {
        "b": {
          "extension": "jpg",
          "height": 768,
          "mimetype": "image/jpeg",
          "secret": "XVxgTA8jEFxFqg3puvOSEZtgtlBACZt9",
          "width": 768
        },
        "c": {
          "extension": "jpg",
          "height": 600,
          "mimetype": "image/jpeg",
          "secret": "XVxgTA8jEFxFqg3puvOSEZtgtlBACZt9",
          "width": 600
        },
        "dc": {
          "extension": "jpg",
          "height": 600,
          "mimetype": "image/jpeg",
          "secret": "XVxgTA8jEFxFqg3puvOSEZtgtlBACZt9",
          "width": 600
        },
        "ds": {
          "extension": "jpg",
          "height": 320,
          "mimetype": "image/jpeg",
          "secret": "XVxgTA8jEFxFqg3puvOSEZtgtlBACZt9",
          "width": 320
        },
        "k": {
          "extension": "jpg",
          "height": 1536,
          "mimetype": "image/jpeg",
          "secret": "XVxgTA8jEFxFqg3puvOSEZtgtlBACZt9",
          "width": 1536
        },
        "n": {
          "extension": "jpg",
          "height": 239,
          "mimetype": "image/jpeg",
          "secret": "XVxgTA8jEFxFqg3puvOSEZtgtlBACZt9",
          "width": 239
        },
        "o": {
          "extension": "jpg",
          "height": 2563,
          "mimetype": "image/jpeg",
          "secret": "aXNEMQzsOlalM2FRmvX7dwtbcyWPcPyw",
          "width": 2563
        },
        "s": {
          "extension": "jpg",
          "height": 320,
          "mimetype": "image/jpeg",
          "secret": "XVxgTA8jEFxFqg3puvOSEZtgtlBACZt9",
          "width": 320
        },
        "z": {
          "extension": "jpg",
          "height": 479,
          "mimetype": "image/jpeg",
          "secret": "XVxgTA8jEFxFqg3puvOSEZtgtlBACZt9",
          "width": 479
        }
      }
    },
    "media:uri_template": "https://millsfield.sfomuseum.org/media/152/782/513/5/1527825135_{secret}_{label}.{extention}",
    "sfomuseum:filename": "42980.tif",
    "sfomuseum:image_index": 5,
    "sfomuseum:placetype": "image",
    "sfomuseum:primary_image": 1,
    "wof:depicts": [
      1511946061
    ],
    "wof:name": "negative: San Francisco International Airport (SFO), construction shop",
    "wof:placetype": "media"
  },
  "geometry": {"coordinates":[-122.386155,37.616358],"type":"Point"}
}
