{
  "type": "Feature",
  "properties": {
    "iso:country": "XX",
    "media:fingerprint": "62767511485c9034570b2c9213db2c48c9cf9345",
    "media:imagehash_avg": "a:f0f0c0c0c024fcff",
    "media:imagehash_diff": "d:6525240d49484818",
    "media:medium": "image",
    "media:mimetype": "image/tiff",
    "media:properties": {
      "colours": [
        {
          "hex": "#808080",
          "name": "#808080",
          "reference": "vibrant"
        },
        {
          "hex": "#b6b6b6",
          "name": "#b6b6b6",
          "reference": "vibrant"
        },
        {
          "hex": "#404040",
          "name": "#404040",
          "reference": "vibrant"
        }
      ],
      "sizes": {
        "b": {
          "extension": "jpg",
          "height": 768,
          "mimetype": "image/jpeg",
          "secret": "c2OgLDjtCl8qAcUKQObip1SdN5VyKDp5",
          "width": 591
        },
        "c": {
          "extension": "jpg",
          "height": 600,
          "mimetype": "image/jpeg",
          "secret": "c2OgLDjtCl8qAcUKQObip1SdN5VyKDp5",
          "width": 462
        },
        "dc": {
          "extension": "jpg",
          "height": 600,
          "mimetype": "image/jpeg",
          "secret": "c2OgLDjtCl8qAcUKQObip1SdN5VyKDp5",
          "width": 462
        },
        "ds": {
          "extension": "jpg",
          "height": 320,
          "mimetype": "image/jpeg",
          "secret": "c2OgLDjtCl8qAcUKQObip1SdN5VyKDp5",
          "width": 320
        },
        "k": {
          "extension": "jpg",
          "height": 1536,
          "mimetype": "image/jpeg",
          "secret": "c2OgLDjtCl8qAcUKQObip1SdN5VyKDp5",
          "width": 1182
        },
        "n": {
          "extension": "jpg",
          "height": 240,
          "mimetype": "image/jpeg",
          "secret": "c2OgLDjtCl8qAcUKQObip1SdN5VyKDp5",
          "width": 184
        },
        "o": {
          "extension": "jpg",
          "height": 8279,
          "mimetype": "image/jpeg",
          "secret": "S5BgwErfKhU1tQBKrJZdr0ecPWuRYQ0F",
          "width": 6375
        },
        "s": {
          "extension": "jpg",
          "height": 320,
          "mimetype": "image/jpeg",
          "secret": "c2OgLDjtCl8qAcUKQObip1SdN5VyKDp5",
          "width": 320
        },
        "z": {
          "extension": "jpg",
          "height": 480,
          "mimetype": "image/jpeg",
          "secret": "c2OgLDjtCl8qAcUKQObip1SdN5VyKDp5",
          "width": 369
        }
      }
    },
    "media:uri_template": "https://static.sfomuseum.org/media/152/783/053/7/1527830537_{secret}_{label}.{extention}",
    "sfomuseum:filename": "57621.tif",
    "sfomuseum:image_index": 5,
    "sfomuseum:image_type": "studio",
    "sfomuseum:placetype": "image",
    "sfomuseum:primary_image": 1,
    "wof:depicts": [
      1159284989,
      1511954891,
      1159286839
    ],
    "wof:name": "career history questionnaire: World Wings International, Sylvia Wallburger Ortlieb",
    "wof:placetype": "custom",
    "wof:placetype_alt": "image"
  },
  "geometry": {"coordinates":[-122.386155,37.616358],"type":"Point"}
}
