{
  "type": "Feature",
  "properties": {
    "iso:country": "US",
    "media:fingerprint": "0401d93b53a35938f8c806031e2bc33b719f9b5c",
    "media:imagehash_avg": "a:c381838f839717c7",
    "media:imagehash_diff": "d:171b3f373767670f",
    "media:medium": "image",
    "media:mimetype": "image/tiff",
    "media:properties": {
      "colours": [
        {
          "hex": "#c6333d",
          "name": "#c6333d",
          "reference": "vibrant"
        }, 
        {
          "hex": "#e09ca9",
          "name": "#e09ca9",
          "reference": "vibrant"
        }, 
        {
          "hex": "#2d3067",
          "name": "#2d3067",
          "reference": "vibrant"
        }, 
        {
          "hex": "#707076",
          "name": "#707076",
          "reference": "vibrant"
        }, 
        {
          "hex": "#c5949e",
          "name": "#c5949e",
          "reference": "vibrant"
        }
      ],
      "sizes": {
        "b": {
          "extension": "jpg",
          "height": 767,
          "mimetype": "image/jpeg",
          "secret": "ot2jntzldctDArVPrWXRvFwAQst1ZSmz",
          "width": 339
        },
        "c": {
          "extension": "jpg",
          "height": 600,
          "mimetype": "image/jpeg",
          "secret": "ot2jntzldctDArVPrWXRvFwAQst1ZSmz",
          "width": 265
        },
        "dc": {
          "extension": "jpg",
          "height": 600,
          "mimetype": "image/jpeg",
          "secret": "ot2jntzldctDArVPrWXRvFwAQst1ZSmz",
          "width": 265
        },
        "ds": {
          "extension": "jpg",
          "height": 320,
          "mimetype": "image/jpeg",
          "secret": "ot2jntzldctDArVPrWXRvFwAQst1ZSmz",
          "width": 296
        },
        "k": {
          "extension": "jpg",
          "height": 1535,
          "mimetype": "image/jpeg",
          "secret": "ot2jntzldctDArVPrWXRvFwAQst1ZSmz",
          "width": 679
        },
        "n": {
          "extension": "jpg",
          "height": 240,
          "mimetype": "image/jpeg",
          "secret": "ot2jntzldctDArVPrWXRvFwAQst1ZSmz",
          "width": 106
        },
        "o": {
          "extension": "jpg",
          "height": 667,
          "mimetype": "image/jpeg",
          "secret": "6Zx5IYXWbF2VwIOH7BPUh1OgiFQkxvW2",
          "width": 295
        },
        "s": {
          "extension": "jpg",
          "height": 320,
          "mimetype": "image/jpeg",
          "secret": "ot2jntzldctDArVPrWXRvFwAQst1ZSmz",
          "width": 296
        },
        "z": {
          "extension": "jpg",
          "height": 480,
          "mimetype": "image/jpeg",
          "secret": "ot2jntzldctDArVPrWXRvFwAQst1ZSmz",
          "width": 212
        }
      }
    },
    "media:uri_template": "https://millsfield.sfomuseum.org/media/152/781/863/7/1527818637_{secret}_{label}.{extention}",
    "sfomuseum:filename": "19115.tif",
    "sfomuseum:image_index": 5,
    "sfomuseum:placetype": "image",
    "sfomuseum:primary_image": 0,
    "wof:depicts": [
      1511909917
    ],
    "wof:name": "timetable: United Airlines, quick reference Chicago",
    "wof:placetype": "media"
  },
  "geometry": {"coordinates":[-122.386155,37.616358],"type":"Point"}
}
