{
  "type": "Feature",
  "properties": {
    "iso:country": "XX",
    "media:fingerprint": "7313c14b4fcb97f5c60a1f9871113fbbc6c12546",
    "media:imagehash_avg": "a:ffff7f3f07030000",
    "media:imagehash_diff": "d:f0f8e8ecfe770780",
    "media:medium": "image",
    "media:mimetype": "image/tiff",
    "media:properties": {
      "colours": [
        {
          "hex": "#868686",
          "name": "#868686",
          "reference": "vibrant"
        }, 
        {
          "hex": "#c0c0c0",
          "name": "#c0c0c0",
          "reference": "vibrant"
        }, 
        {
          "hex": "#404040",
          "name": "#404040",
          "reference": "vibrant"
        }
      ],
      "sizes": {
        "b": {
          "extension": "jpg",
          "height": 768,
          "mimetype": "image/jpeg",
          "secret": "6oinyb7ZMPx2asjXP3fjY2vsXYa4hHLM",
          "width": 768
        },
        "c": {
          "extension": "jpg",
          "height": 600,
          "mimetype": "image/jpeg",
          "secret": "6oinyb7ZMPx2asjXP3fjY2vsXYa4hHLM",
          "width": 600
        },
        "dc": {
          "extension": "jpg",
          "height": 600,
          "mimetype": "image/jpeg",
          "secret": "6oinyb7ZMPx2asjXP3fjY2vsXYa4hHLM",
          "width": 600
        },
        "ds": {
          "extension": "jpg",
          "height": 320,
          "mimetype": "image/jpeg",
          "secret": "6oinyb7ZMPx2asjXP3fjY2vsXYa4hHLM",
          "width": 320
        },
        "k": {
          "extension": "jpg",
          "height": 1536,
          "mimetype": "image/jpeg",
          "secret": "6oinyb7ZMPx2asjXP3fjY2vsXYa4hHLM",
          "width": 1536
        },
        "n": {
          "extension": "jpg",
          "height": 240,
          "mimetype": "image/jpeg",
          "secret": "6oinyb7ZMPx2asjXP3fjY2vsXYa4hHLM",
          "width": 240
        },
        "o": {
          "extension": "jpg",
          "height": 2536,
          "mimetype": "image/jpeg",
          "secret": "4fOnUOvGtqNZoTLnIzjcPNzmxvhNSq5Z",
          "width": 2536
        },
        "s": {
          "extension": "jpg",
          "height": 320,
          "mimetype": "image/jpeg",
          "secret": "6oinyb7ZMPx2asjXP3fjY2vsXYa4hHLM",
          "width": 320
        },
        "z": {
          "extension": "jpg",
          "height": 480,
          "mimetype": "image/jpeg",
          "secret": "6oinyb7ZMPx2asjXP3fjY2vsXYa4hHLM",
          "width": 480
        }
      }
    },
    "media:uri_template": "https://millsfield.sfomuseum.org/media/152/782/519/3/1527825193_{secret}_{label}.{extention}",
    "sfomuseum:filename": "43017.tif",
    "sfomuseum:image_index": 5,
    "sfomuseum:placetype": "image",
    "sfomuseum:primary_image": 1,
    "wof:depicts": [
      1511946121
    ],
    "wof:name": "negative: San Francisco International Airport (SFO), runway or taxiway construction",
    "wof:placetype": "media"
  },
  "geometry": {"coordinates":[-122.386155,37.616358],"type":"Point"}
}
