{
  "type": "Feature",
  "properties": {
    "iso:country": "XX",
    "media:fingerprint": "b27f346efc6af06e3bfe4d475784f7b7dcc6c094",
    "media:imagehash_avg": "a:fffffefe00000000",
    "media:imagehash_diff": "d:8080e07862707c55",
    "media:medium": "image",
    "media:mimetype": "image/tiff",
    "media:properties": {
      "colours": [
        {
          "hex": "#808080",
          "name": "#808080",
          "reference": "vibrant"
        }, 
        {
          "hex": "#b8b8b8",
          "name": "#b8b8b8",
          "reference": "vibrant"
        }, 
        {
          "hex": "#404040",
          "name": "#404040",
          "reference": "vibrant"
        }
      ],
      "sizes": {
        "b": {
          "extension": "jpg",
          "height": 727,
          "mimetype": "image/jpeg",
          "secret": "vXL4d0lLuQLR4lYa8qiFWrf9o5nDSuQI",
          "width": 1024
        },
        "c": {
          "extension": "jpg",
          "height": 568,
          "mimetype": "image/jpeg",
          "secret": "vXL4d0lLuQLR4lYa8qiFWrf9o5nDSuQI",
          "width": 799
        },
        "dc": {
          "extension": "jpg",
          "height": 568,
          "mimetype": "image/jpeg",
          "secret": "vXL4d0lLuQLR4lYa8qiFWrf9o5nDSuQI",
          "width": 799
        },
        "ds": {
          "extension": "jpg",
          "height": 320,
          "mimetype": "image/jpeg",
          "secret": "vXL4d0lLuQLR4lYa8qiFWrf9o5nDSuQI",
          "width": 320
        },
        "k": {
          "extension": "jpg",
          "height": 1454,
          "mimetype": "image/jpeg",
          "secret": "vXL4d0lLuQLR4lYa8qiFWrf9o5nDSuQI",
          "width": 2048
        },
        "n": {
          "extension": "jpg",
          "height": 227,
          "mimetype": "image/jpeg",
          "secret": "vXL4d0lLuQLR4lYa8qiFWrf9o5nDSuQI",
          "width": 320
        },
        "o": {
          "extension": "jpg",
          "height": 4145,
          "mimetype": "image/jpeg",
          "secret": "ijPlQstkP9elv8WHlwynV4HOS5W80ZFc",
          "width": 5836
        },
        "s": {
          "extension": "jpg",
          "height": 320,
          "mimetype": "image/jpeg",
          "secret": "vXL4d0lLuQLR4lYa8qiFWrf9o5nDSuQI",
          "width": 320
        },
        "z": {
          "extension": "jpg",
          "height": 454,
          "mimetype": "image/jpeg",
          "secret": "vXL4d0lLuQLR4lYa8qiFWrf9o5nDSuQI",
          "width": 640
        }
      }
    },
    "media:uri_template": "https://millsfield.sfomuseum.org/media/152/782/151/9/1527821519_{secret}_{label}.{extention}",
    "sfomuseum:filename": "38849.tif",
    "sfomuseum:image_index": 5,
    "sfomuseum:placetype": "image",
    "sfomuseum:primary_image": 1,
    "wof:depicts": [
      1511943603
    ],
    "wof:name": "negative: San Francisco Airport, construction",
    "wof:placetype": "media"
  },
  "geometry": {"coordinates":[-122.386155,37.616358],"type":"Point"}
}
