{
  "type": "Feature",
  "properties": {
    "iso:country": "XX",
    "media:fingerprint": "b2dbb11359882b5cb62b2beac5095de9224e3d10",
    "media:imagehash_avg": "a:f7c383c301ffffff",
    "media:imagehash_diff": "d:8687179f5773dadb",
    "media:medium": "image",
    "media:mimetype": "image/tiff",
    "media:properties": {
      "colours": [
        {
          "hex": "#516fa9",
          "name": "#516fa9",
          "reference": "vibrant"
        }, 
        {
          "hex": "#f6edd8",
          "name": "#f6edd8",
          "reference": "vibrant"
        }, 
        {
          "hex": "#2a3b78",
          "name": "#2a3b78",
          "reference": "vibrant"
        }, 
        {
          "hex": "#48659c",
          "name": "#48659c",
          "reference": "vibrant"
        }, 
        {
          "hex": "#b7bec6",
          "name": "#b7bec6",
          "reference": "vibrant"
        }
      ],
      "sizes": {
        "b": {
          "extension": "jpg",
          "height": 768,
          "mimetype": "image/jpeg",
          "secret": "y8ruoOnNBxpanBZSeQvCYBbhUj1oOwPi",
          "width": 465
        },
        "c": {
          "extension": "jpg",
          "height": 600,
          "mimetype": "image/jpeg",
          "secret": "y8ruoOnNBxpanBZSeQvCYBbhUj1oOwPi",
          "width": 363
        },
        "dc": {
          "extension": "jpg",
          "height": 600,
          "mimetype": "image/jpeg",
          "secret": "y8ruoOnNBxpanBZSeQvCYBbhUj1oOwPi",
          "width": 363
        },
        "ds": {
          "extension": "jpg",
          "height": 320,
          "mimetype": "image/jpeg",
          "secret": "y8ruoOnNBxpanBZSeQvCYBbhUj1oOwPi",
          "width": 320
        },
        "k": {
          "extension": "jpg",
          "height": 1536,
          "mimetype": "image/jpeg",
          "secret": "y8ruoOnNBxpanBZSeQvCYBbhUj1oOwPi",
          "width": 931
        },
        "n": {
          "extension": "jpg",
          "height": 240,
          "mimetype": "image/jpeg",
          "secret": "y8ruoOnNBxpanBZSeQvCYBbhUj1oOwPi",
          "width": 145
        },
        "o": {
          "extension": "jpg",
          "height": 3155,
          "mimetype": "image/jpeg",
          "secret": "sUGc1HebipDs62fOf9C8n8egGcjuR5D7",
          "width": 1913
        },
        "s": {
          "extension": "jpg",
          "height": 320,
          "mimetype": "image/jpeg",
          "secret": "y8ruoOnNBxpanBZSeQvCYBbhUj1oOwPi",
          "width": 320
        },
        "z": {
          "extension": "jpg",
          "height": 480,
          "mimetype": "image/jpeg",
          "secret": "y8ruoOnNBxpanBZSeQvCYBbhUj1oOwPi",
          "width": 291
        }
      }
    },
    "media:uri_template": "https://millsfield.sfomuseum.org/media/152/782/354/3/1527823543_{secret}_{label}.{extention}",
    "sfomuseum:filename": "41648.tif",
    "sfomuseum:image_index": 5,
    "sfomuseum:placetype": "image",
    "sfomuseum:primary_image": 0,
    "wof:depicts": [
      1511927347
    ],
    "wof:name": "airsickness bag: Air New Zealand",
    "wof:placetype": "media"
  },
  "geometry": {"coordinates":[-122.386155,37.616358],"type":"Point"}
}
