{
  "type": "Feature",
  "properties": {
    "iso:country": "XX",
    "media:fingerprint": "ce214db4f3bde8558379e02a203bb23d8dc0f6d5",
    "media:imagehash_avg": "a:1a04fefefefeda88",
    "media:imagehash_diff": "d:726c24148c543232",
    "media:medium": "image",
    "media:mimetype": "image/tiff",
    "media:properties": {
      "colours": [
        {
          "hex": "#c98d8f",
          "name": "#c98d8f",
          "reference": "vibrant"
        },
        {
          "hex": "#8b6d4b",
          "name": "#8b6d4b",
          "reference": "vibrant"
        },
        {
          "hex": "#aecdb9",
          "name": "#aecdb9",
          "reference": "vibrant"
        },
        {
          "hex": "#393e32",
          "name": "#393e32",
          "reference": "vibrant"
        }
      ],
      "sizes": {
        "b": {
          "extension": "jpg",
          "height": 658,
          "mimetype": "image/jpeg",
          "secret": "fC23vws7meQbkpNSzRgBxa3gUTQgz1HQ",
          "width": 1024
        },
        "c": {
          "extension": "jpg",
          "height": 514,
          "mimetype": "image/jpeg",
          "secret": "fC23vws7meQbkpNSzRgBxa3gUTQgz1HQ",
          "width": 800
        },
        "dc": {
          "extension": "jpg",
          "height": 514,
          "mimetype": "image/jpeg",
          "secret": "fC23vws7meQbkpNSzRgBxa3gUTQgz1HQ",
          "width": 800
        },
        "ds": {
          "extension": "jpg",
          "height": 320,
          "mimetype": "image/jpeg",
          "secret": "fC23vws7meQbkpNSzRgBxa3gUTQgz1HQ",
          "width": 320
        },
        "k": {
          "extension": "jpg",
          "height": 1316,
          "mimetype": "image/jpeg",
          "secret": "fC23vws7meQbkpNSzRgBxa3gUTQgz1HQ",
          "width": 2048
        },
        "n": {
          "extension": "jpg",
          "height": 205,
          "mimetype": "image/jpeg",
          "secret": "fC23vws7meQbkpNSzRgBxa3gUTQgz1HQ",
          "width": 320
        },
        "o": {
          "extension": "jpg",
          "height": 2569,
          "mimetype": "image/jpeg",
          "secret": "fx3kAWsoOVUiKIHZH5WV4ny18HxTmNAK",
          "width": 3996
        },
        "s": {
          "extension": "jpg",
          "height": 320,
          "mimetype": "image/jpeg",
          "secret": "fC23vws7meQbkpNSzRgBxa3gUTQgz1HQ",
          "width": 320
        },
        "z": {
          "extension": "jpg",
          "height": 411,
          "mimetype": "image/jpeg",
          "secret": "fC23vws7meQbkpNSzRgBxa3gUTQgz1HQ",
          "width": 640
        }
      }
    },
    "media:uri_template": "https://static.sfomuseum.org/media/152/784/572/1/1527845721_{secret}_{label}.{extention}",
    "sfomuseum:filename": "70441.tif",
    "sfomuseum:image_index": 5,
    "sfomuseum:image_type": "studio",
    "sfomuseum:placetype": "image",
    "sfomuseum:primary_image": 0,
    "wof:depicts": [
      1159284127,
      1511949939
    ],
    "wof:name": "timetable: Cathay Pacific Airways",
    "wof:placetype": "custom",
    "wof:placetype_alt": "image"
  },
  "geometry": {"coordinates":[-122.386155,37.616358],"type":"Point"}
}
