{
  "type": "Feature",
  "properties": {
    "iso:country": "XX",
    "media:fingerprint": "81ec67d6afb2635a0e628c31c846010548002900",
    "media:imagehash_avg": "a:00010000fd7fff7f",
    "media:imagehash_diff": "d:efcfefc783fb3cfc",
    "media:medium": "image",
    "media:mimetype": "image/tiff",
    "media:properties": {
      "colours": [
        {
          "hex": "#808080",
          "name": "#808080",
          "reference": "vibrant"
        }, 
        {
          "hex": "#b8b8b8",
          "name": "#b8b8b8",
          "reference": "vibrant"
        }, 
        {
          "hex": "#484848",
          "name": "#484848",
          "reference": "vibrant"
        }
      ],
      "sizes": {
        "b": {
          "extension": "jpg",
          "height": 768,
          "mimetype": "image/jpeg",
          "secret": "txk8fIhQJAQDvt3amvTSLE24Wb4psmep",
          "width": 768
        },
        "c": {
          "extension": "jpg",
          "height": 600,
          "mimetype": "image/jpeg",
          "secret": "txk8fIhQJAQDvt3amvTSLE24Wb4psmep",
          "width": 600
        },
        "dc": {
          "extension": "jpg",
          "height": 600,
          "mimetype": "image/jpeg",
          "secret": "txk8fIhQJAQDvt3amvTSLE24Wb4psmep",
          "width": 600
        },
        "ds": {
          "extension": "jpg",
          "height": 320,
          "mimetype": "image/jpeg",
          "secret": "txk8fIhQJAQDvt3amvTSLE24Wb4psmep",
          "width": 320
        },
        "k": {
          "extension": "jpg",
          "height": 1536,
          "mimetype": "image/jpeg",
          "secret": "txk8fIhQJAQDvt3amvTSLE24Wb4psmep",
          "width": 1536
        },
        "n": {
          "extension": "jpg",
          "height": 239,
          "mimetype": "image/jpeg",
          "secret": "txk8fIhQJAQDvt3amvTSLE24Wb4psmep",
          "width": 239
        },
        "o": {
          "extension": "jpg",
          "height": 2563,
          "mimetype": "image/jpeg",
          "secret": "uNyeIaEWw5VMt9o8u4IEm5TAwYCDLqa8",
          "width": 2563
        },
        "s": {
          "extension": "jpg",
          "height": 320,
          "mimetype": "image/jpeg",
          "secret": "txk8fIhQJAQDvt3amvTSLE24Wb4psmep",
          "width": 320
        },
        "z": {
          "extension": "jpg",
          "height": 479,
          "mimetype": "image/jpeg",
          "secret": "txk8fIhQJAQDvt3amvTSLE24Wb4psmep",
          "width": 479
        }
      }
    },
    "media:uri_template": "https://millsfield.sfomuseum.org/media/152/782/512/1/1527825121_{secret}_{label}.{extention}",
    "sfomuseum:filename": "42974.tif",
    "sfomuseum:image_index": 5,
    "sfomuseum:placetype": "image",
    "sfomuseum:primary_image": 1,
    "wof:depicts": [
      1511946049
    ],
    "wof:name": "negative: San Francisco International Airport (SFO), construction shop",
    "wof:placetype": "media"
  },
  "geometry": {"coordinates":[-122.386155,37.616358],"type":"Point"}
}
