{
  "type": "Feature",
  "properties": {
    "iso:country": "XX",
    "media:fingerprint": "512a787e4807b2d652d70134c7d4629983d8ee1f",
    "media:imagehash_avg": "a:ff81818181819fff",
    "media:imagehash_diff": "d:1f17171f0f2f3738",
    "media:medium": "image",
    "media:mimetype": "image/tiff",
    "media:properties": {
      "colours": [
        {
          "hex": "#838581",
          "name": "#838581",
          "reference": "vibrant"
        },
        {
          "hex": "#bbbdbc",
          "name": "#bbbdbc",
          "reference": "vibrant"
        },
        {
          "hex": "#43453e",
          "name": "#43453e",
          "reference": "vibrant"
        }
      ],
      "sizes": {
        "b": {
          "extension": "jpg",
          "height": 397,
          "mimetype": "image/jpeg",
          "secret": "S4rOfxY6Z5gxfPKnwXnWJf4f9GUdyE62",
          "width": 1024
        },
        "c": {
          "extension": "jpg",
          "height": 310,
          "mimetype": "image/jpeg",
          "secret": "S4rOfxY6Z5gxfPKnwXnWJf4f9GUdyE62",
          "width": 800
        },
        "dc": {
          "extension": "jpg",
          "height": 310,
          "mimetype": "image/jpeg",
          "secret": "S4rOfxY6Z5gxfPKnwXnWJf4f9GUdyE62",
          "width": 800
        },
        "ds": {
          "extension": "jpg",
          "height": 320,
          "mimetype": "image/jpeg",
          "secret": "S4rOfxY6Z5gxfPKnwXnWJf4f9GUdyE62",
          "width": 320
        },
        "k": {
          "extension": "jpg",
          "height": 795,
          "mimetype": "image/jpeg",
          "secret": "S4rOfxY6Z5gxfPKnwXnWJf4f9GUdyE62",
          "width": 2048
        },
        "n": {
          "extension": "jpg",
          "height": 124,
          "mimetype": "image/jpeg",
          "secret": "S4rOfxY6Z5gxfPKnwXnWJf4f9GUdyE62",
          "width": 320
        },
        "o": {
          "extension": "jpg",
          "height": 1711,
          "mimetype": "image/jpeg",
          "secret": "l3kFIADHvBbngXvIUG7e0tG1J175ktxV",
          "width": 4405
        },
        "s": {
          "extension": "jpg",
          "height": 320,
          "mimetype": "image/jpeg",
          "secret": "S4rOfxY6Z5gxfPKnwXnWJf4f9GUdyE62",
          "width": 320
        },
        "z": {
          "extension": "jpg",
          "height": 248,
          "mimetype": "image/jpeg",
          "secret": "S4rOfxY6Z5gxfPKnwXnWJf4f9GUdyE62",
          "width": 640
        }
      }
    },
    "media:uri_template": "https://static.sfomuseum.org/media/152/785/198/3/1527851983_{secret}_{label}.{extention}",
    "sfomuseum:filename": "85465.tif",
    "sfomuseum:image_index": 5,
    "sfomuseum:image_type": "studio",
    "sfomuseum:placetype": "image",
    "sfomuseum:primary_image": 1,
    "wof:depicts": [
      1511956319
    ],
    "wof:name": "airmail flight cover: Richard Archibald Trans-Pacific Flight / New Guinea Expedition and Return, May 24, 1938 - July 1, 1939",
    "wof:placetype": "custom",
    "wof:placetype_alt": "image"
  },
  "geometry": {"coordinates":[-122.386155,37.616358],"type":"Point"}
}
