{
  "type": "Feature",
  "properties": {
    "iso:country": "US",
    "media:fingerprint": "42410c1dbde9219f5ba34ec1b8795f47ebebde83",
    "media:imagehash_avg": "a:ffe7c7c3c38181cf",
    "media:imagehash_diff": "d:0d0f0f0f13530b3b",
    "media:medium": "image",
    "media:mimetype": "image/tiff",
    "media:properties": {
      "colours": [
        {
          "hex": "#f8e8c8",
          "name": "#f8e8c8",
          "reference": "vibrant"
        }, 
        {
          "hex": "#6c6f88",
          "name": "#6c6f88",
          "reference": "vibrant"
        }, 
        {
          "hex": "#c9c6b7",
          "name": "#c9c6b7",
          "reference": "vibrant"
        }, 
        {
          "hex": "#293055",
          "name": "#293055",
          "reference": "vibrant"
        }
      ],
      "sizes": {
        "b": {
          "extension": "jpg",
          "height": 592,
          "mimetype": "image/jpeg",
          "secret": "byKaSa7ia2XVkUJ8wagc232hL1vDzTWD",
          "width": 1023
        },
        "c": {
          "extension": "jpg",
          "height": 462,
          "mimetype": "image/jpeg",
          "secret": "byKaSa7ia2XVkUJ8wagc232hL1vDzTWD",
          "width": 800
        },
        "dc": {
          "extension": "jpg",
          "height": 462,
          "mimetype": "image/jpeg",
          "secret": "byKaSa7ia2XVkUJ8wagc232hL1vDzTWD",
          "width": 800
        },
        "ds": {
          "extension": "jpg",
          "height": 320,
          "mimetype": "image/jpeg",
          "secret": "byKaSa7ia2XVkUJ8wagc232hL1vDzTWD",
          "width": 320
        },
        "k": {
          "extension": "jpg",
          "height": 1184,
          "mimetype": "image/jpeg",
          "secret": "byKaSa7ia2XVkUJ8wagc232hL1vDzTWD",
          "width": 2047
        },
        "n": {
          "extension": "jpg",
          "height": 185,
          "mimetype": "image/jpeg",
          "secret": "byKaSa7ia2XVkUJ8wagc232hL1vDzTWD",
          "width": 320
        },
        "o": {
          "extension": "jpg",
          "height": 1171,
          "mimetype": "image/jpeg",
          "secret": "IcMT5HN3mO6tGNuTAdxYzkHU1y1jV7KA",
          "width": 2024
        },
        "s": {
          "extension": "jpg",
          "height": 320,
          "mimetype": "image/jpeg",
          "secret": "byKaSa7ia2XVkUJ8wagc232hL1vDzTWD",
          "width": 320
        },
        "z": {
          "extension": "jpg",
          "height": 370,
          "mimetype": "image/jpeg",
          "secret": "byKaSa7ia2XVkUJ8wagc232hL1vDzTWD",
          "width": 640
        }
      }
    },
    "media:uri_template": "https://millsfield.sfomuseum.org/media/152/782/915/3/1527829153_{secret}_{label}.{extention}",
    "sfomuseum:filename": "47541.tif",
    "sfomuseum:image_index": 5,
    "sfomuseum:placetype": "image",
    "sfomuseum:primary_image": 0,
    "wof:depicts": [
      1511907379
    ],
    "wof:name": "airmail flight cover: Pan American World Airways, FAM-19, Honolulu - Sydney route",
    "wof:placetype": "media"
  },
  "geometry": {"coordinates":[-122.386155,37.616358],"type":"Point"}
}
