{
  "type": "Feature",
  "properties": {
    "iso:country": "XX",
    "media:fingerprint": "d42d69a23ba2c633e0fa8cbbb1ea0bc7ae5090fc",
    "media:imagehash_avg": "a:fdc08080f1f980fd",
    "media:imagehash_diff": "d:0b0949092b212929",
    "media:medium": "image",
    "media:mimetype": "image/tiff",
    "media:properties": {
      "colours": [
        {
          "hex": "#1e1e0a",
          "name": "#1e1e0a",
          "reference": "vibrant"
        },
        {
          "hex": "#8a8669",
          "name": "#8a8669",
          "reference": "vibrant"
        },
        {
          "hex": "#d0c6a7",
          "name": "#d0c6a7",
          "reference": "vibrant"
        },
        {
          "hex": "#4a4733",
          "name": "#4a4733",
          "reference": "vibrant"
        }
      ],
      "sizes": {
        "b": {
          "extension": "jpg",
          "height": 734,
          "mimetype": "image/jpeg",
          "secret": "iLq2h4DJC6MBOSWN27UaqbFpHSNjfnG1",
          "width": 1024
        },
        "c": {
          "extension": "jpg",
          "height": 574,
          "mimetype": "image/jpeg",
          "secret": "iLq2h4DJC6MBOSWN27UaqbFpHSNjfnG1",
          "width": 800
        },
        "dc": {
          "extension": "jpg",
          "height": 574,
          "mimetype": "image/jpeg",
          "secret": "iLq2h4DJC6MBOSWN27UaqbFpHSNjfnG1",
          "width": 800
        },
        "ds": {
          "extension": "jpg",
          "height": 320,
          "mimetype": "image/jpeg",
          "secret": "iLq2h4DJC6MBOSWN27UaqbFpHSNjfnG1",
          "width": 320
        },
        "k": {
          "extension": "jpg",
          "height": 1469,
          "mimetype": "image/jpeg",
          "secret": "iLq2h4DJC6MBOSWN27UaqbFpHSNjfnG1",
          "width": 2048
        },
        "n": {
          "extension": "jpg",
          "height": 229,
          "mimetype": "image/jpeg",
          "secret": "iLq2h4DJC6MBOSWN27UaqbFpHSNjfnG1",
          "width": 320
        },
        "o": {
          "extension": "jpg",
          "height": 3032,
          "mimetype": "image/jpeg",
          "secret": "U3FtlkMbTI6k4mT8I03hSkbp9p8yIf2y",
          "width": 4225
        },
        "s": {
          "extension": "jpg",
          "height": 320,
          "mimetype": "image/jpeg",
          "secret": "iLq2h4DJC6MBOSWN27UaqbFpHSNjfnG1",
          "width": 320
        },
        "z": {
          "extension": "jpg",
          "height": 459,
          "mimetype": "image/jpeg",
          "secret": "iLq2h4DJC6MBOSWN27UaqbFpHSNjfnG1",
          "width": 640
        }
      }
    },
    "media:uri_template": "https://static.sfomuseum.org/media/152/785/600/3/1527856003_{secret}_{label}.{extention}",
    "sfomuseum:filename": "100547.tif",
    "sfomuseum:image_index": 5,
    "sfomuseum:image_type": "studio",
    "sfomuseum:placetype": "image",
    "sfomuseum:primary_image": 1,
    "wof:depicts": [
      1511942867
    ],
    "wof:name": "photograph: San Francisco Bay Area, engine",
    "wof:placetype": "custom",
    "wof:placetype_alt": "image"
  },
  "geometry": {"coordinates":[-122.386155,37.616358],"type":"Point"}
}
