{
  "type": "Feature",
  "properties": {
    "iso:country": "XX",
    "media:fingerprint": "a538fd045418b55e7372f0ee2ec6dcd1fdc4f185",
    "media:imagehash_avg": "a:ffff7f0f00f00000",
    "media:imagehash_diff": "d:b7bfbfff15e1cdfb",
    "media:medium": "image",
    "media:mimetype": "image/tiff",
    "media:properties": {
      "colours": [
        {
          "hex": "#808080",
          "name": "#808080",
          "reference": "vibrant"
        },
        {
          "hex": "#c0c0c0",
          "name": "#c0c0c0",
          "reference": "vibrant"
        },
        {
          "hex": "#4a4a4a",
          "name": "#4a4a4a",
          "reference": "vibrant"
        }
      ],
      "sizes": {
        "b": {
          "extension": "jpg",
          "height": 676,
          "mimetype": "image/jpeg",
          "secret": "WcyD6l03svbfpiVfzPlColYH1dUlEKoy",
          "width": 1024
        },
        "c": {
          "extension": "jpg",
          "height": 528,
          "mimetype": "image/jpeg",
          "secret": "WcyD6l03svbfpiVfzPlColYH1dUlEKoy",
          "width": 800
        },
        "dc": {
          "extension": "jpg",
          "height": 528,
          "mimetype": "image/jpeg",
          "secret": "WcyD6l03svbfpiVfzPlColYH1dUlEKoy",
          "width": 800
        },
        "ds": {
          "extension": "jpg",
          "height": 320,
          "mimetype": "image/jpeg",
          "secret": "WcyD6l03svbfpiVfzPlColYH1dUlEKoy",
          "width": 320
        },
        "k": {
          "extension": "jpg",
          "height": 1352,
          "mimetype": "image/jpeg",
          "secret": "WcyD6l03svbfpiVfzPlColYH1dUlEKoy",
          "width": 2048
        },
        "n": {
          "extension": "jpg",
          "height": 211,
          "mimetype": "image/jpeg",
          "secret": "WcyD6l03svbfpiVfzPlColYH1dUlEKoy",
          "width": 320
        },
        "o": {
          "extension": "jpg",
          "height": 887,
          "mimetype": "image/jpeg",
          "secret": "ZzG9iaetODj6OIthxsCtau3TgSnmZfTc",
          "width": 1343
        },
        "s": {
          "extension": "jpg",
          "height": 320,
          "mimetype": "image/jpeg",
          "secret": "WcyD6l03svbfpiVfzPlColYH1dUlEKoy",
          "width": 320
        },
        "z": {
          "extension": "jpg",
          "height": 422,
          "mimetype": "image/jpeg",
          "secret": "WcyD6l03svbfpiVfzPlColYH1dUlEKoy",
          "width": 640
        }
      }
    },
    "media:uri_template": "https://static.sfomuseum.org/media/152/782/088/7/1527820887_{secret}_{label}.{extention}",
    "sfomuseum:filename": "33224.tif",
    "sfomuseum:image_index": 5,
    "sfomuseum:image_type": "studio",
    "sfomuseum:placetype": "image",
    "sfomuseum:primary_image": 1,
    "wof:depicts": [
      1511931327,
      1159284991,
      1159291669,
      1159286839
    ],
    "wof:name": "photograph: Pan American Airways, Sikorsky S-42",
    "wof:placetype": "custom",
    "wof:placetype_alt": "image"
  },
  "geometry": {"coordinates":[-122.386155,37.616358],"type":"Point"}
}
