{
  "type": "Feature",
  "properties": {
    "iso:country": "XX",
    "media:fingerprint": "332ae773a40afd3b18d0afb8016911407cf13ca8",
    "media:imagehash_avg": "a:ff04030302bffcec",
    "media:imagehash_diff": "d:705dcf163e34b098",
    "media:medium": "image",
    "media:mimetype": "image/tiff",
    "media:properties": {
      "colours": [
        {
          "hex": "#808080",
          "name": "#808080",
          "reference": "vibrant"
        }, 
        {
          "hex": "#b8b8b8",
          "name": "#b8b8b8",
          "reference": "vibrant"
        }, 
        {
          "hex": "#484848",
          "name": "#484848",
          "reference": "vibrant"
        }
      ],
      "sizes": {
        "b": {
          "extension": "jpg",
          "height": 767,
          "mimetype": "image/jpeg",
          "secret": "IbCYaMhvX5gYuh891n1v2ZgOtWN3Insc",
          "width": 988
        },
        "c": {
          "extension": "jpg",
          "height": 600,
          "mimetype": "image/jpeg",
          "secret": "IbCYaMhvX5gYuh891n1v2ZgOtWN3Insc",
          "width": 772
        },
        "dc": {
          "extension": "jpg",
          "height": 600,
          "mimetype": "image/jpeg",
          "secret": "IbCYaMhvX5gYuh891n1v2ZgOtWN3Insc",
          "width": 772
        },
        "ds": {
          "extension": "jpg",
          "height": 320,
          "mimetype": "image/jpeg",
          "secret": "IbCYaMhvX5gYuh891n1v2ZgOtWN3Insc",
          "width": 320
        },
        "k": {
          "extension": "jpg",
          "height": 1535,
          "mimetype": "image/jpeg",
          "secret": "IbCYaMhvX5gYuh891n1v2ZgOtWN3Insc",
          "width": 1976
        },
        "n": {
          "extension": "jpg",
          "height": 240,
          "mimetype": "image/jpeg",
          "secret": "IbCYaMhvX5gYuh891n1v2ZgOtWN3Insc",
          "width": 308
        },
        "o": {
          "extension": "jpg",
          "height": 2140,
          "mimetype": "image/jpeg",
          "secret": "KeUyGPF3EMLD4SW2I62JmQ1UhimMf4gn",
          "width": 2754
        },
        "s": {
          "extension": "jpg",
          "height": 320,
          "mimetype": "image/jpeg",
          "secret": "IbCYaMhvX5gYuh891n1v2ZgOtWN3Insc",
          "width": 320
        },
        "z": {
          "extension": "jpg",
          "height": 480,
          "mimetype": "image/jpeg",
          "secret": "IbCYaMhvX5gYuh891n1v2ZgOtWN3Insc",
          "width": 617
        }
      }
    },
    "media:uri_template": "https://millsfield.sfomuseum.org/media/152/782/229/3/1527822293_{secret}_{label}.{extention}",
    "sfomuseum:filename": "40644.tif",
    "sfomuseum:image_index": 5,
    "sfomuseum:placetype": "image",
    "sfomuseum:primary_image": 1,
    "wof:depicts": [
      1511944199
    ],
    "wof:name": "negative: San Francisco International Airport (SFO), drainage canals",
    "wof:placetype": "media"
  },
  "geometry": {"coordinates":[-122.386155,37.616358],"type":"Point"}
}
