{
  "type": "Feature",
  "properties": {
    "iso:country": "XX",
    "media:fingerprint": "f79c16203dbc77a3c03b0a29373d47d868c4a12a",
    "media:imagehash_avg": "a:7effff3e38100001",
    "media:imagehash_diff": "d:f0f8fce0e0e1f1f9",
    "media:medium": "image",
    "media:mimetype": "image/tiff",
    "media:properties": {
      "colours": [
        {
          "hex": "#7a7a7a",
          "name": "#7a7a7a",
          "reference": "vibrant"
        }, 
        {
          "hex": "#b8b8b8",
          "name": "#b8b8b8",
          "reference": "vibrant"
        }, 
        {
          "hex": "#464646",
          "name": "#464646",
          "reference": "vibrant"
        }
      ],
      "sizes": {
        "b": {
          "extension": "jpg",
          "height": 768,
          "mimetype": "image/jpeg",
          "secret": "fF8G3bWMNLrYK8Va8dx46RAoKxGeoXfh",
          "width": 968
        },
        "c": {
          "extension": "jpg",
          "height": 600,
          "mimetype": "image/jpeg",
          "secret": "fF8G3bWMNLrYK8Va8dx46RAoKxGeoXfh",
          "width": 756
        },
        "dc": {
          "extension": "jpg",
          "height": 600,
          "mimetype": "image/jpeg",
          "secret": "fF8G3bWMNLrYK8Va8dx46RAoKxGeoXfh",
          "width": 756
        },
        "ds": {
          "extension": "jpg",
          "height": 320,
          "mimetype": "image/jpeg",
          "secret": "fF8G3bWMNLrYK8Va8dx46RAoKxGeoXfh",
          "width": 320
        },
        "k": {
          "extension": "jpg",
          "height": 1536,
          "mimetype": "image/jpeg",
          "secret": "fF8G3bWMNLrYK8Va8dx46RAoKxGeoXfh",
          "width": 1936
        },
        "n": {
          "extension": "jpg",
          "height": 240,
          "mimetype": "image/jpeg",
          "secret": "fF8G3bWMNLrYK8Va8dx46RAoKxGeoXfh",
          "width": 302
        },
        "o": {
          "extension": "jpg",
          "height": 2195,
          "mimetype": "image/jpeg",
          "secret": "jatjZgE8aEVEhjHvIqzvaZaQdwPJYwj6",
          "width": 2768
        },
        "s": {
          "extension": "jpg",
          "height": 320,
          "mimetype": "image/jpeg",
          "secret": "fF8G3bWMNLrYK8Va8dx46RAoKxGeoXfh",
          "width": 320
        },
        "z": {
          "extension": "jpg",
          "height": 480,
          "mimetype": "image/jpeg",
          "secret": "fF8G3bWMNLrYK8Va8dx46RAoKxGeoXfh",
          "width": 605
        }
      }
    },
    "media:uri_template": "https://millsfield.sfomuseum.org/media/152/782/577/3/1527825773_{secret}_{label}.{extention}",
    "sfomuseum:filename": "43329.tif",
    "sfomuseum:image_index": 5,
    "sfomuseum:placetype": "image",
    "sfomuseum:primary_image": 1,
    "wof:depicts": [
      1511946809
    ],
    "wof:name": "negative: San Francisco International Airport (SFO), aerial",
    "wof:placetype": "media"
  },
  "geometry": {"coordinates":[-122.386155,37.616358],"type":"Point"}
}
