{
  "type": "Feature",
  "properties": {
    "iso:country": "XX",
    "media:fingerprint": "f29abf0b9e31da8b3c0eacb7b7a5b615c1b4235a",
    "media:imagehash_avg": "a:ff898181818181ff",
    "media:imagehash_diff": "d:7b7b636b717b7d71",
    "media:medium": "image",
    "media:mimetype": "image/tiff",
    "media:properties": {
      "colours": [
        {
          "hex": "#f6eac9",
          "name": "#f6eac9",
          "reference": "vibrant"
        },
        {
          "hex": "#45381b",
          "name": "#45381b",
          "reference": "vibrant"
        },
        {
          "hex": "#998b6a",
          "name": "#998b6a",
          "reference": "vibrant"
        },
        {
          "hex": "#d4caa8",
          "name": "#d4caa8",
          "reference": "vibrant"
        },
        {
          "hex": "#5a5235",
          "name": "#5a5235",
          "reference": "vibrant"
        }
      ],
      "sizes": {
        "b": {
          "extension": "jpg",
          "height": 768,
          "mimetype": "image/jpeg",
          "secret": "imxs8zo6Qh3cIDiIyRHKiSCKCFGAgS3X",
          "width": 991
        },
        "c": {
          "extension": "jpg",
          "height": 600,
          "mimetype": "image/jpeg",
          "secret": "imxs8zo6Qh3cIDiIyRHKiSCKCFGAgS3X",
          "width": 774
        },
        "dc": {
          "extension": "jpg",
          "height": 600,
          "mimetype": "image/jpeg",
          "secret": "imxs8zo6Qh3cIDiIyRHKiSCKCFGAgS3X",
          "width": 774
        },
        "ds": {
          "extension": "jpg",
          "height": 320,
          "mimetype": "image/jpeg",
          "secret": "imxs8zo6Qh3cIDiIyRHKiSCKCFGAgS3X",
          "width": 320
        },
        "k": {
          "extension": "jpg",
          "height": 1536,
          "mimetype": "image/jpeg",
          "secret": "imxs8zo6Qh3cIDiIyRHKiSCKCFGAgS3X",
          "width": 1982
        },
        "n": {
          "extension": "jpg",
          "height": 240,
          "mimetype": "image/jpeg",
          "secret": "imxs8zo6Qh3cIDiIyRHKiSCKCFGAgS3X",
          "width": 309
        },
        "o": {
          "extension": "jpg",
          "height": 1064,
          "mimetype": "image/jpeg",
          "secret": "Ufi1c8yLFMVGHLqFuTALuBvCNR95xdLr",
          "width": 1373
        },
        "s": {
          "extension": "jpg",
          "height": 320,
          "mimetype": "image/jpeg",
          "secret": "imxs8zo6Qh3cIDiIyRHKiSCKCFGAgS3X",
          "width": 320
        },
        "z": {
          "extension": "jpg",
          "height": 480,
          "mimetype": "image/jpeg",
          "secret": "imxs8zo6Qh3cIDiIyRHKiSCKCFGAgS3X",
          "width": 619
        }
      }
    },
    "media:uri_template": "https://static.sfomuseum.org/media/152/785/561/1/1527855611_{secret}_{label}.{extention}",
    "sfomuseum:filename": "2010.174.298.tif",
    "sfomuseum:image_index": 5,
    "sfomuseum:image_type": "studio",
    "sfomuseum:placetype": "image",
    "sfomuseum:primary_image": 1,
    "wof:depicts": [
      1511942457
    ],
    "wof:name": "photograph: San Francisco Bay Area aerial, South of Market",
    "wof:placetype": "custom",
    "wof:placetype_alt": "image"
  },
  "geometry": {"coordinates":[-122.386155,37.616358],"type":"Point"}
}
