{
  "type": "Feature",
  "properties": {
    "iso:country": "XX",
    "media:fingerprint": "54ea3886c6fd460f04b2826f2e71932b8b7d00ab",
    "media:imagehash_avg": "a:ff1f1e1f08080880",
    "media:imagehash_diff": "d:b8b878babaf9f838",
    "media:medium": "image",
    "media:mimetype": "image/tiff",
    "media:properties": {
      "colours": [
        {
          "hex": "#8e6b41",
          "name": "#8e6b41",
          "reference": "vibrant"
        }, 
        {
          "hex": "#c0ad74",
          "name": "#c0ad74",
          "reference": "vibrant"
        }, 
        {
          "hex": "#240818",
          "name": "#240818",
          "reference": "vibrant"
        }, 
        {
          "hex": "#9f6873",
          "name": "#9f6873",
          "reference": "vibrant"
        }, 
        {
          "hex": "#d3cfb7",
          "name": "#d3cfb7",
          "reference": "vibrant"
        }
      ],
      "sizes": {
        "b": {
          "extension": "jpg",
          "height": 768,
          "mimetype": "image/jpeg",
          "secret": "Lz7rqvLWgSLjIwTCYDVfEkYTyqtN5yTk",
          "width": 966
        },
        "c": {
          "extension": "jpg",
          "height": 600,
          "mimetype": "image/jpeg",
          "secret": "Lz7rqvLWgSLjIwTCYDVfEkYTyqtN5yTk",
          "width": 755
        },
        "dc": {
          "extension": "jpg",
          "height": 600,
          "mimetype": "image/jpeg",
          "secret": "Lz7rqvLWgSLjIwTCYDVfEkYTyqtN5yTk",
          "width": 755
        },
        "ds": {
          "extension": "jpg",
          "height": 320,
          "mimetype": "image/jpeg",
          "secret": "Lz7rqvLWgSLjIwTCYDVfEkYTyqtN5yTk",
          "width": 320
        },
        "k": {
          "extension": "jpg",
          "height": 1536,
          "mimetype": "image/jpeg",
          "secret": "Lz7rqvLWgSLjIwTCYDVfEkYTyqtN5yTk",
          "width": 1933
        },
        "n": {
          "extension": "jpg",
          "height": 240,
          "mimetype": "image/jpeg",
          "secret": "Lz7rqvLWgSLjIwTCYDVfEkYTyqtN5yTk",
          "width": 302
        },
        "o": {
          "extension": "jpg",
          "height": 2209,
          "mimetype": "image/jpeg",
          "secret": "skq8D4zwjyhR5r71PkXt0EralINVdHUx",
          "width": 2781
        },
        "s": {
          "extension": "jpg",
          "height": 320,
          "mimetype": "image/jpeg",
          "secret": "Lz7rqvLWgSLjIwTCYDVfEkYTyqtN5yTk",
          "width": 320
        },
        "z": {
          "extension": "jpg",
          "height": 480,
          "mimetype": "image/jpeg",
          "secret": "Lz7rqvLWgSLjIwTCYDVfEkYTyqtN5yTk",
          "width": 604
        }
      }
    },
    "media:uri_template": "https://millsfield.sfomuseum.org/media/152/782/701/5/1527827015_{secret}_{label}.{extention}",
    "sfomuseum:filename": "43898.tif",
    "sfomuseum:image_index": 5,
    "sfomuseum:placetype": "image",
    "sfomuseum:primary_image": 1,
    "wof:depicts": [
      1511948053
    ],
    "wof:name": "negative: San Francisco International Airport (SFO), exhibit for California State Fair",
    "wof:placetype": "media"
  },
  "geometry": {"coordinates":[-122.386155,37.616358],"type":"Point"}
}
