{
  "type": "Feature",
  "properties": {
    "iso:country": "XX",
    "media:fingerprint": "e8333757cda53111d966d4797340b4d6122aa4fd",
    "media:imagehash_avg": "a:fee0e0ed8d09111f",
    "media:imagehash_diff": "d:cc4c0c5959716579",
    "media:medium": "image",
    "media:mimetype": "image/tiff",
    "media:properties": {
      "colours": [
        {
          "hex": "#f1681d",
          "name": "#f1681d",
          "reference": "vibrant"
        }, 
        {
          "hex": "#f2b270",
          "name": "#f2b270",
          "reference": "vibrant"
        }, 
        {
          "hex": "#1e2d76",
          "name": "#1e2d76",
          "reference": "vibrant"
        }, 
        {
          "hex": "#6b83ac",
          "name": "#6b83ac",
          "reference": "vibrant"
        }, 
        {
          "hex": "#c7c3b3",
          "name": "#c7c3b3",
          "reference": "vibrant"
        }
      ],
      "sizes": {
        "b": {
          "extension": "jpg",
          "height": 549,
          "mimetype": "image/jpeg",
          "secret": "nUkd9lxaBWukJilM2ICUxP6kukqiqFKT",
          "width": 1024
        },
        "c": {
          "extension": "jpg",
          "height": 429,
          "mimetype": "image/jpeg",
          "secret": "nUkd9lxaBWukJilM2ICUxP6kukqiqFKT",
          "width": 800
        },
        "dc": {
          "extension": "jpg",
          "height": 429,
          "mimetype": "image/jpeg",
          "secret": "nUkd9lxaBWukJilM2ICUxP6kukqiqFKT",
          "width": 800
        },
        "ds": {
          "extension": "jpg",
          "height": 320,
          "mimetype": "image/jpeg",
          "secret": "nUkd9lxaBWukJilM2ICUxP6kukqiqFKT",
          "width": 320
        },
        "k": {
          "extension": "jpg",
          "height": 1099,
          "mimetype": "image/jpeg",
          "secret": "nUkd9lxaBWukJilM2ICUxP6kukqiqFKT",
          "width": 2048
        },
        "n": {
          "extension": "jpg",
          "height": 171,
          "mimetype": "image/jpeg",
          "secret": "nUkd9lxaBWukJilM2ICUxP6kukqiqFKT",
          "width": 320
        },
        "o": {
          "extension": "jpg",
          "height": 1254,
          "mimetype": "image/jpeg",
          "secret": "g5drwVEs0OGpvclgcqw8bSWrzKm3Mpzf",
          "width": 2335
        },
        "s": {
          "extension": "jpg",
          "height": 320,
          "mimetype": "image/jpeg",
          "secret": "nUkd9lxaBWukJilM2ICUxP6kukqiqFKT",
          "width": 320
        },
        "z": {
          "extension": "jpg",
          "height": 343,
          "mimetype": "image/jpeg",
          "secret": "nUkd9lxaBWukJilM2ICUxP6kukqiqFKT",
          "width": 640
        }
      }
    },
    "media:uri_template": "https://millsfield.sfomuseum.org/media/152/782/916/1/1527829161_{secret}_{label}.{extention}",
    "sfomuseum:filename": "47544.tif",
    "sfomuseum:image_index": 5,
    "sfomuseum:placetype": "image",
    "sfomuseum:primary_image": 1,
    "wof:depicts": [
      1511907413
    ],
    "wof:name": "airmail flight cover: Pan American Airways, Honolulu - Wake Island - New York route",
    "wof:placetype": "media"
  },
  "geometry": {"coordinates":[-122.386155,37.616358],"type":"Point"}
}
