{
  "type": "Feature",
  "properties": {
    "iso:country": "XX",
    "media:fingerprint": "ede473a5d91e57f06c28d07c917fc0145857b6f5",
    "media:imagehash_avg": "a:3b81ffe3a3817f3f",
    "media:imagehash_diff": "d:6737554f47435175",
    "media:medium": "image",
    "media:mimetype": "image/tiff",
    "media:properties": {
      "colours": [
        {
          "hex": "#f5ead3",
          "name": "#f5ead3",
          "reference": "vibrant"
        },
        {
          "hex": "#868179",
          "name": "#868179",
          "reference": "vibrant"
        },
        {
          "hex": "#c8c4b1",
          "name": "#c8c4b1",
          "reference": "vibrant"
        },
        {
          "hex": "#48433a",
          "name": "#48433a",
          "reference": "vibrant"
        }
      ],
      "sizes": {
        "b": {
          "extension": "jpg",
          "height": 767,
          "mimetype": "image/jpeg",
          "secret": "LIwpftIRvKRDhCbnDNJWmD5AY0nvSijX",
          "width": 518
        },
        "c": {
          "extension": "jpg",
          "height": 600,
          "mimetype": "image/jpeg",
          "secret": "LIwpftIRvKRDhCbnDNJWmD5AY0nvSijX",
          "width": 404
        },
        "dc": {
          "extension": "jpg",
          "height": 600,
          "mimetype": "image/jpeg",
          "secret": "LIwpftIRvKRDhCbnDNJWmD5AY0nvSijX",
          "width": 404
        },
        "ds": {
          "extension": "jpg",
          "height": 320,
          "mimetype": "image/jpeg",
          "secret": "LIwpftIRvKRDhCbnDNJWmD5AY0nvSijX",
          "width": 320
        },
        "k": {
          "extension": "jpg",
          "height": 1535,
          "mimetype": "image/jpeg",
          "secret": "LIwpftIRvKRDhCbnDNJWmD5AY0nvSijX",
          "width": 1036
        },
        "n": {
          "extension": "jpg",
          "height": 240,
          "mimetype": "image/jpeg",
          "secret": "LIwpftIRvKRDhCbnDNJWmD5AY0nvSijX",
          "width": 161
        },
        "o": {
          "extension": "jpg",
          "height": 2693,
          "mimetype": "image/jpeg",
          "secret": "onSF21qJN4s7aMA2SoDWX3DdlIx7wkbj",
          "width": 1817
        },
        "s": {
          "extension": "jpg",
          "height": 320,
          "mimetype": "image/jpeg",
          "secret": "LIwpftIRvKRDhCbnDNJWmD5AY0nvSijX",
          "width": 320
        },
        "z": {
          "extension": "jpg",
          "height": 480,
          "mimetype": "image/jpeg",
          "secret": "LIwpftIRvKRDhCbnDNJWmD5AY0nvSijX",
          "width": 323
        }
      }
    },
    "media:uri_template": "https://static.sfomuseum.org/media/152/783/031/7/1527830317_{secret}_{label}.{extention}",
    "sfomuseum:filename": "53610.tif",
    "sfomuseum:image_index": 5,
    "sfomuseum:image_type": "studio",
    "sfomuseum:placetype": "image",
    "sfomuseum:primary_image": 1,
    "wof:depicts": [
      1511938159,
      1159283597
    ],
    "wof:name": "airsickness bag: Air Canada",
    "wof:placetype": "custom",
    "wof:placetype_alt": "image"
  },
  "geometry": {"coordinates":[-122.386155,37.616358],"type":"Point"}
}
