{
  "type": "Feature",
  "properties": {
    "iso:country": "XX",
    "media:fingerprint": "36cb01059f4118288e6fc8a39beb21e96b75ed82",
    "media:imagehash_avg": "a:ffffff00000000f8",
    "media:imagehash_diff": "d:80e0adc5656d6341",
    "media:medium": "image",
    "media:mimetype": "image/tiff",
    "media:properties": {
      "colours": [
        {
          "hex": "#808080",
          "name": "#808080",
          "reference": "vibrant"
        },
        {
          "hex": "#c0c0c0",
          "name": "#c0c0c0",
          "reference": "vibrant"
        },
        {
          "hex": "#3a3a3a",
          "name": "#3a3a3a",
          "reference": "vibrant"
        }
      ],
      "sizes": {
        "b": {
          "extension": "jpg",
          "height": 768,
          "mimetype": "image/jpeg",
          "secret": "9RChHrlbMtQpCVBU3C38KQfcF9WJEwlg",
          "width": 610
        },
        "c": {
          "extension": "jpg",
          "height": 600,
          "mimetype": "image/jpeg",
          "secret": "9RChHrlbMtQpCVBU3C38KQfcF9WJEwlg",
          "width": 476
        },
        "dc": {
          "extension": "jpg",
          "height": 600,
          "mimetype": "image/jpeg",
          "secret": "9RChHrlbMtQpCVBU3C38KQfcF9WJEwlg",
          "width": 476
        },
        "ds": {
          "extension": "jpg",
          "height": 320,
          "mimetype": "image/jpeg",
          "secret": "9RChHrlbMtQpCVBU3C38KQfcF9WJEwlg",
          "width": 320
        },
        "k": {
          "extension": "jpg",
          "height": 1536,
          "mimetype": "image/jpeg",
          "secret": "9RChHrlbMtQpCVBU3C38KQfcF9WJEwlg",
          "width": 1220
        },
        "n": {
          "extension": "jpg",
          "height": 240,
          "mimetype": "image/jpeg",
          "secret": "9RChHrlbMtQpCVBU3C38KQfcF9WJEwlg",
          "width": 190
        },
        "o": {
          "extension": "jpg",
          "height": 2097,
          "mimetype": "image/jpeg",
          "secret": "HRuYfN50fSZqBftgreSZpT92dQXYxDQ1",
          "width": 1666
        },
        "s": {
          "extension": "jpg",
          "height": 320,
          "mimetype": "image/jpeg",
          "secret": "9RChHrlbMtQpCVBU3C38KQfcF9WJEwlg",
          "width": 320
        },
        "z": {
          "extension": "jpg",
          "height": 480,
          "mimetype": "image/jpeg",
          "secret": "9RChHrlbMtQpCVBU3C38KQfcF9WJEwlg",
          "width": 381
        }
      }
    },
    "media:uri_template": "https://static.sfomuseum.org/media/152/783/134/1/1527831341_{secret}_{label}.{extention}",
    "sfomuseum:filename": "58347.tif",
    "sfomuseum:image_index": 5,
    "sfomuseum:image_type": "studio",
    "sfomuseum:placetype": "image",
    "sfomuseum:primary_image": 1,
    "wof:depicts": [
      1511955611
    ],
    "wof:name": "glass negative: Panama-Pacific International Exposition, Art Smith",
    "wof:placetype": "custom",
    "wof:placetype_alt": "image"
  },
  "geometry": {"coordinates":[-122.386155,37.616358],"type":"Point"}
}
