{
  "type": "Feature",
  "properties": {
    "iso:country":"AU",
    "media:medium":"image",
    "sfomuseum:filename":"31615.tif",
    "sfomuseum:image_index":0,
    "sfomuseum:placetype":"image",
    "sfomuseum:primary_image":1,
    "wof:depicts":[
        1159285043,
        1159289653,
        1729564087
    ],
    "wof:name":"airmail flight cover order form: Qantas Airways, Boeing 707",
    "wof:placetype":"media"
},
  "geometry": {"coordinates":[-122.386155,37.616357],"type":"Point"}
}