{
  "type": "Feature",
  "properties": {
    "iso:country": "XX",
    "media:fingerprint": "6f98ac90d480a78a26aeb23639db8a644172ce80",
    "media:imagehash_avg": "a:ffffffc100000000",
    "media:imagehash_diff": "d:f0e62f37c3faf8fc",
    "media:medium": "image",
    "media:mimetype": "image/tiff",
    "media:properties": {
      "colours": [
        {
          "hex": "#757575",
          "name": "#757575",
          "reference": "vibrant"
        }, 
        {
          "hex": "#b8b8b8",
          "name": "#b8b8b8",
          "reference": "vibrant"
        }, 
        {
          "hex": "#464646",
          "name": "#464646",
          "reference": "vibrant"
        }
      ],
      "sizes": {
        "b": {
          "extension": "jpg",
          "height": 767,
          "mimetype": "image/jpeg",
          "secret": "YpGxQZKMPXY6HqWdGUmfU4WYpRUn1wjF",
          "width": 776
        },
        "c": {
          "extension": "jpg",
          "height": 600,
          "mimetype": "image/jpeg",
          "secret": "YpGxQZKMPXY6HqWdGUmfU4WYpRUn1wjF",
          "width": 606
        },
        "dc": {
          "extension": "jpg",
          "height": 600,
          "mimetype": "image/jpeg",
          "secret": "YpGxQZKMPXY6HqWdGUmfU4WYpRUn1wjF",
          "width": 606
        },
        "ds": {
          "extension": "jpg",
          "height": 320,
          "mimetype": "image/jpeg",
          "secret": "YpGxQZKMPXY6HqWdGUmfU4WYpRUn1wjF",
          "width": 320
        },
        "k": {
          "extension": "jpg",
          "height": 1535,
          "mimetype": "image/jpeg",
          "secret": "YpGxQZKMPXY6HqWdGUmfU4WYpRUn1wjF",
          "width": 1552
        },
        "n": {
          "extension": "jpg",
          "height": 240,
          "mimetype": "image/jpeg",
          "secret": "YpGxQZKMPXY6HqWdGUmfU4WYpRUn1wjF",
          "width": 242
        },
        "o": {
          "extension": "jpg",
          "height": 2509,
          "mimetype": "image/jpeg",
          "secret": "BGqXgJ8grF8MRWJiEYfeWrO2SZ39JFHN",
          "width": 2536
        },
        "s": {
          "extension": "jpg",
          "height": 320,
          "mimetype": "image/jpeg",
          "secret": "YpGxQZKMPXY6HqWdGUmfU4WYpRUn1wjF",
          "width": 320
        },
        "z": {
          "extension": "jpg",
          "height": 480,
          "mimetype": "image/jpeg",
          "secret": "YpGxQZKMPXY6HqWdGUmfU4WYpRUn1wjF",
          "width": 485
        }
      }
    },
    "media:uri_template": "https://millsfield.sfomuseum.org/media/152/782/636/1/1527826361_{secret}_{label}.{extention}",
    "sfomuseum:filename": "43606.tif",
    "sfomuseum:image_index": 5,
    "sfomuseum:placetype": "image",
    "sfomuseum:primary_image": 1,
    "wof:depicts": [
      1511947401
    ],
    "wof:name": "negative: San Francisco International Airport (SFO), construction of TWA (Trans World Airlines) apron, damaged equipment",
    "wof:placetype": "media"
  },
  "geometry": {"coordinates":[-122.386155,37.616358],"type":"Point"}
}
