{
  "type": "Feature",
  "properties": {
    "iso:country": "XX",
    "media:fingerprint": "2ce363563d32655693149af527a98545d0e93e77",
    "media:imagehash_avg": "a:7f7f017763476741",
    "media:imagehash_diff": "d:a5858fc7cf8f8f97",
    "media:medium": "image",
    "media:mimetype": "image/tiff",
    "media:properties": {
      "colours": [
        {
          "hex": "#3160b1",
          "name": "#3160b1",
          "reference": "vibrant"
        }, 
        {
          "hex": "#f1e9d0",
          "name": "#f1e9d0",
          "reference": "vibrant"
        }, 
        {
          "hex": "#264ea7",
          "name": "#264ea7",
          "reference": "vibrant"
        }, 
        {
          "hex": "#6c7a86",
          "name": "#6c7a86",
          "reference": "vibrant"
        }, 
        {
          "hex": "#c7c3af",
          "name": "#c7c3af",
          "reference": "vibrant"
        }
      ],
      "sizes": {
        "b": {
          "extension": "jpg",
          "height": 768,
          "mimetype": "image/jpeg",
          "secret": "Cq9MC8yFR2kuqe3wjb7ZK0thGYtHa7SL",
          "width": 414
        },
        "c": {
          "extension": "jpg",
          "height": 600,
          "mimetype": "image/jpeg",
          "secret": "Cq9MC8yFR2kuqe3wjb7ZK0thGYtHa7SL",
          "width": 323
        },
        "dc": {
          "extension": "jpg",
          "height": 600,
          "mimetype": "image/jpeg",
          "secret": "Cq9MC8yFR2kuqe3wjb7ZK0thGYtHa7SL",
          "width": 323
        },
        "ds": {
          "extension": "jpg",
          "height": 320,
          "mimetype": "image/jpeg",
          "secret": "Cq9MC8yFR2kuqe3wjb7ZK0thGYtHa7SL",
          "width": 320
        },
        "k": {
          "extension": "jpg",
          "height": 1536,
          "mimetype": "image/jpeg",
          "secret": "Cq9MC8yFR2kuqe3wjb7ZK0thGYtHa7SL",
          "width": 828
        },
        "n": {
          "extension": "jpg",
          "height": 240,
          "mimetype": "image/jpeg",
          "secret": "Cq9MC8yFR2kuqe3wjb7ZK0thGYtHa7SL",
          "width": 129
        },
        "o": {
          "extension": "jpg",
          "height": 2891,
          "mimetype": "image/jpeg",
          "secret": "PwxpDmwmrb2jPoPOaCuCbaWPwLE8x271",
          "width": 1559
        },
        "s": {
          "extension": "jpg",
          "height": 320,
          "mimetype": "image/jpeg",
          "secret": "Cq9MC8yFR2kuqe3wjb7ZK0thGYtHa7SL",
          "width": 320
        },
        "z": {
          "extension": "jpg",
          "height": 480,
          "mimetype": "image/jpeg",
          "secret": "Cq9MC8yFR2kuqe3wjb7ZK0thGYtHa7SL",
          "width": 258
        }
      }
    },
    "media:uri_template": "https://millsfield.sfomuseum.org/media/152/782/441/9/1527824419_{secret}_{label}.{extention}",
    "sfomuseum:filename": "42559.tif",
    "sfomuseum:image_index": 5,
    "sfomuseum:placetype": "image",
    "sfomuseum:primary_image": 0,
    "wof:depicts": [
      1511908559
    ],
    "wof:name": "airsickness bag: Cyprus Airways",
    "wof:placetype": "media"
  },
  "geometry": {"coordinates":[-122.386155,37.616358],"type":"Point"}
}
