{
  "type": "Feature",
  "properties": {
    "date:cessation_lower": "1999-01-01",
    "date:cessation_upper": "1999-12-31",
    "date:inception_lower": "1999-01-01",
    "date:inception_upper": "1999-12-31",
    "iso:country": "XX",
    "millsfield:tailnumbers": [
      "N328AW"
    ],
    "sfomuseum:filename": "125611.tif",
    "sfomuseum:image_index": 1,
    "sfomuseum:image_type": "studio",
    "sfomuseum:placetype": "image",
    "sfomuseum:primary_image": 1,
    "wof:depicts": [
      1159285439,
      102527529,
      1159289851,
      1511926691
    ],
    "wof:name": "slide: America West Airlines, Boeing 737-300, San Jose International Airport (SJC)",
    "wof:placetype": "custom"
  },
  "geometry": {"coordinates":[-122.386155,37.616357],"type":"Point"}
}
