{
  "type": "Feature",
  "properties": {
    "iso:country": "XX",
    "media:fingerprint": "5cb9b9dac5b493b75b0ac1bf2e7eb84a3406fcaf",
    "media:imagehash_avg": "a:ffffff3f1d3c0000",
    "media:imagehash_diff": "d:e0f0f3fbf9e99bc3",
    "media:medium": "image",
    "media:mimetype": "image/tiff",
    "media:properties": {
      "colours": [
        {
          "hex": "#808080",
          "name": "#808080",
          "reference": "vibrant"
        }, 
        {
          "hex": "#b8b8b8",
          "name": "#b8b8b8",
          "reference": "vibrant"
        }, 
        {
          "hex": "#404040",
          "name": "#404040",
          "reference": "vibrant"
        }
      ],
      "sizes": {
        "b": {
          "extension": "jpg",
          "height": 767,
          "mimetype": "image/jpeg",
          "secret": "dkpiNzWKGuzD8phDsTdlW07z8sDwr1C5",
          "width": 973
        },
        "c": {
          "extension": "jpg",
          "height": 600,
          "mimetype": "image/jpeg",
          "secret": "dkpiNzWKGuzD8phDsTdlW07z8sDwr1C5",
          "width": 760
        },
        "dc": {
          "extension": "jpg",
          "height": 600,
          "mimetype": "image/jpeg",
          "secret": "dkpiNzWKGuzD8phDsTdlW07z8sDwr1C5",
          "width": 760
        },
        "ds": {
          "extension": "jpg",
          "height": 320,
          "mimetype": "image/jpeg",
          "secret": "dkpiNzWKGuzD8phDsTdlW07z8sDwr1C5",
          "width": 320
        },
        "k": {
          "extension": "jpg",
          "height": 1535,
          "mimetype": "image/jpeg",
          "secret": "dkpiNzWKGuzD8phDsTdlW07z8sDwr1C5",
          "width": 1947
        },
        "n": {
          "extension": "jpg",
          "height": 240,
          "mimetype": "image/jpeg",
          "secret": "dkpiNzWKGuzD8phDsTdlW07z8sDwr1C5",
          "width": 304
        },
        "o": {
          "extension": "jpg",
          "height": 2140,
          "mimetype": "image/jpeg",
          "secret": "PMPnLaB0NqXfBYUhpS716WSnbOtfxbXo",
          "width": 2713
        },
        "s": {
          "extension": "jpg",
          "height": 320,
          "mimetype": "image/jpeg",
          "secret": "dkpiNzWKGuzD8phDsTdlW07z8sDwr1C5",
          "width": 320
        },
        "z": {
          "extension": "jpg",
          "height": 480,
          "mimetype": "image/jpeg",
          "secret": "dkpiNzWKGuzD8phDsTdlW07z8sDwr1C5",
          "width": 608
        }
      }
    },
    "media:uri_template": "https://millsfield.sfomuseum.org/media/152/782/407/3/1527824073_{secret}_{label}.{extention}",
    "sfomuseum:filename": "42253.tif",
    "sfomuseum:image_index": 5,
    "sfomuseum:placetype": "image",
    "sfomuseum:primary_image": 1,
    "wof:depicts": [
      1511945391
    ],
    "wof:name": "negative: San Francisco International Airport (SFO), firefighting  equipment",
    "wof:placetype": "media"
  },
  "geometry": {"coordinates":[-122.386155,37.616358],"type":"Point"}
}
