{
  "type": "Feature",
  "properties": {
    "iso:country": "XX",
    "media:fingerprint": "b149e72da5a0da6f3f516e5b0c92d916819b7c51",
    "media:imagehash_avg": "a:3e7e7f3f3e0e3e00",
    "media:imagehash_diff": "d:f0f0fef6f0f8e8f0",
    "media:medium": "image",
    "media:mimetype": "image/tiff",
    "media:properties": {
      "colours": [
        {
          "hex": "#808080",
          "name": "#808080",
          "reference": "vibrant"
        }, 
        {
          "hex": "#b8b8b8",
          "name": "#b8b8b8",
          "reference": "vibrant"
        }, 
        {
          "hex": "#464646",
          "name": "#464646",
          "reference": "vibrant"
        }
      ],
      "sizes": {
        "b": {
          "extension": "jpg",
          "height": 768,
          "mimetype": "image/jpeg",
          "secret": "feIEponyS5C4mXql9gyJT2asjV1yCX6I",
          "width": 977
        },
        "c": {
          "extension": "jpg",
          "height": 600,
          "mimetype": "image/jpeg",
          "secret": "feIEponyS5C4mXql9gyJT2asjV1yCX6I",
          "width": 764
        },
        "dc": {
          "extension": "jpg",
          "height": 600,
          "mimetype": "image/jpeg",
          "secret": "feIEponyS5C4mXql9gyJT2asjV1yCX6I",
          "width": 764
        },
        "ds": {
          "extension": "jpg",
          "height": 320,
          "mimetype": "image/jpeg",
          "secret": "feIEponyS5C4mXql9gyJT2asjV1yCX6I",
          "width": 320
        },
        "k": {
          "extension": "jpg",
          "height": 1536,
          "mimetype": "image/jpeg",
          "secret": "feIEponyS5C4mXql9gyJT2asjV1yCX6I",
          "width": 1955
        },
        "n": {
          "extension": "jpg",
          "height": 240,
          "mimetype": "image/jpeg",
          "secret": "feIEponyS5C4mXql9gyJT2asjV1yCX6I",
          "width": 305
        },
        "o": {
          "extension": "jpg",
          "height": 2195,
          "mimetype": "image/jpeg",
          "secret": "RC0aZClmBs2glEHjSy4LilAIWoliFTpB",
          "width": 2795
        },
        "s": {
          "extension": "jpg",
          "height": 320,
          "mimetype": "image/jpeg",
          "secret": "feIEponyS5C4mXql9gyJT2asjV1yCX6I",
          "width": 320
        },
        "z": {
          "extension": "jpg",
          "height": 480,
          "mimetype": "image/jpeg",
          "secret": "feIEponyS5C4mXql9gyJT2asjV1yCX6I",
          "width": 611
        }
      }
    },
    "media:uri_template": "https://millsfield.sfomuseum.org/media/152/782/583/9/1527825839_{secret}_{label}.{extention}",
    "sfomuseum:filename": "43360.tif",
    "sfomuseum:image_index": 5,
    "sfomuseum:placetype": "image",
    "sfomuseum:primary_image": 1,
    "wof:depicts": [
      1511946875
    ],
    "wof:name": "negative: San Francisco International Airport (SFO), architectural diagram",
    "wof:placetype": "media"
  },
  "geometry": {"coordinates":[-122.386155,37.616358],"type":"Point"}
}
