{
  "type": "Feature",
  "properties": {
    "iso:country": "XX",
    "media:fingerprint": "6afdd653a3b6f39b2701eed65cf8863602f3c42f",
    "media:imagehash_avg": "a:2ce070e8cec890b8",
    "media:imagehash_diff": "d:58cbc1c118182263",
    "media:medium": "image",
    "media:mimetype": "image/tiff",
    "media:properties": {
      "colours": [
        {
          "hex": "#d3d9a5",
          "name": "#d3d9a5",
          "reference": "vibrant"
        }, 
        {
          "hex": "#79906a",
          "name": "#79906a",
          "reference": "vibrant"
        }, 
        {
          "hex": "#add1ba",
          "name": "#add1ba",
          "reference": "vibrant"
        }, 
        {
          "hex": "#31482e",
          "name": "#31482e",
          "reference": "vibrant"
        }
      ],
      "sizes": {
        "b": {
          "extension": "jpg",
          "height": 675,
          "mimetype": "image/jpeg",
          "secret": "GWnfd3VRluspn7C58SVYDF2RyMera9bt",
          "width": 1023
        },
        "c": {
          "extension": "jpg",
          "height": 527,
          "mimetype": "image/jpeg",
          "secret": "GWnfd3VRluspn7C58SVYDF2RyMera9bt",
          "width": 800
        },
        "dc": {
          "extension": "jpg",
          "height": 527,
          "mimetype": "image/jpeg",
          "secret": "GWnfd3VRluspn7C58SVYDF2RyMera9bt",
          "width": 800
        },
        "ds": {
          "extension": "jpg",
          "height": 320,
          "mimetype": "image/jpeg",
          "secret": "GWnfd3VRluspn7C58SVYDF2RyMera9bt",
          "width": 320
        },
        "k": {
          "extension": "jpg",
          "height": 1351,
          "mimetype": "image/jpeg",
          "secret": "GWnfd3VRluspn7C58SVYDF2RyMera9bt",
          "width": 2047
        },
        "n": {
          "extension": "jpg",
          "height": 211,
          "mimetype": "image/jpeg",
          "secret": "GWnfd3VRluspn7C58SVYDF2RyMera9bt",
          "width": 320
        },
        "o": {
          "extension": "jpg",
          "height": 1094,
          "mimetype": "image/jpeg",
          "secret": "utRwKgK6I9kOSadTnInMG49F7KcBZvbI",
          "width": 1658
        },
        "s": {
          "extension": "jpg",
          "height": 320,
          "mimetype": "image/jpeg",
          "secret": "GWnfd3VRluspn7C58SVYDF2RyMera9bt",
          "width": 320
        },
        "z": {
          "extension": "jpg",
          "height": 422,
          "mimetype": "image/jpeg",
          "secret": "GWnfd3VRluspn7C58SVYDF2RyMera9bt",
          "width": 640
        }
      }
    },
    "media:uri_template": "https://millsfield.sfomuseum.org/media/152/782/857/5/1527828575_{secret}_{label}.{extention}",
    "sfomuseum:filename": "44661.tif",
    "sfomuseum:image_index": 5,
    "sfomuseum:placetype": "image",
    "sfomuseum:primary_image": 1,
    "wof:depicts": [
      1511949611
    ],
    "wof:name": "negative: San Francisco International Airport (SFO), Annual report press conference",
    "wof:placetype": "media"
  },
  "geometry": {"coordinates":[-122.386155,37.616358],"type":"Point"}
}
