{
  "type": "Feature",
  "properties": {
    "iso:country": "XX",
    "media:fingerprint": "ab48bbfe86724f6d39b33f8804589f8132977616",
    "media:imagehash_avg": "a:ffff7f0300000000",
    "media:imagehash_diff": "d:e0e0f8ffcf9f5420",
    "media:medium": "image",
    "media:mimetype": "image/tiff",
    "media:properties": {
      "colours": [
        {
          "hex": "#808080",
          "name": "#808080",
          "reference": "vibrant"
        }, 
        {
          "hex": "#c0c0c0",
          "name": "#c0c0c0",
          "reference": "vibrant"
        }, 
        {
          "hex": "#464646",
          "name": "#464646",
          "reference": "vibrant"
        }
      ],
      "sizes": {
        "b": {
          "extension": "jpg",
          "height": 768,
          "mimetype": "image/jpeg",
          "secret": "5U4bO7sFxvcyxGjV4hr3W6XikK6rP6P8",
          "width": 975
        },
        "c": {
          "extension": "jpg",
          "height": 600,
          "mimetype": "image/jpeg",
          "secret": "5U4bO7sFxvcyxGjV4hr3W6XikK6rP6P8",
          "width": 762
        },
        "dc": {
          "extension": "jpg",
          "height": 600,
          "mimetype": "image/jpeg",
          "secret": "5U4bO7sFxvcyxGjV4hr3W6XikK6rP6P8",
          "width": 762
        },
        "ds": {
          "extension": "jpg",
          "height": 320,
          "mimetype": "image/jpeg",
          "secret": "5U4bO7sFxvcyxGjV4hr3W6XikK6rP6P8",
          "width": 320
        },
        "k": {
          "extension": "jpg",
          "height": 1536,
          "mimetype": "image/jpeg",
          "secret": "5U4bO7sFxvcyxGjV4hr3W6XikK6rP6P8",
          "width": 1951
        },
        "n": {
          "extension": "jpg",
          "height": 240,
          "mimetype": "image/jpeg",
          "secret": "5U4bO7sFxvcyxGjV4hr3W6XikK6rP6P8",
          "width": 304
        },
        "o": {
          "extension": "jpg",
          "height": 2168,
          "mimetype": "image/jpeg",
          "secret": "wdGFKNudYCdEF2tNGNRbkb3alNFiKwbQ",
          "width": 2754
        },
        "s": {
          "extension": "jpg",
          "height": 320,
          "mimetype": "image/jpeg",
          "secret": "5U4bO7sFxvcyxGjV4hr3W6XikK6rP6P8",
          "width": 320
        },
        "z": {
          "extension": "jpg",
          "height": 480,
          "mimetype": "image/jpeg",
          "secret": "5U4bO7sFxvcyxGjV4hr3W6XikK6rP6P8",
          "width": 609
        }
      }
    },
    "media:uri_template": "https://millsfield.sfomuseum.org/media/152/782/533/3/1527825333_{secret}_{label}.{extention}",
    "sfomuseum:filename": "43096.tif",
    "sfomuseum:image_index": 5,
    "sfomuseum:placetype": "image",
    "sfomuseum:primary_image": 1,
    "wof:depicts": [
      1511946349
    ],
    "wof:name": "negative: SFO Helicopter Airlines, downtown San Francisco heliport site",
    "wof:placetype": "media"
  },
  "geometry": {"coordinates":[-122.386155,37.616358],"type":"Point"}
}
