{
  "type": "Feature",
  "properties": {
    "iso:country": "XX",
    "media:fingerprint": "4a460d267833a98f9bbcb17438f4af6204740663",
    "media:imagehash_avg": "a:ffff7f303c3c0000",
    "media:imagehash_diff": "d:c0f0f864e0fce4f8",
    "media:medium": "image",
    "media:mimetype": "image/tiff",
    "media:properties": {
      "colours": [
        {
          "hex": "#808080",
          "name": "#808080",
          "reference": "vibrant"
        }, 
        {
          "hex": "#c0c0c0",
          "name": "#c0c0c0",
          "reference": "vibrant"
        }, 
        {
          "hex": "#404040",
          "name": "#404040",
          "reference": "vibrant"
        }
      ],
      "sizes": {
        "b": {
          "extension": "jpg",
          "height": 768,
          "mimetype": "image/jpeg",
          "secret": "ifpgJDkzvgakhOAJU7UTRlYxqf85rS6O",
          "width": 972
        },
        "c": {
          "extension": "jpg",
          "height": 600,
          "mimetype": "image/jpeg",
          "secret": "ifpgJDkzvgakhOAJU7UTRlYxqf85rS6O",
          "width": 759
        },
        "dc": {
          "extension": "jpg",
          "height": 600,
          "mimetype": "image/jpeg",
          "secret": "ifpgJDkzvgakhOAJU7UTRlYxqf85rS6O",
          "width": 759
        },
        "ds": {
          "extension": "jpg",
          "height": 320,
          "mimetype": "image/jpeg",
          "secret": "ifpgJDkzvgakhOAJU7UTRlYxqf85rS6O",
          "width": 320
        },
        "k": {
          "extension": "jpg",
          "height": 1536,
          "mimetype": "image/jpeg",
          "secret": "ifpgJDkzvgakhOAJU7UTRlYxqf85rS6O",
          "width": 1944
        },
        "n": {
          "extension": "jpg",
          "height": 240,
          "mimetype": "image/jpeg",
          "secret": "ifpgJDkzvgakhOAJU7UTRlYxqf85rS6O",
          "width": 303
        },
        "o": {
          "extension": "jpg",
          "height": 2154,
          "mimetype": "image/jpeg",
          "secret": "9nVp5ebzxeXlvABW4T5k5nNELpf8DNXM",
          "width": 2727
        },
        "s": {
          "extension": "jpg",
          "height": 320,
          "mimetype": "image/jpeg",
          "secret": "ifpgJDkzvgakhOAJU7UTRlYxqf85rS6O",
          "width": 320
        },
        "z": {
          "extension": "jpg",
          "height": 480,
          "mimetype": "image/jpeg",
          "secret": "ifpgJDkzvgakhOAJU7UTRlYxqf85rS6O",
          "width": 607
        }
      }
    },
    "media:uri_template": "https://millsfield.sfomuseum.org/media/152/782/392/7/1527823927_{secret}_{label}.{extention}",
    "sfomuseum:filename": "41877.tif",
    "sfomuseum:image_index": 5,
    "sfomuseum:placetype": "image",
    "sfomuseum:primary_image": 1,
    "wof:depicts": [
      1511945249
    ],
    "wof:name": "negative: San Francisco International Airport (SFO), aerial",
    "wof:placetype": "media"
  },
  "geometry": {"coordinates":[-122.386155,37.616358],"type":"Point"}
}
