{
  "type": "Feature",
  "properties": {
    "iso:country": "XX",
    "media:fingerprint": "8205141bfa24f17c8ea673b0e35b90f677e65592",
    "media:imagehash_avg": "a:ffbd81c3c3c3ffff",
    "media:imagehash_diff": "d:f93b3b8f8f8fccf0",
    "media:medium": "image",
    "media:mimetype": "image/tiff",
    "media:properties": {
      "colours": [
        {
          "hex": "#872216",
          "name": "#872216",
          "reference": "vibrant"
        }, 
        {
          "hex": "#8d090b",
          "name": "#8d090b",
          "reference": "vibrant"
        }, 
        {
          "hex": "#b38e6e",
          "name": "#b38e6e",
          "reference": "vibrant"
        }, 
        {
          "hex": "#b4b8b8",
          "name": "#b4b8b8",
          "reference": "vibrant"
        }, 
        {
          "hex": "#3c4445",
          "name": "#3c4445",
          "reference": "vibrant"
        }
      ],
      "sizes": {
        "b": {
          "extension": "jpg",
          "height": 685,
          "mimetype": "image/jpeg",
          "secret": "ryWOzjuPx17tNzI6ZYLyvFl68eDmLqXj",
          "width": 1024
        },
        "c": {
          "extension": "jpg",
          "height": 535,
          "mimetype": "image/jpeg",
          "secret": "ryWOzjuPx17tNzI6ZYLyvFl68eDmLqXj",
          "width": 800
        },
        "dc": {
          "extension": "jpg",
          "height": 535,
          "mimetype": "image/jpeg",
          "secret": "ryWOzjuPx17tNzI6ZYLyvFl68eDmLqXj",
          "width": 800
        },
        "ds": {
          "extension": "jpg",
          "height": 320,
          "mimetype": "image/jpeg",
          "secret": "ryWOzjuPx17tNzI6ZYLyvFl68eDmLqXj",
          "width": 320
        },
        "k": {
          "extension": "jpg",
          "height": 1371,
          "mimetype": "image/jpeg",
          "secret": "ryWOzjuPx17tNzI6ZYLyvFl68eDmLqXj",
          "width": 2048
        },
        "n": {
          "extension": "jpg",
          "height": 214,
          "mimetype": "image/jpeg",
          "secret": "ryWOzjuPx17tNzI6ZYLyvFl68eDmLqXj",
          "width": 320
        },
        "o": {
          "extension": "jpg",
          "height": 2400,
          "mimetype": "image/jpeg",
          "secret": "cXpgUphodH1gBtiBqJDMY95Y4BPfhudj",
          "width": 3585
        },
        "s": {
          "extension": "jpg",
          "height": 320,
          "mimetype": "image/jpeg",
          "secret": "ryWOzjuPx17tNzI6ZYLyvFl68eDmLqXj",
          "width": 320
        },
        "z": {
          "extension": "jpg",
          "height": 428,
          "mimetype": "image/jpeg",
          "secret": "ryWOzjuPx17tNzI6ZYLyvFl68eDmLqXj",
          "width": 640
        }
      }
    },
    "media:uri_template": "https://millsfield.sfomuseum.org/media/152/782/884/3/1527828843_{secret}_{label}.{extention}",
    "sfomuseum:filename": "46668.tif",
    "sfomuseum:image_index": 5,
    "sfomuseum:placetype": "image",
    "sfomuseum:primary_image": 0,
    "wof:depicts": [
      1511942059
    ],
    "wof:name": "gate agent hat badge: TWA (Trans World Airlines)",
    "wof:placetype": "media"
  },
  "geometry": {"coordinates":[-122.386155,37.616358],"type":"Point"}
}
