{
  "type": "Feature",
  "properties": {
    "iso:country": "XX",
    "media:fingerprint": "3f35ff8d0ef16d5e4ff8ee48ee654a7f26ecc482",
    "media:imagehash_avg": "a:00ffffffffe76600",
    "media:imagehash_diff": "d:17ccf8d68ecccc1d",
    "media:medium": "image",
    "media:mimetype": "image/tiff",
    "media:properties": {
      "colours": [
        {
          "hex": "#a41d0e",
          "name": "#a41d0e",
          "reference": "vibrant"
        }, 
        {
          "hex": "#971306",
          "name": "#971306",
          "reference": "vibrant"
        }, 
        {
          "hex": "#ad8259",
          "name": "#ad8259",
          "reference": "vibrant"
        }, 
        {
          "hex": "#cdc3a0",
          "name": "#cdc3a0",
          "reference": "vibrant"
        }, 
        {
          "hex": "#383461",
          "name": "#383461",
          "reference": "vibrant"
        }
      ],
      "sizes": {
        "b": {
          "extension": "jpg",
          "height": 468,
          "mimetype": "image/jpeg",
          "secret": "bf1LrqjxXhRFijiuiKul1jfNJSMs6CXs",
          "width": 1024
        },
        "c": {
          "extension": "jpg",
          "height": 365,
          "mimetype": "image/jpeg",
          "secret": "bf1LrqjxXhRFijiuiKul1jfNJSMs6CXs",
          "width": 800
        },
        "dc": {
          "extension": "jpg",
          "height": 365,
          "mimetype": "image/jpeg",
          "secret": "bf1LrqjxXhRFijiuiKul1jfNJSMs6CXs",
          "width": 800
        },
        "ds": {
          "extension": "jpg",
          "height": 320,
          "mimetype": "image/jpeg",
          "secret": "bf1LrqjxXhRFijiuiKul1jfNJSMs6CXs",
          "width": 320
        },
        "k": {
          "extension": "jpg",
          "height": 936,
          "mimetype": "image/jpeg",
          "secret": "bf1LrqjxXhRFijiuiKul1jfNJSMs6CXs",
          "width": 2048
        },
        "n": {
          "extension": "jpg",
          "height": 146,
          "mimetype": "image/jpeg",
          "secret": "bf1LrqjxXhRFijiuiKul1jfNJSMs6CXs",
          "width": 320
        },
        "o": {
          "extension": "jpg",
          "height": 1314,
          "mimetype": "image/jpeg",
          "secret": "7kaGWUG1Y7db3FeM0BVvMzfFUOtSbubE",
          "width": 2874
        },
        "s": {
          "extension": "jpg",
          "height": 320,
          "mimetype": "image/jpeg",
          "secret": "bf1LrqjxXhRFijiuiKul1jfNJSMs6CXs",
          "width": 320
        },
        "z": {
          "extension": "jpg",
          "height": 292,
          "mimetype": "image/jpeg",
          "secret": "bf1LrqjxXhRFijiuiKul1jfNJSMs6CXs",
          "width": 640
        }
      }
    },
    "media:uri_template": "https://millsfield.sfomuseum.org/media/152/782/021/1/1527820211_{secret}_{label}.{extention}",
    "sfomuseum:filename": "31465.tif",
    "sfomuseum:image_index": 5,
    "sfomuseum:placetype": "image",
    "sfomuseum:primary_image": 0,
    "wof:depicts": [
      1511923595
    ],
    "wof:name": "airmail flight cover: Pan American Airways, Boeing 314 “Dixie Clipper”, Clara Adams",
    "wof:placetype": "media"
  },
  "geometry": {"coordinates":[-122.386155,37.616358],"type":"Point"}
}
