{
  "type": "Feature",
  "properties": {
    "iso:country": "XX",
    "media:fingerprint": "b9789454dadc64cb74eff066af3a0098bf267efd",
    "media:imagehash_avg": "a:437171f1e3e3c4c0",
    "media:imagehash_diff": "d:87c7e5c5c64e1d15",
    "media:medium": "image",
    "media:mimetype": "image/tiff",
    "media:properties": {
      "colours": [
        {
          "hex": "#808080",
          "name": "#808080",
          "reference": "vibrant"
        },
        {
          "hex": "#c0c0c0",
          "name": "#c0c0c0",
          "reference": "vibrant"
        },
        {
          "hex": "#464646",
          "name": "#464646",
          "reference": "vibrant"
        }
      ],
      "sizes": {
        "b": {
          "extension": "jpg",
          "height": 727,
          "mimetype": "image/jpeg",
          "secret": "4EZUO2tQ4XBZXkqhBIHmoiPXqJc9UkRS",
          "width": 1024
        },
        "c": {
          "extension": "jpg",
          "height": 568,
          "mimetype": "image/jpeg",
          "secret": "4EZUO2tQ4XBZXkqhBIHmoiPXqJc9UkRS",
          "width": 799
        },
        "dc": {
          "extension": "jpg",
          "height": 568,
          "mimetype": "image/jpeg",
          "secret": "4EZUO2tQ4XBZXkqhBIHmoiPXqJc9UkRS",
          "width": 799
        },
        "ds": {
          "extension": "jpg",
          "height": 320,
          "mimetype": "image/jpeg",
          "secret": "4EZUO2tQ4XBZXkqhBIHmoiPXqJc9UkRS",
          "width": 320
        },
        "k": {
          "extension": "jpg",
          "height": 1455,
          "mimetype": "image/jpeg",
          "secret": "4EZUO2tQ4XBZXkqhBIHmoiPXqJc9UkRS",
          "width": 2048
        },
        "n": {
          "extension": "jpg",
          "height": 227,
          "mimetype": "image/jpeg",
          "secret": "4EZUO2tQ4XBZXkqhBIHmoiPXqJc9UkRS",
          "width": 320
        },
        "o": {
          "extension": "jpg",
          "height": 6192,
          "mimetype": "image/jpeg",
          "secret": "HMO1Twk3z2noCpZNF7feilZ1huSNyJBb",
          "width": 8712
        },
        "s": {
          "extension": "jpg",
          "height": 320,
          "mimetype": "image/jpeg",
          "secret": "4EZUO2tQ4XBZXkqhBIHmoiPXqJc9UkRS",
          "width": 320
        },
        "z": {
          "extension": "jpg",
          "height": 454,
          "mimetype": "image/jpeg",
          "secret": "4EZUO2tQ4XBZXkqhBIHmoiPXqJc9UkRS",
          "width": 640
        }
      }
    },
    "media:uri_template": "https://static.sfomuseum.org/media/152/783/048/9/1527830489_{secret}_{label}.{extention}",
    "sfomuseum:filename": "57598.tif",
    "sfomuseum:image_index": 5,
    "sfomuseum:image_type": "studio",
    "sfomuseum:placetype": "image",
    "sfomuseum:primary_image": 1,
    "wof:depicts": [
      1159284989,
      1511954861
    ],
    "wof:name": "career history questionnaire: World Wings International, Raymonde (Mona) Daumery Klecker",
    "wof:placetype": "custom",
    "wof:placetype_alt": "image"
  },
  "geometry": {"coordinates":[-122.386155,37.616358],"type":"Point"}
}
