{
  "type": "Feature",
  "properties": {
    "iso:country": "XX",
    "media:fingerprint": "e3b50fcda54d2e545d7dc2fe94fb6a0705dea26c",
    "media:imagehash_avg": "a:7fff7f7c0c0c0723",
    "media:imagehash_diff": "d:f0f0f0c4f8f86cc7",
    "media:medium": "image",
    "media:mimetype": "image/tiff",
    "media:properties": {
      "colours": [
        {
          "hex": "#868686",
          "name": "#868686",
          "reference": "vibrant"
        }, 
        {
          "hex": "#c0c0c0",
          "name": "#c0c0c0",
          "reference": "vibrant"
        }, 
        {
          "hex": "#404040",
          "name": "#404040",
          "reference": "vibrant"
        }
      ],
      "sizes": {
        "b": {
          "extension": "jpg",
          "height": 768,
          "mimetype": "image/jpeg",
          "secret": "5w8U4ldyDGgE90nRDd1szQVfFcMGxtzg",
          "width": 975
        },
        "c": {
          "extension": "jpg",
          "height": 600,
          "mimetype": "image/jpeg",
          "secret": "5w8U4ldyDGgE90nRDd1szQVfFcMGxtzg",
          "width": 762
        },
        "dc": {
          "extension": "jpg",
          "height": 600,
          "mimetype": "image/jpeg",
          "secret": "5w8U4ldyDGgE90nRDd1szQVfFcMGxtzg",
          "width": 762
        },
        "ds": {
          "extension": "jpg",
          "height": 320,
          "mimetype": "image/jpeg",
          "secret": "5w8U4ldyDGgE90nRDd1szQVfFcMGxtzg",
          "width": 320
        },
        "k": {
          "extension": "jpg",
          "height": 1536,
          "mimetype": "image/jpeg",
          "secret": "5w8U4ldyDGgE90nRDd1szQVfFcMGxtzg",
          "width": 1951
        },
        "n": {
          "extension": "jpg",
          "height": 240,
          "mimetype": "image/jpeg",
          "secret": "5w8U4ldyDGgE90nRDd1szQVfFcMGxtzg",
          "width": 304
        },
        "o": {
          "extension": "jpg",
          "height": 2168,
          "mimetype": "image/jpeg",
          "secret": "MV9saxYaV3CSizZ7rgKBn3SPIYcE9Frs",
          "width": 2754
        },
        "s": {
          "extension": "jpg",
          "height": 320,
          "mimetype": "image/jpeg",
          "secret": "5w8U4ldyDGgE90nRDd1szQVfFcMGxtzg",
          "width": 320
        },
        "z": {
          "extension": "jpg",
          "height": 480,
          "mimetype": "image/jpeg",
          "secret": "5w8U4ldyDGgE90nRDd1szQVfFcMGxtzg",
          "width": 609
        }
      }
    },
    "media:uri_template": "https://millsfield.sfomuseum.org/media/152/782/562/5/1527825625_{secret}_{label}.{extention}",
    "sfomuseum:filename": "43239.tif",
    "sfomuseum:image_index": 5,
    "sfomuseum:placetype": "image",
    "sfomuseum:primary_image": 1,
    "wof:depicts": [
      1511946663
    ],
    "wof:name": "negative: San Francisco International Airport (SFO), Boarding Area E",
    "wof:placetype": "media"
  },
  "geometry": {"coordinates":[-122.386155,37.616358],"type":"Point"}
}
