{
  "type": "Feature",
  "properties": {
    "iso:country": "XX",
    "media:fingerprint": "27187fdf185a206e388c6efb555d2ea2f8e3b2ee",
    "media:imagehash_avg": "a:e7b981061e9481e7",
    "media:imagehash_diff": "d:0f63613e7a79391f",
    "media:medium": "image",
    "media:mimetype": "image/tiff",
    "media:properties": {
      "colours": [
        {
          "hex": "#f8c818",
          "name": "#f8c818",
          "reference": "vibrant"
        }, 
        {
          "hex": "#e57d67",
          "name": "#e57d67",
          "reference": "vibrant"
        }, 
        {
          "hex": "#08093a",
          "name": "#08093a",
          "reference": "vibrant"
        }, 
        {
          "hex": "#7b7885",
          "name": "#7b7885",
          "reference": "vibrant"
        }, 
        {
          "hex": "#c6ae9b",
          "name": "#c6ae9b",
          "reference": "vibrant"
        }
      ],
      "sizes": {
        "b": {
          "extension": "jpg",
          "height": 764,
          "mimetype": "image/jpeg",
          "secret": "WN7pXb7skzhZGksYxwkOgQmGgwpUAnhT",
          "width": 1024
        },
        "c": {
          "extension": "jpg",
          "height": 597,
          "mimetype": "image/jpeg",
          "secret": "WN7pXb7skzhZGksYxwkOgQmGgwpUAnhT",
          "width": 800
        },
        "dc": {
          "extension": "jpg",
          "height": 597,
          "mimetype": "image/jpeg",
          "secret": "WN7pXb7skzhZGksYxwkOgQmGgwpUAnhT",
          "width": 800
        },
        "ds": {
          "extension": "jpg",
          "height": 320,
          "mimetype": "image/jpeg",
          "secret": "WN7pXb7skzhZGksYxwkOgQmGgwpUAnhT",
          "width": 320
        },
        "k": {
          "extension": "jpg",
          "height": 1528,
          "mimetype": "image/jpeg",
          "secret": "WN7pXb7skzhZGksYxwkOgQmGgwpUAnhT",
          "width": 2048
        },
        "n": {
          "extension": "jpg",
          "height": 238,
          "mimetype": "image/jpeg",
          "secret": "WN7pXb7skzhZGksYxwkOgQmGgwpUAnhT",
          "width": 320
        },
        "o": {
          "extension": "jpg",
          "height": 424,
          "mimetype": "image/jpeg",
          "secret": "bGKy8zbRgTn2HiBLwJIpG2NgVQqYMtwz",
          "width": 568
        },
        "s": {
          "extension": "jpg",
          "height": 320,
          "mimetype": "image/jpeg",
          "secret": "WN7pXb7skzhZGksYxwkOgQmGgwpUAnhT",
          "width": 320
        },
        "z": {
          "extension": "jpg",
          "height": 477,
          "mimetype": "image/jpeg",
          "secret": "WN7pXb7skzhZGksYxwkOgQmGgwpUAnhT",
          "width": 640
        }
      }
    },
    "media:uri_template": "https://millsfield.sfomuseum.org/media/152/781/931/5/1527819315_{secret}_{label}.{extention}",
    "sfomuseum:filename": "26512.tif",
    "sfomuseum:image_index": 5,
    "sfomuseum:placetype": "image",
    "sfomuseum:primary_image": 1,
    "wof:depicts": [
      1511950251
    ],
    "wof:name": "luggage label: SAS (Scandinavian Airlines System)",
    "wof:placetype": "media"
  },
  "geometry": {"coordinates":[-122.386155,37.616358],"type":"Point"}
}
