{
  "type": "Feature",
  "properties": {
    "iso:country": "XX",
    "media:fingerprint": "cd055c1f82835e9013e5ae7dc76744608d8df547",
    "media:imagehash_avg": "a:ff818181b1bdbfbf",
    "media:imagehash_diff": "d:5507070b43716471",
    "media:medium": "image",
    "media:mimetype": "image/tiff",
    "media:properties": {
      "colours": [
        {
          "hex": "#727b8a",
          "name": "#727b8a",
          "reference": "vibrant"
        }, 
        {
          "hex": "#adb8c7",
          "name": "#adb8c7",
          "reference": "vibrant"
        }, 
        {
          "hex": "#3e474c",
          "name": "#3e474c",
          "reference": "vibrant"
        }
      ],
      "sizes": {
        "b": {
          "extension": "jpg",
          "height": 768,
          "mimetype": "image/jpeg",
          "secret": "D5XZOAzmK4Xpzi3xOJmB93uSUhrduxqx",
          "width": 509
        },
        "c": {
          "extension": "jpg",
          "height": 600,
          "mimetype": "image/jpeg",
          "secret": "D5XZOAzmK4Xpzi3xOJmB93uSUhrduxqx",
          "width": 397
        },
        "dc": {
          "extension": "jpg",
          "height": 600,
          "mimetype": "image/jpeg",
          "secret": "D5XZOAzmK4Xpzi3xOJmB93uSUhrduxqx",
          "width": 397
        },
        "ds": {
          "extension": "jpg",
          "height": 320,
          "mimetype": "image/jpeg",
          "secret": "D5XZOAzmK4Xpzi3xOJmB93uSUhrduxqx",
          "width": 320
        },
        "k": {
          "extension": "jpg",
          "height": 1536,
          "mimetype": "image/jpeg",
          "secret": "D5XZOAzmK4Xpzi3xOJmB93uSUhrduxqx",
          "width": 1018
        },
        "n": {
          "extension": "jpg",
          "height": 240,
          "mimetype": "image/jpeg",
          "secret": "D5XZOAzmK4Xpzi3xOJmB93uSUhrduxqx",
          "width": 159
        },
        "o": {
          "extension": "jpg",
          "height": 2904,
          "mimetype": "image/jpeg",
          "secret": "bpjhxGzla1Y61xbpZh1A5MpjLRqkoQtr",
          "width": 1926
        },
        "s": {
          "extension": "jpg",
          "height": 320,
          "mimetype": "image/jpeg",
          "secret": "D5XZOAzmK4Xpzi3xOJmB93uSUhrduxqx",
          "width": 320
        },
        "z": {
          "extension": "jpg",
          "height": 480,
          "mimetype": "image/jpeg",
          "secret": "D5XZOAzmK4Xpzi3xOJmB93uSUhrduxqx",
          "width": 318
        }
      }
    },
    "media:uri_template": "https://millsfield.sfomuseum.org/media/152/782/378/1/1527823781_{secret}_{label}.{extention}",
    "sfomuseum:filename": "41786.tif",
    "sfomuseum:image_index": 5,
    "sfomuseum:placetype": "image",
    "sfomuseum:primary_image": 0,
    "wof:depicts": [
      1511908509
    ],
    "wof:name": "airsickness bag: Cathay Pacific Airways",
    "wof:placetype": "media"
  },
  "geometry": {"coordinates":[-122.386155,37.616358],"type":"Point"}
}
