{
  "type": "Feature",
  "properties": {
    "iso:country": "XX",
    "media:fingerprint": "e2c6ef5fe966c49a4770217c582719c90b5ecba2",
    "media:imagehash_avg": "a:ffffe60380000000",
    "media:imagehash_diff": "d:40000ce735363634",
    "media:medium": "image",
    "media:mimetype": "image/tiff",
    "media:properties": {
      "colours": [
        {
          "hex": "#808080",
          "name": "#808080",
          "reference": "vibrant"
        }, 
        {
          "hex": "#b8b8b8",
          "name": "#b8b8b8",
          "reference": "vibrant"
        }, 
        {
          "hex": "#484848",
          "name": "#484848",
          "reference": "vibrant"
        }
      ],
      "sizes": {
        "b": {
          "extension": "jpg",
          "height": 768,
          "mimetype": "image/jpeg",
          "secret": "0AjCMxlRCRoR7HoOBTlt3Yvk2RG3vYIs",
          "width": 975
        },
        "c": {
          "extension": "jpg",
          "height": 600,
          "mimetype": "image/jpeg",
          "secret": "0AjCMxlRCRoR7HoOBTlt3Yvk2RG3vYIs",
          "width": 762
        },
        "dc": {
          "extension": "jpg",
          "height": 600,
          "mimetype": "image/jpeg",
          "secret": "0AjCMxlRCRoR7HoOBTlt3Yvk2RG3vYIs",
          "width": 762
        },
        "ds": {
          "extension": "jpg",
          "height": 320,
          "mimetype": "image/jpeg",
          "secret": "0AjCMxlRCRoR7HoOBTlt3Yvk2RG3vYIs",
          "width": 320
        },
        "k": {
          "extension": "jpg",
          "height": 1536,
          "mimetype": "image/jpeg",
          "secret": "0AjCMxlRCRoR7HoOBTlt3Yvk2RG3vYIs",
          "width": 1951
        },
        "n": {
          "extension": "jpg",
          "height": 240,
          "mimetype": "image/jpeg",
          "secret": "0AjCMxlRCRoR7HoOBTlt3Yvk2RG3vYIs",
          "width": 304
        },
        "o": {
          "extension": "jpg",
          "height": 2168,
          "mimetype": "image/jpeg",
          "secret": "RQ79taB7CwEr3gi4QoivbrF2M1eFZRoU",
          "width": 2754
        },
        "s": {
          "extension": "jpg",
          "height": 320,
          "mimetype": "image/jpeg",
          "secret": "0AjCMxlRCRoR7HoOBTlt3Yvk2RG3vYIs",
          "width": 320
        },
        "z": {
          "extension": "jpg",
          "height": 480,
          "mimetype": "image/jpeg",
          "secret": "0AjCMxlRCRoR7HoOBTlt3Yvk2RG3vYIs",
          "width": 609
        }
      }
    },
    "media:uri_template": "https://millsfield.sfomuseum.org/media/152/782/526/5/1527825265_{secret}_{label}.{extention}",
    "sfomuseum:filename": "43057.tif",
    "sfomuseum:image_index": 5,
    "sfomuseum:placetype": "image",
    "sfomuseum:primary_image": 1,
    "wof:depicts": [
      1511946283
    ],
    "wof:name": "negative: San Francisco International Airport (SFO), Belford Brown and George Hansen and South Terminal",
    "wof:placetype": "media"
  },
  "geometry": {"coordinates":[-122.386155,37.616358],"type":"Point"}
}
