{
  "type": "Feature",
  "properties": {
    "iso:country": "XX",
    "media:fingerprint": "848faf60e79210f6e16e208ebb9a5ccdfed8b1ec",
    "media:imagehash_avg": "a:ffffff81818181ff",
    "media:imagehash_diff": "d:21612b0f0f070307",
    "media:medium": "image",
    "media:mimetype": "image/tiff",
    "media:properties": {
      "colours": [
        {
          "hex": "#808080",
          "name": "#808080",
          "reference": "vibrant"
        }, 
        {
          "hex": "#b8b8b8",
          "name": "#b8b8b8",
          "reference": "vibrant"
        }, 
        {
          "hex": "#464646",
          "name": "#464646",
          "reference": "vibrant"
        }
      ],
      "sizes": {
        "b": {
          "extension": "jpg",
          "height": 768,
          "mimetype": "image/jpeg",
          "secret": "JPF2FlrBpBwgxUjABqTDGnUXQyEH1lrt",
          "width": 990
        },
        "c": {
          "extension": "jpg",
          "height": 600,
          "mimetype": "image/jpeg",
          "secret": "JPF2FlrBpBwgxUjABqTDGnUXQyEH1lrt",
          "width": 773
        },
        "dc": {
          "extension": "jpg",
          "height": 600,
          "mimetype": "image/jpeg",
          "secret": "JPF2FlrBpBwgxUjABqTDGnUXQyEH1lrt",
          "width": 773
        },
        "ds": {
          "extension": "jpg",
          "height": 320,
          "mimetype": "image/jpeg",
          "secret": "JPF2FlrBpBwgxUjABqTDGnUXQyEH1lrt",
          "width": 320
        },
        "k": {
          "extension": "jpg",
          "height": 1536,
          "mimetype": "image/jpeg",
          "secret": "JPF2FlrBpBwgxUjABqTDGnUXQyEH1lrt",
          "width": 1980
        },
        "n": {
          "extension": "jpg",
          "height": 240,
          "mimetype": "image/jpeg",
          "secret": "JPF2FlrBpBwgxUjABqTDGnUXQyEH1lrt",
          "width": 309
        },
        "o": {
          "extension": "jpg",
          "height": 2382,
          "mimetype": "image/jpeg",
          "secret": "742YVGH4NluJzv0hPf8pJC351VGlG9hz",
          "width": 3071
        },
        "s": {
          "extension": "jpg",
          "height": 320,
          "mimetype": "image/jpeg",
          "secret": "JPF2FlrBpBwgxUjABqTDGnUXQyEH1lrt",
          "width": 320
        },
        "z": {
          "extension": "jpg",
          "height": 480,
          "mimetype": "image/jpeg",
          "secret": "JPF2FlrBpBwgxUjABqTDGnUXQyEH1lrt",
          "width": 618
        }
      }
    },
    "media:uri_template": "https://millsfield.sfomuseum.org/media/152/782/093/1/1527820931_{secret}_{label}.{extention}",
    "sfomuseum:filename": "33244.tif",
    "sfomuseum:image_index": 5,
    "sfomuseum:placetype": "image",
    "sfomuseum:primary_image": 1,
    "wof:depicts": [
      1511931385
    ],
    "wof:name": "photograph: Pan American Airways, Sikorsky S-38",
    "wof:placetype": "media"
  },
  "geometry": {"coordinates":[-122.386155,37.616358],"type":"Point"}
}
