{
  "type": "Feature",
  "properties": {
    "iso:country": "XX",
    "media:fingerprint": "9661f7f912187664521484e0b321a2e90f7c7107",
    "media:imagehash_avg": "a:ffe3c181c1ffff7f",
    "media:imagehash_diff": "d:ba8f8f179787e8e8",
    "media:medium": "image",
    "media:mimetype": "image/tiff",
    "media:properties": {
      "colours": [
        {
          "hex": "#4d65aa",
          "name": "#4d65aa",
          "reference": "vibrant"
        },
        {
          "hex": "#859ac9",
          "name": "#859ac9",
          "reference": "vibrant"
        },
        {
          "hex": "#141d70",
          "name": "#141d70",
          "reference": "vibrant"
        },
        {
          "hex": "#5a6196",
          "name": "#5a6196",
          "reference": "vibrant"
        },
        {
          "hex": "#9eaacd",
          "name": "#9eaacd",
          "reference": "vibrant"
        }
      ],
      "sizes": {
        "b": {
          "extension": "jpg",
          "height": 768,
          "mimetype": "image/jpeg",
          "secret": "kxIk060YxBTk6mrmHCW6lWrlOGDnY1jl",
          "width": 445
        },
        "c": {
          "extension": "jpg",
          "height": 600,
          "mimetype": "image/jpeg",
          "secret": "kxIk060YxBTk6mrmHCW6lWrlOGDnY1jl",
          "width": 347
        },
        "dc": {
          "extension": "jpg",
          "height": 600,
          "mimetype": "image/jpeg",
          "secret": "kxIk060YxBTk6mrmHCW6lWrlOGDnY1jl",
          "width": 347
        },
        "ds": {
          "extension": "jpg",
          "height": 320,
          "mimetype": "image/jpeg",
          "secret": "kxIk060YxBTk6mrmHCW6lWrlOGDnY1jl",
          "width": 320
        },
        "k": {
          "extension": "jpg",
          "height": 1536,
          "mimetype": "image/jpeg",
          "secret": "kxIk060YxBTk6mrmHCW6lWrlOGDnY1jl",
          "width": 890
        },
        "n": {
          "extension": "jpg",
          "height": 239,
          "mimetype": "image/jpeg",
          "secret": "kxIk060YxBTk6mrmHCW6lWrlOGDnY1jl",
          "width": 139
        },
        "o": {
          "extension": "jpg",
          "height": 3288,
          "mimetype": "image/jpeg",
          "secret": "X2G2pJdHYE0ZaCshdjv3ESwtILMg8Vg8",
          "width": 1906
        },
        "s": {
          "extension": "jpg",
          "height": 320,
          "mimetype": "image/jpeg",
          "secret": "kxIk060YxBTk6mrmHCW6lWrlOGDnY1jl",
          "width": 320
        },
        "z": {
          "extension": "jpg",
          "height": 479,
          "mimetype": "image/jpeg",
          "secret": "kxIk060YxBTk6mrmHCW6lWrlOGDnY1jl",
          "width": 278
        }
      }
    },
    "media:uri_template": "https://static.sfomuseum.org/media/152/784/378/5/1527843785_{secret}_{label}.{extention}",
    "sfomuseum:filename": "68679.tif",
    "sfomuseum:image_index": 5,
    "sfomuseum:image_type": "studio",
    "sfomuseum:placetype": "image",
    "sfomuseum:primary_image": 1,
    "wof:depicts": [
      1159283849,
      1511927569
    ],
    "wof:name": "menu: American Airlines, Business Class",
    "wof:placetype": "custom",
    "wof:placetype_alt": "image"
  },
  "geometry": {"coordinates":[-122.386155,37.616358],"type":"Point"}
}
