{
  "type": "Feature",
  "properties": {
    "iso:country": "XX",
    "media:fingerprint": "06f81707ce8d4166b2d2c0dc53e39bc888835fc7",
    "media:imagehash_avg": "a:f03c3f3f3f0f0e00",
    "media:imagehash_diff": "d:40f0f7f8fcfc4ca4",
    "media:medium": "image",
    "media:mimetype": "image/tiff",
    "media:properties": {
      "colours": [
        {
          "hex": "#868686",
          "name": "#868686",
          "reference": "vibrant"
        },
        {
          "hex": "#c0c0c0",
          "name": "#c0c0c0",
          "reference": "vibrant"
        },
        {
          "hex": "#484848",
          "name": "#484848",
          "reference": "vibrant"
        }
      ],
      "sizes": {
        "b": {
          "extension": "jpg",
          "height": 768,
          "mimetype": "image/jpeg",
          "secret": "RS7TjnvlSCeM3GFw7O8KBOiF2G6peCXv",
          "width": 981
        },
        "c": {
          "extension": "jpg",
          "height": 600,
          "mimetype": "image/jpeg",
          "secret": "RS7TjnvlSCeM3GFw7O8KBOiF2G6peCXv",
          "width": 767
        },
        "dc": {
          "extension": "jpg",
          "height": 600,
          "mimetype": "image/jpeg",
          "secret": "RS7TjnvlSCeM3GFw7O8KBOiF2G6peCXv",
          "width": 767
        },
        "ds": {
          "extension": "jpg",
          "height": 320,
          "mimetype": "image/jpeg",
          "secret": "RS7TjnvlSCeM3GFw7O8KBOiF2G6peCXv",
          "width": 320
        },
        "k": {
          "extension": "jpg",
          "height": 1536,
          "mimetype": "image/jpeg",
          "secret": "RS7TjnvlSCeM3GFw7O8KBOiF2G6peCXv",
          "width": 1963
        },
        "n": {
          "extension": "jpg",
          "height": 240,
          "mimetype": "image/jpeg",
          "secret": "RS7TjnvlSCeM3GFw7O8KBOiF2G6peCXv",
          "width": 306
        },
        "o": {
          "extension": "jpg",
          "height": 2154,
          "mimetype": "image/jpeg",
          "secret": "p7zD6XeXoTYXQB5bVjH5kfEcjIxW8WMA",
          "width": 2754
        },
        "s": {
          "extension": "jpg",
          "height": 320,
          "mimetype": "image/jpeg",
          "secret": "RS7TjnvlSCeM3GFw7O8KBOiF2G6peCXv",
          "width": 320
        },
        "z": {
          "extension": "jpg",
          "height": 480,
          "mimetype": "image/jpeg",
          "secret": "RS7TjnvlSCeM3GFw7O8KBOiF2G6peCXv",
          "width": 613
        }
      }
    },
    "media:uri_template": "https://static.sfomuseum.org/media/152/782/438/9/1527824389_{secret}_{label}.{extention}",
    "sfomuseum:filename": "42400.tif",
    "sfomuseum:image_index": 5,
    "sfomuseum:image_type": "studio",
    "sfomuseum:placetype": "image",
    "sfomuseum:primary_image": 1,
    "wof:depicts": [
      102527513,
      1511945711
    ],
    "wof:name": "negative: San Francisco International Airport (SFO), aerial",
    "wof:placetype": "custom",
    "wof:placetype_alt": "image"
  },
  "geometry": {"coordinates":[-122.386155,37.616358],"type":"Point"}
}
