{
  "type": "Feature",
  "properties": {
    "iso:country": "XX",
    "media:fingerprint": "b23dd329c9e25c17f307ca9f67b712e12828684d",
    "media:imagehash_avg": "a:8383e7c3c3e7ffff",
    "media:imagehash_diff": "d:3e0a0e0e0e0e2e1e",
    "media:medium": "image",
    "media:mimetype": "image/tiff",
    "media:properties": {
      "colours": [
        {
          "hex": "#f8e8b8",
          "name": "#f8e8b8",
          "reference": "vibrant"
        },
        {
          "hex": "#232209",
          "name": "#232209",
          "reference": "vibrant"
        },
        {
          "hex": "#999273",
          "name": "#999273",
          "reference": "vibrant"
        },
        {
          "hex": "#d8cea9",
          "name": "#d8cea9",
          "reference": "vibrant"
        },
        {
          "hex": "#544a31",
          "name": "#544a31",
          "reference": "vibrant"
        }
      ],
      "sizes": {
        "b": {
          "extension": "jpg",
          "height": 768,
          "mimetype": "image/jpeg",
          "secret": "FpAzgoUDzj4XVK3vMzWES3gHE3bqp3HR",
          "width": 541
        },
        "c": {
          "extension": "jpg",
          "height": 600,
          "mimetype": "image/jpeg",
          "secret": "FpAzgoUDzj4XVK3vMzWES3gHE3bqp3HR",
          "width": 423
        },
        "dc": {
          "extension": "jpg",
          "height": 600,
          "mimetype": "image/jpeg",
          "secret": "FpAzgoUDzj4XVK3vMzWES3gHE3bqp3HR",
          "width": 423
        },
        "ds": {
          "extension": "jpg",
          "height": 320,
          "mimetype": "image/jpeg",
          "secret": "FpAzgoUDzj4XVK3vMzWES3gHE3bqp3HR",
          "width": 320
        },
        "k": {
          "extension": "jpg",
          "height": 1536,
          "mimetype": "image/jpeg",
          "secret": "FpAzgoUDzj4XVK3vMzWES3gHE3bqp3HR",
          "width": 1083
        },
        "n": {
          "extension": "jpg",
          "height": 240,
          "mimetype": "image/jpeg",
          "secret": "FpAzgoUDzj4XVK3vMzWES3gHE3bqp3HR",
          "width": 169
        },
        "o": {
          "extension": "jpg",
          "height": 3038,
          "mimetype": "image/jpeg",
          "secret": "1GtrubwSrHr04qgI3TG5LtiNl7q1zY9X",
          "width": 2143
        },
        "s": {
          "extension": "jpg",
          "height": 320,
          "mimetype": "image/jpeg",
          "secret": "FpAzgoUDzj4XVK3vMzWES3gHE3bqp3HR",
          "width": 320
        },
        "z": {
          "extension": "jpg",
          "height": 480,
          "mimetype": "image/jpeg",
          "secret": "FpAzgoUDzj4XVK3vMzWES3gHE3bqp3HR",
          "width": 338
        }
      }
    },
    "media:uri_template": "https://millsfield.sfomuseum.org/media/152/784/613/5/1527846135_{secret}_{label}.{extention}",
    "sfomuseum:filename": "2001080200_inside.tif",
    "sfomuseum:image_index": 5,
    "sfomuseum:placetype": "image",
    "sfomuseum:primary_image": 0,
    "wof:depicts": [
      1511922117,
      1159289653,
      1159293593
    ],
    "wof:name": "menu: Pan American World Airways, Historic First Flights series, Boeing 707",
    "wof:placetype": "custom",
    "wof:placetype_alt": "image"
  },
  "geometry": {"coordinates":[-122.386155,37.616358],"type":"Point"}
}
