{
  "type": "Feature",
  "properties": {
    "iso:country": "XX",
    "media:fingerprint": "14acfd7ec090338fdadb2314cb4ebd270e595f80",
    "media:imagehash_avg": "a:3f7f7f7f6f077f08",
    "media:imagehash_diff": "d:b5edadc79ddfdbdb",
    "media:medium": "image",
    "media:mimetype": "image/tiff",
    "media:properties": {
      "colours": [
        {
          "hex": "#f8efdb",
          "name": "#f8efdb",
          "reference": "vibrant"
        }, 
        {
          "hex": "#818685",
          "name": "#818685",
          "reference": "vibrant"
        }, 
        {
          "hex": "#a8b8c8",
          "name": "#a8b8c8",
          "reference": "vibrant"
        }, 
        {
          "hex": "#4e4c41",
          "name": "#4e4c41",
          "reference": "vibrant"
        }
      ],
      "sizes": {
        "b": {
          "extension": "jpg",
          "height": 768,
          "mimetype": "image/jpeg",
          "secret": "R0dpLkogqPXE6BmsvyMbZcnhFNg5p2ol",
          "width": 406
        },
        "c": {
          "extension": "jpg",
          "height": 600,
          "mimetype": "image/jpeg",
          "secret": "R0dpLkogqPXE6BmsvyMbZcnhFNg5p2ol",
          "width": 317
        },
        "dc": {
          "extension": "jpg",
          "height": 600,
          "mimetype": "image/jpeg",
          "secret": "R0dpLkogqPXE6BmsvyMbZcnhFNg5p2ol",
          "width": 317
        },
        "ds": {
          "extension": "jpg",
          "height": 320,
          "mimetype": "image/jpeg",
          "secret": "R0dpLkogqPXE6BmsvyMbZcnhFNg5p2ol",
          "width": 320
        },
        "k": {
          "extension": "jpg",
          "height": 1536,
          "mimetype": "image/jpeg",
          "secret": "R0dpLkogqPXE6BmsvyMbZcnhFNg5p2ol",
          "width": 812
        },
        "n": {
          "extension": "jpg",
          "height": 240,
          "mimetype": "image/jpeg",
          "secret": "R0dpLkogqPXE6BmsvyMbZcnhFNg5p2ol",
          "width": 127
        },
        "o": {
          "extension": "jpg",
          "height": 2880,
          "mimetype": "image/jpeg",
          "secret": "FmfxiSdB2MgcPcBcKGxGvzTWJcWLm25o",
          "width": 1524
        },
        "s": {
          "extension": "jpg",
          "height": 320,
          "mimetype": "image/jpeg",
          "secret": "R0dpLkogqPXE6BmsvyMbZcnhFNg5p2ol",
          "width": 320
        },
        "z": {
          "extension": "jpg",
          "height": 480,
          "mimetype": "image/jpeg",
          "secret": "R0dpLkogqPXE6BmsvyMbZcnhFNg5p2ol",
          "width": 254
        }
      }
    },
    "media:uri_template": "https://millsfield.sfomuseum.org/media/152/782/363/3/1527823633_{secret}_{label}.{extention}",
    "sfomuseum:filename": "41694.tif",
    "sfomuseum:image_index": 5,
    "sfomuseum:placetype": "image",
    "sfomuseum:primary_image": 1,
    "wof:depicts": [
      1511908469
    ],
    "wof:name": "airsickness bag: British Midland Airways",
    "wof:placetype": "media"
  },
  "geometry": {"coordinates":[-122.386155,37.616358],"type":"Point"}
}
