{
  "type": "Feature",
  "properties": {
    "iso:country": "XX",
    "media:fingerprint": "2449a86458992d7d4642a4d1c2875b988955275d",
    "media:imagehash_avg": "a:e78581818181c1ff",
    "media:imagehash_diff": "d:4d4d7b3333591919",
    "media:medium": "image",
    "media:mimetype": "image/tiff",
    "media:properties": {
      "colours": [
        {
          "hex": "#d7c8aa",
          "name": "#d7c8aa",
          "reference": "vibrant"
        }, 
        {
          "hex": "#3c3416",
          "name": "#3c3416",
          "reference": "vibrant"
        }, 
        {
          "hex": "#a0936c",
          "name": "#a0936c",
          "reference": "vibrant"
        }, 
        {
          "hex": "#d0c8a9",
          "name": "#d0c8a9",
          "reference": "vibrant"
        }, 
        {
          "hex": "#524c2d",
          "name": "#524c2d",
          "reference": "vibrant"
        }
      ],
      "sizes": {
        "b": {
          "extension": "jpg",
          "height": 580,
          "mimetype": "image/jpeg",
          "secret": "1t2AN2A5drTnvZRa4CKLwoO7nZe1AMGT",
          "width": 1024
        },
        "c": {
          "extension": "jpg",
          "height": 453,
          "mimetype": "image/jpeg",
          "secret": "1t2AN2A5drTnvZRa4CKLwoO7nZe1AMGT",
          "width": 800
        },
        "dc": {
          "extension": "jpg",
          "height": 453,
          "mimetype": "image/jpeg",
          "secret": "1t2AN2A5drTnvZRa4CKLwoO7nZe1AMGT",
          "width": 800
        },
        "ds": {
          "extension": "jpg",
          "height": 320,
          "mimetype": "image/jpeg",
          "secret": "1t2AN2A5drTnvZRa4CKLwoO7nZe1AMGT",
          "width": 320
        },
        "k": {
          "extension": "jpg",
          "height": 1161,
          "mimetype": "image/jpeg",
          "secret": "1t2AN2A5drTnvZRa4CKLwoO7nZe1AMGT",
          "width": 2048
        },
        "n": {
          "extension": "jpg",
          "height": 181,
          "mimetype": "image/jpeg",
          "secret": "1t2AN2A5drTnvZRa4CKLwoO7nZe1AMGT",
          "width": 320
        },
        "o": {
          "extension": "jpg",
          "height": 1133,
          "mimetype": "image/jpeg",
          "secret": "Dl0tO5rVp6Oh6GJzsp4pVjiK7mG5YWAO",
          "width": 1998
        },
        "s": {
          "extension": "jpg",
          "height": 320,
          "mimetype": "image/jpeg",
          "secret": "1t2AN2A5drTnvZRa4CKLwoO7nZe1AMGT",
          "width": 320
        },
        "z": {
          "extension": "jpg",
          "height": 362,
          "mimetype": "image/jpeg",
          "secret": "1t2AN2A5drTnvZRa4CKLwoO7nZe1AMGT",
          "width": 640
        }
      }
    },
    "media:uri_template": "https://millsfield.sfomuseum.org/media/152/782/050/3/1527820503_{secret}_{label}.{extention}",
    "sfomuseum:filename": "31651.tif",
    "sfomuseum:image_index": 5,
    "sfomuseum:placetype": "image",
    "sfomuseum:primary_image": 0,
    "wof:depicts": [
      1511923751
    ],
    "wof:name": "airmail flight cover: Pan American Airways, first airmail flight, London - New York route",
    "wof:placetype": "media"
  },
  "geometry": {"coordinates":[-122.386155,37.616358],"type":"Point"}
}
