{
  "type": "Feature",
  "properties": {
    "iso:country": "XX",
    "media:fingerprint": "61be9a754645c18ca40365eb7f104d0aec897934",
    "media:imagehash_avg": "a:fffefe0000000000",
    "media:imagehash_diff": "d:00c0c8e0c2c3c0c8",
    "media:medium": "image",
    "media:mimetype": "image/tiff",
    "media:properties": {
      "colours": [
        {
          "hex": "#787878",
          "name": "#787878",
          "reference": "vibrant"
        }, 
        {
          "hex": "#c0c0c0",
          "name": "#c0c0c0",
          "reference": "vibrant"
        }, 
        {
          "hex": "#484848",
          "name": "#484848",
          "reference": "vibrant"
        }
      ],
      "sizes": {
        "b": {
          "extension": "jpg",
          "height": 767,
          "mimetype": "image/jpeg",
          "secret": "jg0cBzN05rUQ5xN3qzpoZ2rOrYJD6rYK",
          "width": 593
        },
        "c": {
          "extension": "jpg",
          "height": 600,
          "mimetype": "image/jpeg",
          "secret": "jg0cBzN05rUQ5xN3qzpoZ2rOrYJD6rYK",
          "width": 463
        },
        "dc": {
          "extension": "jpg",
          "height": 600,
          "mimetype": "image/jpeg",
          "secret": "jg0cBzN05rUQ5xN3qzpoZ2rOrYJD6rYK",
          "width": 463
        },
        "ds": {
          "extension": "jpg",
          "height": 320,
          "mimetype": "image/jpeg",
          "secret": "jg0cBzN05rUQ5xN3qzpoZ2rOrYJD6rYK",
          "width": 320
        },
        "k": {
          "extension": "jpg",
          "height": 1535,
          "mimetype": "image/jpeg",
          "secret": "jg0cBzN05rUQ5xN3qzpoZ2rOrYJD6rYK",
          "width": 1187
        },
        "n": {
          "extension": "jpg",
          "height": 240,
          "mimetype": "image/jpeg",
          "secret": "jg0cBzN05rUQ5xN3qzpoZ2rOrYJD6rYK",
          "width": 185
        },
        "o": {
          "extension": "jpg",
          "height": 2768,
          "mimetype": "image/jpeg",
          "secret": "iFwy0evQDLHokA0mb9kt8jW8cJRacm6C",
          "width": 2140
        },
        "s": {
          "extension": "jpg",
          "height": 320,
          "mimetype": "image/jpeg",
          "secret": "jg0cBzN05rUQ5xN3qzpoZ2rOrYJD6rYK",
          "width": 320
        },
        "z": {
          "extension": "jpg",
          "height": 480,
          "mimetype": "image/jpeg",
          "secret": "jg0cBzN05rUQ5xN3qzpoZ2rOrYJD6rYK",
          "width": 371
        }
      }
    },
    "media:uri_template": "https://millsfield.sfomuseum.org/media/152/782/167/9/1527821679_{secret}_{label}.{extention}",
    "sfomuseum:filename": "38921.tif",
    "sfomuseum:image_index": 5,
    "sfomuseum:placetype": "image",
    "sfomuseum:primary_image": 1,
    "wof:depicts": [
      1511943755
    ],
    "wof:name": "negative: San Francisco Airport, runway maintenance",
    "wof:placetype": "media"
  },
  "geometry": {"coordinates":[-122.386155,37.616358],"type":"Point"}
}
