{
  "type": "Feature",
  "properties": {
    "iso:country": "XX",
    "media:fingerprint": "28437043655a4d3ea63d11f91f3d0002cd151b8b",
    "media:imagehash_avg": "a:9e989c9e989e9d9f",
    "media:imagehash_diff": "d:383a3a3232343932",
    "media:medium": "image",
    "media:mimetype": "image/tiff",
    "media:properties": {
      "colours": [
        {
          "hex": "#bfa12a",
          "name": "#bfa12a",
          "reference": "vibrant"
        },
        {
          "hex": "#e6d798",
          "name": "#e6d798",
          "reference": "vibrant"
        },
        {
          "hex": "#8b8e88",
          "name": "#8b8e88",
          "reference": "vibrant"
        },
        {
          "hex": "#cdc9b2",
          "name": "#cdc9b2",
          "reference": "vibrant"
        },
        {
          "hex": "#4d4c42",
          "name": "#4d4c42",
          "reference": "vibrant"
        }
      ],
      "sizes": {
        "b": {
          "extension": "jpg",
          "height": 694,
          "mimetype": "image/jpeg",
          "secret": "qgb5A0FKhzhaRhG1NClAKJ5u4k1dKxnB",
          "width": 1024
        },
        "c": {
          "extension": "jpg",
          "height": 542,
          "mimetype": "image/jpeg",
          "secret": "qgb5A0FKhzhaRhG1NClAKJ5u4k1dKxnB",
          "width": 800
        },
        "dc": {
          "extension": "jpg",
          "height": 542,
          "mimetype": "image/jpeg",
          "secret": "qgb5A0FKhzhaRhG1NClAKJ5u4k1dKxnB",
          "width": 800
        },
        "ds": {
          "extension": "jpg",
          "height": 320,
          "mimetype": "image/jpeg",
          "secret": "qgb5A0FKhzhaRhG1NClAKJ5u4k1dKxnB",
          "width": 320
        },
        "k": {
          "extension": "jpg",
          "height": 1389,
          "mimetype": "image/jpeg",
          "secret": "qgb5A0FKhzhaRhG1NClAKJ5u4k1dKxnB",
          "width": 2048
        },
        "n": {
          "extension": "jpg",
          "height": 217,
          "mimetype": "image/jpeg",
          "secret": "qgb5A0FKhzhaRhG1NClAKJ5u4k1dKxnB",
          "width": 320
        },
        "o": {
          "extension": "jpg",
          "height": 2036,
          "mimetype": "image/jpeg",
          "secret": "DoyYRwg1Ken8CvLZABPOjrS6PQwtFGad",
          "width": 3000
        },
        "s": {
          "extension": "jpg",
          "height": 320,
          "mimetype": "image/jpeg",
          "secret": "qgb5A0FKhzhaRhG1NClAKJ5u4k1dKxnB",
          "width": 320
        },
        "z": {
          "extension": "jpg",
          "height": 434,
          "mimetype": "image/jpeg",
          "secret": "qgb5A0FKhzhaRhG1NClAKJ5u4k1dKxnB",
          "width": 640
        }
      }
    },
    "media:uri_template": "https://static.sfomuseum.org/media/152/784/356/5/1527843565_{secret}_{label}.{extention}",
    "sfomuseum:filename": "68572.tif",
    "sfomuseum:image_index": 5,
    "sfomuseum:image_type": "studio",
    "sfomuseum:placetype": "image",
    "sfomuseum:primary_image": 0,
    "wof:depicts": [
      1159284153,
      1511927605
    ],
    "wof:name": "menu: China Airlines, Dynasty (Business) Class",
    "wof:placetype": "custom",
    "wof:placetype_alt": "image"
  },
  "geometry": {"coordinates":[-122.386155,37.616358],"type":"Point"}
}
