{
  "type": "Feature",
  "properties": {
    "media:fingerprint": "dbcf3bbb644b1761b0f9b4b7c481894eab607198",
    "media:imagehash_avg": "a:fdf8e0e70707ffff",
    "media:imagehash_diff": "d:5139094f4f2f0974",
    "media:mimetype": "image/tiff",
    "media:properties": {
      "colours": [
        {
          "hex": "#333fd0",
          "name": "#333fd0",
          "reference": "vibrant"
        },
        {
          "hex": "#7c86ea",
          "name": "#7c86ea",
          "reference": "vibrant"
        },
        {
          "hex": "#5d4720",
          "name": "#5d4720",
          "reference": "vibrant"
        },
        {
          "hex": "#9e9358",
          "name": "#9e9358",
          "reference": "vibrant"
        },
        {
          "hex": "#ccc0ad",
          "name": "#ccc0ad",
          "reference": "vibrant"
        }
      ],
      "sizes": {
        "b": {
          "extension": "jpg",
          "height": 729,
          "mimetype": "image/jpeg",
          "secret": "OwXeufsJhj85GTqCv9mKlvrdO4P3lo02",
          "width": 1024
        },
        "c": {
          "extension": "jpg",
          "height": 569,
          "mimetype": "image/jpeg",
          "secret": "OwXeufsJhj85GTqCv9mKlvrdO4P3lo02",
          "width": 800
        },
        "dc": {
          "extension": "jpg",
          "height": 569,
          "mimetype": "image/jpeg",
          "secret": "OwXeufsJhj85GTqCv9mKlvrdO4P3lo02",
          "width": 800
        },
        "ds": {
          "extension": "jpg",
          "height": 320,
          "mimetype": "image/jpeg",
          "secret": "OwXeufsJhj85GTqCv9mKlvrdO4P3lo02",
          "width": 320
        },
        "k": {
          "extension": "jpg",
          "height": 1458,
          "mimetype": "image/jpeg",
          "secret": "OwXeufsJhj85GTqCv9mKlvrdO4P3lo02",
          "width": 2048
        },
        "n": {
          "extension": "jpg",
          "height": 227,
          "mimetype": "image/jpeg",
          "secret": "OwXeufsJhj85GTqCv9mKlvrdO4P3lo02",
          "width": 320
        },
        "o": {
          "extension": "jpg",
          "height": 1373,
          "mimetype": "image/jpeg",
          "secret": "DWif2S0MV68oVQN5VjqMFjMRCgIHp1ws",
          "width": 1928
        },
        "s": {
          "extension": "jpg",
          "height": 320,
          "mimetype": "image/jpeg",
          "secret": "OwXeufsJhj85GTqCv9mKlvrdO4P3lo02",
          "width": 320
        },
        "z": {
          "extension": "jpg",
          "height": 455,
          "mimetype": "image/jpeg",
          "secret": "OwXeufsJhj85GTqCv9mKlvrdO4P3lo02",
          "width": 640
        }
      }
    },
    "media:uri_template": "https://static.sfomuseum.org/media/174/651/215/9/1746512159_{secret}_{label}.{extention}",
    "sfomuseum:filename": "2009.073.002.tif",
    "sfomuseum:image_index": 0,
    "sfomuseum:image_type": "studio",
    "sfomuseum:placetype": "image",
    "sfomuseum:primary_image": 1,
    "wof:depicts": [
      1511935409
    ],
    "wof:name": "airmail flight cover: Romanian Philatelic Federation (Romfilatelia), 100th anniversary of Traian Vuia’s first flight",
    "wof:placetype": "custom",
    "wof:placetype_alt": "image"
  },
  "geometry": {"coordinates":[-122.386155,37.616357],"type":"Point"}
}
