{
  "type": "Feature",
  "properties": {
    "iso:country": "XX",
    "media:fingerprint": "0ecfcc52046cc109427c19f653b92ba03a18f256",
    "media:imagehash_avg": "a:0c3e3f3f3d793000",
    "media:imagehash_diff": "d:f8f8e66661c1c1e4",
    "media:medium": "image",
    "media:mimetype": "image/tiff",
    "media:properties": {
      "colours": [
        {
          "hex": "#bcbd49",
          "name": "#bcbd49",
          "reference": "vibrant"
        }, 
        {
          "hex": "#d5e09d",
          "name": "#d5e09d",
          "reference": "vibrant"
        }, 
        {
          "hex": "#787439",
          "name": "#787439",
          "reference": "vibrant"
        }, 
        {
          "hex": "#9fa162",
          "name": "#9fa162",
          "reference": "vibrant"
        }, 
        {
          "hex": "#aab96a",
          "name": "#aab96a",
          "reference": "vibrant"
        }
      ],
      "sizes": {
        "b": {
          "extension": "jpg",
          "height": 686,
          "mimetype": "image/jpeg",
          "secret": "Dqxqr784qw47fgfAG5ZQm7ZNHr0fGhDn",
          "width": 1024
        },
        "c": {
          "extension": "jpg",
          "height": 536,
          "mimetype": "image/jpeg",
          "secret": "Dqxqr784qw47fgfAG5ZQm7ZNHr0fGhDn",
          "width": 800
        },
        "dc": {
          "extension": "jpg",
          "height": 536,
          "mimetype": "image/jpeg",
          "secret": "Dqxqr784qw47fgfAG5ZQm7ZNHr0fGhDn",
          "width": 800
        },
        "ds": {
          "extension": "jpg",
          "height": 320,
          "mimetype": "image/jpeg",
          "secret": "Dqxqr784qw47fgfAG5ZQm7ZNHr0fGhDn",
          "width": 320
        },
        "k": {
          "extension": "jpg",
          "height": 1372,
          "mimetype": "image/jpeg",
          "secret": "Dqxqr784qw47fgfAG5ZQm7ZNHr0fGhDn",
          "width": 2048
        },
        "n": {
          "extension": "jpg",
          "height": 214,
          "mimetype": "image/jpeg",
          "secret": "Dqxqr784qw47fgfAG5ZQm7ZNHr0fGhDn",
          "width": 320
        },
        "o": {
          "extension": "jpg",
          "height": 1081,
          "mimetype": "image/jpeg",
          "secret": "YvMUucEBlyOwFNT4SuleS3bupFdU7V8o",
          "width": 1613
        },
        "s": {
          "extension": "jpg",
          "height": 320,
          "mimetype": "image/jpeg",
          "secret": "Dqxqr784qw47fgfAG5ZQm7ZNHr0fGhDn",
          "width": 320
        },
        "z": {
          "extension": "jpg",
          "height": 428,
          "mimetype": "image/jpeg",
          "secret": "Dqxqr784qw47fgfAG5ZQm7ZNHr0fGhDn",
          "width": 640
        }
      }
    },
    "media:uri_template": "https://millsfield.sfomuseum.org/media/152/782/755/7/1527827557_{secret}_{label}.{extention}",
    "sfomuseum:filename": "44140.tif",
    "sfomuseum:image_index": 5,
    "sfomuseum:placetype": "image",
    "sfomuseum:primary_image": 1,
    "wof:depicts": [
      1511948591
    ],
    "wof:name": "negative: San Francisco International Airport (SFO), barber shop",
    "wof:placetype": "media"
  },
  "geometry": {"coordinates":[-122.386155,37.616358],"type":"Point"}
}
