{
  "type": "Feature",
  "properties": {
    "iso:country": "XX",
    "media:fingerprint": "0bd9d74118472811a701171bea42fc6a159ec3f1",
    "media:imagehash_avg": "a:87bf9f81818181ff",
    "media:imagehash_diff": "d:2d69797373736333",
    "media:medium": "image",
    "media:mimetype": "image/tiff",
    "media:properties": {
      "colours": [
        {
          "hex": "#090822",
          "name": "#090822",
          "reference": "vibrant"
        },
        {
          "hex": "#8a787b",
          "name": "#8a787b",
          "reference": "vibrant"
        },
        {
          "hex": "#c6c0bf",
          "name": "#c6c0bf",
          "reference": "vibrant"
        },
        {
          "hex": "#3d2e42",
          "name": "#3d2e42",
          "reference": "vibrant"
        }
      ],
      "sizes": {
        "b": {
          "extension": "jpg",
          "height": 768,
          "mimetype": "image/jpeg",
          "secret": "7cplT1U16L7ItXyvzPKtO5WEeQhV4MST",
          "width": 443
        },
        "c": {
          "extension": "jpg",
          "height": 600,
          "mimetype": "image/jpeg",
          "secret": "7cplT1U16L7ItXyvzPKtO5WEeQhV4MST",
          "width": 346
        },
        "dc": {
          "extension": "jpg",
          "height": 600,
          "mimetype": "image/jpeg",
          "secret": "7cplT1U16L7ItXyvzPKtO5WEeQhV4MST",
          "width": 346
        },
        "ds": {
          "extension": "jpg",
          "height": 320,
          "mimetype": "image/jpeg",
          "secret": "7cplT1U16L7ItXyvzPKtO5WEeQhV4MST",
          "width": 320
        },
        "k": {
          "extension": "jpg",
          "height": 1536,
          "mimetype": "image/jpeg",
          "secret": "7cplT1U16L7ItXyvzPKtO5WEeQhV4MST",
          "width": 887
        },
        "n": {
          "extension": "jpg",
          "height": 240,
          "mimetype": "image/jpeg",
          "secret": "7cplT1U16L7ItXyvzPKtO5WEeQhV4MST",
          "width": 138
        },
        "o": {
          "extension": "jpg",
          "height": 2893,
          "mimetype": "image/jpeg",
          "secret": "UkK8g6Rx1FMulkRY4bZXWUdat1RnyMpH",
          "width": 1672
        },
        "s": {
          "extension": "jpg",
          "height": 320,
          "mimetype": "image/jpeg",
          "secret": "7cplT1U16L7ItXyvzPKtO5WEeQhV4MST",
          "width": 320
        },
        "z": {
          "extension": "jpg",
          "height": 480,
          "mimetype": "image/jpeg",
          "secret": "7cplT1U16L7ItXyvzPKtO5WEeQhV4MST",
          "width": 277
        }
      }
    },
    "media:uri_template": "https://static.sfomuseum.org/media/152/784/821/1/1527848211_{secret}_{label}.{extention}",
    "sfomuseum:filename": "72311.tif",
    "sfomuseum:image_index": 5,
    "sfomuseum:image_type": "studio",
    "sfomuseum:placetype": "image",
    "sfomuseum:primary_image": 0,
    "wof:depicts": [
      1511930585,
      1159285291,
      1159287133
    ],
    "wof:name": "menu: Thai Airways International, Royal Silk (Business) Class",
    "wof:placetype": "custom",
    "wof:placetype_alt": "image"
  },
  "geometry": {"coordinates":[-122.386155,37.616358],"type":"Point"}
}
