{
  "type": "Feature",
  "properties": {
    "iso:country": "VN",
    "media:fingerprint": "c13504ca9d2fb94b77f9545f1a1f50ccc417ec63",
    "media:imagehash_avg": "a:f7f1f0f1c3f7f3fd",
    "media:imagehash_diff": "d:6763e7878785a725",
    "media:medium": "image",
    "media:mimetype": "image/tiff",
    "media:properties": {
      "colours": [
        {
          "hex": "#dca738",
          "name": "#dca738",
          "reference": "vibrant"
        }, 
        {
          "hex": "#f8ecd5",
          "name": "#f8ecd5",
          "reference": "vibrant"
        }, 
        {
          "hex": "#313869",
          "name": "#313869",
          "reference": "vibrant"
        }, 
        {
          "hex": "#a5764c",
          "name": "#a5764c",
          "reference": "vibrant"
        }, 
        {
          "hex": "#c6b9b5",
          "name": "#c6b9b5",
          "reference": "vibrant"
        }
      ],
      "sizes": {
        "b": {
          "extension": "jpg",
          "height": 586,
          "mimetype": "image/jpeg",
          "secret": "lwYV7H8tFbmYnxNEQEzpN7ahfMGWRpTE",
          "width": 1024
        },
        "c": {
          "extension": "jpg",
          "height": 458,
          "mimetype": "image/jpeg",
          "secret": "lwYV7H8tFbmYnxNEQEzpN7ahfMGWRpTE",
          "width": 800
        },
        "dc": {
          "extension": "jpg",
          "height": 458,
          "mimetype": "image/jpeg",
          "secret": "lwYV7H8tFbmYnxNEQEzpN7ahfMGWRpTE",
          "width": 800
        },
        "ds": {
          "extension": "jpg",
          "height": 320,
          "mimetype": "image/jpeg",
          "secret": "lwYV7H8tFbmYnxNEQEzpN7ahfMGWRpTE",
          "width": 320
        },
        "k": {
          "extension": "jpg",
          "height": 1173,
          "mimetype": "image/jpeg",
          "secret": "lwYV7H8tFbmYnxNEQEzpN7ahfMGWRpTE",
          "width": 2048
        },
        "n": {
          "extension": "jpg",
          "height": 183,
          "mimetype": "image/jpeg",
          "secret": "lwYV7H8tFbmYnxNEQEzpN7ahfMGWRpTE",
          "width": 320
        },
        "o": {
          "extension": "jpg",
          "height": 1145,
          "mimetype": "image/jpeg",
          "secret": "4bvSbvyWxFLPiN3z8TvElM0rA29B7dVH",
          "width": 1998
        },
        "s": {
          "extension": "jpg",
          "height": 320,
          "mimetype": "image/jpeg",
          "secret": "lwYV7H8tFbmYnxNEQEzpN7ahfMGWRpTE",
          "width": 320
        },
        "z": {
          "extension": "jpg",
          "height": 366,
          "mimetype": "image/jpeg",
          "secret": "lwYV7H8tFbmYnxNEQEzpN7ahfMGWRpTE",
          "width": 640
        }
      }
    },
    "media:uri_template": "https://millsfield.sfomuseum.org/media/152/782/962/5/1527829625_{secret}_{label}.{extention}",
    "sfomuseum:filename": "48648.tif",
    "sfomuseum:image_index": 5,
    "sfomuseum:placetype": "image",
    "sfomuseum:primary_image": 1,
    "wof:depicts": [
      1511907099
    ],
    "wof:name": "airmail flight cover: Pan American World Airways, Saigon - Singapore route",
    "wof:placetype": "media"
  },
  "geometry": {"coordinates":[-122.386155,37.616358],"type":"Point"}
}
