{
  "type": "Feature",
  "properties": {
    "iso:country": "XX",
    "media:fingerprint": "c0196e253cba82fd9495229d25cda2644bbf1998",
    "media:imagehash_avg": "a:ff0400600b3f3f3e",
    "media:imagehash_diff": "d:fcf8d3c3fa7af1e0",
    "media:medium": "image",
    "media:mimetype": "image/tiff",
    "media:properties": {
      "colours": [
        {
          "hex": "#868686",
          "name": "#868686",
          "reference": "vibrant"
        }, 
        {
          "hex": "#b8b8b8",
          "name": "#b8b8b8",
          "reference": "vibrant"
        }, 
        {
          "hex": "#404040",
          "name": "#404040",
          "reference": "vibrant"
        }
      ],
      "sizes": {
        "b": {
          "extension": "jpg",
          "height": 768,
          "mimetype": "image/jpeg",
          "secret": "UIWRMmcEnGmKpuqlE59eRuHgNhc6vqgv",
          "width": 776
        },
        "c": {
          "extension": "jpg",
          "height": 600,
          "mimetype": "image/jpeg",
          "secret": "UIWRMmcEnGmKpuqlE59eRuHgNhc6vqgv",
          "width": 606
        },
        "dc": {
          "extension": "jpg",
          "height": 600,
          "mimetype": "image/jpeg",
          "secret": "UIWRMmcEnGmKpuqlE59eRuHgNhc6vqgv",
          "width": 606
        },
        "ds": {
          "extension": "jpg",
          "height": 320,
          "mimetype": "image/jpeg",
          "secret": "UIWRMmcEnGmKpuqlE59eRuHgNhc6vqgv",
          "width": 320
        },
        "k": {
          "extension": "jpg",
          "height": 1536,
          "mimetype": "image/jpeg",
          "secret": "UIWRMmcEnGmKpuqlE59eRuHgNhc6vqgv",
          "width": 1552
        },
        "n": {
          "extension": "jpg",
          "height": 239,
          "mimetype": "image/jpeg",
          "secret": "UIWRMmcEnGmKpuqlE59eRuHgNhc6vqgv",
          "width": 242
        },
        "o": {
          "extension": "jpg",
          "height": 2563,
          "mimetype": "image/jpeg",
          "secret": "VWOH4z5y9eH1y4iqvkdulonG9RBjAmXl",
          "width": 2590
        },
        "s": {
          "extension": "jpg",
          "height": 320,
          "mimetype": "image/jpeg",
          "secret": "UIWRMmcEnGmKpuqlE59eRuHgNhc6vqgv",
          "width": 320
        },
        "z": {
          "extension": "jpg",
          "height": 479,
          "mimetype": "image/jpeg",
          "secret": "UIWRMmcEnGmKpuqlE59eRuHgNhc6vqgv",
          "width": 485
        }
      }
    },
    "media:uri_template": "https://millsfield.sfomuseum.org/media/152/782/640/5/1527826405_{secret}_{label}.{extention}",
    "sfomuseum:filename": "43625.tif",
    "sfomuseum:image_index": 5,
    "sfomuseum:placetype": "image",
    "sfomuseum:primary_image": 1,
    "wof:depicts": [
      1511947443
    ],
    "wof:name": "negative: San Francisco International Airport (SFO), construction and maintenance",
    "wof:placetype": "media"
  },
  "geometry": {"coordinates":[-122.386155,37.616358],"type":"Point"}
}
