{
  "type": "Feature",
  "properties": {
    "iso:country": "XX",
    "media:fingerprint": "dde016d67213a9e82cb85222f0cf1e7a78d7aad2",
    "media:imagehash_avg": "a:ffbf8380008080c7",
    "media:imagehash_diff": "d:61696b0f454d0b05",
    "media:medium": "image",
    "media:mimetype": "image/tiff",
    "media:properties": {
      "colours": [
        {
          "hex": "#808080",
          "name": "#808080",
          "reference": "vibrant"
        },
        {
          "hex": "#b8b8b8",
          "name": "#b8b8b8",
          "reference": "vibrant"
        },
        {
          "hex": "#464646",
          "name": "#464646",
          "reference": "vibrant"
        }
      ],
      "sizes": {
        "b": {
          "extension": "jpg",
          "height": 701,
          "mimetype": "image/jpeg",
          "secret": "93mPqo3s8D69kF7tXsrCftmpM3gDIl47",
          "width": 1024
        },
        "c": {
          "extension": "jpg",
          "height": 548,
          "mimetype": "image/jpeg",
          "secret": "93mPqo3s8D69kF7tXsrCftmpM3gDIl47",
          "width": 800
        },
        "dc": {
          "extension": "jpg",
          "height": 548,
          "mimetype": "image/jpeg",
          "secret": "93mPqo3s8D69kF7tXsrCftmpM3gDIl47",
          "width": 800
        },
        "ds": {
          "extension": "jpg",
          "height": 320,
          "mimetype": "image/jpeg",
          "secret": "93mPqo3s8D69kF7tXsrCftmpM3gDIl47",
          "width": 320
        },
        "k": {
          "extension": "jpg",
          "height": 1403,
          "mimetype": "image/jpeg",
          "secret": "93mPqo3s8D69kF7tXsrCftmpM3gDIl47",
          "width": 2048
        },
        "n": {
          "extension": "jpg",
          "height": 219,
          "mimetype": "image/jpeg",
          "secret": "93mPqo3s8D69kF7tXsrCftmpM3gDIl47",
          "width": 320
        },
        "o": {
          "extension": "jpg",
          "height": 6330,
          "mimetype": "image/jpeg",
          "secret": "wnp1afoHzBDvwBXpnMJk2C05H15hW6UB",
          "width": 9239
        },
        "s": {
          "extension": "jpg",
          "height": 320,
          "mimetype": "image/jpeg",
          "secret": "93mPqo3s8D69kF7tXsrCftmpM3gDIl47",
          "width": 320
        },
        "z": {
          "extension": "jpg",
          "height": 438,
          "mimetype": "image/jpeg",
          "secret": "93mPqo3s8D69kF7tXsrCftmpM3gDIl47",
          "width": 640
        }
      }
    },
    "media:uri_template": "https://static.sfomuseum.org/media/152/783/049/5/1527830495_{secret}_{label}.{extention}",
    "sfomuseum:filename": "57601.tif",
    "sfomuseum:image_index": 5,
    "sfomuseum:image_type": "studio",
    "sfomuseum:placetype": "image",
    "sfomuseum:primary_image": 0,
    "wof:depicts": [
      1159284989,
      1511954863,
      1159286839
    ],
    "wof:name": "career history questionnaire: World Wings International, Kathleen (Kathy) Cook Gray",
    "wof:placetype": "custom",
    "wof:placetype_alt": "image"
  },
  "geometry": {"coordinates":[-122.386155,37.616358],"type":"Point"}
}
