{
  "type": "Feature",
  "properties": {
    "iso:country": "XX",
    "media:fingerprint": "f14bb94b98012d749f55d09c1ea80fa3ebdb5f8f",
    "media:imagehash_avg": "a:030303070f0f1f3f",
    "media:imagehash_diff": "d:8b36e6ce9d7ebf64",
    "media:medium": "image",
    "media:mimetype": "image/tiff",
    "media:properties": {
      "colours": [
        {
          "hex": "#808080",
          "name": "#808080",
          "reference": "vibrant"
        }, 
        {
          "hex": "#c0c0c0",
          "name": "#c0c0c0",
          "reference": "vibrant"
        }, 
        {
          "hex": "#404040",
          "name": "#404040",
          "reference": "vibrant"
        }
      ],
      "sizes": {
        "b": {
          "extension": "jpg",
          "height": 768,
          "mimetype": "image/jpeg",
          "secret": "Gd9FEgs1cRGUS2hga2NTQwqMhKlXyYN9",
          "width": 768
        },
        "c": {
          "extension": "jpg",
          "height": 600,
          "mimetype": "image/jpeg",
          "secret": "Gd9FEgs1cRGUS2hga2NTQwqMhKlXyYN9",
          "width": 600
        },
        "dc": {
          "extension": "jpg",
          "height": 600,
          "mimetype": "image/jpeg",
          "secret": "Gd9FEgs1cRGUS2hga2NTQwqMhKlXyYN9",
          "width": 600
        },
        "ds": {
          "extension": "jpg",
          "height": 320,
          "mimetype": "image/jpeg",
          "secret": "Gd9FEgs1cRGUS2hga2NTQwqMhKlXyYN9",
          "width": 320
        },
        "k": {
          "extension": "jpg",
          "height": 1536,
          "mimetype": "image/jpeg",
          "secret": "Gd9FEgs1cRGUS2hga2NTQwqMhKlXyYN9",
          "width": 1536
        },
        "n": {
          "extension": "jpg",
          "height": 239,
          "mimetype": "image/jpeg",
          "secret": "Gd9FEgs1cRGUS2hga2NTQwqMhKlXyYN9",
          "width": 239
        },
        "o": {
          "extension": "jpg",
          "height": 2563,
          "mimetype": "image/jpeg",
          "secret": "CExURVL0SQKgyECngR6AMZ1SJyDTuxqc",
          "width": 2563
        },
        "s": {
          "extension": "jpg",
          "height": 320,
          "mimetype": "image/jpeg",
          "secret": "Gd9FEgs1cRGUS2hga2NTQwqMhKlXyYN9",
          "width": 320
        },
        "z": {
          "extension": "jpg",
          "height": 479,
          "mimetype": "image/jpeg",
          "secret": "Gd9FEgs1cRGUS2hga2NTQwqMhKlXyYN9",
          "width": 479
        }
      }
    },
    "media:uri_template": "https://millsfield.sfomuseum.org/media/152/782/514/7/1527825147_{secret}_{label}.{extention}",
    "sfomuseum:filename": "42985.tif",
    "sfomuseum:image_index": 5,
    "sfomuseum:placetype": "image",
    "sfomuseum:primary_image": 1,
    "wof:depicts": [
      1511946073
    ],
    "wof:name": "negative: San Francisco International Airport (SFO), construction",
    "wof:placetype": "media"
  },
  "geometry": {"coordinates":[-122.386155,37.616358],"type":"Point"}
}
