{
  "type": "Feature",
  "properties": {
    "iso:country": "XX",
    "media:fingerprint": "bd6abe7a6289a6b6a3301e6499367bfeed477f0f",
    "media:imagehash_avg": "a:ffffff3f1f000000",
    "media:imagehash_diff": "d:e6d9f979792b9aef",
    "media:medium": "image",
    "media:mimetype": "image/tiff",
    "media:properties": {
      "colours": [
        {
          "hex": "#808080",
          "name": "#808080",
          "reference": "vibrant"
        }, 
        {
          "hex": "#b6b6b6",
          "name": "#b6b6b6",
          "reference": "vibrant"
        }, 
        {
          "hex": "#484848",
          "name": "#484848",
          "reference": "vibrant"
        }
      ],
      "sizes": {
        "b": {
          "extension": "jpg",
          "height": 768,
          "mimetype": "image/jpeg",
          "secret": "HESxBmf34XWs37YPOA6eDhcuS3IYd4s5",
          "width": 980
        },
        "c": {
          "extension": "jpg",
          "height": 600,
          "mimetype": "image/jpeg",
          "secret": "HESxBmf34XWs37YPOA6eDhcuS3IYd4s5",
          "width": 766
        },
        "dc": {
          "extension": "jpg",
          "height": 600,
          "mimetype": "image/jpeg",
          "secret": "HESxBmf34XWs37YPOA6eDhcuS3IYd4s5",
          "width": 766
        },
        "ds": {
          "extension": "jpg",
          "height": 320,
          "mimetype": "image/jpeg",
          "secret": "HESxBmf34XWs37YPOA6eDhcuS3IYd4s5",
          "width": 320
        },
        "k": {
          "extension": "jpg",
          "height": 1536,
          "mimetype": "image/jpeg",
          "secret": "HESxBmf34XWs37YPOA6eDhcuS3IYd4s5",
          "width": 1961
        },
        "n": {
          "extension": "jpg",
          "height": 240,
          "mimetype": "image/jpeg",
          "secret": "HESxBmf34XWs37YPOA6eDhcuS3IYd4s5",
          "width": 306
        },
        "o": {
          "extension": "jpg",
          "height": 2168,
          "mimetype": "image/jpeg",
          "secret": "M0rEUdBjhQyw4aZIoAfyfranJz8JlSYB",
          "width": 2768
        },
        "s": {
          "extension": "jpg",
          "height": 320,
          "mimetype": "image/jpeg",
          "secret": "HESxBmf34XWs37YPOA6eDhcuS3IYd4s5",
          "width": 320
        },
        "z": {
          "extension": "jpg",
          "height": 480,
          "mimetype": "image/jpeg",
          "secret": "HESxBmf34XWs37YPOA6eDhcuS3IYd4s5",
          "width": 612
        }
      }
    },
    "media:uri_template": "https://millsfield.sfomuseum.org/media/152/782/554/3/1527825543_{secret}_{label}.{extention}",
    "sfomuseum:filename": "43201.tif",
    "sfomuseum:image_index": 5,
    "sfomuseum:placetype": "image",
    "sfomuseum:primary_image": 1,
    "wof:depicts": [
      1511946581
    ],
    "wof:name": "negative: San Francisco International Airport (SFO), presentation of airport master plan",
    "wof:placetype": "media"
  },
  "geometry": {"coordinates":[-122.386155,37.616358],"type":"Point"}
}
