{
  "type": "Feature",
  "properties": {
    "iso:country": "XX",
    "media:fingerprint": "9b7444d4c35df28b53a7ceb4febbcea758671f68",
    "media:imagehash_avg": "a:fcffff3818000000",
    "media:imagehash_diff": "d:e8494d68e8e8a928",
    "media:medium": "image",
    "media:mimetype": "image/tiff",
    "media:properties": {
      "colours": [
        {
          "hex": "#808080",
          "name": "#808080",
          "reference": "vibrant"
        }, 
        {
          "hex": "#c0c0c0",
          "name": "#c0c0c0",
          "reference": "vibrant"
        }, 
        {
          "hex": "#484848",
          "name": "#484848",
          "reference": "vibrant"
        }
      ],
      "sizes": {
        "b": {
          "extension": "jpg",
          "height": 767,
          "mimetype": "image/jpeg",
          "secret": "4HzrYRMSfciVjZD5KhCOyM3z9Oh0Hip8",
          "width": 978
        },
        "c": {
          "extension": "jpg",
          "height": 600,
          "mimetype": "image/jpeg",
          "secret": "4HzrYRMSfciVjZD5KhCOyM3z9Oh0Hip8",
          "width": 764
        },
        "dc": {
          "extension": "jpg",
          "height": 600,
          "mimetype": "image/jpeg",
          "secret": "4HzrYRMSfciVjZD5KhCOyM3z9Oh0Hip8",
          "width": 764
        },
        "ds": {
          "extension": "jpg",
          "height": 320,
          "mimetype": "image/jpeg",
          "secret": "4HzrYRMSfciVjZD5KhCOyM3z9Oh0Hip8",
          "width": 320
        },
        "k": {
          "extension": "jpg",
          "height": 1535,
          "mimetype": "image/jpeg",
          "secret": "4HzrYRMSfciVjZD5KhCOyM3z9Oh0Hip8",
          "width": 1957
        },
        "n": {
          "extension": "jpg",
          "height": 240,
          "mimetype": "image/jpeg",
          "secret": "4HzrYRMSfciVjZD5KhCOyM3z9Oh0Hip8",
          "width": 305
        },
        "o": {
          "extension": "jpg",
          "height": 2140,
          "mimetype": "image/jpeg",
          "secret": "rvb9eLvJLpkjBHFqRF9IfqOiYODMmGro",
          "width": 2727
        },
        "s": {
          "extension": "jpg",
          "height": 320,
          "mimetype": "image/jpeg",
          "secret": "4HzrYRMSfciVjZD5KhCOyM3z9Oh0Hip8",
          "width": 320
        },
        "z": {
          "extension": "jpg",
          "height": 480,
          "mimetype": "image/jpeg",
          "secret": "4HzrYRMSfciVjZD5KhCOyM3z9Oh0Hip8",
          "width": 611
        }
      }
    },
    "media:uri_template": "https://millsfield.sfomuseum.org/media/152/782/505/3/1527825053_{secret}_{label}.{extention}",
    "sfomuseum:filename": "42943.tif",
    "sfomuseum:image_index": 5,
    "sfomuseum:placetype": "image",
    "sfomuseum:primary_image": 1,
    "wof:depicts": [
      1511945961
    ],
    "wof:name": "negative: San Francisco International Airport (SFO), South Terminal interior, parking garage construction",
    "wof:placetype": "media"
  },
  "geometry": {"coordinates":[-122.386155,37.616358],"type":"Point"}
}
