{
  "type": "Feature",
  "properties": {
    "iso:country": "XX",
    "media:fingerprint": "ed3eeb4088cf746f39a759b0d361d5eb5834aa7e",
    "media:imagehash_avg": "a:fffffe15060000c0",
    "media:imagehash_diff": "d:631160e97ce86219",
    "media:medium": "image",
    "media:mimetype": "image/tiff",
    "media:properties": {
      "colours": [
        {
          "hex": "#808080",
          "name": "#808080",
          "reference": "vibrant"
        }, 
        {
          "hex": "#b8b8b8",
          "name": "#b8b8b8",
          "reference": "vibrant"
        }, 
        {
          "hex": "#484848",
          "name": "#484848",
          "reference": "vibrant"
        }
      ],
      "sizes": {
        "b": {
          "extension": "jpg",
          "height": 768,
          "mimetype": "image/jpeg",
          "secret": "jEtentxYvuFiz6glfXmpBmqlG5u4U1oy",
          "width": 976
        },
        "c": {
          "extension": "jpg",
          "height": 600,
          "mimetype": "image/jpeg",
          "secret": "jEtentxYvuFiz6glfXmpBmqlG5u4U1oy",
          "width": 763
        },
        "dc": {
          "extension": "jpg",
          "height": 600,
          "mimetype": "image/jpeg",
          "secret": "jEtentxYvuFiz6glfXmpBmqlG5u4U1oy",
          "width": 763
        },
        "ds": {
          "extension": "jpg",
          "height": 320,
          "mimetype": "image/jpeg",
          "secret": "jEtentxYvuFiz6glfXmpBmqlG5u4U1oy",
          "width": 320
        },
        "k": {
          "extension": "jpg",
          "height": 1536,
          "mimetype": "image/jpeg",
          "secret": "jEtentxYvuFiz6glfXmpBmqlG5u4U1oy",
          "width": 1953
        },
        "n": {
          "extension": "jpg",
          "height": 240,
          "mimetype": "image/jpeg",
          "secret": "jEtentxYvuFiz6glfXmpBmqlG5u4U1oy",
          "width": 305
        },
        "o": {
          "extension": "jpg",
          "height": 2154,
          "mimetype": "image/jpeg",
          "secret": "xAEyrBykvUyvHNA0IRVgjMXWmEOWfn8O",
          "width": 2740
        },
        "s": {
          "extension": "jpg",
          "height": 320,
          "mimetype": "image/jpeg",
          "secret": "jEtentxYvuFiz6glfXmpBmqlG5u4U1oy",
          "width": 320
        },
        "z": {
          "extension": "jpg",
          "height": 480,
          "mimetype": "image/jpeg",
          "secret": "jEtentxYvuFiz6glfXmpBmqlG5u4U1oy",
          "width": 610
        }
      }
    },
    "media:uri_template": "https://millsfield.sfomuseum.org/media/152/782/240/3/1527822403_{secret}_{label}.{extention}",
    "sfomuseum:filename": "40730.tif",
    "sfomuseum:image_index": 5,
    "sfomuseum:placetype": "image",
    "sfomuseum:primary_image": 1,
    "wof:depicts": [
      1511944309
    ],
    "wof:name": "negative: San Francisco International Airport (SFO), Pier B exterior",
    "wof:placetype": "media"
  },
  "geometry": {"coordinates":[-122.386155,37.616358],"type":"Point"}
}
