{
  "type": "Feature",
  "properties": {
    "iso:country": "XX",
    "media:fingerprint": "4f72a7a69263a1ed3a63a45e337b42713f676475",
    "media:imagehash_avg": "a:ff080809090f3fff",
    "media:imagehash_diff": "d:71717171797f6f6f",
    "media:medium": "image",
    "media:mimetype": "image/tiff",
    "media:properties": {
      "colours": [
        {
          "hex": "#eae4c8",
          "name": "#eae4c8",
          "reference": "vibrant"
        },
        {
          "hex": "#534727",
          "name": "#534727",
          "reference": "vibrant"
        },
        {
          "hex": "#a7965c",
          "name": "#a7965c",
          "reference": "vibrant"
        },
        {
          "hex": "#d1c8b0",
          "name": "#d1c8b0",
          "reference": "vibrant"
        },
        {
          "hex": "#63562f",
          "name": "#63562f",
          "reference": "vibrant"
        }
      ],
      "sizes": {
        "b": {
          "extension": "jpg",
          "height": 736,
          "mimetype": "image/jpeg",
          "secret": "31D85veMsmpBD691fLjB6x9yOIgEb71Y",
          "width": 1024
        },
        "c": {
          "extension": "jpg",
          "height": 575,
          "mimetype": "image/jpeg",
          "secret": "31D85veMsmpBD691fLjB6x9yOIgEb71Y",
          "width": 800
        },
        "dc": {
          "extension": "jpg",
          "height": 575,
          "mimetype": "image/jpeg",
          "secret": "31D85veMsmpBD691fLjB6x9yOIgEb71Y",
          "width": 800
        },
        "ds": {
          "extension": "jpg",
          "height": 320,
          "mimetype": "image/jpeg",
          "secret": "31D85veMsmpBD691fLjB6x9yOIgEb71Y",
          "width": 320
        },
        "k": {
          "extension": "jpg",
          "height": 1473,
          "mimetype": "image/jpeg",
          "secret": "31D85veMsmpBD691fLjB6x9yOIgEb71Y",
          "width": 2048
        },
        "n": {
          "extension": "jpg",
          "height": 230,
          "mimetype": "image/jpeg",
          "secret": "31D85veMsmpBD691fLjB6x9yOIgEb71Y",
          "width": 320
        },
        "o": {
          "extension": "jpg",
          "height": 1839,
          "mimetype": "image/jpeg",
          "secret": "jXiZQEHbTFKXFj6tyh4PsTBMRItyTqUy",
          "width": 2556
        },
        "s": {
          "extension": "jpg",
          "height": 320,
          "mimetype": "image/jpeg",
          "secret": "31D85veMsmpBD691fLjB6x9yOIgEb71Y",
          "width": 320
        },
        "z": {
          "extension": "jpg",
          "height": 460,
          "mimetype": "image/jpeg",
          "secret": "31D85veMsmpBD691fLjB6x9yOIgEb71Y",
          "width": 640
        }
      }
    },
    "media:uri_template": "https://static.sfomuseum.org/media/152/785/579/7/1527855797_{secret}_{label}.{extention}",
    "sfomuseum:filename": "100452.tif",
    "sfomuseum:image_index": 5,
    "sfomuseum:image_type": "studio",
    "sfomuseum:placetype": "image",
    "sfomuseum:primary_image": 1,
    "wof:depicts": [
      1511942641
    ],
    "wof:name": "photograph: San Francisco Bay Area aerial, Mount Tamalpais",
    "wof:placetype": "custom",
    "wof:placetype_alt": "image"
  },
  "geometry": {"coordinates":[-122.386155,37.616358],"type":"Point"}
}
