{
  "type": "Feature",
  "properties": {
    "iso:country": "XX",
    "media:fingerprint": "278ac37800f9226954e927d57b82262268b91969",
    "media:imagehash_avg": "a:8344c8b1c081e3ff",
    "media:imagehash_diff": "d:378c935707074f0c",
    "media:medium": "image",
    "media:mimetype": "image/tiff",
    "media:properties": {
      "colours": [
        {
          "hex": "#808080",
          "name": "#808080",
          "reference": "vibrant"
        }, 
        {
          "hex": "#b8b8b8",
          "name": "#b8b8b8",
          "reference": "vibrant"
        }, 
        {
          "hex": "#484848",
          "name": "#484848",
          "reference": "vibrant"
        }
      ],
      "sizes": {
        "b": {
          "extension": "jpg",
          "height": 768,
          "mimetype": "image/jpeg",
          "secret": "qAMjYf9t7V7qv7ht5tIqPBdLW0q8IHZ0",
          "width": 768
        },
        "c": {
          "extension": "jpg",
          "height": 600,
          "mimetype": "image/jpeg",
          "secret": "qAMjYf9t7V7qv7ht5tIqPBdLW0q8IHZ0",
          "width": 600
        },
        "dc": {
          "extension": "jpg",
          "height": 600,
          "mimetype": "image/jpeg",
          "secret": "qAMjYf9t7V7qv7ht5tIqPBdLW0q8IHZ0",
          "width": 600
        },
        "ds": {
          "extension": "jpg",
          "height": 320,
          "mimetype": "image/jpeg",
          "secret": "qAMjYf9t7V7qv7ht5tIqPBdLW0q8IHZ0",
          "width": 320
        },
        "k": {
          "extension": "jpg",
          "height": 1536,
          "mimetype": "image/jpeg",
          "secret": "qAMjYf9t7V7qv7ht5tIqPBdLW0q8IHZ0",
          "width": 1536
        },
        "n": {
          "extension": "jpg",
          "height": 240,
          "mimetype": "image/jpeg",
          "secret": "qAMjYf9t7V7qv7ht5tIqPBdLW0q8IHZ0",
          "width": 240
        },
        "o": {
          "extension": "jpg",
          "height": 2536,
          "mimetype": "image/jpeg",
          "secret": "imDX0W2eoOYcSJuGxyWnsL6Q3BNmoSiZ",
          "width": 2536
        },
        "s": {
          "extension": "jpg",
          "height": 320,
          "mimetype": "image/jpeg",
          "secret": "qAMjYf9t7V7qv7ht5tIqPBdLW0q8IHZ0",
          "width": 320
        },
        "z": {
          "extension": "jpg",
          "height": 480,
          "mimetype": "image/jpeg",
          "secret": "qAMjYf9t7V7qv7ht5tIqPBdLW0q8IHZ0",
          "width": 480
        }
      }
    },
    "media:uri_template": "https://millsfield.sfomuseum.org/media/152/782/806/7/1527828067_{secret}_{label}.{extention}",
    "sfomuseum:filename": "44367.tif",
    "sfomuseum:image_index": 5,
    "sfomuseum:placetype": "image",
    "sfomuseum:primary_image": 1,
    "wof:depicts": [
      1511949101
    ],
    "wof:name": "negative: San Francisco International Airport (SFO), damaged roof vent",
    "wof:placetype": "media"
  },
  "geometry": {"coordinates":[-122.386155,37.616358],"type":"Point"}
}
