{
  "type": "Feature",
  "properties": {
    "iso:country": "XX",
    "media:fingerprint": "f70286a64f822d70031a77b51f1e2bc1268bab54",
    "media:imagehash_avg": "a:ffffffff818000c1",
    "media:imagehash_diff": "d:2961617171610909",
    "media:medium": "image",
    "media:mimetype": "image/tiff",
    "media:properties": {
      "colours": [
        {
          "hex": "#e5d8bd",
          "name": "#e5d8bd",
          "reference": "vibrant"
        },
        {
          "hex": "#362f15",
          "name": "#362f15",
          "reference": "vibrant"
        },
        {
          "hex": "#928d72",
          "name": "#928d72",
          "reference": "vibrant"
        },
        {
          "hex": "#d0c2a5",
          "name": "#d0c2a5",
          "reference": "vibrant"
        },
        {
          "hex": "#575437",
          "name": "#575437",
          "reference": "vibrant"
        }
      ],
      "sizes": {
        "b": {
          "extension": "jpg",
          "height": 768,
          "mimetype": "image/jpeg",
          "secret": "W2YmMjTOhiKclVy5MaOqfI2Y738Dq2Jj",
          "width": 994
        },
        "c": {
          "extension": "jpg",
          "height": 600,
          "mimetype": "image/jpeg",
          "secret": "W2YmMjTOhiKclVy5MaOqfI2Y738Dq2Jj",
          "width": 777
        },
        "dc": {
          "extension": "jpg",
          "height": 600,
          "mimetype": "image/jpeg",
          "secret": "W2YmMjTOhiKclVy5MaOqfI2Y738Dq2Jj",
          "width": 777
        },
        "ds": {
          "extension": "jpg",
          "height": 320,
          "mimetype": "image/jpeg",
          "secret": "W2YmMjTOhiKclVy5MaOqfI2Y738Dq2Jj",
          "width": 320
        },
        "k": {
          "extension": "jpg",
          "height": 1536,
          "mimetype": "image/jpeg",
          "secret": "W2YmMjTOhiKclVy5MaOqfI2Y738Dq2Jj",
          "width": 1989
        },
        "n": {
          "extension": "jpg",
          "height": 240,
          "mimetype": "image/jpeg",
          "secret": "W2YmMjTOhiKclVy5MaOqfI2Y738Dq2Jj",
          "width": 310
        },
        "o": {
          "extension": "jpg",
          "height": 2076,
          "mimetype": "image/jpeg",
          "secret": "wowIv4e09h9ofDUKgARsBA14fIQSHIUJ",
          "width": 2689
        },
        "s": {
          "extension": "jpg",
          "height": 320,
          "mimetype": "image/jpeg",
          "secret": "W2YmMjTOhiKclVy5MaOqfI2Y738Dq2Jj",
          "width": 320
        },
        "z": {
          "extension": "jpg",
          "height": 480,
          "mimetype": "image/jpeg",
          "secret": "W2YmMjTOhiKclVy5MaOqfI2Y738Dq2Jj",
          "width": 621
        }
      }
    },
    "media:uri_template": "https://static.sfomuseum.org/media/152/785/605/1/1527856051_{secret}_{label}.{extention}",
    "sfomuseum:filename": "100568.tif",
    "sfomuseum:image_index": 5,
    "sfomuseum:image_type": "studio",
    "sfomuseum:placetype": "image",
    "sfomuseum:primary_image": 1,
    "wof:depicts": [
      1511942917
    ],
    "wof:name": "photograph: San Francisco Bay Area aerial, fleet of ships in Bay",
    "wof:placetype": "custom",
    "wof:placetype_alt": "image"
  },
  "geometry": {"coordinates":[-122.386155,37.616358],"type":"Point"}
}
