{
  "type": "Feature",
  "properties": {
    "iso:country": "XX",
    "media:fingerprint": "df12aeae1f2e05f223ad2f16930805e3dbb39019",
    "media:imagehash_avg": "a:00fffef0e0c0d8c0",
    "media:imagehash_diff": "d:2e0650810202300c",
    "media:medium": "image",
    "media:mimetype": "image/tiff",
    "media:properties": {
      "colours": [
        {
          "hex": "#787878",
          "name": "#787878",
          "reference": "vibrant"
        }, 
        {
          "hex": "#b8b8b8",
          "name": "#b8b8b8",
          "reference": "vibrant"
        }, 
        {
          "hex": "#464646",
          "name": "#464646",
          "reference": "vibrant"
        }
      ],
      "sizes": {
        "b": {
          "extension": "jpg",
          "height": 768,
          "mimetype": "image/jpeg",
          "secret": "ERQDiNE3nxRTZwYFhdoQf9g4EmP81qtU",
          "width": 768
        },
        "c": {
          "extension": "jpg",
          "height": 600,
          "mimetype": "image/jpeg",
          "secret": "ERQDiNE3nxRTZwYFhdoQf9g4EmP81qtU",
          "width": 600
        },
        "dc": {
          "extension": "jpg",
          "height": 600,
          "mimetype": "image/jpeg",
          "secret": "ERQDiNE3nxRTZwYFhdoQf9g4EmP81qtU",
          "width": 600
        },
        "ds": {
          "extension": "jpg",
          "height": 320,
          "mimetype": "image/jpeg",
          "secret": "ERQDiNE3nxRTZwYFhdoQf9g4EmP81qtU",
          "width": 320
        },
        "k": {
          "extension": "jpg",
          "height": 1536,
          "mimetype": "image/jpeg",
          "secret": "ERQDiNE3nxRTZwYFhdoQf9g4EmP81qtU",
          "width": 1536
        },
        "n": {
          "extension": "jpg",
          "height": 240,
          "mimetype": "image/jpeg",
          "secret": "ERQDiNE3nxRTZwYFhdoQf9g4EmP81qtU",
          "width": 240
        },
        "o": {
          "extension": "jpg",
          "height": 2536,
          "mimetype": "image/jpeg",
          "secret": "pHTLA8u9CvfBkYWnw8knrWwZVze0JpP5",
          "width": 2536
        },
        "s": {
          "extension": "jpg",
          "height": 320,
          "mimetype": "image/jpeg",
          "secret": "ERQDiNE3nxRTZwYFhdoQf9g4EmP81qtU",
          "width": 320
        },
        "z": {
          "extension": "jpg",
          "height": 480,
          "mimetype": "image/jpeg",
          "secret": "ERQDiNE3nxRTZwYFhdoQf9g4EmP81qtU",
          "width": 480
        }
      }
    },
    "media:uri_template": "https://millsfield.sfomuseum.org/media/152/782/703/7/1527827037_{secret}_{label}.{extention}",
    "sfomuseum:filename": "43908.tif",
    "sfomuseum:image_index": 5,
    "sfomuseum:placetype": "image",
    "sfomuseum:primary_image": 1,
    "wof:depicts": [
      1511948075
    ],
    "wof:name": "negative: San Francisco International Airport (SFO), Pan American World Airways, Clipper Cargo building",
    "wof:placetype": "media"
  },
  "geometry": {"coordinates":[-122.386155,37.616358],"type":"Point"}
}
