{
  "type": "Feature",
  "properties": {
    "iso:country": "XX",
    "media:fingerprint": "98d0e908fc75a1f0f38de61a49aa22a72e23b795",
    "media:imagehash_avg": "a:030f3ffff4440400",
    "media:imagehash_diff": "d:4f7b7dc5c58d898c",
    "media:medium": "image",
    "media:mimetype": "image/tiff",
    "media:properties": {
      "colours": [
        {
          "hex": "#868686",
          "name": "#868686",
          "reference": "vibrant"
        }, 
        {
          "hex": "#c0c0c0",
          "name": "#c0c0c0",
          "reference": "vibrant"
        }, 
        {
          "hex": "#404040",
          "name": "#404040",
          "reference": "vibrant"
        }
      ],
      "sizes": {
        "b": {
          "extension": "jpg",
          "height": 768,
          "mimetype": "image/jpeg",
          "secret": "zu9AgK8zpa2qkBKb979mOvtaA2dlA3Is",
          "width": 793
        },
        "c": {
          "extension": "jpg",
          "height": 600,
          "mimetype": "image/jpeg",
          "secret": "zu9AgK8zpa2qkBKb979mOvtaA2dlA3Is",
          "width": 619
        },
        "dc": {
          "extension": "jpg",
          "height": 600,
          "mimetype": "image/jpeg",
          "secret": "zu9AgK8zpa2qkBKb979mOvtaA2dlA3Is",
          "width": 619
        },
        "ds": {
          "extension": "jpg",
          "height": 320,
          "mimetype": "image/jpeg",
          "secret": "zu9AgK8zpa2qkBKb979mOvtaA2dlA3Is",
          "width": 320
        },
        "k": {
          "extension": "jpg",
          "height": 1536,
          "mimetype": "image/jpeg",
          "secret": "zu9AgK8zpa2qkBKb979mOvtaA2dlA3Is",
          "width": 1586
        },
        "n": {
          "extension": "jpg",
          "height": 240,
          "mimetype": "image/jpeg",
          "secret": "zu9AgK8zpa2qkBKb979mOvtaA2dlA3Is",
          "width": 247
        },
        "o": {
          "extension": "jpg",
          "height": 2481,
          "mimetype": "image/jpeg",
          "secret": "pFWTtEmt6yrSuUj3AliZVFeMuhYA90wz",
          "width": 2563
        },
        "s": {
          "extension": "jpg",
          "height": 320,
          "mimetype": "image/jpeg",
          "secret": "zu9AgK8zpa2qkBKb979mOvtaA2dlA3Is",
          "width": 320
        },
        "z": {
          "extension": "jpg",
          "height": 480,
          "mimetype": "image/jpeg",
          "secret": "zu9AgK8zpa2qkBKb979mOvtaA2dlA3Is",
          "width": 495
        }
      }
    },
    "media:uri_template": "https://millsfield.sfomuseum.org/media/152/782/664/7/1527826647_{secret}_{label}.{extention}",
    "sfomuseum:filename": "43734.tif",
    "sfomuseum:image_index": 5,
    "sfomuseum:placetype": "image",
    "sfomuseum:primary_image": 1,
    "wof:depicts": [
      1511947687
    ],
    "wof:name": "negative: San Francisco International Airport (SFO), reception for airport operations personnel",
    "wof:placetype": "media"
  },
  "geometry": {"coordinates":[-122.386155,37.616358],"type":"Point"}
}
