{
  "type": "Feature",
  "properties": {
    "iso:country": "XX",
    "media:fingerprint": "6bbe558cb1c61cda8408420d4acdf0257252d98a",
    "media:imagehash_avg": "a:007777772f7f7f73",
    "media:imagehash_diff": "d:fdd4e7cfceaec68b",
    "media:medium": "image",
    "media:mimetype": "image/tiff",
    "media:properties": {
      "colours": [
        {
          "hex": "#c89355",
          "name": "#c89355",
          "reference": "vibrant"
        }, 
        {
          "hex": "#e5c08c",
          "name": "#e5c08c",
          "reference": "vibrant"
        }, 
        {
          "hex": "#af8556",
          "name": "#af8556",
          "reference": "vibrant"
        }, 
        {
          "hex": "#c6c3b4",
          "name": "#c6c3b4",
          "reference": "vibrant"
        }, 
        {
          "hex": "#403e3a",
          "name": "#403e3a",
          "reference": "vibrant"
        }
      ],
      "sizes": {
        "b": {
          "extension": "jpg",
          "height": 768,
          "mimetype": "image/jpeg",
          "secret": "SoqUtFwICGfMZa70dk1UnRYSMTldDBIO",
          "width": 422
        },
        "c": {
          "extension": "jpg",
          "height": 600,
          "mimetype": "image/jpeg",
          "secret": "SoqUtFwICGfMZa70dk1UnRYSMTldDBIO",
          "width": 330
        },
        "dc": {
          "extension": "jpg",
          "height": 600,
          "mimetype": "image/jpeg",
          "secret": "SoqUtFwICGfMZa70dk1UnRYSMTldDBIO",
          "width": 330
        },
        "ds": {
          "extension": "jpg",
          "height": 320,
          "mimetype": "image/jpeg",
          "secret": "SoqUtFwICGfMZa70dk1UnRYSMTldDBIO",
          "width": 320
        },
        "k": {
          "extension": "jpg",
          "height": 1536,
          "mimetype": "image/jpeg",
          "secret": "SoqUtFwICGfMZa70dk1UnRYSMTldDBIO",
          "width": 845
        },
        "n": {
          "extension": "jpg",
          "height": 240,
          "mimetype": "image/jpeg",
          "secret": "SoqUtFwICGfMZa70dk1UnRYSMTldDBIO",
          "width": 132
        },
        "o": {
          "extension": "jpg",
          "height": 2748,
          "mimetype": "image/jpeg",
          "secret": "BVETLNRp5Y0bgvxq8GQre19JfviZKkcd",
          "width": 1512
        },
        "s": {
          "extension": "jpg",
          "height": 320,
          "mimetype": "image/jpeg",
          "secret": "SoqUtFwICGfMZa70dk1UnRYSMTldDBIO",
          "width": 320
        },
        "z": {
          "extension": "jpg",
          "height": 480,
          "mimetype": "image/jpeg",
          "secret": "SoqUtFwICGfMZa70dk1UnRYSMTldDBIO",
          "width": 264
        }
      }
    },
    "media:uri_template": "https://millsfield.sfomuseum.org/media/152/782/348/9/1527823489_{secret}_{label}.{extention}",
    "sfomuseum:filename": "41609.tif",
    "sfomuseum:image_index": 5,
    "sfomuseum:placetype": "image",
    "sfomuseum:primary_image": 0,
    "wof:depicts": [
      1511908409
    ],
    "wof:name": "airsickness bag: Air UK",
    "wof:placetype": "media"
  },
  "geometry": {"coordinates":[-122.386155,37.616358],"type":"Point"}
}
