{
  "type": "Feature",
  "properties": {
    "iso:country": "XX",
    "media:fingerprint": "73ef165ee05a5545ba59e5f698a151297ad7cdc6",
    "media:imagehash_avg": "a:7f7f414343776307",
    "media:imagehash_diff": "d:e5ab8b8f9fef8fcf",
    "media:medium": "image",
    "media:mimetype": "image/tiff",
    "media:properties": {
      "colours": [
        {
          "hex": "#6d7280",
          "name": "#6d7280",
          "reference": "vibrant"
        }, 
        {
          "hex": "#c7bfb9",
          "name": "#c7bfb9",
          "reference": "vibrant"
        }, 
        {
          "hex": "#383d4d",
          "name": "#383d4d",
          "reference": "vibrant"
        }
      ],
      "sizes": {
        "b": {
          "extension": "jpg",
          "height": 768,
          "mimetype": "image/jpeg",
          "secret": "gAUWHpMHcleCs10dM7xhv9zNWsEBcgQL",
          "width": 351
        },
        "c": {
          "extension": "jpg",
          "height": 600,
          "mimetype": "image/jpeg",
          "secret": "gAUWHpMHcleCs10dM7xhv9zNWsEBcgQL",
          "width": 274
        },
        "dc": {
          "extension": "jpg",
          "height": 600,
          "mimetype": "image/jpeg",
          "secret": "gAUWHpMHcleCs10dM7xhv9zNWsEBcgQL",
          "width": 274
        },
        "ds": {
          "extension": "jpg",
          "height": 320,
          "mimetype": "image/jpeg",
          "secret": "gAUWHpMHcleCs10dM7xhv9zNWsEBcgQL",
          "width": 320
        },
        "k": {
          "extension": "jpg",
          "height": 1536,
          "mimetype": "image/jpeg",
          "secret": "gAUWHpMHcleCs10dM7xhv9zNWsEBcgQL",
          "width": 702
        },
        "n": {
          "extension": "jpg",
          "height": 240,
          "mimetype": "image/jpeg",
          "secret": "gAUWHpMHcleCs10dM7xhv9zNWsEBcgQL",
          "width": 109
        },
        "o": {
          "extension": "jpg",
          "height": 3462,
          "mimetype": "image/jpeg",
          "secret": "zDiYftTXv624qBh641VMY1qtkU2DIrOQ",
          "width": 1583
        },
        "s": {
          "extension": "jpg",
          "height": 320,
          "mimetype": "image/jpeg",
          "secret": "gAUWHpMHcleCs10dM7xhv9zNWsEBcgQL",
          "width": 320
        },
        "z": {
          "extension": "jpg",
          "height": 480,
          "mimetype": "image/jpeg",
          "secret": "gAUWHpMHcleCs10dM7xhv9zNWsEBcgQL",
          "width": 219
        }
      }
    },
    "media:uri_template": "https://millsfield.sfomuseum.org/media/152/782/448/5/1527824485_{secret}_{label}.{extention}",
    "sfomuseum:filename": "42590.tif",
    "sfomuseum:image_index": 5,
    "sfomuseum:placetype": "image",
    "sfomuseum:primary_image": 1,
    "wof:depicts": [
      1511908661
    ],
    "wof:name": "airsickness bag: Korean Air Lines",
    "wof:placetype": "media"
  },
  "geometry": {"coordinates":[-122.386155,37.616358],"type":"Point"}
}
