{
  "type": "Feature",
  "properties": {
    "iso:country": "XX",
    "media:fingerprint": "f98212211c57522ffea0124a033b8484d7cb7775",
    "media:imagehash_avg": "a:fffffffb67020000",
    "media:imagehash_diff": "d:82f2c2e7c60e8383",
    "media:medium": "image",
    "media:mimetype": "image/tiff",
    "media:properties": {
      "colours": [
        {
          "hex": "#858585",
          "name": "#858585",
          "reference": "vibrant"
        },
        {
          "hex": "#b6b6b6",
          "name": "#b6b6b6",
          "reference": "vibrant"
        },
        {
          "hex": "#404040",
          "name": "#404040",
          "reference": "vibrant"
        }
      ],
      "sizes": {
        "b": {
          "extension": "jpg",
          "height": 768,
          "mimetype": "image/jpeg",
          "secret": "uiUL8VOVmAY5poYrak5JqsJZnxqYXjEi",
          "width": 967
        },
        "c": {
          "extension": "jpg",
          "height": 600,
          "mimetype": "image/jpeg",
          "secret": "uiUL8VOVmAY5poYrak5JqsJZnxqYXjEi",
          "width": 755
        },
        "dc": {
          "extension": "jpg",
          "height": 600,
          "mimetype": "image/jpeg",
          "secret": "uiUL8VOVmAY5poYrak5JqsJZnxqYXjEi",
          "width": 755
        },
        "ds": {
          "extension": "jpg",
          "height": 320,
          "mimetype": "image/jpeg",
          "secret": "uiUL8VOVmAY5poYrak5JqsJZnxqYXjEi",
          "width": 320
        },
        "k": {
          "extension": "jpg",
          "height": 1536,
          "mimetype": "image/jpeg",
          "secret": "uiUL8VOVmAY5poYrak5JqsJZnxqYXjEi",
          "width": 1934
        },
        "n": {
          "extension": "jpg",
          "height": 240,
          "mimetype": "image/jpeg",
          "secret": "uiUL8VOVmAY5poYrak5JqsJZnxqYXjEi",
          "width": 302
        },
        "o": {
          "extension": "jpg",
          "height": 1665,
          "mimetype": "image/jpeg",
          "secret": "AtB3tobP85NnKzlySbW8FMYNRkF2znuo",
          "width": 2097
        },
        "s": {
          "extension": "jpg",
          "height": 320,
          "mimetype": "image/jpeg",
          "secret": "uiUL8VOVmAY5poYrak5JqsJZnxqYXjEi",
          "width": 320
        },
        "z": {
          "extension": "jpg",
          "height": 480,
          "mimetype": "image/jpeg",
          "secret": "uiUL8VOVmAY5poYrak5JqsJZnxqYXjEi",
          "width": 604
        }
      }
    },
    "media:uri_template": "https://static.sfomuseum.org/media/152/783/132/5/1527831325_{secret}_{label}.{extention}",
    "sfomuseum:filename": "58339.tif",
    "sfomuseum:image_index": 5,
    "sfomuseum:image_type": "studio",
    "sfomuseum:placetype": "image",
    "sfomuseum:primary_image": 1,
    "wof:depicts": [
      1511955593
    ],
    "wof:name": "glass negative: Panama-Pacific International Exposition, Silvio Pettirossi",
    "wof:placetype": "custom",
    "wof:placetype_alt": "image"
  },
  "geometry": {"coordinates":[-122.386155,37.616358],"type":"Point"}
}
