{
  "type": "Feature",
  "properties": {
    "iso:country": "US",
    "media:fingerprint": "d2dc94b704e6642b090d2028c8f776b92a54b552",
    "media:imagehash_avg": "a:f3f18187d0df9fdf",
    "media:imagehash_diff": "d:0703133531353a39",
    "media:medium": "image",
    "media:mimetype": "image/tiff",
    "media:properties": {
      "colours": [
        {
          "hex": "#a8444a",
          "name": "#a8444a",
          "reference": "vibrant"
        }, 
        {
          "hex": "#d3bb96",
          "name": "#d3bb96",
          "reference": "vibrant"
        }, 
        {
          "hex": "#810e08",
          "name": "#810e08",
          "reference": "vibrant"
        }, 
        {
          "hex": "#9d7161",
          "name": "#9d7161",
          "reference": "vibrant"
        }, 
        {
          "hex": "#d8c7a8",
          "name": "#d8c7a8",
          "reference": "vibrant"
        }
      ],
      "sizes": {
        "b": {
          "extension": "jpg",
          "height": 577,
          "mimetype": "image/jpeg",
          "secret": "i5ad6X15KbIC9xZjGNOPKBK2qzhQ7NsN",
          "width": 1024
        },
        "c": {
          "extension": "jpg",
          "height": 451,
          "mimetype": "image/jpeg",
          "secret": "i5ad6X15KbIC9xZjGNOPKBK2qzhQ7NsN",
          "width": 800
        },
        "dc": {
          "extension": "jpg",
          "height": 451,
          "mimetype": "image/jpeg",
          "secret": "i5ad6X15KbIC9xZjGNOPKBK2qzhQ7NsN",
          "width": 800
        },
        "ds": {
          "extension": "jpg",
          "height": 320,
          "mimetype": "image/jpeg",
          "secret": "i5ad6X15KbIC9xZjGNOPKBK2qzhQ7NsN",
          "width": 320
        },
        "k": {
          "extension": "jpg",
          "height": 1155,
          "mimetype": "image/jpeg",
          "secret": "i5ad6X15KbIC9xZjGNOPKBK2qzhQ7NsN",
          "width": 2048
        },
        "n": {
          "extension": "jpg",
          "height": 180,
          "mimetype": "image/jpeg",
          "secret": "i5ad6X15KbIC9xZjGNOPKBK2qzhQ7NsN",
          "width": 320
        },
        "o": {
          "extension": "jpg",
          "height": 1106,
          "mimetype": "image/jpeg",
          "secret": "VzUGjcBoxkZWcn4QjxVLq5Y5WmiH4ODq",
          "width": 1960
        },
        "s": {
          "extension": "jpg",
          "height": 320,
          "mimetype": "image/jpeg",
          "secret": "i5ad6X15KbIC9xZjGNOPKBK2qzhQ7NsN",
          "width": 320
        },
        "z": {
          "extension": "jpg",
          "height": 361,
          "mimetype": "image/jpeg",
          "secret": "i5ad6X15KbIC9xZjGNOPKBK2qzhQ7NsN",
          "width": 640
        }
      }
    },
    "media:uri_template": "https://millsfield.sfomuseum.org/media/152/781/992/7/1527819927_{secret}_{label}.{extention}",
    "sfomuseum:filename": "31176.tif",
    "sfomuseum:image_index": 5,
    "sfomuseum:placetype": "image",
    "sfomuseum:primary_image": 1,
    "wof:depicts": [
      1511908919
    ],
    "wof:name": "airmail flight cover: International Aircraft Show, St. Louis",
    "wof:placetype": "media"
  },
  "geometry": {"coordinates":[-122.386155,37.616358],"type":"Point"}
}
