{
  "type": "Feature",
  "properties": {
    "date:cessation_lower": "1910-01-01",
    "date:cessation_upper": "1910-12-31",
    "date:inception_lower": "1910-01-01",
    "date:inception_upper": "1910-12-31",
    "iso:country": "XX",
    "media:imagehash_avg": "a:818080e0f1ffffe1",
    "media:imagehash_diff": "d:1d3d394bcb818203",
    "media:imagetext": "The\nBOY AVIATORS\nIN RECORD\n• FLIGHT •\nOR THE RIVAL\n• AEROPLANE *\nCAPTAIN-WILBUR •LAWTON",
    "media:imagetext_created": 1701940817,
    "media:mimetype": "image/jpeg",
    "media:properties": {
    },
    "media:uri_template": "https://static.sfomuseum.org/media/174/668/038/3/1746680383_{secret}_{label}.{extension}",
    "millsfield:exhibition_ids": [
      1159160363
    ],
    "millsfield:images_colors": [
      {
        "hex": "#dfcb9c",
        "name": "#dfcb9c",
        "reference": "marekm4"
      },
      {
        "hex": "#deb887",
        "name": "burlywood",
        "reference": "css4"
      },
      {
        "hex": "#e7c697",
        "name": "Gold",
        "reference": "crayola"
      },
      {
        "hex": "#b09d68",
        "name": "#b09d68",
        "reference": "marekm4"
      },
      {
        "hex": "#bdb76b",
        "name": "darkkhaki",
        "reference": "css4"
      },
      {
        "hex": "#bab86c",
        "name": "Olive Green",
        "reference": "crayola"
      },
      {
        "hex": "#63540c",
        "name": "#63540c",
        "reference": "marekm4"
      },
      {
        "hex": "#8b4513",
        "name": "saddlebrown",
        "reference": "css4"
      },
      {
        "hex": "#714b23",
        "name": "Raw Umber",
        "reference": "crayola"
      },
      {
        "hex": "#90522a",
        "name": "#90522a",
        "reference": "marekm4"
      },
      {
        "hex": "#a0522d",
        "name": "sienna",
        "reference": "css4"
      }
    ],
    "millsfield:images_texts": [
      "The\nBOY AVIATORS\nIN RECORD\n• FLIGHT •\nOR THE RIVAL\n• AEROPLANE *\nCAPTAIN-WILBUR •LAWTON"
    ],
    "millsfield:images_texts_ids": [
      1746680383
    ],
    "millsfield:on_view": 0,
    "sfomuseum:filename": "57525.jpg",
    "sfomuseum:image_index": 0,
    "sfomuseum:image_type": "studio",
    "sfomuseum:placetype": "image",
    "sfomuseum:primary_image": 1,
    "wof:depicts": [
      1511913093
    ],
    "wof:name": "The boy aviators in record flight: or, The rival aeroplane",
    "wof:placetype": "custom",
    "wof:placetype_alt": [
      "image"
    ]
  },
  "geometry": {"type":"Point","coordinates":[-122.386155,37.616357]}
}
