{
  "type": "Feature",
  "properties": {
    "iso:country": "XX",
    "media:fingerprint": "773c3f0a80aa30645d9a858ce519fb1c86a95ccb",
    "media:imagehash_avg": "a:9780b39fbf189899",
    "media:imagehash_diff": "d:2525677371317131",
    "media:medium": "image",
    "media:mimetype": "image/tiff",
    "media:properties": {
      "colours": [
        {
          "hex": "#cd6531",
          "name": "#cd6531",
          "reference": "vibrant"
        }, 
        {
          "hex": "#d8be98",
          "name": "#d8be98",
          "reference": "vibrant"
        }, 
        {
          "hex": "#ac5a68",
          "name": "#ac5a68",
          "reference": "vibrant"
        }, 
        {
          "hex": "#d6c7a2",
          "name": "#d6c7a2",
          "reference": "vibrant"
        }, 
        {
          "hex": "#4f493a",
          "name": "#4f493a",
          "reference": "vibrant"
        }
      ],
      "sizes": {
        "b": {
          "extension": "jpg",
          "height": 555,
          "mimetype": "image/jpeg",
          "secret": "8CnwMwe8OWp3zHECp9WlOYe3d9TScrWh",
          "width": 1024
        },
        "c": {
          "extension": "jpg",
          "height": 433,
          "mimetype": "image/jpeg",
          "secret": "8CnwMwe8OWp3zHECp9WlOYe3d9TScrWh",
          "width": 800
        },
        "dc": {
          "extension": "jpg",
          "height": 433,
          "mimetype": "image/jpeg",
          "secret": "8CnwMwe8OWp3zHECp9WlOYe3d9TScrWh",
          "width": 800
        },
        "ds": {
          "extension": "jpg",
          "height": 320,
          "mimetype": "image/jpeg",
          "secret": "8CnwMwe8OWp3zHECp9WlOYe3d9TScrWh",
          "width": 320
        },
        "k": {
          "extension": "jpg",
          "height": 1110,
          "mimetype": "image/jpeg",
          "secret": "8CnwMwe8OWp3zHECp9WlOYe3d9TScrWh",
          "width": 2048
        },
        "n": {
          "extension": "jpg",
          "height": 173,
          "mimetype": "image/jpeg",
          "secret": "8CnwMwe8OWp3zHECp9WlOYe3d9TScrWh",
          "width": 320
        },
        "o": {
          "extension": "jpg",
          "height": 2021,
          "mimetype": "image/jpeg",
          "secret": "La54dWtMsOvzWMQUXh6yh7ydAgCkmEfp",
          "width": 3726
        },
        "s": {
          "extension": "jpg",
          "height": 320,
          "mimetype": "image/jpeg",
          "secret": "8CnwMwe8OWp3zHECp9WlOYe3d9TScrWh",
          "width": 320
        },
        "z": {
          "extension": "jpg",
          "height": 347,
          "mimetype": "image/jpeg",
          "secret": "8CnwMwe8OWp3zHECp9WlOYe3d9TScrWh",
          "width": 640
        }
      }
    },
    "media:uri_template": "https://millsfield.sfomuseum.org/media/152/781/827/9/1527818279_{secret}_{label}.{extention}",
    "sfomuseum:filename": "16361.tif",
    "sfomuseum:image_index": 5,
    "sfomuseum:placetype": "image",
    "sfomuseum:primary_image": 1,
    "wof:depicts": [
      1511931639
    ],
    "wof:name": "airmail flight cover: Pan American Airways, first Pacific survey flight, San Francisco - Honolulu and return",
    "wof:placetype": "media"
  },
  "geometry": {"coordinates":[-122.386155,37.616358],"type":"Point"}
}
