{
  "type": "Feature",
  "properties": {
    "iso:country": "XX",
    "media:fingerprint": "1a5006470cc381c4854e922f14066fdd9aec48c4",
    "media:imagehash_avg": "a:fffffffd0010e080",
    "media:imagehash_diff": "d:f0c8c9c961a38213",
    "media:medium": "image",
    "media:mimetype": "image/tiff",
    "media:properties": {
      "colours": [
        {
          "hex": "#787878",
          "name": "#787878",
          "reference": "vibrant"
        }, 
        {
          "hex": "#b8b8b8",
          "name": "#b8b8b8",
          "reference": "vibrant"
        }, 
        {
          "hex": "#404040",
          "name": "#404040",
          "reference": "vibrant"
        }
      ],
      "sizes": {
        "b": {
          "extension": "jpg",
          "height": 768,
          "mimetype": "image/jpeg",
          "secret": "RPZBPYIA3WIsZ7VrP4AcxQirXVBDglas",
          "width": 975
        },
        "c": {
          "extension": "jpg",
          "height": 600,
          "mimetype": "image/jpeg",
          "secret": "RPZBPYIA3WIsZ7VrP4AcxQirXVBDglas",
          "width": 762
        },
        "dc": {
          "extension": "jpg",
          "height": 600,
          "mimetype": "image/jpeg",
          "secret": "RPZBPYIA3WIsZ7VrP4AcxQirXVBDglas",
          "width": 762
        },
        "ds": {
          "extension": "jpg",
          "height": 320,
          "mimetype": "image/jpeg",
          "secret": "RPZBPYIA3WIsZ7VrP4AcxQirXVBDglas",
          "width": 320
        },
        "k": {
          "extension": "jpg",
          "height": 1536,
          "mimetype": "image/jpeg",
          "secret": "RPZBPYIA3WIsZ7VrP4AcxQirXVBDglas",
          "width": 1951
        },
        "n": {
          "extension": "jpg",
          "height": 240,
          "mimetype": "image/jpeg",
          "secret": "RPZBPYIA3WIsZ7VrP4AcxQirXVBDglas",
          "width": 304
        },
        "o": {
          "extension": "jpg",
          "height": 2168,
          "mimetype": "image/jpeg",
          "secret": "U4eCdLV2MxvOwZwmMDWvKn9dnxNo7xLe",
          "width": 2754
        },
        "s": {
          "extension": "jpg",
          "height": 320,
          "mimetype": "image/jpeg",
          "secret": "RPZBPYIA3WIsZ7VrP4AcxQirXVBDglas",
          "width": 320
        },
        "z": {
          "extension": "jpg",
          "height": 480,
          "mimetype": "image/jpeg",
          "secret": "RPZBPYIA3WIsZ7VrP4AcxQirXVBDglas",
          "width": 609
        }
      }
    },
    "media:uri_template": "https://millsfield.sfomuseum.org/media/152/782/558/3/1527825583_{secret}_{label}.{extention}",
    "sfomuseum:filename": "43219.tif",
    "sfomuseum:image_index": 5,
    "sfomuseum:placetype": "image",
    "sfomuseum:primary_image": 1,
    "wof:depicts": [
      1511946623
    ],
    "wof:name": "negative: San Francisco International Airport (SFO), helipad proposal meeting",
    "wof:placetype": "media"
  },
  "geometry": {"coordinates":[-122.386155,37.616358],"type":"Point"}
}
