{
  "type": "Feature",
  "properties": {
    "iso:country": "XX",
    "media:fingerprint": "06e9d1d2cd571a050d5fc30860872da4c762a6e5",
    "media:imagehash_avg": "a:00f9fffff0700000",
    "media:imagehash_diff": "d:0113231323c30100",
    "media:medium": "image",
    "media:mimetype": "image/tiff",
    "media:properties": {
      "colours": [
        {
          "hex": "#787878",
          "name": "#787878",
          "reference": "vibrant"
        }, 
        {
          "hex": "#b6b6b6",
          "name": "#b6b6b6",
          "reference": "vibrant"
        }, 
        {
          "hex": "#404040",
          "name": "#404040",
          "reference": "vibrant"
        }
      ],
      "sizes": {
        "b": {
          "extension": "jpg",
          "height": 768,
          "mimetype": "image/jpeg",
          "secret": "CwaVNP78gYeQe4QXevxyvS5eb1Uy6qaT",
          "width": 768
        },
        "c": {
          "extension": "jpg",
          "height": 600,
          "mimetype": "image/jpeg",
          "secret": "CwaVNP78gYeQe4QXevxyvS5eb1Uy6qaT",
          "width": 600
        },
        "dc": {
          "extension": "jpg",
          "height": 600,
          "mimetype": "image/jpeg",
          "secret": "CwaVNP78gYeQe4QXevxyvS5eb1Uy6qaT",
          "width": 600
        },
        "ds": {
          "extension": "jpg",
          "height": 320,
          "mimetype": "image/jpeg",
          "secret": "CwaVNP78gYeQe4QXevxyvS5eb1Uy6qaT",
          "width": 320
        },
        "k": {
          "extension": "jpg",
          "height": 1536,
          "mimetype": "image/jpeg",
          "secret": "CwaVNP78gYeQe4QXevxyvS5eb1Uy6qaT",
          "width": 1536
        },
        "n": {
          "extension": "jpg",
          "height": 240,
          "mimetype": "image/jpeg",
          "secret": "CwaVNP78gYeQe4QXevxyvS5eb1Uy6qaT",
          "width": 240
        },
        "o": {
          "extension": "jpg",
          "height": 2536,
          "mimetype": "image/jpeg",
          "secret": "h6nG2mXLkvMxLOvOJcQZs0cJuacsFbWk",
          "width": 2536
        },
        "s": {
          "extension": "jpg",
          "height": 320,
          "mimetype": "image/jpeg",
          "secret": "CwaVNP78gYeQe4QXevxyvS5eb1Uy6qaT",
          "width": 320
        },
        "z": {
          "extension": "jpg",
          "height": 480,
          "mimetype": "image/jpeg",
          "secret": "CwaVNP78gYeQe4QXevxyvS5eb1Uy6qaT",
          "width": 480
        }
      }
    },
    "media:uri_template": "https://millsfield.sfomuseum.org/media/152/782/702/9/1527827029_{secret}_{label}.{extention}",
    "sfomuseum:filename": "43905.tif",
    "sfomuseum:image_index": 5,
    "sfomuseum:placetype": "image",
    "sfomuseum:primary_image": 1,
    "wof:depicts": [
      1511948069
    ],
    "wof:name": "negative: San Francisco International Airport (SFO), cargo building 3",
    "wof:placetype": "media"
  },
  "geometry": {"coordinates":[-122.386155,37.616358],"type":"Point"}
}
