{
  "type": "Feature",
  "properties": {
    "iso:country": "XX",
    "media:fingerprint": "66d2505f3be69001464b06f8d0e9da061c4fa7dd",
    "media:imagehash_avg": "a:007f7f7f67777f00",
    "media:imagehash_diff": "d:138ef0cc8e8eaa07",
    "media:medium": "image",
    "media:mimetype": "image/tiff",
    "media:properties": {
      "colours": [
        {
          "hex": "#d03035",
          "name": "#d03035",
          "reference": "vibrant"
        }, 
        {
          "hex": "#f2a499",
          "name": "#f2a499",
          "reference": "vibrant"
        }, 
        {
          "hex": "#211d67",
          "name": "#211d67",
          "reference": "vibrant"
        }, 
        {
          "hex": "#686c94",
          "name": "#686c94",
          "reference": "vibrant"
        }, 
        {
          "hex": "#bab4a9",
          "name": "#bab4a9",
          "reference": "vibrant"
        }
      ],
      "sizes": {
        "b": {
          "extension": "jpg",
          "height": 460,
          "mimetype": "image/jpeg",
          "secret": "S9lSjZKByg2LjZLW0FT02n6TJNZxknFQ",
          "width": 1024
        },
        "c": {
          "extension": "jpg",
          "height": 359,
          "mimetype": "image/jpeg",
          "secret": "S9lSjZKByg2LjZLW0FT02n6TJNZxknFQ",
          "width": 800
        },
        "dc": {
          "extension": "jpg",
          "height": 359,
          "mimetype": "image/jpeg",
          "secret": "S9lSjZKByg2LjZLW0FT02n6TJNZxknFQ",
          "width": 800
        },
        "ds": {
          "extension": "jpg",
          "height": 320,
          "mimetype": "image/jpeg",
          "secret": "S9lSjZKByg2LjZLW0FT02n6TJNZxknFQ",
          "width": 320
        },
        "k": {
          "extension": "jpg",
          "height": 921,
          "mimetype": "image/jpeg",
          "secret": "S9lSjZKByg2LjZLW0FT02n6TJNZxknFQ",
          "width": 2048
        },
        "n": {
          "extension": "jpg",
          "height": 143,
          "mimetype": "image/jpeg",
          "secret": "S9lSjZKByg2LjZLW0FT02n6TJNZxknFQ",
          "width": 320
        },
        "o": {
          "extension": "jpg",
          "height": 1325,
          "mimetype": "image/jpeg",
          "secret": "NWlE19DpI9mGSLPCIrzdMRxsYdIeH6xU",
          "width": 2946
        },
        "s": {
          "extension": "jpg",
          "height": 320,
          "mimetype": "image/jpeg",
          "secret": "S9lSjZKByg2LjZLW0FT02n6TJNZxknFQ",
          "width": 320
        },
        "z": {
          "extension": "jpg",
          "height": 287,
          "mimetype": "image/jpeg",
          "secret": "S9lSjZKByg2LjZLW0FT02n6TJNZxknFQ",
          "width": 640
        }
      }
    },
    "media:uri_template": "https://millsfield.sfomuseum.org/media/152/782/901/7/1527829017_{secret}_{label}.{extention}",
    "sfomuseum:filename": "47480.tif",
    "sfomuseum:image_index": 5,
    "sfomuseum:placetype": "image",
    "sfomuseum:primary_image": 0,
    "wof:depicts": [
      1511906915
    ],
    "wof:name": "airmail flight cover: Pan American Airways, Singapore - Guam route",
    "wof:placetype": "media"
  },
  "geometry": {"coordinates":[-122.386155,37.616358],"type":"Point"}
}
