{
  "type": "Feature",
  "properties": {
    "iso:country": "XX",
    "media:fingerprint": "a04472c5f8a97613ea882d79466410eff02d6dbb",
    "media:imagehash_avg": "a:ff3f8383c3fff7f7",
    "media:imagehash_diff": "d:0e66363636362656",
    "media:medium": "image",
    "media:mimetype": "image/tiff",
    "media:properties": {
      "colours": [
        {
          "hex": "#7f7f75",
          "name": "#7f7f75",
          "reference": "vibrant"
        },
        {
          "hex": "#bbc0be",
          "name": "#bbc0be",
          "reference": "vibrant"
        },
        {
          "hex": "#413f35",
          "name": "#413f35",
          "reference": "vibrant"
        }
      ],
      "sizes": {
        "b": {
          "extension": "jpg",
          "height": 521,
          "mimetype": "image/jpeg",
          "secret": "4jPcOZLY3kDdY4rVDbutwgQLTZ5OqVLd",
          "width": 1024
        },
        "c": {
          "extension": "jpg",
          "height": 407,
          "mimetype": "image/jpeg",
          "secret": "4jPcOZLY3kDdY4rVDbutwgQLTZ5OqVLd",
          "width": 800
        },
        "dc": {
          "extension": "jpg",
          "height": 407,
          "mimetype": "image/jpeg",
          "secret": "4jPcOZLY3kDdY4rVDbutwgQLTZ5OqVLd",
          "width": 800
        },
        "ds": {
          "extension": "jpg",
          "height": 320,
          "mimetype": "image/jpeg",
          "secret": "4jPcOZLY3kDdY4rVDbutwgQLTZ5OqVLd",
          "width": 320
        },
        "k": {
          "extension": "jpg",
          "height": 1042,
          "mimetype": "image/jpeg",
          "secret": "4jPcOZLY3kDdY4rVDbutwgQLTZ5OqVLd",
          "width": 2048
        },
        "n": {
          "extension": "jpg",
          "height": 162,
          "mimetype": "image/jpeg",
          "secret": "4jPcOZLY3kDdY4rVDbutwgQLTZ5OqVLd",
          "width": 320
        },
        "o": {
          "extension": "jpg",
          "height": 2000,
          "mimetype": "image/jpeg",
          "secret": "TA1jFa4RkBIgAqJYWgdb1yXO9wDF4MUF",
          "width": 3930
        },
        "s": {
          "extension": "jpg",
          "height": 320,
          "mimetype": "image/jpeg",
          "secret": "4jPcOZLY3kDdY4rVDbutwgQLTZ5OqVLd",
          "width": 320
        },
        "z": {
          "extension": "jpg",
          "height": 325,
          "mimetype": "image/jpeg",
          "secret": "4jPcOZLY3kDdY4rVDbutwgQLTZ5OqVLd",
          "width": 640
        }
      }
    },
    "media:uri_template": "https://static.sfomuseum.org/media/152/784/659/1/1527846591_{secret}_{label}.{extention}",
    "sfomuseum:filename": "70968.tif",
    "sfomuseum:image_index": 5,
    "sfomuseum:image_type": "studio",
    "sfomuseum:placetype": "image",
    "sfomuseum:primary_image": 0,
    "wof:depicts": [
      1159285413,
      1511943119
    ],
    "wof:name": "menu: United Airlines, First Class",
    "wof:placetype": "custom",
    "wof:placetype_alt": "image"
  },
  "geometry": {"coordinates":[-122.386155,37.616358],"type":"Point"}
}
