{
  "type": "Feature",
  "properties": {
    "iso:country": "XX",
    "media:fingerprint": "bd1ba21f031ecbfee30e0938c8b6ba7f9b38d532",
    "media:imagehash_avg": "a:5f00ffff1ffd0100",
    "media:imagehash_diff": "d:b6b5bb3f39cd2765",
    "media:medium": "image",
    "media:mimetype": "image/jpeg",
    "media:properties": {
      "colours": [
        {
          "hex": "#cd0e05",
          "name": "#cd0e05",
          "reference": "vibrant"
        }, 
        {
          "hex": "#cea989",
          "name": "#cea989",
          "reference": "vibrant"
        }, 
        {
          "hex": "#a50000",
          "name": "#a50000",
          "reference": "vibrant"
        }, 
        {
          "hex": "#6c7499",
          "name": "#6c7499",
          "reference": "vibrant"
        }, 
        {
          "hex": "#c5c6b8",
          "name": "#c5c6b8",
          "reference": "vibrant"
        }
      ],
      "sizes": {
        "b": {
          "extension": "jpg",
          "height": 767,
          "mimetype": "image/jpeg",
          "secret": "fQn83uK7ClaeIMpkQTs4RfDhpqWXfo14",
          "width": 357
        },
        "c": {
          "extension": "jpg",
          "height": 600,
          "mimetype": "image/jpeg",
          "secret": "fQn83uK7ClaeIMpkQTs4RfDhpqWXfo14",
          "width": 279
        },
        "dc": {
          "extension": "jpg",
          "height": 600,
          "mimetype": "image/jpeg",
          "secret": "fQn83uK7ClaeIMpkQTs4RfDhpqWXfo14",
          "width": 279
        },
        "ds": {
          "extension": "jpg",
          "height": 320,
          "mimetype": "image/jpeg",
          "secret": "fQn83uK7ClaeIMpkQTs4RfDhpqWXfo14",
          "width": 320
        },
        "k": {
          "extension": "jpg",
          "height": 1535,
          "mimetype": "image/jpeg",
          "secret": "fQn83uK7ClaeIMpkQTs4RfDhpqWXfo14",
          "width": 714
        },
        "n": {
          "extension": "jpg",
          "height": 240,
          "mimetype": "image/jpeg",
          "secret": "fQn83uK7ClaeIMpkQTs4RfDhpqWXfo14",
          "width": 111
        },
        "o": {
          "extension": "jpg",
          "height": 2907,
          "mimetype": "image/jpeg",
          "secret": "Hqi6h1RiYGzZ0nNku1IcLIWCufawBaMq",
          "width": 1352
        },
        "s": {
          "extension": "jpg",
          "height": 320,
          "mimetype": "image/jpeg",
          "secret": "fQn83uK7ClaeIMpkQTs4RfDhpqWXfo14",
          "width": 320
        },
        "z": {
          "extension": "jpg",
          "height": 480,
          "mimetype": "image/jpeg",
          "secret": "fQn83uK7ClaeIMpkQTs4RfDhpqWXfo14",
          "width": 223
        }
      }
    },
    "media:uri_template": "https://millsfield.sfomuseum.org/media/152/781/913/7/1527819137_{secret}_{label}.{extention}",
    "sfomuseum:filename": "20177.jpg",
    "sfomuseum:image_index": 5,
    "sfomuseum:placetype": "image",
    "sfomuseum:primary_image": 0,
    "wof:depicts": [
      1511931977
    ],
    "wof:name": "timetable: TWA (Trans World Airlines)",
    "wof:placetype": "media"
  },
  "geometry": {"coordinates":[-122.386155,37.616358],"type":"Point"}
}
