{
  "type": "Feature",
  "properties": {
    "iso:country": "XX",
    "media:fingerprint": "b301133ae4cb234db9e85779522946cf0e966bdc",
    "media:imagehash_avg": "a:ffe3c3c3c3c3c3ff",
    "media:imagehash_diff": "d:074f173b3307171f",
    "media:medium": "image",
    "media:mimetype": "image/tiff",
    "media:properties": {
      "colours": [
        {
          "hex": "#f38806",
          "name": "#f38806",
          "reference": "vibrant"
        },
        {
          "hex": "#e1c891",
          "name": "#e1c891",
          "reference": "vibrant"
        },
        {
          "hex": "#804606",
          "name": "#804606",
          "reference": "vibrant"
        },
        {
          "hex": "#a18759",
          "name": "#a18759",
          "reference": "vibrant"
        },
        {
          "hex": "#b0b0b8",
          "name": "#b0b0b8",
          "reference": "vibrant"
        }
      ],
      "sizes": {
        "b": {
          "extension": "jpg",
          "height": 685,
          "mimetype": "image/jpeg",
          "secret": "SQMZr2VbSwS8OAVRpZUh1efYn4fAvD3J",
          "width": 1024
        },
        "c": {
          "extension": "jpg",
          "height": 535,
          "mimetype": "image/jpeg",
          "secret": "SQMZr2VbSwS8OAVRpZUh1efYn4fAvD3J",
          "width": 800
        },
        "dc": {
          "extension": "jpg",
          "height": 535,
          "mimetype": "image/jpeg",
          "secret": "SQMZr2VbSwS8OAVRpZUh1efYn4fAvD3J",
          "width": 800
        },
        "ds": {
          "extension": "jpg",
          "height": 320,
          "mimetype": "image/jpeg",
          "secret": "SQMZr2VbSwS8OAVRpZUh1efYn4fAvD3J",
          "width": 320
        },
        "k": {
          "extension": "jpg",
          "height": 1371,
          "mimetype": "image/jpeg",
          "secret": "SQMZr2VbSwS8OAVRpZUh1efYn4fAvD3J",
          "width": 2048
        },
        "n": {
          "extension": "jpg",
          "height": 214,
          "mimetype": "image/jpeg",
          "secret": "SQMZr2VbSwS8OAVRpZUh1efYn4fAvD3J",
          "width": 320
        },
        "o": {
          "extension": "jpg",
          "height": 2400,
          "mimetype": "image/jpeg",
          "secret": "AIfV4Sp2rdUMsvHBKqZdTqJoRv8Gd8PJ",
          "width": 3585
        },
        "s": {
          "extension": "jpg",
          "height": 320,
          "mimetype": "image/jpeg",
          "secret": "SQMZr2VbSwS8OAVRpZUh1efYn4fAvD3J",
          "width": 320
        },
        "z": {
          "extension": "jpg",
          "height": 428,
          "mimetype": "image/jpeg",
          "secret": "SQMZr2VbSwS8OAVRpZUh1efYn4fAvD3J",
          "width": 640
        }
      }
    },
    "media:uri_template": "https://millsfield.sfomuseum.org/media/152/785/413/5/1527854135_{secret}_{label}.{extention}",
    "sfomuseum:filename": "2012.147.418.tif",
    "sfomuseum:image_index": 5,
    "sfomuseum:placetype": "image",
    "sfomuseum:primary_image": 1,
    "wof:depicts": [
      1511952699
    ],
    "wof:name": "children's souvenir ring: Pan American World Airways",
    "wof:placetype": "custom",
    "wof:placetype_alt": "image"
  },
  "geometry": {"coordinates":[-122.386155,37.616358],"type":"Point"}
}
