{
  "type": "Feature",
  "properties": {
    "iso:country": "XX",
    "media:fingerprint": "88a3d6532f6efdd5b53129908f1b7d6823b922b6",
    "media:imagehash_avg": "a:f0f0fce000300000",
    "media:imagehash_diff": "d:c4c2404842e0e0e0",
    "media:medium": "image",
    "media:mimetype": "image/tiff",
    "media:properties": {
      "colours": [
        {
          "hex": "#808080",
          "name": "#808080",
          "reference": "vibrant"
        }, 
        {
          "hex": "#bababa",
          "name": "#bababa",
          "reference": "vibrant"
        }, 
        {
          "hex": "#484848",
          "name": "#484848",
          "reference": "vibrant"
        }
      ],
      "sizes": {
        "b": {
          "extension": "jpg",
          "height": 768,
          "mimetype": "image/jpeg",
          "secret": "Q1jFOWrpnCiNwKwIMW4vNaO9uYI8YsnD",
          "width": 759
        },
        "c": {
          "extension": "jpg",
          "height": 600,
          "mimetype": "image/jpeg",
          "secret": "Q1jFOWrpnCiNwKwIMW4vNaO9uYI8YsnD",
          "width": 593
        },
        "dc": {
          "extension": "jpg",
          "height": 600,
          "mimetype": "image/jpeg",
          "secret": "Q1jFOWrpnCiNwKwIMW4vNaO9uYI8YsnD",
          "width": 593
        },
        "ds": {
          "extension": "jpg",
          "height": 320,
          "mimetype": "image/jpeg",
          "secret": "Q1jFOWrpnCiNwKwIMW4vNaO9uYI8YsnD",
          "width": 320
        },
        "k": {
          "extension": "jpg",
          "height": 1536,
          "mimetype": "image/jpeg",
          "secret": "Q1jFOWrpnCiNwKwIMW4vNaO9uYI8YsnD",
          "width": 1519
        },
        "n": {
          "extension": "jpg",
          "height": 239,
          "mimetype": "image/jpeg",
          "secret": "Q1jFOWrpnCiNwKwIMW4vNaO9uYI8YsnD",
          "width": 237
        },
        "o": {
          "extension": "jpg",
          "height": 2563,
          "mimetype": "image/jpeg",
          "secret": "wmuMmc4hy6wT9zMo1RundVnPbWnD9Vl3",
          "width": 2536
        },
        "s": {
          "extension": "jpg",
          "height": 320,
          "mimetype": "image/jpeg",
          "secret": "Q1jFOWrpnCiNwKwIMW4vNaO9uYI8YsnD",
          "width": 320
        },
        "z": {
          "extension": "jpg",
          "height": 479,
          "mimetype": "image/jpeg",
          "secret": "Q1jFOWrpnCiNwKwIMW4vNaO9uYI8YsnD",
          "width": 474
        }
      }
    },
    "media:uri_template": "https://millsfield.sfomuseum.org/media/152/782/628/9/1527826289_{secret}_{label}.{extention}",
    "sfomuseum:filename": "43574.tif",
    "sfomuseum:image_index": 5,
    "sfomuseum:placetype": "image",
    "sfomuseum:primary_image": 1,
    "wof:depicts": [
      1511947329
    ],
    "wof:name": "negative: San Francisco International Airport (SFO), construction",
    "wof:placetype": "media"
  },
  "geometry": {"coordinates":[-122.386155,37.616358],"type":"Point"}
}
