{
  "type": "Feature",
  "properties": {
    "iso:country": "XX",
    "media:fingerprint": "54c204f8b675af6528e2ab69919bf1a43962a845",
    "media:imagehash_avg": "a:7ffff7c30301010f",
    "media:imagehash_diff": "d:e76757474763f1fc",
    "media:medium": "image",
    "media:mimetype": "image/tiff",
    "media:properties": {
      "colours": [
        {
          "hex": "#808080",
          "name": "#808080",
          "reference": "vibrant"
        }, 
        {
          "hex": "#b8b8b8",
          "name": "#b8b8b8",
          "reference": "vibrant"
        }, 
        {
          "hex": "#606060",
          "name": "#606060",
          "reference": "vibrant"
        }
      ],
      "sizes": {
        "b": {
          "extension": "jpg",
          "height": 768,
          "mimetype": "image/jpeg",
          "secret": "EbO6XMvklDh0CXV1s1VTewlfS7vfHslC",
          "width": 768
        },
        "c": {
          "extension": "jpg",
          "height": 600,
          "mimetype": "image/jpeg",
          "secret": "EbO6XMvklDh0CXV1s1VTewlfS7vfHslC",
          "width": 600
        },
        "dc": {
          "extension": "jpg",
          "height": 600,
          "mimetype": "image/jpeg",
          "secret": "EbO6XMvklDh0CXV1s1VTewlfS7vfHslC",
          "width": 600
        },
        "ds": {
          "extension": "jpg",
          "height": 320,
          "mimetype": "image/jpeg",
          "secret": "EbO6XMvklDh0CXV1s1VTewlfS7vfHslC",
          "width": 320
        },
        "k": {
          "extension": "jpg",
          "height": 1536,
          "mimetype": "image/jpeg",
          "secret": "EbO6XMvklDh0CXV1s1VTewlfS7vfHslC",
          "width": 1536
        },
        "n": {
          "extension": "jpg",
          "height": 239,
          "mimetype": "image/jpeg",
          "secret": "EbO6XMvklDh0CXV1s1VTewlfS7vfHslC",
          "width": 239
        },
        "o": {
          "extension": "jpg",
          "height": 1835,
          "mimetype": "image/jpeg",
          "secret": "i6dqLYoe8Uu9PXdR01PF1h7BGsiOFq29",
          "width": 1835
        },
        "s": {
          "extension": "jpg",
          "height": 320,
          "mimetype": "image/jpeg",
          "secret": "EbO6XMvklDh0CXV1s1VTewlfS7vfHslC",
          "width": 320
        },
        "z": {
          "extension": "jpg",
          "height": 479,
          "mimetype": "image/jpeg",
          "secret": "EbO6XMvklDh0CXV1s1VTewlfS7vfHslC",
          "width": 479
        }
      }
    },
    "media:uri_template": "https://millsfield.sfomuseum.org/media/152/782/649/7/1527826497_{secret}_{label}.{extention}",
    "sfomuseum:filename": "43666.tif",
    "sfomuseum:image_index": 5,
    "sfomuseum:placetype": "image",
    "sfomuseum:primary_image": 1,
    "wof:depicts": [
      1511947535
    ],
    "wof:name": "photograph: San Francisco International Airport (SFO), Pacific Southwest Airlines (PSA) jetway and airplane",
    "wof:placetype": "media"
  },
  "geometry": {"coordinates":[-122.386155,37.616358],"type":"Point"}
}
