{
  "type": "Feature",
  "properties": {
    "iso:country": "XX",
    "media:fingerprint": "83967e12913637e507e1ad5f60ad178c4e8689e9",
    "media:imagehash_avg": "a:fcfcfcfefe000ebf",
    "media:imagehash_diff": "d:7070505838783a79",
    "media:medium": "image",
    "media:mimetype": "image/tiff",
    "media:properties": {
      "colours": [
        {
          "hex": "#808080",
          "name": "#808080",
          "reference": "vibrant"
        }, 
        {
          "hex": "#b6b6b6",
          "name": "#b6b6b6",
          "reference": "vibrant"
        }, 
        {
          "hex": "#464646",
          "name": "#464646",
          "reference": "vibrant"
        }
      ],
      "sizes": {
        "b": {
          "extension": "jpg",
          "height": 767,
          "mimetype": "image/jpeg",
          "secret": "OI0s6MChyzSYLlsPB9CibI3sYzE85WOU",
          "width": 993
        },
        "c": {
          "extension": "jpg",
          "height": 600,
          "mimetype": "image/jpeg",
          "secret": "OI0s6MChyzSYLlsPB9CibI3sYzE85WOU",
          "width": 776
        },
        "dc": {
          "extension": "jpg",
          "height": 600,
          "mimetype": "image/jpeg",
          "secret": "OI0s6MChyzSYLlsPB9CibI3sYzE85WOU",
          "width": 776
        },
        "ds": {
          "extension": "jpg",
          "height": 320,
          "mimetype": "image/jpeg",
          "secret": "OI0s6MChyzSYLlsPB9CibI3sYzE85WOU",
          "width": 320
        },
        "k": {
          "extension": "jpg",
          "height": 1535,
          "mimetype": "image/jpeg",
          "secret": "OI0s6MChyzSYLlsPB9CibI3sYzE85WOU",
          "width": 1986
        },
        "n": {
          "extension": "jpg",
          "height": 240,
          "mimetype": "image/jpeg",
          "secret": "OI0s6MChyzSYLlsPB9CibI3sYzE85WOU",
          "width": 310
        },
        "o": {
          "extension": "jpg",
          "height": 2140,
          "mimetype": "image/jpeg",
          "secret": "6dN1yegYEJatLEhu7bqsiAYWZznVKmau",
          "width": 2768
        },
        "s": {
          "extension": "jpg",
          "height": 320,
          "mimetype": "image/jpeg",
          "secret": "OI0s6MChyzSYLlsPB9CibI3sYzE85WOU",
          "width": 320
        },
        "z": {
          "extension": "jpg",
          "height": 480,
          "mimetype": "image/jpeg",
          "secret": "OI0s6MChyzSYLlsPB9CibI3sYzE85WOU",
          "width": 620
        }
      }
    },
    "media:uri_template": "https://millsfield.sfomuseum.org/media/152/782/166/5/1527821665_{secret}_{label}.{extention}",
    "sfomuseum:filename": "38915.tif",
    "sfomuseum:image_index": 5,
    "sfomuseum:placetype": "image",
    "sfomuseum:primary_image": 1,
    "wof:depicts": [
      1511943743
    ],
    "wof:name": "negative: San Francisco Airport, taxiway maintenance",
    "wof:placetype": "media"
  },
  "geometry": {"coordinates":[-122.386155,37.616358],"type":"Point"}
}
