{
  "type": "Feature",
  "properties": {
    "iso:country": "XX",
    "media:fingerprint": "7ae05b36c8fb6700a78eccff628f61132e89b193",
    "media:imagehash_avg": "a:ffe10000ffffbfff",
    "media:imagehash_diff": "d:410501311159535b",
    "media:medium": "image",
    "media:mimetype": "image/tiff",
    "media:properties": {
      "colours": [
        {
          "hex": "#b53423",
          "name": "#b53423",
          "reference": "vibrant"
        }, 
        {
          "hex": "#972a1a",
          "name": "#972a1a",
          "reference": "vibrant"
        }, 
        {
          "hex": "#8b8f76",
          "name": "#8b8f76",
          "reference": "vibrant"
        }, 
        {
          "hex": "#c4c4a7",
          "name": "#c4c4a7",
          "reference": "vibrant"
        }, 
        {
          "hex": "#394651",
          "name": "#394651",
          "reference": "vibrant"
        }
      ],
      "sizes": {
        "b": {
          "extension": "jpg",
          "height": 482,
          "mimetype": "image/jpeg",
          "secret": "2wAKMi3ofQOo6zLOwhN4fY6E1kJLrini",
          "width": 1023
        },
        "c": {
          "extension": "jpg",
          "height": 377,
          "mimetype": "image/jpeg",
          "secret": "2wAKMi3ofQOo6zLOwhN4fY6E1kJLrini",
          "width": 800
        },
        "dc": {
          "extension": "jpg",
          "height": 377,
          "mimetype": "image/jpeg",
          "secret": "2wAKMi3ofQOo6zLOwhN4fY6E1kJLrini",
          "width": 800
        },
        "ds": {
          "extension": "jpg",
          "height": 320,
          "mimetype": "image/jpeg",
          "secret": "2wAKMi3ofQOo6zLOwhN4fY6E1kJLrini",
          "width": 320
        },
        "k": {
          "extension": "jpg",
          "height": 965,
          "mimetype": "image/jpeg",
          "secret": "2wAKMi3ofQOo6zLOwhN4fY6E1kJLrini",
          "width": 2047
        },
        "n": {
          "extension": "jpg",
          "height": 150,
          "mimetype": "image/jpeg",
          "secret": "2wAKMi3ofQOo6zLOwhN4fY6E1kJLrini",
          "width": 320
        },
        "o": {
          "extension": "jpg",
          "height": 1629,
          "mimetype": "image/jpeg",
          "secret": "kfzTXtvZHnrdqHUTHy6EZwp3xpLRB1UN",
          "width": 3454
        },
        "s": {
          "extension": "jpg",
          "height": 320,
          "mimetype": "image/jpeg",
          "secret": "2wAKMi3ofQOo6zLOwhN4fY6E1kJLrini",
          "width": 320
        },
        "z": {
          "extension": "jpg",
          "height": 301,
          "mimetype": "image/jpeg",
          "secret": "2wAKMi3ofQOo6zLOwhN4fY6E1kJLrini",
          "width": 640
        }
      }
    },
    "media:uri_template": "https://millsfield.sfomuseum.org/media/152/781/828/7/1527818287_{secret}_{label}.{extention}",
    "sfomuseum:filename": "16367.tif",
    "sfomuseum:image_index": 5,
    "sfomuseum:placetype": "image",
    "sfomuseum:primary_image": 1,
    "wof:depicts": [
      1511931685
    ],
    "wof:name": "airmail flight cover: Pan American Airways, Westbound from Newark, New Jersey to Manila via Philippine Clipper, December 3-16, 1935",
    "wof:placetype": "media"
  },
  "geometry": {"coordinates":[-122.386155,37.616358],"type":"Point"}
}
