{
  "type": "Feature",
  "properties": {
    "iso:country": "XX",
    "media:fingerprint": "08c104fa10578fcddce1f4afa8b2c0b1ba05efdc",
    "media:imagehash_avg": "a:600002a6c4fef1ff",
    "media:imagehash_diff": "d:c3c6d65c8cca8f22",
    "media:medium": "image",
    "media:mimetype": "image/tiff",
    "media:properties": {
      "colours": [
        {
          "hex": "#808080",
          "name": "#808080",
          "reference": "vibrant"
        }, 
        {
          "hex": "#b8b8b8",
          "name": "#b8b8b8",
          "reference": "vibrant"
        }, 
        {
          "hex": "#484848",
          "name": "#484848",
          "reference": "vibrant"
        }
      ],
      "sizes": {
        "b": {
          "extension": "jpg",
          "height": 768,
          "mimetype": "image/jpeg",
          "secret": "S7F7tw8bh1Us6GwHmdCk6BJdeSJdIcYm",
          "width": 969
        },
        "c": {
          "extension": "jpg",
          "height": 600,
          "mimetype": "image/jpeg",
          "secret": "S7F7tw8bh1Us6GwHmdCk6BJdeSJdIcYm",
          "width": 757
        },
        "dc": {
          "extension": "jpg",
          "height": 600,
          "mimetype": "image/jpeg",
          "secret": "S7F7tw8bh1Us6GwHmdCk6BJdeSJdIcYm",
          "width": 757
        },
        "ds": {
          "extension": "jpg",
          "height": 320,
          "mimetype": "image/jpeg",
          "secret": "S7F7tw8bh1Us6GwHmdCk6BJdeSJdIcYm",
          "width": 320
        },
        "k": {
          "extension": "jpg",
          "height": 1536,
          "mimetype": "image/jpeg",
          "secret": "S7F7tw8bh1Us6GwHmdCk6BJdeSJdIcYm",
          "width": 1939
        },
        "n": {
          "extension": "jpg",
          "height": 240,
          "mimetype": "image/jpeg",
          "secret": "S7F7tw8bh1Us6GwHmdCk6BJdeSJdIcYm",
          "width": 303
        },
        "o": {
          "extension": "jpg",
          "height": 2181,
          "mimetype": "image/jpeg",
          "secret": "KeiUmureJu9OBal7OTYVu03eNX6VFGfi",
          "width": 2754
        },
        "s": {
          "extension": "jpg",
          "height": 320,
          "mimetype": "image/jpeg",
          "secret": "S7F7tw8bh1Us6GwHmdCk6BJdeSJdIcYm",
          "width": 320
        },
        "z": {
          "extension": "jpg",
          "height": 480,
          "mimetype": "image/jpeg",
          "secret": "S7F7tw8bh1Us6GwHmdCk6BJdeSJdIcYm",
          "width": 606
        }
      }
    },
    "media:uri_template": "https://millsfield.sfomuseum.org/media/152/782/319/5/1527823195_{secret}_{label}.{extention}",
    "sfomuseum:filename": "41278.tif",
    "sfomuseum:image_index": 5,
    "sfomuseum:placetype": "image",
    "sfomuseum:primary_image": 1,
    "wof:depicts": [
      1511945095
    ],
    "wof:name": "negative: San Francisco International Airport (SFO), South Terminal construction",
    "wof:placetype": "media"
  },
  "geometry": {"coordinates":[-122.386155,37.616358],"type":"Point"}
}
