{
  "type": "Feature",
  "properties": {
    "iso:country": "XX",
    "media:fingerprint": "ed057af27b1e678b2a873c393c9d7a3b584eef81",
    "media:imagehash_avg": "a:ff818181b18d8181",
    "media:imagehash_diff": "d:c707474763394f13",
    "media:medium": "image",
    "media:mimetype": "image/tiff",
    "media:properties": {
      "colours": [
        {
          "hex": "#de0000",
          "name": "#de0000",
          "reference": "vibrant"
        },
        {
          "hex": "#f77345",
          "name": "#f77345",
          "reference": "vibrant"
        },
        {
          "hex": "#4a2d04",
          "name": "#4a2d04",
          "reference": "vibrant"
        },
        {
          "hex": "#8c7e5f",
          "name": "#8c7e5f",
          "reference": "vibrant"
        },
        {
          "hex": "#d6c3a1",
          "name": "#d6c3a1",
          "reference": "vibrant"
        }
      ],
      "sizes": {
        "b": {
          "extension": "jpg",
          "height": 768,
          "mimetype": "image/jpeg",
          "secret": "ZNwygn5JC9Pa6KsO7I6niAKWC3SNh28B",
          "width": 344
        },
        "c": {
          "extension": "jpg",
          "height": 600,
          "mimetype": "image/jpeg",
          "secret": "ZNwygn5JC9Pa6KsO7I6niAKWC3SNh28B",
          "width": 269
        },
        "dc": {
          "extension": "jpg",
          "height": 600,
          "mimetype": "image/jpeg",
          "secret": "ZNwygn5JC9Pa6KsO7I6niAKWC3SNh28B",
          "width": 269
        },
        "ds": {
          "extension": "jpg",
          "height": 320,
          "mimetype": "image/jpeg",
          "secret": "ZNwygn5JC9Pa6KsO7I6niAKWC3SNh28B",
          "width": 320
        },
        "k": {
          "extension": "jpg",
          "height": 1536,
          "mimetype": "image/jpeg",
          "secret": "ZNwygn5JC9Pa6KsO7I6niAKWC3SNh28B",
          "width": 689
        },
        "n": {
          "extension": "jpg",
          "height": 240,
          "mimetype": "image/jpeg",
          "secret": "ZNwygn5JC9Pa6KsO7I6niAKWC3SNh28B",
          "width": 107
        },
        "o": {
          "extension": "jpg",
          "height": 2676,
          "mimetype": "image/jpeg",
          "secret": "zkYQ78XrSOwmETJ8kldRWAVH9BvHzg8y",
          "width": 1201
        },
        "s": {
          "extension": "jpg",
          "height": 320,
          "mimetype": "image/jpeg",
          "secret": "ZNwygn5JC9Pa6KsO7I6niAKWC3SNh28B",
          "width": 320
        },
        "z": {
          "extension": "jpg",
          "height": 480,
          "mimetype": "image/jpeg",
          "secret": "ZNwygn5JC9Pa6KsO7I6niAKWC3SNh28B",
          "width": 215
        }
      }
    },
    "media:uri_template": "https://millsfield.sfomuseum.org/media/152/784/152/3/1527841523_{secret}_{label}.{extention}",
    "sfomuseum:filename": "2003.105.089.001.tif",
    "sfomuseum:image_index": 5,
    "sfomuseum:placetype": "image",
    "sfomuseum:primary_image": 1,
    "wof:depicts": [
      1511939517,
      1159285043
    ],
    "wof:name": "timetable: Qantas Airways",
    "wof:placetype": "custom",
    "wof:placetype_alt": "image"
  },
  "geometry": {"coordinates":[-122.386155,37.616358],"type":"Point"}
}
