{
  "type": "Feature",
  "properties": {
    "media:fingerprint": "360f45e613e7c71a82ecd0abab80202ff15bd711",
    "media:imagehash_avg": "a:ffffff00020000ff",
    "media:imagehash_diff": "d:4d0f9f391e07396d",
    "media:mimetype": "image/tiff",
    "media:properties": {
      "colours": [
        {
          "hex": "#eabec1",
          "name": "#eabec1",
          "reference": "vibrant"
        },
        {
          "hex": "#b06268",
          "name": "#b06268",
          "reference": "vibrant"
        },
        {
          "hex": "#c1c0ba",
          "name": "#c1c0ba",
          "reference": "vibrant"
        },
        {
          "hex": "#4e5149",
          "name": "#4e5149",
          "reference": "vibrant"
        }
      ],
      "sizes": {
        "b": {
          "extension": "jpg",
          "height": 768,
          "mimetype": "image/jpeg",
          "secret": "TVA28bgOcT0PEuy5CnwWGUXYKB3iorqV",
          "width": 937
        },
        "c": {
          "extension": "jpg",
          "height": 600,
          "mimetype": "image/jpeg",
          "secret": "TVA28bgOcT0PEuy5CnwWGUXYKB3iorqV",
          "width": 732
        },
        "dc": {
          "extension": "jpg",
          "height": 600,
          "mimetype": "image/jpeg",
          "secret": "TVA28bgOcT0PEuy5CnwWGUXYKB3iorqV",
          "width": 732
        },
        "ds": {
          "extension": "jpg",
          "height": 320,
          "mimetype": "image/jpeg",
          "secret": "TVA28bgOcT0PEuy5CnwWGUXYKB3iorqV",
          "width": 320
        },
        "k": {
          "extension": "jpg",
          "height": 1536,
          "mimetype": "image/jpeg",
          "secret": "TVA28bgOcT0PEuy5CnwWGUXYKB3iorqV",
          "width": 1874
        },
        "n": {
          "extension": "jpg",
          "height": 240,
          "mimetype": "image/jpeg",
          "secret": "TVA28bgOcT0PEuy5CnwWGUXYKB3iorqV",
          "width": 292
        },
        "o": {
          "extension": "jpg",
          "height": 1639,
          "mimetype": "image/jpeg",
          "secret": "ygvbJj8jsZudU9Ar3JCBUYXiubJZ68e8",
          "width": 2000
        },
        "s": {
          "extension": "jpg",
          "height": 320,
          "mimetype": "image/jpeg",
          "secret": "TVA28bgOcT0PEuy5CnwWGUXYKB3iorqV",
          "width": 320
        },
        "z": {
          "extension": "jpg",
          "height": 480,
          "mimetype": "image/jpeg",
          "secret": "TVA28bgOcT0PEuy5CnwWGUXYKB3iorqV",
          "width": 585
        }
      }
    },
    "media:uri_template": "https://static.sfomuseum.org/media/174/628/152/5/1746281525_{secret}_{label}.{extention}",
    "sfomuseum:filename": "2006.037.205.006.tif",
    "sfomuseum:image_index": 0,
    "sfomuseum:placetype": "image",
    "sfomuseum:primary_image": 1,
    "wof:depicts": [
      1729565061
    ],
    "wof:name": "photograph: Granville Brothers, Gee Bee NR77V",
    "wof:placetype": "custom",
    "wof:placetype_alt": "image"
  },
  "geometry": {"coordinates":[-122.386155,37.616357],"type":"Point"}
}
