{
  "type": "Feature",
  "properties": {
    "iso:country": "XX",
    "media:fingerprint": "fcb1fa825df7b627046b29eedbb584afed6057e8",
    "media:imagehash_avg": "a:fffffffe20000000",
    "media:imagehash_diff": "d:bc98d8e0c081a382",
    "media:medium": "image",
    "media:mimetype": "image/tiff",
    "media:properties": {
      "colours": [
        {
          "hex": "#808080",
          "name": "#808080",
          "reference": "vibrant"
        }, 
        {
          "hex": "#b8b8b8",
          "name": "#b8b8b8",
          "reference": "vibrant"
        }, 
        {
          "hex": "#404040",
          "name": "#404040",
          "reference": "vibrant"
        }
      ],
      "sizes": {
        "b": {
          "extension": "jpg",
          "height": 726,
          "mimetype": "image/jpeg",
          "secret": "ed4eFqJFCIOMGzLTrQ69t4UVJiZxfc1O",
          "width": 1024
        },
        "c": {
          "extension": "jpg",
          "height": 567,
          "mimetype": "image/jpeg",
          "secret": "ed4eFqJFCIOMGzLTrQ69t4UVJiZxfc1O",
          "width": 800
        },
        "dc": {
          "extension": "jpg",
          "height": 567,
          "mimetype": "image/jpeg",
          "secret": "ed4eFqJFCIOMGzLTrQ69t4UVJiZxfc1O",
          "width": 800
        },
        "ds": {
          "extension": "jpg",
          "height": 320,
          "mimetype": "image/jpeg",
          "secret": "ed4eFqJFCIOMGzLTrQ69t4UVJiZxfc1O",
          "width": 320
        },
        "k": {
          "extension": "jpg",
          "height": 1453,
          "mimetype": "image/jpeg",
          "secret": "ed4eFqJFCIOMGzLTrQ69t4UVJiZxfc1O",
          "width": 2048
        },
        "n": {
          "extension": "jpg",
          "height": 227,
          "mimetype": "image/jpeg",
          "secret": "ed4eFqJFCIOMGzLTrQ69t4UVJiZxfc1O",
          "width": 320
        },
        "o": {
          "extension": "jpg",
          "height": 5861,
          "mimetype": "image/jpeg",
          "secret": "zoTSq5IWYIOR42F6TjgMuYVXC0cTf9E2",
          "width": 8261
        },
        "s": {
          "extension": "jpg",
          "height": 320,
          "mimetype": "image/jpeg",
          "secret": "ed4eFqJFCIOMGzLTrQ69t4UVJiZxfc1O",
          "width": 320
        },
        "z": {
          "extension": "jpg",
          "height": 454,
          "mimetype": "image/jpeg",
          "secret": "ed4eFqJFCIOMGzLTrQ69t4UVJiZxfc1O",
          "width": 640
        }
      }
    },
    "media:uri_template": "https://millsfield.sfomuseum.org/media/152/782/124/5/1527821245_{secret}_{label}.{extention}",
    "sfomuseum:filename": "38649.tif",
    "sfomuseum:image_index": 5,
    "sfomuseum:placetype": "image",
    "sfomuseum:primary_image": 1,
    "wof:depicts": [
      1511949737
    ],
    "wof:name": "negative: Mills Field Municipal Airport of San Francisco",
    "wof:placetype": "media"
  },
  "geometry": {"coordinates":[-122.386155,37.616358],"type":"Point"}
}
