{
  "type": "Feature",
  "properties": {
    "iso:country": "XX",
    "media:fingerprint": "d3ac83885ae1c5b095d4d03fb937c59346a316ea",
    "media:imagehash_avg": "a:ff380000ffffffff",
    "media:imagehash_diff": "d:eee071f3f1f94c58",
    "media:medium": "image",
    "media:mimetype": "image/tiff",
    "media:properties": {
      "colours": [
        {
          "hex": "#808080",
          "name": "#808080",
          "reference": "vibrant"
        },
        {
          "hex": "#b8b8b8",
          "name": "#b8b8b8",
          "reference": "vibrant"
        },
        {
          "hex": "#464646",
          "name": "#464646",
          "reference": "vibrant"
        }
      ],
      "sizes": {
        "b": {
          "extension": "jpg",
          "height": 767,
          "mimetype": "image/jpeg",
          "secret": "GrKrEdL7ohZMlgKXfz7evR5hkmcZSv3u",
          "width": 776
        },
        "c": {
          "extension": "jpg",
          "height": 600,
          "mimetype": "image/jpeg",
          "secret": "GrKrEdL7ohZMlgKXfz7evR5hkmcZSv3u",
          "width": 606
        },
        "dc": {
          "extension": "jpg",
          "height": 600,
          "mimetype": "image/jpeg",
          "secret": "GrKrEdL7ohZMlgKXfz7evR5hkmcZSv3u",
          "width": 606
        },
        "ds": {
          "extension": "jpg",
          "height": 320,
          "mimetype": "image/jpeg",
          "secret": "GrKrEdL7ohZMlgKXfz7evR5hkmcZSv3u",
          "width": 320
        },
        "k": {
          "extension": "jpg",
          "height": 1535,
          "mimetype": "image/jpeg",
          "secret": "GrKrEdL7ohZMlgKXfz7evR5hkmcZSv3u",
          "width": 1552
        },
        "n": {
          "extension": "jpg",
          "height": 240,
          "mimetype": "image/jpeg",
          "secret": "GrKrEdL7ohZMlgKXfz7evR5hkmcZSv3u",
          "width": 242
        },
        "o": {
          "extension": "jpg",
          "height": 2509,
          "mimetype": "image/jpeg",
          "secret": "dKwHZMH19sTRfDaL1cVNm7CjkNyPUTV9",
          "width": 2536
        },
        "s": {
          "extension": "jpg",
          "height": 320,
          "mimetype": "image/jpeg",
          "secret": "GrKrEdL7ohZMlgKXfz7evR5hkmcZSv3u",
          "width": 320
        },
        "z": {
          "extension": "jpg",
          "height": 480,
          "mimetype": "image/jpeg",
          "secret": "GrKrEdL7ohZMlgKXfz7evR5hkmcZSv3u",
          "width": 485
        }
      }
    },
    "media:uri_template": "https://static.sfomuseum.org/media/152/782/813/9/1527828139_{secret}_{label}.{extention}",
    "sfomuseum:filename": "44398.tif",
    "sfomuseum:image_index": 5,
    "sfomuseum:image_type": "studio",
    "sfomuseum:placetype": "image",
    "sfomuseum:primary_image": 1,
    "wof:depicts": [
      102527513,
      1511949171
    ],
    "wof:name": "photograph: San Francisco International Airport (SFO), South Terminal, Rotunda A construction",
    "wof:placetype": "custom",
    "wof:placetype_alt": "image"
  },
  "geometry": {"coordinates":[-122.386155,37.616358],"type":"Point"}
}
