{
  "type": "Feature",
  "properties": {
    "iso:country": "XX",
    "media:fingerprint": "cd40c042f63583f171e55e681300fb40d21ee6b3",
    "media:imagehash_avg": "a:637f3e8e18300301",
    "media:imagehash_diff": "d:c7c7d83ab072f6ef",
    "media:medium": "image",
    "media:mimetype": "image/tiff",
    "media:properties": {
      "colours": [
        {
          "hex": "#808080",
          "name": "#808080",
          "reference": "vibrant"
        }, 
        {
          "hex": "#c0c0c0",
          "name": "#c0c0c0",
          "reference": "vibrant"
        }, 
        {
          "hex": "#464646",
          "name": "#464646",
          "reference": "vibrant"
        }
      ],
      "sizes": {
        "b": {
          "extension": "jpg",
          "height": 768,
          "mimetype": "image/jpeg",
          "secret": "oe0MiYKcYiESMcjYa2XZ9myxGp9j39LW",
          "width": 764
        },
        "c": {
          "extension": "jpg",
          "height": 600,
          "mimetype": "image/jpeg",
          "secret": "oe0MiYKcYiESMcjYa2XZ9myxGp9j39LW",
          "width": 597
        },
        "dc": {
          "extension": "jpg",
          "height": 600,
          "mimetype": "image/jpeg",
          "secret": "oe0MiYKcYiESMcjYa2XZ9myxGp9j39LW",
          "width": 597
        },
        "ds": {
          "extension": "jpg",
          "height": 320,
          "mimetype": "image/jpeg",
          "secret": "oe0MiYKcYiESMcjYa2XZ9myxGp9j39LW",
          "width": 320
        },
        "k": {
          "extension": "jpg",
          "height": 1536,
          "mimetype": "image/jpeg",
          "secret": "oe0MiYKcYiESMcjYa2XZ9myxGp9j39LW",
          "width": 1529
        },
        "n": {
          "extension": "jpg",
          "height": 240,
          "mimetype": "image/jpeg",
          "secret": "oe0MiYKcYiESMcjYa2XZ9myxGp9j39LW",
          "width": 238
        },
        "o": {
          "extension": "jpg",
          "height": 2265,
          "mimetype": "image/jpeg",
          "secret": "dwpqivFT0oYuYkIOKktMpfytYNZHPwam",
          "width": 2255
        },
        "s": {
          "extension": "jpg",
          "height": 320,
          "mimetype": "image/jpeg",
          "secret": "oe0MiYKcYiESMcjYa2XZ9myxGp9j39LW",
          "width": 320
        },
        "z": {
          "extension": "jpg",
          "height": 480,
          "mimetype": "image/jpeg",
          "secret": "oe0MiYKcYiESMcjYa2XZ9myxGp9j39LW",
          "width": 477
        }
      }
    },
    "media:uri_template": "https://millsfield.sfomuseum.org/media/152/782/926/7/1527829267_{secret}_{label}.{extention}",
    "sfomuseum:filename": "47892.tif",
    "sfomuseum:image_index": 5,
    "sfomuseum:placetype": "image",
    "sfomuseum:primary_image": 1,
    "wof:depicts": [
      1511945143
    ],
    "wof:name": "photograph: San Francisco International Airport (SFO), United Airlines",
    "wof:placetype": "media"
  },
  "geometry": {"coordinates":[-122.386155,37.616358],"type":"Point"}
}
