{
  "type": "Feature",
  "properties": {
    "iso:country": "XX",
    "media:fingerprint": "4bca2992ed0984b1221cd02ba0925cbdaed88d37",
    "media:imagehash_avg": "a:c3878f8fa3030181",
    "media:imagehash_diff": "d:1b3b1959476f6f6f",
    "media:medium": "image",
    "media:mimetype": "image/tiff",
    "media:properties": {
      "colours": [
        {
          "hex": "#efe6dd",
          "name": "#efe6dd",
          "reference": "vibrant"
        },
        {
          "hex": "#858184",
          "name": "#858184",
          "reference": "vibrant"
        },
        {
          "hex": "#c0b8ba",
          "name": "#c0b8ba",
          "reference": "vibrant"
        },
        {
          "hex": "#3e3d41",
          "name": "#3e3d41",
          "reference": "vibrant"
        }
      ],
      "sizes": {
        "b": {
          "extension": "jpg",
          "height": 768,
          "mimetype": "image/jpeg",
          "secret": "UWZOcCrPY7NTULCuJlmpWO53038Ez2DK",
          "width": 600
        },
        "c": {
          "extension": "jpg",
          "height": 600,
          "mimetype": "image/jpeg",
          "secret": "UWZOcCrPY7NTULCuJlmpWO53038Ez2DK",
          "width": 469
        },
        "dc": {
          "extension": "jpg",
          "height": 600,
          "mimetype": "image/jpeg",
          "secret": "UWZOcCrPY7NTULCuJlmpWO53038Ez2DK",
          "width": 469
        },
        "ds": {
          "extension": "jpg",
          "height": 320,
          "mimetype": "image/jpeg",
          "secret": "UWZOcCrPY7NTULCuJlmpWO53038Ez2DK",
          "width": 320
        },
        "k": {
          "extension": "jpg",
          "height": 1536,
          "mimetype": "image/jpeg",
          "secret": "UWZOcCrPY7NTULCuJlmpWO53038Ez2DK",
          "width": 1200
        },
        "n": {
          "extension": "jpg",
          "height": 240,
          "mimetype": "image/jpeg",
          "secret": "UWZOcCrPY7NTULCuJlmpWO53038Ez2DK",
          "width": 187
        },
        "o": {
          "extension": "jpg",
          "height": 3324,
          "mimetype": "image/jpeg",
          "secret": "PVNmnQYFNVQjwPHI9l6Jk6AWHvWHKsSg",
          "width": 2599
        },
        "s": {
          "extension": "jpg",
          "height": 320,
          "mimetype": "image/jpeg",
          "secret": "UWZOcCrPY7NTULCuJlmpWO53038Ez2DK",
          "width": 320
        },
        "z": {
          "extension": "jpg",
          "height": 480,
          "mimetype": "image/jpeg",
          "secret": "UWZOcCrPY7NTULCuJlmpWO53038Ez2DK",
          "width": 375
        }
      }
    },
    "media:uri_template": "https://static.sfomuseum.org/media/152/785/350/3/1527853503_{secret}_{label}.{extention}",
    "sfomuseum:filename": "91509.tif",
    "sfomuseum:image_index": 5,
    "sfomuseum:image_type": "studio",
    "sfomuseum:placetype": "image",
    "sfomuseum:primary_image": 1,
    "wof:depicts": [
      1159285415,
      1511956565
    ],
    "wof:name": "photograph: United Air Lines, publicity photographs for Wing Tips employee newsletter, uniform drive",
    "wof:placetype": "custom",
    "wof:placetype_alt": "image"
  },
  "geometry": {"coordinates":[-122.386155,37.616358],"type":"Point"}
}
