{
  "type": "Feature",
  "properties": {
    "iso:country": "XX",
    "media:fingerprint": "47411a32edc65f33d2b19ee5329c2f5c5a251da1",
    "media:imagehash_avg": "a:ffe7c3c3c3c3e3ff",
    "media:imagehash_diff": "d:fcce9797979787e6",
    "media:medium": "image",
    "media:mimetype": "image/tiff",
    "media:properties": {
      "colours": [
        {
          "hex": "#d4471e",
          "name": "#d4471e",
          "reference": "vibrant"
        }, 
        {
          "hex": "#e78268",
          "name": "#e78268",
          "reference": "vibrant"
        }, 
        {
          "hex": "#a32806",
          "name": "#a32806",
          "reference": "vibrant"
        }, 
        {
          "hex": "#a6796f",
          "name": "#a6796f",
          "reference": "vibrant"
        }, 
        {
          "hex": "#b6b4b3",
          "name": "#b6b4b3",
          "reference": "vibrant"
        }
      ],
      "sizes": {
        "b": {
          "extension": "jpg",
          "height": 768,
          "mimetype": "image/jpeg",
          "secret": "ORJtfkOkpsJxo8v7hpR7AIgUEFiHBRs0",
          "width": 965
        },
        "c": {
          "extension": "jpg",
          "height": 600,
          "mimetype": "image/jpeg",
          "secret": "ORJtfkOkpsJxo8v7hpR7AIgUEFiHBRs0",
          "width": 754
        },
        "dc": {
          "extension": "jpg",
          "height": 600,
          "mimetype": "image/jpeg",
          "secret": "ORJtfkOkpsJxo8v7hpR7AIgUEFiHBRs0",
          "width": 754
        },
        "ds": {
          "extension": "jpg",
          "height": 320,
          "mimetype": "image/jpeg",
          "secret": "ORJtfkOkpsJxo8v7hpR7AIgUEFiHBRs0",
          "width": 320
        },
        "k": {
          "extension": "jpg",
          "height": 1536,
          "mimetype": "image/jpeg",
          "secret": "ORJtfkOkpsJxo8v7hpR7AIgUEFiHBRs0",
          "width": 1931
        },
        "n": {
          "extension": "jpg",
          "height": 240,
          "mimetype": "image/jpeg",
          "secret": "ORJtfkOkpsJxo8v7hpR7AIgUEFiHBRs0",
          "width": 301
        },
        "o": {
          "extension": "jpg",
          "height": 1326,
          "mimetype": "image/jpeg",
          "secret": "iLuvkmGmfAf078rf8fSgHojiO1yEiyVY",
          "width": 1667
        },
        "s": {
          "extension": "jpg",
          "height": 320,
          "mimetype": "image/jpeg",
          "secret": "ORJtfkOkpsJxo8v7hpR7AIgUEFiHBRs0",
          "width": 320
        },
        "z": {
          "extension": "jpg",
          "height": 480,
          "mimetype": "image/jpeg",
          "secret": "ORJtfkOkpsJxo8v7hpR7AIgUEFiHBRs0",
          "width": 603
        }
      }
    },
    "media:uri_template": "https://millsfield.sfomuseum.org/media/152/785/714/3/1527857143_{secret}_{label}.{extention}",
    "sfomuseum:filename": "2001.146.005ab_ft2.tif",
    "sfomuseum:image_index": 5,
    "sfomuseum:placetype": "image",
    "sfomuseum:primary_image": 0,
    "wof:depicts": [
      1511922379
    ],
    "wof:name": "airline bag: Aloha Airlines",
    "wof:placetype": "media"
  },
  "geometry": {"coordinates":[-122.386155,37.616358],"type":"Point"}
}
