{
  "type": "Feature",
  "properties": {
    "date:cessation_lower": "1915-01-01",
    "date:cessation_upper": "1915-12-31",
    "date:inception_lower": "1915-01-01",
    "date:inception_upper": "1915-12-31",
    "iso:country": "XX",
    "media:fingerprint": "ae37b0fb376815680fdcb731f1c924cea68f5457",
    "media:imagehash_avg": "a:ffe381818707c1ff",
    "media:imagehash_diff": "d:c3c707370f1f1511",
    "media:mimetype": "image/tiff",
    "media:properties": {
      "colours": [
        {
          "hex": "#82847d",
          "name": "#82847d",
          "reference": "vibrant"
        },
        {
          "hex": "#c5c6c0",
          "name": "#c5c6c0",
          "reference": "vibrant"
        },
        {
          "hex": "#464742",
          "name": "#464742",
          "reference": "vibrant"
        }
      ],
      "sizes": {
        "b": {
          "extension": "jpg",
          "height": 768,
          "mimetype": "image/jpeg",
          "secret": "pQ3phNbIHKucnK2cL0R5h7QgkqjvRVCU",
          "width": 981
        },
        "c": {
          "extension": "jpg",
          "height": 600,
          "mimetype": "image/jpeg",
          "secret": "pQ3phNbIHKucnK2cL0R5h7QgkqjvRVCU",
          "width": 766
        },
        "dc": {
          "extension": "jpg",
          "height": 600,
          "mimetype": "image/jpeg",
          "secret": "pQ3phNbIHKucnK2cL0R5h7QgkqjvRVCU",
          "width": 766
        },
        "ds": {
          "extension": "jpg",
          "height": 320,
          "mimetype": "image/jpeg",
          "secret": "pQ3phNbIHKucnK2cL0R5h7QgkqjvRVCU",
          "width": 320
        },
        "k": {
          "extension": "jpg",
          "height": 1536,
          "mimetype": "image/jpeg",
          "secret": "pQ3phNbIHKucnK2cL0R5h7QgkqjvRVCU",
          "width": 1962
        },
        "n": {
          "extension": "jpg",
          "height": 240,
          "mimetype": "image/jpeg",
          "secret": "pQ3phNbIHKucnK2cL0R5h7QgkqjvRVCU",
          "width": 306
        },
        "o": {
          "extension": "jpg",
          "height": 1565,
          "mimetype": "image/jpeg",
          "secret": "4T0X3NXLqjCXSAU7XqrFsQinECN6GCmY",
          "width": 2000
        },
        "s": {
          "extension": "jpg",
          "height": 320,
          "mimetype": "image/jpeg",
          "secret": "pQ3phNbIHKucnK2cL0R5h7QgkqjvRVCU",
          "width": 320
        },
        "z": {
          "extension": "jpg",
          "height": 480,
          "mimetype": "image/jpeg",
          "secret": "pQ3phNbIHKucnK2cL0R5h7QgkqjvRVCU",
          "width": 613
        }
      }
    },
    "media:uri_template": "https://static.sfomuseum.org/media/176/344/363/7/1763443637_{secret}_{label}.{extension}",
    "sfomuseum:filename": "126569.tif",
    "sfomuseum:image_index": 5,
    "sfomuseum:image_type": "studio",
    "sfomuseum:placetype": "image",
    "sfomuseum:primary_image": 1,
    "wof:depicts": [
      1511958233
    ],
    "wof:name": "photograph: Panama-Pacific International Exposition, Art Smith",
    "wof:placetype": "custom"
  },
  "geometry": {"coordinates":[-122.386155,37.616357],"type":"Point"}
}
