{
  "type": "Feature",
  "properties": {
    "iso:country": "XX",
    "media:fingerprint": "7c49a03506609120ead25991863b929165a1c2fd",
    "media:imagehash_avg": "a:4c6c7ea0c0e0e1f3",
    "media:imagehash_diff": "d:d8d85848868ccfc3",
    "media:medium": "image",
    "media:mimetype": "image/tiff",
    "media:properties": {
      "colours": [
        {
          "hex": "#868686",
          "name": "#868686",
          "reference": "vibrant"
        }, 
        {
          "hex": "#b8b8b8",
          "name": "#b8b8b8",
          "reference": "vibrant"
        }, 
        {
          "hex": "#484848",
          "name": "#484848",
          "reference": "vibrant"
        }
      ],
      "sizes": {
        "b": {
          "extension": "jpg",
          "height": 768,
          "mimetype": "image/jpeg",
          "secret": "JF8qsUc2r8nz3e2or5NtgqmkKhJPftOs",
          "width": 971
        },
        "c": {
          "extension": "jpg",
          "height": 600,
          "mimetype": "image/jpeg",
          "secret": "JF8qsUc2r8nz3e2or5NtgqmkKhJPftOs",
          "width": 759
        },
        "dc": {
          "extension": "jpg",
          "height": 600,
          "mimetype": "image/jpeg",
          "secret": "JF8qsUc2r8nz3e2or5NtgqmkKhJPftOs",
          "width": 759
        },
        "ds": {
          "extension": "jpg",
          "height": 320,
          "mimetype": "image/jpeg",
          "secret": "JF8qsUc2r8nz3e2or5NtgqmkKhJPftOs",
          "width": 320
        },
        "k": {
          "extension": "jpg",
          "height": 1536,
          "mimetype": "image/jpeg",
          "secret": "JF8qsUc2r8nz3e2or5NtgqmkKhJPftOs",
          "width": 1943
        },
        "n": {
          "extension": "jpg",
          "height": 240,
          "mimetype": "image/jpeg",
          "secret": "JF8qsUc2r8nz3e2or5NtgqmkKhJPftOs",
          "width": 303
        },
        "o": {
          "extension": "jpg",
          "height": 2209,
          "mimetype": "image/jpeg",
          "secret": "gmKMKgmu4mn0MtxrykF9VOrUAV0qw1iS",
          "width": 2795
        },
        "s": {
          "extension": "jpg",
          "height": 320,
          "mimetype": "image/jpeg",
          "secret": "JF8qsUc2r8nz3e2or5NtgqmkKhJPftOs",
          "width": 320
        },
        "z": {
          "extension": "jpg",
          "height": 480,
          "mimetype": "image/jpeg",
          "secret": "JF8qsUc2r8nz3e2or5NtgqmkKhJPftOs",
          "width": 607
        }
      }
    },
    "media:uri_template": "https://millsfield.sfomuseum.org/media/152/782/152/1/1527821521_{secret}_{label}.{extention}",
    "sfomuseum:filename": "38850.tif",
    "sfomuseum:image_index": 5,
    "sfomuseum:placetype": "image",
    "sfomuseum:primary_image": 1,
    "wof:depicts": [
      1511943605
    ],
    "wof:name": "negative: San Francisco International Airport (SFO), South Terminal construction",
    "wof:placetype": "media"
  },
  "geometry": {"coordinates":[-122.386155,37.616358],"type":"Point"}
}
