{
  "type": "Feature",
  "properties": {
    "iso:country": "XX",
    "media:fingerprint": "bfe6f81314c4d4d45761e0e390cc84373903f097",
    "media:imagehash_avg": "a:fcee869e8e8e877e",
    "media:imagehash_diff": "d:000a363636363e94",
    "media:medium": "image",
    "media:mimetype": "image/jpeg",
    "media:properties": {
      "colours": [
        {
          "hex": "#554521",
          "name": "#554521",
          "reference": "vibrant"
        },
        {
          "hex": "#857d7b",
          "name": "#857d7b",
          "reference": "vibrant"
        },
        {
          "hex": "#c8c8b8",
          "name": "#c8c8b8",
          "reference": "vibrant"
        },
        {
          "hex": "#524737",
          "name": "#524737",
          "reference": "vibrant"
        }
      ],
      "sizes": {
        "b": {
          "extension": "jpg",
          "height": 768,
          "mimetype": "image/jpeg",
          "secret": "KDHqilxBYcWPij9dDhVKWa48BgCPa8qJ",
          "width": 593
        },
        "c": {
          "extension": "jpg",
          "height": 600,
          "mimetype": "image/jpeg",
          "secret": "KDHqilxBYcWPij9dDhVKWa48BgCPa8qJ",
          "width": 464
        },
        "dc": {
          "extension": "jpg",
          "height": 600,
          "mimetype": "image/jpeg",
          "secret": "KDHqilxBYcWPij9dDhVKWa48BgCPa8qJ",
          "width": 464
        },
        "ds": {
          "extension": "jpg",
          "height": 320,
          "mimetype": "image/jpeg",
          "secret": "KDHqilxBYcWPij9dDhVKWa48BgCPa8qJ",
          "width": 320
        },
        "k": {
          "extension": "jpg",
          "height": 1536,
          "mimetype": "image/jpeg",
          "secret": "KDHqilxBYcWPij9dDhVKWa48BgCPa8qJ",
          "width": 1187
        },
        "n": {
          "extension": "jpg",
          "height": 240,
          "mimetype": "image/jpeg",
          "secret": "KDHqilxBYcWPij9dDhVKWa48BgCPa8qJ",
          "width": 185
        },
        "o": {
          "extension": "jpg",
          "height": 1761,
          "mimetype": "image/jpeg",
          "secret": "m0Ywy3Mn4agzgAaEBIN6cxLTJQZm6B8B",
          "width": 1362
        },
        "s": {
          "extension": "jpg",
          "height": 320,
          "mimetype": "image/jpeg",
          "secret": "KDHqilxBYcWPij9dDhVKWa48BgCPa8qJ",
          "width": 320
        },
        "z": {
          "extension": "jpg",
          "height": 480,
          "mimetype": "image/jpeg",
          "secret": "KDHqilxBYcWPij9dDhVKWa48BgCPa8qJ",
          "width": 371
        }
      }
    },
    "media:uri_template": "https://static.sfomuseum.org/media/152/785/165/3/1527851653_{secret}_{label}.{extention}",
    "sfomuseum:filename": "2002.134.120_ins.jpg",
    "sfomuseum:image_index": 5,
    "sfomuseum:image_type": "studio",
    "sfomuseum:placetype": "image",
    "sfomuseum:primary_image": 0,
    "wof:depicts": [
      1511924883
    ],
    "wof:name": "Airframe and powerplant mechanics certification guide",
    "wof:placetype": "custom",
    "wof:placetype_alt": "image"
  },
  "geometry": {"coordinates":[-122.386155,37.616358],"type":"Point"}
}
