{
  "type": "Feature",
  "properties": {
    "iso:country": "US",
    "media:fingerprint": "343c5c2dd226a0de19294a14ccfc59db4156c293",
    "media:imagehash_avg": "a:ffffff81818181e7",
    "media:imagehash_diff": "d:8f0f3f0327370b0b",
    "media:medium": "image",
    "media:mimetype": "image/tiff",
    "media:properties": {
      "colours": [
        {
          "hex": "#e17818",
          "name": "#e17818",
          "reference": "vibrant"
        }, 
        {
          "hex": "#e9865e",
          "name": "#e9865e",
          "reference": "vibrant"
        }, 
        {
          "hex": "#8e2411",
          "name": "#8e2411",
          "reference": "vibrant"
        }, 
        {
          "hex": "#5b8fad",
          "name": "#5b8fad",
          "reference": "vibrant"
        }, 
        {
          "hex": "#b0c4cf",
          "name": "#b0c4cf",
          "reference": "vibrant"
        }
      ],
      "sizes": {
        "b": {
          "extension": "jpg",
          "height": 768,
          "mimetype": "image/jpeg",
          "secret": "tUS8j0XI3WUyagxjHelzosBzj2rczjOX",
          "width": 362
        },
        "c": {
          "extension": "jpg",
          "height": 600,
          "mimetype": "image/jpeg",
          "secret": "tUS8j0XI3WUyagxjHelzosBzj2rczjOX",
          "width": 283
        },
        "dc": {
          "extension": "jpg",
          "height": 600,
          "mimetype": "image/jpeg",
          "secret": "tUS8j0XI3WUyagxjHelzosBzj2rczjOX",
          "width": 283
        },
        "ds": {
          "extension": "jpg",
          "height": 320,
          "mimetype": "image/jpeg",
          "secret": "tUS8j0XI3WUyagxjHelzosBzj2rczjOX",
          "width": 320
        },
        "k": {
          "extension": "jpg",
          "height": 1536,
          "mimetype": "image/jpeg",
          "secret": "tUS8j0XI3WUyagxjHelzosBzj2rczjOX",
          "width": 724
        },
        "n": {
          "extension": "jpg",
          "height": 240,
          "mimetype": "image/jpeg",
          "secret": "tUS8j0XI3WUyagxjHelzosBzj2rczjOX",
          "width": 113
        },
        "o": {
          "extension": "jpg",
          "height": 693,
          "mimetype": "image/jpeg",
          "secret": "mv8tvyDf9YJzQHp7Lwam85T8ZASQVFwU",
          "width": 327
        },
        "s": {
          "extension": "jpg",
          "height": 320,
          "mimetype": "image/jpeg",
          "secret": "tUS8j0XI3WUyagxjHelzosBzj2rczjOX",
          "width": 320
        },
        "z": {
          "extension": "jpg",
          "height": 480,
          "mimetype": "image/jpeg",
          "secret": "tUS8j0XI3WUyagxjHelzosBzj2rczjOX",
          "width": 226
        }
      }
    },
    "media:uri_template": "https://millsfield.sfomuseum.org/media/152/781/852/1/1527818521_{secret}_{label}.{extention}",
    "sfomuseum:filename": "19063.tif",
    "sfomuseum:image_index": 5,
    "sfomuseum:placetype": "image",
    "sfomuseum:primary_image": 1,
    "wof:depicts": [
      1511909885
    ],
    "wof:name": "timetable: United Airlines, European edition",
    "wof:placetype": "media"
  },
  "geometry": {"coordinates":[-122.386155,37.616358],"type":"Point"}
}
