{
  "type": "Feature",
  "properties": {
    "iso:country": "XX",
    "media:fingerprint": "e3b7d038c2470228d5fb3655e5149e26516d8e0a",
    "media:imagehash_avg": "a:ff918180808181ff",
    "media:imagehash_diff": "d:77736939213b1907",
    "media:medium": "image",
    "media:mimetype": "image/tiff",
    "media:properties": {
      "colours": [
        {
          "hex": "#ad7701",
          "name": "#ad7701",
          "reference": "vibrant"
        },
        {
          "hex": "#6a4209",
          "name": "#6a4209",
          "reference": "vibrant"
        },
        {
          "hex": "#5f958f",
          "name": "#5f958f",
          "reference": "vibrant"
        },
        {
          "hex": "#9db7bd",
          "name": "#9db7bd",
          "reference": "vibrant"
        },
        {
          "hex": "#4a7c59",
          "name": "#4a7c59",
          "reference": "vibrant"
        }
      ],
      "sizes": {
        "b": {
          "extension": "jpg",
          "height": 768,
          "mimetype": "image/jpeg",
          "secret": "HAqgzfDfPg7TZtkab0CPApxuYAvZDyYw",
          "width": 599
        },
        "c": {
          "extension": "jpg",
          "height": 600,
          "mimetype": "image/jpeg",
          "secret": "HAqgzfDfPg7TZtkab0CPApxuYAvZDyYw",
          "width": 468
        },
        "dc": {
          "extension": "jpg",
          "height": 600,
          "mimetype": "image/jpeg",
          "secret": "HAqgzfDfPg7TZtkab0CPApxuYAvZDyYw",
          "width": 468
        },
        "ds": {
          "extension": "jpg",
          "height": 320,
          "mimetype": "image/jpeg",
          "secret": "HAqgzfDfPg7TZtkab0CPApxuYAvZDyYw",
          "width": 320
        },
        "k": {
          "extension": "jpg",
          "height": 1536,
          "mimetype": "image/jpeg",
          "secret": "HAqgzfDfPg7TZtkab0CPApxuYAvZDyYw",
          "width": 1199
        },
        "n": {
          "extension": "jpg",
          "height": 240,
          "mimetype": "image/jpeg",
          "secret": "HAqgzfDfPg7TZtkab0CPApxuYAvZDyYw",
          "width": 187
        },
        "o": {
          "extension": "jpg",
          "height": 2139,
          "mimetype": "image/jpeg",
          "secret": "tBZYSpimz0GXKPtmTHC5BKbHL2UctoBk",
          "width": 1671
        },
        "s": {
          "extension": "jpg",
          "height": 320,
          "mimetype": "image/jpeg",
          "secret": "HAqgzfDfPg7TZtkab0CPApxuYAvZDyYw",
          "width": 320
        },
        "z": {
          "extension": "jpg",
          "height": 480,
          "mimetype": "image/jpeg",
          "secret": "HAqgzfDfPg7TZtkab0CPApxuYAvZDyYw",
          "width": 374
        }
      }
    },
    "media:uri_template": "https://static.sfomuseum.org/media/152/784/652/1/1527846521_{secret}_{label}.{extention}",
    "sfomuseum:filename": "2009021002_front.tif",
    "sfomuseum:image_index": 5,
    "sfomuseum:image_type": "studio",
    "sfomuseum:placetype": "image",
    "sfomuseum:primary_image": 1,
    "wof:depicts": [
      1511935129,
      1159287479,
      1159285043
    ],
    "wof:name": "menu: Qantas Airways, Economy Class",
    "wof:placetype": "custom",
    "wof:placetype_alt": "image"
  },
  "geometry": {"coordinates":[-122.386155,37.616358],"type":"Point"}
}
