{
  "type": "Feature",
  "properties": {
    "iso:country": "XX",
    "media:fingerprint": "64de2479ded126629b058f6af8066275ee0d31f8",
    "media:imagehash_avg": "a:ffffc3e7e7e78181",
    "media:imagehash_diff": "d:5f4f0f0f0f8f0727",
    "media:medium": "image",
    "media:mimetype": "image/tiff",
    "media:properties": {
      "colours": [
        {
          "hex": "#cda682",
          "name": "#cda682",
          "reference": "vibrant"
        }, 
        {
          "hex": "#f2bc95",
          "name": "#f2bc95",
          "reference": "vibrant"
        }, 
        {
          "hex": "#86797a",
          "name": "#86797a",
          "reference": "vibrant"
        }, 
        {
          "hex": "#cab6a3",
          "name": "#cab6a3",
          "reference": "vibrant"
        }, 
        {
          "hex": "#30385c",
          "name": "#30385c",
          "reference": "vibrant"
        }
      ],
      "sizes": {
        "b": {
          "extension": "jpg",
          "height": 768,
          "mimetype": "image/jpeg",
          "secret": "pAZFkHMUGPkV5SEWxpeFPIoT6UymOY7k",
          "width": 409
        },
        "c": {
          "extension": "jpg",
          "height": 600,
          "mimetype": "image/jpeg",
          "secret": "pAZFkHMUGPkV5SEWxpeFPIoT6UymOY7k",
          "width": 319
        },
        "dc": {
          "extension": "jpg",
          "height": 600,
          "mimetype": "image/jpeg",
          "secret": "pAZFkHMUGPkV5SEWxpeFPIoT6UymOY7k",
          "width": 319
        },
        "ds": {
          "extension": "jpg",
          "height": 320,
          "mimetype": "image/jpeg",
          "secret": "pAZFkHMUGPkV5SEWxpeFPIoT6UymOY7k",
          "width": 320
        },
        "k": {
          "extension": "jpg",
          "height": 1536,
          "mimetype": "image/jpeg",
          "secret": "pAZFkHMUGPkV5SEWxpeFPIoT6UymOY7k",
          "width": 818
        },
        "n": {
          "extension": "jpg",
          "height": 240,
          "mimetype": "image/jpeg",
          "secret": "pAZFkHMUGPkV5SEWxpeFPIoT6UymOY7k",
          "width": 127
        },
        "o": {
          "extension": "jpg",
          "height": 2916,
          "mimetype": "image/jpeg",
          "secret": "uQL5i4XNkGfrZHLi8slXiTWmEPhxSaCN",
          "width": 1554
        },
        "s": {
          "extension": "jpg",
          "height": 320,
          "mimetype": "image/jpeg",
          "secret": "pAZFkHMUGPkV5SEWxpeFPIoT6UymOY7k",
          "width": 320
        },
        "z": {
          "extension": "jpg",
          "height": 480,
          "mimetype": "image/jpeg",
          "secret": "pAZFkHMUGPkV5SEWxpeFPIoT6UymOY7k",
          "width": 255
        }
      }
    },
    "media:uri_template": "https://millsfield.sfomuseum.org/media/152/782/474/1/1527824741_{secret}_{label}.{extention}",
    "sfomuseum:filename": "42772.tif",
    "sfomuseum:image_index": 5,
    "sfomuseum:placetype": "image",
    "sfomuseum:primary_image": 1,
    "wof:depicts": [
      1511927423
    ],
    "wof:name": "airsickness bag: Dragonair",
    "wof:placetype": "media"
  },
  "geometry": {"coordinates":[-122.386155,37.616358],"type":"Point"}
}
