{
  "type": "Feature",
  "properties": {
    "iso:country": "XX",
    "media:fingerprint": "53b628c93772e94094ba01092d2e77aebe226e64",
    "media:imagehash_avg": "a:ff8b81818197ffff",
    "media:imagehash_diff": "d:1b3b3f1b0f2f356d",
    "media:medium": "image",
    "media:mimetype": "image/tiff",
    "media:properties": {
      "colours": [
        {
          "hex": "#d8c8a8",
          "name": "#d8c8a8",
          "reference": "vibrant"
        }, 
        {
          "hex": "#878379",
          "name": "#878379",
          "reference": "vibrant"
        }, 
        {
          "hex": "#cfc7a8",
          "name": "#cfc7a8",
          "reference": "vibrant"
        }, 
        {
          "hex": "#434346",
          "name": "#434346",
          "reference": "vibrant"
        }
      ],
      "sizes": {
        "b": {
          "extension": "jpg",
          "height": 768,
          "mimetype": "image/jpeg",
          "secret": "ch9UztNhKci3iVb4ebLZEvpPTXj83HEj",
          "width": 600
        },
        "c": {
          "extension": "jpg",
          "height": 600,
          "mimetype": "image/jpeg",
          "secret": "ch9UztNhKci3iVb4ebLZEvpPTXj83HEj",
          "width": 469
        },
        "dc": {
          "extension": "jpg",
          "height": 600,
          "mimetype": "image/jpeg",
          "secret": "ch9UztNhKci3iVb4ebLZEvpPTXj83HEj",
          "width": 469
        },
        "ds": {
          "extension": "jpg",
          "height": 320,
          "mimetype": "image/jpeg",
          "secret": "ch9UztNhKci3iVb4ebLZEvpPTXj83HEj",
          "width": 320
        },
        "k": {
          "extension": "jpg",
          "height": 1536,
          "mimetype": "image/jpeg",
          "secret": "ch9UztNhKci3iVb4ebLZEvpPTXj83HEj",
          "width": 1200
        },
        "n": {
          "extension": "jpg",
          "height": 240,
          "mimetype": "image/jpeg",
          "secret": "ch9UztNhKci3iVb4ebLZEvpPTXj83HEj",
          "width": 187
        },
        "o": {
          "extension": "jpg",
          "height": 1800,
          "mimetype": "image/jpeg",
          "secret": "nape2BPSX0Os0lLSfVu0fHfhwCTuqYe0",
          "width": 1407
        },
        "s": {
          "extension": "jpg",
          "height": 320,
          "mimetype": "image/jpeg",
          "secret": "ch9UztNhKci3iVb4ebLZEvpPTXj83HEj",
          "width": 320
        },
        "z": {
          "extension": "jpg",
          "height": 480,
          "mimetype": "image/jpeg",
          "secret": "ch9UztNhKci3iVb4ebLZEvpPTXj83HEj",
          "width": 375
        }
      }
    },
    "media:uri_template": "https://millsfield.sfomuseum.org/media/152/785/695/3/1527856953_{secret}_{label}.{extention}",
    "sfomuseum:filename": "2000.018.040.029.tif",
    "sfomuseum:image_index": 0,
    "sfomuseum:placetype": "image",
    "sfomuseum:primary_image": 1,
    "wof:depicts": [
      1511958005
    ],
    "wof:name": "correspondence: Joseph J. Phillips, Right of Way Agent for City and County of San Francisco",
    "wof:placetype": "media"
  },
  "geometry": {"coordinates":[-122.386155,37.616358],"type":"Point"}
}
