{
  "type": "Feature",
  "properties": {
    "date:cessation_lower": "1935-01-01",
    "date:cessation_upper": "1935-12-31",
    "date:inception_lower": "1935-01-01",
    "date:inception_upper": "1935-12-31",
    "iso:country": "XX",
    "media:fingerprint": "f30d209749ff69ad97547c8f0478851c319899f7",
    "media:imagehash_avg": "a:9f9f9fbfbf1f1c00",
    "media:imagehash_diff": "d:313171616161607d",
    "media:mimetype": "image/jpeg",
    "media:properties": {
      "colours": [
        {
          "hex": "#254d63",
          "name": "#254d63",
          "reference": "vibrant"
        },
        {
          "hex": "#8e7e67",
          "name": "#8e7e67",
          "reference": "vibrant"
        },
        {
          "hex": "#cac8ac",
          "name": "#cac8ac",
          "reference": "vibrant"
        },
        {
          "hex": "#3a4c50",
          "name": "#3a4c50",
          "reference": "vibrant"
        }
      ],
      "sizes": {
        "b": {
          "extension": "jpg",
          "height": 768,
          "mimetype": "image/jpeg",
          "secret": "lQfc6aYNG7rOB1WtY0e2RB4aji58pxMW",
          "width": 617
        },
        "c": {
          "extension": "jpg",
          "height": 600,
          "mimetype": "image/jpeg",
          "secret": "lQfc6aYNG7rOB1WtY0e2RB4aji58pxMW",
          "width": 482
        },
        "dc": {
          "extension": "jpg",
          "height": 600,
          "mimetype": "image/jpeg",
          "secret": "lQfc6aYNG7rOB1WtY0e2RB4aji58pxMW",
          "width": 482
        },
        "ds": {
          "extension": "jpg",
          "height": 320,
          "mimetype": "image/jpeg",
          "secret": "lQfc6aYNG7rOB1WtY0e2RB4aji58pxMW",
          "width": 320
        },
        "k": {
          "extension": "jpg",
          "height": 1536,
          "mimetype": "image/jpeg",
          "secret": "lQfc6aYNG7rOB1WtY0e2RB4aji58pxMW",
          "width": 1234
        },
        "n": {
          "extension": "jpg",
          "height": 240,
          "mimetype": "image/jpeg",
          "secret": "lQfc6aYNG7rOB1WtY0e2RB4aji58pxMW",
          "width": 192
        },
        "o": {
          "extension": "jpg",
          "height": 3274,
          "mimetype": "image/jpeg",
          "secret": "1at672mSfioN62AKW8KiTHTDIvMV82fL",
          "width": 2631
        },
        "s": {
          "extension": "jpg",
          "height": 320,
          "mimetype": "image/jpeg",
          "secret": "lQfc6aYNG7rOB1WtY0e2RB4aji58pxMW",
          "width": 320
        },
        "z": {
          "extension": "jpg",
          "height": 480,
          "mimetype": "image/jpeg",
          "secret": "lQfc6aYNG7rOB1WtY0e2RB4aji58pxMW",
          "width": 385
        }
      }
    },
    "media:uri_template": "https://static.sfomuseum.org/media/174/668/116/3/1746681163_{secret}_{label}.{extention}",
    "sfomuseum:filename": "IMG_5096.jpg",
    "sfomuseum:image_index": 0,
    "sfomuseum:image_type": "studio",
    "sfomuseum:placetype": "image",
    "sfomuseum:primary_image": 1,
    "wof:depicts": [
      1511920443
    ],
    "wof:name": "Discovery: the story of the second Byrd Antarctic expedition",
    "wof:placetype": "custom"
  },
  "geometry": {"coordinates":[-122.386155,37.616357],"type":"Point"}
}
