{
  "type": "Feature",
  "properties": {
    "date:cessation_lower": "1929-01-01",
    "date:cessation_upper": "1929-12-31",
    "date:inception_lower": "1929-01-01",
    "date:inception_upper": "1929-12-31",
    "iso:country": "XX",
    "media:imagehash_avg": "a:fdc3feff0f000000",
    "media:imagehash_diff": "d:1107c8787d7f6747",
    "media:imagetext": "FLIGHT\nBY IRWIN. R. FRANKLY\nAdapted from\nCOLUMBIA PICTURE\nCORPORATION'S\nALL - TALKING\nSCREEN. PLAY\nA GREAT EPIC OF THE AIR\nIllustrated\nwith Scenes from\nthe Photoplay",
    "media:imagetext_created": 1701940819,
    "media:mimetype": "image/jpeg",
    "media:properties": {
    },
    "media:uri_template": "https://static.sfomuseum.org/media/174/668/039/3/1746680393_{secret}_{label}.{extension}",
    "millsfield:exhibition_ids": [
      1159160363
    ],
    "millsfield:images_colors": [
      {
        "hex": "#305559",
        "name": "#305559",
        "reference": "marekm4"
      },
      {
        "hex": "#2f4f4f",
        "name": "darkslategrey",
        "reference": "css4"
      },
      {
        "hex": "#414a4c",
        "name": "Outer Space",
        "reference": "crayola"
      },
      {
        "hex": "#eab659",
        "name": "#eab659",
        "reference": "marekm4"
      },
      {
        "hex": "#f4a460",
        "name": "sandybrown",
        "reference": "css4"
      },
      {
        "hex": "#faa76c",
        "name": "Tan",
        "reference": "crayola"
      },
      {
        "hex": "#af6b2f",
        "name": "#af6b2f",
        "reference": "marekm4"
      },
      {
        "hex": "#a0522d",
        "name": "sienna",
        "reference": "css4"
      },
      {
        "hex": "#9c7c38",
        "name": "Metallic Sunburst",
        "reference": "crayola"
      },
      {
        "hex": "#f1e29a",
        "name": "#f1e29a",
        "reference": "marekm4"
      },
      {
        "hex": "#f0e68c",
        "name": "khaki",
        "reference": "css4"
      },
      {
        "hex": "#f0e891",
        "name": "Green Yellow",
        "reference": "crayola"
      },
      {
        "hex": "#3a7085",
        "name": "#3a7085",
        "reference": "marekm4"
      },
      {
        "hex": "#4682b4",
        "name": "steelblue",
        "reference": "css4"
      },
      {
        "hex": "#2e5894",
        "name": "B'dazzled Blue",
        "reference": "crayola"
      }
    ],
    "millsfield:images_texts": [
      "FLIGHT\nBY IRWIN. R. FRANKLY\nAdapted from\nCOLUMBIA PICTURE\nCORPORATION'S\nALL - TALKING\nSCREEN. PLAY\nA GREAT EPIC OF THE AIR\nIllustrated\nwith Scenes from\nthe Photoplay"
    ],
    "millsfield:images_texts_ids": [
      1746680393
    ],
    "millsfield:on_view": 0,
    "sfomuseum:filename": "57529.jpg",
    "sfomuseum:image_index": 0,
    "sfomuseum:image_type": "studio",
    "sfomuseum:placetype": "image",
    "sfomuseum:primary_image": 1,
    "wof:depicts": [
      1511913029
    ],
    "wof:name": "Flight: an epic of the air",
    "wof:placetype": "custom",
    "wof:placetype_alt": [
      "image"
    ]
  },
  "geometry": {"type":"Point","coordinates":[-122.386155,37.616357]}
}
