{
  "type": "Feature",
  "properties": {
    "iso:country": "XX",
    "media:fingerprint": "d0cdb66c842901beb66a3a23e9aefbedcc77fb06",
    "media:imagehash_avg": "a:ffffff0000000007",
    "media:imagehash_diff": "d:064e7f7360627f7f",
    "media:medium": "image",
    "media:mimetype": "image/tiff",
    "media:properties": {
      "colours": [
        {
          "hex": "#c80f15",
          "name": "#c80f15",
          "reference": "vibrant"
        },
        {
          "hex": "#d78b92",
          "name": "#d78b92",
          "reference": "vibrant"
        },
        {
          "hex": "#b20b15",
          "name": "#b20b15",
          "reference": "vibrant"
        },
        {
          "hex": "#a37d83",
          "name": "#a37d83",
          "reference": "vibrant"
        },
        {
          "hex": "#d5b4b3",
          "name": "#d5b4b3",
          "reference": "vibrant"
        }
      ],
      "sizes": {
        "b": {
          "extension": "jpg",
          "height": 768,
          "mimetype": "image/jpeg",
          "secret": "uxpiIn87lpQojixXezwIcPkx0FLuP4kM",
          "width": 467
        },
        "c": {
          "extension": "jpg",
          "height": 600,
          "mimetype": "image/jpeg",
          "secret": "uxpiIn87lpQojixXezwIcPkx0FLuP4kM",
          "width": 364
        },
        "dc": {
          "extension": "jpg",
          "height": 600,
          "mimetype": "image/jpeg",
          "secret": "uxpiIn87lpQojixXezwIcPkx0FLuP4kM",
          "width": 364
        },
        "ds": {
          "extension": "jpg",
          "height": 320,
          "mimetype": "image/jpeg",
          "secret": "uxpiIn87lpQojixXezwIcPkx0FLuP4kM",
          "width": 320
        },
        "k": {
          "extension": "jpg",
          "height": 1536,
          "mimetype": "image/jpeg",
          "secret": "uxpiIn87lpQojixXezwIcPkx0FLuP4kM",
          "width": 934
        },
        "n": {
          "extension": "jpg",
          "height": 240,
          "mimetype": "image/jpeg",
          "secret": "uxpiIn87lpQojixXezwIcPkx0FLuP4kM",
          "width": 145
        },
        "o": {
          "extension": "jpg",
          "height": 3398,
          "mimetype": "image/jpeg",
          "secret": "KTcfqxkRqhlVMVTviagjivUO91g5Hz2U",
          "width": 2067
        },
        "s": {
          "extension": "jpg",
          "height": 320,
          "mimetype": "image/jpeg",
          "secret": "uxpiIn87lpQojixXezwIcPkx0FLuP4kM",
          "width": 320
        },
        "z": {
          "extension": "jpg",
          "height": 480,
          "mimetype": "image/jpeg",
          "secret": "uxpiIn87lpQojixXezwIcPkx0FLuP4kM",
          "width": 291
        }
      }
    },
    "media:uri_template": "https://static.sfomuseum.org/media/152/784/391/3/1527843913_{secret}_{label}.{extention}",
    "sfomuseum:filename": "68736.tif",
    "sfomuseum:image_index": 5,
    "sfomuseum:image_type": "studio",
    "sfomuseum:placetype": "image",
    "sfomuseum:primary_image": 1,
    "wof:depicts": [
      1159287865,
      1159283917,
      1511930581
    ],
    "wof:name": "menu: Asiana Airlines, First Class",
    "wof:placetype": "custom",
    "wof:placetype_alt": "image"
  },
  "geometry": {"coordinates":[-122.386155,37.616358],"type":"Point"}
}
