{
  "type": "Feature",
  "properties": {
    "iso:country": "XX",
    "media:fingerprint": "056f5a9f89d78c947bbb41d3a5e45f3d4e54fbac",
    "media:imagehash_avg": "a:fffff9d081010010",
    "media:imagehash_diff": "d:eee7a3a92929a1a1",
    "media:medium": "image",
    "media:mimetype": "image/tiff",
    "media:properties": {
      "colours": [
        {
          "hex": "#e07640",
          "name": "#e07640",
          "reference": "vibrant"
        }, 
        {
          "hex": "#8bb2da",
          "name": "#8bb2da",
          "reference": "vibrant"
        }, 
        {
          "hex": "#b07653",
          "name": "#b07653",
          "reference": "vibrant"
        }, 
        {
          "hex": "#bdc6bb",
          "name": "#bdc6bb",
          "reference": "vibrant"
        }, 
        {
          "hex": "#404846",
          "name": "#404846",
          "reference": "vibrant"
        }
      ],
      "sizes": {
        "b": {
          "extension": "jpg",
          "height": 657,
          "mimetype": "image/jpeg",
          "secret": "6Zruzigfx1Dk72AQcLqk1HOUzDkj7YeF",
          "width": 1024
        },
        "c": {
          "extension": "jpg",
          "height": 513,
          "mimetype": "image/jpeg",
          "secret": "6Zruzigfx1Dk72AQcLqk1HOUzDkj7YeF",
          "width": 800
        },
        "dc": {
          "extension": "jpg",
          "height": 513,
          "mimetype": "image/jpeg",
          "secret": "6Zruzigfx1Dk72AQcLqk1HOUzDkj7YeF",
          "width": 800
        },
        "ds": {
          "extension": "jpg",
          "height": 320,
          "mimetype": "image/jpeg",
          "secret": "6Zruzigfx1Dk72AQcLqk1HOUzDkj7YeF",
          "width": 320
        },
        "k": {
          "extension": "jpg",
          "height": 1314,
          "mimetype": "image/jpeg",
          "secret": "6Zruzigfx1Dk72AQcLqk1HOUzDkj7YeF",
          "width": 2048
        },
        "n": {
          "extension": "jpg",
          "height": 205,
          "mimetype": "image/jpeg",
          "secret": "6Zruzigfx1Dk72AQcLqk1HOUzDkj7YeF",
          "width": 320
        },
        "o": {
          "extension": "jpg",
          "height": 1060,
          "mimetype": "image/jpeg",
          "secret": "U1zSZKY0d9gQefO3LJYWujsU12O41brM",
          "width": 1652
        },
        "s": {
          "extension": "jpg",
          "height": 320,
          "mimetype": "image/jpeg",
          "secret": "6Zruzigfx1Dk72AQcLqk1HOUzDkj7YeF",
          "width": 320
        },
        "z": {
          "extension": "jpg",
          "height": 410,
          "mimetype": "image/jpeg",
          "secret": "6Zruzigfx1Dk72AQcLqk1HOUzDkj7YeF",
          "width": 640
        }
      }
    },
    "media:uri_template": "https://millsfield.sfomuseum.org/media/152/782/766/7/1527827667_{secret}_{label}.{extention}",
    "sfomuseum:filename": "44189.tif",
    "sfomuseum:image_index": 5,
    "sfomuseum:placetype": "image",
    "sfomuseum:primary_image": 1,
    "wof:depicts": [
      1511948701
    ],
    "wof:name": "negative: San Francisco International Airport (SFO), personnel",
    "wof:placetype": "media"
  },
  "geometry": {"coordinates":[-122.386155,37.616358],"type":"Point"}
}
