{
  "type": "Feature",
  "properties": {
    "iso:country": "XX",
    "media:fingerprint": "fb364b624e931088e8a1e208974238047f0aced5",
    "media:imagehash_avg": "a:ffffff80c000f0e0",
    "media:imagehash_diff": "d:13b353480b002180",
    "media:medium": "image",
    "media:mimetype": "image/tiff",
    "media:properties": {
      "colours": [
        {
          "hex": "#808080",
          "name": "#808080",
          "reference": "vibrant"
        }, 
        {
          "hex": "#c0c0c0",
          "name": "#c0c0c0",
          "reference": "vibrant"
        }, 
        {
          "hex": "#464646",
          "name": "#464646",
          "reference": "vibrant"
        }
      ],
      "sizes": {
        "b": {
          "extension": "jpg",
          "height": 768,
          "mimetype": "image/jpeg",
          "secret": "CrOIV12rx03Rosi2EL4uInPpwABFkAyJ",
          "width": 751
        },
        "c": {
          "extension": "jpg",
          "height": 600,
          "mimetype": "image/jpeg",
          "secret": "CrOIV12rx03Rosi2EL4uInPpwABFkAyJ",
          "width": 587
        },
        "dc": {
          "extension": "jpg",
          "height": 600,
          "mimetype": "image/jpeg",
          "secret": "CrOIV12rx03Rosi2EL4uInPpwABFkAyJ",
          "width": 587
        },
        "ds": {
          "extension": "jpg",
          "height": 320,
          "mimetype": "image/jpeg",
          "secret": "CrOIV12rx03Rosi2EL4uInPpwABFkAyJ",
          "width": 320
        },
        "k": {
          "extension": "jpg",
          "height": 1536,
          "mimetype": "image/jpeg",
          "secret": "CrOIV12rx03Rosi2EL4uInPpwABFkAyJ",
          "width": 1503
        },
        "n": {
          "extension": "jpg",
          "height": 240,
          "mimetype": "image/jpeg",
          "secret": "CrOIV12rx03Rosi2EL4uInPpwABFkAyJ",
          "width": 234
        },
        "o": {
          "extension": "jpg",
          "height": 2590,
          "mimetype": "image/jpeg",
          "secret": "Xvt3MDMdIeTEmwLeB9ALV95bK83TN034",
          "width": 2536
        },
        "s": {
          "extension": "jpg",
          "height": 320,
          "mimetype": "image/jpeg",
          "secret": "CrOIV12rx03Rosi2EL4uInPpwABFkAyJ",
          "width": 320
        },
        "z": {
          "extension": "jpg",
          "height": 480,
          "mimetype": "image/jpeg",
          "secret": "CrOIV12rx03Rosi2EL4uInPpwABFkAyJ",
          "width": 469
        }
      }
    },
    "media:uri_template": "https://millsfield.sfomuseum.org/media/152/782/692/7/1527826927_{secret}_{label}.{extention}",
    "sfomuseum:filename": "43859.tif",
    "sfomuseum:image_index": 5,
    "sfomuseum:placetype": "image",
    "sfomuseum:primary_image": 1,
    "wof:depicts": [
      1511947965
    ],
    "wof:name": "negative: San Francisco International Airport (SFO), parking garage construction",
    "wof:placetype": "media"
  },
  "geometry": {"coordinates":[-122.386155,37.616358],"type":"Point"}
}
