{
  "type": "Feature",
  "properties": {
    "iso:country": "XX",
    "media:fingerprint": "c0ba94fdea1c5f392bba7e2b73919c712cb75848",
    "media:imagehash_avg": "a:7c5f0f9f2f008486",
    "media:imagehash_diff": "d:b0bc3c5d59590c6c",
    "media:medium": "image",
    "media:mimetype": "image/tiff",
    "media:properties": {
      "colours": [
        {
          "hex": "#e8f5e7",
          "name": "#e8f5e7",
          "reference": "vibrant"
        }, 
        {
          "hex": "#6b8872",
          "name": "#6b8872",
          "reference": "vibrant"
        }, 
        {
          "hex": "#b9d4b7",
          "name": "#b9d4b7",
          "reference": "vibrant"
        }, 
        {
          "hex": "#36433e",
          "name": "#36433e",
          "reference": "vibrant"
        }
      ],
      "sizes": {
        "b": {
          "extension": "jpg",
          "height": 654,
          "mimetype": "image/jpeg",
          "secret": "4aj1uISd7yWzHOWYt8SVmfwQn7tcHMhU",
          "width": 1024
        },
        "c": {
          "extension": "jpg",
          "height": 511,
          "mimetype": "image/jpeg",
          "secret": "4aj1uISd7yWzHOWYt8SVmfwQn7tcHMhU",
          "width": 800
        },
        "dc": {
          "extension": "jpg",
          "height": 511,
          "mimetype": "image/jpeg",
          "secret": "4aj1uISd7yWzHOWYt8SVmfwQn7tcHMhU",
          "width": 800
        },
        "ds": {
          "extension": "jpg",
          "height": 320,
          "mimetype": "image/jpeg",
          "secret": "4aj1uISd7yWzHOWYt8SVmfwQn7tcHMhU",
          "width": 320
        },
        "k": {
          "extension": "jpg",
          "height": 1309,
          "mimetype": "image/jpeg",
          "secret": "4aj1uISd7yWzHOWYt8SVmfwQn7tcHMhU",
          "width": 2048
        },
        "n": {
          "extension": "jpg",
          "height": 204,
          "mimetype": "image/jpeg",
          "secret": "4aj1uISd7yWzHOWYt8SVmfwQn7tcHMhU",
          "width": 320
        },
        "o": {
          "extension": "jpg",
          "height": 1063,
          "mimetype": "image/jpeg",
          "secret": "JY9CSbXWoHzBCjCQO7mJrsIc0FQ7NJXe",
          "width": 1663
        },
        "s": {
          "extension": "jpg",
          "height": 320,
          "mimetype": "image/jpeg",
          "secret": "4aj1uISd7yWzHOWYt8SVmfwQn7tcHMhU",
          "width": 320
        },
        "z": {
          "extension": "jpg",
          "height": 409,
          "mimetype": "image/jpeg",
          "secret": "4aj1uISd7yWzHOWYt8SVmfwQn7tcHMhU",
          "width": 640
        }
      }
    },
    "media:uri_template": "https://millsfield.sfomuseum.org/media/152/782/847/7/1527828477_{secret}_{label}.{extention}",
    "sfomuseum:filename": "44616.tif",
    "sfomuseum:image_index": 5,
    "sfomuseum:placetype": "image",
    "sfomuseum:primary_image": 1,
    "wof:depicts": [
      1511949509
    ],
    "wof:name": "negative: San Francisco International Airport (SFO), medical clinic",
    "wof:placetype": "media"
  },
  "geometry": {"coordinates":[-122.386155,37.616358],"type":"Point"}
}
