{
  "type": "Feature",
  "properties": {
    "media:fingerprint": "2fcba02df3ead4fed59690c2abed8dd434082fc3",
    "media:imagehash_avg": "a:fffffbe0c0c0e000",
    "media:imagehash_diff": "d:c4c6c68311888400",
    "media:mimetype": "image/tiff",
    "media:properties": {
      "colours": [
        {
          "hex": "#808080",
          "name": "#808080",
          "reference": "vibrant"
        },
        {
          "hex": "#c0c0c0",
          "name": "#c0c0c0",
          "reference": "vibrant"
        },
        {
          "hex": "#464646",
          "name": "#464646",
          "reference": "vibrant"
        }
      ],
      "sizes": {
        "b": {
          "extension": "jpg",
          "height": 768,
          "mimetype": "image/jpeg",
          "secret": "R2rgxhnBjeD3wqEWtDTFuKGgD1jvI4DP",
          "width": 602
        },
        "c": {
          "extension": "jpg",
          "height": 600,
          "mimetype": "image/jpeg",
          "secret": "R2rgxhnBjeD3wqEWtDTFuKGgD1jvI4DP",
          "width": 470
        },
        "dc": {
          "extension": "jpg",
          "height": 600,
          "mimetype": "image/jpeg",
          "secret": "R2rgxhnBjeD3wqEWtDTFuKGgD1jvI4DP",
          "width": 470
        },
        "ds": {
          "extension": "jpg",
          "height": 320,
          "mimetype": "image/jpeg",
          "secret": "R2rgxhnBjeD3wqEWtDTFuKGgD1jvI4DP",
          "width": 320
        },
        "k": {
          "extension": "jpg",
          "height": 1536,
          "mimetype": "image/jpeg",
          "secret": "R2rgxhnBjeD3wqEWtDTFuKGgD1jvI4DP",
          "width": 1204
        },
        "n": {
          "extension": "jpg",
          "height": 239,
          "mimetype": "image/jpeg",
          "secret": "R2rgxhnBjeD3wqEWtDTFuKGgD1jvI4DP",
          "width": 188
        },
        "o": {
          "extension": "jpg",
          "height": 2713,
          "mimetype": "image/jpeg",
          "secret": "NPsJBpqWdfqTOcXg23duUJqKzIKgkU5y",
          "width": 2127
        },
        "s": {
          "extension": "jpg",
          "height": 320,
          "mimetype": "image/jpeg",
          "secret": "R2rgxhnBjeD3wqEWtDTFuKGgD1jvI4DP",
          "width": 320
        },
        "z": {
          "extension": "jpg",
          "height": 479,
          "mimetype": "image/jpeg",
          "secret": "R2rgxhnBjeD3wqEWtDTFuKGgD1jvI4DP",
          "width": 376
        }
      }
    },
    "media:uri_template": "https://static.sfomuseum.org/media/174/651/209/9/1746512099_{secret}_{label}.{extention}",
    "sfomuseum:filename": "45972.tif",
    "sfomuseum:image_index": 0,
    "sfomuseum:image_type": "studio",
    "sfomuseum:placetype": "image",
    "sfomuseum:primary_image": 1,
    "wof:depicts": [
      1159285393,
      1729563761
    ],
    "wof:name": "negative: TWA (Trans World Airlines), George O. Thornley",
    "wof:placetype": "custom",
    "wof:placetype_alt": "image"
  },
  "geometry": {"coordinates":[-122.386155,37.616357],"type":"Point"}
}
