{
  "type": "Feature",
  "properties": {
    "iso:country": "XX",
    "media:fingerprint": "779991cf9cc246af898e45f31a1a3cbc4ffdac5e",
    "media:imagehash_avg": "a:fefcfe9e88889888",
    "media:imagehash_diff": "d:a060303030787272",
    "media:medium": "image",
    "media:mimetype": "image/tiff",
    "media:properties": {
      "colours": [
        {
          "hex": "#868686",
          "name": "#868686",
          "reference": "vibrant"
        },
        {
          "hex": "#b8b8b8",
          "name": "#b8b8b8",
          "reference": "vibrant"
        },
        {
          "hex": "#484848",
          "name": "#484848",
          "reference": "vibrant"
        }
      ],
      "sizes": {
        "b": {
          "extension": "jpg",
          "height": 767,
          "mimetype": "image/jpeg",
          "secret": "dfd9soxNXc8fq0yPlZi6t9iXyEwKTQuT",
          "width": 978
        },
        "c": {
          "extension": "jpg",
          "height": 600,
          "mimetype": "image/jpeg",
          "secret": "dfd9soxNXc8fq0yPlZi6t9iXyEwKTQuT",
          "width": 764
        },
        "dc": {
          "extension": "jpg",
          "height": 600,
          "mimetype": "image/jpeg",
          "secret": "dfd9soxNXc8fq0yPlZi6t9iXyEwKTQuT",
          "width": 764
        },
        "ds": {
          "extension": "jpg",
          "height": 320,
          "mimetype": "image/jpeg",
          "secret": "dfd9soxNXc8fq0yPlZi6t9iXyEwKTQuT",
          "width": 320
        },
        "k": {
          "extension": "jpg",
          "height": 1535,
          "mimetype": "image/jpeg",
          "secret": "dfd9soxNXc8fq0yPlZi6t9iXyEwKTQuT",
          "width": 1957
        },
        "n": {
          "extension": "jpg",
          "height": 240,
          "mimetype": "image/jpeg",
          "secret": "dfd9soxNXc8fq0yPlZi6t9iXyEwKTQuT",
          "width": 305
        },
        "o": {
          "extension": "jpg",
          "height": 2140,
          "mimetype": "image/jpeg",
          "secret": "VJQpiNYcl0KUwnvbdoODTZSABELOzVCx",
          "width": 2727
        },
        "s": {
          "extension": "jpg",
          "height": 320,
          "mimetype": "image/jpeg",
          "secret": "dfd9soxNXc8fq0yPlZi6t9iXyEwKTQuT",
          "width": 320
        },
        "z": {
          "extension": "jpg",
          "height": 480,
          "mimetype": "image/jpeg",
          "secret": "dfd9soxNXc8fq0yPlZi6t9iXyEwKTQuT",
          "width": 611
        }
      }
    },
    "media:uri_template": "https://static.sfomuseum.org/media/152/782/283/3/1527822833_{secret}_{label}.{extention}",
    "sfomuseum:filename": "41094.tif",
    "sfomuseum:image_index": 5,
    "sfomuseum:image_type": "studio",
    "sfomuseum:placetype": "image",
    "sfomuseum:primary_image": 1,
    "wof:depicts": [
      102527513,
      1511944727
    ],
    "wof:name": "negative: San Francisco International Airport (SFO), Stuart N. Greenberg and Oral L. Moore",
    "wof:placetype": "custom",
    "wof:placetype_alt": "image"
  },
  "geometry": {"coordinates":[-122.386155,37.616358],"type":"Point"}
}
