{
  "type": "Feature",
  "properties": {
    "iso:country": "XX",
    "media:fingerprint": "9c8a6b2e49513951965aea9c050f426ea6eae841",
    "media:imagehash_avg": "a:ff8181819f8181ff",
    "media:imagehash_diff": "d:4343232b3f7f3f1f",
    "media:medium": "image",
    "media:mimetype": "image/tiff",
    "media:properties": {
      "colours": [
        {
          "hex": "#e0d8be",
          "name": "#e0d8be",
          "reference": "vibrant"
        },
        {
          "hex": "#848372",
          "name": "#848372",
          "reference": "vibrant"
        },
        {
          "hex": "#c4c1ae",
          "name": "#c4c1ae",
          "reference": "vibrant"
        },
        {
          "hex": "#464736",
          "name": "#464736",
          "reference": "vibrant"
        }
      ],
      "sizes": {
        "b": {
          "extension": "jpg",
          "height": 759,
          "mimetype": "image/jpeg",
          "secret": "StTK6TvnAZGs7iEK3nR9LdYDo7VgxKXw",
          "width": 1024
        },
        "c": {
          "extension": "jpg",
          "height": 593,
          "mimetype": "image/jpeg",
          "secret": "StTK6TvnAZGs7iEK3nR9LdYDo7VgxKXw",
          "width": 800
        },
        "dc": {
          "extension": "jpg",
          "height": 593,
          "mimetype": "image/jpeg",
          "secret": "StTK6TvnAZGs7iEK3nR9LdYDo7VgxKXw",
          "width": 800
        },
        "ds": {
          "extension": "jpg",
          "height": 320,
          "mimetype": "image/jpeg",
          "secret": "StTK6TvnAZGs7iEK3nR9LdYDo7VgxKXw",
          "width": 320
        },
        "k": {
          "extension": "jpg",
          "height": 1518,
          "mimetype": "image/jpeg",
          "secret": "StTK6TvnAZGs7iEK3nR9LdYDo7VgxKXw",
          "width": 2048
        },
        "n": {
          "extension": "jpg",
          "height": 237,
          "mimetype": "image/jpeg",
          "secret": "StTK6TvnAZGs7iEK3nR9LdYDo7VgxKXw",
          "width": 320
        },
        "o": {
          "extension": "jpg",
          "height": 981,
          "mimetype": "image/jpeg",
          "secret": "N3ft3RbXB5mhGdo5wKr2rfaJYr2DAqo9",
          "width": 1323
        },
        "s": {
          "extension": "jpg",
          "height": 320,
          "mimetype": "image/jpeg",
          "secret": "StTK6TvnAZGs7iEK3nR9LdYDo7VgxKXw",
          "width": 320
        },
        "z": {
          "extension": "jpg",
          "height": 474,
          "mimetype": "image/jpeg",
          "secret": "StTK6TvnAZGs7iEK3nR9LdYDo7VgxKXw",
          "width": 640
        }
      }
    },
    "media:uri_template": "https://static.sfomuseum.org/media/152/785/541/9/1527855419_{secret}_{label}.{extention}",
    "sfomuseum:filename": "2010.174.211.tif",
    "sfomuseum:image_index": 5,
    "sfomuseum:image_type": "studio",
    "sfomuseum:placetype": "image",
    "sfomuseum:primary_image": 1,
    "wof:depicts": [
      1511942177
    ],
    "wof:name": "photograph: San Francisco Bay Area aerial, San Francisco Bay",
    "wof:placetype": "custom",
    "wof:placetype_alt": "image"
  },
  "geometry": {"coordinates":[-122.386155,37.616358],"type":"Point"}
}
