{
  "type": "Feature",
  "properties": {
    "iso:country": "XX",
    "media:fingerprint": "84af7d53a6a56546005879a8f81174ffbd5ccc0f",
    "media:imagehash_avg": "a:01f8f8f9fffef9e8",
    "media:imagehash_diff": "d:7be1e171c26461a3",
    "media:medium": "image",
    "media:mimetype": "image/tiff",
    "media:properties": {
      "colours": [
        {
          "hex": "#b52f14",
          "name": "#b52f14",
          "reference": "vibrant"
        }, 
        {
          "hex": "#d5c29d",
          "name": "#d5c29d",
          "reference": "vibrant"
        }, 
        {
          "hex": "#a62209",
          "name": "#a62209",
          "reference": "vibrant"
        }, 
        {
          "hex": "#938257",
          "name": "#938257",
          "reference": "vibrant"
        }, 
        {
          "hex": "#c8b888",
          "name": "#c8b888",
          "reference": "vibrant"
        }
      ],
      "sizes": {
        "b": {
          "extension": "jpg",
          "height": 586,
          "mimetype": "image/jpeg",
          "secret": "s9NSeApKe5b0LZzhsVoe2h2MoE6iHmEm",
          "width": 1024
        },
        "c": {
          "extension": "jpg",
          "height": 457,
          "mimetype": "image/jpeg",
          "secret": "s9NSeApKe5b0LZzhsVoe2h2MoE6iHmEm",
          "width": 800
        },
        "dc": {
          "extension": "jpg",
          "height": 457,
          "mimetype": "image/jpeg",
          "secret": "s9NSeApKe5b0LZzhsVoe2h2MoE6iHmEm",
          "width": 800
        },
        "ds": {
          "extension": "jpg",
          "height": 320,
          "mimetype": "image/jpeg",
          "secret": "s9NSeApKe5b0LZzhsVoe2h2MoE6iHmEm",
          "width": 320
        },
        "k": {
          "extension": "jpg",
          "height": 1172,
          "mimetype": "image/jpeg",
          "secret": "s9NSeApKe5b0LZzhsVoe2h2MoE6iHmEm",
          "width": 2048
        },
        "n": {
          "extension": "jpg",
          "height": 183,
          "mimetype": "image/jpeg",
          "secret": "s9NSeApKe5b0LZzhsVoe2h2MoE6iHmEm",
          "width": 320
        },
        "o": {
          "extension": "jpg",
          "height": 1128,
          "mimetype": "image/jpeg",
          "secret": "if5jHG0QDpORLdxMKrEXOJXyhpe7ynBj",
          "width": 1971
        },
        "s": {
          "extension": "jpg",
          "height": 320,
          "mimetype": "image/jpeg",
          "secret": "s9NSeApKe5b0LZzhsVoe2h2MoE6iHmEm",
          "width": 320
        },
        "z": {
          "extension": "jpg",
          "height": 366,
          "mimetype": "image/jpeg",
          "secret": "s9NSeApKe5b0LZzhsVoe2h2MoE6iHmEm",
          "width": 640
        }
      }
    },
    "media:uri_template": "https://millsfield.sfomuseum.org/media/152/782/031/9/1527820319_{secret}_{label}.{extention}",
    "sfomuseum:filename": "31518.tif",
    "sfomuseum:image_index": 5,
    "sfomuseum:placetype": "image",
    "sfomuseum:primary_image": 1,
    "wof:depicts": [
      1511923511
    ],
    "wof:name": "airmail flight cover: Pan American Airways, FAM-14, first transpacific airmail flight, San Francisco (Alameda) - Honolulu route",
    "wof:placetype": "media"
  },
  "geometry": {"coordinates":[-122.386155,37.616358],"type":"Point"}
}
