{
  "type": "Feature",
  "properties": {
    "iso:country": "XX",
    "media:fingerprint": "a7785db951e0fe4739464a8a340ef1066740df72",
    "media:imagehash_avg": "a:001e333f3f3d3838",
    "media:imagehash_diff": "d:f8f2666a6ae3f3e2",
    "media:medium": "image",
    "media:mimetype": "image/tiff",
    "media:properties": {
      "colours": [
        {
          "hex": "#ccca50",
          "name": "#ccca50",
          "reference": "vibrant"
        }, 
        {
          "hex": "#e4de5f",
          "name": "#e4de5f",
          "reference": "vibrant"
        }, 
        {
          "hex": "#445b24",
          "name": "#445b24",
          "reference": "vibrant"
        }, 
        {
          "hex": "#a8ad51",
          "name": "#a8ad51",
          "reference": "vibrant"
        }, 
        {
          "hex": "#a6bb73",
          "name": "#a6bb73",
          "reference": "vibrant"
        }
      ],
      "sizes": {
        "b": {
          "extension": "jpg",
          "height": 686,
          "mimetype": "image/jpeg",
          "secret": "CHXyqDKLz0IkHYGpHGXSIZ84V9yYLjGn",
          "width": 1024
        },
        "c": {
          "extension": "jpg",
          "height": 536,
          "mimetype": "image/jpeg",
          "secret": "CHXyqDKLz0IkHYGpHGXSIZ84V9yYLjGn",
          "width": 800
        },
        "dc": {
          "extension": "jpg",
          "height": 536,
          "mimetype": "image/jpeg",
          "secret": "CHXyqDKLz0IkHYGpHGXSIZ84V9yYLjGn",
          "width": 800
        },
        "ds": {
          "extension": "jpg",
          "height": 320,
          "mimetype": "image/jpeg",
          "secret": "CHXyqDKLz0IkHYGpHGXSIZ84V9yYLjGn",
          "width": 320
        },
        "k": {
          "extension": "jpg",
          "height": 1372,
          "mimetype": "image/jpeg",
          "secret": "CHXyqDKLz0IkHYGpHGXSIZ84V9yYLjGn",
          "width": 2048
        },
        "n": {
          "extension": "jpg",
          "height": 214,
          "mimetype": "image/jpeg",
          "secret": "CHXyqDKLz0IkHYGpHGXSIZ84V9yYLjGn",
          "width": 320
        },
        "o": {
          "extension": "jpg",
          "height": 1081,
          "mimetype": "image/jpeg",
          "secret": "jqfL5VAfJPePO0cLhQw9nKOv3q4Yn1Af",
          "width": 1613
        },
        "s": {
          "extension": "jpg",
          "height": 320,
          "mimetype": "image/jpeg",
          "secret": "CHXyqDKLz0IkHYGpHGXSIZ84V9yYLjGn",
          "width": 320
        },
        "z": {
          "extension": "jpg",
          "height": 428,
          "mimetype": "image/jpeg",
          "secret": "CHXyqDKLz0IkHYGpHGXSIZ84V9yYLjGn",
          "width": 640
        }
      }
    },
    "media:uri_template": "https://millsfield.sfomuseum.org/media/152/782/756/3/1527827563_{secret}_{label}.{extention}",
    "sfomuseum:filename": "44143.tif",
    "sfomuseum:image_index": 5,
    "sfomuseum:placetype": "image",
    "sfomuseum:primary_image": 1,
    "wof:depicts": [
      1511948597
    ],
    "wof:name": "negative: San Francisco International Airport (SFO), barber shop",
    "wof:placetype": "media"
  },
  "geometry": {"coordinates":[-122.386155,37.616358],"type":"Point"}
}
