{
  "type": "Feature",
  "properties": {
    "iso:country": "XX",
    "media:fingerprint": "cc21e0496324ec7c190d2eb2d7ba5274977a7bd8",
    "media:imagehash_avg": "a:ffffef0000441800",
    "media:imagehash_diff": "d:e0901a99339cf0e0",
    "media:medium": "image",
    "media:mimetype": "image/tiff",
    "media:properties": {
      "colours": [
        {
          "hex": "#808080",
          "name": "#808080",
          "reference": "vibrant"
        }, 
        {
          "hex": "#bababa",
          "name": "#bababa",
          "reference": "vibrant"
        }, 
        {
          "hex": "#484848",
          "name": "#484848",
          "reference": "vibrant"
        }
      ],
      "sizes": {
        "b": {
          "extension": "jpg",
          "height": 768,
          "mimetype": "image/jpeg",
          "secret": "8bslLdKrEuRorq73gEkCTR9ia0YaQCZ2",
          "width": 755
        },
        "c": {
          "extension": "jpg",
          "height": 600,
          "mimetype": "image/jpeg",
          "secret": "8bslLdKrEuRorq73gEkCTR9ia0YaQCZ2",
          "width": 590
        },
        "dc": {
          "extension": "jpg",
          "height": 600,
          "mimetype": "image/jpeg",
          "secret": "8bslLdKrEuRorq73gEkCTR9ia0YaQCZ2",
          "width": 590
        },
        "ds": {
          "extension": "jpg",
          "height": 320,
          "mimetype": "image/jpeg",
          "secret": "8bslLdKrEuRorq73gEkCTR9ia0YaQCZ2",
          "width": 320
        },
        "k": {
          "extension": "jpg",
          "height": 1536,
          "mimetype": "image/jpeg",
          "secret": "8bslLdKrEuRorq73gEkCTR9ia0YaQCZ2",
          "width": 1511
        },
        "n": {
          "extension": "jpg",
          "height": 240,
          "mimetype": "image/jpeg",
          "secret": "8bslLdKrEuRorq73gEkCTR9ia0YaQCZ2",
          "width": 236
        },
        "o": {
          "extension": "jpg",
          "height": 1772,
          "mimetype": "image/jpeg",
          "secret": "bJ5e4AyNs0Ys5sr5z34MrzBGTWnhFBrq",
          "width": 1744
        },
        "s": {
          "extension": "jpg",
          "height": 320,
          "mimetype": "image/jpeg",
          "secret": "8bslLdKrEuRorq73gEkCTR9ia0YaQCZ2",
          "width": 320
        },
        "z": {
          "extension": "jpg",
          "height": 480,
          "mimetype": "image/jpeg",
          "secret": "8bslLdKrEuRorq73gEkCTR9ia0YaQCZ2",
          "width": 472
        }
      }
    },
    "media:uri_template": "https://millsfield.sfomuseum.org/media/152/782/496/9/1527824969_{secret}_{label}.{extention}",
    "sfomuseum:filename": "42905.tif",
    "sfomuseum:image_index": 5,
    "sfomuseum:placetype": "image",
    "sfomuseum:primary_image": 1,
    "wof:depicts": [
      1511945851
    ],
    "wof:name": "photograph: San Francisco International Airport (SFO), parking garage construction",
    "wof:placetype": "media"
  },
  "geometry": {"coordinates":[-122.386155,37.616358],"type":"Point"}
}
