{
  "type": "Feature",
  "properties": {
    "iso:country": "XX",
    "media:fingerprint": "04d2061736256c3fa527dcf39e4756e9f5e10303",
    "media:imagehash_avg": "a:0000007efffff8f8",
    "media:imagehash_diff": "d:09e0f0c6b3e0e0e0",
    "media:medium": "image",
    "media:mimetype": "image/tiff",
    "media:properties": {
      "colours": [
        {
          "hex": "#868686",
          "name": "#868686",
          "reference": "vibrant"
        }, 
        {
          "hex": "#b8b8b8",
          "name": "#b8b8b8",
          "reference": "vibrant"
        }, 
        {
          "hex": "#484848",
          "name": "#484848",
          "reference": "vibrant"
        }
      ],
      "sizes": {
        "b": {
          "extension": "jpg",
          "height": 768,
          "mimetype": "image/jpeg",
          "secret": "kSCdvhMoyNBcmVtwF0k46YeUILKRS9aP",
          "width": 602
        },
        "c": {
          "extension": "jpg",
          "height": 600,
          "mimetype": "image/jpeg",
          "secret": "kSCdvhMoyNBcmVtwF0k46YeUILKRS9aP",
          "width": 470
        },
        "dc": {
          "extension": "jpg",
          "height": 600,
          "mimetype": "image/jpeg",
          "secret": "kSCdvhMoyNBcmVtwF0k46YeUILKRS9aP",
          "width": 470
        },
        "ds": {
          "extension": "jpg",
          "height": 320,
          "mimetype": "image/jpeg",
          "secret": "kSCdvhMoyNBcmVtwF0k46YeUILKRS9aP",
          "width": 320
        },
        "k": {
          "extension": "jpg",
          "height": 1536,
          "mimetype": "image/jpeg",
          "secret": "kSCdvhMoyNBcmVtwF0k46YeUILKRS9aP",
          "width": 1205
        },
        "n": {
          "extension": "jpg",
          "height": 240,
          "mimetype": "image/jpeg",
          "secret": "kSCdvhMoyNBcmVtwF0k46YeUILKRS9aP",
          "width": 188
        },
        "o": {
          "extension": "jpg",
          "height": 2727,
          "mimetype": "image/jpeg",
          "secret": "UtzJDhChLwHq31lKVBeqpvh3wit8tMvw",
          "width": 2140
        },
        "s": {
          "extension": "jpg",
          "height": 320,
          "mimetype": "image/jpeg",
          "secret": "kSCdvhMoyNBcmVtwF0k46YeUILKRS9aP",
          "width": 320
        },
        "z": {
          "extension": "jpg",
          "height": 480,
          "mimetype": "image/jpeg",
          "secret": "kSCdvhMoyNBcmVtwF0k46YeUILKRS9aP",
          "width": 376
        }
      }
    },
    "media:uri_template": "https://millsfield.sfomuseum.org/media/152/782/298/5/1527822985_{secret}_{label}.{extention}",
    "sfomuseum:filename": "41166.tif",
    "sfomuseum:image_index": 5,
    "sfomuseum:placetype": "image",
    "sfomuseum:primary_image": 1,
    "wof:depicts": [
      1511944879
    ],
    "wof:name": "negative: San Francisco International Airport (SFO), architectural model",
    "wof:placetype": "media"
  },
  "geometry": {"coordinates":[-122.386155,37.616358],"type":"Point"}
}
