{
  "type": "Feature",
  "properties": {
    "iso:country": "XX",
    "media:fingerprint": "47e952d1c1a54ef020172ad0de9d80ce1865da05",
    "media:imagehash_avg": "a:1c3fffff17010010",
    "media:imagehash_diff": "d:fcfcbda4a6f7d2e2",
    "media:medium": "image",
    "media:mimetype": "image/tiff",
    "media:properties": {
      "colours": [
        {
          "hex": "#868686",
          "name": "#868686",
          "reference": "vibrant"
        }, 
        {
          "hex": "#c0c0c0",
          "name": "#c0c0c0",
          "reference": "vibrant"
        }, 
        {
          "hex": "#484848",
          "name": "#484848",
          "reference": "vibrant"
        }
      ],
      "sizes": {
        "b": {
          "extension": "jpg",
          "height": 767,
          "mimetype": "image/jpeg",
          "secret": "2tEFGyIAIKn5anwML67nltv2ICoDmN85",
          "width": 988
        },
        "c": {
          "extension": "jpg",
          "height": 600,
          "mimetype": "image/jpeg",
          "secret": "2tEFGyIAIKn5anwML67nltv2ICoDmN85",
          "width": 772
        },
        "dc": {
          "extension": "jpg",
          "height": 600,
          "mimetype": "image/jpeg",
          "secret": "2tEFGyIAIKn5anwML67nltv2ICoDmN85",
          "width": 772
        },
        "ds": {
          "extension": "jpg",
          "height": 320,
          "mimetype": "image/jpeg",
          "secret": "2tEFGyIAIKn5anwML67nltv2ICoDmN85",
          "width": 320
        },
        "k": {
          "extension": "jpg",
          "height": 1535,
          "mimetype": "image/jpeg",
          "secret": "2tEFGyIAIKn5anwML67nltv2ICoDmN85",
          "width": 1976
        },
        "n": {
          "extension": "jpg",
          "height": 240,
          "mimetype": "image/jpeg",
          "secret": "2tEFGyIAIKn5anwML67nltv2ICoDmN85",
          "width": 308
        },
        "o": {
          "extension": "jpg",
          "height": 2140,
          "mimetype": "image/jpeg",
          "secret": "gwHrJcpGmljtTv0fh4jH7mJ4drM6hwBc",
          "width": 2754
        },
        "s": {
          "extension": "jpg",
          "height": 320,
          "mimetype": "image/jpeg",
          "secret": "2tEFGyIAIKn5anwML67nltv2ICoDmN85",
          "width": 320
        },
        "z": {
          "extension": "jpg",
          "height": 480,
          "mimetype": "image/jpeg",
          "secret": "2tEFGyIAIKn5anwML67nltv2ICoDmN85",
          "width": 617
        }
      }
    },
    "media:uri_template": "https://millsfield.sfomuseum.org/media/152/782/207/9/1527822079_{secret}_{label}.{extention}",
    "sfomuseum:filename": "40193.tif",
    "sfomuseum:image_index": 5,
    "sfomuseum:placetype": "image",
    "sfomuseum:primary_image": 1,
    "wof:depicts": [
      1511944001
    ],
    "wof:name": "negative: San Francisco Airport, passenger waiting room",
    "wof:placetype": "media"
  },
  "geometry": {"coordinates":[-122.386155,37.616358],"type":"Point"}
}
