{
  "type": "Feature",
  "properties": {
    "iso:country": "XX",
    "media:fingerprint": "a8a04ebf5a5cf0551ed1c7416c17f4891b6ac93d",
    "media:imagehash_avg": "a:be8287879f8787ef",
    "media:imagehash_diff": "d:723a3e2f7d7f6f0e",
    "media:medium": "image",
    "media:mimetype": "image/tiff",
    "media:properties": {
      "colours": [
        {
          "hex": "#f8f0e8",
          "name": "#f8f0e8",
          "reference": "vibrant"
        },
        {
          "hex": "#7d7b7f",
          "name": "#7d7b7f",
          "reference": "vibrant"
        },
        {
          "hex": "#c2c1bc",
          "name": "#c2c1bc",
          "reference": "vibrant"
        },
        {
          "hex": "#454444",
          "name": "#454444",
          "reference": "vibrant"
        }
      ],
      "sizes": {
        "b": {
          "extension": "jpg",
          "height": 768,
          "mimetype": "image/jpeg",
          "secret": "0NU4YcWEq5qeyajsRGm1hpYngqNP03R5",
          "width": 498
        },
        "c": {
          "extension": "jpg",
          "height": 600,
          "mimetype": "image/jpeg",
          "secret": "0NU4YcWEq5qeyajsRGm1hpYngqNP03R5",
          "width": 389
        },
        "dc": {
          "extension": "jpg",
          "height": 600,
          "mimetype": "image/jpeg",
          "secret": "0NU4YcWEq5qeyajsRGm1hpYngqNP03R5",
          "width": 389
        },
        "ds": {
          "extension": "jpg",
          "height": 320,
          "mimetype": "image/jpeg",
          "secret": "0NU4YcWEq5qeyajsRGm1hpYngqNP03R5",
          "width": 320
        },
        "k": {
          "extension": "jpg",
          "height": 1536,
          "mimetype": "image/jpeg",
          "secret": "0NU4YcWEq5qeyajsRGm1hpYngqNP03R5",
          "width": 996
        },
        "n": {
          "extension": "jpg",
          "height": 240,
          "mimetype": "image/jpeg",
          "secret": "0NU4YcWEq5qeyajsRGm1hpYngqNP03R5",
          "width": 155
        },
        "o": {
          "extension": "jpg",
          "height": 2556,
          "mimetype": "image/jpeg",
          "secret": "MNEdIuD51Q8rJfEC0QPAHG7lzey9RdOH",
          "width": 1658
        },
        "s": {
          "extension": "jpg",
          "height": 320,
          "mimetype": "image/jpeg",
          "secret": "0NU4YcWEq5qeyajsRGm1hpYngqNP03R5",
          "width": 320
        },
        "z": {
          "extension": "jpg",
          "height": 480,
          "mimetype": "image/jpeg",
          "secret": "0NU4YcWEq5qeyajsRGm1hpYngqNP03R5",
          "width": 311
        }
      }
    },
    "media:uri_template": "https://static.sfomuseum.org/media/152/784/636/5/1527846365_{secret}_{label}.{extention}",
    "sfomuseum:filename": "70856.tif",
    "sfomuseum:image_index": 5,
    "sfomuseum:image_type": "studio",
    "sfomuseum:placetype": "image",
    "sfomuseum:primary_image": 0,
    "wof:depicts": [
      1511928571,
      1159285413
    ],
    "wof:name": "menu: United Airlines, First Class",
    "wof:placetype": "custom",
    "wof:placetype_alt": "image"
  },
  "geometry": {"coordinates":[-122.386155,37.616358],"type":"Point"}
}
