{
  "type": "Feature",
  "properties": {
    "iso:country": "XX",
    "media:fingerprint": "c0549bf13cb44519c73806c1b7662c5052647e7e",
    "media:imagehash_avg": "a:1c1c3e7c7c787870",
    "media:imagehash_diff": "d:f0f8f0f0e1e0c0c4",
    "media:medium": "image",
    "media:mimetype": "image/tiff",
    "media:properties": {
      "colours": [
        {
          "hex": "#808080",
          "name": "#808080",
          "reference": "vibrant"
        }, 
        {
          "hex": "#b8b8b8",
          "name": "#b8b8b8",
          "reference": "vibrant"
        }, 
        {
          "hex": "#404040",
          "name": "#404040",
          "reference": "vibrant"
        }
      ],
      "sizes": {
        "b": {
          "extension": "jpg",
          "height": 767,
          "mimetype": "image/jpeg",
          "secret": "G9b4x5MjNQu92YhCKv1rxdt0UPkpvav5",
          "width": 988
        },
        "c": {
          "extension": "jpg",
          "height": 600,
          "mimetype": "image/jpeg",
          "secret": "G9b4x5MjNQu92YhCKv1rxdt0UPkpvav5",
          "width": 772
        },
        "dc": {
          "extension": "jpg",
          "height": 600,
          "mimetype": "image/jpeg",
          "secret": "G9b4x5MjNQu92YhCKv1rxdt0UPkpvav5",
          "width": 772
        },
        "ds": {
          "extension": "jpg",
          "height": 320,
          "mimetype": "image/jpeg",
          "secret": "G9b4x5MjNQu92YhCKv1rxdt0UPkpvav5",
          "width": 320
        },
        "k": {
          "extension": "jpg",
          "height": 1535,
          "mimetype": "image/jpeg",
          "secret": "G9b4x5MjNQu92YhCKv1rxdt0UPkpvav5",
          "width": 1976
        },
        "n": {
          "extension": "jpg",
          "height": 240,
          "mimetype": "image/jpeg",
          "secret": "G9b4x5MjNQu92YhCKv1rxdt0UPkpvav5",
          "width": 308
        },
        "o": {
          "extension": "jpg",
          "height": 2140,
          "mimetype": "image/jpeg",
          "secret": "TKYAVFJCUxwpuEvRgbA4AglGxQZ75fPs",
          "width": 2754
        },
        "s": {
          "extension": "jpg",
          "height": 320,
          "mimetype": "image/jpeg",
          "secret": "G9b4x5MjNQu92YhCKv1rxdt0UPkpvav5",
          "width": 320
        },
        "z": {
          "extension": "jpg",
          "height": 480,
          "mimetype": "image/jpeg",
          "secret": "G9b4x5MjNQu92YhCKv1rxdt0UPkpvav5",
          "width": 617
        }
      }
    },
    "media:uri_template": "https://millsfield.sfomuseum.org/media/152/782/233/9/1527822339_{secret}_{label}.{extention}",
    "sfomuseum:filename": "40701.tif",
    "sfomuseum:image_index": 5,
    "sfomuseum:placetype": "image",
    "sfomuseum:primary_image": 1,
    "wof:depicts": [
      1511944243
    ],
    "wof:name": "negative: San Francisco International Airport (SFO), aerial",
    "wof:placetype": "media"
  },
  "geometry": {"coordinates":[-122.386155,37.616358],"type":"Point"}
}
