{
  "type": "Feature",
  "properties": {
    "iso:country": "XX",
    "media:fingerprint": "b1606b71fb90aef62e290d49baf79aff0d59654a",
    "media:imagehash_avg": "a:ffffff8100007e2c",
    "media:imagehash_diff": "d:cdeded0d45e4ccc8",
    "media:medium": "image",
    "media:mimetype": "image/tiff",
    "media:properties": {
      "colours": [
        {
          "hex": "#ba5149",
          "name": "#ba5149",
          "reference": "vibrant"
        }, 
        {
          "hex": "#f8edd6",
          "name": "#f8edd6",
          "reference": "vibrant"
        }, 
        {
          "hex": "#92352c",
          "name": "#92352c",
          "reference": "vibrant"
        }, 
        {
          "hex": "#b07e78",
          "name": "#b07e78",
          "reference": "vibrant"
        }, 
        {
          "hex": "#cab4a7",
          "name": "#cab4a7",
          "reference": "vibrant"
        }
      ],
      "sizes": {
        "b": {
          "extension": "jpg",
          "height": 767,
          "mimetype": "image/jpeg",
          "secret": "RmzFUCnHgptTUA2EVGEnqoAre7rmie9z",
          "width": 429
        },
        "c": {
          "extension": "jpg",
          "height": 600,
          "mimetype": "image/jpeg",
          "secret": "RmzFUCnHgptTUA2EVGEnqoAre7rmie9z",
          "width": 335
        },
        "dc": {
          "extension": "jpg",
          "height": 600,
          "mimetype": "image/jpeg",
          "secret": "RmzFUCnHgptTUA2EVGEnqoAre7rmie9z",
          "width": 335
        },
        "ds": {
          "extension": "jpg",
          "height": 320,
          "mimetype": "image/jpeg",
          "secret": "RmzFUCnHgptTUA2EVGEnqoAre7rmie9z",
          "width": 320
        },
        "k": {
          "extension": "jpg",
          "height": 1535,
          "mimetype": "image/jpeg",
          "secret": "RmzFUCnHgptTUA2EVGEnqoAre7rmie9z",
          "width": 859
        },
        "n": {
          "extension": "jpg",
          "height": 240,
          "mimetype": "image/jpeg",
          "secret": "RmzFUCnHgptTUA2EVGEnqoAre7rmie9z",
          "width": 134
        },
        "o": {
          "extension": "jpg",
          "height": 2874,
          "mimetype": "image/jpeg",
          "secret": "G25Tlw5YzKslGx9VqafFaIHB46qvVzOI",
          "width": 1608
        },
        "s": {
          "extension": "jpg",
          "height": 320,
          "mimetype": "image/jpeg",
          "secret": "RmzFUCnHgptTUA2EVGEnqoAre7rmie9z",
          "width": 320
        },
        "z": {
          "extension": "jpg",
          "height": 480,
          "mimetype": "image/jpeg",
          "secret": "RmzFUCnHgptTUA2EVGEnqoAre7rmie9z",
          "width": 268
        }
      }
    },
    "media:uri_template": "https://millsfield.sfomuseum.org/media/152/782/474/9/1527824749_{secret}_{label}.{extention}",
    "sfomuseum:filename": "42775.tif",
    "sfomuseum:image_index": 5,
    "sfomuseum:placetype": "image",
    "sfomuseum:primary_image": 0,
    "wof:depicts": [
      1511927429
    ],
    "wof:name": "airsickness bag: EgyptAir",
    "wof:placetype": "media"
  },
  "geometry": {"coordinates":[-122.386155,37.616358],"type":"Point"}
}
