{
  "type": "Feature",
  "properties": {
    "sfomuseum:filename": "1995.29.18 abcd 001.tif",
    "sfomuseum:image_index": 1,
    "sfomuseum:placetype": "image",
    "sfomuseum:primary_image": 1,
    "wof:name": "toy set: \"Sky Rangers\" lighthouse tower",
    "wof:placetype": "custom",
    "wof:placetype_alt": "image"
  },
  "geometry": {"coordinates":[-122.386155,37.616357],"type":"Point"}
}
