{
  "type": "Feature",
  "properties": {
    "iso:country": "XX",
    "media:fingerprint": "c2079abdb65a6c1e1a3bd12f1688de3af5f61b46",
    "media:imagehash_avg": "a:41ffffffcf9f0000",
    "media:imagehash_diff": "d:939991c999398968",
    "media:medium": "image",
    "media:mimetype": "image/tiff",
    "media:properties": {
      "colours": [
        {
          "hex": "#808080",
          "name": "#808080",
          "reference": "vibrant"
        }, 
        {
          "hex": "#b8b8b8",
          "name": "#b8b8b8",
          "reference": "vibrant"
        }, 
        {
          "hex": "#404040",
          "name": "#404040",
          "reference": "vibrant"
        }
      ],
      "sizes": {
        "b": {
          "extension": "jpg",
          "height": 767,
          "mimetype": "image/jpeg",
          "secret": "iqlsYHQ40ef4UNsKwW6C0eOYtZiwY39X",
          "width": 964
        },
        "c": {
          "extension": "jpg",
          "height": 600,
          "mimetype": "image/jpeg",
          "secret": "iqlsYHQ40ef4UNsKwW6C0eOYtZiwY39X",
          "width": 753
        },
        "dc": {
          "extension": "jpg",
          "height": 600,
          "mimetype": "image/jpeg",
          "secret": "iqlsYHQ40ef4UNsKwW6C0eOYtZiwY39X",
          "width": 753
        },
        "ds": {
          "extension": "jpg",
          "height": 320,
          "mimetype": "image/jpeg",
          "secret": "iqlsYHQ40ef4UNsKwW6C0eOYtZiwY39X",
          "width": 320
        },
        "k": {
          "extension": "jpg",
          "height": 1535,
          "mimetype": "image/jpeg",
          "secret": "iqlsYHQ40ef4UNsKwW6C0eOYtZiwY39X",
          "width": 1929
        },
        "n": {
          "extension": "jpg",
          "height": 240,
          "mimetype": "image/jpeg",
          "secret": "iqlsYHQ40ef4UNsKwW6C0eOYtZiwY39X",
          "width": 301
        },
        "o": {
          "extension": "jpg",
          "height": 2236,
          "mimetype": "image/jpeg",
          "secret": "ZL9XRmhLIiTFuBPFdoqmph352l9NSF9z",
          "width": 2809
        },
        "s": {
          "extension": "jpg",
          "height": 320,
          "mimetype": "image/jpeg",
          "secret": "iqlsYHQ40ef4UNsKwW6C0eOYtZiwY39X",
          "width": 320
        },
        "z": {
          "extension": "jpg",
          "height": 480,
          "mimetype": "image/jpeg",
          "secret": "iqlsYHQ40ef4UNsKwW6C0eOYtZiwY39X",
          "width": 603
        }
      }
    },
    "media:uri_template": "https://millsfield.sfomuseum.org/media/152/782/211/5/1527822115_{secret}_{label}.{extention}",
    "sfomuseum:filename": "40209.tif",
    "sfomuseum:image_index": 5,
    "sfomuseum:placetype": "image",
    "sfomuseum:primary_image": 1,
    "wof:depicts": [
      1511944037
    ],
    "wof:name": "negative: San Francisco International Airport (SFO), Lufthansa German Airlines Boeing 707-430",
    "wof:placetype": "media"
  },
  "geometry": {"coordinates":[-122.386155,37.616358],"type":"Point"}
}
