{
  "type": "Feature",
  "properties": {
    "iso:country": "XX",
    "media:fingerprint": "ac9e1c1dc7bc46c75eea8613eaabedb997431a74",
    "media:imagehash_avg": "a:ffffeb80e0e0c3ff",
    "media:imagehash_diff": "d:181a1607070f8f37",
    "media:medium": "image",
    "media:mimetype": "image/tiff",
    "media:properties": {
      "colours": [
        {
          "hex": "#938878",
          "name": "#938878",
          "reference": "vibrant"
        },
        {
          "hex": "#cabfa8",
          "name": "#cabfa8",
          "reference": "vibrant"
        },
        {
          "hex": "#413e38",
          "name": "#413e38",
          "reference": "vibrant"
        }
      ],
      "sizes": {
        "b": {
          "extension": "jpg",
          "height": 768,
          "mimetype": "image/jpeg",
          "secret": "l9n7k1P7wroQv2pu9ge0bmij2UE9ENkY",
          "width": 1018
        },
        "c": {
          "extension": "jpg",
          "height": 600,
          "mimetype": "image/jpeg",
          "secret": "l9n7k1P7wroQv2pu9ge0bmij2UE9ENkY",
          "width": 795
        },
        "dc": {
          "extension": "jpg",
          "height": 600,
          "mimetype": "image/jpeg",
          "secret": "l9n7k1P7wroQv2pu9ge0bmij2UE9ENkY",
          "width": 795
        },
        "ds": {
          "extension": "jpg",
          "height": 320,
          "mimetype": "image/jpeg",
          "secret": "l9n7k1P7wroQv2pu9ge0bmij2UE9ENkY",
          "width": 320
        },
        "k": {
          "extension": "jpg",
          "height": 1536,
          "mimetype": "image/jpeg",
          "secret": "l9n7k1P7wroQv2pu9ge0bmij2UE9ENkY",
          "width": 2037
        },
        "n": {
          "extension": "jpg",
          "height": 240,
          "mimetype": "image/jpeg",
          "secret": "l9n7k1P7wroQv2pu9ge0bmij2UE9ENkY",
          "width": 318
        },
        "o": {
          "extension": "jpg",
          "height": 2117,
          "mimetype": "image/jpeg",
          "secret": "cis8rf95drERoSJSRWVqAXeznTGnUqiD",
          "width": 2808
        },
        "s": {
          "extension": "jpg",
          "height": 320,
          "mimetype": "image/jpeg",
          "secret": "l9n7k1P7wroQv2pu9ge0bmij2UE9ENkY",
          "width": 320
        },
        "z": {
          "extension": "jpg",
          "height": 480,
          "mimetype": "image/jpeg",
          "secret": "l9n7k1P7wroQv2pu9ge0bmij2UE9ENkY",
          "width": 636
        }
      }
    },
    "media:uri_template": "https://millsfield.sfomuseum.org/media/172/956/527/9/1729565279_{secret}_{label}.{extention}",
    "sfomuseum:filename": "32077.tif",
    "sfomuseum:image_index": 0,
    "sfomuseum:image_type": "curator",
    "sfomuseum:placetype": "image",
    "sfomuseum:primary_image": 1,
    "wof:depicts": [
      1159285395,
      1159293083,
      1729563857
    ],
    "wof:name": "photograph: Transcontinental \u0026 Western Air (TWA), Douglas DC-1",
    "wof:placetype": "custom",
    "wof:placetype_alt": "image"
  },
  "geometry": {"coordinates":[-122.386155,37.616357],"type":"Point"}
}
