{
  "type": "Feature",
  "properties": {
    "iso:country": "XX",
    "media:fingerprint": "29b001b0d43ac02e938a33ab20609c82a275a4c6",
    "media:imagehash_avg": "a:80fefefefefefefe",
    "media:imagehash_diff": "d:1632681818101848",
    "media:medium": "image",
    "media:mimetype": "image/tiff",
    "media:properties": {
      "colours": [
        {
          "hex": "#c1a667",
          "name": "#c1a667",
          "reference": "vibrant"
        },
        {
          "hex": "#e4c683",
          "name": "#e4c683",
          "reference": "vibrant"
        },
        {
          "hex": "#5c3c29",
          "name": "#5c3c29",
          "reference": "vibrant"
        },
        {
          "hex": "#a26c59",
          "name": "#a26c59",
          "reference": "vibrant"
        },
        {
          "hex": "#b9ac8a",
          "name": "#b9ac8a",
          "reference": "vibrant"
        }
      ],
      "sizes": {
        "b": {
          "extension": "jpg",
          "height": 768,
          "mimetype": "image/jpeg",
          "secret": "iGcIlcj18PAwJ6PRBSBgQgvF1lHeqYIa",
          "width": 451
        },
        "c": {
          "extension": "jpg",
          "height": 600,
          "mimetype": "image/jpeg",
          "secret": "iGcIlcj18PAwJ6PRBSBgQgvF1lHeqYIa",
          "width": 352
        },
        "dc": {
          "extension": "jpg",
          "height": 600,
          "mimetype": "image/jpeg",
          "secret": "iGcIlcj18PAwJ6PRBSBgQgvF1lHeqYIa",
          "width": 352
        },
        "ds": {
          "extension": "jpg",
          "height": 320,
          "mimetype": "image/jpeg",
          "secret": "iGcIlcj18PAwJ6PRBSBgQgvF1lHeqYIa",
          "width": 320
        },
        "k": {
          "extension": "jpg",
          "height": 1536,
          "mimetype": "image/jpeg",
          "secret": "iGcIlcj18PAwJ6PRBSBgQgvF1lHeqYIa",
          "width": 902
        },
        "n": {
          "extension": "jpg",
          "height": 240,
          "mimetype": "image/jpeg",
          "secret": "iGcIlcj18PAwJ6PRBSBgQgvF1lHeqYIa",
          "width": 141
        },
        "o": {
          "extension": "jpg",
          "height": 1293,
          "mimetype": "image/jpeg",
          "secret": "cXRwi2zlISM2rDZy19KdTRQNWaUEVJ6Q",
          "width": 760
        },
        "s": {
          "extension": "jpg",
          "height": 320,
          "mimetype": "image/jpeg",
          "secret": "iGcIlcj18PAwJ6PRBSBgQgvF1lHeqYIa",
          "width": 320
        },
        "z": {
          "extension": "jpg",
          "height": 480,
          "mimetype": "image/jpeg",
          "secret": "iGcIlcj18PAwJ6PRBSBgQgvF1lHeqYIa",
          "width": 282
        }
      }
    },
    "media:uri_template": "https://static.sfomuseum.org/media/152/785/418/1/1527854181_{secret}_{label}.{extention}",
    "sfomuseum:filename": "2010.174.023.tif",
    "sfomuseum:image_index": 5,
    "sfomuseum:image_type": "studio",
    "sfomuseum:placetype": "image",
    "sfomuseum:primary_image": 1,
    "wof:depicts": [
      1511942115
    ],
    "wof:name": "logbook: Stanley Henry Page",
    "wof:placetype": "custom",
    "wof:placetype_alt": "image"
  },
  "geometry": {"coordinates":[-122.386155,37.616358],"type":"Point"}
}
