{
  "type": "Feature",
  "properties": {
    "date:cessation_lower": "1915-01-01",
    "date:cessation_upper": "1915-12-31",
    "date:inception_lower": "1915-01-01",
    "date:inception_upper": "1915-12-31",
    "iso:country": "XX",
    "media:fingerprint": "5b3dbf79815322b0d5b61e87cb4142b6868021a0",
    "media:imagehash_avg": "a:fffffde3030000f9",
    "media:imagehash_diff": "d:c0f1e1471f4b0b61",
    "media:mimetype": "image/tiff",
    "media:properties": {
      "colours": [
        {
          "hex": "#82857b",
          "name": "#82857b",
          "reference": "vibrant"
        },
        {
          "hex": "#bfc0b8",
          "name": "#bfc0b8",
          "reference": "vibrant"
        },
        {
          "hex": "#3b4238",
          "name": "#3b4238",
          "reference": "vibrant"
        }
      ],
      "sizes": {
        "b": {
          "extension": "jpg",
          "height": 768,
          "mimetype": "image/jpeg",
          "secret": "Ct0bMB8migXvCabJjS5OIkZICAkFPlbG",
          "width": 600
        },
        "c": {
          "extension": "jpg",
          "height": 600,
          "mimetype": "image/jpeg",
          "secret": "Ct0bMB8migXvCabJjS5OIkZICAkFPlbG",
          "width": 468
        },
        "dc": {
          "extension": "jpg",
          "height": 600,
          "mimetype": "image/jpeg",
          "secret": "Ct0bMB8migXvCabJjS5OIkZICAkFPlbG",
          "width": 468
        },
        "ds": {
          "extension": "jpg",
          "height": 320,
          "mimetype": "image/jpeg",
          "secret": "Ct0bMB8migXvCabJjS5OIkZICAkFPlbG",
          "width": 320
        },
        "k": {
          "extension": "jpg",
          "height": 1536,
          "mimetype": "image/jpeg",
          "secret": "Ct0bMB8migXvCabJjS5OIkZICAkFPlbG",
          "width": 1200
        },
        "n": {
          "extension": "jpg",
          "height": 240,
          "mimetype": "image/jpeg",
          "secret": "Ct0bMB8migXvCabJjS5OIkZICAkFPlbG",
          "width": 187
        },
        "o": {
          "extension": "jpg",
          "height": 2000,
          "mimetype": "image/jpeg",
          "secret": "4eHaQuXJNVKRke2365nl4azWfiTjicw2",
          "width": 1563
        },
        "s": {
          "extension": "jpg",
          "height": 320,
          "mimetype": "image/jpeg",
          "secret": "Ct0bMB8migXvCabJjS5OIkZICAkFPlbG",
          "width": 320
        },
        "z": {
          "extension": "jpg",
          "height": 480,
          "mimetype": "image/jpeg",
          "secret": "Ct0bMB8migXvCabJjS5OIkZICAkFPlbG",
          "width": 375
        }
      }
    },
    "media:uri_template": "https://static.sfomuseum.org/media/176/344/366/1/1763443661_{secret}_{label}.{extension}",
    "sfomuseum:filename": "126580.tif",
    "sfomuseum:image_index": 5,
    "sfomuseum:image_type": "studio",
    "sfomuseum:placetype": "image",
    "sfomuseum:primary_image": 1,
    "wof:depicts": [
      1511958255
    ],
    "wof:name": "photograph: Panama-Pacific International Exposition, Silvio Pettirossi",
    "wof:placetype": "custom"
  },
  "geometry": {"coordinates":[-122.386155,37.616357],"type":"Point"}
}
