{
  "type": "Feature",
  "properties": {
    "iso:country": "XX",
    "media:fingerprint": "91ef0d0fc3f77c9f8a4e462a387d8c15f3e333e8",
    "media:imagehash_avg": "a:ffffffff9d808000",
    "media:imagehash_diff": "d:ffff6f69792b012a",
    "media:medium": "image",
    "media:mimetype": "image/tiff",
    "media:properties": {
      "colours": [
        {
          "hex": "#808080",
          "name": "#808080",
          "reference": "vibrant"
        }, 
        {
          "hex": "#b8b8b8",
          "name": "#b8b8b8",
          "reference": "vibrant"
        }, 
        {
          "hex": "#404040",
          "name": "#404040",
          "reference": "vibrant"
        }
      ],
      "sizes": {
        "b": {
          "extension": "jpg",
          "height": 768,
          "mimetype": "image/jpeg",
          "secret": "SHCkVRhMIxOzpawx0KzbZJgBZ7l6wGV2",
          "width": 751
        },
        "c": {
          "extension": "jpg",
          "height": 600,
          "mimetype": "image/jpeg",
          "secret": "SHCkVRhMIxOzpawx0KzbZJgBZ7l6wGV2",
          "width": 587
        },
        "dc": {
          "extension": "jpg",
          "height": 600,
          "mimetype": "image/jpeg",
          "secret": "SHCkVRhMIxOzpawx0KzbZJgBZ7l6wGV2",
          "width": 587
        },
        "ds": {
          "extension": "jpg",
          "height": 320,
          "mimetype": "image/jpeg",
          "secret": "SHCkVRhMIxOzpawx0KzbZJgBZ7l6wGV2",
          "width": 320
        },
        "k": {
          "extension": "jpg",
          "height": 1536,
          "mimetype": "image/jpeg",
          "secret": "SHCkVRhMIxOzpawx0KzbZJgBZ7l6wGV2",
          "width": 1503
        },
        "n": {
          "extension": "jpg",
          "height": 240,
          "mimetype": "image/jpeg",
          "secret": "SHCkVRhMIxOzpawx0KzbZJgBZ7l6wGV2",
          "width": 234
        },
        "o": {
          "extension": "jpg",
          "height": 2590,
          "mimetype": "image/jpeg",
          "secret": "9qsDgSNDKvkviEkdn9qEp8XiUaiwmMBZ",
          "width": 2536
        },
        "s": {
          "extension": "jpg",
          "height": 320,
          "mimetype": "image/jpeg",
          "secret": "SHCkVRhMIxOzpawx0KzbZJgBZ7l6wGV2",
          "width": 320
        },
        "z": {
          "extension": "jpg",
          "height": 480,
          "mimetype": "image/jpeg",
          "secret": "SHCkVRhMIxOzpawx0KzbZJgBZ7l6wGV2",
          "width": 469
        }
      }
    },
    "media:uri_template": "https://millsfield.sfomuseum.org/media/152/782/709/5/1527827095_{secret}_{label}.{extention}",
    "sfomuseum:filename": "43934.tif",
    "sfomuseum:image_index": 5,
    "sfomuseum:placetype": "image",
    "sfomuseum:primary_image": 1,
    "wof:depicts": [
      1511948135
    ],
    "wof:name": "negative: San Francisco International Airport (SFO), Pan American World Airlines, inaugural Boeing 747 flight to New York",
    "wof:placetype": "media"
  },
  "geometry": {"coordinates":[-122.386155,37.616358],"type":"Point"}
}
