{
  "type": "Feature",
  "properties": {
    "iso:country": "XX",
    "media:fingerprint": "5f5a725137345c6377e8e273134666aa392604ec",
    "media:imagehash_avg": "a:c38181818181ffff",
    "media:imagehash_diff": "d:030b133727035179",
    "media:medium": "image",
    "media:mimetype": "image/tiff",
    "media:properties": {
      "colours": [
        {
          "hex": "#384a82",
          "name": "#384a82",
          "reference": "vibrant"
        }, 
        {
          "hex": "#26375a",
          "name": "#26375a",
          "reference": "vibrant"
        }, 
        {
          "hex": "#52668f",
          "name": "#52668f",
          "reference": "vibrant"
        }, 
        {
          "hex": "#b4bec7",
          "name": "#b4bec7",
          "reference": "vibrant"
        }, 
        {
          "hex": "#2a374b",
          "name": "#2a374b",
          "reference": "vibrant"
        }
      ],
      "sizes": {
        "b": {
          "extension": "jpg",
          "height": 768,
          "mimetype": "image/jpeg",
          "secret": "ZTIvTM2NT52IOtQvGH9TYfqaHu8zNCmn",
          "width": 509
        },
        "c": {
          "extension": "jpg",
          "height": 600,
          "mimetype": "image/jpeg",
          "secret": "ZTIvTM2NT52IOtQvGH9TYfqaHu8zNCmn",
          "width": 397
        },
        "dc": {
          "extension": "jpg",
          "height": 600,
          "mimetype": "image/jpeg",
          "secret": "ZTIvTM2NT52IOtQvGH9TYfqaHu8zNCmn",
          "width": 397
        },
        "ds": {
          "extension": "jpg",
          "height": 320,
          "mimetype": "image/jpeg",
          "secret": "ZTIvTM2NT52IOtQvGH9TYfqaHu8zNCmn",
          "width": 320
        },
        "k": {
          "extension": "jpg",
          "height": 1536,
          "mimetype": "image/jpeg",
          "secret": "ZTIvTM2NT52IOtQvGH9TYfqaHu8zNCmn",
          "width": 1018
        },
        "n": {
          "extension": "jpg",
          "height": 240,
          "mimetype": "image/jpeg",
          "secret": "ZTIvTM2NT52IOtQvGH9TYfqaHu8zNCmn",
          "width": 159
        },
        "o": {
          "extension": "jpg",
          "height": 2724,
          "mimetype": "image/jpeg",
          "secret": "oyzvW6Ml3EoYwivyCLRcHp7Jmo9JHV0E",
          "width": 1806
        },
        "s": {
          "extension": "jpg",
          "height": 320,
          "mimetype": "image/jpeg",
          "secret": "ZTIvTM2NT52IOtQvGH9TYfqaHu8zNCmn",
          "width": 320
        },
        "z": {
          "extension": "jpg",
          "height": 480,
          "mimetype": "image/jpeg",
          "secret": "ZTIvTM2NT52IOtQvGH9TYfqaHu8zNCmn",
          "width": 318
        }
      }
    },
    "media:uri_template": "https://millsfield.sfomuseum.org/media/152/782/455/7/1527824557_{secret}_{label}.{extention}",
    "sfomuseum:filename": "42642.tif",
    "sfomuseum:image_index": 5,
    "sfomuseum:placetype": "image",
    "sfomuseum:primary_image": 0,
    "wof:depicts": [
      1511927407
    ],
    "wof:name": "airsickness bag: Continental Airlines",
    "wof:placetype": "media"
  },
  "geometry": {"coordinates":[-122.386155,37.616358],"type":"Point"}
}
