{
  "type": "Feature",
  "properties": {
    "iso:country": "XX",
    "media:fingerprint": "87085cac052d338e55275091695045080efc79b8",
    "media:imagehash_avg": "a:fcd898dcfed880de",
    "media:imagehash_diff": "d:2a2a2a2a282a3a1a",
    "media:medium": "image",
    "media:mimetype": "image/tiff",
    "media:properties": {
      "colours": [
        {
          "hex": "#f8f3e7",
          "name": "#f8f3e7",
          "reference": "vibrant"
        },
        {
          "hex": "#6a5c29",
          "name": "#6a5c29",
          "reference": "vibrant"
        },
        {
          "hex": "#8b8979",
          "name": "#8b8979",
          "reference": "vibrant"
        },
        {
          "hex": "#cecdbb",
          "name": "#cecdbb",
          "reference": "vibrant"
        },
        {
          "hex": "#544e38",
          "name": "#544e38",
          "reference": "vibrant"
        }
      ],
      "sizes": {
        "b": {
          "extension": "jpg",
          "height": 708,
          "mimetype": "image/jpeg",
          "secret": "sNjUNQfCS6cSt6lu9mYKN0tys4Y3HnN7",
          "width": 1024
        },
        "c": {
          "extension": "jpg",
          "height": 553,
          "mimetype": "image/jpeg",
          "secret": "sNjUNQfCS6cSt6lu9mYKN0tys4Y3HnN7",
          "width": 800
        },
        "dc": {
          "extension": "jpg",
          "height": 553,
          "mimetype": "image/jpeg",
          "secret": "sNjUNQfCS6cSt6lu9mYKN0tys4Y3HnN7",
          "width": 800
        },
        "ds": {
          "extension": "jpg",
          "height": 320,
          "mimetype": "image/jpeg",
          "secret": "sNjUNQfCS6cSt6lu9mYKN0tys4Y3HnN7",
          "width": 320
        },
        "k": {
          "extension": "jpg",
          "height": 1416,
          "mimetype": "image/jpeg",
          "secret": "sNjUNQfCS6cSt6lu9mYKN0tys4Y3HnN7",
          "width": 2048
        },
        "n": {
          "extension": "jpg",
          "height": 221,
          "mimetype": "image/jpeg",
          "secret": "sNjUNQfCS6cSt6lu9mYKN0tys4Y3HnN7",
          "width": 320
        },
        "o": {
          "extension": "jpg",
          "height": 2348,
          "mimetype": "image/jpeg",
          "secret": "5Tq0HV2RNvYtZ3S0FyNJQNidYNmjIFYM",
          "width": 3394
        },
        "s": {
          "extension": "jpg",
          "height": 320,
          "mimetype": "image/jpeg",
          "secret": "sNjUNQfCS6cSt6lu9mYKN0tys4Y3HnN7",
          "width": 320
        },
        "z": {
          "extension": "jpg",
          "height": 442,
          "mimetype": "image/jpeg",
          "secret": "sNjUNQfCS6cSt6lu9mYKN0tys4Y3HnN7",
          "width": 640
        }
      }
    },
    "media:uri_template": "https://static.sfomuseum.org/media/152/784/351/5/1527843515_{secret}_{label}.{extention}",
    "sfomuseum:filename": "68549.tif",
    "sfomuseum:image_index": 5,
    "sfomuseum:image_type": "studio",
    "sfomuseum:placetype": "image",
    "sfomuseum:primary_image": 0,
    "wof:depicts": [
      1159284059,
      1511921361
    ],
    "wof:name": "menu: CAAC (Civil Aviation Administration of China), Business Class",
    "wof:placetype": "custom",
    "wof:placetype_alt": "image"
  },
  "geometry": {"coordinates":[-122.386155,37.616358],"type":"Point"}
}
