{
  "type": "Feature",
  "properties": {
    "iso:country": "XX",
    "media:fingerprint": "c41814c982e720504ed0bbd965968543d758b5ff",
    "media:imagehash_avg": "a:0700001c7fffbc00",
    "media:imagehash_diff": "d:0e8e98f0e4646043",
    "media:medium": "image",
    "media:mimetype": "image/jpeg",
    "media:properties": {
      "colours": [
        {
          "hex": "#285a92",
          "name": "#285a92",
          "reference": "vibrant"
        }, 
        {
          "hex": "#185488",
          "name": "#185488",
          "reference": "vibrant"
        }, 
        {
          "hex": "#a2a56a",
          "name": "#a2a56a",
          "reference": "vibrant"
        }, 
        {
          "hex": "#c8c5b4",
          "name": "#c8c5b4",
          "reference": "vibrant"
        }, 
        {
          "hex": "#494648",
          "name": "#494648",
          "reference": "vibrant"
        }
      ],
      "sizes": {
        "b": {
          "extension": "jpg",
          "height": 768,
          "mimetype": "image/jpeg",
          "secret": "ym5xIOZzvoX6787C9CQTNPpcRqRfS7Pj",
          "width": 749
        },
        "c": {
          "extension": "jpg",
          "height": 600,
          "mimetype": "image/jpeg",
          "secret": "ym5xIOZzvoX6787C9CQTNPpcRqRfS7Pj",
          "width": 585
        },
        "dc": {
          "extension": "jpg",
          "height": 600,
          "mimetype": "image/jpeg",
          "secret": "ym5xIOZzvoX6787C9CQTNPpcRqRfS7Pj",
          "width": 585
        },
        "ds": {
          "extension": "jpg",
          "height": 320,
          "mimetype": "image/jpeg",
          "secret": "ym5xIOZzvoX6787C9CQTNPpcRqRfS7Pj",
          "width": 320
        },
        "k": {
          "extension": "jpg",
          "height": 1536,
          "mimetype": "image/jpeg",
          "secret": "ym5xIOZzvoX6787C9CQTNPpcRqRfS7Pj",
          "width": 1498
        },
        "n": {
          "extension": "jpg",
          "height": 240,
          "mimetype": "image/jpeg",
          "secret": "ym5xIOZzvoX6787C9CQTNPpcRqRfS7Pj",
          "width": 234
        },
        "o": {
          "extension": "jpg",
          "height": 2274,
          "mimetype": "image/jpeg",
          "secret": "npuCqScTWdlLTjYcgINuw183OUEPwUDR",
          "width": 2218
        },
        "s": {
          "extension": "jpg",
          "height": 320,
          "mimetype": "image/jpeg",
          "secret": "ym5xIOZzvoX6787C9CQTNPpcRqRfS7Pj",
          "width": 320
        },
        "z": {
          "extension": "jpg",
          "height": 480,
          "mimetype": "image/jpeg",
          "secret": "ym5xIOZzvoX6787C9CQTNPpcRqRfS7Pj",
          "width": 468
        }
      }
    },
    "media:uri_template": "https://millsfield.sfomuseum.org/media/152/781/918/9/1527819189_{secret}_{label}.{extention}",
    "sfomuseum:filename": "21288.jpg",
    "sfomuseum:image_index": 5,
    "sfomuseum:placetype": "image",
    "sfomuseum:primary_image": 0,
    "wof:depicts": [
      1511930269
    ],
    "wof:name": "brochure: UTA (Union de Transports Aériens), Boeing 747-200",
    "wof:placetype": "media"
  },
  "geometry": {"coordinates":[-122.386155,37.616358],"type":"Point"}
}
