{
  "type": "Feature",
  "properties": {
    "iso:country": "XX",
    "media:fingerprint": "ef4ffa074651b267cd3fcecc0794d59b4b8357d6",
    "media:imagehash_avg": "a:20f0f8f8f8f8f8f8",
    "media:imagehash_diff": "d:e040406101014360",
    "media:medium": "image",
    "media:mimetype": "image/tiff",
    "media:properties": {
      "colours": [
        {
          "hex": "#7b7b7b",
          "name": "#7b7b7b",
          "reference": "vibrant"
        }, 
        {
          "hex": "#b6b6b6",
          "name": "#b6b6b6",
          "reference": "vibrant"
        }, 
        {
          "hex": "#404040",
          "name": "#404040",
          "reference": "vibrant"
        }
      ],
      "sizes": {
        "b": {
          "extension": "jpg",
          "height": 768,
          "mimetype": "image/jpeg",
          "secret": "OXMACa0FJZ6eRirRCV1HicAb0nG4mG4D",
          "width": 980
        },
        "c": {
          "extension": "jpg",
          "height": 600,
          "mimetype": "image/jpeg",
          "secret": "OXMACa0FJZ6eRirRCV1HicAb0nG4mG4D",
          "width": 766
        },
        "dc": {
          "extension": "jpg",
          "height": 600,
          "mimetype": "image/jpeg",
          "secret": "OXMACa0FJZ6eRirRCV1HicAb0nG4mG4D",
          "width": 766
        },
        "ds": {
          "extension": "jpg",
          "height": 320,
          "mimetype": "image/jpeg",
          "secret": "OXMACa0FJZ6eRirRCV1HicAb0nG4mG4D",
          "width": 320
        },
        "k": {
          "extension": "jpg",
          "height": 1536,
          "mimetype": "image/jpeg",
          "secret": "OXMACa0FJZ6eRirRCV1HicAb0nG4mG4D",
          "width": 1961
        },
        "n": {
          "extension": "jpg",
          "height": 240,
          "mimetype": "image/jpeg",
          "secret": "OXMACa0FJZ6eRirRCV1HicAb0nG4mG4D",
          "width": 306
        },
        "o": {
          "extension": "jpg",
          "height": 2168,
          "mimetype": "image/jpeg",
          "secret": "ylAofjZ3eqwN5VM2vkQulDoFtjc1KSor",
          "width": 2768
        },
        "s": {
          "extension": "jpg",
          "height": 320,
          "mimetype": "image/jpeg",
          "secret": "OXMACa0FJZ6eRirRCV1HicAb0nG4mG4D",
          "width": 320
        },
        "z": {
          "extension": "jpg",
          "height": 480,
          "mimetype": "image/jpeg",
          "secret": "OXMACa0FJZ6eRirRCV1HicAb0nG4mG4D",
          "width": 612
        }
      }
    },
    "media:uri_template": "https://millsfield.sfomuseum.org/media/152/782/674/7/1527826747_{secret}_{label}.{extention}",
    "sfomuseum:filename": "43778.tif",
    "sfomuseum:image_index": 5,
    "sfomuseum:placetype": "image",
    "sfomuseum:primary_image": 1,
    "wof:depicts": [
      1511947785
    ],
    "wof:name": "negative: San Francisco International Airport (SFO), architectural drawing",
    "wof:placetype": "media"
  },
  "geometry": {"coordinates":[-122.386155,37.616358],"type":"Point"}
}
