{
  "type": "Feature",
  "properties": {
    "iso:country": "XX",
    "media:fingerprint": "cd2891a3cf6360c91fa57afc9ac91385f9750eb5",
    "media:imagehash_avg": "a:ffe7dfff9f180000",
    "media:imagehash_diff": "d:a01c18183233f1a5",
    "media:medium": "image",
    "media:mimetype": "image/tiff",
    "media:properties": {
      "colours": [
        {
          "hex": "#808080",
          "name": "#808080",
          "reference": "vibrant"
        }, 
        {
          "hex": "#c0c0c0",
          "name": "#c0c0c0",
          "reference": "vibrant"
        }, 
        {
          "hex": "#404040",
          "name": "#404040",
          "reference": "vibrant"
        }
      ],
      "sizes": {
        "b": {
          "extension": "jpg",
          "height": 768,
          "mimetype": "image/jpeg",
          "secret": "JdagmtsGLPxKWcIcCSZgQX0Z30G3YFsD",
          "width": 602
        },
        "c": {
          "extension": "jpg",
          "height": 600,
          "mimetype": "image/jpeg",
          "secret": "JdagmtsGLPxKWcIcCSZgQX0Z30G3YFsD",
          "width": 470
        },
        "dc": {
          "extension": "jpg",
          "height": 600,
          "mimetype": "image/jpeg",
          "secret": "JdagmtsGLPxKWcIcCSZgQX0Z30G3YFsD",
          "width": 470
        },
        "ds": {
          "extension": "jpg",
          "height": 320,
          "mimetype": "image/jpeg",
          "secret": "JdagmtsGLPxKWcIcCSZgQX0Z30G3YFsD",
          "width": 320
        },
        "k": {
          "extension": "jpg",
          "height": 1536,
          "mimetype": "image/jpeg",
          "secret": "JdagmtsGLPxKWcIcCSZgQX0Z30G3YFsD",
          "width": 1205
        },
        "n": {
          "extension": "jpg",
          "height": 240,
          "mimetype": "image/jpeg",
          "secret": "JdagmtsGLPxKWcIcCSZgQX0Z30G3YFsD",
          "width": 188
        },
        "o": {
          "extension": "jpg",
          "height": 2727,
          "mimetype": "image/jpeg",
          "secret": "qFPK9gHUjuEGVDiMfPDgafcnlUxbwWu3",
          "width": 2140
        },
        "s": {
          "extension": "jpg",
          "height": 320,
          "mimetype": "image/jpeg",
          "secret": "JdagmtsGLPxKWcIcCSZgQX0Z30G3YFsD",
          "width": 320
        },
        "z": {
          "extension": "jpg",
          "height": 480,
          "mimetype": "image/jpeg",
          "secret": "JdagmtsGLPxKWcIcCSZgQX0Z30G3YFsD",
          "width": 376
        }
      }
    },
    "media:uri_template": "https://millsfield.sfomuseum.org/media/152/782/304/5/1527823045_{secret}_{label}.{extention}",
    "sfomuseum:filename": "41209.tif",
    "sfomuseum:image_index": 5,
    "sfomuseum:placetype": "image",
    "sfomuseum:primary_image": 1,
    "wof:depicts": [
      1511944941
    ],
    "wof:name": "negative: San Francisco International Airport (SFO), Emmett Smith",
    "wof:placetype": "media"
  },
  "geometry": {"coordinates":[-122.386155,37.616358],"type":"Point"}
}
