{
  "type": "Feature",
  "properties": {
    "iso:country": "XX",
    "media:fingerprint": "0d5aa6e207308fe612763dc34c00bbbfe98d7549",
    "media:imagehash_avg": "a:f7e1ffff9f0f0000",
    "media:imagehash_diff": "d:4f476b3b3f7b5b5b",
    "media:medium": "image",
    "media:mimetype": "image/tiff",
    "media:properties": {
      "colours": [
        {
          "hex": "#b62711",
          "name": "#b62711",
          "reference": "vibrant"
        }, 
        {
          "hex": "#a61e08",
          "name": "#a61e08",
          "reference": "vibrant"
        }, 
        {
          "hex": "#618388",
          "name": "#618388",
          "reference": "vibrant"
        }, 
        {
          "hex": "#c3bd9b",
          "name": "#c3bd9b",
          "reference": "vibrant"
        }, 
        {
          "hex": "#44392a",
          "name": "#44392a",
          "reference": "vibrant"
        }
      ],
      "sizes": {
        "b": {
          "extension": "jpg",
          "height": 768,
          "mimetype": "image/jpeg",
          "secret": "mG2hxYOJBsXrarDKthY0wqgFS2pGI4u8",
          "width": 976
        },
        "c": {
          "extension": "jpg",
          "height": 600,
          "mimetype": "image/jpeg",
          "secret": "mG2hxYOJBsXrarDKthY0wqgFS2pGI4u8",
          "width": 762
        },
        "dc": {
          "extension": "jpg",
          "height": 600,
          "mimetype": "image/jpeg",
          "secret": "mG2hxYOJBsXrarDKthY0wqgFS2pGI4u8",
          "width": 762
        },
        "ds": {
          "extension": "jpg",
          "height": 320,
          "mimetype": "image/jpeg",
          "secret": "mG2hxYOJBsXrarDKthY0wqgFS2pGI4u8",
          "width": 320
        },
        "k": {
          "extension": "jpg",
          "height": 1536,
          "mimetype": "image/jpeg",
          "secret": "mG2hxYOJBsXrarDKthY0wqgFS2pGI4u8",
          "width": 1953
        },
        "n": {
          "extension": "jpg",
          "height": 240,
          "mimetype": "image/jpeg",
          "secret": "mG2hxYOJBsXrarDKthY0wqgFS2pGI4u8",
          "width": 305
        },
        "o": {
          "extension": "jpg",
          "height": 1278,
          "mimetype": "image/jpeg",
          "secret": "MpZKZax069SMwIFeug95qJuYDkyfGuHR",
          "width": 1625
        },
        "s": {
          "extension": "jpg",
          "height": 320,
          "mimetype": "image/jpeg",
          "secret": "mG2hxYOJBsXrarDKthY0wqgFS2pGI4u8",
          "width": 320
        },
        "z": {
          "extension": "jpg",
          "height": 480,
          "mimetype": "image/jpeg",
          "secret": "mG2hxYOJBsXrarDKthY0wqgFS2pGI4u8",
          "width": 610
        }
      }
    },
    "media:uri_template": "https://millsfield.sfomuseum.org/media/152/782/052/7/1527820527_{secret}_{label}.{extention}",
    "sfomuseum:filename": "31673.tif",
    "sfomuseum:image_index": 5,
    "sfomuseum:placetype": "image",
    "sfomuseum:primary_image": 1,
    "wof:depicts": [
      1511923773
    ],
    "wof:name": "airmail flight cover: Panagra, Panair do Brasil",
    "wof:placetype": "media"
  },
  "geometry": {"coordinates":[-122.386155,37.616358],"type":"Point"}
}
