{
  "type": "Feature",
  "properties": {
    "iso:country": "XX",
    "media:fingerprint": "0cf339a7259ac3f11c52e835e7b459ee32c91a1d",
    "media:imagehash_avg": "a:ff80809091ffe7ff",
    "media:imagehash_diff": "d:73737363638f8f8f",
    "media:medium": "image",
    "media:mimetype": "image/tiff",
    "media:properties": {
      "colours": [
        {
          "hex": "#d83828",
          "name": "#d83828",
          "reference": "vibrant"
        }, 
        {
          "hex": "#e6aa9a",
          "name": "#e6aa9a",
          "reference": "vibrant"
        }, 
        {
          "hex": "#9e534c",
          "name": "#9e534c",
          "reference": "vibrant"
        }, 
        {
          "hex": "#e0d8c0",
          "name": "#e0d8c0",
          "reference": "vibrant"
        }, 
        {
          "hex": "#444d4f",
          "name": "#444d4f",
          "reference": "vibrant"
        }
      ],
      "sizes": {
        "b": {
          "extension": "jpg",
          "height": 768,
          "mimetype": "image/jpeg",
          "secret": "9btdF3wfn6Vfb2SIJPu8QSwd5t5cze6F",
          "width": 474
        },
        "c": {
          "extension": "jpg",
          "height": 600,
          "mimetype": "image/jpeg",
          "secret": "9btdF3wfn6Vfb2SIJPu8QSwd5t5cze6F",
          "width": 371
        },
        "dc": {
          "extension": "jpg",
          "height": 600,
          "mimetype": "image/jpeg",
          "secret": "9btdF3wfn6Vfb2SIJPu8QSwd5t5cze6F",
          "width": 371
        },
        "ds": {
          "extension": "jpg",
          "height": 320,
          "mimetype": "image/jpeg",
          "secret": "9btdF3wfn6Vfb2SIJPu8QSwd5t5cze6F",
          "width": 320
        },
        "k": {
          "extension": "jpg",
          "height": 1536,
          "mimetype": "image/jpeg",
          "secret": "9btdF3wfn6Vfb2SIJPu8QSwd5t5cze6F",
          "width": 949
        },
        "n": {
          "extension": "jpg",
          "height": 240,
          "mimetype": "image/jpeg",
          "secret": "9btdF3wfn6Vfb2SIJPu8QSwd5t5cze6F",
          "width": 148
        },
        "o": {
          "extension": "jpg",
          "height": 2862,
          "mimetype": "image/jpeg",
          "secret": "S62oWhK2g2cB3IPtjLbG41Cbnb6wTuzu",
          "width": 1770
        },
        "s": {
          "extension": "jpg",
          "height": 320,
          "mimetype": "image/jpeg",
          "secret": "9btdF3wfn6Vfb2SIJPu8QSwd5t5cze6F",
          "width": 320
        },
        "z": {
          "extension": "jpg",
          "height": 480,
          "mimetype": "image/jpeg",
          "secret": "9btdF3wfn6Vfb2SIJPu8QSwd5t5cze6F",
          "width": 296
        }
      }
    },
    "media:uri_template": "https://millsfield.sfomuseum.org/media/152/782/471/7/1527824717_{secret}_{label}.{extention}",
    "sfomuseum:filename": "42743.tif",
    "sfomuseum:image_index": 5,
    "sfomuseum:placetype": "image",
    "sfomuseum:primary_image": 0,
    "wof:depicts": [
      1511908771
    ],
    "wof:name": "motion sickness bag: ship (Far East Hydrofoil)",
    "wof:placetype": "media"
  },
  "geometry": {"coordinates":[-122.386155,37.616358],"type":"Point"}
}
