{
  "type": "Feature",
  "properties": {
    "iso:country": "XX",
    "media:fingerprint": "813a165bbde6c1cbffb9d4492ef9e2284706fa92",
    "media:imagehash_avg": "a:6b6a7b7b4b433b00",
    "media:imagehash_diff": "d:d2caeaea92d3c2e7",
    "media:medium": "image",
    "media:mimetype": "image/tiff",
    "media:properties": {
      "colours": [
        {
          "hex": "#b58452",
          "name": "#b58452",
          "reference": "vibrant"
        }, 
        {
          "hex": "#f3ebd9",
          "name": "#f3ebd9",
          "reference": "vibrant"
        }, 
        {
          "hex": "#818079",
          "name": "#818079",
          "reference": "vibrant"
        }, 
        {
          "hex": "#d4c8b6",
          "name": "#d4c8b6",
          "reference": "vibrant"
        }, 
        {
          "hex": "#545145",
          "name": "#545145",
          "reference": "vibrant"
        }
      ],
      "sizes": {
        "b": {
          "extension": "jpg",
          "height": 768,
          "mimetype": "image/jpeg",
          "secret": "bVTRlgjuD4tswKxB9HypNkCyeiCdOEcL",
          "width": 452
        },
        "c": {
          "extension": "jpg",
          "height": 600,
          "mimetype": "image/jpeg",
          "secret": "bVTRlgjuD4tswKxB9HypNkCyeiCdOEcL",
          "width": 353
        },
        "dc": {
          "extension": "jpg",
          "height": 600,
          "mimetype": "image/jpeg",
          "secret": "bVTRlgjuD4tswKxB9HypNkCyeiCdOEcL",
          "width": 353
        },
        "ds": {
          "extension": "jpg",
          "height": 320,
          "mimetype": "image/jpeg",
          "secret": "bVTRlgjuD4tswKxB9HypNkCyeiCdOEcL",
          "width": 320
        },
        "k": {
          "extension": "jpg",
          "height": 1536,
          "mimetype": "image/jpeg",
          "secret": "bVTRlgjuD4tswKxB9HypNkCyeiCdOEcL",
          "width": 904
        },
        "n": {
          "extension": "jpg",
          "height": 240,
          "mimetype": "image/jpeg",
          "secret": "bVTRlgjuD4tswKxB9HypNkCyeiCdOEcL",
          "width": 141
        },
        "o": {
          "extension": "jpg",
          "height": 3240,
          "mimetype": "image/jpeg",
          "secret": "apN8QOmOEdr9m8nuhpQSkxni4k8dayz8",
          "width": 1908
        },
        "s": {
          "extension": "jpg",
          "height": 320,
          "mimetype": "image/jpeg",
          "secret": "bVTRlgjuD4tswKxB9HypNkCyeiCdOEcL",
          "width": 320
        },
        "z": {
          "extension": "jpg",
          "height": 480,
          "mimetype": "image/jpeg",
          "secret": "bVTRlgjuD4tswKxB9HypNkCyeiCdOEcL",
          "width": 282
        }
      }
    },
    "media:uri_template": "https://millsfield.sfomuseum.org/media/152/782/454/1/1527824541_{secret}_{label}.{extention}",
    "sfomuseum:filename": "42615.tif",
    "sfomuseum:image_index": 5,
    "sfomuseum:placetype": "image",
    "sfomuseum:primary_image": 0,
    "wof:depicts": [
      1511908793
    ],
    "wof:name": "airsickness bag: Laker Airways",
    "wof:placetype": "media"
  },
  "geometry": {"coordinates":[-122.386155,37.616358],"type":"Point"}
}
