{
  "type": "Feature",
  "properties": {
    "iso:country": "XX",
    "media:fingerprint": "99f781157543bcddfd687b5c18212245ee44479e",
    "media:imagehash_avg": "a:ff80808193b3bfff",
    "media:imagehash_diff": "d:7161273766675379",
    "media:medium": "image",
    "media:mimetype": "image/tiff",
    "media:properties": {
      "colours": [
        {
          "hex": "#e6d5a7",
          "name": "#e6d5a7",
          "reference": "vibrant"
        }, 
        {
          "hex": "#841006",
          "name": "#841006",
          "reference": "vibrant"
        }, 
        {
          "hex": "#80868c",
          "name": "#80868c",
          "reference": "vibrant"
        }, 
        {
          "hex": "#c0c0b1",
          "name": "#c0c0b1",
          "reference": "vibrant"
        }, 
        {
          "hex": "#432523",
          "name": "#432523",
          "reference": "vibrant"
        }
      ],
      "sizes": {
        "b": {
          "extension": "jpg",
          "height": 652,
          "mimetype": "image/jpeg",
          "secret": "0X8ZWqbW7b8HAJy84smSTGIlOAUvtQPX",
          "width": 1024
        },
        "c": {
          "extension": "jpg",
          "height": 509,
          "mimetype": "image/jpeg",
          "secret": "0X8ZWqbW7b8HAJy84smSTGIlOAUvtQPX",
          "width": 800
        },
        "dc": {
          "extension": "jpg",
          "height": 509,
          "mimetype": "image/jpeg",
          "secret": "0X8ZWqbW7b8HAJy84smSTGIlOAUvtQPX",
          "width": 800
        },
        "ds": {
          "extension": "jpg",
          "height": 320,
          "mimetype": "image/jpeg",
          "secret": "0X8ZWqbW7b8HAJy84smSTGIlOAUvtQPX",
          "width": 320
        },
        "k": {
          "extension": "jpg",
          "height": 1304,
          "mimetype": "image/jpeg",
          "secret": "0X8ZWqbW7b8HAJy84smSTGIlOAUvtQPX",
          "width": 2048
        },
        "n": {
          "extension": "jpg",
          "height": 203,
          "mimetype": "image/jpeg",
          "secret": "0X8ZWqbW7b8HAJy84smSTGIlOAUvtQPX",
          "width": 320
        },
        "o": {
          "extension": "jpg",
          "height": 1064,
          "mimetype": "image/jpeg",
          "secret": "BaDZ1kWB8D5JVTli9b2IbN0kMeKBC26P",
          "width": 1670
        },
        "s": {
          "extension": "jpg",
          "height": 320,
          "mimetype": "image/jpeg",
          "secret": "0X8ZWqbW7b8HAJy84smSTGIlOAUvtQPX",
          "width": 320
        },
        "z": {
          "extension": "jpg",
          "height": 407,
          "mimetype": "image/jpeg",
          "secret": "0X8ZWqbW7b8HAJy84smSTGIlOAUvtQPX",
          "width": 640
        }
      }
    },
    "media:uri_template": "https://millsfield.sfomuseum.org/media/152/781/968/1/1527819681_{secret}_{label}.{extention}",
    "sfomuseum:filename": "31056.tif",
    "sfomuseum:image_index": 5,
    "sfomuseum:placetype": "image",
    "sfomuseum:primary_image": 0,
    "wof:depicts": [
      1511930229
    ],
    "wof:name": "flight information packet: TWA (Trans World Airlines), Lockheed L-049 Constellation, Boeing 377",
    "wof:placetype": "media"
  },
  "geometry": {"coordinates":[-122.386155,37.616358],"type":"Point"}
}
