{
  "type": "Feature",
  "properties": {
    "iso:country": "XX",
    "media:fingerprint": "96f944bd7d5a4b266f568cb5092c6cfa06e4ab53",
    "media:imagehash_avg": "a:00fecefefefefefe",
    "media:imagehash_diff": "d:1222180658c080a4",
    "media:medium": "image",
    "media:mimetype": "image/jpeg",
    "media:properties": {
      "colours": [
        {
          "hex": "#797788",
          "name": "#797788",
          "reference": "vibrant"
        }, 
        {
          "hex": "#c8bcb7",
          "name": "#c8bcb7",
          "reference": "vibrant"
        }, 
        {
          "hex": "#565463",
          "name": "#565463",
          "reference": "vibrant"
        }
      ],
      "sizes": {
        "b": {
          "extension": "jpg",
          "height": 768,
          "mimetype": "image/jpeg",
          "secret": "LafMSwKMuAOrFY6CRWHkBb0TVYzi3TpR",
          "width": 597
        },
        "c": {
          "extension": "jpg",
          "height": 600,
          "mimetype": "image/jpeg",
          "secret": "LafMSwKMuAOrFY6CRWHkBb0TVYzi3TpR",
          "width": 466
        },
        "dc": {
          "extension": "jpg",
          "height": 600,
          "mimetype": "image/jpeg",
          "secret": "LafMSwKMuAOrFY6CRWHkBb0TVYzi3TpR",
          "width": 466
        },
        "ds": {
          "extension": "jpg",
          "height": 320,
          "mimetype": "image/jpeg",
          "secret": "LafMSwKMuAOrFY6CRWHkBb0TVYzi3TpR",
          "width": 320
        },
        "k": {
          "extension": "jpg",
          "height": 1536,
          "mimetype": "image/jpeg",
          "secret": "LafMSwKMuAOrFY6CRWHkBb0TVYzi3TpR",
          "width": 1194
        },
        "n": {
          "extension": "jpg",
          "height": 240,
          "mimetype": "image/jpeg",
          "secret": "LafMSwKMuAOrFY6CRWHkBb0TVYzi3TpR",
          "width": 186
        },
        "o": {
          "extension": "jpg",
          "height": 3285,
          "mimetype": "image/jpeg",
          "secret": "bdAJXwspsRbMjdbcuJbJmehYj46eJAJr",
          "width": 2555
        },
        "s": {
          "extension": "jpg",
          "height": 320,
          "mimetype": "image/jpeg",
          "secret": "LafMSwKMuAOrFY6CRWHkBb0TVYzi3TpR",
          "width": 320
        },
        "z": {
          "extension": "jpg",
          "height": 480,
          "mimetype": "image/jpeg",
          "secret": "LafMSwKMuAOrFY6CRWHkBb0TVYzi3TpR",
          "width": 373
        }
      }
    },
    "media:uri_template": "https://millsfield.sfomuseum.org/media/152/782/039/9/1527820399_{secret}_{label}.{extention}",
    "sfomuseum:filename": "31589.jpg",
    "sfomuseum:image_index": 5,
    "sfomuseum:placetype": "image",
    "sfomuseum:primary_image": 0,
    "wof:depicts": [
      1511923597
    ],
    "wof:name": "airmail flight cover: Pan American Airways, Clara Adams",
    "wof:placetype": "media"
  },
  "geometry": {"coordinates":[-122.386155,37.616358],"type":"Point"}
}
