{
  "type": "Feature",
  "properties": {
    "iso:country": "XX",
    "media:fingerprint": "59af3ed9d214f7589ff3658568bfdd02debb74d7",
    "media:imagehash_avg": "a:fff3838181ffffff",
    "media:imagehash_diff": "d:67133f1f0f0f4161",
    "media:medium": "image",
    "media:mimetype": "image/tiff",
    "media:properties": {
      "colours": [
        {
          "hex": "#e7d8b8",
          "name": "#e7d8b8",
          "reference": "vibrant"
        }, 
        {
          "hex": "#868570",
          "name": "#868570",
          "reference": "vibrant"
        }, 
        {
          "hex": "#d1c9af",
          "name": "#d1c9af",
          "reference": "vibrant"
        }, 
        {
          "hex": "#4f4938",
          "name": "#4f4938",
          "reference": "vibrant"
        }
      ],
      "sizes": {
        "b": {
          "extension": "jpg",
          "height": 768,
          "mimetype": "image/jpeg",
          "secret": "SCmT8vjXdpUyEl6YGzYcecoLm3Vq3u4D",
          "width": 598
        },
        "c": {
          "extension": "jpg",
          "height": 600,
          "mimetype": "image/jpeg",
          "secret": "SCmT8vjXdpUyEl6YGzYcecoLm3Vq3u4D",
          "width": 467
        },
        "dc": {
          "extension": "jpg",
          "height": 600,
          "mimetype": "image/jpeg",
          "secret": "SCmT8vjXdpUyEl6YGzYcecoLm3Vq3u4D",
          "width": 467
        },
        "ds": {
          "extension": "jpg",
          "height": 320,
          "mimetype": "image/jpeg",
          "secret": "SCmT8vjXdpUyEl6YGzYcecoLm3Vq3u4D",
          "width": 320
        },
        "k": {
          "extension": "jpg",
          "height": 1536,
          "mimetype": "image/jpeg",
          "secret": "SCmT8vjXdpUyEl6YGzYcecoLm3Vq3u4D",
          "width": 1197
        },
        "n": {
          "extension": "jpg",
          "height": 240,
          "mimetype": "image/jpeg",
          "secret": "SCmT8vjXdpUyEl6YGzYcecoLm3Vq3u4D",
          "width": 187
        },
        "o": {
          "extension": "jpg",
          "height": 1800,
          "mimetype": "image/jpeg",
          "secret": "hqdKvtZXMsqiHr60szQlnGesZb67Sx41",
          "width": 1403
        },
        "s": {
          "extension": "jpg",
          "height": 320,
          "mimetype": "image/jpeg",
          "secret": "SCmT8vjXdpUyEl6YGzYcecoLm3Vq3u4D",
          "width": 320
        },
        "z": {
          "extension": "jpg",
          "height": 480,
          "mimetype": "image/jpeg",
          "secret": "SCmT8vjXdpUyEl6YGzYcecoLm3Vq3u4D",
          "width": 374
        }
      }
    },
    "media:uri_template": "https://millsfield.sfomuseum.org/media/152/785/704/5/1527857045_{secret}_{label}.{extention}",
    "sfomuseum:filename": "2000.018.064.008.tif",
    "sfomuseum:image_index": 0,
    "sfomuseum:placetype": "image",
    "sfomuseum:primary_image": 1,
    "wof:depicts": [
      1511958035
    ],
    "wof:name": "correspondence: Aviation Committee of Down Town Association, Mills Field Municipal Airport of San Francisco",
    "wof:placetype": "media"
  },
  "geometry": {"coordinates":[-122.386155,37.616358],"type":"Point"}
}
