{
  "type": "Feature",
  "properties": {
    "iso:country": "XX",
    "media:fingerprint": "b0cc5efd76135238436279846bdee8fe9ad7032a",
    "media:imagehash_avg": "a:00047fff7f7f7f00",
    "media:imagehash_diff": "d:4575e9edededa9ed",
    "media:medium": "image",
    "media:mimetype": "image/tiff",
    "media:properties": {
      "colours": [
        {
          "hex": "#c70d40",
          "name": "#c70d40",
          "reference": "vibrant"
        }, 
        {
          "hex": "#5c96c8",
          "name": "#5c96c8",
          "reference": "vibrant"
        }, 
        {
          "hex": "#073389",
          "name": "#073389",
          "reference": "vibrant"
        }, 
        {
          "hex": "#ab5783",
          "name": "#ab5783",
          "reference": "vibrant"
        }, 
        {
          "hex": "#99afc6",
          "name": "#99afc6",
          "reference": "vibrant"
        }
      ],
      "sizes": {
        "b": {
          "extension": "jpg",
          "height": 653,
          "mimetype": "image/jpeg",
          "secret": "aRboTvzul12WqpEIGDS7eC0Dcve3crqy",
          "width": 1024
        },
        "c": {
          "extension": "jpg",
          "height": 510,
          "mimetype": "image/jpeg",
          "secret": "aRboTvzul12WqpEIGDS7eC0Dcve3crqy",
          "width": 800
        },
        "dc": {
          "extension": "jpg",
          "height": 510,
          "mimetype": "image/jpeg",
          "secret": "aRboTvzul12WqpEIGDS7eC0Dcve3crqy",
          "width": 800
        },
        "ds": {
          "extension": "jpg",
          "height": 320,
          "mimetype": "image/jpeg",
          "secret": "aRboTvzul12WqpEIGDS7eC0Dcve3crqy",
          "width": 320
        },
        "k": {
          "extension": "jpg",
          "height": 1307,
          "mimetype": "image/jpeg",
          "secret": "aRboTvzul12WqpEIGDS7eC0Dcve3crqy",
          "width": 2048
        },
        "n": {
          "extension": "jpg",
          "height": 204,
          "mimetype": "image/jpeg",
          "secret": "aRboTvzul12WqpEIGDS7eC0Dcve3crqy",
          "width": 320
        },
        "o": {
          "extension": "jpg",
          "height": 1066,
          "mimetype": "image/jpeg",
          "secret": "HwtKSLfUJYmqi3gYSb0a85y4P9etAfFH",
          "width": 1670
        },
        "s": {
          "extension": "jpg",
          "height": 320,
          "mimetype": "image/jpeg",
          "secret": "aRboTvzul12WqpEIGDS7eC0Dcve3crqy",
          "width": 320
        },
        "z": {
          "extension": "jpg",
          "height": 408,
          "mimetype": "image/jpeg",
          "secret": "aRboTvzul12WqpEIGDS7eC0Dcve3crqy",
          "width": 640
        }
      }
    },
    "media:uri_template": "https://millsfield.sfomuseum.org/media/152/785/294/5/1527852945_{secret}_{label}.{extention}",
    "sfomuseum:filename": "2012.149.0720 f_verso.tif",
    "sfomuseum:image_index": 5,
    "sfomuseum:placetype": "image",
    "sfomuseum:primary_image": 0,
    "wof:depicts": [
      1511952635
    ],
    "wof:name": "children’s activity kit: Pan American World Airways",
    "wof:placetype": "media"
  },
  "geometry": {"coordinates":[-122.386155,37.616358],"type":"Point"}
}
