{
  "type": "Feature",
  "properties": {
    "iso:country": "XX",
    "media:fingerprint": "2d7bf92248efc269f05c4f459b0823e9fce20611",
    "media:imagehash_avg": "a:00e0e0f0f00cfbff",
    "media:imagehash_diff": "d:61038385517806f2",
    "media:medium": "image",
    "media:mimetype": "image/tiff",
    "media:properties": {
      "colours": [
        {
          "hex": "#868686",
          "name": "#868686",
          "reference": "vibrant"
        }, 
        {
          "hex": "#c0c0c0",
          "name": "#c0c0c0",
          "reference": "vibrant"
        }, 
        {
          "hex": "#404040",
          "name": "#404040",
          "reference": "vibrant"
        }
      ],
      "sizes": {
        "b": {
          "extension": "jpg",
          "height": 768,
          "mimetype": "image/jpeg",
          "secret": "rcDCNhAiaCwGIBkDSBGTrh70IDhLfc0E",
          "width": 768
        },
        "c": {
          "extension": "jpg",
          "height": 600,
          "mimetype": "image/jpeg",
          "secret": "rcDCNhAiaCwGIBkDSBGTrh70IDhLfc0E",
          "width": 600
        },
        "dc": {
          "extension": "jpg",
          "height": 600,
          "mimetype": "image/jpeg",
          "secret": "rcDCNhAiaCwGIBkDSBGTrh70IDhLfc0E",
          "width": 600
        },
        "ds": {
          "extension": "jpg",
          "height": 320,
          "mimetype": "image/jpeg",
          "secret": "rcDCNhAiaCwGIBkDSBGTrh70IDhLfc0E",
          "width": 320
        },
        "k": {
          "extension": "jpg",
          "height": 1536,
          "mimetype": "image/jpeg",
          "secret": "rcDCNhAiaCwGIBkDSBGTrh70IDhLfc0E",
          "width": 1536
        },
        "n": {
          "extension": "jpg",
          "height": 240,
          "mimetype": "image/jpeg",
          "secret": "rcDCNhAiaCwGIBkDSBGTrh70IDhLfc0E",
          "width": 240
        },
        "o": {
          "extension": "jpg",
          "height": 2590,
          "mimetype": "image/jpeg",
          "secret": "kgYPYKD892fDoTpAJ8rUVCMxyAuKJRlk",
          "width": 2590
        },
        "s": {
          "extension": "jpg",
          "height": 320,
          "mimetype": "image/jpeg",
          "secret": "rcDCNhAiaCwGIBkDSBGTrh70IDhLfc0E",
          "width": 320
        },
        "z": {
          "extension": "jpg",
          "height": 480,
          "mimetype": "image/jpeg",
          "secret": "rcDCNhAiaCwGIBkDSBGTrh70IDhLfc0E",
          "width": 480
        }
      }
    },
    "media:uri_template": "https://millsfield.sfomuseum.org/media/152/782/793/5/1527827935_{secret}_{label}.{extention}",
    "sfomuseum:filename": "44308.tif",
    "sfomuseum:image_index": 5,
    "sfomuseum:placetype": "image",
    "sfomuseum:primary_image": 1,
    "wof:depicts": [
      1511948969
    ],
    "wof:name": "negative: San Francisco International Airport (SFO), South Terminal, Rotunda A construction",
    "wof:placetype": "media"
  },
  "geometry": {"coordinates":[-122.386155,37.616358],"type":"Point"}
}
