{
  "type": "Feature",
  "properties": {
    "iso:country": "XX",
    "media:fingerprint": "eb05c3e303de4385a6a0fe52829df3bfee80d071",
    "media:imagehash_avg": "a:ffffe010000000c0",
    "media:imagehash_diff": "d:fcfc00e0e0f05010",
    "media:medium": "image",
    "media:mimetype": "image/tiff",
    "media:properties": {
      "colours": [
        {
          "hex": "#868686",
          "name": "#868686",
          "reference": "vibrant"
        }, 
        {
          "hex": "#b8b8b8",
          "name": "#b8b8b8",
          "reference": "vibrant"
        }, 
        {
          "hex": "#454545",
          "name": "#454545",
          "reference": "vibrant"
        }
      ],
      "sizes": {
        "b": {
          "extension": "jpg",
          "height": 767,
          "mimetype": "image/jpeg",
          "secret": "HjzJknJwDtTvAiSMcWp2aUsdTxUmJu9K",
          "width": 978
        },
        "c": {
          "extension": "jpg",
          "height": 600,
          "mimetype": "image/jpeg",
          "secret": "HjzJknJwDtTvAiSMcWp2aUsdTxUmJu9K",
          "width": 764
        },
        "dc": {
          "extension": "jpg",
          "height": 600,
          "mimetype": "image/jpeg",
          "secret": "HjzJknJwDtTvAiSMcWp2aUsdTxUmJu9K",
          "width": 764
        },
        "ds": {
          "extension": "jpg",
          "height": 320,
          "mimetype": "image/jpeg",
          "secret": "HjzJknJwDtTvAiSMcWp2aUsdTxUmJu9K",
          "width": 320
        },
        "k": {
          "extension": "jpg",
          "height": 1535,
          "mimetype": "image/jpeg",
          "secret": "HjzJknJwDtTvAiSMcWp2aUsdTxUmJu9K",
          "width": 1957
        },
        "n": {
          "extension": "jpg",
          "height": 240,
          "mimetype": "image/jpeg",
          "secret": "HjzJknJwDtTvAiSMcWp2aUsdTxUmJu9K",
          "width": 305
        },
        "o": {
          "extension": "jpg",
          "height": 2140,
          "mimetype": "image/jpeg",
          "secret": "3K3zI4hfNGPX8WQuEmp9YfEkIkaG0kVp",
          "width": 2727
        },
        "s": {
          "extension": "jpg",
          "height": 320,
          "mimetype": "image/jpeg",
          "secret": "HjzJknJwDtTvAiSMcWp2aUsdTxUmJu9K",
          "width": 320
        },
        "z": {
          "extension": "jpg",
          "height": 480,
          "mimetype": "image/jpeg",
          "secret": "HjzJknJwDtTvAiSMcWp2aUsdTxUmJu9K",
          "width": 611
        }
      }
    },
    "media:uri_template": "https://millsfield.sfomuseum.org/media/152/782/509/1/1527825091_{secret}_{label}.{extention}",
    "sfomuseum:filename": "42960.tif",
    "sfomuseum:image_index": 5,
    "sfomuseum:placetype": "image",
    "sfomuseum:primary_image": 1,
    "wof:depicts": [
      1511946017
    ],
    "wof:name": "negative: San Francisco International Airport (SFO), aerial",
    "wof:placetype": "media"
  },
  "geometry": {"coordinates":[-122.386155,37.616358],"type":"Point"}
}
