{
  "type": "Feature",
  "properties": {
    "media:fingerprint": "51674c9ad210f8fa64de5f69d0c04404ef659552",
    "media:imagehash_avg": "a:383a3f3bc0f0bf8a",
    "media:imagehash_diff": "d:60627466a612765a",
    "media:mimetype": "image/tiff",
    "media:properties": {
      "colours": [
        {
          "hex": "#858585",
          "name": "#858585",
          "reference": "vibrant"
        },
        {
          "hex": "#b8b8b8",
          "name": "#b8b8b8",
          "reference": "vibrant"
        },
        {
          "hex": "#484848",
          "name": "#484848",
          "reference": "vibrant"
        }
      ],
      "sizes": {
        "b": {
          "extension": "jpg",
          "height": 768,
          "mimetype": "image/jpeg",
          "secret": "8rRLbRCoAYm8BXJ2HRl0Z321EtUc2fQD",
          "width": 980
        },
        "c": {
          "extension": "jpg",
          "height": 600,
          "mimetype": "image/jpeg",
          "secret": "8rRLbRCoAYm8BXJ2HRl0Z321EtUc2fQD",
          "width": 765
        },
        "dc": {
          "extension": "jpg",
          "height": 600,
          "mimetype": "image/jpeg",
          "secret": "8rRLbRCoAYm8BXJ2HRl0Z321EtUc2fQD",
          "width": 765
        },
        "ds": {
          "extension": "jpg",
          "height": 320,
          "mimetype": "image/jpeg",
          "secret": "8rRLbRCoAYm8BXJ2HRl0Z321EtUc2fQD",
          "width": 320
        },
        "k": {
          "extension": "jpg",
          "height": 1536,
          "mimetype": "image/jpeg",
          "secret": "8rRLbRCoAYm8BXJ2HRl0Z321EtUc2fQD",
          "width": 1960
        },
        "n": {
          "extension": "jpg",
          "height": 240,
          "mimetype": "image/jpeg",
          "secret": "8rRLbRCoAYm8BXJ2HRl0Z321EtUc2fQD",
          "width": 306
        },
        "o": {
          "extension": "jpg",
          "height": 2088,
          "mimetype": "image/jpeg",
          "secret": "NMb0YtizW28TsdnB92nqMAZhqgaKCfoi",
          "width": 2665
        },
        "s": {
          "extension": "jpg",
          "height": 320,
          "mimetype": "image/jpeg",
          "secret": "8rRLbRCoAYm8BXJ2HRl0Z321EtUc2fQD",
          "width": 320
        },
        "z": {
          "extension": "jpg",
          "height": 480,
          "mimetype": "image/jpeg",
          "secret": "8rRLbRCoAYm8BXJ2HRl0Z321EtUc2fQD",
          "width": 612
        }
      }
    },
    "media:uri_template": "https://static.sfomuseum.org/media/174/651/209/3/1746512093_{secret}_{label}.{extention}",
    "sfomuseum:filename": "45916.tif",
    "sfomuseum:image_index": 0,
    "sfomuseum:image_type": "studio",
    "sfomuseum:placetype": "image",
    "sfomuseum:primary_image": 1,
    "wof:depicts": [
      1159285393,
      1729563763
    ],
    "wof:name": "negative: TWA (Trans World Airlines), Melvin Lee Milligan II, Vice President General Counsel",
    "wof:placetype": "custom",
    "wof:placetype_alt": "image"
  },
  "geometry": {"coordinates":[-122.386155,37.616357],"type":"Point"}
}
