{
  "type": "Feature",
  "properties": {
    "iso:country": "XX",
    "media:fingerprint": "d46006954a23b266c12a8672d47cab303f1b4948",
    "media:imagehash_avg": "a:183c7c7efc383cfc",
    "media:imagehash_diff": "d:71f0f0f0f0f1d9b8",
    "media:medium": "image",
    "media:mimetype": "image/tiff",
    "media:properties": {
      "colours": [
        {
          "hex": "#808080",
          "name": "#808080",
          "reference": "vibrant"
        },
        {
          "hex": "#b6b6b6",
          "name": "#b6b6b6",
          "reference": "vibrant"
        },
        {
          "hex": "#404040",
          "name": "#404040",
          "reference": "vibrant"
        }
      ],
      "sizes": {
        "b": {
          "extension": "jpg",
          "height": 768,
          "mimetype": "image/jpeg",
          "secret": "9V5vQcWqTW6bs40Ftli4EU6QO9W7GjUw",
          "width": 628
        },
        "c": {
          "extension": "jpg",
          "height": 600,
          "mimetype": "image/jpeg",
          "secret": "9V5vQcWqTW6bs40Ftli4EU6QO9W7GjUw",
          "width": 490
        },
        "dc": {
          "extension": "jpg",
          "height": 600,
          "mimetype": "image/jpeg",
          "secret": "9V5vQcWqTW6bs40Ftli4EU6QO9W7GjUw",
          "width": 490
        },
        "ds": {
          "extension": "jpg",
          "height": 320,
          "mimetype": "image/jpeg",
          "secret": "9V5vQcWqTW6bs40Ftli4EU6QO9W7GjUw",
          "width": 320
        },
        "k": {
          "extension": "jpg",
          "height": 1536,
          "mimetype": "image/jpeg",
          "secret": "9V5vQcWqTW6bs40Ftli4EU6QO9W7GjUw",
          "width": 1256
        },
        "n": {
          "extension": "jpg",
          "height": 240,
          "mimetype": "image/jpeg",
          "secret": "9V5vQcWqTW6bs40Ftli4EU6QO9W7GjUw",
          "width": 196
        },
        "o": {
          "extension": "jpg",
          "height": 2097,
          "mimetype": "image/jpeg",
          "secret": "GSL51gjLioZxYlmt304WNc1t5Am73qJg",
          "width": 1716
        },
        "s": {
          "extension": "jpg",
          "height": 320,
          "mimetype": "image/jpeg",
          "secret": "9V5vQcWqTW6bs40Ftli4EU6QO9W7GjUw",
          "width": 320
        },
        "z": {
          "extension": "jpg",
          "height": 480,
          "mimetype": "image/jpeg",
          "secret": "9V5vQcWqTW6bs40Ftli4EU6QO9W7GjUw",
          "width": 392
        }
      }
    },
    "media:uri_template": "https://static.sfomuseum.org/media/152/783/130/3/1527831303_{secret}_{label}.{extention}",
    "sfomuseum:filename": "58322.tif",
    "sfomuseum:image_index": 5,
    "sfomuseum:image_type": "studio",
    "sfomuseum:placetype": "image",
    "sfomuseum:primary_image": 1,
    "wof:depicts": [
      1511955571
    ],
    "wof:name": "glass negative: Panama-Pacific International Exposition",
    "wof:placetype": "custom",
    "wof:placetype_alt": "image"
  },
  "geometry": {"coordinates":[-122.386155,37.616358],"type":"Point"}
}
