{
  "type": "Feature",
  "properties": {
    "iso:country": "XX",
    "media:fingerprint": "bd514d04b457fb3edede33082967905d7f768454",
    "media:imagehash_avg": "a:dfcf870707078fff",
    "media:imagehash_diff": "d:1319496d6f4f2d3b",
    "media:medium": "image",
    "media:mimetype": "image/tiff",
    "media:properties": {
      "colours": [
        {
          "hex": "#f8d745",
          "name": "#f8d745",
          "reference": "vibrant"
        }, 
        {
          "hex": "#f8d955",
          "name": "#f8d955",
          "reference": "vibrant"
        }, 
        {
          "hex": "#2e487f",
          "name": "#2e487f",
          "reference": "vibrant"
        }, 
        {
          "hex": "#a96b7b",
          "name": "#a96b7b",
          "reference": "vibrant"
        }, 
        {
          "hex": "#aeb1bd",
          "name": "#aeb1bd",
          "reference": "vibrant"
        }
      ],
      "sizes": {
        "b": {
          "extension": "jpg",
          "height": 768,
          "mimetype": "image/jpeg",
          "secret": "B9O9mwLSXAjAMRLoQjIeW9kuVIlkagbd",
          "width": 533
        },
        "c": {
          "extension": "jpg",
          "height": 600,
          "mimetype": "image/jpeg",
          "secret": "B9O9mwLSXAjAMRLoQjIeW9kuVIlkagbd",
          "width": 416
        },
        "dc": {
          "extension": "jpg",
          "height": 600,
          "mimetype": "image/jpeg",
          "secret": "B9O9mwLSXAjAMRLoQjIeW9kuVIlkagbd",
          "width": 416
        },
        "ds": {
          "extension": "jpg",
          "height": 320,
          "mimetype": "image/jpeg",
          "secret": "B9O9mwLSXAjAMRLoQjIeW9kuVIlkagbd",
          "width": 320
        },
        "k": {
          "extension": "jpg",
          "height": 1536,
          "mimetype": "image/jpeg",
          "secret": "B9O9mwLSXAjAMRLoQjIeW9kuVIlkagbd",
          "width": 1066
        },
        "n": {
          "extension": "jpg",
          "height": 240,
          "mimetype": "image/jpeg",
          "secret": "B9O9mwLSXAjAMRLoQjIeW9kuVIlkagbd",
          "width": 166
        },
        "o": {
          "extension": "jpg",
          "height": 1540,
          "mimetype": "image/jpeg",
          "secret": "BdqbwbTq2qnOBc4XgNTKENjO6id50RTG",
          "width": 1069
        },
        "s": {
          "extension": "jpg",
          "height": 320,
          "mimetype": "image/jpeg",
          "secret": "B9O9mwLSXAjAMRLoQjIeW9kuVIlkagbd",
          "width": 320
        },
        "z": {
          "extension": "jpg",
          "height": 480,
          "mimetype": "image/jpeg",
          "secret": "B9O9mwLSXAjAMRLoQjIeW9kuVIlkagbd",
          "width": 333
        }
      }
    },
    "media:uri_template": "https://millsfield.sfomuseum.org/media/152/782/924/7/1527829247_{secret}_{label}.{extention}",
    "sfomuseum:filename": "47680.tif",
    "sfomuseum:image_index": 5,
    "sfomuseum:placetype": "image",
    "sfomuseum:primary_image": 1,
    "wof:depicts": [
      1511951341
    ],
    "wof:name": "advertisement: Panagra (Pan American-Grace Airways) and Pan American World Airways",
    "wof:placetype": "media"
  },
  "geometry": {"coordinates":[-122.386155,37.616358],"type":"Point"}
}
