{
  "type": "Feature",
  "properties": {
    "date:cessation_lower": "1915-01-01",
    "date:cessation_upper": "1915-12-31",
    "date:inception_lower": "1915-01-01",
    "date:inception_upper": "1915-12-31",
    "iso:country": "XX",
    "media:fingerprint": "07dcbc5f3fab41b99400e04045762a8e3020dfe7",
    "media:imagehash_avg": "a:ff998d85858181cf",
    "media:imagehash_diff": "d:63737d5d1d0d0d19",
    "media:mimetype": "image/tiff",
    "media:properties": {
      "colours": [
        {
          "hex": "#858782",
          "name": "#858782",
          "reference": "vibrant"
        },
        {
          "hex": "#b5b8af",
          "name": "#b5b8af",
          "reference": "vibrant"
        },
        {
          "hex": "#3a3d3a",
          "name": "#3a3d3a",
          "reference": "vibrant"
        }
      ],
      "sizes": {
        "b": {
          "extension": "jpg",
          "height": 768,
          "mimetype": "image/jpeg",
          "secret": "gvKO4VMKFj1WMpP2BkX8zYUMAWkGp6g7",
          "width": 980
        },
        "c": {
          "extension": "jpg",
          "height": 600,
          "mimetype": "image/jpeg",
          "secret": "gvKO4VMKFj1WMpP2BkX8zYUMAWkGp6g7",
          "width": 766
        },
        "dc": {
          "extension": "jpg",
          "height": 600,
          "mimetype": "image/jpeg",
          "secret": "gvKO4VMKFj1WMpP2BkX8zYUMAWkGp6g7",
          "width": 766
        },
        "ds": {
          "extension": "jpg",
          "height": 320,
          "mimetype": "image/jpeg",
          "secret": "gvKO4VMKFj1WMpP2BkX8zYUMAWkGp6g7",
          "width": 320
        },
        "k": {
          "extension": "jpg",
          "height": 1536,
          "mimetype": "image/jpeg",
          "secret": "gvKO4VMKFj1WMpP2BkX8zYUMAWkGp6g7",
          "width": 1961
        },
        "n": {
          "extension": "jpg",
          "height": 239,
          "mimetype": "image/jpeg",
          "secret": "gvKO4VMKFj1WMpP2BkX8zYUMAWkGp6g7",
          "width": 306
        },
        "o": {
          "extension": "jpg",
          "height": 1566,
          "mimetype": "image/jpeg",
          "secret": "skNAmt7CeXImwvjEmokhvnqZFY8nZ63p",
          "width": 2000
        },
        "s": {
          "extension": "jpg",
          "height": 320,
          "mimetype": "image/jpeg",
          "secret": "gvKO4VMKFj1WMpP2BkX8zYUMAWkGp6g7",
          "width": 320
        },
        "z": {
          "extension": "jpg",
          "height": 479,
          "mimetype": "image/jpeg",
          "secret": "gvKO4VMKFj1WMpP2BkX8zYUMAWkGp6g7",
          "width": 613
        }
      }
    },
    "media:uri_template": "https://static.sfomuseum.org/media/176/344/359/1/1763443591_{secret}_{label}.{extension}",
    "sfomuseum:filename": "126547.tif",
    "sfomuseum:image_index": 5,
    "sfomuseum:image_type": "studio",
    "sfomuseum:placetype": "image",
    "sfomuseum:primary_image": 1,
    "wof:depicts": [
      1511958185
    ],
    "wof:name": "photograph: Panama-Pacific International Exposition, aviator Art Smith",
    "wof:placetype": "custom"
  },
  "geometry": {"coordinates":[-122.386155,37.616357],"type":"Point"}
}
