{
  "type": "Feature",
  "properties": {
    "iso:country": "XX",
    "media:fingerprint": "5e8c8072281a3d00f7bf7b58d24e23d34ac3caf0",
    "media:imagehash_avg": "a:ff81cbcb01d1c1df",
    "media:imagehash_diff": "d:3b1b333b39a5b517",
    "media:medium": "image",
    "media:mimetype": "image/tiff",
    "media:properties": {
      "colours": [
        {
          "hex": "#eacb4b",
          "name": "#eacb4b",
          "reference": "vibrant"
        },
        {
          "hex": "#f8f88a",
          "name": "#f8f88a",
          "reference": "vibrant"
        },
        {
          "hex": "#786612",
          "name": "#786612",
          "reference": "vibrant"
        }
      ],
      "sizes": {
        "b": {
          "extension": "jpg",
          "height": 641,
          "mimetype": "image/jpeg",
          "secret": "KlCg2Iq9gC4qd0ntXWlbfJA7P3pQ8RcW",
          "width": 1024
        },
        "c": {
          "extension": "jpg",
          "height": 501,
          "mimetype": "image/jpeg",
          "secret": "KlCg2Iq9gC4qd0ntXWlbfJA7P3pQ8RcW",
          "width": 800
        },
        "dc": {
          "extension": "jpg",
          "height": 501,
          "mimetype": "image/jpeg",
          "secret": "KlCg2Iq9gC4qd0ntXWlbfJA7P3pQ8RcW",
          "width": 800
        },
        "ds": {
          "extension": "jpg",
          "height": 320,
          "mimetype": "image/jpeg",
          "secret": "KlCg2Iq9gC4qd0ntXWlbfJA7P3pQ8RcW",
          "width": 320
        },
        "k": {
          "extension": "jpg",
          "height": 1283,
          "mimetype": "image/jpeg",
          "secret": "KlCg2Iq9gC4qd0ntXWlbfJA7P3pQ8RcW",
          "width": 2048
        },
        "n": {
          "extension": "jpg",
          "height": 200,
          "mimetype": "image/jpeg",
          "secret": "KlCg2Iq9gC4qd0ntXWlbfJA7P3pQ8RcW",
          "width": 320
        },
        "o": {
          "extension": "jpg",
          "height": 2560,
          "mimetype": "image/jpeg",
          "secret": "o9fwcDnSOWMWmWrE5m0tvGonfvMVP5s8",
          "width": 4085
        },
        "s": {
          "extension": "jpg",
          "height": 320,
          "mimetype": "image/jpeg",
          "secret": "KlCg2Iq9gC4qd0ntXWlbfJA7P3pQ8RcW",
          "width": 320
        },
        "z": {
          "extension": "jpg",
          "height": 401,
          "mimetype": "image/jpeg",
          "secret": "KlCg2Iq9gC4qd0ntXWlbfJA7P3pQ8RcW",
          "width": 640
        }
      }
    },
    "media:uri_template": "https://static.sfomuseum.org/media/152/785/363/3/1527853633_{secret}_{label}.{extention}",
    "sfomuseum:filename": "92694.tif",
    "sfomuseum:image_index": 5,
    "sfomuseum:image_type": "studio",
    "sfomuseum:placetype": "image",
    "sfomuseum:primary_image": 1,
    "wof:depicts": [
      1159284991,
      1511956631,
      1159284989,
      1159286839
    ],
    "wof:name": "timetable: Pan American World Airways, cargo schedule",
    "wof:placetype": "custom",
    "wof:placetype_alt": "image"
  },
  "geometry": {"coordinates":[-122.386155,37.616358],"type":"Point"}
}
