{
  "type": "Feature",
  "properties": {
    "iso:country": "US",
    "media:fingerprint": "23fa48054ee7b55cb8ea99c494d8395fe43637d7",
    "media:imagehash_avg": "a:fffcf8e380c040e0",
    "media:imagehash_diff": "d:c10490070c9cceca",
    "media:medium": "image",
    "media:mimetype": "image/jpeg",
    "media:properties": {
      "colours": [
        {
          "hex": "#808080",
          "name": "#808080",
          "reference": "vibrant"
        }, 
        {
          "hex": "#bababa",
          "name": "#bababa",
          "reference": "vibrant"
        }, 
        {
          "hex": "#484848",
          "name": "#484848",
          "reference": "vibrant"
        }
      ],
      "sizes": {
        "b": {
          "extension": "jpg",
          "height": 768,
          "mimetype": "image/jpeg",
          "secret": "DYcvtKZTOmD5FeysFKCOTXywqV5rTENr",
          "width": 966
        },
        "c": {
          "extension": "jpg",
          "height": 600,
          "mimetype": "image/jpeg",
          "secret": "DYcvtKZTOmD5FeysFKCOTXywqV5rTENr",
          "width": 755
        },
        "dc": {
          "extension": "jpg",
          "height": 600,
          "mimetype": "image/jpeg",
          "secret": "DYcvtKZTOmD5FeysFKCOTXywqV5rTENr",
          "width": 755
        },
        "ds": {
          "extension": "jpg",
          "height": 320,
          "mimetype": "image/jpeg",
          "secret": "DYcvtKZTOmD5FeysFKCOTXywqV5rTENr",
          "width": 320
        },
        "k": {
          "extension": "jpg",
          "height": 1536,
          "mimetype": "image/jpeg",
          "secret": "DYcvtKZTOmD5FeysFKCOTXywqV5rTENr",
          "width": 1932
        },
        "n": {
          "extension": "jpg",
          "height": 240,
          "mimetype": "image/jpeg",
          "secret": "DYcvtKZTOmD5FeysFKCOTXywqV5rTENr",
          "width": 302
        },
        "o": {
          "extension": "jpg",
          "height": 2229,
          "mimetype": "image/jpeg",
          "secret": "FzOGL26Abeuz1ZbWE3mfkSm1cUilXgwW",
          "width": 2805
        },
        "s": {
          "extension": "jpg",
          "height": 320,
          "mimetype": "image/jpeg",
          "secret": "DYcvtKZTOmD5FeysFKCOTXywqV5rTENr",
          "width": 320
        },
        "z": {
          "extension": "jpg",
          "height": 480,
          "mimetype": "image/jpeg",
          "secret": "DYcvtKZTOmD5FeysFKCOTXywqV5rTENr",
          "width": 604
        }
      }
    },
    "media:uri_template": "https://millsfield.sfomuseum.org/media/152/781/916/9/1527819169_{secret}_{label}.{extention}",
    "sfomuseum:filename": "21001.jpg",
    "sfomuseum:image_index": 5,
    "sfomuseum:placetype": "image",
    "sfomuseum:primary_image": 1,
    "wof:depicts": [
      1511942983
    ],
    "wof:name": "photograph: San Francisco International Airport (SFO), Central Terminal Building",
    "wof:placetype": "media"
  },
  "geometry": {"coordinates":[-122.386155,37.616358],"type":"Point"}
}
