{
  "type": "Feature",
  "properties": {
    "sfomuseum:filename": "10642.JPG",
    "sfomuseum:image_index": 1,
    "sfomuseum:image_type": "curator",
    "sfomuseum:placetype": "image",
    "sfomuseum:primary_image": 1,
    "wof:depicts": [
      1511941387,
      1159285477,
      1159288707
    ],
    "wof:name": "phonograph record: VIASA Venezuelan International Airways, Music in the air...",
    "wof:placetype": "custom"
  },
  "geometry": {"coordinates":[-122.386155,37.616357],"type":"Point"}
}
