{
  "type": "Feature",
  "properties": {
    "iso:country": "XX",
    "media:fingerprint": "0f11eeed823c484ab6f58545f963cfcdc7d0fbe3",
    "media:imagehash_avg": "a:ff7cfef9c0800000",
    "media:imagehash_diff": "d:e0c8c89321256573",
    "media:medium": "image",
    "media:mimetype": "image/tiff",
    "media:properties": {
      "colours": [
        {
          "hex": "#808080",
          "name": "#808080",
          "reference": "vibrant"
        }, 
        {
          "hex": "#c0c0c0",
          "name": "#c0c0c0",
          "reference": "vibrant"
        }, 
        {
          "hex": "#464646",
          "name": "#464646",
          "reference": "vibrant"
        }
      ],
      "sizes": {
        "b": {
          "extension": "jpg",
          "height": 768,
          "mimetype": "image/jpeg",
          "secret": "MN6bKWIKVn7Ve8smbT17eE4bANWLxvYX",
          "width": 986
        },
        "c": {
          "extension": "jpg",
          "height": 600,
          "mimetype": "image/jpeg",
          "secret": "MN6bKWIKVn7Ve8smbT17eE4bANWLxvYX",
          "width": 771
        },
        "dc": {
          "extension": "jpg",
          "height": 600,
          "mimetype": "image/jpeg",
          "secret": "MN6bKWIKVn7Ve8smbT17eE4bANWLxvYX",
          "width": 771
        },
        "ds": {
          "extension": "jpg",
          "height": 320,
          "mimetype": "image/jpeg",
          "secret": "MN6bKWIKVn7Ve8smbT17eE4bANWLxvYX",
          "width": 320
        },
        "k": {
          "extension": "jpg",
          "height": 1536,
          "mimetype": "image/jpeg",
          "secret": "MN6bKWIKVn7Ve8smbT17eE4bANWLxvYX",
          "width": 1973
        },
        "n": {
          "extension": "jpg",
          "height": 240,
          "mimetype": "image/jpeg",
          "secret": "MN6bKWIKVn7Ve8smbT17eE4bANWLxvYX",
          "width": 308
        },
        "o": {
          "extension": "jpg",
          "height": 2154,
          "mimetype": "image/jpeg",
          "secret": "X30rzVfBKS0NnuTaGslhJvKqj9DBExkU",
          "width": 2768
        },
        "s": {
          "extension": "jpg",
          "height": 320,
          "mimetype": "image/jpeg",
          "secret": "MN6bKWIKVn7Ve8smbT17eE4bANWLxvYX",
          "width": 320
        },
        "z": {
          "extension": "jpg",
          "height": 480,
          "mimetype": "image/jpeg",
          "secret": "MN6bKWIKVn7Ve8smbT17eE4bANWLxvYX",
          "width": 616
        }
      }
    },
    "media:uri_template": "https://millsfield.sfomuseum.org/media/152/782/165/5/1527821655_{secret}_{label}.{extention}",
    "sfomuseum:filename": "38910.tif",
    "sfomuseum:image_index": 5,
    "sfomuseum:placetype": "image",
    "sfomuseum:primary_image": 1,
    "wof:depicts": [
      1511943731
    ],
    "wof:name": "negative: San Francisco Airport, runway maintenance",
    "wof:placetype": "media"
  },
  "geometry": {"coordinates":[-122.386155,37.616358],"type":"Point"}
}
