{
  "type": "Feature",
  "properties": {
    "iso:country": "XX",
    "media:fingerprint": "d6c13d15c491507a46b31bd1e9febbd2781aa12d",
    "media:imagehash_avg": "a:c781c181818181c7",
    "media:imagehash_diff": "d:1f0f0f0f3b393907",
    "media:medium": "image",
    "media:mimetype": "image/tiff",
    "media:properties": {
      "colours": [
        {
          "hex": "#dfd5b7",
          "name": "#dfd5b7",
          "reference": "vibrant"
        },
        {
          "hex": "#a08e6a",
          "name": "#a08e6a",
          "reference": "vibrant"
        },
        {
          "hex": "#d8ceb7",
          "name": "#d8ceb7",
          "reference": "vibrant"
        },
        {
          "hex": "#474236",
          "name": "#474236",
          "reference": "vibrant"
        }
      ],
      "sizes": {
        "b": {
          "extension": "jpg",
          "height": 768,
          "mimetype": "image/jpeg",
          "secret": "816PTuhC4EISNSTzOkgFd2gMm2ubykmh",
          "width": 595
        },
        "c": {
          "extension": "jpg",
          "height": 600,
          "mimetype": "image/jpeg",
          "secret": "816PTuhC4EISNSTzOkgFd2gMm2ubykmh",
          "width": 464
        },
        "dc": {
          "extension": "jpg",
          "height": 600,
          "mimetype": "image/jpeg",
          "secret": "816PTuhC4EISNSTzOkgFd2gMm2ubykmh",
          "width": 464
        },
        "ds": {
          "extension": "jpg",
          "height": 320,
          "mimetype": "image/jpeg",
          "secret": "816PTuhC4EISNSTzOkgFd2gMm2ubykmh",
          "width": 320
        },
        "k": {
          "extension": "jpg",
          "height": 1536,
          "mimetype": "image/jpeg",
          "secret": "816PTuhC4EISNSTzOkgFd2gMm2ubykmh",
          "width": 1190
        },
        "n": {
          "extension": "jpg",
          "height": 240,
          "mimetype": "image/jpeg",
          "secret": "816PTuhC4EISNSTzOkgFd2gMm2ubykmh",
          "width": 185
        },
        "o": {
          "extension": "jpg",
          "height": 3313,
          "mimetype": "image/jpeg",
          "secret": "1siEbxU3mGaGRtxXgFefihYjPVx7Tjzr",
          "width": 2567
        },
        "s": {
          "extension": "jpg",
          "height": 320,
          "mimetype": "image/jpeg",
          "secret": "816PTuhC4EISNSTzOkgFd2gMm2ubykmh",
          "width": 320
        },
        "z": {
          "extension": "jpg",
          "height": 480,
          "mimetype": "image/jpeg",
          "secret": "816PTuhC4EISNSTzOkgFd2gMm2ubykmh",
          "width": 371
        }
      }
    },
    "media:uri_template": "https://static.sfomuseum.org/media/152/785/200/1/1527852001_{secret}_{label}.{extention}",
    "sfomuseum:filename": "85968.tif",
    "sfomuseum:image_index": 5,
    "sfomuseum:image_type": "studio",
    "sfomuseum:placetype": "image",
    "sfomuseum:primary_image": 0,
    "wof:depicts": [
      1511954239,
      1159284991
    ],
    "wof:name": "airmail flight cover test: Pan American Airways, FAM-18, New York - Marseilles route",
    "wof:placetype": "custom",
    "wof:placetype_alt": "image"
  },
  "geometry": {"coordinates":[-122.386155,37.616358],"type":"Point"}
}
