{
  "type": "Feature",
  "properties": {
    "iso:country": "XX",
    "media:fingerprint": "4134a8ae529b9bf81720c6955f58ff2ccdf85e36",
    "media:imagehash_avg": "a:3f19b9e183f79dff",
    "media:imagehash_diff": "d:697161254f6d3135",
    "media:medium": "image",
    "media:mimetype": "image/tiff",
    "media:properties": {
      "colours": [
        {
          "hex": "#7f3831",
          "name": "#7f3831",
          "reference": "vibrant"
        }, 
        {
          "hex": "#0a0e46",
          "name": "#0a0e46",
          "reference": "vibrant"
        }, 
        {
          "hex": "#986a5c",
          "name": "#986a5c",
          "reference": "vibrant"
        }, 
        {
          "hex": "#cfc5a7",
          "name": "#cfc5a7",
          "reference": "vibrant"
        }, 
        {
          "hex": "#64372d",
          "name": "#64372d",
          "reference": "vibrant"
        }
      ],
      "sizes": {
        "b": {
          "extension": "jpg",
          "height": 468,
          "mimetype": "image/jpeg",
          "secret": "Ul8TEcaDWSRS4NtAZglF2QVhFiZLGeDR",
          "width": 1024
        },
        "c": {
          "extension": "jpg",
          "height": 365,
          "mimetype": "image/jpeg",
          "secret": "Ul8TEcaDWSRS4NtAZglF2QVhFiZLGeDR",
          "width": 800
        },
        "dc": {
          "extension": "jpg",
          "height": 365,
          "mimetype": "image/jpeg",
          "secret": "Ul8TEcaDWSRS4NtAZglF2QVhFiZLGeDR",
          "width": 800
        },
        "ds": {
          "extension": "jpg",
          "height": 320,
          "mimetype": "image/jpeg",
          "secret": "Ul8TEcaDWSRS4NtAZglF2QVhFiZLGeDR",
          "width": 320
        },
        "k": {
          "extension": "jpg",
          "height": 936,
          "mimetype": "image/jpeg",
          "secret": "Ul8TEcaDWSRS4NtAZglF2QVhFiZLGeDR",
          "width": 2048
        },
        "n": {
          "extension": "jpg",
          "height": 146,
          "mimetype": "image/jpeg",
          "secret": "Ul8TEcaDWSRS4NtAZglF2QVhFiZLGeDR",
          "width": 320
        },
        "o": {
          "extension": "jpg",
          "height": 1260,
          "mimetype": "image/jpeg",
          "secret": "I0drKMfokoZ7ruAKLMlxTPgAiPrVk38G",
          "width": 2756
        },
        "s": {
          "extension": "jpg",
          "height": 320,
          "mimetype": "image/jpeg",
          "secret": "Ul8TEcaDWSRS4NtAZglF2QVhFiZLGeDR",
          "width": 320
        },
        "z": {
          "extension": "jpg",
          "height": 292,
          "mimetype": "image/jpeg",
          "secret": "Ul8TEcaDWSRS4NtAZglF2QVhFiZLGeDR",
          "width": 640
        }
      }
    },
    "media:uri_template": "https://millsfield.sfomuseum.org/media/152/782/064/7/1527820647_{secret}_{label}.{extention}",
    "sfomuseum:filename": "31850.tif",
    "sfomuseum:image_index": 5,
    "sfomuseum:placetype": "image",
    "sfomuseum:primary_image": 1,
    "wof:depicts": [
      1511930333
    ],
    "wof:name": "airmail flight cover: Pan American Airways, first airmail flight, Sydney - San Francisco route",
    "wof:placetype": "media"
  },
  "geometry": {"coordinates":[-122.386155,37.616358],"type":"Point"}
}
