{
  "type": "Feature",
  "properties": {
    "iso:country": "XX",
    "media:fingerprint": "db0251d37846bc43243694ba68277c6993cd630b",
    "media:imagehash_avg": "a:ff818181808081ff",
    "media:imagehash_diff": "d:1b292703070d0113",
    "media:medium": "image",
    "media:mimetype": "image/tiff",
    "media:properties": {
      "colours": [
        {
          "hex": "#90563d",
          "name": "#90563d",
          "reference": "vibrant"
        },
        {
          "hex": "#653628",
          "name": "#653628",
          "reference": "vibrant"
        },
        {
          "hex": "#878c7c",
          "name": "#878c7c",
          "reference": "vibrant"
        },
        {
          "hex": "#c8ccbf",
          "name": "#c8ccbf",
          "reference": "vibrant"
        },
        {
          "hex": "#583830",
          "name": "#583830",
          "reference": "vibrant"
        }
      ],
      "sizes": {
        "b": {
          "extension": "jpg",
          "height": 768,
          "mimetype": "image/jpeg",
          "secret": "IEH8srDFLAVMNyUP2HALlxibrZlGnpnX",
          "width": 505
        },
        "c": {
          "extension": "jpg",
          "height": 600,
          "mimetype": "image/jpeg",
          "secret": "IEH8srDFLAVMNyUP2HALlxibrZlGnpnX",
          "width": 395
        },
        "dc": {
          "extension": "jpg",
          "height": 600,
          "mimetype": "image/jpeg",
          "secret": "IEH8srDFLAVMNyUP2HALlxibrZlGnpnX",
          "width": 395
        },
        "ds": {
          "extension": "jpg",
          "height": 320,
          "mimetype": "image/jpeg",
          "secret": "IEH8srDFLAVMNyUP2HALlxibrZlGnpnX",
          "width": 320
        },
        "k": {
          "extension": "jpg",
          "height": 1536,
          "mimetype": "image/jpeg",
          "secret": "IEH8srDFLAVMNyUP2HALlxibrZlGnpnX",
          "width": 1011
        },
        "n": {
          "extension": "jpg",
          "height": 240,
          "mimetype": "image/jpeg",
          "secret": "IEH8srDFLAVMNyUP2HALlxibrZlGnpnX",
          "width": 158
        },
        "o": {
          "extension": "jpg",
          "height": 1388,
          "mimetype": "image/jpeg",
          "secret": "uJi5ovBkHGQmZWHTahXnygIKj1rLJhad",
          "width": 914
        },
        "s": {
          "extension": "jpg",
          "height": 320,
          "mimetype": "image/jpeg",
          "secret": "IEH8srDFLAVMNyUP2HALlxibrZlGnpnX",
          "width": 320
        },
        "z": {
          "extension": "jpg",
          "height": 480,
          "mimetype": "image/jpeg",
          "secret": "IEH8srDFLAVMNyUP2HALlxibrZlGnpnX",
          "width": 316
        }
      }
    },
    "media:uri_template": "https://static.sfomuseum.org/media/152/785/416/7/1527854167_{secret}_{label}.{extention}",
    "sfomuseum:filename": "2010.174.019.tif",
    "sfomuseum:image_index": 5,
    "sfomuseum:image_type": "studio",
    "sfomuseum:placetype": "image",
    "sfomuseum:primary_image": 1,
    "wof:depicts": [
      1511942107
    ],
    "wof:name": "logbook: Stanley Henry Page",
    "wof:placetype": "custom",
    "wof:placetype_alt": "image"
  },
  "geometry": {"coordinates":[-122.386155,37.616358],"type":"Point"}
}
