{
  "type": "Feature",
  "properties": {
    "iso:country": "XX",
    "media:fingerprint": "5547e91f8c59782045b1559a911edb8d9ca1409a",
    "media:imagehash_avg": "a:ff818181818181ff",
    "media:imagehash_diff": "d:0b273f472323232f",
    "media:medium": "image",
    "media:mimetype": "image/tiff",
    "media:properties": {
      "colours": [
        {
          "hex": "#b79b68",
          "name": "#b79b68",
          "reference": "vibrant"
        },
        {
          "hex": "#d2bf9a",
          "name": "#d2bf9a",
          "reference": "vibrant"
        },
        {
          "hex": "#1f5873",
          "name": "#1f5873",
          "reference": "vibrant"
        },
        {
          "hex": "#aa9564",
          "name": "#aa9564",
          "reference": "vibrant"
        },
        {
          "hex": "#c7ac7e",
          "name": "#c7ac7e",
          "reference": "vibrant"
        }
      ],
      "sizes": {
        "b": {
          "extension": "jpg",
          "height": 768,
          "mimetype": "image/jpeg",
          "secret": "ZEyXeAzyAbZTAt1xB6tGnP8AVjXzqCVF",
          "width": 460
        },
        "c": {
          "extension": "jpg",
          "height": 600,
          "mimetype": "image/jpeg",
          "secret": "ZEyXeAzyAbZTAt1xB6tGnP8AVjXzqCVF",
          "width": 359
        },
        "dc": {
          "extension": "jpg",
          "height": 600,
          "mimetype": "image/jpeg",
          "secret": "ZEyXeAzyAbZTAt1xB6tGnP8AVjXzqCVF",
          "width": 359
        },
        "ds": {
          "extension": "jpg",
          "height": 320,
          "mimetype": "image/jpeg",
          "secret": "ZEyXeAzyAbZTAt1xB6tGnP8AVjXzqCVF",
          "width": 320
        },
        "k": {
          "extension": "jpg",
          "height": 1536,
          "mimetype": "image/jpeg",
          "secret": "ZEyXeAzyAbZTAt1xB6tGnP8AVjXzqCVF",
          "width": 920
        },
        "n": {
          "extension": "jpg",
          "height": 240,
          "mimetype": "image/jpeg",
          "secret": "ZEyXeAzyAbZTAt1xB6tGnP8AVjXzqCVF",
          "width": 143
        },
        "o": {
          "extension": "jpg",
          "height": 1856,
          "mimetype": "image/jpeg",
          "secret": "ajsinDJaYjnG1qApgp6iclJGFaciG41x",
          "width": 1112
        },
        "s": {
          "extension": "jpg",
          "height": 320,
          "mimetype": "image/jpeg",
          "secret": "ZEyXeAzyAbZTAt1xB6tGnP8AVjXzqCVF",
          "width": 320
        },
        "z": {
          "extension": "jpg",
          "height": 480,
          "mimetype": "image/jpeg",
          "secret": "ZEyXeAzyAbZTAt1xB6tGnP8AVjXzqCVF",
          "width": 287
        }
      }
    },
    "media:uri_template": "https://static.sfomuseum.org/media/152/785/612/9/1527856129_{secret}_{label}.{extention}",
    "sfomuseum:filename": "2012.149.0738_bk.tif",
    "sfomuseum:image_index": 5,
    "sfomuseum:image_type": "studio",
    "sfomuseum:placetype": "image",
    "sfomuseum:primary_image": 0,
    "wof:depicts": [
      1511952665
    ],
    "wof:name": "cruising power calculator: Pratt \u0026 Whitney",
    "wof:placetype": "custom",
    "wof:placetype_alt": "image"
  },
  "geometry": {"coordinates":[-122.386155,37.616358],"type":"Point"}
}
