{
  "type": "Feature",
  "properties": {
    "iso:country": "XX",
    "media:fingerprint": "7cdd0d63c6fca2a08d04ef467e5897659fe631b7",
    "media:imagehash_avg": "a:ff8181838181c387",
    "media:imagehash_diff": "d:2b37273f2f2b1f0f",
    "media:medium": "image",
    "media:mimetype": "image/tiff",
    "media:properties": {
      "colours": [
        {
          "hex": "#1b36bf",
          "name": "#1b36bf",
          "reference": "vibrant"
        }, 
        {
          "hex": "#e8d8c8",
          "name": "#e8d8c8",
          "reference": "vibrant"
        }, 
        {
          "hex": "#1128ba",
          "name": "#1128ba",
          "reference": "vibrant"
        }, 
        {
          "hex": "#5e67ad",
          "name": "#5e67ad",
          "reference": "vibrant"
        }, 
        {
          "hex": "#dcd6c0",
          "name": "#dcd6c0",
          "reference": "vibrant"
        }
      ],
      "sizes": {
        "b": {
          "extension": "jpg",
          "height": 768,
          "mimetype": "image/jpeg",
          "secret": "XBeDKJWnlNRfVPj8nbe68H8CgWMfsyu7",
          "width": 344
        },
        "c": {
          "extension": "jpg",
          "height": 600,
          "mimetype": "image/jpeg",
          "secret": "XBeDKJWnlNRfVPj8nbe68H8CgWMfsyu7",
          "width": 268
        },
        "dc": {
          "extension": "jpg",
          "height": 600,
          "mimetype": "image/jpeg",
          "secret": "XBeDKJWnlNRfVPj8nbe68H8CgWMfsyu7",
          "width": 268
        },
        "ds": {
          "extension": "jpg",
          "height": 320,
          "mimetype": "image/jpeg",
          "secret": "XBeDKJWnlNRfVPj8nbe68H8CgWMfsyu7",
          "width": 320
        },
        "k": {
          "extension": "jpg",
          "height": 1536,
          "mimetype": "image/jpeg",
          "secret": "XBeDKJWnlNRfVPj8nbe68H8CgWMfsyu7",
          "width": 688
        },
        "n": {
          "extension": "jpg",
          "height": 240,
          "mimetype": "image/jpeg",
          "secret": "XBeDKJWnlNRfVPj8nbe68H8CgWMfsyu7",
          "width": 107
        },
        "o": {
          "extension": "jpg",
          "height": 2732,
          "mimetype": "image/jpeg",
          "secret": "0ZJY7CjPqH6Yk1C9KoT4VwgG0eWgv514",
          "width": 1224
        },
        "s": {
          "extension": "jpg",
          "height": 320,
          "mimetype": "image/jpeg",
          "secret": "XBeDKJWnlNRfVPj8nbe68H8CgWMfsyu7",
          "width": 320
        },
        "z": {
          "extension": "jpg",
          "height": 480,
          "mimetype": "image/jpeg",
          "secret": "XBeDKJWnlNRfVPj8nbe68H8CgWMfsyu7",
          "width": 215
        }
      }
    },
    "media:uri_template": "https://millsfield.sfomuseum.org/media/152/781/964/5/1527819645_{secret}_{label}.{extention}",
    "sfomuseum:filename": "31020.tif",
    "sfomuseum:image_index": 5,
    "sfomuseum:placetype": "image",
    "sfomuseum:primary_image": 0,
    "wof:depicts": [
      1511921167
    ],
    "wof:name": "flight information packet: Northwest Orient Airlines",
    "wof:placetype": "media"
  },
  "geometry": {"coordinates":[-122.386155,37.616358],"type":"Point"}
}
