{
  "type": "Feature",
  "properties": {
    "iso:country": "XX",
    "media:fingerprint": "5676167c28d7ec8a0a496f1e9ec2a821d4eb87c4",
    "media:imagehash_avg": "a:fffefcfc3c000000",
    "media:imagehash_diff": "d:c0c0f0e0f03140c0",
    "media:medium": "image",
    "media:mimetype": "image/tiff",
    "media:properties": {
      "colours": [
        {
          "hex": "#868686",
          "name": "#868686",
          "reference": "vibrant"
        }, 
        {
          "hex": "#b8b8b8",
          "name": "#b8b8b8",
          "reference": "vibrant"
        }, 
        {
          "hex": "#484848",
          "name": "#484848",
          "reference": "vibrant"
        }
      ],
      "sizes": {
        "b": {
          "extension": "jpg",
          "height": 768,
          "mimetype": "image/jpeg",
          "secret": "hsagEqOblUegCXyd2FBoNPFMaACj9mjv",
          "width": 975
        },
        "c": {
          "extension": "jpg",
          "height": 600,
          "mimetype": "image/jpeg",
          "secret": "hsagEqOblUegCXyd2FBoNPFMaACj9mjv",
          "width": 762
        },
        "dc": {
          "extension": "jpg",
          "height": 600,
          "mimetype": "image/jpeg",
          "secret": "hsagEqOblUegCXyd2FBoNPFMaACj9mjv",
          "width": 762
        },
        "ds": {
          "extension": "jpg",
          "height": 320,
          "mimetype": "image/jpeg",
          "secret": "hsagEqOblUegCXyd2FBoNPFMaACj9mjv",
          "width": 320
        },
        "k": {
          "extension": "jpg",
          "height": 1536,
          "mimetype": "image/jpeg",
          "secret": "hsagEqOblUegCXyd2FBoNPFMaACj9mjv",
          "width": 1951
        },
        "n": {
          "extension": "jpg",
          "height": 240,
          "mimetype": "image/jpeg",
          "secret": "hsagEqOblUegCXyd2FBoNPFMaACj9mjv",
          "width": 304
        },
        "o": {
          "extension": "jpg",
          "height": 2168,
          "mimetype": "image/jpeg",
          "secret": "Z7Cirhx85BkJlGKM5imvX3d63lZdIKAB",
          "width": 2754
        },
        "s": {
          "extension": "jpg",
          "height": 320,
          "mimetype": "image/jpeg",
          "secret": "hsagEqOblUegCXyd2FBoNPFMaACj9mjv",
          "width": 320
        },
        "z": {
          "extension": "jpg",
          "height": 480,
          "mimetype": "image/jpeg",
          "secret": "hsagEqOblUegCXyd2FBoNPFMaACj9mjv",
          "width": 609
        }
      }
    },
    "media:uri_template": "https://millsfield.sfomuseum.org/media/152/782/666/9/1527826669_{secret}_{label}.{extention}",
    "sfomuseum:filename": "43744.tif",
    "sfomuseum:image_index": 5,
    "sfomuseum:placetype": "image",
    "sfomuseum:primary_image": 1,
    "wof:depicts": [
      1511947709
    ],
    "wof:name": "negative: San Francisco International Airport (SFO), aerial",
    "wof:placetype": "media"
  },
  "geometry": {"coordinates":[-122.386155,37.616358],"type":"Point"}
}
