{
  "type": "Feature",
  "properties": {
    "iso:country": "XX",
    "media:fingerprint": "a8a0414fe11370f39d32894f9330a1e02597b6dc",
    "media:imagehash_avg": "a:fefeffff03000000",
    "media:imagehash_diff": "d:80c8f37e67c3c3c7",
    "media:medium": "image",
    "media:mimetype": "image/tiff",
    "media:properties": {
      "colours": [
        {
          "hex": "#808080",
          "name": "#808080",
          "reference": "vibrant"
        }, 
        {
          "hex": "#b8b8b8",
          "name": "#b8b8b8",
          "reference": "vibrant"
        }, 
        {
          "hex": "#484848",
          "name": "#484848",
          "reference": "vibrant"
        }
      ],
      "sizes": {
        "b": {
          "extension": "jpg",
          "height": 768,
          "mimetype": "image/jpeg",
          "secret": "XvruQyEcIrzRSxYVei286nzGuBOFs2oY",
          "width": 768
        },
        "c": {
          "extension": "jpg",
          "height": 600,
          "mimetype": "image/jpeg",
          "secret": "XvruQyEcIrzRSxYVei286nzGuBOFs2oY",
          "width": 600
        },
        "dc": {
          "extension": "jpg",
          "height": 600,
          "mimetype": "image/jpeg",
          "secret": "XvruQyEcIrzRSxYVei286nzGuBOFs2oY",
          "width": 600
        },
        "ds": {
          "extension": "jpg",
          "height": 320,
          "mimetype": "image/jpeg",
          "secret": "XvruQyEcIrzRSxYVei286nzGuBOFs2oY",
          "width": 320
        },
        "k": {
          "extension": "jpg",
          "height": 1536,
          "mimetype": "image/jpeg",
          "secret": "XvruQyEcIrzRSxYVei286nzGuBOFs2oY",
          "width": 1536
        },
        "n": {
          "extension": "jpg",
          "height": 239,
          "mimetype": "image/jpeg",
          "secret": "XvruQyEcIrzRSxYVei286nzGuBOFs2oY",
          "width": 239
        },
        "o": {
          "extension": "jpg",
          "height": 2563,
          "mimetype": "image/jpeg",
          "secret": "3XBbW4XQbX5ToanhRg9SZDaSg4xaMRFd",
          "width": 2563
        },
        "s": {
          "extension": "jpg",
          "height": 320,
          "mimetype": "image/jpeg",
          "secret": "XvruQyEcIrzRSxYVei286nzGuBOFs2oY",
          "width": 320
        },
        "z": {
          "extension": "jpg",
          "height": 479,
          "mimetype": "image/jpeg",
          "secret": "XvruQyEcIrzRSxYVei286nzGuBOFs2oY",
          "width": 479
        }
      }
    },
    "media:uri_template": "https://millsfield.sfomuseum.org/media/152/782/518/9/1527825189_{secret}_{label}.{extention}",
    "sfomuseum:filename": "43004.tif",
    "sfomuseum:image_index": 5,
    "sfomuseum:placetype": "image",
    "sfomuseum:primary_image": 1,
    "wof:depicts": [
      1511946115
    ],
    "wof:name": "negative: San Francisco International Airport (SFO), United Air Lines, Douglas DC-8-50",
    "wof:placetype": "media"
  },
  "geometry": {"coordinates":[-122.386155,37.616358],"type":"Point"}
}
