{
  "type": "Feature",
  "properties": {
    "iso:country": "US",
    "media:fingerprint": "c754d256d79563165ae413663066ebbf7f1dcb98",
    "media:imagehash_avg": "a:8783818181ffffff",
    "media:imagehash_diff": "d:3f3723333733f1f3",
    "media:medium": "image",
    "media:mimetype": "image/tiff",
    "media:properties": {
      "colours": [
        {
          "hex": "#f530b3",
          "name": "#f530b3",
          "reference": "vibrant"
        }, 
        {
          "hex": "#f8b790",
          "name": "#f8b790",
          "reference": "vibrant"
        }, 
        {
          "hex": "#878175",
          "name": "#878175",
          "reference": "vibrant"
        }, 
        {
          "hex": "#d6b1b4",
          "name": "#d6b1b4",
          "reference": "vibrant"
        }, 
        {
          "hex": "#4b4840",
          "name": "#4b4840",
          "reference": "vibrant"
        }
      ],
      "sizes": {
        "b": {
          "extension": "jpg",
          "height": 768,
          "mimetype": "image/jpeg",
          "secret": "cdIOPxavgvq6qCLvIkHWsVF2fXFWw5kQ",
          "width": 367
        },
        "c": {
          "extension": "jpg",
          "height": 600,
          "mimetype": "image/jpeg",
          "secret": "cdIOPxavgvq6qCLvIkHWsVF2fXFWw5kQ",
          "width": 287
        },
        "dc": {
          "extension": "jpg",
          "height": 600,
          "mimetype": "image/jpeg",
          "secret": "cdIOPxavgvq6qCLvIkHWsVF2fXFWw5kQ",
          "width": 287
        },
        "ds": {
          "extension": "jpg",
          "height": 320,
          "mimetype": "image/jpeg",
          "secret": "cdIOPxavgvq6qCLvIkHWsVF2fXFWw5kQ",
          "width": 320
        },
        "k": {
          "extension": "jpg",
          "height": 1536,
          "mimetype": "image/jpeg",
          "secret": "cdIOPxavgvq6qCLvIkHWsVF2fXFWw5kQ",
          "width": 735
        },
        "n": {
          "extension": "jpg",
          "height": 240,
          "mimetype": "image/jpeg",
          "secret": "cdIOPxavgvq6qCLvIkHWsVF2fXFWw5kQ",
          "width": 114
        },
        "o": {
          "extension": "jpg",
          "height": 683,
          "mimetype": "image/jpeg",
          "secret": "i27FW4QCkjVYoJu9T3Mdq9JcoUjU9JRU",
          "width": 327
        },
        "s": {
          "extension": "jpg",
          "height": 320,
          "mimetype": "image/jpeg",
          "secret": "cdIOPxavgvq6qCLvIkHWsVF2fXFWw5kQ",
          "width": 320
        },
        "z": {
          "extension": "jpg",
          "height": 480,
          "mimetype": "image/jpeg",
          "secret": "cdIOPxavgvq6qCLvIkHWsVF2fXFWw5kQ",
          "width": 229
        }
      }
    },
    "media:uri_template": "https://millsfield.sfomuseum.org/media/152/781/877/3/1527818773_{secret}_{label}.{extention}",
    "sfomuseum:filename": "19270.tif",
    "sfomuseum:image_index": 5,
    "sfomuseum:placetype": "image",
    "sfomuseum:primary_image": 0,
    "wof:depicts": [
      1511909243
    ],
    "wof:name": "timetable: Air West",
    "wof:placetype": "media"
  },
  "geometry": {"coordinates":[-122.386155,37.616358],"type":"Point"}
}
