{
  "type": "Feature",
  "properties": {
    "iso:country": "XX",
    "media:fingerprint": "150462e07c2275ce8d954c6f1d7abc26d269c291",
    "media:imagehash_avg": "a:b9a1c1c9e9e9c1e9",
    "media:imagehash_diff": "d:734b171b5b5b0b0b",
    "media:medium": "image",
    "media:mimetype": "image/tiff",
    "media:properties": {
      "colours": [
        {
          "hex": "#e5d8c0",
          "name": "#e5d8c0",
          "reference": "vibrant"
        },
        {
          "hex": "#584b29",
          "name": "#584b29",
          "reference": "vibrant"
        },
        {
          "hex": "#90846f",
          "name": "#90846f",
          "reference": "vibrant"
        },
        {
          "hex": "#d7d3b6",
          "name": "#d7d3b6",
          "reference": "vibrant"
        },
        {
          "hex": "#523a26",
          "name": "#523a26",
          "reference": "vibrant"
        }
      ],
      "sizes": {
        "b": {
          "extension": "jpg",
          "height": 768,
          "mimetype": "image/jpeg",
          "secret": "jM7if5UkvnW2ZVUdPB4i84cgovQ8JpRw",
          "width": 476
        },
        "c": {
          "extension": "jpg",
          "height": 600,
          "mimetype": "image/jpeg",
          "secret": "jM7if5UkvnW2ZVUdPB4i84cgovQ8JpRw",
          "width": 372
        },
        "dc": {
          "extension": "jpg",
          "height": 600,
          "mimetype": "image/jpeg",
          "secret": "jM7if5UkvnW2ZVUdPB4i84cgovQ8JpRw",
          "width": 372
        },
        "ds": {
          "extension": "jpg",
          "height": 320,
          "mimetype": "image/jpeg",
          "secret": "jM7if5UkvnW2ZVUdPB4i84cgovQ8JpRw",
          "width": 320
        },
        "k": {
          "extension": "jpg",
          "height": 1536,
          "mimetype": "image/jpeg",
          "secret": "jM7if5UkvnW2ZVUdPB4i84cgovQ8JpRw",
          "width": 952
        },
        "n": {
          "extension": "jpg",
          "height": 240,
          "mimetype": "image/jpeg",
          "secret": "jM7if5UkvnW2ZVUdPB4i84cgovQ8JpRw",
          "width": 148
        },
        "o": {
          "extension": "jpg",
          "height": 2400,
          "mimetype": "image/jpeg",
          "secret": "H5Eukmo39lyDlDyvxOmWCACTK3MPTIuP",
          "width": 1488
        },
        "s": {
          "extension": "jpg",
          "height": 320,
          "mimetype": "image/jpeg",
          "secret": "jM7if5UkvnW2ZVUdPB4i84cgovQ8JpRw",
          "width": 320
        },
        "z": {
          "extension": "jpg",
          "height": 480,
          "mimetype": "image/jpeg",
          "secret": "jM7if5UkvnW2ZVUdPB4i84cgovQ8JpRw",
          "width": 297
        }
      }
    },
    "media:uri_template": "https://static.sfomuseum.org/media/152/784/491/3/1527844913_{secret}_{label}.{extention}",
    "sfomuseum:filename": "1997593906_front.tif",
    "sfomuseum:image_index": 5,
    "sfomuseum:placetype": "image",
    "sfomuseum:primary_image": 1,
    "wof:depicts": [
      1159284989,
      1511908247
    ],
    "wof:name": "menu: Pan American World Airways",
    "wof:placetype": "custom",
    "wof:placetype_alt": "image"
  },
  "geometry": {"coordinates":[-122.386155,37.616358],"type":"Point"}
}
