{
  "type": "Feature",
  "properties": {
    "iso:country": "XX",
    "media:fingerprint": "7c7efd4f6873dc324728fd102a1a20ed2d8154e7",
    "media:imagehash_avg": "a:ffffe08080c0fefe",
    "media:imagehash_diff": "d:4c18060f27090c0e",
    "media:medium": "image",
    "media:mimetype": "image/tiff",
    "media:properties": {
      "colours": [
        {
          "hex": "#c61002",
          "name": "#c61002",
          "reference": "vibrant"
        },
        {
          "hex": "#f39859",
          "name": "#f39859",
          "reference": "vibrant"
        },
        {
          "hex": "#610000",
          "name": "#610000",
          "reference": "vibrant"
        },
        {
          "hex": "#946699",
          "name": "#946699",
          "reference": "vibrant"
        },
        {
          "hex": "#a69dc5",
          "name": "#a69dc5",
          "reference": "vibrant"
        }
      ],
      "sizes": {
        "b": {
          "extension": "jpg",
          "height": 768,
          "mimetype": "image/jpeg",
          "secret": "8wKVEVxPO38xE0FusoQVewrFeMcb7gsx",
          "width": 275
        },
        "c": {
          "extension": "jpg",
          "height": 600,
          "mimetype": "image/jpeg",
          "secret": "8wKVEVxPO38xE0FusoQVewrFeMcb7gsx",
          "width": 215
        },
        "dc": {
          "extension": "jpg",
          "height": 600,
          "mimetype": "image/jpeg",
          "secret": "8wKVEVxPO38xE0FusoQVewrFeMcb7gsx",
          "width": 215
        },
        "ds": {
          "extension": "jpg",
          "height": 320,
          "mimetype": "image/jpeg",
          "secret": "8wKVEVxPO38xE0FusoQVewrFeMcb7gsx",
          "width": 320
        },
        "k": {
          "extension": "jpg",
          "height": 1536,
          "mimetype": "image/jpeg",
          "secret": "8wKVEVxPO38xE0FusoQVewrFeMcb7gsx",
          "width": 551
        },
        "n": {
          "extension": "jpg",
          "height": 240,
          "mimetype": "image/jpeg",
          "secret": "8wKVEVxPO38xE0FusoQVewrFeMcb7gsx",
          "width": 86
        },
        "o": {
          "extension": "jpg",
          "height": 3490,
          "mimetype": "image/jpeg",
          "secret": "sQiSFS1bORv4q0VFHNuAu4qet9JZ7pcA",
          "width": 1254
        },
        "s": {
          "extension": "jpg",
          "height": 320,
          "mimetype": "image/jpeg",
          "secret": "8wKVEVxPO38xE0FusoQVewrFeMcb7gsx",
          "width": 320
        },
        "z": {
          "extension": "jpg",
          "height": 480,
          "mimetype": "image/jpeg",
          "secret": "8wKVEVxPO38xE0FusoQVewrFeMcb7gsx",
          "width": 172
        }
      }
    },
    "media:uri_template": "https://static.sfomuseum.org/media/152/784/507/5/1527845075_{secret}_{label}.{extention}",
    "sfomuseum:filename": "69561.tif",
    "sfomuseum:image_index": 5,
    "sfomuseum:image_type": "studio",
    "sfomuseum:placetype": "image",
    "sfomuseum:primary_image": 1,
    "wof:depicts": [
      1159284613,
      1511930641,
      1159287541
    ],
    "wof:name": "wine list: KLM (Royal Dutch Airlines), Business Class",
    "wof:placetype": "custom",
    "wof:placetype_alt": "image"
  },
  "geometry": {"coordinates":[-122.386155,37.616358],"type":"Point"}
}
