{
  "type": "Feature",
  "properties": {
    "iso:country": "XX",
    "media:fingerprint": "2d76fbe75332dfe0e05eb79e2477f41f925a33a5",
    "media:imagehash_avg": "a:ffffffffff830000",
    "media:imagehash_diff": "d:8e171f1f1f5f4b3f",
    "media:medium": "image",
    "media:mimetype": "image/tiff",
    "media:properties": {
      "colours": [
        {
          "hex": "#dd383a",
          "name": "#dd383a",
          "reference": "vibrant"
        }, 
        {
          "hex": "#e88685",
          "name": "#e88685",
          "reference": "vibrant"
        }, 
        {
          "hex": "#80888d",
          "name": "#80888d",
          "reference": "vibrant"
        }, 
        {
          "hex": "#cfbcb3",
          "name": "#cfbcb3",
          "reference": "vibrant"
        }, 
        {
          "hex": "#373843",
          "name": "#373843",
          "reference": "vibrant"
        }
      ],
      "sizes": {
        "b": {
          "extension": "jpg",
          "height": 768,
          "mimetype": "image/jpeg",
          "secret": "GV7QrNlUrSoaiLxLxnYh5weJdgt8M69p",
          "width": 398
        },
        "c": {
          "extension": "jpg",
          "height": 600,
          "mimetype": "image/jpeg",
          "secret": "GV7QrNlUrSoaiLxLxnYh5weJdgt8M69p",
          "width": 311
        },
        "dc": {
          "extension": "jpg",
          "height": 600,
          "mimetype": "image/jpeg",
          "secret": "GV7QrNlUrSoaiLxLxnYh5weJdgt8M69p",
          "width": 311
        },
        "ds": {
          "extension": "jpg",
          "height": 320,
          "mimetype": "image/jpeg",
          "secret": "GV7QrNlUrSoaiLxLxnYh5weJdgt8M69p",
          "width": 320
        },
        "k": {
          "extension": "jpg",
          "height": 1536,
          "mimetype": "image/jpeg",
          "secret": "GV7QrNlUrSoaiLxLxnYh5weJdgt8M69p",
          "width": 796
        },
        "n": {
          "extension": "jpg",
          "height": 240,
          "mimetype": "image/jpeg",
          "secret": "GV7QrNlUrSoaiLxLxnYh5weJdgt8M69p",
          "width": 124
        },
        "o": {
          "extension": "jpg",
          "height": 2880,
          "mimetype": "image/jpeg",
          "secret": "vWKuXHlxmcibxon36odQshMokD9ocGkH",
          "width": 1493
        },
        "s": {
          "extension": "jpg",
          "height": 320,
          "mimetype": "image/jpeg",
          "secret": "GV7QrNlUrSoaiLxLxnYh5weJdgt8M69p",
          "width": 320
        },
        "z": {
          "extension": "jpg",
          "height": 480,
          "mimetype": "image/jpeg",
          "secret": "GV7QrNlUrSoaiLxLxnYh5weJdgt8M69p",
          "width": 248
        }
      }
    },
    "media:uri_template": "https://millsfield.sfomuseum.org/media/152/782/361/3/1527823613_{secret}_{label}.{extention}",
    "sfomuseum:filename": "41685.tif",
    "sfomuseum:image_index": 5,
    "sfomuseum:placetype": "image",
    "sfomuseum:primary_image": 1,
    "wof:depicts": [
      1511908457
    ],
    "wof:name": "airsickness bag: British Airways",
    "wof:placetype": "media"
  },
  "geometry": {"coordinates":[-122.386155,37.616358],"type":"Point"}
}
