{
  "type": "Feature",
  "properties": {
    "iso:country": "XX",
    "media:fingerprint": "9154df10d67b9c3edfd60464b53214fbb479cfc6",
    "media:imagehash_avg": "a:fd980807878387ff",
    "media:imagehash_diff": "d:313179dd3f171d2d",
    "media:medium": "image",
    "media:mimetype": "image/tiff",
    "media:properties": {
      "colours": [
        {
          "hex": "#dfd4a9",
          "name": "#dfd4a9",
          "reference": "vibrant"
        }, 
        {
          "hex": "#652d48",
          "name": "#652d48",
          "reference": "vibrant"
        }, 
        {
          "hex": "#9b8664",
          "name": "#9b8664",
          "reference": "vibrant"
        }, 
        {
          "hex": "#cfc49a",
          "name": "#cfc49a",
          "reference": "vibrant"
        }, 
        {
          "hex": "#564f2e",
          "name": "#564f2e",
          "reference": "vibrant"
        }
      ],
      "sizes": {
        "b": {
          "extension": "jpg",
          "height": 584,
          "mimetype": "image/jpeg",
          "secret": "XbYSYJcFnlMnhYUjzrTp0vnePAq3UtKt",
          "width": 1023
        },
        "c": {
          "extension": "jpg",
          "height": 456,
          "mimetype": "image/jpeg",
          "secret": "XbYSYJcFnlMnhYUjzrTp0vnePAq3UtKt",
          "width": 800
        },
        "dc": {
          "extension": "jpg",
          "height": 456,
          "mimetype": "image/jpeg",
          "secret": "XbYSYJcFnlMnhYUjzrTp0vnePAq3UtKt",
          "width": 800
        },
        "ds": {
          "extension": "jpg",
          "height": 320,
          "mimetype": "image/jpeg",
          "secret": "XbYSYJcFnlMnhYUjzrTp0vnePAq3UtKt",
          "width": 320
        },
        "k": {
          "extension": "jpg",
          "height": 1168,
          "mimetype": "image/jpeg",
          "secret": "XbYSYJcFnlMnhYUjzrTp0vnePAq3UtKt",
          "width": 2047
        },
        "n": {
          "extension": "jpg",
          "height": 182,
          "mimetype": "image/jpeg",
          "secret": "XbYSYJcFnlMnhYUjzrTp0vnePAq3UtKt",
          "width": 320
        },
        "o": {
          "extension": "jpg",
          "height": 1139,
          "mimetype": "image/jpeg",
          "secret": "UugIJOyHlqf5cyHcE0Tr1LMBWU8k1QU4",
          "width": 1996
        },
        "s": {
          "extension": "jpg",
          "height": 320,
          "mimetype": "image/jpeg",
          "secret": "XbYSYJcFnlMnhYUjzrTp0vnePAq3UtKt",
          "width": 320
        },
        "z": {
          "extension": "jpg",
          "height": 365,
          "mimetype": "image/jpeg",
          "secret": "XbYSYJcFnlMnhYUjzrTp0vnePAq3UtKt",
          "width": 640
        }
      }
    },
    "media:uri_template": "https://millsfield.sfomuseum.org/media/152/782/043/1/1527820431_{secret}_{label}.{extention}",
    "sfomuseum:filename": "31606.tif",
    "sfomuseum:image_index": 5,
    "sfomuseum:placetype": "image",
    "sfomuseum:primary_image": 1,
    "wof:depicts": [
      1511920301
    ],
    "wof:name": "airmail flight cover: Pan American Airways, Alameda Chamber of Commerce \r",
    "wof:placetype": "media"
  },
  "geometry": {"coordinates":[-122.386155,37.616358],"type":"Point"}
}
