{
  "type": "Feature",
  "properties": {
    "date:cessation_lower": "1940-01-01",
    "date:cessation_upper": "1949-12-31",
    "date:inception_lower": "1940-01-01",
    "date:inception_upper": "1949-12-31",
    "iso:country": "XX",
    "sfomuseum:filename": "115610.tif",
    "sfomuseum:image_index": 5,
    "sfomuseum:image_type": "studio",
    "sfomuseum:placetype": "image",
    "sfomuseum:primary_image": 1,
    "wof:depicts": [
      1511919449,
      1159285415,
      1159288779
    ],
    "wof:name": "sewing kit: United Air Lines",
    "wof:placetype": "custom"
  },
  "geometry": {"coordinates":[-122.386155,37.616357],"type":"Point"}
}
