{
  "type": "Feature",
  "properties": {
    "iso:country": "XX",
    "media:fingerprint": "a06b1149882b5171380a52e8671148c6c71a60c4",
    "media:imagehash_avg": "a:ff858d81818181ff",
    "media:imagehash_diff": "d:6d69797373677171",
    "media:medium": "image",
    "media:mimetype": "image/tiff",
    "media:properties": {
      "colours": [
        {
          "hex": "#6c073c",
          "name": "#6c073c",
          "reference": "vibrant"
        },
        {
          "hex": "#817874",
          "name": "#817874",
          "reference": "vibrant"
        },
        {
          "hex": "#c9c8c1",
          "name": "#c9c8c1",
          "reference": "vibrant"
        },
        {
          "hex": "#363357",
          "name": "#363357",
          "reference": "vibrant"
        }
      ],
      "sizes": {
        "b": {
          "extension": "jpg",
          "height": 768,
          "mimetype": "image/jpeg",
          "secret": "XGPx4ofwTuXKeAkhzlTfHfEyFLCfbJTt",
          "width": 419
        },
        "c": {
          "extension": "jpg",
          "height": 600,
          "mimetype": "image/jpeg",
          "secret": "XGPx4ofwTuXKeAkhzlTfHfEyFLCfbJTt",
          "width": 327
        },
        "dc": {
          "extension": "jpg",
          "height": 600,
          "mimetype": "image/jpeg",
          "secret": "XGPx4ofwTuXKeAkhzlTfHfEyFLCfbJTt",
          "width": 327
        },
        "ds": {
          "extension": "jpg",
          "height": 320,
          "mimetype": "image/jpeg",
          "secret": "XGPx4ofwTuXKeAkhzlTfHfEyFLCfbJTt",
          "width": 320
        },
        "k": {
          "extension": "jpg",
          "height": 1536,
          "mimetype": "image/jpeg",
          "secret": "XGPx4ofwTuXKeAkhzlTfHfEyFLCfbJTt",
          "width": 838
        },
        "n": {
          "extension": "jpg",
          "height": 240,
          "mimetype": "image/jpeg",
          "secret": "XGPx4ofwTuXKeAkhzlTfHfEyFLCfbJTt",
          "width": 131
        },
        "o": {
          "extension": "jpg",
          "height": 3365,
          "mimetype": "image/jpeg",
          "secret": "cljoXCzZklGxUzFzg4Zry6gcEWsOrRAt",
          "width": 1837
        },
        "s": {
          "extension": "jpg",
          "height": 320,
          "mimetype": "image/jpeg",
          "secret": "XGPx4ofwTuXKeAkhzlTfHfEyFLCfbJTt",
          "width": 320
        },
        "z": {
          "extension": "jpg",
          "height": 480,
          "mimetype": "image/jpeg",
          "secret": "XGPx4ofwTuXKeAkhzlTfHfEyFLCfbJTt",
          "width": 262
        }
      }
    },
    "media:uri_template": "https://static.sfomuseum.org/media/152/785/026/7/1527850267_{secret}_{label}.{extention}",
    "sfomuseum:filename": "80625.tif",
    "sfomuseum:image_index": 5,
    "sfomuseum:image_type": "studio",
    "sfomuseum:placetype": "image",
    "sfomuseum:primary_image": 1,
    "wof:depicts": [
      1511930585,
      1159285291
    ],
    "wof:name": "menu: Thai Airways International, Royal Silk (Business) Class",
    "wof:placetype": "custom",
    "wof:placetype_alt": "image"
  },
  "geometry": {"coordinates":[-122.386155,37.616358],"type":"Point"}
}
