{
  "type": "Feature",
  "properties": {
    "iso:country": "XX",
    "media:fingerprint": "c85c14727bca51417ab8c5af9bb6fb3d6ebd0ad8",
    "media:imagehash_avg": "a:ffe0c0ed0d01111f",
    "media:imagehash_diff": "d:884c0d59595d77fd",
    "media:medium": "image",
    "media:mimetype": "image/tiff",
    "media:properties": {
      "colours": [
        {
          "hex": "#f2772e",
          "name": "#f2772e",
          "reference": "vibrant"
        }, 
        {
          "hex": "#f3b97a",
          "name": "#f3b97a",
          "reference": "vibrant"
        }, 
        {
          "hex": "#21316d",
          "name": "#21316d",
          "reference": "vibrant"
        }, 
        {
          "hex": "#5b80ae",
          "name": "#5b80ae",
          "reference": "vibrant"
        }, 
        {
          "hex": "#d1c4aa",
          "name": "#d1c4aa",
          "reference": "vibrant"
        }
      ],
      "sizes": {
        "b": {
          "extension": "jpg",
          "height": 552,
          "mimetype": "image/jpeg",
          "secret": "qcqOgBu5Yp1SZfoMqJpcRGKmYKQDread",
          "width": 1024
        },
        "c": {
          "extension": "jpg",
          "height": 431,
          "mimetype": "image/jpeg",
          "secret": "qcqOgBu5Yp1SZfoMqJpcRGKmYKQDread",
          "width": 800
        },
        "dc": {
          "extension": "jpg",
          "height": 431,
          "mimetype": "image/jpeg",
          "secret": "qcqOgBu5Yp1SZfoMqJpcRGKmYKQDread",
          "width": 800
        },
        "ds": {
          "extension": "jpg",
          "height": 320,
          "mimetype": "image/jpeg",
          "secret": "qcqOgBu5Yp1SZfoMqJpcRGKmYKQDread",
          "width": 320
        },
        "k": {
          "extension": "jpg",
          "height": 1104,
          "mimetype": "image/jpeg",
          "secret": "qcqOgBu5Yp1SZfoMqJpcRGKmYKQDread",
          "width": 2048
        },
        "n": {
          "extension": "jpg",
          "height": 172,
          "mimetype": "image/jpeg",
          "secret": "qcqOgBu5Yp1SZfoMqJpcRGKmYKQDread",
          "width": 320
        },
        "o": {
          "extension": "jpg",
          "height": 1270,
          "mimetype": "image/jpeg",
          "secret": "OBLP1a8rE9tpnd3uV2vmhxmlIj84nSuN",
          "width": 2355
        },
        "s": {
          "extension": "jpg",
          "height": 320,
          "mimetype": "image/jpeg",
          "secret": "qcqOgBu5Yp1SZfoMqJpcRGKmYKQDread",
          "width": 320
        },
        "z": {
          "extension": "jpg",
          "height": 345,
          "mimetype": "image/jpeg",
          "secret": "qcqOgBu5Yp1SZfoMqJpcRGKmYKQDread",
          "width": 640
        }
      }
    },
    "media:uri_template": "https://millsfield.sfomuseum.org/media/152/782/916/3/1527829163_{secret}_{label}.{extention}",
    "sfomuseum:filename": "47545.tif",
    "sfomuseum:image_index": 5,
    "sfomuseum:placetype": "image",
    "sfomuseum:primary_image": 1,
    "wof:depicts": [
      1511907415
    ],
    "wof:name": "airmail flight cover: Pan American Airways, Honolulu - Wake Island - New York route",
    "wof:placetype": "media"
  },
  "geometry": {"coordinates":[-122.386155,37.616358],"type":"Point"}
}
