{
  "type": "Feature",
  "properties": {
    "iso:country": "XX",
    "media:fingerprint": "033feac2bbdfd3d08469fdcdd70bcbef6a159bec",
    "media:imagehash_avg": "a:3ffdf9c98dc9c9ff",
    "media:imagehash_diff": "d:e9f151191911134c",
    "media:medium": "image",
    "media:mimetype": "image/tiff",
    "media:properties": {
      "colours": [
        {
          "hex": "#f8edd8",
          "name": "#f8edd8",
          "reference": "vibrant"
        },
        {
          "hex": "#4c4523",
          "name": "#4c4523",
          "reference": "vibrant"
        },
        {
          "hex": "#827f6a",
          "name": "#827f6a",
          "reference": "vibrant"
        },
        {
          "hex": "#c9c7b3",
          "name": "#c9c7b3",
          "reference": "vibrant"
        },
        {
          "hex": "#4e4c3d",
          "name": "#4e4c3d",
          "reference": "vibrant"
        }
      ],
      "sizes": {
        "b": {
          "extension": "jpg",
          "height": 349,
          "mimetype": "image/jpeg",
          "secret": "Xh90kRL0jBJHRADUwTc6Z0erUK3fSUgw",
          "width": 1024
        },
        "c": {
          "extension": "jpg",
          "height": 273,
          "mimetype": "image/jpeg",
          "secret": "Xh90kRL0jBJHRADUwTc6Z0erUK3fSUgw",
          "width": 800
        },
        "dc": {
          "extension": "jpg",
          "height": 273,
          "mimetype": "image/jpeg",
          "secret": "Xh90kRL0jBJHRADUwTc6Z0erUK3fSUgw",
          "width": 800
        },
        "ds": {
          "extension": "jpg",
          "height": 320,
          "mimetype": "image/jpeg",
          "secret": "Xh90kRL0jBJHRADUwTc6Z0erUK3fSUgw",
          "width": 320
        },
        "k": {
          "extension": "jpg",
          "height": 699,
          "mimetype": "image/jpeg",
          "secret": "Xh90kRL0jBJHRADUwTc6Z0erUK3fSUgw",
          "width": 2048
        },
        "n": {
          "extension": "jpg",
          "height": 109,
          "mimetype": "image/jpeg",
          "secret": "Xh90kRL0jBJHRADUwTc6Z0erUK3fSUgw",
          "width": 320
        },
        "o": {
          "extension": "jpg",
          "height": 1140,
          "mimetype": "image/jpeg",
          "secret": "HUYkuFlPRdq5Zi9tpBj4NGhUOHkTloQw",
          "width": 3337
        },
        "s": {
          "extension": "jpg",
          "height": 320,
          "mimetype": "image/jpeg",
          "secret": "Xh90kRL0jBJHRADUwTc6Z0erUK3fSUgw",
          "width": 320
        },
        "z": {
          "extension": "jpg",
          "height": 218,
          "mimetype": "image/jpeg",
          "secret": "Xh90kRL0jBJHRADUwTc6Z0erUK3fSUgw",
          "width": 640
        }
      }
    },
    "media:uri_template": "https://static.sfomuseum.org/media/152/784/553/9/1527845539_{secret}_{label}.{extention}",
    "sfomuseum:filename": "2001039148_inside.tif",
    "sfomuseum:image_index": 5,
    "sfomuseum:image_type": "studio",
    "sfomuseum:placetype": "image",
    "sfomuseum:primary_image": 0,
    "wof:depicts": [
      1159285415,
      1511921135
    ],
    "wof:name": "menu: United Air Lines",
    "wof:placetype": "custom",
    "wof:placetype_alt": "image"
  },
  "geometry": {"coordinates":[-122.386155,37.616358],"type":"Point"}
}
