{
  "type": "Feature",
  "properties": {
    "iso:country": "XX",
    "media:fingerprint": "d45441c6b5c0c86e593cd97ebf9fffb4ae682744",
    "media:imagehash_avg": "a:00f8fcfcecf83cff",
    "media:imagehash_diff": "d:6a70b1b189a9717b",
    "media:medium": "image",
    "media:mimetype": "image/tiff",
    "media:properties": {
      "colours": [
        {
          "hex": "#da3425",
          "name": "#da3425",
          "reference": "vibrant"
        }, 
        {
          "hex": "#f3aea0",
          "name": "#f3aea0",
          "reference": "vibrant"
        }, 
        {
          "hex": "#773224",
          "name": "#773224",
          "reference": "vibrant"
        }, 
        {
          "hex": "#6274a5",
          "name": "#6274a5",
          "reference": "vibrant"
        }, 
        {
          "hex": "#c6ad94",
          "name": "#c6ad94",
          "reference": "vibrant"
        }
      ],
      "sizes": {
        "b": {
          "extension": "jpg",
          "height": 460,
          "mimetype": "image/jpeg",
          "secret": "aivtOiPCtJSXBik3F24kRkeA7qDX4iNt",
          "width": 1024
        },
        "c": {
          "extension": "jpg",
          "height": 359,
          "mimetype": "image/jpeg",
          "secret": "aivtOiPCtJSXBik3F24kRkeA7qDX4iNt",
          "width": 800
        },
        "dc": {
          "extension": "jpg",
          "height": 359,
          "mimetype": "image/jpeg",
          "secret": "aivtOiPCtJSXBik3F24kRkeA7qDX4iNt",
          "width": 800
        },
        "ds": {
          "extension": "jpg",
          "height": 320,
          "mimetype": "image/jpeg",
          "secret": "aivtOiPCtJSXBik3F24kRkeA7qDX4iNt",
          "width": 320
        },
        "k": {
          "extension": "jpg",
          "height": 921,
          "mimetype": "image/jpeg",
          "secret": "aivtOiPCtJSXBik3F24kRkeA7qDX4iNt",
          "width": 2048
        },
        "n": {
          "extension": "jpg",
          "height": 143,
          "mimetype": "image/jpeg",
          "secret": "aivtOiPCtJSXBik3F24kRkeA7qDX4iNt",
          "width": 320
        },
        "o": {
          "extension": "jpg",
          "height": 1325,
          "mimetype": "image/jpeg",
          "secret": "ETA3xOgO7hEKEWxbFDfgxQdIdnk8Tcnm",
          "width": 2946
        },
        "s": {
          "extension": "jpg",
          "height": 320,
          "mimetype": "image/jpeg",
          "secret": "aivtOiPCtJSXBik3F24kRkeA7qDX4iNt",
          "width": 320
        },
        "z": {
          "extension": "jpg",
          "height": 287,
          "mimetype": "image/jpeg",
          "secret": "aivtOiPCtJSXBik3F24kRkeA7qDX4iNt",
          "width": 640
        }
      }
    },
    "media:uri_template": "https://millsfield.sfomuseum.org/media/152/782/903/3/1527829033_{secret}_{label}.{extention}",
    "sfomuseum:filename": "47487.tif",
    "sfomuseum:image_index": 5,
    "sfomuseum:placetype": "image",
    "sfomuseum:primary_image": 1,
    "wof:depicts": [
      1511906923
    ],
    "wof:name": "airmail flight cover: Pan American Airways, Singapore - San Francisco route",
    "wof:placetype": "media"
  },
  "geometry": {"coordinates":[-122.386155,37.616358],"type":"Point"}
}
