{
  "type": "Feature",
  "properties": {
    "iso:country": "XX",
    "media:fingerprint": "4dd005fafa02c39586fc629b68b24f125246a6ff",
    "media:imagehash_avg": "a:000046ccc0c080d0",
    "media:imagehash_diff": "d:c08a9c1c32102120",
    "media:medium": "image",
    "media:mimetype": "image/tiff",
    "media:properties": {
      "colours": [
        {
          "hex": "#868686",
          "name": "#868686",
          "reference": "vibrant"
        }, 
        {
          "hex": "#c0c0c0",
          "name": "#c0c0c0",
          "reference": "vibrant"
        }, 
        {
          "hex": "#404040",
          "name": "#404040",
          "reference": "vibrant"
        }
      ],
      "sizes": {
        "b": {
          "extension": "jpg",
          "height": 768,
          "mimetype": "image/jpeg",
          "secret": "8YOeyiwyu0xiSkPw5JnOLPpt7SRBSkQJ",
          "width": 970
        },
        "c": {
          "extension": "jpg",
          "height": 600,
          "mimetype": "image/jpeg",
          "secret": "8YOeyiwyu0xiSkPw5JnOLPpt7SRBSkQJ",
          "width": 758
        },
        "dc": {
          "extension": "jpg",
          "height": 600,
          "mimetype": "image/jpeg",
          "secret": "8YOeyiwyu0xiSkPw5JnOLPpt7SRBSkQJ",
          "width": 758
        },
        "ds": {
          "extension": "jpg",
          "height": 320,
          "mimetype": "image/jpeg",
          "secret": "8YOeyiwyu0xiSkPw5JnOLPpt7SRBSkQJ",
          "width": 320
        },
        "k": {
          "extension": "jpg",
          "height": 1536,
          "mimetype": "image/jpeg",
          "secret": "8YOeyiwyu0xiSkPw5JnOLPpt7SRBSkQJ",
          "width": 1941
        },
        "n": {
          "extension": "jpg",
          "height": 240,
          "mimetype": "image/jpeg",
          "secret": "8YOeyiwyu0xiSkPw5JnOLPpt7SRBSkQJ",
          "width": 303
        },
        "o": {
          "extension": "jpg",
          "height": 2168,
          "mimetype": "image/jpeg",
          "secret": "NkbGzw5BwkgzhV2VOcHIaFcNfRJvJeNr",
          "width": 2740
        },
        "s": {
          "extension": "jpg",
          "height": 320,
          "mimetype": "image/jpeg",
          "secret": "8YOeyiwyu0xiSkPw5JnOLPpt7SRBSkQJ",
          "width": 320
        },
        "z": {
          "extension": "jpg",
          "height": 480,
          "mimetype": "image/jpeg",
          "secret": "8YOeyiwyu0xiSkPw5JnOLPpt7SRBSkQJ",
          "width": 606
        }
      }
    },
    "media:uri_template": "https://millsfield.sfomuseum.org/media/152/782/425/5/1527824255_{secret}_{label}.{extention}",
    "sfomuseum:filename": "42338.tif",
    "sfomuseum:image_index": 5,
    "sfomuseum:placetype": "image",
    "sfomuseum:primary_image": 1,
    "wof:depicts": [
      1511945579
    ],
    "wof:name": "negative: San Francisco International Airport (SFO), South Terminal dedication",
    "wof:placetype": "media"
  },
  "geometry": {"coordinates":[-122.386155,37.616358],"type":"Point"}
}
