{
  "type": "Feature",
  "properties": {
    "iso:country":"US",
    "media:medium":"image",
    "sfomuseum:filename":"2008.056.0915.tif",
    "sfomuseum:image_index":5,
    "sfomuseum:placetype":"image",
    "sfomuseum:primary_image":1,
    "wof:depicts":[
        1511931293
    ],
    "wof:name":"stationery: SCADTA (Sociedad Colombo-Alemana de Transpoertes Aereos)",
    "wof:placetype":"media"
},
  "geometry": {"coordinates":[-122.386155,37.616358],"type":"Point"}
}