{
  "type": "Feature",
  "properties": {
    "iso:country": "XX",
    "media:fingerprint": "855ffe8a1560099f9521c9e9902d2ba464cf046f",
    "media:imagehash_avg": "a:fb20e0f9f3e7f7ff",
    "media:imagehash_diff": "d:6345416347454525",
    "media:medium": "image",
    "media:mimetype": "image/tiff",
    "media:properties": {
      "colours": [
        {
          "hex": "#343d96",
          "name": "#343d96",
          "reference": "vibrant"
        }, 
        {
          "hex": "#e8d8ad",
          "name": "#e8d8ad",
          "reference": "vibrant"
        }, 
        {
          "hex": "#111f7d",
          "name": "#111f7d",
          "reference": "vibrant"
        }, 
        {
          "hex": "#985f76",
          "name": "#985f76",
          "reference": "vibrant"
        }, 
        {
          "hex": "#cdb899",
          "name": "#cdb899",
          "reference": "vibrant"
        }
      ],
      "sizes": {
        "b": {
          "extension": "jpg",
          "height": 536,
          "mimetype": "image/jpeg",
          "secret": "8DStytV2EZh3ZdhwhV4qwxGdbBc6kxq2",
          "width": 1024
        },
        "c": {
          "extension": "jpg",
          "height": 418,
          "mimetype": "image/jpeg",
          "secret": "8DStytV2EZh3ZdhwhV4qwxGdbBc6kxq2",
          "width": 800
        },
        "dc": {
          "extension": "jpg",
          "height": 418,
          "mimetype": "image/jpeg",
          "secret": "8DStytV2EZh3ZdhwhV4qwxGdbBc6kxq2",
          "width": 800
        },
        "ds": {
          "extension": "jpg",
          "height": 320,
          "mimetype": "image/jpeg",
          "secret": "8DStytV2EZh3ZdhwhV4qwxGdbBc6kxq2",
          "width": 320
        },
        "k": {
          "extension": "jpg",
          "height": 1072,
          "mimetype": "image/jpeg",
          "secret": "8DStytV2EZh3ZdhwhV4qwxGdbBc6kxq2",
          "width": 2048
        },
        "n": {
          "extension": "jpg",
          "height": 167,
          "mimetype": "image/jpeg",
          "secret": "8DStytV2EZh3ZdhwhV4qwxGdbBc6kxq2",
          "width": 320
        },
        "o": {
          "extension": "jpg",
          "height": 1196,
          "mimetype": "image/jpeg",
          "secret": "wFuiOFkovJof9DclG3HGAIuVg5nfvHsY",
          "width": 2284
        },
        "s": {
          "extension": "jpg",
          "height": 320,
          "mimetype": "image/jpeg",
          "secret": "8DStytV2EZh3ZdhwhV4qwxGdbBc6kxq2",
          "width": 320
        },
        "z": {
          "extension": "jpg",
          "height": 335,
          "mimetype": "image/jpeg",
          "secret": "8DStytV2EZh3ZdhwhV4qwxGdbBc6kxq2",
          "width": 640
        }
      }
    },
    "media:uri_template": "https://millsfield.sfomuseum.org/media/152/782/064/5/1527820645_{secret}_{label}.{extention}",
    "sfomuseum:filename": "31848.tif",
    "sfomuseum:image_index": 5,
    "sfomuseum:placetype": "image",
    "sfomuseum:primary_image": 0,
    "wof:depicts": [
      1511930329
    ],
    "wof:name": "airmail flight cover: Pan American Airways, first Pacific survey flight, San Francisco - Hawaii route",
    "wof:placetype": "media"
  },
  "geometry": {"coordinates":[-122.386155,37.616358],"type":"Point"}
}
