{
  "type": "Feature",
  "properties": {
    "iso:country": "XX",
    "media:fingerprint": "b40fa40a5a73dc82740a997e827bdfe5d6363a7b",
    "media:imagehash_avg": "a:d0b8b820a6a4bcff",
    "media:imagehash_diff": "d:206042484c4c647e",
    "media:medium": "image",
    "media:mimetype": "image/tiff",
    "media:properties": {
      "colours": [
        {
          "hex": "#ca4b33",
          "name": "#ca4b33",
          "reference": "vibrant"
        }, 
        {
          "hex": "#c77e73",
          "name": "#c77e73",
          "reference": "vibrant"
        }, 
        {
          "hex": "#952814",
          "name": "#952814",
          "reference": "vibrant"
        }, 
        {
          "hex": "#788198",
          "name": "#788198",
          "reference": "vibrant"
        }, 
        {
          "hex": "#c2bfb7",
          "name": "#c2bfb7",
          "reference": "vibrant"
        }
      ],
      "sizes": {
        "b": {
          "extension": "jpg",
          "height": 460,
          "mimetype": "image/jpeg",
          "secret": "o7v9hdp0uDq8BI8hwnrILB1NidpUjwvV",
          "width": 1024
        },
        "c": {
          "extension": "jpg",
          "height": 359,
          "mimetype": "image/jpeg",
          "secret": "o7v9hdp0uDq8BI8hwnrILB1NidpUjwvV",
          "width": 800
        },
        "dc": {
          "extension": "jpg",
          "height": 359,
          "mimetype": "image/jpeg",
          "secret": "o7v9hdp0uDq8BI8hwnrILB1NidpUjwvV",
          "width": 800
        },
        "ds": {
          "extension": "jpg",
          "height": 320,
          "mimetype": "image/jpeg",
          "secret": "o7v9hdp0uDq8BI8hwnrILB1NidpUjwvV",
          "width": 320
        },
        "k": {
          "extension": "jpg",
          "height": 921,
          "mimetype": "image/jpeg",
          "secret": "o7v9hdp0uDq8BI8hwnrILB1NidpUjwvV",
          "width": 2048
        },
        "n": {
          "extension": "jpg",
          "height": 143,
          "mimetype": "image/jpeg",
          "secret": "o7v9hdp0uDq8BI8hwnrILB1NidpUjwvV",
          "width": 320
        },
        "o": {
          "extension": "jpg",
          "height": 1325,
          "mimetype": "image/jpeg",
          "secret": "c9wZnM8TAEx3cmsWJ6pr7wjkTqcWKb4c",
          "width": 2946
        },
        "s": {
          "extension": "jpg",
          "height": 320,
          "mimetype": "image/jpeg",
          "secret": "o7v9hdp0uDq8BI8hwnrILB1NidpUjwvV",
          "width": 320
        },
        "z": {
          "extension": "jpg",
          "height": 287,
          "mimetype": "image/jpeg",
          "secret": "o7v9hdp0uDq8BI8hwnrILB1NidpUjwvV",
          "width": 640
        }
      }
    },
    "media:uri_template": "https://millsfield.sfomuseum.org/media/152/782/918/3/1527829183_{secret}_{label}.{extention}",
    "sfomuseum:filename": "47554.tif",
    "sfomuseum:image_index": 5,
    "sfomuseum:placetype": "image",
    "sfomuseum:primary_image": 1,
    "wof:depicts": [
      1511907429
    ],
    "wof:name": "airmail flight cover: Pan American Airways, Guam - Singapore route",
    "wof:placetype": "media"
  },
  "geometry": {"coordinates":[-122.386155,37.616358],"type":"Point"}
}
