{
  "type": "Feature",
  "properties": {
    "iso:country": "XX",
    "media:fingerprint": "23714d34e47c4b728502eef23076a9e2f8367b4b",
    "media:imagehash_avg": "a:f0f0f0f0f0f0f0f0",
    "media:imagehash_diff": "d:2765616161612127",
    "media:medium": "image",
    "media:mimetype": "image/tiff",
    "media:properties": {
      "colours": [
        {
          "hex": "#e73a2a",
          "name": "#e73a2a",
          "reference": "vibrant"
        }, 
        {
          "hex": "#e75544",
          "name": "#e75544",
          "reference": "vibrant"
        }, 
        {
          "hex": "#05267e",
          "name": "#05267e",
          "reference": "vibrant"
        }, 
        {
          "hex": "#8e8c7b",
          "name": "#8e8c7b",
          "reference": "vibrant"
        }, 
        {
          "hex": "#d6d1b6",
          "name": "#d6d1b6",
          "reference": "vibrant"
        }
      ],
      "sizes": {
        "b": {
          "extension": "jpg",
          "height": 768,
          "mimetype": "image/jpeg",
          "secret": "g2M1H1b5WHtfmGMKRciAyxwoKpwL14tT",
          "width": 1002
        },
        "c": {
          "extension": "jpg",
          "height": 600,
          "mimetype": "image/jpeg",
          "secret": "g2M1H1b5WHtfmGMKRciAyxwoKpwL14tT",
          "width": 782
        },
        "dc": {
          "extension": "jpg",
          "height": 600,
          "mimetype": "image/jpeg",
          "secret": "g2M1H1b5WHtfmGMKRciAyxwoKpwL14tT",
          "width": 782
        },
        "ds": {
          "extension": "jpg",
          "height": 320,
          "mimetype": "image/jpeg",
          "secret": "g2M1H1b5WHtfmGMKRciAyxwoKpwL14tT",
          "width": 320
        },
        "k": {
          "extension": "jpg",
          "height": 1536,
          "mimetype": "image/jpeg",
          "secret": "g2M1H1b5WHtfmGMKRciAyxwoKpwL14tT",
          "width": 2004
        },
        "n": {
          "extension": "jpg",
          "height": 240,
          "mimetype": "image/jpeg",
          "secret": "g2M1H1b5WHtfmGMKRciAyxwoKpwL14tT",
          "width": 313
        },
        "o": {
          "extension": "jpg",
          "height": 1155,
          "mimetype": "image/jpeg",
          "secret": "AnLWdckpy7vJ9VuQeQhgat8T0aFPuwIy",
          "width": 1507
        },
        "s": {
          "extension": "jpg",
          "height": 320,
          "mimetype": "image/jpeg",
          "secret": "g2M1H1b5WHtfmGMKRciAyxwoKpwL14tT",
          "width": 320
        },
        "z": {
          "extension": "jpg",
          "height": 480,
          "mimetype": "image/jpeg",
          "secret": "g2M1H1b5WHtfmGMKRciAyxwoKpwL14tT",
          "width": 626
        }
      }
    },
    "media:uri_template": "https://millsfield.sfomuseum.org/media/152/781/965/5/1527819655_{secret}_{label}.{extention}",
    "sfomuseum:filename": "31025.tif",
    "sfomuseum:image_index": 5,
    "sfomuseum:placetype": "image",
    "sfomuseum:primary_image": 0,
    "wof:depicts": [
      1511920181
    ],
    "wof:name": "flight information packet: Transcontinental \u0026 Western Air (TWA), Douglas DC-3",
    "wof:placetype": "media"
  },
  "geometry": {"coordinates":[-122.386155,37.616358],"type":"Point"}
}
