{
  "type": "Feature",
  "properties": {
    "iso:country": "XX",
    "media:fingerprint": "21e859720d02743c6af7f7edb9f91a88e9e540cc",
    "media:imagehash_avg": "a:7f3e103018243633",
    "media:imagehash_diff": "d:e0e4e0e0f0d5e4e6",
    "media:medium": "image",
    "media:mimetype": "image/tiff",
    "media:properties": {
      "colours": [
        {
          "hex": "#737990",
          "name": "#737990",
          "reference": "vibrant"
        },
        {
          "hex": "#9daace",
          "name": "#9daace",
          "reference": "vibrant"
        },
        {
          "hex": "#493e2e",
          "name": "#493e2e",
          "reference": "vibrant"
        }
      ],
      "sizes": {
        "b": {
          "extension": "jpg",
          "height": 675,
          "mimetype": "image/jpeg",
          "secret": "Rb6ZEc1lN42KZAtjiei3pXcU1nZs4lHe",
          "width": 1024
        },
        "c": {
          "extension": "jpg",
          "height": 527,
          "mimetype": "image/jpeg",
          "secret": "Rb6ZEc1lN42KZAtjiei3pXcU1nZs4lHe",
          "width": 800
        },
        "dc": {
          "extension": "jpg",
          "height": 527,
          "mimetype": "image/jpeg",
          "secret": "Rb6ZEc1lN42KZAtjiei3pXcU1nZs4lHe",
          "width": 800
        },
        "ds": {
          "extension": "jpg",
          "height": 320,
          "mimetype": "image/jpeg",
          "secret": "Rb6ZEc1lN42KZAtjiei3pXcU1nZs4lHe",
          "width": 320
        },
        "k": {
          "extension": "jpg",
          "height": 1350,
          "mimetype": "image/jpeg",
          "secret": "Rb6ZEc1lN42KZAtjiei3pXcU1nZs4lHe",
          "width": 2048
        },
        "n": {
          "extension": "jpg",
          "height": 210,
          "mimetype": "image/jpeg",
          "secret": "Rb6ZEc1lN42KZAtjiei3pXcU1nZs4lHe",
          "width": 320
        },
        "o": {
          "extension": "jpg",
          "height": 1058,
          "mimetype": "image/jpeg",
          "secret": "xLX40r4Six8V9CMtcwQOxqgMgAd5HZLb",
          "width": 1605
        },
        "s": {
          "extension": "jpg",
          "height": 320,
          "mimetype": "image/jpeg",
          "secret": "Rb6ZEc1lN42KZAtjiei3pXcU1nZs4lHe",
          "width": 320
        },
        "z": {
          "extension": "jpg",
          "height": 421,
          "mimetype": "image/jpeg",
          "secret": "Rb6ZEc1lN42KZAtjiei3pXcU1nZs4lHe",
          "width": 640
        }
      }
    },
    "media:uri_template": "https://static.sfomuseum.org/media/152/782/834/3/1527828343_{secret}_{label}.{extention}",
    "sfomuseum:filename": "44550.tif",
    "sfomuseum:image_index": 5,
    "sfomuseum:image_type": "studio",
    "sfomuseum:placetype": "image",
    "sfomuseum:primary_image": 1,
    "wof:depicts": [
      1511949377,
      102527513
    ],
    "wof:name": "negative: San Francisco International Airport (SFO)",
    "wof:placetype": "custom",
    "wof:placetype_alt": "image"
  },
  "geometry": {"coordinates":[-122.386155,37.616358],"type":"Point"}
}
