{
  "type": "Feature",
  "properties": {
    "iso:country": "XX",
    "media:fingerprint": "8c525b688ae4fe25eb8cb7bb74b97181721272c2",
    "media:imagehash_avg": "a:ff818181818181ff",
    "media:imagehash_diff": "d:576f656d6d6d6f69",
    "media:medium": "image",
    "media:mimetype": "image/tiff",
    "media:properties": {
      "colours": [
        {
          "hex": "#e1573a",
          "name": "#e1573a",
          "reference": "vibrant"
        },
        {
          "hex": "#9c3f43",
          "name": "#9c3f43",
          "reference": "vibrant"
        },
        {
          "hex": "#7d7a86",
          "name": "#7d7a86",
          "reference": "vibrant"
        },
        {
          "hex": "#c6c5c2",
          "name": "#c6c5c2",
          "reference": "vibrant"
        },
        {
          "hex": "#3c3b56",
          "name": "#3c3b56",
          "reference": "vibrant"
        }
      ],
      "sizes": {
        "b": {
          "extension": "jpg",
          "height": 768,
          "mimetype": "image/jpeg",
          "secret": "OQhVXZAel1MopnSrEyma2LyhZGJV6R6B",
          "width": 411
        },
        "c": {
          "extension": "jpg",
          "height": 600,
          "mimetype": "image/jpeg",
          "secret": "OQhVXZAel1MopnSrEyma2LyhZGJV6R6B",
          "width": 321
        },
        "dc": {
          "extension": "jpg",
          "height": 600,
          "mimetype": "image/jpeg",
          "secret": "OQhVXZAel1MopnSrEyma2LyhZGJV6R6B",
          "width": 321
        },
        "ds": {
          "extension": "jpg",
          "height": 320,
          "mimetype": "image/jpeg",
          "secret": "OQhVXZAel1MopnSrEyma2LyhZGJV6R6B",
          "width": 320
        },
        "k": {
          "extension": "jpg",
          "height": 1536,
          "mimetype": "image/jpeg",
          "secret": "OQhVXZAel1MopnSrEyma2LyhZGJV6R6B",
          "width": 823
        },
        "n": {
          "extension": "jpg",
          "height": 240,
          "mimetype": "image/jpeg",
          "secret": "OQhVXZAel1MopnSrEyma2LyhZGJV6R6B",
          "width": 128
        },
        "o": {
          "extension": "jpg",
          "height": 2886,
          "mimetype": "image/jpeg",
          "secret": "179qsdW9FekVicywJPMJwrgFqxpIkaM9",
          "width": 1548
        },
        "s": {
          "extension": "jpg",
          "height": 320,
          "mimetype": "image/jpeg",
          "secret": "OQhVXZAel1MopnSrEyma2LyhZGJV6R6B",
          "width": 320
        },
        "z": {
          "extension": "jpg",
          "height": 480,
          "mimetype": "image/jpeg",
          "secret": "OQhVXZAel1MopnSrEyma2LyhZGJV6R6B",
          "width": 257
        }
      }
    },
    "media:uri_template": "https://static.sfomuseum.org/media/152/782/465/1/1527824651_{secret}_{label}.{extention}",
    "sfomuseum:filename": "42714.tif",
    "sfomuseum:image_index": 5,
    "sfomuseum:image_type": "studio",
    "sfomuseum:placetype": "image",
    "sfomuseum:primary_image": 1,
    "wof:depicts": [
      1159284279,
      1511908579
    ],
    "wof:name": "airsickness bag: Deutsche BA",
    "wof:placetype": "custom",
    "wof:placetype_alt": "image"
  },
  "geometry": {"coordinates":[-122.386155,37.616358],"type":"Point"}
}
