{
  "type": "Feature",
  "properties": {
    "iso:country":"XX",
    "media:medium":"image",
    "sfomuseum:filename":"2011197028_front.tif",
    "sfomuseum:image_index":5,
    "sfomuseum:placetype":"image",
    "sfomuseum:primary_image":1,
    "wof:depicts":[
        1511951433
    ],
    "wof:name":"menu: United Airlines, Business Class",
    "wof:placetype":"media"
},
  "geometry": {"coordinates":[-122.386155,37.616358],"type":"Point"}
}