{
  "type": "Feature",
  "properties": {
    "iso:country": "XX",
    "media:fingerprint": "e75b8e5246e2d0a311224836d3131ee6a60dccf9",
    "media:imagehash_avg": "a:000098383cbebe88",
    "media:imagehash_diff": "d:7c533363f0706878",
    "media:medium": "image",
    "media:mimetype": "image/tiff",
    "media:properties": {
      "colours": [
        {
          "hex": "#7a7a7a",
          "name": "#7a7a7a",
          "reference": "vibrant"
        }, 
        {
          "hex": "#c0c0c0",
          "name": "#c0c0c0",
          "reference": "vibrant"
        }, 
        {
          "hex": "#464646",
          "name": "#464646",
          "reference": "vibrant"
        }
      ],
      "sizes": {
        "b": {
          "extension": "jpg",
          "height": 768,
          "mimetype": "image/jpeg",
          "secret": "Ld160aCOxV9tnWPVk0eFUChAjNUZwBHF",
          "width": 776
        },
        "c": {
          "extension": "jpg",
          "height": 600,
          "mimetype": "image/jpeg",
          "secret": "Ld160aCOxV9tnWPVk0eFUChAjNUZwBHF",
          "width": 606
        },
        "dc": {
          "extension": "jpg",
          "height": 600,
          "mimetype": "image/jpeg",
          "secret": "Ld160aCOxV9tnWPVk0eFUChAjNUZwBHF",
          "width": 606
        },
        "ds": {
          "extension": "jpg",
          "height": 320,
          "mimetype": "image/jpeg",
          "secret": "Ld160aCOxV9tnWPVk0eFUChAjNUZwBHF",
          "width": 320
        },
        "k": {
          "extension": "jpg",
          "height": 1536,
          "mimetype": "image/jpeg",
          "secret": "Ld160aCOxV9tnWPVk0eFUChAjNUZwBHF",
          "width": 1552
        },
        "n": {
          "extension": "jpg",
          "height": 239,
          "mimetype": "image/jpeg",
          "secret": "Ld160aCOxV9tnWPVk0eFUChAjNUZwBHF",
          "width": 242
        },
        "o": {
          "extension": "jpg",
          "height": 2563,
          "mimetype": "image/jpeg",
          "secret": "TLm1POfP1ZESuyluScfUXjvQk7KErl6y",
          "width": 2590
        },
        "s": {
          "extension": "jpg",
          "height": 320,
          "mimetype": "image/jpeg",
          "secret": "Ld160aCOxV9tnWPVk0eFUChAjNUZwBHF",
          "width": 320
        },
        "z": {
          "extension": "jpg",
          "height": 479,
          "mimetype": "image/jpeg",
          "secret": "Ld160aCOxV9tnWPVk0eFUChAjNUZwBHF",
          "width": 485
        }
      }
    },
    "media:uri_template": "https://millsfield.sfomuseum.org/media/152/782/601/1/1527826011_{secret}_{label}.{extention}",
    "sfomuseum:filename": "43449.tif",
    "sfomuseum:image_index": 5,
    "sfomuseum:placetype": "image",
    "sfomuseum:primary_image": 1,
    "wof:depicts": [
      1511947045
    ],
    "wof:name": "negative: San Francisco International Airport (SFO), Dean Rusk visit",
    "wof:placetype": "media"
  },
  "geometry": {"coordinates":[-122.386155,37.616358],"type":"Point"}
}
