{
  "type": "Feature",
  "properties": {
    "iso:country": "XX",
    "media:fingerprint": "075b8f0b1929f090ad9560ead48183469067990a",
    "media:imagehash_avg": "a:01017d7f3f3f1f0f",
    "media:imagehash_diff": "d:0961e1ecef6fbf3f",
    "media:medium": "image",
    "media:mimetype": "image/jpeg",
    "media:properties": {
      "colours": [
        {
          "hex": "#e34f03",
          "name": "#e34f03",
          "reference": "vibrant"
        }, 
        {
          "hex": "#791707",
          "name": "#791707",
          "reference": "vibrant"
        }, 
        {
          "hex": "#9e7f6a",
          "name": "#9e7f6a",
          "reference": "vibrant"
        }, 
        {
          "hex": "#cdc5a5",
          "name": "#cdc5a5",
          "reference": "vibrant"
        }, 
        {
          "hex": "#642f32",
          "name": "#642f32",
          "reference": "vibrant"
        }
      ],
      "sizes": {
        "b": {
          "extension": "jpg",
          "height": 768,
          "mimetype": "image/jpeg",
          "secret": "5peTWhkOw51y5Yz87j678G9NLlU0QlEP",
          "width": 376
        },
        "c": {
          "extension": "jpg",
          "height": 600,
          "mimetype": "image/jpeg",
          "secret": "5peTWhkOw51y5Yz87j678G9NLlU0QlEP",
          "width": 294
        },
        "dc": {
          "extension": "jpg",
          "height": 600,
          "mimetype": "image/jpeg",
          "secret": "5peTWhkOw51y5Yz87j678G9NLlU0QlEP",
          "width": 294
        },
        "ds": {
          "extension": "jpg",
          "height": 320,
          "mimetype": "image/jpeg",
          "secret": "5peTWhkOw51y5Yz87j678G9NLlU0QlEP",
          "width": 320
        },
        "k": {
          "extension": "jpg",
          "height": 1536,
          "mimetype": "image/jpeg",
          "secret": "5peTWhkOw51y5Yz87j678G9NLlU0QlEP",
          "width": 752
        },
        "n": {
          "extension": "jpg",
          "height": 240,
          "mimetype": "image/jpeg",
          "secret": "5peTWhkOw51y5Yz87j678G9NLlU0QlEP",
          "width": 117
        },
        "o": {
          "extension": "jpg",
          "height": 2012,
          "mimetype": "image/jpeg",
          "secret": "iQ9u9CvGDwYjOdVG8bBrvM9tI8obqAkw",
          "width": 986
        },
        "s": {
          "extension": "jpg",
          "height": 320,
          "mimetype": "image/jpeg",
          "secret": "5peTWhkOw51y5Yz87j678G9NLlU0QlEP",
          "width": 320
        },
        "z": {
          "extension": "jpg",
          "height": 480,
          "mimetype": "image/jpeg",
          "secret": "5peTWhkOw51y5Yz87j678G9NLlU0QlEP",
          "width": 235
        }
      }
    },
    "media:uri_template": "https://millsfield.sfomuseum.org/media/152/782/111/5/1527821115_{secret}_{label}.{extention}",
    "sfomuseum:filename": "37237.jpg",
    "sfomuseum:image_index": 5,
    "sfomuseum:placetype": "image",
    "sfomuseum:primary_image": 1,
    "wof:depicts": [
      1511937949
    ],
    "wof:name": "timetable: Lufthansa German Airlines",
    "wof:placetype": "media"
  },
  "geometry": {"coordinates":[-122.386155,37.616358],"type":"Point"}
}
