{
  "type": "Feature",
  "properties": {
    "iso:country": "XX",
    "media:fingerprint": "b2401a651cfdc18bb44e7cbd2802321963ae78f7",
    "media:imagehash_avg": "a:f8d9d91f0f0e0400",
    "media:imagehash_diff": "d:003bb3b9bd3c383c",
    "media:medium": "image",
    "media:mimetype": "image/tiff",
    "media:properties": {
      "colours": [
        {
          "hex": "#808080",
          "name": "#808080",
          "reference": "vibrant"
        }, 
        {
          "hex": "#c0c0c0",
          "name": "#c0c0c0",
          "reference": "vibrant"
        }, 
        {
          "hex": "#464646",
          "name": "#464646",
          "reference": "vibrant"
        }
      ],
      "sizes": {
        "b": {
          "extension": "jpg",
          "height": 693,
          "mimetype": "image/jpeg",
          "secret": "bo4yhpYQxdXru9atuqFLrR0m2P9yK7kF",
          "width": 1024
        },
        "c": {
          "extension": "jpg",
          "height": 542,
          "mimetype": "image/jpeg",
          "secret": "bo4yhpYQxdXru9atuqFLrR0m2P9yK7kF",
          "width": 800
        },
        "dc": {
          "extension": "jpg",
          "height": 542,
          "mimetype": "image/jpeg",
          "secret": "bo4yhpYQxdXru9atuqFLrR0m2P9yK7kF",
          "width": 800
        },
        "ds": {
          "extension": "jpg",
          "height": 320,
          "mimetype": "image/jpeg",
          "secret": "bo4yhpYQxdXru9atuqFLrR0m2P9yK7kF",
          "width": 320
        },
        "k": {
          "extension": "jpg",
          "height": 1387,
          "mimetype": "image/jpeg",
          "secret": "bo4yhpYQxdXru9atuqFLrR0m2P9yK7kF",
          "width": 2048
        },
        "n": {
          "extension": "jpg",
          "height": 216,
          "mimetype": "image/jpeg",
          "secret": "bo4yhpYQxdXru9atuqFLrR0m2P9yK7kF",
          "width": 320
        },
        "o": {
          "extension": "jpg",
          "height": 1076,
          "mimetype": "image/jpeg",
          "secret": "K3Veuq37FeSA970bOdlV4tlm2iswFVHo",
          "width": 1588
        },
        "s": {
          "extension": "jpg",
          "height": 320,
          "mimetype": "image/jpeg",
          "secret": "bo4yhpYQxdXru9atuqFLrR0m2P9yK7kF",
          "width": 320
        },
        "z": {
          "extension": "jpg",
          "height": 433,
          "mimetype": "image/jpeg",
          "secret": "bo4yhpYQxdXru9atuqFLrR0m2P9yK7kF",
          "width": 640
        }
      }
    },
    "media:uri_template": "https://millsfield.sfomuseum.org/media/152/782/841/3/1527828413_{secret}_{label}.{extention}",
    "sfomuseum:filename": "44581.tif",
    "sfomuseum:image_index": 5,
    "sfomuseum:placetype": "image",
    "sfomuseum:primary_image": 1,
    "wof:depicts": [
      1511949445
    ],
    "wof:name": "negative: San Francisco International Airport (SFO), Central Terminal interior",
    "wof:placetype": "media"
  },
  "geometry": {"coordinates":[-122.386155,37.616358],"type":"Point"}
}
