{
  "type": "Feature",
  "properties": {
    "iso:country": "XX",
    "media:fingerprint": "3bca916499f0c20b844a0d48bdda28a0ed5d48b6",
    "media:imagehash_avg": "a:ffff7f0000300080",
    "media:imagehash_diff": "d:cd8dcf7063626819",
    "media:medium": "image",
    "media:mimetype": "image/tiff",
    "media:properties": {
      "colours": [
        {
          "hex": "#808080",
          "name": "#808080",
          "reference": "vibrant"
        },
        {
          "hex": "#c0c0c0",
          "name": "#c0c0c0",
          "reference": "vibrant"
        },
        {
          "hex": "#464646",
          "name": "#464646",
          "reference": "vibrant"
        }
      ],
      "sizes": {
        "b": {
          "extension": "jpg",
          "height": 768,
          "mimetype": "image/jpeg",
          "secret": "I6D27bd7l2A7XsHk8XMlDyKdFt4wa0lv",
          "width": 980
        },
        "c": {
          "extension": "jpg",
          "height": 600,
          "mimetype": "image/jpeg",
          "secret": "I6D27bd7l2A7XsHk8XMlDyKdFt4wa0lv",
          "width": 766
        },
        "dc": {
          "extension": "jpg",
          "height": 600,
          "mimetype": "image/jpeg",
          "secret": "I6D27bd7l2A7XsHk8XMlDyKdFt4wa0lv",
          "width": 766
        },
        "ds": {
          "extension": "jpg",
          "height": 320,
          "mimetype": "image/jpeg",
          "secret": "I6D27bd7l2A7XsHk8XMlDyKdFt4wa0lv",
          "width": 320
        },
        "k": {
          "extension": "jpg",
          "height": 1536,
          "mimetype": "image/jpeg",
          "secret": "I6D27bd7l2A7XsHk8XMlDyKdFt4wa0lv",
          "width": 1961
        },
        "n": {
          "extension": "jpg",
          "height": 240,
          "mimetype": "image/jpeg",
          "secret": "I6D27bd7l2A7XsHk8XMlDyKdFt4wa0lv",
          "width": 306
        },
        "o": {
          "extension": "jpg",
          "height": 2190,
          "mimetype": "image/jpeg",
          "secret": "XQxqOPvfVQVp8YQExtngRfFL5etRotwy",
          "width": 2797
        },
        "s": {
          "extension": "jpg",
          "height": 320,
          "mimetype": "image/jpeg",
          "secret": "I6D27bd7l2A7XsHk8XMlDyKdFt4wa0lv",
          "width": 320
        },
        "z": {
          "extension": "jpg",
          "height": 480,
          "mimetype": "image/jpeg",
          "secret": "I6D27bd7l2A7XsHk8XMlDyKdFt4wa0lv",
          "width": 613
        }
      }
    },
    "media:uri_template": "https://static.sfomuseum.org/media/172/956/537/7/1729565377_{secret}_{label}.{extention}",
    "sfomuseum:filename": "39595.tif",
    "sfomuseum:image_index": 0,
    "sfomuseum:image_type": "studio",
    "sfomuseum:placetype": "image",
    "sfomuseum:primary_image": 1,
    "wof:depicts": [
      1159285393,
      1729564277
    ],
    "wof:name": "photograph: TWA (Trans World Airlines), office desk",
    "wof:placetype": "custom",
    "wof:placetype_alt": "image"
  },
  "geometry": {"coordinates":[-122.386155,37.616357],"type":"Point"}
}
