{
  "type": "Feature",
  "properties": {
    "iso:country": "XX",
    "media:fingerprint": "80e85614fd5f9712f5f08e0fdcdce913a315dc05",
    "media:imagehash_avg": "a:60e3e3e3e3e3e320",
    "media:imagehash_diff": "d:cecfcfcfcfcfcfcf",
    "media:medium": "image",
    "media:mimetype": "image/jpeg",
    "media:properties": {
      "colours": [
        {
          "hex": "#58abb9",
          "name": "#58abb9",
          "reference": "vibrant"
        }, 
        {
          "hex": "#a3d6df",
          "name": "#a3d6df",
          "reference": "vibrant"
        }, 
        {
          "hex": "#1c5761",
          "name": "#1c5761",
          "reference": "vibrant"
        }, 
        {
          "hex": "#629397",
          "name": "#629397",
          "reference": "vibrant"
        }, 
        {
          "hex": "#b5c6c2",
          "name": "#b5c6c2",
          "reference": "vibrant"
        }
      ],
      "sizes": {
        "b": {
          "extension": "jpg",
          "height": 768,
          "mimetype": "image/jpeg",
          "secret": "afbE72ofnsW4JS6sH2xR3DOfSOqnwI2A",
          "width": 565
        },
        "c": {
          "extension": "jpg",
          "height": 600,
          "mimetype": "image/jpeg",
          "secret": "afbE72ofnsW4JS6sH2xR3DOfSOqnwI2A",
          "width": 442
        },
        "dc": {
          "extension": "jpg",
          "height": 600,
          "mimetype": "image/jpeg",
          "secret": "afbE72ofnsW4JS6sH2xR3DOfSOqnwI2A",
          "width": 442
        },
        "ds": {
          "extension": "jpg",
          "height": 320,
          "mimetype": "image/jpeg",
          "secret": "afbE72ofnsW4JS6sH2xR3DOfSOqnwI2A",
          "width": 320
        },
        "k": {
          "extension": "jpg",
          "height": 1536,
          "mimetype": "image/jpeg",
          "secret": "afbE72ofnsW4JS6sH2xR3DOfSOqnwI2A",
          "width": 1131
        },
        "n": {
          "extension": "jpg",
          "height": 240,
          "mimetype": "image/jpeg",
          "secret": "afbE72ofnsW4JS6sH2xR3DOfSOqnwI2A",
          "width": 176
        },
        "o": {
          "extension": "jpg",
          "height": 612,
          "mimetype": "image/jpeg",
          "secret": "UCE6sWf1dvkos5CrD8woYqSA5qjTCdKl",
          "width": 451
        },
        "s": {
          "extension": "jpg",
          "height": 320,
          "mimetype": "image/jpeg",
          "secret": "afbE72ofnsW4JS6sH2xR3DOfSOqnwI2A",
          "width": 320
        },
        "z": {
          "extension": "jpg",
          "height": 480,
          "mimetype": "image/jpeg",
          "secret": "afbE72ofnsW4JS6sH2xR3DOfSOqnwI2A",
          "width": 353
        }
      }
    },
    "media:uri_template": "https://millsfield.sfomuseum.org/media/152/781/812/5/1527818125_{secret}_{label}.{extention}",
    "sfomuseum:filename": "13741.jpg",
    "sfomuseum:image_index": 1,
    "sfomuseum:placetype": "image",
    "sfomuseum:primary_image": 0,
    "wof:depicts": [
      1511906807
    ],
    "wof:name": "menu: Pan American World Airways",
    "wof:placetype": "media"
  },
  "geometry": {"coordinates":[-122.386155,37.616358],"type":"Point"}
}
