{
  "type": "Feature",
  "properties": {
    "iso:country": "US",
    "media:fingerprint": "43f229ba4df799a05eeb04b10a9c728be43d99b0",
    "media:imagehash_avg": "a:fffc7c78000030ff",
    "media:imagehash_diff": "d:b858d1c1c1e0e0f0",
    "media:medium": "image",
    "media:mimetype": "image/jpeg",
    "media:properties": {
      "colours": [
        {
          "hex": "#868686",
          "name": "#868686",
          "reference": "vibrant"
        }, 
        {
          "hex": "#b8b8b8",
          "name": "#b8b8b8",
          "reference": "vibrant"
        }, 
        {
          "hex": "#484848",
          "name": "#484848",
          "reference": "vibrant"
        }
      ],
      "sizes": {
        "b": {
          "extension": "jpg",
          "height": 715,
          "mimetype": "image/jpeg",
          "secret": "rhC6VPG6OrEH7lAF4Hcs4FKgatVUBjfP",
          "width": 1024
        },
        "c": {
          "extension": "jpg",
          "height": 558,
          "mimetype": "image/jpeg",
          "secret": "rhC6VPG6OrEH7lAF4Hcs4FKgatVUBjfP",
          "width": 800
        },
        "dc": {
          "extension": "jpg",
          "height": 558,
          "mimetype": "image/jpeg",
          "secret": "rhC6VPG6OrEH7lAF4Hcs4FKgatVUBjfP",
          "width": 800
        },
        "ds": {
          "extension": "jpg",
          "height": 320,
          "mimetype": "image/jpeg",
          "secret": "rhC6VPG6OrEH7lAF4Hcs4FKgatVUBjfP",
          "width": 320
        },
        "k": {
          "extension": "jpg",
          "height": 1430,
          "mimetype": "image/jpeg",
          "secret": "rhC6VPG6OrEH7lAF4Hcs4FKgatVUBjfP",
          "width": 2048
        },
        "n": {
          "extension": "jpg",
          "height": 223,
          "mimetype": "image/jpeg",
          "secret": "rhC6VPG6OrEH7lAF4Hcs4FKgatVUBjfP",
          "width": 320
        },
        "o": {
          "extension": "jpg",
          "height": 2005,
          "mimetype": "image/jpeg",
          "secret": "toIvgZdVqOz7nKOghvChrkF7Vluyoj4f",
          "width": 2870
        },
        "s": {
          "extension": "jpg",
          "height": 320,
          "mimetype": "image/jpeg",
          "secret": "rhC6VPG6OrEH7lAF4Hcs4FKgatVUBjfP",
          "width": 320
        },
        "z": {
          "extension": "jpg",
          "height": 447,
          "mimetype": "image/jpeg",
          "secret": "rhC6VPG6OrEH7lAF4Hcs4FKgatVUBjfP",
          "width": 640
        }
      }
    },
    "media:uri_template": "https://millsfield.sfomuseum.org/media/152/781/881/5/1527818815_{secret}_{label}.{extention}",
    "sfomuseum:filename": "19778.jpg",
    "sfomuseum:image_index": 5,
    "sfomuseum:placetype": "image",
    "sfomuseum:primary_image": 1,
    "wof:depicts": [
      1511924105
    ],
    "wof:name": "photograph: San Francisco Airport, aerial view",
    "wof:placetype": "media"
  },
  "geometry": {"coordinates":[-122.386155,37.616358],"type":"Point"}
}
