{
  "type": "Feature",
  "properties": {
    "iso:country": "XX",
    "media:fingerprint": "eafe4c43ea684c0e3f48df0a0eb876d7b53f5229",
    "media:imagehash_avg": "a:7f3e7eff72200000",
    "media:imagehash_diff": "d:fcf8986dc6c2e3ed",
    "media:medium": "image",
    "media:mimetype": "image/tiff",
    "media:properties": {
      "colours": [
        {
          "hex": "#9e681a",
          "name": "#9e681a",
          "reference": "vibrant"
        }, 
        {
          "hex": "#c1d99b",
          "name": "#c1d99b",
          "reference": "vibrant"
        }, 
        {
          "hex": "#8a591a",
          "name": "#8a591a",
          "reference": "vibrant"
        }, 
        {
          "hex": "#989b6d",
          "name": "#989b6d",
          "reference": "vibrant"
        }, 
        {
          "hex": "#a9bea1",
          "name": "#a9bea1",
          "reference": "vibrant"
        }
      ],
      "sizes": {
        "b": {
          "extension": "jpg",
          "height": 707,
          "mimetype": "image/jpeg",
          "secret": "4KDezXYLc0lKmqB2WljRpwcs6cl2fBtJ",
          "width": 1024
        },
        "c": {
          "extension": "jpg",
          "height": 553,
          "mimetype": "image/jpeg",
          "secret": "4KDezXYLc0lKmqB2WljRpwcs6cl2fBtJ",
          "width": 800
        },
        "dc": {
          "extension": "jpg",
          "height": 553,
          "mimetype": "image/jpeg",
          "secret": "4KDezXYLc0lKmqB2WljRpwcs6cl2fBtJ",
          "width": 800
        },
        "ds": {
          "extension": "jpg",
          "height": 320,
          "mimetype": "image/jpeg",
          "secret": "4KDezXYLc0lKmqB2WljRpwcs6cl2fBtJ",
          "width": 320
        },
        "k": {
          "extension": "jpg",
          "height": 1415,
          "mimetype": "image/jpeg",
          "secret": "4KDezXYLc0lKmqB2WljRpwcs6cl2fBtJ",
          "width": 2048
        },
        "n": {
          "extension": "jpg",
          "height": 221,
          "mimetype": "image/jpeg",
          "secret": "4KDezXYLc0lKmqB2WljRpwcs6cl2fBtJ",
          "width": 320
        },
        "o": {
          "extension": "jpg",
          "height": 1120,
          "mimetype": "image/jpeg",
          "secret": "Cqb0QdvYq8HSxlDYnA1MRdfVQLbhVYlb",
          "width": 1620
        },
        "s": {
          "extension": "jpg",
          "height": 320,
          "mimetype": "image/jpeg",
          "secret": "4KDezXYLc0lKmqB2WljRpwcs6cl2fBtJ",
          "width": 320
        },
        "z": {
          "extension": "jpg",
          "height": 442,
          "mimetype": "image/jpeg",
          "secret": "4KDezXYLc0lKmqB2WljRpwcs6cl2fBtJ",
          "width": 640
        }
      }
    },
    "media:uri_template": "https://millsfield.sfomuseum.org/media/152/782/753/1/1527827531_{secret}_{label}.{extention}",
    "sfomuseum:filename": "44129.tif",
    "sfomuseum:image_index": 5,
    "sfomuseum:placetype": "image",
    "sfomuseum:primary_image": 1,
    "wof:depicts": [
      1511948567
    ],
    "wof:name": "negative: San Francisco International Airport (SFO), United Air Lines boarding area interior",
    "wof:placetype": "media"
  },
  "geometry": {"coordinates":[-122.386155,37.616358],"type":"Point"}
}
