{
  "type": "Feature",
  "properties": {
    "iso:country": "XX",
    "media:fingerprint": "05d000a25aea5c408dc945b79b682b3c5f543232",
    "media:imagehash_avg": "a:3d3d7f7f6f4f4705",
    "media:imagehash_diff": "d:e9e9ede9cb9999bd",
    "media:medium": "image",
    "media:mimetype": "image/tiff",
    "media:properties": {
      "colours": [
        {
          "hex": "#b84e2b",
          "name": "#b84e2b",
          "reference": "vibrant"
        },
        {
          "hex": "#d8c7ac",
          "name": "#d8c7ac",
          "reference": "vibrant"
        },
        {
          "hex": "#6c7d8e",
          "name": "#6c7d8e",
          "reference": "vibrant"
        },
        {
          "hex": "#cfc4ab",
          "name": "#cfc4ab",
          "reference": "vibrant"
        },
        {
          "hex": "#453f3a",
          "name": "#453f3a",
          "reference": "vibrant"
        }
      ],
      "sizes": {
        "b": {
          "extension": "jpg",
          "height": 768,
          "mimetype": "image/jpeg",
          "secret": "RI2shdVD2eDYz2r6ExVUKHW3u2gfOUtB",
          "width": 429
        },
        "c": {
          "extension": "jpg",
          "height": 600,
          "mimetype": "image/jpeg",
          "secret": "RI2shdVD2eDYz2r6ExVUKHW3u2gfOUtB",
          "width": 335
        },
        "dc": {
          "extension": "jpg",
          "height": 600,
          "mimetype": "image/jpeg",
          "secret": "RI2shdVD2eDYz2r6ExVUKHW3u2gfOUtB",
          "width": 335
        },
        "ds": {
          "extension": "jpg",
          "height": 320,
          "mimetype": "image/jpeg",
          "secret": "RI2shdVD2eDYz2r6ExVUKHW3u2gfOUtB",
          "width": 320
        },
        "k": {
          "extension": "jpg",
          "height": 1536,
          "mimetype": "image/jpeg",
          "secret": "RI2shdVD2eDYz2r6ExVUKHW3u2gfOUtB",
          "width": 859
        },
        "n": {
          "extension": "jpg",
          "height": 240,
          "mimetype": "image/jpeg",
          "secret": "RI2shdVD2eDYz2r6ExVUKHW3u2gfOUtB",
          "width": 134
        },
        "o": {
          "extension": "jpg",
          "height": 3336,
          "mimetype": "image/jpeg",
          "secret": "a3nKFLcG7yi8ZNcWLjWzDUgU3bsbqoPn",
          "width": 1866
        },
        "s": {
          "extension": "jpg",
          "height": 320,
          "mimetype": "image/jpeg",
          "secret": "RI2shdVD2eDYz2r6ExVUKHW3u2gfOUtB",
          "width": 320
        },
        "z": {
          "extension": "jpg",
          "height": 480,
          "mimetype": "image/jpeg",
          "secret": "RI2shdVD2eDYz2r6ExVUKHW3u2gfOUtB",
          "width": 268
        }
      }
    },
    "media:uri_template": "https://static.sfomuseum.org/media/152/782/333/7/1527823337_{secret}_{label}.{extention}",
    "sfomuseum:filename": "41504.tif",
    "sfomuseum:image_index": 5,
    "sfomuseum:image_type": "studio",
    "sfomuseum:placetype": "image",
    "sfomuseum:primary_image": 0,
    "wof:depicts": [
      1159283539,
      1511908351,
      1159287499
    ],
    "wof:name": "airsickness bag: AeroMexico",
    "wof:placetype": "custom",
    "wof:placetype_alt": "image"
  },
  "geometry": {"coordinates":[-122.386155,37.616358],"type":"Point"}
}
