{
  "type": "Feature",
  "properties": {
    "iso:country": "XX",
    "media:fingerprint": "ab46fd32524b7a4ee73eb423c42291c5244c7d00",
    "media:imagehash_avg": "a:67797f6f7f6f3f01",
    "media:imagehash_diff": "d:cbab8989ababebef",
    "media:medium": "image",
    "media:mimetype": "image/tiff",
    "media:properties": {
      "colours": [
        {
          "hex": "#e8e0c8",
          "name": "#e8e0c8",
          "reference": "vibrant"
        }, 
        {
          "hex": "#6c7f8e",
          "name": "#6c7f8e",
          "reference": "vibrant"
        }, 
        {
          "hex": "#c2bbac",
          "name": "#c2bbac",
          "reference": "vibrant"
        }, 
        {
          "hex": "#444138",
          "name": "#444138",
          "reference": "vibrant"
        }
      ],
      "sizes": {
        "b": {
          "extension": "jpg",
          "height": 768,
          "mimetype": "image/jpeg",
          "secret": "eYaDKO6LzHfediWQ5wcCFcTFSkThx2Yy",
          "width": 415
        },
        "c": {
          "extension": "jpg",
          "height": 600,
          "mimetype": "image/jpeg",
          "secret": "eYaDKO6LzHfediWQ5wcCFcTFSkThx2Yy",
          "width": 324
        },
        "dc": {
          "extension": "jpg",
          "height": 600,
          "mimetype": "image/jpeg",
          "secret": "eYaDKO6LzHfediWQ5wcCFcTFSkThx2Yy",
          "width": 324
        },
        "ds": {
          "extension": "jpg",
          "height": 320,
          "mimetype": "image/jpeg",
          "secret": "eYaDKO6LzHfediWQ5wcCFcTFSkThx2Yy",
          "width": 320
        },
        "k": {
          "extension": "jpg",
          "height": 1536,
          "mimetype": "image/jpeg",
          "secret": "eYaDKO6LzHfediWQ5wcCFcTFSkThx2Yy",
          "width": 830
        },
        "n": {
          "extension": "jpg",
          "height": 240,
          "mimetype": "image/jpeg",
          "secret": "eYaDKO6LzHfediWQ5wcCFcTFSkThx2Yy",
          "width": 129
        },
        "o": {
          "extension": "jpg",
          "height": 2904,
          "mimetype": "image/jpeg",
          "secret": "TJhIRqx5N7I6VeIJ7qjsuafT0JT9f61g",
          "width": 1571
        },
        "s": {
          "extension": "jpg",
          "height": 320,
          "mimetype": "image/jpeg",
          "secret": "eYaDKO6LzHfediWQ5wcCFcTFSkThx2Yy",
          "width": 320
        },
        "z": {
          "extension": "jpg",
          "height": 480,
          "mimetype": "image/jpeg",
          "secret": "eYaDKO6LzHfediWQ5wcCFcTFSkThx2Yy",
          "width": 259
        }
      }
    },
    "media:uri_template": "https://millsfield.sfomuseum.org/media/152/782/374/7/1527823747_{secret}_{label}.{extention}",
    "sfomuseum:filename": "41771.tif",
    "sfomuseum:image_index": 5,
    "sfomuseum:placetype": "image",
    "sfomuseum:primary_image": 0,
    "wof:depicts": [
      1511908491
    ],
    "wof:name": "airsickness bag: CAAC (Civil Aviation Administration of China)",
    "wof:placetype": "media"
  },
  "geometry": {"coordinates":[-122.386155,37.616358],"type":"Point"}
}
