{
  "type": "Feature",
  "properties": {
    "iso:country": "XX",
    "media:fingerprint": "d7d1769f83c41bd6e1b656ab107aa8cf54d4eb5c",
    "media:imagehash_avg": "a:9181818101a3a9ff",
    "media:imagehash_diff": "d:7767557367555571",
    "media:medium": "image",
    "media:mimetype": "image/tiff",
    "media:properties": {
      "colours": [
        {
          "hex": "#dd1b11",
          "name": "#dd1b11",
          "reference": "vibrant"
        },
        {
          "hex": "#f1b29d",
          "name": "#f1b29d",
          "reference": "vibrant"
        },
        {
          "hex": "#182b71",
          "name": "#182b71",
          "reference": "vibrant"
        },
        {
          "hex": "#ae685c",
          "name": "#ae685c",
          "reference": "vibrant"
        },
        {
          "hex": "#bfc0b9",
          "name": "#bfc0b9",
          "reference": "vibrant"
        }
      ],
      "sizes": {
        "b": {
          "extension": "jpg",
          "height": 714,
          "mimetype": "image/jpeg",
          "secret": "MXgid96XFGtfCYhy7oLVOgIAUzYq9JAg",
          "width": 1024
        },
        "c": {
          "extension": "jpg",
          "height": 557,
          "mimetype": "image/jpeg",
          "secret": "MXgid96XFGtfCYhy7oLVOgIAUzYq9JAg",
          "width": 800
        },
        "dc": {
          "extension": "jpg",
          "height": 557,
          "mimetype": "image/jpeg",
          "secret": "MXgid96XFGtfCYhy7oLVOgIAUzYq9JAg",
          "width": 800
        },
        "ds": {
          "extension": "jpg",
          "height": 320,
          "mimetype": "image/jpeg",
          "secret": "MXgid96XFGtfCYhy7oLVOgIAUzYq9JAg",
          "width": 320
        },
        "k": {
          "extension": "jpg",
          "height": 1428,
          "mimetype": "image/jpeg",
          "secret": "MXgid96XFGtfCYhy7oLVOgIAUzYq9JAg",
          "width": 2048
        },
        "n": {
          "extension": "jpg",
          "height": 223,
          "mimetype": "image/jpeg",
          "secret": "MXgid96XFGtfCYhy7oLVOgIAUzYq9JAg",
          "width": 320
        },
        "o": {
          "extension": "jpg",
          "height": 689,
          "mimetype": "image/jpeg",
          "secret": "M3Ewrouk4nkAIWESF0gBtNLWnArqGJH2",
          "width": 988
        },
        "s": {
          "extension": "jpg",
          "height": 320,
          "mimetype": "image/jpeg",
          "secret": "MXgid96XFGtfCYhy7oLVOgIAUzYq9JAg",
          "width": 320
        },
        "z": {
          "extension": "jpg",
          "height": 446,
          "mimetype": "image/jpeg",
          "secret": "MXgid96XFGtfCYhy7oLVOgIAUzYq9JAg",
          "width": 640
        }
      }
    },
    "media:uri_template": "https://static.sfomuseum.org/media/152/785/300/3/1527853003_{secret}_{label}.{extention}",
    "sfomuseum:filename": "2012.149.1541.tif",
    "sfomuseum:image_index": 5,
    "sfomuseum:image_type": "studio",
    "sfomuseum:placetype": "image",
    "sfomuseum:primary_image": 1,
    "wof:depicts": [
      1511953041
    ],
    "wof:name": "postage stamps: United States Airmail",
    "wof:placetype": "custom",
    "wof:placetype_alt": "image"
  },
  "geometry": {"coordinates":[-122.386155,37.616358],"type":"Point"}
}
