{
  "type": "Feature",
  "properties": {
    "iso:country": "XX",
    "media:fingerprint": "2e6084cb5003c7f4b4d1f7d19a7976aa0130cdc1",
    "media:imagehash_avg": "a:7f7fff9b11010000",
    "media:imagehash_diff": "d:f9cdbfb7333b33f1",
    "media:medium": "image",
    "media:mimetype": "image/tiff",
    "media:properties": {
      "colours": [
        {
          "hex": "#808080",
          "name": "#808080",
          "reference": "vibrant"
        }, 
        {
          "hex": "#bababa",
          "name": "#bababa",
          "reference": "vibrant"
        }, 
        {
          "hex": "#404040",
          "name": "#404040",
          "reference": "vibrant"
        }
      ],
      "sizes": {
        "b": {
          "extension": "jpg",
          "height": 768,
          "mimetype": "image/jpeg",
          "secret": "G5U8AYPemaFLScfFDpOBUevDesFvXCMX",
          "width": 969
        },
        "c": {
          "extension": "jpg",
          "height": 600,
          "mimetype": "image/jpeg",
          "secret": "G5U8AYPemaFLScfFDpOBUevDesFvXCMX",
          "width": 757
        },
        "dc": {
          "extension": "jpg",
          "height": 600,
          "mimetype": "image/jpeg",
          "secret": "G5U8AYPemaFLScfFDpOBUevDesFvXCMX",
          "width": 757
        },
        "ds": {
          "extension": "jpg",
          "height": 320,
          "mimetype": "image/jpeg",
          "secret": "G5U8AYPemaFLScfFDpOBUevDesFvXCMX",
          "width": 320
        },
        "k": {
          "extension": "jpg",
          "height": 1536,
          "mimetype": "image/jpeg",
          "secret": "G5U8AYPemaFLScfFDpOBUevDesFvXCMX",
          "width": 1939
        },
        "n": {
          "extension": "jpg",
          "height": 240,
          "mimetype": "image/jpeg",
          "secret": "G5U8AYPemaFLScfFDpOBUevDesFvXCMX",
          "width": 303
        },
        "o": {
          "extension": "jpg",
          "height": 2181,
          "mimetype": "image/jpeg",
          "secret": "xCtUAMGkmgKcjNE15NTbOsKWh2kjC7Cy",
          "width": 2754
        },
        "s": {
          "extension": "jpg",
          "height": 320,
          "mimetype": "image/jpeg",
          "secret": "G5U8AYPemaFLScfFDpOBUevDesFvXCMX",
          "width": 320
        },
        "z": {
          "extension": "jpg",
          "height": 480,
          "mimetype": "image/jpeg",
          "secret": "G5U8AYPemaFLScfFDpOBUevDesFvXCMX",
          "width": 606
        }
      }
    },
    "media:uri_template": "https://millsfield.sfomuseum.org/media/152/782/323/1/1527823231_{secret}_{label}.{extention}",
    "sfomuseum:filename": "41294.tif",
    "sfomuseum:image_index": 5,
    "sfomuseum:placetype": "image",
    "sfomuseum:primary_image": 1,
    "wof:depicts": [
      1511945131
    ],
    "wof:name": "negative: San Francisco International Airport (SFO), dedication of South Terminal",
    "wof:placetype": "media"
  },
  "geometry": {"coordinates":[-122.386155,37.616358],"type":"Point"}
}
