{
  "type": "Feature",
  "properties": {
    "iso:country": "XX",
    "media:fingerprint": "018ac08a2a0e5f406f35d3c899037fec3326cdec",
    "media:imagehash_avg": "a:ffff3f180e1a0c00",
    "media:imagehash_diff": "d:2000f0f2fcf2fc79",
    "media:medium": "image",
    "media:mimetype": "image/tiff",
    "media:properties": {
      "colours": [
        {
          "hex": "#808080",
          "name": "#808080",
          "reference": "vibrant"
        }, 
        {
          "hex": "#b8b8b8",
          "name": "#b8b8b8",
          "reference": "vibrant"
        }, 
        {
          "hex": "#484848",
          "name": "#484848",
          "reference": "vibrant"
        }
      ],
      "sizes": {
        "b": {
          "extension": "jpg",
          "height": 767,
          "mimetype": "image/jpeg",
          "secret": "cNXEy9qG9X5mwNDHv8xrXH8duU72Rldh",
          "width": 978
        },
        "c": {
          "extension": "jpg",
          "height": 600,
          "mimetype": "image/jpeg",
          "secret": "cNXEy9qG9X5mwNDHv8xrXH8duU72Rldh",
          "width": 764
        },
        "dc": {
          "extension": "jpg",
          "height": 600,
          "mimetype": "image/jpeg",
          "secret": "cNXEy9qG9X5mwNDHv8xrXH8duU72Rldh",
          "width": 764
        },
        "ds": {
          "extension": "jpg",
          "height": 320,
          "mimetype": "image/jpeg",
          "secret": "cNXEy9qG9X5mwNDHv8xrXH8duU72Rldh",
          "width": 320
        },
        "k": {
          "extension": "jpg",
          "height": 1535,
          "mimetype": "image/jpeg",
          "secret": "cNXEy9qG9X5mwNDHv8xrXH8duU72Rldh",
          "width": 1957
        },
        "n": {
          "extension": "jpg",
          "height": 240,
          "mimetype": "image/jpeg",
          "secret": "cNXEy9qG9X5mwNDHv8xrXH8duU72Rldh",
          "width": 305
        },
        "o": {
          "extension": "jpg",
          "height": 2140,
          "mimetype": "image/jpeg",
          "secret": "Mv1yaLIcwnV2Ei7jP9zd2DpAXSyZiFbt",
          "width": 2727
        },
        "s": {
          "extension": "jpg",
          "height": 320,
          "mimetype": "image/jpeg",
          "secret": "cNXEy9qG9X5mwNDHv8xrXH8duU72Rldh",
          "width": 320
        },
        "z": {
          "extension": "jpg",
          "height": 480,
          "mimetype": "image/jpeg",
          "secret": "cNXEy9qG9X5mwNDHv8xrXH8duU72Rldh",
          "width": 611
        }
      }
    },
    "media:uri_template": "https://millsfield.sfomuseum.org/media/152/782/292/3/1527822923_{secret}_{label}.{extention}",
    "sfomuseum:filename": "41136.tif",
    "sfomuseum:image_index": 5,
    "sfomuseum:placetype": "image",
    "sfomuseum:primary_image": 1,
    "wof:depicts": [
      1511944817
    ],
    "wof:name": "negative: San Francisco International Airport (SFO), aerial",
    "wof:placetype": "media"
  },
  "geometry": {"coordinates":[-122.386155,37.616358],"type":"Point"}
}
