{
  "type": "Feature",
  "properties": {
    "iso:country": "XX",
    "media:fingerprint": "02e3b82a37c901981e9588dd6d098dab6496ebf9",
    "media:imagehash_avg": "a:ffffffef00000000",
    "media:imagehash_diff": "d:d898989cfca89890",
    "media:medium": "image",
    "media:mimetype": "image/tiff",
    "media:properties": {
      "colours": [
        {
          "hex": "#808080",
          "name": "#808080",
          "reference": "vibrant"
        }, 
        {
          "hex": "#c0c0c0",
          "name": "#c0c0c0",
          "reference": "vibrant"
        }, 
        {
          "hex": "#404040",
          "name": "#404040",
          "reference": "vibrant"
        }
      ],
      "sizes": {
        "b": {
          "extension": "jpg",
          "height": 613,
          "mimetype": "image/jpeg",
          "secret": "NR5wED8tzdSYINrT3cFwDaPeBtqVa938",
          "width": 1024
        },
        "c": {
          "extension": "jpg",
          "height": 479,
          "mimetype": "image/jpeg",
          "secret": "NR5wED8tzdSYINrT3cFwDaPeBtqVa938",
          "width": 800
        },
        "dc": {
          "extension": "jpg",
          "height": 479,
          "mimetype": "image/jpeg",
          "secret": "NR5wED8tzdSYINrT3cFwDaPeBtqVa938",
          "width": 800
        },
        "ds": {
          "extension": "jpg",
          "height": 320,
          "mimetype": "image/jpeg",
          "secret": "NR5wED8tzdSYINrT3cFwDaPeBtqVa938",
          "width": 320
        },
        "k": {
          "extension": "jpg",
          "height": 1227,
          "mimetype": "image/jpeg",
          "secret": "NR5wED8tzdSYINrT3cFwDaPeBtqVa938",
          "width": 2048
        },
        "n": {
          "extension": "jpg",
          "height": 191,
          "mimetype": "image/jpeg",
          "secret": "NR5wED8tzdSYINrT3cFwDaPeBtqVa938",
          "width": 320
        },
        "o": {
          "extension": "jpg",
          "height": 4118,
          "mimetype": "image/jpeg",
          "secret": "K1jyPSIeotRT4sWaDpWLSPGQq6NTow2S",
          "width": 6872
        },
        "s": {
          "extension": "jpg",
          "height": 320,
          "mimetype": "image/jpeg",
          "secret": "NR5wED8tzdSYINrT3cFwDaPeBtqVa938",
          "width": 320
        },
        "z": {
          "extension": "jpg",
          "height": 383,
          "mimetype": "image/jpeg",
          "secret": "NR5wED8tzdSYINrT3cFwDaPeBtqVa938",
          "width": 640
        }
      }
    },
    "media:uri_template": "https://millsfield.sfomuseum.org/media/152/782/133/9/1527821339_{secret}_{label}.{extention}",
    "sfomuseum:filename": "38702.tif",
    "sfomuseum:image_index": 5,
    "sfomuseum:placetype": "image",
    "sfomuseum:primary_image": 1,
    "wof:depicts": [
      1511943513
    ],
    "wof:name": "negative: Mills Field Municipal Airport of San Francisco, pump house",
    "wof:placetype": "media"
  },
  "geometry": {"coordinates":[-122.386155,37.616358],"type":"Point"}
}
