{
  "type": "Feature",
  "properties": {
    "iso:country": "XX",
    "media:fingerprint": "c68e840b18a2ddd63e8ceda45c734881c9034058",
    "media:imagehash_avg": "a:fe7e7a6242427e9c",
    "media:imagehash_diff": "d:68d0c6c68e8ecc68",
    "media:medium": "image",
    "media:mimetype": "image/tiff",
    "media:properties": {
      "colours": [
        {
          "hex": "#a6b455",
          "name": "#a6b455",
          "reference": "vibrant"
        },
        {
          "hex": "#f5e9cf",
          "name": "#f5e9cf",
          "reference": "vibrant"
        },
        {
          "hex": "#503506",
          "name": "#503506",
          "reference": "vibrant"
        },
        {
          "hex": "#9c9955",
          "name": "#9c9955",
          "reference": "vibrant"
        },
        {
          "hex": "#dbd3bf",
          "name": "#dbd3bf",
          "reference": "vibrant"
        }
      ],
      "sizes": {
        "b": {
          "extension": "jpg",
          "height": 768,
          "mimetype": "image/jpeg",
          "secret": "H28e6QPmiSwdpZpnAgh7CR87B1cq0wFf",
          "width": 552
        },
        "c": {
          "extension": "jpg",
          "height": 600,
          "mimetype": "image/jpeg",
          "secret": "H28e6QPmiSwdpZpnAgh7CR87B1cq0wFf",
          "width": 431
        },
        "dc": {
          "extension": "jpg",
          "height": 600,
          "mimetype": "image/jpeg",
          "secret": "H28e6QPmiSwdpZpnAgh7CR87B1cq0wFf",
          "width": 431
        },
        "ds": {
          "extension": "jpg",
          "height": 320,
          "mimetype": "image/jpeg",
          "secret": "H28e6QPmiSwdpZpnAgh7CR87B1cq0wFf",
          "width": 320
        },
        "k": {
          "extension": "jpg",
          "height": 1536,
          "mimetype": "image/jpeg",
          "secret": "H28e6QPmiSwdpZpnAgh7CR87B1cq0wFf",
          "width": 1105
        },
        "n": {
          "extension": "jpg",
          "height": 240,
          "mimetype": "image/jpeg",
          "secret": "H28e6QPmiSwdpZpnAgh7CR87B1cq0wFf",
          "width": 172
        },
        "o": {
          "extension": "jpg",
          "height": 2110,
          "mimetype": "image/jpeg",
          "secret": "8TN8KfexqAi703MUQCBQx0kiPlDoQdj7",
          "width": 1518
        },
        "s": {
          "extension": "jpg",
          "height": 320,
          "mimetype": "image/jpeg",
          "secret": "H28e6QPmiSwdpZpnAgh7CR87B1cq0wFf",
          "width": 320
        },
        "z": {
          "extension": "jpg",
          "height": 480,
          "mimetype": "image/jpeg",
          "secret": "H28e6QPmiSwdpZpnAgh7CR87B1cq0wFf",
          "width": 345
        }
      }
    },
    "media:uri_template": "https://static.sfomuseum.org/media/152/784/811/5/1527848115_{secret}_{label}.{extention}",
    "sfomuseum:filename": "2002113418_front.tif",
    "sfomuseum:image_index": 5,
    "sfomuseum:image_type": "studio",
    "sfomuseum:placetype": "image",
    "sfomuseum:primary_image": 1,
    "wof:depicts": [
      1159285393,
      1511925189
    ],
    "wof:name": "menu: TWA (Trans World Airlines)",
    "wof:placetype": "custom",
    "wof:placetype_alt": "image"
  },
  "geometry": {"coordinates":[-122.386155,37.616358],"type":"Point"}
}
