{
  "type": "Feature",
  "properties": {
    "iso:country": "XX",
    "media:fingerprint": "7af63820d30b4362ac066d4db385eb01b63bffef",
    "media:imagehash_avg": "a:3f3f3f3f01010303",
    "media:imagehash_diff": "d:f0f9f8df73e7e7f7",
    "media:medium": "image",
    "media:mimetype": "image/tiff",
    "media:properties": {
      "colours": [
        {
          "hex": "#cfe3bd",
          "name": "#cfe3bd",
          "reference": "vibrant"
        }, 
        {
          "hex": "#929d64",
          "name": "#929d64",
          "reference": "vibrant"
        }, 
        {
          "hex": "#b2d9b1",
          "name": "#b2d9b1",
          "reference": "vibrant"
        }, 
        {
          "hex": "#5a5735",
          "name": "#5a5735",
          "reference": "vibrant"
        }
      ],
      "sizes": {
        "b": {
          "extension": "jpg",
          "height": 661,
          "mimetype": "image/jpeg",
          "secret": "5u0eKIusfSZN3mMvQptr6CwlgLCyTYId",
          "width": 1024
        },
        "c": {
          "extension": "jpg",
          "height": 516,
          "mimetype": "image/jpeg",
          "secret": "5u0eKIusfSZN3mMvQptr6CwlgLCyTYId",
          "width": 800
        },
        "dc": {
          "extension": "jpg",
          "height": 516,
          "mimetype": "image/jpeg",
          "secret": "5u0eKIusfSZN3mMvQptr6CwlgLCyTYId",
          "width": 800
        },
        "ds": {
          "extension": "jpg",
          "height": 320,
          "mimetype": "image/jpeg",
          "secret": "5u0eKIusfSZN3mMvQptr6CwlgLCyTYId",
          "width": 320
        },
        "k": {
          "extension": "jpg",
          "height": 1322,
          "mimetype": "image/jpeg",
          "secret": "5u0eKIusfSZN3mMvQptr6CwlgLCyTYId",
          "width": 2048
        },
        "n": {
          "extension": "jpg",
          "height": 206,
          "mimetype": "image/jpeg",
          "secret": "5u0eKIusfSZN3mMvQptr6CwlgLCyTYId",
          "width": 320
        },
        "o": {
          "extension": "jpg",
          "height": 1078,
          "mimetype": "image/jpeg",
          "secret": "mbS9NuJnyFxd7TOl8v7QOhJptzoqetHa",
          "width": 1669
        },
        "s": {
          "extension": "jpg",
          "height": 320,
          "mimetype": "image/jpeg",
          "secret": "5u0eKIusfSZN3mMvQptr6CwlgLCyTYId",
          "width": 320
        },
        "z": {
          "extension": "jpg",
          "height": 413,
          "mimetype": "image/jpeg",
          "secret": "5u0eKIusfSZN3mMvQptr6CwlgLCyTYId",
          "width": 640
        }
      }
    },
    "media:uri_template": "https://millsfield.sfomuseum.org/media/152/782/759/1/1527827591_{secret}_{label}.{extention}",
    "sfomuseum:filename": "44155.tif",
    "sfomuseum:image_index": 5,
    "sfomuseum:placetype": "image",
    "sfomuseum:primary_image": 1,
    "wof:depicts": [
      1511948625
    ],
    "wof:name": "negative: San Francisco International Airport (SFO), terminal interior",
    "wof:placetype": "media"
  },
  "geometry": {"coordinates":[-122.386155,37.616358],"type":"Point"}
}
