{
  "type": "Feature",
  "properties": {
    "iso:country": "XX",
    "media:fingerprint": "d2acf06bff7e6b4f6a85fd52999a7c32dc7725f6",
    "media:medium": "image",
    "media:properties": {
      "colours": [
        {
          "hex": "#f2e8d4",
          "name": "#f2e8d4",
          "reference": "vibrant"
        },
        {
          "hex": "#858274",
          "name": "#858274",
          "reference": "vibrant"
        },
        {
          "hex": "#c4c0b2",
          "name": "#c4c0b2",
          "reference": "vibrant"
        },
        {
          "hex": "#444239",
          "name": "#444239",
          "reference": "vibrant"
        }
      ],
      "sizes": {
        "b": {
          "extension": "jpg",
          "height": 652,
          "mimetype": "image/jpeg",
          "secret": "WDEsgFHYEDUOKzOAi80sZVJ9v2yOsEOi",
          "width": 1023
        },
        "c": {
          "extension": "jpg",
          "height": 509,
          "mimetype": "image/jpeg",
          "secret": "WDEsgFHYEDUOKzOAi80sZVJ9v2yOsEOi",
          "width": 800
        },
        "dc": {
          "extension": "jpg",
          "height": 509,
          "mimetype": "image/jpeg",
          "secret": "WDEsgFHYEDUOKzOAi80sZVJ9v2yOsEOi",
          "width": 800
        },
        "ds": {
          "extension": "jpg",
          "height": 320,
          "mimetype": "image/jpeg",
          "secret": "WDEsgFHYEDUOKzOAi80sZVJ9v2yOsEOi",
          "width": 320
        },
        "k": {
          "extension": "jpg",
          "height": 1304,
          "mimetype": "image/jpeg",
          "secret": "WDEsgFHYEDUOKzOAi80sZVJ9v2yOsEOi",
          "width": 2047
        },
        "n": {
          "extension": "jpg",
          "height": 203,
          "mimetype": "image/jpeg",
          "secret": "WDEsgFHYEDUOKzOAi80sZVJ9v2yOsEOi",
          "width": 320
        },
        "o": {
          "extension": "jpg",
          "height": 1068,
          "mimetype": "image/jpeg",
          "secret": "qHUBlMsOIO14wXiZBjnaygVum98zGAFO",
          "width": 1677
        },
        "s": {
          "extension": "jpg",
          "height": 320,
          "mimetype": "image/jpeg",
          "secret": "WDEsgFHYEDUOKzOAi80sZVJ9v2yOsEOi",
          "width": 320
        },
        "z": {
          "extension": "jpg",
          "height": 407,
          "mimetype": "image/jpeg",
          "secret": "WDEsgFHYEDUOKzOAi80sZVJ9v2yOsEOi",
          "width": 640
        }
      }
    },
    "media:uri_template": "https://static.sfomuseum.org/media/172/956/583/7/1729565837_{secret}_{label}.{extention}",
    "sfomuseum:filename": "2002.113.473_verso.tif",
    "sfomuseum:image_index": 5,
    "sfomuseum:image_type": "studio",
    "sfomuseum:placetype": "image",
    "sfomuseum:primary_image": 0,
    "wof:depicts": [
      1729564391,
      1159285393,
      1159289617
    ],
    "wof:name": "postcard: TWA (Trans World Airlines), Boeing 307 Stratoliner",
    "wof:placetype": "custom",
    "wof:placetype_alt": "image"
  },
  "geometry": {"coordinates":[-122.386155,37.616357],"type":"Point"}
}
