{
  "type": "Feature",
  "properties": {
    "iso:country": "XX",
    "media:fingerprint": "85cd68ad04ec02c8d4944ff73d7e852421b1f96b",
    "media:imagehash_avg": "a:fcfcfcfcf8800000",
    "media:imagehash_diff": "d:e0e0e0c0101000f0",
    "media:medium": "image",
    "media:mimetype": "image/tiff",
    "media:properties": {
      "colours": [
        {
          "hex": "#858585",
          "name": "#858585",
          "reference": "vibrant"
        }, 
        {
          "hex": "#c0c0c0",
          "name": "#c0c0c0",
          "reference": "vibrant"
        }, 
        {
          "hex": "#484848",
          "name": "#484848",
          "reference": "vibrant"
        }
      ],
      "sizes": {
        "b": {
          "extension": "jpg",
          "height": 700,
          "mimetype": "image/jpeg",
          "secret": "qDFZpZAmk8B6QaF8ZSkKmUBl1CG5xtEj",
          "width": 1024
        },
        "c": {
          "extension": "jpg",
          "height": 547,
          "mimetype": "image/jpeg",
          "secret": "qDFZpZAmk8B6QaF8ZSkKmUBl1CG5xtEj",
          "width": 800
        },
        "dc": {
          "extension": "jpg",
          "height": 547,
          "mimetype": "image/jpeg",
          "secret": "qDFZpZAmk8B6QaF8ZSkKmUBl1CG5xtEj",
          "width": 800
        },
        "ds": {
          "extension": "jpg",
          "height": 320,
          "mimetype": "image/jpeg",
          "secret": "qDFZpZAmk8B6QaF8ZSkKmUBl1CG5xtEj",
          "width": 320
        },
        "k": {
          "extension": "jpg",
          "height": 1400,
          "mimetype": "image/jpeg",
          "secret": "qDFZpZAmk8B6QaF8ZSkKmUBl1CG5xtEj",
          "width": 2048
        },
        "n": {
          "extension": "jpg",
          "height": 218,
          "mimetype": "image/jpeg",
          "secret": "qDFZpZAmk8B6QaF8ZSkKmUBl1CG5xtEj",
          "width": 320
        },
        "o": {
          "extension": "jpg",
          "height": 1063,
          "mimetype": "image/jpeg",
          "secret": "tDSY0ymeDKz4CmpJzTOSRXbARxImjovE",
          "width": 1554
        },
        "s": {
          "extension": "jpg",
          "height": 320,
          "mimetype": "image/jpeg",
          "secret": "qDFZpZAmk8B6QaF8ZSkKmUBl1CG5xtEj",
          "width": 320
        },
        "z": {
          "extension": "jpg",
          "height": 437,
          "mimetype": "image/jpeg",
          "secret": "qDFZpZAmk8B6QaF8ZSkKmUBl1CG5xtEj",
          "width": 640
        }
      }
    },
    "media:uri_template": "https://millsfield.sfomuseum.org/media/152/782/850/1/1527828501_{secret}_{label}.{extention}",
    "sfomuseum:filename": "44627.tif",
    "sfomuseum:image_index": 5,
    "sfomuseum:placetype": "image",
    "sfomuseum:primary_image": 1,
    "wof:depicts": [
      1511949533
    ],
    "wof:name": "negative: San Francisco International Airport (SFO), Central Terminal",
    "wof:placetype": "media"
  },
  "geometry": {"coordinates":[-122.386155,37.616358],"type":"Point"}
}
