{
  "type": "Feature",
  "properties": {
    "date:cessation_lower": "1912-01-01",
    "date:cessation_upper": "1912-12-31",
    "date:inception_lower": "1912-01-01",
    "date:inception_upper": "1912-12-31",
    "iso:country": "XX",
    "media:imagehash_avg": "a:ff3f000060391181",
    "media:imagehash_diff": "d:a4793f33c3632721",
    "media:imagetext": "THE BIRD BOYS\nOr the\nYoung\nSky Pilots\nFirst\nAir Voyage\nJOHN LUTHER LANGWORTHY",
    "media:imagetext_created": 1701940814,
    "media:mimetype": "image/jpeg",
    "media:properties": {
    },
    "media:uri_template": "https://static.sfomuseum.org/media/174/668/037/1/1746680371_{secret}_{label}.{extention}",
    "millsfield:exhibition_ids": [
      1159160363
    ],
    "millsfield:images_texts": [
      "THE BIRD BOYS\nOr the\nYoung\nSky Pilots\nFirst\nAir Voyage\nJOHN LUTHER LANGWORTHY"
    ],
    "millsfield:images_texts_ids": [
      1746680371
    ],
    "millsfield:on_view": 0,
    "sfomuseum:filename": "57520.jpg",
    "sfomuseum:image_index": 0,
    "sfomuseum:image_type": "studio",
    "sfomuseum:placetype": "image",
    "sfomuseum:primary_image": 1,
    "wof:depicts": [
      1511951865
    ],
    "wof:name": "The bird boys, or, The young sky pilot's first air voyage",
    "wof:placetype": "custom"
  },
  "geometry": {"coordinates":[-122.386155,37.616357],"type":"Point"}
}
