{
  "type": "Feature",
  "properties": {
    "iso:country": "XX",
    "media:fingerprint": "3242ed3d3702be9602d77a3e62f36c30a27baf0b",
    "media:imagehash_avg": "a:0f0f07c33b0f0303",
    "media:imagehash_diff": "d:b9dd2f07e379e7df",
    "media:medium": "image",
    "media:mimetype": "image/tiff",
    "media:properties": {
      "colours": [
        {
          "hex": "#808080",
          "name": "#808080",
          "reference": "vibrant"
        }, 
        {
          "hex": "#b8b8b8",
          "name": "#b8b8b8",
          "reference": "vibrant"
        }, 
        {
          "hex": "#404040",
          "name": "#404040",
          "reference": "vibrant"
        }
      ],
      "sizes": {
        "b": {
          "extension": "jpg",
          "height": 768,
          "mimetype": "image/jpeg",
          "secret": "gergrJqCvsuMhfgtmdYBzk2p23TtIQCJ",
          "width": 759
        },
        "c": {
          "extension": "jpg",
          "height": 600,
          "mimetype": "image/jpeg",
          "secret": "gergrJqCvsuMhfgtmdYBzk2p23TtIQCJ",
          "width": 593
        },
        "dc": {
          "extension": "jpg",
          "height": 600,
          "mimetype": "image/jpeg",
          "secret": "gergrJqCvsuMhfgtmdYBzk2p23TtIQCJ",
          "width": 593
        },
        "ds": {
          "extension": "jpg",
          "height": 320,
          "mimetype": "image/jpeg",
          "secret": "gergrJqCvsuMhfgtmdYBzk2p23TtIQCJ",
          "width": 320
        },
        "k": {
          "extension": "jpg",
          "height": 1536,
          "mimetype": "image/jpeg",
          "secret": "gergrJqCvsuMhfgtmdYBzk2p23TtIQCJ",
          "width": 1519
        },
        "n": {
          "extension": "jpg",
          "height": 240,
          "mimetype": "image/jpeg",
          "secret": "gergrJqCvsuMhfgtmdYBzk2p23TtIQCJ",
          "width": 237
        },
        "o": {
          "extension": "jpg",
          "height": 2590,
          "mimetype": "image/jpeg",
          "secret": "IgBxzwkCir6d0lkXOMOEDSkWanHaHZfx",
          "width": 2563
        },
        "s": {
          "extension": "jpg",
          "height": 320,
          "mimetype": "image/jpeg",
          "secret": "gergrJqCvsuMhfgtmdYBzk2p23TtIQCJ",
          "width": 320
        },
        "z": {
          "extension": "jpg",
          "height": 480,
          "mimetype": "image/jpeg",
          "secret": "gergrJqCvsuMhfgtmdYBzk2p23TtIQCJ",
          "width": 474
        }
      }
    },
    "media:uri_template": "https://millsfield.sfomuseum.org/media/152/782/568/3/1527825683_{secret}_{label}.{extention}",
    "sfomuseum:filename": "43264.tif",
    "sfomuseum:image_index": 5,
    "sfomuseum:placetype": "image",
    "sfomuseum:primary_image": 1,
    "wof:depicts": [
      1511946719
    ],
    "wof:name": "negative: San Francisco International Airport (SFO), building exterior",
    "wof:placetype": "media"
  },
  "geometry": {"coordinates":[-122.386155,37.616358],"type":"Point"}
}
