{
  "type": "Feature",
  "properties": {
    "iso:country": "XX",
    "media:fingerprint": "adc8c01bf6bf5176c8c081dbec8a27cb0cec14ce",
    "media:imagehash_avg": "a:807e664042667e00",
    "media:imagehash_diff": "d:20cccc8a8ecccc40",
    "media:medium": "image",
    "media:mimetype": "image/tiff",
    "media:properties": {
      "colours": [
        {
          "hex": "#989d18",
          "name": "#989d18",
          "reference": "vibrant"
        },
        {
          "hex": "#ebe5cb",
          "name": "#ebe5cb",
          "reference": "vibrant"
        },
        {
          "hex": "#7f5d16",
          "name": "#7f5d16",
          "reference": "vibrant"
        },
        {
          "hex": "#a7685e",
          "name": "#a7685e",
          "reference": "vibrant"
        },
        {
          "hex": "#98aaa2",
          "name": "#98aaa2",
          "reference": "vibrant"
        }
      ],
      "sizes": {
        "b": {
          "extension": "jpg",
          "height": 768,
          "mimetype": "image/jpeg",
          "secret": "WdSExiBMsGziqgfqs2ayeANjM7qgMqOq",
          "width": 552
        },
        "c": {
          "extension": "jpg",
          "height": 600,
          "mimetype": "image/jpeg",
          "secret": "WdSExiBMsGziqgfqs2ayeANjM7qgMqOq",
          "width": 431
        },
        "dc": {
          "extension": "jpg",
          "height": 600,
          "mimetype": "image/jpeg",
          "secret": "WdSExiBMsGziqgfqs2ayeANjM7qgMqOq",
          "width": 431
        },
        "ds": {
          "extension": "jpg",
          "height": 320,
          "mimetype": "image/jpeg",
          "secret": "WdSExiBMsGziqgfqs2ayeANjM7qgMqOq",
          "width": 320
        },
        "k": {
          "extension": "jpg",
          "height": 1536,
          "mimetype": "image/jpeg",
          "secret": "WdSExiBMsGziqgfqs2ayeANjM7qgMqOq",
          "width": 1105
        },
        "n": {
          "extension": "jpg",
          "height": 240,
          "mimetype": "image/jpeg",
          "secret": "WdSExiBMsGziqgfqs2ayeANjM7qgMqOq",
          "width": 172
        },
        "o": {
          "extension": "jpg",
          "height": 2103,
          "mimetype": "image/jpeg",
          "secret": "syIQwlZgBNhc2FZTBw0O3hqrOKQDIXNJ",
          "width": 1514
        },
        "s": {
          "extension": "jpg",
          "height": 320,
          "mimetype": "image/jpeg",
          "secret": "WdSExiBMsGziqgfqs2ayeANjM7qgMqOq",
          "width": 320
        },
        "z": {
          "extension": "jpg",
          "height": 480,
          "mimetype": "image/jpeg",
          "secret": "WdSExiBMsGziqgfqs2ayeANjM7qgMqOq",
          "width": 345
        }
      }
    },
    "media:uri_template": "https://static.sfomuseum.org/media/152/784/811/9/1527848119_{secret}_{label}.{extention}",
    "sfomuseum:filename": "2002113419_front.tif",
    "sfomuseum:image_index": 5,
    "sfomuseum:image_type": "studio",
    "sfomuseum:placetype": "image",
    "sfomuseum:primary_image": 1,
    "wof:depicts": [
      1159287531,
      1511925191,
      1159285393
    ],
    "wof:name": "menu: TWA (Trans World Airlines)",
    "wof:placetype": "custom",
    "wof:placetype_alt": "image"
  },
  "geometry": {"coordinates":[-122.386155,37.616358],"type":"Point"}
}
