{
  "type": "Feature",
  "properties": {
    "iso:country": "XX",
    "media:fingerprint": "c765dbd31fb6b3587e7cc2f05d6e149838857338",
    "media:imagehash_avg": "a:017f7f7f2f2f3900",
    "media:imagehash_diff": "d:d5d5f5d1d9cde1e3",
    "media:medium": "image",
    "media:mimetype": "image/tiff",
    "media:properties": {
      "colours": [
        {
          "hex": "#f8e8d0",
          "name": "#f8e8d0",
          "reference": "vibrant"
        }, 
        {
          "hex": "#7b8081",
          "name": "#7b8081",
          "reference": "vibrant"
        }, 
        {
          "hex": "#c6c3b6",
          "name": "#c6c3b6",
          "reference": "vibrant"
        }, 
        {
          "hex": "#5b564f",
          "name": "#5b564f",
          "reference": "vibrant"
        }
      ],
      "sizes": {
        "b": {
          "extension": "jpg",
          "height": 768,
          "mimetype": "image/jpeg",
          "secret": "wIR1X0v6QINeobf6x8li2GZ2RGtIRfs7",
          "width": 377
        },
        "c": {
          "extension": "jpg",
          "height": 600,
          "mimetype": "image/jpeg",
          "secret": "wIR1X0v6QINeobf6x8li2GZ2RGtIRfs7",
          "width": 294
        },
        "dc": {
          "extension": "jpg",
          "height": 600,
          "mimetype": "image/jpeg",
          "secret": "wIR1X0v6QINeobf6x8li2GZ2RGtIRfs7",
          "width": 294
        },
        "ds": {
          "extension": "jpg",
          "height": 320,
          "mimetype": "image/jpeg",
          "secret": "wIR1X0v6QINeobf6x8li2GZ2RGtIRfs7",
          "width": 320
        },
        "k": {
          "extension": "jpg",
          "height": 1536,
          "mimetype": "image/jpeg",
          "secret": "wIR1X0v6QINeobf6x8li2GZ2RGtIRfs7",
          "width": 754
        },
        "n": {
          "extension": "jpg",
          "height": 239,
          "mimetype": "image/jpeg",
          "secret": "wIR1X0v6QINeobf6x8li2GZ2RGtIRfs7",
          "width": 117
        },
        "o": {
          "extension": "jpg",
          "height": 3126,
          "mimetype": "image/jpeg",
          "secret": "pjxUCn3ztCP1Myb1WXmdu9qVXZjV9U19",
          "width": 1535
        },
        "s": {
          "extension": "jpg",
          "height": 320,
          "mimetype": "image/jpeg",
          "secret": "wIR1X0v6QINeobf6x8li2GZ2RGtIRfs7",
          "width": 320
        },
        "z": {
          "extension": "jpg",
          "height": 479,
          "mimetype": "image/jpeg",
          "secret": "wIR1X0v6QINeobf6x8li2GZ2RGtIRfs7",
          "width": 235
        }
      }
    },
    "media:uri_template": "https://millsfield.sfomuseum.org/media/152/782/378/5/1527823785_{secret}_{label}.{extention}",
    "sfomuseum:filename": "41788.tif",
    "sfomuseum:image_index": 5,
    "sfomuseum:placetype": "image",
    "sfomuseum:primary_image": 0,
    "wof:depicts": [
      1511908511
    ],
    "wof:name": "airsickness bag: Cathay Pacific Airways",
    "wof:placetype": "media"
  },
  "geometry": {"coordinates":[-122.386155,37.616358],"type":"Point"}
}
