{
  "type": "Feature",
  "properties": {
    "iso:country": "XX",
    "media:fingerprint": "23322b3175c29cd3f39154a6fec411f79eac7715",
    "media:imagehash_avg": "a:097f7f81ffff0000",
    "media:imagehash_diff": "d:79c4ff3b27790131",
    "media:medium": "image",
    "media:mimetype": "image/tiff",
    "media:properties": {
      "colours": [
        {
          "hex": "#c24439",
          "name": "#c24439",
          "reference": "vibrant"
        }, 
        {
          "hex": "#c86c65",
          "name": "#c86c65",
          "reference": "vibrant"
        }, 
        {
          "hex": "#987e66",
          "name": "#987e66",
          "reference": "vibrant"
        }, 
        {
          "hex": "#c9c0a7",
          "name": "#c9c0a7",
          "reference": "vibrant"
        }, 
        {
          "hex": "#404354",
          "name": "#404354",
          "reference": "vibrant"
        }
      ],
      "sizes": {
        "b": {
          "extension": "jpg",
          "height": 768,
          "mimetype": "image/jpeg",
          "secret": "umFi8W6hCgfuaBPFNdQR0kOLScArzZNf",
          "width": 600
        },
        "c": {
          "extension": "jpg",
          "height": 600,
          "mimetype": "image/jpeg",
          "secret": "umFi8W6hCgfuaBPFNdQR0kOLScArzZNf",
          "width": 469
        },
        "dc": {
          "extension": "jpg",
          "height": 600,
          "mimetype": "image/jpeg",
          "secret": "umFi8W6hCgfuaBPFNdQR0kOLScArzZNf",
          "width": 469
        },
        "ds": {
          "extension": "jpg",
          "height": 320,
          "mimetype": "image/jpeg",
          "secret": "umFi8W6hCgfuaBPFNdQR0kOLScArzZNf",
          "width": 320
        },
        "k": {
          "extension": "jpg",
          "height": 1536,
          "mimetype": "image/jpeg",
          "secret": "umFi8W6hCgfuaBPFNdQR0kOLScArzZNf",
          "width": 1200
        },
        "n": {
          "extension": "jpg",
          "height": 240,
          "mimetype": "image/jpeg",
          "secret": "umFi8W6hCgfuaBPFNdQR0kOLScArzZNf",
          "width": 187
        },
        "o": {
          "extension": "jpg",
          "height": 2808,
          "mimetype": "image/jpeg",
          "secret": "r8QVGfqZcfKbFgPGKYJuFEwptnRV3VGy",
          "width": 2195
        },
        "s": {
          "extension": "jpg",
          "height": 320,
          "mimetype": "image/jpeg",
          "secret": "umFi8W6hCgfuaBPFNdQR0kOLScArzZNf",
          "width": 320
        },
        "z": {
          "extension": "jpg",
          "height": 480,
          "mimetype": "image/jpeg",
          "secret": "umFi8W6hCgfuaBPFNdQR0kOLScArzZNf",
          "width": 375
        }
      }
    },
    "media:uri_template": "https://millsfield.sfomuseum.org/media/152/782/033/1/1527820331_{secret}_{label}.{extention}",
    "sfomuseum:filename": "31524.tif",
    "sfomuseum:image_index": 5,
    "sfomuseum:placetype": "image",
    "sfomuseum:primary_image": 0,
    "wof:depicts": [
      1511920137
    ],
    "wof:name": "flight information packet: United Air Lines, Douglas DC-4, Lockheed L-049 Constellation",
    "wof:placetype": "media"
  },
  "geometry": {"coordinates":[-122.386155,37.616358],"type":"Point"}
}
