{
  "type": "Feature",
  "properties": {
    "media:fingerprint": "d6c5ee7b0ba100c61799901cc4d6b0faeebf5084",
    "media:imagehash_avg": "a:3f3f1b4f47011f1f",
    "media:imagehash_diff": "d:f8f2d2968f8ffefc",
    "media:mimetype": "image/tiff",
    "media:properties": {
      "colours": [
        {
          "hex": "#d51e07",
          "name": "#d51e07",
          "reference": "vibrant"
        },
        {
          "hex": "#d97158",
          "name": "#d97158",
          "reference": "vibrant"
        },
        {
          "hex": "#262aa6",
          "name": "#262aa6",
          "reference": "vibrant"
        },
        {
          "hex": "#847c77",
          "name": "#847c77",
          "reference": "vibrant"
        },
        {
          "hex": "#c6bfb9",
          "name": "#c6bfb9",
          "reference": "vibrant"
        }
      ],
      "sizes": {
        "b": {
          "extension": "jpg",
          "height": 682,
          "mimetype": "image/jpeg",
          "secret": "F7FoPRv1k5b09gNx7epF9f59OG1TlPS9",
          "width": 1024
        },
        "c": {
          "extension": "jpg",
          "height": 533,
          "mimetype": "image/jpeg",
          "secret": "F7FoPRv1k5b09gNx7epF9f59OG1TlPS9",
          "width": 800
        },
        "dc": {
          "extension": "jpg",
          "height": 533,
          "mimetype": "image/jpeg",
          "secret": "F7FoPRv1k5b09gNx7epF9f59OG1TlPS9",
          "width": 800
        },
        "ds": {
          "extension": "jpg",
          "height": 320,
          "mimetype": "image/jpeg",
          "secret": "F7FoPRv1k5b09gNx7epF9f59OG1TlPS9",
          "width": 320
        },
        "k": {
          "extension": "jpg",
          "height": 1365,
          "mimetype": "image/jpeg",
          "secret": "F7FoPRv1k5b09gNx7epF9f59OG1TlPS9",
          "width": 2048
        },
        "n": {
          "extension": "jpg",
          "height": 213,
          "mimetype": "image/jpeg",
          "secret": "F7FoPRv1k5b09gNx7epF9f59OG1TlPS9",
          "width": 320
        },
        "o": {
          "extension": "jpg",
          "height": 2400,
          "mimetype": "image/jpeg",
          "secret": "eFZfV78ZMY0OBWJlFV7hMB0t9ZEsadmB",
          "width": 3600
        },
        "s": {
          "extension": "jpg",
          "height": 320,
          "mimetype": "image/jpeg",
          "secret": "F7FoPRv1k5b09gNx7epF9f59OG1TlPS9",
          "width": 320
        },
        "z": {
          "extension": "jpg",
          "height": 426,
          "mimetype": "image/jpeg",
          "secret": "F7FoPRv1k5b09gNx7epF9f59OG1TlPS9",
          "width": 640
        }
      }
    },
    "media:uri_template": "https://static.sfomuseum.org/media/174/668/080/3/1746680803_{secret}_{label}.{extention}",
    "sfomuseum:filename": "2003.096.005 003.tif",
    "sfomuseum:image_index": 1,
    "sfomuseum:image_type": "curator",
    "sfomuseum:placetype": "image",
    "sfomuseum:primary_image": 1,
    "wof:depicts": [
      1511924699,
      1159289915
    ],
    "wof:name": "model airplane: Boeing 747-400",
    "wof:placetype": "custom"
  },
  "geometry": {"coordinates":[-122.386155,37.616357],"type":"Point"}
}
