{
  "type": "Feature",
  "properties": {
    "iso:country": "XX",
    "media:fingerprint": "b50253ae46346793697c863e932af3ba0f7a2031",
    "media:imagehash_avg": "a:f8f8f8f8f0800000",
    "media:imagehash_diff": "d:d292a0a0220207c7",
    "media:medium": "image",
    "media:mimetype": "image/tiff",
    "media:properties": {
      "colours": [
        {
          "hex": "#858585",
          "name": "#858585",
          "reference": "vibrant"
        }, 
        {
          "hex": "#c0c0c0",
          "name": "#c0c0c0",
          "reference": "vibrant"
        }, 
        {
          "hex": "#464646",
          "name": "#464646",
          "reference": "vibrant"
        }
      ],
      "sizes": {
        "b": {
          "extension": "jpg",
          "height": 768,
          "mimetype": "image/jpeg",
          "secret": "rJ65mZzYeZ5jCUqn9sO3RNKG1nGBlo1O",
          "width": 776
        },
        "c": {
          "extension": "jpg",
          "height": 600,
          "mimetype": "image/jpeg",
          "secret": "rJ65mZzYeZ5jCUqn9sO3RNKG1nGBlo1O",
          "width": 606
        },
        "dc": {
          "extension": "jpg",
          "height": 600,
          "mimetype": "image/jpeg",
          "secret": "rJ65mZzYeZ5jCUqn9sO3RNKG1nGBlo1O",
          "width": 606
        },
        "ds": {
          "extension": "jpg",
          "height": 320,
          "mimetype": "image/jpeg",
          "secret": "rJ65mZzYeZ5jCUqn9sO3RNKG1nGBlo1O",
          "width": 320
        },
        "k": {
          "extension": "jpg",
          "height": 1536,
          "mimetype": "image/jpeg",
          "secret": "rJ65mZzYeZ5jCUqn9sO3RNKG1nGBlo1O",
          "width": 1552
        },
        "n": {
          "extension": "jpg",
          "height": 240,
          "mimetype": "image/jpeg",
          "secret": "rJ65mZzYeZ5jCUqn9sO3RNKG1nGBlo1O",
          "width": 242
        },
        "o": {
          "extension": "jpg",
          "height": 2536,
          "mimetype": "image/jpeg",
          "secret": "qKDn1BSA1ZOGJHzLf6yWhIeEXSB0ENJ7",
          "width": 2563
        },
        "s": {
          "extension": "jpg",
          "height": 320,
          "mimetype": "image/jpeg",
          "secret": "rJ65mZzYeZ5jCUqn9sO3RNKG1nGBlo1O",
          "width": 320
        },
        "z": {
          "extension": "jpg",
          "height": 480,
          "mimetype": "image/jpeg",
          "secret": "rJ65mZzYeZ5jCUqn9sO3RNKG1nGBlo1O",
          "width": 485
        }
      }
    },
    "media:uri_template": "https://millsfield.sfomuseum.org/media/152/782/632/5/1527826325_{secret}_{label}.{extention}",
    "sfomuseum:filename": "43590.tif",
    "sfomuseum:image_index": 5,
    "sfomuseum:placetype": "image",
    "sfomuseum:primary_image": 1,
    "wof:depicts": [
      1511947365
    ],
    "wof:name": "negative: San Francisco International Airport (SFO), parking garage construction",
    "wof:placetype": "media"
  },
  "geometry": {"coordinates":[-122.386155,37.616358],"type":"Point"}
}
