{
  "type": "Feature",
  "properties": {
    "iso:country": "XX",
    "media:fingerprint": "075c3f9b47ad34f6463d23ca6444a1beb150668f",
    "media:imagehash_avg": "a:fffffffffffd0000",
    "media:imagehash_diff": "d:35353525216d6d3f",
    "media:medium": "image",
    "media:mimetype": "image/tiff",
    "media:properties": {
      "colours": [
        {
          "hex": "#564828",
          "name": "#564828",
          "reference": "vibrant"
        },
        {
          "hex": "#888573",
          "name": "#888573",
          "reference": "vibrant"
        },
        {
          "hex": "#d1c8ac",
          "name": "#d1c8ac",
          "reference": "vibrant"
        },
        {
          "hex": "#505142",
          "name": "#505142",
          "reference": "vibrant"
        }
      ],
      "sizes": {
        "b": {
          "extension": "jpg",
          "height": 610,
          "mimetype": "image/jpeg",
          "secret": "0jD0v8s4zXdDv3S9XAJBt5YUsUzsHULu",
          "width": 1024
        },
        "c": {
          "extension": "jpg",
          "height": 476,
          "mimetype": "image/jpeg",
          "secret": "0jD0v8s4zXdDv3S9XAJBt5YUsUzsHULu",
          "width": 800
        },
        "dc": {
          "extension": "jpg",
          "height": 476,
          "mimetype": "image/jpeg",
          "secret": "0jD0v8s4zXdDv3S9XAJBt5YUsUzsHULu",
          "width": 800
        },
        "ds": {
          "extension": "jpg",
          "height": 320,
          "mimetype": "image/jpeg",
          "secret": "0jD0v8s4zXdDv3S9XAJBt5YUsUzsHULu",
          "width": 320
        },
        "k": {
          "extension": "jpg",
          "height": 1220,
          "mimetype": "image/jpeg",
          "secret": "0jD0v8s4zXdDv3S9XAJBt5YUsUzsHULu",
          "width": 2048
        },
        "n": {
          "extension": "jpg",
          "height": 190,
          "mimetype": "image/jpeg",
          "secret": "0jD0v8s4zXdDv3S9XAJBt5YUsUzsHULu",
          "width": 320
        },
        "o": {
          "extension": "jpg",
          "height": 1968,
          "mimetype": "image/jpeg",
          "secret": "7ZgEgtO0wmX7LVsvbX3N7FNdS09CJWuX",
          "width": 3301
        },
        "s": {
          "extension": "jpg",
          "height": 320,
          "mimetype": "image/jpeg",
          "secret": "0jD0v8s4zXdDv3S9XAJBt5YUsUzsHULu",
          "width": 320
        },
        "z": {
          "extension": "jpg",
          "height": 381,
          "mimetype": "image/jpeg",
          "secret": "0jD0v8s4zXdDv3S9XAJBt5YUsUzsHULu",
          "width": 640
        }
      }
    },
    "media:uri_template": "https://static.sfomuseum.org/media/152/785/599/5/1527855995_{secret}_{label}.{extention}",
    "sfomuseum:filename": "100543.tif",
    "sfomuseum:image_index": 5,
    "sfomuseum:image_type": "studio",
    "sfomuseum:placetype": "image",
    "sfomuseum:primary_image": 1,
    "wof:depicts": [
      1159294035,
      1511942857,
      1159293227
    ],
    "wof:name": "photograph: Wright Model B, 1911 Aviation Meet, Tanforan",
    "wof:placetype": "custom",
    "wof:placetype_alt": "image"
  },
  "geometry": {"coordinates":[-122.386155,37.616358],"type":"Point"}
}
