{
  "type": "Feature",
  "properties": {
    "iso:country":"XX",
    "media:medium":"image",
    "sfomuseum:filename":"2013.057.027.tif",
    "sfomuseum:image_index":5,
    "sfomuseum:placetype":"image",
    "sfomuseum:primary_image":1,
    "wof:depicts":[
        1511955979
    ],
    "wof:name":"employee identification card: TWA (Trans World Airlines), Audrey McNamara Nevis",
    "wof:placetype":"media"
},
  "geometry": {"coordinates":[-122.386155,37.616358],"type":"Point"}
}