{
  "type": "Feature",
  "properties": {
    "iso:country": "XX",
    "media:fingerprint": "c6aa4cbe2238b56355cdf6a221aa3d8bbc9ecfb3",
    "media:imagehash_avg": "a:00bf0f070f8dfdff",
    "media:imagehash_diff": "d:4471391b1b393958",
    "media:medium": "image",
    "media:mimetype": "image/tiff",
    "media:properties": {
      "colours": [
        {
          "hex": "#ac211a",
          "name": "#ac211a",
          "reference": "vibrant"
        },
        {
          "hex": "#a98458",
          "name": "#a98458",
          "reference": "vibrant"
        },
        {
          "hex": "#b8b4ad",
          "name": "#b8b4ad",
          "reference": "vibrant"
        },
        {
          "hex": "#474642",
          "name": "#474642",
          "reference": "vibrant"
        }
      ],
      "sizes": {
        "b": {
          "extension": "jpg",
          "height": 470,
          "mimetype": "image/jpeg",
          "secret": "o6rRYUMQlzWxA9n60eQpz5pKaQJdb71D",
          "width": 1024
        },
        "c": {
          "extension": "jpg",
          "height": 367,
          "mimetype": "image/jpeg",
          "secret": "o6rRYUMQlzWxA9n60eQpz5pKaQJdb71D",
          "width": 800
        },
        "dc": {
          "extension": "jpg",
          "height": 367,
          "mimetype": "image/jpeg",
          "secret": "o6rRYUMQlzWxA9n60eQpz5pKaQJdb71D",
          "width": 800
        },
        "ds": {
          "extension": "jpg",
          "height": 320,
          "mimetype": "image/jpeg",
          "secret": "o6rRYUMQlzWxA9n60eQpz5pKaQJdb71D",
          "width": 320
        },
        "k": {
          "extension": "jpg",
          "height": 940,
          "mimetype": "image/jpeg",
          "secret": "o6rRYUMQlzWxA9n60eQpz5pKaQJdb71D",
          "width": 2048
        },
        "n": {
          "extension": "jpg",
          "height": 146,
          "mimetype": "image/jpeg",
          "secret": "o6rRYUMQlzWxA9n60eQpz5pKaQJdb71D",
          "width": 320
        },
        "o": {
          "extension": "jpg",
          "height": 1180,
          "mimetype": "image/jpeg",
          "secret": "g0Cz4NZPd5teWIfch3rXNFwqpY9IPWAY",
          "width": 2570
        },
        "s": {
          "extension": "jpg",
          "height": 320,
          "mimetype": "image/jpeg",
          "secret": "o6rRYUMQlzWxA9n60eQpz5pKaQJdb71D",
          "width": 320
        },
        "z": {
          "extension": "jpg",
          "height": 293,
          "mimetype": "image/jpeg",
          "secret": "o6rRYUMQlzWxA9n60eQpz5pKaQJdb71D",
          "width": 640
        }
      }
    },
    "media:uri_template": "https://static.sfomuseum.org/media/152/785/047/5/1527850475_{secret}_{label}.{extention}",
    "sfomuseum:filename": "2003.105.097.017.tif",
    "sfomuseum:image_index": 5,
    "sfomuseum:image_type": "studio",
    "sfomuseum:placetype": "image",
    "sfomuseum:primary_image": 0,
    "wof:depicts": [
      1159285591,
      1511939639
    ],
    "wof:name": "timetable: Southwest Airlines",
    "wof:placetype": "custom",
    "wof:placetype_alt": "image"
  },
  "geometry": {"coordinates":[-122.386155,37.616358],"type":"Point"}
}
