{
  "type": "Feature",
  "properties": {
    "iso:country": "XX",
    "media:fingerprint": "b922a1d4a89fc8c9615e622068ee5b03b6719cbb",
    "media:imagehash_avg": "a:ffd181818181ffff",
    "media:imagehash_diff": "d:3327171b130f0f0f",
    "media:medium": "image",
    "media:mimetype": "image/tiff",
    "media:properties": {
      "colours": [
        {
          "hex": "#94865b",
          "name": "#94865b",
          "reference": "vibrant"
        },
        {
          "hex": "#ccc0ae",
          "name": "#ccc0ae",
          "reference": "vibrant"
        },
        {
          "hex": "#4e4a40",
          "name": "#4e4a40",
          "reference": "vibrant"
        }
      ],
      "sizes": {
        "b": {
          "extension": "jpg",
          "height": 768,
          "mimetype": "image/jpeg",
          "secret": "SuFd4NvX0yXrNFRcsI0l08FqF7ZwB3o9",
          "width": 491
        },
        "c": {
          "extension": "jpg",
          "height": 600,
          "mimetype": "image/jpeg",
          "secret": "SuFd4NvX0yXrNFRcsI0l08FqF7ZwB3o9",
          "width": 383
        },
        "dc": {
          "extension": "jpg",
          "height": 600,
          "mimetype": "image/jpeg",
          "secret": "SuFd4NvX0yXrNFRcsI0l08FqF7ZwB3o9",
          "width": 383
        },
        "ds": {
          "extension": "jpg",
          "height": 320,
          "mimetype": "image/jpeg",
          "secret": "SuFd4NvX0yXrNFRcsI0l08FqF7ZwB3o9",
          "width": 320
        },
        "k": {
          "extension": "jpg",
          "height": 1536,
          "mimetype": "image/jpeg",
          "secret": "SuFd4NvX0yXrNFRcsI0l08FqF7ZwB3o9",
          "width": 982
        },
        "n": {
          "extension": "jpg",
          "height": 240,
          "mimetype": "image/jpeg",
          "secret": "SuFd4NvX0yXrNFRcsI0l08FqF7ZwB3o9",
          "width": 153
        },
        "o": {
          "extension": "jpg",
          "height": 2097,
          "mimetype": "image/jpeg",
          "secret": "SRXa18WkuEo3PE3DMFpe7tplCFpiuP9B",
          "width": 1341
        },
        "s": {
          "extension": "jpg",
          "height": 320,
          "mimetype": "image/jpeg",
          "secret": "SuFd4NvX0yXrNFRcsI0l08FqF7ZwB3o9",
          "width": 320
        },
        "z": {
          "extension": "jpg",
          "height": 480,
          "mimetype": "image/jpeg",
          "secret": "SuFd4NvX0yXrNFRcsI0l08FqF7ZwB3o9",
          "width": 306
        }
      }
    },
    "media:uri_template": "https://static.sfomuseum.org/media/152/783/191/9/1527831919_{secret}_{label}.{extention}",
    "sfomuseum:filename": "60802.tif",
    "sfomuseum:image_index": 5,
    "sfomuseum:image_type": "studio",
    "sfomuseum:placetype": "image",
    "sfomuseum:primary_image": 1,
    "wof:depicts": [
      1511955941,
      1159287531,
      1159285393
    ],
    "wof:name": "photograph: TWA (Trans World Airlines)",
    "wof:placetype": "custom",
    "wof:placetype_alt": "image"
  },
  "geometry": {"coordinates":[-122.386155,37.616358],"type":"Point"}
}
