{
  "type": "Feature",
  "properties": {
    "iso:country": "US",
    "media:fingerprint": "dee825bf3ef81ac5f71a1e6f35700e39a68592dc",
    "media:imagehash_avg": "a:ffc381818181c3ff",
    "media:imagehash_diff": "d:0f0f1f13430f0f0f",
    "media:medium": "image",
    "media:mimetype": "image/tiff",
    "media:properties": {
      "colours": [
        {
          "hex": "#a8382d",
          "name": "#a8382d",
          "reference": "vibrant"
        }, 
        {
          "hex": "#d8c4a6",
          "name": "#d8c4a6",
          "reference": "vibrant"
        }, 
        {
          "hex": "#982718",
          "name": "#982718",
          "reference": "vibrant"
        }, 
        {
          "hex": "#be9781",
          "name": "#be9781",
          "reference": "vibrant"
        }, 
        {
          "hex": "#cfc6b7",
          "name": "#cfc6b7",
          "reference": "vibrant"
        }
      ],
      "sizes": {
        "b": {
          "extension": "jpg",
          "height": 768,
          "mimetype": "image/jpeg",
          "secret": "RHMxa3JehBJ4ildOpXLAqon5GeVnlCZu",
          "width": 771
        },
        "c": {
          "extension": "jpg",
          "height": 600,
          "mimetype": "image/jpeg",
          "secret": "RHMxa3JehBJ4ildOpXLAqon5GeVnlCZu",
          "width": 602
        },
        "dc": {
          "extension": "jpg",
          "height": 600,
          "mimetype": "image/jpeg",
          "secret": "RHMxa3JehBJ4ildOpXLAqon5GeVnlCZu",
          "width": 602
        },
        "ds": {
          "extension": "jpg",
          "height": 320,
          "mimetype": "image/jpeg",
          "secret": "RHMxa3JehBJ4ildOpXLAqon5GeVnlCZu",
          "width": 320
        },
        "k": {
          "extension": "jpg",
          "height": 1536,
          "mimetype": "image/jpeg",
          "secret": "RHMxa3JehBJ4ildOpXLAqon5GeVnlCZu",
          "width": 1542
        },
        "n": {
          "extension": "jpg",
          "height": 240,
          "mimetype": "image/jpeg",
          "secret": "RHMxa3JehBJ4ildOpXLAqon5GeVnlCZu",
          "width": 240
        },
        "o": {
          "extension": "jpg",
          "height": 1272,
          "mimetype": "image/jpeg",
          "secret": "4UVLGvniXIH1e9qtWlgykB463nlr1mxJ",
          "width": 1277
        },
        "s": {
          "extension": "jpg",
          "height": 320,
          "mimetype": "image/jpeg",
          "secret": "RHMxa3JehBJ4ildOpXLAqon5GeVnlCZu",
          "width": 320
        },
        "z": {
          "extension": "jpg",
          "height": 480,
          "mimetype": "image/jpeg",
          "secret": "RHMxa3JehBJ4ildOpXLAqon5GeVnlCZu",
          "width": 481
        }
      }
    },
    "media:uri_template": "https://millsfield.sfomuseum.org/media/152/781/821/9/1527818219_{secret}_{label}.{extention}",
    "sfomuseum:filename": "15869.tif",
    "sfomuseum:image_index": 5,
    "sfomuseum:placetype": "image",
    "sfomuseum:primary_image": 1,
    "wof:depicts": [
      1511909977
    ],
    "wof:name": "luggage label: Varney Speed Lines",
    "wof:placetype": "media"
  },
  "geometry": {"coordinates":[-122.386155,37.616358],"type":"Point"}
}
