{
  "type": "Feature",
  "properties": {
    "iso:country": "XX",
    "media:fingerprint": "40c80d12ad8149588e4a34628780e77c06f404f7",
    "media:imagehash_avg": "a:ff818181818381ff",
    "media:imagehash_diff": "d:5b1b7373370d3d45",
    "media:medium": "image",
    "media:mimetype": "image/jpeg",
    "media:properties": {
      "colours": [
        {
          "hex": "#91675d",
          "name": "#91675d",
          "reference": "vibrant"
        }, 
        {
          "hex": "#cabeab",
          "name": "#cabeab",
          "reference": "vibrant"
        }, 
        {
          "hex": "#463833",
          "name": "#463833",
          "reference": "vibrant"
        }
      ],
      "sizes": {
        "b": {
          "extension": "jpg",
          "height": 524,
          "mimetype": "image/jpeg",
          "secret": "05KZAPH0PSpUwIQSnS58I4io0WiH3KNB",
          "width": 1024
        },
        "c": {
          "extension": "jpg",
          "height": 409,
          "mimetype": "image/jpeg",
          "secret": "05KZAPH0PSpUwIQSnS58I4io0WiH3KNB",
          "width": 800
        },
        "dc": {
          "extension": "jpg",
          "height": 409,
          "mimetype": "image/jpeg",
          "secret": "05KZAPH0PSpUwIQSnS58I4io0WiH3KNB",
          "width": 800
        },
        "ds": {
          "extension": "jpg",
          "height": 320,
          "mimetype": "image/jpeg",
          "secret": "05KZAPH0PSpUwIQSnS58I4io0WiH3KNB",
          "width": 320
        },
        "k": {
          "extension": "jpg",
          "height": 1048,
          "mimetype": "image/jpeg",
          "secret": "05KZAPH0PSpUwIQSnS58I4io0WiH3KNB",
          "width": 2048
        },
        "n": {
          "extension": "jpg",
          "height": 163,
          "mimetype": "image/jpeg",
          "secret": "05KZAPH0PSpUwIQSnS58I4io0WiH3KNB",
          "width": 320
        },
        "o": {
          "extension": "jpg",
          "height": 714,
          "mimetype": "image/jpeg",
          "secret": "unbg5YVPQgpSFpCbRuqKlkuMpCor202U",
          "width": 1395
        },
        "s": {
          "extension": "jpg",
          "height": 320,
          "mimetype": "image/jpeg",
          "secret": "05KZAPH0PSpUwIQSnS58I4io0WiH3KNB",
          "width": 320
        },
        "z": {
          "extension": "jpg",
          "height": 327,
          "mimetype": "image/jpeg",
          "secret": "05KZAPH0PSpUwIQSnS58I4io0WiH3KNB",
          "width": 640
        }
      }
    },
    "media:uri_template": "https://millsfield.sfomuseum.org/media/152/781/946/1/1527819461_{secret}_{label}.{extention}",
    "sfomuseum:filename": "30797.jpg",
    "sfomuseum:image_index": 5,
    "sfomuseum:placetype": "image",
    "sfomuseum:primary_image": 1,
    "wof:depicts": [
      1511942095
    ],
    "wof:name": "admission ticket: Pan American Aeronautic Exposition, Aero Club of America",
    "wof:placetype": "media"
  },
  "geometry": {"coordinates":[-122.386155,37.616358],"type":"Point"}
}
