{
  "type": "Feature",
  "properties": {
    "iso:country": "XX",
    "media:fingerprint": "367dd1b5170b187961492cab181e9f36bb8472e1",
    "media:imagehash_avg": "a:ffffffff87030301",
    "media:imagehash_diff": "d:40081d983e767733",
    "media:medium": "image",
    "media:mimetype": "image/tiff",
    "media:properties": {
      "colours": [
        {
          "hex": "#808080",
          "name": "#808080",
          "reference": "vibrant"
        }, 
        {
          "hex": "#c0c0c0",
          "name": "#c0c0c0",
          "reference": "vibrant"
        }, 
        {
          "hex": "#464646",
          "name": "#464646",
          "reference": "vibrant"
        }
      ],
      "sizes": {
        "b": {
          "extension": "jpg",
          "height": 767,
          "mimetype": "image/jpeg",
          "secret": "1RzleSc2GZBjhvLm6XylSZpk7HlPdF4Z",
          "width": 601
        },
        "c": {
          "extension": "jpg",
          "height": 600,
          "mimetype": "image/jpeg",
          "secret": "1RzleSc2GZBjhvLm6XylSZpk7HlPdF4Z",
          "width": 469
        },
        "dc": {
          "extension": "jpg",
          "height": 600,
          "mimetype": "image/jpeg",
          "secret": "1RzleSc2GZBjhvLm6XylSZpk7HlPdF4Z",
          "width": 469
        },
        "ds": {
          "extension": "jpg",
          "height": 320,
          "mimetype": "image/jpeg",
          "secret": "1RzleSc2GZBjhvLm6XylSZpk7HlPdF4Z",
          "width": 320
        },
        "k": {
          "extension": "jpg",
          "height": 1535,
          "mimetype": "image/jpeg",
          "secret": "1RzleSc2GZBjhvLm6XylSZpk7HlPdF4Z",
          "width": 1203
        },
        "n": {
          "extension": "jpg",
          "height": 240,
          "mimetype": "image/jpeg",
          "secret": "1RzleSc2GZBjhvLm6XylSZpk7HlPdF4Z",
          "width": 187
        },
        "o": {
          "extension": "jpg",
          "height": 2768,
          "mimetype": "image/jpeg",
          "secret": "nglXc6ETy0DAbJUfsZe4WPhmSM73kEF7",
          "width": 2168
        },
        "s": {
          "extension": "jpg",
          "height": 320,
          "mimetype": "image/jpeg",
          "secret": "1RzleSc2GZBjhvLm6XylSZpk7HlPdF4Z",
          "width": 320
        },
        "z": {
          "extension": "jpg",
          "height": 480,
          "mimetype": "image/jpeg",
          "secret": "1RzleSc2GZBjhvLm6XylSZpk7HlPdF4Z",
          "width": 375
        }
      }
    },
    "media:uri_template": "https://millsfield.sfomuseum.org/media/152/782/768/9/1527827689_{secret}_{label}.{extention}",
    "sfomuseum:filename": "44199.tif",
    "sfomuseum:image_index": 5,
    "sfomuseum:placetype": "image",
    "sfomuseum:primary_image": 1,
    "wof:depicts": [
      1511948723
    ],
    "wof:name": "negative: San Francisco International Airport (SFO), Walter Wight",
    "wof:placetype": "media"
  },
  "geometry": {"coordinates":[-122.386155,37.616358],"type":"Point"}
}
