{
  "type": "Feature",
  "properties": {
    "iso:country": "XX",
    "media:fingerprint": "a85874df5fa0c737c16296db964a6f3d8af7d5c4",
    "media:imagehash_avg": "a:fffff8e080000001",
    "media:imagehash_diff": "d:79610105074f5f7f",
    "media:medium": "image",
    "media:mimetype": "image/tiff",
    "media:properties": {
      "colours": [
        {
          "hex": "#00002e",
          "name": "#00002e",
          "reference": "vibrant"
        },
        {
          "hex": "#676597",
          "name": "#676597",
          "reference": "vibrant"
        },
        {
          "hex": "#9f9cc4",
          "name": "#9f9cc4",
          "reference": "vibrant"
        },
        {
          "hex": "#383468",
          "name": "#383468",
          "reference": "vibrant"
        }
      ],
      "sizes": {
        "b": {
          "extension": "jpg",
          "height": 768,
          "mimetype": "image/jpeg",
          "secret": "RUMOteEJxcA7boIg5OdWpK3HUWc81TdT",
          "width": 406
        },
        "c": {
          "extension": "jpg",
          "height": 600,
          "mimetype": "image/jpeg",
          "secret": "RUMOteEJxcA7boIg5OdWpK3HUWc81TdT",
          "width": 317
        },
        "dc": {
          "extension": "jpg",
          "height": 600,
          "mimetype": "image/jpeg",
          "secret": "RUMOteEJxcA7boIg5OdWpK3HUWc81TdT",
          "width": 317
        },
        "ds": {
          "extension": "jpg",
          "height": 320,
          "mimetype": "image/jpeg",
          "secret": "RUMOteEJxcA7boIg5OdWpK3HUWc81TdT",
          "width": 320
        },
        "k": {
          "extension": "jpg",
          "height": 1536,
          "mimetype": "image/jpeg",
          "secret": "RUMOteEJxcA7boIg5OdWpK3HUWc81TdT",
          "width": 813
        },
        "n": {
          "extension": "jpg",
          "height": 240,
          "mimetype": "image/jpeg",
          "secret": "RUMOteEJxcA7boIg5OdWpK3HUWc81TdT",
          "width": 127
        },
        "o": {
          "extension": "jpg",
          "height": 2832,
          "mimetype": "image/jpeg",
          "secret": "izEwyP1WXrSyGC7zgavYJcuoG219cSHB",
          "width": 1499
        },
        "s": {
          "extension": "jpg",
          "height": 320,
          "mimetype": "image/jpeg",
          "secret": "RUMOteEJxcA7boIg5OdWpK3HUWc81TdT",
          "width": 320
        },
        "z": {
          "extension": "jpg",
          "height": 480,
          "mimetype": "image/jpeg",
          "secret": "RUMOteEJxcA7boIg5OdWpK3HUWc81TdT",
          "width": 254
        }
      }
    },
    "media:uri_template": "https://static.sfomuseum.org/media/152/784/243/7/1527842437_{secret}_{label}.{extention}",
    "sfomuseum:filename": "67589.tif",
    "sfomuseum:image_index": 5,
    "sfomuseum:image_type": "studio",
    "sfomuseum:placetype": "image",
    "sfomuseum:primary_image": 1,
    "wof:depicts": [
      1511927481,
      1159285163
    ],
    "wof:name": "airsickness bag: Singapore Airlines",
    "wof:placetype": "custom",
    "wof:placetype_alt": "image"
  },
  "geometry": {"coordinates":[-122.386155,37.616358],"type":"Point"}
}
