{
  "type": "Feature",
  "properties": {
    "iso:country": "XX",
    "media:fingerprint": "f534a6a745d34c0c0cd53e1e52299ab9fb0bb7d5",
    "media:imagehash_avg": "a:7e7e7e7e3e383818",
    "media:imagehash_diff": "d:d8f8f8f0f0f3f3f3",
    "media:medium": "image",
    "media:mimetype": "image/tiff",
    "media:properties": {
      "colours": [
        {
          "hex": "#c3bc7b",
          "name": "#c3bc7b",
          "reference": "vibrant"
        }, 
        {
          "hex": "#e5e0b1",
          "name": "#e5e0b1",
          "reference": "vibrant"
        }, 
        {
          "hex": "#999559",
          "name": "#999559",
          "reference": "vibrant"
        }, 
        {
          "hex": "#d4cd9e",
          "name": "#d4cd9e",
          "reference": "vibrant"
        }, 
        {
          "hex": "#5d5d37",
          "name": "#5d5d37",
          "reference": "vibrant"
        }
      ],
      "sizes": {
        "b": {
          "extension": "jpg",
          "height": 670,
          "mimetype": "image/jpeg",
          "secret": "k8JX9yHSv8idBlxS70g4FMmr0zc0j3nt",
          "width": 1024
        },
        "c": {
          "extension": "jpg",
          "height": 523,
          "mimetype": "image/jpeg",
          "secret": "k8JX9yHSv8idBlxS70g4FMmr0zc0j3nt",
          "width": 800
        },
        "dc": {
          "extension": "jpg",
          "height": 523,
          "mimetype": "image/jpeg",
          "secret": "k8JX9yHSv8idBlxS70g4FMmr0zc0j3nt",
          "width": 800
        },
        "ds": {
          "extension": "jpg",
          "height": 320,
          "mimetype": "image/jpeg",
          "secret": "k8JX9yHSv8idBlxS70g4FMmr0zc0j3nt",
          "width": 320
        },
        "k": {
          "extension": "jpg",
          "height": 1340,
          "mimetype": "image/jpeg",
          "secret": "k8JX9yHSv8idBlxS70g4FMmr0zc0j3nt",
          "width": 2048
        },
        "n": {
          "extension": "jpg",
          "height": 209,
          "mimetype": "image/jpeg",
          "secret": "k8JX9yHSv8idBlxS70g4FMmr0zc0j3nt",
          "width": 320
        },
        "o": {
          "extension": "jpg",
          "height": 1081,
          "mimetype": "image/jpeg",
          "secret": "G5siDkK8I93Frx54oJzGVDA9rAntmunZ",
          "width": 1652
        },
        "s": {
          "extension": "jpg",
          "height": 320,
          "mimetype": "image/jpeg",
          "secret": "k8JX9yHSv8idBlxS70g4FMmr0zc0j3nt",
          "width": 320
        },
        "z": {
          "extension": "jpg",
          "height": 418,
          "mimetype": "image/jpeg",
          "secret": "k8JX9yHSv8idBlxS70g4FMmr0zc0j3nt",
          "width": 640
        }
      }
    },
    "media:uri_template": "https://millsfield.sfomuseum.org/media/152/782/756/9/1527827569_{secret}_{label}.{extention}",
    "sfomuseum:filename": "44146.tif",
    "sfomuseum:image_index": 5,
    "sfomuseum:placetype": "image",
    "sfomuseum:primary_image": 1,
    "wof:depicts": [
      1511948605
    ],
    "wof:name": "negative: San Francisco International Airport (SFO)",
    "wof:placetype": "media"
  },
  "geometry": {"coordinates":[-122.386155,37.616358],"type":"Point"}
}
