{
  "type": "Feature",
  "properties": {
    "iso:country": "MM",
    "media:fingerprint": "9a43d120b482d67107d50a996c795d4b6379165b",
    "media:imagehash_avg": "a:f5e0e0f0fd7f7f0f",
    "media:imagehash_diff": "d:85c585a599d9de5b",
    "media:medium": "image",
    "media:mimetype": "image/tiff",
    "media:properties": {
      "colours": [
        {
          "hex": "#e52122",
          "name": "#e52122",
          "reference": "vibrant"
        }, 
        {
          "hex": "#97a0f1",
          "name": "#97a0f1",
          "reference": "vibrant"
        }, 
        {
          "hex": "#be1316",
          "name": "#be1316",
          "reference": "vibrant"
        }, 
        {
          "hex": "#5575b3",
          "name": "#5575b3",
          "reference": "vibrant"
        }, 
        {
          "hex": "#b9bea3",
          "name": "#b9bea3",
          "reference": "vibrant"
        }
      ],
      "sizes": {
        "b": {
          "extension": "jpg",
          "height": 588,
          "mimetype": "image/jpeg",
          "secret": "vK1JZzLHTDGCtvYuVUTVAMzUfeRay9n5",
          "width": 1024
        },
        "c": {
          "extension": "jpg",
          "height": 459,
          "mimetype": "image/jpeg",
          "secret": "vK1JZzLHTDGCtvYuVUTVAMzUfeRay9n5",
          "width": 800
        },
        "dc": {
          "extension": "jpg",
          "height": 459,
          "mimetype": "image/jpeg",
          "secret": "vK1JZzLHTDGCtvYuVUTVAMzUfeRay9n5",
          "width": 800
        },
        "ds": {
          "extension": "jpg",
          "height": 320,
          "mimetype": "image/jpeg",
          "secret": "vK1JZzLHTDGCtvYuVUTVAMzUfeRay9n5",
          "width": 320
        },
        "k": {
          "extension": "jpg",
          "height": 1176,
          "mimetype": "image/jpeg",
          "secret": "vK1JZzLHTDGCtvYuVUTVAMzUfeRay9n5",
          "width": 2048
        },
        "n": {
          "extension": "jpg",
          "height": 183,
          "mimetype": "image/jpeg",
          "secret": "vK1JZzLHTDGCtvYuVUTVAMzUfeRay9n5",
          "width": 320
        },
        "o": {
          "extension": "jpg",
          "height": 1158,
          "mimetype": "image/jpeg",
          "secret": "4UOQrEnmDl93z7XEVsXVUw2wp7Aia7N8",
          "width": 2016
        },
        "s": {
          "extension": "jpg",
          "height": 320,
          "mimetype": "image/jpeg",
          "secret": "vK1JZzLHTDGCtvYuVUTVAMzUfeRay9n5",
          "width": 320
        },
        "z": {
          "extension": "jpg",
          "height": 367,
          "mimetype": "image/jpeg",
          "secret": "vK1JZzLHTDGCtvYuVUTVAMzUfeRay9n5",
          "width": 640
        }
      }
    },
    "media:uri_template": "https://millsfield.sfomuseum.org/media/152/782/951/7/1527829517_{secret}_{label}.{extention}",
    "sfomuseum:filename": "48278.tif",
    "sfomuseum:image_index": 5,
    "sfomuseum:placetype": "image",
    "sfomuseum:primary_image": 1,
    "wof:depicts": [
      1511907015
    ],
    "wof:name": "airmail flight cover: Pan American World Airways, Rangoon - Tokyo route",
    "wof:placetype": "media"
  },
  "geometry": {"coordinates":[-122.386155,37.616358],"type":"Point"}
}
