{
  "type": "Feature",
  "properties": {
    "iso:country": "XX",
    "media:fingerprint": "6e70f58dcf8be7d83b91895b1f90d5633c1d10dc",
    "media:imagehash_avg": "a:fffe3e3c78100000",
    "media:imagehash_diff": "d:c0d0f8f0d0d0e080",
    "media:medium": "image",
    "media:mimetype": "image/tiff",
    "media:properties": {
      "colours": [
        {
          "hex": "#808080",
          "name": "#808080",
          "reference": "vibrant"
        },
        {
          "hex": "#c0c0c0",
          "name": "#c0c0c0",
          "reference": "vibrant"
        },
        {
          "hex": "#3a3a3a",
          "name": "#3a3a3a",
          "reference": "vibrant"
        }
      ],
      "sizes": {
        "b": {
          "extension": "jpg",
          "height": 768,
          "mimetype": "image/jpeg",
          "secret": "eqdl4PeFCeAE7MIYeBZvBySrHZ42LDjq",
          "width": 981
        },
        "c": {
          "extension": "jpg",
          "height": 600,
          "mimetype": "image/jpeg",
          "secret": "eqdl4PeFCeAE7MIYeBZvBySrHZ42LDjq",
          "width": 767
        },
        "dc": {
          "extension": "jpg",
          "height": 600,
          "mimetype": "image/jpeg",
          "secret": "eqdl4PeFCeAE7MIYeBZvBySrHZ42LDjq",
          "width": 767
        },
        "ds": {
          "extension": "jpg",
          "height": 320,
          "mimetype": "image/jpeg",
          "secret": "eqdl4PeFCeAE7MIYeBZvBySrHZ42LDjq",
          "width": 320
        },
        "k": {
          "extension": "jpg",
          "height": 1536,
          "mimetype": "image/jpeg",
          "secret": "eqdl4PeFCeAE7MIYeBZvBySrHZ42LDjq",
          "width": 1963
        },
        "n": {
          "extension": "jpg",
          "height": 240,
          "mimetype": "image/jpeg",
          "secret": "eqdl4PeFCeAE7MIYeBZvBySrHZ42LDjq",
          "width": 306
        },
        "o": {
          "extension": "jpg",
          "height": 2154,
          "mimetype": "image/jpeg",
          "secret": "NkSoNO9vwPz7H0KXwspDtg2MzmKUwtUx",
          "width": 2754
        },
        "s": {
          "extension": "jpg",
          "height": 320,
          "mimetype": "image/jpeg",
          "secret": "eqdl4PeFCeAE7MIYeBZvBySrHZ42LDjq",
          "width": 320
        },
        "z": {
          "extension": "jpg",
          "height": 480,
          "mimetype": "image/jpeg",
          "secret": "eqdl4PeFCeAE7MIYeBZvBySrHZ42LDjq",
          "width": 613
        }
      }
    },
    "media:uri_template": "https://static.sfomuseum.org/media/152/782/432/1/1527824321_{secret}_{label}.{extention}",
    "sfomuseum:filename": "42368.tif",
    "sfomuseum:image_index": 5,
    "sfomuseum:image_type": "studio",
    "sfomuseum:placetype": "image",
    "sfomuseum:primary_image": 1,
    "wof:depicts": [
      1511945643,
      102527513
    ],
    "wof:name": "negative: San Francisco International Airport (SFO), aerial",
    "wof:placetype": "custom",
    "wof:placetype_alt": "image"
  },
  "geometry": {"coordinates":[-122.386155,37.616358],"type":"Point"}
}
