{
  "type": "Feature",
  "properties": {
    "iso:country": "XX",
    "media:fingerprint": "7c5de9e489fa74bf73705a8f94828132731f9f93",
    "media:imagehash_avg": "a:c3f1e0f0f0e1e1f1",
    "media:imagehash_diff": "d:078707e585878783",
    "media:medium": "image",
    "media:mimetype": "image/tiff",
    "media:properties": {
      "colours": [
        {
          "hex": "#b43731",
          "name": "#b43731",
          "reference": "vibrant"
        }, 
        {
          "hex": "#cf8280",
          "name": "#cf8280",
          "reference": "vibrant"
        }, 
        {
          "hex": "#85362e",
          "name": "#85362e",
          "reference": "vibrant"
        }, 
        {
          "hex": "#ad5956",
          "name": "#ad5956",
          "reference": "vibrant"
        }, 
        {
          "hex": "#cab5a6",
          "name": "#cab5a6",
          "reference": "vibrant"
        }
      ],
      "sizes": {
        "b": {
          "extension": "jpg",
          "height": 768,
          "mimetype": "image/jpeg",
          "secret": "XaJM4RMc2xMnOYtSJcXZfbHyM3UvAKkx",
          "width": 412
        },
        "c": {
          "extension": "jpg",
          "height": 600,
          "mimetype": "image/jpeg",
          "secret": "XaJM4RMc2xMnOYtSJcXZfbHyM3UvAKkx",
          "width": 322
        },
        "dc": {
          "extension": "jpg",
          "height": 600,
          "mimetype": "image/jpeg",
          "secret": "XaJM4RMc2xMnOYtSJcXZfbHyM3UvAKkx",
          "width": 322
        },
        "ds": {
          "extension": "jpg",
          "height": 320,
          "mimetype": "image/jpeg",
          "secret": "XaJM4RMc2xMnOYtSJcXZfbHyM3UvAKkx",
          "width": 320
        },
        "k": {
          "extension": "jpg",
          "height": 1536,
          "mimetype": "image/jpeg",
          "secret": "XaJM4RMc2xMnOYtSJcXZfbHyM3UvAKkx",
          "width": 824
        },
        "n": {
          "extension": "jpg",
          "height": 240,
          "mimetype": "image/jpeg",
          "secret": "XaJM4RMc2xMnOYtSJcXZfbHyM3UvAKkx",
          "width": 128
        },
        "o": {
          "extension": "jpg",
          "height": 3083,
          "mimetype": "image/jpeg",
          "secret": "dGdMX9sfaeN6TyldkShXAfRz86Kv4QPI",
          "width": 1655
        },
        "s": {
          "extension": "jpg",
          "height": 320,
          "mimetype": "image/jpeg",
          "secret": "XaJM4RMc2xMnOYtSJcXZfbHyM3UvAKkx",
          "width": 320
        },
        "z": {
          "extension": "jpg",
          "height": 480,
          "mimetype": "image/jpeg",
          "secret": "XaJM4RMc2xMnOYtSJcXZfbHyM3UvAKkx",
          "width": 257
        }
      }
    },
    "media:uri_template": "https://millsfield.sfomuseum.org/media/152/782/484/5/1527824845_{secret}_{label}.{extention}",
    "sfomuseum:filename": "42832.tif",
    "sfomuseum:image_index": 5,
    "sfomuseum:placetype": "image",
    "sfomuseum:primary_image": 1,
    "wof:depicts": [
      1511927441
    ],
    "wof:name": "airsickness bag: JAL (Japan Airlines)",
    "wof:placetype": "media"
  },
  "geometry": {"coordinates":[-122.386155,37.616358],"type":"Point"}
}
