{
  "type": "Feature",
  "properties": {
    "iso:country": "XX",
    "media:fingerprint": "d2cb1aa3a987de943f103f925f2d36570985add5",
    "media:imagehash_avg": "a:fef8303070000000",
    "media:imagehash_diff": "d:60606262a2e22323",
    "media:medium": "image",
    "media:mimetype": "image/tiff",
    "media:properties": {
      "colours": [
        {
          "hex": "#a76684",
          "name": "#a76684",
          "reference": "vibrant"
        }, 
        {
          "hex": "#b9b8d3",
          "name": "#b9b8d3",
          "reference": "vibrant"
        }, 
        {
          "hex": "#46332a",
          "name": "#46332a",
          "reference": "vibrant"
        }
      ],
      "sizes": {
        "b": {
          "extension": "jpg",
          "height": 664,
          "mimetype": "image/jpeg",
          "secret": "uRXH1vLztR81yQtv5qDqBbsZF7Riy1dI",
          "width": 1024
        },
        "c": {
          "extension": "jpg",
          "height": 519,
          "mimetype": "image/jpeg",
          "secret": "uRXH1vLztR81yQtv5qDqBbsZF7Riy1dI",
          "width": 800
        },
        "dc": {
          "extension": "jpg",
          "height": 519,
          "mimetype": "image/jpeg",
          "secret": "uRXH1vLztR81yQtv5qDqBbsZF7Riy1dI",
          "width": 800
        },
        "ds": {
          "extension": "jpg",
          "height": 320,
          "mimetype": "image/jpeg",
          "secret": "uRXH1vLztR81yQtv5qDqBbsZF7Riy1dI",
          "width": 320
        },
        "k": {
          "extension": "jpg",
          "height": 1329,
          "mimetype": "image/jpeg",
          "secret": "uRXH1vLztR81yQtv5qDqBbsZF7Riy1dI",
          "width": 2048
        },
        "n": {
          "extension": "jpg",
          "height": 207,
          "mimetype": "image/jpeg",
          "secret": "uRXH1vLztR81yQtv5qDqBbsZF7Riy1dI",
          "width": 320
        },
        "o": {
          "extension": "jpg",
          "height": 1009,
          "mimetype": "image/jpeg",
          "secret": "35mKCaynYXghYfoFghZcVLIeqSdPTDJ4",
          "width": 1554
        },
        "s": {
          "extension": "jpg",
          "height": 320,
          "mimetype": "image/jpeg",
          "secret": "uRXH1vLztR81yQtv5qDqBbsZF7Riy1dI",
          "width": 320
        },
        "z": {
          "extension": "jpg",
          "height": 415,
          "mimetype": "image/jpeg",
          "secret": "uRXH1vLztR81yQtv5qDqBbsZF7Riy1dI",
          "width": 640
        }
      }
    },
    "media:uri_template": "https://millsfield.sfomuseum.org/media/152/782/827/5/1527828275_{secret}_{label}.{extention}",
    "sfomuseum:filename": "44518.tif",
    "sfomuseum:image_index": 5,
    "sfomuseum:placetype": "image",
    "sfomuseum:primary_image": 1,
    "wof:depicts": [
      1511949307
    ],
    "wof:name": "negative: San Francisco International Airport (SFO), film crews",
    "wof:placetype": "media"
  },
  "geometry": {"coordinates":[-122.386155,37.616358],"type":"Point"}
}
