{
  "type": "Feature",
  "properties": {
    "iso:country": "XX",
    "media:fingerprint": "10c94806deaf38a75ee4752da6ca2f1d572f4037",
    "media:imagehash_avg": "a:9e889e98989e9eff",
    "media:imagehash_diff": "d:1a3a3a323a3a302a",
    "media:medium": "image",
    "media:mimetype": "image/tiff",
    "media:properties": {
      "colours": [
        {
          "hex": "#d8293f",
          "name": "#d8293f",
          "reference": "vibrant"
        },
        {
          "hex": "#f8eccb",
          "name": "#f8eccb",
          "reference": "vibrant"
        },
        {
          "hex": "#c10018",
          "name": "#c10018",
          "reference": "vibrant"
        },
        {
          "hex": "#9c987b",
          "name": "#9c987b",
          "reference": "vibrant"
        },
        {
          "hex": "#d7c4ab",
          "name": "#d7c4ab",
          "reference": "vibrant"
        }
      ],
      "sizes": {
        "b": {
          "extension": "jpg",
          "height": 724,
          "mimetype": "image/jpeg",
          "secret": "ed3RihoHpYwoGUhSRNPHFNI1yBHU9xYF",
          "width": 1024
        },
        "c": {
          "extension": "jpg",
          "height": 565,
          "mimetype": "image/jpeg",
          "secret": "ed3RihoHpYwoGUhSRNPHFNI1yBHU9xYF",
          "width": 800
        },
        "dc": {
          "extension": "jpg",
          "height": 565,
          "mimetype": "image/jpeg",
          "secret": "ed3RihoHpYwoGUhSRNPHFNI1yBHU9xYF",
          "width": 800
        },
        "ds": {
          "extension": "jpg",
          "height": 320,
          "mimetype": "image/jpeg",
          "secret": "ed3RihoHpYwoGUhSRNPHFNI1yBHU9xYF",
          "width": 320
        },
        "k": {
          "extension": "jpg",
          "height": 1448,
          "mimetype": "image/jpeg",
          "secret": "ed3RihoHpYwoGUhSRNPHFNI1yBHU9xYF",
          "width": 2048
        },
        "n": {
          "extension": "jpg",
          "height": 226,
          "mimetype": "image/jpeg",
          "secret": "ed3RihoHpYwoGUhSRNPHFNI1yBHU9xYF",
          "width": 320
        },
        "o": {
          "extension": "jpg",
          "height": 1486,
          "mimetype": "image/jpeg",
          "secret": "iDsw30JC0rMCU6lRqkfFY9ROvzutQ1fX",
          "width": 2101
        },
        "s": {
          "extension": "jpg",
          "height": 320,
          "mimetype": "image/jpeg",
          "secret": "ed3RihoHpYwoGUhSRNPHFNI1yBHU9xYF",
          "width": 320
        },
        "z": {
          "extension": "jpg",
          "height": 452,
          "mimetype": "image/jpeg",
          "secret": "ed3RihoHpYwoGUhSRNPHFNI1yBHU9xYF",
          "width": 640
        }
      }
    },
    "media:uri_template": "https://static.sfomuseum.org/media/152/784/811/3/1527848113_{secret}_{label}.{extention}",
    "sfomuseum:filename": "2002113412_inside.tif",
    "sfomuseum:image_index": 5,
    "sfomuseum:image_type": "studio",
    "sfomuseum:placetype": "image",
    "sfomuseum:primary_image": 0,
    "wof:depicts": [
      1159285393,
      1511925187
    ],
    "wof:name": "menu: TWA (Trans World Airlines), Ambassador (Business) Class",
    "wof:placetype": "custom",
    "wof:placetype_alt": "image"
  },
  "geometry": {"coordinates":[-122.386155,37.616358],"type":"Point"}
}
