{
  "type": "Feature",
  "properties": {
    "iso:country": "NZ",
    "media:fingerprint": "a0b59e267f0f301b0a205d66e5cac0259ae1bb9c",
    "media:imagehash_avg": "a:f980c1e3e7f7ffff",
    "media:imagehash_diff": "d:61311b8f0f6f2f59",
    "media:medium": "image",
    "media:mimetype": "image/tiff",
    "media:properties": {
      "colours": [
        {
          "hex": "#e63a33",
          "name": "#e63a33",
          "reference": "vibrant"
        }, 
        {
          "hex": "#f76a61",
          "name": "#f76a61",
          "reference": "vibrant"
        }, 
        {
          "hex": "#195189",
          "name": "#195189",
          "reference": "vibrant"
        }, 
        {
          "hex": "#a48d64",
          "name": "#a48d64",
          "reference": "vibrant"
        }, 
        {
          "hex": "#c0b190",
          "name": "#c0b190",
          "reference": "vibrant"
        }
      ],
      "sizes": {
        "b": {
          "extension": "jpg",
          "height": 475,
          "mimetype": "image/jpeg",
          "secret": "VC57JyPHMk7imf2acYISa4wFM3ktoRtO",
          "width": 1024
        },
        "c": {
          "extension": "jpg",
          "height": 371,
          "mimetype": "image/jpeg",
          "secret": "VC57JyPHMk7imf2acYISa4wFM3ktoRtO",
          "width": 800
        },
        "dc": {
          "extension": "jpg",
          "height": 371,
          "mimetype": "image/jpeg",
          "secret": "VC57JyPHMk7imf2acYISa4wFM3ktoRtO",
          "width": 800
        },
        "ds": {
          "extension": "jpg",
          "height": 320,
          "mimetype": "image/jpeg",
          "secret": "VC57JyPHMk7imf2acYISa4wFM3ktoRtO",
          "width": 320
        },
        "k": {
          "extension": "jpg",
          "height": 950,
          "mimetype": "image/jpeg",
          "secret": "VC57JyPHMk7imf2acYISa4wFM3ktoRtO",
          "width": 2048
        },
        "n": {
          "extension": "jpg",
          "height": 148,
          "mimetype": "image/jpeg",
          "secret": "VC57JyPHMk7imf2acYISa4wFM3ktoRtO",
          "width": 320
        },
        "o": {
          "extension": "jpg",
          "height": 1294,
          "mimetype": "image/jpeg",
          "secret": "7WFW78D24WkmW2GJXw7P5YbhR3pMZ4qd",
          "width": 2787
        },
        "s": {
          "extension": "jpg",
          "height": 320,
          "mimetype": "image/jpeg",
          "secret": "VC57JyPHMk7imf2acYISa4wFM3ktoRtO",
          "width": 320
        },
        "z": {
          "extension": "jpg",
          "height": 297,
          "mimetype": "image/jpeg",
          "secret": "VC57JyPHMk7imf2acYISa4wFM3ktoRtO",
          "width": 640
        }
      }
    },
    "media:uri_template": "https://millsfield.sfomuseum.org/media/152/782/917/5/1527829175_{secret}_{label}.{extention}",
    "sfomuseum:filename": "47550.tif",
    "sfomuseum:image_index": 5,
    "sfomuseum:placetype": "image",
    "sfomuseum:primary_image": 1,
    "wof:depicts": [
      1511907425
    ],
    "wof:name": "airmail flight cover: Pan American Airways, Auckland - San Francisco route",
    "wof:placetype": "media"
  },
  "geometry": {"coordinates":[-122.386155,37.616358],"type":"Point"}
}
