{
  "type": "Feature",
  "properties": {
    "iso:country": "XX",
    "media:fingerprint": "01169defb96cc05b06854b93b851b65220400812",
    "media:imagehash_avg": "a:ffffa8c08000c280",
    "media:imagehash_diff": "d:91d3521b1b030636",
    "media:medium": "image",
    "media:mimetype": "image/tiff",
    "media:properties": {
      "colours": [
        {
          "hex": "#868686",
          "name": "#868686",
          "reference": "vibrant"
        }, 
        {
          "hex": "#b8b8b8",
          "name": "#b8b8b8",
          "reference": "vibrant"
        }, 
        {
          "hex": "#404040",
          "name": "#404040",
          "reference": "vibrant"
        }
      ],
      "sizes": {
        "b": {
          "extension": "jpg",
          "height": 768,
          "mimetype": "image/jpeg",
          "secret": "hiam6BAxSehg2uDVn16t6D7MAhX5YCpZ",
          "width": 759
        },
        "c": {
          "extension": "jpg",
          "height": 600,
          "mimetype": "image/jpeg",
          "secret": "hiam6BAxSehg2uDVn16t6D7MAhX5YCpZ",
          "width": 593
        },
        "dc": {
          "extension": "jpg",
          "height": 600,
          "mimetype": "image/jpeg",
          "secret": "hiam6BAxSehg2uDVn16t6D7MAhX5YCpZ",
          "width": 593
        },
        "ds": {
          "extension": "jpg",
          "height": 320,
          "mimetype": "image/jpeg",
          "secret": "hiam6BAxSehg2uDVn16t6D7MAhX5YCpZ",
          "width": 320
        },
        "k": {
          "extension": "jpg",
          "height": 1536,
          "mimetype": "image/jpeg",
          "secret": "hiam6BAxSehg2uDVn16t6D7MAhX5YCpZ",
          "width": 1519
        },
        "n": {
          "extension": "jpg",
          "height": 239,
          "mimetype": "image/jpeg",
          "secret": "hiam6BAxSehg2uDVn16t6D7MAhX5YCpZ",
          "width": 237
        },
        "o": {
          "extension": "jpg",
          "height": 2563,
          "mimetype": "image/jpeg",
          "secret": "zri4nJdTngxJ8FJ5KHXvfqp7XUN59faU",
          "width": 2536
        },
        "s": {
          "extension": "jpg",
          "height": 320,
          "mimetype": "image/jpeg",
          "secret": "hiam6BAxSehg2uDVn16t6D7MAhX5YCpZ",
          "width": 320
        },
        "z": {
          "extension": "jpg",
          "height": 479,
          "mimetype": "image/jpeg",
          "secret": "hiam6BAxSehg2uDVn16t6D7MAhX5YCpZ",
          "width": 474
        }
      }
    },
    "media:uri_template": "https://millsfield.sfomuseum.org/media/152/782/689/7/1527826897_{secret}_{label}.{extention}",
    "sfomuseum:filename": "43846.tif",
    "sfomuseum:image_index": 5,
    "sfomuseum:placetype": "image",
    "sfomuseum:primary_image": 1,
    "wof:depicts": [
      1511947937
    ],
    "wof:name": "negative: San Francisco International Airport (SFO), parking garage construction",
    "wof:placetype": "media"
  },
  "geometry": {"coordinates":[-122.386155,37.616358],"type":"Point"}
}
