{
  "type": "Feature",
  "properties": {
    "iso:country": "XX",
    "media:fingerprint": "1dfc42935148cfa7bb0275ebaad9979e3080036a",
    "media:imagehash_avg": "a:fe9efe9899ffe7ff",
    "media:imagehash_diff": "d:ae323a323b2b0e0e",
    "media:medium": "image",
    "media:mimetype": "image/tiff",
    "media:properties": {
      "colours": [
        {
          "hex": "#f6ecd8",
          "name": "#f6ecd8",
          "reference": "vibrant"
        },
        {
          "hex": "#413309",
          "name": "#413309",
          "reference": "vibrant"
        },
        {
          "hex": "#7d7e74",
          "name": "#7d7e74",
          "reference": "vibrant"
        },
        {
          "hex": "#c4c3b6",
          "name": "#c4c3b6",
          "reference": "vibrant"
        },
        {
          "hex": "#485850",
          "name": "#485850",
          "reference": "vibrant"
        }
      ],
      "sizes": {
        "b": {
          "extension": "jpg",
          "height": 662,
          "mimetype": "image/jpeg",
          "secret": "4wWK56F6VhZYDAeaoysoVJaUhaYONvga",
          "width": 1024
        },
        "c": {
          "extension": "jpg",
          "height": 517,
          "mimetype": "image/jpeg",
          "secret": "4wWK56F6VhZYDAeaoysoVJaUhaYONvga",
          "width": 800
        },
        "dc": {
          "extension": "jpg",
          "height": 517,
          "mimetype": "image/jpeg",
          "secret": "4wWK56F6VhZYDAeaoysoVJaUhaYONvga",
          "width": 800
        },
        "ds": {
          "extension": "jpg",
          "height": 320,
          "mimetype": "image/jpeg",
          "secret": "4wWK56F6VhZYDAeaoysoVJaUhaYONvga",
          "width": 320
        },
        "k": {
          "extension": "jpg",
          "height": 1324,
          "mimetype": "image/jpeg",
          "secret": "4wWK56F6VhZYDAeaoysoVJaUhaYONvga",
          "width": 2048
        },
        "n": {
          "extension": "jpg",
          "height": 206,
          "mimetype": "image/jpeg",
          "secret": "4wWK56F6VhZYDAeaoysoVJaUhaYONvga",
          "width": 320
        },
        "o": {
          "extension": "jpg",
          "height": 2069,
          "mimetype": "image/jpeg",
          "secret": "mNM17DfZkm18kJN1CoLTUYqWcumDQGi9",
          "width": 3200
        },
        "s": {
          "extension": "jpg",
          "height": 320,
          "mimetype": "image/jpeg",
          "secret": "4wWK56F6VhZYDAeaoysoVJaUhaYONvga",
          "width": 320
        },
        "z": {
          "extension": "jpg",
          "height": 413,
          "mimetype": "image/jpeg",
          "secret": "4wWK56F6VhZYDAeaoysoVJaUhaYONvga",
          "width": 640
        }
      }
    },
    "media:uri_template": "https://static.sfomuseum.org/media/152/784/405/3/1527844053_{secret}_{label}.{extention}",
    "sfomuseum:filename": "68864.tif",
    "sfomuseum:image_index": 5,
    "sfomuseum:image_type": "studio",
    "sfomuseum:placetype": "image",
    "sfomuseum:primary_image": 0,
    "wof:depicts": [
      1360700617,
      1511925385,
      1159283627
    ],
    "wof:name": "menu: Air France",
    "wof:placetype": "custom",
    "wof:placetype_alt": "image"
  },
  "geometry": {"coordinates":[-122.386155,37.616358],"type":"Point"}
}
