{
  "type": "Feature",
  "properties": {
    "iso:country": "XX",
    "media:fingerprint": "28dabfdeded13cc652223e4971a19677ee460d48",
    "media:imagehash_avg": "a:ffffffff8f810000",
    "media:imagehash_diff": "d:7b5d694d3d3d4531",
    "media:medium": "image",
    "media:mimetype": "image/tiff",
    "media:properties": {
      "colours": [
        {
          "hex": "#ceb431",
          "name": "#ceb431",
          "reference": "vibrant"
        }, 
        {
          "hex": "#b73628",
          "name": "#b73628",
          "reference": "vibrant"
        }, 
        {
          "hex": "#888671",
          "name": "#888671",
          "reference": "vibrant"
        }, 
        {
          "hex": "#bdb7ac",
          "name": "#bdb7ac",
          "reference": "vibrant"
        }, 
        {
          "hex": "#513631",
          "name": "#513631",
          "reference": "vibrant"
        }
      ],
      "sizes": {
        "b": {
          "extension": "jpg",
          "height": 768,
          "mimetype": "image/jpeg",
          "secret": "SsrGaNReL5DNFgFKSZfKXlPIflYOthaS",
          "width": 504
        },
        "c": {
          "extension": "jpg",
          "height": 600,
          "mimetype": "image/jpeg",
          "secret": "SsrGaNReL5DNFgFKSZfKXlPIflYOthaS",
          "width": 393
        },
        "dc": {
          "extension": "jpg",
          "height": 600,
          "mimetype": "image/jpeg",
          "secret": "SsrGaNReL5DNFgFKSZfKXlPIflYOthaS",
          "width": 393
        },
        "ds": {
          "extension": "jpg",
          "height": 320,
          "mimetype": "image/jpeg",
          "secret": "SsrGaNReL5DNFgFKSZfKXlPIflYOthaS",
          "width": 320
        },
        "k": {
          "extension": "jpg",
          "height": 1536,
          "mimetype": "image/jpeg",
          "secret": "SsrGaNReL5DNFgFKSZfKXlPIflYOthaS",
          "width": 1008
        },
        "n": {
          "extension": "jpg",
          "height": 240,
          "mimetype": "image/jpeg",
          "secret": "SsrGaNReL5DNFgFKSZfKXlPIflYOthaS",
          "width": 157
        },
        "o": {
          "extension": "jpg",
          "height": 2603,
          "mimetype": "image/jpeg",
          "secret": "ARJgtv3Rgo1I5a1QJa9GZbqLrH1p7riF",
          "width": 1709
        },
        "s": {
          "extension": "jpg",
          "height": 320,
          "mimetype": "image/jpeg",
          "secret": "SsrGaNReL5DNFgFKSZfKXlPIflYOthaS",
          "width": 320
        },
        "z": {
          "extension": "jpg",
          "height": 480,
          "mimetype": "image/jpeg",
          "secret": "SsrGaNReL5DNFgFKSZfKXlPIflYOthaS",
          "width": 315
        }
      }
    },
    "media:uri_template": "https://millsfield.sfomuseum.org/media/152/782/033/7/1527820337_{secret}_{label}.{extention}",
    "sfomuseum:filename": "31526.tif",
    "sfomuseum:image_index": 5,
    "sfomuseum:placetype": "image",
    "sfomuseum:primary_image": 0,
    "wof:depicts": [
      1511920137
    ],
    "wof:name": "flight information packet: United Air Lines, Douglas DC-4, Lockheed L-049 Constellation",
    "wof:placetype": "media"
  },
  "geometry": {"coordinates":[-122.386155,37.616358],"type":"Point"}
}
