{
  "type": "Feature",
  "properties": {
    "iso:country": "XX",
    "media:fingerprint": "d433f6ba656d3b7e3ae70468f0c9edc88c7853e1",
    "media:imagehash_avg": "a:000030f8f8fffffc",
    "media:imagehash_diff": "d:0000606021713080",
    "media:medium": "image",
    "media:mimetype": "image/tiff",
    "media:properties": {
      "colours": [
        {
          "hex": "#7a7a7a",
          "name": "#7a7a7a",
          "reference": "vibrant"
        }, 
        {
          "hex": "#b6b6b6",
          "name": "#b6b6b6",
          "reference": "vibrant"
        }, 
        {
          "hex": "#404040",
          "name": "#404040",
          "reference": "vibrant"
        }
      ],
      "sizes": {
        "b": {
          "extension": "jpg",
          "height": 767,
          "mimetype": "image/jpeg",
          "secret": "Ve7v2YgHRAf5Nw9x2aqekuFb8Yb27NH3",
          "width": 983
        },
        "c": {
          "extension": "jpg",
          "height": 600,
          "mimetype": "image/jpeg",
          "secret": "Ve7v2YgHRAf5Nw9x2aqekuFb8Yb27NH3",
          "width": 768
        },
        "dc": {
          "extension": "jpg",
          "height": 600,
          "mimetype": "image/jpeg",
          "secret": "Ve7v2YgHRAf5Nw9x2aqekuFb8Yb27NH3",
          "width": 768
        },
        "ds": {
          "extension": "jpg",
          "height": 320,
          "mimetype": "image/jpeg",
          "secret": "Ve7v2YgHRAf5Nw9x2aqekuFb8Yb27NH3",
          "width": 320
        },
        "k": {
          "extension": "jpg",
          "height": 1535,
          "mimetype": "image/jpeg",
          "secret": "Ve7v2YgHRAf5Nw9x2aqekuFb8Yb27NH3",
          "width": 1966
        },
        "n": {
          "extension": "jpg",
          "height": 240,
          "mimetype": "image/jpeg",
          "secret": "Ve7v2YgHRAf5Nw9x2aqekuFb8Yb27NH3",
          "width": 307
        },
        "o": {
          "extension": "jpg",
          "height": 2140,
          "mimetype": "image/jpeg",
          "secret": "SpVWUzxofpwkKIarfj4T6ETBI1Gf4rnv",
          "width": 2740
        },
        "s": {
          "extension": "jpg",
          "height": 320,
          "mimetype": "image/jpeg",
          "secret": "Ve7v2YgHRAf5Nw9x2aqekuFb8Yb27NH3",
          "width": 320
        },
        "z": {
          "extension": "jpg",
          "height": 480,
          "mimetype": "image/jpeg",
          "secret": "Ve7v2YgHRAf5Nw9x2aqekuFb8Yb27NH3",
          "width": 614
        }
      }
    },
    "media:uri_template": "https://millsfield.sfomuseum.org/media/152/782/403/5/1527824035_{secret}_{label}.{extention}",
    "sfomuseum:filename": "42236.tif",
    "sfomuseum:image_index": 5,
    "sfomuseum:placetype": "image",
    "sfomuseum:primary_image": 1,
    "wof:depicts": [
      1511945353
    ],
    "wof:name": "negative: San Francisco, view toward Golden Gate Bridge",
    "wof:placetype": "media"
  },
  "geometry": {"coordinates":[-122.386155,37.616358],"type":"Point"}
}
