{
  "type": "Feature",
  "properties": {
    "iso:country": "XX",
    "media:fingerprint": "8c16d41bfeedeeb4c50a0fc41258a1de5b03a5f6",
    "media:imagehash_avg": "a:e7818520008181e7",
    "media:imagehash_diff": "d:1733554d5549230f",
    "media:medium": "image",
    "media:mimetype": "image/tiff",
    "media:properties": {
      "colours": [
        {
          "hex": "#c52213",
          "name": "#c52213",
          "reference": "vibrant"
        }, 
        {
          "hex": "#e4d4b5",
          "name": "#e4d4b5",
          "reference": "vibrant"
        }, 
        {
          "hex": "#b81808",
          "name": "#b81808",
          "reference": "vibrant"
        }, 
        {
          "hex": "#98927b",
          "name": "#98927b",
          "reference": "vibrant"
        }, 
        {
          "hex": "#b3ae9c",
          "name": "#b3ae9c",
          "reference": "vibrant"
        }
      ],
      "sizes": {
        "b": {
          "extension": "jpg",
          "height": 768,
          "mimetype": "image/jpeg",
          "secret": "moIlLYyDADfeN2FROWCZWZJlGXQpjSFb",
          "width": 762
        },
        "c": {
          "extension": "jpg",
          "height": 600,
          "mimetype": "image/jpeg",
          "secret": "moIlLYyDADfeN2FROWCZWZJlGXQpjSFb",
          "width": 595
        },
        "dc": {
          "extension": "jpg",
          "height": 600,
          "mimetype": "image/jpeg",
          "secret": "moIlLYyDADfeN2FROWCZWZJlGXQpjSFb",
          "width": 595
        },
        "ds": {
          "extension": "jpg",
          "height": 320,
          "mimetype": "image/jpeg",
          "secret": "moIlLYyDADfeN2FROWCZWZJlGXQpjSFb",
          "width": 320
        },
        "k": {
          "extension": "jpg",
          "height": 1536,
          "mimetype": "image/jpeg",
          "secret": "moIlLYyDADfeN2FROWCZWZJlGXQpjSFb",
          "width": 1525
        },
        "n": {
          "extension": "jpg",
          "height": 240,
          "mimetype": "image/jpeg",
          "secret": "moIlLYyDADfeN2FROWCZWZJlGXQpjSFb",
          "width": 238
        },
        "o": {
          "extension": "jpg",
          "height": 1299,
          "mimetype": "image/jpeg",
          "secret": "irhTnyad5rZeRd4GmRfPZ5nHCVRdvtD8",
          "width": 1290
        },
        "s": {
          "extension": "jpg",
          "height": 320,
          "mimetype": "image/jpeg",
          "secret": "moIlLYyDADfeN2FROWCZWZJlGXQpjSFb",
          "width": 320
        },
        "z": {
          "extension": "jpg",
          "height": 480,
          "mimetype": "image/jpeg",
          "secret": "moIlLYyDADfeN2FROWCZWZJlGXQpjSFb",
          "width": 476
        }
      }
    },
    "media:uri_template": "https://millsfield.sfomuseum.org/media/152/781/954/9/1527819549_{secret}_{label}.{extention}",
    "sfomuseum:filename": "30922.tif",
    "sfomuseum:image_index": 5,
    "sfomuseum:placetype": "image",
    "sfomuseum:primary_image": 0,
    "wof:depicts": [
      1511910419
    ],
    "wof:name": "flight information packet: Colonial Airlines",
    "wof:placetype": "media"
  },
  "geometry": {"coordinates":[-122.386155,37.616358],"type":"Point"}
}
