{
  "type": "Feature",
  "properties": {
    "iso:country": "XX",
    "media:fingerprint": "f5c87aeb1e15225a1e84639863c215a5ab589287",
    "media:imagehash_avg": "a:80ffffffff3e1e00",
    "media:imagehash_diff": "d:29b0b2ba70f0f05b",
    "media:medium": "image",
    "media:mimetype": "image/tiff",
    "media:properties": {
      "colours": [
        {
          "hex": "#ea3819",
          "name": "#ea3819",
          "reference": "vibrant"
        }, 
        {
          "hex": "#f8af8d",
          "name": "#f8af8d",
          "reference": "vibrant"
        }, 
        {
          "hex": "#12133b",
          "name": "#12133b",
          "reference": "vibrant"
        }, 
        {
          "hex": "#707076",
          "name": "#707076",
          "reference": "vibrant"
        }, 
        {
          "hex": "#d0bfa5",
          "name": "#d0bfa5",
          "reference": "vibrant"
        }
      ],
      "sizes": {
        "b": {
          "extension": "jpg",
          "height": 460,
          "mimetype": "image/jpeg",
          "secret": "EmPhQLRD60FqdgigW9aFuSMfVmoMpjUo",
          "width": 1024
        },
        "c": {
          "extension": "jpg",
          "height": 359,
          "mimetype": "image/jpeg",
          "secret": "EmPhQLRD60FqdgigW9aFuSMfVmoMpjUo",
          "width": 800
        },
        "dc": {
          "extension": "jpg",
          "height": 359,
          "mimetype": "image/jpeg",
          "secret": "EmPhQLRD60FqdgigW9aFuSMfVmoMpjUo",
          "width": 800
        },
        "ds": {
          "extension": "jpg",
          "height": 320,
          "mimetype": "image/jpeg",
          "secret": "EmPhQLRD60FqdgigW9aFuSMfVmoMpjUo",
          "width": 320
        },
        "k": {
          "extension": "jpg",
          "height": 921,
          "mimetype": "image/jpeg",
          "secret": "EmPhQLRD60FqdgigW9aFuSMfVmoMpjUo",
          "width": 2048
        },
        "n": {
          "extension": "jpg",
          "height": 143,
          "mimetype": "image/jpeg",
          "secret": "EmPhQLRD60FqdgigW9aFuSMfVmoMpjUo",
          "width": 320
        },
        "o": {
          "extension": "jpg",
          "height": 1325,
          "mimetype": "image/jpeg",
          "secret": "gVMP1tqGh4GU4EdfjPA2u7qgVj8y52qw",
          "width": 2946
        },
        "s": {
          "extension": "jpg",
          "height": 320,
          "mimetype": "image/jpeg",
          "secret": "EmPhQLRD60FqdgigW9aFuSMfVmoMpjUo",
          "width": 320
        },
        "z": {
          "extension": "jpg",
          "height": 287,
          "mimetype": "image/jpeg",
          "secret": "EmPhQLRD60FqdgigW9aFuSMfVmoMpjUo",
          "width": 640
        }
      }
    },
    "media:uri_template": "https://millsfield.sfomuseum.org/media/152/782/891/7/1527828917_{secret}_{label}.{extention}",
    "sfomuseum:filename": "47377.tif",
    "sfomuseum:image_index": 5,
    "sfomuseum:placetype": "image",
    "sfomuseum:primary_image": 0,
    "wof:depicts": [
      1511906865
    ],
    "wof:name": "airmail flight cover: Pan American Airways, FAM-14, Guam - San Francisco (Alameda) route",
    "wof:placetype": "media"
  },
  "geometry": {"coordinates":[-122.386155,37.616358],"type":"Point"}
}
