{
  "type": "Feature",
  "properties": {
    "iso:country": "XX",
    "media:fingerprint": "a67da0df5f9a230548186cff2cbc368824ebe4fb",
    "media:imagehash_avg": "a:fffffc7c1eb8e080",
    "media:imagehash_diff": "d:e0d0d0e0f8708103",
    "media:medium": "image",
    "media:mimetype": "image/tiff",
    "media:properties": {
      "colours": [
        {
          "hex": "#808080",
          "name": "#808080",
          "reference": "vibrant"
        }, 
        {
          "hex": "#b8b8b8",
          "name": "#b8b8b8",
          "reference": "vibrant"
        }, 
        {
          "hex": "#454545",
          "name": "#454545",
          "reference": "vibrant"
        }
      ],
      "sizes": {
        "b": {
          "extension": "jpg",
          "height": 768,
          "mimetype": "image/jpeg",
          "secret": "uGu3Mw9uh6ya6sqOJ9aRYyRSa7HP3FDM",
          "width": 969
        },
        "c": {
          "extension": "jpg",
          "height": 600,
          "mimetype": "image/jpeg",
          "secret": "uGu3Mw9uh6ya6sqOJ9aRYyRSa7HP3FDM",
          "width": 757
        },
        "dc": {
          "extension": "jpg",
          "height": 600,
          "mimetype": "image/jpeg",
          "secret": "uGu3Mw9uh6ya6sqOJ9aRYyRSa7HP3FDM",
          "width": 757
        },
        "ds": {
          "extension": "jpg",
          "height": 320,
          "mimetype": "image/jpeg",
          "secret": "uGu3Mw9uh6ya6sqOJ9aRYyRSa7HP3FDM",
          "width": 320
        },
        "k": {
          "extension": "jpg",
          "height": 1536,
          "mimetype": "image/jpeg",
          "secret": "uGu3Mw9uh6ya6sqOJ9aRYyRSa7HP3FDM",
          "width": 1939
        },
        "n": {
          "extension": "jpg",
          "height": 240,
          "mimetype": "image/jpeg",
          "secret": "uGu3Mw9uh6ya6sqOJ9aRYyRSa7HP3FDM",
          "width": 303
        },
        "o": {
          "extension": "jpg",
          "height": 2181,
          "mimetype": "image/jpeg",
          "secret": "3dt403VdPAbcmMOQAFpucmotRq1IWBEu",
          "width": 2754
        },
        "s": {
          "extension": "jpg",
          "height": 320,
          "mimetype": "image/jpeg",
          "secret": "uGu3Mw9uh6ya6sqOJ9aRYyRSa7HP3FDM",
          "width": 320
        },
        "z": {
          "extension": "jpg",
          "height": 480,
          "mimetype": "image/jpeg",
          "secret": "uGu3Mw9uh6ya6sqOJ9aRYyRSa7HP3FDM",
          "width": 606
        }
      }
    },
    "media:uri_template": "https://millsfield.sfomuseum.org/media/152/782/327/3/1527823273_{secret}_{label}.{extention}",
    "sfomuseum:filename": "41475.tif",
    "sfomuseum:image_index": 5,
    "sfomuseum:placetype": "image",
    "sfomuseum:primary_image": 1,
    "wof:depicts": [
      1511945173
    ],
    "wof:name": "negative: San Francisco International Airport (SFO), parking garage construction",
    "wof:placetype": "media"
  },
  "geometry": {"coordinates":[-122.386155,37.616358],"type":"Point"}
}
