{
  "type": "Feature",
  "properties": {
    "media:fingerprint": "f61238a56ea53deda898bef378c7cb79ff022666",
    "media:imagehash_avg": "a:0800011f3f3f1f19",
    "media:imagehash_diff": "d:7179397979717173",
    "media:mimetype": "image/jpeg",
    "media:properties": {
      "colours": [
        {
          "hex": "#d76c00",
          "name": "#d76c00",
          "reference": "vibrant"
        },
        {
          "hex": "#ebda91",
          "name": "#ebda91",
          "reference": "vibrant"
        },
        {
          "hex": "#942507",
          "name": "#942507",
          "reference": "vibrant"
        },
        {
          "hex": "#a35f4a",
          "name": "#a35f4a",
          "reference": "vibrant"
        },
        {
          "hex": "#c0ae9d",
          "name": "#c0ae9d",
          "reference": "vibrant"
        }
      ],
      "sizes": {
        "b": {
          "extension": "jpg",
          "height": 768,
          "mimetype": "image/jpeg",
          "secret": "oiEWLrW8bRatADZ4Vd3cL12f9Ikv6nDo",
          "width": 771
        },
        "c": {
          "extension": "jpg",
          "height": 600,
          "mimetype": "image/jpeg",
          "secret": "oiEWLrW8bRatADZ4Vd3cL12f9Ikv6nDo",
          "width": 603
        },
        "dc": {
          "extension": "jpg",
          "height": 600,
          "mimetype": "image/jpeg",
          "secret": "oiEWLrW8bRatADZ4Vd3cL12f9Ikv6nDo",
          "width": 603
        },
        "ds": {
          "extension": "jpg",
          "height": 320,
          "mimetype": "image/jpeg",
          "secret": "oiEWLrW8bRatADZ4Vd3cL12f9Ikv6nDo",
          "width": 320
        },
        "k": {
          "extension": "jpg",
          "height": 1536,
          "mimetype": "image/jpeg",
          "secret": "oiEWLrW8bRatADZ4Vd3cL12f9Ikv6nDo",
          "width": 1543
        },
        "n": {
          "extension": "jpg",
          "height": 239,
          "mimetype": "image/jpeg",
          "secret": "oiEWLrW8bRatADZ4Vd3cL12f9Ikv6nDo",
          "width": 241
        },
        "o": {
          "extension": "jpg",
          "height": 2358,
          "mimetype": "image/jpeg",
          "secret": "zgHFPBnarMijqDzn8xAaofSjlGBHzLGu",
          "width": 2370
        },
        "s": {
          "extension": "jpg",
          "height": 320,
          "mimetype": "image/jpeg",
          "secret": "oiEWLrW8bRatADZ4Vd3cL12f9Ikv6nDo",
          "width": 320
        },
        "z": {
          "extension": "jpg",
          "height": 479,
          "mimetype": "image/jpeg",
          "secret": "oiEWLrW8bRatADZ4Vd3cL12f9Ikv6nDo",
          "width": 482
        }
      }
    },
    "media:uri_template": "https://static.sfomuseum.org/media/174/668/009/5/1746680095_{secret}_{label}.{extention}",
    "sfomuseum:filename": "10648.JPG",
    "sfomuseum:image_index": 1,
    "sfomuseum:image_type": "curator",
    "sfomuseum:placetype": "image",
    "sfomuseum:primary_image": 1,
    "wof:depicts": [
      1159288429,
      1159284841,
      1511941391
    ],
    "wof:name": "phonograph record: National Airlines, Watch Us Shine",
    "wof:placetype": "custom"
  },
  "geometry": {"coordinates":[-122.386155,37.616357],"type":"Point"}
}
