{
  "type": "Feature",
  "properties": {
    "iso:country": "XX",
    "media:fingerprint": "29d139a4edc16901679c08ef79bf47efea740c72",
    "media:imagehash_avg": "a:8b9009199f9f99ff",
    "media:imagehash_diff": "d:33731333383633ea",
    "media:medium": "image",
    "media:mimetype": "image/tiff",
    "media:properties": {
      "colours": [
        {
          "hex": "#bb3710",
          "name": "#bb3710",
          "reference": "vibrant"
        },
        {
          "hex": "#d7c598",
          "name": "#d7c598",
          "reference": "vibrant"
        },
        {
          "hex": "#ac2607",
          "name": "#ac2607",
          "reference": "vibrant"
        },
        {
          "hex": "#998b6e",
          "name": "#998b6e",
          "reference": "vibrant"
        },
        {
          "hex": "#c8b895",
          "name": "#c8b895",
          "reference": "vibrant"
        }
      ],
      "sizes": {
        "b": {
          "extension": "jpg",
          "height": 581,
          "mimetype": "image/jpeg",
          "secret": "hAQYTP2vydjtElENGA5MhCw2FgO9wlOt",
          "width": 1023
        },
        "c": {
          "extension": "jpg",
          "height": 454,
          "mimetype": "image/jpeg",
          "secret": "hAQYTP2vydjtElENGA5MhCw2FgO9wlOt",
          "width": 800
        },
        "dc": {
          "extension": "jpg",
          "height": 454,
          "mimetype": "image/jpeg",
          "secret": "hAQYTP2vydjtElENGA5MhCw2FgO9wlOt",
          "width": 800
        },
        "ds": {
          "extension": "jpg",
          "height": 320,
          "mimetype": "image/jpeg",
          "secret": "hAQYTP2vydjtElENGA5MhCw2FgO9wlOt",
          "width": 320
        },
        "k": {
          "extension": "jpg",
          "height": 1163,
          "mimetype": "image/jpeg",
          "secret": "hAQYTP2vydjtElENGA5MhCw2FgO9wlOt",
          "width": 2047
        },
        "n": {
          "extension": "jpg",
          "height": 181,
          "mimetype": "image/jpeg",
          "secret": "hAQYTP2vydjtElENGA5MhCw2FgO9wlOt",
          "width": 320
        },
        "o": {
          "extension": "jpg",
          "height": 947,
          "mimetype": "image/jpeg",
          "secret": "hlFk38dj9FKULij7C0GCWSLjNU9i7gPF",
          "width": 1667
        },
        "s": {
          "extension": "jpg",
          "height": 320,
          "mimetype": "image/jpeg",
          "secret": "hAQYTP2vydjtElENGA5MhCw2FgO9wlOt",
          "width": 320
        },
        "z": {
          "extension": "jpg",
          "height": 363,
          "mimetype": "image/jpeg",
          "secret": "hAQYTP2vydjtElENGA5MhCw2FgO9wlOt",
          "width": 640
        }
      }
    },
    "media:uri_template": "https://static.sfomuseum.org/media/152/785/668/9/1527856689_{secret}_{label}.{extention}",
    "sfomuseum:filename": "152646.tif",
    "sfomuseum:image_index": 5,
    "sfomuseum:image_type": "studio",
    "sfomuseum:placetype": "image",
    "sfomuseum:primary_image": 1,
    "wof:depicts": [
      1511957597
    ],
    "wof:name": "airmail flight cover: Yellowstone National Park Airport",
    "wof:placetype": "custom",
    "wof:placetype_alt": "image"
  },
  "geometry": {"coordinates":[-122.386155,37.616358],"type":"Point"}
}
