{
  "type": "Feature",
  "properties": {
    "iso:country": "XX",
    "media:fingerprint": "fb4b29cfc1095078194b5228891269de87953fed",
    "media:imagehash_avg": "a:3e3e7e7e7e3e0c00",
    "media:imagehash_diff": "d:f0f8f0f0f0e0f8f8",
    "media:medium": "image",
    "media:mimetype": "image/tiff",
    "media:properties": {
      "colours": [
        {
          "hex": "#868686",
          "name": "#868686",
          "reference": "vibrant"
        }, 
        {
          "hex": "#c0c0c0",
          "name": "#c0c0c0",
          "reference": "vibrant"
        }, 
        {
          "hex": "#404040",
          "name": "#404040",
          "reference": "vibrant"
        }
      ],
      "sizes": {
        "b": {
          "extension": "jpg",
          "height": 768,
          "mimetype": "image/jpeg",
          "secret": "GxFHov72nK6ez81NWF3PfB2ig1h5bicR",
          "width": 966
        },
        "c": {
          "extension": "jpg",
          "height": 600,
          "mimetype": "image/jpeg",
          "secret": "GxFHov72nK6ez81NWF3PfB2ig1h5bicR",
          "width": 755
        },
        "dc": {
          "extension": "jpg",
          "height": 600,
          "mimetype": "image/jpeg",
          "secret": "GxFHov72nK6ez81NWF3PfB2ig1h5bicR",
          "width": 755
        },
        "ds": {
          "extension": "jpg",
          "height": 320,
          "mimetype": "image/jpeg",
          "secret": "GxFHov72nK6ez81NWF3PfB2ig1h5bicR",
          "width": 320
        },
        "k": {
          "extension": "jpg",
          "height": 1536,
          "mimetype": "image/jpeg",
          "secret": "GxFHov72nK6ez81NWF3PfB2ig1h5bicR",
          "width": 1933
        },
        "n": {
          "extension": "jpg",
          "height": 240,
          "mimetype": "image/jpeg",
          "secret": "GxFHov72nK6ez81NWF3PfB2ig1h5bicR",
          "width": 302
        },
        "o": {
          "extension": "jpg",
          "height": 2209,
          "mimetype": "image/jpeg",
          "secret": "g0IxnLju5Z9PqnftFLKdxmwcVCrF7o8M",
          "width": 2781
        },
        "s": {
          "extension": "jpg",
          "height": 320,
          "mimetype": "image/jpeg",
          "secret": "GxFHov72nK6ez81NWF3PfB2ig1h5bicR",
          "width": 320
        },
        "z": {
          "extension": "jpg",
          "height": 480,
          "mimetype": "image/jpeg",
          "secret": "GxFHov72nK6ez81NWF3PfB2ig1h5bicR",
          "width": 604
        }
      }
    },
    "media:uri_template": "https://millsfield.sfomuseum.org/media/152/782/779/7/1527827797_{secret}_{label}.{extention}",
    "sfomuseum:filename": "44247.tif",
    "sfomuseum:image_index": 5,
    "sfomuseum:placetype": "image",
    "sfomuseum:primary_image": 1,
    "wof:depicts": [
      1511948831
    ],
    "wof:name": "negative: San Francisco International Airport (SFO), aerial",
    "wof:placetype": "media"
  },
  "geometry": {"coordinates":[-122.386155,37.616358],"type":"Point"}
}
