{
  "type": "Feature",
  "properties": {
    "iso:country": "XX",
    "media:fingerprint": "8f31ec4e0f4ca6d551bd12cec488afd6b37677c4",
    "media:imagehash_avg": "a:04000100ec35d7ff",
    "media:imagehash_diff": "d:e8f5b589d9d5260d",
    "media:medium": "image",
    "media:mimetype": "image/tiff",
    "media:properties": {
      "colours": [
        {
          "hex": "#808080",
          "name": "#808080",
          "reference": "vibrant"
        }, 
        {
          "hex": "#c0c0c0",
          "name": "#c0c0c0",
          "reference": "vibrant"
        }, 
        {
          "hex": "#404040",
          "name": "#404040",
          "reference": "vibrant"
        }
      ],
      "sizes": {
        "b": {
          "extension": "jpg",
          "height": 768,
          "mimetype": "image/jpeg",
          "secret": "yg8t1jqp0YUtUDyIcK5cCoMeG5SxTIBT",
          "width": 991
        },
        "c": {
          "extension": "jpg",
          "height": 600,
          "mimetype": "image/jpeg",
          "secret": "yg8t1jqp0YUtUDyIcK5cCoMeG5SxTIBT",
          "width": 774
        },
        "dc": {
          "extension": "jpg",
          "height": 600,
          "mimetype": "image/jpeg",
          "secret": "yg8t1jqp0YUtUDyIcK5cCoMeG5SxTIBT",
          "width": 774
        },
        "ds": {
          "extension": "jpg",
          "height": 320,
          "mimetype": "image/jpeg",
          "secret": "yg8t1jqp0YUtUDyIcK5cCoMeG5SxTIBT",
          "width": 320
        },
        "k": {
          "extension": "jpg",
          "height": 1536,
          "mimetype": "image/jpeg",
          "secret": "yg8t1jqp0YUtUDyIcK5cCoMeG5SxTIBT",
          "width": 1983
        },
        "n": {
          "extension": "jpg",
          "height": 240,
          "mimetype": "image/jpeg",
          "secret": "yg8t1jqp0YUtUDyIcK5cCoMeG5SxTIBT",
          "width": 309
        },
        "o": {
          "extension": "jpg",
          "height": 2154,
          "mimetype": "image/jpeg",
          "secret": "SXWDZSaAOscptvUXQ4V14fEpUXr7Pr32",
          "width": 2781
        },
        "s": {
          "extension": "jpg",
          "height": 320,
          "mimetype": "image/jpeg",
          "secret": "yg8t1jqp0YUtUDyIcK5cCoMeG5SxTIBT",
          "width": 320
        },
        "z": {
          "extension": "jpg",
          "height": 480,
          "mimetype": "image/jpeg",
          "secret": "yg8t1jqp0YUtUDyIcK5cCoMeG5SxTIBT",
          "width": 619
        }
      }
    },
    "media:uri_template": "https://millsfield.sfomuseum.org/media/152/782/787/3/1527827873_{secret}_{label}.{extention}",
    "sfomuseum:filename": "44281.tif",
    "sfomuseum:image_index": 5,
    "sfomuseum:placetype": "image",
    "sfomuseum:primary_image": 1,
    "wof:depicts": [
      1511948909
    ],
    "wof:name": "negative: San Francisco International Airport (SFO), engineering division personnel",
    "wof:placetype": "media"
  },
  "geometry": {"coordinates":[-122.386155,37.616358],"type":"Point"}
}
