{
  "type": "Feature",
  "properties": {
    "iso:country": "XX",
    "media:fingerprint": "f52b5e8e88b09c527495df21282c19f80940e9e8",
    "media:imagehash_avg": "a:ffff030183ffffff",
    "media:imagehash_diff": "d:ddcf1f1f1ff4fcfc",
    "media:medium": "image",
    "media:mimetype": "image/tiff",
    "media:properties": {
      "colours": [
        {
          "hex": "#c7a556",
          "name": "#c7a556",
          "reference": "vibrant"
        }, 
        {
          "hex": "#e4c27a",
          "name": "#e4c27a",
          "reference": "vibrant"
        }, 
        {
          "hex": "#00266a",
          "name": "#00266a",
          "reference": "vibrant"
        }, 
        {
          "hex": "#a79774",
          "name": "#a79774",
          "reference": "vibrant"
        }, 
        {
          "hex": "#b8b8b8",
          "name": "#b8b8b8",
          "reference": "vibrant"
        }
      ],
      "sizes": {
        "b": {
          "extension": "jpg",
          "height": 753,
          "mimetype": "image/jpeg",
          "secret": "uB6A1iDczwzpkQKHBWsLYhMihRQe95EZ",
          "width": 1024
        },
        "c": {
          "extension": "jpg",
          "height": 588,
          "mimetype": "image/jpeg",
          "secret": "uB6A1iDczwzpkQKHBWsLYhMihRQe95EZ",
          "width": 800
        },
        "dc": {
          "extension": "jpg",
          "height": 588,
          "mimetype": "image/jpeg",
          "secret": "uB6A1iDczwzpkQKHBWsLYhMihRQe95EZ",
          "width": 800
        },
        "ds": {
          "extension": "jpg",
          "height": 320,
          "mimetype": "image/jpeg",
          "secret": "uB6A1iDczwzpkQKHBWsLYhMihRQe95EZ",
          "width": 320
        },
        "k": {
          "extension": "jpg",
          "height": 1506,
          "mimetype": "image/jpeg",
          "secret": "uB6A1iDczwzpkQKHBWsLYhMihRQe95EZ",
          "width": 2048
        },
        "n": {
          "extension": "jpg",
          "height": 235,
          "mimetype": "image/jpeg",
          "secret": "uB6A1iDczwzpkQKHBWsLYhMihRQe95EZ",
          "width": 320
        },
        "o": {
          "extension": "jpg",
          "height": 2823,
          "mimetype": "image/jpeg",
          "secret": "pe6OC5zYur4wqJ8jzJVfkiwFu4bx8Pne",
          "width": 3837
        },
        "s": {
          "extension": "jpg",
          "height": 320,
          "mimetype": "image/jpeg",
          "secret": "uB6A1iDczwzpkQKHBWsLYhMihRQe95EZ",
          "width": 320
        },
        "z": {
          "extension": "jpg",
          "height": 470,
          "mimetype": "image/jpeg",
          "secret": "uB6A1iDczwzpkQKHBWsLYhMihRQe95EZ",
          "width": 640
        }
      }
    },
    "media:uri_template": "https://millsfield.sfomuseum.org/media/152/782/883/3/1527828833_{secret}_{label}.{extention}",
    "sfomuseum:filename": "46630.tif",
    "sfomuseum:image_index": 5,
    "sfomuseum:placetype": "image",
    "sfomuseum:primary_image": 1,
    "wof:depicts": [
      1511930219
    ],
    "wof:name": "flight officer wings: Canadian Pacific Airlines",
    "wof:placetype": "media"
  },
  "geometry": {"coordinates":[-122.386155,37.616358],"type":"Point"}
}
