{
  "type": "Feature",
  "properties": {
    "iso:country": "XX",
    "media:fingerprint": "ea331aaebffa3d108b1f87e3ffba46e52091be26",
    "media:imagehash_avg": "a:07fff7e3777f7f00",
    "media:imagehash_diff": "d:fbe4868686c3d681",
    "media:medium": "image",
    "media:mimetype": "image/jpeg",
    "media:properties": {
      "colours": [
        {
          "hex": "#f8f8e8",
          "name": "#f8f8e8",
          "reference": "vibrant"
        }, 
        {
          "hex": "#888483",
          "name": "#888483",
          "reference": "vibrant"
        }, 
        {
          "hex": "#bfbdb8",
          "name": "#bfbdb8",
          "reference": "vibrant"
        }, 
        {
          "hex": "#39454a",
          "name": "#39454a",
          "reference": "vibrant"
        }
      ],
      "sizes": {
        "b": {
          "extension": "jpg",
          "height": 721,
          "mimetype": "image/jpeg",
          "secret": "pf3FCxDIqoF0TraJP8MJBK5hge5wJzk9",
          "width": 1024
        },
        "c": {
          "extension": "jpg",
          "height": 563,
          "mimetype": "image/jpeg",
          "secret": "pf3FCxDIqoF0TraJP8MJBK5hge5wJzk9",
          "width": 800
        },
        "dc": {
          "extension": "jpg",
          "height": 563,
          "mimetype": "image/jpeg",
          "secret": "pf3FCxDIqoF0TraJP8MJBK5hge5wJzk9",
          "width": 800
        },
        "ds": {
          "extension": "jpg",
          "height": 320,
          "mimetype": "image/jpeg",
          "secret": "pf3FCxDIqoF0TraJP8MJBK5hge5wJzk9",
          "width": 320
        },
        "k": {
          "extension": "jpg",
          "height": 1443,
          "mimetype": "image/jpeg",
          "secret": "pf3FCxDIqoF0TraJP8MJBK5hge5wJzk9",
          "width": 2048
        },
        "n": {
          "extension": "jpg",
          "height": 225,
          "mimetype": "image/jpeg",
          "secret": "pf3FCxDIqoF0TraJP8MJBK5hge5wJzk9",
          "width": 320
        },
        "o": {
          "extension": "jpg",
          "height": 1343,
          "mimetype": "image/jpeg",
          "secret": "gISOyHnWZ2z4KwNKSxNaAOVAqDVgEw1B",
          "width": 1905
        },
        "s": {
          "extension": "jpg",
          "height": 320,
          "mimetype": "image/jpeg",
          "secret": "pf3FCxDIqoF0TraJP8MJBK5hge5wJzk9",
          "width": 320
        },
        "z": {
          "extension": "jpg",
          "height": 451,
          "mimetype": "image/jpeg",
          "secret": "pf3FCxDIqoF0TraJP8MJBK5hge5wJzk9",
          "width": 640
        }
      }
    },
    "media:uri_template": "https://millsfield.sfomuseum.org/media/152/782/045/5/1527820455_{secret}_{label}.{extention}",
    "sfomuseum:filename": "31619.jpg",
    "sfomuseum:image_index": 5,
    "sfomuseum:placetype": "image",
    "sfomuseum:primary_image": 0,
    "wof:depicts": [
      1511925889
    ],
    "wof:name": "airmail flight cover: Swissair, 50th anniversary",
    "wof:placetype": "media"
  },
  "geometry": {"coordinates":[-122.386155,37.616358],"type":"Point"}
}
