{
  "type": "Feature",
  "properties": {
    "iso:country": "XX",
    "media:fingerprint": "784b92592d3ff79d03500c8a49a779b25397ec74",
    "media:imagehash_avg": "a:ffffb8c0c0400000",
    "media:imagehash_diff": "d:005071179389f4a4",
    "media:medium": "image",
    "media:mimetype": "image/tiff",
    "media:properties": {
      "colours": [
        {
          "hex": "#a16646",
          "name": "#a16646",
          "reference": "vibrant"
        }, 
        {
          "hex": "#dbf19f",
          "name": "#dbf19f",
          "reference": "vibrant"
        }, 
        {
          "hex": "#959546",
          "name": "#959546",
          "reference": "vibrant"
        }, 
        {
          "hex": "#839768",
          "name": "#839768",
          "reference": "vibrant"
        }, 
        {
          "hex": "#acdbc4",
          "name": "#acdbc4",
          "reference": "vibrant"
        }
      ],
      "sizes": {
        "b": {
          "extension": "jpg",
          "height": 768,
          "mimetype": "image/jpeg",
          "secret": "JaVNwc0dJsXArs3wx8WkfOfrKTRfgeFd",
          "width": 776
        },
        "c": {
          "extension": "jpg",
          "height": 600,
          "mimetype": "image/jpeg",
          "secret": "JaVNwc0dJsXArs3wx8WkfOfrKTRfgeFd",
          "width": 606
        },
        "dc": {
          "extension": "jpg",
          "height": 600,
          "mimetype": "image/jpeg",
          "secret": "JaVNwc0dJsXArs3wx8WkfOfrKTRfgeFd",
          "width": 606
        },
        "ds": {
          "extension": "jpg",
          "height": 320,
          "mimetype": "image/jpeg",
          "secret": "JaVNwc0dJsXArs3wx8WkfOfrKTRfgeFd",
          "width": 320
        },
        "k": {
          "extension": "jpg",
          "height": 1536,
          "mimetype": "image/jpeg",
          "secret": "JaVNwc0dJsXArs3wx8WkfOfrKTRfgeFd",
          "width": 1552
        },
        "n": {
          "extension": "jpg",
          "height": 240,
          "mimetype": "image/jpeg",
          "secret": "JaVNwc0dJsXArs3wx8WkfOfrKTRfgeFd",
          "width": 242
        },
        "o": {
          "extension": "jpg",
          "height": 2536,
          "mimetype": "image/jpeg",
          "secret": "4E0afe4PtTSGIiZLx9EqMk2LMUsxT1Z8",
          "width": 2563
        },
        "s": {
          "extension": "jpg",
          "height": 320,
          "mimetype": "image/jpeg",
          "secret": "JaVNwc0dJsXArs3wx8WkfOfrKTRfgeFd",
          "width": 320
        },
        "z": {
          "extension": "jpg",
          "height": 480,
          "mimetype": "image/jpeg",
          "secret": "JaVNwc0dJsXArs3wx8WkfOfrKTRfgeFd",
          "width": 485
        }
      }
    },
    "media:uri_template": "https://millsfield.sfomuseum.org/media/152/782/778/9/1527827789_{secret}_{label}.{extention}",
    "sfomuseum:filename": "44243.tif",
    "sfomuseum:image_index": 5,
    "sfomuseum:placetype": "image",
    "sfomuseum:primary_image": 1,
    "wof:depicts": [
      1511948823
    ],
    "wof:name": "negative: San Francisco International Airport (SFO), construction and maintenance equipment",
    "wof:placetype": "media"
  },
  "geometry": {"coordinates":[-122.386155,37.616358],"type":"Point"}
}
