{
  "type": "Feature",
  "properties": {
    "iso:country": "XX",
    "media:fingerprint": "f83929d9968d5e46fce0bc6f74085edf7f0fb4a3",
    "media:imagehash_avg": "a:0c1f1c1e0f67240e",
    "media:imagehash_diff": "d:bcfdf5fc19cdcd5c",
    "media:medium": "image",
    "media:mimetype": "image/tiff",
    "media:properties": {
      "colours": [
        {
          "hex": "#808080",
          "name": "#808080",
          "reference": "vibrant"
        },
        {
          "hex": "#b8b8b8",
          "name": "#b8b8b8",
          "reference": "vibrant"
        },
        {
          "hex": "#464646",
          "name": "#464646",
          "reference": "vibrant"
        }
      ],
      "sizes": {
        "b": {
          "extension": "jpg",
          "height": 768,
          "mimetype": "image/jpeg",
          "secret": "dfoGkxdmAZ6kWlofUCvYXg5WcUK3klTD",
          "width": 976
        },
        "c": {
          "extension": "jpg",
          "height": 600,
          "mimetype": "image/jpeg",
          "secret": "dfoGkxdmAZ6kWlofUCvYXg5WcUK3klTD",
          "width": 763
        },
        "dc": {
          "extension": "jpg",
          "height": 600,
          "mimetype": "image/jpeg",
          "secret": "dfoGkxdmAZ6kWlofUCvYXg5WcUK3klTD",
          "width": 763
        },
        "ds": {
          "extension": "jpg",
          "height": 320,
          "mimetype": "image/jpeg",
          "secret": "dfoGkxdmAZ6kWlofUCvYXg5WcUK3klTD",
          "width": 320
        },
        "k": {
          "extension": "jpg",
          "height": 1536,
          "mimetype": "image/jpeg",
          "secret": "dfoGkxdmAZ6kWlofUCvYXg5WcUK3klTD",
          "width": 1953
        },
        "n": {
          "extension": "jpg",
          "height": 240,
          "mimetype": "image/jpeg",
          "secret": "dfoGkxdmAZ6kWlofUCvYXg5WcUK3klTD",
          "width": 305
        },
        "o": {
          "extension": "jpg",
          "height": 2154,
          "mimetype": "image/jpeg",
          "secret": "QkZqrPukAQphsZgc1GJTo6Yhf5pVNbVX",
          "width": 2740
        },
        "s": {
          "extension": "jpg",
          "height": 320,
          "mimetype": "image/jpeg",
          "secret": "dfoGkxdmAZ6kWlofUCvYXg5WcUK3klTD",
          "width": 320
        },
        "z": {
          "extension": "jpg",
          "height": 480,
          "mimetype": "image/jpeg",
          "secret": "dfoGkxdmAZ6kWlofUCvYXg5WcUK3klTD",
          "width": 610
        }
      }
    },
    "media:uri_template": "https://static.sfomuseum.org/media/152/782/250/3/1527822503_{secret}_{label}.{extention}",
    "sfomuseum:filename": "40775.tif",
    "sfomuseum:image_index": 5,
    "sfomuseum:image_type": "studio",
    "sfomuseum:placetype": "image",
    "sfomuseum:primary_image": 1,
    "wof:depicts": [
      102527513,
      1511944409
    ],
    "wof:name": "negative: San Francisco International Airport (SFO), aerial, South Terminal construction",
    "wof:placetype": "custom",
    "wof:placetype_alt": "image"
  },
  "geometry": {"coordinates":[-122.386155,37.616358],"type":"Point"}
}
