{
  "type": "Feature",
  "properties": {
    "iso:country": "XX",
    "media:fingerprint": "eb8ab940208a77fbbf0dbdd6531bf9025444b8be",
    "media:imagehash_avg": "a:fff0f00000fcfdf0",
    "media:imagehash_diff": "d:01c0c0b8b8a18181",
    "media:medium": "image",
    "media:mimetype": "image/tiff",
    "media:properties": {
      "colours": [
        {
          "hex": "#808080",
          "name": "#808080",
          "reference": "vibrant"
        }, 
        {
          "hex": "#b8b8b8",
          "name": "#b8b8b8",
          "reference": "vibrant"
        }, 
        {
          "hex": "#464646",
          "name": "#464646",
          "reference": "vibrant"
        }
      ],
      "sizes": {
        "b": {
          "extension": "jpg",
          "height": 768,
          "mimetype": "image/jpeg",
          "secret": "VBvW5ncS98sQd5chIbg03XUrREV2m042",
          "width": 768
        },
        "c": {
          "extension": "jpg",
          "height": 600,
          "mimetype": "image/jpeg",
          "secret": "VBvW5ncS98sQd5chIbg03XUrREV2m042",
          "width": 600
        },
        "dc": {
          "extension": "jpg",
          "height": 600,
          "mimetype": "image/jpeg",
          "secret": "VBvW5ncS98sQd5chIbg03XUrREV2m042",
          "width": 600
        },
        "ds": {
          "extension": "jpg",
          "height": 320,
          "mimetype": "image/jpeg",
          "secret": "VBvW5ncS98sQd5chIbg03XUrREV2m042",
          "width": 320
        },
        "k": {
          "extension": "jpg",
          "height": 1536,
          "mimetype": "image/jpeg",
          "secret": "VBvW5ncS98sQd5chIbg03XUrREV2m042",
          "width": 1536
        },
        "n": {
          "extension": "jpg",
          "height": 240,
          "mimetype": "image/jpeg",
          "secret": "VBvW5ncS98sQd5chIbg03XUrREV2m042",
          "width": 240
        },
        "o": {
          "extension": "jpg",
          "height": 2536,
          "mimetype": "image/jpeg",
          "secret": "kaOD2pImtXVJ1c4QIUtWiz4kg6I6eQSs",
          "width": 2536
        },
        "s": {
          "extension": "jpg",
          "height": 320,
          "mimetype": "image/jpeg",
          "secret": "VBvW5ncS98sQd5chIbg03XUrREV2m042",
          "width": 320
        },
        "z": {
          "extension": "jpg",
          "height": 480,
          "mimetype": "image/jpeg",
          "secret": "VBvW5ncS98sQd5chIbg03XUrREV2m042",
          "width": 480
        }
      }
    },
    "media:uri_template": "https://millsfield.sfomuseum.org/media/152/782/807/1/1527828071_{secret}_{label}.{extention}",
    "sfomuseum:filename": "44368.tif",
    "sfomuseum:image_index": 5,
    "sfomuseum:placetype": "image",
    "sfomuseum:primary_image": 1,
    "wof:depicts": [
      1511949103
    ],
    "wof:name": "negative: San Francisco International Airport (SFO), damaged roof vent",
    "wof:placetype": "media"
  },
  "geometry": {"coordinates":[-122.386155,37.616358],"type":"Point"}
}
