{
  "type": "Feature",
  "properties": {
    "iso:country": "XX",
    "media:fingerprint": "358b282f89450083f0f325c1d38a78f3ac1810c9",
    "media:imagehash_avg": "a:fffffff8c00001ff",
    "media:imagehash_diff": "d:4d4d4d41050d79d9",
    "media:medium": "image",
    "media:mimetype": "image/tiff",
    "media:properties": {
      "colours": [
        {
          "hex": "#808080",
          "name": "#808080",
          "reference": "vibrant"
        }, 
        {
          "hex": "#b8b8b8",
          "name": "#b8b8b8",
          "reference": "vibrant"
        }, 
        {
          "hex": "#404040",
          "name": "#404040",
          "reference": "vibrant"
        }
      ],
      "sizes": {
        "b": {
          "extension": "jpg",
          "height": 276,
          "mimetype": "image/jpeg",
          "secret": "qZbCE7knJyYM2O2Ht8WMimqQ2qXqXrnj",
          "width": 1024
        },
        "c": {
          "extension": "jpg",
          "height": 216,
          "mimetype": "image/jpeg",
          "secret": "qZbCE7knJyYM2O2Ht8WMimqQ2qXqXrnj",
          "width": 800
        },
        "dc": {
          "extension": "jpg",
          "height": 216,
          "mimetype": "image/jpeg",
          "secret": "qZbCE7knJyYM2O2Ht8WMimqQ2qXqXrnj",
          "width": 800
        },
        "ds": {
          "extension": "jpg",
          "height": 320,
          "mimetype": "image/jpeg",
          "secret": "qZbCE7knJyYM2O2Ht8WMimqQ2qXqXrnj",
          "width": 320
        },
        "k": {
          "extension": "jpg",
          "height": 553,
          "mimetype": "image/jpeg",
          "secret": "qZbCE7knJyYM2O2Ht8WMimqQ2qXqXrnj",
          "width": 2048
        },
        "n": {
          "extension": "jpg",
          "height": 86,
          "mimetype": "image/jpeg",
          "secret": "qZbCE7knJyYM2O2Ht8WMimqQ2qXqXrnj",
          "width": 320
        },
        "o": {
          "extension": "jpg",
          "height": 714,
          "mimetype": "image/jpeg",
          "secret": "jKL5AMR0eqtiwQ6APcy3qovUm2fo5IhA",
          "width": 2640
        },
        "s": {
          "extension": "jpg",
          "height": 320,
          "mimetype": "image/jpeg",
          "secret": "qZbCE7knJyYM2O2Ht8WMimqQ2qXqXrnj",
          "width": 320
        },
        "z": {
          "extension": "jpg",
          "height": 173,
          "mimetype": "image/jpeg",
          "secret": "qZbCE7knJyYM2O2Ht8WMimqQ2qXqXrnj",
          "width": 640
        }
      }
    },
    "media:uri_template": "https://millsfield.sfomuseum.org/media/152/782/106/5/1527821065_{secret}_{label}.{extention}",
    "sfomuseum:filename": "33312.tif",
    "sfomuseum:image_index": 5,
    "sfomuseum:placetype": "image",
    "sfomuseum:primary_image": 1,
    "wof:depicts": [
      1511931371
    ],
    "wof:name": "photograph: Pan American Airways, Boeing 314",
    "wof:placetype": "media"
  },
  "geometry": {"coordinates":[-122.386155,37.616358],"type":"Point"}
}
