{
  "type": "Feature",
  "properties": {
    "iso:country": "XX",
    "media:fingerprint": "f20c493d2418691f55c9f82fcf2cab9eb9c0bdd1",
    "media:imagehash_avg": "a:ff8dd9f1f1e1c1f9",
    "media:imagehash_diff": "d:b131312121812199",
    "media:medium": "image",
    "media:mimetype": "image/tiff",
    "media:properties": {
      "colours": [
        {
          "hex": "#7a7a7a",
          "name": "#7a7a7a",
          "reference": "vibrant"
        }, 
        {
          "hex": "#b8b8b8",
          "name": "#b8b8b8",
          "reference": "vibrant"
        }, 
        {
          "hex": "#404040",
          "name": "#404040",
          "reference": "vibrant"
        }
      ],
      "sizes": {
        "b": {
          "extension": "jpg",
          "height": 768,
          "mimetype": "image/jpeg",
          "secret": "gog76bNsoTDHGdXzPk932ksBwBWZXDzT",
          "width": 984
        },
        "c": {
          "extension": "jpg",
          "height": 600,
          "mimetype": "image/jpeg",
          "secret": "gog76bNsoTDHGdXzPk932ksBwBWZXDzT",
          "width": 769
        },
        "dc": {
          "extension": "jpg",
          "height": 600,
          "mimetype": "image/jpeg",
          "secret": "gog76bNsoTDHGdXzPk932ksBwBWZXDzT",
          "width": 769
        },
        "ds": {
          "extension": "jpg",
          "height": 320,
          "mimetype": "image/jpeg",
          "secret": "gog76bNsoTDHGdXzPk932ksBwBWZXDzT",
          "width": 320
        },
        "k": {
          "extension": "jpg",
          "height": 1536,
          "mimetype": "image/jpeg",
          "secret": "gog76bNsoTDHGdXzPk932ksBwBWZXDzT",
          "width": 1969
        },
        "n": {
          "extension": "jpg",
          "height": 240,
          "mimetype": "image/jpeg",
          "secret": "gog76bNsoTDHGdXzPk932ksBwBWZXDzT",
          "width": 307
        },
        "o": {
          "extension": "jpg",
          "height": 2127,
          "mimetype": "image/jpeg",
          "secret": "mCQNwfzSN4nUWPrMNVg8YTwK12wcApOD",
          "width": 2727
        },
        "s": {
          "extension": "jpg",
          "height": 320,
          "mimetype": "image/jpeg",
          "secret": "gog76bNsoTDHGdXzPk932ksBwBWZXDzT",
          "width": 320
        },
        "z": {
          "extension": "jpg",
          "height": 480,
          "mimetype": "image/jpeg",
          "secret": "gog76bNsoTDHGdXzPk932ksBwBWZXDzT",
          "width": 615
        }
      }
    },
    "media:uri_template": "https://millsfield.sfomuseum.org/media/152/782/266/7/1527822667_{secret}_{label}.{extention}",
    "sfomuseum:filename": "40850.tif",
    "sfomuseum:image_index": 5,
    "sfomuseum:placetype": "image",
    "sfomuseum:primary_image": 1,
    "wof:depicts": [
      1511944573
    ],
    "wof:name": "negative: San Francisco International Airport (SFO), aerial",
    "wof:placetype": "media"
  },
  "geometry": {"coordinates":[-122.386155,37.616358],"type":"Point"}
}
