{
  "type": "Feature",
  "properties": {
    "iso:country": "XX",
    "media:fingerprint": "4bd31ce5c35013e136e279ec2510206b43fe09dd",
    "media:imagehash_avg": "a:f8f8f0f0feeef0f8",
    "media:imagehash_diff": "d:40010040c89c03e0",
    "media:medium": "image",
    "media:mimetype": "image/tiff",
    "media:properties": {
      "colours": [
        {
          "hex": "#808080",
          "name": "#808080",
          "reference": "vibrant"
        }, 
        {
          "hex": "#c0c0c0",
          "name": "#c0c0c0",
          "reference": "vibrant"
        }, 
        {
          "hex": "#404040",
          "name": "#404040",
          "reference": "vibrant"
        }
      ],
      "sizes": {
        "b": {
          "extension": "jpg",
          "height": 768,
          "mimetype": "image/jpeg",
          "secret": "VxR5axXPjvO3tPY5F10K13I6E6sYIeiW",
          "width": 1004
        },
        "c": {
          "extension": "jpg",
          "height": 600,
          "mimetype": "image/jpeg",
          "secret": "VxR5axXPjvO3tPY5F10K13I6E6sYIeiW",
          "width": 784
        },
        "dc": {
          "extension": "jpg",
          "height": 600,
          "mimetype": "image/jpeg",
          "secret": "VxR5axXPjvO3tPY5F10K13I6E6sYIeiW",
          "width": 784
        },
        "ds": {
          "extension": "jpg",
          "height": 320,
          "mimetype": "image/jpeg",
          "secret": "VxR5axXPjvO3tPY5F10K13I6E6sYIeiW",
          "width": 320
        },
        "k": {
          "extension": "jpg",
          "height": 1536,
          "mimetype": "image/jpeg",
          "secret": "VxR5axXPjvO3tPY5F10K13I6E6sYIeiW",
          "width": 2009
        },
        "n": {
          "extension": "jpg",
          "height": 240,
          "mimetype": "image/jpeg",
          "secret": "VxR5axXPjvO3tPY5F10K13I6E6sYIeiW",
          "width": 313
        },
        "o": {
          "extension": "jpg",
          "height": 1032,
          "mimetype": "image/jpeg",
          "secret": "mrHtYTEAslo4Fh6XBOIjVFOD7AHPorlt",
          "width": 1350
        },
        "s": {
          "extension": "jpg",
          "height": 320,
          "mimetype": "image/jpeg",
          "secret": "VxR5axXPjvO3tPY5F10K13I6E6sYIeiW",
          "width": 320
        },
        "z": {
          "extension": "jpg",
          "height": 480,
          "mimetype": "image/jpeg",
          "secret": "VxR5axXPjvO3tPY5F10K13I6E6sYIeiW",
          "width": 627
        }
      }
    },
    "media:uri_template": "https://millsfield.sfomuseum.org/media/152/782/098/1/1527820981_{secret}_{label}.{extention}",
    "sfomuseum:filename": "33269.tif",
    "sfomuseum:image_index": 5,
    "sfomuseum:placetype": "image",
    "sfomuseum:primary_image": 1,
    "wof:depicts": [
      1511931449
    ],
    "wof:name": "photograph: Pan American World Airways, Lockheed L-049 Constellation",
    "wof:placetype": "media"
  },
  "geometry": {"coordinates":[-122.386155,37.616358],"type":"Point"}
}
