{
  "type": "Feature",
  "properties": {
    "iso:country": "XX",
    "media:fingerprint": "cb9ecbed809527ad329e4add8978834dff19e486",
    "media:imagehash_avg": "a:80c0ffe1e1fff800",
    "media:imagehash_diff": "d:00000e030b170001",
    "media:medium": "image",
    "media:mimetype": "image/jpeg",
    "media:properties": {
      "colours": [
        {
          "hex": "#0087bb",
          "name": "#0087bb",
          "reference": "vibrant"
        }, 
        {
          "hex": "#55b8e8",
          "name": "#55b8e8",
          "reference": "vibrant"
        }, 
        {
          "hex": "#00538c",
          "name": "#00538c",
          "reference": "vibrant"
        }, 
        {
          "hex": "#5b8eab",
          "name": "#5b8eab",
          "reference": "vibrant"
        }, 
        {
          "hex": "#c7afa7",
          "name": "#c7afa7",
          "reference": "vibrant"
        }
      ],
      "sizes": {
        "b": {
          "extension": "jpg",
          "height": 768,
          "mimetype": "image/jpeg",
          "secret": "M5LXIFPKpRaCHBnuFSPuUWtNTST65do0",
          "width": 343
        },
        "c": {
          "extension": "jpg",
          "height": 600,
          "mimetype": "image/jpeg",
          "secret": "M5LXIFPKpRaCHBnuFSPuUWtNTST65do0",
          "width": 268
        },
        "dc": {
          "extension": "jpg",
          "height": 600,
          "mimetype": "image/jpeg",
          "secret": "M5LXIFPKpRaCHBnuFSPuUWtNTST65do0",
          "width": 268
        },
        "ds": {
          "extension": "jpg",
          "height": 320,
          "mimetype": "image/jpeg",
          "secret": "M5LXIFPKpRaCHBnuFSPuUWtNTST65do0",
          "width": 320
        },
        "k": {
          "extension": "jpg",
          "height": 1536,
          "mimetype": "image/jpeg",
          "secret": "M5LXIFPKpRaCHBnuFSPuUWtNTST65do0",
          "width": 686
        },
        "n": {
          "extension": "jpg",
          "height": 240,
          "mimetype": "image/jpeg",
          "secret": "M5LXIFPKpRaCHBnuFSPuUWtNTST65do0",
          "width": 107
        },
        "o": {
          "extension": "jpg",
          "height": 3263,
          "mimetype": "image/jpeg",
          "secret": "Oo2pDERyZiNYmabp17R9jbUa4IO4uK9F",
          "width": 1459
        },
        "s": {
          "extension": "jpg",
          "height": 320,
          "mimetype": "image/jpeg",
          "secret": "M5LXIFPKpRaCHBnuFSPuUWtNTST65do0",
          "width": 320
        },
        "z": {
          "extension": "jpg",
          "height": 480,
          "mimetype": "image/jpeg",
          "secret": "M5LXIFPKpRaCHBnuFSPuUWtNTST65do0",
          "width": 214
        }
      }
    },
    "media:uri_template": "https://millsfield.sfomuseum.org/media/152/781/924/3/1527819243_{secret}_{label}.{extention}",
    "sfomuseum:filename": "25154.jpg",
    "sfomuseum:image_index": 5,
    "sfomuseum:placetype": "image",
    "sfomuseum:primary_image": 1,
    "wof:depicts": [
      1511937973
    ],
    "wof:name": "timetable: Mexicana de Aviacion",
    "wof:placetype": "media"
  },
  "geometry": {"coordinates":[-122.386155,37.616358],"type":"Point"}
}
