{
  "type": "Feature",
  "properties": {
    "iso:country": "XX",
    "media:fingerprint": "de6bbcc7146a8b21bf2b7324595d49003481d711",
    "media:imagehash_avg": "a:ffffffff00000000",
    "media:imagehash_diff": "d:f0d0d21b3bfcc0d0",
    "media:medium": "image",
    "media:mimetype": "image/tiff",
    "media:properties": {
      "colours": [
        {
          "hex": "#808080",
          "name": "#808080",
          "reference": "vibrant"
        }, 
        {
          "hex": "#b8b8b8",
          "name": "#b8b8b8",
          "reference": "vibrant"
        }, 
        {
          "hex": "#484848",
          "name": "#484848",
          "reference": "vibrant"
        }
      ],
      "sizes": {
        "b": {
          "extension": "jpg",
          "height": 768,
          "mimetype": "image/jpeg",
          "secret": "pvXRnpRqwm1p7zNR6sJwXV2edWB0GdBX",
          "width": 768
        },
        "c": {
          "extension": "jpg",
          "height": 600,
          "mimetype": "image/jpeg",
          "secret": "pvXRnpRqwm1p7zNR6sJwXV2edWB0GdBX",
          "width": 600
        },
        "dc": {
          "extension": "jpg",
          "height": 600,
          "mimetype": "image/jpeg",
          "secret": "pvXRnpRqwm1p7zNR6sJwXV2edWB0GdBX",
          "width": 600
        },
        "ds": {
          "extension": "jpg",
          "height": 320,
          "mimetype": "image/jpeg",
          "secret": "pvXRnpRqwm1p7zNR6sJwXV2edWB0GdBX",
          "width": 320
        },
        "k": {
          "extension": "jpg",
          "height": 1536,
          "mimetype": "image/jpeg",
          "secret": "pvXRnpRqwm1p7zNR6sJwXV2edWB0GdBX",
          "width": 1536
        },
        "n": {
          "extension": "jpg",
          "height": 240,
          "mimetype": "image/jpeg",
          "secret": "pvXRnpRqwm1p7zNR6sJwXV2edWB0GdBX",
          "width": 240
        },
        "o": {
          "extension": "jpg",
          "height": 1740,
          "mimetype": "image/jpeg",
          "secret": "UHjuFx4oNTOanvH7X72Ng9NEQXzjnGIa",
          "width": 1740
        },
        "s": {
          "extension": "jpg",
          "height": 320,
          "mimetype": "image/jpeg",
          "secret": "pvXRnpRqwm1p7zNR6sJwXV2edWB0GdBX",
          "width": 320
        },
        "z": {
          "extension": "jpg",
          "height": 480,
          "mimetype": "image/jpeg",
          "secret": "pvXRnpRqwm1p7zNR6sJwXV2edWB0GdBX",
          "width": 480
        }
      }
    },
    "media:uri_template": "https://millsfield.sfomuseum.org/media/152/782/657/1/1527826571_{secret}_{label}.{extention}",
    "sfomuseum:filename": "43700.tif",
    "sfomuseum:image_index": 5,
    "sfomuseum:placetype": "image",
    "sfomuseum:primary_image": 1,
    "wof:depicts": [
      1511947609
    ],
    "wof:name": "photograph: San Francisco International Airport (SFO), construction, damaged equipment",
    "wof:placetype": "media"
  },
  "geometry": {"coordinates":[-122.386155,37.616358],"type":"Point"}
}
