{
  "type": "Feature",
  "properties": {
    "iso:country": "XX",
    "media:fingerprint": "22e7153b3bf1697ab5b3d43d0019c664385a3a79",
    "media:imagehash_avg": "a:ffff3e10181c1c10",
    "media:imagehash_diff": "d:f9f178f0f8f8f0f0",
    "media:medium": "image",
    "media:mimetype": "image/tiff",
    "media:properties": {
      "colours": [
        {
          "hex": "#808080",
          "name": "#808080",
          "reference": "vibrant"
        }, 
        {
          "hex": "#c0c0c0",
          "name": "#c0c0c0",
          "reference": "vibrant"
        }, 
        {
          "hex": "#404040",
          "name": "#404040",
          "reference": "vibrant"
        }
      ],
      "sizes": {
        "b": {
          "extension": "jpg",
          "height": 767,
          "mimetype": "image/jpeg",
          "secret": "CfnoVMQxVMqbtj7v7gHpOurks1gF3NOl",
          "width": 988
        },
        "c": {
          "extension": "jpg",
          "height": 600,
          "mimetype": "image/jpeg",
          "secret": "CfnoVMQxVMqbtj7v7gHpOurks1gF3NOl",
          "width": 772
        },
        "dc": {
          "extension": "jpg",
          "height": 600,
          "mimetype": "image/jpeg",
          "secret": "CfnoVMQxVMqbtj7v7gHpOurks1gF3NOl",
          "width": 772
        },
        "ds": {
          "extension": "jpg",
          "height": 320,
          "mimetype": "image/jpeg",
          "secret": "CfnoVMQxVMqbtj7v7gHpOurks1gF3NOl",
          "width": 320
        },
        "k": {
          "extension": "jpg",
          "height": 1535,
          "mimetype": "image/jpeg",
          "secret": "CfnoVMQxVMqbtj7v7gHpOurks1gF3NOl",
          "width": 1976
        },
        "n": {
          "extension": "jpg",
          "height": 240,
          "mimetype": "image/jpeg",
          "secret": "CfnoVMQxVMqbtj7v7gHpOurks1gF3NOl",
          "width": 308
        },
        "o": {
          "extension": "jpg",
          "height": 2140,
          "mimetype": "image/jpeg",
          "secret": "VyAwurF0eltKFrFc0UA7vykVdSGNECcQ",
          "width": 2754
        },
        "s": {
          "extension": "jpg",
          "height": 320,
          "mimetype": "image/jpeg",
          "secret": "CfnoVMQxVMqbtj7v7gHpOurks1gF3NOl",
          "width": 320
        },
        "z": {
          "extension": "jpg",
          "height": 480,
          "mimetype": "image/jpeg",
          "secret": "CfnoVMQxVMqbtj7v7gHpOurks1gF3NOl",
          "width": 617
        }
      }
    },
    "media:uri_template": "https://millsfield.sfomuseum.org/media/152/782/228/9/1527822289_{secret}_{label}.{extention}",
    "sfomuseum:filename": "40642.tif",
    "sfomuseum:image_index": 5,
    "sfomuseum:placetype": "image",
    "sfomuseum:primary_image": 1,
    "wof:depicts": [
      1511944195
    ],
    "wof:name": "negative: San Francisco International Airport (SFO), drainage canals",
    "wof:placetype": "media"
  },
  "geometry": {"coordinates":[-122.386155,37.616358],"type":"Point"}
}
