{
  "type": "Feature",
  "properties": {
    "iso:country": "XX",
    "media:fingerprint": "ea5f2578f4296a2e7fe480fc48f2b3498bad5f6d",
    "media:imagehash_avg": "a:ffc7c3c3c3e3ffff",
    "media:imagehash_diff": "d:c89e9e868686cc8e",
    "media:medium": "image",
    "media:mimetype": "image/tiff",
    "media:properties": {
      "colours": [
        {
          "hex": "#d8ad10",
          "name": "#d8ad10",
          "reference": "vibrant"
        },
        {
          "hex": "#78aedc",
          "name": "#78aedc",
          "reference": "vibrant"
        },
        {
          "hex": "#7d320c",
          "name": "#7d320c",
          "reference": "vibrant"
        },
        {
          "hex": "#8c836d",
          "name": "#8c836d",
          "reference": "vibrant"
        },
        {
          "hex": "#739cbd",
          "name": "#739cbd",
          "reference": "vibrant"
        }
      ],
      "sizes": {
        "b": {
          "extension": "jpg",
          "height": 767,
          "mimetype": "image/jpeg",
          "secret": "JlEjIvIygxQFICB3rgtFYLqoM4YXWET3",
          "width": 556
        },
        "c": {
          "extension": "jpg",
          "height": 600,
          "mimetype": "image/jpeg",
          "secret": "JlEjIvIygxQFICB3rgtFYLqoM4YXWET3",
          "width": 434
        },
        "dc": {
          "extension": "jpg",
          "height": 600,
          "mimetype": "image/jpeg",
          "secret": "JlEjIvIygxQFICB3rgtFYLqoM4YXWET3",
          "width": 434
        },
        "ds": {
          "extension": "jpg",
          "height": 320,
          "mimetype": "image/jpeg",
          "secret": "JlEjIvIygxQFICB3rgtFYLqoM4YXWET3",
          "width": 320
        },
        "k": {
          "extension": "jpg",
          "height": 1535,
          "mimetype": "image/jpeg",
          "secret": "JlEjIvIygxQFICB3rgtFYLqoM4YXWET3",
          "width": 1112
        },
        "n": {
          "extension": "jpg",
          "height": 240,
          "mimetype": "image/jpeg",
          "secret": "JlEjIvIygxQFICB3rgtFYLqoM4YXWET3",
          "width": 173
        },
        "o": {
          "extension": "jpg",
          "height": 2868,
          "mimetype": "image/jpeg",
          "secret": "Ws6jBNIWLHCtAiJ7lHq8Hmy3L1f91t2E",
          "width": 2078
        },
        "s": {
          "extension": "jpg",
          "height": 320,
          "mimetype": "image/jpeg",
          "secret": "JlEjIvIygxQFICB3rgtFYLqoM4YXWET3",
          "width": 320
        },
        "z": {
          "extension": "jpg",
          "height": 480,
          "mimetype": "image/jpeg",
          "secret": "JlEjIvIygxQFICB3rgtFYLqoM4YXWET3",
          "width": 347
        }
      }
    },
    "media:uri_template": "https://static.sfomuseum.org/media/152/784/833/5/1527848335_{secret}_{label}.{extention}",
    "sfomuseum:filename": "72408.tif",
    "sfomuseum:image_index": 5,
    "sfomuseum:image_type": "studio",
    "sfomuseum:placetype": "image",
    "sfomuseum:primary_image": 1,
    "wof:depicts": [
      1159285413,
      1511928583
    ],
    "wof:name": "menu: United Airlines, First Class",
    "wof:placetype": "custom",
    "wof:placetype_alt": "image"
  },
  "geometry": {"coordinates":[-122.386155,37.616358],"type":"Point"}
}
