{
  "type": "Feature",
  "properties": {
    "iso:country": "XX",
    "media:fingerprint": "6db72880c0da46e3723180895a28ed94e8b7dd75",
    "media:imagehash_avg": "a:011139391901ffff",
    "media:imagehash_diff": "d:61e1e1e1e969e1f0",
    "media:medium": "image",
    "media:mimetype": "image/tiff",
    "media:properties": {
      "colours": [
        {
          "hex": "#808080",
          "name": "#808080",
          "reference": "vibrant"
        }, 
        {
          "hex": "#c0c0c0",
          "name": "#c0c0c0",
          "reference": "vibrant"
        }, 
        {
          "hex": "#404040",
          "name": "#404040",
          "reference": "vibrant"
        }
      ],
      "sizes": {
        "b": {
          "extension": "jpg",
          "height": 768,
          "mimetype": "image/jpeg",
          "secret": "JDPEujIjxfWo7SZslrhSdeOzMaTq2ZpS",
          "width": 976
        },
        "c": {
          "extension": "jpg",
          "height": 600,
          "mimetype": "image/jpeg",
          "secret": "JDPEujIjxfWo7SZslrhSdeOzMaTq2ZpS",
          "width": 763
        },
        "dc": {
          "extension": "jpg",
          "height": 600,
          "mimetype": "image/jpeg",
          "secret": "JDPEujIjxfWo7SZslrhSdeOzMaTq2ZpS",
          "width": 763
        },
        "ds": {
          "extension": "jpg",
          "height": 320,
          "mimetype": "image/jpeg",
          "secret": "JDPEujIjxfWo7SZslrhSdeOzMaTq2ZpS",
          "width": 320
        },
        "k": {
          "extension": "jpg",
          "height": 1536,
          "mimetype": "image/jpeg",
          "secret": "JDPEujIjxfWo7SZslrhSdeOzMaTq2ZpS",
          "width": 1953
        },
        "n": {
          "extension": "jpg",
          "height": 240,
          "mimetype": "image/jpeg",
          "secret": "JDPEujIjxfWo7SZslrhSdeOzMaTq2ZpS",
          "width": 305
        },
        "o": {
          "extension": "jpg",
          "height": 2154,
          "mimetype": "image/jpeg",
          "secret": "WGfOvq1UtrZA9L5N3L4iwmra4V1suRG3",
          "width": 2740
        },
        "s": {
          "extension": "jpg",
          "height": 320,
          "mimetype": "image/jpeg",
          "secret": "JDPEujIjxfWo7SZslrhSdeOzMaTq2ZpS",
          "width": 320
        },
        "z": {
          "extension": "jpg",
          "height": 480,
          "mimetype": "image/jpeg",
          "secret": "JDPEujIjxfWo7SZslrhSdeOzMaTq2ZpS",
          "width": 610
        }
      }
    },
    "media:uri_template": "https://millsfield.sfomuseum.org/media/152/782/592/1/1527825921_{secret}_{label}.{extention}",
    "sfomuseum:filename": "43396.tif",
    "sfomuseum:image_index": 5,
    "sfomuseum:placetype": "image",
    "sfomuseum:primary_image": 1,
    "wof:depicts": [
      1511946955
    ],
    "wof:name": "negative: San Francisco International Airport (SFO), diagram of regional flights",
    "wof:placetype": "media"
  },
  "geometry": {"coordinates":[-122.386155,37.616358],"type":"Point"}
}
