{
  "type": "Feature",
  "properties": {
    "iso:country":"XX",
    "media:medium":"image",
    "sfomuseum:filename":"62906.tif",
    "sfomuseum:image_index":5,
    "sfomuseum:placetype":"image",
    "sfomuseum:primary_image":0,
    "wof:depicts":[
        1511954115
    ],
    "wof:name":"airmail flight cover: Panagra (Pan American-Grace Airways), Douglas DC-8, FAM-5, FAM-9",
    "wof:placetype":"media"
},
  "geometry": {"coordinates":[-122.386155,37.616358],"type":"Point"}
}