{
  "type": "Feature",
  "properties": {
    "media:fingerprint": "b95a3ebfe0e79350caee54c68dc91a54640b33f3",
    "media:imagehash_avg": "a:ffffff7820000000",
    "media:imagehash_diff": "d:e2cecbc0d8416060",
    "media:mimetype": "image/tiff",
    "media:properties": {
      "colours": [
        {
          "hex": "#7a7a7a",
          "name": "#7a7a7a",
          "reference": "vibrant"
        },
        {
          "hex": "#b8b8b8",
          "name": "#b8b8b8",
          "reference": "vibrant"
        },
        {
          "hex": "#464646",
          "name": "#464646",
          "reference": "vibrant"
        }
      ],
      "sizes": {
        "b": {
          "extension": "jpg",
          "height": 768,
          "mimetype": "image/jpeg",
          "secret": "ps9QteomZH01msMX3LRPiaywgrJ6k1TU",
          "width": 601
        },
        "c": {
          "extension": "jpg",
          "height": 600,
          "mimetype": "image/jpeg",
          "secret": "ps9QteomZH01msMX3LRPiaywgrJ6k1TU",
          "width": 470
        },
        "dc": {
          "extension": "jpg",
          "height": 600,
          "mimetype": "image/jpeg",
          "secret": "ps9QteomZH01msMX3LRPiaywgrJ6k1TU",
          "width": 470
        },
        "ds": {
          "extension": "jpg",
          "height": 320,
          "mimetype": "image/jpeg",
          "secret": "ps9QteomZH01msMX3LRPiaywgrJ6k1TU",
          "width": 320
        },
        "k": {
          "extension": "jpg",
          "height": 1536,
          "mimetype": "image/jpeg",
          "secret": "ps9QteomZH01msMX3LRPiaywgrJ6k1TU",
          "width": 1203
        },
        "n": {
          "extension": "jpg",
          "height": 240,
          "mimetype": "image/jpeg",
          "secret": "ps9QteomZH01msMX3LRPiaywgrJ6k1TU",
          "width": 188
        },
        "o": {
          "extension": "jpg",
          "height": 2665,
          "mimetype": "image/jpeg",
          "secret": "XuQEjxDZefXgqJy6WGRKHRDReV9fuMhw",
          "width": 2088
        },
        "s": {
          "extension": "jpg",
          "height": 320,
          "mimetype": "image/jpeg",
          "secret": "ps9QteomZH01msMX3LRPiaywgrJ6k1TU",
          "width": 320
        },
        "z": {
          "extension": "jpg",
          "height": 480,
          "mimetype": "image/jpeg",
          "secret": "ps9QteomZH01msMX3LRPiaywgrJ6k1TU",
          "width": 376
        }
      }
    },
    "media:uri_template": "https://static.sfomuseum.org/media/174/651/208/5/1746512085_{secret}_{label}.{extention}",
    "sfomuseum:filename": "45906.tif",
    "sfomuseum:image_index": 0,
    "sfomuseum:image_type": "studio",
    "sfomuseum:placetype": "image",
    "sfomuseum:primary_image": 1,
    "wof:depicts": [
      1159285393,
      1159287531,
      1729563711
    ],
    "wof:name": "negative: TWA (Trans World Airlines), William E. Malarkey, Vice President, Labor Relations",
    "wof:placetype": "custom",
    "wof:placetype_alt": "image"
  },
  "geometry": {"coordinates":[-122.386155,37.616357],"type":"Point"}
}
