{
  "type": "Feature",
  "properties": {
    "iso:country": "XX",
    "media:fingerprint": "0c895fea111b271cede3161792797bd05c5b9e08",
    "media:imagehash_avg": "a:bfffdcfcbc020000",
    "media:imagehash_diff": "d:476d3424705cd8d4",
    "media:medium": "image",
    "media:mimetype": "image/tiff",
    "media:properties": {
      "colours": [
        {
          "hex": "#e1e9d1",
          "name": "#e1e9d1",
          "reference": "vibrant"
        },
        {
          "hex": "#99905f",
          "name": "#99905f",
          "reference": "vibrant"
        },
        {
          "hex": "#b4d9b1",
          "name": "#b4d9b1",
          "reference": "vibrant"
        },
        {
          "hex": "#50452a",
          "name": "#50452a",
          "reference": "vibrant"
        }
      ],
      "sizes": {
        "b": {
          "extension": "jpg",
          "height": 671,
          "mimetype": "image/jpeg",
          "secret": "JgRgkQLubJYk79bc7E8xvcWw6gRav39s",
          "width": 1024
        },
        "c": {
          "extension": "jpg",
          "height": 524,
          "mimetype": "image/jpeg",
          "secret": "JgRgkQLubJYk79bc7E8xvcWw6gRav39s",
          "width": 800
        },
        "dc": {
          "extension": "jpg",
          "height": 524,
          "mimetype": "image/jpeg",
          "secret": "JgRgkQLubJYk79bc7E8xvcWw6gRav39s",
          "width": 800
        },
        "ds": {
          "extension": "jpg",
          "height": 320,
          "mimetype": "image/jpeg",
          "secret": "JgRgkQLubJYk79bc7E8xvcWw6gRav39s",
          "width": 320
        },
        "k": {
          "extension": "jpg",
          "height": 1342,
          "mimetype": "image/jpeg",
          "secret": "JgRgkQLubJYk79bc7E8xvcWw6gRav39s",
          "width": 2048
        },
        "n": {
          "extension": "jpg",
          "height": 209,
          "mimetype": "image/jpeg",
          "secret": "JgRgkQLubJYk79bc7E8xvcWw6gRav39s",
          "width": 320
        },
        "o": {
          "extension": "jpg",
          "height": 1041,
          "mimetype": "image/jpeg",
          "secret": "YzRui0wUFvSLrcIXlK5kmy3tBWmoPtxF",
          "width": 1588
        },
        "s": {
          "extension": "jpg",
          "height": 320,
          "mimetype": "image/jpeg",
          "secret": "JgRgkQLubJYk79bc7E8xvcWw6gRav39s",
          "width": 320
        },
        "z": {
          "extension": "jpg",
          "height": 419,
          "mimetype": "image/jpeg",
          "secret": "JgRgkQLubJYk79bc7E8xvcWw6gRav39s",
          "width": 640
        }
      }
    },
    "media:uri_template": "https://static.sfomuseum.org/media/152/782/839/3/1527828393_{secret}_{label}.{extention}",
    "sfomuseum:filename": "44572.tif",
    "sfomuseum:image_index": 5,
    "sfomuseum:image_type": "studio",
    "sfomuseum:placetype": "image",
    "sfomuseum:primary_image": 1,
    "wof:depicts": [
      1511949425,
      102527513
    ],
    "wof:name": "negative: San Francisco International Airport (SFO), Medical Clinic dedication",
    "wof:placetype": "custom",
    "wof:placetype_alt": "image"
  },
  "geometry": {"coordinates":[-122.386155,37.616358],"type":"Point"}
}
