{
  "type": "Feature",
  "properties": {
    "iso:country": "XX",
    "media:fingerprint": "7b4d20704a957bdb438c303bf620d32de607d8c8",
    "media:imagehash_avg": "a:1c04063f39393d38",
    "media:imagehash_diff": "d:f9ec6cebd3e3f1f1",
    "media:medium": "image",
    "media:mimetype": "image/tiff",
    "media:properties": {
      "colours": [
        {
          "hex": "#a78846",
          "name": "#a78846",
          "reference": "vibrant"
        }, 
        {
          "hex": "#d9e49c",
          "name": "#d9e49c",
          "reference": "vibrant"
        }, 
        {
          "hex": "#686f34",
          "name": "#686f34",
          "reference": "vibrant"
        }, 
        {
          "hex": "#83a45e",
          "name": "#83a45e",
          "reference": "vibrant"
        }, 
        {
          "hex": "#b1b26a",
          "name": "#b1b26a",
          "reference": "vibrant"
        }
      ],
      "sizes": {
        "b": {
          "extension": "jpg",
          "height": 664,
          "mimetype": "image/jpeg",
          "secret": "jwyeFJ4BSOsxsDP5zya8FsuxOUNZxOWc",
          "width": 1024
        },
        "c": {
          "extension": "jpg",
          "height": 519,
          "mimetype": "image/jpeg",
          "secret": "jwyeFJ4BSOsxsDP5zya8FsuxOUNZxOWc",
          "width": 800
        },
        "dc": {
          "extension": "jpg",
          "height": 519,
          "mimetype": "image/jpeg",
          "secret": "jwyeFJ4BSOsxsDP5zya8FsuxOUNZxOWc",
          "width": 800
        },
        "ds": {
          "extension": "jpg",
          "height": 320,
          "mimetype": "image/jpeg",
          "secret": "jwyeFJ4BSOsxsDP5zya8FsuxOUNZxOWc",
          "width": 320
        },
        "k": {
          "extension": "jpg",
          "height": 1329,
          "mimetype": "image/jpeg",
          "secret": "jwyeFJ4BSOsxsDP5zya8FsuxOUNZxOWc",
          "width": 2048
        },
        "n": {
          "extension": "jpg",
          "height": 207,
          "mimetype": "image/jpeg",
          "secret": "jwyeFJ4BSOsxsDP5zya8FsuxOUNZxOWc",
          "width": 320
        },
        "o": {
          "extension": "jpg",
          "height": 1009,
          "mimetype": "image/jpeg",
          "secret": "5zfZVED5JmC7GuKgeRKbRrnudNbMbaXM",
          "width": 1554
        },
        "s": {
          "extension": "jpg",
          "height": 320,
          "mimetype": "image/jpeg",
          "secret": "jwyeFJ4BSOsxsDP5zya8FsuxOUNZxOWc",
          "width": 320
        },
        "z": {
          "extension": "jpg",
          "height": 415,
          "mimetype": "image/jpeg",
          "secret": "jwyeFJ4BSOsxsDP5zya8FsuxOUNZxOWc",
          "width": 640
        }
      }
    },
    "media:uri_template": "https://millsfield.sfomuseum.org/media/152/782/815/9/1527828159_{secret}_{label}.{extention}",
    "sfomuseum:filename": "44407.tif",
    "sfomuseum:image_index": 5,
    "sfomuseum:placetype": "image",
    "sfomuseum:primary_image": 1,
    "wof:depicts": [
      1511949191
    ],
    "wof:name": "negative: San Francisco International Airport (SFO), personnel",
    "wof:placetype": "media"
  },
  "geometry": {"coordinates":[-122.386155,37.616358],"type":"Point"}
}
