{
  "type": "Feature",
  "properties": {
    "iso:country": "XX",
    "media:fingerprint": "17bd86541eabb0ec822d858e513e2719af9d0387",
    "media:imagehash_avg": "a:7f7c447070f0e3ff",
    "media:imagehash_diff": "d:e3d88ae6e6a72e9c",
    "media:medium": "image",
    "media:mimetype": "image/tiff",
    "media:properties": {
      "colours": [
        {
          "hex": "#c53330",
          "name": "#c53330",
          "reference": "vibrant"
        }, 
        {
          "hex": "#75a3ce",
          "name": "#75a3ce",
          "reference": "vibrant"
        }, 
        {
          "hex": "#901f20",
          "name": "#901f20",
          "reference": "vibrant"
        }, 
        {
          "hex": "#5b7f9f",
          "name": "#5b7f9f",
          "reference": "vibrant"
        }, 
        {
          "hex": "#cd9e99",
          "name": "#cd9e99",
          "reference": "vibrant"
        }
      ],
      "sizes": {
        "b": {
          "extension": "jpg",
          "height": 768,
          "mimetype": "image/jpeg",
          "secret": "tgyLp1cBrYnbZEjB8EOYoADzO2rtHtM8",
          "width": 965
        },
        "c": {
          "extension": "jpg",
          "height": 600,
          "mimetype": "image/jpeg",
          "secret": "tgyLp1cBrYnbZEjB8EOYoADzO2rtHtM8",
          "width": 754
        },
        "dc": {
          "extension": "jpg",
          "height": 600,
          "mimetype": "image/jpeg",
          "secret": "tgyLp1cBrYnbZEjB8EOYoADzO2rtHtM8",
          "width": 754
        },
        "ds": {
          "extension": "jpg",
          "height": 320,
          "mimetype": "image/jpeg",
          "secret": "tgyLp1cBrYnbZEjB8EOYoADzO2rtHtM8",
          "width": 320
        },
        "k": {
          "extension": "jpg",
          "height": 1536,
          "mimetype": "image/jpeg",
          "secret": "tgyLp1cBrYnbZEjB8EOYoADzO2rtHtM8",
          "width": 1931
        },
        "n": {
          "extension": "jpg",
          "height": 240,
          "mimetype": "image/jpeg",
          "secret": "tgyLp1cBrYnbZEjB8EOYoADzO2rtHtM8",
          "width": 301
        },
        "o": {
          "extension": "jpg",
          "height": 1326,
          "mimetype": "image/jpeg",
          "secret": "LohASpki7qN7wvjXymJrwgYWNcADx75y",
          "width": 1667
        },
        "s": {
          "extension": "jpg",
          "height": 320,
          "mimetype": "image/jpeg",
          "secret": "tgyLp1cBrYnbZEjB8EOYoADzO2rtHtM8",
          "width": 320
        },
        "z": {
          "extension": "jpg",
          "height": 480,
          "mimetype": "image/jpeg",
          "secret": "tgyLp1cBrYnbZEjB8EOYoADzO2rtHtM8",
          "width": 603
        }
      }
    },
    "media:uri_template": "https://millsfield.sfomuseum.org/media/152/785/737/5/1527857375_{secret}_{label}.{extention}",
    "sfomuseum:filename": "1998.110.002_bk1.tif",
    "sfomuseum:image_index": 0,
    "sfomuseum:placetype": "image",
    "sfomuseum:primary_image": 0,
    "wof:depicts": [
      1511908315
    ],
    "wof:name": "airline bag: TWA (Trans World Airlines)",
    "wof:placetype": "media"
  },
  "geometry": {"coordinates":[-122.386155,37.616358],"type":"Point"}
}
