{
  "type": "Feature",
  "properties": {
    "sfomuseum:filename": "themometer.jpg",
    "sfomuseum:image_index": 1,
    "sfomuseum:image_type": "curator",
    "sfomuseum:placetype": "image",
    "sfomuseum:primary_image": 1,
    "wof:depicts": [
      1511924749,
      1159284991,
      1159291193
    ],
    "wof:name": "thermometer: Pan American Airways, Martin M-130 “China Clipper”",
    "wof:placetype": "custom"
  },
  "geometry": {"coordinates":[-122.386155,37.616357],"type":"Point"}
}
