{
  "type": "Feature",
  "properties": {
    "iso:country": "XX",
    "media:fingerprint": "28a808e4e37b974d1803e4b762517635c6061410",
    "media:imagehash_avg": "a:ffffff0000f0fcf8",
    "media:imagehash_diff": "d:e0e0e0fa02c0a0b0",
    "media:medium": "image",
    "media:mimetype": "image/tiff",
    "media:properties": {
      "colours": [
        {
          "hex": "#808080",
          "name": "#808080",
          "reference": "vibrant"
        }, 
        {
          "hex": "#c6c6c6",
          "name": "#c6c6c6",
          "reference": "vibrant"
        }, 
        {
          "hex": "#454545",
          "name": "#454545",
          "reference": "vibrant"
        }
      ],
      "sizes": {
        "b": {
          "extension": "jpg",
          "height": 768,
          "mimetype": "image/jpeg",
          "secret": "7TXuYQmUc1UQNh6PMhJUm5TduFZAQWMb",
          "width": 767
        },
        "c": {
          "extension": "jpg",
          "height": 600,
          "mimetype": "image/jpeg",
          "secret": "7TXuYQmUc1UQNh6PMhJUm5TduFZAQWMb",
          "width": 599
        },
        "dc": {
          "extension": "jpg",
          "height": 600,
          "mimetype": "image/jpeg",
          "secret": "7TXuYQmUc1UQNh6PMhJUm5TduFZAQWMb",
          "width": 599
        },
        "ds": {
          "extension": "jpg",
          "height": 320,
          "mimetype": "image/jpeg",
          "secret": "7TXuYQmUc1UQNh6PMhJUm5TduFZAQWMb",
          "width": 320
        },
        "k": {
          "extension": "jpg",
          "height": 1536,
          "mimetype": "image/jpeg",
          "secret": "7TXuYQmUc1UQNh6PMhJUm5TduFZAQWMb",
          "width": 1535
        },
        "n": {
          "extension": "jpg",
          "height": 240,
          "mimetype": "image/jpeg",
          "secret": "7TXuYQmUc1UQNh6PMhJUm5TduFZAQWMb",
          "width": 239
        },
        "o": {
          "extension": "jpg",
          "height": 1836,
          "mimetype": "image/jpeg",
          "secret": "IXInpSoAyEx5kfZVzG5C9sbNDFP50wU2",
          "width": 1835
        },
        "s": {
          "extension": "jpg",
          "height": 320,
          "mimetype": "image/jpeg",
          "secret": "7TXuYQmUc1UQNh6PMhJUm5TduFZAQWMb",
          "width": 320
        },
        "z": {
          "extension": "jpg",
          "height": 480,
          "mimetype": "image/jpeg",
          "secret": "7TXuYQmUc1UQNh6PMhJUm5TduFZAQWMb",
          "width": 479
        }
      }
    },
    "media:uri_template": "https://millsfield.sfomuseum.org/media/152/782/646/7/1527826467_{secret}_{label}.{extention}",
    "sfomuseum:filename": "43653.tif",
    "sfomuseum:image_index": 5,
    "sfomuseum:placetype": "image",
    "sfomuseum:primary_image": 1,
    "wof:depicts": [
      1511947507
    ],
    "wof:name": "photograph: San Francisco International Airport (SFO), United Air Lines service center construction",
    "wof:placetype": "media"
  },
  "geometry": {"coordinates":[-122.386155,37.616358],"type":"Point"}
}
