{
  "type": "Feature",
  "properties": {
    "iso:country":"US",
    "media:medium":"image",
    "sfomuseum:filename":"1999.015.061.tif",
    "sfomuseum:image_index":5,
    "sfomuseum:placetype":"image",
    "sfomuseum:primary_image":1,
    "wof:depicts":[
        1511908991
    ],
    "wof:name":"route map: United Air Lines, system map",
    "wof:placetype":"media"
},
  "geometry": {"coordinates":[-122.386155,37.616358],"type":"Point"}
}