{
  "type": "Feature",
  "properties": {
    "iso:country": "XX",
    "media:fingerprint": "5be6e7461539ab764171ab6a2ee42ea0f27287da",
    "media:imagehash_avg": "a:ffffff7f01000000",
    "media:imagehash_diff": "d:4060e8ef073730e0",
    "media:medium": "image",
    "media:mimetype": "image/tiff",
    "media:properties": {
      "colours": [
        {
          "hex": "#808080",
          "name": "#808080",
          "reference": "vibrant"
        }, 
        {
          "hex": "#b6b6b6",
          "name": "#b6b6b6",
          "reference": "vibrant"
        }, 
        {
          "hex": "#484848",
          "name": "#484848",
          "reference": "vibrant"
        }
      ],
      "sizes": {
        "b": {
          "extension": "jpg",
          "height": 768,
          "mimetype": "image/jpeg",
          "secret": "XI2AqaDkmkaGvdCVrHipGkl5kJvxzqu3",
          "width": 776
        },
        "c": {
          "extension": "jpg",
          "height": 600,
          "mimetype": "image/jpeg",
          "secret": "XI2AqaDkmkaGvdCVrHipGkl5kJvxzqu3",
          "width": 606
        },
        "dc": {
          "extension": "jpg",
          "height": 600,
          "mimetype": "image/jpeg",
          "secret": "XI2AqaDkmkaGvdCVrHipGkl5kJvxzqu3",
          "width": 606
        },
        "ds": {
          "extension": "jpg",
          "height": 320,
          "mimetype": "image/jpeg",
          "secret": "XI2AqaDkmkaGvdCVrHipGkl5kJvxzqu3",
          "width": 320
        },
        "k": {
          "extension": "jpg",
          "height": 1536,
          "mimetype": "image/jpeg",
          "secret": "XI2AqaDkmkaGvdCVrHipGkl5kJvxzqu3",
          "width": 1552
        },
        "n": {
          "extension": "jpg",
          "height": 239,
          "mimetype": "image/jpeg",
          "secret": "XI2AqaDkmkaGvdCVrHipGkl5kJvxzqu3",
          "width": 242
        },
        "o": {
          "extension": "jpg",
          "height": 2563,
          "mimetype": "image/jpeg",
          "secret": "YfrkO2QX94WoN0xFhZQARDFdvQmnMwNl",
          "width": 2590
        },
        "s": {
          "extension": "jpg",
          "height": 320,
          "mimetype": "image/jpeg",
          "secret": "XI2AqaDkmkaGvdCVrHipGkl5kJvxzqu3",
          "width": 320
        },
        "z": {
          "extension": "jpg",
          "height": 479,
          "mimetype": "image/jpeg",
          "secret": "XI2AqaDkmkaGvdCVrHipGkl5kJvxzqu3",
          "width": 485
        }
      }
    },
    "media:uri_template": "https://millsfield.sfomuseum.org/media/152/782/723/7/1527827237_{secret}_{label}.{extention}",
    "sfomuseum:filename": "43998.tif",
    "sfomuseum:image_index": 5,
    "sfomuseum:placetype": "image",
    "sfomuseum:primary_image": 1,
    "wof:depicts": [
      1511948275
    ],
    "wof:name": "negative: San Francisco International Airport (SFO), aerial, Central Terminal",
    "wof:placetype": "media"
  },
  "geometry": {"coordinates":[-122.386155,37.616358],"type":"Point"}
}
