{
  "type": "Feature",
  "properties": {
    "iso:country": "XX",
    "media:fingerprint": "7e4f53fe7476fccad749d7c27e48e9b27d2ee61c",
    "media:imagehash_avg": "a:ff1f0918011f1fbf",
    "media:imagehash_diff": "d:797d71713d7d7d7d",
    "media:medium": "image",
    "media:mimetype": "image/tiff",
    "media:properties": {
      "colours": [
        {
          "hex": "#f0e7c8",
          "name": "#f0e7c8",
          "reference": "vibrant"
        },
        {
          "hex": "#969075",
          "name": "#969075",
          "reference": "vibrant"
        },
        {
          "hex": "#c7bca1",
          "name": "#c7bca1",
          "reference": "vibrant"
        },
        {
          "hex": "#464533",
          "name": "#464533",
          "reference": "vibrant"
        }
      ],
      "sizes": {
        "b": {
          "extension": "jpg",
          "height": 768,
          "mimetype": "image/jpeg",
          "secret": "Y7iIkwJNMeOcx0dWj9HyaEGc1IBOBLzS",
          "width": 999
        },
        "c": {
          "extension": "jpg",
          "height": 600,
          "mimetype": "image/jpeg",
          "secret": "Y7iIkwJNMeOcx0dWj9HyaEGc1IBOBLzS",
          "width": 780
        },
        "dc": {
          "extension": "jpg",
          "height": 600,
          "mimetype": "image/jpeg",
          "secret": "Y7iIkwJNMeOcx0dWj9HyaEGc1IBOBLzS",
          "width": 780
        },
        "ds": {
          "extension": "jpg",
          "height": 320,
          "mimetype": "image/jpeg",
          "secret": "Y7iIkwJNMeOcx0dWj9HyaEGc1IBOBLzS",
          "width": 320
        },
        "k": {
          "extension": "jpg",
          "height": 1536,
          "mimetype": "image/jpeg",
          "secret": "Y7iIkwJNMeOcx0dWj9HyaEGc1IBOBLzS",
          "width": 1998
        },
        "n": {
          "extension": "jpg",
          "height": 240,
          "mimetype": "image/jpeg",
          "secret": "Y7iIkwJNMeOcx0dWj9HyaEGc1IBOBLzS",
          "width": 312
        },
        "o": {
          "extension": "jpg",
          "height": 1003,
          "mimetype": "image/jpeg",
          "secret": "mjTmdA1SqdsS676Mx5oNXmeYZK3AVhkl",
          "width": 1305
        },
        "s": {
          "extension": "jpg",
          "height": 320,
          "mimetype": "image/jpeg",
          "secret": "Y7iIkwJNMeOcx0dWj9HyaEGc1IBOBLzS",
          "width": 320
        },
        "z": {
          "extension": "jpg",
          "height": 480,
          "mimetype": "image/jpeg",
          "secret": "Y7iIkwJNMeOcx0dWj9HyaEGc1IBOBLzS",
          "width": 624
        }
      }
    },
    "media:uri_template": "https://static.sfomuseum.org/media/152/785/555/3/1527855553_{secret}_{label}.{extention}",
    "sfomuseum:filename": "2010.174.272.tif",
    "sfomuseum:image_index": 5,
    "sfomuseum:image_type": "studio",
    "sfomuseum:placetype": "image",
    "sfomuseum:primary_image": 1,
    "wof:depicts": [
      1511942399
    ],
    "wof:name": "photograph: San Francisco Bay Area aerial, Bernal Heights",
    "wof:placetype": "custom",
    "wof:placetype_alt": "image"
  },
  "geometry": {"coordinates":[-122.386155,37.616358],"type":"Point"}
}
