{
  "type": "Feature",
  "properties": {
    "iso:country": "XX",
    "media:fingerprint": "61d78c2a1a5c9a17d08154a42cfeea8a40abb86f",
    "media:imagehash_avg": "a:fffff9e1c0d00000",
    "media:imagehash_diff": "d:f0f82307062465e4",
    "media:medium": "image",
    "media:mimetype": "image/tiff",
    "media:properties": {
      "colours": [
        {
          "hex": "#808080",
          "name": "#808080",
          "reference": "vibrant"
        }, 
        {
          "hex": "#b6b6b6",
          "name": "#b6b6b6",
          "reference": "vibrant"
        }, 
        {
          "hex": "#404040",
          "name": "#404040",
          "reference": "vibrant"
        }
      ],
      "sizes": {
        "b": {
          "extension": "jpg",
          "height": 767,
          "mimetype": "image/jpeg",
          "secret": "oFZTWcQbfA2zrLfj3CG79hzhjeVb6yT8",
          "width": 776
        },
        "c": {
          "extension": "jpg",
          "height": 600,
          "mimetype": "image/jpeg",
          "secret": "oFZTWcQbfA2zrLfj3CG79hzhjeVb6yT8",
          "width": 606
        },
        "dc": {
          "extension": "jpg",
          "height": 600,
          "mimetype": "image/jpeg",
          "secret": "oFZTWcQbfA2zrLfj3CG79hzhjeVb6yT8",
          "width": 606
        },
        "ds": {
          "extension": "jpg",
          "height": 320,
          "mimetype": "image/jpeg",
          "secret": "oFZTWcQbfA2zrLfj3CG79hzhjeVb6yT8",
          "width": 320
        },
        "k": {
          "extension": "jpg",
          "height": 1535,
          "mimetype": "image/jpeg",
          "secret": "oFZTWcQbfA2zrLfj3CG79hzhjeVb6yT8",
          "width": 1552
        },
        "n": {
          "extension": "jpg",
          "height": 240,
          "mimetype": "image/jpeg",
          "secret": "oFZTWcQbfA2zrLfj3CG79hzhjeVb6yT8",
          "width": 242
        },
        "o": {
          "extension": "jpg",
          "height": 2509,
          "mimetype": "image/jpeg",
          "secret": "VEqI2LXDdlYXurLmpCOz5NOKngwLeiTU",
          "width": 2536
        },
        "s": {
          "extension": "jpg",
          "height": 320,
          "mimetype": "image/jpeg",
          "secret": "oFZTWcQbfA2zrLfj3CG79hzhjeVb6yT8",
          "width": 320
        },
        "z": {
          "extension": "jpg",
          "height": 480,
          "mimetype": "image/jpeg",
          "secret": "oFZTWcQbfA2zrLfj3CG79hzhjeVb6yT8",
          "width": 485
        }
      }
    },
    "media:uri_template": "https://millsfield.sfomuseum.org/media/152/782/464/3/1527824643_{secret}_{label}.{extention}",
    "sfomuseum:filename": "42709.tif",
    "sfomuseum:image_index": 5,
    "sfomuseum:placetype": "image",
    "sfomuseum:primary_image": 1,
    "wof:depicts": [
      1511945731
    ],
    "wof:name": "negative: San Francisco International Airport (SFO), construction",
    "wof:placetype": "media"
  },
  "geometry": {"coordinates":[-122.386155,37.616358],"type":"Point"}
}
