{
  "type": "Feature",
  "properties": {
    "iso:country": "XX",
    "media:fingerprint": "25c60c477c0498652627e715282a6ae04ad68a27",
    "media:imagehash_avg": "a:000000000081e7ff",
    "media:imagehash_diff": "d:d95878b153131f0f",
    "media:medium": "image",
    "media:mimetype": "image/tiff",
    "media:properties": {
      "colours": [
        {
          "hex": "#808080",
          "name": "#808080",
          "reference": "vibrant"
        }, 
        {
          "hex": "#c0c0c0",
          "name": "#c0c0c0",
          "reference": "vibrant"
        }, 
        {
          "hex": "#484848",
          "name": "#484848",
          "reference": "vibrant"
        }
      ],
      "sizes": {
        "b": {
          "extension": "jpg",
          "height": 768,
          "mimetype": "image/jpeg",
          "secret": "QvrX9a2Fs6w2PKujmYVlVzGJ2WHoQJhG",
          "width": 607
        },
        "c": {
          "extension": "jpg",
          "height": 600,
          "mimetype": "image/jpeg",
          "secret": "QvrX9a2Fs6w2PKujmYVlVzGJ2WHoQJhG",
          "width": 474
        },
        "dc": {
          "extension": "jpg",
          "height": 600,
          "mimetype": "image/jpeg",
          "secret": "QvrX9a2Fs6w2PKujmYVlVzGJ2WHoQJhG",
          "width": 474
        },
        "ds": {
          "extension": "jpg",
          "height": 320,
          "mimetype": "image/jpeg",
          "secret": "QvrX9a2Fs6w2PKujmYVlVzGJ2WHoQJhG",
          "width": 320
        },
        "k": {
          "extension": "jpg",
          "height": 1536,
          "mimetype": "image/jpeg",
          "secret": "QvrX9a2Fs6w2PKujmYVlVzGJ2WHoQJhG",
          "width": 1215
        },
        "n": {
          "extension": "jpg",
          "height": 240,
          "mimetype": "image/jpeg",
          "secret": "QvrX9a2Fs6w2PKujmYVlVzGJ2WHoQJhG",
          "width": 189
        },
        "o": {
          "extension": "jpg",
          "height": 2740,
          "mimetype": "image/jpeg",
          "secret": "dRKE7KayMVts5IDrOP5hlLXbdc5hFNeF",
          "width": 2168
        },
        "s": {
          "extension": "jpg",
          "height": 320,
          "mimetype": "image/jpeg",
          "secret": "QvrX9a2Fs6w2PKujmYVlVzGJ2WHoQJhG",
          "width": 320
        },
        "z": {
          "extension": "jpg",
          "height": 480,
          "mimetype": "image/jpeg",
          "secret": "QvrX9a2Fs6w2PKujmYVlVzGJ2WHoQJhG",
          "width": 379
        }
      }
    },
    "media:uri_template": "https://millsfield.sfomuseum.org/media/152/782/493/5/1527824935_{secret}_{label}.{extention}",
    "sfomuseum:filename": "42890.tif",
    "sfomuseum:image_index": 5,
    "sfomuseum:placetype": "image",
    "sfomuseum:primary_image": 1,
    "wof:depicts": [
      1511945817
    ],
    "wof:name": "negative: San Francisco International Airport (SFO), damage to Pier G conduits",
    "wof:placetype": "media"
  },
  "geometry": {"coordinates":[-122.386155,37.616358],"type":"Point"}
}
