{
  "type": "Feature",
  "properties": {
    "iso:country": "XX",
    "media:fingerprint": "b89e915d08dc6f644068006429d0985ce5076309",
    "media:imagehash_avg": "a:ffe3e3c381bfbf8b",
    "media:imagehash_diff": "d:6d4f47070f6f6b5b",
    "media:medium": "image",
    "media:mimetype": "image/tiff",
    "media:properties": {
      "colours": [
        {
          "hex": "#dc7867",
          "name": "#dc7867",
          "reference": "vibrant"
        }, 
        {
          "hex": "#f1bfaa",
          "name": "#f1bfaa",
          "reference": "vibrant"
        }, 
        {
          "hex": "#656682",
          "name": "#656682",
          "reference": "vibrant"
        }, 
        {
          "hex": "#d8d0b8",
          "name": "#d8d0b8",
          "reference": "vibrant"
        }, 
        {
          "hex": "#41486e",
          "name": "#41486e",
          "reference": "vibrant"
        }
      ],
      "sizes": {
        "b": {
          "extension": "jpg",
          "height": 768,
          "mimetype": "image/jpeg",
          "secret": "k6JSksTbguZmSRD1G2MbJIHdaeEdci0h",
          "width": 553
        },
        "c": {
          "extension": "jpg",
          "height": 600,
          "mimetype": "image/jpeg",
          "secret": "k6JSksTbguZmSRD1G2MbJIHdaeEdci0h",
          "width": 432
        },
        "dc": {
          "extension": "jpg",
          "height": 600,
          "mimetype": "image/jpeg",
          "secret": "k6JSksTbguZmSRD1G2MbJIHdaeEdci0h",
          "width": 432
        },
        "ds": {
          "extension": "jpg",
          "height": 320,
          "mimetype": "image/jpeg",
          "secret": "k6JSksTbguZmSRD1G2MbJIHdaeEdci0h",
          "width": 320
        },
        "k": {
          "extension": "jpg",
          "height": 1536,
          "mimetype": "image/jpeg",
          "secret": "k6JSksTbguZmSRD1G2MbJIHdaeEdci0h",
          "width": 1106
        },
        "n": {
          "extension": "jpg",
          "height": 239,
          "mimetype": "image/jpeg",
          "secret": "k6JSksTbguZmSRD1G2MbJIHdaeEdci0h",
          "width": 172
        },
        "o": {
          "extension": "jpg",
          "height": 2741,
          "mimetype": "image/jpeg",
          "secret": "kowO8SUXfYX8Q5eW1pdqM7f0kLR1j0d2",
          "width": 1974
        },
        "s": {
          "extension": "jpg",
          "height": 320,
          "mimetype": "image/jpeg",
          "secret": "k6JSksTbguZmSRD1G2MbJIHdaeEdci0h",
          "width": 320
        },
        "z": {
          "extension": "jpg",
          "height": 479,
          "mimetype": "image/jpeg",
          "secret": "k6JSksTbguZmSRD1G2MbJIHdaeEdci0h",
          "width": 345
        }
      }
    },
    "media:uri_template": "https://millsfield.sfomuseum.org/media/152/782/444/5/1527824445_{secret}_{label}.{extention}",
    "sfomuseum:filename": "42570.tif",
    "sfomuseum:image_index": 5,
    "sfomuseum:placetype": "image",
    "sfomuseum:primary_image": 1,
    "wof:depicts": [
      1511908573
    ],
    "wof:name": "airsickness bag: Delta Air Lines",
    "wof:placetype": "media"
  },
  "geometry": {"coordinates":[-122.386155,37.616358],"type":"Point"}
}
