{
  "type": "Feature",
  "properties": {
    "iso:country": "XX",
    "media:fingerprint": "19d9c8fd97a05921f0cf7a795e48e1faa32e6b77",
    "media:imagehash_avg": "a:ffbf1f3f3c380000",
    "media:imagehash_diff": "d:f87cfff4d8d980f8",
    "media:medium": "image",
    "media:mimetype": "image/tiff",
    "media:properties": {
      "colours": [
        {
          "hex": "#808080",
          "name": "#808080",
          "reference": "vibrant"
        }, 
        {
          "hex": "#b8b8b8",
          "name": "#b8b8b8",
          "reference": "vibrant"
        }, 
        {
          "hex": "#383838",
          "name": "#383838",
          "reference": "vibrant"
        }
      ],
      "sizes": {
        "b": {
          "extension": "jpg",
          "height": 767,
          "mimetype": "image/jpeg",
          "secret": "VybFbh4j7peQa984WZXfRGKs3yzbonEj",
          "width": 776
        },
        "c": {
          "extension": "jpg",
          "height": 600,
          "mimetype": "image/jpeg",
          "secret": "VybFbh4j7peQa984WZXfRGKs3yzbonEj",
          "width": 606
        },
        "dc": {
          "extension": "jpg",
          "height": 600,
          "mimetype": "image/jpeg",
          "secret": "VybFbh4j7peQa984WZXfRGKs3yzbonEj",
          "width": 606
        },
        "ds": {
          "extension": "jpg",
          "height": 320,
          "mimetype": "image/jpeg",
          "secret": "VybFbh4j7peQa984WZXfRGKs3yzbonEj",
          "width": 320
        },
        "k": {
          "extension": "jpg",
          "height": 1535,
          "mimetype": "image/jpeg",
          "secret": "VybFbh4j7peQa984WZXfRGKs3yzbonEj",
          "width": 1552
        },
        "n": {
          "extension": "jpg",
          "height": 240,
          "mimetype": "image/jpeg",
          "secret": "VybFbh4j7peQa984WZXfRGKs3yzbonEj",
          "width": 242
        },
        "o": {
          "extension": "jpg",
          "height": 2509,
          "mimetype": "image/jpeg",
          "secret": "emwVQVwDlog1Biy9CmOawF5byIl4REyL",
          "width": 2536
        },
        "s": {
          "extension": "jpg",
          "height": 320,
          "mimetype": "image/jpeg",
          "secret": "VybFbh4j7peQa984WZXfRGKs3yzbonEj",
          "width": 320
        },
        "z": {
          "extension": "jpg",
          "height": 480,
          "mimetype": "image/jpeg",
          "secret": "VybFbh4j7peQa984WZXfRGKs3yzbonEj",
          "width": 485
        }
      }
    },
    "media:uri_template": "https://millsfield.sfomuseum.org/media/152/782/464/1/1527824641_{secret}_{label}.{extention}",
    "sfomuseum:filename": "42708.tif",
    "sfomuseum:image_index": 5,
    "sfomuseum:placetype": "image",
    "sfomuseum:primary_image": 1,
    "wof:depicts": [
      1511945729
    ],
    "wof:name": "negative: San Francisco International Airport (SFO), construction",
    "wof:placetype": "media"
  },
  "geometry": {"coordinates":[-122.386155,37.616358],"type":"Point"}
}
