{
  "type": "Feature",
  "properties": {
    "iso:country": "XX",
    "media:fingerprint": "e333d463d35e204937dd133dced89e93507bdbbb",
    "media:imagehash_avg": "a:0e6672384c067efe",
    "media:imagehash_diff": "d:9ccee670989cfc9c",
    "media:medium": "image",
    "media:mimetype": "image/tiff",
    "media:properties": {
      "colours": [
        {
          "hex": "#edc329",
          "name": "#edc329",
          "reference": "vibrant"
        },
        {
          "hex": "#d7e394",
          "name": "#d7e394",
          "reference": "vibrant"
        },
        {
          "hex": "#666924",
          "name": "#666924",
          "reference": "vibrant"
        },
        {
          "hex": "#88a66e",
          "name": "#88a66e",
          "reference": "vibrant"
        },
        {
          "hex": "#c4d197",
          "name": "#c4d197",
          "reference": "vibrant"
        }
      ],
      "sizes": {
        "b": {
          "extension": "jpg",
          "height": 768,
          "mimetype": "image/jpeg",
          "secret": "1hGZo6TAKPQFwmJpCQBjcv3CF1vVUNBI",
          "width": 486
        },
        "c": {
          "extension": "jpg",
          "height": 600,
          "mimetype": "image/jpeg",
          "secret": "1hGZo6TAKPQFwmJpCQBjcv3CF1vVUNBI",
          "width": 380
        },
        "dc": {
          "extension": "jpg",
          "height": 600,
          "mimetype": "image/jpeg",
          "secret": "1hGZo6TAKPQFwmJpCQBjcv3CF1vVUNBI",
          "width": 380
        },
        "ds": {
          "extension": "jpg",
          "height": 320,
          "mimetype": "image/jpeg",
          "secret": "1hGZo6TAKPQFwmJpCQBjcv3CF1vVUNBI",
          "width": 320
        },
        "k": {
          "extension": "jpg",
          "height": 1536,
          "mimetype": "image/jpeg",
          "secret": "1hGZo6TAKPQFwmJpCQBjcv3CF1vVUNBI",
          "width": 973
        },
        "n": {
          "extension": "jpg",
          "height": 240,
          "mimetype": "image/jpeg",
          "secret": "1hGZo6TAKPQFwmJpCQBjcv3CF1vVUNBI",
          "width": 152
        },
        "o": {
          "extension": "jpg",
          "height": 3034,
          "mimetype": "image/jpeg",
          "secret": "Ira4HUm1gZeZXYHZwOz9vIuHmMLH7XIP",
          "width": 1923
        },
        "s": {
          "extension": "jpg",
          "height": 320,
          "mimetype": "image/jpeg",
          "secret": "1hGZo6TAKPQFwmJpCQBjcv3CF1vVUNBI",
          "width": 320
        },
        "z": {
          "extension": "jpg",
          "height": 480,
          "mimetype": "image/jpeg",
          "secret": "1hGZo6TAKPQFwmJpCQBjcv3CF1vVUNBI",
          "width": 304
        }
      }
    },
    "media:uri_template": "https://static.sfomuseum.org/media/152/784/367/7/1527843677_{secret}_{label}.{extention}",
    "sfomuseum:filename": "68631.tif",
    "sfomuseum:image_index": 5,
    "sfomuseum:image_type": "studio",
    "sfomuseum:placetype": "image",
    "sfomuseum:primary_image": 1,
    "wof:depicts": [
      1159284127,
      1511927655,
      1159286837
    ],
    "wof:name": "menu: Cathay Pacific Airways, Business Class",
    "wof:placetype": "custom",
    "wof:placetype_alt": "image"
  },
  "geometry": {"coordinates":[-122.386155,37.616358],"type":"Point"}
}
