{
  "type": "Feature",
  "properties": {
    "iso:country": "XX",
    "media:fingerprint": "616ee65161094aa5ac4e022c28983d99e9f97264",
    "media:imagehash_avg": "a:ff87e3e11f1f0101",
    "media:imagehash_diff": "d:2f2e45477f3b7b7b",
    "media:medium": "image",
    "media:mimetype": "image/tiff",
    "media:properties": {
      "colours": [
        {
          "hex": "#bbae45",
          "name": "#bbae45",
          "reference": "vibrant"
        },
        {
          "hex": "#503b13",
          "name": "#503b13",
          "reference": "vibrant"
        },
        {
          "hex": "#9a8860",
          "name": "#9a8860",
          "reference": "vibrant"
        },
        {
          "hex": "#e5ded0",
          "name": "#e5ded0",
          "reference": "vibrant"
        },
        {
          "hex": "#355258",
          "name": "#355258",
          "reference": "vibrant"
        }
      ],
      "sizes": {
        "b": {
          "extension": "jpg",
          "height": 768,
          "mimetype": "image/jpeg",
          "secret": "xfjQsSTPQlaeGPGOedYANBSZcounhrty",
          "width": 504
        },
        "c": {
          "extension": "jpg",
          "height": 600,
          "mimetype": "image/jpeg",
          "secret": "xfjQsSTPQlaeGPGOedYANBSZcounhrty",
          "width": 394
        },
        "dc": {
          "extension": "jpg",
          "height": 600,
          "mimetype": "image/jpeg",
          "secret": "xfjQsSTPQlaeGPGOedYANBSZcounhrty",
          "width": 394
        },
        "ds": {
          "extension": "jpg",
          "height": 320,
          "mimetype": "image/jpeg",
          "secret": "xfjQsSTPQlaeGPGOedYANBSZcounhrty",
          "width": 320
        },
        "k": {
          "extension": "jpg",
          "height": 1536,
          "mimetype": "image/jpeg",
          "secret": "xfjQsSTPQlaeGPGOedYANBSZcounhrty",
          "width": 1008
        },
        "n": {
          "extension": "jpg",
          "height": 240,
          "mimetype": "image/jpeg",
          "secret": "xfjQsSTPQlaeGPGOedYANBSZcounhrty",
          "width": 157
        },
        "o": {
          "extension": "jpg",
          "height": 2552,
          "mimetype": "image/jpeg",
          "secret": "Ro4SiYOV17tdY5ZWDJyqvS9lveCRg3Hc",
          "width": 1676
        },
        "s": {
          "extension": "jpg",
          "height": 320,
          "mimetype": "image/jpeg",
          "secret": "xfjQsSTPQlaeGPGOedYANBSZcounhrty",
          "width": 320
        },
        "z": {
          "extension": "jpg",
          "height": 480,
          "mimetype": "image/jpeg",
          "secret": "xfjQsSTPQlaeGPGOedYANBSZcounhrty",
          "width": 315
        }
      }
    },
    "media:uri_template": "https://millsfield.sfomuseum.org/media/152/785/313/7/1527853137_{secret}_{label}.{extention}",
    "sfomuseum:filename": "2013.095.015.tif",
    "sfomuseum:image_index": 5,
    "sfomuseum:placetype": "image",
    "sfomuseum:primary_image": 1,
    "wof:depicts": [
      1511956471
    ],
    "wof:name": "menu: Pan American World Airways, Clipper (Business) Class",
    "wof:placetype": "custom",
    "wof:placetype_alt": "image"
  },
  "geometry": {"coordinates":[-122.386155,37.616358],"type":"Point"}
}
