{
  "type": "Feature",
  "properties": {
    "iso:country": "XX",
    "media:fingerprint": "914cb7b8b0b709e18f3cb30b1faec21e8b640d83",
    "media:imagehash_avg": "a:040c9c9f9f9f9f8f",
    "media:imagehash_diff": "d:58393531367a3a35",
    "media:medium": "image",
    "media:mimetype": "image/tiff",
    "media:properties": {
      "colours": [
        {
          "hex": "#cc371f",
          "name": "#cc371f",
          "reference": "vibrant"
        }, 
        {
          "hex": "#e1c9a4",
          "name": "#e1c9a4",
          "reference": "vibrant"
        }, 
        {
          "hex": "#695f1e",
          "name": "#695f1e",
          "reference": "vibrant"
        }, 
        {
          "hex": "#9d8e4e",
          "name": "#9d8e4e",
          "reference": "vibrant"
        }, 
        {
          "hex": "#d8c8a8",
          "name": "#d8c8a8",
          "reference": "vibrant"
        }
      ],
      "sizes": {
        "b": {
          "extension": "jpg",
          "height": 585,
          "mimetype": "image/jpeg",
          "secret": "KSFw18HRaO0WETfuYwrfFZroKd5yFb83",
          "width": 1024
        },
        "c": {
          "extension": "jpg",
          "height": 457,
          "mimetype": "image/jpeg",
          "secret": "KSFw18HRaO0WETfuYwrfFZroKd5yFb83",
          "width": 800
        },
        "dc": {
          "extension": "jpg",
          "height": 457,
          "mimetype": "image/jpeg",
          "secret": "KSFw18HRaO0WETfuYwrfFZroKd5yFb83",
          "width": 800
        },
        "ds": {
          "extension": "jpg",
          "height": 320,
          "mimetype": "image/jpeg",
          "secret": "KSFw18HRaO0WETfuYwrfFZroKd5yFb83",
          "width": 320
        },
        "k": {
          "extension": "jpg",
          "height": 1170,
          "mimetype": "image/jpeg",
          "secret": "KSFw18HRaO0WETfuYwrfFZroKd5yFb83",
          "width": 2048
        },
        "n": {
          "extension": "jpg",
          "height": 182,
          "mimetype": "image/jpeg",
          "secret": "KSFw18HRaO0WETfuYwrfFZroKd5yFb83",
          "width": 320
        },
        "o": {
          "extension": "jpg",
          "height": 1140,
          "mimetype": "image/jpeg",
          "secret": "5I7xNSltmuzdnuWjOdsXFB8Rt8U6w5Sh",
          "width": 1995
        },
        "s": {
          "extension": "jpg",
          "height": 320,
          "mimetype": "image/jpeg",
          "secret": "KSFw18HRaO0WETfuYwrfFZroKd5yFb83",
          "width": 320
        },
        "z": {
          "extension": "jpg",
          "height": 365,
          "mimetype": "image/jpeg",
          "secret": "KSFw18HRaO0WETfuYwrfFZroKd5yFb83",
          "width": 640
        }
      }
    },
    "media:uri_template": "https://millsfield.sfomuseum.org/media/152/782/045/3/1527820453_{secret}_{label}.{extention}",
    "sfomuseum:filename": "31618.tif",
    "sfomuseum:image_index": 5,
    "sfomuseum:placetype": "image",
    "sfomuseum:primary_image": 1,
    "wof:depicts": [
      1511920309
    ],
    "wof:name": "airmail flight cover: Pan American Airways, Transpacific Air Mail \r",
    "wof:placetype": "media"
  },
  "geometry": {"coordinates":[-122.386155,37.616358],"type":"Point"}
}
