{
  "type": "Feature",
  "properties": {
    "iso:country": "XX",
    "media:fingerprint": "6848cdc3b2dd27dff3101a8308a37c1b4e7dc603",
    "media:imagehash_avg": "a:7f7f7f7f3c000000",
    "media:imagehash_diff": "d:f8f8f8f8f8f8f0c0",
    "media:medium": "image",
    "media:mimetype": "image/tiff",
    "media:properties": {
      "colours": [
        {
          "hex": "#ba303b",
          "name": "#ba303b",
          "reference": "vibrant"
        }, 
        {
          "hex": "#c26079",
          "name": "#c26079",
          "reference": "vibrant"
        }, 
        {
          "hex": "#888377",
          "name": "#888377",
          "reference": "vibrant"
        }, 
        {
          "hex": "#c9d0b7",
          "name": "#c9d0b7",
          "reference": "vibrant"
        }, 
        {
          "hex": "#4c433f",
          "name": "#4c433f",
          "reference": "vibrant"
        }
      ],
      "sizes": {
        "b": {
          "extension": "jpg",
          "height": 664,
          "mimetype": "image/jpeg",
          "secret": "MdN3dq2u8oi60s18U7Tmj16QkAcYLDKf",
          "width": 1024
        },
        "c": {
          "extension": "jpg",
          "height": 519,
          "mimetype": "image/jpeg",
          "secret": "MdN3dq2u8oi60s18U7Tmj16QkAcYLDKf",
          "width": 800
        },
        "dc": {
          "extension": "jpg",
          "height": 519,
          "mimetype": "image/jpeg",
          "secret": "MdN3dq2u8oi60s18U7Tmj16QkAcYLDKf",
          "width": 800
        },
        "ds": {
          "extension": "jpg",
          "height": 320,
          "mimetype": "image/jpeg",
          "secret": "MdN3dq2u8oi60s18U7Tmj16QkAcYLDKf",
          "width": 320
        },
        "k": {
          "extension": "jpg",
          "height": 1329,
          "mimetype": "image/jpeg",
          "secret": "MdN3dq2u8oi60s18U7Tmj16QkAcYLDKf",
          "width": 2048
        },
        "n": {
          "extension": "jpg",
          "height": 207,
          "mimetype": "image/jpeg",
          "secret": "MdN3dq2u8oi60s18U7Tmj16QkAcYLDKf",
          "width": 320
        },
        "o": {
          "extension": "jpg",
          "height": 1009,
          "mimetype": "image/jpeg",
          "secret": "4pRGuaI679UnVfkc5OkvKlwFQTGHrYxq",
          "width": 1554
        },
        "s": {
          "extension": "jpg",
          "height": 320,
          "mimetype": "image/jpeg",
          "secret": "MdN3dq2u8oi60s18U7Tmj16QkAcYLDKf",
          "width": 320
        },
        "z": {
          "extension": "jpg",
          "height": 415,
          "mimetype": "image/jpeg",
          "secret": "MdN3dq2u8oi60s18U7Tmj16QkAcYLDKf",
          "width": 640
        }
      }
    },
    "media:uri_template": "https://millsfield.sfomuseum.org/media/152/782/822/9/1527828229_{secret}_{label}.{extention}",
    "sfomuseum:filename": "44440.tif",
    "sfomuseum:image_index": 5,
    "sfomuseum:placetype": "image",
    "sfomuseum:primary_image": 1,
    "wof:depicts": [
      1511949261
    ],
    "wof:name": "negative: San Francisco International Airport (SFO), Concorde",
    "wof:placetype": "media"
  },
  "geometry": {"coordinates":[-122.386155,37.616358],"type":"Point"}
}
