{
  "type": "Feature",
  "properties": {
    "iso:country": "XX",
    "media:fingerprint": "12bdc7026f369e94676aace824940523b6376fc9",
    "media:imagehash_avg": "a:8181ffff7b677f09",
    "media:imagehash_diff": "d:3323b38687cdd9fb",
    "media:medium": "image",
    "media:mimetype": "image/tiff",
    "media:properties": {
      "colours": [
        {
          "hex": "#f7ebd7",
          "name": "#f7ebd7",
          "reference": "vibrant"
        }, 
        {
          "hex": "#988f77",
          "name": "#988f77",
          "reference": "vibrant"
        }, 
        {
          "hex": "#d6d3c1",
          "name": "#d6d3c1",
          "reference": "vibrant"
        }, 
        {
          "hex": "#3f3966",
          "name": "#3f3966",
          "reference": "vibrant"
        }
      ],
      "sizes": {
        "b": {
          "extension": "jpg",
          "height": 768,
          "mimetype": "image/jpeg",
          "secret": "SMgp3PUds19LdgtAZ61qNFiMTfg5m3Ag",
          "width": 427
        },
        "c": {
          "extension": "jpg",
          "height": 600,
          "mimetype": "image/jpeg",
          "secret": "SMgp3PUds19LdgtAZ61qNFiMTfg5m3Ag",
          "width": 333
        },
        "dc": {
          "extension": "jpg",
          "height": 600,
          "mimetype": "image/jpeg",
          "secret": "SMgp3PUds19LdgtAZ61qNFiMTfg5m3Ag",
          "width": 333
        },
        "ds": {
          "extension": "jpg",
          "height": 320,
          "mimetype": "image/jpeg",
          "secret": "SMgp3PUds19LdgtAZ61qNFiMTfg5m3Ag",
          "width": 320
        },
        "k": {
          "extension": "jpg",
          "height": 1536,
          "mimetype": "image/jpeg",
          "secret": "SMgp3PUds19LdgtAZ61qNFiMTfg5m3Ag",
          "width": 854
        },
        "n": {
          "extension": "jpg",
          "height": 240,
          "mimetype": "image/jpeg",
          "secret": "SMgp3PUds19LdgtAZ61qNFiMTfg5m3Ag",
          "width": 133
        },
        "o": {
          "extension": "jpg",
          "height": 2922,
          "mimetype": "image/jpeg",
          "secret": "nvIRPofTwrBPAfl3wAdW9hHEuRuOAvTL",
          "width": 1625
        },
        "s": {
          "extension": "jpg",
          "height": 320,
          "mimetype": "image/jpeg",
          "secret": "SMgp3PUds19LdgtAZ61qNFiMTfg5m3Ag",
          "width": 320
        },
        "z": {
          "extension": "jpg",
          "height": 480,
          "mimetype": "image/jpeg",
          "secret": "SMgp3PUds19LdgtAZ61qNFiMTfg5m3Ag",
          "width": 266
        }
      }
    },
    "media:uri_template": "https://millsfield.sfomuseum.org/media/152/782/375/9/1527823759_{secret}_{label}.{extention}",
    "sfomuseum:filename": "41776.tif",
    "sfomuseum:image_index": 5,
    "sfomuseum:placetype": "image",
    "sfomuseum:primary_image": 0,
    "wof:depicts": [
      1511908499
    ],
    "wof:name": "airsickness bag: Cathay Pacific Airways",
    "wof:placetype": "media"
  },
  "geometry": {"coordinates":[-122.386155,37.616358],"type":"Point"}
}
