{
  "type": "Feature",
  "properties": {
    "media:fingerprint": "0c91cb93249aa30aa672a15bf0a5113fe0c5199c",
    "media:imagehash_avg": "a:fff7c1e1c18081ff",
    "media:imagehash_diff": "d:736703830b13336f",
    "media:mimetype": "image/jpeg",
    "media:properties": {
      "colours": [
        {
          "hex": "#cc5216",
          "name": "#cc5216",
          "reference": "vibrant"
        },
        {
          "hex": "#cdb277",
          "name": "#cdb277",
          "reference": "vibrant"
        },
        {
          "hex": "#911814",
          "name": "#911814",
          "reference": "vibrant"
        },
        {
          "hex": "#9d8e52",
          "name": "#9d8e52",
          "reference": "vibrant"
        },
        {
          "hex": "#d9d3b6",
          "name": "#d9d3b6",
          "reference": "vibrant"
        }
      ],
      "sizes": {
        "b": {
          "extension": "jpg",
          "height": 768,
          "mimetype": "image/jpeg",
          "secret": "oXj9zvfdlnkS1mAxqZbXjpKabHenXmMx",
          "width": 750
        },
        "c": {
          "extension": "jpg",
          "height": 600,
          "mimetype": "image/jpeg",
          "secret": "oXj9zvfdlnkS1mAxqZbXjpKabHenXmMx",
          "width": 586
        },
        "dc": {
          "extension": "jpg",
          "height": 600,
          "mimetype": "image/jpeg",
          "secret": "oXj9zvfdlnkS1mAxqZbXjpKabHenXmMx",
          "width": 586
        },
        "ds": {
          "extension": "jpg",
          "height": 320,
          "mimetype": "image/jpeg",
          "secret": "oXj9zvfdlnkS1mAxqZbXjpKabHenXmMx",
          "width": 320
        },
        "k": {
          "extension": "jpg",
          "height": 1536,
          "mimetype": "image/jpeg",
          "secret": "oXj9zvfdlnkS1mAxqZbXjpKabHenXmMx",
          "width": 1501
        },
        "n": {
          "extension": "jpg",
          "height": 240,
          "mimetype": "image/jpeg",
          "secret": "oXj9zvfdlnkS1mAxqZbXjpKabHenXmMx",
          "width": 234
        },
        "o": {
          "extension": "jpg",
          "height": 2259,
          "mimetype": "image/jpeg",
          "secret": "NHJLd6a9uAwdsguHqK5Shld4xjbI0plg",
          "width": 2208
        },
        "s": {
          "extension": "jpg",
          "height": 320,
          "mimetype": "image/jpeg",
          "secret": "oXj9zvfdlnkS1mAxqZbXjpKabHenXmMx",
          "width": 320
        },
        "z": {
          "extension": "jpg",
          "height": 480,
          "mimetype": "image/jpeg",
          "secret": "oXj9zvfdlnkS1mAxqZbXjpKabHenXmMx",
          "width": 469
        }
      }
    },
    "media:uri_template": "https://static.sfomuseum.org/media/174/668/005/9/1746680059_{secret}_{label}.{extention}",
    "sfomuseum:filename": "10606.JPG",
    "sfomuseum:image_index": 1,
    "sfomuseum:image_type": "curator",
    "sfomuseum:placetype": "image",
    "sfomuseum:primary_image": 1,
    "wof:depicts": [
      1511939959,
      1159285129,
      1159287667
    ],
    "wof:name": "phonograph record: SAS (Scandinavian Airlines System), A Mitch Miller Musical European Holiday",
    "wof:placetype": "custom"
  },
  "geometry": {"coordinates":[-122.386155,37.616357],"type":"Point"}
}
