{
  "type": "Feature",
  "properties": {
    "iso:country": "XX",
    "media:fingerprint": "ec314a7ff3790da157496a558dde97581b0ebd2a",
    "media:imagehash_avg": "a:ffffffcf00000000",
    "media:imagehash_diff": "d:373b3b391c6a57e0",
    "media:medium": "image",
    "media:mimetype": "image/tiff",
    "media:properties": {
      "colours": [
        {
          "hex": "#808080",
          "name": "#808080",
          "reference": "vibrant"
        }, 
        {
          "hex": "#c0c0c0",
          "name": "#c0c0c0",
          "reference": "vibrant"
        }, 
        {
          "hex": "#404040",
          "name": "#404040",
          "reference": "vibrant"
        }
      ],
      "sizes": {
        "b": {
          "extension": "jpg",
          "height": 768,
          "mimetype": "image/jpeg",
          "secret": "ZW4sBU4OHBoXk4XtDgf6NECl9Fn3yI5G",
          "width": 757
        },
        "c": {
          "extension": "jpg",
          "height": 600,
          "mimetype": "image/jpeg",
          "secret": "ZW4sBU4OHBoXk4XtDgf6NECl9Fn3yI5G",
          "width": 591
        },
        "dc": {
          "extension": "jpg",
          "height": 600,
          "mimetype": "image/jpeg",
          "secret": "ZW4sBU4OHBoXk4XtDgf6NECl9Fn3yI5G",
          "width": 591
        },
        "ds": {
          "extension": "jpg",
          "height": 320,
          "mimetype": "image/jpeg",
          "secret": "ZW4sBU4OHBoXk4XtDgf6NECl9Fn3yI5G",
          "width": 320
        },
        "k": {
          "extension": "jpg",
          "height": 1536,
          "mimetype": "image/jpeg",
          "secret": "ZW4sBU4OHBoXk4XtDgf6NECl9Fn3yI5G",
          "width": 1514
        },
        "n": {
          "extension": "jpg",
          "height": 240,
          "mimetype": "image/jpeg",
          "secret": "ZW4sBU4OHBoXk4XtDgf6NECl9Fn3yI5G",
          "width": 236
        },
        "o": {
          "extension": "jpg",
          "height": 1776,
          "mimetype": "image/jpeg",
          "secret": "KZAVZzZlbe6gIvwGjgnBmabEusFiD4Jn",
          "width": 1751
        },
        "s": {
          "extension": "jpg",
          "height": 320,
          "mimetype": "image/jpeg",
          "secret": "ZW4sBU4OHBoXk4XtDgf6NECl9Fn3yI5G",
          "width": 320
        },
        "z": {
          "extension": "jpg",
          "height": 480,
          "mimetype": "image/jpeg",
          "secret": "ZW4sBU4OHBoXk4XtDgf6NECl9Fn3yI5G",
          "width": 473
        }
      }
    },
    "media:uri_template": "https://millsfield.sfomuseum.org/media/152/782/542/5/1527825425_{secret}_{label}.{extention}",
    "sfomuseum:filename": "43149.tif",
    "sfomuseum:image_index": 5,
    "sfomuseum:placetype": "image",
    "sfomuseum:primary_image": 1,
    "wof:depicts": [
      1511946465
    ],
    "wof:name": "photograph: San Francisco International Airport (SFO), runway construction",
    "wof:placetype": "media"
  },
  "geometry": {"coordinates":[-122.386155,37.616358],"type":"Point"}
}
