{
  "type": "Feature",
  "properties": {
    "iso:country": "XX",
    "media:fingerprint": "0402f0f1101ecaafd98a394f488c8fa80f306853",
    "media:imagehash_avg": "a:ffff300018380800",
    "media:imagehash_diff": "d:e2f8e0b1f3f1b8f6",
    "media:medium": "image",
    "media:mimetype": "image/tiff",
    "media:properties": {
      "colours": [
        {
          "hex": "#808080",
          "name": "#808080",
          "reference": "vibrant"
        },
        {
          "hex": "#b8b8b8",
          "name": "#b8b8b8",
          "reference": "vibrant"
        },
        {
          "hex": "#4a4a4a",
          "name": "#4a4a4a",
          "reference": "vibrant"
        }
      ],
      "sizes": {
        "b": {
          "extension": "jpg",
          "height": 767,
          "mimetype": "image/jpeg",
          "secret": "9JHcTZj7KeVgm5dXOer1YBZ9zjlda7dK",
          "width": 978
        },
        "c": {
          "extension": "jpg",
          "height": 600,
          "mimetype": "image/jpeg",
          "secret": "9JHcTZj7KeVgm5dXOer1YBZ9zjlda7dK",
          "width": 764
        },
        "dc": {
          "extension": "jpg",
          "height": 600,
          "mimetype": "image/jpeg",
          "secret": "9JHcTZj7KeVgm5dXOer1YBZ9zjlda7dK",
          "width": 764
        },
        "ds": {
          "extension": "jpg",
          "height": 320,
          "mimetype": "image/jpeg",
          "secret": "9JHcTZj7KeVgm5dXOer1YBZ9zjlda7dK",
          "width": 320
        },
        "k": {
          "extension": "jpg",
          "height": 1535,
          "mimetype": "image/jpeg",
          "secret": "9JHcTZj7KeVgm5dXOer1YBZ9zjlda7dK",
          "width": 1957
        },
        "n": {
          "extension": "jpg",
          "height": 240,
          "mimetype": "image/jpeg",
          "secret": "9JHcTZj7KeVgm5dXOer1YBZ9zjlda7dK",
          "width": 305
        },
        "o": {
          "extension": "jpg",
          "height": 2140,
          "mimetype": "image/jpeg",
          "secret": "Q2KGOxMBkYfB1RmwnJtJS7XV4VbCaXp0",
          "width": 2727
        },
        "s": {
          "extension": "jpg",
          "height": 320,
          "mimetype": "image/jpeg",
          "secret": "9JHcTZj7KeVgm5dXOer1YBZ9zjlda7dK",
          "width": 320
        },
        "z": {
          "extension": "jpg",
          "height": 480,
          "mimetype": "image/jpeg",
          "secret": "9JHcTZj7KeVgm5dXOer1YBZ9zjlda7dK",
          "width": 611
        }
      }
    },
    "media:uri_template": "https://static.sfomuseum.org/media/152/782/286/3/1527822863_{secret}_{label}.{extention}",
    "sfomuseum:filename": "41107.tif",
    "sfomuseum:image_index": 5,
    "sfomuseum:image_type": "studio",
    "sfomuseum:placetype": "image",
    "sfomuseum:primary_image": 1,
    "wof:depicts": [
      102527513,
      1511944757
    ],
    "wof:name": "negative: San Francisco International Airport (SFO), aerial, South Terminal construction",
    "wof:placetype": "custom",
    "wof:placetype_alt": "image"
  },
  "geometry": {"coordinates":[-122.386155,37.616358],"type":"Point"}
}
