{
  "type": "Feature",
  "properties": {
    "iso:country": "XX",
    "media:fingerprint": "f4083b89816149aed5acdf491298ddfcb981c78e",
    "media:imagehash_avg": "a:8084a6a6969c8cff",
    "media:imagehash_diff": "d:184c4c6464741858",
    "media:medium": "image",
    "media:mimetype": "image/tiff",
    "media:properties": {
      "colours": [
        {
          "hex": "#b00000",
          "name": "#b00000",
          "reference": "vibrant"
        },
        {
          "hex": "#763b1e",
          "name": "#763b1e",
          "reference": "vibrant"
        },
        {
          "hex": "#8f8271",
          "name": "#8f8271",
          "reference": "vibrant"
        },
        {
          "hex": "#b6b1b1",
          "name": "#b6b1b1",
          "reference": "vibrant"
        },
        {
          "hex": "#554137",
          "name": "#554137",
          "reference": "vibrant"
        }
      ],
      "sizes": {
        "b": {
          "extension": "jpg",
          "height": 768,
          "mimetype": "image/jpeg",
          "secret": "JUoQt2CUNEAhMZjPjmI9eApk2aYWufDk",
          "width": 338
        },
        "c": {
          "extension": "jpg",
          "height": 600,
          "mimetype": "image/jpeg",
          "secret": "JUoQt2CUNEAhMZjPjmI9eApk2aYWufDk",
          "width": 264
        },
        "dc": {
          "extension": "jpg",
          "height": 600,
          "mimetype": "image/jpeg",
          "secret": "JUoQt2CUNEAhMZjPjmI9eApk2aYWufDk",
          "width": 264
        },
        "ds": {
          "extension": "jpg",
          "height": 320,
          "mimetype": "image/jpeg",
          "secret": "JUoQt2CUNEAhMZjPjmI9eApk2aYWufDk",
          "width": 320
        },
        "k": {
          "extension": "jpg",
          "height": 1536,
          "mimetype": "image/jpeg",
          "secret": "JUoQt2CUNEAhMZjPjmI9eApk2aYWufDk",
          "width": 676
        },
        "n": {
          "extension": "jpg",
          "height": 240,
          "mimetype": "image/jpeg",
          "secret": "JUoQt2CUNEAhMZjPjmI9eApk2aYWufDk",
          "width": 105
        },
        "o": {
          "extension": "jpg",
          "height": 3659,
          "mimetype": "image/jpeg",
          "secret": "Po2Hk58rY6M2n120GJ1k3BQ4R2SwOa4O",
          "width": 1611
        },
        "s": {
          "extension": "jpg",
          "height": 320,
          "mimetype": "image/jpeg",
          "secret": "JUoQt2CUNEAhMZjPjmI9eApk2aYWufDk",
          "width": 320
        },
        "z": {
          "extension": "jpg",
          "height": 480,
          "mimetype": "image/jpeg",
          "secret": "JUoQt2CUNEAhMZjPjmI9eApk2aYWufDk",
          "width": 211
        }
      }
    },
    "media:uri_template": "https://static.sfomuseum.org/media/152/784/510/9/1527845109_{secret}_{label}.{extention}",
    "sfomuseum:filename": "69577.tif",
    "sfomuseum:image_index": 5,
    "sfomuseum:image_type": "studio",
    "sfomuseum:placetype": "image",
    "sfomuseum:primary_image": 1,
    "wof:depicts": [
      1511941593,
      1159284261
    ],
    "wof:name": "menu: Delta Air Lines, BusinessElite Class",
    "wof:placetype": "custom",
    "wof:placetype_alt": "image"
  },
  "geometry": {"coordinates":[-122.386155,37.616358],"type":"Point"}
}
