{
  "type": "Feature",
  "properties": {
    "iso:country": "XX",
    "media:fingerprint": "50a8ee5a19256b6b300c734394e44e470a42021e",
    "media:imagehash_avg": "a:ffffff990c0c0000",
    "media:imagehash_diff": "d:c9e2b331387870c6",
    "media:medium": "image",
    "media:mimetype": "image/tiff",
    "media:properties": {
      "colours": [
        {
          "hex": "#808080",
          "name": "#808080",
          "reference": "vibrant"
        }, 
        {
          "hex": "#b8b8b8",
          "name": "#b8b8b8",
          "reference": "vibrant"
        }, 
        {
          "hex": "#484848",
          "name": "#484848",
          "reference": "vibrant"
        }
      ],
      "sizes": {
        "b": {
          "extension": "jpg",
          "height": 768,
          "mimetype": "image/jpeg",
          "secret": "T5f8pxdUtxGX2dZgeXzj3mwyz4QRlq5k",
          "width": 768
        },
        "c": {
          "extension": "jpg",
          "height": 600,
          "mimetype": "image/jpeg",
          "secret": "T5f8pxdUtxGX2dZgeXzj3mwyz4QRlq5k",
          "width": 600
        },
        "dc": {
          "extension": "jpg",
          "height": 600,
          "mimetype": "image/jpeg",
          "secret": "T5f8pxdUtxGX2dZgeXzj3mwyz4QRlq5k",
          "width": 600
        },
        "ds": {
          "extension": "jpg",
          "height": 320,
          "mimetype": "image/jpeg",
          "secret": "T5f8pxdUtxGX2dZgeXzj3mwyz4QRlq5k",
          "width": 320
        },
        "k": {
          "extension": "jpg",
          "height": 1536,
          "mimetype": "image/jpeg",
          "secret": "T5f8pxdUtxGX2dZgeXzj3mwyz4QRlq5k",
          "width": 1536
        },
        "n": {
          "extension": "jpg",
          "height": 239,
          "mimetype": "image/jpeg",
          "secret": "T5f8pxdUtxGX2dZgeXzj3mwyz4QRlq5k",
          "width": 240
        },
        "o": {
          "extension": "jpg",
          "height": 1835,
          "mimetype": "image/jpeg",
          "secret": "dL21fbOJNKFYgMDp3GWrwrkNspT0X21s",
          "width": 1836
        },
        "s": {
          "extension": "jpg",
          "height": 320,
          "mimetype": "image/jpeg",
          "secret": "T5f8pxdUtxGX2dZgeXzj3mwyz4QRlq5k",
          "width": 320
        },
        "z": {
          "extension": "jpg",
          "height": 479,
          "mimetype": "image/jpeg",
          "secret": "T5f8pxdUtxGX2dZgeXzj3mwyz4QRlq5k",
          "width": 480
        }
      }
    },
    "media:uri_template": "https://millsfield.sfomuseum.org/media/152/782/649/3/1527826493_{secret}_{label}.{extention}",
    "sfomuseum:filename": "43664.tif",
    "sfomuseum:image_index": 5,
    "sfomuseum:placetype": "image",
    "sfomuseum:primary_image": 1,
    "wof:depicts": [
      1511947531
    ],
    "wof:name": "photograph: San Francisco International Airport (SFO), construction",
    "wof:placetype": "media"
  },
  "geometry": {"coordinates":[-122.386155,37.616358],"type":"Point"}
}
