{
  "type": "Feature",
  "properties": {
    "iso:country": "XX",
    "media:fingerprint": "5fefb5e419de9445cb2a6fdf8c447be121ea7ca6",
    "media:imagehash_avg": "a:003f7f7f7f7b7b29",
    "media:imagehash_diff": "d:d9db97d397d3d3d3",
    "media:medium": "image",
    "media:mimetype": "image/tiff",
    "media:properties": {
      "colours": [
        {
          "hex": "#c43737",
          "name": "#c43737",
          "reference": "vibrant"
        }, 
        {
          "hex": "#e8dbc8",
          "name": "#e8dbc8",
          "reference": "vibrant"
        }, 
        {
          "hex": "#98968d",
          "name": "#98968d",
          "reference": "vibrant"
        }, 
        {
          "hex": "#d8baaf",
          "name": "#d8baaf",
          "reference": "vibrant"
        }, 
        {
          "hex": "#393735",
          "name": "#393735",
          "reference": "vibrant"
        }
      ],
      "sizes": {
        "b": {
          "extension": "jpg",
          "height": 768,
          "mimetype": "image/jpeg",
          "secret": "thMBRHiw2B0LV1bh8LiMKihGiKM0KWpI",
          "width": 368
        },
        "c": {
          "extension": "jpg",
          "height": 600,
          "mimetype": "image/jpeg",
          "secret": "thMBRHiw2B0LV1bh8LiMKihGiKM0KWpI",
          "width": 288
        },
        "dc": {
          "extension": "jpg",
          "height": 600,
          "mimetype": "image/jpeg",
          "secret": "thMBRHiw2B0LV1bh8LiMKihGiKM0KWpI",
          "width": 288
        },
        "ds": {
          "extension": "jpg",
          "height": 320,
          "mimetype": "image/jpeg",
          "secret": "thMBRHiw2B0LV1bh8LiMKihGiKM0KWpI",
          "width": 320
        },
        "k": {
          "extension": "jpg",
          "height": 1536,
          "mimetype": "image/jpeg",
          "secret": "thMBRHiw2B0LV1bh8LiMKihGiKM0KWpI",
          "width": 737
        },
        "n": {
          "extension": "jpg",
          "height": 240,
          "mimetype": "image/jpeg",
          "secret": "thMBRHiw2B0LV1bh8LiMKihGiKM0KWpI",
          "width": 115
        },
        "o": {
          "extension": "jpg",
          "height": 3383,
          "mimetype": "image/jpeg",
          "secret": "2EYExDVSN0moslaudcYkyWpugNMGfwDT",
          "width": 1625
        },
        "s": {
          "extension": "jpg",
          "height": 320,
          "mimetype": "image/jpeg",
          "secret": "thMBRHiw2B0LV1bh8LiMKihGiKM0KWpI",
          "width": 320
        },
        "z": {
          "extension": "jpg",
          "height": 480,
          "mimetype": "image/jpeg",
          "secret": "thMBRHiw2B0LV1bh8LiMKihGiKM0KWpI",
          "width": 230
        }
      }
    },
    "media:uri_template": "https://millsfield.sfomuseum.org/media/152/782/482/9/1527824829_{secret}_{label}.{extention}",
    "sfomuseum:filename": "42815.tif",
    "sfomuseum:image_index": 5,
    "sfomuseum:placetype": "image",
    "sfomuseum:primary_image": 0,
    "wof:depicts": [
      1511908797
    ],
    "wof:name": "airsickness bag: JAL (Japan Airlines)",
    "wof:placetype": "media"
  },
  "geometry": {"coordinates":[-122.386155,37.616358],"type":"Point"}
}
