{
  "type": "Feature",
  "properties": {
    "iso:country": "XX",
    "media:fingerprint": "f27f373a9c3fc1b9ade6469e407e8589df42a6e0",
    "media:imagehash_avg": "a:ffcfc3c3c38f81bb",
    "media:imagehash_diff": "d:5d1f1717131b1763",
    "media:medium": "image",
    "media:mimetype": "image/tiff",
    "media:properties": {
      "colours": [
        {
          "hex": "#d03a41",
          "name": "#d03a41",
          "reference": "vibrant"
        }, 
        {
          "hex": "#f18d87",
          "name": "#f18d87",
          "reference": "vibrant"
        }, 
        {
          "hex": "#797b7d",
          "name": "#797b7d",
          "reference": "vibrant"
        }, 
        {
          "hex": "#cec2af",
          "name": "#cec2af",
          "reference": "vibrant"
        }, 
        {
          "hex": "#453e3a",
          "name": "#453e3a",
          "reference": "vibrant"
        }
      ],
      "sizes": {
        "b": {
          "extension": "jpg",
          "height": 768,
          "mimetype": "image/jpeg",
          "secret": "7cIiLce5jr98xVyKqQnwyiG6gdQlb2qX",
          "width": 508
        },
        "c": {
          "extension": "jpg",
          "height": 600,
          "mimetype": "image/jpeg",
          "secret": "7cIiLce5jr98xVyKqQnwyiG6gdQlb2qX",
          "width": 397
        },
        "dc": {
          "extension": "jpg",
          "height": 600,
          "mimetype": "image/jpeg",
          "secret": "7cIiLce5jr98xVyKqQnwyiG6gdQlb2qX",
          "width": 397
        },
        "ds": {
          "extension": "jpg",
          "height": 320,
          "mimetype": "image/jpeg",
          "secret": "7cIiLce5jr98xVyKqQnwyiG6gdQlb2qX",
          "width": 320
        },
        "k": {
          "extension": "jpg",
          "height": 1536,
          "mimetype": "image/jpeg",
          "secret": "7cIiLce5jr98xVyKqQnwyiG6gdQlb2qX",
          "width": 1016
        },
        "n": {
          "extension": "jpg",
          "height": 239,
          "mimetype": "image/jpeg",
          "secret": "7cIiLce5jr98xVyKqQnwyiG6gdQlb2qX",
          "width": 158
        },
        "o": {
          "extension": "jpg",
          "height": 2729,
          "mimetype": "image/jpeg",
          "secret": "NXiga7dqJzHgzaJb3HW8GlojbVz06PIO",
          "width": 1806
        },
        "s": {
          "extension": "jpg",
          "height": 320,
          "mimetype": "image/jpeg",
          "secret": "7cIiLce5jr98xVyKqQnwyiG6gdQlb2qX",
          "width": 320
        },
        "z": {
          "extension": "jpg",
          "height": 479,
          "mimetype": "image/jpeg",
          "secret": "7cIiLce5jr98xVyKqQnwyiG6gdQlb2qX",
          "width": 317
        }
      }
    },
    "media:uri_template": "https://millsfield.sfomuseum.org/media/152/782/456/3/1527824563_{secret}_{label}.{extention}",
    "sfomuseum:filename": "42645.tif",
    "sfomuseum:image_index": 5,
    "sfomuseum:placetype": "image",
    "sfomuseum:primary_image": 1,
    "wof:depicts": [
      1511927409
    ],
    "wof:name": "airsickness bag: Continental Airlines",
    "wof:placetype": "media"
  },
  "geometry": {"coordinates":[-122.386155,37.616358],"type":"Point"}
}
