{
  "type": "Feature",
  "properties": {
    "iso:country": "XX",
    "media:fingerprint": "fa0434bd07f34e54ac147552b26b43d2a595464c",
    "media:imagehash_avg": "a:ffffffffc7830100",
    "media:imagehash_diff": "d:70f0cccc96323a1f",
    "media:medium": "image",
    "media:mimetype": "image/tiff",
    "media:properties": {
      "colours": [
        {
          "hex": "#808080",
          "name": "#808080",
          "reference": "vibrant"
        }, 
        {
          "hex": "#b6b6b6",
          "name": "#b6b6b6",
          "reference": "vibrant"
        }, 
        {
          "hex": "#464646",
          "name": "#464646",
          "reference": "vibrant"
        }
      ],
      "sizes": {
        "b": {
          "extension": "jpg",
          "height": 767,
          "mimetype": "image/jpeg",
          "secret": "LzvXbNvwyxu1rp2YDzcWHqEuXbVMO2Om",
          "width": 601
        },
        "c": {
          "extension": "jpg",
          "height": 600,
          "mimetype": "image/jpeg",
          "secret": "LzvXbNvwyxu1rp2YDzcWHqEuXbVMO2Om",
          "width": 469
        },
        "dc": {
          "extension": "jpg",
          "height": 600,
          "mimetype": "image/jpeg",
          "secret": "LzvXbNvwyxu1rp2YDzcWHqEuXbVMO2Om",
          "width": 469
        },
        "ds": {
          "extension": "jpg",
          "height": 320,
          "mimetype": "image/jpeg",
          "secret": "LzvXbNvwyxu1rp2YDzcWHqEuXbVMO2Om",
          "width": 320
        },
        "k": {
          "extension": "jpg",
          "height": 1535,
          "mimetype": "image/jpeg",
          "secret": "LzvXbNvwyxu1rp2YDzcWHqEuXbVMO2Om",
          "width": 1203
        },
        "n": {
          "extension": "jpg",
          "height": 240,
          "mimetype": "image/jpeg",
          "secret": "LzvXbNvwyxu1rp2YDzcWHqEuXbVMO2Om",
          "width": 187
        },
        "o": {
          "extension": "jpg",
          "height": 2768,
          "mimetype": "image/jpeg",
          "secret": "lcDT9mSF2aAJafOL1cKGreqcUq3wmnHE",
          "width": 2168
        },
        "s": {
          "extension": "jpg",
          "height": 320,
          "mimetype": "image/jpeg",
          "secret": "LzvXbNvwyxu1rp2YDzcWHqEuXbVMO2Om",
          "width": 320
        },
        "z": {
          "extension": "jpg",
          "height": 480,
          "mimetype": "image/jpeg",
          "secret": "LzvXbNvwyxu1rp2YDzcWHqEuXbVMO2Om",
          "width": 375
        }
      }
    },
    "media:uri_template": "https://millsfield.sfomuseum.org/media/152/782/590/1/1527825901_{secret}_{label}.{extention}",
    "sfomuseum:filename": "43387.tif",
    "sfomuseum:image_index": 5,
    "sfomuseum:placetype": "image",
    "sfomuseum:primary_image": 1,
    "wof:depicts": [
      1511946935
    ],
    "wof:name": "negative: San Francisco International Airport (SFO), Steve Misera",
    "wof:placetype": "media"
  },
  "geometry": {"coordinates":[-122.386155,37.616358],"type":"Point"}
}
