{
  "type": "Feature",
  "properties": {
    "iso:country": "XX",
    "media:fingerprint": "970b8ab34142bd576920b08ba62ce158986d0040",
    "media:imagehash_avg": "a:7e7f7e7e00020200",
    "media:imagehash_diff": "d:f8fcf0e6e4e6f6ea",
    "media:medium": "image",
    "media:mimetype": "image/tiff",
    "media:properties": {
      "colours": [
        {
          "hex": "#808080",
          "name": "#808080",
          "reference": "vibrant"
        }, 
        {
          "hex": "#b8b8b8",
          "name": "#b8b8b8",
          "reference": "vibrant"
        }, 
        {
          "hex": "#464646",
          "name": "#464646",
          "reference": "vibrant"
        }
      ],
      "sizes": {
        "b": {
          "extension": "jpg",
          "height": 703,
          "mimetype": "image/jpeg",
          "secret": "e4qXJ2umW2nUxH0mWj3EzBwlw2OpHq7U",
          "width": 1024
        },
        "c": {
          "extension": "jpg",
          "height": 549,
          "mimetype": "image/jpeg",
          "secret": "e4qXJ2umW2nUxH0mWj3EzBwlw2OpHq7U",
          "width": 799
        },
        "dc": {
          "extension": "jpg",
          "height": 549,
          "mimetype": "image/jpeg",
          "secret": "e4qXJ2umW2nUxH0mWj3EzBwlw2OpHq7U",
          "width": 799
        },
        "ds": {
          "extension": "jpg",
          "height": 320,
          "mimetype": "image/jpeg",
          "secret": "e4qXJ2umW2nUxH0mWj3EzBwlw2OpHq7U",
          "width": 320
        },
        "k": {
          "extension": "jpg",
          "height": 1406,
          "mimetype": "image/jpeg",
          "secret": "e4qXJ2umW2nUxH0mWj3EzBwlw2OpHq7U",
          "width": 2048
        },
        "n": {
          "extension": "jpg",
          "height": 219,
          "mimetype": "image/jpeg",
          "secret": "e4qXJ2umW2nUxH0mWj3EzBwlw2OpHq7U",
          "width": 320
        },
        "o": {
          "extension": "jpg",
          "height": 4200,
          "mimetype": "image/jpeg",
          "secret": "bemwnIJTwVIfRuOCtBXJV4SH1yXRkIuV",
          "width": 6115
        },
        "s": {
          "extension": "jpg",
          "height": 320,
          "mimetype": "image/jpeg",
          "secret": "e4qXJ2umW2nUxH0mWj3EzBwlw2OpHq7U",
          "width": 320
        },
        "z": {
          "extension": "jpg",
          "height": 439,
          "mimetype": "image/jpeg",
          "secret": "e4qXJ2umW2nUxH0mWj3EzBwlw2OpHq7U",
          "width": 640
        }
      }
    },
    "media:uri_template": "https://millsfield.sfomuseum.org/media/152/782/149/3/1527821493_{secret}_{label}.{extention}",
    "sfomuseum:filename": "38792.tif",
    "sfomuseum:image_index": 5,
    "sfomuseum:placetype": "image",
    "sfomuseum:primary_image": 1,
    "wof:depicts": [
      1511950011
    ],
    "wof:name": "negative: San Francisco Airport, levee construction",
    "wof:placetype": "media"
  },
  "geometry": {"coordinates":[-122.386155,37.616358],"type":"Point"}
}
