{
  "type": "Feature",
  "properties": {
    "iso:country": "XX",
    "media:fingerprint": "18dd824d50740fa262d2ce246a3ffde5bde656d4",
    "media:imagehash_avg": "a:701303477f7f7f04",
    "media:imagehash_diff": "d:82a68e9ef6b6be8c",
    "media:medium": "image",
    "media:mimetype": "image/tiff",
    "media:properties": {
      "colours": [
        {
          "hex": "#808080",
          "name": "#808080",
          "reference": "vibrant"
        },
        {
          "hex": "#b8b8b8",
          "name": "#b8b8b8",
          "reference": "vibrant"
        },
        {
          "hex": "#404040",
          "name": "#404040",
          "reference": "vibrant"
        }
      ],
      "sizes": {
        "b": {
          "extension": "jpg",
          "height": 732,
          "mimetype": "image/jpeg",
          "secret": "BJWmqRlGZh6N06SMvCl4Dh3tWvdxUH9N",
          "width": 1024
        },
        "c": {
          "extension": "jpg",
          "height": 572,
          "mimetype": "image/jpeg",
          "secret": "BJWmqRlGZh6N06SMvCl4Dh3tWvdxUH9N",
          "width": 800
        },
        "dc": {
          "extension": "jpg",
          "height": 572,
          "mimetype": "image/jpeg",
          "secret": "BJWmqRlGZh6N06SMvCl4Dh3tWvdxUH9N",
          "width": 800
        },
        "ds": {
          "extension": "jpg",
          "height": 320,
          "mimetype": "image/jpeg",
          "secret": "BJWmqRlGZh6N06SMvCl4Dh3tWvdxUH9N",
          "width": 320
        },
        "k": {
          "extension": "jpg",
          "height": 1465,
          "mimetype": "image/jpeg",
          "secret": "BJWmqRlGZh6N06SMvCl4Dh3tWvdxUH9N",
          "width": 2048
        },
        "n": {
          "extension": "jpg",
          "height": 228,
          "mimetype": "image/jpeg",
          "secret": "BJWmqRlGZh6N06SMvCl4Dh3tWvdxUH9N",
          "width": 320
        },
        "o": {
          "extension": "jpg",
          "height": 2391,
          "mimetype": "image/jpeg",
          "secret": "gVdOpCG1oW0xF9GejaCsgoSxVeTrFSnw",
          "width": 3342
        },
        "s": {
          "extension": "jpg",
          "height": 320,
          "mimetype": "image/jpeg",
          "secret": "BJWmqRlGZh6N06SMvCl4Dh3tWvdxUH9N",
          "width": 320
        },
        "z": {
          "extension": "jpg",
          "height": 457,
          "mimetype": "image/jpeg",
          "secret": "BJWmqRlGZh6N06SMvCl4Dh3tWvdxUH9N",
          "width": 640
        }
      }
    },
    "media:uri_template": "https://static.sfomuseum.org/media/152/785/289/5/1527852895_{secret}_{label}.{extention}",
    "sfomuseum:filename": "87680.tif",
    "sfomuseum:image_index": 5,
    "sfomuseum:image_type": "studio",
    "sfomuseum:placetype": "image",
    "sfomuseum:primary_image": 1,
    "wof:depicts": [
      1511955545
    ],
    "wof:name": "glass negative: Panama-Pacific International Exposition",
    "wof:placetype": "custom",
    "wof:placetype_alt": "image"
  },
  "geometry": {"coordinates":[-122.386155,37.616358],"type":"Point"}
}
