{
  "type": "Feature",
  "properties": {
    "iso:country":"US",
    "media:medium":"image",
    "sfomuseum:filename":"1999.049.004c.tif",
    "sfomuseum:image_index":5,
    "sfomuseum:placetype":"image",
    "sfomuseum:primary_image":0,
    "wof:depicts":[
        1511909403
    ],
    "wof:name":"flight information packet: Pan American World Airways, Boeing 377 Stratocruiser",
    "wof:placetype":"media"
},
  "geometry": {"coordinates":[-122.386155,37.616358],"type":"Point"}
}