{
  "type": "Feature",
  "properties": {
    "iso:country": "XX",
    "media:fingerprint": "e8c154904ef441e6e5d79f5eba32410364a40b9f",
    "media:imagehash_avg": "a:ffff3e3e3c000000",
    "media:imagehash_diff": "d:f8f8f8f0e06c7c7e",
    "media:medium": "image",
    "media:mimetype": "image/tiff",
    "media:properties": {
      "colours": [
        {
          "hex": "#7a7a7a",
          "name": "#7a7a7a",
          "reference": "vibrant"
        }, 
        {
          "hex": "#b6b6b6",
          "name": "#b6b6b6",
          "reference": "vibrant"
        }, 
        {
          "hex": "#404040",
          "name": "#404040",
          "reference": "vibrant"
        }
      ],
      "sizes": {
        "b": {
          "extension": "jpg",
          "height": 767,
          "mimetype": "image/jpeg",
          "secret": "IxCgRTBwX8yb4XeDTjmGveiA0ecOwPHP",
          "width": 988
        },
        "c": {
          "extension": "jpg",
          "height": 600,
          "mimetype": "image/jpeg",
          "secret": "IxCgRTBwX8yb4XeDTjmGveiA0ecOwPHP",
          "width": 772
        },
        "dc": {
          "extension": "jpg",
          "height": 600,
          "mimetype": "image/jpeg",
          "secret": "IxCgRTBwX8yb4XeDTjmGveiA0ecOwPHP",
          "width": 772
        },
        "ds": {
          "extension": "jpg",
          "height": 320,
          "mimetype": "image/jpeg",
          "secret": "IxCgRTBwX8yb4XeDTjmGveiA0ecOwPHP",
          "width": 320
        },
        "k": {
          "extension": "jpg",
          "height": 1535,
          "mimetype": "image/jpeg",
          "secret": "IxCgRTBwX8yb4XeDTjmGveiA0ecOwPHP",
          "width": 1976
        },
        "n": {
          "extension": "jpg",
          "height": 240,
          "mimetype": "image/jpeg",
          "secret": "IxCgRTBwX8yb4XeDTjmGveiA0ecOwPHP",
          "width": 308
        },
        "o": {
          "extension": "jpg",
          "height": 2140,
          "mimetype": "image/jpeg",
          "secret": "yMJDLJgprG4uFGclFbrem53vacWzm8Ef",
          "width": 2754
        },
        "s": {
          "extension": "jpg",
          "height": 320,
          "mimetype": "image/jpeg",
          "secret": "IxCgRTBwX8yb4XeDTjmGveiA0ecOwPHP",
          "width": 320
        },
        "z": {
          "extension": "jpg",
          "height": 480,
          "mimetype": "image/jpeg",
          "secret": "IxCgRTBwX8yb4XeDTjmGveiA0ecOwPHP",
          "width": 617
        }
      }
    },
    "media:uri_template": "https://millsfield.sfomuseum.org/media/152/782/242/7/1527822427_{secret}_{label}.{extention}",
    "sfomuseum:filename": "40741.tif",
    "sfomuseum:image_index": 5,
    "sfomuseum:placetype": "image",
    "sfomuseum:primary_image": 1,
    "wof:depicts": [
      1511944331
    ],
    "wof:name": "negative: San Francisco International Airport (SFO), aerial",
    "wof:placetype": "media"
  },
  "geometry": {"coordinates":[-122.386155,37.616358],"type":"Point"}
}
