{
  "type": "Feature",
  "properties": {
    "date:cessation_lower": "1944-01-01",
    "date:cessation_upper": "1944-12-31",
    "date:inception_lower": "1944-01-01",
    "date:inception_upper": "1944-12-31",
    "iso:country": "US",
    "media:imagetext": "SYSTEM NAVIGATION COURSE\nStudent's Guide\nPAN AMERICAN AIRWAYS SISTEN\n\"The System of the Flying Clippers\"\n1997.38.39",
    "media:imagetext_created": 1711611028,
    "millsfield:images_texts": [
      "SYSTEM NAVIGATION COURSE\nPAN AMERICAN AIRWAYS SISTEN\n\"The System of the Flying Clippers\""
    ],
    "millsfield:images_texts_ids": [
      1746680847
    ],
    "sfomuseum:filename": "1997.38.39_ins.jpg",
    "sfomuseum:image_index": 1,
    "sfomuseum:image_type": "studio",
    "sfomuseum:placetype": "image",
    "sfomuseum:primary_image": 0,
    "wof:depicts": [
      1511908169,
      1159284991,
      1159286839
    ],
    "wof:name": "training manual: Pan American Airways, System navigation course",
    "wof:placetype": "custom"
  },
  "geometry": {"coordinates":[-122.386155,37.616357],"type":"Point"}
}
