{
  "type": "Feature",
  "properties": {
    "iso:country": "XX",
    "media:fingerprint": "33d46fd2ae6975c3336d7aa857fa6fb50afa4829",
    "media:imagehash_avg": "a:8100e6e4e0feecff",
    "media:imagehash_diff": "d:714d4c4c40c84959",
    "media:medium": "image",
    "media:mimetype": "image/tiff",
    "media:properties": {
      "colours": [
        {
          "hex": "#721204",
          "name": "#721204",
          "reference": "vibrant"
        },
        {
          "hex": "#7e8f5d",
          "name": "#7e8f5d",
          "reference": "vibrant"
        },
        {
          "hex": "#c6c89d",
          "name": "#c6c89d",
          "reference": "vibrant"
        },
        {
          "hex": "#47572d",
          "name": "#47572d",
          "reference": "vibrant"
        }
      ],
      "sizes": {
        "b": {
          "extension": "jpg",
          "height": 739,
          "mimetype": "image/jpeg",
          "secret": "If1IWukrG60ozZpCGgKFERKnRevcVlI7",
          "width": 1024
        },
        "c": {
          "extension": "jpg",
          "height": 577,
          "mimetype": "image/jpeg",
          "secret": "If1IWukrG60ozZpCGgKFERKnRevcVlI7",
          "width": 800
        },
        "dc": {
          "extension": "jpg",
          "height": 577,
          "mimetype": "image/jpeg",
          "secret": "If1IWukrG60ozZpCGgKFERKnRevcVlI7",
          "width": 800
        },
        "ds": {
          "extension": "jpg",
          "height": 320,
          "mimetype": "image/jpeg",
          "secret": "If1IWukrG60ozZpCGgKFERKnRevcVlI7",
          "width": 320
        },
        "k": {
          "extension": "jpg",
          "height": 1479,
          "mimetype": "image/jpeg",
          "secret": "If1IWukrG60ozZpCGgKFERKnRevcVlI7",
          "width": 2048
        },
        "n": {
          "extension": "jpg",
          "height": 231,
          "mimetype": "image/jpeg",
          "secret": "If1IWukrG60ozZpCGgKFERKnRevcVlI7",
          "width": 320
        },
        "o": {
          "extension": "jpg",
          "height": 1515,
          "mimetype": "image/jpeg",
          "secret": "tYcmO65Yr72rQHJx72pN1Dvf65GOHDN6",
          "width": 2097
        },
        "s": {
          "extension": "jpg",
          "height": 320,
          "mimetype": "image/jpeg",
          "secret": "If1IWukrG60ozZpCGgKFERKnRevcVlI7",
          "width": 320
        },
        "z": {
          "extension": "jpg",
          "height": 462,
          "mimetype": "image/jpeg",
          "secret": "If1IWukrG60ozZpCGgKFERKnRevcVlI7",
          "width": 640
        }
      }
    },
    "media:uri_template": "https://static.sfomuseum.org/media/152/783/148/3/1527831483_{secret}_{label}.{extention}",
    "sfomuseum:filename": "60495.tif",
    "sfomuseum:image_index": 5,
    "sfomuseum:image_type": "studio",
    "sfomuseum:placetype": "image",
    "sfomuseum:primary_image": 1,
    "wof:depicts": [
      1511943239
    ],
    "wof:name": "stock certificate: Aviation Corporation of the Americas",
    "wof:placetype": "custom",
    "wof:placetype_alt": "image"
  },
  "geometry": {"coordinates":[-122.386155,37.616358],"type":"Point"}
}
