{
  "type": "Feature",
  "properties": {
    "iso:country": "XX",
    "media:fingerprint": "93925538c357c5c0ee7b068014d7504f6d4d113a",
    "media:imagehash_avg": "a:3e7f7f7f3e1e1c1c",
    "media:imagehash_diff": "d:f4e0f0f0fcf8f8f8",
    "media:medium": "image",
    "media:mimetype": "image/tiff",
    "media:properties": {
      "colours": [
        {
          "hex": "#b8c57f",
          "name": "#b8c57f",
          "reference": "vibrant"
        }, 
        {
          "hex": "#d1de9b",
          "name": "#d1de9b",
          "reference": "vibrant"
        }, 
        {
          "hex": "#98a663",
          "name": "#98a663",
          "reference": "vibrant"
        }, 
        {
          "hex": "#afc7a3",
          "name": "#afc7a3",
          "reference": "vibrant"
        }, 
        {
          "hex": "#40483a",
          "name": "#40483a",
          "reference": "vibrant"
        }
      ],
      "sizes": {
        "b": {
          "extension": "jpg",
          "height": 664,
          "mimetype": "image/jpeg",
          "secret": "oz5qnKBxAOifmjCxzOrLKpXJAi1R3iHR",
          "width": 1024
        },
        "c": {
          "extension": "jpg",
          "height": 519,
          "mimetype": "image/jpeg",
          "secret": "oz5qnKBxAOifmjCxzOrLKpXJAi1R3iHR",
          "width": 800
        },
        "dc": {
          "extension": "jpg",
          "height": 519,
          "mimetype": "image/jpeg",
          "secret": "oz5qnKBxAOifmjCxzOrLKpXJAi1R3iHR",
          "width": 800
        },
        "ds": {
          "extension": "jpg",
          "height": 320,
          "mimetype": "image/jpeg",
          "secret": "oz5qnKBxAOifmjCxzOrLKpXJAi1R3iHR",
          "width": 320
        },
        "k": {
          "extension": "jpg",
          "height": 1329,
          "mimetype": "image/jpeg",
          "secret": "oz5qnKBxAOifmjCxzOrLKpXJAi1R3iHR",
          "width": 2048
        },
        "n": {
          "extension": "jpg",
          "height": 207,
          "mimetype": "image/jpeg",
          "secret": "oz5qnKBxAOifmjCxzOrLKpXJAi1R3iHR",
          "width": 320
        },
        "o": {
          "extension": "jpg",
          "height": 1009,
          "mimetype": "image/jpeg",
          "secret": "hyLobur9A3mRJGklgmUsqc4dSACgvV2b",
          "width": 1554
        },
        "s": {
          "extension": "jpg",
          "height": 320,
          "mimetype": "image/jpeg",
          "secret": "oz5qnKBxAOifmjCxzOrLKpXJAi1R3iHR",
          "width": 320
        },
        "z": {
          "extension": "jpg",
          "height": 415,
          "mimetype": "image/jpeg",
          "secret": "oz5qnKBxAOifmjCxzOrLKpXJAi1R3iHR",
          "width": 640
        }
      }
    },
    "media:uri_template": "https://millsfield.sfomuseum.org/media/152/782/816/9/1527828169_{secret}_{label}.{extention}",
    "sfomuseum:filename": "44411.tif",
    "sfomuseum:image_index": 5,
    "sfomuseum:placetype": "image",
    "sfomuseum:primary_image": 1,
    "wof:depicts": [
      1511949201
    ],
    "wof:name": "negative: San Francisco International Airport (SFO), personnel",
    "wof:placetype": "media"
  },
  "geometry": {"coordinates":[-122.386155,37.616358],"type":"Point"}
}
