{
  "type": "Feature",
  "properties": {
    "iso:country": "US",
    "media:fingerprint": "8ffd4fca1516abf8431591013a3c2ba67bffca5a",
    "media:imagehash_avg": "a:e7c1fff18187ffff",
    "media:imagehash_diff": "d:ce0f8fc3073f94b4",
    "media:medium": "image",
    "media:mimetype": "image/tiff",
    "media:properties": {
      "colours": [
        {
          "hex": "#d73449",
          "name": "#d73449",
          "reference": "vibrant"
        }, 
        {
          "hex": "#df8392",
          "name": "#df8392",
          "reference": "vibrant"
        }, 
        {
          "hex": "#a63866",
          "name": "#a63866",
          "reference": "vibrant"
        }, 
        {
          "hex": "#5374aa",
          "name": "#5374aa",
          "reference": "vibrant"
        }, 
        {
          "hex": "#8d9ebe",
          "name": "#8d9ebe",
          "reference": "vibrant"
        }
      ],
      "sizes": {
        "b": {
          "extension": "jpg",
          "height": 768,
          "mimetype": "image/jpeg",
          "secret": "Aq0EZOXW2P7iGUruKMIQ1J3A6N3MSeZb",
          "width": 341
        },
        "c": {
          "extension": "jpg",
          "height": 600,
          "mimetype": "image/jpeg",
          "secret": "Aq0EZOXW2P7iGUruKMIQ1J3A6N3MSeZb",
          "width": 266
        },
        "dc": {
          "extension": "jpg",
          "height": 600,
          "mimetype": "image/jpeg",
          "secret": "Aq0EZOXW2P7iGUruKMIQ1J3A6N3MSeZb",
          "width": 266
        },
        "ds": {
          "extension": "jpg",
          "height": 320,
          "mimetype": "image/jpeg",
          "secret": "Aq0EZOXW2P7iGUruKMIQ1J3A6N3MSeZb",
          "width": 300
        },
        "k": {
          "extension": "jpg",
          "height": 1536,
          "mimetype": "image/jpeg",
          "secret": "Aq0EZOXW2P7iGUruKMIQ1J3A6N3MSeZb",
          "width": 682
        },
        "n": {
          "extension": "jpg",
          "height": 240,
          "mimetype": "image/jpeg",
          "secret": "Aq0EZOXW2P7iGUruKMIQ1J3A6N3MSeZb",
          "width": 106
        },
        "o": {
          "extension": "jpg",
          "height": 673,
          "mimetype": "image/jpeg",
          "secret": "uHNTpDjSZ46htqazj4XnfREQTCEa8nzY",
          "width": 299
        },
        "s": {
          "extension": "jpg",
          "height": 320,
          "mimetype": "image/jpeg",
          "secret": "Aq0EZOXW2P7iGUruKMIQ1J3A6N3MSeZb",
          "width": 300
        },
        "z": {
          "extension": "jpg",
          "height": 480,
          "mimetype": "image/jpeg",
          "secret": "Aq0EZOXW2P7iGUruKMIQ1J3A6N3MSeZb",
          "width": 213
        }
      }
    },
    "media:uri_template": "https://millsfield.sfomuseum.org/media/152/781/862/7/1527818627_{secret}_{label}.{extention}",
    "sfomuseum:filename": "19110.tif",
    "sfomuseum:image_index": 5,
    "sfomuseum:placetype": "image",
    "sfomuseum:primary_image": 1,
    "wof:depicts": [
      1511909871
    ],
    "wof:name": "timetable: United Airlines, quick reference Chicago",
    "wof:placetype": "media"
  },
  "geometry": {"coordinates":[-122.386155,37.616358],"type":"Point"}
}
