{
  "type": "Feature",
  "properties": {
    "iso:country": "XX",
    "media:fingerprint": "90a17a2e4169b91813c7ed6b6cf64ffccc29ac56",
    "media:imagehash_avg": "a:ffffffffdb000000",
    "media:imagehash_diff": "d:fe9eb2b232335968",
    "media:medium": "image",
    "media:mimetype": "image/tiff",
    "media:properties": {
      "colours": [
        {
          "hex": "#787878",
          "name": "#787878",
          "reference": "vibrant"
        }, 
        {
          "hex": "#c0c0c0",
          "name": "#c0c0c0",
          "reference": "vibrant"
        }, 
        {
          "hex": "#404040",
          "name": "#404040",
          "reference": "vibrant"
        }
      ],
      "sizes": {
        "b": {
          "extension": "jpg",
          "height": 768,
          "mimetype": "image/jpeg",
          "secret": "XoLN2mHen6DIYBG3YaxgjBA6K2w8WFmr",
          "width": 603
        },
        "c": {
          "extension": "jpg",
          "height": 600,
          "mimetype": "image/jpeg",
          "secret": "XoLN2mHen6DIYBG3YaxgjBA6K2w8WFmr",
          "width": 471
        },
        "dc": {
          "extension": "jpg",
          "height": 600,
          "mimetype": "image/jpeg",
          "secret": "XoLN2mHen6DIYBG3YaxgjBA6K2w8WFmr",
          "width": 471
        },
        "ds": {
          "extension": "jpg",
          "height": 320,
          "mimetype": "image/jpeg",
          "secret": "XoLN2mHen6DIYBG3YaxgjBA6K2w8WFmr",
          "width": 320
        },
        "k": {
          "extension": "jpg",
          "height": 1536,
          "mimetype": "image/jpeg",
          "secret": "XoLN2mHen6DIYBG3YaxgjBA6K2w8WFmr",
          "width": 1207
        },
        "n": {
          "extension": "jpg",
          "height": 240,
          "mimetype": "image/jpeg",
          "secret": "XoLN2mHen6DIYBG3YaxgjBA6K2w8WFmr",
          "width": 188
        },
        "o": {
          "extension": "jpg",
          "height": 2740,
          "mimetype": "image/jpeg",
          "secret": "0UiN3I8g92DZOwgvFvwm9DmrgOgbBqXk",
          "width": 2154
        },
        "s": {
          "extension": "jpg",
          "height": 320,
          "mimetype": "image/jpeg",
          "secret": "XoLN2mHen6DIYBG3YaxgjBA6K2w8WFmr",
          "width": 320
        },
        "z": {
          "extension": "jpg",
          "height": 480,
          "mimetype": "image/jpeg",
          "secret": "XoLN2mHen6DIYBG3YaxgjBA6K2w8WFmr",
          "width": 377
        }
      }
    },
    "media:uri_template": "https://millsfield.sfomuseum.org/media/152/782/405/1/1527824051_{secret}_{label}.{extention}",
    "sfomuseum:filename": "42243.tif",
    "sfomuseum:image_index": 5,
    "sfomuseum:placetype": "image",
    "sfomuseum:primary_image": 1,
    "wof:depicts": [
      1511945369
    ],
    "wof:name": "negative: San Francisco International Airport (SFO), Jorgen W. Jorgensen",
    "wof:placetype": "media"
  },
  "geometry": {"coordinates":[-122.386155,37.616358],"type":"Point"}
}
