{
  "type": "Feature",
  "properties": {
    "iso:country": "NZ",
    "media:fingerprint": "8548f6ade329edf8a0ea2a1a9a5f3b5b7286d564",
    "media:imagehash_avg": "a:00f8fefc7f3b3f01",
    "media:imagehash_diff": "d:61f1b1a1e2f2f05b",
    "media:medium": "image",
    "media:mimetype": "image/tiff",
    "media:properties": {
      "colours": [
        {
          "hex": "#e12613",
          "name": "#e12613",
          "reference": "vibrant"
        }, 
        {
          "hex": "#f8c3ac",
          "name": "#f8c3ac",
          "reference": "vibrant"
        }, 
        {
          "hex": "#222b4d",
          "name": "#222b4d",
          "reference": "vibrant"
        }, 
        {
          "hex": "#a49977",
          "name": "#a49977",
          "reference": "vibrant"
        }, 
        {
          "hex": "#c2b0c4",
          "name": "#c2b0c4",
          "reference": "vibrant"
        }
      ],
      "sizes": {
        "b": {
          "extension": "jpg",
          "height": 460,
          "mimetype": "image/jpeg",
          "secret": "4Nn0eb4UyFQu6Yg53odT87xPpV9XAczc",
          "width": 1024
        },
        "c": {
          "extension": "jpg",
          "height": 359,
          "mimetype": "image/jpeg",
          "secret": "4Nn0eb4UyFQu6Yg53odT87xPpV9XAczc",
          "width": 800
        },
        "dc": {
          "extension": "jpg",
          "height": 359,
          "mimetype": "image/jpeg",
          "secret": "4Nn0eb4UyFQu6Yg53odT87xPpV9XAczc",
          "width": 800
        },
        "ds": {
          "extension": "jpg",
          "height": 320,
          "mimetype": "image/jpeg",
          "secret": "4Nn0eb4UyFQu6Yg53odT87xPpV9XAczc",
          "width": 320
        },
        "k": {
          "extension": "jpg",
          "height": 921,
          "mimetype": "image/jpeg",
          "secret": "4Nn0eb4UyFQu6Yg53odT87xPpV9XAczc",
          "width": 2048
        },
        "n": {
          "extension": "jpg",
          "height": 143,
          "mimetype": "image/jpeg",
          "secret": "4Nn0eb4UyFQu6Yg53odT87xPpV9XAczc",
          "width": 320
        },
        "o": {
          "extension": "jpg",
          "height": 1325,
          "mimetype": "image/jpeg",
          "secret": "2bz75FQl3A7dr2haKteNmGOzmd6auoph",
          "width": 2946
        },
        "s": {
          "extension": "jpg",
          "height": 320,
          "mimetype": "image/jpeg",
          "secret": "4Nn0eb4UyFQu6Yg53odT87xPpV9XAczc",
          "width": 320
        },
        "z": {
          "extension": "jpg",
          "height": 287,
          "mimetype": "image/jpeg",
          "secret": "4Nn0eb4UyFQu6Yg53odT87xPpV9XAczc",
          "width": 640
        }
      }
    },
    "media:uri_template": "https://millsfield.sfomuseum.org/media/152/782/910/5/1527829105_{secret}_{label}.{extention}",
    "sfomuseum:filename": "47519.tif",
    "sfomuseum:image_index": 5,
    "sfomuseum:placetype": "image",
    "sfomuseum:primary_image": 1,
    "wof:depicts": [
      1511907257
    ],
    "wof:name": "airmail flight cover: Air Mail Service, Auckland - Honolulu route",
    "wof:placetype": "media"
  },
  "geometry": {"coordinates":[-122.386155,37.616358],"type":"Point"}
}
