{
  "type": "Feature",
  "properties": {
    "iso:country": "XX",
    "media:fingerprint": "0d667ece48ca8b6f98beb6c359150107a219a8ba",
    "media:imagehash_avg": "a:00fcfffffff7f7ff",
    "media:imagehash_diff": "d:f0d8941441848686",
    "media:medium": "image",
    "media:mimetype": "image/tiff",
    "media:properties": {
      "colours": [
        {
          "hex": "#1a1809",
          "name": "#1a1809",
          "reference": "vibrant"
        },
        {
          "hex": "#8b6a79",
          "name": "#8b6a79",
          "reference": "vibrant"
        },
        {
          "hex": "#c3c0bd",
          "name": "#c3c0bd",
          "reference": "vibrant"
        },
        {
          "hex": "#643245",
          "name": "#643245",
          "reference": "vibrant"
        }
      ],
      "sizes": {
        "b": {
          "extension": "jpg",
          "height": 746,
          "mimetype": "image/jpeg",
          "secret": "I6XdOhCAlWq3kWqbXyr7YcCyTZnQ4jRh",
          "width": 1023
        },
        "c": {
          "extension": "jpg",
          "height": 583,
          "mimetype": "image/jpeg",
          "secret": "I6XdOhCAlWq3kWqbXyr7YcCyTZnQ4jRh",
          "width": 800
        },
        "dc": {
          "extension": "jpg",
          "height": 583,
          "mimetype": "image/jpeg",
          "secret": "I6XdOhCAlWq3kWqbXyr7YcCyTZnQ4jRh",
          "width": 800
        },
        "ds": {
          "extension": "jpg",
          "height": 320,
          "mimetype": "image/jpeg",
          "secret": "I6XdOhCAlWq3kWqbXyr7YcCyTZnQ4jRh",
          "width": 320
        },
        "k": {
          "extension": "jpg",
          "height": 1493,
          "mimetype": "image/jpeg",
          "secret": "I6XdOhCAlWq3kWqbXyr7YcCyTZnQ4jRh",
          "width": 2047
        },
        "n": {
          "extension": "jpg",
          "height": 233,
          "mimetype": "image/jpeg",
          "secret": "I6XdOhCAlWq3kWqbXyr7YcCyTZnQ4jRh",
          "width": 320
        },
        "o": {
          "extension": "jpg",
          "height": 2400,
          "mimetype": "image/jpeg",
          "secret": "mPjOXGAjVKXIxIDZCdfzRWqDfSVzvjMf",
          "width": 3291
        },
        "s": {
          "extension": "jpg",
          "height": 320,
          "mimetype": "image/jpeg",
          "secret": "I6XdOhCAlWq3kWqbXyr7YcCyTZnQ4jRh",
          "width": 320
        },
        "z": {
          "extension": "jpg",
          "height": 466,
          "mimetype": "image/jpeg",
          "secret": "I6XdOhCAlWq3kWqbXyr7YcCyTZnQ4jRh",
          "width": 640
        }
      }
    },
    "media:uri_template": "https://static.sfomuseum.org/media/152/784/501/5/1527845015_{secret}_{label}.{extention}",
    "sfomuseum:filename": "69532.tif",
    "sfomuseum:image_index": 5,
    "sfomuseum:image_type": "studio",
    "sfomuseum:placetype": "image",
    "sfomuseum:primary_image": 0,
    "wof:depicts": [
      1159284261,
      1511921725
    ],
    "wof:name": "menu: Delta Air Lines, Business Class",
    "wof:placetype": "custom",
    "wof:placetype_alt": "image"
  },
  "geometry": {"coordinates":[-122.386155,37.616358],"type":"Point"}
}
