{
  "type": "Feature",
  "properties": {
    "iso:country": "XX",
    "media:fingerprint": "a49b63eafebd168de7253deb1c092a1d577b77e8",
    "media:imagehash_avg": "a:fedefefebcfcfc00",
    "media:imagehash_diff": "d:0814545070505064",
    "media:medium": "image",
    "media:mimetype": "image/tiff",
    "media:properties": {
      "colours": [
        {
          "hex": "#b6c621",
          "name": "#b6c621",
          "reference": "vibrant"
        },
        {
          "hex": "#96afd8",
          "name": "#96afd8",
          "reference": "vibrant"
        },
        {
          "hex": "#7d3c0f",
          "name": "#7d3c0f",
          "reference": "vibrant"
        },
        {
          "hex": "#b6b663",
          "name": "#b6b663",
          "reference": "vibrant"
        },
        {
          "hex": "#d5d8a9",
          "name": "#d5d8a9",
          "reference": "vibrant"
        }
      ],
      "sizes": {
        "b": {
          "extension": "jpg",
          "height": 768,
          "mimetype": "image/jpeg",
          "secret": "kicgZV32RcTEhC8poBj8t4wFK9JUy9qZ",
          "width": 970
        },
        "c": {
          "extension": "jpg",
          "height": 600,
          "mimetype": "image/jpeg",
          "secret": "kicgZV32RcTEhC8poBj8t4wFK9JUy9qZ",
          "width": 758
        },
        "dc": {
          "extension": "jpg",
          "height": 600,
          "mimetype": "image/jpeg",
          "secret": "kicgZV32RcTEhC8poBj8t4wFK9JUy9qZ",
          "width": 758
        },
        "ds": {
          "extension": "jpg",
          "height": 320,
          "mimetype": "image/jpeg",
          "secret": "kicgZV32RcTEhC8poBj8t4wFK9JUy9qZ",
          "width": 320
        },
        "k": {
          "extension": "jpg",
          "height": 1536,
          "mimetype": "image/jpeg",
          "secret": "kicgZV32RcTEhC8poBj8t4wFK9JUy9qZ",
          "width": 1941
        },
        "n": {
          "extension": "jpg",
          "height": 239,
          "mimetype": "image/jpeg",
          "secret": "kicgZV32RcTEhC8poBj8t4wFK9JUy9qZ",
          "width": 303
        },
        "o": {
          "extension": "jpg",
          "height": 1899,
          "mimetype": "image/jpeg",
          "secret": "cREOZHYI7FYc5TmWDCPWJSsahcDglvAq",
          "width": 2400
        },
        "s": {
          "extension": "jpg",
          "height": 320,
          "mimetype": "image/jpeg",
          "secret": "kicgZV32RcTEhC8poBj8t4wFK9JUy9qZ",
          "width": 320
        },
        "z": {
          "extension": "jpg",
          "height": 479,
          "mimetype": "image/jpeg",
          "secret": "kicgZV32RcTEhC8poBj8t4wFK9JUy9qZ",
          "width": 606
        }
      }
    },
    "media:uri_template": "https://static.sfomuseum.org/media/152/784/366/9/1527843669_{secret}_{label}.{extention}",
    "sfomuseum:filename": "68627.tif",
    "sfomuseum:image_index": 5,
    "sfomuseum:image_type": "studio",
    "sfomuseum:placetype": "image",
    "sfomuseum:primary_image": 0,
    "wof:depicts": [
      1159284127,
      1159286837,
      1511927641
    ],
    "wof:name": "menu: Cathay Pacific Airways, Business Class",
    "wof:placetype": "custom",
    "wof:placetype_alt": "image"
  },
  "geometry": {"coordinates":[-122.386155,37.616358],"type":"Point"}
}
