{
  "type": "Feature",
  "properties": {
    "iso:country": "XX",
    "media:fingerprint": "8c46cef9dc514c4789d2adc6260bcfcf10ab10a8",
    "media:imagehash_avg": "a:f8f8fcfcfefffffe",
    "media:imagehash_diff": "d:a0808080c0c0c0c0",
    "media:medium": "image",
    "media:mimetype": "image/tiff",
    "media:properties": {
      "colours": [
        {
          "hex": "#808080",
          "name": "#808080",
          "reference": "vibrant"
        }, 
        {
          "hex": "#c0c0c0",
          "name": "#c0c0c0",
          "reference": "vibrant"
        }, 
        {
          "hex": "#404040",
          "name": "#404040",
          "reference": "vibrant"
        }
      ],
      "sizes": {
        "b": {
          "extension": "jpg",
          "height": 768,
          "mimetype": "image/jpeg",
          "secret": "3aXzaBAV3pJz6DqH0AwNfcbfSaWuty0T",
          "width": 784
        },
        "c": {
          "extension": "jpg",
          "height": 600,
          "mimetype": "image/jpeg",
          "secret": "3aXzaBAV3pJz6DqH0AwNfcbfSaWuty0T",
          "width": 612
        },
        "dc": {
          "extension": "jpg",
          "height": 600,
          "mimetype": "image/jpeg",
          "secret": "3aXzaBAV3pJz6DqH0AwNfcbfSaWuty0T",
          "width": 612
        },
        "ds": {
          "extension": "jpg",
          "height": 320,
          "mimetype": "image/jpeg",
          "secret": "3aXzaBAV3pJz6DqH0AwNfcbfSaWuty0T",
          "width": 320
        },
        "k": {
          "extension": "jpg",
          "height": 1536,
          "mimetype": "image/jpeg",
          "secret": "3aXzaBAV3pJz6DqH0AwNfcbfSaWuty0T",
          "width": 1568
        },
        "n": {
          "extension": "jpg",
          "height": 240,
          "mimetype": "image/jpeg",
          "secret": "3aXzaBAV3pJz6DqH0AwNfcbfSaWuty0T",
          "width": 245
        },
        "o": {
          "extension": "jpg",
          "height": 2536,
          "mimetype": "image/jpeg",
          "secret": "IrPItxEGhS4Hej4UuECysgmxMvHRekNA",
          "width": 2590
        },
        "s": {
          "extension": "jpg",
          "height": 320,
          "mimetype": "image/jpeg",
          "secret": "3aXzaBAV3pJz6DqH0AwNfcbfSaWuty0T",
          "width": 320
        },
        "z": {
          "extension": "jpg",
          "height": 480,
          "mimetype": "image/jpeg",
          "secret": "3aXzaBAV3pJz6DqH0AwNfcbfSaWuty0T",
          "width": 490
        }
      }
    },
    "media:uri_template": "https://millsfield.sfomuseum.org/media/152/782/414/1/1527824141_{secret}_{label}.{extention}",
    "sfomuseum:filename": "42284.tif",
    "sfomuseum:image_index": 5,
    "sfomuseum:placetype": "image",
    "sfomuseum:primary_image": 1,
    "wof:depicts": [
      1511945459
    ],
    "wof:name": "negative: San Francisco International Airport (SFO), parking garage construction",
    "wof:placetype": "media"
  },
  "geometry": {"coordinates":[-122.386155,37.616358],"type":"Point"}
}
