{
  "type": "Feature",
  "properties": {
    "iso:country": "XX",
    "media:fingerprint": "dd76f80a875fafbb74a7a6212470c8b99f0911ba",
    "media:imagehash_avg": "a:3e0efefe04000000",
    "media:imagehash_diff": "d:f0fc40ec4c64b831",
    "media:medium": "image",
    "media:mimetype": "image/tiff",
    "media:properties": {
      "colours": [
        {
          "hex": "#808080",
          "name": "#808080",
          "reference": "vibrant"
        }, 
        {
          "hex": "#c0c0c0",
          "name": "#c0c0c0",
          "reference": "vibrant"
        }, 
        {
          "hex": "#464646",
          "name": "#464646",
          "reference": "vibrant"
        }
      ],
      "sizes": {
        "b": {
          "extension": "jpg",
          "height": 693,
          "mimetype": "image/jpeg",
          "secret": "YU2RVRC5FtaKEJBdECJGgZ0uCp0ACciW",
          "width": 1024
        },
        "c": {
          "extension": "jpg",
          "height": 542,
          "mimetype": "image/jpeg",
          "secret": "YU2RVRC5FtaKEJBdECJGgZ0uCp0ACciW",
          "width": 800
        },
        "dc": {
          "extension": "jpg",
          "height": 542,
          "mimetype": "image/jpeg",
          "secret": "YU2RVRC5FtaKEJBdECJGgZ0uCp0ACciW",
          "width": 800
        },
        "ds": {
          "extension": "jpg",
          "height": 320,
          "mimetype": "image/jpeg",
          "secret": "YU2RVRC5FtaKEJBdECJGgZ0uCp0ACciW",
          "width": 320
        },
        "k": {
          "extension": "jpg",
          "height": 1387,
          "mimetype": "image/jpeg",
          "secret": "YU2RVRC5FtaKEJBdECJGgZ0uCp0ACciW",
          "width": 2048
        },
        "n": {
          "extension": "jpg",
          "height": 216,
          "mimetype": "image/jpeg",
          "secret": "YU2RVRC5FtaKEJBdECJGgZ0uCp0ACciW",
          "width": 320
        },
        "o": {
          "extension": "jpg",
          "height": 1076,
          "mimetype": "image/jpeg",
          "secret": "0HXUo2pdsEVkTJDzQh7TC78oe1gWeghy",
          "width": 1588
        },
        "s": {
          "extension": "jpg",
          "height": 320,
          "mimetype": "image/jpeg",
          "secret": "YU2RVRC5FtaKEJBdECJGgZ0uCp0ACciW",
          "width": 320
        },
        "z": {
          "extension": "jpg",
          "height": 433,
          "mimetype": "image/jpeg",
          "secret": "YU2RVRC5FtaKEJBdECJGgZ0uCp0ACciW",
          "width": 640
        }
      }
    },
    "media:uri_template": "https://millsfield.sfomuseum.org/media/152/782/841/5/1527828415_{secret}_{label}.{extention}",
    "sfomuseum:filename": "44582.tif",
    "sfomuseum:image_index": 5,
    "sfomuseum:placetype": "image",
    "sfomuseum:primary_image": 1,
    "wof:depicts": [
      1511949449
    ],
    "wof:name": "negative: San Francisco International Airport (SFO), Central Terminal interior",
    "wof:placetype": "media"
  },
  "geometry": {"coordinates":[-122.386155,37.616358],"type":"Point"}
}
