{
  "type": "Feature",
  "properties": {
    "date:cessation_lower": "1910-01-01",
    "date:cessation_upper": "1910-12-31",
    "date:inception_lower": "1910-01-01",
    "date:inception_upper": "1910-12-31",
    "iso:country": "XX",
    "media:imagehash_avg": "a:e19d80030323173f",
    "media:imagehash_diff": "d:017d511e5666aefb",
    "media:imagetext": "THE\nMOTOR BOYS\nIN\nTHE\nCLOUDS\nмотор\nBOYS\nSERIES.\nCLARENCE YOUNG",
    "media:imagetext_created": 1701940816,
    "media:mimetype": "image/jpeg",
    "media:properties": {
    },
    "media:uri_template": "https://static.sfomuseum.org/media/174/668/038/1/1746680381_{secret}_{label}.{extention}",
    "millsfield:exhibition_ids": [
      1159160363
    ],
    "millsfield:images_texts": [
      "THE\nMOTOR BOYS\nIN\nTHE\nCLOUDS\nмотор\nBOYS\nSERIES.\nCLARENCE YOUNG"
    ],
    "millsfield:images_texts_ids": [
      1746680381
    ],
    "millsfield:on_view": 0,
    "sfomuseum:filename": "57524.jpg",
    "sfomuseum:image_index": 0,
    "sfomuseum:image_type": "studio",
    "sfomuseum:placetype": "image",
    "sfomuseum:primary_image": 1,
    "wof:depicts": [
      1511913167
    ],
    "wof:name": "The motor boys in the clouds: or, A trip for fame and fortune",
    "wof:placetype": "custom"
  },
  "geometry": {"coordinates":[-122.386155,37.616357],"type":"Point"}
}
