{
  "type": "Feature",
  "properties": {
    "media:imagehash_avg": "a:e19d80030323173f",
    "media:imagehash_diff": "d:017d511e5666aefb",
    "media:mimetype": "image/jpeg",
    "media:properties": {
    },
    "media:uri_template": "https://static.sfomuseum.org/media/174/668/038/1/1746680381_{secret}_{label}.{extention}",
    "sfomuseum:filename": "57524.jpg",
    "sfomuseum:image_index": 0,
    "sfomuseum:image_type": "curator",
    "sfomuseum:placetype": "image",
    "sfomuseum:primary_image": 1,
    "wof:depicts": [
      1511913167
    ],
    "wof:name": "The motor boys in the clouds: or, A trip for fame and fortune",
    "wof:placetype": "custom"
  },
  "geometry": {"coordinates":[-122.386155,37.616357],"type":"Point"}
}
