{
  "type": "Feature",
  "properties": {
    "iso:country": "XX",
    "media:fingerprint": "263ad6a1982b682a09e2bcddf1c3aa1be4188208",
    "media:imagehash_avg": "a:ffff7f7e7e600000",
    "media:imagehash_diff": "d:888480808080a0a0",
    "media:medium": "image",
    "media:mimetype": "image/tiff",
    "media:properties": {
      "colours": [
        {
          "hex": "#e8e8f8",
          "name": "#e8e8f8",
          "reference": "vibrant"
        },
        {
          "hex": "#808189",
          "name": "#808189",
          "reference": "vibrant"
        },
        {
          "hex": "#babdc2",
          "name": "#babdc2",
          "reference": "vibrant"
        }
      ],
      "sizes": {
        "b": {
          "extension": "jpg",
          "height": 768,
          "mimetype": "image/jpeg",
          "secret": "eFK6hMcapotnA8twk52103sc4TxFgmgP",
          "width": 544
        },
        "c": {
          "extension": "jpg",
          "height": 600,
          "mimetype": "image/jpeg",
          "secret": "eFK6hMcapotnA8twk52103sc4TxFgmgP",
          "width": 425
        },
        "dc": {
          "extension": "jpg",
          "height": 600,
          "mimetype": "image/jpeg",
          "secret": "eFK6hMcapotnA8twk52103sc4TxFgmgP",
          "width": 425
        },
        "ds": {
          "extension": "jpg",
          "height": 320,
          "mimetype": "image/jpeg",
          "secret": "eFK6hMcapotnA8twk52103sc4TxFgmgP",
          "width": 320
        },
        "k": {
          "extension": "jpg",
          "height": 1536,
          "mimetype": "image/jpeg",
          "secret": "eFK6hMcapotnA8twk52103sc4TxFgmgP",
          "width": 1088
        },
        "n": {
          "extension": "jpg",
          "height": 239,
          "mimetype": "image/jpeg",
          "secret": "eFK6hMcapotnA8twk52103sc4TxFgmgP",
          "width": 170
        },
        "o": {
          "extension": "jpg",
          "height": 3587,
          "mimetype": "image/jpeg",
          "secret": "heZxrb0VG9Rd1HryN8t5Lk2G9YDtlGxy",
          "width": 2543
        },
        "s": {
          "extension": "jpg",
          "height": 320,
          "mimetype": "image/jpeg",
          "secret": "eFK6hMcapotnA8twk52103sc4TxFgmgP",
          "width": 320
        },
        "z": {
          "extension": "jpg",
          "height": 479,
          "mimetype": "image/jpeg",
          "secret": "eFK6hMcapotnA8twk52103sc4TxFgmgP",
          "width": 340
        }
      }
    },
    "media:uri_template": "https://static.sfomuseum.org/media/152/783/035/1/1527830351_{secret}_{label}.{extention}",
    "sfomuseum:filename": "53659.tif",
    "sfomuseum:image_index": 5,
    "sfomuseum:image_type": "studio",
    "sfomuseum:placetype": "image",
    "sfomuseum:primary_image": 0,
    "wof:depicts": [
      1159290173,
      1159293811,
      1159284021,
      1511938167
    ],
    "wof:name": "flight information packet: British Airways, Concorde",
    "wof:placetype": "custom",
    "wof:placetype_alt": "image"
  },
  "geometry": {"coordinates":[-122.386155,37.616358],"type":"Point"}
}
