{
  "type": "Feature",
  "properties": {
    "iso:country": "XX",
    "media:fingerprint": "359294089777501074191cd18b359027627cfce5",
    "media:imagehash_avg": "a:ffcbc7070b016701",
    "media:imagehash_diff": "d:979b8f0f9b8b8fa5",
    "media:medium": "image",
    "media:mimetype": "image/tiff",
    "media:properties": {
      "colours": [
        {
          "hex": "#405790",
          "name": "#405790",
          "reference": "vibrant"
        }, 
        {
          "hex": "#f4e7c8",
          "name": "#f4e7c8",
          "reference": "vibrant"
        }, 
        {
          "hex": "#2f427a",
          "name": "#2f427a",
          "reference": "vibrant"
        }, 
        {
          "hex": "#62769d",
          "name": "#62769d",
          "reference": "vibrant"
        }, 
        {
          "hex": "#d4cbb7",
          "name": "#d4cbb7",
          "reference": "vibrant"
        }
      ],
      "sizes": {
        "b": {
          "extension": "jpg",
          "height": 768,
          "mimetype": "image/jpeg",
          "secret": "THwZVlHh8VAVgIFJaTmpSThlPt6bTKip",
          "width": 429
        },
        "c": {
          "extension": "jpg",
          "height": 600,
          "mimetype": "image/jpeg",
          "secret": "THwZVlHh8VAVgIFJaTmpSThlPt6bTKip",
          "width": 335
        },
        "dc": {
          "extension": "jpg",
          "height": 600,
          "mimetype": "image/jpeg",
          "secret": "THwZVlHh8VAVgIFJaTmpSThlPt6bTKip",
          "width": 335
        },
        "ds": {
          "extension": "jpg",
          "height": 320,
          "mimetype": "image/jpeg",
          "secret": "THwZVlHh8VAVgIFJaTmpSThlPt6bTKip",
          "width": 320
        },
        "k": {
          "extension": "jpg",
          "height": 1536,
          "mimetype": "image/jpeg",
          "secret": "THwZVlHh8VAVgIFJaTmpSThlPt6bTKip",
          "width": 858
        },
        "n": {
          "extension": "jpg",
          "height": 240,
          "mimetype": "image/jpeg",
          "secret": "THwZVlHh8VAVgIFJaTmpSThlPt6bTKip",
          "width": 134
        },
        "o": {
          "extension": "jpg",
          "height": 2951,
          "mimetype": "image/jpeg",
          "secret": "NWiwrH6EuSUnif1Pr4v1nSZEP9u35FbF",
          "width": 1650
        },
        "s": {
          "extension": "jpg",
          "height": 320,
          "mimetype": "image/jpeg",
          "secret": "THwZVlHh8VAVgIFJaTmpSThlPt6bTKip",
          "width": 320
        },
        "z": {
          "extension": "jpg",
          "height": 480,
          "mimetype": "image/jpeg",
          "secret": "THwZVlHh8VAVgIFJaTmpSThlPt6bTKip",
          "width": 268
        }
      }
    },
    "media:uri_template": "https://millsfield.sfomuseum.org/media/152/782/480/7/1527824807_{secret}_{label}.{extention}",
    "sfomuseum:filename": "42805.tif",
    "sfomuseum:image_index": 5,
    "sfomuseum:placetype": "image",
    "sfomuseum:primary_image": 0,
    "wof:depicts": [
      1511908637
    ],
    "wof:name": "airsickness bag: JAL (Japan Air Lines)",
    "wof:placetype": "media"
  },
  "geometry": {"coordinates":[-122.386155,37.616358],"type":"Point"}
}
