{
  "type": "Feature",
  "properties": {
    "iso:country": "XX",
    "media:fingerprint": "1f1d30ea88216dd89d77736d51203a779fc8f450",
    "media:imagehash_avg": "a:ffff7f1090800000",
    "media:imagehash_diff": "d:50f0f0a121602c29",
    "media:medium": "image",
    "media:mimetype": "image/tiff",
    "media:properties": {
      "colours": [
        {
          "hex": "#808080",
          "name": "#808080",
          "reference": "vibrant"
        }, 
        {
          "hex": "#b8b8b8",
          "name": "#b8b8b8",
          "reference": "vibrant"
        }, 
        {
          "hex": "#4a4a4a",
          "name": "#4a4a4a",
          "reference": "vibrant"
        }
      ],
      "sizes": {
        "b": {
          "extension": "jpg",
          "height": 768,
          "mimetype": "image/jpeg",
          "secret": "uMNJmjr5Rq1JaOZF0ujuvwBpcn5VXC6f",
          "width": 975
        },
        "c": {
          "extension": "jpg",
          "height": 600,
          "mimetype": "image/jpeg",
          "secret": "uMNJmjr5Rq1JaOZF0ujuvwBpcn5VXC6f",
          "width": 762
        },
        "dc": {
          "extension": "jpg",
          "height": 600,
          "mimetype": "image/jpeg",
          "secret": "uMNJmjr5Rq1JaOZF0ujuvwBpcn5VXC6f",
          "width": 762
        },
        "ds": {
          "extension": "jpg",
          "height": 320,
          "mimetype": "image/jpeg",
          "secret": "uMNJmjr5Rq1JaOZF0ujuvwBpcn5VXC6f",
          "width": 320
        },
        "k": {
          "extension": "jpg",
          "height": 1536,
          "mimetype": "image/jpeg",
          "secret": "uMNJmjr5Rq1JaOZF0ujuvwBpcn5VXC6f",
          "width": 1951
        },
        "n": {
          "extension": "jpg",
          "height": 240,
          "mimetype": "image/jpeg",
          "secret": "uMNJmjr5Rq1JaOZF0ujuvwBpcn5VXC6f",
          "width": 304
        },
        "o": {
          "extension": "jpg",
          "height": 2168,
          "mimetype": "image/jpeg",
          "secret": "5THUn3tVRQNuGkden618zxAO4h1ozSqZ",
          "width": 2754
        },
        "s": {
          "extension": "jpg",
          "height": 320,
          "mimetype": "image/jpeg",
          "secret": "uMNJmjr5Rq1JaOZF0ujuvwBpcn5VXC6f",
          "width": 320
        },
        "z": {
          "extension": "jpg",
          "height": 480,
          "mimetype": "image/jpeg",
          "secret": "uMNJmjr5Rq1JaOZF0ujuvwBpcn5VXC6f",
          "width": 609
        }
      }
    },
    "media:uri_template": "https://millsfield.sfomuseum.org/media/152/782/527/1/1527825271_{secret}_{label}.{extention}",
    "sfomuseum:filename": "43059.tif",
    "sfomuseum:image_index": 5,
    "sfomuseum:placetype": "image",
    "sfomuseum:primary_image": 1,
    "wof:depicts": [
      1511946287
    ],
    "wof:name": "negative: San Francisco Transbay Terminal",
    "wof:placetype": "media"
  },
  "geometry": {"coordinates":[-122.386155,37.616358],"type":"Point"}
}
