{
  "type": "Feature",
  "properties": {
    "iso:country": "XX",
    "media:fingerprint": "79a4680138d2735a024eaf2e3b9f1cbd1a94e357",
    "media:imagehash_avg": "a:7f3f0fffff00017f",
    "media:imagehash_diff": "d:ca7b73d2d317ddc9",
    "media:medium": "image",
    "media:mimetype": "image/tiff",
    "media:properties": {
      "colours": [
        {
          "hex": "#f7efe7",
          "name": "#f7efe7",
          "reference": "vibrant"
        }, 
        {
          "hex": "#636a99",
          "name": "#636a99",
          "reference": "vibrant"
        }, 
        {
          "hex": "#bbbec3",
          "name": "#bbbec3",
          "reference": "vibrant"
        }, 
        {
          "hex": "#454f83",
          "name": "#454f83",
          "reference": "vibrant"
        }
      ],
      "sizes": {
        "b": {
          "extension": "jpg",
          "height": 768,
          "mimetype": "image/jpeg",
          "secret": "cP0pg2X3jcR3MLz6cuQCiXjJDhOBTzmn",
          "width": 386
        },
        "c": {
          "extension": "jpg",
          "height": 600,
          "mimetype": "image/jpeg",
          "secret": "cP0pg2X3jcR3MLz6cuQCiXjJDhOBTzmn",
          "width": 302
        },
        "dc": {
          "extension": "jpg",
          "height": 600,
          "mimetype": "image/jpeg",
          "secret": "cP0pg2X3jcR3MLz6cuQCiXjJDhOBTzmn",
          "width": 302
        },
        "ds": {
          "extension": "jpg",
          "height": 320,
          "mimetype": "image/jpeg",
          "secret": "cP0pg2X3jcR3MLz6cuQCiXjJDhOBTzmn",
          "width": 320
        },
        "k": {
          "extension": "jpg",
          "height": 1536,
          "mimetype": "image/jpeg",
          "secret": "cP0pg2X3jcR3MLz6cuQCiXjJDhOBTzmn",
          "width": 773
        },
        "n": {
          "extension": "jpg",
          "height": 239,
          "mimetype": "image/jpeg",
          "secret": "cP0pg2X3jcR3MLz6cuQCiXjJDhOBTzmn",
          "width": 120
        },
        "o": {
          "extension": "jpg",
          "height": 2928,
          "mimetype": "image/jpeg",
          "secret": "y3cPV9MoYz2ucLQbDE8pdTIxgstCjUPU",
          "width": 1475
        },
        "s": {
          "extension": "jpg",
          "height": 320,
          "mimetype": "image/jpeg",
          "secret": "cP0pg2X3jcR3MLz6cuQCiXjJDhOBTzmn",
          "width": 320
        },
        "z": {
          "extension": "jpg",
          "height": 479,
          "mimetype": "image/jpeg",
          "secret": "cP0pg2X3jcR3MLz6cuQCiXjJDhOBTzmn",
          "width": 241
        }
      }
    },
    "media:uri_template": "https://millsfield.sfomuseum.org/media/152/782/336/1/1527823361_{secret}_{label}.{extention}",
    "sfomuseum:filename": "41516.tif",
    "sfomuseum:image_index": 5,
    "sfomuseum:placetype": "image",
    "sfomuseum:primary_image": 1,
    "wof:depicts": [
      1511908361
    ],
    "wof:name": "airsickness bag: Air Europa",
    "wof:placetype": "media"
  },
  "geometry": {"coordinates":[-122.386155,37.616358],"type":"Point"}
}
