{
  "type": "Feature",
  "properties": {
    "iso:country": "XX",
    "media:fingerprint": "3c506d3227f6ca102c9ab5150a00d29611c82760",
    "media:imagehash_avg": "a:ffff0000c3e7ffff",
    "media:imagehash_diff": "d:0000616b0f0e0400",
    "media:medium": "image",
    "media:mimetype": "image/tiff",
    "media:properties": {
      "colours": [
        {
          "hex": "#e2b341",
          "name": "#e2b341",
          "reference": "vibrant"
        },
        {
          "hex": "#edd091",
          "name": "#edd091",
          "reference": "vibrant"
        },
        {
          "hex": "#593e1b",
          "name": "#593e1b",
          "reference": "vibrant"
        },
        {
          "hex": "#a3804f",
          "name": "#a3804f",
          "reference": "vibrant"
        },
        {
          "hex": "#b0b0b8",
          "name": "#b0b0b8",
          "reference": "vibrant"
        }
      ],
      "sizes": {
        "b": {
          "extension": "jpg",
          "height": 685,
          "mimetype": "image/jpeg",
          "secret": "xrOFTDFq0X0dIaHsupfkpCjSq2HWR9pR",
          "width": 1024
        },
        "c": {
          "extension": "jpg",
          "height": 535,
          "mimetype": "image/jpeg",
          "secret": "xrOFTDFq0X0dIaHsupfkpCjSq2HWR9pR",
          "width": 800
        },
        "dc": {
          "extension": "jpg",
          "height": 535,
          "mimetype": "image/jpeg",
          "secret": "xrOFTDFq0X0dIaHsupfkpCjSq2HWR9pR",
          "width": 800
        },
        "ds": {
          "extension": "jpg",
          "height": 320,
          "mimetype": "image/jpeg",
          "secret": "xrOFTDFq0X0dIaHsupfkpCjSq2HWR9pR",
          "width": 320
        },
        "k": {
          "extension": "jpg",
          "height": 1371,
          "mimetype": "image/jpeg",
          "secret": "xrOFTDFq0X0dIaHsupfkpCjSq2HWR9pR",
          "width": 2048
        },
        "n": {
          "extension": "jpg",
          "height": 214,
          "mimetype": "image/jpeg",
          "secret": "xrOFTDFq0X0dIaHsupfkpCjSq2HWR9pR",
          "width": 320
        },
        "o": {
          "extension": "jpg",
          "height": 2400,
          "mimetype": "image/jpeg",
          "secret": "GjJ4aRIhecNFY7hPlBHVfeop23hE7PQt",
          "width": 3585
        },
        "s": {
          "extension": "jpg",
          "height": 320,
          "mimetype": "image/jpeg",
          "secret": "xrOFTDFq0X0dIaHsupfkpCjSq2HWR9pR",
          "width": 320
        },
        "z": {
          "extension": "jpg",
          "height": 428,
          "mimetype": "image/jpeg",
          "secret": "xrOFTDFq0X0dIaHsupfkpCjSq2HWR9pR",
          "width": 640
        }
      }
    },
    "media:uri_template": "https://millsfield.sfomuseum.org/media/152/785/412/5/1527854125_{secret}_{label}.{extention}",
    "sfomuseum:filename": "2012.147.141.tif",
    "sfomuseum:image_index": 5,
    "sfomuseum:placetype": "image",
    "sfomuseum:primary_image": 1,
    "wof:depicts": [
      1511952619
    ],
    "wof:name": "in-flight manager wings: Thai Airways International",
    "wof:placetype": "custom",
    "wof:placetype_alt": "image"
  },
  "geometry": {"coordinates":[-122.386155,37.616358],"type":"Point"}
}
