{
  "type": "Feature",
  "properties": {
    "iso:country": "XX",
    "media:fingerprint": "cbc80ad75ad235056c6bbf9e3001fedb3e62d62c",
    "media:imagehash_avg": "a:ffffeff0e0e0e000",
    "media:imagehash_diff": "d:8c8e8c8585818084",
    "media:medium": "image",
    "media:mimetype": "image/tiff",
    "media:properties": {
      "colours": [
        {
          "hex": "#868686",
          "name": "#868686",
          "reference": "vibrant"
        }, 
        {
          "hex": "#b8b8b8",
          "name": "#b8b8b8",
          "reference": "vibrant"
        }, 
        {
          "hex": "#404040",
          "name": "#404040",
          "reference": "vibrant"
        }
      ],
      "sizes": {
        "b": {
          "extension": "jpg",
          "height": 768,
          "mimetype": "image/jpeg",
          "secret": "41bKTHvqJlsBXlw7DXfMJXgT9WLiMo6s",
          "width": 768
        },
        "c": {
          "extension": "jpg",
          "height": 600,
          "mimetype": "image/jpeg",
          "secret": "41bKTHvqJlsBXlw7DXfMJXgT9WLiMo6s",
          "width": 600
        },
        "dc": {
          "extension": "jpg",
          "height": 600,
          "mimetype": "image/jpeg",
          "secret": "41bKTHvqJlsBXlw7DXfMJXgT9WLiMo6s",
          "width": 600
        },
        "ds": {
          "extension": "jpg",
          "height": 320,
          "mimetype": "image/jpeg",
          "secret": "41bKTHvqJlsBXlw7DXfMJXgT9WLiMo6s",
          "width": 320
        },
        "k": {
          "extension": "jpg",
          "height": 1536,
          "mimetype": "image/jpeg",
          "secret": "41bKTHvqJlsBXlw7DXfMJXgT9WLiMo6s",
          "width": 1536
        },
        "n": {
          "extension": "jpg",
          "height": 240,
          "mimetype": "image/jpeg",
          "secret": "41bKTHvqJlsBXlw7DXfMJXgT9WLiMo6s",
          "width": 240
        },
        "o": {
          "extension": "jpg",
          "height": 2481,
          "mimetype": "image/jpeg",
          "secret": "pYbS6wiwzoHmg12xFyu6ZDIDbH4lALAW",
          "width": 2481
        },
        "s": {
          "extension": "jpg",
          "height": 320,
          "mimetype": "image/jpeg",
          "secret": "41bKTHvqJlsBXlw7DXfMJXgT9WLiMo6s",
          "width": 320
        },
        "z": {
          "extension": "jpg",
          "height": 480,
          "mimetype": "image/jpeg",
          "secret": "41bKTHvqJlsBXlw7DXfMJXgT9WLiMo6s",
          "width": 480
        }
      }
    },
    "media:uri_template": "https://millsfield.sfomuseum.org/media/152/782/496/3/1527824963_{secret}_{label}.{extention}",
    "sfomuseum:filename": "42902.tif",
    "sfomuseum:image_index": 5,
    "sfomuseum:placetype": "image",
    "sfomuseum:primary_image": 1,
    "wof:depicts": [
      1511945843
    ],
    "wof:name": "photograph: San Francisco International Airport (SFO), parking garage construction",
    "wof:placetype": "media"
  },
  "geometry": {"coordinates":[-122.386155,37.616358],"type":"Point"}
}
