{
  "type": "Feature",
  "properties": {
    "iso:country": "XX",
    "media:fingerprint": "a6ceb89299fb2bc33d92d6703c1c58aa513e4253",
    "media:imagehash_avg": "a:fff7f7ff63674300",
    "media:imagehash_diff": "d:c58587878ecf971f",
    "media:medium": "image",
    "media:mimetype": "image/tiff",
    "media:properties": {
      "colours": [
        {
          "hex": "#f65f5a",
          "name": "#f65f5a",
          "reference": "vibrant"
        }, 
        {
          "hex": "#f89093",
          "name": "#f89093",
          "reference": "vibrant"
        }, 
        {
          "hex": "#6c3145",
          "name": "#6c3145",
          "reference": "vibrant"
        }, 
        {
          "hex": "#975069",
          "name": "#975069",
          "reference": "vibrant"
        }, 
        {
          "hex": "#d5c6af",
          "name": "#d5c6af",
          "reference": "vibrant"
        }
      ],
      "sizes": {
        "b": {
          "extension": "jpg",
          "height": 768,
          "mimetype": "image/jpeg",
          "secret": "DJmzZNmA0w5MzDFbNiPh3XUpHi6xPTDs",
          "width": 414
        },
        "c": {
          "extension": "jpg",
          "height": 600,
          "mimetype": "image/jpeg",
          "secret": "DJmzZNmA0w5MzDFbNiPh3XUpHi6xPTDs",
          "width": 323
        },
        "dc": {
          "extension": "jpg",
          "height": 600,
          "mimetype": "image/jpeg",
          "secret": "DJmzZNmA0w5MzDFbNiPh3XUpHi6xPTDs",
          "width": 323
        },
        "ds": {
          "extension": "jpg",
          "height": 320,
          "mimetype": "image/jpeg",
          "secret": "DJmzZNmA0w5MzDFbNiPh3XUpHi6xPTDs",
          "width": 320
        },
        "k": {
          "extension": "jpg",
          "height": 1536,
          "mimetype": "image/jpeg",
          "secret": "DJmzZNmA0w5MzDFbNiPh3XUpHi6xPTDs",
          "width": 828
        },
        "n": {
          "extension": "jpg",
          "height": 240,
          "mimetype": "image/jpeg",
          "secret": "DJmzZNmA0w5MzDFbNiPh3XUpHi6xPTDs",
          "width": 129
        },
        "o": {
          "extension": "jpg",
          "height": 2880,
          "mimetype": "image/jpeg",
          "secret": "M5RUK5s5i1KaKcAVlxTz0BQnRl2TeHTV",
          "width": 1554
        },
        "s": {
          "extension": "jpg",
          "height": 320,
          "mimetype": "image/jpeg",
          "secret": "DJmzZNmA0w5MzDFbNiPh3XUpHi6xPTDs",
          "width": 320
        },
        "z": {
          "extension": "jpg",
          "height": 480,
          "mimetype": "image/jpeg",
          "secret": "DJmzZNmA0w5MzDFbNiPh3XUpHi6xPTDs",
          "width": 259
        }
      }
    },
    "media:uri_template": "https://millsfield.sfomuseum.org/media/152/782/483/3/1527824833_{secret}_{label}.{extention}",
    "sfomuseum:filename": "42827.tif",
    "sfomuseum:image_index": 5,
    "sfomuseum:placetype": "image",
    "sfomuseum:primary_image": 0,
    "wof:depicts": [
      1511927437
    ],
    "wof:name": "airsickness bag: Gulf Air",
    "wof:placetype": "media"
  },
  "geometry": {"coordinates":[-122.386155,37.616358],"type":"Point"}
}
