{
  "type": "Feature",
  "properties": {
    "iso:country": "XX",
    "media:fingerprint": "a9af4ae0af3edba97c3b043fc276b7d2a3089653",
    "media:imagehash_avg": "a:ff91bdbdbc9080bd",
    "media:imagehash_diff": "d:6161616161616161",
    "media:medium": "image",
    "media:mimetype": "image/tiff",
    "media:properties": {
      "colours": [
        {
          "hex": "#e2d8ba",
          "name": "#e2d8ba",
          "reference": "vibrant"
        },
        {
          "hex": "#201f0b",
          "name": "#201f0b",
          "reference": "vibrant"
        },
        {
          "hex": "#8f8871",
          "name": "#8f8871",
          "reference": "vibrant"
        },
        {
          "hex": "#d4c8ab",
          "name": "#d4c8ab",
          "reference": "vibrant"
        },
        {
          "hex": "#504d37",
          "name": "#504d37",
          "reference": "vibrant"
        }
      ],
      "sizes": {
        "b": {
          "extension": "jpg",
          "height": 768,
          "mimetype": "image/jpeg",
          "secret": "S12ZTKxkmaike50FALH3pZc5gS9ztp3s",
          "width": 979
        },
        "c": {
          "extension": "jpg",
          "height": 600,
          "mimetype": "image/jpeg",
          "secret": "S12ZTKxkmaike50FALH3pZc5gS9ztp3s",
          "width": 765
        },
        "dc": {
          "extension": "jpg",
          "height": 600,
          "mimetype": "image/jpeg",
          "secret": "S12ZTKxkmaike50FALH3pZc5gS9ztp3s",
          "width": 765
        },
        "ds": {
          "extension": "jpg",
          "height": 320,
          "mimetype": "image/jpeg",
          "secret": "S12ZTKxkmaike50FALH3pZc5gS9ztp3s",
          "width": 320
        },
        "k": {
          "extension": "jpg",
          "height": 1536,
          "mimetype": "image/jpeg",
          "secret": "S12ZTKxkmaike50FALH3pZc5gS9ztp3s",
          "width": 1958
        },
        "n": {
          "extension": "jpg",
          "height": 240,
          "mimetype": "image/jpeg",
          "secret": "S12ZTKxkmaike50FALH3pZc5gS9ztp3s",
          "width": 306
        },
        "o": {
          "extension": "jpg",
          "height": 2092,
          "mimetype": "image/jpeg",
          "secret": "PGJ7IfqjR3AOyXrLvZfIUpTQIc5h9YaU",
          "width": 2668
        },
        "s": {
          "extension": "jpg",
          "height": 320,
          "mimetype": "image/jpeg",
          "secret": "S12ZTKxkmaike50FALH3pZc5gS9ztp3s",
          "width": 320
        },
        "z": {
          "extension": "jpg",
          "height": 480,
          "mimetype": "image/jpeg",
          "secret": "S12ZTKxkmaike50FALH3pZc5gS9ztp3s",
          "width": 612
        }
      }
    },
    "media:uri_template": "https://static.sfomuseum.org/media/152/785/604/1/1527856041_{secret}_{label}.{extention}",
    "sfomuseum:filename": "100564.tif",
    "sfomuseum:image_index": 5,
    "sfomuseum:image_type": "studio",
    "sfomuseum:placetype": "image",
    "sfomuseum:primary_image": 1,
    "wof:depicts": [
      1511942907
    ],
    "wof:name": "photograph: San Francisco Bay Area aerial, Bay and clouds",
    "wof:placetype": "custom",
    "wof:placetype_alt": "image"
  },
  "geometry": {"coordinates":[-122.386155,37.616358],"type":"Point"}
}
