{
  "type": "Feature",
  "properties": {
    "iso:country": "US",
    "media:fingerprint": "8d9c725b36a76ed9cd1a78e7acb82c3ccedb8228",
    "media:imagehash_avg": "a:ffffff0000301860",
    "media:imagehash_diff": "d:e1f3e1cd0d40f3c3",
    "media:medium": "image",
    "media:mimetype": "image/jpeg",
    "media:properties": {
      "colours": [
        {
          "hex": "#7a7a7a",
          "name": "#7a7a7a",
          "reference": "vibrant"
        }, 
        {
          "hex": "#b6b6b6",
          "name": "#b6b6b6",
          "reference": "vibrant"
        }, 
        {
          "hex": "#404040",
          "name": "#404040",
          "reference": "vibrant"
        }
      ],
      "sizes": {
        "b": {
          "extension": "jpg",
          "height": 689,
          "mimetype": "image/jpeg",
          "secret": "Bijw9iuAsVkydWbJzWk5v5J2N6Uc5QI6",
          "width": 1024
        },
        "c": {
          "extension": "jpg",
          "height": 538,
          "mimetype": "image/jpeg",
          "secret": "Bijw9iuAsVkydWbJzWk5v5J2N6Uc5QI6",
          "width": 800
        },
        "dc": {
          "extension": "jpg",
          "height": 538,
          "mimetype": "image/jpeg",
          "secret": "Bijw9iuAsVkydWbJzWk5v5J2N6Uc5QI6",
          "width": 800
        },
        "ds": {
          "extension": "jpg",
          "height": 320,
          "mimetype": "image/jpeg",
          "secret": "Bijw9iuAsVkydWbJzWk5v5J2N6Uc5QI6",
          "width": 320
        },
        "k": {
          "extension": "jpg",
          "height": 1378,
          "mimetype": "image/jpeg",
          "secret": "Bijw9iuAsVkydWbJzWk5v5J2N6Uc5QI6",
          "width": 2048
        },
        "n": {
          "extension": "jpg",
          "height": 215,
          "mimetype": "image/jpeg",
          "secret": "Bijw9iuAsVkydWbJzWk5v5J2N6Uc5QI6",
          "width": 320
        },
        "o": {
          "extension": "jpg",
          "height": 1891,
          "mimetype": "image/jpeg",
          "secret": "sHm5lgwkov8Gw6KBLCKyQXrnSQb17ODS",
          "width": 2810
        },
        "s": {
          "extension": "jpg",
          "height": 320,
          "mimetype": "image/jpeg",
          "secret": "Bijw9iuAsVkydWbJzWk5v5J2N6Uc5QI6",
          "width": 320
        },
        "z": {
          "extension": "jpg",
          "height": 430,
          "mimetype": "image/jpeg",
          "secret": "Bijw9iuAsVkydWbJzWk5v5J2N6Uc5QI6",
          "width": 640
        }
      }
    },
    "media:uri_template": "https://millsfield.sfomuseum.org/media/152/781/891/5/1527818915_{secret}_{label}.{extention}",
    "sfomuseum:filename": "19825.jpg",
    "sfomuseum:image_index": 5,
    "sfomuseum:placetype": "image",
    "sfomuseum:primary_image": 1,
    "wof:depicts": [
      1511924203
    ],
    "wof:name": "photograph: San Francisco International Airport (SFO), Pan American World Airways, Boeing 747",
    "wof:placetype": "media"
  },
  "geometry": {"coordinates":[-122.386155,37.616358],"type":"Point"}
}
