{
  "type": "Feature",
  "properties": {
    "iso:country": "XX",
    "media:fingerprint": "f8ab584a5df9869958d5c5254ca04e0cee5f2cbe",
    "media:imagehash_avg": "a:667eff7b390102d8",
    "media:imagehash_diff": "d:ccc6d2f2f3dbd6b0",
    "media:medium": "image",
    "media:mimetype": "image/tiff",
    "media:properties": {
      "colours": [
        {
          "hex": "#808080",
          "name": "#808080",
          "reference": "vibrant"
        }, 
        {
          "hex": "#bababa",
          "name": "#bababa",
          "reference": "vibrant"
        }, 
        {
          "hex": "#4a4a4a",
          "name": "#4a4a4a",
          "reference": "vibrant"
        }
      ],
      "sizes": {
        "b": {
          "extension": "jpg",
          "height": 768,
          "mimetype": "image/jpeg",
          "secret": "h8ZpOJikVGQSZPxy4po4cElMpq90wRiz",
          "width": 759
        },
        "c": {
          "extension": "jpg",
          "height": 600,
          "mimetype": "image/jpeg",
          "secret": "h8ZpOJikVGQSZPxy4po4cElMpq90wRiz",
          "width": 593
        },
        "dc": {
          "extension": "jpg",
          "height": 600,
          "mimetype": "image/jpeg",
          "secret": "h8ZpOJikVGQSZPxy4po4cElMpq90wRiz",
          "width": 593
        },
        "ds": {
          "extension": "jpg",
          "height": 320,
          "mimetype": "image/jpeg",
          "secret": "h8ZpOJikVGQSZPxy4po4cElMpq90wRiz",
          "width": 320
        },
        "k": {
          "extension": "jpg",
          "height": 1536,
          "mimetype": "image/jpeg",
          "secret": "h8ZpOJikVGQSZPxy4po4cElMpq90wRiz",
          "width": 1519
        },
        "n": {
          "extension": "jpg",
          "height": 240,
          "mimetype": "image/jpeg",
          "secret": "h8ZpOJikVGQSZPxy4po4cElMpq90wRiz",
          "width": 237
        },
        "o": {
          "extension": "jpg",
          "height": 2590,
          "mimetype": "image/jpeg",
          "secret": "xlxZD4Mc4C5IMpZczAPXv5TBFAK8RFSJ",
          "width": 2563
        },
        "s": {
          "extension": "jpg",
          "height": 320,
          "mimetype": "image/jpeg",
          "secret": "h8ZpOJikVGQSZPxy4po4cElMpq90wRiz",
          "width": 320
        },
        "z": {
          "extension": "jpg",
          "height": 480,
          "mimetype": "image/jpeg",
          "secret": "h8ZpOJikVGQSZPxy4po4cElMpq90wRiz",
          "width": 474
        }
      }
    },
    "media:uri_template": "https://millsfield.sfomuseum.org/media/152/782/730/7/1527827307_{secret}_{label}.{extention}",
    "sfomuseum:filename": "44029.tif",
    "sfomuseum:image_index": 5,
    "sfomuseum:placetype": "image",
    "sfomuseum:primary_image": 1,
    "wof:depicts": [
      1511948345
    ],
    "wof:name": "negative: San Francisco International Airport (SFO), aerial",
    "wof:placetype": "media"
  },
  "geometry": {"coordinates":[-122.386155,37.616358],"type":"Point"}
}
