{
  "type": "Feature",
  "properties": {
    "iso:country": "XX",
    "media:fingerprint": "cf3165b66d85c3c23b273d8257d0af8b51562859",
    "media:imagehash_avg": "a:7fff8343437f7f00",
    "media:imagehash_diff": "d:cc8e8f968ecc9689",
    "media:medium": "image",
    "media:mimetype": "image/tiff",
    "media:properties": {
      "colours": [
        {
          "hex": "#df4136",
          "name": "#df4136",
          "reference": "vibrant"
        }, 
        {
          "hex": "#e86a5f",
          "name": "#e86a5f",
          "reference": "vibrant"
        }, 
        {
          "hex": "#7f847d",
          "name": "#7f847d",
          "reference": "vibrant"
        }, 
        {
          "hex": "#c6c4ba",
          "name": "#c6c4ba",
          "reference": "vibrant"
        }, 
        {
          "hex": "#636563",
          "name": "#636563",
          "reference": "vibrant"
        }
      ],
      "sizes": {
        "b": {
          "extension": "jpg",
          "height": 768,
          "mimetype": "image/jpeg",
          "secret": "4sxyHGAJFtUxfFQ0lqZyPN8HGMQaJZcM",
          "width": 423
        },
        "c": {
          "extension": "jpg",
          "height": 600,
          "mimetype": "image/jpeg",
          "secret": "4sxyHGAJFtUxfFQ0lqZyPN8HGMQaJZcM",
          "width": 330
        },
        "dc": {
          "extension": "jpg",
          "height": 600,
          "mimetype": "image/jpeg",
          "secret": "4sxyHGAJFtUxfFQ0lqZyPN8HGMQaJZcM",
          "width": 330
        },
        "ds": {
          "extension": "jpg",
          "height": 320,
          "mimetype": "image/jpeg",
          "secret": "4sxyHGAJFtUxfFQ0lqZyPN8HGMQaJZcM",
          "width": 320
        },
        "k": {
          "extension": "jpg",
          "height": 1536,
          "mimetype": "image/jpeg",
          "secret": "4sxyHGAJFtUxfFQ0lqZyPN8HGMQaJZcM",
          "width": 846
        },
        "n": {
          "extension": "jpg",
          "height": 240,
          "mimetype": "image/jpeg",
          "secret": "4sxyHGAJFtUxfFQ0lqZyPN8HGMQaJZcM",
          "width": 132
        },
        "o": {
          "extension": "jpg",
          "height": 2766,
          "mimetype": "image/jpeg",
          "secret": "Z373wBc8S7JvMTbdJT2mzkwB1fjl3dmy",
          "width": 1524
        },
        "s": {
          "extension": "jpg",
          "height": 320,
          "mimetype": "image/jpeg",
          "secret": "4sxyHGAJFtUxfFQ0lqZyPN8HGMQaJZcM",
          "width": 320
        },
        "z": {
          "extension": "jpg",
          "height": 480,
          "mimetype": "image/jpeg",
          "secret": "4sxyHGAJFtUxfFQ0lqZyPN8HGMQaJZcM",
          "width": 264
        }
      }
    },
    "media:uri_template": "https://millsfield.sfomuseum.org/media/152/782/466/5/1527824665_{secret}_{label}.{extention}",
    "sfomuseum:filename": "42720.tif",
    "sfomuseum:image_index": 5,
    "sfomuseum:placetype": "image",
    "sfomuseum:primary_image": 1,
    "wof:depicts": [
      1511908585
    ],
    "wof:name": "airsickness bag: Dragonair",
    "wof:placetype": "media"
  },
  "geometry": {"coordinates":[-122.386155,37.616358],"type":"Point"}
}
