{
  "type": "Feature",
  "properties": {
    "iso:country": "XX",
    "media:fingerprint": "01b117d8cbbee0c721e91f0a9dbe916077a476d2",
    "media:imagehash_avg": "a:ffff03837f7f6743",
    "media:imagehash_diff": "d:aeee5f1feccc8e8f",
    "media:medium": "image",
    "media:mimetype": "image/tiff",
    "media:properties": {
      "colours": [
        {
          "hex": "#e75957",
          "name": "#e75957",
          "reference": "vibrant"
        }, 
        {
          "hex": "#f8f0e0",
          "name": "#f8f0e0",
          "reference": "vibrant"
        }, 
        {
          "hex": "#34419b",
          "name": "#34419b",
          "reference": "vibrant"
        }, 
        {
          "hex": "#5f70b9",
          "name": "#5f70b9",
          "reference": "vibrant"
        }, 
        {
          "hex": "#97a2c3",
          "name": "#97a2c3",
          "reference": "vibrant"
        }
      ],
      "sizes": {
        "b": {
          "extension": "jpg",
          "height": 768,
          "mimetype": "image/jpeg",
          "secret": "7Jn1KOrqRoM1gShJWxMG04jPmrR1UpMY",
          "width": 413
        },
        "c": {
          "extension": "jpg",
          "height": 600,
          "mimetype": "image/jpeg",
          "secret": "7Jn1KOrqRoM1gShJWxMG04jPmrR1UpMY",
          "width": 322
        },
        "dc": {
          "extension": "jpg",
          "height": 600,
          "mimetype": "image/jpeg",
          "secret": "7Jn1KOrqRoM1gShJWxMG04jPmrR1UpMY",
          "width": 322
        },
        "ds": {
          "extension": "jpg",
          "height": 320,
          "mimetype": "image/jpeg",
          "secret": "7Jn1KOrqRoM1gShJWxMG04jPmrR1UpMY",
          "width": 320
        },
        "k": {
          "extension": "jpg",
          "height": 1536,
          "mimetype": "image/jpeg",
          "secret": "7Jn1KOrqRoM1gShJWxMG04jPmrR1UpMY",
          "width": 826
        },
        "n": {
          "extension": "jpg",
          "height": 240,
          "mimetype": "image/jpeg",
          "secret": "7Jn1KOrqRoM1gShJWxMG04jPmrR1UpMY",
          "width": 129
        },
        "o": {
          "extension": "jpg",
          "height": 2898,
          "mimetype": "image/jpeg",
          "secret": "PjIKCJwilYWeF7aYrf6nyvFrp7j2QwXI",
          "width": 1560
        },
        "s": {
          "extension": "jpg",
          "height": 320,
          "mimetype": "image/jpeg",
          "secret": "7Jn1KOrqRoM1gShJWxMG04jPmrR1UpMY",
          "width": 320
        },
        "z": {
          "extension": "jpg",
          "height": 480,
          "mimetype": "image/jpeg",
          "secret": "7Jn1KOrqRoM1gShJWxMG04jPmrR1UpMY",
          "width": 258
        }
      }
    },
    "media:uri_template": "https://millsfield.sfomuseum.org/media/152/782/443/1/1527824431_{secret}_{label}.{extention}",
    "sfomuseum:filename": "42564.tif",
    "sfomuseum:image_index": 5,
    "sfomuseum:placetype": "image",
    "sfomuseum:primary_image": 1,
    "wof:depicts": [
      1511908565
    ],
    "wof:name": "airsickness bag: Dan-Air",
    "wof:placetype": "media"
  },
  "geometry": {"coordinates":[-122.386155,37.616358],"type":"Point"}
}
