{
  "type": "Feature",
  "properties": {
    "date:cessation_lower": "1956-01-01",
    "date:cessation_upper": "1956-12-31",
    "date:inception_lower": "1956-01-01",
    "date:inception_upper": "1956-12-31",
    "iso:country": "XX",
    "sfomuseum:filename": "47642.tif",
    "sfomuseum:image_index": 3,
    "sfomuseum:image_type": "studio",
    "sfomuseum:placetype": "image",
    "sfomuseum:primary_image": 1,
    "wof:depicts": [
      1511951281,
      1159284989,
      1159286839
    ],
    "wof:name": "advertisement: Pan American World Airways, Holiday magazine",
    "wof:placetype": "custom"
  },
  "geometry": {"coordinates":[-122.386155,37.616357],"type":"Point"}
}
