{
  "type": "Feature",
  "properties": {
    "iso:country": "XX",
    "media:fingerprint": "1e74e464578ef2d35cc95a8a2ce693f27e1dd37f",
    "media:imagehash_avg": "a:fffffffd1d090000",
    "media:imagehash_diff": "d:07071b3135717131",
    "media:medium": "image",
    "media:mimetype": "image/tiff",
    "media:properties": {
      "colours": [
        {
          "hex": "#808080",
          "name": "#808080",
          "reference": "vibrant"
        },
        {
          "hex": "#c0c0c0",
          "name": "#c0c0c0",
          "reference": "vibrant"
        },
        {
          "hex": "#404040",
          "name": "#404040",
          "reference": "vibrant"
        }
      ],
      "sizes": {
        "b": {
          "extension": "jpg",
          "height": 768,
          "mimetype": "image/jpeg",
          "secret": "KlgX5MYIdP4pvTJHgdkLicsIt5qIYH2U",
          "width": 614
        },
        "c": {
          "extension": "jpg",
          "height": 600,
          "mimetype": "image/jpeg",
          "secret": "KlgX5MYIdP4pvTJHgdkLicsIt5qIYH2U",
          "width": 480
        },
        "dc": {
          "extension": "jpg",
          "height": 600,
          "mimetype": "image/jpeg",
          "secret": "KlgX5MYIdP4pvTJHgdkLicsIt5qIYH2U",
          "width": 480
        },
        "ds": {
          "extension": "jpg",
          "height": 320,
          "mimetype": "image/jpeg",
          "secret": "KlgX5MYIdP4pvTJHgdkLicsIt5qIYH2U",
          "width": 320
        },
        "k": {
          "extension": "jpg",
          "height": 1536,
          "mimetype": "image/jpeg",
          "secret": "KlgX5MYIdP4pvTJHgdkLicsIt5qIYH2U",
          "width": 1229
        },
        "n": {
          "extension": "jpg",
          "height": 240,
          "mimetype": "image/jpeg",
          "secret": "KlgX5MYIdP4pvTJHgdkLicsIt5qIYH2U",
          "width": 192
        },
        "o": {
          "extension": "jpg",
          "height": 2832,
          "mimetype": "image/jpeg",
          "secret": "n08EGqteiQCrZRpDW2OiB4OwJGbriHa6",
          "width": 2267
        },
        "s": {
          "extension": "jpg",
          "height": 320,
          "mimetype": "image/jpeg",
          "secret": "KlgX5MYIdP4pvTJHgdkLicsIt5qIYH2U",
          "width": 320
        },
        "z": {
          "extension": "jpg",
          "height": 480,
          "mimetype": "image/jpeg",
          "secret": "KlgX5MYIdP4pvTJHgdkLicsIt5qIYH2U",
          "width": 384
        }
      }
    },
    "media:uri_template": "https://static.sfomuseum.org/media/172/956/540/5/1729565405_{secret}_{label}.{extention}",
    "sfomuseum:filename": "39613.tif",
    "sfomuseum:image_index": 0,
    "sfomuseum:image_type": "studio",
    "sfomuseum:placetype": "image",
    "sfomuseum:primary_image": 1,
    "wof:depicts": [
      1159285395,
      1729564313,
      1159287531
    ],
    "wof:name": "photograph: Transcontinental \u0026 Western Air (TWA), chief hostess Ida Staggers",
    "wof:placetype": "custom",
    "wof:placetype_alt": "image"
  },
  "geometry": {"coordinates":[-122.386155,37.616357],"type":"Point"}
}
