{
  "type": "Feature",
  "properties": {
    "iso:country": "XX",
    "media:fingerprint": "21390a1e1f890fb6004d5d64923f12db96dec8b3",
    "media:imagehash_avg": "a:ffffbf0001ffffff",
    "media:imagehash_diff": "d:000065755b040000",
    "media:medium": "image",
    "media:mimetype": "image/tiff",
    "media:properties": {
      "colours": [
        {
          "hex": "#eb3a20",
          "name": "#eb3a20",
          "reference": "vibrant"
        },
        {
          "hex": "#e1c78b",
          "name": "#e1c78b",
          "reference": "vibrant"
        },
        {
          "hex": "#733918",
          "name": "#733918",
          "reference": "vibrant"
        },
        {
          "hex": "#977f56",
          "name": "#977f56",
          "reference": "vibrant"
        },
        {
          "hex": "#b0b0b8",
          "name": "#b0b0b8",
          "reference": "vibrant"
        }
      ],
      "sizes": {
        "b": {
          "extension": "jpg",
          "height": 685,
          "mimetype": "image/jpeg",
          "secret": "6y4CaP4mX4zreKhKx4LfceYpA7Sgpecg",
          "width": 1024
        },
        "c": {
          "extension": "jpg",
          "height": 535,
          "mimetype": "image/jpeg",
          "secret": "6y4CaP4mX4zreKhKx4LfceYpA7Sgpecg",
          "width": 800
        },
        "dc": {
          "extension": "jpg",
          "height": 535,
          "mimetype": "image/jpeg",
          "secret": "6y4CaP4mX4zreKhKx4LfceYpA7Sgpecg",
          "width": 800
        },
        "ds": {
          "extension": "jpg",
          "height": 320,
          "mimetype": "image/jpeg",
          "secret": "6y4CaP4mX4zreKhKx4LfceYpA7Sgpecg",
          "width": 320
        },
        "k": {
          "extension": "jpg",
          "height": 1371,
          "mimetype": "image/jpeg",
          "secret": "6y4CaP4mX4zreKhKx4LfceYpA7Sgpecg",
          "width": 2048
        },
        "n": {
          "extension": "jpg",
          "height": 214,
          "mimetype": "image/jpeg",
          "secret": "6y4CaP4mX4zreKhKx4LfceYpA7Sgpecg",
          "width": 320
        },
        "o": {
          "extension": "jpg",
          "height": 2400,
          "mimetype": "image/jpeg",
          "secret": "F7faw63rQ4cJGCQ0qIhy26hVXPatFd5e",
          "width": 3585
        },
        "s": {
          "extension": "jpg",
          "height": 320,
          "mimetype": "image/jpeg",
          "secret": "6y4CaP4mX4zreKhKx4LfceYpA7Sgpecg",
          "width": 320
        },
        "z": {
          "extension": "jpg",
          "height": 428,
          "mimetype": "image/jpeg",
          "secret": "6y4CaP4mX4zreKhKx4LfceYpA7Sgpecg",
          "width": 640
        }
      }
    },
    "media:uri_template": "https://millsfield.sfomuseum.org/media/152/785/412/9/1527854129_{secret}_{label}.{extention}",
    "sfomuseum:filename": "2012.147.378.tif",
    "sfomuseum:image_index": 5,
    "sfomuseum:placetype": "image",
    "sfomuseum:primary_image": 1,
    "wof:depicts": [
      1511952649
    ],
    "wof:name": "flight attendant pin: Ethiopian Airlines",
    "wof:placetype": "custom",
    "wof:placetype_alt": "image"
  },
  "geometry": {"coordinates":[-122.386155,37.616358],"type":"Point"}
}
