{
  "type": "Feature",
  "properties": {
    "iso:country": "XX",
    "media:fingerprint": "108afc005d0979f0aa9d3bf1c82ada46f5a8a0a0",
    "media:imagehash_avg": "a:0018fcf8f8e0a000",
    "media:imagehash_diff": "d:7030301000106040",
    "media:medium": "image",
    "media:mimetype": "image/tiff",
    "media:properties": {
      "colours": [
        {
          "hex": "#808080",
          "name": "#808080",
          "reference": "vibrant"
        }, 
        {
          "hex": "#c0c0c0",
          "name": "#c0c0c0",
          "reference": "vibrant"
        }, 
        {
          "hex": "#464646",
          "name": "#464646",
          "reference": "vibrant"
        }
      ],
      "sizes": {
        "b": {
          "extension": "jpg",
          "height": 768,
          "mimetype": "image/jpeg",
          "secret": "kLrcNQR7NLU5EO4O1t3sQIGxg6X8RpGq",
          "width": 986
        },
        "c": {
          "extension": "jpg",
          "height": 600,
          "mimetype": "image/jpeg",
          "secret": "kLrcNQR7NLU5EO4O1t3sQIGxg6X8RpGq",
          "width": 771
        },
        "dc": {
          "extension": "jpg",
          "height": 600,
          "mimetype": "image/jpeg",
          "secret": "kLrcNQR7NLU5EO4O1t3sQIGxg6X8RpGq",
          "width": 771
        },
        "ds": {
          "extension": "jpg",
          "height": 320,
          "mimetype": "image/jpeg",
          "secret": "kLrcNQR7NLU5EO4O1t3sQIGxg6X8RpGq",
          "width": 320
        },
        "k": {
          "extension": "jpg",
          "height": 1536,
          "mimetype": "image/jpeg",
          "secret": "kLrcNQR7NLU5EO4O1t3sQIGxg6X8RpGq",
          "width": 1973
        },
        "n": {
          "extension": "jpg",
          "height": 240,
          "mimetype": "image/jpeg",
          "secret": "kLrcNQR7NLU5EO4O1t3sQIGxg6X8RpGq",
          "width": 308
        },
        "o": {
          "extension": "jpg",
          "height": 2154,
          "mimetype": "image/jpeg",
          "secret": "LboQusSIlr19tGhXVXgP9kLlqehME0mW",
          "width": 2768
        },
        "s": {
          "extension": "jpg",
          "height": 320,
          "mimetype": "image/jpeg",
          "secret": "kLrcNQR7NLU5EO4O1t3sQIGxg6X8RpGq",
          "width": 320
        },
        "z": {
          "extension": "jpg",
          "height": 480,
          "mimetype": "image/jpeg",
          "secret": "kLrcNQR7NLU5EO4O1t3sQIGxg6X8RpGq",
          "width": 616
        }
      }
    },
    "media:uri_template": "https://millsfield.sfomuseum.org/media/152/782/549/3/1527825493_{secret}_{label}.{extention}",
    "sfomuseum:filename": "43179.tif",
    "sfomuseum:image_index": 5,
    "sfomuseum:placetype": "image",
    "sfomuseum:primary_image": 1,
    "wof:depicts": [
      1511946533
    ],
    "wof:name": "negative: San Francisco International Airport (SFO), aerial",
    "wof:placetype": "media"
  },
  "geometry": {"coordinates":[-122.386155,37.616358],"type":"Point"}
}
