{
  "type": "Feature",
  "properties": {
    "iso:country": "XX",
    "media:fingerprint": "b5a84a543ef422ecc112088c0b2300e6450f7fcd",
    "media:imagehash_avg": "a:ffbf21010101011d",
    "media:imagehash_diff": "d:e7736b431393fbf9",
    "media:medium": "image",
    "media:mimetype": "image/tiff",
    "media:properties": {
      "colours": [
        {
          "hex": "#808080",
          "name": "#808080",
          "reference": "vibrant"
        }, 
        {
          "hex": "#b6b6b6",
          "name": "#b6b6b6",
          "reference": "vibrant"
        }, 
        {
          "hex": "#464646",
          "name": "#464646",
          "reference": "vibrant"
        }
      ],
      "sizes": {
        "b": {
          "extension": "jpg",
          "height": 716,
          "mimetype": "image/jpeg",
          "secret": "l3XEnlgDVQGeaTsGWp7bfwzEZTochn0M",
          "width": 1024
        },
        "c": {
          "extension": "jpg",
          "height": 560,
          "mimetype": "image/jpeg",
          "secret": "l3XEnlgDVQGeaTsGWp7bfwzEZTochn0M",
          "width": 800
        },
        "dc": {
          "extension": "jpg",
          "height": 560,
          "mimetype": "image/jpeg",
          "secret": "l3XEnlgDVQGeaTsGWp7bfwzEZTochn0M",
          "width": 800
        },
        "ds": {
          "extension": "jpg",
          "height": 320,
          "mimetype": "image/jpeg",
          "secret": "l3XEnlgDVQGeaTsGWp7bfwzEZTochn0M",
          "width": 320
        },
        "k": {
          "extension": "jpg",
          "height": 1433,
          "mimetype": "image/jpeg",
          "secret": "l3XEnlgDVQGeaTsGWp7bfwzEZTochn0M",
          "width": 2048
        },
        "n": {
          "extension": "jpg",
          "height": 224,
          "mimetype": "image/jpeg",
          "secret": "l3XEnlgDVQGeaTsGWp7bfwzEZTochn0M",
          "width": 320
        },
        "o": {
          "extension": "jpg",
          "height": 1008,
          "mimetype": "image/jpeg",
          "secret": "6bO4ClfAQpz5txUg6LWT76i46THOwIKN",
          "width": 1440
        },
        "s": {
          "extension": "jpg",
          "height": 320,
          "mimetype": "image/jpeg",
          "secret": "l3XEnlgDVQGeaTsGWp7bfwzEZTochn0M",
          "width": 320
        },
        "z": {
          "extension": "jpg",
          "height": 448,
          "mimetype": "image/jpeg",
          "secret": "l3XEnlgDVQGeaTsGWp7bfwzEZTochn0M",
          "width": 640
        }
      }
    },
    "media:uri_template": "https://millsfield.sfomuseum.org/media/152/782/928/3/1527829283_{secret}_{label}.{extention}",
    "sfomuseum:filename": "47917.tif",
    "sfomuseum:image_index": 5,
    "sfomuseum:placetype": "image",
    "sfomuseum:primary_image": 1,
    "wof:depicts": [
      1511945969
    ],
    "wof:name": "photograph: San Francisco International Airport (SFO), Central Terminal",
    "wof:placetype": "media"
  },
  "geometry": {"coordinates":[-122.386155,37.616358],"type":"Point"}
}
