{
  "type": "Feature",
  "properties": {
    "iso:country": "US",
    "media:fingerprint": "c0980ce16def87f2ca2a0b698b99b240737ea3c0",
    "media:imagehash_avg": "a:ffff8f81818199ff",
    "media:imagehash_diff": "d:0b1f5f1f1b737367",
    "media:medium": "image",
    "media:mimetype": "image/tiff",
    "media:properties": {
      "colours": [
        {
          "hex": "#5da1c5",
          "name": "#5da1c5",
          "reference": "vibrant"
        }, 
        {
          "hex": "#80acca",
          "name": "#80acca",
          "reference": "vibrant"
        }, 
        {
          "hex": "#1d200f",
          "name": "#1d200f",
          "reference": "vibrant"
        }, 
        {
          "hex": "#976d9a",
          "name": "#976d9a",
          "reference": "vibrant"
        }, 
        {
          "hex": "#a8b0cf",
          "name": "#a8b0cf",
          "reference": "vibrant"
        }
      ],
      "sizes": {
        "b": {
          "extension": "jpg",
          "height": 768,
          "mimetype": "image/jpeg",
          "secret": "rq5MCS2K8LyOITPnKnyrZEm43xhTCV0A",
          "width": 353
        },
        "c": {
          "extension": "jpg",
          "height": 600,
          "mimetype": "image/jpeg",
          "secret": "rq5MCS2K8LyOITPnKnyrZEm43xhTCV0A",
          "width": 276
        },
        "dc": {
          "extension": "jpg",
          "height": 600,
          "mimetype": "image/jpeg",
          "secret": "rq5MCS2K8LyOITPnKnyrZEm43xhTCV0A",
          "width": 276
        },
        "ds": {
          "extension": "jpg",
          "height": 320,
          "mimetype": "image/jpeg",
          "secret": "rq5MCS2K8LyOITPnKnyrZEm43xhTCV0A",
          "width": 310
        },
        "k": {
          "extension": "jpg",
          "height": 1536,
          "mimetype": "image/jpeg",
          "secret": "rq5MCS2K8LyOITPnKnyrZEm43xhTCV0A",
          "width": 707
        },
        "n": {
          "extension": "jpg",
          "height": 240,
          "mimetype": "image/jpeg",
          "secret": "rq5MCS2K8LyOITPnKnyrZEm43xhTCV0A",
          "width": 110
        },
        "o": {
          "extension": "jpg",
          "height": 671,
          "mimetype": "image/jpeg",
          "secret": "50sCTY6xTqejup3flPOVTyNxzbAySfh9",
          "width": 309
        },
        "s": {
          "extension": "jpg",
          "height": 320,
          "mimetype": "image/jpeg",
          "secret": "rq5MCS2K8LyOITPnKnyrZEm43xhTCV0A",
          "width": 310
        },
        "z": {
          "extension": "jpg",
          "height": 480,
          "mimetype": "image/jpeg",
          "secret": "rq5MCS2K8LyOITPnKnyrZEm43xhTCV0A",
          "width": 221
        }
      }
    },
    "media:uri_template": "https://millsfield.sfomuseum.org/media/152/781/844/1/1527818441_{secret}_{label}.{extention}",
    "sfomuseum:filename": "19017.tif",
    "sfomuseum:image_index": 5,
    "sfomuseum:placetype": "image",
    "sfomuseum:primary_image": 1,
    "wof:depicts": [
      1511909493
    ],
    "wof:name": "timetable: United Air Lines",
    "wof:placetype": "media"
  },
  "geometry": {"coordinates":[-122.386155,37.616358],"type":"Point"}
}
