{
  "type": "Feature",
  "properties": {
    "iso:country": "XX",
    "media:fingerprint": "b98c816657dfadc7f55ad2c5364f041ee973d6c7",
    "media:imagehash_avg": "a:ff7fff010100460f",
    "media:imagehash_diff": "d:c0faf36b2b3fbc9c",
    "media:medium": "image",
    "media:mimetype": "image/tiff",
    "media:properties": {
      "colours": [
        {
          "hex": "#888888",
          "name": "#888888",
          "reference": "vibrant"
        }, 
        {
          "hex": "#b5b5b5",
          "name": "#b5b5b5",
          "reference": "vibrant"
        }, 
        {
          "hex": "#404040",
          "name": "#404040",
          "reference": "vibrant"
        }
      ],
      "sizes": {
        "b": {
          "extension": "jpg",
          "height": 767,
          "mimetype": "image/jpeg",
          "secret": "lFHilT7KQs25AEUnwlEAHa9I49xPtZ5l",
          "width": 988
        },
        "c": {
          "extension": "jpg",
          "height": 600,
          "mimetype": "image/jpeg",
          "secret": "lFHilT7KQs25AEUnwlEAHa9I49xPtZ5l",
          "width": 772
        },
        "dc": {
          "extension": "jpg",
          "height": 600,
          "mimetype": "image/jpeg",
          "secret": "lFHilT7KQs25AEUnwlEAHa9I49xPtZ5l",
          "width": 772
        },
        "ds": {
          "extension": "jpg",
          "height": 320,
          "mimetype": "image/jpeg",
          "secret": "lFHilT7KQs25AEUnwlEAHa9I49xPtZ5l",
          "width": 320
        },
        "k": {
          "extension": "jpg",
          "height": 1535,
          "mimetype": "image/jpeg",
          "secret": "lFHilT7KQs25AEUnwlEAHa9I49xPtZ5l",
          "width": 1976
        },
        "n": {
          "extension": "jpg",
          "height": 240,
          "mimetype": "image/jpeg",
          "secret": "lFHilT7KQs25AEUnwlEAHa9I49xPtZ5l",
          "width": 308
        },
        "o": {
          "extension": "jpg",
          "height": 2140,
          "mimetype": "image/jpeg",
          "secret": "DF1oeh3yckwJeFKtDWiP83eGTHLsicZi",
          "width": 2754
        },
        "s": {
          "extension": "jpg",
          "height": 320,
          "mimetype": "image/jpeg",
          "secret": "lFHilT7KQs25AEUnwlEAHa9I49xPtZ5l",
          "width": 320
        },
        "z": {
          "extension": "jpg",
          "height": 480,
          "mimetype": "image/jpeg",
          "secret": "lFHilT7KQs25AEUnwlEAHa9I49xPtZ5l",
          "width": 617
        }
      }
    },
    "media:uri_template": "https://millsfield.sfomuseum.org/media/152/782/230/3/1527822303_{secret}_{label}.{extention}",
    "sfomuseum:filename": "40648.tif",
    "sfomuseum:image_index": 5,
    "sfomuseum:placetype": "image",
    "sfomuseum:primary_image": 1,
    "wof:depicts": [
      1511944207
    ],
    "wof:name": "negative: San Francisco International Airport (SFO), drainage canals",
    "wof:placetype": "media"
  },
  "geometry": {"coordinates":[-122.386155,37.616358],"type":"Point"}
}
