{
  "type": "Feature",
  "properties": {
    "iso:country": "XX",
    "media:fingerprint": "68da52290636386a7851ac97c018fe8ca20962a9",
    "media:imagehash_avg": "a:c380e1f1f9f9bc3f",
    "media:imagehash_diff": "d:1f0f4f6363616171",
    "media:medium": "image",
    "media:mimetype": "image/tiff",
    "media:properties": {
      "colours": [
        {
          "hex": "#f7f1d5",
          "name": "#f7f1d5",
          "reference": "vibrant"
        },
        {
          "hex": "#938e75",
          "name": "#938e75",
          "reference": "vibrant"
        },
        {
          "hex": "#c7bfa8",
          "name": "#c7bfa8",
          "reference": "vibrant"
        },
        {
          "hex": "#55513b",
          "name": "#55513b",
          "reference": "vibrant"
        }
      ],
      "sizes": {
        "b": {
          "extension": "jpg",
          "height": 768,
          "mimetype": "image/jpeg",
          "secret": "p0ZfP7EV3wI8OlYA9l1UkNZRXVvHNgIO",
          "width": 993
        },
        "c": {
          "extension": "jpg",
          "height": 600,
          "mimetype": "image/jpeg",
          "secret": "p0ZfP7EV3wI8OlYA9l1UkNZRXVvHNgIO",
          "width": 775
        },
        "dc": {
          "extension": "jpg",
          "height": 600,
          "mimetype": "image/jpeg",
          "secret": "p0ZfP7EV3wI8OlYA9l1UkNZRXVvHNgIO",
          "width": 775
        },
        "ds": {
          "extension": "jpg",
          "height": 320,
          "mimetype": "image/jpeg",
          "secret": "p0ZfP7EV3wI8OlYA9l1UkNZRXVvHNgIO",
          "width": 320
        },
        "k": {
          "extension": "jpg",
          "height": 1536,
          "mimetype": "image/jpeg",
          "secret": "p0ZfP7EV3wI8OlYA9l1UkNZRXVvHNgIO",
          "width": 1986
        },
        "n": {
          "extension": "jpg",
          "height": 240,
          "mimetype": "image/jpeg",
          "secret": "p0ZfP7EV3wI8OlYA9l1UkNZRXVvHNgIO",
          "width": 310
        },
        "o": {
          "extension": "jpg",
          "height": 1023,
          "mimetype": "image/jpeg",
          "secret": "ldsK4RIOZTOZGrLTnVftgApM2IsV4No7",
          "width": 1323
        },
        "s": {
          "extension": "jpg",
          "height": 320,
          "mimetype": "image/jpeg",
          "secret": "p0ZfP7EV3wI8OlYA9l1UkNZRXVvHNgIO",
          "width": 320
        },
        "z": {
          "extension": "jpg",
          "height": 480,
          "mimetype": "image/jpeg",
          "secret": "p0ZfP7EV3wI8OlYA9l1UkNZRXVvHNgIO",
          "width": 620
        }
      }
    },
    "media:uri_template": "https://static.sfomuseum.org/media/152/785/542/7/1527855427_{secret}_{label}.{extention}",
    "sfomuseum:filename": "2010.174.216.tif",
    "sfomuseum:image_index": 5,
    "sfomuseum:image_type": "studio",
    "sfomuseum:placetype": "image",
    "sfomuseum:primary_image": 1,
    "wof:depicts": [
      1511942187
    ],
    "wof:name": "photograph: San Francisco Bay Area aerial, city obscured by clouds",
    "wof:placetype": "custom",
    "wof:placetype_alt": "image"
  },
  "geometry": {"coordinates":[-122.386155,37.616358],"type":"Point"}
}
