{
  "type": "Feature",
  "properties": {
    "iso:country": "XX",
    "media:fingerprint": "8c44f8d4cba63d5dbd62ba2ce990adcdab2e6dda",
    "media:imagehash_avg": "a:181c1f7f6e0420fe",
    "media:imagehash_diff": "d:3131b3f5ecece8b0",
    "media:medium": "image",
    "media:mimetype": "image/tiff",
    "media:properties": {
      "colours": [
        {
          "hex": "#868686",
          "name": "#868686",
          "reference": "vibrant"
        }, 
        {
          "hex": "#c0c0c0",
          "name": "#c0c0c0",
          "reference": "vibrant"
        }, 
        {
          "hex": "#454545",
          "name": "#454545",
          "reference": "vibrant"
        }
      ],
      "sizes": {
        "b": {
          "extension": "jpg",
          "height": 768,
          "mimetype": "image/jpeg",
          "secret": "Jko2S2SZRZN3eRqljOQFE0rpXkfG63qr",
          "width": 768
        },
        "c": {
          "extension": "jpg",
          "height": 600,
          "mimetype": "image/jpeg",
          "secret": "Jko2S2SZRZN3eRqljOQFE0rpXkfG63qr",
          "width": 600
        },
        "dc": {
          "extension": "jpg",
          "height": 600,
          "mimetype": "image/jpeg",
          "secret": "Jko2S2SZRZN3eRqljOQFE0rpXkfG63qr",
          "width": 600
        },
        "ds": {
          "extension": "jpg",
          "height": 320,
          "mimetype": "image/jpeg",
          "secret": "Jko2S2SZRZN3eRqljOQFE0rpXkfG63qr",
          "width": 320
        },
        "k": {
          "extension": "jpg",
          "height": 1536,
          "mimetype": "image/jpeg",
          "secret": "Jko2S2SZRZN3eRqljOQFE0rpXkfG63qr",
          "width": 1536
        },
        "n": {
          "extension": "jpg",
          "height": 240,
          "mimetype": "image/jpeg",
          "secret": "Jko2S2SZRZN3eRqljOQFE0rpXkfG63qr",
          "width": 240
        },
        "o": {
          "extension": "jpg",
          "height": 2590,
          "mimetype": "image/jpeg",
          "secret": "hHUZ8sFz291VEZuR1mHUEoqARqUlblRM",
          "width": 2590
        },
        "s": {
          "extension": "jpg",
          "height": 320,
          "mimetype": "image/jpeg",
          "secret": "Jko2S2SZRZN3eRqljOQFE0rpXkfG63qr",
          "width": 320
        },
        "z": {
          "extension": "jpg",
          "height": 480,
          "mimetype": "image/jpeg",
          "secret": "Jko2S2SZRZN3eRqljOQFE0rpXkfG63qr",
          "width": 480
        }
      }
    },
    "media:uri_template": "https://millsfield.sfomuseum.org/media/152/782/716/5/1527827165_{secret}_{label}.{extention}",
    "sfomuseum:filename": "43965.tif",
    "sfomuseum:image_index": 5,
    "sfomuseum:placetype": "image",
    "sfomuseum:primary_image": 1,
    "wof:depicts": [
      1511948203
    ],
    "wof:name": "negative: San Francisco International Airport (SFO), swearing-in ceremony for new Airport Commissioners",
    "wof:placetype": "media"
  },
  "geometry": {"coordinates":[-122.386155,37.616358],"type":"Point"}
}
