{
  "type": "Feature",
  "properties": {
    "iso:country": "XX",
    "media:fingerprint": "850a7cc9ae29083635b3626afcb3ebee6aada775",
    "media:imagehash_avg": "a:ffffffa0000000ff",
    "media:imagehash_diff": "d:174b6d4d4d6d6323",
    "media:medium": "image",
    "media:mimetype": "image/tiff",
    "media:properties": {
      "colours": [
        {
          "hex": "#dc301c",
          "name": "#dc301c",
          "reference": "vibrant"
        }, 
        {
          "hex": "#d6b97a",
          "name": "#d6b97a",
          "reference": "vibrant"
        }, 
        {
          "hex": "#273857",
          "name": "#273857",
          "reference": "vibrant"
        }, 
        {
          "hex": "#4969a2",
          "name": "#4969a2",
          "reference": "vibrant"
        }, 
        {
          "hex": "#bcb5ab",
          "name": "#bcb5ab",
          "reference": "vibrant"
        }
      ],
      "sizes": {
        "b": {
          "extension": "jpg",
          "height": 768,
          "mimetype": "image/jpeg",
          "secret": "csdxqjfuAMXbRb4o9Y1abzI96HWAeWwj",
          "width": 569
        },
        "c": {
          "extension": "jpg",
          "height": 600,
          "mimetype": "image/jpeg",
          "secret": "csdxqjfuAMXbRb4o9Y1abzI96HWAeWwj",
          "width": 444
        },
        "dc": {
          "extension": "jpg",
          "height": 600,
          "mimetype": "image/jpeg",
          "secret": "csdxqjfuAMXbRb4o9Y1abzI96HWAeWwj",
          "width": 444
        },
        "ds": {
          "extension": "jpg",
          "height": 320,
          "mimetype": "image/jpeg",
          "secret": "csdxqjfuAMXbRb4o9Y1abzI96HWAeWwj",
          "width": 320
        },
        "k": {
          "extension": "jpg",
          "height": 1536,
          "mimetype": "image/jpeg",
          "secret": "csdxqjfuAMXbRb4o9Y1abzI96HWAeWwj",
          "width": 1138
        },
        "n": {
          "extension": "jpg",
          "height": 240,
          "mimetype": "image/jpeg",
          "secret": "csdxqjfuAMXbRb4o9Y1abzI96HWAeWwj",
          "width": 177
        },
        "o": {
          "extension": "jpg",
          "height": 3787,
          "mimetype": "image/jpeg",
          "secret": "tezrhsU5D9XRdBm5sI4FMho3Qqlhkpur",
          "width": 2808
        },
        "s": {
          "extension": "jpg",
          "height": 320,
          "mimetype": "image/jpeg",
          "secret": "csdxqjfuAMXbRb4o9Y1abzI96HWAeWwj",
          "width": 320
        },
        "z": {
          "extension": "jpg",
          "height": 480,
          "mimetype": "image/jpeg",
          "secret": "csdxqjfuAMXbRb4o9Y1abzI96HWAeWwj",
          "width": 355
        }
      }
    },
    "media:uri_template": "https://millsfield.sfomuseum.org/media/152/782/072/5/1527820725_{secret}_{label}.{extention}",
    "sfomuseum:filename": "32460.tif",
    "sfomuseum:image_index": 5,
    "sfomuseum:placetype": "image",
    "sfomuseum:primary_image": 1,
    "wof:depicts": [
      1511932053
    ],
    "wof:name": "brochure: Northeast Airlines",
    "wof:placetype": "media"
  },
  "geometry": {"coordinates":[-122.386155,37.616358],"type":"Point"}
}
