{
  "type": "Feature",
  "properties": {
    "media:fingerprint": "c5f0e37522af7ee8602d453f9cede5b38f408d3c",
    "media:imagehash_avg": "a:5f1f0f0f0f4f0000",
    "media:imagehash_diff": "d:bc39393999ddfcea",
    "media:mimetype": "image/tiff",
    "media:properties": {
      "colours": [
        {
          "hex": "#808080",
          "name": "#808080",
          "reference": "vibrant"
        },
        {
          "hex": "#c0c0c0",
          "name": "#c0c0c0",
          "reference": "vibrant"
        },
        {
          "hex": "#464646",
          "name": "#464646",
          "reference": "vibrant"
        }
      ],
      "sizes": {
        "b": {
          "extension": "jpg",
          "height": 768,
          "mimetype": "image/jpeg",
          "secret": "qMhzrd2n1C0EPaTLl0jJBOKtXgPTwYAr",
          "width": 646
        },
        "c": {
          "extension": "jpg",
          "height": 600,
          "mimetype": "image/jpeg",
          "secret": "qMhzrd2n1C0EPaTLl0jJBOKtXgPTwYAr",
          "width": 505
        },
        "dc": {
          "extension": "jpg",
          "height": 600,
          "mimetype": "image/jpeg",
          "secret": "qMhzrd2n1C0EPaTLl0jJBOKtXgPTwYAr",
          "width": 505
        },
        "ds": {
          "extension": "jpg",
          "height": 320,
          "mimetype": "image/jpeg",
          "secret": "qMhzrd2n1C0EPaTLl0jJBOKtXgPTwYAr",
          "width": 320
        },
        "k": {
          "extension": "jpg",
          "height": 1536,
          "mimetype": "image/jpeg",
          "secret": "qMhzrd2n1C0EPaTLl0jJBOKtXgPTwYAr",
          "width": 1293
        },
        "n": {
          "extension": "jpg",
          "height": 240,
          "mimetype": "image/jpeg",
          "secret": "qMhzrd2n1C0EPaTLl0jJBOKtXgPTwYAr",
          "width": 202
        },
        "o": {
          "extension": "jpg",
          "height": 2480,
          "mimetype": "image/jpeg",
          "secret": "nqH7j1pOCvxABPejS4rPwWbR8Z4dJ2cO",
          "width": 2088
        },
        "s": {
          "extension": "jpg",
          "height": 320,
          "mimetype": "image/jpeg",
          "secret": "qMhzrd2n1C0EPaTLl0jJBOKtXgPTwYAr",
          "width": 320
        },
        "z": {
          "extension": "jpg",
          "height": 480,
          "mimetype": "image/jpeg",
          "secret": "qMhzrd2n1C0EPaTLl0jJBOKtXgPTwYAr",
          "width": 404
        }
      }
    },
    "media:uri_template": "https://static.sfomuseum.org/media/174/651/208/3/1746512083_{secret}_{label}.{extention}",
    "sfomuseum:filename": "45903.tif",
    "sfomuseum:image_index": 0,
    "sfomuseum:image_type": "studio",
    "sfomuseum:placetype": "image",
    "sfomuseum:primary_image": 1,
    "wof:depicts": [
      1729563773,
      1159285393,
      1159287531
    ],
    "wof:name": "negative: TWA (Trans World Airlines), E. F. MacMillan",
    "wof:placetype": "custom",
    "wof:placetype_alt": "image"
  },
  "geometry": {"coordinates":[-122.386155,37.616357],"type":"Point"}
}
