{
  "type": "Feature",
  "properties": {
    "iso:country": "XX",
    "media:fingerprint": "536eae5066e6a668f6bc6621ab6e14bd96d72a4a",
    "media:imagehash_avg": "a:fbf363710e00002f",
    "media:imagehash_diff": "d:e7c3ebeac8f8e6ce",
    "media:medium": "image",
    "media:mimetype": "image/tiff",
    "media:properties": {
      "colours": [
        {
          "hex": "#808080",
          "name": "#808080",
          "reference": "vibrant"
        }, 
        {
          "hex": "#b8b8b8",
          "name": "#b8b8b8",
          "reference": "vibrant"
        }, 
        {
          "hex": "#404040",
          "name": "#404040",
          "reference": "vibrant"
        }
      ],
      "sizes": {
        "b": {
          "extension": "jpg",
          "height": 768,
          "mimetype": "image/jpeg",
          "secret": "9GW4VrxbXhSehoRsSOLP2AqvjyJuQeui",
          "width": 759
        },
        "c": {
          "extension": "jpg",
          "height": 600,
          "mimetype": "image/jpeg",
          "secret": "9GW4VrxbXhSehoRsSOLP2AqvjyJuQeui",
          "width": 593
        },
        "dc": {
          "extension": "jpg",
          "height": 600,
          "mimetype": "image/jpeg",
          "secret": "9GW4VrxbXhSehoRsSOLP2AqvjyJuQeui",
          "width": 593
        },
        "ds": {
          "extension": "jpg",
          "height": 320,
          "mimetype": "image/jpeg",
          "secret": "9GW4VrxbXhSehoRsSOLP2AqvjyJuQeui",
          "width": 320
        },
        "k": {
          "extension": "jpg",
          "height": 1536,
          "mimetype": "image/jpeg",
          "secret": "9GW4VrxbXhSehoRsSOLP2AqvjyJuQeui",
          "width": 1519
        },
        "n": {
          "extension": "jpg",
          "height": 240,
          "mimetype": "image/jpeg",
          "secret": "9GW4VrxbXhSehoRsSOLP2AqvjyJuQeui",
          "width": 237
        },
        "o": {
          "extension": "jpg",
          "height": 2536,
          "mimetype": "image/jpeg",
          "secret": "LtltjKAnpgElmlLhFCQJ3ZaDr9LbQsuj",
          "width": 2509
        },
        "s": {
          "extension": "jpg",
          "height": 320,
          "mimetype": "image/jpeg",
          "secret": "9GW4VrxbXhSehoRsSOLP2AqvjyJuQeui",
          "width": 320
        },
        "z": {
          "extension": "jpg",
          "height": 480,
          "mimetype": "image/jpeg",
          "secret": "9GW4VrxbXhSehoRsSOLP2AqvjyJuQeui",
          "width": 474
        }
      }
    },
    "media:uri_template": "https://millsfield.sfomuseum.org/media/152/782/486/5/1527824865_{secret}_{label}.{extention}",
    "sfomuseum:filename": "42859.tif",
    "sfomuseum:image_index": 5,
    "sfomuseum:placetype": "image",
    "sfomuseum:primary_image": 1,
    "wof:depicts": [
      1511945747
    ],
    "wof:name": "negative: San Francisco International Airport (SFO), parking garage construction",
    "wof:placetype": "media"
  },
  "geometry": {"coordinates":[-122.386155,37.616358],"type":"Point"}
}
