{
  "type": "Feature",
  "properties": {
    "iso:country": "XX",
    "media:fingerprint": "21f877a26580a1a4d43571ceab7a0e5c25149f37",
    "media:imagehash_avg": "a:7f7f7f7f07000000",
    "media:imagehash_diff": "d:f8f8f0cccccff1f0",
    "media:medium": "image",
    "media:mimetype": "image/tiff",
    "media:properties": {
      "colours": [
        {
          "hex": "#4087be",
          "name": "#4087be",
          "reference": "vibrant"
        }, 
        {
          "hex": "#4d7798",
          "name": "#4d7798",
          "reference": "vibrant"
        }, 
        {
          "hex": "#b5b7b4",
          "name": "#b5b7b4",
          "reference": "vibrant"
        }, 
        {
          "hex": "#2f3f5e",
          "name": "#2f3f5e",
          "reference": "vibrant"
        }
      ],
      "sizes": {
        "b": {
          "extension": "jpg",
          "height": 685,
          "mimetype": "image/jpeg",
          "secret": "MSKdtj3b97KMaGcZTv97d6oSfT1rxahU",
          "width": 1024
        },
        "c": {
          "extension": "jpg",
          "height": 535,
          "mimetype": "image/jpeg",
          "secret": "MSKdtj3b97KMaGcZTv97d6oSfT1rxahU",
          "width": 800
        },
        "dc": {
          "extension": "jpg",
          "height": 535,
          "mimetype": "image/jpeg",
          "secret": "MSKdtj3b97KMaGcZTv97d6oSfT1rxahU",
          "width": 800
        },
        "ds": {
          "extension": "jpg",
          "height": 320,
          "mimetype": "image/jpeg",
          "secret": "MSKdtj3b97KMaGcZTv97d6oSfT1rxahU",
          "width": 320
        },
        "k": {
          "extension": "jpg",
          "height": 1371,
          "mimetype": "image/jpeg",
          "secret": "MSKdtj3b97KMaGcZTv97d6oSfT1rxahU",
          "width": 2048
        },
        "n": {
          "extension": "jpg",
          "height": 214,
          "mimetype": "image/jpeg",
          "secret": "MSKdtj3b97KMaGcZTv97d6oSfT1rxahU",
          "width": 320
        },
        "o": {
          "extension": "jpg",
          "height": 2400,
          "mimetype": "image/jpeg",
          "secret": "fJA3CoLWrNwE9WawtNd5StpR4AKIJmSZ",
          "width": 3585
        },
        "s": {
          "extension": "jpg",
          "height": 320,
          "mimetype": "image/jpeg",
          "secret": "MSKdtj3b97KMaGcZTv97d6oSfT1rxahU",
          "width": 320
        },
        "z": {
          "extension": "jpg",
          "height": 428,
          "mimetype": "image/jpeg",
          "secret": "MSKdtj3b97KMaGcZTv97d6oSfT1rxahU",
          "width": 640
        }
      }
    },
    "media:uri_template": "https://millsfield.sfomuseum.org/media/152/782/882/9/1527828829_{secret}_{label}.{extention}",
    "sfomuseum:filename": "46614.tif",
    "sfomuseum:image_index": 5,
    "sfomuseum:placetype": "image",
    "sfomuseum:primary_image": 0,
    "wof:depicts": [
      1511930193
    ],
    "wof:name": "flight officer wings: Republic Airlines",
    "wof:placetype": "media"
  },
  "geometry": {"coordinates":[-122.386155,37.616358],"type":"Point"}
}
