{
  "type": "Feature",
  "properties": {
    "iso:country": "XX",
    "media:fingerprint": "014e56e0820022fe9b69293a7f300326a56d1beb",
    "media:imagehash_avg": "a:81ff81bf81ff81ff",
    "media:imagehash_diff": "d:171747732f071775",
    "media:medium": "image",
    "media:mimetype": "image/tiff",
    "media:properties": {
      "colours": [
        {
          "hex": "#c33935",
          "name": "#c33935",
          "reference": "vibrant"
        }, 
        {
          "hex": "#e7d8c9",
          "name": "#e7d8c9",
          "reference": "vibrant"
        }, 
        {
          "hex": "#742018",
          "name": "#742018",
          "reference": "vibrant"
        }, 
        {
          "hex": "#928176",
          "name": "#928176",
          "reference": "vibrant"
        }, 
        {
          "hex": "#c0b4ad",
          "name": "#c0b4ad",
          "reference": "vibrant"
        }
      ],
      "sizes": {
        "b": {
          "extension": "jpg",
          "height": 768,
          "mimetype": "image/jpeg",
          "secret": "04dQbe8HJOBwyWjEqRzjoTniLvBKBQP2",
          "width": 417
        },
        "c": {
          "extension": "jpg",
          "height": 600,
          "mimetype": "image/jpeg",
          "secret": "04dQbe8HJOBwyWjEqRzjoTniLvBKBQP2",
          "width": 326
        },
        "dc": {
          "extension": "jpg",
          "height": 600,
          "mimetype": "image/jpeg",
          "secret": "04dQbe8HJOBwyWjEqRzjoTniLvBKBQP2",
          "width": 326
        },
        "ds": {
          "extension": "jpg",
          "height": 320,
          "mimetype": "image/jpeg",
          "secret": "04dQbe8HJOBwyWjEqRzjoTniLvBKBQP2",
          "width": 320
        },
        "k": {
          "extension": "jpg",
          "height": 1536,
          "mimetype": "image/jpeg",
          "secret": "04dQbe8HJOBwyWjEqRzjoTniLvBKBQP2",
          "width": 835
        },
        "n": {
          "extension": "jpg",
          "height": 240,
          "mimetype": "image/jpeg",
          "secret": "04dQbe8HJOBwyWjEqRzjoTniLvBKBQP2",
          "width": 130
        },
        "o": {
          "extension": "jpg",
          "height": 1667,
          "mimetype": "image/jpeg",
          "secret": "ubAiMq4tdf30Y9CJz2dcZf6PzFw1QRzZ",
          "width": 907
        },
        "s": {
          "extension": "jpg",
          "height": 320,
          "mimetype": "image/jpeg",
          "secret": "04dQbe8HJOBwyWjEqRzjoTniLvBKBQP2",
          "width": 320
        },
        "z": {
          "extension": "jpg",
          "height": 480,
          "mimetype": "image/jpeg",
          "secret": "04dQbe8HJOBwyWjEqRzjoTniLvBKBQP2",
          "width": 261
        }
      }
    },
    "media:uri_template": "https://millsfield.sfomuseum.org/media/152/785/827/1/1527858271_{secret}_{label}.{extention}",
    "sfomuseum:filename": "2006.010.799_2.tif",
    "sfomuseum:image_index": 0,
    "sfomuseum:placetype": "image",
    "sfomuseum:primary_image": 0,
    "wof:depicts": [
      1511930279
    ],
    "wof:name": "desk calendar: Avianca Airlines, 1985",
    "wof:placetype": "media"
  },
  "geometry": {"coordinates":[-122.386155,37.616358],"type":"Point"}
}
