{
  "type": "Feature",
  "properties": {
    "iso:country": "XX",
    "media:fingerprint": "0be9d9dc11c751eb2ccfc3c812900281a8b9743f",
    "media:imagehash_avg": "a:383c3e3efebe3320",
    "media:imagehash_diff": "d:f0e0d858506ce661",
    "media:medium": "image",
    "media:mimetype": "image/tiff",
    "media:properties": {
      "colours": [
        {
          "hex": "#d3c07b",
          "name": "#d3c07b",
          "reference": "vibrant"
        }, 
        {
          "hex": "#997b66",
          "name": "#997b66",
          "reference": "vibrant"
        }, 
        {
          "hex": "#acb2bf",
          "name": "#acb2bf",
          "reference": "vibrant"
        }, 
        {
          "hex": "#424b48",
          "name": "#424b48",
          "reference": "vibrant"
        }
      ],
      "sizes": {
        "b": {
          "extension": "jpg",
          "height": 661,
          "mimetype": "image/jpeg",
          "secret": "fF9BsmKVXRmheRfiDOrdRmYht9aFBeZi",
          "width": 1024
        },
        "c": {
          "extension": "jpg",
          "height": 516,
          "mimetype": "image/jpeg",
          "secret": "fF9BsmKVXRmheRfiDOrdRmYht9aFBeZi",
          "width": 800
        },
        "dc": {
          "extension": "jpg",
          "height": 516,
          "mimetype": "image/jpeg",
          "secret": "fF9BsmKVXRmheRfiDOrdRmYht9aFBeZi",
          "width": 800
        },
        "ds": {
          "extension": "jpg",
          "height": 320,
          "mimetype": "image/jpeg",
          "secret": "fF9BsmKVXRmheRfiDOrdRmYht9aFBeZi",
          "width": 320
        },
        "k": {
          "extension": "jpg",
          "height": 1322,
          "mimetype": "image/jpeg",
          "secret": "fF9BsmKVXRmheRfiDOrdRmYht9aFBeZi",
          "width": 2048
        },
        "n": {
          "extension": "jpg",
          "height": 206,
          "mimetype": "image/jpeg",
          "secret": "fF9BsmKVXRmheRfiDOrdRmYht9aFBeZi",
          "width": 320
        },
        "o": {
          "extension": "jpg",
          "height": 1078,
          "mimetype": "image/jpeg",
          "secret": "bo8mDTs6UakEispPRpIxcfXeUJMX9sNW",
          "width": 1669
        },
        "s": {
          "extension": "jpg",
          "height": 320,
          "mimetype": "image/jpeg",
          "secret": "fF9BsmKVXRmheRfiDOrdRmYht9aFBeZi",
          "width": 320
        },
        "z": {
          "extension": "jpg",
          "height": 413,
          "mimetype": "image/jpeg",
          "secret": "fF9BsmKVXRmheRfiDOrdRmYht9aFBeZi",
          "width": 640
        }
      }
    },
    "media:uri_template": "https://millsfield.sfomuseum.org/media/152/782/760/9/1527827609_{secret}_{label}.{extention}",
    "sfomuseum:filename": "44163.tif",
    "sfomuseum:image_index": 5,
    "sfomuseum:placetype": "image",
    "sfomuseum:primary_image": 1,
    "wof:depicts": [
      1511948643
    ],
    "wof:name": "negative: San Francisco International Airport (SFO), personnel",
    "wof:placetype": "media"
  },
  "geometry": {"coordinates":[-122.386155,37.616358],"type":"Point"}
}
