{
  "type": "Feature",
  "properties": {
    "iso:country": "XX",
    "media:fingerprint": "1c7f65e1de8d6b03f922a07f0edf07e6c8c6b3bb",
    "media:imagehash_avg": "a:3c3e7f3e001c1e38",
    "media:imagehash_diff": "d:f0f8f8f081f0f8e0",
    "media:medium": "image",
    "media:mimetype": "image/tiff",
    "media:properties": {
      "colours": [
        {
          "hex": "#868686",
          "name": "#868686",
          "reference": "vibrant"
        }, 
        {
          "hex": "#b8b8b8",
          "name": "#b8b8b8",
          "reference": "vibrant"
        }, 
        {
          "hex": "#404040",
          "name": "#404040",
          "reference": "vibrant"
        }
      ],
      "sizes": {
        "b": {
          "extension": "jpg",
          "height": 767,
          "mimetype": "image/jpeg",
          "secret": "AJWdJwJARkTBujWsp0tdj8u0mV6q8q2K",
          "width": 978
        },
        "c": {
          "extension": "jpg",
          "height": 600,
          "mimetype": "image/jpeg",
          "secret": "AJWdJwJARkTBujWsp0tdj8u0mV6q8q2K",
          "width": 764
        },
        "dc": {
          "extension": "jpg",
          "height": 600,
          "mimetype": "image/jpeg",
          "secret": "AJWdJwJARkTBujWsp0tdj8u0mV6q8q2K",
          "width": 764
        },
        "ds": {
          "extension": "jpg",
          "height": 320,
          "mimetype": "image/jpeg",
          "secret": "AJWdJwJARkTBujWsp0tdj8u0mV6q8q2K",
          "width": 320
        },
        "k": {
          "extension": "jpg",
          "height": 1535,
          "mimetype": "image/jpeg",
          "secret": "AJWdJwJARkTBujWsp0tdj8u0mV6q8q2K",
          "width": 1957
        },
        "n": {
          "extension": "jpg",
          "height": 240,
          "mimetype": "image/jpeg",
          "secret": "AJWdJwJARkTBujWsp0tdj8u0mV6q8q2K",
          "width": 305
        },
        "o": {
          "extension": "jpg",
          "height": 2140,
          "mimetype": "image/jpeg",
          "secret": "RuJBnxnt6zj5mDcCr9uFU9nfwsdO2AZK",
          "width": 2727
        },
        "s": {
          "extension": "jpg",
          "height": 320,
          "mimetype": "image/jpeg",
          "secret": "AJWdJwJARkTBujWsp0tdj8u0mV6q8q2K",
          "width": 320
        },
        "z": {
          "extension": "jpg",
          "height": 480,
          "mimetype": "image/jpeg",
          "secret": "AJWdJwJARkTBujWsp0tdj8u0mV6q8q2K",
          "width": 611
        }
      }
    },
    "media:uri_template": "https://millsfield.sfomuseum.org/media/152/782/301/9/1527823019_{secret}_{label}.{extention}",
    "sfomuseum:filename": "41191.tif",
    "sfomuseum:image_index": 5,
    "sfomuseum:placetype": "image",
    "sfomuseum:primary_image": 1,
    "wof:depicts": [
      1511944915
    ],
    "wof:name": "negative: San Francisco International Airport (SFO), cargo buildings and hangars",
    "wof:placetype": "media"
  },
  "geometry": {"coordinates":[-122.386155,37.616358],"type":"Point"}
}
