{
  "type": "Feature",
  "properties": {
    "iso:country": "XX",
    "media:fingerprint": "7414afa4b98bc5de8a83c587f8c41f2b18599e5e",
    "media:imagehash_avg": "a:7f7f0f7f7f01001f",
    "media:imagehash_diff": "d:9afa7bdbbbd9dbd7",
    "media:medium": "image",
    "media:mimetype": "image/tiff",
    "media:properties": {
      "colours": [
        {
          "hex": "#e74c47",
          "name": "#e74c47",
          "reference": "vibrant"
        }, 
        {
          "hex": "#eb9e9f",
          "name": "#eb9e9f",
          "reference": "vibrant"
        }, 
        {
          "hex": "#80868f",
          "name": "#80868f",
          "reference": "vibrant"
        }, 
        {
          "hex": "#c0c3c6",
          "name": "#c0c3c6",
          "reference": "vibrant"
        }, 
        {
          "hex": "#5b5b5d",
          "name": "#5b5b5d",
          "reference": "vibrant"
        }
      ],
      "sizes": {
        "b": {
          "extension": "jpg",
          "height": 768,
          "mimetype": "image/jpeg",
          "secret": "qkPzPr4bF3eZhLRIkad659rqdqYaROBS",
          "width": 396
        },
        "c": {
          "extension": "jpg",
          "height": 600,
          "mimetype": "image/jpeg",
          "secret": "qkPzPr4bF3eZhLRIkad659rqdqYaROBS",
          "width": 309
        },
        "dc": {
          "extension": "jpg",
          "height": 600,
          "mimetype": "image/jpeg",
          "secret": "qkPzPr4bF3eZhLRIkad659rqdqYaROBS",
          "width": 309
        },
        "ds": {
          "extension": "jpg",
          "height": 320,
          "mimetype": "image/jpeg",
          "secret": "qkPzPr4bF3eZhLRIkad659rqdqYaROBS",
          "width": 320
        },
        "k": {
          "extension": "jpg",
          "height": 1536,
          "mimetype": "image/jpeg",
          "secret": "qkPzPr4bF3eZhLRIkad659rqdqYaROBS",
          "width": 793
        },
        "n": {
          "extension": "jpg",
          "height": 240,
          "mimetype": "image/jpeg",
          "secret": "qkPzPr4bF3eZhLRIkad659rqdqYaROBS",
          "width": 123
        },
        "o": {
          "extension": "jpg",
          "height": 2904,
          "mimetype": "image/jpeg",
          "secret": "qHyMREiI4Kt5c5amhVROV0gusiga9qUr",
          "width": 1500
        },
        "s": {
          "extension": "jpg",
          "height": 320,
          "mimetype": "image/jpeg",
          "secret": "qkPzPr4bF3eZhLRIkad659rqdqYaROBS",
          "width": 320
        },
        "z": {
          "extension": "jpg",
          "height": 480,
          "mimetype": "image/jpeg",
          "secret": "qkPzPr4bF3eZhLRIkad659rqdqYaROBS",
          "width": 247
        }
      }
    },
    "media:uri_template": "https://millsfield.sfomuseum.org/media/152/782/336/5/1527823365_{secret}_{label}.{extention}",
    "sfomuseum:filename": "41518.tif",
    "sfomuseum:image_index": 5,
    "sfomuseum:placetype": "image",
    "sfomuseum:primary_image": 1,
    "wof:depicts": [
      1511908363
    ],
    "wof:name": "airsickness bag: Air Europa",
    "wof:placetype": "media"
  },
  "geometry": {"coordinates":[-122.386155,37.616358],"type":"Point"}
}
