{
  "type": "Feature",
  "properties": {
    "iso:country": "XX",
    "media:fingerprint": "9282fdcabed8dc9fe5c456846c6a15fc363c210b",
    "media:imagehash_avg": "a:ff7df56101011011",
    "media:imagehash_diff": "d:7de5ed85858db177",
    "media:medium": "image",
    "media:mimetype": "image/tiff",
    "media:properties": {
      "colours": [
        {
          "hex": "#e6d7b9",
          "name": "#e6d7b9",
          "reference": "vibrant"
        }, 
        {
          "hex": "#9c8c76",
          "name": "#9c8c76",
          "reference": "vibrant"
        }, 
        {
          "hex": "#cbbba4",
          "name": "#cbbba4",
          "reference": "vibrant"
        }, 
        {
          "hex": "#585147",
          "name": "#585147",
          "reference": "vibrant"
        }
      ],
      "sizes": {
        "b": {
          "extension": "jpg",
          "height": 767,
          "mimetype": "image/jpeg",
          "secret": "rxVQAiE3sCMeEYKh8BIfcHhOoj0A30E2",
          "width": 390
        },
        "c": {
          "extension": "jpg",
          "height": 600,
          "mimetype": "image/jpeg",
          "secret": "rxVQAiE3sCMeEYKh8BIfcHhOoj0A30E2",
          "width": 305
        },
        "dc": {
          "extension": "jpg",
          "height": 600,
          "mimetype": "image/jpeg",
          "secret": "rxVQAiE3sCMeEYKh8BIfcHhOoj0A30E2",
          "width": 305
        },
        "ds": {
          "extension": "jpg",
          "height": 320,
          "mimetype": "image/jpeg",
          "secret": "rxVQAiE3sCMeEYKh8BIfcHhOoj0A30E2",
          "width": 320
        },
        "k": {
          "extension": "jpg",
          "height": 1535,
          "mimetype": "image/jpeg",
          "secret": "rxVQAiE3sCMeEYKh8BIfcHhOoj0A30E2",
          "width": 780
        },
        "n": {
          "extension": "jpg",
          "height": 240,
          "mimetype": "image/jpeg",
          "secret": "rxVQAiE3sCMeEYKh8BIfcHhOoj0A30E2",
          "width": 122
        },
        "o": {
          "extension": "jpg",
          "height": 2939,
          "mimetype": "image/jpeg",
          "secret": "D5zOSvOw1HFGyfQK2htfaRlHzqonG9US",
          "width": 1494
        },
        "s": {
          "extension": "jpg",
          "height": 320,
          "mimetype": "image/jpeg",
          "secret": "rxVQAiE3sCMeEYKh8BIfcHhOoj0A30E2",
          "width": 320
        },
        "z": {
          "extension": "jpg",
          "height": 480,
          "mimetype": "image/jpeg",
          "secret": "rxVQAiE3sCMeEYKh8BIfcHhOoj0A30E2",
          "width": 244
        }
      }
    },
    "media:uri_template": "https://millsfield.sfomuseum.org/media/152/782/346/5/1527823465_{secret}_{label}.{extention}",
    "sfomuseum:filename": "41599.tif",
    "sfomuseum:image_index": 5,
    "sfomuseum:placetype": "image",
    "sfomuseum:primary_image": 0,
    "wof:depicts": [
      1511908397
    ],
    "wof:name": "airsickness bag: Air Siam",
    "wof:placetype": "media"
  },
  "geometry": {"coordinates":[-122.386155,37.616358],"type":"Point"}
}
