{
  "type": "Feature",
  "properties": {
    "iso:country": "XX",
    "media:fingerprint": "f495f694cd46920232f46727b78a6bb067b3d24d",
    "media:imagehash_avg": "a:bf8181f1f1f1e1ff",
    "media:imagehash_diff": "d:7773614141454545",
    "media:medium": "image",
    "media:mimetype": "image/tiff",
    "media:properties": {
      "colours": [
        {
          "hex": "#7c8b98",
          "name": "#7c8b98",
          "reference": "vibrant"
        }, 
        {
          "hex": "#b4bec2",
          "name": "#b4bec2",
          "reference": "vibrant"
        }, 
        {
          "hex": "#2c3950",
          "name": "#2c3950",
          "reference": "vibrant"
        }
      ],
      "sizes": {
        "b": {
          "extension": "jpg",
          "height": 768,
          "mimetype": "image/jpeg",
          "secret": "cJ0VI9st93OMi2MeaLpoe04eaIQnHOdj",
          "width": 413
        },
        "c": {
          "extension": "jpg",
          "height": 600,
          "mimetype": "image/jpeg",
          "secret": "cJ0VI9st93OMi2MeaLpoe04eaIQnHOdj",
          "width": 322
        },
        "dc": {
          "extension": "jpg",
          "height": 600,
          "mimetype": "image/jpeg",
          "secret": "cJ0VI9st93OMi2MeaLpoe04eaIQnHOdj",
          "width": 322
        },
        "ds": {
          "extension": "jpg",
          "height": 320,
          "mimetype": "image/jpeg",
          "secret": "cJ0VI9st93OMi2MeaLpoe04eaIQnHOdj",
          "width": 320
        },
        "k": {
          "extension": "jpg",
          "height": 1536,
          "mimetype": "image/jpeg",
          "secret": "cJ0VI9st93OMi2MeaLpoe04eaIQnHOdj",
          "width": 826
        },
        "n": {
          "extension": "jpg",
          "height": 240,
          "mimetype": "image/jpeg",
          "secret": "cJ0VI9st93OMi2MeaLpoe04eaIQnHOdj",
          "width": 129
        },
        "o": {
          "extension": "jpg",
          "height": 2885,
          "mimetype": "image/jpeg",
          "secret": "R2kRCrWUpCjWFUCujsxXNFTjMNu7GNfo",
          "width": 1553
        },
        "s": {
          "extension": "jpg",
          "height": 320,
          "mimetype": "image/jpeg",
          "secret": "cJ0VI9st93OMi2MeaLpoe04eaIQnHOdj",
          "width": 320
        },
        "z": {
          "extension": "jpg",
          "height": 480,
          "mimetype": "image/jpeg",
          "secret": "cJ0VI9st93OMi2MeaLpoe04eaIQnHOdj",
          "width": 258
        }
      }
    },
    "media:uri_template": "https://millsfield.sfomuseum.org/media/152/782/372/1/1527823721_{secret}_{label}.{extention}",
    "sfomuseum:filename": "41755.tif",
    "sfomuseum:image_index": 5,
    "sfomuseum:placetype": "image",
    "sfomuseum:primary_image": 1,
    "wof:depicts": [
      1511927507
    ],
    "wof:name": "airsickness bag: Arkia Israel Airlines",
    "wof:placetype": "media"
  },
  "geometry": {"coordinates":[-122.386155,37.616358],"type":"Point"}
}
