{
  "type": "Feature",
  "properties": {
    "iso:country": "XX",
    "media:fingerprint": "101fcede78ba13e27641f6971fd1344e0d3dcf02",
    "media:imagehash_avg": "a:f0f0f0f0f0f0f0f0",
    "media:imagehash_diff": "d:2022212323272526",
    "media:medium": "image",
    "media:mimetype": "image/tiff",
    "media:properties": {
      "colours": [
        {
          "hex": "#e8b800",
          "name": "#e8b800",
          "reference": "vibrant"
        },
        {
          "hex": "#f3d964",
          "name": "#f3d964",
          "reference": "vibrant"
        },
        {
          "hex": "#938300",
          "name": "#938300",
          "reference": "vibrant"
        },
        {
          "hex": "#90669e",
          "name": "#90669e",
          "reference": "vibrant"
        },
        {
          "hex": "#d0c7bd",
          "name": "#d0c7bd",
          "reference": "vibrant"
        }
      ],
      "sizes": {
        "b": {
          "extension": "jpg",
          "height": 721,
          "mimetype": "image/jpeg",
          "secret": "WUnS7SQdpBkZp51qQBnEA1xyCgsoZ0vl",
          "width": 1023
        },
        "c": {
          "extension": "jpg",
          "height": 563,
          "mimetype": "image/jpeg",
          "secret": "WUnS7SQdpBkZp51qQBnEA1xyCgsoZ0vl",
          "width": 800
        },
        "dc": {
          "extension": "jpg",
          "height": 563,
          "mimetype": "image/jpeg",
          "secret": "WUnS7SQdpBkZp51qQBnEA1xyCgsoZ0vl",
          "width": 800
        },
        "ds": {
          "extension": "jpg",
          "height": 320,
          "mimetype": "image/jpeg",
          "secret": "WUnS7SQdpBkZp51qQBnEA1xyCgsoZ0vl",
          "width": 320
        },
        "k": {
          "extension": "jpg",
          "height": 1442,
          "mimetype": "image/jpeg",
          "secret": "WUnS7SQdpBkZp51qQBnEA1xyCgsoZ0vl",
          "width": 2047
        },
        "n": {
          "extension": "jpg",
          "height": 225,
          "mimetype": "image/jpeg",
          "secret": "WUnS7SQdpBkZp51qQBnEA1xyCgsoZ0vl",
          "width": 320
        },
        "o": {
          "extension": "jpg",
          "height": 2042,
          "mimetype": "image/jpeg",
          "secret": "zxjuKlOjmi5zwh4VU5k2N0mZEqLlhF0v",
          "width": 2900
        },
        "s": {
          "extension": "jpg",
          "height": 320,
          "mimetype": "image/jpeg",
          "secret": "WUnS7SQdpBkZp51qQBnEA1xyCgsoZ0vl",
          "width": 320
        },
        "z": {
          "extension": "jpg",
          "height": 450,
          "mimetype": "image/jpeg",
          "secret": "WUnS7SQdpBkZp51qQBnEA1xyCgsoZ0vl",
          "width": 640
        }
      }
    },
    "media:uri_template": "https://static.sfomuseum.org/media/152/784/641/5/1527846415_{secret}_{label}.{extention}",
    "sfomuseum:filename": "70882.tif",
    "sfomuseum:image_index": 5,
    "sfomuseum:image_type": "studio",
    "sfomuseum:placetype": "image",
    "sfomuseum:primary_image": 1,
    "wof:depicts": [
      1511930563,
      1159285291
    ],
    "wof:name": "menu: Thai Airways International, Economy Class",
    "wof:placetype": "custom",
    "wof:placetype_alt": "image"
  },
  "geometry": {"coordinates":[-122.386155,37.616358],"type":"Point"}
}
