{
  "type": "Feature",
  "properties": {
    "iso:country": "XX",
    "media:fingerprint": "19620378650242a104ce3b7c9d120628426e07e4",
    "media:imagehash_avg": "a:1e0000008fffffff",
    "media:imagehash_diff": "d:ec6a2c6c1d6d4f4d",
    "media:medium": "image",
    "media:mimetype": "image/tiff",
    "media:properties": {
      "colours": [
        {
          "hex": "#cf4127",
          "name": "#cf4127",
          "reference": "vibrant"
        }, 
        {
          "hex": "#d5c278",
          "name": "#d5c278",
          "reference": "vibrant"
        }, 
        {
          "hex": "#714124",
          "name": "#714124",
          "reference": "vibrant"
        }, 
        {
          "hex": "#92876d",
          "name": "#92876d",
          "reference": "vibrant"
        }, 
        {
          "hex": "#cdc2a6",
          "name": "#cdc2a6",
          "reference": "vibrant"
        }
      ],
      "sizes": {
        "b": {
          "extension": "jpg",
          "height": 768,
          "mimetype": "image/jpeg",
          "secret": "l1rSV3r6oDI9hsY1TMIDckdeHMNegpLM",
          "width": 513
        },
        "c": {
          "extension": "jpg",
          "height": 600,
          "mimetype": "image/jpeg",
          "secret": "l1rSV3r6oDI9hsY1TMIDckdeHMNegpLM",
          "width": 401
        },
        "dc": {
          "extension": "jpg",
          "height": 600,
          "mimetype": "image/jpeg",
          "secret": "l1rSV3r6oDI9hsY1TMIDckdeHMNegpLM",
          "width": 401
        },
        "ds": {
          "extension": "jpg",
          "height": 320,
          "mimetype": "image/jpeg",
          "secret": "l1rSV3r6oDI9hsY1TMIDckdeHMNegpLM",
          "width": 320
        },
        "k": {
          "extension": "jpg",
          "height": 1536,
          "mimetype": "image/jpeg",
          "secret": "l1rSV3r6oDI9hsY1TMIDckdeHMNegpLM",
          "width": 1026
        },
        "n": {
          "extension": "jpg",
          "height": 240,
          "mimetype": "image/jpeg",
          "secret": "l1rSV3r6oDI9hsY1TMIDckdeHMNegpLM",
          "width": 160
        },
        "o": {
          "extension": "jpg",
          "height": 2970,
          "mimetype": "image/jpeg",
          "secret": "RNIGWZOGY38RSF2vuVDsuljdFmOqnoOz",
          "width": 1985
        },
        "s": {
          "extension": "jpg",
          "height": 320,
          "mimetype": "image/jpeg",
          "secret": "l1rSV3r6oDI9hsY1TMIDckdeHMNegpLM",
          "width": 320
        },
        "z": {
          "extension": "jpg",
          "height": 480,
          "mimetype": "image/jpeg",
          "secret": "l1rSV3r6oDI9hsY1TMIDckdeHMNegpLM",
          "width": 320
        }
      }
    },
    "media:uri_template": "https://millsfield.sfomuseum.org/media/152/781/941/9/1527819419_{secret}_{label}.{extention}",
    "sfomuseum:filename": "30371.tif",
    "sfomuseum:image_index": 5,
    "sfomuseum:placetype": "image",
    "sfomuseum:primary_image": 1,
    "wof:depicts": [
      1511923111
    ],
    "wof:name": "advertisement: United Air Lines, National Geographic",
    "wof:placetype": "media"
  },
  "geometry": {"coordinates":[-122.386155,37.616358],"type":"Point"}
}
