{
  "type": "Feature",
  "properties": {
    "iso:country": "XX",
    "media:fingerprint": "75f9bda11e14c93a2ab6b85b170a4272701afd6f",
    "media:imagehash_avg": "a:ffc381818181c3ff",
    "media:imagehash_diff": "d:0f0f0f2737170f0f",
    "media:medium": "image",
    "media:mimetype": "image/tiff",
    "media:properties": {
      "colours": [
        {
          "hex": "#c19a4b",
          "name": "#c19a4b",
          "reference": "vibrant"
        }, 
        {
          "hex": "#e7cb9a",
          "name": "#e7cb9a",
          "reference": "vibrant"
        }, 
        {
          "hex": "#9b7a3c",
          "name": "#9b7a3c",
          "reference": "vibrant"
        }, 
        {
          "hex": "#737e8e",
          "name": "#737e8e",
          "reference": "vibrant"
        }, 
        {
          "hex": "#bec3cc",
          "name": "#bec3cc",
          "reference": "vibrant"
        }
      ],
      "sizes": {
        "b": {
          "extension": "jpg",
          "height": 768,
          "mimetype": "image/jpeg",
          "secret": "Ukvf0kvqsCLC49MTPZgHAUeKW3T5ZBuj",
          "width": 777
        },
        "c": {
          "extension": "jpg",
          "height": 600,
          "mimetype": "image/jpeg",
          "secret": "Ukvf0kvqsCLC49MTPZgHAUeKW3T5ZBuj",
          "width": 607
        },
        "dc": {
          "extension": "jpg",
          "height": 600,
          "mimetype": "image/jpeg",
          "secret": "Ukvf0kvqsCLC49MTPZgHAUeKW3T5ZBuj",
          "width": 607
        },
        "ds": {
          "extension": "jpg",
          "height": 320,
          "mimetype": "image/jpeg",
          "secret": "Ukvf0kvqsCLC49MTPZgHAUeKW3T5ZBuj",
          "width": 320
        },
        "k": {
          "extension": "jpg",
          "height": 1536,
          "mimetype": "image/jpeg",
          "secret": "Ukvf0kvqsCLC49MTPZgHAUeKW3T5ZBuj",
          "width": 1554
        },
        "n": {
          "extension": "jpg",
          "height": 240,
          "mimetype": "image/jpeg",
          "secret": "Ukvf0kvqsCLC49MTPZgHAUeKW3T5ZBuj",
          "width": 242
        },
        "o": {
          "extension": "jpg",
          "height": 424,
          "mimetype": "image/jpeg",
          "secret": "cB8LOIUvU1oxu6cv4JioEX6hV9yHMTsU",
          "width": 429
        },
        "s": {
          "extension": "jpg",
          "height": 320,
          "mimetype": "image/jpeg",
          "secret": "Ukvf0kvqsCLC49MTPZgHAUeKW3T5ZBuj",
          "width": 320
        },
        "z": {
          "extension": "jpg",
          "height": 480,
          "mimetype": "image/jpeg",
          "secret": "Ukvf0kvqsCLC49MTPZgHAUeKW3T5ZBuj",
          "width": 485
        }
      }
    },
    "media:uri_template": "https://millsfield.sfomuseum.org/media/152/781/930/5/1527819305_{secret}_{label}.{extention}",
    "sfomuseum:filename": "26365.tif",
    "sfomuseum:image_index": 5,
    "sfomuseum:placetype": "image",
    "sfomuseum:primary_image": 1,
    "wof:depicts": [
      1511950243
    ],
    "wof:name": "sticker: Flying Tiger Line",
    "wof:placetype": "media"
  },
  "geometry": {"coordinates":[-122.386155,37.616358],"type":"Point"}
}
