{
  "type": "Feature",
  "properties": {
    "iso:country": "XX",
    "media:fingerprint": "eaf0bfccfa97bcd9cb7a918bb3b9a9765343e99d",
    "media:imagehash_avg": "a:7efffe10701e0400",
    "media:imagehash_diff": "d:f0e08860e2f0fcfc",
    "media:medium": "image",
    "media:mimetype": "image/tiff",
    "media:properties": {
      "colours": [
        {
          "hex": "#808080",
          "name": "#808080",
          "reference": "vibrant"
        }, 
        {
          "hex": "#b8b8b8",
          "name": "#b8b8b8",
          "reference": "vibrant"
        }, 
        {
          "hex": "#464646",
          "name": "#464646",
          "reference": "vibrant"
        }
      ],
      "sizes": {
        "b": {
          "extension": "jpg",
          "height": 713,
          "mimetype": "image/jpeg",
          "secret": "0ODFZos291lSKEBTkyDI4XUtnqczVzPC",
          "width": 1024
        },
        "c": {
          "extension": "jpg",
          "height": 557,
          "mimetype": "image/jpeg",
          "secret": "0ODFZos291lSKEBTkyDI4XUtnqczVzPC",
          "width": 800
        },
        "dc": {
          "extension": "jpg",
          "height": 557,
          "mimetype": "image/jpeg",
          "secret": "0ODFZos291lSKEBTkyDI4XUtnqczVzPC",
          "width": 800
        },
        "ds": {
          "extension": "jpg",
          "height": 320,
          "mimetype": "image/jpeg",
          "secret": "0ODFZos291lSKEBTkyDI4XUtnqczVzPC",
          "width": 320
        },
        "k": {
          "extension": "jpg",
          "height": 1427,
          "mimetype": "image/jpeg",
          "secret": "0ODFZos291lSKEBTkyDI4XUtnqczVzPC",
          "width": 2048
        },
        "n": {
          "extension": "jpg",
          "height": 223,
          "mimetype": "image/jpeg",
          "secret": "0ODFZos291lSKEBTkyDI4XUtnqczVzPC",
          "width": 320
        },
        "o": {
          "extension": "jpg",
          "height": 6000,
          "mimetype": "image/jpeg",
          "secret": "lqv7LlIOdlgwX3rwFNq1qMj3fSw39CLd",
          "width": 8607
        },
        "s": {
          "extension": "jpg",
          "height": 320,
          "mimetype": "image/jpeg",
          "secret": "0ODFZos291lSKEBTkyDI4XUtnqczVzPC",
          "width": 320
        },
        "z": {
          "extension": "jpg",
          "height": 446,
          "mimetype": "image/jpeg",
          "secret": "0ODFZos291lSKEBTkyDI4XUtnqczVzPC",
          "width": 640
        }
      }
    },
    "media:uri_template": "https://millsfield.sfomuseum.org/media/152/782/137/3/1527821373_{secret}_{label}.{extention}",
    "sfomuseum:filename": "38717.tif",
    "sfomuseum:image_index": 5,
    "sfomuseum:placetype": "image",
    "sfomuseum:primary_image": 1,
    "wof:depicts": [
      1511949857
    ],
    "wof:name": "negative: Mills Field Municipal Airport of San Francisco, Hangar No. 2",
    "wof:placetype": "media"
  },
  "geometry": {"coordinates":[-122.386155,37.616358],"type":"Point"}
}
