{
  "type": "Feature",
  "properties": {
    "iso:country": "XX",
    "media:fingerprint": "f2d231aceba51dbf6dadd900e5b8be787e77b83d",
    "media:imagehash_avg": "a:fe7c2038a8e0c080",
    "media:imagehash_diff": "d:d8c0e1614b5a1920",
    "media:medium": "image",
    "media:mimetype": "image/tiff",
    "media:properties": {
      "colours": [
        {
          "hex": "#868686",
          "name": "#868686",
          "reference": "vibrant"
        }, 
        {
          "hex": "#b8b8b8",
          "name": "#b8b8b8",
          "reference": "vibrant"
        }, 
        {
          "hex": "#484848",
          "name": "#484848",
          "reference": "vibrant"
        }
      ],
      "sizes": {
        "b": {
          "extension": "jpg",
          "height": 700,
          "mimetype": "image/jpeg",
          "secret": "spi0sV37d9t9QCGJv13sfEsetTmALezT",
          "width": 1024
        },
        "c": {
          "extension": "jpg",
          "height": 547,
          "mimetype": "image/jpeg",
          "secret": "spi0sV37d9t9QCGJv13sfEsetTmALezT",
          "width": 800
        },
        "dc": {
          "extension": "jpg",
          "height": 547,
          "mimetype": "image/jpeg",
          "secret": "spi0sV37d9t9QCGJv13sfEsetTmALezT",
          "width": 800
        },
        "ds": {
          "extension": "jpg",
          "height": 320,
          "mimetype": "image/jpeg",
          "secret": "spi0sV37d9t9QCGJv13sfEsetTmALezT",
          "width": 320
        },
        "k": {
          "extension": "jpg",
          "height": 1400,
          "mimetype": "image/jpeg",
          "secret": "spi0sV37d9t9QCGJv13sfEsetTmALezT",
          "width": 2048
        },
        "n": {
          "extension": "jpg",
          "height": 218,
          "mimetype": "image/jpeg",
          "secret": "spi0sV37d9t9QCGJv13sfEsetTmALezT",
          "width": 320
        },
        "o": {
          "extension": "jpg",
          "height": 1063,
          "mimetype": "image/jpeg",
          "secret": "jBMpCEibdeTHtsBF4j1CO4kTen7KEjdM",
          "width": 1554
        },
        "s": {
          "extension": "jpg",
          "height": 320,
          "mimetype": "image/jpeg",
          "secret": "spi0sV37d9t9QCGJv13sfEsetTmALezT",
          "width": 320
        },
        "z": {
          "extension": "jpg",
          "height": 437,
          "mimetype": "image/jpeg",
          "secret": "spi0sV37d9t9QCGJv13sfEsetTmALezT",
          "width": 640
        }
      }
    },
    "media:uri_template": "https://millsfield.sfomuseum.org/media/152/782/855/5/1527828555_{secret}_{label}.{extention}",
    "sfomuseum:filename": "44651.tif",
    "sfomuseum:image_index": 5,
    "sfomuseum:placetype": "image",
    "sfomuseum:primary_image": 1,
    "wof:depicts": [
      1511949587
    ],
    "wof:name": "negative: San Francisco International Airport (SFO), North Terminal interior",
    "wof:placetype": "media"
  },
  "geometry": {"coordinates":[-122.386155,37.616358],"type":"Point"}
}
