{
  "type": "Feature",
  "properties": {
    "iso:country": "XX",
    "media:fingerprint": "710ac94613f20f557ee392c7fc95acfc383a918c",
    "media:imagehash_avg": "a:8000183c3f3ebcff",
    "media:imagehash_diff": "d:6171517179787171",
    "media:medium": "image",
    "media:mimetype": "image/tiff",
    "media:properties": {
      "colours": [
        {
          "hex": "#201f0e",
          "name": "#201f0e",
          "reference": "vibrant"
        },
        {
          "hex": "#a1956c",
          "name": "#a1956c",
          "reference": "vibrant"
        },
        {
          "hex": "#c9bf9c",
          "name": "#c9bf9c",
          "reference": "vibrant"
        },
        {
          "hex": "#534e34",
          "name": "#534e34",
          "reference": "vibrant"
        }
      ],
      "sizes": {
        "b": {
          "extension": "jpg",
          "height": 722,
          "mimetype": "image/jpeg",
          "secret": "2xbKWQaoDelPXUMI5QlbaX1bhBisRO5T",
          "width": 1024
        },
        "c": {
          "extension": "jpg",
          "height": 564,
          "mimetype": "image/jpeg",
          "secret": "2xbKWQaoDelPXUMI5QlbaX1bhBisRO5T",
          "width": 800
        },
        "dc": {
          "extension": "jpg",
          "height": 564,
          "mimetype": "image/jpeg",
          "secret": "2xbKWQaoDelPXUMI5QlbaX1bhBisRO5T",
          "width": 800
        },
        "ds": {
          "extension": "jpg",
          "height": 320,
          "mimetype": "image/jpeg",
          "secret": "2xbKWQaoDelPXUMI5QlbaX1bhBisRO5T",
          "width": 320
        },
        "k": {
          "extension": "jpg",
          "height": 1445,
          "mimetype": "image/jpeg",
          "secret": "2xbKWQaoDelPXUMI5QlbaX1bhBisRO5T",
          "width": 2048
        },
        "n": {
          "extension": "jpg",
          "height": 225,
          "mimetype": "image/jpeg",
          "secret": "2xbKWQaoDelPXUMI5QlbaX1bhBisRO5T",
          "width": 320
        },
        "o": {
          "extension": "jpg",
          "height": 3012,
          "mimetype": "image/jpeg",
          "secret": "epfrWVzA9B16Os1CHauJA6yRiquefXCa",
          "width": 4268
        },
        "s": {
          "extension": "jpg",
          "height": 320,
          "mimetype": "image/jpeg",
          "secret": "2xbKWQaoDelPXUMI5QlbaX1bhBisRO5T",
          "width": 320
        },
        "z": {
          "extension": "jpg",
          "height": 451,
          "mimetype": "image/jpeg",
          "secret": "2xbKWQaoDelPXUMI5QlbaX1bhBisRO5T",
          "width": 640
        }
      }
    },
    "media:uri_template": "https://static.sfomuseum.org/media/152/785/570/9/1527855709_{secret}_{label}.{extention}",
    "sfomuseum:filename": "100413.tif",
    "sfomuseum:image_index": 5,
    "sfomuseum:image_type": "studio",
    "sfomuseum:placetype": "image",
    "sfomuseum:primary_image": 1,
    "wof:depicts": [
      1108830803,
      85922583,
      85688637,
      85633793,
      1511942555
    ],
    "wof:name": "photograph: San Francisco, Sunset District, aerial",
    "wof:placetype": "custom",
    "wof:placetype_alt": "image"
  },
  "geometry": {"coordinates":[-122.386155,37.616358],"type":"Point"}
}
