{
  "type": "Feature",
  "properties": {
    "iso:country":"XX",
    "media:medium":"image",
    "sfomuseum:filename":"2015.052.001b.tif",
    "sfomuseum:image_index":0,
    "sfomuseum:placetype":"image",
    "sfomuseum:primary_image":0,
    "wof:depicts":[
        1511958293
    ],
    "wof:name":"airmail flight cover: Lockheed, 150th anniversary U.S. Frigate Constitution",
    "wof:placetype":"media"
},
  "geometry": {"coordinates":[-122.386155,37.616358],"type":"Point"}
}