{
  "type": "Feature",
  "properties": {
    "iso:country": "XX",
    "media:fingerprint": "602aca6cdb8844d19c0ec60b47c3c2498cc54493",
    "media:imagehash_avg": "a:fff78181818181ff",
    "media:imagehash_diff": "d:41074d4d25256541",
    "media:medium": "image",
    "media:mimetype": "image/tiff",
    "media:properties": {
      "colours": [
        {
          "hex": "#e8d8c6",
          "name": "#e8d8c6",
          "reference": "vibrant"
        },
        {
          "hex": "#898873",
          "name": "#898873",
          "reference": "vibrant"
        },
        {
          "hex": "#d8d8b8",
          "name": "#d8d8b8",
          "reference": "vibrant"
        },
        {
          "hex": "#454634",
          "name": "#454634",
          "reference": "vibrant"
        }
      ],
      "sizes": {
        "b": {
          "extension": "jpg",
          "height": 768,
          "mimetype": "image/jpeg",
          "secret": "1YrLsilHsmhMxse591qId0EcXKIvyfKG",
          "width": 594
        },
        "c": {
          "extension": "jpg",
          "height": 600,
          "mimetype": "image/jpeg",
          "secret": "1YrLsilHsmhMxse591qId0EcXKIvyfKG",
          "width": 464
        },
        "dc": {
          "extension": "jpg",
          "height": 600,
          "mimetype": "image/jpeg",
          "secret": "1YrLsilHsmhMxse591qId0EcXKIvyfKG",
          "width": 464
        },
        "ds": {
          "extension": "jpg",
          "height": 320,
          "mimetype": "image/jpeg",
          "secret": "1YrLsilHsmhMxse591qId0EcXKIvyfKG",
          "width": 320
        },
        "k": {
          "extension": "jpg",
          "height": 1536,
          "mimetype": "image/jpeg",
          "secret": "1YrLsilHsmhMxse591qId0EcXKIvyfKG",
          "width": 1188
        },
        "n": {
          "extension": "jpg",
          "height": 240,
          "mimetype": "image/jpeg",
          "secret": "1YrLsilHsmhMxse591qId0EcXKIvyfKG",
          "width": 185
        },
        "o": {
          "extension": "jpg",
          "height": 1800,
          "mimetype": "image/jpeg",
          "secret": "0IVyhyTxgFa2ijvAZJnqJxHSJNe3mYGm",
          "width": 1393
        },
        "s": {
          "extension": "jpg",
          "height": 320,
          "mimetype": "image/jpeg",
          "secret": "1YrLsilHsmhMxse591qId0EcXKIvyfKG",
          "width": 320
        },
        "z": {
          "extension": "jpg",
          "height": 480,
          "mimetype": "image/jpeg",
          "secret": "1YrLsilHsmhMxse591qId0EcXKIvyfKG",
          "width": 371
        }
      }
    },
    "media:uri_template": "https://static.sfomuseum.org/media/152/785/683/3/1527856833_{secret}_{label}.{extention}",
    "sfomuseum:filename": "157208.tif",
    "sfomuseum:image_index": 5,
    "sfomuseum:image_type": "studio",
    "sfomuseum:placetype": "image",
    "sfomuseum:primary_image": 1,
    "wof:depicts": [
      1360695653,
      1511958067
    ],
    "wof:name": "report: City and County of San Francisco, cost analysis for proposed airport sites",
    "wof:placetype": "custom",
    "wof:placetype_alt": "image"
  },
  "geometry": {"coordinates":[-122.386155,37.616358],"type":"Point"}
}
