{
  "type": "Feature",
  "properties": {
    "iso:country": "XX",
    "media:fingerprint": "b71a0bc25ea72d0c31d483deb3bbfbca36e900cb",
    "media:imagehash_avg": "a:05f9f39412332333",
    "media:imagehash_diff": "d:3d0b472d2ee76767",
    "media:medium": "image",
    "media:mimetype": "image/tiff",
    "media:properties": {
      "colours": [
        {
          "hex": "#808080",
          "name": "#808080",
          "reference": "vibrant"
        },
        {
          "hex": "#b8b8b8",
          "name": "#b8b8b8",
          "reference": "vibrant"
        },
        {
          "hex": "#404040",
          "name": "#404040",
          "reference": "vibrant"
        }
      ],
      "sizes": {
        "b": {
          "extension": "jpg",
          "height": 754,
          "mimetype": "image/jpeg",
          "secret": "Hc9LoqORYWZzNEjUFQiade3gLkQJ1nSQ",
          "width": 1024
        },
        "c": {
          "extension": "jpg",
          "height": 589,
          "mimetype": "image/jpeg",
          "secret": "Hc9LoqORYWZzNEjUFQiade3gLkQJ1nSQ",
          "width": 800
        },
        "dc": {
          "extension": "jpg",
          "height": 589,
          "mimetype": "image/jpeg",
          "secret": "Hc9LoqORYWZzNEjUFQiade3gLkQJ1nSQ",
          "width": 800
        },
        "ds": {
          "extension": "jpg",
          "height": 320,
          "mimetype": "image/jpeg",
          "secret": "Hc9LoqORYWZzNEjUFQiade3gLkQJ1nSQ",
          "width": 320
        },
        "k": {
          "extension": "jpg",
          "height": 1509,
          "mimetype": "image/jpeg",
          "secret": "Hc9LoqORYWZzNEjUFQiade3gLkQJ1nSQ",
          "width": 2048
        },
        "n": {
          "extension": "jpg",
          "height": 235,
          "mimetype": "image/jpeg",
          "secret": "Hc9LoqORYWZzNEjUFQiade3gLkQJ1nSQ",
          "width": 320
        },
        "o": {
          "extension": "jpg",
          "height": 2951,
          "mimetype": "image/jpeg",
          "secret": "iJ7oeczJpE6ZW0Pr9yuic0IAHgIAeTsj",
          "width": 4004
        },
        "s": {
          "extension": "jpg",
          "height": 320,
          "mimetype": "image/jpeg",
          "secret": "Hc9LoqORYWZzNEjUFQiade3gLkQJ1nSQ",
          "width": 320
        },
        "z": {
          "extension": "jpg",
          "height": 471,
          "mimetype": "image/jpeg",
          "secret": "Hc9LoqORYWZzNEjUFQiade3gLkQJ1nSQ",
          "width": 640
        }
      }
    },
    "media:uri_template": "https://static.sfomuseum.org/media/172/956/543/5/1729565435_{secret}_{label}.{extention}",
    "sfomuseum:filename": "39626.tif",
    "sfomuseum:image_index": 0,
    "sfomuseum:image_type": "studio",
    "sfomuseum:placetype": "image",
    "sfomuseum:primary_image": 1,
    "wof:depicts": [
      1729564343,
      1159287531,
      1159285395
    ],
    "wof:name": "photograph: Transcontinental \u0026 Western Air (TWA), air hostesses",
    "wof:placetype": "custom",
    "wof:placetype_alt": "image"
  },
  "geometry": {"coordinates":[-122.386155,37.616357],"type":"Point"}
}
