{
  "type": "Feature",
  "properties": {
    "iso:country": "XX",
    "media:fingerprint": "0d69db837dd82f521e83bb75f1ff8b05a8b266f2",
    "media:imagehash_avg": "a:fff99898989898ff",
    "media:imagehash_diff": "d:3333333333323331",
    "media:medium": "image",
    "media:mimetype": "image/tiff",
    "media:properties": {
      "colours": [
        {
          "hex": "#3c4aae",
          "name": "#3c4aae",
          "reference": "vibrant"
        },
        {
          "hex": "#959fce",
          "name": "#959fce",
          "reference": "vibrant"
        },
        {
          "hex": "#001088",
          "name": "#001088",
          "reference": "vibrant"
        },
        {
          "hex": "#606db7",
          "name": "#606db7",
          "reference": "vibrant"
        },
        {
          "hex": "#b4bdd7",
          "name": "#b4bdd7",
          "reference": "vibrant"
        }
      ],
      "sizes": {
        "b": {
          "extension": "jpg",
          "height": 768,
          "mimetype": "image/jpeg",
          "secret": "c6J49pRxHPVwCADv2qA9zEdMoxl3lhjM",
          "width": 825
        },
        "c": {
          "extension": "jpg",
          "height": 600,
          "mimetype": "image/jpeg",
          "secret": "c6J49pRxHPVwCADv2qA9zEdMoxl3lhjM",
          "width": 644
        },
        "dc": {
          "extension": "jpg",
          "height": 600,
          "mimetype": "image/jpeg",
          "secret": "c6J49pRxHPVwCADv2qA9zEdMoxl3lhjM",
          "width": 644
        },
        "ds": {
          "extension": "jpg",
          "height": 320,
          "mimetype": "image/jpeg",
          "secret": "c6J49pRxHPVwCADv2qA9zEdMoxl3lhjM",
          "width": 320
        },
        "k": {
          "extension": "jpg",
          "height": 1536,
          "mimetype": "image/jpeg",
          "secret": "c6J49pRxHPVwCADv2qA9zEdMoxl3lhjM",
          "width": 1651
        },
        "n": {
          "extension": "jpg",
          "height": 240,
          "mimetype": "image/jpeg",
          "secret": "c6J49pRxHPVwCADv2qA9zEdMoxl3lhjM",
          "width": 257
        },
        "o": {
          "extension": "jpg",
          "height": 2642,
          "mimetype": "image/jpeg",
          "secret": "B1q8iyilZs43wo2u1l659CDe5IyLBbGd",
          "width": 2840
        },
        "s": {
          "extension": "jpg",
          "height": 320,
          "mimetype": "image/jpeg",
          "secret": "c6J49pRxHPVwCADv2qA9zEdMoxl3lhjM",
          "width": 320
        },
        "z": {
          "extension": "jpg",
          "height": 480,
          "mimetype": "image/jpeg",
          "secret": "c6J49pRxHPVwCADv2qA9zEdMoxl3lhjM",
          "width": 515
        }
      }
    },
    "media:uri_template": "https://millsfield.sfomuseum.org/media/152/784/362/1/1527843621_{secret}_{label}.{extention}",
    "sfomuseum:filename": "2001080175_inside.tif",
    "sfomuseum:image_index": 5,
    "sfomuseum:placetype": "image",
    "sfomuseum:primary_image": 0,
    "wof:depicts": [
      1159284021,
      1511922093
    ],
    "wof:name": "menu: British Airways, Club World (Business) Class",
    "wof:placetype": "media"
  },
  "geometry": {"coordinates":[-122.386155,37.616358],"type":"Point"}
}
