{
  "type": "Feature",
  "properties": {
    "iso:country": "XX",
    "media:fingerprint": "e80b96ea3f81e4e422ba8b3a2f10b68bfcf105f7",
    "media:imagehash_avg": "a:7e7f7e3600000000",
    "media:imagehash_diff": "d:f8f8f4e4ecf8f8ec",
    "media:medium": "image",
    "media:mimetype": "image/tiff",
    "media:properties": {
      "colours": [
        {
          "hex": "#808080",
          "name": "#808080",
          "reference": "vibrant"
        }, 
        {
          "hex": "#b8b8b8",
          "name": "#b8b8b8",
          "reference": "vibrant"
        }, 
        {
          "hex": "#464646",
          "name": "#464646",
          "reference": "vibrant"
        }
      ],
      "sizes": {
        "b": {
          "extension": "jpg",
          "height": 607,
          "mimetype": "image/jpeg",
          "secret": "TGycABX7UWfGilAb7IX2nbTN8FoakOeX",
          "width": 1024
        },
        "c": {
          "extension": "jpg",
          "height": 474,
          "mimetype": "image/jpeg",
          "secret": "TGycABX7UWfGilAb7IX2nbTN8FoakOeX",
          "width": 800
        },
        "dc": {
          "extension": "jpg",
          "height": 474,
          "mimetype": "image/jpeg",
          "secret": "TGycABX7UWfGilAb7IX2nbTN8FoakOeX",
          "width": 800
        },
        "ds": {
          "extension": "jpg",
          "height": 320,
          "mimetype": "image/jpeg",
          "secret": "TGycABX7UWfGilAb7IX2nbTN8FoakOeX",
          "width": 320
        },
        "k": {
          "extension": "jpg",
          "height": 1214,
          "mimetype": "image/jpeg",
          "secret": "TGycABX7UWfGilAb7IX2nbTN8FoakOeX",
          "width": 2048
        },
        "n": {
          "extension": "jpg",
          "height": 189,
          "mimetype": "image/jpeg",
          "secret": "TGycABX7UWfGilAb7IX2nbTN8FoakOeX",
          "width": 320
        },
        "o": {
          "extension": "jpg",
          "height": 4336,
          "mimetype": "image/jpeg",
          "secret": "8B1RPqt19uKI9zht6t4XJwRAZIRqBP4o",
          "width": 7309
        },
        "s": {
          "extension": "jpg",
          "height": 320,
          "mimetype": "image/jpeg",
          "secret": "TGycABX7UWfGilAb7IX2nbTN8FoakOeX",
          "width": 320
        },
        "z": {
          "extension": "jpg",
          "height": 379,
          "mimetype": "image/jpeg",
          "secret": "TGycABX7UWfGilAb7IX2nbTN8FoakOeX",
          "width": 640
        }
      }
    },
    "media:uri_template": "https://millsfield.sfomuseum.org/media/152/782/118/3/1527821183_{secret}_{label}.{extention}",
    "sfomuseum:filename": "38617.tif",
    "sfomuseum:image_index": 5,
    "sfomuseum:placetype": "image",
    "sfomuseum:primary_image": 1,
    "wof:depicts": [
      1511943477
    ],
    "wof:name": "negative: Oakland Airport, runway construction",
    "wof:placetype": "media"
  },
  "geometry": {"coordinates":[-122.386155,37.616358],"type":"Point"}
}
