{
  "type": "Feature",
  "properties": {
    "iso:country": "XX",
    "media:fingerprint": "d8817f254f963a2a246cdab0c5558aa5a0b62776",
    "media:imagehash_avg": "a:80989e9f9f0c0c00",
    "media:imagehash_diff": "d:1338303c3838384c",
    "media:medium": "image",
    "media:mimetype": "image/tiff",
    "media:properties": {
      "colours": [
        {
          "hex": "#808080",
          "name": "#808080",
          "reference": "vibrant"
        },
        {
          "hex": "#c0c0c0",
          "name": "#c0c0c0",
          "reference": "vibrant"
        },
        {
          "hex": "#404040",
          "name": "#404040",
          "reference": "vibrant"
        }
      ],
      "sizes": {
        "b": {
          "extension": "jpg",
          "height": 768,
          "mimetype": "image/jpeg",
          "secret": "2Ce6NImhfWUWsHP1k9VH4cLCcIX8FOHw",
          "width": 768
        },
        "c": {
          "extension": "jpg",
          "height": 600,
          "mimetype": "image/jpeg",
          "secret": "2Ce6NImhfWUWsHP1k9VH4cLCcIX8FOHw",
          "width": 600
        },
        "dc": {
          "extension": "jpg",
          "height": 600,
          "mimetype": "image/jpeg",
          "secret": "2Ce6NImhfWUWsHP1k9VH4cLCcIX8FOHw",
          "width": 600
        },
        "ds": {
          "extension": "jpg",
          "height": 320,
          "mimetype": "image/jpeg",
          "secret": "2Ce6NImhfWUWsHP1k9VH4cLCcIX8FOHw",
          "width": 320
        },
        "k": {
          "extension": "jpg",
          "height": 1536,
          "mimetype": "image/jpeg",
          "secret": "2Ce6NImhfWUWsHP1k9VH4cLCcIX8FOHw",
          "width": 1536
        },
        "n": {
          "extension": "jpg",
          "height": 239,
          "mimetype": "image/jpeg",
          "secret": "2Ce6NImhfWUWsHP1k9VH4cLCcIX8FOHw",
          "width": 239
        },
        "o": {
          "extension": "jpg",
          "height": 2563,
          "mimetype": "image/jpeg",
          "secret": "lmNyok0ZayCpU4lx9ozLgVWDi80tfC94",
          "width": 2563
        },
        "s": {
          "extension": "jpg",
          "height": 320,
          "mimetype": "image/jpeg",
          "secret": "2Ce6NImhfWUWsHP1k9VH4cLCcIX8FOHw",
          "width": 320
        },
        "z": {
          "extension": "jpg",
          "height": 479,
          "mimetype": "image/jpeg",
          "secret": "2Ce6NImhfWUWsHP1k9VH4cLCcIX8FOHw",
          "width": 479
        }
      }
    },
    "media:uri_template": "https://static.sfomuseum.org/media/152/782/513/3/1527825133_{secret}_{label}.{extention}",
    "sfomuseum:filename": "42979.tif",
    "sfomuseum:image_index": 5,
    "sfomuseum:image_type": "studio",
    "sfomuseum:placetype": "image",
    "sfomuseum:primary_image": 1,
    "wof:depicts": [
      1511946059,
      102527513
    ],
    "wof:name": "negative: San Francisco International Airport (SFO), construction shop",
    "wof:placetype": "custom",
    "wof:placetype_alt": "image"
  },
  "geometry": {"coordinates":[-122.386155,37.616358],"type":"Point"}
}
