{
  "type": "Feature",
  "properties": {
    "iso:country": "XX",
    "media:fingerprint": "379768193ea2ce5c451aed100307e38ab0e66687",
    "media:imagehash_avg": "a:fefefe7e0200001c",
    "media:imagehash_diff": "d:c0c0c8ccdef8d8f8",
    "media:medium": "image",
    "media:mimetype": "image/tiff",
    "media:properties": {
      "colours": [
        {
          "hex": "#7a7a7a",
          "name": "#7a7a7a",
          "reference": "vibrant"
        }, 
        {
          "hex": "#b8b8b8",
          "name": "#b8b8b8",
          "reference": "vibrant"
        }, 
        {
          "hex": "#404040",
          "name": "#404040",
          "reference": "vibrant"
        }
      ],
      "sizes": {
        "b": {
          "extension": "jpg",
          "height": 609,
          "mimetype": "image/jpeg",
          "secret": "zP4xsd8zJhDoOcPMUfriojsgyEeTHuKp",
          "width": 1024
        },
        "c": {
          "extension": "jpg",
          "height": 476,
          "mimetype": "image/jpeg",
          "secret": "zP4xsd8zJhDoOcPMUfriojsgyEeTHuKp",
          "width": 800
        },
        "dc": {
          "extension": "jpg",
          "height": 476,
          "mimetype": "image/jpeg",
          "secret": "zP4xsd8zJhDoOcPMUfriojsgyEeTHuKp",
          "width": 800
        },
        "ds": {
          "extension": "jpg",
          "height": 320,
          "mimetype": "image/jpeg",
          "secret": "zP4xsd8zJhDoOcPMUfriojsgyEeTHuKp",
          "width": 320
        },
        "k": {
          "extension": "jpg",
          "height": 1219,
          "mimetype": "image/jpeg",
          "secret": "zP4xsd8zJhDoOcPMUfriojsgyEeTHuKp",
          "width": 2048
        },
        "n": {
          "extension": "jpg",
          "height": 190,
          "mimetype": "image/jpeg",
          "secret": "zP4xsd8zJhDoOcPMUfriojsgyEeTHuKp",
          "width": 320
        },
        "o": {
          "extension": "jpg",
          "height": 893,
          "mimetype": "image/jpeg",
          "secret": "8csWCWiFjWPxL9fxB7MlwQzDjI9JPqdR",
          "width": 1500
        },
        "s": {
          "extension": "jpg",
          "height": 320,
          "mimetype": "image/jpeg",
          "secret": "zP4xsd8zJhDoOcPMUfriojsgyEeTHuKp",
          "width": 320
        },
        "z": {
          "extension": "jpg",
          "height": 381,
          "mimetype": "image/jpeg",
          "secret": "zP4xsd8zJhDoOcPMUfriojsgyEeTHuKp",
          "width": 640
        }
      }
    },
    "media:uri_template": "https://millsfield.sfomuseum.org/media/152/782/095/1/1527820951_{secret}_{label}.{extention}",
    "sfomuseum:filename": "33253.tif",
    "sfomuseum:image_index": 5,
    "sfomuseum:placetype": "image",
    "sfomuseum:primary_image": 1,
    "wof:depicts": [
      1511931417
    ],
    "wof:name": "photograph: Pan American Airways, Havana, Cuba",
    "wof:placetype": "media"
  },
  "geometry": {"coordinates":[-122.386155,37.616358],"type":"Point"}
}
