{
  "type": "Feature",
  "properties": {
    "iso:country": "XX",
    "media:fingerprint": "06a106fc24162d0b79715768eda61c00e4ee7a30",
    "media:imagehash_avg": "a:7fffe747017f7f7f",
    "media:imagehash_diff": "d:c4c58d8f0fa3cfbb",
    "media:medium": "image",
    "media:mimetype": "image/tiff",
    "media:properties": {
      "colours": [
        {
          "hex": "#e84a43",
          "name": "#e84a43",
          "reference": "vibrant"
        }, 
        {
          "hex": "#f85a52",
          "name": "#f85a52",
          "reference": "vibrant"
        }, 
        {
          "hex": "#8a8f90",
          "name": "#8a8f90",
          "reference": "vibrant"
        }, 
        {
          "hex": "#d2c3c4",
          "name": "#d2c3c4",
          "reference": "vibrant"
        }, 
        {
          "hex": "#444a67",
          "name": "#444a67",
          "reference": "vibrant"
        }
      ],
      "sizes": {
        "b": {
          "extension": "jpg",
          "height": 767,
          "mimetype": "image/jpeg",
          "secret": "hbXmB3rQ0wdbmFTn2KlZlXrhXCPIfOkP",
          "width": 419
        },
        "c": {
          "extension": "jpg",
          "height": 600,
          "mimetype": "image/jpeg",
          "secret": "hbXmB3rQ0wdbmFTn2KlZlXrhXCPIfOkP",
          "width": 327
        },
        "dc": {
          "extension": "jpg",
          "height": 600,
          "mimetype": "image/jpeg",
          "secret": "hbXmB3rQ0wdbmFTn2KlZlXrhXCPIfOkP",
          "width": 327
        },
        "ds": {
          "extension": "jpg",
          "height": 320,
          "mimetype": "image/jpeg",
          "secret": "hbXmB3rQ0wdbmFTn2KlZlXrhXCPIfOkP",
          "width": 320
        },
        "k": {
          "extension": "jpg",
          "height": 1535,
          "mimetype": "image/jpeg",
          "secret": "hbXmB3rQ0wdbmFTn2KlZlXrhXCPIfOkP",
          "width": 839
        },
        "n": {
          "extension": "jpg",
          "height": 240,
          "mimetype": "image/jpeg",
          "secret": "hbXmB3rQ0wdbmFTn2KlZlXrhXCPIfOkP",
          "width": 131
        },
        "o": {
          "extension": "jpg",
          "height": 2844,
          "mimetype": "image/jpeg",
          "secret": "wc80G9Ppcr0O6yM4bFBwEeviB72psqKG",
          "width": 1554
        },
        "s": {
          "extension": "jpg",
          "height": 320,
          "mimetype": "image/jpeg",
          "secret": "hbXmB3rQ0wdbmFTn2KlZlXrhXCPIfOkP",
          "width": 320
        },
        "z": {
          "extension": "jpg",
          "height": 480,
          "mimetype": "image/jpeg",
          "secret": "hbXmB3rQ0wdbmFTn2KlZlXrhXCPIfOkP",
          "width": 262
        }
      }
    },
    "media:uri_template": "https://millsfield.sfomuseum.org/media/152/782/345/5/1527823455_{secret}_{label}.{extention}",
    "sfomuseum:filename": "41594.tif",
    "sfomuseum:image_index": 5,
    "sfomuseum:placetype": "image",
    "sfomuseum:primary_image": 1,
    "wof:depicts": [
      1511908391
    ],
    "wof:name": "airsickness bag: Air Malta",
    "wof:placetype": "media"
  },
  "geometry": {"coordinates":[-122.386155,37.616358],"type":"Point"}
}
