{
  "type": "Feature",
  "properties": {
    "iso:country": "XX",
    "media:fingerprint": "98677f29b0b30ce6a3b69a2fbce777811da169b3",
    "media:imagehash_avg": "a:1f1f071f3d3d3f7f",
    "media:imagehash_diff": "d:fb6b6f736979f1f9",
    "media:medium": "image",
    "media:mimetype": "image/tiff",
    "media:properties": {
      "colours": [
        {
          "hex": "#e8d8b2",
          "name": "#e8d8b2",
          "reference": "vibrant"
        },
        {
          "hex": "#978563",
          "name": "#978563",
          "reference": "vibrant"
        },
        {
          "hex": "#d3c09b",
          "name": "#d3c09b",
          "reference": "vibrant"
        },
        {
          "hex": "#3b3d43",
          "name": "#3b3d43",
          "reference": "vibrant"
        }
      ],
      "sizes": {
        "b": {
          "extension": "jpg",
          "height": 768,
          "mimetype": "image/jpeg",
          "secret": "LFNlnqFGXbWTdqYHuwDiU2fhK3W8CjLH",
          "width": 592
        },
        "c": {
          "extension": "jpg",
          "height": 600,
          "mimetype": "image/jpeg",
          "secret": "LFNlnqFGXbWTdqYHuwDiU2fhK3W8CjLH",
          "width": 463
        },
        "dc": {
          "extension": "jpg",
          "height": 600,
          "mimetype": "image/jpeg",
          "secret": "LFNlnqFGXbWTdqYHuwDiU2fhK3W8CjLH",
          "width": 463
        },
        "ds": {
          "extension": "jpg",
          "height": 320,
          "mimetype": "image/jpeg",
          "secret": "LFNlnqFGXbWTdqYHuwDiU2fhK3W8CjLH",
          "width": 320
        },
        "k": {
          "extension": "jpg",
          "height": 1536,
          "mimetype": "image/jpeg",
          "secret": "LFNlnqFGXbWTdqYHuwDiU2fhK3W8CjLH",
          "width": 1185
        },
        "n": {
          "extension": "jpg",
          "height": 240,
          "mimetype": "image/jpeg",
          "secret": "LFNlnqFGXbWTdqYHuwDiU2fhK3W8CjLH",
          "width": 185
        },
        "o": {
          "extension": "jpg",
          "height": 1800,
          "mimetype": "image/jpeg",
          "secret": "fzJ8Z6o2x46MW8ZO91qB3OZ8NpzJyoMZ",
          "width": 1389
        },
        "s": {
          "extension": "jpg",
          "height": 320,
          "mimetype": "image/jpeg",
          "secret": "LFNlnqFGXbWTdqYHuwDiU2fhK3W8CjLH",
          "width": 320
        },
        "z": {
          "extension": "jpg",
          "height": 480,
          "mimetype": "image/jpeg",
          "secret": "LFNlnqFGXbWTdqYHuwDiU2fhK3W8CjLH",
          "width": 370
        }
      }
    },
    "media:uri_template": "https://static.sfomuseum.org/media/152/785/672/9/1527856729_{secret}_{label}.{extention}",
    "sfomuseum:filename": "2000.018.008b.tif",
    "sfomuseum:image_index": 5,
    "sfomuseum:image_type": "studio",
    "sfomuseum:placetype": "image",
    "sfomuseum:primary_image": 0,
    "wof:depicts": [
      1360695653,
      1511910043
    ],
    "wof:name": "directory: United States Chamber of Commerce, airplane manufacturers",
    "wof:placetype": "custom",
    "wof:placetype_alt": "image"
  },
  "geometry": {"coordinates":[-122.386155,37.616358],"type":"Point"}
}
