{
  "type": "Feature",
  "properties": {
    "iso:country": "XX",
    "media:fingerprint": "8b8bed42da9f142b20c41c98ab0b5d79b2696c31",
    "media:imagehash_avg": "a:0101061dcbc78ecf",
    "media:imagehash_diff": "d:7f3b0c39921f5e1e",
    "media:medium": "image",
    "media:mimetype": "image/tiff",
    "media:properties": {
      "colours": [
        {
          "hex": "#808080",
          "name": "#808080",
          "reference": "vibrant"
        }, 
        {
          "hex": "#b8b8b8",
          "name": "#b8b8b8",
          "reference": "vibrant"
        }, 
        {
          "hex": "#404040",
          "name": "#404040",
          "reference": "vibrant"
        }
      ],
      "sizes": {
        "b": {
          "extension": "jpg",
          "height": 768,
          "mimetype": "image/jpeg",
          "secret": "SDIKPsxo1h2VTyuAHyRGrd4U0bynxKfD",
          "width": 768
        },
        "c": {
          "extension": "jpg",
          "height": 600,
          "mimetype": "image/jpeg",
          "secret": "SDIKPsxo1h2VTyuAHyRGrd4U0bynxKfD",
          "width": 600
        },
        "dc": {
          "extension": "jpg",
          "height": 600,
          "mimetype": "image/jpeg",
          "secret": "SDIKPsxo1h2VTyuAHyRGrd4U0bynxKfD",
          "width": 600
        },
        "ds": {
          "extension": "jpg",
          "height": 320,
          "mimetype": "image/jpeg",
          "secret": "SDIKPsxo1h2VTyuAHyRGrd4U0bynxKfD",
          "width": 320
        },
        "k": {
          "extension": "jpg",
          "height": 1536,
          "mimetype": "image/jpeg",
          "secret": "SDIKPsxo1h2VTyuAHyRGrd4U0bynxKfD",
          "width": 1536
        },
        "n": {
          "extension": "jpg",
          "height": 240,
          "mimetype": "image/jpeg",
          "secret": "SDIKPsxo1h2VTyuAHyRGrd4U0bynxKfD",
          "width": 240
        },
        "o": {
          "extension": "jpg",
          "height": 2590,
          "mimetype": "image/jpeg",
          "secret": "rTDWFVXKhKEsnEnFVXWpRa9TVRok9zB2",
          "width": 2590
        },
        "s": {
          "extension": "jpg",
          "height": 320,
          "mimetype": "image/jpeg",
          "secret": "SDIKPsxo1h2VTyuAHyRGrd4U0bynxKfD",
          "width": 320
        },
        "z": {
          "extension": "jpg",
          "height": 480,
          "mimetype": "image/jpeg",
          "secret": "SDIKPsxo1h2VTyuAHyRGrd4U0bynxKfD",
          "width": 480
        }
      }
    },
    "media:uri_template": "https://millsfield.sfomuseum.org/media/152/782/791/7/1527827917_{secret}_{label}.{extention}",
    "sfomuseum:filename": "44300.tif",
    "sfomuseum:image_index": 5,
    "sfomuseum:placetype": "image",
    "sfomuseum:primary_image": 1,
    "wof:depicts": [
      1511948951
    ],
    "wof:name": "negative: San Francisco International Airport (SFO), road construction",
    "wof:placetype": "media"
  },
  "geometry": {"coordinates":[-122.386155,37.616358],"type":"Point"}
}
