{
  "type": "Feature",
  "properties": {
    "iso:country": "XX",
    "media:fingerprint": "2fab68c967b37b1e843ab717a4cb1c2860a2e1fe",
    "media:imagehash_avg": "a:00fee7e33870f0f8",
    "media:imagehash_diff": "d:66e446c6f2f3e1e3",
    "media:medium": "image",
    "media:mimetype": "image/tiff",
    "media:properties": {
      "colours": [
        {
          "hex": "#808080",
          "name": "#808080",
          "reference": "vibrant"
        }, 
        {
          "hex": "#b8b8b8",
          "name": "#b8b8b8",
          "reference": "vibrant"
        }, 
        {
          "hex": "#404040",
          "name": "#404040",
          "reference": "vibrant"
        }
      ],
      "sizes": {
        "b": {
          "extension": "jpg",
          "height": 768,
          "mimetype": "image/jpeg",
          "secret": "STlySJkQIyjxpsKnelKwyvrA0IHJi9rW",
          "width": 759
        },
        "c": {
          "extension": "jpg",
          "height": 600,
          "mimetype": "image/jpeg",
          "secret": "STlySJkQIyjxpsKnelKwyvrA0IHJi9rW",
          "width": 593
        },
        "dc": {
          "extension": "jpg",
          "height": 600,
          "mimetype": "image/jpeg",
          "secret": "STlySJkQIyjxpsKnelKwyvrA0IHJi9rW",
          "width": 593
        },
        "ds": {
          "extension": "jpg",
          "height": 320,
          "mimetype": "image/jpeg",
          "secret": "STlySJkQIyjxpsKnelKwyvrA0IHJi9rW",
          "width": 320
        },
        "k": {
          "extension": "jpg",
          "height": 1536,
          "mimetype": "image/jpeg",
          "secret": "STlySJkQIyjxpsKnelKwyvrA0IHJi9rW",
          "width": 1519
        },
        "n": {
          "extension": "jpg",
          "height": 240,
          "mimetype": "image/jpeg",
          "secret": "STlySJkQIyjxpsKnelKwyvrA0IHJi9rW",
          "width": 237
        },
        "o": {
          "extension": "jpg",
          "height": 1309,
          "mimetype": "image/jpeg",
          "secret": "f7oHiQR4H3AFWls6nrHU9HfP86WkYScR",
          "width": 1295
        },
        "s": {
          "extension": "jpg",
          "height": 320,
          "mimetype": "image/jpeg",
          "secret": "STlySJkQIyjxpsKnelKwyvrA0IHJi9rW",
          "width": 320
        },
        "z": {
          "extension": "jpg",
          "height": 480,
          "mimetype": "image/jpeg",
          "secret": "STlySJkQIyjxpsKnelKwyvrA0IHJi9rW",
          "width": 474
        }
      }
    },
    "media:uri_template": "https://millsfield.sfomuseum.org/media/152/782/213/9/1527822139_{secret}_{label}.{extention}",
    "sfomuseum:filename": "40219.tif",
    "sfomuseum:image_index": 5,
    "sfomuseum:placetype": "image",
    "sfomuseum:primary_image": 1,
    "wof:depicts": [
      1511944059
    ],
    "wof:name": "negative: San Francisco International Airport (SFO), dedication events for new Terminal Building",
    "wof:placetype": "media"
  },
  "geometry": {"coordinates":[-122.386155,37.616358],"type":"Point"}
}
