{
  "type": "Feature",
  "properties": {
    "iso:country": "XX",
    "media:fingerprint": "e3ff59a2cad2478204260e8aa100db4924197d16",
    "media:imagehash_avg": "a:001c3c3c3c3c0000",
    "media:imagehash_diff": "d:a8f8e8796971938e",
    "media:medium": "image",
    "media:mimetype": "image/tiff",
    "media:properties": {
      "colours": [
        {
          "hex": "#b18e59",
          "name": "#b18e59",
          "reference": "vibrant"
        }, 
        {
          "hex": "#d7be98",
          "name": "#d7be98",
          "reference": "vibrant"
        }, 
        {
          "hex": "#a78754",
          "name": "#a78754",
          "reference": "vibrant"
        }, 
        {
          "hex": "#d4c6aa",
          "name": "#d4c6aa",
          "reference": "vibrant"
        }
      ],
      "sizes": {
        "b": {
          "extension": "jpg",
          "height": 768,
          "mimetype": "image/jpeg",
          "secret": "RGcomJg4wUzWa41nQMBfK2ySKnKi3SAf",
          "width": 965
        },
        "c": {
          "extension": "jpg",
          "height": 600,
          "mimetype": "image/jpeg",
          "secret": "RGcomJg4wUzWa41nQMBfK2ySKnKi3SAf",
          "width": 754
        },
        "dc": {
          "extension": "jpg",
          "height": 600,
          "mimetype": "image/jpeg",
          "secret": "RGcomJg4wUzWa41nQMBfK2ySKnKi3SAf",
          "width": 754
        },
        "ds": {
          "extension": "jpg",
          "height": 320,
          "mimetype": "image/jpeg",
          "secret": "RGcomJg4wUzWa41nQMBfK2ySKnKi3SAf",
          "width": 320
        },
        "k": {
          "extension": "jpg",
          "height": 1536,
          "mimetype": "image/jpeg",
          "secret": "RGcomJg4wUzWa41nQMBfK2ySKnKi3SAf",
          "width": 1931
        },
        "n": {
          "extension": "jpg",
          "height": 240,
          "mimetype": "image/jpeg",
          "secret": "RGcomJg4wUzWa41nQMBfK2ySKnKi3SAf",
          "width": 301
        },
        "o": {
          "extension": "jpg",
          "height": 1667,
          "mimetype": "image/jpeg",
          "secret": "aejmuVe1RncQCIJaT1ohoeJzSqFe5sk3",
          "width": 2096
        },
        "s": {
          "extension": "jpg",
          "height": 320,
          "mimetype": "image/jpeg",
          "secret": "RGcomJg4wUzWa41nQMBfK2ySKnKi3SAf",
          "width": 320
        },
        "z": {
          "extension": "jpg",
          "height": 480,
          "mimetype": "image/jpeg",
          "secret": "RGcomJg4wUzWa41nQMBfK2ySKnKi3SAf",
          "width": 603
        }
      }
    },
    "media:uri_template": "https://millsfield.sfomuseum.org/media/152/785/848/7/1527858487_{secret}_{label}.{extention}",
    "sfomuseum:filename": "2002.094.022.tif",
    "sfomuseum:image_index": 0,
    "sfomuseum:placetype": "image",
    "sfomuseum:primary_image": 1,
    "wof:depicts": [
      1511923651
    ],
    "wof:name": "butter dish: CP Air (Canadian Pacific Airlines)",
    "wof:placetype": "media"
  },
  "geometry": {"coordinates":[-122.386155,37.616358],"type":"Point"}
}
