{
  "type": "Feature",
  "properties": {
    "iso:country": "XX",
    "media:fingerprint": "8cfd9f69f2a4af0d4d3d116fe52e5067727c94a6",
    "media:imagehash_avg": "a:e7818181819f8ff7",
    "media:imagehash_diff": "d:0f4f0f5f3b333b0f",
    "media:medium": "image",
    "media:mimetype": "image/tiff",
    "media:properties": {
      "colours": [
        {
          "hex": "#931607",
          "name": "#931607",
          "reference": "vibrant"
        }, 
        {
          "hex": "#d7c39a",
          "name": "#d7c39a",
          "reference": "vibrant"
        }, 
        {
          "hex": "#643425",
          "name": "#643425",
          "reference": "vibrant"
        }, 
        {
          "hex": "#a58764",
          "name": "#a58764",
          "reference": "vibrant"
        }, 
        {
          "hex": "#d8c8a8",
          "name": "#d8c8a8",
          "reference": "vibrant"
        }
      ],
      "sizes": {
        "b": {
          "extension": "jpg",
          "height": 768,
          "mimetype": "image/jpeg",
          "secret": "UOnsKDIwVxWe8Nj6dCaFW0UrLwVsfTYI",
          "width": 370
        },
        "c": {
          "extension": "jpg",
          "height": 600,
          "mimetype": "image/jpeg",
          "secret": "UOnsKDIwVxWe8Nj6dCaFW0UrLwVsfTYI",
          "width": 289
        },
        "dc": {
          "extension": "jpg",
          "height": 600,
          "mimetype": "image/jpeg",
          "secret": "UOnsKDIwVxWe8Nj6dCaFW0UrLwVsfTYI",
          "width": 289
        },
        "ds": {
          "extension": "jpg",
          "height": 320,
          "mimetype": "image/jpeg",
          "secret": "UOnsKDIwVxWe8Nj6dCaFW0UrLwVsfTYI",
          "width": 320
        },
        "k": {
          "extension": "jpg",
          "height": 1536,
          "mimetype": "image/jpeg",
          "secret": "UOnsKDIwVxWe8Nj6dCaFW0UrLwVsfTYI",
          "width": 740
        },
        "n": {
          "extension": "jpg",
          "height": 240,
          "mimetype": "image/jpeg",
          "secret": "UOnsKDIwVxWe8Nj6dCaFW0UrLwVsfTYI",
          "width": 115
        },
        "o": {
          "extension": "jpg",
          "height": 3160,
          "mimetype": "image/jpeg",
          "secret": "ETL5YTUfiNhpIcFGQ8DVJb453TjM7Iah",
          "width": 1524
        },
        "s": {
          "extension": "jpg",
          "height": 320,
          "mimetype": "image/jpeg",
          "secret": "UOnsKDIwVxWe8Nj6dCaFW0UrLwVsfTYI",
          "width": 320
        },
        "z": {
          "extension": "jpg",
          "height": 480,
          "mimetype": "image/jpeg",
          "secret": "UOnsKDIwVxWe8Nj6dCaFW0UrLwVsfTYI",
          "width": 231
        }
      }
    },
    "media:uri_template": "https://millsfield.sfomuseum.org/media/152/781/966/7/1527819667_{secret}_{label}.{extention}",
    "sfomuseum:filename": "31048.tif",
    "sfomuseum:image_index": 5,
    "sfomuseum:placetype": "image",
    "sfomuseum:primary_image": 1,
    "wof:depicts": [
      1511930229
    ],
    "wof:name": "flight information packet: TWA (Trans World Airlines), Lockheed L-049 Constellation, Boeing 377",
    "wof:placetype": "media"
  },
  "geometry": {"coordinates":[-122.386155,37.616358],"type":"Point"}
}
