{
  "type": "Feature",
  "properties": {
    "iso:country": "XX",
    "media:fingerprint": "29fe9589b04aeb7becc7730b8166051592369a0a",
    "media:imagehash_avg": "a:f8f8d080f1fee47c",
    "media:imagehash_diff": "d:c18123278b8c8cc8",
    "media:medium": "image",
    "media:mimetype": "image/tiff",
    "media:properties": {
      "colours": [
        {
          "hex": "#808080",
          "name": "#808080",
          "reference": "vibrant"
        }, 
        {
          "hex": "#b8b8b8",
          "name": "#b8b8b8",
          "reference": "vibrant"
        }, 
        {
          "hex": "#404040",
          "name": "#404040",
          "reference": "vibrant"
        }
      ],
      "sizes": {
        "b": {
          "extension": "jpg",
          "height": 767,
          "mimetype": "image/jpeg",
          "secret": "lxDQin1eMptRbJr1LEGXkvSwo9wH50YP",
          "width": 978
        },
        "c": {
          "extension": "jpg",
          "height": 600,
          "mimetype": "image/jpeg",
          "secret": "lxDQin1eMptRbJr1LEGXkvSwo9wH50YP",
          "width": 764
        },
        "dc": {
          "extension": "jpg",
          "height": 600,
          "mimetype": "image/jpeg",
          "secret": "lxDQin1eMptRbJr1LEGXkvSwo9wH50YP",
          "width": 764
        },
        "ds": {
          "extension": "jpg",
          "height": 320,
          "mimetype": "image/jpeg",
          "secret": "lxDQin1eMptRbJr1LEGXkvSwo9wH50YP",
          "width": 320
        },
        "k": {
          "extension": "jpg",
          "height": 1535,
          "mimetype": "image/jpeg",
          "secret": "lxDQin1eMptRbJr1LEGXkvSwo9wH50YP",
          "width": 1957
        },
        "n": {
          "extension": "jpg",
          "height": 240,
          "mimetype": "image/jpeg",
          "secret": "lxDQin1eMptRbJr1LEGXkvSwo9wH50YP",
          "width": 305
        },
        "o": {
          "extension": "jpg",
          "height": 2140,
          "mimetype": "image/jpeg",
          "secret": "htJacSxkU8Xmk73iqzKFz8dK5A4s8g1Q",
          "width": 2727
        },
        "s": {
          "extension": "jpg",
          "height": 320,
          "mimetype": "image/jpeg",
          "secret": "lxDQin1eMptRbJr1LEGXkvSwo9wH50YP",
          "width": 320
        },
        "z": {
          "extension": "jpg",
          "height": 480,
          "mimetype": "image/jpeg",
          "secret": "lxDQin1eMptRbJr1LEGXkvSwo9wH50YP",
          "width": 611
        }
      }
    },
    "media:uri_template": "https://millsfield.sfomuseum.org/media/152/782/279/3/1527822793_{secret}_{label}.{extention}",
    "sfomuseum:filename": "41076.tif",
    "sfomuseum:image_index": 5,
    "sfomuseum:placetype": "image",
    "sfomuseum:primary_image": 1,
    "wof:depicts": [
      1511944687
    ],
    "wof:name": "negative: San Francisco International Airport (SFO), architectural diagram",
    "wof:placetype": "media"
  },
  "geometry": {"coordinates":[-122.386155,37.616358],"type":"Point"}
}
