{
  "type": "Feature",
  "properties": {
    "media:fingerprint": "2263194093eeab46a9b1f4c136568c26a1e7fd99",
    "media:imagehash_avg": "a:ffffdfdf03000000",
    "media:imagehash_diff": "d:5e9cbc3c66e7cccd",
    "media:mimetype": "image/tiff",
    "media:properties": {
      "colours": [
        {
          "hex": "#808080",
          "name": "#808080",
          "reference": "vibrant"
        },
        {
          "hex": "#c8c8c8",
          "name": "#c8c8c8",
          "reference": "vibrant"
        },
        {
          "hex": "#404040",
          "name": "#404040",
          "reference": "vibrant"
        }
      ],
      "sizes": {
        "b": {
          "extension": "jpg",
          "height": 768,
          "mimetype": "image/jpeg",
          "secret": "Fi3ghMY41WGdDnpwY0LDGUvx3smKODEu",
          "width": 601
        },
        "c": {
          "extension": "jpg",
          "height": 600,
          "mimetype": "image/jpeg",
          "secret": "Fi3ghMY41WGdDnpwY0LDGUvx3smKODEu",
          "width": 470
        },
        "dc": {
          "extension": "jpg",
          "height": 600,
          "mimetype": "image/jpeg",
          "secret": "Fi3ghMY41WGdDnpwY0LDGUvx3smKODEu",
          "width": 470
        },
        "ds": {
          "extension": "jpg",
          "height": 320,
          "mimetype": "image/jpeg",
          "secret": "Fi3ghMY41WGdDnpwY0LDGUvx3smKODEu",
          "width": 320
        },
        "k": {
          "extension": "jpg",
          "height": 1536,
          "mimetype": "image/jpeg",
          "secret": "Fi3ghMY41WGdDnpwY0LDGUvx3smKODEu",
          "width": 1203
        },
        "n": {
          "extension": "jpg",
          "height": 240,
          "mimetype": "image/jpeg",
          "secret": "Fi3ghMY41WGdDnpwY0LDGUvx3smKODEu",
          "width": 188
        },
        "o": {
          "extension": "jpg",
          "height": 2665,
          "mimetype": "image/jpeg",
          "secret": "nhXerL6kvLVCka1VFR4xhl8wxNY8gzio",
          "width": 2088
        },
        "s": {
          "extension": "jpg",
          "height": 320,
          "mimetype": "image/jpeg",
          "secret": "Fi3ghMY41WGdDnpwY0LDGUvx3smKODEu",
          "width": 320
        },
        "z": {
          "extension": "jpg",
          "height": 480,
          "mimetype": "image/jpeg",
          "secret": "Fi3ghMY41WGdDnpwY0LDGUvx3smKODEu",
          "width": 376
        }
      }
    },
    "media:uri_template": "https://static.sfomuseum.org/media/174/651/208/1/1746512081_{secret}_{label}.{extention}",
    "sfomuseum:filename": "45899.tif",
    "sfomuseum:image_index": 0,
    "sfomuseum:image_type": "studio",
    "sfomuseum:placetype": "image",
    "sfomuseum:primary_image": 1,
    "wof:depicts": [
      1159285393,
      1729563713,
      1159287531
    ],
    "wof:name": "negative: TWA (Trans World Airlines), William T. Leslie",
    "wof:placetype": "custom",
    "wof:placetype_alt": "image"
  },
  "geometry": {"coordinates":[-122.386155,37.616357],"type":"Point"}
}
