{
  "type": "Feature",
  "properties": {
    "iso:country": "XX",
    "media:fingerprint": "9b3ad0a25e7e0390423a1d435e7fab31ecb85019",
    "media:imagehash_avg": "a:ffffffff03000070",
    "media:imagehash_diff": "d:f079fa811f1c9cc0",
    "media:medium": "image",
    "media:mimetype": "image/tiff",
    "media:properties": {
      "colours": [
        {
          "hex": "#808080",
          "name": "#808080",
          "reference": "vibrant"
        }, 
        {
          "hex": "#b7b7b7",
          "name": "#b7b7b7",
          "reference": "vibrant"
        }, 
        {
          "hex": "#474747",
          "name": "#474747",
          "reference": "vibrant"
        }
      ],
      "sizes": {
        "b": {
          "extension": "jpg",
          "height": 647,
          "mimetype": "image/jpeg",
          "secret": "IoEjNt8T4kRt4NUM9iuhTxiLTF3KvWHP",
          "width": 1024
        },
        "c": {
          "extension": "jpg",
          "height": 505,
          "mimetype": "image/jpeg",
          "secret": "IoEjNt8T4kRt4NUM9iuhTxiLTF3KvWHP",
          "width": 800
        },
        "dc": {
          "extension": "jpg",
          "height": 505,
          "mimetype": "image/jpeg",
          "secret": "IoEjNt8T4kRt4NUM9iuhTxiLTF3KvWHP",
          "width": 800
        },
        "ds": {
          "extension": "jpg",
          "height": 320,
          "mimetype": "image/jpeg",
          "secret": "IoEjNt8T4kRt4NUM9iuhTxiLTF3KvWHP",
          "width": 320
        },
        "k": {
          "extension": "jpg",
          "height": 1294,
          "mimetype": "image/jpeg",
          "secret": "IoEjNt8T4kRt4NUM9iuhTxiLTF3KvWHP",
          "width": 2048
        },
        "n": {
          "extension": "jpg",
          "height": 202,
          "mimetype": "image/jpeg",
          "secret": "IoEjNt8T4kRt4NUM9iuhTxiLTF3KvWHP",
          "width": 320
        },
        "o": {
          "extension": "jpg",
          "height": 1380,
          "mimetype": "image/jpeg",
          "secret": "NzYKxVLsRbDNChvxkbyHkrmEoCN0vuHI",
          "width": 2183
        },
        "s": {
          "extension": "jpg",
          "height": 320,
          "mimetype": "image/jpeg",
          "secret": "IoEjNt8T4kRt4NUM9iuhTxiLTF3KvWHP",
          "width": 320
        },
        "z": {
          "extension": "jpg",
          "height": 404,
          "mimetype": "image/jpeg",
          "secret": "IoEjNt8T4kRt4NUM9iuhTxiLTF3KvWHP",
          "width": 640
        }
      }
    },
    "media:uri_template": "https://millsfield.sfomuseum.org/media/152/782/090/7/1527820907_{secret}_{label}.{extention}",
    "sfomuseum:filename": "33234.tif",
    "sfomuseum:image_index": 5,
    "sfomuseum:placetype": "image",
    "sfomuseum:primary_image": 1,
    "wof:depicts": [
      1511931347
    ],
    "wof:name": "photograph: Pan American Airways, Sikorsky S-40",
    "wof:placetype": "media"
  },
  "geometry": {"coordinates":[-122.386155,37.616358],"type":"Point"}
}
