{
  "type": "Feature",
  "properties": {
    "iso:country": "XX",
    "media:fingerprint": "b5b009bfaec377721861f99f83b8bf8476d90cc6",
    "media:imagehash_avg": "a:a1008080fdffffff",
    "media:imagehash_diff": "d:2d25450301e18181",
    "media:medium": "image",
    "media:mimetype": "image/tiff",
    "media:properties": {
      "colours": [
        {
          "hex": "#dc612c",
          "name": "#dc612c",
          "reference": "vibrant"
        },
        {
          "hex": "#dfa350",
          "name": "#dfa350",
          "reference": "vibrant"
        },
        {
          "hex": "#aaa34e",
          "name": "#aaa34e",
          "reference": "vibrant"
        },
        {
          "hex": "#cab9b3",
          "name": "#cab9b3",
          "reference": "vibrant"
        },
        {
          "hex": "#45403e",
          "name": "#45403e",
          "reference": "vibrant"
        }
      ],
      "sizes": {
        "b": {
          "extension": "jpg",
          "height": 768,
          "mimetype": "image/jpeg",
          "secret": "T6r2I8L7w08JWUuq5vDEMXvqxquoMgNn",
          "width": 536
        },
        "c": {
          "extension": "jpg",
          "height": 600,
          "mimetype": "image/jpeg",
          "secret": "T6r2I8L7w08JWUuq5vDEMXvqxquoMgNn",
          "width": 418
        },
        "dc": {
          "extension": "jpg",
          "height": 600,
          "mimetype": "image/jpeg",
          "secret": "T6r2I8L7w08JWUuq5vDEMXvqxquoMgNn",
          "width": 418
        },
        "ds": {
          "extension": "jpg",
          "height": 320,
          "mimetype": "image/jpeg",
          "secret": "T6r2I8L7w08JWUuq5vDEMXvqxquoMgNn",
          "width": 320
        },
        "k": {
          "extension": "jpg",
          "height": 1536,
          "mimetype": "image/jpeg",
          "secret": "T6r2I8L7w08JWUuq5vDEMXvqxquoMgNn",
          "width": 1072
        },
        "n": {
          "extension": "jpg",
          "height": 240,
          "mimetype": "image/jpeg",
          "secret": "T6r2I8L7w08JWUuq5vDEMXvqxquoMgNn",
          "width": 167
        },
        "o": {
          "extension": "jpg",
          "height": 3037,
          "mimetype": "image/jpeg",
          "secret": "IE5NEj2LsAxjPqQnB4SkERD0gjvSVr2m",
          "width": 2120
        },
        "s": {
          "extension": "jpg",
          "height": 320,
          "mimetype": "image/jpeg",
          "secret": "T6r2I8L7w08JWUuq5vDEMXvqxquoMgNn",
          "width": 320
        },
        "z": {
          "extension": "jpg",
          "height": 480,
          "mimetype": "image/jpeg",
          "secret": "T6r2I8L7w08JWUuq5vDEMXvqxquoMgNn",
          "width": 335
        }
      }
    },
    "media:uri_template": "https://static.sfomuseum.org/media/152/784/777/5/1527847775_{secret}_{label}.{extention}",
    "sfomuseum:filename": "71983.tif",
    "sfomuseum:image_index": 5,
    "sfomuseum:image_type": "studio",
    "sfomuseum:placetype": "image",
    "sfomuseum:primary_image": 1,
    "wof:depicts": [
      1159284989,
      1511921433,
      1159286839
    ],
    "wof:name": "menu: Pan American World Airways, First Class",
    "wof:placetype": "custom",
    "wof:placetype_alt": "image"
  },
  "geometry": {"coordinates":[-122.386155,37.616358],"type":"Point"}
}
