{
  "type": "Feature",
  "properties": {
    "iso:country": "XX",
    "media:fingerprint": "e88e974775f4ce9b56a487e1b7dc41d3716b71f4",
    "media:imagehash_avg": "a:ffffffc5818180e1",
    "media:imagehash_diff": "d:1f773b2b29190901",
    "media:medium": "image",
    "media:mimetype": "image/tiff",
    "media:properties": {
      "colours": [
        {
          "hex": "#b09858",
          "name": "#b09858",
          "reference": "vibrant"
        },
        {
          "hex": "#d8c8a5",
          "name": "#d8c8a5",
          "reference": "vibrant"
        },
        {
          "hex": "#634c19",
          "name": "#634c19",
          "reference": "vibrant"
        },
        {
          "hex": "#a89858",
          "name": "#a89858",
          "reference": "vibrant"
        },
        {
          "hex": "#dad1ac",
          "name": "#dad1ac",
          "reference": "vibrant"
        }
      ],
      "sizes": {
        "b": {
          "extension": "jpg",
          "height": 766,
          "mimetype": "image/jpeg",
          "secret": "2VDITqUKYAXslt89sLmyKw5oZGzeW3Lg",
          "width": 1024
        },
        "c": {
          "extension": "jpg",
          "height": 598,
          "mimetype": "image/jpeg",
          "secret": "2VDITqUKYAXslt89sLmyKw5oZGzeW3Lg",
          "width": 800
        },
        "dc": {
          "extension": "jpg",
          "height": 598,
          "mimetype": "image/jpeg",
          "secret": "2VDITqUKYAXslt89sLmyKw5oZGzeW3Lg",
          "width": 800
        },
        "ds": {
          "extension": "jpg",
          "height": 320,
          "mimetype": "image/jpeg",
          "secret": "2VDITqUKYAXslt89sLmyKw5oZGzeW3Lg",
          "width": 320
        },
        "k": {
          "extension": "jpg",
          "height": 1533,
          "mimetype": "image/jpeg",
          "secret": "2VDITqUKYAXslt89sLmyKw5oZGzeW3Lg",
          "width": 2048
        },
        "n": {
          "extension": "jpg",
          "height": 239,
          "mimetype": "image/jpeg",
          "secret": "2VDITqUKYAXslt89sLmyKw5oZGzeW3Lg",
          "width": 320
        },
        "o": {
          "extension": "jpg",
          "height": 983,
          "mimetype": "image/jpeg",
          "secret": "zL2m1XczGsGkwxJwUSMNo8bOUVC6hYfC",
          "width": 1313
        },
        "s": {
          "extension": "jpg",
          "height": 320,
          "mimetype": "image/jpeg",
          "secret": "2VDITqUKYAXslt89sLmyKw5oZGzeW3Lg",
          "width": 320
        },
        "z": {
          "extension": "jpg",
          "height": 479,
          "mimetype": "image/jpeg",
          "secret": "2VDITqUKYAXslt89sLmyKw5oZGzeW3Lg",
          "width": 640
        }
      }
    },
    "media:uri_template": "https://static.sfomuseum.org/media/152/785/549/3/1527855493_{secret}_{label}.{extention}",
    "sfomuseum:filename": "2010.174.244.tif",
    "sfomuseum:image_index": 5,
    "sfomuseum:image_type": "studio",
    "sfomuseum:placetype": "image",
    "sfomuseum:primary_image": 1,
    "wof:depicts": [
      1511942251
    ],
    "wof:name": "photograph: San Francisco Bay Area, three men in field",
    "wof:placetype": "custom",
    "wof:placetype_alt": "image"
  },
  "geometry": {"coordinates":[-122.386155,37.616358],"type":"Point"}
}
