{
  "type": "Feature",
  "properties": {
    "iso:country": "XX",
    "media:fingerprint": "4cf5b00b3f7a1168d24c2a2edc9b9ac28bc0958c",
    "media:imagehash_avg": "a:ff8383838387ffff",
    "media:imagehash_diff": "d:6b0f3f2f2f2f5b47",
    "media:medium": "image",
    "media:mimetype": "image/tiff",
    "media:properties": {
      "colours": [
        {
          "hex": "#cd4348",
          "name": "#cd4348",
          "reference": "vibrant"
        }, 
        {
          "hex": "#d87376",
          "name": "#d87376",
          "reference": "vibrant"
        }, 
        {
          "hex": "#686c8d",
          "name": "#686c8d",
          "reference": "vibrant"
        }, 
        {
          "hex": "#c5c1b7",
          "name": "#c5c1b7",
          "reference": "vibrant"
        }, 
        {
          "hex": "#3b406b",
          "name": "#3b406b",
          "reference": "vibrant"
        }
      ],
      "sizes": {
        "b": {
          "extension": "jpg",
          "height": 768,
          "mimetype": "image/jpeg",
          "secret": "VAJDM3Goe7WtdtVz0TtUuX7OVKZsnNUl",
          "width": 526
        },
        "c": {
          "extension": "jpg",
          "height": 600,
          "mimetype": "image/jpeg",
          "secret": "VAJDM3Goe7WtdtVz0TtUuX7OVKZsnNUl",
          "width": 411
        },
        "dc": {
          "extension": "jpg",
          "height": 600,
          "mimetype": "image/jpeg",
          "secret": "VAJDM3Goe7WtdtVz0TtUuX7OVKZsnNUl",
          "width": 411
        },
        "ds": {
          "extension": "jpg",
          "height": 320,
          "mimetype": "image/jpeg",
          "secret": "VAJDM3Goe7WtdtVz0TtUuX7OVKZsnNUl",
          "width": 320
        },
        "k": {
          "extension": "jpg",
          "height": 1536,
          "mimetype": "image/jpeg",
          "secret": "VAJDM3Goe7WtdtVz0TtUuX7OVKZsnNUl",
          "width": 1052
        },
        "n": {
          "extension": "jpg",
          "height": 240,
          "mimetype": "image/jpeg",
          "secret": "VAJDM3Goe7WtdtVz0TtUuX7OVKZsnNUl",
          "width": 164
        },
        "o": {
          "extension": "jpg",
          "height": 2724,
          "mimetype": "image/jpeg",
          "secret": "qUvc8zYbTO5E7nC4AziLi3yiVcOVhto7",
          "width": 1866
        },
        "s": {
          "extension": "jpg",
          "height": 320,
          "mimetype": "image/jpeg",
          "secret": "VAJDM3Goe7WtdtVz0TtUuX7OVKZsnNUl",
          "width": 320
        },
        "z": {
          "extension": "jpg",
          "height": 480,
          "mimetype": "image/jpeg",
          "secret": "VAJDM3Goe7WtdtVz0TtUuX7OVKZsnNUl",
          "width": 328
        }
      }
    },
    "media:uri_template": "https://millsfield.sfomuseum.org/media/152/782/352/5/1527823525_{secret}_{label}.{extention}",
    "sfomuseum:filename": "41625.tif",
    "sfomuseum:image_index": 5,
    "sfomuseum:placetype": "image",
    "sfomuseum:primary_image": 0,
    "wof:depicts": [
      1511908427
    ],
    "wof:name": "airsickness bag: American Airlines",
    "wof:placetype": "media"
  },
  "geometry": {"coordinates":[-122.386155,37.616358],"type":"Point"}
}
