{
  "type": "Feature",
  "properties": {
    "date:cessation_lower": "1960-01-01",
    "date:cessation_upper": "1969-12-31",
    "date:inception_lower": "1960-01-01",
    "date:inception_upper": "1969-12-31",
    "iso:country": "XX",
    "media:fingerprint": "bec8a9a0515a5a283e58bc8c1868b8abe5ccc4e9",
    "media:imagehash_avg": "a:ffff9fbf8c060000",
    "media:imagehash_diff": "d:f0e030503884b6f0",
    "media:mimetype": "image/tiff",
    "media:properties": {
      "colours": [
        {
          "hex": "#847b75",
          "name": "#847b75",
          "reference": "vibrant"
        },
        {
          "hex": "#c1b9ae",
          "name": "#c1b9ae",
          "reference": "vibrant"
        },
        {
          "hex": "#4e4946",
          "name": "#4e4946",
          "reference": "vibrant"
        }
      ],
      "sizes": {
        "b": {
          "extension": "jpg",
          "height": 768,
          "mimetype": "image/jpeg",
          "secret": "FO92BhFIa73D9x1koNgQAS4okPabVxz3",
          "width": 965
        },
        "c": {
          "extension": "jpg",
          "height": 600,
          "mimetype": "image/jpeg",
          "secret": "FO92BhFIa73D9x1koNgQAS4okPabVxz3",
          "width": 753
        },
        "dc": {
          "extension": "jpg",
          "height": 600,
          "mimetype": "image/jpeg",
          "secret": "FO92BhFIa73D9x1koNgQAS4okPabVxz3",
          "width": 753
        },
        "ds": {
          "extension": "jpg",
          "height": 320,
          "mimetype": "image/jpeg",
          "secret": "FO92BhFIa73D9x1koNgQAS4okPabVxz3",
          "width": 320
        },
        "k": {
          "extension": "jpg",
          "height": 1536,
          "mimetype": "image/jpeg",
          "secret": "FO92BhFIa73D9x1koNgQAS4okPabVxz3",
          "width": 1930
        },
        "n": {
          "extension": "jpg",
          "height": 240,
          "mimetype": "image/jpeg",
          "secret": "FO92BhFIa73D9x1koNgQAS4okPabVxz3",
          "width": 301
        },
        "o": {
          "extension": "jpg",
          "height": 1668,
          "mimetype": "image/jpeg",
          "secret": "l3V5VLTvqFya81gcRuNdEeo3SHR1EMkr",
          "width": 2096
        },
        "s": {
          "extension": "jpg",
          "height": 320,
          "mimetype": "image/jpeg",
          "secret": "FO92BhFIa73D9x1koNgQAS4okPabVxz3",
          "width": 320
        },
        "z": {
          "extension": "jpg",
          "height": 480,
          "mimetype": "image/jpeg",
          "secret": "FO92BhFIa73D9x1koNgQAS4okPabVxz3",
          "width": 603
        }
      }
    },
    "media:uri_template": "https://static.sfomuseum.org/media/176/337/271/1/1763372711_{secret}_{label}.{extention}",
    "sfomuseum:filename": "106975.tif",
    "sfomuseum:image_index": 5,
    "sfomuseum:image_type": "studio",
    "sfomuseum:placetype": "image",
    "sfomuseum:primary_image": 1,
    "wof:depicts": [
      1511927809,
      1159285415,
      1159288779
    ],
    "wof:name": "spoon: United Air Lines",
    "wof:placetype": "custom"
  },
  "geometry": {"coordinates":[-122.386155,37.616357],"type":"Point"}
}
