{
  "type": "Feature",
  "properties": {
    "iso:country": "XX",
    "media:fingerprint": "6999d2ae32dd4042ddc6fcc755be97ddf521385a",
    "media:imagehash_avg": "a:fffe7e26808000c0",
    "media:imagehash_diff": "d:0e90d8d436456183",
    "media:medium": "image",
    "media:mimetype": "image/tiff",
    "media:properties": {
      "colours": [
        {
          "hex": "#808080",
          "name": "#808080",
          "reference": "vibrant"
        }, 
        {
          "hex": "#b8b8b8",
          "name": "#b8b8b8",
          "reference": "vibrant"
        }, 
        {
          "hex": "#404040",
          "name": "#404040",
          "reference": "vibrant"
        }
      ],
      "sizes": {
        "b": {
          "extension": "jpg",
          "height": 768,
          "mimetype": "image/jpeg",
          "secret": "WAys4jZNCc0BEXuHq601cSfqdVDSjbAN",
          "width": 974
        },
        "c": {
          "extension": "jpg",
          "height": 600,
          "mimetype": "image/jpeg",
          "secret": "WAys4jZNCc0BEXuHq601cSfqdVDSjbAN",
          "width": 761
        },
        "dc": {
          "extension": "jpg",
          "height": 600,
          "mimetype": "image/jpeg",
          "secret": "WAys4jZNCc0BEXuHq601cSfqdVDSjbAN",
          "width": 761
        },
        "ds": {
          "extension": "jpg",
          "height": 320,
          "mimetype": "image/jpeg",
          "secret": "WAys4jZNCc0BEXuHq601cSfqdVDSjbAN",
          "width": 320
        },
        "k": {
          "extension": "jpg",
          "height": 1536,
          "mimetype": "image/jpeg",
          "secret": "WAys4jZNCc0BEXuHq601cSfqdVDSjbAN",
          "width": 1949
        },
        "n": {
          "extension": "jpg",
          "height": 240,
          "mimetype": "image/jpeg",
          "secret": "WAys4jZNCc0BEXuHq601cSfqdVDSjbAN",
          "width": 304
        },
        "o": {
          "extension": "jpg",
          "height": 2181,
          "mimetype": "image/jpeg",
          "secret": "wsHpMRU8dR0tMfW8gMk09XrzECt03X3z",
          "width": 2768
        },
        "s": {
          "extension": "jpg",
          "height": 320,
          "mimetype": "image/jpeg",
          "secret": "WAys4jZNCc0BEXuHq601cSfqdVDSjbAN",
          "width": 320
        },
        "z": {
          "extension": "jpg",
          "height": 480,
          "mimetype": "image/jpeg",
          "secret": "WAys4jZNCc0BEXuHq601cSfqdVDSjbAN",
          "width": 609
        }
      }
    },
    "media:uri_template": "https://millsfield.sfomuseum.org/media/152/782/700/1/1527827001_{secret}_{label}.{extention}",
    "sfomuseum:filename": "43892.tif",
    "sfomuseum:image_index": 5,
    "sfomuseum:placetype": "image",
    "sfomuseum:primary_image": 1,
    "wof:depicts": [
      1511948039
    ],
    "wof:name": "negative: San Francisco International Airport (SFO), image of plans for California State Fair exhibit",
    "wof:placetype": "media"
  },
  "geometry": {"coordinates":[-122.386155,37.616358],"type":"Point"}
}
