{
  "type": "Feature",
  "properties": {
    "iso:country": "XX",
    "media:fingerprint": "7f47b6f0471c2895340e6c98625853d1361ff1d6",
    "media:imagehash_avg": "a:ffffffc1008103b7",
    "media:imagehash_diff": "d:7d7d5f1f31474767",
    "media:medium": "image",
    "media:mimetype": "image/tiff",
    "media:properties": {
      "colours": [
        {
          "hex": "#efe8cb",
          "name": "#efe8cb",
          "reference": "vibrant"
        },
        {
          "hex": "#1a190c",
          "name": "#1a190c",
          "reference": "vibrant"
        },
        {
          "hex": "#9b9268",
          "name": "#9b9268",
          "reference": "vibrant"
        },
        {
          "hex": "#d1c8a8",
          "name": "#d1c8a8",
          "reference": "vibrant"
        },
        {
          "hex": "#504a38",
          "name": "#504a38",
          "reference": "vibrant"
        }
      ],
      "sizes": {
        "b": {
          "extension": "jpg",
          "height": 768,
          "mimetype": "image/jpeg",
          "secret": "HNXKZYfIrbFE8M8NciRfUfuN1EKP1ty8",
          "width": 997
        },
        "c": {
          "extension": "jpg",
          "height": 600,
          "mimetype": "image/jpeg",
          "secret": "HNXKZYfIrbFE8M8NciRfUfuN1EKP1ty8",
          "width": 779
        },
        "dc": {
          "extension": "jpg",
          "height": 600,
          "mimetype": "image/jpeg",
          "secret": "HNXKZYfIrbFE8M8NciRfUfuN1EKP1ty8",
          "width": 779
        },
        "ds": {
          "extension": "jpg",
          "height": 320,
          "mimetype": "image/jpeg",
          "secret": "HNXKZYfIrbFE8M8NciRfUfuN1EKP1ty8",
          "width": 320
        },
        "k": {
          "extension": "jpg",
          "height": 1536,
          "mimetype": "image/jpeg",
          "secret": "HNXKZYfIrbFE8M8NciRfUfuN1EKP1ty8",
          "width": 1994
        },
        "n": {
          "extension": "jpg",
          "height": 240,
          "mimetype": "image/jpeg",
          "secret": "HNXKZYfIrbFE8M8NciRfUfuN1EKP1ty8",
          "width": 311
        },
        "o": {
          "extension": "jpg",
          "height": 1012,
          "mimetype": "image/jpeg",
          "secret": "cBX6OJ2aHOhaXlY81UWhf4Po2pjeCzTh",
          "width": 1314
        },
        "s": {
          "extension": "jpg",
          "height": 320,
          "mimetype": "image/jpeg",
          "secret": "HNXKZYfIrbFE8M8NciRfUfuN1EKP1ty8",
          "width": 320
        },
        "z": {
          "extension": "jpg",
          "height": 480,
          "mimetype": "image/jpeg",
          "secret": "HNXKZYfIrbFE8M8NciRfUfuN1EKP1ty8",
          "width": 623
        }
      }
    },
    "media:uri_template": "https://static.sfomuseum.org/media/152/785/555/1/1527855551_{secret}_{label}.{extention}",
    "sfomuseum:filename": "2010.174.271.tif",
    "sfomuseum:image_index": 5,
    "sfomuseum:image_type": "studio",
    "sfomuseum:placetype": "image",
    "sfomuseum:primary_image": 1,
    "wof:depicts": [
      1511942397
    ],
    "wof:name": "photograph: San Francisco Bay Area aerial, Marina District",
    "wof:placetype": "custom",
    "wof:placetype_alt": "image"
  },
  "geometry": {"coordinates":[-122.386155,37.616358],"type":"Point"}
}
