{
  "type": "Feature",
  "properties": {
    "iso:country": "XX",
    "media:fingerprint": "44b66623b62e3407fe7d9dbea20d8cf58a347413",
    "media:imagehash_avg": "a:ef8331797078787c",
    "media:imagehash_diff": "d:0f2763e3c3c1c1d0",
    "media:medium": "image",
    "media:mimetype": "image/tiff",
    "media:properties": {
      "colours": [
        {
          "hex": "#e67f0e",
          "name": "#e67f0e",
          "reference": "vibrant"
        },
        {
          "hex": "#e05b8b",
          "name": "#e05b8b",
          "reference": "vibrant"
        },
        {
          "hex": "#b21205",
          "name": "#b21205",
          "reference": "vibrant"
        },
        {
          "hex": "#4c7c9c",
          "name": "#4c7c9c",
          "reference": "vibrant"
        },
        {
          "hex": "#afb8a1",
          "name": "#afb8a1",
          "reference": "vibrant"
        }
      ],
      "sizes": {
        "b": {
          "extension": "jpg",
          "height": 768,
          "mimetype": "image/jpeg",
          "secret": "E2Kc53seFXIfYgkJDmfYLp8hnzpKr6LJ",
          "width": 557
        },
        "c": {
          "extension": "jpg",
          "height": 600,
          "mimetype": "image/jpeg",
          "secret": "E2Kc53seFXIfYgkJDmfYLp8hnzpKr6LJ",
          "width": 435
        },
        "dc": {
          "extension": "jpg",
          "height": 600,
          "mimetype": "image/jpeg",
          "secret": "E2Kc53seFXIfYgkJDmfYLp8hnzpKr6LJ",
          "width": 435
        },
        "ds": {
          "extension": "jpg",
          "height": 320,
          "mimetype": "image/jpeg",
          "secret": "E2Kc53seFXIfYgkJDmfYLp8hnzpKr6LJ",
          "width": 320
        },
        "k": {
          "extension": "jpg",
          "height": 1536,
          "mimetype": "image/jpeg",
          "secret": "E2Kc53seFXIfYgkJDmfYLp8hnzpKr6LJ",
          "width": 1115
        },
        "n": {
          "extension": "jpg",
          "height": 240,
          "mimetype": "image/jpeg",
          "secret": "E2Kc53seFXIfYgkJDmfYLp8hnzpKr6LJ",
          "width": 174
        },
        "o": {
          "extension": "jpg",
          "height": 2101,
          "mimetype": "image/jpeg",
          "secret": "os2OA6WcP1jOvJtDpoSTQKzkX1aUCWuL",
          "width": 1526
        },
        "s": {
          "extension": "jpg",
          "height": 320,
          "mimetype": "image/jpeg",
          "secret": "E2Kc53seFXIfYgkJDmfYLp8hnzpKr6LJ",
          "width": 320
        },
        "z": {
          "extension": "jpg",
          "height": 480,
          "mimetype": "image/jpeg",
          "secret": "E2Kc53seFXIfYgkJDmfYLp8hnzpKr6LJ",
          "width": 348
        }
      }
    },
    "media:uri_template": "https://static.sfomuseum.org/media/152/784/807/7/1527848077_{secret}_{label}.{extention}",
    "sfomuseum:filename": "2002113305_front.tif",
    "sfomuseum:image_index": 5,
    "sfomuseum:image_type": "studio",
    "sfomuseum:placetype": "image",
    "sfomuseum:primary_image": 1,
    "wof:depicts": [
      1159285393,
      1511925155
    ],
    "wof:name": "menu: TWA (Trans World Airlines), Ambassador (Business) Class",
    "wof:placetype": "custom",
    "wof:placetype_alt": "image"
  },
  "geometry": {"coordinates":[-122.386155,37.616358],"type":"Point"}
}
