{
  "type": "Feature",
  "properties": {
    "iso:country": "XX",
    "media:fingerprint": "bf9c46eae6da53baecb45cc6c14eb836925d0eb8",
    "media:imagehash_avg": "a:10f8b13fbfbbdf01",
    "media:imagehash_diff": "d:e3e1636d63533253",
    "media:medium": "image",
    "media:mimetype": "image/tiff",
    "media:properties": {
      "colours": [
        {
          "hex": "#e52814",
          "name": "#e52814",
          "reference": "vibrant"
        }, 
        {
          "hex": "#e3b79f",
          "name": "#e3b79f",
          "reference": "vibrant"
        }, 
        {
          "hex": "#d42110",
          "name": "#d42110",
          "reference": "vibrant"
        }, 
        {
          "hex": "#64709b",
          "name": "#64709b",
          "reference": "vibrant"
        }, 
        {
          "hex": "#c5bbad",
          "name": "#c5bbad",
          "reference": "vibrant"
        }
      ],
      "sizes": {
        "b": {
          "extension": "jpg",
          "height": 460,
          "mimetype": "image/jpeg",
          "secret": "ZrUPfLPQ6oPbymuwUXMVQyGXuL6PYNIh",
          "width": 1024
        },
        "c": {
          "extension": "jpg",
          "height": 359,
          "mimetype": "image/jpeg",
          "secret": "ZrUPfLPQ6oPbymuwUXMVQyGXuL6PYNIh",
          "width": 800
        },
        "dc": {
          "extension": "jpg",
          "height": 359,
          "mimetype": "image/jpeg",
          "secret": "ZrUPfLPQ6oPbymuwUXMVQyGXuL6PYNIh",
          "width": 800
        },
        "ds": {
          "extension": "jpg",
          "height": 320,
          "mimetype": "image/jpeg",
          "secret": "ZrUPfLPQ6oPbymuwUXMVQyGXuL6PYNIh",
          "width": 320
        },
        "k": {
          "extension": "jpg",
          "height": 921,
          "mimetype": "image/jpeg",
          "secret": "ZrUPfLPQ6oPbymuwUXMVQyGXuL6PYNIh",
          "width": 2048
        },
        "n": {
          "extension": "jpg",
          "height": 143,
          "mimetype": "image/jpeg",
          "secret": "ZrUPfLPQ6oPbymuwUXMVQyGXuL6PYNIh",
          "width": 320
        },
        "o": {
          "extension": "jpg",
          "height": 1325,
          "mimetype": "image/jpeg",
          "secret": "xC2tBnlbLQTlKujOiyvbKac4PmDKOVG3",
          "width": 2946
        },
        "s": {
          "extension": "jpg",
          "height": 320,
          "mimetype": "image/jpeg",
          "secret": "ZrUPfLPQ6oPbymuwUXMVQyGXuL6PYNIh",
          "width": 320
        },
        "z": {
          "extension": "jpg",
          "height": 287,
          "mimetype": "image/jpeg",
          "secret": "ZrUPfLPQ6oPbymuwUXMVQyGXuL6PYNIh",
          "width": 640
        }
      }
    },
    "media:uri_template": "https://millsfield.sfomuseum.org/media/152/782/909/3/1527829093_{secret}_{label}.{extention}",
    "sfomuseum:filename": "47514.tif",
    "sfomuseum:image_index": 5,
    "sfomuseum:placetype": "image",
    "sfomuseum:primary_image": 1,
    "wof:depicts": [
      1511907245
    ],
    "wof:name": "airmail flight cover: Pan American Airways, first airmail flight, Noumea (New Caledonia) - Auckland route",
    "wof:placetype": "media"
  },
  "geometry": {"coordinates":[-122.386155,37.616358],"type":"Point"}
}
