{
  "type": "Feature",
  "properties": {
    "iso:country": "MM",
    "media:fingerprint": "defb08ce2139b5622be26293987e31c282ce8317",
    "media:imagehash_avg": "a:83f0f0f0f7ff7f8f",
    "media:imagehash_diff": "d:45e1a5a5a487be1b",
    "media:medium": "image",
    "media:mimetype": "image/tiff",
    "media:properties": {
      "colours": [
        {
          "hex": "#e81f22",
          "name": "#e81f22",
          "reference": "vibrant"
        }, 
        {
          "hex": "#f86b6d",
          "name": "#f86b6d",
          "reference": "vibrant"
        }, 
        {
          "hex": "#c60e10",
          "name": "#c60e10",
          "reference": "vibrant"
        }, 
        {
          "hex": "#828971",
          "name": "#828971",
          "reference": "vibrant"
        }, 
        {
          "hex": "#d5d2b6",
          "name": "#d5d2b6",
          "reference": "vibrant"
        }
      ],
      "sizes": {
        "b": {
          "extension": "jpg",
          "height": 588,
          "mimetype": "image/jpeg",
          "secret": "DgKBxsaEZRnNh8lpPYnavY0JolVibH5T",
          "width": 1024
        },
        "c": {
          "extension": "jpg",
          "height": 459,
          "mimetype": "image/jpeg",
          "secret": "DgKBxsaEZRnNh8lpPYnavY0JolVibH5T",
          "width": 800
        },
        "dc": {
          "extension": "jpg",
          "height": 459,
          "mimetype": "image/jpeg",
          "secret": "DgKBxsaEZRnNh8lpPYnavY0JolVibH5T",
          "width": 800
        },
        "ds": {
          "extension": "jpg",
          "height": 320,
          "mimetype": "image/jpeg",
          "secret": "DgKBxsaEZRnNh8lpPYnavY0JolVibH5T",
          "width": 320
        },
        "k": {
          "extension": "jpg",
          "height": 1176,
          "mimetype": "image/jpeg",
          "secret": "DgKBxsaEZRnNh8lpPYnavY0JolVibH5T",
          "width": 2048
        },
        "n": {
          "extension": "jpg",
          "height": 183,
          "mimetype": "image/jpeg",
          "secret": "DgKBxsaEZRnNh8lpPYnavY0JolVibH5T",
          "width": 320
        },
        "o": {
          "extension": "jpg",
          "height": 1158,
          "mimetype": "image/jpeg",
          "secret": "Kxj5Tp2s2hKOdTC6qe6dYw71yko7kRJd",
          "width": 2016
        },
        "s": {
          "extension": "jpg",
          "height": 320,
          "mimetype": "image/jpeg",
          "secret": "DgKBxsaEZRnNh8lpPYnavY0JolVibH5T",
          "width": 320
        },
        "z": {
          "extension": "jpg",
          "height": 367,
          "mimetype": "image/jpeg",
          "secret": "DgKBxsaEZRnNh8lpPYnavY0JolVibH5T",
          "width": 640
        }
      }
    },
    "media:uri_template": "https://millsfield.sfomuseum.org/media/152/782/955/7/1527829557_{secret}_{label}.{extention}",
    "sfomuseum:filename": "48296.tif",
    "sfomuseum:image_index": 5,
    "sfomuseum:placetype": "image",
    "sfomuseum:primary_image": 1,
    "wof:depicts": [
      1511907035
    ],
    "wof:name": "airmail flight cover: Pan American World Airways, Rangoon - Hong Kong route",
    "wof:placetype": "media"
  },
  "geometry": {"coordinates":[-122.386155,37.616358],"type":"Point"}
}
