{
  "type": "Feature",
  "properties": {
    "iso:country": "XX",
    "media:fingerprint": "d541e21f1bbf5aada3f6b3cbdfd6366f814b0779",
    "media:imagehash_avg": "a:fefffffcf8c04000",
    "media:imagehash_diff": "d:20e0c0c040809090",
    "media:medium": "image",
    "media:mimetype": "image/tiff",
    "media:properties": {
      "colours": [
        {
          "hex": "#808080",
          "name": "#808080",
          "reference": "vibrant"
        }, 
        {
          "hex": "#bababa",
          "name": "#bababa",
          "reference": "vibrant"
        }, 
        {
          "hex": "#464646",
          "name": "#464646",
          "reference": "vibrant"
        }
      ],
      "sizes": {
        "b": {
          "extension": "jpg",
          "height": 768,
          "mimetype": "image/jpeg",
          "secret": "cQyHMIv3wAasIt36S6l8Po7JB3CcmAzY",
          "width": 768
        },
        "c": {
          "extension": "jpg",
          "height": 600,
          "mimetype": "image/jpeg",
          "secret": "cQyHMIv3wAasIt36S6l8Po7JB3CcmAzY",
          "width": 600
        },
        "dc": {
          "extension": "jpg",
          "height": 600,
          "mimetype": "image/jpeg",
          "secret": "cQyHMIv3wAasIt36S6l8Po7JB3CcmAzY",
          "width": 600
        },
        "ds": {
          "extension": "jpg",
          "height": 320,
          "mimetype": "image/jpeg",
          "secret": "cQyHMIv3wAasIt36S6l8Po7JB3CcmAzY",
          "width": 320
        },
        "k": {
          "extension": "jpg",
          "height": 1536,
          "mimetype": "image/jpeg",
          "secret": "cQyHMIv3wAasIt36S6l8Po7JB3CcmAzY",
          "width": 1536
        },
        "n": {
          "extension": "jpg",
          "height": 239,
          "mimetype": "image/jpeg",
          "secret": "cQyHMIv3wAasIt36S6l8Po7JB3CcmAzY",
          "width": 239
        },
        "o": {
          "extension": "jpg",
          "height": 2563,
          "mimetype": "image/jpeg",
          "secret": "rc9osqupFU6EMEdJUugzQr3NoXkue5ts",
          "width": 2563
        },
        "s": {
          "extension": "jpg",
          "height": 320,
          "mimetype": "image/jpeg",
          "secret": "cQyHMIv3wAasIt36S6l8Po7JB3CcmAzY",
          "width": 320
        },
        "z": {
          "extension": "jpg",
          "height": 479,
          "mimetype": "image/jpeg",
          "secret": "cQyHMIv3wAasIt36S6l8Po7JB3CcmAzY",
          "width": 479
        }
      }
    },
    "media:uri_template": "https://millsfield.sfomuseum.org/media/152/782/595/7/1527825957_{secret}_{label}.{extention}",
    "sfomuseum:filename": "43412.tif",
    "sfomuseum:image_index": 5,
    "sfomuseum:placetype": "image",
    "sfomuseum:primary_image": 1,
    "wof:depicts": [
      1511946991
    ],
    "wof:name": "negative: San Francisco International Airport (SFO), damage to Pier B",
    "wof:placetype": "media"
  },
  "geometry": {"coordinates":[-122.386155,37.616358],"type":"Point"}
}
