{
  "type": "Feature",
  "properties": {
    "iso:country": "PH",
    "media:fingerprint": "b8dc58e1f20a3797fb70132baec9fc379877ac5f",
    "media:imagehash_avg": "a:0338f8d99fdfdf80",
    "media:imagehash_diff": "d:57f3b1b1b037b62b",
    "media:medium": "image",
    "media:mimetype": "image/tiff",
    "media:properties": {
      "colours": [
        {
          "hex": "#c42717",
          "name": "#c42717",
          "reference": "vibrant"
        }, 
        {
          "hex": "#df6786",
          "name": "#df6786",
          "reference": "vibrant"
        }, 
        {
          "hex": "#9f2011",
          "name": "#9f2011",
          "reference": "vibrant"
        }, 
        {
          "hex": "#a15d4a",
          "name": "#a15d4a",
          "reference": "vibrant"
        }, 
        {
          "hex": "#d9c1bc",
          "name": "#d9c1bc",
          "reference": "vibrant"
        }
      ],
      "sizes": {
        "b": {
          "extension": "jpg",
          "height": 581,
          "mimetype": "image/jpeg",
          "secret": "U3jOl5PEODWRBartPqTRE24Dl1DUGlYy",
          "width": 1024
        },
        "c": {
          "extension": "jpg",
          "height": 454,
          "mimetype": "image/jpeg",
          "secret": "U3jOl5PEODWRBartPqTRE24Dl1DUGlYy",
          "width": 800
        },
        "dc": {
          "extension": "jpg",
          "height": 454,
          "mimetype": "image/jpeg",
          "secret": "U3jOl5PEODWRBartPqTRE24Dl1DUGlYy",
          "width": 800
        },
        "ds": {
          "extension": "jpg",
          "height": 320,
          "mimetype": "image/jpeg",
          "secret": "U3jOl5PEODWRBartPqTRE24Dl1DUGlYy",
          "width": 320
        },
        "k": {
          "extension": "jpg",
          "height": 1162,
          "mimetype": "image/jpeg",
          "secret": "U3jOl5PEODWRBartPqTRE24Dl1DUGlYy",
          "width": 2048
        },
        "n": {
          "extension": "jpg",
          "height": 181,
          "mimetype": "image/jpeg",
          "secret": "U3jOl5PEODWRBartPqTRE24Dl1DUGlYy",
          "width": 320
        },
        "o": {
          "extension": "jpg",
          "height": 1127,
          "mimetype": "image/jpeg",
          "secret": "WBdfHqe0ta4JWFXowTOD1eCQ4w4dX1UW",
          "width": 1985
        },
        "s": {
          "extension": "jpg",
          "height": 320,
          "mimetype": "image/jpeg",
          "secret": "U3jOl5PEODWRBartPqTRE24Dl1DUGlYy",
          "width": 320
        },
        "z": {
          "extension": "jpg",
          "height": 363,
          "mimetype": "image/jpeg",
          "secret": "U3jOl5PEODWRBartPqTRE24Dl1DUGlYy",
          "width": 640
        }
      }
    },
    "media:uri_template": "https://millsfield.sfomuseum.org/media/152/782/935/9/1527829359_{secret}_{label}.{extention}",
    "sfomuseum:filename": "48204.tif",
    "sfomuseum:image_index": 5,
    "sfomuseum:placetype": "image",
    "sfomuseum:primary_image": 1,
    "wof:depicts": [
      1511906947
    ],
    "wof:name": "airmail flight cover: Pan American World Airways, Manila - Bangkok route",
    "wof:placetype": "media"
  },
  "geometry": {"coordinates":[-122.386155,37.616358],"type":"Point"}
}
