{
  "type": "Feature",
  "properties": {
    "iso:country": "XX",
    "media:fingerprint": "49ac35e4a5acd966247082132d423ba832823328",
    "media:imagehash_avg": "a:ffffe7c74303073f",
    "media:imagehash_diff": "d:f4ecce9e968ecef8",
    "media:medium": "image",
    "media:mimetype": "image/tiff",
    "media:properties": {
      "colours": [
        {
          "hex": "#bf953c",
          "name": "#bf953c",
          "reference": "vibrant"
        }, 
        {
          "hex": "#f1cf7d",
          "name": "#f1cf7d",
          "reference": "vibrant"
        }, 
        {
          "hex": "#6f4f1b",
          "name": "#6f4f1b",
          "reference": "vibrant"
        }, 
        {
          "hex": "#957b51",
          "name": "#957b51",
          "reference": "vibrant"
        }, 
        {
          "hex": "#d7cbb9",
          "name": "#d7cbb9",
          "reference": "vibrant"
        }
      ],
      "sizes": {
        "b": {
          "extension": "jpg",
          "height": 753,
          "mimetype": "image/jpeg",
          "secret": "l7QWSUomDaQ5lheWtT6wQgWkgUj6MwXv",
          "width": 1023
        },
        "c": {
          "extension": "jpg",
          "height": 588,
          "mimetype": "image/jpeg",
          "secret": "l7QWSUomDaQ5lheWtT6wQgWkgUj6MwXv",
          "width": 800
        },
        "dc": {
          "extension": "jpg",
          "height": 588,
          "mimetype": "image/jpeg",
          "secret": "l7QWSUomDaQ5lheWtT6wQgWkgUj6MwXv",
          "width": 800
        },
        "ds": {
          "extension": "jpg",
          "height": 320,
          "mimetype": "image/jpeg",
          "secret": "l7QWSUomDaQ5lheWtT6wQgWkgUj6MwXv",
          "width": 320
        },
        "k": {
          "extension": "jpg",
          "height": 1507,
          "mimetype": "image/jpeg",
          "secret": "l7QWSUomDaQ5lheWtT6wQgWkgUj6MwXv",
          "width": 2047
        },
        "n": {
          "extension": "jpg",
          "height": 235,
          "mimetype": "image/jpeg",
          "secret": "l7QWSUomDaQ5lheWtT6wQgWkgUj6MwXv",
          "width": 320
        },
        "o": {
          "extension": "jpg",
          "height": 2483,
          "mimetype": "image/jpeg",
          "secret": "KS60KD3TrV4HPADthQ6lBjJNIlGUiwrc",
          "width": 3374
        },
        "s": {
          "extension": "jpg",
          "height": 320,
          "mimetype": "image/jpeg",
          "secret": "l7QWSUomDaQ5lheWtT6wQgWkgUj6MwXv",
          "width": 320
        },
        "z": {
          "extension": "jpg",
          "height": 470,
          "mimetype": "image/jpeg",
          "secret": "l7QWSUomDaQ5lheWtT6wQgWkgUj6MwXv",
          "width": 640
        }
      }
    },
    "media:uri_template": "https://millsfield.sfomuseum.org/media/152/782/881/1/1527828811_{secret}_{label}.{extention}",
    "sfomuseum:filename": "46603.tif",
    "sfomuseum:image_index": 5,
    "sfomuseum:placetype": "image",
    "sfomuseum:primary_image": 1,
    "wof:depicts": [
      1511929673
    ],
    "wof:name": "stewardess hat badge: Trans-Canada Air Lines (TCA)",
    "wof:placetype": "media"
  },
  "geometry": {"coordinates":[-122.386155,37.616358],"type":"Point"}
}
