{
  "type": "Feature",
  "properties": {
    "iso:country": "XX",
    "media:fingerprint": "34324fedcbf2eb5436bbd609297af39f6c1c611e",
    "media:imagehash_avg": "a:bf81818181a9818f",
    "media:imagehash_diff": "d:797b373575511b3f",
    "media:medium": "image",
    "media:mimetype": "image/tiff",
    "media:properties": {
      "colours": [
        {
          "hex": "#dbccaa",
          "name": "#dbccaa",
          "reference": "vibrant"
        },
        {
          "hex": "#858374",
          "name": "#858374",
          "reference": "vibrant"
        },
        {
          "hex": "#ccc7ae",
          "name": "#ccc7ae",
          "reference": "vibrant"
        },
        {
          "hex": "#444335",
          "name": "#444335",
          "reference": "vibrant"
        }
      ],
      "sizes": {
        "b": {
          "extension": "jpg",
          "height": 768,
          "mimetype": "image/jpeg",
          "secret": "0BvDVawrhvtcoiQZJXDhIwVCFYH52kg3",
          "width": 597
        },
        "c": {
          "extension": "jpg",
          "height": 600,
          "mimetype": "image/jpeg",
          "secret": "0BvDVawrhvtcoiQZJXDhIwVCFYH52kg3",
          "width": 466
        },
        "dc": {
          "extension": "jpg",
          "height": 600,
          "mimetype": "image/jpeg",
          "secret": "0BvDVawrhvtcoiQZJXDhIwVCFYH52kg3",
          "width": 466
        },
        "ds": {
          "extension": "jpg",
          "height": 320,
          "mimetype": "image/jpeg",
          "secret": "0BvDVawrhvtcoiQZJXDhIwVCFYH52kg3",
          "width": 320
        },
        "k": {
          "extension": "jpg",
          "height": 1536,
          "mimetype": "image/jpeg",
          "secret": "0BvDVawrhvtcoiQZJXDhIwVCFYH52kg3",
          "width": 1195
        },
        "n": {
          "extension": "jpg",
          "height": 240,
          "mimetype": "image/jpeg",
          "secret": "0BvDVawrhvtcoiQZJXDhIwVCFYH52kg3",
          "width": 186
        },
        "o": {
          "extension": "jpg",
          "height": 3315,
          "mimetype": "image/jpeg",
          "secret": "V0jF6n1JW6oDBipiVPwA6Zf7RpHSHWbi",
          "width": 2580
        },
        "s": {
          "extension": "jpg",
          "height": 320,
          "mimetype": "image/jpeg",
          "secret": "0BvDVawrhvtcoiQZJXDhIwVCFYH52kg3",
          "width": 320
        },
        "z": {
          "extension": "jpg",
          "height": 480,
          "mimetype": "image/jpeg",
          "secret": "0BvDVawrhvtcoiQZJXDhIwVCFYH52kg3",
          "width": 373
        }
      }
    },
    "media:uri_template": "https://static.sfomuseum.org/media/152/784/564/9/1527845649_{secret}_{label}.{extention}",
    "sfomuseum:filename": "70383.tif",
    "sfomuseum:image_index": 5,
    "sfomuseum:image_type": "studio",
    "sfomuseum:placetype": "image",
    "sfomuseum:primary_image": 1,
    "wof:depicts": [
      1511925491,
      1159284153
    ],
    "wof:name": "timetable: China Airlines",
    "wof:placetype": "custom",
    "wof:placetype_alt": "image"
  },
  "geometry": {"coordinates":[-122.386155,37.616358],"type":"Point"}
}
