{
  "type": "Feature",
  "properties": {
    "iso:country": "XX",
    "media:fingerprint": "3ba5c3caa915a3bac19c92cae7d5c22164572f35",
    "media:imagehash_avg": "a:0000003e7f7f7f7f",
    "media:imagehash_diff": "d:fcf8e8f0f0f0f0f4",
    "media:medium": "image",
    "media:mimetype": "image/tiff",
    "media:properties": {
      "colours": [
        {
          "hex": "#747d79",
          "name": "#747d79",
          "reference": "vibrant"
        },
        {
          "hex": "#bdc0bd",
          "name": "#bdc0bd",
          "reference": "vibrant"
        },
        {
          "hex": "#444836",
          "name": "#444836",
          "reference": "vibrant"
        }
      ],
      "sizes": {
        "b": {
          "extension": "jpg",
          "height": 670,
          "mimetype": "image/jpeg",
          "secret": "PtkPHeAzB8uxUSr7P8zhBHaCUtoWN7cX",
          "width": 1024
        },
        "c": {
          "extension": "jpg",
          "height": 523,
          "mimetype": "image/jpeg",
          "secret": "PtkPHeAzB8uxUSr7P8zhBHaCUtoWN7cX",
          "width": 800
        },
        "dc": {
          "extension": "jpg",
          "height": 523,
          "mimetype": "image/jpeg",
          "secret": "PtkPHeAzB8uxUSr7P8zhBHaCUtoWN7cX",
          "width": 800
        },
        "ds": {
          "extension": "jpg",
          "height": 320,
          "mimetype": "image/jpeg",
          "secret": "PtkPHeAzB8uxUSr7P8zhBHaCUtoWN7cX",
          "width": 320
        },
        "k": {
          "extension": "jpg",
          "height": 1340,
          "mimetype": "image/jpeg",
          "secret": "PtkPHeAzB8uxUSr7P8zhBHaCUtoWN7cX",
          "width": 2048
        },
        "n": {
          "extension": "jpg",
          "height": 209,
          "mimetype": "image/jpeg",
          "secret": "PtkPHeAzB8uxUSr7P8zhBHaCUtoWN7cX",
          "width": 320
        },
        "o": {
          "extension": "jpg",
          "height": 1081,
          "mimetype": "image/jpeg",
          "secret": "oGaBKpc9X1TpuxgfEfheOM1n8JA6zysa",
          "width": 1652
        },
        "s": {
          "extension": "jpg",
          "height": 320,
          "mimetype": "image/jpeg",
          "secret": "PtkPHeAzB8uxUSr7P8zhBHaCUtoWN7cX",
          "width": 320
        },
        "z": {
          "extension": "jpg",
          "height": 418,
          "mimetype": "image/jpeg",
          "secret": "PtkPHeAzB8uxUSr7P8zhBHaCUtoWN7cX",
          "width": 640
        }
      }
    },
    "media:uri_template": "https://static.sfomuseum.org/media/152/782/758/7/1527827587_{secret}_{label}.{extention}",
    "sfomuseum:filename": "44154.tif",
    "sfomuseum:image_index": 5,
    "sfomuseum:image_type": "studio",
    "sfomuseum:placetype": "image",
    "sfomuseum:primary_image": 1,
    "wof:depicts": [
      102527513,
      1511948623
    ],
    "wof:name": "negative: San Francisco International Airport (SFO), architectural model",
    "wof:placetype": "custom",
    "wof:placetype_alt": "image"
  },
  "geometry": {"coordinates":[-122.386155,37.616358],"type":"Point"}
}
