{
  "type": "Feature",
  "properties": {
    "iso:country": "XX",
    "media:fingerprint": "6f19823317b2bada18a5afbe3c95e32d35a5d506",
    "media:imagehash_avg": "a:f101010183a1b1ff",
    "media:imagehash_diff": "d:4371596d47434747",
    "media:medium": "image",
    "media:mimetype": "image/tiff",
    "media:properties": {
      "colours": [
        {
          "hex": "#ce0a0e",
          "name": "#ce0a0e",
          "reference": "vibrant"
        }, 
        {
          "hex": "#daa5a3",
          "name": "#daa5a3",
          "reference": "vibrant"
        }, 
        {
          "hex": "#c30708",
          "name": "#c30708",
          "reference": "vibrant"
        }, 
        {
          "hex": "#a96864",
          "name": "#a96864",
          "reference": "vibrant"
        }, 
        {
          "hex": "#bc8081",
          "name": "#bc8081",
          "reference": "vibrant"
        }
      ],
      "sizes": {
        "b": {
          "extension": "jpg",
          "height": 768,
          "mimetype": "image/jpeg",
          "secret": "xVGlMJNbdXVOEiTfpa24uNK3OJ50ip4k",
          "width": 390
        },
        "c": {
          "extension": "jpg",
          "height": 600,
          "mimetype": "image/jpeg",
          "secret": "xVGlMJNbdXVOEiTfpa24uNK3OJ50ip4k",
          "width": 304
        },
        "dc": {
          "extension": "jpg",
          "height": 600,
          "mimetype": "image/jpeg",
          "secret": "xVGlMJNbdXVOEiTfpa24uNK3OJ50ip4k",
          "width": 304
        },
        "ds": {
          "extension": "jpg",
          "height": 320,
          "mimetype": "image/jpeg",
          "secret": "xVGlMJNbdXVOEiTfpa24uNK3OJ50ip4k",
          "width": 320
        },
        "k": {
          "extension": "jpg",
          "height": 1536,
          "mimetype": "image/jpeg",
          "secret": "xVGlMJNbdXVOEiTfpa24uNK3OJ50ip4k",
          "width": 780
        },
        "n": {
          "extension": "jpg",
          "height": 239,
          "mimetype": "image/jpeg",
          "secret": "xVGlMJNbdXVOEiTfpa24uNK3OJ50ip4k",
          "width": 121
        },
        "o": {
          "extension": "jpg",
          "height": 2416,
          "mimetype": "image/jpeg",
          "secret": "eOM30TJWwdBmuc98Oh07NeyxJauKQ9Sc",
          "width": 1227
        },
        "s": {
          "extension": "jpg",
          "height": 320,
          "mimetype": "image/jpeg",
          "secret": "xVGlMJNbdXVOEiTfpa24uNK3OJ50ip4k",
          "width": 320
        },
        "z": {
          "extension": "jpg",
          "height": 479,
          "mimetype": "image/jpeg",
          "secret": "xVGlMJNbdXVOEiTfpa24uNK3OJ50ip4k",
          "width": 243
        }
      }
    },
    "media:uri_template": "https://millsfield.sfomuseum.org/media/152/785/279/1/1527852791_{secret}_{label}.{extention}",
    "sfomuseum:filename": "2012.173.521_verso.tif",
    "sfomuseum:image_index": 5,
    "sfomuseum:placetype": "image",
    "sfomuseum:primary_image": 0,
    "wof:depicts": [
      1511955489
    ],
    "wof:name": "seating guide: TWA (Trans World Airlines)",
    "wof:placetype": "media"
  },
  "geometry": {"coordinates":[-122.386155,37.616358],"type":"Point"}
}
