{
  "type": "Feature",
  "properties": {
    "iso:country": "XX",
    "media:fingerprint": "ce1a19520153322272dbc5d7b597ac715db1e445",
    "media:imagehash_avg": "a:107c7e7efe7c7800",
    "media:imagehash_diff": "d:e0e0e0e880e0e0e0",
    "media:medium": "image",
    "media:mimetype": "image/tiff",
    "media:properties": {
      "colours": [
        {
          "hex": "#808080",
          "name": "#808080",
          "reference": "vibrant"
        }, 
        {
          "hex": "#b8b8b8",
          "name": "#b8b8b8",
          "reference": "vibrant"
        }, 
        {
          "hex": "#484848",
          "name": "#484848",
          "reference": "vibrant"
        }
      ],
      "sizes": {
        "b": {
          "extension": "jpg",
          "height": 768,
          "mimetype": "image/jpeg",
          "secret": "saBQiogOh73PuFh4vNV89y7XqCSpdSrs",
          "width": 768
        },
        "c": {
          "extension": "jpg",
          "height": 600,
          "mimetype": "image/jpeg",
          "secret": "saBQiogOh73PuFh4vNV89y7XqCSpdSrs",
          "width": 600
        },
        "dc": {
          "extension": "jpg",
          "height": 600,
          "mimetype": "image/jpeg",
          "secret": "saBQiogOh73PuFh4vNV89y7XqCSpdSrs",
          "width": 600
        },
        "ds": {
          "extension": "jpg",
          "height": 320,
          "mimetype": "image/jpeg",
          "secret": "saBQiogOh73PuFh4vNV89y7XqCSpdSrs",
          "width": 320
        },
        "k": {
          "extension": "jpg",
          "height": 1536,
          "mimetype": "image/jpeg",
          "secret": "saBQiogOh73PuFh4vNV89y7XqCSpdSrs",
          "width": 1536
        },
        "n": {
          "extension": "jpg",
          "height": 239,
          "mimetype": "image/jpeg",
          "secret": "saBQiogOh73PuFh4vNV89y7XqCSpdSrs",
          "width": 239
        },
        "o": {
          "extension": "jpg",
          "height": 2563,
          "mimetype": "image/jpeg",
          "secret": "oDVE8rHJm2ADwv0W0mhTbYWIkjS1kNyD",
          "width": 2563
        },
        "s": {
          "extension": "jpg",
          "height": 320,
          "mimetype": "image/jpeg",
          "secret": "saBQiogOh73PuFh4vNV89y7XqCSpdSrs",
          "width": 320
        },
        "z": {
          "extension": "jpg",
          "height": 479,
          "mimetype": "image/jpeg",
          "secret": "saBQiogOh73PuFh4vNV89y7XqCSpdSrs",
          "width": 479
        }
      }
    },
    "media:uri_template": "https://millsfield.sfomuseum.org/media/152/782/604/9/1527826049_{secret}_{label}.{extention}",
    "sfomuseum:filename": "43466.tif",
    "sfomuseum:image_index": 5,
    "sfomuseum:placetype": "image",
    "sfomuseum:primary_image": 1,
    "wof:depicts": [
      1511947083
    ],
    "wof:name": "negative: San Francisco International Airport (SFO), United Air Lines service center construction",
    "wof:placetype": "media"
  },
  "geometry": {"coordinates":[-122.386155,37.616358],"type":"Point"}
}
