{
  "type": "Feature",
  "properties": {
    "iso:country": "US",
    "media:fingerprint": "d0cff350aab9352d5fd466e9f10cdf427f48cd7b",
    "media:imagehash_avg": "a:81818181878787ef",
    "media:imagehash_diff": "d:155553571715175d",
    "media:medium": "image",
    "media:mimetype": "image/tiff",
    "media:properties": {
      "colours": [
        {
          "hex": "#f8ed6b",
          "name": "#f8ed6b",
          "reference": "vibrant"
        }, 
        {
          "hex": "#ede77d",
          "name": "#ede77d",
          "reference": "vibrant"
        }, 
        {
          "hex": "#635d1f",
          "name": "#635d1f",
          "reference": "vibrant"
        }, 
        {
          "hex": "#797c8c",
          "name": "#797c8c",
          "reference": "vibrant"
        }, 
        {
          "hex": "#afb0a3",
          "name": "#afb0a3",
          "reference": "vibrant"
        }
      ],
      "sizes": {
        "b": {
          "extension": "jpg",
          "height": 768,
          "mimetype": "image/jpeg",
          "secret": "BLzbGZouzH425Kjr1ceL2LveFdZimxwY",
          "width": 361
        },
        "c": {
          "extension": "jpg",
          "height": 600,
          "mimetype": "image/jpeg",
          "secret": "BLzbGZouzH425Kjr1ceL2LveFdZimxwY",
          "width": 282
        },
        "dc": {
          "extension": "jpg",
          "height": 600,
          "mimetype": "image/jpeg",
          "secret": "BLzbGZouzH425Kjr1ceL2LveFdZimxwY",
          "width": 282
        },
        "ds": {
          "extension": "jpg",
          "height": 320,
          "mimetype": "image/jpeg",
          "secret": "BLzbGZouzH425Kjr1ceL2LveFdZimxwY",
          "width": 300
        },
        "k": {
          "extension": "jpg",
          "height": 1536,
          "mimetype": "image/jpeg",
          "secret": "BLzbGZouzH425Kjr1ceL2LveFdZimxwY",
          "width": 723
        },
        "n": {
          "extension": "jpg",
          "height": 240,
          "mimetype": "image/jpeg",
          "secret": "BLzbGZouzH425Kjr1ceL2LveFdZimxwY",
          "width": 113
        },
        "o": {
          "extension": "jpg",
          "height": 635,
          "mimetype": "image/jpeg",
          "secret": "4Kl5t9lzbHmaKxjvS10rNc4YjY3XCkAk",
          "width": 299
        },
        "s": {
          "extension": "jpg",
          "height": 320,
          "mimetype": "image/jpeg",
          "secret": "BLzbGZouzH425Kjr1ceL2LveFdZimxwY",
          "width": 300
        },
        "z": {
          "extension": "jpg",
          "height": 480,
          "mimetype": "image/jpeg",
          "secret": "BLzbGZouzH425Kjr1ceL2LveFdZimxwY",
          "width": 226
        }
      }
    },
    "media:uri_template": "https://millsfield.sfomuseum.org/media/152/781/865/9/1527818659_{secret}_{label}.{extention}",
    "sfomuseum:filename": "19125.tif",
    "sfomuseum:image_index": 5,
    "sfomuseum:placetype": "image",
    "sfomuseum:primary_image": 0,
    "wof:depicts": [
      1511909959
    ],
    "wof:name": "fare schedule: United Airlines",
    "wof:placetype": "media"
  },
  "geometry": {"coordinates":[-122.386155,37.616358],"type":"Point"}
}
