{
  "type": "Feature",
  "properties": {
    "iso:country": "US",
    "media:fingerprint": "950db31534e3415e651d1f23c95d600501f3124c",
    "media:imagehash_avg": "a:ffff83838381c3ff",
    "media:imagehash_diff": "d:630f0e27373707e6",
    "media:medium": "image",
    "media:mimetype": "image/tiff",
    "media:properties": {
      "colours": [
        {
          "hex": "#4576b6",
          "name": "#4576b6",
          "reference": "vibrant"
        }, 
        {
          "hex": "#7a9ecc",
          "name": "#7a9ecc",
          "reference": "vibrant"
        }, 
        {
          "hex": "#193a64",
          "name": "#193a64",
          "reference": "vibrant"
        }, 
        {
          "hex": "#6e7c91",
          "name": "#6e7c91",
          "reference": "vibrant"
        }, 
        {
          "hex": "#c3c5c8",
          "name": "#c3c5c8",
          "reference": "vibrant"
        }
      ],
      "sizes": {
        "b": {
          "extension": "jpg",
          "height": 768,
          "mimetype": "image/jpeg",
          "secret": "dPR6vSpOdxuYx4wMHt8nruE1dFDxGZEw",
          "width": 965
        },
        "c": {
          "extension": "jpg",
          "height": 600,
          "mimetype": "image/jpeg",
          "secret": "dPR6vSpOdxuYx4wMHt8nruE1dFDxGZEw",
          "width": 754
        },
        "dc": {
          "extension": "jpg",
          "height": 600,
          "mimetype": "image/jpeg",
          "secret": "dPR6vSpOdxuYx4wMHt8nruE1dFDxGZEw",
          "width": 754
        },
        "ds": {
          "extension": "jpg",
          "height": 320,
          "mimetype": "image/jpeg",
          "secret": "dPR6vSpOdxuYx4wMHt8nruE1dFDxGZEw",
          "width": 320
        },
        "k": {
          "extension": "jpg",
          "height": 1536,
          "mimetype": "image/jpeg",
          "secret": "dPR6vSpOdxuYx4wMHt8nruE1dFDxGZEw",
          "width": 1931
        },
        "n": {
          "extension": "jpg",
          "height": 240,
          "mimetype": "image/jpeg",
          "secret": "dPR6vSpOdxuYx4wMHt8nruE1dFDxGZEw",
          "width": 301
        },
        "o": {
          "extension": "jpg",
          "height": 1326,
          "mimetype": "image/jpeg",
          "secret": "KFrKqWS8KX3xV8LfusEbgF54za1Xiybo",
          "width": 1667
        },
        "s": {
          "extension": "jpg",
          "height": 320,
          "mimetype": "image/jpeg",
          "secret": "dPR6vSpOdxuYx4wMHt8nruE1dFDxGZEw",
          "width": 320
        },
        "z": {
          "extension": "jpg",
          "height": 480,
          "mimetype": "image/jpeg",
          "secret": "dPR6vSpOdxuYx4wMHt8nruE1dFDxGZEw",
          "width": 603
        }
      }
    },
    "media:uri_template": "https://millsfield.sfomuseum.org/media/152/785/731/5/1527857315_{secret}_{label}.{extention}",
    "sfomuseum:filename": "1996.08.22.01_ft2.tif",
    "sfomuseum:image_index": 5,
    "sfomuseum:placetype": "image",
    "sfomuseum:primary_image": 1,
    "wof:depicts": [
      1511907503
    ],
    "wof:name": "airline bag: Pan American World Airways",
    "wof:placetype": "media"
  },
  "geometry": {"coordinates":[-122.386155,37.616358],"type":"Point"}
}
