{
  "type": "Feature",
  "properties": {
    "iso:country": "XX",
    "media:fingerprint": "a4376b00e905317888c5f2a1a3c91ce4d5d33c05",
    "media:imagehash_avg": "a:7effff3c20000020",
    "media:imagehash_diff": "d:f8f8f8f8c0d0c4c0",
    "media:medium": "image",
    "media:mimetype": "image/tiff",
    "media:properties": {
      "colours": [
        {
          "hex": "#b87d4d",
          "name": "#b87d4d",
          "reference": "vibrant"
        }, 
        {
          "hex": "#eee3c0",
          "name": "#eee3c0",
          "reference": "vibrant"
        }, 
        {
          "hex": "#757785",
          "name": "#757785",
          "reference": "vibrant"
        }, 
        {
          "hex": "#d6ccac",
          "name": "#d6ccac",
          "reference": "vibrant"
        }, 
        {
          "hex": "#2d3655",
          "name": "#2d3655",
          "reference": "vibrant"
        }
      ],
      "sizes": {
        "b": {
          "extension": "jpg",
          "height": 766,
          "mimetype": "image/jpeg",
          "secret": "iack8bBrvJisP2Uo3SnkMqMsiLj34zGW",
          "width": 1024
        },
        "c": {
          "extension": "jpg",
          "height": 598,
          "mimetype": "image/jpeg",
          "secret": "iack8bBrvJisP2Uo3SnkMqMsiLj34zGW",
          "width": 800
        },
        "dc": {
          "extension": "jpg",
          "height": 598,
          "mimetype": "image/jpeg",
          "secret": "iack8bBrvJisP2Uo3SnkMqMsiLj34zGW",
          "width": 800
        },
        "ds": {
          "extension": "jpg",
          "height": 320,
          "mimetype": "image/jpeg",
          "secret": "iack8bBrvJisP2Uo3SnkMqMsiLj34zGW",
          "width": 320
        },
        "k": {
          "extension": "jpg",
          "height": 1532,
          "mimetype": "image/jpeg",
          "secret": "iack8bBrvJisP2Uo3SnkMqMsiLj34zGW",
          "width": 2048
        },
        "n": {
          "extension": "jpg",
          "height": 239,
          "mimetype": "image/jpeg",
          "secret": "iack8bBrvJisP2Uo3SnkMqMsiLj34zGW",
          "width": 320
        },
        "o": {
          "extension": "jpg",
          "height": 1295,
          "mimetype": "image/jpeg",
          "secret": "81T5w3DXQeoaplJZPgDgpkzwOTvBGTdK",
          "width": 1731
        },
        "s": {
          "extension": "jpg",
          "height": 320,
          "mimetype": "image/jpeg",
          "secret": "iack8bBrvJisP2Uo3SnkMqMsiLj34zGW",
          "width": 320
        },
        "z": {
          "extension": "jpg",
          "height": 478,
          "mimetype": "image/jpeg",
          "secret": "iack8bBrvJisP2Uo3SnkMqMsiLj34zGW",
          "width": 640
        }
      }
    },
    "media:uri_template": "https://millsfield.sfomuseum.org/media/152/782/208/7/1527822087_{secret}_{label}.{extention}",
    "sfomuseum:filename": "40196.tif",
    "sfomuseum:image_index": 5,
    "sfomuseum:placetype": "image",
    "sfomuseum:primary_image": 1,
    "wof:depicts": [
      1511944007
    ],
    "wof:name": "negative: San Francisco International Airport (SFO), aerial",
    "wof:placetype": "media"
  },
  "geometry": {"coordinates":[-122.386155,37.616358],"type":"Point"}
}
