{
  "type": "Feature",
  "properties": {
    "iso:country": "XX",
    "media:fingerprint": "63fe7ee034afee7fd7d9b3f51932a6a178780681",
    "media:imagehash_avg": "a:fffffffc00000000",
    "media:imagehash_diff": "d:80888c80983880e0",
    "media:medium": "image",
    "media:mimetype": "image/tiff",
    "media:properties": {
      "colours": [
        {
          "hex": "#949143",
          "name": "#949143",
          "reference": "vibrant"
        }, 
        {
          "hex": "#d8da8f",
          "name": "#d8da8f",
          "reference": "vibrant"
        }, 
        {
          "hex": "#989b58",
          "name": "#989b58",
          "reference": "vibrant"
        }, 
        {
          "hex": "#a6d4d1",
          "name": "#a6d4d1",
          "reference": "vibrant"
        }, 
        {
          "hex": "#495433",
          "name": "#495433",
          "reference": "vibrant"
        }
      ],
      "sizes": {
        "b": {
          "extension": "jpg",
          "height": 768,
          "mimetype": "image/jpeg",
          "secret": "jOqp4NAbajYpo29TPCIjKim7VuaGCJzh",
          "width": 784
        },
        "c": {
          "extension": "jpg",
          "height": 600,
          "mimetype": "image/jpeg",
          "secret": "jOqp4NAbajYpo29TPCIjKim7VuaGCJzh",
          "width": 612
        },
        "dc": {
          "extension": "jpg",
          "height": 600,
          "mimetype": "image/jpeg",
          "secret": "jOqp4NAbajYpo29TPCIjKim7VuaGCJzh",
          "width": 612
        },
        "ds": {
          "extension": "jpg",
          "height": 320,
          "mimetype": "image/jpeg",
          "secret": "jOqp4NAbajYpo29TPCIjKim7VuaGCJzh",
          "width": 320
        },
        "k": {
          "extension": "jpg",
          "height": 1536,
          "mimetype": "image/jpeg",
          "secret": "jOqp4NAbajYpo29TPCIjKim7VuaGCJzh",
          "width": 1568
        },
        "n": {
          "extension": "jpg",
          "height": 239,
          "mimetype": "image/jpeg",
          "secret": "jOqp4NAbajYpo29TPCIjKim7VuaGCJzh",
          "width": 245
        },
        "o": {
          "extension": "jpg",
          "height": 2563,
          "mimetype": "image/jpeg",
          "secret": "UMUiKwUo02QsLxSJEN6px5k1nbkg9tON",
          "width": 2618
        },
        "s": {
          "extension": "jpg",
          "height": 320,
          "mimetype": "image/jpeg",
          "secret": "jOqp4NAbajYpo29TPCIjKim7VuaGCJzh",
          "width": 320
        },
        "z": {
          "extension": "jpg",
          "height": 479,
          "mimetype": "image/jpeg",
          "secret": "jOqp4NAbajYpo29TPCIjKim7VuaGCJzh",
          "width": 490
        }
      }
    },
    "media:uri_template": "https://millsfield.sfomuseum.org/media/152/782/544/3/1527825443_{secret}_{label}.{extention}",
    "sfomuseum:filename": "43157.tif",
    "sfomuseum:image_index": 5,
    "sfomuseum:placetype": "image",
    "sfomuseum:primary_image": 1,
    "wof:depicts": [
      1511946483
    ],
    "wof:name": "negative: San Francisco International Airport (SFO), parking garage",
    "wof:placetype": "media"
  },
  "geometry": {"coordinates":[-122.386155,37.616358],"type":"Point"}
}
