{
  "type": "Feature",
  "properties": {
    "iso:country": "XX",
    "media:fingerprint": "f7e68b61f989d056597ee89be9610e4f607e683a",
    "media:imagehash_avg": "a:38fefffe3c000000",
    "media:imagehash_diff": "d:f0f0f8f0f0f0f0f8",
    "media:medium": "image",
    "media:mimetype": "image/tiff",
    "media:properties": {
      "colours": [
        {
          "hex": "#808080",
          "name": "#808080",
          "reference": "vibrant"
        }, 
        {
          "hex": "#b8b8b8",
          "name": "#b8b8b8",
          "reference": "vibrant"
        }, 
        {
          "hex": "#404040",
          "name": "#404040",
          "reference": "vibrant"
        }
      ],
      "sizes": {
        "b": {
          "extension": "jpg",
          "height": 767,
          "mimetype": "image/jpeg",
          "secret": "Zf8J2KuK8EbEJzL47k9cWw7sOyU13YWZ",
          "width": 978
        },
        "c": {
          "extension": "jpg",
          "height": 600,
          "mimetype": "image/jpeg",
          "secret": "Zf8J2KuK8EbEJzL47k9cWw7sOyU13YWZ",
          "width": 764
        },
        "dc": {
          "extension": "jpg",
          "height": 600,
          "mimetype": "image/jpeg",
          "secret": "Zf8J2KuK8EbEJzL47k9cWw7sOyU13YWZ",
          "width": 764
        },
        "ds": {
          "extension": "jpg",
          "height": 320,
          "mimetype": "image/jpeg",
          "secret": "Zf8J2KuK8EbEJzL47k9cWw7sOyU13YWZ",
          "width": 320
        },
        "k": {
          "extension": "jpg",
          "height": 1535,
          "mimetype": "image/jpeg",
          "secret": "Zf8J2KuK8EbEJzL47k9cWw7sOyU13YWZ",
          "width": 1957
        },
        "n": {
          "extension": "jpg",
          "height": 240,
          "mimetype": "image/jpeg",
          "secret": "Zf8J2KuK8EbEJzL47k9cWw7sOyU13YWZ",
          "width": 305
        },
        "o": {
          "extension": "jpg",
          "height": 2140,
          "mimetype": "image/jpeg",
          "secret": "n0BaPd6F9eaI15gyulYpATnwmoZOfoUD",
          "width": 2727
        },
        "s": {
          "extension": "jpg",
          "height": 320,
          "mimetype": "image/jpeg",
          "secret": "Zf8J2KuK8EbEJzL47k9cWw7sOyU13YWZ",
          "width": 320
        },
        "z": {
          "extension": "jpg",
          "height": 480,
          "mimetype": "image/jpeg",
          "secret": "Zf8J2KuK8EbEJzL47k9cWw7sOyU13YWZ",
          "width": 611
        }
      }
    },
    "media:uri_template": "https://millsfield.sfomuseum.org/media/152/782/284/1/1527822841_{secret}_{label}.{extention}",
    "sfomuseum:filename": "41097.tif",
    "sfomuseum:image_index": 5,
    "sfomuseum:placetype": "image",
    "sfomuseum:primary_image": 1,
    "wof:depicts": [
      1511944735
    ],
    "wof:name": "negative: San Francisco International Airport (SFO), runway construction",
    "wof:placetype": "media"
  },
  "geometry": {"coordinates":[-122.386155,37.616358],"type":"Point"}
}
