{
  "type": "Feature",
  "properties": {
    "iso:country": "XX",
    "media:fingerprint": "6418b21b65f148f462b4145244a7f4a9e050f3d2",
    "media:imagehash_avg": "a:ff8080e0ffff0000",
    "media:imagehash_diff": "d:360901058ccc4d6d",
    "media:medium": "image",
    "media:mimetype": "image/tiff",
    "media:properties": {
      "colours": [
        {
          "hex": "#cd2f2a",
          "name": "#cd2f2a",
          "reference": "vibrant"
        }, 
        {
          "hex": "#ea9b57",
          "name": "#ea9b57",
          "reference": "vibrant"
        }, 
        {
          "hex": "#093974",
          "name": "#093974",
          "reference": "vibrant"
        }, 
        {
          "hex": "#9c806e",
          "name": "#9c806e",
          "reference": "vibrant"
        }, 
        {
          "hex": "#c2baab",
          "name": "#c2baab",
          "reference": "vibrant"
        }
      ],
      "sizes": {
        "b": {
          "extension": "jpg",
          "height": 768,
          "mimetype": "image/jpeg",
          "secret": "R6Ty6yPy8Y7DKdOvI3JjsLmZzd3Ss0AE",
          "width": 354
        },
        "c": {
          "extension": "jpg",
          "height": 600,
          "mimetype": "image/jpeg",
          "secret": "R6Ty6yPy8Y7DKdOvI3JjsLmZzd3Ss0AE",
          "width": 277
        },
        "dc": {
          "extension": "jpg",
          "height": 600,
          "mimetype": "image/jpeg",
          "secret": "R6Ty6yPy8Y7DKdOvI3JjsLmZzd3Ss0AE",
          "width": 277
        },
        "ds": {
          "extension": "jpg",
          "height": 320,
          "mimetype": "image/jpeg",
          "secret": "R6Ty6yPy8Y7DKdOvI3JjsLmZzd3Ss0AE",
          "width": 320
        },
        "k": {
          "extension": "jpg",
          "height": 1536,
          "mimetype": "image/jpeg",
          "secret": "R6Ty6yPy8Y7DKdOvI3JjsLmZzd3Ss0AE",
          "width": 709
        },
        "n": {
          "extension": "jpg",
          "height": 240,
          "mimetype": "image/jpeg",
          "secret": "R6Ty6yPy8Y7DKdOvI3JjsLmZzd3Ss0AE",
          "width": 110
        },
        "o": {
          "extension": "jpg",
          "height": 2736,
          "mimetype": "image/jpeg",
          "secret": "kK86PBxnqEKA1YZ8l5Vx1hNmJvnG6lnV",
          "width": 1264
        },
        "s": {
          "extension": "jpg",
          "height": 320,
          "mimetype": "image/jpeg",
          "secret": "R6Ty6yPy8Y7DKdOvI3JjsLmZzd3Ss0AE",
          "width": 320
        },
        "z": {
          "extension": "jpg",
          "height": 480,
          "mimetype": "image/jpeg",
          "secret": "R6Ty6yPy8Y7DKdOvI3JjsLmZzd3Ss0AE",
          "width": 221
        }
      }
    },
    "media:uri_template": "https://millsfield.sfomuseum.org/media/152/781/836/1/1527818361_{secret}_{label}.{extention}",
    "sfomuseum:filename": "18524.tif",
    "sfomuseum:image_index": 5,
    "sfomuseum:placetype": "image",
    "sfomuseum:primary_image": 0,
    "wof:depicts": [
      1511935435
    ],
    "wof:name": "flight information booklet: Northwest Orient Airlines",
    "wof:placetype": "media"
  },
  "geometry": {"coordinates":[-122.386155,37.616358],"type":"Point"}
}
