{
  "type": "Feature",
  "properties": {
    "date:cessation_lower": "1915-01-01",
    "date:cessation_upper": "1915-12-31",
    "date:inception_lower": "1915-01-01",
    "date:inception_upper": "1915-12-31",
    "iso:country": "XX",
    "media:fingerprint": "270a4d3a16794935fa57868e707d9cc8710c89a6",
    "media:imagehash_avg": "a:fbe981a18180a1ff",
    "media:imagehash_diff": "d:73534b4b6b61656d",
    "media:imagetext": "873",
    "media:mimetype": "image/tiff",
    "media:properties": {
      "colours": [
        {
          "hex": "#868781",
          "name": "#868781",
          "reference": "vibrant"
        },
        {
          "hex": "#c0c0ba",
          "name": "#c0c0ba",
          "reference": "vibrant"
        },
        {
          "hex": "#434640",
          "name": "#434640",
          "reference": "vibrant"
        }
      ],
      "sizes": {
        "b": {
          "extension": "jpg",
          "height": 768,
          "mimetype": "image/jpeg",
          "secret": "iFJzvzpTw4zcaKwAk0UstuL8dBo4vLse",
          "width": 980
        },
        "c": {
          "extension": "jpg",
          "height": 600,
          "mimetype": "image/jpeg",
          "secret": "iFJzvzpTw4zcaKwAk0UstuL8dBo4vLse",
          "width": 766
        },
        "dc": {
          "extension": "jpg",
          "height": 600,
          "mimetype": "image/jpeg",
          "secret": "iFJzvzpTw4zcaKwAk0UstuL8dBo4vLse",
          "width": 766
        },
        "ds": {
          "extension": "jpg",
          "height": 320,
          "mimetype": "image/jpeg",
          "secret": "iFJzvzpTw4zcaKwAk0UstuL8dBo4vLse",
          "width": 320
        },
        "k": {
          "extension": "jpg",
          "height": 1536,
          "mimetype": "image/jpeg",
          "secret": "iFJzvzpTw4zcaKwAk0UstuL8dBo4vLse",
          "width": 1961
        },
        "n": {
          "extension": "jpg",
          "height": 239,
          "mimetype": "image/jpeg",
          "secret": "iFJzvzpTw4zcaKwAk0UstuL8dBo4vLse",
          "width": 306
        },
        "o": {
          "extension": "jpg",
          "height": 1566,
          "mimetype": "image/jpeg",
          "secret": "7SHYrNQxsb6yGMPkDPuGJSQPphHvC6xe",
          "width": 2000
        },
        "s": {
          "extension": "jpg",
          "height": 320,
          "mimetype": "image/jpeg",
          "secret": "iFJzvzpTw4zcaKwAk0UstuL8dBo4vLse",
          "width": 320
        },
        "z": {
          "extension": "jpg",
          "height": 479,
          "mimetype": "image/jpeg",
          "secret": "iFJzvzpTw4zcaKwAk0UstuL8dBo4vLse",
          "width": 613
        }
      }
    },
    "media:uri_template": "https://static.sfomuseum.org/media/176/344/362/1/1763443621_{secret}_{label}.{extension}",
    "millsfield:images_texts": [
      "873"
    ],
    "millsfield:images_texts_ids": [
      1763443621
    ],
    "sfomuseum:filename": "126562.tif",
    "sfomuseum:image_index": 5,
    "sfomuseum:image_type": "studio",
    "sfomuseum:placetype": "image",
    "sfomuseum:primary_image": 1,
    "wof:depicts": [
      1511958217
    ],
    "wof:name": "photograph: Panama-Pacific International Exposition, Art Smith",
    "wof:placetype": "custom"
  },
  "geometry": {"coordinates":[-122.386155,37.616357],"type":"Point"}
}
