{
  "type": "Feature",
  "properties": {
    "iso:country": "XX",
    "media:fingerprint": "248ed17706bc2b4dfdd7a7240372f5712b0269f1",
    "media:imagehash_avg": "a:ffff9d81838fffff",
    "media:imagehash_diff": "d:001031271f3c7000",
    "media:medium": "image",
    "media:mimetype": "image/tiff",
    "media:properties": {
      "colours": [
        {
          "hex": "#967a67",
          "name": "#967a67",
          "reference": "vibrant"
        },
        {
          "hex": "#b0b0b8",
          "name": "#b0b0b8",
          "reference": "vibrant"
        },
        {
          "hex": "#554438",
          "name": "#554438",
          "reference": "vibrant"
        }
      ],
      "sizes": {
        "b": {
          "extension": "jpg",
          "height": 685,
          "mimetype": "image/jpeg",
          "secret": "h2gRW7j2FXydKONnaZb3UpbmzAncCUyB",
          "width": 1024
        },
        "c": {
          "extension": "jpg",
          "height": 535,
          "mimetype": "image/jpeg",
          "secret": "h2gRW7j2FXydKONnaZb3UpbmzAncCUyB",
          "width": 800
        },
        "dc": {
          "extension": "jpg",
          "height": 535,
          "mimetype": "image/jpeg",
          "secret": "h2gRW7j2FXydKONnaZb3UpbmzAncCUyB",
          "width": 800
        },
        "ds": {
          "extension": "jpg",
          "height": 320,
          "mimetype": "image/jpeg",
          "secret": "h2gRW7j2FXydKONnaZb3UpbmzAncCUyB",
          "width": 320
        },
        "k": {
          "extension": "jpg",
          "height": 1371,
          "mimetype": "image/jpeg",
          "secret": "h2gRW7j2FXydKONnaZb3UpbmzAncCUyB",
          "width": 2048
        },
        "n": {
          "extension": "jpg",
          "height": 214,
          "mimetype": "image/jpeg",
          "secret": "h2gRW7j2FXydKONnaZb3UpbmzAncCUyB",
          "width": 320
        },
        "o": {
          "extension": "jpg",
          "height": 2400,
          "mimetype": "image/jpeg",
          "secret": "QXgnk9Q8uZgul2NfVATMEaOsN2LDS5ZC",
          "width": 3585
        },
        "s": {
          "extension": "jpg",
          "height": 320,
          "mimetype": "image/jpeg",
          "secret": "h2gRW7j2FXydKONnaZb3UpbmzAncCUyB",
          "width": 320
        },
        "z": {
          "extension": "jpg",
          "height": 428,
          "mimetype": "image/jpeg",
          "secret": "h2gRW7j2FXydKONnaZb3UpbmzAncCUyB",
          "width": 640
        }
      }
    },
    "media:uri_template": "https://millsfield.sfomuseum.org/media/152/785/409/9/1527854099_{secret}_{label}.{extention}",
    "sfomuseum:filename": "2012.147.087.tif",
    "sfomuseum:image_index": 1,
    "sfomuseum:placetype": "image",
    "sfomuseum:primary_image": 0,
    "wof:depicts": [
      1511952527
    ],
    "wof:name": "stewardess wing: North Central Airlines",
    "wof:placetype": "custom",
    "wof:placetype_alt": "image"
  },
  "geometry": {"coordinates":[-122.386155,37.616358],"type":"Point"}
}
