{
  "type": "Feature",
  "properties": {
    "iso:country": "XX",
    "media:fingerprint": "1de4bec94254a0cd0c02704ccc2c6ce7f9d03c39",
    "media:imagehash_avg": "a:88f8b89f9f1f1f01",
    "media:imagehash_diff": "d:59f161307372703b",
    "media:medium": "image",
    "media:mimetype": "image/tiff",
    "media:properties": {
      "colours": [
        {
          "hex": "#df372c",
          "name": "#df372c",
          "reference": "vibrant"
        }, 
        {
          "hex": "#dc8b93",
          "name": "#dc8b93",
          "reference": "vibrant"
        }, 
        {
          "hex": "#101447",
          "name": "#101447",
          "reference": "vibrant"
        }, 
        {
          "hex": "#bc7b82",
          "name": "#bc7b82",
          "reference": "vibrant"
        }, 
        {
          "hex": "#dac4b3",
          "name": "#dac4b3",
          "reference": "vibrant"
        }
      ],
      "sizes": {
        "b": {
          "extension": "jpg",
          "height": 460,
          "mimetype": "image/jpeg",
          "secret": "4SPFibUogA9VHWcsnH6snxAUrduEdT8u",
          "width": 1024
        },
        "c": {
          "extension": "jpg",
          "height": 359,
          "mimetype": "image/jpeg",
          "secret": "4SPFibUogA9VHWcsnH6snxAUrduEdT8u",
          "width": 800
        },
        "dc": {
          "extension": "jpg",
          "height": 359,
          "mimetype": "image/jpeg",
          "secret": "4SPFibUogA9VHWcsnH6snxAUrduEdT8u",
          "width": 800
        },
        "ds": {
          "extension": "jpg",
          "height": 320,
          "mimetype": "image/jpeg",
          "secret": "4SPFibUogA9VHWcsnH6snxAUrduEdT8u",
          "width": 320
        },
        "k": {
          "extension": "jpg",
          "height": 921,
          "mimetype": "image/jpeg",
          "secret": "4SPFibUogA9VHWcsnH6snxAUrduEdT8u",
          "width": 2048
        },
        "n": {
          "extension": "jpg",
          "height": 143,
          "mimetype": "image/jpeg",
          "secret": "4SPFibUogA9VHWcsnH6snxAUrduEdT8u",
          "width": 320
        },
        "o": {
          "extension": "jpg",
          "height": 1325,
          "mimetype": "image/jpeg",
          "secret": "6paNLog4G3gLFQdUXlq25QhEiRGUQy5w",
          "width": 2946
        },
        "s": {
          "extension": "jpg",
          "height": 320,
          "mimetype": "image/jpeg",
          "secret": "4SPFibUogA9VHWcsnH6snxAUrduEdT8u",
          "width": 320
        },
        "z": {
          "extension": "jpg",
          "height": 287,
          "mimetype": "image/jpeg",
          "secret": "4SPFibUogA9VHWcsnH6snxAUrduEdT8u",
          "width": 640
        }
      }
    },
    "media:uri_template": "https://millsfield.sfomuseum.org/media/152/782/913/9/1527829139_{secret}_{label}.{extention}",
    "sfomuseum:filename": "47534.tif",
    "sfomuseum:image_index": 5,
    "sfomuseum:placetype": "image",
    "sfomuseum:primary_image": 1,
    "wof:depicts": [
      1511907289
    ],
    "wof:name": "airmail flight cover: United States Air Mail, FAM-19, Canton Island - Los Angeles route",
    "wof:placetype": "media"
  },
  "geometry": {"coordinates":[-122.386155,37.616358],"type":"Point"}
}
