{
  "type": "Feature",
  "properties": {
    "media:fingerprint": "72d5430c22435593bcf7ab0160d21bb68fa264cc",
    "media:imagehash_avg": "a:0001ffffff3f0301",
    "media:imagehash_diff": "d:0369ffbbbbfb276f",
    "media:mimetype": "image/tiff",
    "media:properties": {
      "colours": [
        {
          "hex": "#b40000",
          "name": "#b40000",
          "reference": "vibrant"
        },
        {
          "hex": "#eac978",
          "name": "#eac978",
          "reference": "vibrant"
        },
        {
          "hex": "#b30901",
          "name": "#b30901",
          "reference": "vibrant"
        },
        {
          "hex": "#ac9978",
          "name": "#ac9978",
          "reference": "vibrant"
        },
        {
          "hex": "#d8c8a8",
          "name": "#d8c8a8",
          "reference": "vibrant"
        }
      ],
      "sizes": {
        "b": {
          "extension": "jpg",
          "height": 539,
          "mimetype": "image/jpeg",
          "secret": "3lxh8t4PZJQXHfUCW2owfQJFctHuLqeF",
          "width": 1023
        },
        "c": {
          "extension": "jpg",
          "height": 421,
          "mimetype": "image/jpeg",
          "secret": "3lxh8t4PZJQXHfUCW2owfQJFctHuLqeF",
          "width": 800
        },
        "dc": {
          "extension": "jpg",
          "height": 421,
          "mimetype": "image/jpeg",
          "secret": "3lxh8t4PZJQXHfUCW2owfQJFctHuLqeF",
          "width": 800
        },
        "ds": {
          "extension": "jpg",
          "height": 320,
          "mimetype": "image/jpeg",
          "secret": "3lxh8t4PZJQXHfUCW2owfQJFctHuLqeF",
          "width": 320
        },
        "k": {
          "extension": "jpg",
          "height": 1078,
          "mimetype": "image/jpeg",
          "secret": "3lxh8t4PZJQXHfUCW2owfQJFctHuLqeF",
          "width": 2047
        },
        "n": {
          "extension": "jpg",
          "height": 168,
          "mimetype": "image/jpeg",
          "secret": "3lxh8t4PZJQXHfUCW2owfQJFctHuLqeF",
          "width": 320
        },
        "o": {
          "extension": "jpg",
          "height": 1052,
          "mimetype": "image/jpeg",
          "secret": "e3wp7dgk6TnbM9feURUOw39OT3LeUwsX",
          "width": 1997
        },
        "s": {
          "extension": "jpg",
          "height": 320,
          "mimetype": "image/jpeg",
          "secret": "3lxh8t4PZJQXHfUCW2owfQJFctHuLqeF",
          "width": 320
        },
        "z": {
          "extension": "jpg",
          "height": 337,
          "mimetype": "image/jpeg",
          "secret": "3lxh8t4PZJQXHfUCW2owfQJFctHuLqeF",
          "width": 640
        }
      }
    },
    "media:uri_template": "https://static.sfomuseum.org/media/174/668/089/9/1746680899_{secret}_{label}.{extention}",
    "sfomuseum:filename": "1999.024.022_fr.tif",
    "sfomuseum:image_index": 1,
    "sfomuseum:image_type": "curator",
    "sfomuseum:placetype": "image",
    "sfomuseum:primary_image": 1,
    "wof:depicts": [
      1511909213
    ],
    "wof:name": "shipping calculator: Air Express",
    "wof:placetype": "custom"
  },
  "geometry": {"coordinates":[-122.386155,37.616357],"type":"Point"}
}
