{
  "type": "Feature",
  "properties": {
    "iso:country": "XX",
    "media:fingerprint": "e455258833d4292a9bad98e6c1d3b5477984e76c",
    "media:imagehash_avg": "a:fffc808080818fff",
    "media:imagehash_diff": "d:7d1901050d6d7967",
    "media:medium": "image",
    "media:mimetype": "image/tiff",
    "media:properties": {
      "colours": [
        {
          "hex": "#95320a",
          "name": "#95320a",
          "reference": "vibrant"
        },
        {
          "hex": "#d6c168",
          "name": "#d6c168",
          "reference": "vibrant"
        },
        {
          "hex": "#27465f",
          "name": "#27465f",
          "reference": "vibrant"
        },
        {
          "hex": "#568c95",
          "name": "#568c95",
          "reference": "vibrant"
        },
        {
          "hex": "#d4c9ab",
          "name": "#d4c9ab",
          "reference": "vibrant"
        }
      ],
      "sizes": {
        "b": {
          "extension": "jpg",
          "height": 768,
          "mimetype": "image/jpeg",
          "secret": "eFfe81iuxy5jDeKjpJegLnEeYeo80wfV",
          "width": 632
        },
        "c": {
          "extension": "jpg",
          "height": 600,
          "mimetype": "image/jpeg",
          "secret": "eFfe81iuxy5jDeKjpJegLnEeYeo80wfV",
          "width": 493
        },
        "dc": {
          "extension": "jpg",
          "height": 600,
          "mimetype": "image/jpeg",
          "secret": "eFfe81iuxy5jDeKjpJegLnEeYeo80wfV",
          "width": 493
        },
        "ds": {
          "extension": "jpg",
          "height": 320,
          "mimetype": "image/jpeg",
          "secret": "eFfe81iuxy5jDeKjpJegLnEeYeo80wfV",
          "width": 320
        },
        "k": {
          "extension": "jpg",
          "height": 1536,
          "mimetype": "image/jpeg",
          "secret": "eFfe81iuxy5jDeKjpJegLnEeYeo80wfV",
          "width": 1264
        },
        "n": {
          "extension": "jpg",
          "height": 240,
          "mimetype": "image/jpeg",
          "secret": "eFfe81iuxy5jDeKjpJegLnEeYeo80wfV",
          "width": 197
        },
        "o": {
          "extension": "jpg",
          "height": 1941,
          "mimetype": "image/jpeg",
          "secret": "vkiNQCcXtuvw1Ivi28DwJ5kSEMN05cOA",
          "width": 1598
        },
        "s": {
          "extension": "jpg",
          "height": 320,
          "mimetype": "image/jpeg",
          "secret": "eFfe81iuxy5jDeKjpJegLnEeYeo80wfV",
          "width": 320
        },
        "z": {
          "extension": "jpg",
          "height": 480,
          "mimetype": "image/jpeg",
          "secret": "eFfe81iuxy5jDeKjpJegLnEeYeo80wfV",
          "width": 395
        }
      }
    },
    "media:uri_template": "https://static.sfomuseum.org/media/152/784/815/3/1527848153_{secret}_{label}.{extention}",
    "sfomuseum:filename": "2005008066_front.tif",
    "sfomuseum:image_index": 5,
    "sfomuseum:image_type": "studio",
    "sfomuseum:placetype": "image",
    "sfomuseum:primary_image": 1,
    "wof:depicts": [
      1159285413,
      1511925643
    ],
    "wof:name": "menu: United Airlines",
    "wof:placetype": "custom",
    "wof:placetype_alt": "image"
  },
  "geometry": {"coordinates":[-122.386155,37.616358],"type":"Point"}
}
