{
  "type": "Feature",
  "properties": {
    "iso:country": "XX",
    "media:fingerprint": "138882b75ebfd9d0ca2f437034979789500da767",
    "media:imagehash_avg": "a:7e7f7f64647f7f00",
    "media:imagehash_diff": "d:d5f4b28dcdcdcd89",
    "media:medium": "image",
    "media:mimetype": "image/tiff",
    "media:properties": {
      "colours": [
        {
          "hex": "#dd4535",
          "name": "#dd4535",
          "reference": "vibrant"
        }, 
        {
          "hex": "#ec9693",
          "name": "#ec9693",
          "reference": "vibrant"
        }, 
        {
          "hex": "#898878",
          "name": "#898878",
          "reference": "vibrant"
        }, 
        {
          "hex": "#cbc2b6",
          "name": "#cbc2b6",
          "reference": "vibrant"
        }, 
        {
          "hex": "#57564e",
          "name": "#57564e",
          "reference": "vibrant"
        }
      ],
      "sizes": {
        "b": {
          "extension": "jpg",
          "height": 768,
          "mimetype": "image/jpeg",
          "secret": "5JePJze1fWhtEA3d0xlstbyuKDbrdMwM",
          "width": 412
        },
        "c": {
          "extension": "jpg",
          "height": 600,
          "mimetype": "image/jpeg",
          "secret": "5JePJze1fWhtEA3d0xlstbyuKDbrdMwM",
          "width": 322
        },
        "dc": {
          "extension": "jpg",
          "height": 600,
          "mimetype": "image/jpeg",
          "secret": "5JePJze1fWhtEA3d0xlstbyuKDbrdMwM",
          "width": 322
        },
        "ds": {
          "extension": "jpg",
          "height": 320,
          "mimetype": "image/jpeg",
          "secret": "5JePJze1fWhtEA3d0xlstbyuKDbrdMwM",
          "width": 320
        },
        "k": {
          "extension": "jpg",
          "height": 1536,
          "mimetype": "image/jpeg",
          "secret": "5JePJze1fWhtEA3d0xlstbyuKDbrdMwM",
          "width": 824
        },
        "n": {
          "extension": "jpg",
          "height": 240,
          "mimetype": "image/jpeg",
          "secret": "5JePJze1fWhtEA3d0xlstbyuKDbrdMwM",
          "width": 128
        },
        "o": {
          "extension": "jpg",
          "height": 2916,
          "mimetype": "image/jpeg",
          "secret": "IV1nFZi1zPIcSVb2KJEMXbUkdLNLW5E8",
          "width": 1566
        },
        "s": {
          "extension": "jpg",
          "height": 320,
          "mimetype": "image/jpeg",
          "secret": "5JePJze1fWhtEA3d0xlstbyuKDbrdMwM",
          "width": 320
        },
        "z": {
          "extension": "jpg",
          "height": 480,
          "mimetype": "image/jpeg",
          "secret": "5JePJze1fWhtEA3d0xlstbyuKDbrdMwM",
          "width": 257
        }
      }
    },
    "media:uri_template": "https://millsfield.sfomuseum.org/media/152/782/364/3/1527823643_{secret}_{label}.{extention}",
    "sfomuseum:filename": "41699.tif",
    "sfomuseum:image_index": 5,
    "sfomuseum:placetype": "image",
    "sfomuseum:primary_image": 1,
    "wof:depicts": [
      1511908473
    ],
    "wof:name": "airsickness bag: British Midland Airways",
    "wof:placetype": "media"
  },
  "geometry": {"coordinates":[-122.386155,37.616358],"type":"Point"}
}
