{
  "type": "Feature",
  "properties": {
    "iso:country": "XX",
    "media:fingerprint": "a9e224daf425e477ba9e66754b6c0db3e33e1664",
    "media:imagehash_avg": "a:ff819f8183818fff",
    "media:imagehash_diff": "d:617777270f4f3f5e",
    "media:medium": "image",
    "media:mimetype": "image/tiff",
    "media:properties": {
      "colours": [
        {
          "hex": "#cd8969",
          "name": "#cd8969",
          "reference": "vibrant"
        },
        {
          "hex": "#efe8cc",
          "name": "#efe8cc",
          "reference": "vibrant"
        },
        {
          "hex": "#9e9a76",
          "name": "#9e9a76",
          "reference": "vibrant"
        },
        {
          "hex": "#d4cca7",
          "name": "#d4cca7",
          "reference": "vibrant"
        },
        {
          "hex": "#3a3a4e",
          "name": "#3a3a4e",
          "reference": "vibrant"
        }
      ],
      "sizes": {
        "b": {
          "extension": "jpg",
          "height": 736,
          "mimetype": "image/jpeg",
          "secret": "kf7GJ6eEHlioJFr9Dt7BLeQsnLMzcHbS",
          "width": 1024
        },
        "c": {
          "extension": "jpg",
          "height": 575,
          "mimetype": "image/jpeg",
          "secret": "kf7GJ6eEHlioJFr9Dt7BLeQsnLMzcHbS",
          "width": 800
        },
        "dc": {
          "extension": "jpg",
          "height": 575,
          "mimetype": "image/jpeg",
          "secret": "kf7GJ6eEHlioJFr9Dt7BLeQsnLMzcHbS",
          "width": 800
        },
        "ds": {
          "extension": "jpg",
          "height": 320,
          "mimetype": "image/jpeg",
          "secret": "kf7GJ6eEHlioJFr9Dt7BLeQsnLMzcHbS",
          "width": 320
        },
        "k": {
          "extension": "jpg",
          "height": 1473,
          "mimetype": "image/jpeg",
          "secret": "kf7GJ6eEHlioJFr9Dt7BLeQsnLMzcHbS",
          "width": 2048
        },
        "n": {
          "extension": "jpg",
          "height": 230,
          "mimetype": "image/jpeg",
          "secret": "kf7GJ6eEHlioJFr9Dt7BLeQsnLMzcHbS",
          "width": 320
        },
        "o": {
          "extension": "jpg",
          "height": 1522,
          "mimetype": "image/jpeg",
          "secret": "5efkuqTlMYc2hHe9XGvjn96OTPxzdVWu",
          "width": 2116
        },
        "s": {
          "extension": "jpg",
          "height": 320,
          "mimetype": "image/jpeg",
          "secret": "kf7GJ6eEHlioJFr9Dt7BLeQsnLMzcHbS",
          "width": 320
        },
        "z": {
          "extension": "jpg",
          "height": 460,
          "mimetype": "image/jpeg",
          "secret": "kf7GJ6eEHlioJFr9Dt7BLeQsnLMzcHbS",
          "width": 640
        }
      }
    },
    "media:uri_template": "https://millsfield.sfomuseum.org/media/152/784/614/9/1527846149_{secret}_{label}.{extention}",
    "sfomuseum:filename": "2001080203_front.tif",
    "sfomuseum:image_index": 5,
    "sfomuseum:placetype": "image",
    "sfomuseum:primary_image": 1,
    "wof:depicts": [
      1511922125
    ],
    "wof:name": "menu: Pan American World Airways, Historic First Flights series, Boeing 314",
    "wof:placetype": "custom",
    "wof:placetype_alt": "image"
  },
  "geometry": {"coordinates":[-122.386155,37.616358],"type":"Point"}
}
