{
  "type": "Feature",
  "properties": {
    "iso:country": "XX",
    "media:fingerprint": "465f239bfe6d853e6e7c76e1493e9c155d2f9ba0",
    "media:imagehash_avg": "a:ffffff1f01000000",
    "media:imagehash_diff": "d:beecf83a3b1aa29c",
    "media:medium": "image",
    "media:mimetype": "image/tiff",
    "media:properties": {
      "colours": [
        {
          "hex": "#808080",
          "name": "#808080",
          "reference": "vibrant"
        },
        {
          "hex": "#c0c0c0",
          "name": "#c0c0c0",
          "reference": "vibrant"
        },
        {
          "hex": "#464646",
          "name": "#464646",
          "reference": "vibrant"
        }
      ],
      "sizes": {
        "b": {
          "extension": "jpg",
          "height": 730,
          "mimetype": "image/jpeg",
          "secret": "v2vtQqi1rquKX9WKG9Li3xVKjpzfcBRH",
          "width": 1024
        },
        "c": {
          "extension": "jpg",
          "height": 570,
          "mimetype": "image/jpeg",
          "secret": "v2vtQqi1rquKX9WKG9Li3xVKjpzfcBRH",
          "width": 800
        },
        "dc": {
          "extension": "jpg",
          "height": 570,
          "mimetype": "image/jpeg",
          "secret": "v2vtQqi1rquKX9WKG9Li3xVKjpzfcBRH",
          "width": 800
        },
        "ds": {
          "extension": "jpg",
          "height": 320,
          "mimetype": "image/jpeg",
          "secret": "v2vtQqi1rquKX9WKG9Li3xVKjpzfcBRH",
          "width": 320
        },
        "k": {
          "extension": "jpg",
          "height": 1460,
          "mimetype": "image/jpeg",
          "secret": "v2vtQqi1rquKX9WKG9Li3xVKjpzfcBRH",
          "width": 2048
        },
        "n": {
          "extension": "jpg",
          "height": 228,
          "mimetype": "image/jpeg",
          "secret": "v2vtQqi1rquKX9WKG9Li3xVKjpzfcBRH",
          "width": 320
        },
        "o": {
          "extension": "jpg",
          "height": 1495,
          "mimetype": "image/jpeg",
          "secret": "vmsbODC1qtldiWSaLH6ycwXUj7yqVC6u",
          "width": 2097
        },
        "s": {
          "extension": "jpg",
          "height": 320,
          "mimetype": "image/jpeg",
          "secret": "v2vtQqi1rquKX9WKG9Li3xVKjpzfcBRH",
          "width": 320
        },
        "z": {
          "extension": "jpg",
          "height": 456,
          "mimetype": "image/jpeg",
          "secret": "v2vtQqi1rquKX9WKG9Li3xVKjpzfcBRH",
          "width": 640
        }
      }
    },
    "media:uri_template": "https://static.sfomuseum.org/media/152/783/125/7/1527831257_{secret}_{label}.{extention}",
    "sfomuseum:filename": "58295.tif",
    "sfomuseum:image_index": 5,
    "sfomuseum:image_type": "studio",
    "sfomuseum:placetype": "image",
    "sfomuseum:primary_image": 1,
    "wof:depicts": [
      1511955507
    ],
    "wof:name": "glass negative: Panama-Pacific International Exposition",
    "wof:placetype": "custom",
    "wof:placetype_alt": "image"
  },
  "geometry": {"coordinates":[-122.386155,37.616358],"type":"Point"}
}
