{
  "type": "Feature",
  "properties": {
    "iso:country": "XX",
    "media:fingerprint": "e64fef54ae1e163ad7c246523f7a9ebc201cb635",
    "media:imagehash_avg": "a:3f3f3f0e0e0e0400",
    "media:imagehash_diff": "d:f9f0fc787cfcfcfc",
    "media:medium": "image",
    "media:mimetype": "image/tiff",
    "media:properties": {
      "colours": [
        {
          "hex": "#868686",
          "name": "#868686",
          "reference": "vibrant"
        }, 
        {
          "hex": "#c0c0c0",
          "name": "#c0c0c0",
          "reference": "vibrant"
        }, 
        {
          "hex": "#484848",
          "name": "#484848",
          "reference": "vibrant"
        }
      ],
      "sizes": {
        "b": {
          "extension": "jpg",
          "height": 693,
          "mimetype": "image/jpeg",
          "secret": "TDlQHaoEq8Q2DQlHhHmomvuFTQK9Xpzs",
          "width": 1024
        },
        "c": {
          "extension": "jpg",
          "height": 542,
          "mimetype": "image/jpeg",
          "secret": "TDlQHaoEq8Q2DQlHhHmomvuFTQK9Xpzs",
          "width": 800
        },
        "dc": {
          "extension": "jpg",
          "height": 542,
          "mimetype": "image/jpeg",
          "secret": "TDlQHaoEq8Q2DQlHhHmomvuFTQK9Xpzs",
          "width": 800
        },
        "ds": {
          "extension": "jpg",
          "height": 320,
          "mimetype": "image/jpeg",
          "secret": "TDlQHaoEq8Q2DQlHhHmomvuFTQK9Xpzs",
          "width": 320
        },
        "k": {
          "extension": "jpg",
          "height": 1387,
          "mimetype": "image/jpeg",
          "secret": "TDlQHaoEq8Q2DQlHhHmomvuFTQK9Xpzs",
          "width": 2048
        },
        "n": {
          "extension": "jpg",
          "height": 216,
          "mimetype": "image/jpeg",
          "secret": "TDlQHaoEq8Q2DQlHhHmomvuFTQK9Xpzs",
          "width": 320
        },
        "o": {
          "extension": "jpg",
          "height": 1076,
          "mimetype": "image/jpeg",
          "secret": "bNGZ4rHZ5JSswJ3H5ZTnyDo2ONBJOnbw",
          "width": 1588
        },
        "s": {
          "extension": "jpg",
          "height": 320,
          "mimetype": "image/jpeg",
          "secret": "TDlQHaoEq8Q2DQlHhHmomvuFTQK9Xpzs",
          "width": 320
        },
        "z": {
          "extension": "jpg",
          "height": 433,
          "mimetype": "image/jpeg",
          "secret": "TDlQHaoEq8Q2DQlHhHmomvuFTQK9Xpzs",
          "width": 640
        }
      }
    },
    "media:uri_template": "https://millsfield.sfomuseum.org/media/152/782/842/1/1527828421_{secret}_{label}.{extention}",
    "sfomuseum:filename": "44584.tif",
    "sfomuseum:image_index": 5,
    "sfomuseum:placetype": "image",
    "sfomuseum:primary_image": 1,
    "wof:depicts": [
      1511949453
    ],
    "wof:name": "negative: San Francisco International Airport (SFO), Central Terminal lobby",
    "wof:placetype": "media"
  },
  "geometry": {"coordinates":[-122.386155,37.616358],"type":"Point"}
}
