{
  "type": "Feature",
  "properties": {
    "iso:country": "XX",
    "media:fingerprint": "f7e48b1cf764992760333b51b2e70f4f5eeefc3d",
    "media:imagehash_avg": "a:fffe3c201c1c0800",
    "media:imagehash_diff": "d:e07061e0e8f0f8f0",
    "media:medium": "image",
    "media:mimetype": "image/tiff",
    "media:properties": {
      "colours": [
        {
          "hex": "#808080",
          "name": "#808080",
          "reference": "vibrant"
        }, 
        {
          "hex": "#bababa",
          "name": "#bababa",
          "reference": "vibrant"
        }, 
        {
          "hex": "#484848",
          "name": "#484848",
          "reference": "vibrant"
        }
      ],
      "sizes": {
        "b": {
          "extension": "jpg",
          "height": 768,
          "mimetype": "image/jpeg",
          "secret": "vibrqfNM3L8MuDqFDypKdKB8QvrOHyun",
          "width": 980
        },
        "c": {
          "extension": "jpg",
          "height": 600,
          "mimetype": "image/jpeg",
          "secret": "vibrqfNM3L8MuDqFDypKdKB8QvrOHyun",
          "width": 766
        },
        "dc": {
          "extension": "jpg",
          "height": 600,
          "mimetype": "image/jpeg",
          "secret": "vibrqfNM3L8MuDqFDypKdKB8QvrOHyun",
          "width": 766
        },
        "ds": {
          "extension": "jpg",
          "height": 320,
          "mimetype": "image/jpeg",
          "secret": "vibrqfNM3L8MuDqFDypKdKB8QvrOHyun",
          "width": 320
        },
        "k": {
          "extension": "jpg",
          "height": 1536,
          "mimetype": "image/jpeg",
          "secret": "vibrqfNM3L8MuDqFDypKdKB8QvrOHyun",
          "width": 1961
        },
        "n": {
          "extension": "jpg",
          "height": 240,
          "mimetype": "image/jpeg",
          "secret": "vibrqfNM3L8MuDqFDypKdKB8QvrOHyun",
          "width": 306
        },
        "o": {
          "extension": "jpg",
          "height": 2168,
          "mimetype": "image/jpeg",
          "secret": "GXimt7ajmJdsruhpnvUjNMin51FwTBrU",
          "width": 2768
        },
        "s": {
          "extension": "jpg",
          "height": 320,
          "mimetype": "image/jpeg",
          "secret": "vibrqfNM3L8MuDqFDypKdKB8QvrOHyun",
          "width": 320
        },
        "z": {
          "extension": "jpg",
          "height": 480,
          "mimetype": "image/jpeg",
          "secret": "vibrqfNM3L8MuDqFDypKdKB8QvrOHyun",
          "width": 612
        }
      }
    },
    "media:uri_template": "https://millsfield.sfomuseum.org/media/152/782/609/1/1527826091_{secret}_{label}.{extention}",
    "sfomuseum:filename": "43485.tif",
    "sfomuseum:image_index": 5,
    "sfomuseum:placetype": "image",
    "sfomuseum:primary_image": 1,
    "wof:depicts": [
      1511947127
    ],
    "wof:name": "negative: San Francisco International Airport (SFO), aerial",
    "wof:placetype": "media"
  },
  "geometry": {"coordinates":[-122.386155,37.616358],"type":"Point"}
}
