{
  "type": "Feature",
  "properties": {
    "sfomuseum:filename": "L2020.2501.004.jpg",
    "sfomuseum:image_index": 0,
    "sfomuseum:image_type": "curator",
    "sfomuseum:placetype": "image",
    "sfomuseum:primary_image": 1,
    "wof:depicts": [
      1159284025,
      1729564771,
      1159286739
    ],
    "wof:name": "ashtray: British Commonwealth Pacific Airlines (BCPA)",
    "wof:placetype": "custom"
  },
  "geometry": {"coordinates":[-122.386155,37.616357],"type":"Point"}
}
