{
  "type": "Feature",
  "properties": {
    "media:fingerprint": "757c43d9dfe232bac326e850cbb4c1478765da7d",
    "media:imagehash_avg": "a:e7818100008181ef",
    "media:imagehash_diff": "d:0f3371715569330f",
    "media:mimetype": "image/jpeg",
    "media:properties": {
      "colours": [
        {
          "hex": "#915e11",
          "name": "#915e11",
          "reference": "vibrant"
        },
        {
          "hex": "#d6b185",
          "name": "#d6b185",
          "reference": "vibrant"
        },
        {
          "hex": "#874701",
          "name": "#874701",
          "reference": "vibrant"
        },
        {
          "hex": "#9d8154",
          "name": "#9d8154",
          "reference": "vibrant"
        },
        {
          "hex": "#beb7b2",
          "name": "#beb7b2",
          "reference": "vibrant"
        }
      ],
      "sizes": {
        "b": {
          "extension": "jpg",
          "height": 768,
          "mimetype": "image/jpeg",
          "secret": "ZbWZq1keNgsja3kgbS0Uxd6shQxtDaAE",
          "width": 806
        },
        "c": {
          "extension": "jpg",
          "height": 600,
          "mimetype": "image/jpeg",
          "secret": "ZbWZq1keNgsja3kgbS0Uxd6shQxtDaAE",
          "width": 629
        },
        "dc": {
          "extension": "jpg",
          "height": 600,
          "mimetype": "image/jpeg",
          "secret": "ZbWZq1keNgsja3kgbS0Uxd6shQxtDaAE",
          "width": 629
        },
        "ds": {
          "extension": "jpg",
          "height": 320,
          "mimetype": "image/jpeg",
          "secret": "ZbWZq1keNgsja3kgbS0Uxd6shQxtDaAE",
          "width": 320
        },
        "k": {
          "extension": "jpg",
          "height": 1536,
          "mimetype": "image/jpeg",
          "secret": "ZbWZq1keNgsja3kgbS0Uxd6shQxtDaAE",
          "width": 1612
        },
        "n": {
          "extension": "jpg",
          "height": 240,
          "mimetype": "image/jpeg",
          "secret": "ZbWZq1keNgsja3kgbS0Uxd6shQxtDaAE",
          "width": 251
        },
        "o": {
          "extension": "jpg",
          "height": 1429,
          "mimetype": "image/jpeg",
          "secret": "MBQUV3Imn4v1HygbgluFjEf0vbzcw7w5",
          "width": 1500
        },
        "s": {
          "extension": "jpg",
          "height": 320,
          "mimetype": "image/jpeg",
          "secret": "ZbWZq1keNgsja3kgbS0Uxd6shQxtDaAE",
          "width": 320
        },
        "z": {
          "extension": "jpg",
          "height": 480,
          "mimetype": "image/jpeg",
          "secret": "ZbWZq1keNgsja3kgbS0Uxd6shQxtDaAE",
          "width": 503
        }
      }
    },
    "media:uri_template": "https://static.sfomuseum.org/media/174/668/136/9/1746681369_{secret}_{label}.{extention}",
    "sfomuseum:filename": "L2020.2501.004.jpg",
    "sfomuseum:image_index": 0,
    "sfomuseum:image_type": "curator",
    "sfomuseum:placetype": "image",
    "sfomuseum:primary_image": 1,
    "wof:depicts": [
      1159286739,
      1159284025,
      1729564771
    ],
    "wof:name": "ashtray: British Commonwealth Pacific Airlines (BCPA)",
    "wof:placetype": "custom"
  },
  "geometry": {"coordinates":[-122.386155,37.616357],"type":"Point"}
}
