{
  "type": "Feature",
  "properties": {
    "iso:country": "XX",
    "media:fingerprint": "73fbb352e68f37c6c88e9d9913aeaee59837ff31",
    "media:imagehash_avg": "a:fefe7f3f3f7f0600",
    "media:imagehash_diff": "d:1cdcf8e066f1fef3",
    "media:medium": "image",
    "media:mimetype": "image/tiff",
    "media:properties": {
      "colours": [
        {
          "hex": "#808080",
          "name": "#808080",
          "reference": "vibrant"
        }, 
        {
          "hex": "#b8b8b8",
          "name": "#b8b8b8",
          "reference": "vibrant"
        }, 
        {
          "hex": "#464646",
          "name": "#464646",
          "reference": "vibrant"
        }
      ],
      "sizes": {
        "b": {
          "extension": "jpg",
          "height": 768,
          "mimetype": "image/jpeg",
          "secret": "BC4lb2dTkcP5Fi2PKFdVvZae083dFTxh",
          "width": 981
        },
        "c": {
          "extension": "jpg",
          "height": 600,
          "mimetype": "image/jpeg",
          "secret": "BC4lb2dTkcP5Fi2PKFdVvZae083dFTxh",
          "width": 767
        },
        "dc": {
          "extension": "jpg",
          "height": 600,
          "mimetype": "image/jpeg",
          "secret": "BC4lb2dTkcP5Fi2PKFdVvZae083dFTxh",
          "width": 767
        },
        "ds": {
          "extension": "jpg",
          "height": 320,
          "mimetype": "image/jpeg",
          "secret": "BC4lb2dTkcP5Fi2PKFdVvZae083dFTxh",
          "width": 320
        },
        "k": {
          "extension": "jpg",
          "height": 1536,
          "mimetype": "image/jpeg",
          "secret": "BC4lb2dTkcP5Fi2PKFdVvZae083dFTxh",
          "width": 1963
        },
        "n": {
          "extension": "jpg",
          "height": 240,
          "mimetype": "image/jpeg",
          "secret": "BC4lb2dTkcP5Fi2PKFdVvZae083dFTxh",
          "width": 306
        },
        "o": {
          "extension": "jpg",
          "height": 2154,
          "mimetype": "image/jpeg",
          "secret": "kfnyj3HKjT0eYf7RgW84sUrOiIWAysEh",
          "width": 2754
        },
        "s": {
          "extension": "jpg",
          "height": 320,
          "mimetype": "image/jpeg",
          "secret": "BC4lb2dTkcP5Fi2PKFdVvZae083dFTxh",
          "width": 320
        },
        "z": {
          "extension": "jpg",
          "height": 480,
          "mimetype": "image/jpeg",
          "secret": "BC4lb2dTkcP5Fi2PKFdVvZae083dFTxh",
          "width": 613
        }
      }
    },
    "media:uri_template": "https://millsfield.sfomuseum.org/media/152/782/437/1/1527824371_{secret}_{label}.{extention}",
    "sfomuseum:filename": "42392.tif",
    "sfomuseum:image_index": 5,
    "sfomuseum:placetype": "image",
    "sfomuseum:primary_image": 1,
    "wof:depicts": [
      1511945693
    ],
    "wof:name": "negative: San Francisco, view of Bayview",
    "wof:placetype": "media"
  },
  "geometry": {"coordinates":[-122.386155,37.616358],"type":"Point"}
}
