{
  "type": "Feature",
  "properties": {
    "iso:country": "XX",
    "media:fingerprint": "71b17968fc4b34c4326045a267d0378b876dd0ed",
    "media:imagehash_avg": "a:18ff7e7e38181818",
    "media:imagehash_diff": "d:f0dcc8f27173f3f3",
    "media:medium": "image",
    "media:mimetype": "image/tiff",
    "media:properties": {
      "colours": [
        {
          "hex": "#808080",
          "name": "#808080",
          "reference": "vibrant"
        }, 
        {
          "hex": "#b5b5b5",
          "name": "#b5b5b5",
          "reference": "vibrant"
        }, 
        {
          "hex": "#404040",
          "name": "#404040",
          "reference": "vibrant"
        }
      ],
      "sizes": {
        "b": {
          "extension": "jpg",
          "height": 768,
          "mimetype": "image/jpeg",
          "secret": "hF4d6ATEC7TqArTKJm8f6OKc3Qb6Gl8m",
          "width": 984
        },
        "c": {
          "extension": "jpg",
          "height": 600,
          "mimetype": "image/jpeg",
          "secret": "hF4d6ATEC7TqArTKJm8f6OKc3Qb6Gl8m",
          "width": 768
        },
        "dc": {
          "extension": "jpg",
          "height": 600,
          "mimetype": "image/jpeg",
          "secret": "hF4d6ATEC7TqArTKJm8f6OKc3Qb6Gl8m",
          "width": 768
        },
        "ds": {
          "extension": "jpg",
          "height": 320,
          "mimetype": "image/jpeg",
          "secret": "hF4d6ATEC7TqArTKJm8f6OKc3Qb6Gl8m",
          "width": 320
        },
        "k": {
          "extension": "jpg",
          "height": 1536,
          "mimetype": "image/jpeg",
          "secret": "hF4d6ATEC7TqArTKJm8f6OKc3Qb6Gl8m",
          "width": 1968
        },
        "n": {
          "extension": "jpg",
          "height": 240,
          "mimetype": "image/jpeg",
          "secret": "hF4d6ATEC7TqArTKJm8f6OKc3Qb6Gl8m",
          "width": 307
        },
        "o": {
          "extension": "jpg",
          "height": 2181,
          "mimetype": "image/jpeg",
          "secret": "lT34VvMmsFrdUGDiSH8RQSPyQTMVDmNB",
          "width": 2795
        },
        "s": {
          "extension": "jpg",
          "height": 320,
          "mimetype": "image/jpeg",
          "secret": "hF4d6ATEC7TqArTKJm8f6OKc3Qb6Gl8m",
          "width": 320
        },
        "z": {
          "extension": "jpg",
          "height": 480,
          "mimetype": "image/jpeg",
          "secret": "hF4d6ATEC7TqArTKJm8f6OKc3Qb6Gl8m",
          "width": 615
        }
      }
    },
    "media:uri_template": "https://millsfield.sfomuseum.org/media/152/782/154/3/1527821543_{secret}_{label}.{extention}",
    "sfomuseum:filename": "38860.tif",
    "sfomuseum:image_index": 5,
    "sfomuseum:placetype": "image",
    "sfomuseum:primary_image": 1,
    "wof:depicts": [
      1511943627
    ],
    "wof:name": "negative: San Francisco Airport, meeting with National Security Resources Board",
    "wof:placetype": "media"
  },
  "geometry": {"coordinates":[-122.386155,37.616358],"type":"Point"}
}
