{
  "type": "Feature",
  "properties": {
    "iso:country": "XX",
    "media:fingerprint": "e8c07e593077565da3fdb39cd4cd02127fbe9d60",
    "media:imagehash_avg": "a:fffef8fc1c000000",
    "media:imagehash_diff": "d:81808070fcecfddd",
    "media:medium": "image",
    "media:mimetype": "image/tiff",
    "media:properties": {
      "colours": [
        {
          "hex": "#868686",
          "name": "#868686",
          "reference": "vibrant"
        }, 
        {
          "hex": "#b8b8b8",
          "name": "#b8b8b8",
          "reference": "vibrant"
        }, 
        {
          "hex": "#484848",
          "name": "#484848",
          "reference": "vibrant"
        }
      ],
      "sizes": {
        "b": {
          "extension": "jpg",
          "height": 768,
          "mimetype": "image/jpeg",
          "secret": "tOl3BCNsZah3X5sVkLVJNQPMBFKYaZrb",
          "width": 970
        },
        "c": {
          "extension": "jpg",
          "height": 600,
          "mimetype": "image/jpeg",
          "secret": "tOl3BCNsZah3X5sVkLVJNQPMBFKYaZrb",
          "width": 758
        },
        "dc": {
          "extension": "jpg",
          "height": 600,
          "mimetype": "image/jpeg",
          "secret": "tOl3BCNsZah3X5sVkLVJNQPMBFKYaZrb",
          "width": 758
        },
        "ds": {
          "extension": "jpg",
          "height": 320,
          "mimetype": "image/jpeg",
          "secret": "tOl3BCNsZah3X5sVkLVJNQPMBFKYaZrb",
          "width": 320
        },
        "k": {
          "extension": "jpg",
          "height": 1536,
          "mimetype": "image/jpeg",
          "secret": "tOl3BCNsZah3X5sVkLVJNQPMBFKYaZrb",
          "width": 1941
        },
        "n": {
          "extension": "jpg",
          "height": 240,
          "mimetype": "image/jpeg",
          "secret": "tOl3BCNsZah3X5sVkLVJNQPMBFKYaZrb",
          "width": 303
        },
        "o": {
          "extension": "jpg",
          "height": 2168,
          "mimetype": "image/jpeg",
          "secret": "Jjn5uU7SXWL1gEBr3BgOiQXfNILJU6aL",
          "width": 2740
        },
        "s": {
          "extension": "jpg",
          "height": 320,
          "mimetype": "image/jpeg",
          "secret": "tOl3BCNsZah3X5sVkLVJNQPMBFKYaZrb",
          "width": 320
        },
        "z": {
          "extension": "jpg",
          "height": 480,
          "mimetype": "image/jpeg",
          "secret": "tOl3BCNsZah3X5sVkLVJNQPMBFKYaZrb",
          "width": 606
        }
      }
    },
    "media:uri_template": "https://millsfield.sfomuseum.org/media/152/782/422/7/1527824227_{secret}_{label}.{extention}",
    "sfomuseum:filename": "42325.tif",
    "sfomuseum:image_index": 5,
    "sfomuseum:placetype": "image",
    "sfomuseum:primary_image": 1,
    "wof:depicts": [
      1511945549
    ],
    "wof:name": "negative: San Francisco International Airport (SFO), aerial",
    "wof:placetype": "media"
  },
  "geometry": {"coordinates":[-122.386155,37.616358],"type":"Point"}
}
