{
  "type": "Feature",
  "properties": {
    "iso:country": "XX",
    "media:fingerprint": "f33078c59b5c5f50788dc72013292d4818c0eebe",
    "media:imagehash_avg": "a:fffffff301000000",
    "media:imagehash_diff": "d:e0a08207d3f6f8f8",
    "media:medium": "image",
    "media:mimetype": "image/tiff",
    "media:properties": {
      "colours": [
        {
          "hex": "#868686",
          "name": "#868686",
          "reference": "vibrant"
        }, 
        {
          "hex": "#c0c0c0",
          "name": "#c0c0c0",
          "reference": "vibrant"
        }, 
        {
          "hex": "#464646",
          "name": "#464646",
          "reference": "vibrant"
        }
      ],
      "sizes": {
        "b": {
          "extension": "jpg",
          "height": 751,
          "mimetype": "image/jpeg",
          "secret": "SONutTQ9aLQMqQx3AbwhFV2Dmiynv7cL",
          "width": 1024
        },
        "c": {
          "extension": "jpg",
          "height": 587,
          "mimetype": "image/jpeg",
          "secret": "SONutTQ9aLQMqQx3AbwhFV2Dmiynv7cL",
          "width": 800
        },
        "dc": {
          "extension": "jpg",
          "height": 587,
          "mimetype": "image/jpeg",
          "secret": "SONutTQ9aLQMqQx3AbwhFV2Dmiynv7cL",
          "width": 800
        },
        "ds": {
          "extension": "jpg",
          "height": 320,
          "mimetype": "image/jpeg",
          "secret": "SONutTQ9aLQMqQx3AbwhFV2Dmiynv7cL",
          "width": 320
        },
        "k": {
          "extension": "jpg",
          "height": 1503,
          "mimetype": "image/jpeg",
          "secret": "SONutTQ9aLQMqQx3AbwhFV2Dmiynv7cL",
          "width": 2048
        },
        "n": {
          "extension": "jpg",
          "height": 234,
          "mimetype": "image/jpeg",
          "secret": "SONutTQ9aLQMqQx3AbwhFV2Dmiynv7cL",
          "width": 320
        },
        "o": {
          "extension": "jpg",
          "height": 1732,
          "mimetype": "image/jpeg",
          "secret": "mKuyEZApf9lZKG1EQGYy2RV3zPkJZJN3",
          "width": 2359
        },
        "s": {
          "extension": "jpg",
          "height": 320,
          "mimetype": "image/jpeg",
          "secret": "SONutTQ9aLQMqQx3AbwhFV2Dmiynv7cL",
          "width": 320
        },
        "z": {
          "extension": "jpg",
          "height": 469,
          "mimetype": "image/jpeg",
          "secret": "SONutTQ9aLQMqQx3AbwhFV2Dmiynv7cL",
          "width": 640
        }
      }
    },
    "media:uri_template": "https://millsfield.sfomuseum.org/media/152/782/199/3/1527821993_{secret}_{label}.{extention}",
    "sfomuseum:filename": "40153.tif",
    "sfomuseum:image_index": 5,
    "sfomuseum:placetype": "image",
    "sfomuseum:primary_image": 1,
    "wof:depicts": [
      1511943913
    ],
    "wof:name": "negative: San Francisco Airport, Terminal Building construction",
    "wof:placetype": "media"
  },
  "geometry": {"coordinates":[-122.386155,37.616358],"type":"Point"}
}
