{
  "type": "Feature",
  "properties": {
    "iso:country": "XX",
    "media:fingerprint": "d3483ffca8e59fa5c2c6bddf52c8f2b89bb77016",
    "media:imagehash_avg": "a:ffffffc300000000",
    "media:imagehash_diff": "d:f2e78f0f3373e0f0",
    "media:medium": "image",
    "media:mimetype": "image/tiff",
    "media:properties": {
      "colours": [
        {
          "hex": "#858585",
          "name": "#858585",
          "reference": "vibrant"
        }, 
        {
          "hex": "#b8b8b8",
          "name": "#b8b8b8",
          "reference": "vibrant"
        }, 
        {
          "hex": "#404040",
          "name": "#404040",
          "reference": "vibrant"
        }
      ],
      "sizes": {
        "b": {
          "extension": "jpg",
          "height": 767,
          "mimetype": "image/jpeg",
          "secret": "FezAp2rQKqUPY9qVnB2ap8uoUv0mtfnq",
          "width": 784
        },
        "c": {
          "extension": "jpg",
          "height": 600,
          "mimetype": "image/jpeg",
          "secret": "FezAp2rQKqUPY9qVnB2ap8uoUv0mtfnq",
          "width": 612
        },
        "dc": {
          "extension": "jpg",
          "height": 600,
          "mimetype": "image/jpeg",
          "secret": "FezAp2rQKqUPY9qVnB2ap8uoUv0mtfnq",
          "width": 612
        },
        "ds": {
          "extension": "jpg",
          "height": 320,
          "mimetype": "image/jpeg",
          "secret": "FezAp2rQKqUPY9qVnB2ap8uoUv0mtfnq",
          "width": 320
        },
        "k": {
          "extension": "jpg",
          "height": 1535,
          "mimetype": "image/jpeg",
          "secret": "FezAp2rQKqUPY9qVnB2ap8uoUv0mtfnq",
          "width": 1569
        },
        "n": {
          "extension": "jpg",
          "height": 240,
          "mimetype": "image/jpeg",
          "secret": "FezAp2rQKqUPY9qVnB2ap8uoUv0mtfnq",
          "width": 245
        },
        "o": {
          "extension": "jpg",
          "height": 2509,
          "mimetype": "image/jpeg",
          "secret": "v5Rpf04v434NKlUgx7uXY6EHkdftRdQ9",
          "width": 2563
        },
        "s": {
          "extension": "jpg",
          "height": 320,
          "mimetype": "image/jpeg",
          "secret": "FezAp2rQKqUPY9qVnB2ap8uoUv0mtfnq",
          "width": 320
        },
        "z": {
          "extension": "jpg",
          "height": 480,
          "mimetype": "image/jpeg",
          "secret": "FezAp2rQKqUPY9qVnB2ap8uoUv0mtfnq",
          "width": 490
        }
      }
    },
    "media:uri_template": "https://millsfield.sfomuseum.org/media/152/782/639/1/1527826391_{secret}_{label}.{extention}",
    "sfomuseum:filename": "43619.tif",
    "sfomuseum:image_index": 5,
    "sfomuseum:placetype": "image",
    "sfomuseum:primary_image": 1,
    "wof:depicts": [
      1511947429
    ],
    "wof:name": "negative: San Francisco International Airport (SFO), construction of Pacific Southwest Airlines (PSA) pier and jetways",
    "wof:placetype": "media"
  },
  "geometry": {"coordinates":[-122.386155,37.616358],"type":"Point"}
}
