{
  "type": "Feature",
  "properties": {
    "iso:country": "XX",
    "media:fingerprint": "5d730e4caa94bec448f7917e16030cc0499af91b",
    "media:imagehash_avg": "a:00fffffeff0f0600",
    "media:imagehash_diff": "d:a978f6323a2c6c65",
    "media:medium": "image",
    "media:mimetype": "image/tiff",
    "media:properties": {
      "colours": [
        {
          "hex": "#b52607",
          "name": "#b52607",
          "reference": "vibrant"
        }, 
        {
          "hex": "#e1c898",
          "name": "#e1c898",
          "reference": "vibrant"
        }, 
        {
          "hex": "#a32f17",
          "name": "#a32f17",
          "reference": "vibrant"
        }, 
        {
          "hex": "#9a8d6c",
          "name": "#9a8d6c",
          "reference": "vibrant"
        }, 
        {
          "hex": "#d0c9a7",
          "name": "#d0c9a7",
          "reference": "vibrant"
        }
      ],
      "sizes": {
        "b": {
          "extension": "jpg",
          "height": 576,
          "mimetype": "image/jpeg",
          "secret": "snaSCWIsbwIMjBVQwUg2cXmiEm19L1dK",
          "width": 1024
        },
        "c": {
          "extension": "jpg",
          "height": 450,
          "mimetype": "image/jpeg",
          "secret": "snaSCWIsbwIMjBVQwUg2cXmiEm19L1dK",
          "width": 800
        },
        "dc": {
          "extension": "jpg",
          "height": 450,
          "mimetype": "image/jpeg",
          "secret": "snaSCWIsbwIMjBVQwUg2cXmiEm19L1dK",
          "width": 800
        },
        "ds": {
          "extension": "jpg",
          "height": 320,
          "mimetype": "image/jpeg",
          "secret": "snaSCWIsbwIMjBVQwUg2cXmiEm19L1dK",
          "width": 320
        },
        "k": {
          "extension": "jpg",
          "height": 1152,
          "mimetype": "image/jpeg",
          "secret": "snaSCWIsbwIMjBVQwUg2cXmiEm19L1dK",
          "width": 2048
        },
        "n": {
          "extension": "jpg",
          "height": 180,
          "mimetype": "image/jpeg",
          "secret": "snaSCWIsbwIMjBVQwUg2cXmiEm19L1dK",
          "width": 320
        },
        "o": {
          "extension": "jpg",
          "height": 1115,
          "mimetype": "image/jpeg",
          "secret": "WZtsa82H2bcNk47cT6ayVG5z2A86NC6q",
          "width": 1982
        },
        "s": {
          "extension": "jpg",
          "height": 320,
          "mimetype": "image/jpeg",
          "secret": "snaSCWIsbwIMjBVQwUg2cXmiEm19L1dK",
          "width": 320
        },
        "z": {
          "extension": "jpg",
          "height": 360,
          "mimetype": "image/jpeg",
          "secret": "snaSCWIsbwIMjBVQwUg2cXmiEm19L1dK",
          "width": 640
        }
      }
    },
    "media:uri_template": "https://millsfield.sfomuseum.org/media/152/782/032/1/1527820321_{secret}_{label}.{extention}",
    "sfomuseum:filename": "31519.tif",
    "sfomuseum:image_index": 5,
    "sfomuseum:placetype": "image",
    "sfomuseum:primary_image": 0,
    "wof:depicts": [
      1511923511
    ],
    "wof:name": "airmail flight cover: Pan American Airways, FAM-14, first transpacific airmail flight, San Francisco (Alameda) - Honolulu route",
    "wof:placetype": "media"
  },
  "geometry": {"coordinates":[-122.386155,37.616358],"type":"Point"}
}
