{
  "type": "Feature",
  "properties": {
    "iso:country": "XX",
    "media:fingerprint": "c69f4e90d6348f4c7e7ffe1da4e0a1938ef2e552",
    "media:imagehash_avg": "a:e3e3c38383c7ffff",
    "media:imagehash_diff": "d:6646060f161c48e8",
    "media:medium": "image",
    "media:mimetype": "image/tiff",
    "media:properties": {
      "colours": [
        {
          "hex": "#808080",
          "name": "#808080",
          "reference": "vibrant"
        }, 
        {
          "hex": "#b8b8b8",
          "name": "#b8b8b8",
          "reference": "vibrant"
        }, 
        {
          "hex": "#484848",
          "name": "#484848",
          "reference": "vibrant"
        }
      ],
      "sizes": {
        "b": {
          "extension": "jpg",
          "height": 767,
          "mimetype": "image/jpeg",
          "secret": "YuglsNUmu6Q0VIOMQ0HVXiFu1tFLiVUC",
          "width": 993
        },
        "c": {
          "extension": "jpg",
          "height": 600,
          "mimetype": "image/jpeg",
          "secret": "YuglsNUmu6Q0VIOMQ0HVXiFu1tFLiVUC",
          "width": 776
        },
        "dc": {
          "extension": "jpg",
          "height": 600,
          "mimetype": "image/jpeg",
          "secret": "YuglsNUmu6Q0VIOMQ0HVXiFu1tFLiVUC",
          "width": 776
        },
        "ds": {
          "extension": "jpg",
          "height": 320,
          "mimetype": "image/jpeg",
          "secret": "YuglsNUmu6Q0VIOMQ0HVXiFu1tFLiVUC",
          "width": 320
        },
        "k": {
          "extension": "jpg",
          "height": 1535,
          "mimetype": "image/jpeg",
          "secret": "YuglsNUmu6Q0VIOMQ0HVXiFu1tFLiVUC",
          "width": 1986
        },
        "n": {
          "extension": "jpg",
          "height": 240,
          "mimetype": "image/jpeg",
          "secret": "YuglsNUmu6Q0VIOMQ0HVXiFu1tFLiVUC",
          "width": 310
        },
        "o": {
          "extension": "jpg",
          "height": 2140,
          "mimetype": "image/jpeg",
          "secret": "o6ytKm9lhvLyCwIl6riAW2QwONUa7ISD",
          "width": 2768
        },
        "s": {
          "extension": "jpg",
          "height": 320,
          "mimetype": "image/jpeg",
          "secret": "YuglsNUmu6Q0VIOMQ0HVXiFu1tFLiVUC",
          "width": 320
        },
        "z": {
          "extension": "jpg",
          "height": 480,
          "mimetype": "image/jpeg",
          "secret": "YuglsNUmu6Q0VIOMQ0HVXiFu1tFLiVUC",
          "width": 620
        }
      }
    },
    "media:uri_template": "https://millsfield.sfomuseum.org/media/152/782/168/1/1527821681_{secret}_{label}.{extention}",
    "sfomuseum:filename": "38922.tif",
    "sfomuseum:image_index": 5,
    "sfomuseum:placetype": "image",
    "sfomuseum:primary_image": 1,
    "wof:depicts": [
      1511943757
    ],
    "wof:name": "negative: San Francisco Airport, runway maintenance",
    "wof:placetype": "media"
  },
  "geometry": {"coordinates":[-122.386155,37.616358],"type":"Point"}
}
