{
  "type": "Feature",
  "properties": {
    "iso:country": "XX",
    "media:fingerprint": "94bc405af8090987ca950cf3304b3ef175c95ed0",
    "media:imagehash_avg": "a:e7c38f8181f9ffff",
    "media:imagehash_diff": "d:4f0f3b1f23336141",
    "media:medium": "image",
    "media:mimetype": "image/tiff",
    "media:properties": {
      "colours": [
        {
          "hex": "#977c43",
          "name": "#977c43",
          "reference": "vibrant"
        }, 
        {
          "hex": "#e8d8ad",
          "name": "#e8d8ad",
          "reference": "vibrant"
        }, 
        {
          "hex": "#534c23",
          "name": "#534c23",
          "reference": "vibrant"
        }, 
        {
          "hex": "#968e68",
          "name": "#968e68",
          "reference": "vibrant"
        }, 
        {
          "hex": "#d9d3ad",
          "name": "#d9d3ad",
          "reference": "vibrant"
        }
      ],
      "sizes": {
        "b": {
          "extension": "jpg",
          "height": 768,
          "mimetype": "image/jpeg",
          "secret": "yC7iIE0hmZVBOIxNjV5T0ws1pPC0j01e",
          "width": 590
        },
        "c": {
          "extension": "jpg",
          "height": 600,
          "mimetype": "image/jpeg",
          "secret": "yC7iIE0hmZVBOIxNjV5T0ws1pPC0j01e",
          "width": 461
        },
        "dc": {
          "extension": "jpg",
          "height": 600,
          "mimetype": "image/jpeg",
          "secret": "yC7iIE0hmZVBOIxNjV5T0ws1pPC0j01e",
          "width": 461
        },
        "ds": {
          "extension": "jpg",
          "height": 320,
          "mimetype": "image/jpeg",
          "secret": "yC7iIE0hmZVBOIxNjV5T0ws1pPC0j01e",
          "width": 320
        },
        "k": {
          "extension": "jpg",
          "height": 1536,
          "mimetype": "image/jpeg",
          "secret": "yC7iIE0hmZVBOIxNjV5T0ws1pPC0j01e",
          "width": 1181
        },
        "n": {
          "extension": "jpg",
          "height": 240,
          "mimetype": "image/jpeg",
          "secret": "yC7iIE0hmZVBOIxNjV5T0ws1pPC0j01e",
          "width": 184
        },
        "o": {
          "extension": "jpg",
          "height": 1800,
          "mimetype": "image/jpeg",
          "secret": "tDhnBGsxMpDpEe2BGMwN6NZeuweK3oc3",
          "width": 1385
        },
        "s": {
          "extension": "jpg",
          "height": 320,
          "mimetype": "image/jpeg",
          "secret": "yC7iIE0hmZVBOIxNjV5T0ws1pPC0j01e",
          "width": 320
        },
        "z": {
          "extension": "jpg",
          "height": 480,
          "mimetype": "image/jpeg",
          "secret": "yC7iIE0hmZVBOIxNjV5T0ws1pPC0j01e",
          "width": 369
        }
      }
    },
    "media:uri_template": "https://millsfield.sfomuseum.org/media/152/785/690/1/1527856901_{secret}_{label}.{extention}",
    "sfomuseum:filename": "2000.018.040.006.tif",
    "sfomuseum:image_index": 0,
    "sfomuseum:placetype": "image",
    "sfomuseum:primary_image": 1,
    "wof:depicts": [
      1511957953
    ],
    "wof:name": "correspondence: Joseph J. Phillips, Right of Way Agent for City and County of San Francisco, proposed airport sites",
    "wof:placetype": "media"
  },
  "geometry": {"coordinates":[-122.386155,37.616358],"type":"Point"}
}
