{
  "type": "Feature",
  "properties": {
    "iso:country": "XX",
    "media:fingerprint": "138680a5292c3786491a7ff9b372f360d3f1b449",
    "media:imagehash_avg": "a:ffffe7c7c3c3ffff",
    "media:imagehash_diff": "d:480c0c0e0e0e4c1c",
    "media:medium": "image",
    "media:mimetype": "image/tiff",
    "media:properties": {
      "colours": [
        {
          "hex": "#aa7239",
          "name": "#aa7239",
          "reference": "vibrant"
        },
        {
          "hex": "#f8f1d9",
          "name": "#f8f1d9",
          "reference": "vibrant"
        },
        {
          "hex": "#963c30",
          "name": "#963c30",
          "reference": "vibrant"
        },
        {
          "hex": "#a0a45a",
          "name": "#a0a45a",
          "reference": "vibrant"
        },
        {
          "hex": "#bab798",
          "name": "#bab798",
          "reference": "vibrant"
        }
      ],
      "sizes": {
        "b": {
          "extension": "jpg",
          "height": 768,
          "mimetype": "image/jpeg",
          "secret": "kIhSnYqJ10VxEPYVkzxUh0z8hUcrfeOI",
          "width": 525
        },
        "c": {
          "extension": "jpg",
          "height": 600,
          "mimetype": "image/jpeg",
          "secret": "kIhSnYqJ10VxEPYVkzxUh0z8hUcrfeOI",
          "width": 410
        },
        "dc": {
          "extension": "jpg",
          "height": 600,
          "mimetype": "image/jpeg",
          "secret": "kIhSnYqJ10VxEPYVkzxUh0z8hUcrfeOI",
          "width": 410
        },
        "ds": {
          "extension": "jpg",
          "height": 320,
          "mimetype": "image/jpeg",
          "secret": "kIhSnYqJ10VxEPYVkzxUh0z8hUcrfeOI",
          "width": 320
        },
        "k": {
          "extension": "jpg",
          "height": 1536,
          "mimetype": "image/jpeg",
          "secret": "kIhSnYqJ10VxEPYVkzxUh0z8hUcrfeOI",
          "width": 1050
        },
        "n": {
          "extension": "jpg",
          "height": 240,
          "mimetype": "image/jpeg",
          "secret": "kIhSnYqJ10VxEPYVkzxUh0z8hUcrfeOI",
          "width": 164
        },
        "o": {
          "extension": "jpg",
          "height": 3294,
          "mimetype": "image/jpeg",
          "secret": "Z3CWXeSIzjD9qQgwZXwfuOT7qN6c8MzA",
          "width": 2252
        },
        "s": {
          "extension": "jpg",
          "height": 320,
          "mimetype": "image/jpeg",
          "secret": "kIhSnYqJ10VxEPYVkzxUh0z8hUcrfeOI",
          "width": 320
        },
        "z": {
          "extension": "jpg",
          "height": 480,
          "mimetype": "image/jpeg",
          "secret": "kIhSnYqJ10VxEPYVkzxUh0z8hUcrfeOI",
          "width": 328
        }
      }
    },
    "media:uri_template": "https://static.sfomuseum.org/media/152/784/399/7/1527843997_{secret}_{label}.{extention}",
    "sfomuseum:filename": "68783.tif",
    "sfomuseum:image_index": 5,
    "sfomuseum:image_type": "studio",
    "sfomuseum:placetype": "image",
    "sfomuseum:primary_image": 1,
    "wof:depicts": [
      1159283849,
      1511921719
    ],
    "wof:name": "menu: American Airlines, Business Class",
    "wof:placetype": "custom",
    "wof:placetype_alt": "image"
  },
  "geometry": {"coordinates":[-122.386155,37.616358],"type":"Point"}
}
