{
  "type": "Feature",
  "properties": {
    "iso:country": "US",
    "media:fingerprint": "da8ad56d114fcbcc432fb21efca108a18b113b08",
    "media:imagehash_avg": "a:ff0c193a00e080ff",
    "media:imagehash_diff": "d:4c7c716260046c66",
    "media:medium": "image",
    "media:mimetype": "image/tiff",
    "media:properties": {
      "colours": [
        {
          "hex": "#f8e2b7",
          "name": "#f8e2b7",
          "reference": "vibrant"
        }, 
        {
          "hex": "#082643",
          "name": "#082643",
          "reference": "vibrant"
        }, 
        {
          "hex": "#7e8473",
          "name": "#7e8473",
          "reference": "vibrant"
        }, 
        {
          "hex": "#cfcbb2",
          "name": "#cfcbb2",
          "reference": "vibrant"
        }, 
        {
          "hex": "#384e56",
          "name": "#384e56",
          "reference": "vibrant"
        }
      ],
      "sizes": {
        "b": {
          "extension": "jpg",
          "height": 768,
          "mimetype": "image/jpeg",
          "secret": "5YKphLGMOMXjMjc8iLbfP1BwlF9GcD8d",
          "width": 624
        },
        "c": {
          "extension": "jpg",
          "height": 600,
          "mimetype": "image/jpeg",
          "secret": "5YKphLGMOMXjMjc8iLbfP1BwlF9GcD8d",
          "width": 488
        },
        "dc": {
          "extension": "jpg",
          "height": 600,
          "mimetype": "image/jpeg",
          "secret": "5YKphLGMOMXjMjc8iLbfP1BwlF9GcD8d",
          "width": 488
        },
        "ds": {
          "extension": "jpg",
          "height": 320,
          "mimetype": "image/jpeg",
          "secret": "5YKphLGMOMXjMjc8iLbfP1BwlF9GcD8d",
          "width": 320
        },
        "k": {
          "extension": "jpg",
          "height": 1536,
          "mimetype": "image/jpeg",
          "secret": "5YKphLGMOMXjMjc8iLbfP1BwlF9GcD8d",
          "width": 1249
        },
        "n": {
          "extension": "jpg",
          "height": 240,
          "mimetype": "image/jpeg",
          "secret": "5YKphLGMOMXjMjc8iLbfP1BwlF9GcD8d",
          "width": 195
        },
        "o": {
          "extension": "jpg",
          "height": 1356,
          "mimetype": "image/jpeg",
          "secret": "0NdcpUQ3NjaJR0kDFKqDjmUQTUQM7qPN",
          "width": 1103
        },
        "s": {
          "extension": "jpg",
          "height": 320,
          "mimetype": "image/jpeg",
          "secret": "5YKphLGMOMXjMjc8iLbfP1BwlF9GcD8d",
          "width": 320
        },
        "z": {
          "extension": "jpg",
          "height": 480,
          "mimetype": "image/jpeg",
          "secret": "5YKphLGMOMXjMjc8iLbfP1BwlF9GcD8d",
          "width": 390
        }
      }
    },
    "media:uri_template": "https://millsfield.sfomuseum.org/media/152/782/079/3/1527820793_{secret}_{label}.{extention}",
    "sfomuseum:filename": "33107.tif",
    "sfomuseum:image_index": 5,
    "sfomuseum:placetype": "image",
    "sfomuseum:primary_image": 1,
    "wof:depicts": [
      1511931259
    ],
    "wof:name": "luggage label: New York, Rio \u0026 Buenos Aires Line (NYRBA)",
    "wof:placetype": "media"
  },
  "geometry": {"coordinates":[-122.386155,37.616358],"type":"Point"}
}
