{
  "type": "Feature",
  "properties": {
    "iso:country":"US",
    "media:medium":"image",
    "sfomuseum:filename":"1999.059.027_ft1.tif",
    "sfomuseum:image_index":5,
    "sfomuseum:placetype":"image",
    "sfomuseum:primary_image":1,
    "wof:depicts":[
        1511910007
    ],
    "wof:name":"airline bag: Pan American World Airways",
    "wof:placetype":"media"
},
  "geometry": {"coordinates":[-122.386155,37.616358],"type":"Point"}
}