{
  "type": "Feature",
  "properties": {
    "iso:country": "XX",
    "media:fingerprint": "b9e8e31a9a505795c40f6345dfc4853ac9178031",
    "media:imagehash_avg": "a:ff818181898901ff",
    "media:imagehash_diff": "d:7571717171797951",
    "media:medium": "image",
    "media:mimetype": "image/tiff",
    "media:properties": {
      "colours": [
        {
          "hex": "#f4e1be",
          "name": "#f4e1be",
          "reference": "vibrant"
        },
        {
          "hex": "#19180c",
          "name": "#19180c",
          "reference": "vibrant"
        },
        {
          "hex": "#918d71",
          "name": "#918d71",
          "reference": "vibrant"
        },
        {
          "hex": "#cfc8aa",
          "name": "#cfc8aa",
          "reference": "vibrant"
        },
        {
          "hex": "#544f39",
          "name": "#544f39",
          "reference": "vibrant"
        }
      ],
      "sizes": {
        "b": {
          "extension": "jpg",
          "height": 768,
          "mimetype": "image/jpeg",
          "secret": "6BQY4hFtyOzVjlCMhBtbBfOxsIV2qXUr",
          "width": 1008
        },
        "c": {
          "extension": "jpg",
          "height": 600,
          "mimetype": "image/jpeg",
          "secret": "6BQY4hFtyOzVjlCMhBtbBfOxsIV2qXUr",
          "width": 787
        },
        "dc": {
          "extension": "jpg",
          "height": 600,
          "mimetype": "image/jpeg",
          "secret": "6BQY4hFtyOzVjlCMhBtbBfOxsIV2qXUr",
          "width": 787
        },
        "ds": {
          "extension": "jpg",
          "height": 320,
          "mimetype": "image/jpeg",
          "secret": "6BQY4hFtyOzVjlCMhBtbBfOxsIV2qXUr",
          "width": 320
        },
        "k": {
          "extension": "jpg",
          "height": 1536,
          "mimetype": "image/jpeg",
          "secret": "6BQY4hFtyOzVjlCMhBtbBfOxsIV2qXUr",
          "width": 2017
        },
        "n": {
          "extension": "jpg",
          "height": 240,
          "mimetype": "image/jpeg",
          "secret": "6BQY4hFtyOzVjlCMhBtbBfOxsIV2qXUr",
          "width": 315
        },
        "o": {
          "extension": "jpg",
          "height": 1223,
          "mimetype": "image/jpeg",
          "secret": "o8rHuvg8KvsgSuFM3qfdktGlteRVhqkK",
          "width": 1606
        },
        "s": {
          "extension": "jpg",
          "height": 320,
          "mimetype": "image/jpeg",
          "secret": "6BQY4hFtyOzVjlCMhBtbBfOxsIV2qXUr",
          "width": 320
        },
        "z": {
          "extension": "jpg",
          "height": 480,
          "mimetype": "image/jpeg",
          "secret": "6BQY4hFtyOzVjlCMhBtbBfOxsIV2qXUr",
          "width": 630
        }
      }
    },
    "media:uri_template": "https://static.sfomuseum.org/media/152/785/577/9/1527855779_{secret}_{label}.{extention}",
    "sfomuseum:filename": "2010.174.372.tif",
    "sfomuseum:image_index": 5,
    "sfomuseum:image_type": "studio",
    "sfomuseum:placetype": "image",
    "sfomuseum:primary_image": 1,
    "wof:depicts": [
      1511942623
    ],
    "wof:name": "photograph: San Francisco Bay Area aerial, San Rafael",
    "wof:placetype": "custom",
    "wof:placetype_alt": "image"
  },
  "geometry": {"coordinates":[-122.386155,37.616358],"type":"Point"}
}
