{
  "type": "Feature",
  "properties": {
    "iso:country": "XX",
    "media:fingerprint": "23f8db6ad4e1d85de92eef91d0d9362150d577b4",
    "media:imagehash_avg": "a:fd11010101017d21",
    "media:imagehash_diff": "d:757507b7c971c1cd",
    "media:medium": "image",
    "media:mimetype": "image/tiff",
    "media:properties": {
      "colours": [
        {
          "hex": "#e8b875",
          "name": "#e8b875",
          "reference": "vibrant"
        }, 
        {
          "hex": "#e9c278",
          "name": "#e9c278",
          "reference": "vibrant"
        }, 
        {
          "hex": "#9e8351",
          "name": "#9e8351",
          "reference": "vibrant"
        }, 
        {
          "hex": "#c0af8d",
          "name": "#c0af8d",
          "reference": "vibrant"
        }, 
        {
          "hex": "#4e413a",
          "name": "#4e413a",
          "reference": "vibrant"
        }
      ],
      "sizes": {
        "b": {
          "extension": "jpg",
          "height": 768,
          "mimetype": "image/jpeg",
          "secret": "4xVv2XRzYoX326O4rfdgrMDKc1JU9qkJ",
          "width": 419
        },
        "c": {
          "extension": "jpg",
          "height": 600,
          "mimetype": "image/jpeg",
          "secret": "4xVv2XRzYoX326O4rfdgrMDKc1JU9qkJ",
          "width": 327
        },
        "dc": {
          "extension": "jpg",
          "height": 600,
          "mimetype": "image/jpeg",
          "secret": "4xVv2XRzYoX326O4rfdgrMDKc1JU9qkJ",
          "width": 327
        },
        "ds": {
          "extension": "jpg",
          "height": 320,
          "mimetype": "image/jpeg",
          "secret": "4xVv2XRzYoX326O4rfdgrMDKc1JU9qkJ",
          "width": 320
        },
        "k": {
          "extension": "jpg",
          "height": 1536,
          "mimetype": "image/jpeg",
          "secret": "4xVv2XRzYoX326O4rfdgrMDKc1JU9qkJ",
          "width": 838
        },
        "n": {
          "extension": "jpg",
          "height": 240,
          "mimetype": "image/jpeg",
          "secret": "4xVv2XRzYoX326O4rfdgrMDKc1JU9qkJ",
          "width": 130
        },
        "o": {
          "extension": "jpg",
          "height": 2891,
          "mimetype": "image/jpeg",
          "secret": "jPTlksc1TmEkvEwaR1gskFnwxmMy0IjH",
          "width": 1578
        },
        "s": {
          "extension": "jpg",
          "height": 320,
          "mimetype": "image/jpeg",
          "secret": "4xVv2XRzYoX326O4rfdgrMDKc1JU9qkJ",
          "width": 320
        },
        "z": {
          "extension": "jpg",
          "height": 480,
          "mimetype": "image/jpeg",
          "secret": "4xVv2XRzYoX326O4rfdgrMDKc1JU9qkJ",
          "width": 261
        }
      }
    },
    "media:uri_template": "https://millsfield.sfomuseum.org/media/152/782/483/9/1527824839_{secret}_{label}.{extention}",
    "sfomuseum:filename": "42829.tif",
    "sfomuseum:image_index": 5,
    "sfomuseum:placetype": "image",
    "sfomuseum:primary_image": 0,
    "wof:depicts": [
      1511927439
    ],
    "wof:name": "airsickness bag: Gulf Air",
    "wof:placetype": "media"
  },
  "geometry": {"coordinates":[-122.386155,37.616358],"type":"Point"}
}
