{
  "type": "Feature",
  "properties": {
    "iso:country": "XX",
    "media:fingerprint": "05a98b780192ea85084b910870e5c970272c49b6",
    "media:imagehash_avg": "a:ffffbfc700000000",
    "media:imagehash_diff": "d:e0607c1ed8e87870",
    "media:medium": "image",
    "media:mimetype": "image/tiff",
    "media:properties": {
      "colours": [
        {
          "hex": "#a9641e",
          "name": "#a9641e",
          "reference": "vibrant"
        }, 
        {
          "hex": "#c2a264",
          "name": "#c2a264",
          "reference": "vibrant"
        }, 
        {
          "hex": "#5f4015",
          "name": "#5f4015",
          "reference": "vibrant"
        }, 
        {
          "hex": "#a19161",
          "name": "#a19161",
          "reference": "vibrant"
        }, 
        {
          "hex": "#cfc5a3",
          "name": "#cfc5a3",
          "reference": "vibrant"
        }
      ],
      "sizes": {
        "b": {
          "extension": "jpg",
          "height": 654,
          "mimetype": "image/jpeg",
          "secret": "ldMfkU1UGpLpixUp3fwAwz5l4naUYFCu",
          "width": 1024
        },
        "c": {
          "extension": "jpg",
          "height": 511,
          "mimetype": "image/jpeg",
          "secret": "ldMfkU1UGpLpixUp3fwAwz5l4naUYFCu",
          "width": 800
        },
        "dc": {
          "extension": "jpg",
          "height": 511,
          "mimetype": "image/jpeg",
          "secret": "ldMfkU1UGpLpixUp3fwAwz5l4naUYFCu",
          "width": 800
        },
        "ds": {
          "extension": "jpg",
          "height": 320,
          "mimetype": "image/jpeg",
          "secret": "ldMfkU1UGpLpixUp3fwAwz5l4naUYFCu",
          "width": 320
        },
        "k": {
          "extension": "jpg",
          "height": 1309,
          "mimetype": "image/jpeg",
          "secret": "ldMfkU1UGpLpixUp3fwAwz5l4naUYFCu",
          "width": 2048
        },
        "n": {
          "extension": "jpg",
          "height": 204,
          "mimetype": "image/jpeg",
          "secret": "ldMfkU1UGpLpixUp3fwAwz5l4naUYFCu",
          "width": 320
        },
        "o": {
          "extension": "jpg",
          "height": 1063,
          "mimetype": "image/jpeg",
          "secret": "5QvspvdnNhpc3tAt6KJTfiDHZlIiBc81",
          "width": 1663
        },
        "s": {
          "extension": "jpg",
          "height": 320,
          "mimetype": "image/jpeg",
          "secret": "ldMfkU1UGpLpixUp3fwAwz5l4naUYFCu",
          "width": 320
        },
        "z": {
          "extension": "jpg",
          "height": 409,
          "mimetype": "image/jpeg",
          "secret": "ldMfkU1UGpLpixUp3fwAwz5l4naUYFCu",
          "width": 640
        }
      }
    },
    "media:uri_template": "https://millsfield.sfomuseum.org/media/152/782/843/3/1527828433_{secret}_{label}.{extention}",
    "sfomuseum:filename": "44597.tif",
    "sfomuseum:image_index": 5,
    "sfomuseum:placetype": "image",
    "sfomuseum:primary_image": 1,
    "wof:depicts": [
      1511949467
    ],
    "wof:name": "negative: San Francisco International Airport (SFO), Flying Tiger Line Douglas DC-8",
    "wof:placetype": "media"
  },
  "geometry": {"coordinates":[-122.386155,37.616358],"type":"Point"}
}
