{
  "type": "Feature",
  "properties": {
    "iso:country": "XX",
    "media:fingerprint": "25107894e31bfdce924efc861dfef5963709f4a7",
    "media:imagehash_avg": "a:ff8983e7e7c3bdff",
    "media:imagehash_diff": "d:49290f0f0d0f7949",
    "media:medium": "image",
    "media:mimetype": "image/tiff",
    "media:properties": {
      "colours": [
        {
          "hex": "#e8d8bd",
          "name": "#e8d8bd",
          "reference": "vibrant"
        }, 
        {
          "hex": "#302b11",
          "name": "#302b11",
          "reference": "vibrant"
        }, 
        {
          "hex": "#938b75",
          "name": "#938b75",
          "reference": "vibrant"
        }, 
        {
          "hex": "#cbc5b0",
          "name": "#cbc5b0",
          "reference": "vibrant"
        }, 
        {
          "hex": "#504834",
          "name": "#504834",
          "reference": "vibrant"
        }
      ],
      "sizes": {
        "b": {
          "extension": "jpg",
          "height": 451,
          "mimetype": "image/jpeg",
          "secret": "grv5EROfDWrLQqaIsf5CnSCxwiFMsIiy",
          "width": 1024
        },
        "c": {
          "extension": "jpg",
          "height": 353,
          "mimetype": "image/jpeg",
          "secret": "grv5EROfDWrLQqaIsf5CnSCxwiFMsIiy",
          "width": 800
        },
        "dc": {
          "extension": "jpg",
          "height": 353,
          "mimetype": "image/jpeg",
          "secret": "grv5EROfDWrLQqaIsf5CnSCxwiFMsIiy",
          "width": 800
        },
        "ds": {
          "extension": "jpg",
          "height": 320,
          "mimetype": "image/jpeg",
          "secret": "grv5EROfDWrLQqaIsf5CnSCxwiFMsIiy",
          "width": 320
        },
        "k": {
          "extension": "jpg",
          "height": 903,
          "mimetype": "image/jpeg",
          "secret": "grv5EROfDWrLQqaIsf5CnSCxwiFMsIiy",
          "width": 2048
        },
        "n": {
          "extension": "jpg",
          "height": 141,
          "mimetype": "image/jpeg",
          "secret": "grv5EROfDWrLQqaIsf5CnSCxwiFMsIiy",
          "width": 320
        },
        "o": {
          "extension": "jpg",
          "height": 1275,
          "mimetype": "image/jpeg",
          "secret": "E4iavbyNXNmuVDHnlHADezPsGMB1tzva",
          "width": 2889
        },
        "s": {
          "extension": "jpg",
          "height": 320,
          "mimetype": "image/jpeg",
          "secret": "grv5EROfDWrLQqaIsf5CnSCxwiFMsIiy",
          "width": 320
        },
        "z": {
          "extension": "jpg",
          "height": 282,
          "mimetype": "image/jpeg",
          "secret": "grv5EROfDWrLQqaIsf5CnSCxwiFMsIiy",
          "width": 640
        }
      }
    },
    "media:uri_template": "https://millsfield.sfomuseum.org/media/152/782/025/9/1527820259_{secret}_{label}.{extention}",
    "sfomuseum:filename": "31492.tif",
    "sfomuseum:image_index": 5,
    "sfomuseum:placetype": "image",
    "sfomuseum:primary_image": 0,
    "wof:depicts": [
      1511909319
    ],
    "wof:name": "airmail flight cover: Pan American World Airways, first airmail flight, Djakarta - Manila route",
    "wof:placetype": "media"
  },
  "geometry": {"coordinates":[-122.386155,37.616358],"type":"Point"}
}
