{
  "type": "Feature",
  "properties": {
    "iso:country": "XX",
    "media:fingerprint": "3e852e884292a2769c2d9bc124772202e42f3601",
    "media:imagehash_avg": "a:00ffcfc3c3c3c387",
    "media:imagehash_diff": "d:0db89fbf8f8f8f9f",
    "media:medium": "image",
    "media:mimetype": "image/tiff",
    "media:properties": {
      "colours": [
        {
          "hex": "#e64f49",
          "name": "#e64f49",
          "reference": "vibrant"
        }, 
        {
          "hex": "#ee8684",
          "name": "#ee8684",
          "reference": "vibrant"
        }, 
        {
          "hex": "#807972",
          "name": "#807972",
          "reference": "vibrant"
        }, 
        {
          "hex": "#cdb6b2",
          "name": "#cdb6b2",
          "reference": "vibrant"
        }, 
        {
          "hex": "#605a53",
          "name": "#605a53",
          "reference": "vibrant"
        }
      ],
      "sizes": {
        "b": {
          "extension": "jpg",
          "height": 768,
          "mimetype": "image/jpeg",
          "secret": "OBw287eTrVn78M0szagENtrHwpk1lp6b",
          "width": 412
        },
        "c": {
          "extension": "jpg",
          "height": 600,
          "mimetype": "image/jpeg",
          "secret": "OBw287eTrVn78M0szagENtrHwpk1lp6b",
          "width": 322
        },
        "dc": {
          "extension": "jpg",
          "height": 600,
          "mimetype": "image/jpeg",
          "secret": "OBw287eTrVn78M0szagENtrHwpk1lp6b",
          "width": 322
        },
        "ds": {
          "extension": "jpg",
          "height": 320,
          "mimetype": "image/jpeg",
          "secret": "OBw287eTrVn78M0szagENtrHwpk1lp6b",
          "width": 320
        },
        "k": {
          "extension": "jpg",
          "height": 1536,
          "mimetype": "image/jpeg",
          "secret": "OBw287eTrVn78M0szagENtrHwpk1lp6b",
          "width": 824
        },
        "n": {
          "extension": "jpg",
          "height": 240,
          "mimetype": "image/jpeg",
          "secret": "OBw287eTrVn78M0szagENtrHwpk1lp6b",
          "width": 128
        },
        "o": {
          "extension": "jpg",
          "height": 2892,
          "mimetype": "image/jpeg",
          "secret": "u0Dc3aEVudGs27Vr5zGtK4Za2uLHRnbc",
          "width": 1553
        },
        "s": {
          "extension": "jpg",
          "height": 320,
          "mimetype": "image/jpeg",
          "secret": "OBw287eTrVn78M0szagENtrHwpk1lp6b",
          "width": 320
        },
        "z": {
          "extension": "jpg",
          "height": 480,
          "mimetype": "image/jpeg",
          "secret": "OBw287eTrVn78M0szagENtrHwpk1lp6b",
          "width": 257
        }
      }
    },
    "media:uri_template": "https://millsfield.sfomuseum.org/media/152/782/471/5/1527824715_{secret}_{label}.{extention}",
    "sfomuseum:filename": "42742.tif",
    "sfomuseum:image_index": 5,
    "sfomuseum:placetype": "image",
    "sfomuseum:primary_image": 1,
    "wof:depicts": [
      1511908769
    ],
    "wof:name": "motion sickness bag: ship (Far East Jetfoils)",
    "wof:placetype": "media"
  },
  "geometry": {"coordinates":[-122.386155,37.616358],"type":"Point"}
}
