{
  "type": "Feature",
  "properties": {
    "iso:country": "XX",
    "media:fingerprint": "52dd998883a8ad3ed035da10beac59ab6ad99c37",
    "media:imagehash_avg": "a:ff1f1e38786c0000",
    "media:imagehash_diff": "d:4838f8f2b8d0949e",
    "media:medium": "image",
    "media:mimetype": "image/tiff",
    "media:properties": {
      "colours": [
        {
          "hex": "#88773b",
          "name": "#88773b",
          "reference": "vibrant"
        }, 
        {
          "hex": "#bbcfe6",
          "name": "#bbcfe6",
          "reference": "vibrant"
        }, 
        {
          "hex": "#a8a66f",
          "name": "#a8a66f",
          "reference": "vibrant"
        }, 
        {
          "hex": "#b7b9bb",
          "name": "#b7b9bb",
          "reference": "vibrant"
        }, 
        {
          "hex": "#573933",
          "name": "#573933",
          "reference": "vibrant"
        }
      ],
      "sizes": {
        "b": {
          "extension": "jpg",
          "height": 768,
          "mimetype": "image/jpeg",
          "secret": "kXGUMScFTdVeX5dxracfPb1ZVCpEhDL1",
          "width": 484
        },
        "c": {
          "extension": "jpg",
          "height": 600,
          "mimetype": "image/jpeg",
          "secret": "kXGUMScFTdVeX5dxracfPb1ZVCpEhDL1",
          "width": 378
        },
        "dc": {
          "extension": "jpg",
          "height": 600,
          "mimetype": "image/jpeg",
          "secret": "kXGUMScFTdVeX5dxracfPb1ZVCpEhDL1",
          "width": 378
        },
        "ds": {
          "extension": "jpg",
          "height": 320,
          "mimetype": "image/jpeg",
          "secret": "kXGUMScFTdVeX5dxracfPb1ZVCpEhDL1",
          "width": 320
        },
        "k": {
          "extension": "jpg",
          "height": 1536,
          "mimetype": "image/jpeg",
          "secret": "kXGUMScFTdVeX5dxracfPb1ZVCpEhDL1",
          "width": 968
        },
        "n": {
          "extension": "jpg",
          "height": 240,
          "mimetype": "image/jpeg",
          "secret": "kXGUMScFTdVeX5dxracfPb1ZVCpEhDL1",
          "width": 151
        },
        "o": {
          "extension": "jpg",
          "height": 1679,
          "mimetype": "image/jpeg",
          "secret": "Fc79Qpwqhb1tsOKHUqR47TjWPxfkbUB2",
          "width": 1059
        },
        "s": {
          "extension": "jpg",
          "height": 320,
          "mimetype": "image/jpeg",
          "secret": "kXGUMScFTdVeX5dxracfPb1ZVCpEhDL1",
          "width": 320
        },
        "z": {
          "extension": "jpg",
          "height": 480,
          "mimetype": "image/jpeg",
          "secret": "kXGUMScFTdVeX5dxracfPb1ZVCpEhDL1",
          "width": 302
        }
      }
    },
    "media:uri_template": "https://millsfield.sfomuseum.org/media/152/782/762/9/1527827629_{secret}_{label}.{extention}",
    "sfomuseum:filename": "44172.tif",
    "sfomuseum:image_index": 5,
    "sfomuseum:placetype": "image",
    "sfomuseum:primary_image": 1,
    "wof:depicts": [
      1511948663
    ],
    "wof:name": "negative: San Francisco International Airport (SFO), boarding area interior",
    "wof:placetype": "media"
  },
  "geometry": {"coordinates":[-122.386155,37.616358],"type":"Point"}
}
