{
  "type": "Feature",
  "properties": {
    "iso:country": "XX",
    "media:fingerprint": "dbd296876059354112d29df3984beab8d73176ac",
    "media:imagehash_avg": "a:00c381c3fffffffd",
    "media:imagehash_diff": "d:3117330724307029",
    "media:medium": "image",
    "media:mimetype": "image/tiff",
    "media:properties": {
      "colours": [
        {
          "hex": "#e1d2aa",
          "name": "#e1d2aa",
          "reference": "vibrant"
        },
        {
          "hex": "#8d8872",
          "name": "#8d8872",
          "reference": "vibrant"
        },
        {
          "hex": "#d8cfab",
          "name": "#d8cfab",
          "reference": "vibrant"
        },
        {
          "hex": "#434338",
          "name": "#434338",
          "reference": "vibrant"
        }
      ],
      "sizes": {
        "b": {
          "extension": "jpg",
          "height": 767,
          "mimetype": "image/jpeg",
          "secret": "8zTzvWaxkHZ9un1j0kFwcQLWMxMLcoAM",
          "width": 349
        },
        "c": {
          "extension": "jpg",
          "height": 600,
          "mimetype": "image/jpeg",
          "secret": "8zTzvWaxkHZ9un1j0kFwcQLWMxMLcoAM",
          "width": 272
        },
        "dc": {
          "extension": "jpg",
          "height": 600,
          "mimetype": "image/jpeg",
          "secret": "8zTzvWaxkHZ9un1j0kFwcQLWMxMLcoAM",
          "width": 272
        },
        "ds": {
          "extension": "jpg",
          "height": 320,
          "mimetype": "image/jpeg",
          "secret": "8zTzvWaxkHZ9un1j0kFwcQLWMxMLcoAM",
          "width": 320
        },
        "k": {
          "extension": "jpg",
          "height": 1535,
          "mimetype": "image/jpeg",
          "secret": "8zTzvWaxkHZ9un1j0kFwcQLWMxMLcoAM",
          "width": 698
        },
        "n": {
          "extension": "jpg",
          "height": 240,
          "mimetype": "image/jpeg",
          "secret": "8zTzvWaxkHZ9un1j0kFwcQLWMxMLcoAM",
          "width": 109
        },
        "o": {
          "extension": "jpg",
          "height": 2781,
          "mimetype": "image/jpeg",
          "secret": "Hk3rqatlPi0nCj3vDMj80fcGOLHbnNh9",
          "width": 1264
        },
        "s": {
          "extension": "jpg",
          "height": 320,
          "mimetype": "image/jpeg",
          "secret": "8zTzvWaxkHZ9un1j0kFwcQLWMxMLcoAM",
          "width": 320
        },
        "z": {
          "extension": "jpg",
          "height": 480,
          "mimetype": "image/jpeg",
          "secret": "8zTzvWaxkHZ9un1j0kFwcQLWMxMLcoAM",
          "width": 218
        }
      }
    },
    "media:uri_template": "https://static.sfomuseum.org/media/152/785/492/1/1527854921_{secret}_{label}.{extention}",
    "sfomuseum:filename": "2009.122.342_verso.tif",
    "sfomuseum:image_index": 5,
    "sfomuseum:image_type": "studio",
    "sfomuseum:placetype": "image",
    "sfomuseum:primary_image": 0,
    "wof:depicts": [
      1159285785,
      1511940673
    ],
    "wof:name": "timetable: JAL (Japan Air Lines)",
    "wof:placetype": "custom",
    "wof:placetype_alt": "image"
  },
  "geometry": {"coordinates":[-122.386155,37.616358],"type":"Point"}
}
