{
  "type": "Feature",
  "properties": {
    "iso:country": "XX",
    "media:fingerprint": "e41a7f6ee3ff20f55abe345fc6ba2927c5416542",
    "media:imagehash_avg": "a:ff9c940d0f1f9ffe",
    "media:imagehash_diff": "d:3c3c29793b373730",
    "media:medium": "image",
    "media:mimetype": "image/tiff",
    "media:properties": {
      "colours": [
        {
          "hex": "#b3934f",
          "name": "#b3934f",
          "reference": "vibrant"
        }, 
        {
          "hex": "#ed8f77",
          "name": "#ed8f77",
          "reference": "vibrant"
        }, 
        {
          "hex": "#896353",
          "name": "#896353",
          "reference": "vibrant"
        }, 
        {
          "hex": "#c4c4be",
          "name": "#c4c4be",
          "reference": "vibrant"
        }, 
        {
          "hex": "#413a39",
          "name": "#413a39",
          "reference": "vibrant"
        }
      ],
      "sizes": {
        "b": {
          "extension": "jpg",
          "height": 576,
          "mimetype": "image/jpeg",
          "secret": "I8i0S1sbNQlBPuwbDjfztEvuYbVJWTMp",
          "width": 1024
        },
        "c": {
          "extension": "jpg",
          "height": 450,
          "mimetype": "image/jpeg",
          "secret": "I8i0S1sbNQlBPuwbDjfztEvuYbVJWTMp",
          "width": 800
        },
        "dc": {
          "extension": "jpg",
          "height": 450,
          "mimetype": "image/jpeg",
          "secret": "I8i0S1sbNQlBPuwbDjfztEvuYbVJWTMp",
          "width": 800
        },
        "ds": {
          "extension": "jpg",
          "height": 320,
          "mimetype": "image/jpeg",
          "secret": "I8i0S1sbNQlBPuwbDjfztEvuYbVJWTMp",
          "width": 320
        },
        "k": {
          "extension": "jpg",
          "height": 1152,
          "mimetype": "image/jpeg",
          "secret": "I8i0S1sbNQlBPuwbDjfztEvuYbVJWTMp",
          "width": 2048
        },
        "n": {
          "extension": "jpg",
          "height": 180,
          "mimetype": "image/jpeg",
          "secret": "I8i0S1sbNQlBPuwbDjfztEvuYbVJWTMp",
          "width": 320
        },
        "o": {
          "extension": "jpg",
          "height": 1074,
          "mimetype": "image/jpeg",
          "secret": "lT4JOC0KUlIlhwshlJTs8YykL8TPkXm1",
          "width": 1908
        },
        "s": {
          "extension": "jpg",
          "height": 320,
          "mimetype": "image/jpeg",
          "secret": "I8i0S1sbNQlBPuwbDjfztEvuYbVJWTMp",
          "width": 320
        },
        "z": {
          "extension": "jpg",
          "height": 360,
          "mimetype": "image/jpeg",
          "secret": "I8i0S1sbNQlBPuwbDjfztEvuYbVJWTMp",
          "width": 640
        }
      }
    },
    "media:uri_template": "https://millsfield.sfomuseum.org/media/152/781/980/7/1527819807_{secret}_{label}.{extention}",
    "sfomuseum:filename": "31117.tif",
    "sfomuseum:image_index": 5,
    "sfomuseum:placetype": "image",
    "sfomuseum:primary_image": 1,
    "wof:depicts": [
      1511906785
    ],
    "wof:name": "airmail flight cover: National Air and Space Museum, Smithsonian Institution, Daniel Guggenheim Fund",
    "wof:placetype": "media"
  },
  "geometry": {"coordinates":[-122.386155,37.616358],"type":"Point"}
}
