{
  "type": "Feature",
  "properties": {
    "iso:country": "XX",
    "media:fingerprint": "8a98d4730c402f40274f3680b7c241a0909854fb",
    "media:imagehash_avg": "a:0000ffffff389800",
    "media:imagehash_diff": "d:0f1f71d81a6232f8",
    "media:medium": "image",
    "media:mimetype": "image/tiff",
    "media:properties": {
      "colours": [
        {
          "hex": "#858585",
          "name": "#858585",
          "reference": "vibrant"
        }, 
        {
          "hex": "#c0c0c0",
          "name": "#c0c0c0",
          "reference": "vibrant"
        }, 
        {
          "hex": "#404040",
          "name": "#404040",
          "reference": "vibrant"
        }
      ],
      "sizes": {
        "b": {
          "extension": "jpg",
          "height": 768,
          "mimetype": "image/jpeg",
          "secret": "9jNYE6HeyUCuyVaANdfu0UKJqBAqCe3B",
          "width": 785
        },
        "c": {
          "extension": "jpg",
          "height": 600,
          "mimetype": "image/jpeg",
          "secret": "9jNYE6HeyUCuyVaANdfu0UKJqBAqCe3B",
          "width": 613
        },
        "dc": {
          "extension": "jpg",
          "height": 600,
          "mimetype": "image/jpeg",
          "secret": "9jNYE6HeyUCuyVaANdfu0UKJqBAqCe3B",
          "width": 613
        },
        "ds": {
          "extension": "jpg",
          "height": 320,
          "mimetype": "image/jpeg",
          "secret": "9jNYE6HeyUCuyVaANdfu0UKJqBAqCe3B",
          "width": 320
        },
        "k": {
          "extension": "jpg",
          "height": 1536,
          "mimetype": "image/jpeg",
          "secret": "9jNYE6HeyUCuyVaANdfu0UKJqBAqCe3B",
          "width": 1570
        },
        "n": {
          "extension": "jpg",
          "height": 240,
          "mimetype": "image/jpeg",
          "secret": "9jNYE6HeyUCuyVaANdfu0UKJqBAqCe3B",
          "width": 245
        },
        "o": {
          "extension": "jpg",
          "height": 2481,
          "mimetype": "image/jpeg",
          "secret": "eN9E4nrszf8DecQWbM7I6hfsJNmQHaFy",
          "width": 2536
        },
        "s": {
          "extension": "jpg",
          "height": 320,
          "mimetype": "image/jpeg",
          "secret": "9jNYE6HeyUCuyVaANdfu0UKJqBAqCe3B",
          "width": 320
        },
        "z": {
          "extension": "jpg",
          "height": 480,
          "mimetype": "image/jpeg",
          "secret": "9jNYE6HeyUCuyVaANdfu0UKJqBAqCe3B",
          "width": 490
        }
      }
    },
    "media:uri_template": "https://millsfield.sfomuseum.org/media/152/782/661/5/1527826615_{secret}_{label}.{extention}",
    "sfomuseum:filename": "43720.tif",
    "sfomuseum:image_index": 5,
    "sfomuseum:placetype": "image",
    "sfomuseum:primary_image": 1,
    "wof:depicts": [
      1511947655
    ],
    "wof:name": "negative: San Francisco International Airport (SFO), Central Terminal and control tower",
    "wof:placetype": "media"
  },
  "geometry": {"coordinates":[-122.386155,37.616358],"type":"Point"}
}
