{
  "type": "Feature",
  "properties": {
    "iso:country": "XX",
    "media:fingerprint": "158f00d02eadc8fac12b307b9dfd5e0e6f593d5a",
    "media:imagehash_avg": "a:00003cf8d8c3ffff",
    "media:imagehash_diff": "d:e0e0e022b296e8e0",
    "media:medium": "image",
    "media:mimetype": "image/tiff",
    "media:properties": {
      "colours": [
        {
          "hex": "#7f817b",
          "name": "#7f817b",
          "reference": "vibrant"
        },
        {
          "hex": "#b7b7b6",
          "name": "#b7b7b6",
          "reference": "vibrant"
        },
        {
          "hex": "#43433d",
          "name": "#43433d",
          "reference": "vibrant"
        }
      ],
      "sizes": {
        "b": {
          "extension": "jpg",
          "height": 768,
          "mimetype": "image/jpeg",
          "secret": "IYVh1YoV7EJSgchQ8h9P1Q6UuHYdfyq1",
          "width": 965
        },
        "c": {
          "extension": "jpg",
          "height": 600,
          "mimetype": "image/jpeg",
          "secret": "IYVh1YoV7EJSgchQ8h9P1Q6UuHYdfyq1",
          "width": 754
        },
        "dc": {
          "extension": "jpg",
          "height": 600,
          "mimetype": "image/jpeg",
          "secret": "IYVh1YoV7EJSgchQ8h9P1Q6UuHYdfyq1",
          "width": 754
        },
        "ds": {
          "extension": "jpg",
          "height": 320,
          "mimetype": "image/jpeg",
          "secret": "IYVh1YoV7EJSgchQ8h9P1Q6UuHYdfyq1",
          "width": 320
        },
        "k": {
          "extension": "jpg",
          "height": 1536,
          "mimetype": "image/jpeg",
          "secret": "IYVh1YoV7EJSgchQ8h9P1Q6UuHYdfyq1",
          "width": 1931
        },
        "n": {
          "extension": "jpg",
          "height": 240,
          "mimetype": "image/jpeg",
          "secret": "IYVh1YoV7EJSgchQ8h9P1Q6UuHYdfyq1",
          "width": 301
        },
        "o": {
          "extension": "jpg",
          "height": 1667,
          "mimetype": "image/jpeg",
          "secret": "7qmrfvIXkt3l9SVeYvNBfancUFpl317s",
          "width": 2096
        },
        "s": {
          "extension": "jpg",
          "height": 320,
          "mimetype": "image/jpeg",
          "secret": "IYVh1YoV7EJSgchQ8h9P1Q6UuHYdfyq1",
          "width": 320
        },
        "z": {
          "extension": "jpg",
          "height": 480,
          "mimetype": "image/jpeg",
          "secret": "IYVh1YoV7EJSgchQ8h9P1Q6UuHYdfyq1",
          "width": 603
        }
      }
    },
    "media:uri_template": "https://static.sfomuseum.org/media/152/785/845/5/1527858455_{secret}_{label}.{extention}",
    "sfomuseum:filename": "2002.063.012.tif",
    "sfomuseum:image_index": 5,
    "sfomuseum:image_type": "studio",
    "sfomuseum:placetype": "image",
    "sfomuseum:primary_image": 1,
    "wof:depicts": [
      1511923439,
      1159283539,
      1159287499
    ],
    "wof:name": "butter dish: AeroMexico",
    "wof:placetype": "custom",
    "wof:placetype_alt": "image"
  },
  "geometry": {"coordinates":[-122.386155,37.616358],"type":"Point"}
}
