{
  "type": "Feature",
  "properties": {
    "iso:country": "XX",
    "media:fingerprint": "54a3697f4e15de91ef2ebd5a987212021afe8bfe",
    "media:imagehash_avg": "a:038387e7e7e0c3c2",
    "media:imagehash_diff": "d:7636350d0d0f0e0c",
    "media:medium": "image",
    "media:mimetype": "image/tiff",
    "media:properties": {
      "colours": [
        {
          "hex": "#808080",
          "name": "#808080",
          "reference": "vibrant"
        }, 
        {
          "hex": "#b8b8b8",
          "name": "#b8b8b8",
          "reference": "vibrant"
        }, 
        {
          "hex": "#484848",
          "name": "#484848",
          "reference": "vibrant"
        }
      ],
      "sizes": {
        "b": {
          "extension": "jpg",
          "height": 768,
          "mimetype": "image/jpeg",
          "secret": "0Fb4MsnBFsfBjAuWgYPnZY8wTtzjXO9k",
          "width": 969
        },
        "c": {
          "extension": "jpg",
          "height": 600,
          "mimetype": "image/jpeg",
          "secret": "0Fb4MsnBFsfBjAuWgYPnZY8wTtzjXO9k",
          "width": 757
        },
        "dc": {
          "extension": "jpg",
          "height": 600,
          "mimetype": "image/jpeg",
          "secret": "0Fb4MsnBFsfBjAuWgYPnZY8wTtzjXO9k",
          "width": 757
        },
        "ds": {
          "extension": "jpg",
          "height": 320,
          "mimetype": "image/jpeg",
          "secret": "0Fb4MsnBFsfBjAuWgYPnZY8wTtzjXO9k",
          "width": 320
        },
        "k": {
          "extension": "jpg",
          "height": 1536,
          "mimetype": "image/jpeg",
          "secret": "0Fb4MsnBFsfBjAuWgYPnZY8wTtzjXO9k",
          "width": 1939
        },
        "n": {
          "extension": "jpg",
          "height": 240,
          "mimetype": "image/jpeg",
          "secret": "0Fb4MsnBFsfBjAuWgYPnZY8wTtzjXO9k",
          "width": 303
        },
        "o": {
          "extension": "jpg",
          "height": 2181,
          "mimetype": "image/jpeg",
          "secret": "7gXbL0F0oHYW4cqocNZYsnmrWj7rBouy",
          "width": 2754
        },
        "s": {
          "extension": "jpg",
          "height": 320,
          "mimetype": "image/jpeg",
          "secret": "0Fb4MsnBFsfBjAuWgYPnZY8wTtzjXO9k",
          "width": 320
        },
        "z": {
          "extension": "jpg",
          "height": 480,
          "mimetype": "image/jpeg",
          "secret": "0Fb4MsnBFsfBjAuWgYPnZY8wTtzjXO9k",
          "width": 606
        }
      }
    },
    "media:uri_template": "https://millsfield.sfomuseum.org/media/152/782/322/7/1527823227_{secret}_{label}.{extention}",
    "sfomuseum:filename": "41292.tif",
    "sfomuseum:image_index": 5,
    "sfomuseum:placetype": "image",
    "sfomuseum:primary_image": 1,
    "wof:depicts": [
      1511945125
    ],
    "wof:name": "negative: San Francisco International Airport (SFO), South Terminal construction",
    "wof:placetype": "media"
  },
  "geometry": {"coordinates":[-122.386155,37.616358],"type":"Point"}
}
