{
  "type": "Feature",
  "properties": {
    "iso:country": "TH",
    "media:fingerprint": "41622f109438664a517777ef1f41a1344bcdb1b6",
    "media:imagehash_avg": "a:ffc7e7f7b780beff",
    "media:imagehash_diff": "d:414d4d6d4d4d6869",
    "media:medium": "image",
    "media:mimetype": "image/tiff",
    "media:properties": {
      "colours": [
        {
          "hex": "#d0bb95",
          "name": "#d0bb95",
          "reference": "vibrant"
        }, 
        {
          "hex": "#f6ecdf",
          "name": "#f6ecdf",
          "reference": "vibrant"
        }, 
        {
          "hex": "#191956",
          "name": "#191956",
          "reference": "vibrant"
        }, 
        {
          "hex": "#79778c",
          "name": "#79778c",
          "reference": "vibrant"
        }, 
        {
          "hex": "#c8bda2",
          "name": "#c8bda2",
          "reference": "vibrant"
        }
      ],
      "sizes": {
        "b": {
          "extension": "jpg",
          "height": 768,
          "mimetype": "image/jpeg",
          "secret": "7fNn78MojoDzJiVZeyPhlOVlHSlqcFiK",
          "width": 435
        },
        "c": {
          "extension": "jpg",
          "height": 600,
          "mimetype": "image/jpeg",
          "secret": "7fNn78MojoDzJiVZeyPhlOVlHSlqcFiK",
          "width": 340
        },
        "dc": {
          "extension": "jpg",
          "height": 600,
          "mimetype": "image/jpeg",
          "secret": "7fNn78MojoDzJiVZeyPhlOVlHSlqcFiK",
          "width": 340
        },
        "ds": {
          "extension": "jpg",
          "height": 320,
          "mimetype": "image/jpeg",
          "secret": "7fNn78MojoDzJiVZeyPhlOVlHSlqcFiK",
          "width": 320
        },
        "k": {
          "extension": "jpg",
          "height": 1536,
          "mimetype": "image/jpeg",
          "secret": "7fNn78MojoDzJiVZeyPhlOVlHSlqcFiK",
          "width": 870
        },
        "n": {
          "extension": "jpg",
          "height": 240,
          "mimetype": "image/jpeg",
          "secret": "7fNn78MojoDzJiVZeyPhlOVlHSlqcFiK",
          "width": 136
        },
        "o": {
          "extension": "jpg",
          "height": 1956,
          "mimetype": "image/jpeg",
          "secret": "UpiUoaMSWU5BSKOfq5jGmDendRdDeWJa",
          "width": 1109
        },
        "s": {
          "extension": "jpg",
          "height": 320,
          "mimetype": "image/jpeg",
          "secret": "7fNn78MojoDzJiVZeyPhlOVlHSlqcFiK",
          "width": 320
        },
        "z": {
          "extension": "jpg",
          "height": 480,
          "mimetype": "image/jpeg",
          "secret": "7fNn78MojoDzJiVZeyPhlOVlHSlqcFiK",
          "width": 272
        }
      }
    },
    "media:uri_template": "https://millsfield.sfomuseum.org/media/152/782/942/1/1527829421_{secret}_{label}.{extention}",
    "sfomuseum:filename": "48234.tif",
    "sfomuseum:image_index": 5,
    "sfomuseum:placetype": "image",
    "sfomuseum:primary_image": 0,
    "wof:depicts": [
      1511906971
    ],
    "wof:name": "airmail flight cover: Pan American World Airways, Bangkok - Calcutta route",
    "wof:placetype": "media"
  },
  "geometry": {"coordinates":[-122.386155,37.616358],"type":"Point"}
}
