{
  "type": "Feature",
  "properties": {
    "iso:country": "XX",
    "media:fingerprint": "b6ae87a2d9de6a5d77d72ab0615fc0d2d6c59c21",
    "media:imagehash_avg": "a:f7c181808181c3ff",
    "media:imagehash_diff": "d:0f1743270f2b070f",
    "media:medium": "image",
    "media:mimetype": "image/tiff",
    "media:properties": {
      "colours": [
        {
          "hex": "#e8eff5",
          "name": "#e8eff5",
          "reference": "vibrant"
        }, 
        {
          "hex": "#5d8878",
          "name": "#5d8878",
          "reference": "vibrant"
        }, 
        {
          "hex": "#d4cdb8",
          "name": "#d4cdb8",
          "reference": "vibrant"
        }, 
        {
          "hex": "#58463a",
          "name": "#58463a",
          "reference": "vibrant"
        }
      ],
      "sizes": {
        "b": {
          "extension": "jpg",
          "height": 640,
          "mimetype": "image/jpeg",
          "secret": "LBjCSg0cTwvFpNVdnsV1j5tJ1RGkSpIo",
          "width": 1024
        },
        "c": {
          "extension": "jpg",
          "height": 500,
          "mimetype": "image/jpeg",
          "secret": "LBjCSg0cTwvFpNVdnsV1j5tJ1RGkSpIo",
          "width": 800
        },
        "dc": {
          "extension": "jpg",
          "height": 500,
          "mimetype": "image/jpeg",
          "secret": "LBjCSg0cTwvFpNVdnsV1j5tJ1RGkSpIo",
          "width": 800
        },
        "ds": {
          "extension": "jpg",
          "height": 320,
          "mimetype": "image/jpeg",
          "secret": "LBjCSg0cTwvFpNVdnsV1j5tJ1RGkSpIo",
          "width": 320
        },
        "k": {
          "extension": "jpg",
          "height": 1280,
          "mimetype": "image/jpeg",
          "secret": "LBjCSg0cTwvFpNVdnsV1j5tJ1RGkSpIo",
          "width": 2048
        },
        "n": {
          "extension": "jpg",
          "height": 200,
          "mimetype": "image/jpeg",
          "secret": "LBjCSg0cTwvFpNVdnsV1j5tJ1RGkSpIo",
          "width": 320
        },
        "o": {
          "extension": "jpg",
          "height": 1350,
          "mimetype": "image/jpeg",
          "secret": "RfSBYRlphMoui6yClb3ds0mDqVSjfxbj",
          "width": 2160
        },
        "s": {
          "extension": "jpg",
          "height": 320,
          "mimetype": "image/jpeg",
          "secret": "LBjCSg0cTwvFpNVdnsV1j5tJ1RGkSpIo",
          "width": 320
        },
        "z": {
          "extension": "jpg",
          "height": 400,
          "mimetype": "image/jpeg",
          "secret": "LBjCSg0cTwvFpNVdnsV1j5tJ1RGkSpIo",
          "width": 640
        }
      }
    },
    "media:uri_template": "https://millsfield.sfomuseum.org/media/152/781/823/1/1527818231_{secret}_{label}.{extention}",
    "sfomuseum:filename": "16048.tif",
    "sfomuseum:image_index": 5,
    "sfomuseum:placetype": "image",
    "sfomuseum:primary_image": 1,
    "wof:depicts": [
      1511923859
    ],
    "wof:name": "luggage label: China National Aviation Corporation (CNAC)",
    "wof:placetype": "media"
  },
  "geometry": {"coordinates":[-122.386155,37.616358],"type":"Point"}
}
