{
  "type": "Feature",
  "properties": {
    "iso:country": "XX",
    "media:fingerprint": "b806f0fe039836a2a5ef2798777e7961bf029e96",
    "media:imagehash_avg": "a:8100e4e0e0ff00ff",
    "media:imagehash_diff": "d:1149cd4d45c84d5d",
    "media:medium": "image",
    "media:mimetype": "image/tiff",
    "media:properties": {
      "colours": [
        {
          "hex": "#903f35",
          "name": "#903f35",
          "reference": "vibrant"
        },
        {
          "hex": "#25364e",
          "name": "#25364e",
          "reference": "vibrant"
        },
        {
          "hex": "#718685",
          "name": "#718685",
          "reference": "vibrant"
        },
        {
          "hex": "#c6bf97",
          "name": "#c6bf97",
          "reference": "vibrant"
        },
        {
          "hex": "#354a56",
          "name": "#354a56",
          "reference": "vibrant"
        }
      ],
      "sizes": {
        "b": {
          "extension": "jpg",
          "height": 739,
          "mimetype": "image/jpeg",
          "secret": "BlPBQ7h9oPRPuB9ELKJSDehQNfSs0uwa",
          "width": 1024
        },
        "c": {
          "extension": "jpg",
          "height": 577,
          "mimetype": "image/jpeg",
          "secret": "BlPBQ7h9oPRPuB9ELKJSDehQNfSs0uwa",
          "width": 800
        },
        "dc": {
          "extension": "jpg",
          "height": 577,
          "mimetype": "image/jpeg",
          "secret": "BlPBQ7h9oPRPuB9ELKJSDehQNfSs0uwa",
          "width": 800
        },
        "ds": {
          "extension": "jpg",
          "height": 320,
          "mimetype": "image/jpeg",
          "secret": "BlPBQ7h9oPRPuB9ELKJSDehQNfSs0uwa",
          "width": 320
        },
        "k": {
          "extension": "jpg",
          "height": 1479,
          "mimetype": "image/jpeg",
          "secret": "BlPBQ7h9oPRPuB9ELKJSDehQNfSs0uwa",
          "width": 2048
        },
        "n": {
          "extension": "jpg",
          "height": 231,
          "mimetype": "image/jpeg",
          "secret": "BlPBQ7h9oPRPuB9ELKJSDehQNfSs0uwa",
          "width": 320
        },
        "o": {
          "extension": "jpg",
          "height": 1515,
          "mimetype": "image/jpeg",
          "secret": "r4myqCak0xH1ZRFS8kvi2FBQc4v3ypze",
          "width": 2097
        },
        "s": {
          "extension": "jpg",
          "height": 320,
          "mimetype": "image/jpeg",
          "secret": "BlPBQ7h9oPRPuB9ELKJSDehQNfSs0uwa",
          "width": 320
        },
        "z": {
          "extension": "jpg",
          "height": 462,
          "mimetype": "image/jpeg",
          "secret": "BlPBQ7h9oPRPuB9ELKJSDehQNfSs0uwa",
          "width": 640
        }
      }
    },
    "media:uri_template": "https://static.sfomuseum.org/media/152/783/150/7/1527831507_{secret}_{label}.{extention}",
    "sfomuseum:filename": "60549.tif",
    "sfomuseum:image_index": 5,
    "sfomuseum:image_type": "studio",
    "sfomuseum:placetype": "image",
    "sfomuseum:primary_image": 1,
    "wof:depicts": [
      1511943263
    ],
    "wof:name": "stock certificate: Aviation Corporation of the Americas",
    "wof:placetype": "custom",
    "wof:placetype_alt": "image"
  },
  "geometry": {"coordinates":[-122.386155,37.616358],"type":"Point"}
}
