{
  "type": "Feature",
  "properties": {
    "date:cessation_lower": "1931-06-13",
    "date:cessation_upper": "1931-06-13",
    "date:inception_lower": "1931-06-13",
    "date:inception_upper": "1931-06-13",
    "iso:country": "XX",
    "millsfield:exhibition_ids": [
      1159160119
    ],
    "millsfield:images_texts": [
      "FIRST PACIFIC COAST\nSHIP-TO - SHORE\nAIR MAIL TRANSFER\nS.S. City of Los Angeles\nand\nGoodyear Airship\" Volunteer\nSAN FRANCISCO\nLOS ANGELES.\nGOOD FYEAR\nСЕЗіСА,\nJUN13\n'AAM\nVIA AIR MAIL\nFrederick M.Baker\n458 East 5th st.\nDayton, Ohio."
    ],
    "millsfield:images_texts_ids": [
      1527831727
    ],
    "millsfield:on_view": 0,
    "sfomuseum:filename": "2008.075.008_reverse.tif",
    "sfomuseum:image_index": 0,
    "sfomuseum:image_type": "studio",
    "sfomuseum:placetype": "image",
    "sfomuseum:primary_image": 0,
    "wof:depicts": [
      1511931515
    ],
    "wof:name": "airmail flight cover: First Pacific coast ship-to-shore airmail, S.S. City of Los Angeles - Los Angeles, June 13, 1931",
    "wof:placetype": "custom"
  },
  "geometry": {"coordinates":[-122.386155,37.616357],"type":"Point"}
}
