{
  "type": "Feature",
  "properties": {
    "iso:country": "XX",
    "media:fingerprint": "0576f0aba8bdf688159043b0ee66858fb60182e0",
    "media:imagehash_avg": "a:000001006c17dfff",
    "media:imagehash_diff": "d:c8e5b9d9ddf52e0d",
    "media:medium": "image",
    "media:mimetype": "image/tiff",
    "media:properties": {
      "colours": [
        {
          "hex": "#858585",
          "name": "#858585",
          "reference": "vibrant"
        }, 
        {
          "hex": "#c0c0c0",
          "name": "#c0c0c0",
          "reference": "vibrant"
        }, 
        {
          "hex": "#484848",
          "name": "#484848",
          "reference": "vibrant"
        }
      ],
      "sizes": {
        "b": {
          "extension": "jpg",
          "height": 768,
          "mimetype": "image/jpeg",
          "secret": "IPtzVIgRA5oJpz1aNnfhvYKfJcRsF2gG",
          "width": 991
        },
        "c": {
          "extension": "jpg",
          "height": 600,
          "mimetype": "image/jpeg",
          "secret": "IPtzVIgRA5oJpz1aNnfhvYKfJcRsF2gG",
          "width": 774
        },
        "dc": {
          "extension": "jpg",
          "height": 600,
          "mimetype": "image/jpeg",
          "secret": "IPtzVIgRA5oJpz1aNnfhvYKfJcRsF2gG",
          "width": 774
        },
        "ds": {
          "extension": "jpg",
          "height": 320,
          "mimetype": "image/jpeg",
          "secret": "IPtzVIgRA5oJpz1aNnfhvYKfJcRsF2gG",
          "width": 320
        },
        "k": {
          "extension": "jpg",
          "height": 1536,
          "mimetype": "image/jpeg",
          "secret": "IPtzVIgRA5oJpz1aNnfhvYKfJcRsF2gG",
          "width": 1983
        },
        "n": {
          "extension": "jpg",
          "height": 240,
          "mimetype": "image/jpeg",
          "secret": "IPtzVIgRA5oJpz1aNnfhvYKfJcRsF2gG",
          "width": 309
        },
        "o": {
          "extension": "jpg",
          "height": 2154,
          "mimetype": "image/jpeg",
          "secret": "7lU48c7FvE6N4EaMVogoRwdUNm9o3Kni",
          "width": 2781
        },
        "s": {
          "extension": "jpg",
          "height": 320,
          "mimetype": "image/jpeg",
          "secret": "IPtzVIgRA5oJpz1aNnfhvYKfJcRsF2gG",
          "width": 320
        },
        "z": {
          "extension": "jpg",
          "height": 480,
          "mimetype": "image/jpeg",
          "secret": "IPtzVIgRA5oJpz1aNnfhvYKfJcRsF2gG",
          "width": 619
        }
      }
    },
    "media:uri_template": "https://millsfield.sfomuseum.org/media/152/782/787/1/1527827871_{secret}_{label}.{extention}",
    "sfomuseum:filename": "44280.tif",
    "sfomuseum:image_index": 5,
    "sfomuseum:placetype": "image",
    "sfomuseum:primary_image": 1,
    "wof:depicts": [
      1511948905
    ],
    "wof:name": "negative: San Francisco International Airport (SFO), engineering division personnel",
    "wof:placetype": "media"
  },
  "geometry": {"coordinates":[-122.386155,37.616358],"type":"Point"}
}
