{
  "type": "Feature",
  "properties": {
    "iso:country": "XX",
    "media:fingerprint": "900285bffe78d954efc3c2d0b4513a6741eadc54",
    "media:imagehash_avg": "a:073c1f1ffff7ff00",
    "media:imagehash_diff": "d:7d7939388c8e8a0d",
    "media:medium": "image",
    "media:mimetype": "image/tiff",
    "media:properties": {
      "colours": [
        {
          "hex": "#ab2216",
          "name": "#ab2216",
          "reference": "vibrant"
        }, 
        {
          "hex": "#d9c58e",
          "name": "#d9c58e",
          "reference": "vibrant"
        }, 
        {
          "hex": "#182b63",
          "name": "#182b63",
          "reference": "vibrant"
        }, 
        {
          "hex": "#b16951",
          "name": "#b16951",
          "reference": "vibrant"
        }, 
        {
          "hex": "#c8b888",
          "name": "#c8b888",
          "reference": "vibrant"
        }
      ],
      "sizes": {
        "b": {
          "extension": "jpg",
          "height": 456,
          "mimetype": "image/jpeg",
          "secret": "8d2g35T0xj1M5lRCD40YmznZRuZsunUW",
          "width": 1024
        },
        "c": {
          "extension": "jpg",
          "height": 356,
          "mimetype": "image/jpeg",
          "secret": "8d2g35T0xj1M5lRCD40YmznZRuZsunUW",
          "width": 800
        },
        "dc": {
          "extension": "jpg",
          "height": 356,
          "mimetype": "image/jpeg",
          "secret": "8d2g35T0xj1M5lRCD40YmznZRuZsunUW",
          "width": 800
        },
        "ds": {
          "extension": "jpg",
          "height": 320,
          "mimetype": "image/jpeg",
          "secret": "8d2g35T0xj1M5lRCD40YmznZRuZsunUW",
          "width": 320
        },
        "k": {
          "extension": "jpg",
          "height": 912,
          "mimetype": "image/jpeg",
          "secret": "8d2g35T0xj1M5lRCD40YmznZRuZsunUW",
          "width": 2048
        },
        "n": {
          "extension": "jpg",
          "height": 142,
          "mimetype": "image/jpeg",
          "secret": "8d2g35T0xj1M5lRCD40YmznZRuZsunUW",
          "width": 320
        },
        "o": {
          "extension": "jpg",
          "height": 1296,
          "mimetype": "image/jpeg",
          "secret": "70nksX5fvMmRUaXbPTZF6irhPQwPENjO",
          "width": 2908
        },
        "s": {
          "extension": "jpg",
          "height": 320,
          "mimetype": "image/jpeg",
          "secret": "8d2g35T0xj1M5lRCD40YmznZRuZsunUW",
          "width": 320
        },
        "z": {
          "extension": "jpg",
          "height": 285,
          "mimetype": "image/jpeg",
          "secret": "8d2g35T0xj1M5lRCD40YmznZRuZsunUW",
          "width": 640
        }
      }
    },
    "media:uri_template": "https://millsfield.sfomuseum.org/media/152/782/037/7/1527820377_{secret}_{label}.{extention}",
    "sfomuseum:filename": "31547.tif",
    "sfomuseum:image_index": 5,
    "sfomuseum:placetype": "image",
    "sfomuseum:primary_image": 1,
    "wof:depicts": [
      1511923593
    ],
    "wof:name": "airmail flight cover: Pan American Airways, Boeing 314 “Dixie Clipper”, Clara Adams",
    "wof:placetype": "media"
  },
  "geometry": {"coordinates":[-122.386155,37.616358],"type":"Point"}
}
