{
  "type": "Feature",
  "properties": {
    "iso:country": "XX",
    "media:fingerprint": "def2668d2e296b99300841207054ed81f5f4b799",
    "media:imagehash_avg": "a:ffbd881898bc3cbc",
    "media:imagehash_diff": "d:7159513333796c78",
    "media:medium": "image",
    "media:mimetype": "image/tiff",
    "media:properties": {
      "colours": [
        {
          "hex": "#c19b36",
          "name": "#c19b36",
          "reference": "vibrant"
        },
        {
          "hex": "#f6dea7",
          "name": "#f6dea7",
          "reference": "vibrant"
        },
        {
          "hex": "#69530f",
          "name": "#69530f",
          "reference": "vibrant"
        },
        {
          "hex": "#99875d",
          "name": "#99875d",
          "reference": "vibrant"
        },
        {
          "hex": "#cbb68c",
          "name": "#cbb68c",
          "reference": "vibrant"
        }
      ],
      "sizes": {
        "b": {
          "extension": "jpg",
          "height": 577,
          "mimetype": "image/jpeg",
          "secret": "p8cvfIm6Fq3jMDjmJrseiogcG6zpzl7K",
          "width": 1024
        },
        "c": {
          "extension": "jpg",
          "height": 451,
          "mimetype": "image/jpeg",
          "secret": "p8cvfIm6Fq3jMDjmJrseiogcG6zpzl7K",
          "width": 800
        },
        "dc": {
          "extension": "jpg",
          "height": 451,
          "mimetype": "image/jpeg",
          "secret": "p8cvfIm6Fq3jMDjmJrseiogcG6zpzl7K",
          "width": 800
        },
        "ds": {
          "extension": "jpg",
          "height": 320,
          "mimetype": "image/jpeg",
          "secret": "p8cvfIm6Fq3jMDjmJrseiogcG6zpzl7K",
          "width": 320
        },
        "k": {
          "extension": "jpg",
          "height": 1155,
          "mimetype": "image/jpeg",
          "secret": "p8cvfIm6Fq3jMDjmJrseiogcG6zpzl7K",
          "width": 2048
        },
        "n": {
          "extension": "jpg",
          "height": 180,
          "mimetype": "image/jpeg",
          "secret": "p8cvfIm6Fq3jMDjmJrseiogcG6zpzl7K",
          "width": 320
        },
        "o": {
          "extension": "jpg",
          "height": 1107,
          "mimetype": "image/jpeg",
          "secret": "CizGYsZazeBtzT484iQzMhA1tNkvjNhR",
          "width": 1962
        },
        "s": {
          "extension": "jpg",
          "height": 320,
          "mimetype": "image/jpeg",
          "secret": "p8cvfIm6Fq3jMDjmJrseiogcG6zpzl7K",
          "width": 320
        },
        "z": {
          "extension": "jpg",
          "height": 361,
          "mimetype": "image/jpeg",
          "secret": "p8cvfIm6Fq3jMDjmJrseiogcG6zpzl7K",
          "width": 640
        }
      }
    },
    "media:uri_template": "https://static.sfomuseum.org/media/152/785/373/9/1527853739_{secret}_{label}.{extention}",
    "sfomuseum:filename": "2008.075.078a_verso.tif",
    "sfomuseum:image_index": 5,
    "sfomuseum:image_type": "studio",
    "sfomuseum:placetype": "image",
    "sfomuseum:primary_image": 0,
    "wof:depicts": [
      1511931835
    ],
    "wof:name": "airmail flight cover: USS Fox, May 17, 1935",
    "wof:placetype": "custom",
    "wof:placetype_alt": "image"
  },
  "geometry": {"coordinates":[-122.386155,37.616358],"type":"Point"}
}
