{
  "type": "Feature",
  "properties": {
    "iso:country": "US",
    "media:fingerprint": "8e50a95ef434c3c37e373b71b0b5ff9cdd76faed",
    "media:imagehash_avg": "a:007effdf7ebc7e00",
    "media:imagehash_diff": "d:57c696b2aa78f02b",
    "media:medium": "image",
    "media:mimetype": "image/tiff",
    "media:properties": {
      "colours": [
        {
          "hex": "#b54c30",
          "name": "#b54c30",
          "reference": "vibrant"
        }, 
        {
          "hex": "#d9caa4",
          "name": "#d9caa4",
          "reference": "vibrant"
        }, 
        {
          "hex": "#831708",
          "name": "#831708",
          "reference": "vibrant"
        }, 
        {
          "hex": "#a39471",
          "name": "#a39471",
          "reference": "vibrant"
        }, 
        {
          "hex": "#cab996",
          "name": "#cab996",
          "reference": "vibrant"
        }
      ],
      "sizes": {
        "b": {
          "extension": "jpg",
          "height": 577,
          "mimetype": "image/jpeg",
          "secret": "6XPcSxB8KU65YfsSwIJvp15mQi9aL92f",
          "width": 1024
        },
        "c": {
          "extension": "jpg",
          "height": 451,
          "mimetype": "image/jpeg",
          "secret": "6XPcSxB8KU65YfsSwIJvp15mQi9aL92f",
          "width": 800
        },
        "dc": {
          "extension": "jpg",
          "height": 451,
          "mimetype": "image/jpeg",
          "secret": "6XPcSxB8KU65YfsSwIJvp15mQi9aL92f",
          "width": 800
        },
        "ds": {
          "extension": "jpg",
          "height": 320,
          "mimetype": "image/jpeg",
          "secret": "6XPcSxB8KU65YfsSwIJvp15mQi9aL92f",
          "width": 320
        },
        "k": {
          "extension": "jpg",
          "height": 1154,
          "mimetype": "image/jpeg",
          "secret": "6XPcSxB8KU65YfsSwIJvp15mQi9aL92f",
          "width": 2048
        },
        "n": {
          "extension": "jpg",
          "height": 180,
          "mimetype": "image/jpeg",
          "secret": "6XPcSxB8KU65YfsSwIJvp15mQi9aL92f",
          "width": 320
        },
        "o": {
          "extension": "jpg",
          "height": 1112,
          "mimetype": "image/jpeg",
          "secret": "h2XpzrQFtCY0vW15YsxQrJG57GsQ97sH",
          "width": 1972
        },
        "s": {
          "extension": "jpg",
          "height": 320,
          "mimetype": "image/jpeg",
          "secret": "6XPcSxB8KU65YfsSwIJvp15mQi9aL92f",
          "width": 320
        },
        "z": {
          "extension": "jpg",
          "height": 360,
          "mimetype": "image/jpeg",
          "secret": "6XPcSxB8KU65YfsSwIJvp15mQi9aL92f",
          "width": 640
        }
      }
    },
    "media:uri_template": "https://millsfield.sfomuseum.org/media/152/781/998/3/1527819983_{secret}_{label}.{extention}",
    "sfomuseum:filename": "31224.tif",
    "sfomuseum:image_index": 5,
    "sfomuseum:placetype": "image",
    "sfomuseum:primary_image": 0,
    "wof:depicts": [
      1511908949
    ],
    "wof:name": "airmail flight cover: Euclid Avenue Airport",
    "wof:placetype": "media"
  },
  "geometry": {"coordinates":[-122.386155,37.616358],"type":"Point"}
}
