{
  "type": "Feature",
  "properties": {
    "iso:country": "XX",
    "media:fingerprint": "b79201891b25a6bc7dc57c4d80bd688566aada95",
    "media:imagehash_avg": "a:007eff3f00e0803f",
    "media:imagehash_diff": "d:f0f8f0f2e2c838f5",
    "media:medium": "image",
    "media:mimetype": "image/tiff",
    "media:properties": {
      "colours": [
        {
          "hex": "#808080",
          "name": "#808080",
          "reference": "vibrant"
        }, 
        {
          "hex": "#b8b8b8",
          "name": "#b8b8b8",
          "reference": "vibrant"
        }, 
        {
          "hex": "#464646",
          "name": "#464646",
          "reference": "vibrant"
        }
      ],
      "sizes": {
        "b": {
          "extension": "jpg",
          "height": 768,
          "mimetype": "image/jpeg",
          "secret": "usU9VbTtHd1ib0TlOvjRQfzLnNhFPJwW",
          "width": 975
        },
        "c": {
          "extension": "jpg",
          "height": 600,
          "mimetype": "image/jpeg",
          "secret": "usU9VbTtHd1ib0TlOvjRQfzLnNhFPJwW",
          "width": 762
        },
        "dc": {
          "extension": "jpg",
          "height": 600,
          "mimetype": "image/jpeg",
          "secret": "usU9VbTtHd1ib0TlOvjRQfzLnNhFPJwW",
          "width": 762
        },
        "ds": {
          "extension": "jpg",
          "height": 320,
          "mimetype": "image/jpeg",
          "secret": "usU9VbTtHd1ib0TlOvjRQfzLnNhFPJwW",
          "width": 320
        },
        "k": {
          "extension": "jpg",
          "height": 1536,
          "mimetype": "image/jpeg",
          "secret": "usU9VbTtHd1ib0TlOvjRQfzLnNhFPJwW",
          "width": 1951
        },
        "n": {
          "extension": "jpg",
          "height": 240,
          "mimetype": "image/jpeg",
          "secret": "usU9VbTtHd1ib0TlOvjRQfzLnNhFPJwW",
          "width": 304
        },
        "o": {
          "extension": "jpg",
          "height": 2168,
          "mimetype": "image/jpeg",
          "secret": "JkmlaZIrsT19RCYK2UT3yn1QXLfsGy6g",
          "width": 2754
        },
        "s": {
          "extension": "jpg",
          "height": 320,
          "mimetype": "image/jpeg",
          "secret": "usU9VbTtHd1ib0TlOvjRQfzLnNhFPJwW",
          "width": 320
        },
        "z": {
          "extension": "jpg",
          "height": 480,
          "mimetype": "image/jpeg",
          "secret": "usU9VbTtHd1ib0TlOvjRQfzLnNhFPJwW",
          "width": 609
        }
      }
    },
    "media:uri_template": "https://millsfield.sfomuseum.org/media/152/782/532/5/1527825325_{secret}_{label}.{extention}",
    "sfomuseum:filename": "43092.tif",
    "sfomuseum:image_index": 5,
    "sfomuseum:placetype": "image",
    "sfomuseum:primary_image": 1,
    "wof:depicts": [
      1511946341
    ],
    "wof:name": "negative: San Francisco International Airport (SFO), airport grounds",
    "wof:placetype": "media"
  },
  "geometry": {"coordinates":[-122.386155,37.616358],"type":"Point"}
}
