{
  "type": "Feature",
  "properties": {
    "date:cessation_lower": "1945-01-01",
    "date:cessation_upper": "1945-12-31",
    "date:inception_lower": "1945-01-01",
    "date:inception_upper": "1945-12-31",
    "iso:country": "XX",
    "sfomuseum:image_index": 5,
    "sfomuseum:image_type": "studio",
    "sfomuseum:placetype": "image",
    "sfomuseum:primary_image": 0,
    "wof:depicts": [
      1159286839,
      1511910311,
      1159284989
    ],
    "wof:name": "poster: Pan American World Airways, Routes of the Flying Clipper Ships",
    "wof:placetype": "custom"
  },
  "geometry": {"coordinates":[-122.386155,37.616357],"type":"Point"}
}
