{
  "type": "Feature",
  "properties": {
    "iso:country": "XX",
    "media:fingerprint": "1a72eb2bc1c09b3c920fa6e34fc8831b97f0925c",
    "media:imagehash_avg": "a:009987bfada5a5ff",
    "media:imagehash_diff": "d:3a3b6d69696d494c",
    "media:medium": "image",
    "media:mimetype": "image/tiff",
    "media:properties": {
      "colours": [
        {
          "hex": "#1f3fb9",
          "name": "#1f3fb9",
          "reference": "vibrant"
        },
        {
          "hex": "#a6aed7",
          "name": "#a6aed7",
          "reference": "vibrant"
        },
        {
          "hex": "#6b7ab0",
          "name": "#6b7ab0",
          "reference": "vibrant"
        },
        {
          "hex": "#b9c2d8",
          "name": "#b9c2d8",
          "reference": "vibrant"
        }
      ],
      "sizes": {
        "b": {
          "extension": "jpg",
          "height": 742,
          "mimetype": "image/jpeg",
          "secret": "pisGReHh8YLvEibuIQPKV73w2Eq6Te5K",
          "width": 1024
        },
        "c": {
          "extension": "jpg",
          "height": 579,
          "mimetype": "image/jpeg",
          "secret": "pisGReHh8YLvEibuIQPKV73w2Eq6Te5K",
          "width": 800
        },
        "dc": {
          "extension": "jpg",
          "height": 579,
          "mimetype": "image/jpeg",
          "secret": "pisGReHh8YLvEibuIQPKV73w2Eq6Te5K",
          "width": 800
        },
        "ds": {
          "extension": "jpg",
          "height": 320,
          "mimetype": "image/jpeg",
          "secret": "pisGReHh8YLvEibuIQPKV73w2Eq6Te5K",
          "width": 320
        },
        "k": {
          "extension": "jpg",
          "height": 1484,
          "mimetype": "image/jpeg",
          "secret": "pisGReHh8YLvEibuIQPKV73w2Eq6Te5K",
          "width": 2048
        },
        "n": {
          "extension": "jpg",
          "height": 231,
          "mimetype": "image/jpeg",
          "secret": "pisGReHh8YLvEibuIQPKV73w2Eq6Te5K",
          "width": 320
        },
        "o": {
          "extension": "jpg",
          "height": 1800,
          "mimetype": "image/jpeg",
          "secret": "pBfqU2jo9l9OCF4OahxoUBOFQkwxA8cU",
          "width": 2484
        },
        "s": {
          "extension": "jpg",
          "height": 320,
          "mimetype": "image/jpeg",
          "secret": "pisGReHh8YLvEibuIQPKV73w2Eq6Te5K",
          "width": 320
        },
        "z": {
          "extension": "jpg",
          "height": 463,
          "mimetype": "image/jpeg",
          "secret": "pisGReHh8YLvEibuIQPKV73w2Eq6Te5K",
          "width": 640
        }
      }
    },
    "media:uri_template": "https://static.sfomuseum.org/media/152/784/393/1/1527843931_{secret}_{label}.{extention}",
    "sfomuseum:filename": "68744.tif",
    "sfomuseum:image_index": 5,
    "sfomuseum:image_type": "studio",
    "sfomuseum:placetype": "image",
    "sfomuseum:primary_image": 0,
    "wof:depicts": [
      1159283999,
      1511928823
    ],
    "wof:name": "menu: BOAC (British Overseas Airways Corporation)",
    "wof:placetype": "custom",
    "wof:placetype_alt": "image"
  },
  "geometry": {"coordinates":[-122.386155,37.616358],"type":"Point"}
}
