{
  "type": "Feature",
  "properties": {
    "iso:country": "XX",
    "media:fingerprint": "0d94f54ef86dc7cc25b8e7876bb20609fb55ba3e",
    "media:imagehash_avg": "a:01fffffc18000003",
    "media:imagehash_diff": "d:a3a3c10170682f1f",
    "media:medium": "image",
    "media:mimetype": "image/tiff",
    "media:properties": {
      "colours": [
        {
          "hex": "#868686",
          "name": "#868686",
          "reference": "vibrant"
        }, 
        {
          "hex": "#b8b8b8",
          "name": "#b8b8b8",
          "reference": "vibrant"
        }, 
        {
          "hex": "#484848",
          "name": "#484848",
          "reference": "vibrant"
        }
      ],
      "sizes": {
        "b": {
          "extension": "jpg",
          "height": 768,
          "mimetype": "image/jpeg",
          "secret": "uAlIDKjwSb2M0i5H1a7tycil5QLB7fMv",
          "width": 759
        },
        "c": {
          "extension": "jpg",
          "height": 600,
          "mimetype": "image/jpeg",
          "secret": "uAlIDKjwSb2M0i5H1a7tycil5QLB7fMv",
          "width": 593
        },
        "dc": {
          "extension": "jpg",
          "height": 600,
          "mimetype": "image/jpeg",
          "secret": "uAlIDKjwSb2M0i5H1a7tycil5QLB7fMv",
          "width": 593
        },
        "ds": {
          "extension": "jpg",
          "height": 320,
          "mimetype": "image/jpeg",
          "secret": "uAlIDKjwSb2M0i5H1a7tycil5QLB7fMv",
          "width": 320
        },
        "k": {
          "extension": "jpg",
          "height": 1536,
          "mimetype": "image/jpeg",
          "secret": "uAlIDKjwSb2M0i5H1a7tycil5QLB7fMv",
          "width": 1519
        },
        "n": {
          "extension": "jpg",
          "height": 240,
          "mimetype": "image/jpeg",
          "secret": "uAlIDKjwSb2M0i5H1a7tycil5QLB7fMv",
          "width": 237
        },
        "o": {
          "extension": "jpg",
          "height": 2590,
          "mimetype": "image/jpeg",
          "secret": "C40lK8CIHQWMDV0j6qNzrQeky92hxdgF",
          "width": 2563
        },
        "s": {
          "extension": "jpg",
          "height": 320,
          "mimetype": "image/jpeg",
          "secret": "uAlIDKjwSb2M0i5H1a7tycil5QLB7fMv",
          "width": 320
        },
        "z": {
          "extension": "jpg",
          "height": 480,
          "mimetype": "image/jpeg",
          "secret": "uAlIDKjwSb2M0i5H1a7tycil5QLB7fMv",
          "width": 474
        }
      }
    },
    "media:uri_template": "https://millsfield.sfomuseum.org/media/152/782/720/5/1527827205_{secret}_{label}.{extention}",
    "sfomuseum:filename": "43983.tif",
    "sfomuseum:image_index": 5,
    "sfomuseum:placetype": "image",
    "sfomuseum:primary_image": 1,
    "wof:depicts": [
      1511948245
    ],
    "wof:name": "negative: San Francisco International Airport (SFO), aerial, roundabout",
    "wof:placetype": "media"
  },
  "geometry": {"coordinates":[-122.386155,37.616358],"type":"Point"}
}
