{
  "type": "Feature",
  "properties": {
    "iso:country": "US",
    "media:fingerprint": "923a6cc2b268e34cb6cbb1791ef37d28a9008c31",
    "media:imagehash_avg": "a:cf8181c1c3c3e3ff",
    "media:imagehash_diff": "d:1f170707030e8686",
    "media:medium": "image",
    "media:mimetype": "image/tiff",
    "media:properties": {
      "colours": [
        {
          "hex": "#10a7a1",
          "name": "#10a7a1",
          "reference": "vibrant"
        }, 
        {
          "hex": "#f8f8e5",
          "name": "#f8f8e5",
          "reference": "vibrant"
        }, 
        {
          "hex": "#087e79",
          "name": "#087e79",
          "reference": "vibrant"
        }, 
        {
          "hex": "#67b0a9",
          "name": "#67b0a9",
          "reference": "vibrant"
        }, 
        {
          "hex": "#c0c1b7",
          "name": "#c0c1b7",
          "reference": "vibrant"
        }
      ],
      "sizes": {
        "b": {
          "extension": "jpg",
          "height": 768,
          "mimetype": "image/jpeg",
          "secret": "AmBwSMPORjWElJGogzuqai8oN0FasNRh",
          "width": 355
        },
        "c": {
          "extension": "jpg",
          "height": 600,
          "mimetype": "image/jpeg",
          "secret": "AmBwSMPORjWElJGogzuqai8oN0FasNRh",
          "width": 277
        },
        "dc": {
          "extension": "jpg",
          "height": 600,
          "mimetype": "image/jpeg",
          "secret": "AmBwSMPORjWElJGogzuqai8oN0FasNRh",
          "width": 277
        },
        "ds": {
          "extension": "jpg",
          "height": 320,
          "mimetype": "image/jpeg",
          "secret": "AmBwSMPORjWElJGogzuqai8oN0FasNRh",
          "width": 320
        },
        "k": {
          "extension": "jpg",
          "height": 1536,
          "mimetype": "image/jpeg",
          "secret": "AmBwSMPORjWElJGogzuqai8oN0FasNRh",
          "width": 710
        },
        "n": {
          "extension": "jpg",
          "height": 239,
          "mimetype": "image/jpeg",
          "secret": "AmBwSMPORjWElJGogzuqai8oN0FasNRh",
          "width": 110
        },
        "o": {
          "extension": "jpg",
          "height": 703,
          "mimetype": "image/jpeg",
          "secret": "RQeAecKHewKRPJBD0AfMHtICH6pKAIwu",
          "width": 325
        },
        "s": {
          "extension": "jpg",
          "height": 320,
          "mimetype": "image/jpeg",
          "secret": "AmBwSMPORjWElJGogzuqai8oN0FasNRh",
          "width": 320
        },
        "z": {
          "extension": "jpg",
          "height": 479,
          "mimetype": "image/jpeg",
          "secret": "AmBwSMPORjWElJGogzuqai8oN0FasNRh",
          "width": 221
        }
      }
    },
    "media:uri_template": "https://millsfield.sfomuseum.org/media/152/781/841/1/1527818411_{secret}_{label}.{extention}",
    "sfomuseum:filename": "19003.tif",
    "sfomuseum:image_index": 5,
    "sfomuseum:placetype": "image",
    "sfomuseum:primary_image": 0,
    "wof:depicts": [
      1511909269
    ],
    "wof:name": "timetable: Frontier Airlines",
    "wof:placetype": "media"
  },
  "geometry": {"coordinates":[-122.386155,37.616358],"type":"Point"}
}
