{
  "type": "Feature",
  "properties": {
    "iso:country": "XX",
    "media:fingerprint": "7c69c8db4b4d2bc92e17506e624b01b2f6a324ff",
    "media:imagehash_avg": "a:003c3c3e3c3c1800",
    "media:imagehash_diff": "d:f0f0f0e8e8e8b0cc",
    "media:medium": "image",
    "media:mimetype": "image/tiff",
    "media:properties": {
      "colours": [
        {
          "hex": "#b2945f",
          "name": "#b2945f",
          "reference": "vibrant"
        },
        {
          "hex": "#a0865b",
          "name": "#a0865b",
          "reference": "vibrant"
        },
        {
          "hex": "#b8b8b8",
          "name": "#b8b8b8",
          "reference": "vibrant"
        },
        {
          "hex": "#877549",
          "name": "#877549",
          "reference": "vibrant"
        }
      ],
      "sizes": {
        "b": {
          "extension": "jpg",
          "height": 768,
          "mimetype": "image/jpeg",
          "secret": "k1KunBFoq9dxGFasrXrpZFvemcOkWwfm",
          "width": 965
        },
        "c": {
          "extension": "jpg",
          "height": 600,
          "mimetype": "image/jpeg",
          "secret": "k1KunBFoq9dxGFasrXrpZFvemcOkWwfm",
          "width": 754
        },
        "dc": {
          "extension": "jpg",
          "height": 600,
          "mimetype": "image/jpeg",
          "secret": "k1KunBFoq9dxGFasrXrpZFvemcOkWwfm",
          "width": 754
        },
        "ds": {
          "extension": "jpg",
          "height": 320,
          "mimetype": "image/jpeg",
          "secret": "k1KunBFoq9dxGFasrXrpZFvemcOkWwfm",
          "width": 320
        },
        "k": {
          "extension": "jpg",
          "height": 1536,
          "mimetype": "image/jpeg",
          "secret": "k1KunBFoq9dxGFasrXrpZFvemcOkWwfm",
          "width": 1931
        },
        "n": {
          "extension": "jpg",
          "height": 240,
          "mimetype": "image/jpeg",
          "secret": "k1KunBFoq9dxGFasrXrpZFvemcOkWwfm",
          "width": 301
        },
        "o": {
          "extension": "jpg",
          "height": 1667,
          "mimetype": "image/jpeg",
          "secret": "jNnB69dutvN7qlQarkyzZbDa7t5hTnqO",
          "width": 2096
        },
        "s": {
          "extension": "jpg",
          "height": 320,
          "mimetype": "image/jpeg",
          "secret": "k1KunBFoq9dxGFasrXrpZFvemcOkWwfm",
          "width": 320
        },
        "z": {
          "extension": "jpg",
          "height": 480,
          "mimetype": "image/jpeg",
          "secret": "k1KunBFoq9dxGFasrXrpZFvemcOkWwfm",
          "width": 603
        }
      }
    },
    "media:uri_template": "https://static.sfomuseum.org/media/152/785/842/9/1527858429_{secret}_{label}.{extention}",
    "sfomuseum:filename": "2002.018.039.tif",
    "sfomuseum:image_index": 5,
    "sfomuseum:image_type": "studio",
    "sfomuseum:placetype": "image",
    "sfomuseum:primary_image": 1,
    "wof:depicts": [
      1159285043,
      1511922935
    ],
    "wof:name": "dinner plate: Qantas Airways",
    "wof:placetype": "custom",
    "wof:placetype_alt": "image"
  },
  "geometry": {"coordinates":[-122.386155,37.616358],"type":"Point"}
}
