{
  "type": "Feature",
  "properties": {
    "iso:country": "XX",
    "media:fingerprint": "cf8e401de45d84ebf2b516edeaa1f36a941dabc0",
    "media:imagehash_avg": "a:007cff80004effff",
    "media:imagehash_diff": "d:e0e0e1203098bce0",
    "media:medium": "image",
    "media:mimetype": "image/tiff",
    "media:properties": {
      "colours": [
        {
          "hex": "#d6351f",
          "name": "#d6351f",
          "reference": "vibrant"
        }, 
        {
          "hex": "#80c2de",
          "name": "#80c2de",
          "reference": "vibrant"
        }, 
        {
          "hex": "#9e6c3d",
          "name": "#9e6c3d",
          "reference": "vibrant"
        }, 
        {
          "hex": "#9aa165",
          "name": "#9aa165",
          "reference": "vibrant"
        }, 
        {
          "hex": "#c3d49c",
          "name": "#c3d49c",
          "reference": "vibrant"
        }
      ],
      "sizes": {
        "b": {
          "extension": "jpg",
          "height": 768,
          "mimetype": "image/jpeg",
          "secret": "3KrXrZCmYmg7nQDEOAYz3YJPuGpQ1bWg",
          "width": 784
        },
        "c": {
          "extension": "jpg",
          "height": 600,
          "mimetype": "image/jpeg",
          "secret": "3KrXrZCmYmg7nQDEOAYz3YJPuGpQ1bWg",
          "width": 612
        },
        "dc": {
          "extension": "jpg",
          "height": 600,
          "mimetype": "image/jpeg",
          "secret": "3KrXrZCmYmg7nQDEOAYz3YJPuGpQ1bWg",
          "width": 612
        },
        "ds": {
          "extension": "jpg",
          "height": 320,
          "mimetype": "image/jpeg",
          "secret": "3KrXrZCmYmg7nQDEOAYz3YJPuGpQ1bWg",
          "width": 320
        },
        "k": {
          "extension": "jpg",
          "height": 1536,
          "mimetype": "image/jpeg",
          "secret": "3KrXrZCmYmg7nQDEOAYz3YJPuGpQ1bWg",
          "width": 1568
        },
        "n": {
          "extension": "jpg",
          "height": 239,
          "mimetype": "image/jpeg",
          "secret": "3KrXrZCmYmg7nQDEOAYz3YJPuGpQ1bWg",
          "width": 245
        },
        "o": {
          "extension": "jpg",
          "height": 2563,
          "mimetype": "image/jpeg",
          "secret": "XRlH4vebpNjToXsw5IoFzDMts58xvmLg",
          "width": 2618
        },
        "s": {
          "extension": "jpg",
          "height": 320,
          "mimetype": "image/jpeg",
          "secret": "3KrXrZCmYmg7nQDEOAYz3YJPuGpQ1bWg",
          "width": 320
        },
        "z": {
          "extension": "jpg",
          "height": 479,
          "mimetype": "image/jpeg",
          "secret": "3KrXrZCmYmg7nQDEOAYz3YJPuGpQ1bWg",
          "width": 490
        }
      }
    },
    "media:uri_template": "https://millsfield.sfomuseum.org/media/152/782/543/9/1527825439_{secret}_{label}.{extention}",
    "sfomuseum:filename": "43155.tif",
    "sfomuseum:image_index": 5,
    "sfomuseum:placetype": "image",
    "sfomuseum:primary_image": 1,
    "wof:depicts": [
      1511946479
    ],
    "wof:name": "negative: San Francisco International Airport (SFO), parking garage",
    "wof:placetype": "media"
  },
  "geometry": {"coordinates":[-122.386155,37.616358],"type":"Point"}
}
