{
  "type": "Feature",
  "properties": {
    "iso:country": "XX",
    "media:fingerprint": "206ba12f019d7f0d9aa05c71f1165a69519a9f94",
    "media:imagehash_avg": "a:f9999999999909ff",
    "media:imagehash_diff": "d:333b333333337373",
    "media:medium": "image",
    "media:mimetype": "image/tiff",
    "media:properties": {
      "colours": [
        {
          "hex": "#f4e2c8",
          "name": "#f4e2c8",
          "reference": "vibrant"
        },
        {
          "hex": "#420707",
          "name": "#420707",
          "reference": "vibrant"
        },
        {
          "hex": "#a07a70",
          "name": "#a07a70",
          "reference": "vibrant"
        },
        {
          "hex": "#d0b7a3",
          "name": "#d0b7a3",
          "reference": "vibrant"
        },
        {
          "hex": "#2f6865",
          "name": "#2f6865",
          "reference": "vibrant"
        }
      ],
      "sizes": {
        "b": {
          "extension": "jpg",
          "height": 758,
          "mimetype": "image/jpeg",
          "secret": "K0VtfbBoJyvkrYZ7yYQw0uhis06vxgTl",
          "width": 1024
        },
        "c": {
          "extension": "jpg",
          "height": 592,
          "mimetype": "image/jpeg",
          "secret": "K0VtfbBoJyvkrYZ7yYQw0uhis06vxgTl",
          "width": 800
        },
        "dc": {
          "extension": "jpg",
          "height": 592,
          "mimetype": "image/jpeg",
          "secret": "K0VtfbBoJyvkrYZ7yYQw0uhis06vxgTl",
          "width": 800
        },
        "ds": {
          "extension": "jpg",
          "height": 320,
          "mimetype": "image/jpeg",
          "secret": "K0VtfbBoJyvkrYZ7yYQw0uhis06vxgTl",
          "width": 320
        },
        "k": {
          "extension": "jpg",
          "height": 1516,
          "mimetype": "image/jpeg",
          "secret": "K0VtfbBoJyvkrYZ7yYQw0uhis06vxgTl",
          "width": 2048
        },
        "n": {
          "extension": "jpg",
          "height": 236,
          "mimetype": "image/jpeg",
          "secret": "K0VtfbBoJyvkrYZ7yYQw0uhis06vxgTl",
          "width": 320
        },
        "o": {
          "extension": "jpg",
          "height": 2078,
          "mimetype": "image/jpeg",
          "secret": "1OvYz6ZWv9tsxgl9N7pdcq8CXCkE8ka9",
          "width": 2807
        },
        "s": {
          "extension": "jpg",
          "height": 320,
          "mimetype": "image/jpeg",
          "secret": "K0VtfbBoJyvkrYZ7yYQw0uhis06vxgTl",
          "width": 320
        },
        "z": {
          "extension": "jpg",
          "height": 473,
          "mimetype": "image/jpeg",
          "secret": "K0VtfbBoJyvkrYZ7yYQw0uhis06vxgTl",
          "width": 640
        }
      }
    },
    "media:uri_template": "https://static.sfomuseum.org/media/152/784/820/3/1527848203_{secret}_{label}.{extention}",
    "sfomuseum:filename": "72305.tif",
    "sfomuseum:image_index": 5,
    "sfomuseum:image_type": "studio",
    "sfomuseum:placetype": "image",
    "sfomuseum:primary_image": 0,
    "wof:depicts": [
      1511930291,
      1159285393
    ],
    "wof:name": "menu: TWA (Trans World Airlines)",
    "wof:placetype": "custom",
    "wof:placetype_alt": "image"
  },
  "geometry": {"coordinates":[-122.386155,37.616358],"type":"Point"}
}
