{
  "type": "Feature",
  "properties": {
    "iso:country": "XX",
    "media:fingerprint": "4a9c2505f5d96e4ce61f3f697fd7c408ef55d42c",
    "media:imagehash_avg": "a:317dffff0f0f0100",
    "media:imagehash_diff": "d:61e16d7c5d99074f",
    "media:medium": "image",
    "media:mimetype": "image/tiff",
    "media:properties": {
      "colours": [
        {
          "hex": "#7a7a7a",
          "name": "#7a7a7a",
          "reference": "vibrant"
        }, 
        {
          "hex": "#c0c0c0",
          "name": "#c0c0c0",
          "reference": "vibrant"
        }, 
        {
          "hex": "#484848",
          "name": "#484848",
          "reference": "vibrant"
        }
      ],
      "sizes": {
        "b": {
          "extension": "jpg",
          "height": 768,
          "mimetype": "image/jpeg",
          "secret": "g26OC03ls26c7XSkvf5uOznoIHDfpR8E",
          "width": 759
        },
        "c": {
          "extension": "jpg",
          "height": 600,
          "mimetype": "image/jpeg",
          "secret": "g26OC03ls26c7XSkvf5uOznoIHDfpR8E",
          "width": 593
        },
        "dc": {
          "extension": "jpg",
          "height": 600,
          "mimetype": "image/jpeg",
          "secret": "g26OC03ls26c7XSkvf5uOznoIHDfpR8E",
          "width": 593
        },
        "ds": {
          "extension": "jpg",
          "height": 320,
          "mimetype": "image/jpeg",
          "secret": "g26OC03ls26c7XSkvf5uOznoIHDfpR8E",
          "width": 320
        },
        "k": {
          "extension": "jpg",
          "height": 1536,
          "mimetype": "image/jpeg",
          "secret": "g26OC03ls26c7XSkvf5uOznoIHDfpR8E",
          "width": 1519
        },
        "n": {
          "extension": "jpg",
          "height": 239,
          "mimetype": "image/jpeg",
          "secret": "g26OC03ls26c7XSkvf5uOznoIHDfpR8E",
          "width": 237
        },
        "o": {
          "extension": "jpg",
          "height": 2563,
          "mimetype": "image/jpeg",
          "secret": "ltqNuwxKNFudErxdTuRz5UJYfWyQc0kg",
          "width": 2536
        },
        "s": {
          "extension": "jpg",
          "height": 320,
          "mimetype": "image/jpeg",
          "secret": "g26OC03ls26c7XSkvf5uOznoIHDfpR8E",
          "width": 320
        },
        "z": {
          "extension": "jpg",
          "height": 479,
          "mimetype": "image/jpeg",
          "secret": "g26OC03ls26c7XSkvf5uOznoIHDfpR8E",
          "width": 474
        }
      }
    },
    "media:uri_template": "https://millsfield.sfomuseum.org/media/152/782/612/7/1527826127_{secret}_{label}.{extention}",
    "sfomuseum:filename": "43501.tif",
    "sfomuseum:image_index": 5,
    "sfomuseum:placetype": "image",
    "sfomuseum:primary_image": 1,
    "wof:depicts": [
      1511947155
    ],
    "wof:name": "negative: San Francisco International Airport (SFO), presentation of airport master plan",
    "wof:placetype": "media"
  },
  "geometry": {"coordinates":[-122.386155,37.616358],"type":"Point"}
}
