{
  "type": "Feature",
  "properties": {
    "iso:country": "XX",
    "media:fingerprint": "0febfdf2308c7e30cad4dcd3953f31147e872d82",
    "media:imagehash_avg": "a:ffc3c3c3c3c3e7ff",
    "media:imagehash_diff": "d:0e0f1f1b0f1f0f0e",
    "media:medium": "image",
    "media:mimetype": "image/tiff",
    "media:properties": {
      "colours": [
        {
          "hex": "#8e8268",
          "name": "#8e8268",
          "reference": "vibrant"
        },
        {
          "hex": "#c7bca4",
          "name": "#c7bca4",
          "reference": "vibrant"
        },
        {
          "hex": "#443f2f",
          "name": "#443f2f",
          "reference": "vibrant"
        }
      ],
      "sizes": {
        "b": {
          "extension": "jpg",
          "height": 685,
          "mimetype": "image/jpeg",
          "secret": "OyK4HTCAHgjm6trylqdz4UxQx2mYVzTP",
          "width": 1024
        },
        "c": {
          "extension": "jpg",
          "height": 535,
          "mimetype": "image/jpeg",
          "secret": "OyK4HTCAHgjm6trylqdz4UxQx2mYVzTP",
          "width": 800
        },
        "dc": {
          "extension": "jpg",
          "height": 535,
          "mimetype": "image/jpeg",
          "secret": "OyK4HTCAHgjm6trylqdz4UxQx2mYVzTP",
          "width": 800
        },
        "ds": {
          "extension": "jpg",
          "height": 320,
          "mimetype": "image/jpeg",
          "secret": "OyK4HTCAHgjm6trylqdz4UxQx2mYVzTP",
          "width": 320
        },
        "k": {
          "extension": "jpg",
          "height": 1371,
          "mimetype": "image/jpeg",
          "secret": "OyK4HTCAHgjm6trylqdz4UxQx2mYVzTP",
          "width": 2048
        },
        "n": {
          "extension": "jpg",
          "height": 214,
          "mimetype": "image/jpeg",
          "secret": "OyK4HTCAHgjm6trylqdz4UxQx2mYVzTP",
          "width": 320
        },
        "o": {
          "extension": "jpg",
          "height": 1339,
          "mimetype": "image/jpeg",
          "secret": "b0yMvFLSvbuqQpGuDXOYOHj0RasdUjuQ",
          "width": 2000
        },
        "s": {
          "extension": "jpg",
          "height": 320,
          "mimetype": "image/jpeg",
          "secret": "OyK4HTCAHgjm6trylqdz4UxQx2mYVzTP",
          "width": 320
        },
        "z": {
          "extension": "jpg",
          "height": 428,
          "mimetype": "image/jpeg",
          "secret": "OyK4HTCAHgjm6trylqdz4UxQx2mYVzTP",
          "width": 640
        }
      }
    },
    "media:uri_template": "https://static.sfomuseum.org/media/172/956/685/1/1729566851_{secret}_{label}.{extention}",
    "sfomuseum:filename": "2012.147.448 back.tif",
    "sfomuseum:image_index": 5,
    "sfomuseum:image_type": "studio",
    "sfomuseum:placetype": "image",
    "sfomuseum:primary_image": 1,
    "wof:depicts": [
      1159284989,
      1511952735
    ],
    "wof:name": "commemorative medallion: Pan American World Airways",
    "wof:placetype": "custom",
    "wof:placetype_alt": "image"
  },
  "geometry": {"coordinates":[-122.386155,37.616357],"type":"Point"}
}
