{
  "type": "Feature",
  "properties": {
    "iso:country": "XX",
    "media:fingerprint": "838b40ddff285f84066c569fa050af94e2454212",
    "media:imagehash_avg": "a:ffcfc18741604400",
    "media:imagehash_diff": "d:0f1b170f97cbac3e",
    "media:medium": "image",
    "media:mimetype": "image/tiff",
    "media:properties": {
      "colours": [
        {
          "hex": "#808080",
          "name": "#808080",
          "reference": "vibrant"
        }, 
        {
          "hex": "#b8b8b8",
          "name": "#b8b8b8",
          "reference": "vibrant"
        }, 
        {
          "hex": "#484848",
          "name": "#484848",
          "reference": "vibrant"
        }
      ],
      "sizes": {
        "b": {
          "extension": "jpg",
          "height": 768,
          "mimetype": "image/jpeg",
          "secret": "9Go1n7oT2Wcn7S5hvAMtRwciM9QfDUdx",
          "width": 768
        },
        "c": {
          "extension": "jpg",
          "height": 600,
          "mimetype": "image/jpeg",
          "secret": "9Go1n7oT2Wcn7S5hvAMtRwciM9QfDUdx",
          "width": 600
        },
        "dc": {
          "extension": "jpg",
          "height": 600,
          "mimetype": "image/jpeg",
          "secret": "9Go1n7oT2Wcn7S5hvAMtRwciM9QfDUdx",
          "width": 600
        },
        "ds": {
          "extension": "jpg",
          "height": 320,
          "mimetype": "image/jpeg",
          "secret": "9Go1n7oT2Wcn7S5hvAMtRwciM9QfDUdx",
          "width": 320
        },
        "k": {
          "extension": "jpg",
          "height": 1536,
          "mimetype": "image/jpeg",
          "secret": "9Go1n7oT2Wcn7S5hvAMtRwciM9QfDUdx",
          "width": 1536
        },
        "n": {
          "extension": "jpg",
          "height": 240,
          "mimetype": "image/jpeg",
          "secret": "9Go1n7oT2Wcn7S5hvAMtRwciM9QfDUdx",
          "width": 240
        },
        "o": {
          "extension": "jpg",
          "height": 2590,
          "mimetype": "image/jpeg",
          "secret": "jdIhDSix0Wb9r9R9sAs8fDO9W5CpE6eP",
          "width": 2590
        },
        "s": {
          "extension": "jpg",
          "height": 320,
          "mimetype": "image/jpeg",
          "secret": "9Go1n7oT2Wcn7S5hvAMtRwciM9QfDUdx",
          "width": 320
        },
        "z": {
          "extension": "jpg",
          "height": 480,
          "mimetype": "image/jpeg",
          "secret": "9Go1n7oT2Wcn7S5hvAMtRwciM9QfDUdx",
          "width": 480
        }
      }
    },
    "media:uri_template": "https://millsfield.sfomuseum.org/media/152/782/795/9/1527827959_{secret}_{label}.{extention}",
    "sfomuseum:filename": "44319.tif",
    "sfomuseum:image_index": 5,
    "sfomuseum:placetype": "image",
    "sfomuseum:primary_image": 1,
    "wof:depicts": [
      1511948993
    ],
    "wof:name": "negative: San Francisco International Airport (SFO), South Terminal, Rotunda A construction",
    "wof:placetype": "media"
  },
  "geometry": {"coordinates":[-122.386155,37.616358],"type":"Point"}
}
