{
  "type": "Feature",
  "properties": {
    "iso:country": "XX",
    "media:fingerprint": "1e821ec631e941c7e0cd2c5badd8b64dcb3d1149",
    "media:imagehash_avg": "a:c38199f98989e9e1",
    "media:imagehash_diff": "d:1b2b2b2b2b2b0b89",
    "media:medium": "image",
    "media:mimetype": "image/tiff",
    "media:properties": {
      "colours": [
        {
          "hex": "#ab934b",
          "name": "#ab934b",
          "reference": "vibrant"
        }, 
        {
          "hex": "#c9b983",
          "name": "#c9b983",
          "reference": "vibrant"
        }, 
        {
          "hex": "#826d35",
          "name": "#826d35",
          "reference": "vibrant"
        }, 
        {
          "hex": "#aa975b",
          "name": "#aa975b",
          "reference": "vibrant"
        }, 
        {
          "hex": "#cecbb9",
          "name": "#cecbb9",
          "reference": "vibrant"
        }
      ],
      "sizes": {
        "b": {
          "extension": "jpg",
          "height": 644,
          "mimetype": "image/jpeg",
          "secret": "Juxs2drMlFplNjpleLKwdGAuMm0niE5P",
          "width": 1024
        },
        "c": {
          "extension": "jpg",
          "height": 503,
          "mimetype": "image/jpeg",
          "secret": "Juxs2drMlFplNjpleLKwdGAuMm0niE5P",
          "width": 800
        },
        "dc": {
          "extension": "jpg",
          "height": 503,
          "mimetype": "image/jpeg",
          "secret": "Juxs2drMlFplNjpleLKwdGAuMm0niE5P",
          "width": 800
        },
        "ds": {
          "extension": "jpg",
          "height": 320,
          "mimetype": "image/jpeg",
          "secret": "Juxs2drMlFplNjpleLKwdGAuMm0niE5P",
          "width": 320
        },
        "k": {
          "extension": "jpg",
          "height": 1288,
          "mimetype": "image/jpeg",
          "secret": "Juxs2drMlFplNjpleLKwdGAuMm0niE5P",
          "width": 2048
        },
        "n": {
          "extension": "jpg",
          "height": 201,
          "mimetype": "image/jpeg",
          "secret": "Juxs2drMlFplNjpleLKwdGAuMm0niE5P",
          "width": 320
        },
        "o": {
          "extension": "jpg",
          "height": 3628,
          "mimetype": "image/jpeg",
          "secret": "o1ag54z5jcfybsLDtJKscuSHiJajIFvQ",
          "width": 5765
        },
        "s": {
          "extension": "jpg",
          "height": 320,
          "mimetype": "image/jpeg",
          "secret": "Juxs2drMlFplNjpleLKwdGAuMm0niE5P",
          "width": 320
        },
        "z": {
          "extension": "jpg",
          "height": 402,
          "mimetype": "image/jpeg",
          "secret": "Juxs2drMlFplNjpleLKwdGAuMm0niE5P",
          "width": 640
        }
      }
    },
    "media:uri_template": "https://millsfield.sfomuseum.org/media/152/782/874/3/1527828743_{secret}_{label}.{extention}",
    "sfomuseum:filename": "46018.tif",
    "sfomuseum:image_index": 5,
    "sfomuseum:placetype": "image",
    "sfomuseum:primary_image": 0,
    "wof:depicts": [
      1511925391
    ],
    "wof:name": "menu: Pan American World Airways, President (First) Class",
    "wof:placetype": "media"
  },
  "geometry": {"coordinates":[-122.386155,37.616358],"type":"Point"}
}
