{
  "type": "Feature",
  "properties": {
    "iso:country": "XX",
    "media:fingerprint": "fa843799b3635631bb7a5914836d769c20123f55",
    "media:imagehash_avg": "a:fce0f8fc84c0c000",
    "media:imagehash_diff": "d:91088190389c9408",
    "media:medium": "image",
    "media:mimetype": "image/tiff",
    "media:properties": {
      "colours": [
        {
          "hex": "#808080",
          "name": "#808080",
          "reference": "vibrant"
        }, 
        {
          "hex": "#c0c0c0",
          "name": "#c0c0c0",
          "reference": "vibrant"
        }, 
        {
          "hex": "#464646",
          "name": "#464646",
          "reference": "vibrant"
        }
      ],
      "sizes": {
        "b": {
          "extension": "jpg",
          "height": 767,
          "mimetype": "image/jpeg",
          "secret": "Rc3DGLfYiNRqHzZBkPlOwPoFJ5gpm0zP",
          "width": 988
        },
        "c": {
          "extension": "jpg",
          "height": 600,
          "mimetype": "image/jpeg",
          "secret": "Rc3DGLfYiNRqHzZBkPlOwPoFJ5gpm0zP",
          "width": 772
        },
        "dc": {
          "extension": "jpg",
          "height": 600,
          "mimetype": "image/jpeg",
          "secret": "Rc3DGLfYiNRqHzZBkPlOwPoFJ5gpm0zP",
          "width": 772
        },
        "ds": {
          "extension": "jpg",
          "height": 320,
          "mimetype": "image/jpeg",
          "secret": "Rc3DGLfYiNRqHzZBkPlOwPoFJ5gpm0zP",
          "width": 320
        },
        "k": {
          "extension": "jpg",
          "height": 1535,
          "mimetype": "image/jpeg",
          "secret": "Rc3DGLfYiNRqHzZBkPlOwPoFJ5gpm0zP",
          "width": 1976
        },
        "n": {
          "extension": "jpg",
          "height": 240,
          "mimetype": "image/jpeg",
          "secret": "Rc3DGLfYiNRqHzZBkPlOwPoFJ5gpm0zP",
          "width": 308
        },
        "o": {
          "extension": "jpg",
          "height": 2140,
          "mimetype": "image/jpeg",
          "secret": "S4gRQHobhNa5NnIueQAGtbp72StuX4n5",
          "width": 2754
        },
        "s": {
          "extension": "jpg",
          "height": 320,
          "mimetype": "image/jpeg",
          "secret": "Rc3DGLfYiNRqHzZBkPlOwPoFJ5gpm0zP",
          "width": 320
        },
        "z": {
          "extension": "jpg",
          "height": 480,
          "mimetype": "image/jpeg",
          "secret": "Rc3DGLfYiNRqHzZBkPlOwPoFJ5gpm0zP",
          "width": 617
        }
      }
    },
    "media:uri_template": "https://millsfield.sfomuseum.org/media/152/782/257/1/1527822571_{secret}_{label}.{extention}",
    "sfomuseum:filename": "40807.tif",
    "sfomuseum:image_index": 5,
    "sfomuseum:placetype": "image",
    "sfomuseum:primary_image": 1,
    "wof:depicts": [
      1511944475
    ],
    "wof:name": "negative: San Francisco International Airport (SFO), Michael Bagan",
    "wof:placetype": "media"
  },
  "geometry": {"coordinates":[-122.386155,37.616358],"type":"Point"}
}
