{
  "type": "Feature",
  "properties": {
    "media:fingerprint": "274f2f77fec33c89be5f140c0db5f5d6c0d13f96",
    "media:imagehash_avg": "a:ff818181818181ff",
    "media:imagehash_diff": "d:0d0f0d0d0f0f0f0d",
    "media:mimetype": "image/tiff",
    "media:properties": {
      "colours": [
        {
          "hex": "#af971e",
          "name": "#af971e",
          "reference": "vibrant"
        },
        {
          "hex": "#d6c79f",
          "name": "#d6c79f",
          "reference": "vibrant"
        },
        {
          "hex": "#6d6118",
          "name": "#6d6118",
          "reference": "vibrant"
        },
        {
          "hex": "#ebe7d6",
          "name": "#ebe7d6",
          "reference": "vibrant"
        },
        {
          "hex": "#333020",
          "name": "#333020",
          "reference": "vibrant"
        }
      ],
      "sizes": {
        "b": {
          "extension": "jpg",
          "height": 768,
          "mimetype": "image/jpeg",
          "secret": "KL571gAPlPgmecqxLOtL9VCXzwvs9wit",
          "width": 506
        },
        "c": {
          "extension": "jpg",
          "height": 600,
          "mimetype": "image/jpeg",
          "secret": "KL571gAPlPgmecqxLOtL9VCXzwvs9wit",
          "width": 395
        },
        "dc": {
          "extension": "jpg",
          "height": 600,
          "mimetype": "image/jpeg",
          "secret": "KL571gAPlPgmecqxLOtL9VCXzwvs9wit",
          "width": 395
        },
        "ds": {
          "extension": "jpg",
          "height": 320,
          "mimetype": "image/jpeg",
          "secret": "KL571gAPlPgmecqxLOtL9VCXzwvs9wit",
          "width": 320
        },
        "k": {
          "extension": "jpg",
          "height": 1536,
          "mimetype": "image/jpeg",
          "secret": "KL571gAPlPgmecqxLOtL9VCXzwvs9wit",
          "width": 1012
        },
        "n": {
          "extension": "jpg",
          "height": 240,
          "mimetype": "image/jpeg",
          "secret": "KL571gAPlPgmecqxLOtL9VCXzwvs9wit",
          "width": 158
        },
        "o": {
          "extension": "jpg",
          "height": 2000,
          "mimetype": "image/jpeg",
          "secret": "VmAtcvWhcUmwLSxOuZxYmMpQjDExFMXI",
          "width": 1319
        },
        "s": {
          "extension": "jpg",
          "height": 320,
          "mimetype": "image/jpeg",
          "secret": "KL571gAPlPgmecqxLOtL9VCXzwvs9wit",
          "width": 320
        },
        "z": {
          "extension": "jpg",
          "height": 480,
          "mimetype": "image/jpeg",
          "secret": "KL571gAPlPgmecqxLOtL9VCXzwvs9wit",
          "width": 316
        }
      }
    },
    "media:uri_template": "https://static.sfomuseum.org/media/174/630/805/9/1746308059_{secret}_{label}.{extention}",
    "sfomuseum:filename": "1997.59.39.05_int1.tif",
    "sfomuseum:image_index": 5,
    "sfomuseum:placetype": "image",
    "sfomuseum:primary_image": 0,
    "wof:depicts": [
      1511908243,
      1159284989
    ],
    "wof:name": "menu: Pan American World Airways",
    "wof:placetype": "custom",
    "wof:placetype_alt": "image"
  },
  "geometry": {"coordinates":[-122.386155,37.616357],"type":"Point"}
}
